Workbook

Sheet Start
A1: SAMPLE COPY: every row in this file is SAMPLE data. Illustrative placeholders, not results. Use conversation-tracker.xlsx for real work.
A2: =Config!$B$3&" · conversation tracker" -> Desk Drop · conversation tracker
A3: What this is: the conversation and notes log for discovery and selling, one row per conversation, keyed by the Clay row_id.
A4: It is not a status store. Status, touches, replies, next actions and do-not-contact live in the Clay tables only (CONTRACTS 6.2).
A6: After every call (ten minutes, calls/post-call-note-template.md)
A7: 1. Fill Note_Office or Note_Brand top to bottom (verbatims first, then numbers and codes), copy its 'row to paste', and paste it into the next empty log row as values only (Ctrl+Shift+V). Or type straight into the log row.
A8: 2. Write back to the Clay row: call_date, status (call_done or yes_in_principle), yes_in_principle, call_notes ('see tracker <date>'), next_action, next_action_date.
A9: 3. Set clay_updated = Y and note_minutes.
A11: Every Friday (15 minutes)
A12: 1. Export the Clay offices table (all columns) and paste it on Clay_Offices at A1. Same for brands on Clay_Brands. Type both export dates on Config.
A13: 2. Open Scorecard. Fix every FIX under Data checks (the Sync tab and the red calc_sync_issue cells show where).
A14: 3. Read the Gate 0 block, the medians, the top objections and the reply rates. If a reply-rate check says UNDER 20% (conversation replies) or an opt-out check says OPT-OUTS OVER 5%, run sending guide section 6.
A15: 4. Download pipeline_log as CSV (File > Download > CSV, this tab only) to desk-drop-outreach/exports/pipeline_log.csv and paste it into the financial model's Pipeline tab.
A16: 5. When an office signs or a brand pays: add the row on signed_offices or paid_brands, download that tab as CSV to desk-drop-outreach/handoff/.
... A28: Dates as YYYY-MM-DD. Money as plain numbers. Rows whose row_id starts with SAMPLE are ignored while include_sample = N.

Sheet Scorecard
A1: =IF((COUNTIF(Office_Log!$A$2:$A$201,"SAMPLE*")+COUNTIF(Brand_Log!$A$2:$A$201,"SAMPLE*")+COUNTIF(signed_offices!$W$2:$W$51,"SAMPLE*")+COUNTIF(paid_brands!$AC$2:$AC$51,"SAMPLE*")+COUNTIF(later_events!$C$2:$C$101,"SAMPLE*")+IFERROR(COUNTIF(INDEX(Clay_Offices!$A$2:$FZ$601,0,Sync!$C$5),"SAMPLE*"),0)+IFERROR(COUNTIF(INDEX(Clay_Brands!$A$2:$FZ$601,0,Sync!$D$5),"SAMPLE*"),0))>0,"SAMPLE: this file holds "&(COUNTIF(Office_Log!$A$2:$A$201,"SAMPLE*")+COUNTIF(Brand_Log!$A$2:$A$201,"SAMPLE*")+COUNTIF(signed_offices!$W$2:$W$51,"SAMPLE*")+COUNTIF(paid_brands!$AC$2:$AC$51,"SAMPLE*")+COUNTIF(later_events!$C$2:$C$101,"SAMPLE*")+IFERROR(COUNTIF(INDEX(Clay_Offices!$A$2:$FZ$601,0,Sync!$C$5),"SAMPLE*"),0)+IFERROR(COUNTIF(INDEX(Clay_Brands!$A$2:$FZ$601,0,Sync!$D$5),"SAMPLE*"),0))&" SAMPLE rows. Illustrative placeholders, not results. include_sample = "&Config!$B$19&IF(Config!$B$19="Y"," (SAMPLE rows are counted)"," (SAMPLE rows are ignored)"),"") -> SAMPLE: this file holds 118 SAMPLE rows. Illustrative placeholders, not results. include_sample = Y (SAMPLE rows are counted)
A2: =Config!$B$3&" · Friday scorecard" -> Desk Drop · Friday scorecard
A3: ="As of "&TEXT(Config!$B$5,"ddd yyyy-mm-dd")&". Gate 0 is "&TEXT(Config!$B$8,"ddd yyyy-mm-dd")&" (derived, founder to confirm). Counts are distinct offices or brands, by call_date." -> As of Fri 2026-12-11. Gate 0 is Fri 2026-11-13 (derived, founder to confirm). Counts are distinct offices or brands, by call_date.
A5: Measure | B5: Fri wk 1 | C5: Fri wk 2 | D5: Gate 0 | E5: As of | F5: Target | G5: How it is counted
A6: Cut-off date | B6: =Config!$B$6 -> 46325 | C6: =Config!$B$7 -> 46332 | D6: =Config!$B$8 -> 46339 | E6: =Config!$B$5 -> 46367
A7: Offices (Gate 0: at least 5 of 15 say yes in principle AND name a pantry owner AND a receiving window)
A8: Office conversations held | B8: =COUNTIFS(Office_Log!$BC$2:$BC$201,1,Office_Log!$H$2:$H$201,"<"&(B$6+1)) -> 3 | C8: =COUNTIFS(Office_Log!$BC$2:$BC$201,1,Office_Log!$H$2:$H$201,"<"&(C$6+1)) -> 7 | D8: =COUNTIFS(Office_Log!$BC$2:$BC$201,1,Office_Log!$H$2:$H$201,"<"&(D$6+1)) -> 13 | E8: =COUNTIFS(Office_Log!$BC$2:$BC$201,1,Office_Log!$H$2:$H$201,"<"&(E$6+1)) -> 14 | F8: =Config!$B$10 -> 15 | G8: Distinct offices (calc_org on Office_Log) by the cut-off. Two contacts at one company count once.
A9: Yes in principle, pantry owner named, receiving window named | B9: =COUNTIF(Office_Log!$DL$2:$DL$201,1) -> 1 | C9: =COUNTIF(Office_Log!$DM$2:$DM$201,1) -> 3 | D9: =COUNTIF(Office_Log!$DN$2:$DN$201,1) -> 5 | E9: =COUNTIF(Office_Log!$DO$2:$DO$201,1) -> 6 | F9: =Config!$B$11 -> 5 | G9: The Gate 0 count: one per office (calc_org), while its latest answer (Y, N or maybe, from any contact) by the cut-off is still Y. Under 30 or over 250 on a Tuesday: not counted (row below).
A10: Gate 0, office side | B10: =IF(B9>=Config!$B$11,"PASS",IF(B$6<Config!$B$8,"not yet",IF(OR(B8>=Config!$B$10,B$6>=Config!$B$34),"FAIL","INCOMPLETE: "&B8&" of "&Config!$B$10&" conversations"))) -> not yet | C10: =IF(C9>=Config!$B$11,"PASS",IF(C$6<Config!$B$8,"not yet",IF(OR(C8>=Config!$B$10,C$6>=Config!$B$34),"FAIL","INCOMPLETE: "&C8&" of "&Config!$B$10&" conversations"))) -> not yet | D10: =IF(D9>=Config!$B$11,"PASS",IF(D$6<Config!$B$8,"not yet",IF(OR(D8>=Config!$B$10,D$6>=Config!$B$34),"FAIL","INCOMPLETE: "&D8&" of "&Config!$B$10&" conversations"))) -> PASS | E10: =IF(E9>=Config!$B$11,"PASS",IF(E$6<Config!$B$8,"not yet",IF(OR(E8>=Config!$B$10,E$6>=Config!$B$34),"FAIL","INCOMPLETE: "&E8&" of "&Config!$B$10&" conversations"))) -> PASS | G10: PASS at the target. Before Gate 0 a shortfall is 'not yet'. From Gate 0: FAIL once 15 conversations are held; with fewer, INCOMPLETE (no failure response yet) until the final read, Fri 2026-11-27 (Config gate0_final_read), when a shortfall is FAIL.
A11: Yes in principle, any (owner or window may be missing) | B11: =COUNTIF(Office_Log!$DP$2:$DP$201,1) -> 2 | C11: =COUNTIF(Office_Log!$DQ$2:$DQ$201,1) -> 4 | D11: =COUNTIF(Office_Log!$DR$2:$DR$201,1) -> 7 | E11: =COUNTIF(Office_Log!$DS$2:$DS$201,1) -> 8 | G11: Offices whose latest answer is Y. The gap to the row above is follow-up work: get the owner and the window.
A12: Withdrawn after a yes (latest answer N or maybe): not counted | B12: =COUNTIF(Office_Log!$DT$2:$DT$201,1) -> 0 | C12: =COUNTIF(Office_Log!$DU$2:$DU$201,1) -> 0 | D12: =COUNTIF(Office_Log!$DV$2:$DV$201,1) -> 1 | E12: =COUNTIF(Office_Log!$DW$2:$DW$201,1) -> 1 | G12: Offices that said Y and later said N or maybe, by the cut-off. Set their Clay status to no or not_now.
A13: Yes with owner and window, but under 30 or over 250 on a Tuesday: not counted | B13: =COUNTIF(Office_Log!$EK$2:$EK$201,1) -> 0 | C13: =COUNTIF(Office_Log!$EL$2:$EL$201,1) -> 0 | D13: =COUNTIF(Office_Log!$EM$2:$EM$201,1) -> 0 | E13: =COUNTIF(Office_Log!$EN$2:$EN$201,1) -> 0 | G13: Plan: under 30 or over 250 on a Tuesday is excluded (Config office_floor, office_ceiling). If the number is right, it is not a participating office.
A14: Of the counted yeses: 30 to 39 on a Tuesday (your call) | B14: =COUNTIF(Office_Log!$EO$2:$EO$201,1) -> 0 | C14: =COUNTIF(Office_Log!$EP$2:$EP$201,1) -> 0 | D14: =COUNTIF(Office_Log!$EQ$2:$EQ$201,1) -> 0 | E14: =COUNTIF(Office_Log!$ER$2:$ER$201,1) -> 0 | G14: Counted above. The plan's band is 40 to 250; 30 to 39 is the founder's call before signing.
A15: Conversations with people you already know (channel warm-intro) | B15: =COUNTIFS(Office_Log!$CH$2:$CH$201,1,Office_Log!$H$2:$H$201,"<"&(B$6+1)) -> 1 | C15: =COUNTIFS(Office_Log!$CH$2:$CH$201,1,Office_Log!$H$2:$H$201,"<"&(C$6+1)) -> 1 | D15: =COUNTIFS(Office_Log!$CH$2:$CH$201,1,Office_Log!$H$2:$H$201,"<"&(D$6+1)) -> 3 | E15: =COUNTIFS(Office_Log!$CH$2:$CH$201,1,Office_Log!$H$2:$H$201,"<"&(E$6+1)) -> 3 | F15: 5 | G15: Plan Phase 0: five of the fifteen office conversations should come from your own network. Set channel = warm-intro for anyone you knew before.
A16: Said maybe at least once (someone else must agree) | B16: =COUNTIFS(Office_Log!$CB$2:$CB$201,1,Office_Log!$H$2:$H$201,"<"&(B$6+1)) -> 0 | C16: =COUNTIFS(Office_Log!$CB$2:$CB$201,1,Office_Log!$H$2:$H$201,"<"&(C$6+1)) -> 1 | D16: =COUNTIFS(Office_Log!$CB$2:$CB$201,1,Office_Log!$H$2:$H$201,"<"&(D$6+1)) -> 2 | E16: =COUNTIFS(Office_Log!$CB$2:$CB$201,1,Office_Log!$H$2:$H$201,"<"&(E$6+1)) -> 2 | G16: Plan Phase 1: 'I need to ask facilities and HR' is a maybe, not a yes.
A17: Median budget-probe answer, USD a month | B17: =IF(COUNT(Office_Log!$BJ$2:$BJ$201)=0,"none yet",MEDIAN(Office_Log!$BJ$2:$BJ$201)) -> 50 | C17: =IF(COUNT(Office_Log!$BK$2:$BK$201)=0,"none yet",MEDIAN(Office_Log!$BK$2:$BK$201)) -> 50 | D17: =IF(COUNT(Office_Log!$BL$2:$BL$201)=0,"none yet",MEDIAN(Office_Log!$BL$2:$BL$201)) -> 75 | E17: =IF(COUNT(Office_Log!$BM$2:$BM$201)=0,"none yet",MEDIAN(Office_Log!$BM$2:$BM$201)) -> 75 | G17: First numeric answer per office; a range counts at its low end; 'no budget' counts as 0; no number is left out.
A18: Offices that gave a number (0 included) | B18: =COUNT(Office_Log!$BJ$2:$BJ$201) -> 2 | C18: =COUNT(Office_Log!$BK$2:$BK$201) -> 5 | D18: =COUNT(Office_Log!$BL$2:$BL$201) -> 8 | E18: =COUNT(Office_Log!$BM$2:$BM$201) -> 8 | G18: The n behind the median.
A19: Of those, said no budget (0) | B19: =COUNTIF(Office_Log!$BJ$2:$BJ$201,0) -> 1 | C19: =COUNTIF(Office_Log!$BK$2:$BK$201,0) -> 2 | D19: =COUNTIF(Office_Log!$BL$2:$BL$201,0) -> 3 | E19: =COUNTIF(Office_Log!$BM$2:$BM$201,0) -> 3 | G19: Counted inside the median.
A20: Offices naming $100 a month or more (decision-rule input), as of | E20: =COUNTIFS(Office_Log!$BN$2:$BN$201,1,Office_Log!$H$2:$H$201,"<"&(E$6+1)) -> 4 | G20: Plan decision rule: office-paid tier is tested if at least five offices named $100 a month or more.
A21: Shortlisted offices (shortlist = Y) | B21: =COUNTIFS(Office_Log!$CF$2:$CF$201,1,Office_Log!$H$2:$H$201,"<"&(B$6+1)) -> 2 | C21: =COUNTIFS(Office_Log!$CF$2:$CF$201,1,Office_Log!$H$2:$H$201,"<"&(C$6+1)) -> 5 | D21: =COUNTIFS(Office_Log!$CF$2:$CF$201,1,Office_Log!$H$2:$H$201,"<"&(D$6+1)) -> 9 | E21: =COUNTIFS(Office_Log!$CF$2:$CF$201,1,Office_Log!$H$2:$H$201,"<"&(E$6+1)) -> 10 | F21: 8 | G21: Plan Phase 0 deliverable: a shortlist of 8 offices to pursue.
A22: Median monthly pantry spend today, USD, as of | E22: =IF(COUNT(Office_Log!$BQ$2:$BQ$201)=0,"none yet",MEDIAN(Office_Log!$BQ$2:$BQ$201)) -> 850 | F22: =COUNT(Office_Log!$BQ$2:$BQ$201) -> 8 | G22: First number per office, from Q1. Context for the budget probe.
A24: Brands (Gate 0: at least 3 of 15 say they would pay $500 or more AND the speaker controls the budget)
A25: Brand conversations held | B25: =COUNTIFS(Brand_Log!$AZ$2:$AZ$201,1,Brand_Log!$H$2:$H$201,"<"&(B$6+1)) -> 3 | C25: =COUNTIFS(Brand_Log!$AZ$2:$AZ$201,1,Brand_Log!$H$2:$H$201,"<"&(C$6+1)) -> 7 | D25: =COUNTIFS(Brand_Log!$AZ$2:$AZ$201,1,Brand_Log!$H$2:$H$201,"<"&(D$6+1)) -> 13 | E25: =COUNTIFS(Brand_Log!$AZ$2:$AZ$201,1,Brand_Log!$H$2:$H$201,"<"&(E$6+1)) -> 15 | F25: =Config!$B$12 -> 15 | G25: Distinct brands (calc_org on Brand_Log) by the cut-off. Two founders of one brand, or brands A grouped as one (company_group), count once.
A26: Would pay $500 or more and controls the budget | B26: =COUNTIF(Brand_Log!$DD$2:$DD$201,1) -> 2 | C26: =COUNTIF(Brand_Log!$DE$2:$DE$201,1) -> 3 | D26: =COUNTIF(Brand_Log!$DF$2:$DF$201,1) -> 6 | E26: =COUNTIF(Brand_Log!$DG$2:$DG$201,1) -> 7 | F26: =Config!$B$13 -> 3 | G26: The Gate 0 count, one per brand (calc_org): the higher of the two numbers is $500 or more and controls_budget = Y, while its latest answer by the cut-off, from any contact, still qualifies (a later controls_budget = N, or every number under $500, withdraws it).
A27: Gate 0, brand side | B27: =IF(B26>=Config!$B$13,"PASS",IF(B$6<Config!$B$8,"not yet",IF(OR(B25>=Config!$B$12,B$6>=Config!$B$34),"FAIL","INCOMPLETE: "&B25&" of "&Config!$B$12&" conversations"))) -> not yet | C27: =IF(C26>=Config!$B$13,"PASS",IF(C$6<Config!$B$8,"not yet",IF(OR(C25>=Config!$B$12,C$6>=Config!$B$34),"FAIL","INCOMPLETE: "&C25&" of "&Config!$B$12&" conversations"))) -> PASS | D27: =IF(D26>=Config!$B$13,"PASS",IF(D$6<Config!$B$8,"not yet",IF(OR(D25>=Config!$B$12,D$6>=Config!$B$34),"FAIL","INCOMPLETE: "&D25&" of "&Config!$B$12&" conversations"))) -> PASS | E27: =IF(E26>=Config!$B$13,"PASS",IF(E$6<Config!$B$8,"not yet",IF(OR(E25>=Config!$B$12,E$6>=Config!$B$34),"FAIL","INCOMPLETE: "&E25&" of "&Config!$B$12&" conversations"))) -> PASS | G27: PASS at the target. Before Gate 0 a shortfall is 'not yet'. From Gate 0: FAIL once 15 conversations are held; with fewer, INCOMPLETE (no failure response yet) until the final read, Fri 2026-11-27 (Config gate0_final_read), when a shortfall is FAIL.
A28: Strict read: named $500 or more BEFORE hearing $1,500, and controls the budget | B28: =COUNTIF(Brand_Log!$DH$2:$DH$201,1) -> 1 | C28: =COUNTIF(Brand_Log!$DI$2:$DI$201,1) -> 2 | D28: =COUNTIF(Brand_Log!$DJ$2:$DJ$201,1) -> 5 | E28: =COUNTIF(Brand_Log!$DK$2:$DK$201,1) -> 6 | G28: Shown so an anchored answer is not mistaken for an unprompted one. Withdrawn answers are left out here too.
A29: Withdrawn after saying $500 or more (a later call: no budget control, or a lower number): not counted | B29: =COUNTIF(Brand_Log!$DL$2:$DL$201,1) -> 0 | C29: =COUNTIF(Brand_Log!$DM$2:$DM$201,1) -> 0 | D29: =COUNTIF(Brand_Log!$DN$2:$DN$201,1) -> 0 | E29: =COUNTIF(Brand_Log!$DO$2:$DO$201,1) -> 0 | G29: Brands that qualified and later withdrew, by the cut-off. The financial model still counts them until it adopts the same rule (HANDOFF 2.3).
A30: Said $500 or more but the speaker does not control the budget | B30: =COUNTIFS(Brand_Log!$BG$2:$BG$201,1,Brand_Log!$H$2:$H$201,"<"&(B$6+1)) -> 0 | C30: =COUNTIFS(Brand_Log!$BG$2:$BG$201,1,Brand_Log!$H$2:$H$201,"<"&(C$6+1)) -> 1 | D30: =COUNTIFS(Brand_Log!$BG$2:$BG$201,1,Brand_Log!$H$2:$H$201,"<"&(D$6+1)) -> 1 | E30: =COUNTIFS(Brand_Log!$BG$2:$BG$201,1,Brand_Log!$H$2:$H$201,"<"&(E$6+1)) -> 1 | G30: Not counted for Gate 0 from that conversation. Ask for a call with the budget owner.
A31: Median brand number before $1,500 was mentioned, USD per campaign | B31: =IF(COUNT(Brand_Log!$BJ$2:$BJ$201)=0,"none yet",MEDIAN(Brand_Log!$BJ$2:$BJ$201)) -> 375 | C31: =IF(COUNT(Brand_Log!$BK$2:$BK$201)=0,"none yet",MEDIAN(Brand_Log!$BK$2:$BK$201)) -> 400 | D31: =IF(COUNT(Brand_Log!$BL$2:$BL$201)=0,"none yet",MEDIAN(Brand_Log!$BL$2:$BL$201)) -> 500 | E31: =IF(COUNT(Brand_Log!$BM$2:$BM$201)=0,"none yet",MEDIAN(Brand_Log!$BM$2:$BM$201)) -> 500 | G31: First numeric before-answer per brand; 'nothing' counts as 0; no number is left out.
A32: Brands that named a number before $1,500 | B32: =COUNT(Brand_Log!$BJ$2:$BJ$201) -> 2 | C32: =COUNT(Brand_Log!$BK$2:$BK$201) -> 6 | D32: =COUNT(Brand_Log!$BL$2:$BL$201) -> 11 | E32: =COUNT(Brand_Log!$BM$2:$BM$201) -> 13 | G32: The n behind the median.
A33: Median brand number after hearing $1,500, USD per campaign | B33: =IF(COUNT(Brand_Log!$BP$2:$BP$201)=0,"none yet",MEDIAN(Brand_Log!$BP$2:$BP$201)) -> 600 | C33: =IF(COUNT(Brand_Log!$BQ$2:$BQ$201)=0,"none yet",MEDIAN(Brand_Log!$BQ$2:$BQ$201)) -> 700 | D33: =IF(COUNT(Brand_Log!$BR$2:$BR$201)=0,"none yet",MEDIAN(Brand_Log!$BR$2:$BR$201)) -> 800 | E33: =IF(COUNT(Brand_Log!$BS$2:$BS$201)=0,"none yet",MEDIAN(Brand_Log!$BS$2:$BS$201)) -> 850 | G33: First numeric after-answer per brand.
A34: Brands that answered after hearing $1,500 | B34: =COUNT(Brand_Log!$BP$2:$BP$201) -> 3 | C34: =COUNT(Brand_Log!$BQ$2:$BQ$201) -> 6 | D34: =COUNT(Brand_Log!$BR$2:$BR$201) -> 7 | E34: =COUNT(Brand_Log!$BS$2:$BS$201) -> 8 | G34: The n behind the median.
A35: Brands qualified on a call (all seven checks Y, not excluded) | B35: =COUNTIFS(Brand_Log!$CE$2:$CE$201,1,Brand_Log!$H$2:$H$201,"<"&(B$6+1)) -> 2 | C35: =COUNTIFS(Brand_Log!$CE$2:$CE$201,1,Brand_Log!$H$2:$H$201,"<"&(C$6+1)) -> 2 | D35: =COUNTIFS(Brand_Log!$CE$2:$CE$201,1,Brand_Log!$H$2:$H$201,"<"&(D$6+1)) -> 5 | E35: =COUNTIFS(Brand_Log!$CE$2:$CE$201,1,Brand_Log!$H$2:$H$201,"<"&(E$6+1)) -> 5 | G35: From the qualifying-call columns (qual_q1 to qual_q7, qual_not_excluded). The brand's word; the founder verifies at payment.
A36: Shortlisted brands (shortlist = Y) | B36: =COUNTIFS(Brand_Log!$CG$2:$CG$201,1,Brand_Log!$H$2:$H$201,"<"&(B$6+1)) -> 2 | C36: =COUNTIFS(Brand_Log!$CG$2:$CG$201,1,Brand_Log!$H$2:$H$201,"<"&(C$6+1)) -> 3 | D36: =COUNTIFS(Brand_Log!$CG$2:$CG$201,1,Brand_Log!$H$2:$H$201,"<"&(D$6+1)) -> 6 | E36: =COUNTIFS(Brand_Log!$CG$2:$CG$201,1,Brand_Log!$H$2:$H$201,"<"&(E$6+1)) -> 7 | F36: 6 | G36: Plan Phase 0 deliverable: a shortlist of 6 brands to pursue.
A37: Median quarterly sampling budget, USD (low end), as of | E37: =IF(COUNT(Brand_Log!$BV$2:$BV$201)=0,"none yet",MEDIAN(Brand_Log!$BV$2:$BV$201)) -> 2000 | F37: =COUNT(Brand_Log!$BV$2:$BV$201) -> 15 | G37: From Q2. Context: a $600 or $1,500 campaign against what they spend now.
A39: Gate 0 overall | J39: Objection counts used for the top three (as of). Ties go to the code listed first.
A40: Gate 0 result | B40: =IF(AND(B10="PASS",B27="PASS"),"PASS",IF(OR(B10="FAIL",B27="FAIL"),"FAIL",IF(OR(LEFT(B10,10)="INCOMPLETE",LEFT(B27,10)="INCOMPLETE"),"INCOMPLETE","not yet"))) -> not yet | C40: =IF(AND(C10="PASS",C27="PASS"),"PASS",IF(OR(C10="FAIL",C27="FAIL"),"FAIL",IF(OR(LEFT(C10,10)="INCOMPLETE",LEFT(C27,10)="INCOMPLETE"),"INCOMPLETE","not yet"))) -> not yet | D40: =IF(AND(D10="PASS",D27="PASS"),"PASS",IF(OR(D10="FAIL",D27="FAIL"),"FAIL",IF(OR(LEFT(D10,10)="INCOMPLETE",LEFT(D27,10)="INCOMPLETE"),"INCOMPLETE","not yet"))) -> PASS | E40: =IF(AND(E10="PASS",E27="PASS"),"PASS",IF(OR(E10="FAIL",E27="FAIL"),"FAIL",IF(OR(LEFT(E10,10)="INCOMPLETE",LEFT(E27,10)="INCOMPLETE"),"INCOMPLETE","not yet"))) -> PASS | J40: office code | K40: office label | L40: office mentions | M40: office score | O40: brand code | P40: brand label | Q40: brand mentions | R40: brand score
A41: Sentence for the Gate 0 decision (as of) | B41: ="As of "&TEXT(E$6,"yyyy-mm-dd")&": "&E9&" of "&E8&" offices said yes with a pantry owner and a receiving window (target "&F9&"); "&E26&" of "&E25&" brands would pay $"&Config!$B$14&" or more and control the budget (target "&F26&"). Gate 0: "&E40&"." -> As of 2026-12-11: 6 of 14 offices said yes with a pantry owner and a receiving window (target 5); 7 of 15 brands would pay $500 or more and control the budget (target 3). Gate 0: PASS. | J41: needs_approval | K41: I need to ask facilities, HR or someone else | L41: =COUNTIFS(Office_Log!$BV$2:$BV$201,J41,Office_Log!$H$2:$H$201,"<"&($E$6+1))+COUNTIFS(Office_Log!$BW$2:$BW$201,J41,Office_Log!$H$2:$H$201,"<"&($E$6+1))+COUNTIFS(Office_Log!$BX$2:$BX$201,J41,Office_Log!$H$2:$H$201,"<"&($E$6+1)) -> 6 | M41: =L41-1/1000 -> 5.999 | O41: seed_ourselves | P41: We can seed offices ourselves for free | Q41: =COUNTIFS(Brand_Log!$BX$2:$BX$201,O41,Brand_Log!$H$2:$H$201,"<"&($E$6+1))+COUNTIFS(Brand_Log!$BY$2:$BY$201,O41,Brand_Log!$H$2:$H$201,"<"&($E$6+1))+COUNTIFS(Brand_Log!$BZ$2:$BZ$201,O41,Brand_Log!$H$2:$H$201,"<"&($E$6+1)) -> 3 | R41: =Q41-1/1000 -> 2.999
A42: If it fails (plan) | B42: Fewer than 3 brands: test the office-paid version for three more weeks. Fewer than 5 offices: change the cluster or the office size band, not the model. | J42: existing_vendor | K42: We already have a pantry vendor or contract | L42: =COUNTIFS(Office_Log!$BV$2:$BV$201,J42,Office_Log!$H$2:$H$201,"<"&($E$6+1))+COUNTIFS(Office_Log!$BW$2:$BW$201,J42,Office_Log!$H$2:$H$201,"<"&($E$6+1))+COUNTIFS(Office_Log!$BX$2:$BX$201,J42,Office_Log!$H$2:$H$201,"<"&($E$6+1)) -> 2 | M42: =L42-2/1000 -> 1.998 | O42: price_per_sample | P42: $600 / the price is more than we pay per sample elsewhere | Q42: =COUNTIFS(Brand_Log!$BX$2:$BX$201,O42,Brand_Log!$H$2:$H$201,"<"&($E$6+1))+COUNTIFS(Brand_Log!$BY$2:$BY$201,O42,Brand_Log!$H$2:$H$201,"<"&($E$6+1))+COUNTIFS(Brand_Log!$BZ$2:$BZ$201,O42,Brand_Log!$H$2:$H$201,"<"&($E$6+1)) -> 4 | R42: =Q42-2/1000 -> 3.998
A43: If a side is INCOMPLETE (default, founder to confirm) | B43: Do not apply the failure response above to an INCOMPLETE side yet: the plan's test (5 of 15, 3 of 15) has not been run. Keep booking discovery calls on that side and read the As of column again on Fri 2026-11-20 (set Config as_of_date). The final read is Fri 2026-11-27 (Config gate0_final_read): from then a side still short reads FAIL and the response applies, the plan's 'stretch the weeks but keep the gates'. A side that passed goes ahead meanwhile. | J43: allergy_policy | K43: Allergy or food-safety worry | L43: =COUNTIFS(Office_Log!$BV$2:$BV$201,J43,Office_Log!$H$2:$H$201,"<"&($E$6+1))+COUNTIFS(Office_Log!$BW$2:$BW$201,J43,Office_Log!$H$2:$H$201,"<"&($E$6+1))+COUNTIFS(Office_Log!$BX$2:$BX$201,J43,Office_Log!$H$2:$H$201,"<"&($E$6+1)) -> 5 | M43: =L43-3/1000 -> 4.997 | O43: free_trial | P43: Can we do a free trial first? | Q43: =COUNTIFS(Brand_Log!$BX$2:$BX$201,O43,Brand_Log!$H$2:$H$201,"<"&($E$6+1))+COUNTIFS(Brand_Log!$BY$2:$BY$201,O43,Brand_Log!$H$2:$H$201,"<"&($E$6+1))+COUNTIFS(Brand_Log!$BZ$2:$BZ$201,O43,Brand_Log!$H$2:$H$201,"<"&($E$6+1)) -> 2 | R43: =Q43-3/1000 -> 1.997
J44: healthy_policy | K44: We only stock healthy items (wellness policy) | L44: =COUNTIFS(Office_Log!$BV$2:$BV$201,J44,Office_Log!$H$2:$H$201,"<"&($E$6+1))+COUNTIFS(Office_Log!$BW$2:$BW$201,J44,Office_Log!$H$2:$H$201,"<"&($E$6+1))+COUNTIFS(Office_Log!$BX$2:$BX$201,J44,Office_Log!$H$2:$H$201,"<"&($E$6+1)) -> 0 | M44: =L44-4/1000 -> -0.004 | O44: what_we_get | P44: What do we actually get out of it? | Q44: =COUNTIFS(Brand_Log!$BX$2:$BX$201,O44,Brand_Log!$H$2:$H$201,"<"&($E$6+1))+COUNTIFS(Brand_Log!$BY$2:$BY$201,O44,Brand_Log!$H$2:$H$201,"<"&($E$6+1))+COUNTIFS(Brand_Log!$BZ$2:$BZ$201,O44,Brand_Log!$H$2:$H$201,"<"&($E$6+1)) -> 3 | R44: =Q44-4/1000 -> 2.996
A45: Top three objections per side, as of (mentions across objection_1 to objection_3) | J45: building_receiving | K45: Building security, receiving or certificate rules | L45: =COUNTIFS(Office_Log!$BV$2:$BV$201,J45,Office_Log!$H$2:$H$201,"<"&($E$6+1))+COUNTIFS(Office_Log!$BW$2:$BW$201,J45,Office_Log!$H$2:$H$201,"<"&($E$6+1))+COUNTIFS(Office_Log!$BX$2:$BX$201,J45,Office_Log!$H$2:$H$201,"<"&($E$6+1)) -> 2 | M45: =L45-5/1000 -> 1.995 | O45: budget_timing | P45: No budget now / budget timing | Q45: =COUNTIFS(Brand_Log!$BX$2:$BX$201,O45,Brand_Log!$H$2:$H$201,"<"&($E$6+1))+COUNTIFS(Brand_Log!$BY$2:$BY$201,O45,Brand_Log!$H$2:$H$201,"<"&($E$6+1))+COUNTIFS(Brand_Log!$BZ$2:$BZ$201,O45,Brand_Log!$H$2:$H$201,"<"&($E$6+1)) -> 2 | R45: =Q45-5/1000 -> 1.995
A46: Office | B46: Mentions | C46: First quote logged for that code | J46: low_attendance | K46: Not enough people in on a given day | L46: =COUNTIFS(Office_Log!$BV$2:$BV$201,J46,Office_Log!$H$2:$H$201,"<"&($E$6+1))+COUNTIFS(Office_Log!$BW$2:$BW$201,J46,Office_Log!$H$2:$H$201,"<"&($E$6+1))+COUNTIFS(Office_Log!$BX$2:$BX$201,J46,Office_Log!$H$2:$H$201,"<"&($E$6+1)) -> 0 | M46: =L46-6/1000 -> -0.006 | O46: inventory | P46: Inventory or shipping the units | Q46: =COUNTIFS(Brand_Log!$BX$2:$BX$201,O46,Brand_Log!$H$2:$H$201,"<"&($E$6+1))+COUNTIFS(Brand_Log!$BY$2:$BY$201,O46,Brand_Log!$H$2:$H$201,"<"&($E$6+1))+COUNTIFS(Brand_Log!$BZ$2:$BZ$201,O46,Brand_Log!$H$2:$H$201,"<"&($E$6+1)) -> 1 | R46: =Q46-6/1000 -> 0.994
A47: Office side | J47: commitments_too_much | K47: Photos, survey or debrief are too much work | L47: =COUNTIFS(Office_Log!$BV$2:$BV$201,J47,Office_Log!$H$2:$H$201,"<"&($E$6+1))+COUNTIFS(Office_Log!$BW$2:$BW$201,J47,Office_Log!$H$2:$H$201,"<"&($E$6+1))+COUNTIFS(Office_Log!$BX$2:$BX$201,J47,Office_Log!$H$2:$H$201,"<"&($E$6+1)) -> 1 | M47: =L47-7/1000 -> 0.993 | O47: shelf_life | P47: Shelf life | Q47: =COUNTIFS(Brand_Log!$BX$2:$BX$201,O47,Brand_Log!$H$2:$H$201,"<"&($E$6+1))+COUNTIFS(Brand_Log!$BY$2:$BY$201,O47,Brand_Log!$H$2:$H$201,"<"&($E$6+1))+COUNTIFS(Brand_Log!$BZ$2:$BZ$201,O47,Brand_Log!$H$2:$H$201,"<"&($E$6+1)) -> 1 | R47: =Q47-7/1000 -> 0.993
A48: =IF(INDEX($L$41:$L$53,MATCH(LARGE($M$41:$M$53,1),$M$41:$M$53,0))<1,"1. none logged yet","1. "&INDEX($K$41:$K$53,MATCH(LARGE($M$41:$M$53,1),$M$41:$M$53,0))&" ("&INDEX($J$41:$J$53,MATCH(LARGE($M$41:$M$53,1),$M$41:$M$53,0))&")") -> 1. I need to ask facilities, HR or someone else (needs_approval) | B48: =INDEX($L$41:$L$53,MATCH(LARGE($M$41:$M$53,1),$M$41:$M$53,0)) -> 6 | C48: =IF(B48<1,"",IFERROR(INDEX(Office_Log!$AQ$2:$AQ$201,MATCH(INDEX($J$41:$J$53,MATCH(LARGE($M$41:$M$53,1),$M$41:$M$53,0)),Office_Log!$BV$2:$BV$201,0)),IFERROR(INDEX(Office_Log!$AQ$2:$AQ$201,MATCH(INDEX($J$41:$J$53,MATCH(LARGE($M$41:$M$53,1),$M$41:$M$53,0)),Office_Log!$BW$2:$BW$201,0)),IFERROR(INDEX(Office_Log!$AQ$2:$AQ$201,MATCH(INDEX($J$41:$J$53,MATCH(LARGE($M$41:$M$53,1),$M$41:$M$53,0)),Office_Log!$BX$2:$BX$201,0)),"")))) -> SAMPLE: needs_approval (office 04) | J48: survey_concern | K48: Survey or employee-data worry | L48: =COUNTIFS(Office_Log!$BV$2:$BV$201,J48,Office_Log!$H$2:$H$201,"<"&($E$6+1))+COUNTIFS(Office_Log!$BW$2:$BW$201,J48,Office_Log!$H$2:$H$201,"<"&($E$6+1))+COUNTIFS(Office_Log!$BX$2:$BX$201,J48,Office_Log!$H$2:$H$201,"<"&($E$6+1)) -> 0 | M48: =L48-8/1000 -> -0.008 | O48: not_our_audience | P48: Office workers aren't our customer | Q48: =COUNTIFS(Brand_Log!$BX$2:$BX$201,O48,Brand_Log!$H$2:$H$201,"<"&($E$6+1))+COUNTIFS(Brand_Log!$BY$2:$BY$201,O48,Brand_Log!$H$2:$H$201,"<"&($E$6+1))+COUNTIFS(Brand_Log!$BZ$2:$BZ$201,O48,Brand_Log!$H$2:$H$201,"<"&($E$6+1)) -> 1 | R48: =Q48-8/1000 -> 0.992
A49: =IF(INDEX($L$41:$L$53,MATCH(LARGE($M$41:$M$53,2),$M$41:$M$53,0))<1,"2. none logged yet","2. "&INDEX($K$41:$K$53,MATCH(LARGE($M$41:$M$53,2),$M$41:$M$53,0))&" ("&INDEX($J$41:$J$53,MATCH(LARGE($M$41:$M$53,2),$M$41:$M$53,0))&")") -> 2. Allergy or food-safety worry (allergy_policy) | B49: =INDEX($L$41:$L$53,MATCH(LARGE($M$41:$M$53,2),$M$41:$M$53,0)) -> 5 | C49: =IF(B49<1,"",IFERROR(INDEX(Office_Log!$AQ$2:$AQ$201,MATCH(INDEX($J$41:$J$53,MATCH(LARGE($M$41:$M$53,2),$M$41:$M$53,0)),Office_Log!$BV$2:$BV$201,0)),IFERROR(INDEX(Office_Log!$AQ$2:$AQ$201,MATCH(INDEX($J$41:$J$53,MATCH(LARGE($M$41:$M$53,2),$M$41:$M$53,0)),Office_Log!$BW$2:$BW$201,0)),IFERROR(INDEX(Office_Log!$AQ$2:$AQ$201,MATCH(INDEX($J$41:$J$53,MATCH(LARGE($M$41:$M$53,2),$M$41:$M$53,0)),Office_Log!$BX$2:$BX$201,0)),"")))) -> SAMPLE: allergy_policy (office 01) | J49: vendor_fatigue | K49: We don't want vendors or marketing in the office | L49: =COUNTIFS(Office_Log!$BV$2:$BV$201,J49,Office_Log!$H$2:$H$201,"<"&($E$6+1))+COUNTIFS(Office_Log!$BW$2:$BW$201,J49,Office_Log!$H$2:$H$201,"<"&($E$6+1))+COUNTIFS(Office_Log!$BX$2:$BX$201,J49,Office_Log!$H$2:$H$201,"<"&($E$6+1)) -> 1 | M49: =L49-9/1000 -> 0.991 | O49: want_proof | P49: Show me results from other brands first | Q49: =COUNTIFS(Brand_Log!$BX$2:$BX$201,O49,Brand_Log!$H$2:$H$201,"<"&($E$6+1))+COUNTIFS(Brand_Log!$BY$2:$BY$201,O49,Brand_Log!$H$2:$H$201,"<"&($E$6+1))+COUNTIFS(Brand_Log!$BZ$2:$BZ$201,O49,Brand_Log!$H$2:$H$201,"<"&($E$6+1)) -> 0 | R49: =Q49-9/1000 -> -0.009
A50: =IF(INDEX($L$41:$L$53,MATCH(LARGE($M$41:$M$53,3),$M$41:$M$53,0))<1,"3. none logged yet","3. "&INDEX($K$41:$K$53,MATCH(LARGE($M$41:$M$53,3),$M$41:$M$53,0))&" ("&INDEX($J$41:$J$53,MATCH(LARGE($M$41:$M$53,3),$M$41:$M$53,0))&")") -> 3. We already have a pantry vendor or contract (existing_vendor) | B50: =INDEX($L$41:$L$53,MATCH(LARGE($M$41:$M$53,3),$M$41:$M$53,0)) -> 2 | C50: =IF(B50<1,"",IFERROR(INDEX(Office_Log!$AQ$2:$AQ$201,MATCH(INDEX($J$41:$J$53,MATCH(LARGE($M$41:$M$53,3),$M$41:$M$53,0)),Office_Log!$BV$2:$BV$201,0)),IFERROR(INDEX(Office_Log!$AQ$2:$AQ$201,MATCH(INDEX($J$41:$J$53,MATCH(LARGE($M$41:$M$53,3),$M$41:$M$53,0)),Office_Log!$BW$2:$BW$201,0)),IFERROR(INDEX(Office_Log!$AQ$2:$AQ$201,MATCH(INDEX($J$41:$J$53,MATCH(LARGE($M$41:$M$53,3),$M$41:$M$53,0)),Office_Log!$BX$2:$BX$201,0)),"")))) -> SAMPLE: existing_vendor / allergy_policy (office 02) | J50: space | K50: No shelf or counter space | L50: =COUNTIFS(Office_Log!$BV$2:$BV$201,J50,Office_Log!$H$2:$H$201,"<"&($E$6+1))+COUNTIFS(Office_Log!$BW$2:$BW$201,J50,Office_Log!$H$2:$H$201,"<"&($E$6+1))+COUNTIFS(Office_Log!$BX$2:$BX$201,J50,Office_Log!$H$2:$H$201,"<"&($E$6+1)) -> 0 | M50: =L50-10/1000 -> -0.01 | O50: want_sales_data | P50: We need sales or lift data, not feedback | Q50: =COUNTIFS(Brand_Log!$BX$2:$BX$201,O50,Brand_Log!$H$2:$H$201,"<"&($E$6+1))+COUNTIFS(Brand_Log!$BY$2:$BY$201,O50,Brand_Log!$H$2:$H$201,"<"&($E$6+1))+COUNTIFS(Brand_Log!$BZ$2:$BZ$201,O50,Brand_Log!$H$2:$H$201,"<"&($E$6+1)) -> 1 | R50: =Q50-10/1000 -> 0.99
A51: Brand side | J51: supply_irregular | K51: Irregular, roughly monthly supply isn't useful | L51: =COUNTIFS(Office_Log!$BV$2:$BV$201,J51,Office_Log!$H$2:$H$201,"<"&($E$6+1))+COUNTIFS(Office_Log!$BW$2:$BW$201,J51,Office_Log!$H$2:$H$201,"<"&($E$6+1))+COUNTIFS(Office_Log!$BX$2:$BX$201,J51,Office_Log!$H$2:$H$201,"<"&($E$6+1)) -> 0 | M51: =L51-11/1000 -> -0.011 | O51: no_buy_path | P51: No store near the cluster and no online code | Q51: =COUNTIFS(Brand_Log!$BX$2:$BX$201,O51,Brand_Log!$H$2:$H$201,"<"&($E$6+1))+COUNTIFS(Brand_Log!$BY$2:$BY$201,O51,Brand_Log!$H$2:$H$201,"<"&($E$6+1))+COUNTIFS(Brand_Log!$BZ$2:$BZ$201,O51,Brand_Log!$H$2:$H$201,"<"&($E$6+1)) -> 0 | R51: =Q51-11/1000 -> -0.011
A52: =IF(INDEX($Q$41:$Q$53,MATCH(LARGE($R$41:$R$53,1),$R$41:$R$53,0))<1,"1. none logged yet","1. "&INDEX($P$41:$P$53,MATCH(LARGE($R$41:$R$53,1),$R$41:$R$53,0))&" ("&INDEX($O$41:$O$53,MATCH(LARGE($R$41:$R$53,1),$R$41:$R$53,0))&")") -> 1. $600 / the price is more than we pay per sample elsewhere (price_per_sample) | B52: =INDEX($Q$41:$Q$53,MATCH(LARGE($R$41:$R$53,1),$R$41:$R$53,0)) -> 4 | C52: =IF(B52<1,"",IFERROR(INDEX(Brand_Log!$AM$2:$AM$201,MATCH(INDEX($O$41:$O$53,MATCH(LARGE($R$41:$R$53,1),$R$41:$R$53,0)),Brand_Log!$BX$2:$BX$201,0)),IFERROR(INDEX(Brand_Log!$AM$2:$AM$201,MATCH(INDEX($O$41:$O$53,MATCH(LARGE($R$41:$R$53,1),$R$41:$R$53,0)),Brand_Log!$BY$2:$BY$201,0)),IFERROR(INDEX(Brand_Log!$AM$2:$AM$201,MATCH(INDEX($O$41:$O$53,MATCH(LARGE($R$41:$R$53,1),$R$41:$R$53,0)),Brand_Log!$BZ$2:$BZ$201,0)),"")))) -> SAMPLE: price_per_sample / what_we_get (brand 01) | J52: quality_unknown | K52: Don't know these brands; quality worry | L52: =COUNTIFS(Office_Log!$BV$2:$BV$201,J52,Office_Log!$H$2:$H$201,"<"&($E$6+1))+COUNTIFS(Office_Log!$BW$2:$BW$201,J52,Office_Log!$H$2:$H$201,"<"&($E$6+1))+COUNTIFS(Office_Log!$BX$2:$BX$201,J52,Office_Log!$H$2:$H$201,"<"&($E$6+1)) -> 0 | M52: =L52-12/1000 -> -0.012 | O52: insurance | P52: No product liability certificate | Q52: =COUNTIFS(Brand_Log!$BX$2:$BX$201,O52,Brand_Log!$H$2:$H$201,"<"&($E$6+1))+COUNTIFS(Brand_Log!$BY$2:$BY$201,O52,Brand_Log!$H$2:$H$201,"<"&($E$6+1))+COUNTIFS(Brand_Log!$BZ$2:$BZ$201,O52,Brand_Log!$H$2:$H$201,"<"&($E$6+1)) -> 0 | R52: =Q52-12/1000 -> -0.012
A53: =IF(INDEX($Q$41:$Q$53,MATCH(LARGE($R$41:$R$53,2),$R$41:$R$53,0))<1,"2. none logged yet","2. "&INDEX($P$41:$P$53,MATCH(LARGE($R$41:$R$53,2),$R$41:$R$53,0))&" ("&INDEX($O$41:$O$53,MATCH(LARGE($R$41:$R$53,2),$R$41:$R$53,0))&")") -> 2. We can seed offices ourselves for free (seed_ourselves) | B53: =INDEX($Q$41:$Q$53,MATCH(LARGE($R$41:$R$53,2),$R$41:$R$53,0)) -> 3 | C53: =IF(B53<1,"",IFERROR(INDEX(Brand_Log!$AM$2:$AM$201,MATCH(INDEX($O$41:$O$53,MATCH(LARGE($R$41:$R$53,2),$R$41:$R$53,0)),Brand_Log!$BX$2:$BX$201,0)),IFERROR(INDEX(Brand_Log!$AM$2:$AM$201,MATCH(INDEX($O$41:$O$53,MATCH(LARGE($R$41:$R$53,2),$R$41:$R$53,0)),Brand_Log!$BY$2:$BY$201,0)),IFERROR(INDEX(Brand_Log!$AM$2:$AM$201,MATCH(INDEX($O$41:$O$53,MATCH(LARGE($R$41:$R$53,2),$R$41:$R$53,0)),Brand_Log!$BZ$2:$BZ$201,0)),"")))) -> SAMPLE: seed_ourselves / price_per_sample (brand 03) | J53: other | K53: Other (read the quotes) | L53: =COUNTIFS(Office_Log!$BV$2:$BV$201,J53,Office_Log!$H$2:$H$201,"<"&($E$6+1))+COUNTIFS(Office_Log!$BW$2:$BW$201,J53,Office_Log!$H$2:$H$201,"<"&($E$6+1))+COUNTIFS(Office_Log!$BX$2:$BX$201,J53,Office_Log!$H$2:$H$201,"<"&($E$6+1)) -> 0 | M53: =L53-13/1000 -> -0.013 | O53: other | P53: Other (read the quotes) | Q53: =COUNTIFS(Brand_Log!$BX$2:$BX$201,O53,Brand_Log!$H$2:$H$201,"<"&($E$6+1))+COUNTIFS(Brand_Log!$BY$2:$BY$201,O53,Brand_Log!$H$2:$H$201,"<"&($E$6+1))+COUNTIFS(Brand_Log!$BZ$2:$BZ$201,O53,Brand_Log!$H$2:$H$201,"<"&($E$6+1)) -> 0 | R53: =Q53-13/1000 -> -0.013
A54: =IF(INDEX($Q$41:$Q$53,MATCH(LARGE($R$41:$R$53,3),$R$41:$R$53,0))<1,"3. none logged yet","3. "&INDEX($P$41:$P$53,MATCH(LARGE($R$41:$R$53,3),$R$41:$R$53,0))&" ("&INDEX($O$41:$O$53,MATCH(LARGE($R$41:$R$53,3),$R$41:$R$53,0))&")") -> 3. What do we actually get out of it? (what_we_get) | B54: =INDEX($Q$41:$Q$53,MATCH(LARGE($R$41:$R$53,3),$R$41:$R$53,0)) -> 3 | C54: =IF(B54<1,"",IFERROR(INDEX(Brand_Log!$AM$2:$AM$201,MATCH(INDEX($O$41:$O$53,MATCH(LARGE($R$41:$R$53,3),$R$41:$R$53,0)),Brand_Log!$BX$2:$BX$201,0)),IFERROR(INDEX(Brand_Log!$AM$2:$AM$201,MATCH(INDEX($O$41:$O$53,MATCH(LARGE($R$41:$R$53,3),$R$41:$R$53,0)),Brand_Log!$BY$2:$BY$201,0)),IFERROR(INDEX(Brand_Log!$AM$2:$AM$201,MATCH(INDEX($O$41:$O$53,MATCH(LARGE($R$41:$R$53,3),$R$41:$R$53,0)),Brand_Log!$BZ$2:$BZ$201,0)),"")))) -> SAMPLE: what_we_get (brand 04)
A56: Pace and reply rate (from the Friday Clay paste)
A57: Measure | B57: Fri wk 1 | C57: Fri wk 2 | D57: Gate 0 | E57: As of | G57: How it is counted
A58: Office first touches sent | B58: =IFERROR(COUNTIFS(INDEX(Clay_Offices!$A$2:$FZ$601,0,Sync!$C$11),"<"&(B$6+1),INDEX(Clay_Offices!$A$2:$FZ$601,0,Sync!$C$5),Config!$B$20),0) -> 14 | C58: =IFERROR(COUNTIFS(INDEX(Clay_Offices!$A$2:$FZ$601,0,Sync!$C$11),"<"&(C$6+1),INDEX(Clay_Offices!$A$2:$FZ$601,0,Sync!$C$5),Config!$B$20),0) -> 27 | D58: =IFERROR(COUNTIFS(INDEX(Clay_Offices!$A$2:$FZ$601,0,Sync!$C$11),"<"&(D$6+1),INDEX(Clay_Offices!$A$2:$FZ$601,0,Sync!$C$5),Config!$B$20),0) -> 33 | E58: =IFERROR(COUNTIFS(INDEX(Clay_Offices!$A$2:$FZ$601,0,Sync!$C$11),"<"&(E$6+1),INDEX(Clay_Offices!$A$2:$FZ$601,0,Sync!$C$5),Config!$B$20),0) -> 39 | G58: Clay rows with touch_1_date on or before the cut-off.
A59: Office replies, all (any human reply, opt-outs included) | B59: =IFERROR(COUNTIFS(INDEX(Clay_Offices!$A$2:$FZ$601,0,Sync!$C$14),"<"&(B$6+1),INDEX(Clay_Offices!$A$2:$FZ$601,0,Sync!$C$5),Config!$B$20,INDEX(Clay_Offices!$A$2:$FZ$601,0,Sync!$C$15),"<>bounce",INDEX(Clay_Offices!$A$2:$FZ$601,0,Sync!$C$15),"<>out_of_office"),0) -> 9 | C59: =IFERROR(COUNTIFS(INDEX(Clay_Offices!$A$2:$FZ$601,0,Sync!$C$14),"<"&(C$6+1),INDEX(Clay_Offices!$A$2:$FZ$601,0,Sync!$C$5),Config!$B$20,INDEX(Clay_Offices!$A$2:$FZ$601,0,Sync!$C$15),"<>bounce",INDEX(Clay_Offices!$A$2:$FZ$601,0,Sync!$C$15),"<>out_of_office"),0) -> 18 | D59: =IFERROR(COUNTIFS(INDEX(Clay_Offices!$A$2:$FZ$601,0,Sync!$C$14),"<"&(D$6+1),INDEX(Clay_Offices!$A$2:$FZ$601,0,Sync!$C$5),Config!$B$20,INDEX(Clay_Offices!$A$2:$FZ$601,0,Sync!$C$15),"<>bounce",INDEX(Clay_Offices!$A$2:$FZ$601,0,Sync!$C$15),"<>out_of_office"),0) -> 22 | E59: =IFERROR(COUNTIFS(INDEX(Clay_Offices!$A$2:$FZ$601,0,Sync!$C$14),"<"&(E$6+1),INDEX(Clay_Offices!$A$2:$FZ$601,0,Sync!$C$5),Config!$B$20,INDEX(Clay_Offices!$A$2:$FZ$601,0,Sync!$C$15),"<>bounce",INDEX(Clay_Offices!$A$2:$FZ$601,0,Sync!$C$15),"<>out_of_office"),0) -> 24 | G59: Rows with last_reply_date on or before the cut-off; bounces and auto-replies excluded. Information only.
A60: Office reply rate, all replies (information only) | B60: =IF(B58=0,"",B59/B58) -> 0.64285714 | C60: =IF(C58=0,"",C59/C58) -> 0.66666667 | D60: =IF(D58=0,"",D59/D58) -> 0.66666667 | E60: =IF(E58=0,"",E59/E58) -> 0.61538462 | G60: All replies / first touches. Opt-outs and refusals count here, so this rate can look healthy while conversations fall short. It does not drive the check.
A61: Office conversation replies | B61: =IFERROR(COUNTIFS(INDEX(Clay_Offices!$A$2:$FZ$601,0,Sync!$C$14),"<"&(B$6+1),INDEX(Clay_Offices!$A$2:$FZ$601,0,Sync!$C$5),Config!$B$20,INDEX(Clay_Offices!$A$2:$FZ$601,0,Sync!$C$15),"yes"),0)+IFERROR(COUNTIFS(INDEX(Clay_Offices!$A$2:$FZ$601,0,Sync!$C$14),"<"&(B$6+1),INDEX(Clay_Offices!$A$2:$FZ$601,0,Sync!$C$5),Config!$B$20,INDEX(Clay_Offices!$A$2:$FZ$601,0,Sync!$C$15),"maybe"),0)+IFERROR(COUNTIFS(INDEX(Clay_Offices!$A$2:$FZ$601,0,Sync!$C$14),"<"&(B$6+1),INDEX(Clay_Offices!$A$2:$FZ$601,0,Sync!$C$5),Config!$B$20,INDEX(Clay_Offices!$A$2:$FZ$601,0,Sync!$C$15),"needs_approval"),0)+IFERROR(COUNTIFS(INDEX(Clay_Offices!$A$2:$FZ$601,0,Sync!$C$14),"<"&(B$6+1),INDEX(Clay_Offices!$A$2:$FZ$601,0,Sync!$C$5),Config!$B$20,INDEX(Clay_Offices!$A$2:$FZ$601,0,Sync!$C$15),"send_info"),0)+IFERROR(COUNTIFS(INDEX(Clay_Offices!$A$2:$FZ$601,0,Sync!$C$14),"<"&(B$6+1),INDEX(Clay_Offices!$A$2:$FZ$601,0,Sync!$C$5),Config!$B$20,INDEX(Clay_Offices!$A$2:$FZ$601,0,Sync!$C$15),"referral"),0)+IFERROR(COUNTIFS(INDEX(Clay_Offices!$A$2:$FZ$601,0,Sync!$C$14),"<"&(B$6+1),INDEX(Clay_Offices!$A$2:$FZ$601,0,Sync!$C$5),Config!$B$20,INDEX(Clay_Offices!$A$2:$FZ$601,0,Sync!$C$15),"not_now"),0)+IFERROR(COUNTIFS(INDEX(Clay_Offices!$A$2:$FZ$601,0,Sync!$C$14),"<"&(B$6+1),INDEX(Clay_Offices!$A$2:$FZ$601,0,Sync!$C$5),Config!$B$20,INDEX(Clay_Offices!$A$2:$FZ$601,0,Sync!$C$15),"obj_seed_ourselves"),0)+IFERROR(COUNTIFS(INDEX(Clay_Offices!$A$2:$FZ$601,0,Sync!$C$14),"<"&(B$6+1),INDEX(Clay_Offices!$A$2:$FZ$601,0,Sync!$C$5),Config!$B$20,INDEX(Clay_Offices!$A$2:$FZ$601,0,Sync!$C$15),"obj_price"),0)+IFERROR(COUNTIFS(INDEX(Clay_Offices!$A$2:$FZ$601,0,Sync!$C$14),"<"&(B$6+1),INDEX(Clay_Offices!$A$2:$FZ$601,0,Sync!$C$5),Config!$B$20,INDEX(Clay_Offices!$A$2:$FZ$601,0,Sync!$C$15),"obj_free_trial"),0)+IFERROR(COUNTIFS(INDEX(Clay_Offices!$A$2:$FZ$601,0,Sync!$C$14),"<"&(B$6+1),INDEX(Clay_Offices!$A$2:$FZ$601,0,Sync!$C$5),Config!$B$20,INDEX(Clay_Offices!$A$2:$FZ$601,0,Sync!$C$15),"obj_what_we_get"),0)+IFERROR(COUNTIFS(INDEX(Clay_Offices!$A$2:$FZ$601,0,Sync!$C$14),"<"&(B$6+1),INDEX(Clay_Offices!$A$2:$FZ$601,0,Sync!$C$5),Config!$B$20,INDEX(Clay_Offices!$A$2:$FZ$601,0,Sync!$C$15),"obj_other"),0) -> 8 | C61: =IFERROR(COUNTIFS(INDEX(Clay_Offices!$A$2:$FZ$601,0,Sync!$C$14),"<"&(C$6+1),INDEX(Clay_Offices!$A$2:$FZ$601,0,Sync!$C$5),Config!$B$20,INDEX(Clay_Offices!$A$2:$FZ$601,0,Sync!$C$15),"yes"),0)+IFERROR(COUNTIFS(INDEX(Clay_Offices!$A$2:$FZ$601,0,Sync!$C$14),"<"&(C$6+1),INDEX(Clay_Offices!$A$2:$FZ$601,0,Sync!$C$5),Config!$B$20,INDEX(Clay_Offices!$A$2:$FZ$601,0,Sync!$C$15),"maybe"),0)+IFERROR(COUNTIFS(INDEX(Clay_Offices!$A$2:$FZ$601,0,Sync!$C$14),"<"&(C$6+1),INDEX(Clay_Offices!$A$2:$FZ$601,0,Sync!$C$5),Config!$B$20,INDEX(Clay_Offices!$A$2:$FZ$601,0,Sync!$C$15),"needs_approval"),0)+IFERROR(COUNTIFS(INDEX(Clay_Offices!$A$2:$FZ$601,0,Sync!$C$14),"<"&(C$6+1),INDEX(Clay_Offices!$A$2:$FZ$601,0,Sync!$C$5),Config!$B$20,INDEX(Clay_Offices!$A$2:$FZ$601,0,Sync!$C$15),"send_info"),0)+IFERROR(COUNTIFS(INDEX(Clay_Offices!$A$2:$FZ$601,0,Sync!$C$14),"<"&(C$6+1),INDEX(Clay_Offices!$A$2:$FZ$601,0,Sync!$C$5),Config!$B$20,INDEX(Clay_Offices!$A$2:$FZ$601,0,Sync!$C$15),"referral"),0)+IFERROR(COUNTIFS(INDEX(Clay_Offices!$A$2:$FZ$601,0,Sync!$C$14),"<"&(C$6+1),INDEX(Clay_Offices!$A$2:$FZ$601,0,Sync!$C$5),Config!$B$20,INDEX(Clay_Offices!$A$2:$FZ$601,0,Sync!$C$15),"not_now"),0)+IFERROR(COUNTIFS(INDEX(Clay_Offices!$A$2:$FZ$601,0,Sync!$C$14),"<"&(C$6+1),INDEX(Clay_Offices!$A$2:$FZ$601,0,Sync!$C$5),Config!$B$20,INDEX(Clay_Offices!$A$2:$FZ$601,0,Sync!$C$15),"obj_seed_ourselves"),0)+IFERROR(COUNTIFS(INDEX(Clay_Offices!$A$2:$FZ$601,0,Sync!$C$14),"<"&(C$6+1),INDEX(Clay_Offices!$A$2:$FZ$601,0,Sync!$C$5),Config!$B$20,INDEX(Clay_Offices!$A$2:$FZ$601,0,Sync!$C$15),"obj_price"),0)+IFERROR(COUNTIFS(INDEX(Clay_Offices!$A$2:$FZ$601,0,Sync!$C$14),"<"&(C$6+1),INDEX(Clay_Offices!$A$2:$FZ$601,0,Sync!$C$5),Config!$B$20,INDEX(Clay_Offices!$A$2:$FZ$601,0,Sync!$C$15),"obj_free_trial"),0)+IFERROR(COUNTIFS(INDEX(Clay_Offices!$A$2:$FZ$601,0,Sync!$C$14),"<"&(C$6+1),INDEX(Clay_Offices!$A$2:$FZ$601,0,Sync!$C$5),Config!$B$20,INDEX(Clay_Offices!$A$2:$FZ$601,0,Sync!$C$15),"obj_what_we_get"),0)+IFERROR(COUNTIFS(INDEX(Clay_Offices!$A$2:$FZ$601,0,Sync!$C$14),"<"&(C$6+1),INDEX(Clay_Offices!$A$2:$FZ$601,0,Sync!$C$5),Config!$B$20,INDEX(Clay_Offices!$A$2:$FZ$601,0,Sync!$C$15),"obj_other"),0) -> 16 | D61: =IFERROR(COUNTIFS(INDEX(Clay_Offices!$A$2:$FZ$601,0,Sync!$C$14),"<"&(D$6+1),INDEX(Clay_Offices!$A$2:$FZ$601,0,Sync!$C$5),Config!$B$20,INDEX(Clay_Offices!$A$2:$FZ$601,0,Sync!$C$15),"yes"),0)+IFERROR(COUNTIFS(INDEX(Clay_Offices!$A$2:$FZ$601,0,Sync!$C$14),"<"&(D$6+1),INDEX(Clay_Offices!$A$2:$FZ$601,0,Sync!$C$5),Config!$B$20,INDEX(Clay_Offices!$A$2:$FZ$601,0,Sync!$C$15),"maybe"),0)+IFERROR(COUNTIFS(INDEX(Clay_Offices!$A$2:$FZ$601,0,Sync!$C$14),"<"&(D$6+1),INDEX(Clay_Offices!$A$2:$FZ$601,0,Sync!$C$5),Config!$B$20,INDEX(Clay_Offices!$A$2:$FZ$601,0,Sync!$C$15),"needs_approval"),0)+IFERROR(COUNTIFS(INDEX(Clay_Offices!$A$2:$FZ$601,0,Sync!$C$14),"<"&(D$6+1),INDEX(Clay_Offices!$A$2:$FZ$601,0,Sync!$C$5),Config!$B$20,INDEX(Clay_Offices!$A$2:$FZ$601,0,Sync!$C$15),"send_info"),0)+IFERROR(COUNTIFS(INDEX(Clay_Offices!$A$2:$FZ$601,0,Sync!$C$14),"<"&(D$6+1),INDEX(Clay_Offices!$A$2:$FZ$601,0,Sync!$C$5),Config!$B$20,INDEX(Clay_Offices!$A$2:$FZ$601,0,Sync!$C$15),"referral"),0)+IFERROR(COUNTIFS(INDEX(Clay_Offices!$A$2:$FZ$601,0,Sync!$C$14),"<"&(D$6+1),INDEX(Clay_Offices!$A$2:$FZ$601,0,Sync!$C$5),Config!$B$20,INDEX(Clay_Offices!$A$2:$FZ$601,0,Sync!$C$15),"not_now"),0)+IFERROR(COUNTIFS(INDEX(Clay_Offices!$A$2:$FZ$601,0,Sync!$C$14),"<"&(D$6+1),INDEX(Clay_Offices!$A$2:$FZ$601,0,Sync!$C$5),Config!$B$20,INDEX(Clay_Offices!$A$2:$FZ$601,0,Sync!$C$15),"obj_seed_ourselves"),0)+IFERROR(COUNTIFS(INDEX(Clay_Offices!$A$2:$FZ$601,0,Sync!$C$14),"<"&(D$6+1),INDEX(Clay_Offices!$A$2:$FZ$601,0,Sync!$C$5),Config!$B$20,INDEX(Clay_Offices!$A$2:$FZ$601,0,Sync!$C$15),"obj_price"),0)+IFERROR(COUNTIFS(INDEX(Clay_Offices!$A$2:$FZ$601,0,Sync!$C$14),"<"&(D$6+1),INDEX(Clay_Offices!$A$2:$FZ$601,0,Sync!$C$5),Config!$B$20,INDEX(Clay_Offices!$A$2:$FZ$601,0,Sync!$C$15),"obj_free_trial"),0)+IFERROR(COUNTIFS(INDEX(Clay_Offices!$A$2:$FZ$601,0,Sync!$C$14),"<"&(D$6+1),INDEX(Clay_Offices!$A$2:$FZ$601,0,Sync!$C$5),Config!$B$20,INDEX(Clay_Offices!$A$2:$FZ$601,0,Sync!$C$15),"obj_what_we_get"),0)+IFERROR(COUNTIFS(INDEX(Clay_Offices!$A$2:$FZ$601,0,Sync!$C$14),"<"&(D$6+1),INDEX(Clay_Offices!$A$2:$FZ$601,0,Sync!$C$5),Config!$B$20,INDEX(Clay_Offices!$A$2:$FZ$601,0,Sync!$C$15),"obj_other"),0) -> 18 | E61: =IFERROR(COUNTIFS(INDEX(Clay_Offices!$A$2:$FZ$601,0,Sync!$C$14),"<"&(E$6+1),INDEX(Clay_Offices!$A$2:$FZ$601,0,Sync!$C$5),Config!$B$20,INDEX(Clay_Offices!$A$2:$FZ$601,0,Sync!$C$15),"yes"),0)+IFERROR(COUNTIFS(INDEX(Clay_Offices!$A$2:$FZ$601,0,Sync!$C$14),"<"&(E$6+1),INDEX(Clay_Offices!$A$2:$FZ$601,0,Sync!$C$5),Config!$B$20,INDEX(Clay_Offices!$A$2:$FZ$601,0,Sync!$C$15),"maybe"),0)+IFERROR(COUNTIFS(INDEX(Clay_Offices!$A$2:$FZ$601,0,Sync!$C$14),"<"&(E$6+1),INDEX(Clay_Offices!$A$2:$FZ$601,0,Sync!$C$5),Config!$B$20,INDEX(Clay_Offices!$A$2:$FZ$601,0,Sync!$C$15),"needs_approval"),0)+IFERROR(COUNTIFS(INDEX(Clay_Offices!$A$2:$FZ$601,0,Sync!$C$14),"<"&(E$6+1),INDEX(Clay_Offices!$A$2:$FZ$601,0,Sync!$C$5),Config!$B$20,INDEX(Clay_Offices!$A$2:$FZ$601,0,Sync!$C$15),"send_info"),0)+IFERROR(COUNTIFS(INDEX(Clay_Offices!$A$2:$FZ$601,0,Sync!$C$14),"<"&(E$6+1),INDEX(Clay_Offices!$A$2:$FZ$601,0,Sync!$C$5),Config!$B$20,INDEX(Clay_Offices!$A$2:$FZ$601,0,Sync!$C$15),"referral"),0)+IFERROR(COUNTIFS(INDEX(Clay_Offices!$A$2:$FZ$601,0,Sync!$C$14),"<"&(E$6+1),INDEX(Clay_Offices!$A$2:$FZ$601,0,Sync!$C$5),Config!$B$20,INDEX(Clay_Offices!$A$2:$FZ$601,0,Sync!$C$15),"not_now"),0)+IFERROR(COUNTIFS(INDEX(Clay_Offices!$A$2:$FZ$601,0,Sync!$C$14),"<"&(E$6+1),INDEX(Clay_Offices!$A$2:$FZ$601,0,Sync!$C$5),Config!$B$20,INDEX(Clay_Offices!$A$2:$FZ$601,0,Sync!$C$15),"obj_seed_ourselves"),0)+IFERROR(COUNTIFS(INDEX(Clay_Offices!$A$2:$FZ$601,0,Sync!$C$14),"<"&(E$6+1),INDEX(Clay_Offices!$A$2:$FZ$601,0,Sync!$C$5),Config!$B$20,INDEX(Clay_Offices!$A$2:$FZ$601,0,Sync!$C$15),"obj_price"),0)+IFERROR(COUNTIFS(INDEX(Clay_Offices!$A$2:$FZ$601,0,Sync!$C$14),"<"&(E$6+1),INDEX(Clay_Offices!$A$2:$FZ$601,0,Sync!$C$5),Config!$B$20,INDEX(Clay_Offices!$A$2:$FZ$601,0,Sync!$C$15),"obj_free_trial"),0)+IFERROR(COUNTIFS(INDEX(Clay_Offices!$A$2:$FZ$601,0,Sync!$C$14),"<"&(E$6+1),INDEX(Clay_Offices!$A$2:$FZ$601,0,Sync!$C$5),Config!$B$20,INDEX(Clay_Offices!$A$2:$FZ$601,0,Sync!$C$15),"obj_what_we_get"),0)+IFERROR(COUNTIFS(INDEX(Clay_Offices!$A$2:$FZ$601,0,Sync!$C$14),"<"&(E$6+1),INDEX(Clay_Offices!$A$2:$FZ$601,0,Sync!$C$5),Config!$B$20,INDEX(Clay_Offices!$A$2:$FZ$601,0,Sync!$C$15),"obj_other"),0) -> 20 | G61: reply_type yes, maybe, needs_approval, send_info, referral, not_now or an objection (obj_*): a reply that can become a conversation. Not opt_out, no, wrong_person, bounce or out_of_office.
A62: Office conversation-reply rate | B62: =IF(B58=0,"",B61/B58) -> 0.57142857 | C62: =IF(C58=0,"",C61/C58) -> 0.59259259 | D62: =IF(D58=0,"",D61/D58) -> 0.54545455 | E62: =IF(E58=0,"",E61/E58) -> 0.51282051 | G62: Conversation replies / first touches. This drives the 20% check below: the plan's 150 messages at 20% is 30 conversations.
A63: Office conversations per first touch | B63: =IF(B58=0,"",B8/B58) -> 0.21428571 | C63: =IF(C58=0,"",C8/C58) -> 0.25925926 | D63: =IF(D58=0,"",D8/D58) -> 0.39393939 | E63: =IF(E58=0,"",E8/E58) -> 0.35897436 | G63: Conversations (above) / first touches. 15 from about 75 first touches is 20%.
A64: Office opt-outs | B64: =IFERROR(COUNTIFS(INDEX(Clay_Offices!$A$2:$FZ$601,0,Sync!$C$18),"<"&(B$6+1),INDEX(Clay_Offices!$A$2:$FZ$601,0,Sync!$C$5),Config!$B$20),0) -> 0 | C64: =IFERROR(COUNTIFS(INDEX(Clay_Offices!$A$2:$FZ$601,0,Sync!$C$18),"<"&(C$6+1),INDEX(Clay_Offices!$A$2:$FZ$601,0,Sync!$C$5),Config!$B$20),0) -> 1 | D64: =IFERROR(COUNTIFS(INDEX(Clay_Offices!$A$2:$FZ$601,0,Sync!$C$18),"<"&(D$6+1),INDEX(Clay_Offices!$A$2:$FZ$601,0,Sync!$C$5),Config!$B$20),0) -> 2 | E64: =IFERROR(COUNTIFS(INDEX(Clay_Offices!$A$2:$FZ$601,0,Sync!$C$18),"<"&(E$6+1),INDEX(Clay_Offices!$A$2:$FZ$601,0,Sync!$C$5),Config!$B$20),0) -> 2 | G64: Rows with opt_out_date on or before the cut-off. Every one must have do_not_contact = Y.
A65: Office opt-out rate | B65: =IF(B58=0,"",B64/B58) -> 0 | C65: =IF(C58=0,"",C64/C58) -> 0.037037037 | D65: =IF(D58=0,"",D64/D58) -> 0.060606061 | E65: =IF(E58=0,"",E64/E58) -> 0.051282051 | G65: Opt-outs / first touches. Over 5% (Config opt_out_rate_flag) with 3 or more opt-outs (opt_out_min_count) and 30 or more first touches: check targeting and copy (sending guide 6.3 to 6.4).
A66: Office reply-rate check (as of) | B66: =IF(E58<Config!$B$17,"Too few first touches to judge ("&E58&" of "&Config!$B$17&").",IF(E62<Config!$B$16,"UNDER 20%: conversation replies are under 20% of first touches. Run sending/sending-setup.md section 6 before sending more.","OK: conversation replies at or above 20%.")) -> OK: conversation replies at or above 20%.
A67: Office opt-out check (as of) | B67: =IF(E58<Config!$B$17,"Too few first touches to judge ("&E58&" of "&Config!$B$17&").",IF(AND(E64>=Config!$B$30,E65>Config!$B$29),"OPT-OUTS OVER 5%: check targeting and copy (sending/sending-setup.md 6.3 to 6.4).","OK: fewer than 3 opt-outs, or 5% or under.")) -> OK: fewer than 3 opt-outs, or 5% or under.
A68: Brand first touches sent | B68: =IFERROR(COUNTIFS(INDEX(Clay_Brands!$A$2:$FZ$601,0,Sync!$D$11),"<"&(B$6+1),INDEX(Clay_Brands!$A$2:$FZ$601,0,Sync!$D$5),Config!$B$20),0) -> 14 | C68: =IFERROR(COUNTIFS(INDEX(Clay_Brands!$A$2:$FZ$601,0,Sync!$D$11),"<"&(C$6+1),INDEX(Clay_Brands!$A$2:$FZ$601,0,Sync!$D$5),Config!$B$20),0) -> 26 | D68: =IFERROR(COUNTIFS(INDEX(Clay_Brands!$A$2:$FZ$601,0,Sync!$D$11),"<"&(D$6+1),INDEX(Clay_Brands!$A$2:$FZ$601,0,Sync!$D$5),Config!$B$20),0) -> 34 | E68: =IFERROR(COUNTIFS(INDEX(Clay_Brands!$A$2:$FZ$601,0,Sync!$D$11),"<"&(E$6+1),INDEX(Clay_Brands!$A$2:$FZ$601,0,Sync!$D$5),Config!$B$20),0) -> 40 | G68: Clay rows with touch_1_date on or before the cut-off.
A69: Brand replies, all (any human reply, opt-outs included) | B69: =IFERROR(COUNTIFS(INDEX(Clay_Brands!$A$2:$FZ$601,0,Sync!$D$14),"<"&(B$6+1),INDEX(Clay_Brands!$A$2:$FZ$601,0,Sync!$D$5),Config!$B$20,INDEX(Clay_Brands!$A$2:$FZ$601,0,Sync!$D$15),"<>bounce",INDEX(Clay_Brands!$A$2:$FZ$601,0,Sync!$D$15),"<>out_of_office"),0) -> 9 | C69: =IFERROR(COUNTIFS(INDEX(Clay_Brands!$A$2:$FZ$601,0,Sync!$D$14),"<"&(C$6+1),INDEX(Clay_Brands!$A$2:$FZ$601,0,Sync!$D$5),Config!$B$20,INDEX(Clay_Brands!$A$2:$FZ$601,0,Sync!$D$15),"<>bounce",INDEX(Clay_Brands!$A$2:$FZ$601,0,Sync!$D$15),"<>out_of_office"),0) -> 16 | D69: =IFERROR(COUNTIFS(INDEX(Clay_Brands!$A$2:$FZ$601,0,Sync!$D$14),"<"&(D$6+1),INDEX(Clay_Brands!$A$2:$FZ$601,0,Sync!$D$5),Config!$B$20,INDEX(Clay_Brands!$A$2:$FZ$601,0,Sync!$D$15),"<>bounce",INDEX(Clay_Brands!$A$2:$FZ$601,0,Sync!$D$15),"<>out_of_office"),0) -> 23 | E69: =IFERROR(COUNTIFS(INDEX(Clay_Brands!$A$2:$FZ$601,0,Sync!$D$14),"<"&(E$6+1),INDEX(Clay_Brands!$A$2:$FZ$601,0,Sync!$D$5),Config!$B$20,INDEX(Clay_Brands!$A$2:$FZ$601,0,Sync!$D$15),"<>bounce",INDEX(Clay_Brands!$A$2:$FZ$601,0,Sync!$D$15),"<>out_of_office"),0) -> 25 | G69: Rows with last_reply_date on or before the cut-off; bounces and auto-replies excluded. Information only.
A70: Brand reply rate, all replies (information only) | B70: =IF(B68=0,"",B69/B68) -> 0.64285714 | C70: =IF(C68=0,"",C69/C68) -> 0.61538462 | D70: =IF(D68=0,"",D69/D68) -> 0.67647059 | E70: =IF(E68=0,"",E69/E68) -> 0.625 | G70: All replies / first touches. Opt-outs and refusals count here, so this rate can look healthy while conversations fall short. It does not drive the check.
A71: Brand conversation replies | B71: =IFERROR(COUNTIFS(INDEX(Clay_Brands!$A$2:$FZ$601,0,Sync!$D$14),"<"&(B$6+1),INDEX(Clay_Brands!$A$2:$FZ$601,0,Sync!$D$5),Config!$B$20,INDEX(Clay_Brands!$A$2:$FZ$601,0,Sync!$D$15),"yes"),0)+IFERROR(COUNTIFS(INDEX(Clay_Brands!$A$2:$FZ$601,0,Sync!$D$14),"<"&(B$6+1),INDEX(Clay_Brands!$A$2:$FZ$601,0,Sync!$D$5),Config!$B$20,INDEX(Clay_Brands!$A$2:$FZ$601,0,Sync!$D$15),"maybe"),0)+IFERROR(COUNTIFS(INDEX(Clay_Brands!$A$2:$FZ$601,0,Sync!$D$14),"<"&(B$6+1),INDEX(Clay_Brands!$A$2:$FZ$601,0,Sync!$D$5),Config!$B$20,INDEX(Clay_Brands!$A$2:$FZ$601,0,Sync!$D$15),"needs_approval"),0)+IFERROR(COUNTIFS(INDEX(Clay_Brands!$A$2:$FZ$601,0,Sync!$D$14),"<"&(B$6+1),INDEX(Clay_Brands!$A$2:$FZ$601,0,Sync!$D$5),Config!$B$20,INDEX(Clay_Brands!$A$2:$FZ$601,0,Sync!$D$15),"send_info"),0)+IFERROR(COUNTIFS(INDEX(Clay_Brands!$A$2:$FZ$601,0,Sync!$D$14),"<"&(B$6+1),INDEX(Clay_Brands!$A$2:$FZ$601,0,Sync!$D$5),Config!$B$20,INDEX(Clay_Brands!$A$2:$FZ$601,0,Sync!$D$15),"referral"),0)+IFERROR(COUNTIFS(INDEX(Clay_Brands!$A$2:$FZ$601,0,Sync!$D$14),"<"&(B$6+1),INDEX(Clay_Brands!$A$2:$FZ$601,0,Sync!$D$5),Config!$B$20,INDEX(Clay_Brands!$A$2:$FZ$601,0,Sync!$D$15),"not_now"),0)+IFERROR(COUNTIFS(INDEX(Clay_Brands!$A$2:$FZ$601,0,Sync!$D$14),"<"&(B$6+1),INDEX(Clay_Brands!$A$2:$FZ$601,0,Sync!$D$5),Config!$B$20,INDEX(Clay_Brands!$A$2:$FZ$601,0,Sync!$D$15),"obj_seed_ourselves"),0)+IFERROR(COUNTIFS(INDEX(Clay_Brands!$A$2:$FZ$601,0,Sync!$D$14),"<"&(B$6+1),INDEX(Clay_Brands!$A$2:$FZ$601,0,Sync!$D$5),Config!$B$20,INDEX(Clay_Brands!$A$2:$FZ$601,0,Sync!$D$15),"obj_price"),0)+IFERROR(COUNTIFS(INDEX(Clay_Brands!$A$2:$FZ$601,0,Sync!$D$14),"<"&(B$6+1),INDEX(Clay_Brands!$A$2:$FZ$601,0,Sync!$D$5),Config!$B$20,INDEX(Clay_Brands!$A$2:$FZ$601,0,Sync!$D$15),"obj_free_trial"),0)+IFERROR(COUNTIFS(INDEX(Clay_Brands!$A$2:$FZ$601,0,Sync!$D$14),"<"&(B$6+1),INDEX(Clay_Brands!$A$2:$FZ$601,0,Sync!$D$5),Config!$B$20,INDEX(Clay_Brands!$A$2:$FZ$601,0,Sync!$D$15),"obj_what_we_get"),0)+IFERROR(COUNTIFS(INDEX(Clay_Brands!$A$2:$FZ$601,0,Sync!$D$14),"<"&(B$6+1),INDEX(Clay_Brands!$A$2:$FZ$601,0,Sync!$D$5),Config!$B$20,INDEX(Clay_Brands!$A$2:$FZ$601,0,Sync!$D$15),"obj_other"),0) -> 8 | C71: =IFERROR(COUNTIFS(INDEX(Clay_Brands!$A$2:$FZ$601,0,Sync!$D$14),"<"&(C$6+1),INDEX(Clay_Brands!$A$2:$FZ$601,0,Sync!$D$5),Config!$B$20,INDEX(Clay_Brands!$A$2:$FZ$601,0,Sync!$D$15),"yes"),0)+IFERROR(COUNTIFS(INDEX(Clay_Brands!$A$2:$FZ$601,0,Sync!$D$14),"<"&(C$6+1),INDEX(Clay_Brands!$A$2:$FZ$601,0,Sync!$D$5),Config!$B$20,INDEX(Clay_Brands!$A$2:$FZ$601,0,Sync!$D$15),"maybe"),0)+IFERROR(COUNTIFS(INDEX(Clay_Brands!$A$2:$FZ$601,0,Sync!$D$14),"<"&(C$6+1),INDEX(Clay_Brands!$A$2:$FZ$601,0,Sync!$D$5),Config!$B$20,INDEX(Clay_Brands!$A$2:$FZ$601,0,Sync!$D$15),"needs_approval"),0)+IFERROR(COUNTIFS(INDEX(Clay_Brands!$A$2:$FZ$601,0,Sync!$D$14),"<"&(C$6+1),INDEX(Clay_Brands!$A$2:$FZ$601,0,Sync!$D$5),Config!$B$20,INDEX(Clay_Brands!$A$2:$FZ$601,0,Sync!$D$15),"send_info"),0)+IFERROR(COUNTIFS(INDEX(Clay_Brands!$A$2:$FZ$601,0,Sync!$D$14),"<"&(C$6+1),INDEX(Clay_Brands!$A$2:$FZ$601,0,Sync!$D$5),Config!$B$20,INDEX(Clay_Brands!$A$2:$FZ$601,0,Sync!$D$15),"referral"),0)+IFERROR(COUNTIFS(INDEX(Clay_Brands!$A$2:$FZ$601,0,Sync!$D$14),"<"&(C$6+1),INDEX(Clay_Brands!$A$2:$FZ$601,0,Sync!$D$5),Config!$B$20,INDEX(Clay_Brands!$A$2:$FZ$601,0,Sync!$D$15),"not_now"),0)+IFERROR(COUNTIFS(INDEX(Clay_Brands!$A$2:$FZ$601,0,Sync!$D$14),"<"&(C$6+1),INDEX(Clay_Brands!$A$2:$FZ$601,0,Sync!$D$5),Config!$B$20,INDEX(Clay_Brands!$A$2:$FZ$601,0,Sync!$D$15),"obj_seed_ourselves"),0)+IFERROR(COUNTIFS(INDEX(Clay_Brands!$A$2:$FZ$601,0,Sync!$D$14),"<"&(C$6+1),INDEX(Clay_Brands!$A$2:$FZ$601,0,Sync!$D$5),Config!$B$20,INDEX(Clay_Brands!$A$2:$FZ$601,0,Sync!$D$15),"obj_price"),0)+IFERROR(COUNTIFS(INDEX(Clay_Brands!$A$2:$FZ$601,0,Sync!$D$14),"<"&(C$6+1),INDEX(Clay_Brands!$A$2:$FZ$601,0,Sync!$D$5),Config!$B$20,INDEX(Clay_Brands!$A$2:$FZ$601,0,Sync!$D$15),"obj_free_trial"),0)+IFERROR(COUNTIFS(INDEX(Clay_Brands!$A$2:$FZ$601,0,Sync!$D$14),"<"&(C$6+1),INDEX(Clay_Brands!$A$2:$FZ$601,0,Sync!$D$5),Config!$B$20,INDEX(Clay_Brands!$A$2:$FZ$601,0,Sync!$D$15),"obj_what_we_get"),0)+IFERROR(COUNTIFS(INDEX(Clay_Brands!$A$2:$FZ$601,0,Sync!$D$14),"<"&(C$6+1),INDEX(Clay_Brands!$A$2:$FZ$601,0,Sync!$D$5),Config!$B$20,INDEX(Clay_Brands!$A$2:$FZ$601,0,Sync!$D$15),"obj_other"),0) -> 14 | D71: =IFERROR(COUNTIFS(INDEX(Clay_Brands!$A$2:$FZ$601,0,Sync!$D$14),"<"&(D$6+1),INDEX(Clay_Brands!$A$2:$FZ$601,0,Sync!$D$5),Config!$B$20,INDEX(Clay_Brands!$A$2:$FZ$601,0,Sync!$D$15),"yes"),0)+IFERROR(COUNTIFS(INDEX(Clay_Brands!$A$2:$FZ$601,0,Sync!$D$14),"<"&(D$6+1),INDEX(Clay_Brands!$A$2:$FZ$601,0,Sync!$D$5),Config!$B$20,INDEX(Clay_Brands!$A$2:$FZ$601,0,Sync!$D$15),"maybe"),0)+IFERROR(COUNTIFS(INDEX(Clay_Brands!$A$2:$FZ$601,0,Sync!$D$14),"<"&(D$6+1),INDEX(Clay_Brands!$A$2:$FZ$601,0,Sync!$D$5),Config!$B$20,INDEX(Clay_Brands!$A$2:$FZ$601,0,Sync!$D$15),"needs_approval"),0)+IFERROR(COUNTIFS(INDEX(Clay_Brands!$A$2:$FZ$601,0,Sync!$D$14),"<"&(D$6+1),INDEX(Clay_Brands!$A$2:$FZ$601,0,Sync!$D$5),Config!$B$20,INDEX(Clay_Brands!$A$2:$FZ$601,0,Sync!$D$15),"send_info"),0)+IFERROR(COUNTIFS(INDEX(Clay_Brands!$A$2:$FZ$601,0,Sync!$D$14),"<"&(D$6+1),INDEX(Clay_Brands!$A$2:$FZ$601,0,Sync!$D$5),Config!$B$20,INDEX(Clay_Brands!$A$2:$FZ$601,0,Sync!$D$15),"referral"),0)+IFERROR(COUNTIFS(INDEX(Clay_Brands!$A$2:$FZ$601,0,Sync!$D$14),"<"&(D$6+1),INDEX(Clay_Brands!$A$2:$FZ$601,0,Sync!$D$5),Config!$B$20,INDEX(Clay_Brands!$A$2:$FZ$601,0,Sync!$D$15),"not_now"),0)+IFERROR(COUNTIFS(INDEX(Clay_Brands!$A$2:$FZ$601,0,Sync!$D$14),"<"&(D$6+1),INDEX(Clay_Brands!$A$2:$FZ$601,0,Sync!$D$5),Config!$B$20,INDEX(Clay_Brands!$A$2:$FZ$601,0,Sync!$D$15),"obj_seed_ourselves"),0)+IFERROR(COUNTIFS(INDEX(Clay_Brands!$A$2:$FZ$601,0,Sync!$D$14),"<"&(D$6+1),INDEX(Clay_Brands!$A$2:$FZ$601,0,Sync!$D$5),Config!$B$20,INDEX(Clay_Brands!$A$2:$FZ$601,0,Sync!$D$15),"obj_price"),0)+IFERROR(COUNTIFS(INDEX(Clay_Brands!$A$2:$FZ$601,0,Sync!$D$14),"<"&(D$6+1),INDEX(Clay_Brands!$A$2:$FZ$601,0,Sync!$D$5),Config!$B$20,INDEX(Clay_Brands!$A$2:$FZ$601,0,Sync!$D$15),"obj_free_trial"),0)+IFERROR(COUNTIFS(INDEX(Clay_Brands!$A$2:$FZ$601,0,Sync!$D$14),"<"&(D$6+1),INDEX(Clay_Brands!$A$2:$FZ$601,0,Sync!$D$5),Config!$B$20,INDEX(Clay_Brands!$A$2:$FZ$601,0,Sync!$D$15),"obj_what_we_get"),0)+IFERROR(COUNTIFS(INDEX(Clay_Brands!$A$2:$FZ$601,0,Sync!$D$14),"<"&(D$6+1),INDEX(Clay_Brands!$A$2:$FZ$601,0,Sync!$D$5),Config!$B$20,INDEX(Clay_Brands!$A$2:$FZ$601,0,Sync!$D$15),"obj_other"),0) -> 19 | E71: =IFERROR(COUNTIFS(INDEX(Clay_Brands!$A$2:$FZ$601,0,Sync!$D$14),"<"&(E$6+1),INDEX(Clay_Brands!$A$2:$FZ$601,0,Sync!$D$5),Config!$B$20,INDEX(Clay_Brands!$A$2:$FZ$601,0,Sync!$D$15),"yes"),0)+IFERROR(COUNTIFS(INDEX(Clay_Brands!$A$2:$FZ$601,0,Sync!$D$14),"<"&(E$6+1),INDEX(Clay_Brands!$A$2:$FZ$601,0,Sync!$D$5),Config!$B$20,INDEX(Clay_Brands!$A$2:$FZ$601,0,Sync!$D$15),"maybe"),0)+IFERROR(COUNTIFS(INDEX(Clay_Brands!$A$2:$FZ$601,0,Sync!$D$14),"<"&(E$6+1),INDEX(Clay_Brands!$A$2:$FZ$601,0,Sync!$D$5),Config!$B$20,INDEX(Clay_Brands!$A$2:$FZ$601,0,Sync!$D$15),"needs_approval"),0)+IFERROR(COUNTIFS(INDEX(Clay_Brands!$A$2:$FZ$601,0,Sync!$D$14),"<"&(E$6+1),INDEX(Clay_Brands!$A$2:$FZ$601,0,Sync!$D$5),Config!$B$20,INDEX(Clay_Brands!$A$2:$FZ$601,0,Sync!$D$15),"send_info"),0)+IFERROR(COUNTIFS(INDEX(Clay_Brands!$A$2:$FZ$601,0,Sync!$D$14),"<"&(E$6+1),INDEX(Clay_Brands!$A$2:$FZ$601,0,Sync!$D$5),Config!$B$20,INDEX(Clay_Brands!$A$2:$FZ$601,0,Sync!$D$15),"referral"),0)+IFERROR(COUNTIFS(INDEX(Clay_Brands!$A$2:$FZ$601,0,Sync!$D$14),"<"&(E$6+1),INDEX(Clay_Brands!$A$2:$FZ$601,0,Sync!$D$5),Config!$B$20,INDEX(Clay_Brands!$A$2:$FZ$601,0,Sync!$D$15),"not_now"),0)+IFERROR(COUNTIFS(INDEX(Clay_Brands!$A$2:$FZ$601,0,Sync!$D$14),"<"&(E$6+1),INDEX(Clay_Brands!$A$2:$FZ$601,0,Sync!$D$5),Config!$B$20,INDEX(Clay_Brands!$A$2:$FZ$601,0,Sync!$D$15),"obj_seed_ourselves"),0)+IFERROR(COUNTIFS(INDEX(Clay_Brands!$A$2:$FZ$601,0,Sync!$D$14),"<"&(E$6+1),INDEX(Clay_Brands!$A$2:$FZ$601,0,Sync!$D$5),Config!$B$20,INDEX(Clay_Brands!$A$2:$FZ$601,0,Sync!$D$15),"obj_price"),0)+IFERROR(COUNTIFS(INDEX(Clay_Brands!$A$2:$FZ$601,0,Sync!$D$14),"<"&(E$6+1),INDEX(Clay_Brands!$A$2:$FZ$601,0,Sync!$D$5),Config!$B$20,INDEX(Clay_Brands!$A$2:$FZ$601,0,Sync!$D$15),"obj_free_trial"),0)+IFERROR(COUNTIFS(INDEX(Clay_Brands!$A$2:$FZ$601,0,Sync!$D$14),"<"&(E$6+1),INDEX(Clay_Brands!$A$2:$FZ$601,0,Sync!$D$5),Config!$B$20,INDEX(Clay_Brands!$A$2:$FZ$601,0,Sync!$D$15),"obj_what_we_get"),0)+IFERROR(COUNTIFS(INDEX(Clay_Brands!$A$2:$FZ$601,0,Sync!$D$14),"<"&(E$6+1),INDEX(Clay_Brands!$A$2:$FZ$601,0,Sync!$D$5),Config!$B$20,INDEX(Clay_Brands!$A$2:$FZ$601,0,Sync!$D$15),"obj_other"),0) -> 21 | G71: reply_type yes, maybe, needs_approval, send_info, referral, not_now or an objection (obj_*): a reply that can become a conversation. Not opt_out, no, wrong_person, bounce or out_of_office.
A72: Brand conversation-reply rate | B72: =IF(B68=0,"",B71/B68) -> 0.57142857 | C72: =IF(C68=0,"",C71/C68) -> 0.53846154 | D72: =IF(D68=0,"",D71/D68) -> 0.55882353 | E72: =IF(E68=0,"",E71/E68) -> 0.525 | G72: Conversation replies / first touches. This drives the 20% check below: the plan's 150 messages at 20% is 30 conversations.
A73: Brand conversations per first touch | B73: =IF(B68=0,"",B25/B68) -> 0.21428571 | C73: =IF(C68=0,"",C25/C68) -> 0.26923077 | D73: =IF(D68=0,"",D25/D68) -> 0.38235294 | E73: =IF(E68=0,"",E25/E68) -> 0.375 | G73: Conversations (above) / first touches. 15 from about 75 first touches is 20%.
A74: Brand opt-outs | B74: =IFERROR(COUNTIFS(INDEX(Clay_Brands!$A$2:$FZ$601,0,Sync!$D$18),"<"&(B$6+1),INDEX(Clay_Brands!$A$2:$FZ$601,0,Sync!$D$5),Config!$B$20),0) -> 0 | C74: =IFERROR(COUNTIFS(INDEX(Clay_Brands!$A$2:$FZ$601,0,Sync!$D$18),"<"&(C$6+1),INDEX(Clay_Brands!$A$2:$FZ$601,0,Sync!$D$5),Config!$B$20),0) -> 1 | D74: =IFERROR(COUNTIFS(INDEX(Clay_Brands!$A$2:$FZ$601,0,Sync!$D$18),"<"&(D$6+1),INDEX(Clay_Brands!$A$2:$FZ$601,0,Sync!$D$5),Config!$B$20),0) -> 2 | E74: =IFERROR(COUNTIFS(INDEX(Clay_Brands!$A$2:$FZ$601,0,Sync!$D$18),"<"&(E$6+1),INDEX(Clay_Brands!$A$2:$FZ$601,0,Sync!$D$5),Config!$B$20),0) -> 2 | G74: Rows with opt_out_date on or before the cut-off. Every one must have do_not_contact = Y.
A75: Brand opt-out rate | B75: =IF(B68=0,"",B74/B68) -> 0 | C75: =IF(C68=0,"",C74/C68) -> 0.038461538 | D75: =IF(D68=0,"",D74/D68) -> 0.058823529 | E75: =IF(E68=0,"",E74/E68) -> 0.05 | G75: Opt-outs / first touches. Over 5% (Config opt_out_rate_flag) with 3 or more opt-outs (opt_out_min_count) and 30 or more first touches: check targeting and copy (sending guide 6.3 to 6.4).
A76: Brand reply-rate check (as of) | B76: =IF(E68<Config!$B$17,"Too few first touches to judge ("&E68&" of "&Config!$B$17&").",IF(E72<Config!$B$16,"UNDER 20%: conversation replies are under 20% of first touches. Run sending/sending-setup.md section 6 before sending more.","OK: conversation replies at or above 20%.")) -> OK: conversation replies at or above 20%.
A77: Brand opt-out check (as of) | B77: =IF(E68<Config!$B$17,"Too few first touches to judge ("&E68&" of "&Config!$B$17&").",IF(AND(E74>=Config!$B$30,E75>Config!$B$29),"OPT-OUTS OVER 5%: check targeting and copy (sending/sending-setup.md 6.3 to 6.4).","OK: fewer than 3 opt-outs, or 5% or under.")) -> OK: fewer than 3 opt-outs, or 5% or under.
A78: Email bounces to date (offices + brands) / first touches to date | E78: =IF((E58+E68)=0,"",(IFERROR(COUNTIFS(INDEX(Clay_Offices!$A$2:$FZ$601,0,Sync!$C$15),"bounce",INDEX(Clay_Offices!$A$2:$FZ$601,0,Sync!$C$5),Config!$B$20),0)+IFERROR(COUNTIFS(INDEX(Clay_Brands!$A$2:$FZ$601,0,Sync!$D$15),"bounce",INDEX(Clay_Brands!$A$2:$FZ$601,0,Sync!$D$5),Config!$B$20),0))/(E58+E68)) -> 0.050632911 | G78: Two or more bounces in a week, or over 2% once 100 email first touches have gone, pauses cold email for five business days (sending guide 3.4).
A80: By sequence variant and by channel, as of (pick winners only on large gaps; see sending guide 6.4)
A81: Sequence or channel | B81: Side | C81: First touches | D81: Replies, all | E81: Reply rate, all | G81: Conversation replies
A82: office-discovery-A | B82: office | C82: =IFERROR(COUNTIFS(INDEX(Clay_Offices!$A$2:$FZ$601,0,Sync!$C$10),A82,INDEX(Clay_Offices!$A$2:$FZ$601,0,Sync!$C$11),"<"&($E$6+1),INDEX(Clay_Offices!$A$2:$FZ$601,0,Sync!$C$5),Config!$B$20),0) -> 20 | D82: =IFERROR(COUNTIFS(INDEX(Clay_Offices!$A$2:$FZ$601,0,Sync!$C$10),A82,INDEX(Clay_Offices!$A$2:$FZ$601,0,Sync!$C$14),"<"&($E$6+1),INDEX(Clay_Offices!$A$2:$FZ$601,0,Sync!$C$5),Config!$B$20,INDEX(Clay_Offices!$A$2:$FZ$601,0,Sync!$C$15),"<>bounce",INDEX(Clay_Offices!$A$2:$FZ$601,0,Sync!$C$15),"<>out_of_office"),0) -> 9 | E82: =IF(C82=0,"",D82/C82) -> 0.45 | G82: =IFERROR(COUNTIFS(INDEX(Clay_Offices!$A$2:$FZ$601,0,Sync!$C$10),A82,INDEX(Clay_Offices!$A$2:$FZ$601,0,Sync!$C$14),"<"&($E$6+1),INDEX(Clay_Offices!$A$2:$FZ$601,0,Sync!$C$5),Config!$B$20,INDEX(Clay_Offices!$A$2:$FZ$601,0,Sync!$C$15),"yes"),0)+IFERROR(COUNTIFS(INDEX(Clay_Offices!$A$2:$FZ$601,0,Sync!$C$10),A82,INDEX(Clay_Offices!$A$2:$FZ$601,0,Sync!$C$14),"<"&($E$6+1),INDEX(Clay_Offices!$A$2:$FZ$601,0,Sync!$C$5),Config!$B$20,INDEX(Clay_Offices!$A$2:$FZ$601,0,Sync!$C$15),"maybe"),0)+IFERROR(COUNTIFS(INDEX(Clay_Offices!$A$2:$FZ$601,0,Sync!$C$10),A82,INDEX(Clay_Offices!$A$2:$FZ$601,0,Sync!$C$14),"<"&($E$6+1),INDEX(Clay_Offices!$A$2:$FZ$601,0,Sync!$C$5),Config!$B$20,INDEX(Clay_Offices!$A$2:$FZ$601,0,Sync!$C$15),"needs_approval"),0)+IFERROR(COUNTIFS(INDEX(Clay_Offices!$A$2:$FZ$601,0,Sync!$C$10),A82,INDEX(Clay_Offices!$A$2:$FZ$601,0,Sync!$C$14),"<"&($E$6+1),INDEX(Clay_Offices!$A$2:$FZ$601,0,Sync!$C$5),Config!$B$20,INDEX(Clay_Offices!$A$2:$FZ$601,0,Sync!$C$15),"send_info"),0)+IFERROR(COUNTIFS(INDEX(Clay_Offices!$A$2:$FZ$601,0,Sync!$C$10),A82,INDEX(Clay_Offices!$A$2:$FZ$601,0,Sync!$C$14),"<"&($E$6+1),INDEX(Clay_Offices!$A$2:$FZ$601,0,Sync!$C$5),Config!$B$20,INDEX(Clay_Offices!$A$2:$FZ$601,0,Sync!$C$15),"referral"),0)+IFERROR(COUNTIFS(INDEX(Clay_Offices!$A$2:$FZ$601,0,Sync!$C$10),A82,INDEX(Clay_Offices!$A$2:$FZ$601,0,Sync!$C$14),"<"&($E$6+1),INDEX(Clay_Offices!$A$2:$FZ$601,0,Sync!$C$5),Config!$B$20,INDEX(Clay_Offices!$A$2:$FZ$601,0,Sync!$C$15),"not_now"),0)+IFERROR(COUNTIFS(INDEX(Clay_Offices!$A$2:$FZ$601,0,Sync!$C$10),A82,INDEX(Clay_Offices!$A$2:$FZ$601,0,Sync!$C$14),"<"&($E$6+1),INDEX(Clay_Offices!$A$2:$FZ$601,0,Sync!$C$5),Config!$B$20,INDEX(Clay_Offices!$A$2:$FZ$601,0,Sync!$C$15),"obj_seed_ourselves"),0)+IFERROR(COUNTIFS(INDEX(Clay_Offices!$A$2:$FZ$601,0,Sync!$C$10),A82,INDEX(Clay_Offices!$A$2:$FZ$601,0,Sync!$C$14),"<"&($E$6+1),INDEX(Clay_Offices!$A$2:$FZ$601,0,Sync!$C$5),Config!$B$20,INDEX(Clay_Offices!$A$2:$FZ$601,0,Sync!$C$15),"obj_price"),0)+IFERROR(COUNTIFS(INDEX(Clay_Offices!$A$2:$FZ$601,0,Sync!$C$10),A82,INDEX(Clay_Offices!$A$2:$FZ$601,0,Sync!$C$14),"<"&($E$6+1),INDEX(Clay_Offices!$A$2:$FZ$601,0,Sync!$C$5),Config!$B$20,INDEX(Clay_Offices!$A$2:$FZ$601,0,Sync!$C$15),"obj_free_trial"),0)+IFERROR(COUNTIFS(INDEX(Clay_Offices!$A$2:$FZ$601,0,Sync!$C$10),A82,INDEX(Clay_Offices!$A$2:$FZ$601,0,Sync!$C$14),"<"&($E$6+1),INDEX(Clay_Offices!$A$2:$FZ$601,0,Sync!$C$5),Config!$B$20,INDEX(Clay_Offices!$A$2:$FZ$601,0,Sync!$C$15),"obj_what_we_get"),0)+IFERROR(COUNTIFS(INDEX(Clay_Offices!$A$2:$FZ$601,0,Sync!$C$10),A82,INDEX(Clay_Offices!$A$2:$FZ$601,0,Sync!$C$14),"<"&($E$6+1),INDEX(Clay_Offices!$A$2:$FZ$601,0,Sync!$C$5),Config!$B$20,INDEX(Clay_Offices!$A$2:$FZ$601,0,Sync!$C$15),"obj_other"),0) -> 7
A83: office-discovery-B | B83: office | C83: =IFERROR(COUNTIFS(INDEX(Clay_Offices!$A$2:$FZ$601,0,Sync!$C$10),A83,INDEX(Clay_Offices!$A$2:$FZ$601,0,Sync!$C$11),"<"&($E$6+1),INDEX(Clay_Offices!$A$2:$FZ$601,0,Sync!$C$5),Config!$B$20),0) -> 19 | D83: =IFERROR(COUNTIFS(INDEX(Clay_Offices!$A$2:$FZ$601,0,Sync!$C$10),A83,INDEX(Clay_Offices!$A$2:$FZ$601,0,Sync!$C$14),"<"&($E$6+1),INDEX(Clay_Offices!$A$2:$FZ$601,0,Sync!$C$5),Config!$B$20,INDEX(Clay_Offices!$A$2:$FZ$601,0,Sync!$C$15),"<>bounce",INDEX(Clay_Offices!$A$2:$FZ$601,0,Sync!$C$15),"<>out_of_office"),0) -> 15 | E83: =IF(C83=0,"",D83/C83) -> 0.78947368 | G83: =IFERROR(COUNTIFS(INDEX(Clay_Offices!$A$2:$FZ$601,0,Sync!$C$10),A83,INDEX(Clay_Offices!$A$2:$FZ$601,0,Sync!$C$14),"<"&($E$6+1),INDEX(Clay_Offices!$A$2:$FZ$601,0,Sync!$C$5),Config!$B$20,INDEX(Clay_Offices!$A$2:$FZ$601,0,Sync!$C$15),"yes"),0)+IFERROR(COUNTIFS(INDEX(Clay_Offices!$A$2:$FZ$601,0,Sync!$C$10),A83,INDEX(Clay_Offices!$A$2:$FZ$601,0,Sync!$C$14),"<"&($E$6+1),INDEX(Clay_Offices!$A$2:$FZ$601,0,Sync!$C$5),Config!$B$20,INDEX(Clay_Offices!$A$2:$FZ$601,0,Sync!$C$15),"maybe"),0)+IFERROR(COUNTIFS(INDEX(Clay_Offices!$A$2:$FZ$601,0,Sync!$C$10),A83,INDEX(Clay_Offices!$A$2:$FZ$601,0,Sync!$C$14),"<"&($E$6+1),INDEX(Clay_Offices!$A$2:$FZ$601,0,Sync!$C$5),Config!$B$20,INDEX(Clay_Offices!$A$2:$FZ$601,0,Sync!$C$15),"needs_approval"),0)+IFERROR(COUNTIFS(INDEX(Clay_Offices!$A$2:$FZ$601,0,Sync!$C$10),A83,INDEX(Clay_Offices!$A$2:$FZ$601,0,Sync!$C$14),"<"&($E$6+1),INDEX(Clay_Offices!$A$2:$FZ$601,0,Sync!$C$5),Config!$B$20,INDEX(Clay_Offices!$A$2:$FZ$601,0,Sync!$C$15),"send_info"),0)+IFERROR(COUNTIFS(INDEX(Clay_Offices!$A$2:$FZ$601,0,Sync!$C$10),A83,INDEX(Clay_Offices!$A$2:$FZ$601,0,Sync!$C$14),"<"&($E$6+1),INDEX(Clay_Offices!$A$2:$FZ$601,0,Sync!$C$5),Config!$B$20,INDEX(Clay_Offices!$A$2:$FZ$601,0,Sync!$C$15),"referral"),0)+IFERROR(COUNTIFS(INDEX(Clay_Offices!$A$2:$FZ$601,0,Sync!$C$10),A83,INDEX(Clay_Offices!$A$2:$FZ$601,0,Sync!$C$14),"<"&($E$6+1),INDEX(Clay_Offices!$A$2:$FZ$601,0,Sync!$C$5),Config!$B$20,INDEX(Clay_Offices!$A$2:$FZ$601,0,Sync!$C$15),"not_now"),0)+IFERROR(COUNTIFS(INDEX(Clay_Offices!$A$2:$FZ$601,0,Sync!$C$10),A83,INDEX(Clay_Offices!$A$2:$FZ$601,0,Sync!$C$14),"<"&($E$6+1),INDEX(Clay_Offices!$A$2:$FZ$601,0,Sync!$C$5),Config!$B$20,INDEX(Clay_Offices!$A$2:$FZ$601,0,Sync!$C$15),"obj_seed_ourselves"),0)+IFERROR(COUNTIFS(INDEX(Clay_Offices!$A$2:$FZ$601,0,Sync!$C$10),A83,INDEX(Clay_Offices!$A$2:$FZ$601,0,Sync!$C$14),"<"&($E$6+1),INDEX(Clay_Offices!$A$2:$FZ$601,0,Sync!$C$5),Config!$B$20,INDEX(Clay_Offices!$A$2:$FZ$601,0,Sync!$C$15),"obj_price"),0)+IFERROR(COUNTIFS(INDEX(Clay_Offices!$A$2:$FZ$601,0,Sync!$C$10),A83,INDEX(Clay_Offices!$A$2:$FZ$601,0,Sync!$C$14),"<"&($E$6+1),INDEX(Clay_Offices!$A$2:$FZ$601,0,Sync!$C$5),Config!$B$20,INDEX(Clay_Offices!$A$2:$FZ$601,0,Sync!$C$15),"obj_free_trial"),0)+IFERROR(COUNTIFS(INDEX(Clay_Offices!$A$2:$FZ$601,0,Sync!$C$10),A83,INDEX(Clay_Offices!$A$2:$FZ$601,0,Sync!$C$14),"<"&($E$6+1),INDEX(Clay_Offices!$A$2:$FZ$601,0,Sync!$C$5),Config!$B$20,INDEX(Clay_Offices!$A$2:$FZ$601,0,Sync!$C$15),"obj_what_we_get"),0)+IFERROR(COUNTIFS(INDEX(Clay_Offices!$A$2:$FZ$601,0,Sync!$C$10),A83,INDEX(Clay_Offices!$A$2:$FZ$601,0,Sync!$C$14),"<"&($E$6+1),INDEX(Clay_Offices!$A$2:$FZ$601,0,Sync!$C$5),Config!$B$20,INDEX(Clay_Offices!$A$2:$FZ$601,0,Sync!$C$15),"obj_other"),0) -> 13
A84: office-selling-A | B84: office | C84: =IFERROR(COUNTIFS(INDEX(Clay_Offices!$A$2:$FZ$601,0,Sync!$C$10),A84,INDEX(Clay_Offices!$A$2:$FZ$601,0,Sync!$C$11),"<"&($E$6+1),INDEX(Clay_Offices!$A$2:$FZ$601,0,Sync!$C$5),Config!$B$20),0) -> 0 | D84: =IFERROR(COUNTIFS(INDEX(Clay_Offices!$A$2:$FZ$601,0,Sync!$C$10),A84,INDEX(Clay_Offices!$A$2:$FZ$601,0,Sync!$C$14),"<"&($E$6+1),INDEX(Clay_Offices!$A$2:$FZ$601,0,Sync!$C$5),Config!$B$20,INDEX(Clay_Offices!$A$2:$FZ$601,0,Sync!$C$15),"<>bounce",INDEX(Clay_Offices!$A$2:$FZ$601,0,Sync!$C$15),"<>out_of_office"),0) -> 0 | E84: =IF(C84=0,"",D84/C84) | G84: =IFERROR(COUNTIFS(INDEX(Clay_Offices!$A$2:$FZ$601,0,Sync!$C$10),A84,INDEX(Clay_Offices!$A$2:$FZ$601,0,Sync!$C$14),"<"&($E$6+1),INDEX(Clay_Offices!$A$2:$FZ$601,0,Sync!$C$5),Config!$B$20,INDEX(Clay_Offices!$A$2:$FZ$601,0,Sync!$C$15),"yes"),0)+IFERROR(COUNTIFS(INDEX(Clay_Offices!$A$2:$FZ$601,0,Sync!$C$10),A84,INDEX(Clay_Offices!$A$2:$FZ$601,0,Sync!$C$14),"<"&($E$6+1),INDEX(Clay_Offices!$A$2:$FZ$601,0,Sync!$C$5),Config!$B$20,INDEX(Clay_Offices!$A$2:$FZ$601,0,Sync!$C$15),"maybe"),0)+IFERROR(COUNTIFS(INDEX(Clay_Offices!$A$2:$FZ$601,0,Sync!$C$10),A84,INDEX(Clay_Offices!$A$2:$FZ$601,0,Sync!$C$14),"<"&($E$6+1),INDEX(Clay_Offices!$A$2:$FZ$601,0,Sync!$C$5),Config!$B$20,INDEX(Clay_Offices!$A$2:$FZ$601,0,Sync!$C$15),"needs_approval"),0)+IFERROR(COUNTIFS(INDEX(Clay_Offices!$A$2:$FZ$601,0,Sync!$C$10),A84,INDEX(Clay_Offices!$A$2:$FZ$601,0,Sync!$C$14),"<"&($E$6+1),INDEX(Clay_Offices!$A$2:$FZ$601,0,Sync!$C$5),Config!$B$20,INDEX(Clay_Offices!$A$2:$FZ$601,0,Sync!$C$15),"send_info"),0)+IFERROR(COUNTIFS(INDEX(Clay_Offices!$A$2:$FZ$601,0,Sync!$C$10),A84,INDEX(Clay_Offices!$A$2:$FZ$601,0,Sync!$C$14),"<"&($E$6+1),INDEX(Clay_Offices!$A$2:$FZ$601,0,Sync!$C$5),Config!$B$20,INDEX(Clay_Offices!$A$2:$FZ$601,0,Sync!$C$15),"referral"),0)+IFERROR(COUNTIFS(INDEX(Clay_Offices!$A$2:$FZ$601,0,Sync!$C$10),A84,INDEX(Clay_Offices!$A$2:$FZ$601,0,Sync!$C$14),"<"&($E$6+1),INDEX(Clay_Offices!$A$2:$FZ$601,0,Sync!$C$5),Config!$B$20,INDEX(Clay_Offices!$A$2:$FZ$601,0,Sync!$C$15),"not_now"),0)+IFERROR(COUNTIFS(INDEX(Clay_Offices!$A$2:$FZ$601,0,Sync!$C$10),A84,INDEX(Clay_Offices!$A$2:$FZ$601,0,Sync!$C$14),"<"&($E$6+1),INDEX(Clay_Offices!$A$2:$FZ$601,0,Sync!$C$5),Config!$B$20,INDEX(Clay_Offices!$A$2:$FZ$601,0,Sync!$C$15),"obj_seed_ourselves"),0)+IFERROR(COUNTIFS(INDEX(Clay_Offices!$A$2:$FZ$601,0,Sync!$C$10),A84,INDEX(Clay_Offices!$A$2:$FZ$601,0,Sync!$C$14),"<"&($E$6+1),INDEX(Clay_Offices!$A$2:$FZ$601,0,Sync!$C$5),Config!$B$20,INDEX(Clay_Offices!$A$2:$FZ$601,0,Sync!$C$15),"obj_price"),0)+IFERROR(COUNTIFS(INDEX(Clay_Offices!$A$2:$FZ$601,0,Sync!$C$10),A84,INDEX(Clay_Offices!$A$2:$FZ$601,0,Sync!$C$14),"<"&($E$6+1),INDEX(Clay_Offices!$A$2:$FZ$601,0,Sync!$C$5),Config!$B$20,INDEX(Clay_Offices!$A$2:$FZ$601,0,Sync!$C$15),"obj_free_trial"),0)+IFERROR(COUNTIFS(INDEX(Clay_Offices!$A$2:$FZ$601,0,Sync!$C$10),A84,INDEX(Clay_Offices!$A$2:$FZ$601,0,Sync!$C$14),"<"&($E$6+1),INDEX(Clay_Offices!$A$2:$FZ$601,0,Sync!$C$5),Config!$B$20,INDEX(Clay_Offices!$A$2:$FZ$601,0,Sync!$C$15),"obj_what_we_get"),0)+IFERROR(COUNTIFS(INDEX(Clay_Offices!$A$2:$FZ$601,0,Sync!$C$10),A84,INDEX(Clay_Offices!$A$2:$FZ$601,0,Sync!$C$14),"<"&($E$6+1),INDEX(Clay_Offices!$A$2:$FZ$601,0,Sync!$C$5),Config!$B$20,INDEX(Clay_Offices!$A$2:$FZ$601,0,Sync!$C$15),"obj_other"),0) -> 0
A85: office-selling-B | B85: office | C85: =IFERROR(COUNTIFS(INDEX(Clay_Offices!$A$2:$FZ$601,0,Sync!$C$10),A85,INDEX(Clay_Offices!$A$2:$FZ$601,0,Sync!$C$11),"<"&($E$6+1),INDEX(Clay_Offices!$A$2:$FZ$601,0,Sync!$C$5),Config!$B$20),0) -> 0 | D85: =IFERROR(COUNTIFS(INDEX(Clay_Offices!$A$2:$FZ$601,0,Sync!$C$10),A85,INDEX(Clay_Offices!$A$2:$FZ$601,0,Sync!$C$14),"<"&($E$6+1),INDEX(Clay_Offices!$A$2:$FZ$601,0,Sync!$C$5),Config!$B$20,INDEX(Clay_Offices!$A$2:$FZ$601,0,Sync!$C$15),"<>bounce",INDEX(Clay_Offices!$A$2:$FZ$601,0,Sync!$C$15),"<>out_of_office"),0) -> 0 | E85: =IF(C85=0,"",D85/C85) | G85: =IFERROR(COUNTIFS(INDEX(Clay_Offices!$A$2:$FZ$601,0,Sync!$C$10),A85,INDEX(Clay_Offices!$A$2:$FZ$601,0,Sync!$C$14),"<"&($E$6+1),INDEX(Clay_Offices!$A$2:$FZ$601,0,Sync!$C$5),Config!$B$20,INDEX(Clay_Offices!$A$2:$FZ$601,0,Sync!$C$15),"yes"),0)+IFERROR(COUNTIFS(INDEX(Clay_Offices!$A$2:$FZ$601,0,Sync!$C$10),A85,INDEX(Clay_Offices!$A$2:$FZ$601,0,Sync!$C$14),"<"&($E$6+1),INDEX(Clay_Offices!$A$2:$FZ$601,0,Sync!$C$5),Config!$B$20,INDEX(Clay_Offices!$A$2:$FZ$601,0,Sync!$C$15),"maybe"),0)+IFERROR(COUNTIFS(INDEX(Clay_Offices!$A$2:$FZ$601,0,Sync!$C$10),A85,INDEX(Clay_Offices!$A$2:$FZ$601,0,Sync!$C$14),"<"&($E$6+1),INDEX(Clay_Offices!$A$2:$FZ$601,0,Sync!$C$5),Config!$B$20,INDEX(Clay_Offices!$A$2:$FZ$601,0,Sync!$C$15),"needs_approval"),0)+IFERROR(COUNTIFS(INDEX(Clay_Offices!$A$2:$FZ$601,0,Sync!$C$10),A85,INDEX(Clay_Offices!$A$2:$FZ$601,0,Sync!$C$14),"<"&($E$6+1),INDEX(Clay_Offices!$A$2:$FZ$601,0,Sync!$C$5),Config!$B$20,INDEX(Clay_Offices!$A$2:$FZ$601,0,Sync!$C$15),"send_info"),0)+IFERROR(COUNTIFS(INDEX(Clay_Offices!$A$2:$FZ$601,0,Sync!$C$10),A85,INDEX(Clay_Offices!$A$2:$FZ$601,0,Sync!$C$14),"<"&($E$6+1),INDEX(Clay_Offices!$A$2:$FZ$601,0,Sync!$C$5),Config!$B$20,INDEX(Clay_Offices!$A$2:$FZ$601,0,Sync!$C$15),"referral"),0)+IFERROR(COUNTIFS(INDEX(Clay_Offices!$A$2:$FZ$601,0,Sync!$C$10),A85,INDEX(Clay_Offices!$A$2:$FZ$601,0,Sync!$C$14),"<"&($E$6+1),INDEX(Clay_Offices!$A$2:$FZ$601,0,Sync!$C$5),Config!$B$20,INDEX(Clay_Offices!$A$2:$FZ$601,0,Sync!$C$15),"not_now"),0)+IFERROR(COUNTIFS(INDEX(Clay_Offices!$A$2:$FZ$601,0,Sync!$C$10),A85,INDEX(Clay_Offices!$A$2:$FZ$601,0,Sync!$C$14),"<"&($E$6+1),INDEX(Clay_Offices!$A$2:$FZ$601,0,Sync!$C$5),Config!$B$20,INDEX(Clay_Offices!$A$2:$FZ$601,0,Sync!$C$15),"obj_seed_ourselves"),0)+IFERROR(COUNTIFS(INDEX(Clay_Offices!$A$2:$FZ$601,0,Sync!$C$10),A85,INDEX(Clay_Offices!$A$2:$FZ$601,0,Sync!$C$14),"<"&($E$6+1),INDEX(Clay_Offices!$A$2:$FZ$601,0,Sync!$C$5),Config!$B$20,INDEX(Clay_Offices!$A$2:$FZ$601,0,Sync!$C$15),"obj_price"),0)+IFERROR(COUNTIFS(INDEX(Clay_Offices!$A$2:$FZ$601,0,Sync!$C$10),A85,INDEX(Clay_Offices!$A$2:$FZ$601,0,Sync!$C$14),"<"&($E$6+1),INDEX(Clay_Offices!$A$2:$FZ$601,0,Sync!$C$5),Config!$B$20,INDEX(Clay_Offices!$A$2:$FZ$601,0,Sync!$C$15),"obj_free_trial"),0)+IFERROR(COUNTIFS(INDEX(Clay_Offices!$A$2:$FZ$601,0,Sync!$C$10),A85,INDEX(Clay_Offices!$A$2:$FZ$601,0,Sync!$C$14),"<"&($E$6+1),INDEX(Clay_Offices!$A$2:$FZ$601,0,Sync!$C$5),Config!$B$20,INDEX(Clay_Offices!$A$2:$FZ$601,0,Sync!$C$15),"obj_what_we_get"),0)+IFERROR(COUNTIFS(INDEX(Clay_Offices!$A$2:$FZ$601,0,Sync!$C$10),A85,INDEX(Clay_Offices!$A$2:$FZ$601,0,Sync!$C$14),"<"&($E$6+1),INDEX(Clay_Offices!$A$2:$FZ$601,0,Sync!$C$5),Config!$B$20,INDEX(Clay_Offices!$A$2:$FZ$601,0,Sync!$C$15),"obj_other"),0) -> 0
A86: brand-discovery-A | B86: brand | C86: =IFERROR(COUNTIFS(INDEX(Clay_Brands!$A$2:$FZ$601,0,Sync!$D$10),A86,INDEX(Clay_Brands!$A$2:$FZ$601,0,Sync!$D$11),"<"&($E$6+1),INDEX(Clay_Brands!$A$2:$FZ$601,0,Sync!$D$5),Config!$B$20),0) -> 20 | D86: =IFERROR(COUNTIFS(INDEX(Clay_Brands!$A$2:$FZ$601,0,Sync!$D$10),A86,INDEX(Clay_Brands!$A$2:$FZ$601,0,Sync!$D$14),"<"&($E$6+1),INDEX(Clay_Brands!$A$2:$FZ$601,0,Sync!$D$5),Config!$B$20,INDEX(Clay_Brands!$A$2:$FZ$601,0,Sync!$D$15),"<>bounce",INDEX(Clay_Brands!$A$2:$FZ$601,0,Sync!$D$15),"<>out_of_office"),0) -> 10 | E86: =IF(C86=0,"",D86/C86) -> 0.5 | G86: =IFERROR(COUNTIFS(INDEX(Clay_Brands!$A$2:$FZ$601,0,Sync!$D$10),A86,INDEX(Clay_Brands!$A$2:$FZ$601,0,Sync!$D$14),"<"&($E$6+1),INDEX(Clay_Brands!$A$2:$FZ$601,0,Sync!$D$5),Config!$B$20,INDEX(Clay_Brands!$A$2:$FZ$601,0,Sync!$D$15),"yes"),0)+IFERROR(COUNTIFS(INDEX(Clay_Brands!$A$2:$FZ$601,0,Sync!$D$10),A86,INDEX(Clay_Brands!$A$2:$FZ$601,0,Sync!$D$14),"<"&($E$6+1),INDEX(Clay_Brands!$A$2:$FZ$601,0,Sync!$D$5),Config!$B$20,INDEX(Clay_Brands!$A$2:$FZ$601,0,Sync!$D$15),"maybe"),0)+IFERROR(COUNTIFS(INDEX(Clay_Brands!$A$2:$FZ$601,0,Sync!$D$10),A86,INDEX(Clay_Brands!$A$2:$FZ$601,0,Sync!$D$14),"<"&($E$6+1),INDEX(Clay_Brands!$A$2:$FZ$601,0,Sync!$D$5),Config!$B$20,INDEX(Clay_Brands!$A$2:$FZ$601,0,Sync!$D$15),"needs_approval"),0)+IFERROR(COUNTIFS(INDEX(Clay_Brands!$A$2:$FZ$601,0,Sync!$D$10),A86,INDEX(Clay_Brands!$A$2:$FZ$601,0,Sync!$D$14),"<"&($E$6+1),INDEX(Clay_Brands!$A$2:$FZ$601,0,Sync!$D$5),Config!$B$20,INDEX(Clay_Brands!$A$2:$FZ$601,0,Sync!$D$15),"send_info"),0)+IFERROR(COUNTIFS(INDEX(Clay_Brands!$A$2:$FZ$601,0,Sync!$D$10),A86,INDEX(Clay_Brands!$A$2:$FZ$601,0,Sync!$D$14),"<"&($E$6+1),INDEX(Clay_Brands!$A$2:$FZ$601,0,Sync!$D$5),Config!$B$20,INDEX(Clay_Brands!$A$2:$FZ$601,0,Sync!$D$15),"referral"),0)+IFERROR(COUNTIFS(INDEX(Clay_Brands!$A$2:$FZ$601,0,Sync!$D$10),A86,INDEX(Clay_Brands!$A$2:$FZ$601,0,Sync!$D$14),"<"&($E$6+1),INDEX(Clay_Brands!$A$2:$FZ$601,0,Sync!$D$5),Config!$B$20,INDEX(Clay_Brands!$A$2:$FZ$601,0,Sync!$D$15),"not_now"),0)+IFERROR(COUNTIFS(INDEX(Clay_Brands!$A$2:$FZ$601,0,Sync!$D$10),A86,INDEX(Clay_Brands!$A$2:$FZ$601,0,Sync!$D$14),"<"&($E$6+1),INDEX(Clay_Brands!$A$2:$FZ$601,0,Sync!$D$5),Config!$B$20,INDEX(Clay_Brands!$A$2:$FZ$601,0,Sync!$D$15),"obj_seed_ourselves"),0)+IFERROR(COUNTIFS(INDEX(Clay_Brands!$A$2:$FZ$601,0,Sync!$D$10),A86,INDEX(Clay_Brands!$A$2:$FZ$601,0,Sync!$D$14),"<"&($E$6+1),INDEX(Clay_Brands!$A$2:$FZ$601,0,Sync!$D$5),Config!$B$20,INDEX(Clay_Brands!$A$2:$FZ$601,0,Sync!$D$15),"obj_price"),0)+IFERROR(COUNTIFS(INDEX(Clay_Brands!$A$2:$FZ$601,0,Sync!$D$10),A86,INDEX(Clay_Brands!$A$2:$FZ$601,0,Sync!$D$14),"<"&($E$6+1),INDEX(Clay_Brands!$A$2:$FZ$601,0,Sync!$D$5),Config!$B$20,INDEX(Clay_Brands!$A$2:$FZ$601,0,Sync!$D$15),"obj_free_trial"),0)+IFERROR(COUNTIFS(INDEX(Clay_Brands!$A$2:$FZ$601,0,Sync!$D$10),A86,INDEX(Clay_Brands!$A$2:$FZ$601,0,Sync!$D$14),"<"&($E$6+1),INDEX(Clay_Brands!$A$2:$FZ$601,0,Sync!$D$5),Config!$B$20,INDEX(Clay_Brands!$A$2:$FZ$601,0,Sync!$D$15),"obj_what_we_get"),0)+IFERROR(COUNTIFS(INDEX(Clay_Brands!$A$2:$FZ$601,0,Sync!$D$10),A86,INDEX(Clay_Brands!$A$2:$FZ$601,0,Sync!$D$14),"<"&($E$6+1),INDEX(Clay_Brands!$A$2:$FZ$601,0,Sync!$D$5),Config!$B$20,INDEX(Clay_Brands!$A$2:$FZ$601,0,Sync!$D$15),"obj_other"),0) -> 8
A87: brand-discovery-B | B87: brand | C87: =IFERROR(COUNTIFS(INDEX(Clay_Brands!$A$2:$FZ$601,0,Sync!$D$10),A87,INDEX(Clay_Brands!$A$2:$FZ$601,0,Sync!$D$11),"<"&($E$6+1),INDEX(Clay_Brands!$A$2:$FZ$601,0,Sync!$D$5),Config!$B$20),0) -> 20 | D87: =IFERROR(COUNTIFS(INDEX(Clay_Brands!$A$2:$FZ$601,0,Sync!$D$10),A87,INDEX(Clay_Brands!$A$2:$FZ$601,0,Sync!$D$14),"<"&($E$6+1),INDEX(Clay_Brands!$A$2:$FZ$601,0,Sync!$D$5),Config!$B$20,INDEX(Clay_Brands!$A$2:$FZ$601,0,Sync!$D$15),"<>bounce",INDEX(Clay_Brands!$A$2:$FZ$601,0,Sync!$D$15),"<>out_of_office"),0) -> 15 | E87: =IF(C87=0,"",D87/C87) -> 0.75 | G87: =IFERROR(COUNTIFS(INDEX(Clay_Brands!$A$2:$FZ$601,0,Sync!$D$10),A87,INDEX(Clay_Brands!$A$2:$FZ$601,0,Sync!$D$14),"<"&($E$6+1),INDEX(Clay_Brands!$A$2:$FZ$601,0,Sync!$D$5),Config!$B$20,INDEX(Clay_Brands!$A$2:$FZ$601,0,Sync!$D$15),"yes"),0)+IFERROR(COUNTIFS(INDEX(Clay_Brands!$A$2:$FZ$601,0,Sync!$D$10),A87,INDEX(Clay_Brands!$A$2:$FZ$601,0,Sync!$D$14),"<"&($E$6+1),INDEX(Clay_Brands!$A$2:$FZ$601,0,Sync!$D$5),Config!$B$20,INDEX(Clay_Brands!$A$2:$FZ$601,0,Sync!$D$15),"maybe"),0)+IFERROR(COUNTIFS(INDEX(Clay_Brands!$A$2:$FZ$601,0,Sync!$D$10),A87,INDEX(Clay_Brands!$A$2:$FZ$601,0,Sync!$D$14),"<"&($E$6+1),INDEX(Clay_Brands!$A$2:$FZ$601,0,Sync!$D$5),Config!$B$20,INDEX(Clay_Brands!$A$2:$FZ$601,0,Sync!$D$15),"needs_approval"),0)+IFERROR(COUNTIFS(INDEX(Clay_Brands!$A$2:$FZ$601,0,Sync!$D$10),A87,INDEX(Clay_Brands!$A$2:$FZ$601,0,Sync!$D$14),"<"&($E$6+1),INDEX(Clay_Brands!$A$2:$FZ$601,0,Sync!$D$5),Config!$B$20,INDEX(Clay_Brands!$A$2:$FZ$601,0,Sync!$D$15),"send_info"),0)+IFERROR(COUNTIFS(INDEX(Clay_Brands!$A$2:$FZ$601,0,Sync!$D$10),A87,INDEX(Clay_Brands!$A$2:$FZ$601,0,Sync!$D$14),"<"&($E$6+1),INDEX(Clay_Brands!$A$2:$FZ$601,0,Sync!$D$5),Config!$B$20,INDEX(Clay_Brands!$A$2:$FZ$601,0,Sync!$D$15),"referral"),0)+IFERROR(COUNTIFS(INDEX(Clay_Brands!$A$2:$FZ$601,0,Sync!$D$10),A87,INDEX(Clay_Brands!$A$2:$FZ$601,0,Sync!$D$14),"<"&($E$6+1),INDEX(Clay_Brands!$A$2:$FZ$601,0,Sync!$D$5),Config!$B$20,INDEX(Clay_Brands!$A$2:$FZ$601,0,Sync!$D$15),"not_now"),0)+IFERROR(COUNTIFS(INDEX(Clay_Brands!$A$2:$FZ$601,0,Sync!$D$10),A87,INDEX(Clay_Brands!$A$2:$FZ$601,0,Sync!$D$14),"<"&($E$6+1),INDEX(Clay_Brands!$A$2:$FZ$601,0,Sync!$D$5),Config!$B$20,INDEX(Clay_Brands!$A$2:$FZ$601,0,Sync!$D$15),"obj_seed_ourselves"),0)+IFERROR(COUNTIFS(INDEX(Clay_Brands!$A$2:$FZ$601,0,Sync!$D$10),A87,INDEX(Clay_Brands!$A$2:$FZ$601,0,Sync!$D$14),"<"&($E$6+1),INDEX(Clay_Brands!$A$2:$FZ$601,0,Sync!$D$5),Config!$B$20,INDEX(Clay_Brands!$A$2:$FZ$601,0,Sync!$D$15),"obj_price"),0)+IFERROR(COUNTIFS(INDEX(Clay_Brands!$A$2:$FZ$601,0,Sync!$D$10),A87,INDEX(Clay_Brands!$A$2:$FZ$601,0,Sync!$D$14),"<"&($E$6+1),INDEX(Clay_Brands!$A$2:$FZ$601,0,Sync!$D$5),Config!$B$20,INDEX(Clay_Brands!$A$2:$FZ$601,0,Sync!$D$15),"obj_free_trial"),0)+IFERROR(COUNTIFS(INDEX(Clay_Brands!$A$2:$FZ$601,0,Sync!$D$10),A87,INDEX(Clay_Brands!$A$2:$FZ$601,0,Sync!$D$14),"<"&($E$6+1),INDEX(Clay_Brands!$A$2:$FZ$601,0,Sync!$D$5),Config!$B$20,INDEX(Clay_Brands!$A$2:$FZ$601,0,Sync!$D$15),"obj_what_we_get"),0)+IFERROR(COUNTIFS(INDEX(Clay_Brands!$A$2:$FZ$601,0,Sync!$D$10),A87,INDEX(Clay_Brands!$A$2:$FZ$601,0,Sync!$D$14),"<"&($E$6+1),INDEX(Clay_Brands!$A$2:$FZ$601,0,Sync!$D$5),Config!$B$20,INDEX(Clay_Brands!$A$2:$FZ$601,0,Sync!$D$15),"obj_other"),0) -> 13
A88: brand-selling-A | B88: brand | C88: =IFERROR(COUNTIFS(INDEX(Clay_Brands!$A$2:$FZ$601,0,Sync!$D$10),A88,INDEX(Clay_Brands!$A$2:$FZ$601,0,Sync!$D$11),"<"&($E$6+1),INDEX(Clay_Brands!$A$2:$FZ$601,0,Sync!$D$5),Config!$B$20),0) -> 0 | D88: =IFERROR(COUNTIFS(INDEX(Clay_Brands!$A$2:$FZ$601,0,Sync!$D$10),A88,INDEX(Clay_Brands!$A$2:$FZ$601,0,Sync!$D$14),"<"&($E$6+1),INDEX(Clay_Brands!$A$2:$FZ$601,0,Sync!$D$5),Config!$B$20,INDEX(Clay_Brands!$A$2:$FZ$601,0,Sync!$D$15),"<>bounce",INDEX(Clay_Brands!$A$2:$FZ$601,0,Sync!$D$15),"<>out_of_office"),0) -> 0 | E88: =IF(C88=0,"",D88/C88) | G88: =IFERROR(COUNTIFS(INDEX(Clay_Brands!$A$2:$FZ$601,0,Sync!$D$10),A88,INDEX(Clay_Brands!$A$2:$FZ$601,0,Sync!$D$14),"<"&($E$6+1),INDEX(Clay_Brands!$A$2:$FZ$601,0,Sync!$D$5),Config!$B$20,INDEX(Clay_Brands!$A$2:$FZ$601,0,Sync!$D$15),"yes"),0)+IFERROR(COUNTIFS(INDEX(Clay_Brands!$A$2:$FZ$601,0,Sync!$D$10),A88,INDEX(Clay_Brands!$A$2:$FZ$601,0,Sync!$D$14),"<"&($E$6+1),INDEX(Clay_Brands!$A$2:$FZ$601,0,Sync!$D$5),Config!$B$20,INDEX(Clay_Brands!$A$2:$FZ$601,0,Sync!$D$15),"maybe"),0)+IFERROR(COUNTIFS(INDEX(Clay_Brands!$A$2:$FZ$601,0,Sync!$D$10),A88,INDEX(Clay_Brands!$A$2:$FZ$601,0,Sync!$D$14),"<"&($E$6+1),INDEX(Clay_Brands!$A$2:$FZ$601,0,Sync!$D$5),Config!$B$20,INDEX(Clay_Brands!$A$2:$FZ$601,0,Sync!$D$15),"needs_approval"),0)+IFERROR(COUNTIFS(INDEX(Clay_Brands!$A$2:$FZ$601,0,Sync!$D$10),A88,INDEX(Clay_Brands!$A$2:$FZ$601,0,Sync!$D$14),"<"&($E$6+1),INDEX(Clay_Brands!$A$2:$FZ$601,0,Sync!$D$5),Config!$B$20,INDEX(Clay_Brands!$A$2:$FZ$601,0,Sync!$D$15),"send_info"),0)+IFERROR(COUNTIFS(INDEX(Clay_Brands!$A$2:$FZ$601,0,Sync!$D$10),A88,INDEX(Clay_Brands!$A$2:$FZ$601,0,Sync!$D$14),"<"&($E$6+1),INDEX(Clay_Brands!$A$2:$FZ$601,0,Sync!$D$5),Config!$B$20,INDEX(Clay_Brands!$A$2:$FZ$601,0,Sync!$D$15),"referral"),0)+IFERROR(COUNTIFS(INDEX(Clay_Brands!$A$2:$FZ$601,0,Sync!$D$10),A88,INDEX(Clay_Brands!$A$2:$FZ$601,0,Sync!$D$14),"<"&($E$6+1),INDEX(Clay_Brands!$A$2:$FZ$601,0,Sync!$D$5),Config!$B$20,INDEX(Clay_Brands!$A$2:$FZ$601,0,Sync!$D$15),"not_now"),0)+IFERROR(COUNTIFS(INDEX(Clay_Brands!$A$2:$FZ$601,0,Sync!$D$10),A88,INDEX(Clay_Brands!$A$2:$FZ$601,0,Sync!$D$14),"<"&($E$6+1),INDEX(Clay_Brands!$A$2:$FZ$601,0,Sync!$D$5),Config!$B$20,INDEX(Clay_Brands!$A$2:$FZ$601,0,Sync!$D$15),"obj_seed_ourselves"),0)+IFERROR(COUNTIFS(INDEX(Clay_Brands!$A$2:$FZ$601,0,Sync!$D$10),A88,INDEX(Clay_Brands!$A$2:$FZ$601,0,Sync!$D$14),"<"&($E$6+1),INDEX(Clay_Brands!$A$2:$FZ$601,0,Sync!$D$5),Config!$B$20,INDEX(Clay_Brands!$A$2:$FZ$601,0,Sync!$D$15),"obj_price"),0)+IFERROR(COUNTIFS(INDEX(Clay_Brands!$A$2:$FZ$601,0,Sync!$D$10),A88,INDEX(Clay_Brands!$A$2:$FZ$601,0,Sync!$D$14),"<"&($E$6+1),INDEX(Clay_Brands!$A$2:$FZ$601,0,Sync!$D$5),Config!$B$20,INDEX(Clay_Brands!$A$2:$FZ$601,0,Sync!$D$15),"obj_free_trial"),0)+IFERROR(COUNTIFS(INDEX(Clay_Brands!$A$2:$FZ$601,0,Sync!$D$10),A88,INDEX(Clay_Brands!$A$2:$FZ$601,0,Sync!$D$14),"<"&($E$6+1),INDEX(Clay_Brands!$A$2:$FZ$601,0,Sync!$D$5),Config!$B$20,INDEX(Clay_Brands!$A$2:$FZ$601,0,Sync!$D$15),"obj_what_we_get"),0)+IFERROR(COUNTIFS(INDEX(Clay_Brands!$A$2:$FZ$601,0,Sync!$D$10),A88,INDEX(Clay_Brands!$A$2:$FZ$601,0,Sync!$D$14),"<"&($E$6+1),INDEX(Clay_Brands!$A$2:$FZ$601,0,Sync!$D$5),Config!$B$20,INDEX(Clay_Brands!$A$2:$FZ$601,0,Sync!$D$15),"obj_other"),0) -> 0
A89: brand-selling-B | B89: brand | C89: =IFERROR(COUNTIFS(INDEX(Clay_Brands!$A$2:$FZ$601,0,Sync!$D$10),A89,INDEX(Clay_Brands!$A$2:$FZ$601,0,Sync!$D$11),"<"&($E$6+1),INDEX(Clay_Brands!$A$2:$FZ$601,0,Sync!$D$5),Config!$B$20),0) -> 0 | D89: =IFERROR(COUNTIFS(INDEX(Clay_Brands!$A$2:$FZ$601,0,Sync!$D$10),A89,INDEX(Clay_Brands!$A$2:$FZ$601,0,Sync!$D$14),"<"&($E$6+1),INDEX(Clay_Brands!$A$2:$FZ$601,0,Sync!$D$5),Config!$B$20,INDEX(Clay_Brands!$A$2:$FZ$601,0,Sync!$D$15),"<>bounce",INDEX(Clay_Brands!$A$2:$FZ$601,0,Sync!$D$15),"<>out_of_office"),0) -> 0 | E89: =IF(C89=0,"",D89/C89) | G89: =IFERROR(COUNTIFS(INDEX(Clay_Brands!$A$2:$FZ$601,0,Sync!$D$10),A89,INDEX(Clay_Brands!$A$2:$FZ$601,0,Sync!$D$14),"<"&($E$6+1),INDEX(Clay_Brands!$A$2:$FZ$601,0,Sync!$D$5),Config!$B$20,INDEX(Clay_Brands!$A$2:$FZ$601,0,Sync!$D$15),"yes"),0)+IFERROR(COUNTIFS(INDEX(Clay_Brands!$A$2:$FZ$601,0,Sync!$D$10),A89,INDEX(Clay_Brands!$A$2:$FZ$601,0,Sync!$D$14),"<"&($E$6+1),INDEX(Clay_Brands!$A$2:$FZ$601,0,Sync!$D$5),Config!$B$20,INDEX(Clay_Brands!$A$2:$FZ$601,0,Sync!$D$15),"maybe"),0)+IFERROR(COUNTIFS(INDEX(Clay_Brands!$A$2:$FZ$601,0,Sync!$D$10),A89,INDEX(Clay_Brands!$A$2:$FZ$601,0,Sync!$D$14),"<"&($E$6+1),INDEX(Clay_Brands!$A$2:$FZ$601,0,Sync!$D$5),Config!$B$20,INDEX(Clay_Brands!$A$2:$FZ$601,0,Sync!$D$15),"needs_approval"),0)+IFERROR(COUNTIFS(INDEX(Clay_Brands!$A$2:$FZ$601,0,Sync!$D$10),A89,INDEX(Clay_Brands!$A$2:$FZ$601,0,Sync!$D$14),"<"&($E$6+1),INDEX(Clay_Brands!$A$2:$FZ$601,0,Sync!$D$5),Config!$B$20,INDEX(Clay_Brands!$A$2:$FZ$601,0,Sync!$D$15),"send_info"),0)+IFERROR(COUNTIFS(INDEX(Clay_Brands!$A$2:$FZ$601,0,Sync!$D$10),A89,INDEX(Clay_Brands!$A$2:$FZ$601,0,Sync!$D$14),"<"&($E$6+1),INDEX(Clay_Brands!$A$2:$FZ$601,0,Sync!$D$5),Config!$B$20,INDEX(Clay_Brands!$A$2:$FZ$601,0,Sync!$D$15),"referral"),0)+IFERROR(COUNTIFS(INDEX(Clay_Brands!$A$2:$FZ$601,0,Sync!$D$10),A89,INDEX(Clay_Brands!$A$2:$FZ$601,0,Sync!$D$14),"<"&($E$6+1),INDEX(Clay_Brands!$A$2:$FZ$601,0,Sync!$D$5),Config!$B$20,INDEX(Clay_Brands!$A$2:$FZ$601,0,Sync!$D$15),"not_now"),0)+IFERROR(COUNTIFS(INDEX(Clay_Brands!$A$2:$FZ$601,0,Sync!$D$10),A89,INDEX(Clay_Brands!$A$2:$FZ$601,0,Sync!$D$14),"<"&($E$6+1),INDEX(Clay_Brands!$A$2:$FZ$601,0,Sync!$D$5),Config!$B$20,INDEX(Clay_Brands!$A$2:$FZ$601,0,Sync!$D$15),"obj_seed_ourselves"),0)+IFERROR(COUNTIFS(INDEX(Clay_Brands!$A$2:$FZ$601,0,Sync!$D$10),A89,INDEX(Clay_Brands!$A$2:$FZ$601,0,Sync!$D$14),"<"&($E$6+1),INDEX(Clay_Brands!$A$2:$FZ$601,0,Sync!$D$5),Config!$B$20,INDEX(Clay_Brands!$A$2:$FZ$601,0,Sync!$D$15),"obj_price"),0)+IFERROR(COUNTIFS(INDEX(Clay_Brands!$A$2:$FZ$601,0,Sync!$D$10),A89,INDEX(Clay_Brands!$A$2:$FZ$601,0,Sync!$D$14),"<"&($E$6+1),INDEX(Clay_Brands!$A$2:$FZ$601,0,Sync!$D$5),Config!$B$20,INDEX(Clay_Brands!$A$2:$FZ$601,0,Sync!$D$15),"obj_free_trial"),0)+IFERROR(COUNTIFS(INDEX(Clay_Brands!$A$2:$FZ$601,0,Sync!$D$10),A89,INDEX(Clay_Brands!$A$2:$FZ$601,0,Sync!$D$14),"<"&($E$6+1),INDEX(Clay_Brands!$A$2:$FZ$601,0,Sync!$D$5),Config!$B$20,INDEX(Clay_Brands!$A$2:$FZ$601,0,Sync!$D$15),"obj_what_we_get"),0)+IFERROR(COUNTIFS(INDEX(Clay_Brands!$A$2:$FZ$601,0,Sync!$D$10),A89,INDEX(Clay_Brands!$A$2:$FZ$601,0,Sync!$D$14),"<"&($E$6+1),INDEX(Clay_Brands!$A$2:$FZ$601,0,Sync!$D$5),Config!$B$20,INDEX(Clay_Brands!$A$2:$FZ$601,0,Sync!$D$15),"obj_other"),0) -> 0
A90: office-conversion-A | B90: office | C90: =IFERROR(COUNTIFS(INDEX(Clay_Offices!$A$2:$FZ$601,0,Sync!$C$10),A90,INDEX(Clay_Offices!$A$2:$FZ$601,0,Sync!$C$11),"<"&($E$6+1),INDEX(Clay_Offices!$A$2:$FZ$601,0,Sync!$C$5),Config!$B$20),0) -> 0 | D90: =IFERROR(COUNTIFS(INDEX(Clay_Offices!$A$2:$FZ$601,0,Sync!$C$10),A90,INDEX(Clay_Offices!$A$2:$FZ$601,0,Sync!$C$14),"<"&($E$6+1),INDEX(Clay_Offices!$A$2:$FZ$601,0,Sync!$C$5),Config!$B$20,INDEX(Clay_Offices!$A$2:$FZ$601,0,Sync!$C$15),"<>bounce",INDEX(Clay_Offices!$A$2:$FZ$601,0,Sync!$C$15),"<>out_of_office"),0) -> 0 | E90: =IF(C90=0,"",D90/C90) | G90: =IFERROR(COUNTIFS(INDEX(Clay_Offices!$A$2:$FZ$601,0,Sync!$C$10),A90,INDEX(Clay_Offices!$A$2:$FZ$601,0,Sync!$C$14),"<"&($E$6+1),INDEX(Clay_Offices!$A$2:$FZ$601,0,Sync!$C$5),Config!$B$20,INDEX(Clay_Offices!$A$2:$FZ$601,0,Sync!$C$15),"yes"),0)+IFERROR(COUNTIFS(INDEX(Clay_Offices!$A$2:$FZ$601,0,Sync!$C$10),A90,INDEX(Clay_Offices!$A$2:$FZ$601,0,Sync!$C$14),"<"&($E$6+1),INDEX(Clay_Offices!$A$2:$FZ$601,0,Sync!$C$5),Config!$B$20,INDEX(Clay_Offices!$A$2:$FZ$601,0,Sync!$C$15),"maybe"),0)+IFERROR(COUNTIFS(INDEX(Clay_Offices!$A$2:$FZ$601,0,Sync!$C$10),A90,INDEX(Clay_Offices!$A$2:$FZ$601,0,Sync!$C$14),"<"&($E$6+1),INDEX(Clay_Offices!$A$2:$FZ$601,0,Sync!$C$5),Config!$B$20,INDEX(Clay_Offices!$A$2:$FZ$601,0,Sync!$C$15),"needs_approval"),0)+IFERROR(COUNTIFS(INDEX(Clay_Offices!$A$2:$FZ$601,0,Sync!$C$10),A90,INDEX(Clay_Offices!$A$2:$FZ$601,0,Sync!$C$14),"<"&($E$6+1),INDEX(Clay_Offices!$A$2:$FZ$601,0,Sync!$C$5),Config!$B$20,INDEX(Clay_Offices!$A$2:$FZ$601,0,Sync!$C$15),"send_info"),0)+IFERROR(COUNTIFS(INDEX(Clay_Offices!$A$2:$FZ$601,0,Sync!$C$10),A90,INDEX(Clay_Offices!$A$2:$FZ$601,0,Sync!$C$14),"<"&($E$6+1),INDEX(Clay_Offices!$A$2:$FZ$601,0,Sync!$C$5),Config!$B$20,INDEX(Clay_Offices!$A$2:$FZ$601,0,Sync!$C$15),"referral"),0)+IFERROR(COUNTIFS(INDEX(Clay_Offices!$A$2:$FZ$601,0,Sync!$C$10),A90,INDEX(Clay_Offices!$A$2:$FZ$601,0,Sync!$C$14),"<"&($E$6+1),INDEX(Clay_Offices!$A$2:$FZ$601,0,Sync!$C$5),Config!$B$20,INDEX(Clay_Offices!$A$2:$FZ$601,0,Sync!$C$15),"not_now"),0)+IFERROR(COUNTIFS(INDEX(Clay_Offices!$A$2:$FZ$601,0,Sync!$C$10),A90,INDEX(Clay_Offices!$A$2:$FZ$601,0,Sync!$C$14),"<"&($E$6+1),INDEX(Clay_Offices!$A$2:$FZ$601,0,Sync!$C$5),Config!$B$20,INDEX(Clay_Offices!$A$2:$FZ$601,0,Sync!$C$15),"obj_seed_ourselves"),0)+IFERROR(COUNTIFS(INDEX(Clay_Offices!$A$2:$FZ$601,0,Sync!$C$10),A90,INDEX(Clay_Offices!$A$2:$FZ$601,0,Sync!$C$14),"<"&($E$6+1),INDEX(Clay_Offices!$A$2:$FZ$601,0,Sync!$C$5),Config!$B$20,INDEX(Clay_Offices!$A$2:$FZ$601,0,Sync!$C$15),"obj_price"),0)+IFERROR(COUNTIFS(INDEX(Clay_Offices!$A$2:$FZ$601,0,Sync!$C$10),A90,INDEX(Clay_Offices!$A$2:$FZ$601,0,Sync!$C$14),"<"&($E$6+1),INDEX(Clay_Offices!$A$2:$FZ$601,0,Sync!$C$5),Config!$B$20,INDEX(Clay_Offices!$A$2:$FZ$601,0,Sync!$C$15),"obj_free_trial"),0)+IFERROR(COUNTIFS(INDEX(Clay_Offices!$A$2:$FZ$601,0,Sync!$C$10),A90,INDEX(Clay_Offices!$A$2:$FZ$601,0,Sync!$C$14),"<"&($E$6+1),INDEX(Clay_Offices!$A$2:$FZ$601,0,Sync!$C$5),Config!$B$20,INDEX(Clay_Offices!$A$2:$FZ$601,0,Sync!$C$15),"obj_what_we_get"),0)+IFERROR(COUNTIFS(INDEX(Clay_Offices!$A$2:$FZ$601,0,Sync!$C$10),A90,INDEX(Clay_Offices!$A$2:$FZ$601,0,Sync!$C$14),"<"&($E$6+1),INDEX(Clay_Offices!$A$2:$FZ$601,0,Sync!$C$5),Config!$B$20,INDEX(Clay_Offices!$A$2:$FZ$601,0,Sync!$C$15),"obj_other"),0) -> 0
A91: brand-conversion-A | B91: brand | C91: =IFERROR(COUNTIFS(INDEX(Clay_Brands!$A$2:$FZ$601,0,Sync!$D$10),A91,INDEX(Clay_Brands!$A$2:$FZ$601,0,Sync!$D$11),"<"&($E$6+1),INDEX(Clay_Brands!$A$2:$FZ$601,0,Sync!$D$5),Config!$B$20),0) -> 0 | D91: =IFERROR(COUNTIFS(INDEX(Clay_Brands!$A$2:$FZ$601,0,Sync!$D$10),A91,INDEX(Clay_Brands!$A$2:$FZ$601,0,Sync!$D$14),"<"&($E$6+1),INDEX(Clay_Brands!$A$2:$FZ$601,0,Sync!$D$5),Config!$B$20,INDEX(Clay_Brands!$A$2:$FZ$601,0,Sync!$D$15),"<>bounce",INDEX(Clay_Brands!$A$2:$FZ$601,0,Sync!$D$15),"<>out_of_office"),0) -> 0 | E91: =IF(C91=0,"",D91/C91) | G91: =IFERROR(COUNTIFS(INDEX(Clay_Brands!$A$2:$FZ$601,0,Sync!$D$10),A91,INDEX(Clay_Brands!$A$2:$FZ$601,0,Sync!$D$14),"<"&($E$6+1),INDEX(Clay_Brands!$A$2:$FZ$601,0,Sync!$D$5),Config!$B$20,INDEX(Clay_Brands!$A$2:$FZ$601,0,Sync!$D$15),"yes"),0)+IFERROR(COUNTIFS(INDEX(Clay_Brands!$A$2:$FZ$601,0,Sync!$D$10),A91,INDEX(Clay_Brands!$A$2:$FZ$601,0,Sync!$D$14),"<"&($E$6+1),INDEX(Clay_Brands!$A$2:$FZ$601,0,Sync!$D$5),Config!$B$20,INDEX(Clay_Brands!$A$2:$FZ$601,0,Sync!$D$15),"maybe"),0)+IFERROR(COUNTIFS(INDEX(Clay_Brands!$A$2:$FZ$601,0,Sync!$D$10),A91,INDEX(Clay_Brands!$A$2:$FZ$601,0,Sync!$D$14),"<"&($E$6+1),INDEX(Clay_Brands!$A$2:$FZ$601,0,Sync!$D$5),Config!$B$20,INDEX(Clay_Brands!$A$2:$FZ$601,0,Sync!$D$15),"needs_approval"),0)+IFERROR(COUNTIFS(INDEX(Clay_Brands!$A$2:$FZ$601,0,Sync!$D$10),A91,INDEX(Clay_Brands!$A$2:$FZ$601,0,Sync!$D$14),"<"&($E$6+1),INDEX(Clay_Brands!$A$2:$FZ$601,0,Sync!$D$5),Config!$B$20,INDEX(Clay_Brands!$A$2:$FZ$601,0,Sync!$D$15),"send_info"),0)+IFERROR(COUNTIFS(INDEX(Clay_Brands!$A$2:$FZ$601,0,Sync!$D$10),A91,INDEX(Clay_Brands!$A$2:$FZ$601,0,Sync!$D$14),"<"&($E$6+1),INDEX(Clay_Brands!$A$2:$FZ$601,0,Sync!$D$5),Config!$B$20,INDEX(Clay_Brands!$A$2:$FZ$601,0,Sync!$D$15),"referral"),0)+IFERROR(COUNTIFS(INDEX(Clay_Brands!$A$2:$FZ$601,0,Sync!$D$10),A91,INDEX(Clay_Brands!$A$2:$FZ$601,0,Sync!$D$14),"<"&($E$6+1),INDEX(Clay_Brands!$A$2:$FZ$601,0,Sync!$D$5),Config!$B$20,INDEX(Clay_Brands!$A$2:$FZ$601,0,Sync!$D$15),"not_now"),0)+IFERROR(COUNTIFS(INDEX(Clay_Brands!$A$2:$FZ$601,0,Sync!$D$10),A91,INDEX(Clay_Brands!$A$2:$FZ$601,0,Sync!$D$14),"<"&($E$6+1),INDEX(Clay_Brands!$A$2:$FZ$601,0,Sync!$D$5),Config!$B$20,INDEX(Clay_Brands!$A$2:$FZ$601,0,Sync!$D$15),"obj_seed_ourselves"),0)+IFERROR(COUNTIFS(INDEX(Clay_Brands!$A$2:$FZ$601,0,Sync!$D$10),A91,INDEX(Clay_Brands!$A$2:$FZ$601,0,Sync!$D$14),"<"&($E$6+1),INDEX(Clay_Brands!$A$2:$FZ$601,0,Sync!$D$5),Config!$B$20,INDEX(Clay_Brands!$A$2:$FZ$601,0,Sync!$D$15),"obj_price"),0)+IFERROR(COUNTIFS(INDEX(Clay_Brands!$A$2:$FZ$601,0,Sync!$D$10),A91,INDEX(Clay_Brands!$A$2:$FZ$601,0,Sync!$D$14),"<"&($E$6+1),INDEX(Clay_Brands!$A$2:$FZ$601,0,Sync!$D$5),Config!$B$20,INDEX(Clay_Brands!$A$2:$FZ$601,0,Sync!$D$15),"obj_free_trial"),0)+IFERROR(COUNTIFS(INDEX(Clay_Brands!$A$2:$FZ$601,0,Sync!$D$10),A91,INDEX(Clay_Brands!$A$2:$FZ$601,0,Sync!$D$14),"<"&($E$6+1),INDEX(Clay_Brands!$A$2:$FZ$601,0,Sync!$D$5),Config!$B$20,INDEX(Clay_Brands!$A$2:$FZ$601,0,Sync!$D$15),"obj_what_we_get"),0)+IFERROR(COUNTIFS(INDEX(Clay_Brands!$A$2:$FZ$601,0,Sync!$D$10),A91,INDEX(Clay_Brands!$A$2:$FZ$601,0,Sync!$D$14),"<"&($E$6+1),INDEX(Clay_Brands!$A$2:$FZ$601,0,Sync!$D$5),Config!$B$20,INDEX(Clay_Brands!$A$2:$FZ$601,0,Sync!$D$15),"obj_other"),0) -> 0
A92: channel: email | B92: office | C92: =IFERROR(COUNTIFS(INDEX(Clay_Offices!$A$2:$FZ$601,0,Sync!$C$9),"email",INDEX(Clay_Offices!$A$2:$FZ$601,0,Sync!$C$11),"<"&($E$6+1),INDEX(Clay_Offices!$A$2:$FZ$601,0,Sync!$C$5),Config!$B$20),0) -> 9 | D92: =IFERROR(COUNTIFS(INDEX(Clay_Offices!$A$2:$FZ$601,0,Sync!$C$9),"email",INDEX(Clay_Offices!$A$2:$FZ$601,0,Sync!$C$14),"<"&($E$6+1),INDEX(Clay_Offices!$A$2:$FZ$601,0,Sync!$C$5),Config!$B$20,INDEX(Clay_Offices!$A$2:$FZ$601,0,Sync!$C$15),"<>bounce",INDEX(Clay_Offices!$A$2:$FZ$601,0,Sync!$C$15),"<>out_of_office"),0) -> 2 | E92: =IF(C92=0,"",D92/C92) -> 0.22222222 | G92: =IFERROR(COUNTIFS(INDEX(Clay_Offices!$A$2:$FZ$601,0,Sync!$C$9),"email",INDEX(Clay_Offices!$A$2:$FZ$601,0,Sync!$C$14),"<"&($E$6+1),INDEX(Clay_Offices!$A$2:$FZ$601,0,Sync!$C$5),Config!$B$20,INDEX(Clay_Offices!$A$2:$FZ$601,0,Sync!$C$15),"yes"),0)+IFERROR(COUNTIFS(INDEX(Clay_Offices!$A$2:$FZ$601,0,Sync!$C$9),"email",INDEX(Clay_Offices!$A$2:$FZ$601,0,Sync!$C$14),"<"&($E$6+1),INDEX(Clay_Offices!$A$2:$FZ$601,0,Sync!$C$5),Config!$B$20,INDEX(Clay_Offices!$A$2:$FZ$601,0,Sync!$C$15),"maybe"),0)+IFERROR(COUNTIFS(INDEX(Clay_Offices!$A$2:$FZ$601,0,Sync!$C$9),"email",INDEX(Clay_Offices!$A$2:$FZ$601,0,Sync!$C$14),"<"&($E$6+1),INDEX(Clay_Offices!$A$2:$FZ$601,0,Sync!$C$5),Config!$B$20,INDEX(Clay_Offices!$A$2:$FZ$601,0,Sync!$C$15),"needs_approval"),0)+IFERROR(COUNTIFS(INDEX(Clay_Offices!$A$2:$FZ$601,0,Sync!$C$9),"email",INDEX(Clay_Offices!$A$2:$FZ$601,0,Sync!$C$14),"<"&($E$6+1),INDEX(Clay_Offices!$A$2:$FZ$601,0,Sync!$C$5),Config!$B$20,INDEX(Clay_Offices!$A$2:$FZ$601,0,Sync!$C$15),"send_info"),0)+IFERROR(COUNTIFS(INDEX(Clay_Offices!$A$2:$FZ$601,0,Sync!$C$9),"email",INDEX(Clay_Offices!$A$2:$FZ$601,0,Sync!$C$14),"<"&($E$6+1),INDEX(Clay_Offices!$A$2:$FZ$601,0,Sync!$C$5),Config!$B$20,INDEX(Clay_Offices!$A$2:$FZ$601,0,Sync!$C$15),"referral"),0)+IFERROR(COUNTIFS(INDEX(Clay_Offices!$A$2:$FZ$601,0,Sync!$C$9),"email",INDEX(Clay_Offices!$A$2:$FZ$601,0,Sync!$C$14),"<"&($E$6+1),INDEX(Clay_Offices!$A$2:$FZ$601,0,Sync!$C$5),Config!$B$20,INDEX(Clay_Offices!$A$2:$FZ$601,0,Sync!$C$15),"not_now"),0)+IFERROR(COUNTIFS(INDEX(Clay_Offices!$A$2:$FZ$601,0,Sync!$C$9),"email",INDEX(Clay_Offices!$A$2:$FZ$601,0,Sync!$C$14),"<"&($E$6+1),INDEX(Clay_Offices!$A$2:$FZ$601,0,Sync!$C$5),Config!$B$20,INDEX(Clay_Offices!$A$2:$FZ$601,0,Sync!$C$15),"obj_seed_ourselves"),0)+IFERROR(COUNTIFS(INDEX(Clay_Offices!$A$2:$FZ$601,0,Sync!$C$9),"email",INDEX(Clay_Offices!$A$2:$FZ$601,0,Sync!$C$14),"<"&($E$6+1),INDEX(Clay_Offices!$A$2:$FZ$601,0,Sync!$C$5),Config!$B$20,INDEX(Clay_Offices!$A$2:$FZ$601,0,Sync!$C$15),"obj_price"),0)+IFERROR(COUNTIFS(INDEX(Clay_Offices!$A$2:$FZ$601,0,Sync!$C$9),"email",INDEX(Clay_Offices!$A$2:$FZ$601,0,Sync!$C$14),"<"&($E$6+1),INDEX(Clay_Offices!$A$2:$FZ$601,0,Sync!$C$5),Config!$B$20,INDEX(Clay_Offices!$A$2:$FZ$601,0,Sync!$C$15),"obj_free_trial"),0)+IFERROR(COUNTIFS(INDEX(Clay_Offices!$A$2:$FZ$601,0,Sync!$C$9),"email",INDEX(Clay_Offices!$A$2:$FZ$601,0,Sync!$C$14),"<"&($E$6+1),INDEX(Clay_Offices!$A$2:$FZ$601,0,Sync!$C$5),Config!$B$20,INDEX(Clay_Offices!$A$2:$FZ$601,0,Sync!$C$15),"obj_what_we_get"),0)+IFERROR(COUNTIFS(INDEX(Clay_Offices!$A$2:$FZ$601,0,Sync!$C$9),"email",INDEX(Clay_Offices!$A$2:$FZ$601,0,Sync!$C$14),"<"&($E$6+1),INDEX(Clay_Offices!$A$2:$FZ$601,0,Sync!$C$5),Config!$B$20,INDEX(Clay_Offices!$A$2:$FZ$601,0,Sync!$C$15),"obj_other"),0) -> 1
A93: channel: email | B93: brand | C93: =IFERROR(COUNTIFS(INDEX(Clay_Brands!$A$2:$FZ$601,0,Sync!$D$9),"email",INDEX(Clay_Brands!$A$2:$FZ$601,0,Sync!$D$11),"<"&($E$6+1),INDEX(Clay_Brands!$A$2:$FZ$601,0,Sync!$D$5),Config!$B$20),0) -> 10 | D93: =IFERROR(COUNTIFS(INDEX(Clay_Brands!$A$2:$FZ$601,0,Sync!$D$9),"email",INDEX(Clay_Brands!$A$2:$FZ$601,0,Sync!$D$14),"<"&($E$6+1),INDEX(Clay_Brands!$A$2:$FZ$601,0,Sync!$D$5),Config!$B$20,INDEX(Clay_Brands!$A$2:$FZ$601,0,Sync!$D$15),"<>bounce",INDEX(Clay_Brands!$A$2:$FZ$601,0,Sync!$D$15),"<>out_of_office"),0) -> 3 | E93: =IF(C93=0,"",D93/C93) -> 0.3 | G93: =IFERROR(COUNTIFS(INDEX(Clay_Brands!$A$2:$FZ$601,0,Sync!$D$9),"email",INDEX(Clay_Brands!$A$2:$FZ$601,0,Sync!$D$14),"<"&($E$6+1),INDEX(Clay_Brands!$A$2:$FZ$601,0,Sync!$D$5),Config!$B$20,INDEX(Clay_Brands!$A$2:$FZ$601,0,Sync!$D$15),"yes"),0)+IFERROR(COUNTIFS(INDEX(Clay_Brands!$A$2:$FZ$601,0,Sync!$D$9),"email",INDEX(Clay_Brands!$A$2:$FZ$601,0,Sync!$D$14),"<"&($E$6+1),INDEX(Clay_Brands!$A$2:$FZ$601,0,Sync!$D$5),Config!$B$20,INDEX(Clay_Brands!$A$2:$FZ$601,0,Sync!$D$15),"maybe"),0)+IFERROR(COUNTIFS(INDEX(Clay_Brands!$A$2:$FZ$601,0,Sync!$D$9),"email",INDEX(Clay_Brands!$A$2:$FZ$601,0,Sync!$D$14),"<"&($E$6+1),INDEX(Clay_Brands!$A$2:$FZ$601,0,Sync!$D$5),Config!$B$20,INDEX(Clay_Brands!$A$2:$FZ$601,0,Sync!$D$15),"needs_approval"),0)+IFERROR(COUNTIFS(INDEX(Clay_Brands!$A$2:$FZ$601,0,Sync!$D$9),"email",INDEX(Clay_Brands!$A$2:$FZ$601,0,Sync!$D$14),"<"&($E$6+1),INDEX(Clay_Brands!$A$2:$FZ$601,0,Sync!$D$5),Config!$B$20,INDEX(Clay_Brands!$A$2:$FZ$601,0,Sync!$D$15),"send_info"),0)+IFERROR(COUNTIFS(INDEX(Clay_Brands!$A$2:$FZ$601,0,Sync!$D$9),"email",INDEX(Clay_Brands!$A$2:$FZ$601,0,Sync!$D$14),"<"&($E$6+1),INDEX(Clay_Brands!$A$2:$FZ$601,0,Sync!$D$5),Config!$B$20,INDEX(Clay_Brands!$A$2:$FZ$601,0,Sync!$D$15),"referral"),0)+IFERROR(COUNTIFS(INDEX(Clay_Brands!$A$2:$FZ$601,0,Sync!$D$9),"email",INDEX(Clay_Brands!$A$2:$FZ$601,0,Sync!$D$14),"<"&($E$6+1),INDEX(Clay_Brands!$A$2:$FZ$601,0,Sync!$D$5),Config!$B$20,INDEX(Clay_Brands!$A$2:$FZ$601,0,Sync!$D$15),"not_now"),0)+IFERROR(COUNTIFS(INDEX(Clay_Brands!$A$2:$FZ$601,0,Sync!$D$9),"email",INDEX(Clay_Brands!$A$2:$FZ$601,0,Sync!$D$14),"<"&($E$6+1),INDEX(Clay_Brands!$A$2:$FZ$601,0,Sync!$D$5),Config!$B$20,INDEX(Clay_Brands!$A$2:$FZ$601,0,Sync!$D$15),"obj_seed_ourselves"),0)+IFERROR(COUNTIFS(INDEX(Clay_Brands!$A$2:$FZ$601,0,Sync!$D$9),"email",INDEX(Clay_Brands!$A$2:$FZ$601,0,Sync!$D$14),"<"&($E$6+1),INDEX(Clay_Brands!$A$2:$FZ$601,0,Sync!$D$5),Config!$B$20,INDEX(Clay_Brands!$A$2:$FZ$601,0,Sync!$D$15),"obj_price"),0)+IFERROR(COUNTIFS(INDEX(Clay_Brands!$A$2:$FZ$601,0,Sync!$D$9),"email",INDEX(Clay_Brands!$A$2:$FZ$601,0,Sync!$D$14),"<"&($E$6+1),INDEX(Clay_Brands!$A$2:$FZ$601,0,Sync!$D$5),Config!$B$20,INDEX(Clay_Brands!$A$2:$FZ$601,0,Sync!$D$15),"obj_free_trial"),0)+IFERROR(COUNTIFS(INDEX(Clay_Brands!$A$2:$FZ$601,0,Sync!$D$9),"email",INDEX(Clay_Brands!$A$2:$FZ$601,0,Sync!$D$14),"<"&($E$6+1),INDEX(Clay_Brands!$A$2:$FZ$601,0,Sync!$D$5),Config!$B$20,INDEX(Clay_Brands!$A$2:$FZ$601,0,Sync!$D$15),"obj_what_we_get"),0)+IFERROR(COUNTIFS(INDEX(Clay_Brands!$A$2:$FZ$601,0,Sync!$D$9),"email",INDEX(Clay_Brands!$A$2:$FZ$601,0,Sync!$D$14),"<"&($E$6+1),INDEX(Clay_Brands!$A$2:$FZ$601,0,Sync!$D$5),Config!$B$20,INDEX(Clay_Brands!$A$2:$FZ$601,0,Sync!$D$15),"obj_other"),0) -> 2
A94: channel: linkedin | B94: office | C94: =IFERROR(COUNTIFS(INDEX(Clay_Offices!$A$2:$FZ$601,0,Sync!$C$9),"linkedin",INDEX(Clay_Offices!$A$2:$FZ$601,0,Sync!$C$11),"<"&($E$6+1),INDEX(Clay_Offices!$A$2:$FZ$601,0,Sync!$C$5),Config!$B$20),0) -> 24 | D94: =IFERROR(COUNTIFS(INDEX(Clay_Offices!$A$2:$FZ$601,0,Sync!$C$9),"linkedin",INDEX(Clay_Offices!$A$2:$FZ$601,0,Sync!$C$14),"<"&($E$6+1),INDEX(Clay_Offices!$A$2:$FZ$601,0,Sync!$C$5),Config!$B$20,INDEX(Clay_Offices!$A$2:$FZ$601,0,Sync!$C$15),"<>bounce",INDEX(Clay_Offices!$A$2:$FZ$601,0,Sync!$C$15),"<>out_of_office"),0) -> 16 | E94: =IF(C94=0,"",D94/C94) -> 0.66666667 | G94: =IFERROR(COUNTIFS(INDEX(Clay_Offices!$A$2:$FZ$601,0,Sync!$C$9),"linkedin",INDEX(Clay_Offices!$A$2:$FZ$601,0,Sync!$C$14),"<"&($E$6+1),INDEX(Clay_Offices!$A$2:$FZ$601,0,Sync!$C$5),Config!$B$20,INDEX(Clay_Offices!$A$2:$FZ$601,0,Sync!$C$15),"yes"),0)+IFERROR(COUNTIFS(INDEX(Clay_Offices!$A$2:$FZ$601,0,Sync!$C$9),"linkedin",INDEX(Clay_Offices!$A$2:$FZ$601,0,Sync!$C$14),"<"&($E$6+1),INDEX(Clay_Offices!$A$2:$FZ$601,0,Sync!$C$5),Config!$B$20,INDEX(Clay_Offices!$A$2:$FZ$601,0,Sync!$C$15),"maybe"),0)+IFERROR(COUNTIFS(INDEX(Clay_Offices!$A$2:$FZ$601,0,Sync!$C$9),"linkedin",INDEX(Clay_Offices!$A$2:$FZ$601,0,Sync!$C$14),"<"&($E$6+1),INDEX(Clay_Offices!$A$2:$FZ$601,0,Sync!$C$5),Config!$B$20,INDEX(Clay_Offices!$A$2:$FZ$601,0,Sync!$C$15),"needs_approval"),0)+IFERROR(COUNTIFS(INDEX(Clay_Offices!$A$2:$FZ$601,0,Sync!$C$9),"linkedin",INDEX(Clay_Offices!$A$2:$FZ$601,0,Sync!$C$14),"<"&($E$6+1),INDEX(Clay_Offices!$A$2:$FZ$601,0,Sync!$C$5),Config!$B$20,INDEX(Clay_Offices!$A$2:$FZ$601,0,Sync!$C$15),"send_info"),0)+IFERROR(COUNTIFS(INDEX(Clay_Offices!$A$2:$FZ$601,0,Sync!$C$9),"linkedin",INDEX(Clay_Offices!$A$2:$FZ$601,0,Sync!$C$14),"<"&($E$6+1),INDEX(Clay_Offices!$A$2:$FZ$601,0,Sync!$C$5),Config!$B$20,INDEX(Clay_Offices!$A$2:$FZ$601,0,Sync!$C$15),"referral"),0)+IFERROR(COUNTIFS(INDEX(Clay_Offices!$A$2:$FZ$601,0,Sync!$C$9),"linkedin",INDEX(Clay_Offices!$A$2:$FZ$601,0,Sync!$C$14),"<"&($E$6+1),INDEX(Clay_Offices!$A$2:$FZ$601,0,Sync!$C$5),Config!$B$20,INDEX(Clay_Offices!$A$2:$FZ$601,0,Sync!$C$15),"not_now"),0)+IFERROR(COUNTIFS(INDEX(Clay_Offices!$A$2:$FZ$601,0,Sync!$C$9),"linkedin",INDEX(Clay_Offices!$A$2:$FZ$601,0,Sync!$C$14),"<"&($E$6+1),INDEX(Clay_Offices!$A$2:$FZ$601,0,Sync!$C$5),Config!$B$20,INDEX(Clay_Offices!$A$2:$FZ$601,0,Sync!$C$15),"obj_seed_ourselves"),0)+IFERROR(COUNTIFS(INDEX(Clay_Offices!$A$2:$FZ$601,0,Sync!$C$9),"linkedin",INDEX(Clay_Offices!$A$2:$FZ$601,0,Sync!$C$14),"<"&($E$6+1),INDEX(Clay_Offices!$A$2:$FZ$601,0,Sync!$C$5),Config!$B$20,INDEX(Clay_Offices!$A$2:$FZ$601,0,Sync!$C$15),"obj_price"),0)+IFERROR(COUNTIFS(INDEX(Clay_Offices!$A$2:$FZ$601,0,Sync!$C$9),"linkedin",INDEX(Clay_Offices!$A$2:$FZ$601,0,Sync!$C$14),"<"&($E$6+1),INDEX(Clay_Offices!$A$2:$FZ$601,0,Sync!$C$5),Config!$B$20,INDEX(Clay_Offices!$A$2:$FZ$601,0,Sync!$C$15),"obj_free_trial"),0)+IFERROR(COUNTIFS(INDEX(Clay_Offices!$A$2:$FZ$601,0,Sync!$C$9),"linkedin",INDEX(Clay_Offices!$A$2:$FZ$601,0,Sync!$C$14),"<"&($E$6+1),INDEX(Clay_Offices!$A$2:$FZ$601,0,Sync!$C$5),Config!$B$20,INDEX(Clay_Offices!$A$2:$FZ$601,0,Sync!$C$15),"obj_what_we_get"),0)+IFERROR(COUNTIFS(INDEX(Clay_Offices!$A$2:$FZ$601,0,Sync!$C$9),"linkedin",INDEX(Clay_Offices!$A$2:$FZ$601,0,Sync!$C$14),"<"&($E$6+1),INDEX(Clay_Offices!$A$2:$FZ$601,0,Sync!$C$5),Config!$B$20,INDEX(Clay_Offices!$A$2:$FZ$601,0,Sync!$C$15),"obj_other"),0) -> 13
A95: channel: linkedin | B95: brand | C95: =IFERROR(COUNTIFS(INDEX(Clay_Brands!$A$2:$FZ$601,0,Sync!$D$9),"linkedin",INDEX(Clay_Brands!$A$2:$FZ$601,0,Sync!$D$11),"<"&($E$6+1),INDEX(Clay_Brands!$A$2:$FZ$601,0,Sync!$D$5),Config!$B$20),0) -> 21 | D95: =IFERROR(COUNTIFS(INDEX(Clay_Brands!$A$2:$FZ$601,0,Sync!$D$9),"linkedin",INDEX(Clay_Brands!$A$2:$FZ$601,0,Sync!$D$14),"<"&($E$6+1),INDEX(Clay_Brands!$A$2:$FZ$601,0,Sync!$D$5),Config!$B$20,INDEX(Clay_Brands!$A$2:$FZ$601,0,Sync!$D$15),"<>bounce",INDEX(Clay_Brands!$A$2:$FZ$601,0,Sync!$D$15),"<>out_of_office"),0) -> 13 | E95: =IF(C95=0,"",D95/C95) -> 0.61904762 | G95: =IFERROR(COUNTIFS(INDEX(Clay_Brands!$A$2:$FZ$601,0,Sync!$D$9),"linkedin",INDEX(Clay_Brands!$A$2:$FZ$601,0,Sync!$D$14),"<"&($E$6+1),INDEX(Clay_Brands!$A$2:$FZ$601,0,Sync!$D$5),Config!$B$20,INDEX(Clay_Brands!$A$2:$FZ$601,0,Sync!$D$15),"yes"),0)+IFERROR(COUNTIFS(INDEX(Clay_Brands!$A$2:$FZ$601,0,Sync!$D$9),"linkedin",INDEX(Clay_Brands!$A$2:$FZ$601,0,Sync!$D$14),"<"&($E$6+1),INDEX(Clay_Brands!$A$2:$FZ$601,0,Sync!$D$5),Config!$B$20,INDEX(Clay_Brands!$A$2:$FZ$601,0,Sync!$D$15),"maybe"),0)+IFERROR(COUNTIFS(INDEX(Clay_Brands!$A$2:$FZ$601,0,Sync!$D$9),"linkedin",INDEX(Clay_Brands!$A$2:$FZ$601,0,Sync!$D$14),"<"&($E$6+1),INDEX(Clay_Brands!$A$2:$FZ$601,0,Sync!$D$5),Config!$B$20,INDEX(Clay_Brands!$A$2:$FZ$601,0,Sync!$D$15),"needs_approval"),0)+IFERROR(COUNTIFS(INDEX(Clay_Brands!$A$2:$FZ$601,0,Sync!$D$9),"linkedin",INDEX(Clay_Brands!$A$2:$FZ$601,0,Sync!$D$14),"<"&($E$6+1),INDEX(Clay_Brands!$A$2:$FZ$601,0,Sync!$D$5),Config!$B$20,INDEX(Clay_Brands!$A$2:$FZ$601,0,Sync!$D$15),"send_info"),0)+IFERROR(COUNTIFS(INDEX(Clay_Brands!$A$2:$FZ$601,0,Sync!$D$9),"linkedin",INDEX(Clay_Brands!$A$2:$FZ$601,0,Sync!$D$14),"<"&($E$6+1),INDEX(Clay_Brands!$A$2:$FZ$601,0,Sync!$D$5),Config!$B$20,INDEX(Clay_Brands!$A$2:$FZ$601,0,Sync!$D$15),"referral"),0)+IFERROR(COUNTIFS(INDEX(Clay_Brands!$A$2:$FZ$601,0,Sync!$D$9),"linkedin",INDEX(Clay_Brands!$A$2:$FZ$601,0,Sync!$D$14),"<"&($E$6+1),INDEX(Clay_Brands!$A$2:$FZ$601,0,Sync!$D$5),Config!$B$20,INDEX(Clay_Brands!$A$2:$FZ$601,0,Sync!$D$15),"not_now"),0)+IFERROR(COUNTIFS(INDEX(Clay_Brands!$A$2:$FZ$601,0,Sync!$D$9),"linkedin",INDEX(Clay_Brands!$A$2:$FZ$601,0,Sync!$D$14),"<"&($E$6+1),INDEX(Clay_Brands!$A$2:$FZ$601,0,Sync!$D$5),Config!$B$20,INDEX(Clay_Brands!$A$2:$FZ$601,0,Sync!$D$15),"obj_seed_ourselves"),0)+IFERROR(COUNTIFS(INDEX(Clay_Brands!$A$2:$FZ$601,0,Sync!$D$9),"linkedin",INDEX(Clay_Brands!$A$2:$FZ$601,0,Sync!$D$14),"<"&($E$6+1),INDEX(Clay_Brands!$A$2:$FZ$601,0,Sync!$D$5),Config!$B$20,INDEX(Clay_Brands!$A$2:$FZ$601,0,Sync!$D$15),"obj_price"),0)+IFERROR(COUNTIFS(INDEX(Clay_Brands!$A$2:$FZ$601,0,Sync!$D$9),"linkedin",INDEX(Clay_Brands!$A$2:$FZ$601,0,Sync!$D$14),"<"&($E$6+1),INDEX(Clay_Brands!$A$2:$FZ$601,0,Sync!$D$5),Config!$B$20,INDEX(Clay_Brands!$A$2:$FZ$601,0,Sync!$D$15),"obj_free_trial"),0)+IFERROR(COUNTIFS(INDEX(Clay_Brands!$A$2:$FZ$601,0,Sync!$D$9),"linkedin",INDEX(Clay_Brands!$A$2:$FZ$601,0,Sync!$D$14),"<"&($E$6+1),INDEX(Clay_Brands!$A$2:$FZ$601,0,Sync!$D$5),Config!$B$20,INDEX(Clay_Brands!$A$2:$FZ$601,0,Sync!$D$15),"obj_what_we_get"),0)+IFERROR(COUNTIFS(INDEX(Clay_Brands!$A$2:$FZ$601,0,Sync!$D$9),"linkedin",INDEX(Clay_Brands!$A$2:$FZ$601,0,Sync!$D$14),"<"&($E$6+1),INDEX(Clay_Brands!$A$2:$FZ$601,0,Sync!$D$5),Config!$B$20,INDEX(Clay_Brands!$A$2:$FZ$601,0,Sync!$D$15),"obj_other"),0) -> 10
A96: channel: warm-intro | B96: office | C96: =IFERROR(COUNTIFS(INDEX(Clay_Offices!$A$2:$FZ$601,0,Sync!$C$9),"warm-intro",INDEX(Clay_Offices!$A$2:$FZ$601,0,Sync!$C$11),"<"&($E$6+1),INDEX(Clay_Offices!$A$2:$FZ$601,0,Sync!$C$5),Config!$B$20),0) -> 3 | D96: =IFERROR(COUNTIFS(INDEX(Clay_Offices!$A$2:$FZ$601,0,Sync!$C$9),"warm-intro",INDEX(Clay_Offices!$A$2:$FZ$601,0,Sync!$C$14),"<"&($E$6+1),INDEX(Clay_Offices!$A$2:$FZ$601,0,Sync!$C$5),Config!$B$20,INDEX(Clay_Offices!$A$2:$FZ$601,0,Sync!$C$15),"<>bounce",INDEX(Clay_Offices!$A$2:$FZ$601,0,Sync!$C$15),"<>out_of_office"),0) -> 3 | E96: =IF(C96=0,"",D96/C96) -> 1 | G96: =IFERROR(COUNTIFS(INDEX(Clay_Offices!$A$2:$FZ$601,0,Sync!$C$9),"warm-intro",INDEX(Clay_Offices!$A$2:$FZ$601,0,Sync!$C$14),"<"&($E$6+1),INDEX(Clay_Offices!$A$2:$FZ$601,0,Sync!$C$5),Config!$B$20,INDEX(Clay_Offices!$A$2:$FZ$601,0,Sync!$C$15),"yes"),0)+IFERROR(COUNTIFS(INDEX(Clay_Offices!$A$2:$FZ$601,0,Sync!$C$9),"warm-intro",INDEX(Clay_Offices!$A$2:$FZ$601,0,Sync!$C$14),"<"&($E$6+1),INDEX(Clay_Offices!$A$2:$FZ$601,0,Sync!$C$5),Config!$B$20,INDEX(Clay_Offices!$A$2:$FZ$601,0,Sync!$C$15),"maybe"),0)+IFERROR(COUNTIFS(INDEX(Clay_Offices!$A$2:$FZ$601,0,Sync!$C$9),"warm-intro",INDEX(Clay_Offices!$A$2:$FZ$601,0,Sync!$C$14),"<"&($E$6+1),INDEX(Clay_Offices!$A$2:$FZ$601,0,Sync!$C$5),Config!$B$20,INDEX(Clay_Offices!$A$2:$FZ$601,0,Sync!$C$15),"needs_approval"),0)+IFERROR(COUNTIFS(INDEX(Clay_Offices!$A$2:$FZ$601,0,Sync!$C$9),"warm-intro",INDEX(Clay_Offices!$A$2:$FZ$601,0,Sync!$C$14),"<"&($E$6+1),INDEX(Clay_Offices!$A$2:$FZ$601,0,Sync!$C$5),Config!$B$20,INDEX(Clay_Offices!$A$2:$FZ$601,0,Sync!$C$15),"send_info"),0)+IFERROR(COUNTIFS(INDEX(Clay_Offices!$A$2:$FZ$601,0,Sync!$C$9),"warm-intro",INDEX(Clay_Offices!$A$2:$FZ$601,0,Sync!$C$14),"<"&($E$6+1),INDEX(Clay_Offices!$A$2:$FZ$601,0,Sync!$C$5),Config!$B$20,INDEX(Clay_Offices!$A$2:$FZ$601,0,Sync!$C$15),"referral"),0)+IFERROR(COUNTIFS(INDEX(Clay_Offices!$A$2:$FZ$601,0,Sync!$C$9),"warm-intro",INDEX(Clay_Offices!$A$2:$FZ$601,0,Sync!$C$14),"<"&($E$6+1),INDEX(Clay_Offices!$A$2:$FZ$601,0,Sync!$C$5),Config!$B$20,INDEX(Clay_Offices!$A$2:$FZ$601,0,Sync!$C$15),"not_now"),0)+IFERROR(COUNTIFS(INDEX(Clay_Offices!$A$2:$FZ$601,0,Sync!$C$9),"warm-intro",INDEX(Clay_Offices!$A$2:$FZ$601,0,Sync!$C$14),"<"&($E$6+1),INDEX(Clay_Offices!$A$2:$FZ$601,0,Sync!$C$5),Config!$B$20,INDEX(Clay_Offices!$A$2:$FZ$601,0,Sync!$C$15),"obj_seed_ourselves"),0)+IFERROR(COUNTIFS(INDEX(Clay_Offices!$A$2:$FZ$601,0,Sync!$C$9),"warm-intro",INDEX(Clay_Offices!$A$2:$FZ$601,0,Sync!$C$14),"<"&($E$6+1),INDEX(Clay_Offices!$A$2:$FZ$601,0,Sync!$C$5),Config!$B$20,INDEX(Clay_Offices!$A$2:$FZ$601,0,Sync!$C$15),"obj_price"),0)+IFERROR(COUNTIFS(INDEX(Clay_Offices!$A$2:$FZ$601,0,Sync!$C$9),"warm-intro",INDEX(Clay_Offices!$A$2:$FZ$601,0,Sync!$C$14),"<"&($E$6+1),INDEX(Clay_Offices!$A$2:$FZ$601,0,Sync!$C$5),Config!$B$20,INDEX(Clay_Offices!$A$2:$FZ$601,0,Sync!$C$15),"obj_free_trial"),0)+IFERROR(COUNTIFS(INDEX(Clay_Offices!$A$2:$FZ$601,0,Sync!$C$9),"warm-intro",INDEX(Clay_Offices!$A$2:$FZ$601,0,Sync!$C$14),"<"&($E$6+1),INDEX(Clay_Offices!$A$2:$FZ$601,0,Sync!$C$5),Config!$B$20,INDEX(Clay_Offices!$A$2:$FZ$601,0,Sync!$C$15),"obj_what_we_get"),0)+IFERROR(COUNTIFS(INDEX(Clay_Offices!$A$2:$FZ$601,0,Sync!$C$9),"warm-intro",INDEX(Clay_Offices!$A$2:$FZ$601,0,Sync!$C$14),"<"&($E$6+1),INDEX(Clay_Offices!$A$2:$FZ$601,0,Sync!$C$5),Config!$B$20,INDEX(Clay_Offices!$A$2:$FZ$601,0,Sync!$C$15),"obj_other"),0) -> 3
A97: channel: warm-intro | B97: brand | C97: =IFERROR(COUNTIFS(INDEX(Clay_Brands!$A$2:$FZ$601,0,Sync!$D$9),"warm-intro",INDEX(Clay_Brands!$A$2:$FZ$601,0,Sync!$D$11),"<"&($E$6+1),INDEX(Clay_Brands!$A$2:$FZ$601,0,Sync!$D$5),Config!$B$20),0) -> 9 | D97: =IFERROR(COUNTIFS(INDEX(Clay_Brands!$A$2:$FZ$601,0,Sync!$D$9),"warm-intro",INDEX(Clay_Brands!$A$2:$FZ$601,0,Sync!$D$14),"<"&($E$6+1),INDEX(Clay_Brands!$A$2:$FZ$601,0,Sync!$D$5),Config!$B$20,INDEX(Clay_Brands!$A$2:$FZ$601,0,Sync!$D$15),"<>bounce",INDEX(Clay_Brands!$A$2:$FZ$601,0,Sync!$D$15),"<>out_of_office"),0) -> 9 | E97: =IF(C97=0,"",D97/C97) -> 1 | G97: =IFERROR(COUNTIFS(INDEX(Clay_Brands!$A$2:$FZ$601,0,Sync!$D$9),"warm-intro",INDEX(Clay_Brands!$A$2:$FZ$601,0,Sync!$D$14),"<"&($E$6+1),INDEX(Clay_Brands!$A$2:$FZ$601,0,Sync!$D$5),Config!$B$20,INDEX(Clay_Brands!$A$2:$FZ$601,0,Sync!$D$15),"yes"),0)+IFERROR(COUNTIFS(INDEX(Clay_Brands!$A$2:$FZ$601,0,Sync!$D$9),"warm-intro",INDEX(Clay_Brands!$A$2:$FZ$601,0,Sync!$D$14),"<"&($E$6+1),INDEX(Clay_Brands!$A$2:$FZ$601,0,Sync!$D$5),Config!$B$20,INDEX(Clay_Brands!$A$2:$FZ$601,0,Sync!$D$15),"maybe"),0)+IFERROR(COUNTIFS(INDEX(Clay_Brands!$A$2:$FZ$601,0,Sync!$D$9),"warm-intro",INDEX(Clay_Brands!$A$2:$FZ$601,0,Sync!$D$14),"<"&($E$6+1),INDEX(Clay_Brands!$A$2:$FZ$601,0,Sync!$D$5),Config!$B$20,INDEX(Clay_Brands!$A$2:$FZ$601,0,Sync!$D$15),"needs_approval"),0)+IFERROR(COUNTIFS(INDEX(Clay_Brands!$A$2:$FZ$601,0,Sync!$D$9),"warm-intro",INDEX(Clay_Brands!$A$2:$FZ$601,0,Sync!$D$14),"<"&($E$6+1),INDEX(Clay_Brands!$A$2:$FZ$601,0,Sync!$D$5),Config!$B$20,INDEX(Clay_Brands!$A$2:$FZ$601,0,Sync!$D$15),"send_info"),0)+IFERROR(COUNTIFS(INDEX(Clay_Brands!$A$2:$FZ$601,0,Sync!$D$9),"warm-intro",INDEX(Clay_Brands!$A$2:$FZ$601,0,Sync!$D$14),"<"&($E$6+1),INDEX(Clay_Brands!$A$2:$FZ$601,0,Sync!$D$5),Config!$B$20,INDEX(Clay_Brands!$A$2:$FZ$601,0,Sync!$D$15),"referral"),0)+IFERROR(COUNTIFS(INDEX(Clay_Brands!$A$2:$FZ$601,0,Sync!$D$9),"warm-intro",INDEX(Clay_Brands!$A$2:$FZ$601,0,Sync!$D$14),"<"&($E$6+1),INDEX(Clay_Brands!$A$2:$FZ$601,0,Sync!$D$5),Config!$B$20,INDEX(Clay_Brands!$A$2:$FZ$601,0,Sync!$D$15),"not_now"),0)+IFERROR(COUNTIFS(INDEX(Clay_Brands!$A$2:$FZ$601,0,Sync!$D$9),"warm-intro",INDEX(Clay_Brands!$A$2:$FZ$601,0,Sync!$D$14),"<"&($E$6+1),INDEX(Clay_Brands!$A$2:$FZ$601,0,Sync!$D$5),Config!$B$20,INDEX(Clay_Brands!$A$2:$FZ$601,0,Sync!$D$15),"obj_seed_ourselves"),0)+IFERROR(COUNTIFS(INDEX(Clay_Brands!$A$2:$FZ$601,0,Sync!$D$9),"warm-intro",INDEX(Clay_Brands!$A$2:$FZ$601,0,Sync!$D$14),"<"&($E$6+1),INDEX(Clay_Brands!$A$2:$FZ$601,0,Sync!$D$5),Config!$B$20,INDEX(Clay_Brands!$A$2:$FZ$601,0,Sync!$D$15),"obj_price"),0)+IFERROR(COUNTIFS(INDEX(Clay_Brands!$A$2:$FZ$601,0,Sync!$D$9),"warm-intro",INDEX(Clay_Brands!$A$2:$FZ$601,0,Sync!$D$14),"<"&($E$6+1),INDEX(Clay_Brands!$A$2:$FZ$601,0,Sync!$D$5),Config!$B$20,INDEX(Clay_Brands!$A$2:$FZ$601,0,Sync!$D$15),"obj_free_trial"),0)+IFERROR(COUNTIFS(INDEX(Clay_Brands!$A$2:$FZ$601,0,Sync!$D$9),"warm-intro",INDEX(Clay_Brands!$A$2:$FZ$601,0,Sync!$D$14),"<"&($E$6+1),INDEX(Clay_Brands!$A$2:$FZ$601,0,Sync!$D$5),Config!$B$20,INDEX(Clay_Brands!$A$2:$FZ$601,0,Sync!$D$15),"obj_what_we_get"),0)+IFERROR(COUNTIFS(INDEX(Clay_Brands!$A$2:$FZ$601,0,Sync!$D$9),"warm-intro",INDEX(Clay_Brands!$A$2:$FZ$601,0,Sync!$D$14),"<"&($E$6+1),INDEX(Clay_Brands!$A$2:$FZ$601,0,Sync!$D$5),Config!$B$20,INDEX(Clay_Brands!$A$2:$FZ$601,0,Sync!$D$15),"obj_other"),0) -> 9
A98: channel: walk-in | B98: office | C98: =IFERROR(COUNTIFS(INDEX(Clay_Offices!$A$2:$FZ$601,0,Sync!$C$9),"walk-in",INDEX(Clay_Offices!$A$2:$FZ$601,0,Sync!$C$11),"<"&($E$6+1),INDEX(Clay_Offices!$A$2:$FZ$601,0,Sync!$C$5),Config!$B$20),0) -> 3 | D98: =IFERROR(COUNTIFS(INDEX(Clay_Offices!$A$2:$FZ$601,0,Sync!$C$9),"walk-in",INDEX(Clay_Offices!$A$2:$FZ$601,0,Sync!$C$14),"<"&($E$6+1),INDEX(Clay_Offices!$A$2:$FZ$601,0,Sync!$C$5),Config!$B$20,INDEX(Clay_Offices!$A$2:$FZ$601,0,Sync!$C$15),"<>bounce",INDEX(Clay_Offices!$A$2:$FZ$601,0,Sync!$C$15),"<>out_of_office"),0) -> 3 | E98: =IF(C98=0,"",D98/C98) -> 1 | G98: =IFERROR(COUNTIFS(INDEX(Clay_Offices!$A$2:$FZ$601,0,Sync!$C$9),"walk-in",INDEX(Clay_Offices!$A$2:$FZ$601,0,Sync!$C$14),"<"&($E$6+1),INDEX(Clay_Offices!$A$2:$FZ$601,0,Sync!$C$5),Config!$B$20,INDEX(Clay_Offices!$A$2:$FZ$601,0,Sync!$C$15),"yes"),0)+IFERROR(COUNTIFS(INDEX(Clay_Offices!$A$2:$FZ$601,0,Sync!$C$9),"walk-in",INDEX(Clay_Offices!$A$2:$FZ$601,0,Sync!$C$14),"<"&($E$6+1),INDEX(Clay_Offices!$A$2:$FZ$601,0,Sync!$C$5),Config!$B$20,INDEX(Clay_Offices!$A$2:$FZ$601,0,Sync!$C$15),"maybe"),0)+IFERROR(COUNTIFS(INDEX(Clay_Offices!$A$2:$FZ$601,0,Sync!$C$9),"walk-in",INDEX(Clay_Offices!$A$2:$FZ$601,0,Sync!$C$14),"<"&($E$6+1),INDEX(Clay_Offices!$A$2:$FZ$601,0,Sync!$C$5),Config!$B$20,INDEX(Clay_Offices!$A$2:$FZ$601,0,Sync!$C$15),"needs_approval"),0)+IFERROR(COUNTIFS(INDEX(Clay_Offices!$A$2:$FZ$601,0,Sync!$C$9),"walk-in",INDEX(Clay_Offices!$A$2:$FZ$601,0,Sync!$C$14),"<"&($E$6+1),INDEX(Clay_Offices!$A$2:$FZ$601,0,Sync!$C$5),Config!$B$20,INDEX(Clay_Offices!$A$2:$FZ$601,0,Sync!$C$15),"send_info"),0)+IFERROR(COUNTIFS(INDEX(Clay_Offices!$A$2:$FZ$601,0,Sync!$C$9),"walk-in",INDEX(Clay_Offices!$A$2:$FZ$601,0,Sync!$C$14),"<"&($E$6+1),INDEX(Clay_Offices!$A$2:$FZ$601,0,Sync!$C$5),Config!$B$20,INDEX(Clay_Offices!$A$2:$FZ$601,0,Sync!$C$15),"referral"),0)+IFERROR(COUNTIFS(INDEX(Clay_Offices!$A$2:$FZ$601,0,Sync!$C$9),"walk-in",INDEX(Clay_Offices!$A$2:$FZ$601,0,Sync!$C$14),"<"&($E$6+1),INDEX(Clay_Offices!$A$2:$FZ$601,0,Sync!$C$5),Config!$B$20,INDEX(Clay_Offices!$A$2:$FZ$601,0,Sync!$C$15),"not_now"),0)+IFERROR(COUNTIFS(INDEX(Clay_Offices!$A$2:$FZ$601,0,Sync!$C$9),"walk-in",INDEX(Clay_Offices!$A$2:$FZ$601,0,Sync!$C$14),"<"&($E$6+1),INDEX(Clay_Offices!$A$2:$FZ$601,0,Sync!$C$5),Config!$B$20,INDEX(Clay_Offices!$A$2:$FZ$601,0,Sync!$C$15),"obj_seed_ourselves"),0)+IFERROR(COUNTIFS(INDEX(Clay_Offices!$A$2:$FZ$601,0,Sync!$C$9),"walk-in",INDEX(Clay_Offices!$A$2:$FZ$601,0,Sync!$C$14),"<"&($E$6+1),INDEX(Clay_Offices!$A$2:$FZ$601,0,Sync!$C$5),Config!$B$20,INDEX(Clay_Offices!$A$2:$FZ$601,0,Sync!$C$15),"obj_price"),0)+IFERROR(COUNTIFS(INDEX(Clay_Offices!$A$2:$FZ$601,0,Sync!$C$9),"walk-in",INDEX(Clay_Offices!$A$2:$FZ$601,0,Sync!$C$14),"<"&($E$6+1),INDEX(Clay_Offices!$A$2:$FZ$601,0,Sync!$C$5),Config!$B$20,INDEX(Clay_Offices!$A$2:$FZ$601,0,Sync!$C$15),"obj_free_trial"),0)+IFERROR(COUNTIFS(INDEX(Clay_Offices!$A$2:$FZ$601,0,Sync!$C$9),"walk-in",INDEX(Clay_Offices!$A$2:$FZ$601,0,Sync!$C$14),"<"&($E$6+1),INDEX(Clay_Offices!$A$2:$FZ$601,0,Sync!$C$5),Config!$B$20,INDEX(Clay_Offices!$A$2:$FZ$601,0,Sync!$C$15),"obj_what_we_get"),0)+IFERROR(COUNTIFS(INDEX(Clay_Offices!$A$2:$FZ$601,0,Sync!$C$9),"walk-in",INDEX(Clay_Offices!$A$2:$FZ$601,0,Sync!$C$14),"<"&($E$6+1),INDEX(Clay_Offices!$A$2:$FZ$601,0,Sync!$C$5),Config!$B$20,INDEX(Clay_Offices!$A$2:$FZ$601,0,Sync!$C$15),"obj_other"),0) -> 3
A99: channel: walk-in | B99: brand | C99: =IFERROR(COUNTIFS(INDEX(Clay_Brands!$A$2:$FZ$601,0,Sync!$D$9),"walk-in",INDEX(Clay_Brands!$A$2:$FZ$601,0,Sync!$D$11),"<"&($E$6+1),INDEX(Clay_Brands!$A$2:$FZ$601,0,Sync!$D$5),Config!$B$20),0) -> 0 | D99: =IFERROR(COUNTIFS(INDEX(Clay_Brands!$A$2:$FZ$601,0,Sync!$D$9),"walk-in",INDEX(Clay_Brands!$A$2:$FZ$601,0,Sync!$D$14),"<"&($E$6+1),INDEX(Clay_Brands!$A$2:$FZ$601,0,Sync!$D$5),Config!$B$20,INDEX(Clay_Brands!$A$2:$FZ$601,0,Sync!$D$15),"<>bounce",INDEX(Clay_Brands!$A$2:$FZ$601,0,Sync!$D$15),"<>out_of_office"),0) -> 0 | E99: =IF(C99=0,"",D99/C99) | G99: =IFERROR(COUNTIFS(INDEX(Clay_Brands!$A$2:$FZ$601,0,Sync!$D$9),"walk-in",INDEX(Clay_Brands!$A$2:$FZ$601,0,Sync!$D$14),"<"&($E$6+1),INDEX(Clay_Brands!$A$2:$FZ$601,0,Sync!$D$5),Config!$B$20,INDEX(Clay_Brands!$A$2:$FZ$601,0,Sync!$D$15),"yes"),0)+IFERROR(COUNTIFS(INDEX(Clay_Brands!$A$2:$FZ$601,0,Sync!$D$9),"walk-in",INDEX(Clay_Brands!$A$2:$FZ$601,0,Sync!$D$14),"<"&($E$6+1),INDEX(Clay_Brands!$A$2:$FZ$601,0,Sync!$D$5),Config!$B$20,INDEX(Clay_Brands!$A$2:$FZ$601,0,Sync!$D$15),"maybe"),0)+IFERROR(COUNTIFS(INDEX(Clay_Brands!$A$2:$FZ$601,0,Sync!$D$9),"walk-in",INDEX(Clay_Brands!$A$2:$FZ$601,0,Sync!$D$14),"<"&($E$6+1),INDEX(Clay_Brands!$A$2:$FZ$601,0,Sync!$D$5),Config!$B$20,INDEX(Clay_Brands!$A$2:$FZ$601,0,Sync!$D$15),"needs_approval"),0)+IFERROR(COUNTIFS(INDEX(Clay_Brands!$A$2:$FZ$601,0,Sync!$D$9),"walk-in",INDEX(Clay_Brands!$A$2:$FZ$601,0,Sync!$D$14),"<"&($E$6+1),INDEX(Clay_Brands!$A$2:$FZ$601,0,Sync!$D$5),Config!$B$20,INDEX(Clay_Brands!$A$2:$FZ$601,0,Sync!$D$15),"send_info"),0)+IFERROR(COUNTIFS(INDEX(Clay_Brands!$A$2:$FZ$601,0,Sync!$D$9),"walk-in",INDEX(Clay_Brands!$A$2:$FZ$601,0,Sync!$D$14),"<"&($E$6+1),INDEX(Clay_Brands!$A$2:$FZ$601,0,Sync!$D$5),Config!$B$20,INDEX(Clay_Brands!$A$2:$FZ$601,0,Sync!$D$15),"referral"),0)+IFERROR(COUNTIFS(INDEX(Clay_Brands!$A$2:$FZ$601,0,Sync!$D$9),"walk-in",INDEX(Clay_Brands!$A$2:$FZ$601,0,Sync!$D$14),"<"&($E$6+1),INDEX(Clay_Brands!$A$2:$FZ$601,0,Sync!$D$5),Config!$B$20,INDEX(Clay_Brands!$A$2:$FZ$601,0,Sync!$D$15),"not_now"),0)+IFERROR(COUNTIFS(INDEX(Clay_Brands!$A$2:$FZ$601,0,Sync!$D$9),"walk-in",INDEX(Clay_Brands!$A$2:$FZ$601,0,Sync!$D$14),"<"&($E$6+1),INDEX(Clay_Brands!$A$2:$FZ$601,0,Sync!$D$5),Config!$B$20,INDEX(Clay_Brands!$A$2:$FZ$601,0,Sync!$D$15),"obj_seed_ourselves"),0)+IFERROR(COUNTIFS(INDEX(Clay_Brands!$A$2:$FZ$601,0,Sync!$D$9),"walk-in",INDEX(Clay_Brands!$A$2:$FZ$601,0,Sync!$D$14),"<"&($E$6+1),INDEX(Clay_Brands!$A$2:$FZ$601,0,Sync!$D$5),Config!$B$20,INDEX(Clay_Brands!$A$2:$FZ$601,0,Sync!$D$15),"obj_price"),0)+IFERROR(COUNTIFS(INDEX(Clay_Brands!$A$2:$FZ$601,0,Sync!$D$9),"walk-in",INDEX(Clay_Brands!$A$2:$FZ$601,0,Sync!$D$14),"<"&($E$6+1),INDEX(Clay_Brands!$A$2:$FZ$601,0,Sync!$D$5),Config!$B$20,INDEX(Clay_Brands!$A$2:$FZ$601,0,Sync!$D$15),"obj_free_trial"),0)+IFERROR(COUNTIFS(INDEX(Clay_Brands!$A$2:$FZ$601,0,Sync!$D$9),"walk-in",INDEX(Clay_Brands!$A$2:$FZ$601,0,Sync!$D$14),"<"&($E$6+1),INDEX(Clay_Brands!$A$2:$FZ$601,0,Sync!$D$5),Config!$B$20,INDEX(Clay_Brands!$A$2:$FZ$601,0,Sync!$D$15),"obj_what_we_get"),0)+IFERROR(COUNTIFS(INDEX(Clay_Brands!$A$2:$FZ$601,0,Sync!$D$9),"walk-in",INDEX(Clay_Brands!$A$2:$FZ$601,0,Sync!$D$14),"<"&($E$6+1),INDEX(Clay_Brands!$A$2:$FZ$601,0,Sync!$D$5),Config!$B$20,INDEX(Clay_Brands!$A$2:$FZ$601,0,Sync!$D$15),"obj_other"),0) -> 0
A100: Sequence names come from Clay's sequence column. Edit the names in column A to match the variants in messages/05 to 07.
A102: After Gate 0: Gate 1 progress (five offices signed with 350+ on a Tuesday; two founding brands paid in full)
A103: Measure | D103: Gate 1 | E103: As of | F103: Target | G103: How it is counted
A104: Cut-off date | D104: =Config!$B$24 -> 46367 | E104: =Config!$B$5 -> 46367
A105: Offices signed (signed_offices rows) | D105: =COUNTIFS(signed_offices!$W$2:$W$51,"<>",signed_offices!$W$2:$W$51,Config!$B$20,signed_offices!$X$2:$X$51,"<"&(D$104+1)) -> 5 | E105: =COUNTIFS(signed_offices!$W$2:$W$51,"<>",signed_offices!$W$2:$W$51,Config!$B$20,signed_offices!$X$2:$X$51,"<"&(E$104+1)) -> 5 | F105: =Config!$B$25 -> 5 | G105: Rows with a clay_row_id and agreement_signed_date on or before the cut-off.
A106: Combined Tuesday headcount of signed offices | D106: =SUMIFS(signed_offices!$J$2:$J$51,signed_offices!$W$2:$W$51,"<>",signed_offices!$W$2:$W$51,Config!$B$20,signed_offices!$X$2:$X$51,"<"&(D$104+1)) -> 362 | E106: =SUMIFS(signed_offices!$J$2:$J$51,signed_offices!$W$2:$W$51,"<>",signed_offices!$W$2:$W$51,Config!$B$20,signed_offices!$X$2:$X$51,"<"&(E$104+1)) -> 362 | F106: =Config!$B$26 -> 350 | G106: Each office's own intake number, never the Clay estimate.
...

Sheet Office_Log
A1: row_id | B1: company | C1: org_key | D1: contact_name | E1: contact_title | F1: source | G1: channel | H1: call_date | I1: call_type | J1: q1_pantry_today_verbatim | K1: pantry_vendor | L1: uses_snack_service | M1: monthly_pantry_spend_usd | N1: monthly_pantry_spend_verbatim | O1: tuesday_headcount | P1: headcount_verbatim | Q1: q3_brands_reach_out | R1: q3_free_product_verbatim | S1: q4_yes_needs_verbatim | T1: q4_no_triggers_verbatim | U1: q5_photo_and_survey | V1: q5_verbatim | W1: budget_probe_asked | X1: budget_probe_verbatim | Y1: budget_probe_low_usd | Z1: budget_probe_high_usd | AA1: referrals_given_count | AB1: referrals_given | AC1: pantry_owner_named | AD1: pantry_owner_name | AE1: pantry_owner_title | AF1: owner_can_say_yes_alone | AG1: other_approver | AH1: receiving_window | AI1: receiving_type | AJ1: coi_required | AK1: security_notes | AL1: veto_categories | AM1: veto_verbatim | AN1: objection_1 | AO1: objection_2 | AP1: objection_3 | AQ1: objections_verbatim | AR1: yes_in_principle | AS1: yes_signals | AT1: shortlist | AU1: quote_ok_to_share | AV1: note_minutes | AW1: clay_updated | AX1: notes | AY1: calc_sync_issue | AZ1: calc_org | BA1: calc_row | BB1: calc_valid | BC1: calc_conv_first | BD1: calc_latest | BE1: calc_q_yes | BF1: calc_q_yes_first | BG1: calc_yes_incomplete | BH1: calc_bp_has | BI1: calc_bp_first | BJ1: calc_bp_w1 | BK1: calc_bp_w2 | BL1: calc_bp_g0 | BM1: calc_bp_asof | BN1: calc_bp100_first | BO1: calc_spend_has | BP1: calc_spend_first | BQ1: calc_spend_asof | BR1: calc_probe_row | BS1: calc_probe_first | BT1: calc_probe_key | BU1: calc_probe_missing_text | BV1: calc_obj1 | BW1: calc_obj2 | BX1: calc_obj3 | BY1: calc_note_min | BZ1: calc_yes_any | CA1: calc_maybe | CB1: calc_maybe_first | CC1: calc_yes_any_first | CD1: calc_bp100 | CE1: calc_short | CF1: calc_short_first | CG1: calc_warm | CH1: calc_warm_first | CI1: calc_reach | CJ1: calc_reach_first | CK1: calc_alone | CL1: calc_alone_first | CM1: calc_q5y | CN1: calc_q5y_first | CO1: calc_svc | CP1: calc_svc_first | CQ1: calc_hc_has | CR1: calc_hc_first | CS1: calc_hc_asof | CT1: calc_appr | CU1: calc_quote | CV1: calc_quote_first | CW1: calc_clay_idx | CX1: calc_clay_status | CY1: calc_clay_rank | CZ1: calc_clay_yes | DA1: calc_clay_call_date | DB1: calc_ans | DC1: calc_ylast | DD1: calc_last_w1 | DE1: calc_last_w2 | DF1: calc_last_g0 | DG1: calc_last_asof | DH1: calc_stand_w1 | DI1: calc_stand_w2 | DJ1: calc_stand_g0 | DK1: calc_stand_asof | DL1: calc_qc_w1 | DM1: calc_qc_w2 | DN1: calc_qc_g0 | DO1: calc_qc_asof | DP1: calc_yac_w1 | DQ1: calc_yac_w2 | DR1: calc_yac_g0 | DS1: calc_yac_asof | DT1: calc_wd_w1 | DU1: calc_wd_w2 | DV1: calc_wd_g0 | DW1: calc_wd_asof | DX1: calc_num_text | DY1: calc_has_time | DZ1: calc_cokey | EA1: calc_grp | EB1: calc_cogrp | EC1: calc_orgfirst | ED1: calc_orgrid | EE1: calc_rid_first | EF1: calc_multi | EG1: calc_hc_last | EH1: calc_hc_org | EI1: calc_hc_out | EJ1: calc_hc_3039 | EK1: calc_qcout_w1 | EL1: calc_qcout_w2 | EM1: calc_qcout_g0 | EN1: calc_qcout_asof | EO1: calc_qc3039_w1 | EP1: calc_qc3039_w2 | EQ1: calc_qc3039_g0 | ER1: calc_qc3039_asof
A2: SAMPLE-O-001 | B2: SAMPLE Office 01 | D2: SAMPLE Contact O01 | E2: Office Manager | F2: SAMPLE warm network | G2: warm-intro | H2: 46322 | I2: video | J2: SAMPLE: pantry answer 01 | K2: SAMPLE grocery order | L2: N | M2: 800 | N2: SAMPLE: about $800 a month | O2: 60 | P2: SAMPLE: around 60 on a Tuesday | Q2: Y | R2: SAMPLE: brands email us, we ignore most | S2: SAMPLE: allergen info and no work for me | T2: SAMPLE: anything with nuts | U2: Y | V2: SAMPLE: a photo is fine | W2: Y | X2: SAMPLE: maybe $100 to $200 a month | Y2: 100 | Z2: 200 | AA2: 1 | AB2: SAMPLE Office 30 - Office Manager | AC2: Y | AD2: SAMPLE Owner O01 | AE2: Office Manager | AF2: Y | AH2: SAMPLE Tue-Wed 9-11am | AI2: front desk | AJ2: no | AK2: SAMPLE: sign in at desk | AL2: meat-snacks | AM2: SAMPLE: no jerky | AN2: allergy_policy | AQ2: SAMPLE: allergy_policy (office 01) | AR2: Y | AS2: asked_when | AT2: Y | AU2: Y | AV2: 9 | AW2: Y | AY2: =IF(TRIM($A2)="","",IF(AND(LEFT($A2,6)="SAMPLE",Config!$B$19<>"Y"),"",IF(NOT(ISNUMBER(H2)),"call_date is blank or not a date",IF(Sync!$C$5="","Clay paste is empty or has no row_id column: paste the Clay export on Clay_Offices",IF(CW2="","row_id not found in the Clay paste: add the Clay row or fix the row_id",IF(AND(ISNUMBER(CY2),CY2>=1,CY2<=5),"Clay status is "&CX2&": set call_done or later",IF(AND(BD2=1,CZ2<>BZ2),"Clay yes_in_principle should be "&BZ2,IF(AND(BD2=1,DA2<>H2),"Clay call_date should be "&TEXT(H2,"yyyy-mm-dd"),"")))))))) | AZ2: =IF(TRIM($A2)="","",IF(TRIM(C2)<>"",SUBSTITUTE(SUBSTITUTE(SUBSTITUTE(SUBSTITUTE(SUBSTITUTE(SUBSTITUTE(LOWER(TRIM(C2)),"~",""),"*",""),"?",""),"<",""),">",""),"=",""),IF(EA2<>"",EA2,IFERROR(INDEX($EA$2:$EA$201,MATCH(DZ2,$EB$2:$EB$201,0)),DZ2)))) -> sample office 01 | BA2: =ROW() -> 2 | BB2: =IF(AND(TRIM($A2)<>"",ISNUMBER(H2)),IF(AND(LEFT($A2,6)="SAMPLE",Config!$B$19<>"Y"),0,1),0) -> 1 | BC2: =IF(BB2=1,IF(COUNTIFS($AZ$2:$AZ$201,AZ2,$BB$2:$BB$201,1,$H$2:$H$201,"<"&H2)+COUNTIFS($AZ$2:$AZ$201,AZ2,$BB$2:$BB$201,1,$H$2:$H$201,H2,$BA$2:$BA$201,"<"&BA2)=0,1,0),0) -> 1 | BD2: =IF(BB2=1,IF(COUNTIFS($A$2:$A$201,$A2,$BB$2:$BB$201,1,$H$2:$H$201,">"&H2)+COUNTIFS($A$2:$A$201,$A2,$BB$2:$BB$201,1,$H$2:$H$201,H2,$BA$2:$BA$201,">"&BA2)=0,1,0),0) -> 0 | BE2: =IF(AND(BB2=1,AR2="Y",AC2="Y",TRIM(AH2)<>""),1,0) -> 1 | BF2: =IF(BE2=1,IF(COUNTIFS($AZ$2:$AZ$201,AZ2,$BE$2:$BE$201,1,$H$2:$H$201,"<"&H2)+COUNTIFS($AZ$2:$AZ$201,AZ2,$BE$2:$BE$201,1,$H$2:$H$201,H2,$BA$2:$BA$201,"<"&BA2)=0,1,0),0) -> 1 | BG2: =IF(AND(BB2=1,AR2="Y",BE2=0),1,0) -> 0 | BH2: =IF(AND(BB2=1,ISNUMBER(Y2)),1,0) -> 1 | BI2: =IF(BH2=1,IF(COUNTIFS($AZ$2:$AZ$201,AZ2,$BH$2:$BH$201,1,$H$2:$H$201,"<"&H2)+COUNTIFS($AZ$2:$AZ$201,AZ2,$BH$2:$BH$201,1,$H$2:$H$201,H2,$BA$2:$BA$201,"<"&BA2)=0,1,0),0) -> 1 | BJ2: =IF(AND(BI2=1,INT(N(H2))<=Config!$B$6),Y2,"") -> 100 | BK2: =IF(AND(BI2=1,INT(N(H2))<=Config!$B$7),Y2,"") -> 100 | BL2: =IF(AND(BI2=1,INT(N(H2))<=Config!$B$8),Y2,"") -> 100 | BM2: =IF(AND(BI2=1,INT(N(H2))<=Config!$B$5),Y2,"") -> 100 | BN2: =IF(CD2=1,IF(COUNTIFS($AZ$2:$AZ$201,AZ2,$CD$2:$CD$201,1,$H$2:$H$201,"<"&H2)+COUNTIFS($AZ$2:$AZ$201,AZ2,$CD$2:$CD$201,1,$H$2:$H$201,H2,$BA$2:$BA$201,"<"&BA2)=0,1,0),0) -> 1 | BO2: =IF(AND(BB2=1,ISNUMBER(M2)),1,0) -> 1 | BP2: =IF(BO2=1,IF(COUNTIFS($AZ$2:$AZ$201,AZ2,$BO$2:$BO$201,1,$H$2:$H$201,"<"&H2)+COUNTIFS($AZ$2:$AZ$201,AZ2,$BO$2:$BO$201,1,$H$2:$H$201,H2,$BA$2:$BA$201,"<"&BA2)=0,1,0),0) -> 1 | BQ2: =IF(AND(BP2=1,INT(N(H2))<=Config!$B$5),M2,"") -> 800 | BR2: =IF(AND(BB2=1,OR(TRIM(X2)<>"",ISNUMBER(Y2))),1,0) -> 1 | BS2: =IF(BR2=1,IF(COUNTIFS($AZ$2:$AZ$201,AZ2,$BR$2:$BR$201,1,$H$2:$H$201,"<"&H2)+COUNTIFS($AZ$2:$AZ$201,AZ2,$BR$2:$BR$201,1,$H$2:$H$201,H2,$BA$2:$BA$201,"<"&BA2)=0,1,0),0) -> 1 | BT2: =IF(BS2=1,AZ2,"") -> sample office 01 | BU2: =IF(AND(BB2=1,W2="Y",TRIM(X2)=""),1,0) -> 0 | BV2: =IF(BB2=1,AN2&"","") -> allergy_policy | BW2: =IF(BB2=1,AO2&"","") | BX2: =IF(BB2=1,AP2&"","") | BY2: =IF(AND(BB2=1,ISNUMBER(AV2),INT(N(H2))<=Config!$B$5),AV2,"") -> 9 | BZ2: =IF(BB2=1,IF(COUNTIFS($A$2:$A$201,$A2,$DC$2:$DC$201,1,$AR$2:$AR$201,"Y")>0,"Y","N"),"") -> Y | CA2: =IF(AND(BB2=1,AR2="maybe"),1,0) -> 0 | CB2: =IF(CA2=1,IF(COUNTIFS($AZ$2:$AZ$201,AZ2,$CA$2:$CA$201,1,$H$2:$H$201,"<"&H2)+COUNTIFS($AZ$2:$AZ$201,AZ2,$CA$2:$CA$201,1,$H$2:$H$201,H2,$BA$2:$BA$201,"<"&BA2)=0,1,0),0) -> 0 | CC2: =IF(AND(BB2=1,AR2="Y"),IF(COUNTIFS($AZ$2:$AZ$201,AZ2,$AR$2:$AR$201,"Y",$BB$2:$BB$201,1,$H$2:$H$201,"<"&H2)+COUNTIFS($AZ$2:$AZ$201,AZ2,$AR$2:$AR$201,"Y",$BB$2:$BB$201,1,$H$2:$H$201,H2,$BA$2:$BA$201,"<"&BA2)=0,1,0),0) -> 1 | CD2: =IF(AND(BH2=1,N(Y2)>=Config!$B$15),1,0) -> 1 | CE2: =IF(AND(BB2=1,AT2="Y"),1,0) -> 1 | CF2: =IF(CE2=1,IF(COUNTIFS($AZ$2:$AZ$201,AZ2,$CE$2:$CE$201,1,$H$2:$H$201,"<"&H2)+COUNTIFS($AZ$2:$AZ$201,AZ2,$CE$2:$CE$201,1,$H$2:$H$201,H2,$BA$2:$BA$201,"<"&BA2)=0,1,0),0) -> 1 | CG2: =IF(AND(BB2=1,G2="warm-intro"),1,0) -> 1 | CH2: =IF(CG2=1,IF(COUNTIFS($AZ$2:$AZ$201,AZ2,$CG$2:$CG$201,1,$H$2:$H$201,"<"&H2)+COUNTIFS($AZ$2:$AZ$201,AZ2,$CG$2:$CG$201,1,$H$2:$H$201,H2,$BA$2:$BA$201,"<"&BA2)=0,1,0),0) -> 1 | CI2: =IF(AND(BB2=1,Q2="Y"),1,0) -> 1 | CJ2: =IF(CI2=1,IF(COUNTIFS($AZ$2:$AZ$201,AZ2,$CI$2:$CI$201,1,$H$2:$H$201,"<"&H2)+COUNTIFS($AZ$2:$AZ$201,AZ2,$CI$2:$CI$201,1,$H$2:$H$201,H2,$BA$2:$BA$201,"<"&BA2)=0,1,0),0) -> 1 | CK2: =IF(AND(BB2=1,AF2="Y"),1,0) -> 1 | CL2: =IF(CK2=1,IF(COUNTIFS($AZ$2:$AZ$201,AZ2,$CK$2:$CK$201,1,$H$2:$H$201,"<"&H2)+COUNTIFS($AZ$2:$AZ$201,AZ2,$CK$2:$CK$201,1,$H$2:$H$201,H2,$BA$2:$BA$201,"<"&BA2)=0,1,0),0) -> 1 | CM2: =IF(AND(BB2=1,U2="Y"),1,0) -> 1 | CN2: =IF(CM2=1,IF(COUNTIFS($AZ$2:$AZ$201,AZ2,$CM$2:$CM$201,1,$H$2:$H$201,"<"&H2)+COUNTIFS($AZ$2:$AZ$201,AZ2,$CM$2:$CM$201,1,$H$2:$H$201,H2,$BA$2:$BA$201,"<"&BA2)=0,1,0),0) -> 1 | CO2: =IF(AND(BB2=1,L2="Y"),1,0) -> 0 | CP2: =IF(CO2=1,IF(COUNTIFS($AZ$2:$AZ$201,AZ2,$CO$2:$CO$201,1,$H$2:$H$201,"<"&H2)+COUNTIFS($AZ$2:$AZ$201,AZ2,$CO$2:$CO$201,1,$H$2:$H$201,H2,$BA$2:$BA$201,"<"&BA2)=0,1,0),0) -> 0 | CQ2: =IF(AND(BB2=1,ISNUMBER(O2)),1,0) -> 1 | CR2: =IF(CQ2=1,IF(COUNTIFS($AZ$2:$AZ$201,AZ2,$CQ$2:$CQ$201,1,$H$2:$H$201,"<"&H2)+COUNTIFS($AZ$2:$AZ$201,AZ2,$CQ$2:$CQ$201,1,$H$2:$H$201,H2,$BA$2:$BA$201,"<"&BA2)=0,1,0),0) -> 1 | CS2: =IF(AND(CR2=1,INT(N(H2))<=Config!$B$5),O2,"") -> 60 | CT2: =IF(AND(BB2=1,INT(N(H2))<=Config!$B$5),AG2&"","") | CU2: =IF(AND(BB2=1,AU2="Y"),1,0) -> 1 | CV2: =IF(CU2=1,IF(COUNTIFS($AZ$2:$AZ$201,AZ2,$CU$2:$CU$201,1,$H$2:$H$201,"<"&H2)+COUNTIFS($AZ$2:$AZ$201,AZ2,$CU$2:$CU$201,1,$H$2:$H$201,H2,$BA$2:$BA$201,"<"&BA2)=0,1,0),0) -> 1 | CW2: =IF(BB2=1,IFERROR(MATCH($A2,INDEX(Clay_Offices!$A$2:$FZ$601,0,Sync!$C$5),0),""),"") -> 1 | CX2: =IF(CW2="","",IFERROR(INDEX(Clay_Offices!$A$2:$FZ$601,CW2,Sync!$C$7)&"","")) -> signed | CY2: =IF(CX2="","",IFERROR(INDEX(Lists!$K$2:$K$15,MATCH(CX2,Lists!$J$2:$J$15,0)),"")) -> 9 | CZ2: =IF(CW2="","",IFERROR(INDEX(Clay_Offices!$A$2:$FZ$601,CW2,Sync!$C$17)&"","")) -> Y | DA2: =IF(CW2="","",IFERROR(N(INDEX(Clay_Offices!$A$2:$FZ$601,CW2,Sync!$C$16)),0)) -> 46332 | DB2: =IF(AND(BB2=1,OR(AR2="Y",AR2="N",AR2="maybe")),1,0) -> 1 | DC2: =IF(AND(DB2=1),IF(COUNTIFS($A$2:$A$201,$A2,$DB$2:$DB$201,1,$H$2:$H$201,">"&H2)+COUNTIFS($A$2:$A$201,$A2,$DB$2:$DB$201,1,$H$2:$H$201,H2,$BA$2:$BA$201,">"&BA2)=0,1,0),0) -> 0 | DD2: =IF(AND(DB2=1,INT(N(H2))<=Config!$B$6),IF(COUNTIFS($AZ$2:$AZ$201,AZ2,$DB$2:$DB$201,1,$H$2:$H$201,">"&H2,$H$2:$H$201,"<"&(Config!$B$6+1))+COUNTIFS($AZ$2:$AZ$201,AZ2,$DB$2:$DB$201,1,$H$2:$H$201,H2,$BA$2:$BA$201,">"&BA2)=0,1,0),0) -> 1 | DE2: =IF(AND(DB2=1,INT(N(H2))<=Config!$B$7),IF(COUNTIFS($AZ$2:$AZ$201,AZ2,$DB$2:$DB$201,1,$H$2:$H$201,">"&H2,$H$2:$H$201,"<"&(Config!$B$7+1))+COUNTIFS($AZ$2:$AZ$201,AZ2,$DB$2:$DB$201,1,$H$2:$H$201,H2,$BA$2:$BA$201,">"&BA2)=0,1,0),0) -> 0 | DF2: =IF(AND(DB2=1,INT(N(H2))<=Config!$B$8),IF(COUNTIFS($AZ$2:$AZ$201,AZ2,$DB$2:$DB$201,1,$H$2:$H$201,">"&H2,$H$2:$H$201,"<"&(Config!$B$8+1))+COUNTIFS($AZ$2:$AZ$201,AZ2,$DB$2:$DB$201,1,$H$2:$H$201,H2,$BA$2:$BA$201,">"&BA2)=0,1,0),0) -> 0 | DG2: =IF(AND(DB2=1,INT(N(H2))<=Config!$B$5),IF(COUNTIFS($AZ$2:$AZ$201,AZ2,$DB$2:$DB$201,1,$H$2:$H$201,">"&H2,$H$2:$H$201,"<"&(Config!$B$5+1))+COUNTIFS($AZ$2:$AZ$201,AZ2,$DB$2:$DB$201,1,$H$2:$H$201,H2,$BA$2:$BA$201,">"&BA2)=0,1,0),0) -> 0 | DH2: =IF(BB2=1,IF(COUNTIFS($AZ$2:$AZ$201,AZ2,$DD$2:$DD$201,1,$AR$2:$AR$201,"Y")>0,1,0),0) -> 1 | DI2: =IF(BB2=1,IF(COUNTIFS($AZ$2:$AZ$201,AZ2,$DE$2:$DE$201,1,$AR$2:$AR$201,"Y")>0,1,0),0) -> 1 | DJ2: =IF(BB2=1,IF(COUNTIFS($AZ$2:$AZ$201,AZ2,$DF$2:$DF$201,1,$AR$2:$AR$201,"Y")>0,1,0),0) -> 1 | DK2: =IF(BB2=1,IF(COUNTIFS($AZ$2:$AZ$201,AZ2,$DG$2:$DG$201,1,$AR$2:$AR$201,"Y")>0,1,0),0) -> 1 | DL2: =IF(AND(BF2=1,INT(N(H2))<=Config!$B$6,DH2=1,EI2=0),1,0) -> 1 | DM2: =IF(AND(BF2=1,INT(N(H2))<=Config!$B$7,DI2=1,EI2=0),1,0) -> 1 | DN2: =IF(AND(BF2=1,INT(N(H2))<=Config!$B$8,DJ2=1,EI2=0),1,0) -> 1 | DO2: =IF(AND(BF2=1,INT(N(H2))<=Config!$B$5,DK2=1,EI2=0),1,0) -> 1 | DP2: =IF(AND(CC2=1,INT(N(H2))<=Config!$B$6,DH2=1,EI2=0),1,0) -> 1 | DQ2: =IF(AND(CC2=1,INT(N(H2))<=Config!$B$7,DI2=1,EI2=0),1,0) -> 1 | DR2: =IF(AND(CC2=1,INT(N(H2))<=Config!$B$8,DJ2=1,EI2=0),1,0) -> 1 | DS2: =IF(AND(CC2=1,INT(N(H2))<=Config!$B$5,DK2=1,EI2=0),1,0) -> 1 | DT2: =IF(AND(CC2=1,INT(N(H2))<=Config!$B$6,DH2=0),1,0) -> 0 | DU2: =IF(AND(CC2=1,INT(N(H2))<=Config!$B$7,DI2=0),1,0) -> 0 | DV2: =IF(AND(CC2=1,INT(N(H2))<=Config!$B$8,DJ2=0),1,0) -> 0 | DW2: =IF(AND(CC2=1,INT(N(H2))<=Config!$B$5,DK2=0),1,0) -> 0 | DX2: =IF(TRIM($A2)="",0,ISTEXT(M2)+ISTEXT(O2)+ISTEXT(Y2)+ISTEXT(Z2)+ISTEXT(AA2)+ISTEXT(AV2)) -> 0 | DY2: =IF(BB2=1,IF(H2<>INT(H2),1,0),0) -> 0 | DZ2: =IF(TRIM($A2)="","",IF(TRIM(B2)="",SUBSTITUTE(SUBSTITUTE(SUBSTITUTE(SUBSTITUTE(SUBSTITUTE(SUBSTITUTE(LOWER(TRIM($A2)),"~",""),"*",""),"?",""),"<",""),">",""),"=",""),SUBSTITUTE(SUBSTITUTE(SUBSTITUTE(SUBSTITUTE(SUBSTITUTE(SUBSTITUTE(LOWER(TRIM(B2)),"~",""),"*",""),"?",""),"<",""),">",""),"=",""))) -> sample office 01 | EA2: =IF(CW2="","",IFERROR(IF(LEFT(LOWER(TRIM(INDEX(Clay_Offices!$A$2:$FZ$601,CW2,Sync!$C$19)&"")),4)="grp-",SUBSTITUTE(SUBSTITUTE(SUBSTITUTE(SUBSTITUTE(SUBSTITUTE(SUBSTITUTE(LOWER(TRIM(INDEX(Clay_Offices!$A$2:$FZ$601,CW2,Sync!$C$19)&"")),"~",""),"*",""),"?",""),"<",""),">",""),"=",""),""),"")) | EB2: =IF(EA2<>"",DZ2,"") | EC2: =IF(BC2=1,AZ2,"") -> sample office 01 | ED2: =IF(TRIM($A2)="","",IFERROR(INDEX($A$2:$A$201,MATCH(AZ2,$EC$2:$EC$201,0))&"",$A2&"")) -> SAMPLE-O-001 | EE2: =IF(BB2=1,IF(COUNTIFS($A$2:$A$201,$A2,$BB$2:$BB$201,1,$H$2:$H$201,"<"&H2)+COUNTIFS($A$2:$A$201,$A2,$BB$2:$BB$201,1,$H$2:$H$201,H2,$BA$2:$BA$201,"<"&BA2)=0,1,0),0) -> 1 | EF2: =IF(BC2=1,IF(COUNTIFS($AZ$2:$AZ$201,AZ2,$EE$2:$EE$201,1)>1,1,0),0) -> 0 | EG2: =IF(AND(CQ2=1),IF(COUNTIFS($AZ$2:$AZ$201,AZ2,$CQ$2:$CQ$201,1,$H$2:$H$201,">"&H2)+COUNTIFS($AZ$2:$AZ$201,AZ2,$CQ$2:$CQ$201,1,$H$2:$H$201,H2,$BA$2:$BA$201,">"&BA2)=0,1,0),0) -> 0 | EH2: =IF(BB2=1,IF(COUNTIFS($AZ$2:$AZ$201,AZ2,$EG$2:$EG$201,1)=0,"",SUMIFS($O$2:$O$201,$AZ$2:$AZ$201,AZ2,$EG$2:$EG$201,1)),"") -> 62 | EI2: =IF(AND(ISNUMBER(EH2),OR(N(EH2)<Config!$B$31,N(EH2)>Config!$B$33)),1,0) -> 0 | EJ2: =IF(AND(ISNUMBER(EH2),N(EH2)>=Config!$B$31,N(EH2)<Config!$B$32),1,0) -> 0 | EK2: =IF(AND(BF2=1,INT(N(H2))<=Config!$B$6,DH2=1,EI2=1),1,0) -> 0 | EL2: =IF(AND(BF2=1,INT(N(H2))<=Config!$B$7,DI2=1,EI2=1),1,0) -> 0 | EM2: =IF(AND(BF2=1,INT(N(H2))<=Config!$B$8,DJ2=1,EI2=1),1,0) -> 0 | EN2: =IF(AND(BF2=1,INT(N(H2))<=Config!$B$5,DK2=1,EI2=1),1,0) -> 0 | EO2: =IF(AND(DL2=1,EJ2=1),1,0) -> 0 | EP2: =IF(AND(DM2=1,EJ2=1),1,0) -> 0 | EQ2: =IF(AND(DN2=1,EJ2=1),1,0) -> 0 | ER2: =IF(AND(DO2=1,EJ2=1),1,0) -> 0
A3: SAMPLE-O-002 | B3: SAMPLE Office 02 | D3: SAMPLE Contact O02 | E3: Workplace Experience Manager | F3: SAMPLE Clay offices table | G3: linkedin | H3: 46323 | I3: phone | J3: SAMPLE: pantry answer 02 | K3: SAMPLE grocery order | L3: N | M3: 400 | N3: SAMPLE: about $400 a month | O3: 45 | P3: SAMPLE: around 45 on a Tuesday | Q3: N | R3: SAMPLE: brands email us, we ignore most | S3: SAMPLE: allergen info and no work for me | T3: SAMPLE: anything with nuts | U3: Y | V3: SAMPLE: a photo is fine | W3: Y | X3: SAMPLE: honestly, no budget for that | Y3: 0 | Z3: 0 | AA3: 0 | AC3: Y | AD3: SAMPLE Owner O02 | AE3: Office Manager | AF3: Y | AI3: front desk | AJ3: no | AK3: SAMPLE: sign in at desk | AL3: chocolate-candy;sparkling-soda | AM3: SAMPLE: no jerky | AN3: existing_vendor | AO3: allergy_policy | AQ3: SAMPLE: existing_vendor / allergy_policy (office 02) | AR3: Y | AS3: asked_when | AT3: Y | AV3: 12 | AW3: Y | AY3: =IF(TRIM($A3)="","",IF(AND(LEFT($A3,6)="SAMPLE",Config!$B$19<>"Y"),"",IF(NOT(ISNUMBER(H3)),"call_date is blank or not a date",IF(Sync!$C$5="","Clay paste is empty or has no row_id column: paste the Clay export on Clay_Offices",IF(CW3="","row_id not found in the Clay paste: add the Clay row or fix the row_id",IF(AND(ISNUMBER(CY3),CY3>=1,CY3<=5),"Clay status is "&CX3&": set call_done or later",IF(AND(BD3=1,CZ3<>BZ3),"Clay yes_in_principle should be "&BZ3,IF(AND(BD3=1,DA3<>H3),"Clay call_date should be "&TEXT(H3,"yyyy-mm-dd"),"")))))))) | AZ3: =IF(TRIM($A3)="","",IF(TRIM(C3)<>"",SUBSTITUTE(SUBSTITUTE(SUBSTITUTE(SUBSTITUTE(SUBSTITUTE(SUBSTITUTE(LOWER(TRIM(C3)),"~",""),"*",""),"?",""),"<",""),">",""),"=",""),IF(EA3<>"",EA3,IFERROR(INDEX($EA$2:$EA$201,MATCH(DZ3,$EB$2:$EB$201,0)),DZ3)))) -> sample office 02 | BA3: =ROW() -> 3 | BB3: =IF(AND(TRIM($A3)<>"",ISNUMBER(H3)),IF(AND(LEFT($A3,6)="SAMPLE",Config!$B$19<>"Y"),0,1),0) -> 1 | BC3: =IF(BB3=1,IF(COUNTIFS($AZ$2:$AZ$201,AZ3,$BB$2:$BB$201,1,$H$2:$H$201,"<"&H3)+COUNTIFS($AZ$2:$AZ$201,AZ3,$BB$2:$BB$201,1,$H$2:$H$201,H3,$BA$2:$BA$201,"<"&BA3)=0,1,0),0) -> 1 | BD3: =IF(BB3=1,IF(COUNTIFS($A$2:$A$201,$A3,$BB$2:$BB$201,1,$H$2:$H$201,">"&H3)+COUNTIFS($A$2:$A$201,$A3,$BB$2:$BB$201,1,$H$2:$H$201,H3,$BA$2:$BA$201,">"&BA3)=0,1,0),0) -> 1 | BE3: =IF(AND(BB3=1,AR3="Y",AC3="Y",TRIM(AH3)<>""),1,0) -> 0 | BF3: =IF(BE3=1,IF(COUNTIFS($AZ$2:$AZ$201,AZ3,$BE$2:$BE$201,1,$H$2:$H$201,"<"&H3)+COUNTIFS($AZ$2:$AZ$201,AZ3,$BE$2:$BE$201,1,$H$2:$H$201,H3,$BA$2:$BA$201,"<"&BA3)=0,1,0),0) -> 0 | BG3: =IF(AND(BB3=1,AR3="Y",BE3=0),1,0) -> 1 | BH3: =IF(AND(BB3=1,ISNUMBER(Y3)),1,0) -> 1 | BI3: =IF(BH3=1,IF(COUNTIFS($AZ$2:$AZ$201,AZ3,$BH$2:$BH$201,1,$H$2:$H$201,"<"&H3)+COUNTIFS($AZ$2:$AZ$201,AZ3,$BH$2:$BH$201,1,$H$2:$H$201,H3,$BA$2:$BA$201,"<"&BA3)=0,1,0),0) -> 1 | BJ3: =IF(AND(BI3=1,INT(N(H3))<=Config!$B$6),Y3,"") -> 0 | BK3: =IF(AND(BI3=1,INT(N(H3))<=Config!$B$7),Y3,"") -> 0 | BL3: =IF(AND(BI3=1,INT(N(H3))<=Config!$B$8),Y3,"") -> 0 | BM3: =IF(AND(BI3=1,INT(N(H3))<=Config!$B$5),Y3,"") -> 0 | BN3: =IF(CD3=1,IF(COUNTIFS($AZ$2:$AZ$201,AZ3,$CD$2:$CD$201,1,$H$2:$H$201,"<"&H3)+COUNTIFS($AZ$2:$AZ$201,AZ3,$CD$2:$CD$201,1,$H$2:$H$201,H3,$BA$2:$BA$201,"<"&BA3)=0,1,0),0) -> 0 | BO3: =IF(AND(BB3=1,ISNUMBER(M3)),1,0) -> 1 | BP3: =IF(BO3=1,IF(COUNTIFS($AZ$2:$AZ$201,AZ3,$BO$2:$BO$201,1,$H$2:$H$201,"<"&H3)+COUNTIFS($AZ$2:$AZ$201,AZ3,$BO$2:$BO$201,1,$H$2:$H$201,H3,$BA$2:$BA$201,"<"&BA3)=0,1,0),0) -> 1 | BQ3: =IF(AND(BP3=1,INT(N(H3))<=Config!$B$5),M3,"") -> 400 | BR3: =IF(AND(BB3=1,OR(TRIM(X3)<>"",ISNUMBER(Y3))),1,0) -> 1 | BS3: =IF(BR3=1,IF(COUNTIFS($AZ$2:$AZ$201,AZ3,$BR$2:$BR$201,1,$H$2:$H$201,"<"&H3)+COUNTIFS($AZ$2:$AZ$201,AZ3,$BR$2:$BR$201,1,$H$2:$H$201,H3,$BA$2:$BA$201,"<"&BA3)=0,1,0),0) -> 1 | BT3: =IF(BS3=1,AZ3,"") -> sample office 02 | BU3: =IF(AND(BB3=1,W3="Y",TRIM(X3)=""),1,0) -> 0 | BV3: =IF(BB3=1,AN3&"","") -> existing_vendor | BW3: =IF(BB3=1,AO3&"","") -> allergy_policy | BX3: =IF(BB3=1,AP3&"","") | BY3: =IF(AND(BB3=1,ISNUMBER(AV3),INT(N(H3))<=Config!$B$5),AV3,"") -> 12 | BZ3: =IF(BB3=1,IF(COUNTIFS($A$2:$A$201,$A3,$DC$2:$DC$201,1,$AR$2:$AR$201,"Y")>0,"Y","N"),"") -> Y | CA3: =IF(AND(BB3=1,AR3="maybe"),1,0) -> 0 | CB3: =IF(CA3=1,IF(COUNTIFS($AZ$2:$AZ$201,AZ3,$CA$2:$CA$201,1,$H$2:$H$201,"<"&H3)+COUNTIFS($AZ$2:$AZ$201,AZ3,$CA$2:$CA$201,1,$H$2:$H$201,H3,$BA$2:$BA$201,"<"&BA3)=0,1,0),0) -> 0 | CC3: =IF(AND(BB3=1,AR3="Y"),IF(COUNTIFS($AZ$2:$AZ$201,AZ3,$AR$2:$AR$201,"Y",$BB$2:$BB$201,1,$H$2:$H$201,"<"&H3)+COUNTIFS($AZ$2:$AZ$201,AZ3,$AR$2:$AR$201,"Y",$BB$2:$BB$201,1,$H$2:$H$201,H3,$BA$2:$BA$201,"<"&BA3)=0,1,0),0) -> 1 | CD3: =IF(AND(BH3=1,N(Y3)>=Config!$B$15),1,0) -> 0 | CE3: =IF(AND(BB3=1,AT3="Y"),1,0) -> 1 | CF3: =IF(CE3=1,IF(COUNTIFS($AZ$2:$AZ$201,AZ3,$CE$2:$CE$201,1,$H$2:$H$201,"<"&H3)+COUNTIFS($AZ$2:$AZ$201,AZ3,$CE$2:$CE$201,1,$H$2:$H$201,H3,$BA$2:$BA$201,"<"&BA3)=0,1,0),0) -> 1 | CG3: =IF(AND(BB3=1,G3="warm-intro"),1,0) -> 0 | CH3: =IF(CG3=1,IF(COUNTIFS($AZ$2:$AZ$201,AZ3,$CG$2:$CG$201,1,$H$2:$H$201,"<"&H3)+COUNTIFS($AZ$2:$AZ$201,AZ3,$CG$2:$CG$201,1,$H$2:$H$201,H3,$BA$2:$BA$201,"<"&BA3)=0,1,0),0) -> 0 | CI3: =IF(AND(BB3=1,Q3="Y"),1,0) -> 0 | CJ3: =IF(CI3=1,IF(COUNTIFS($AZ$2:$AZ$201,AZ3,$CI$2:$CI$201,1,$H$2:$H$201,"<"&H3)+COUNTIFS($AZ$2:$AZ$201,AZ3,$CI$2:$CI$201,1,$H$2:$H$201,H3,$BA$2:$BA$201,"<"&BA3)=0,1,0),0) -> 0 | CK3: =IF(AND(BB3=1,AF3="Y"),1,0) -> 1 | CL3: =IF(CK3=1,IF(COUNTIFS($AZ$2:$AZ$201,AZ3,$CK$2:$CK$201,1,$H$2:$H$201,"<"&H3)+COUNTIFS($AZ$2:$AZ$201,AZ3,$CK$2:$CK$201,1,$H$2:$H$201,H3,$BA$2:$BA$201,"<"&BA3)=0,1,0),0) -> 1 | CM3: =IF(AND(BB3=1,U3="Y"),1,0) -> 1 | CN3: =IF(CM3=1,IF(COUNTIFS($AZ$2:$AZ$201,AZ3,$CM$2:$CM$201,1,$H$2:$H$201,"<"&H3)+COUNTIFS($AZ$2:$AZ$201,AZ3,$CM$2:$CM$201,1,$H$2:$H$201,H3,$BA$2:$BA$201,"<"&BA3)=0,1,0),0) -> 1 | CO3: =IF(AND(BB3=1,L3="Y"),1,0) -> 0 | CP3: =IF(CO3=1,IF(COUNTIFS($AZ$2:$AZ$201,AZ3,$CO$2:$CO$201,1,$H$2:$H$201,"<"&H3)+COUNTIFS($AZ$2:$AZ$201,AZ3,$CO$2:$CO$201,1,$H$2:$H$201,H3,$BA$2:$BA$201,"<"&BA3)=0,1,0),0) -> 0 | CQ3: =IF(AND(BB3=1,ISNUMBER(O3)),1,0) -> 1 | CR3: =IF(CQ3=1,IF(COUNTIFS($AZ$2:$AZ$201,AZ3,$CQ$2:$CQ$201,1,$H$2:$H$201,"<"&H3)+COUNTIFS($AZ$2:$AZ$201,AZ3,$CQ$2:$CQ$201,1,$H$2:$H$201,H3,$BA$2:$BA$201,"<"&BA3)=0,1,0),0) -> 1 | CS3: =IF(AND(CR3=1,INT(N(H3))<=Config!$B$5),O3,"") -> 45 | CT3: =IF(AND(BB3=1,INT(N(H3))<=Config!$B$5),AG3&"","") | CU3: =IF(AND(BB3=1,AU3="Y"),1,0) -> 0 | CV3: =IF(CU3=1,IF(COUNTIFS($AZ$2:$AZ$201,AZ3,$CU$2:$CU$201,1,$H$2:$H$201,"<"&H3)+COUNTIFS($AZ$2:$AZ$201,AZ3,$CU$2:$CU$201,1,$H$2:$H$201,H3,$BA$2:$BA$201,"<"&BA3)=0,1,0),0) -> 0 | CW3: =IF(BB3=1,IFERROR(MATCH($A3,INDEX(Clay_Offices!$A$2:$FZ$601,0,Sync!$C$5),0),""),"") -> 2 | CX3: =IF(CW3="","",IFERROR(INDEX(Clay_Offices!$A$2:$FZ$601,CW3,Sync!$C$7)&"","")) -> yes_in_principle | CY3: =IF(CX3="","",IFERROR(INDEX(Lists!$K$2:$K$15,MATCH(CX3,Lists!$J$2:$J$15,0)),"")) -> 7 | CZ3: =IF(CW3="","",IFERROR(INDEX(Clay_Offices!$A$2:$FZ$601,CW3,Sync!$C$17)&"","")) -> Y | DA3: =IF(CW3="","",IFERROR(N(INDEX(Clay_Offices!$A$2:$FZ$601,CW3,Sync!$C$16)),0)) -> 46323 | DB3: =IF(AND(BB3=1,OR(AR3="Y",AR3="N",AR3="maybe")),1,0) -> 1 | DC3: =IF(AND(DB3=1),IF(COUNTIFS($A$2:$A$201,$A3,$DB$2:$DB$201,1,$H$2:$H$201,">"&H3)+COUNTIFS($A$2:$A$201,$A3,$DB$2:$DB$201,1,$H$2:$H$201,H3,$BA$2:$BA$201,">"&BA3)=0,1,0),0) -> 1 | DD3: =IF(AND(DB3=1,INT(N(H3))<=Config!$B$6),IF(COUNTIFS($AZ$2:$AZ$201,AZ3,$DB$2:$DB$201,1,$H$2:$H$201,">"&H3,$H$2:$H$201,"<"&(Config!$B$6+1))+COUNTIFS($AZ$2:$AZ$201,AZ3,$DB$2:$DB$201,1,$H$2:$H$201,H3,$BA$2:$BA$201,">"&BA3)=0,1,0),0) -> 1 | DE3: =IF(AND(DB3=1,INT(N(H3))<=Config!$B$7),IF(COUNTIFS($AZ$2:$AZ$201,AZ3,$DB$2:$DB$201,1,$H$2:$H$201,">"&H3,$H$2:$H$201,"<"&(Config!$B$7+1))+COUNTIFS($AZ$2:$AZ$201,AZ3,$DB$2:$DB$201,1,$H$2:$H$201,H3,$BA$2:$BA$201,">"&BA3)=0,1,0),0) -> 1 | DF3: =IF(AND(DB3=1,INT(N(H3))<=Config!$B$8),IF(COUNTIFS($AZ$2:$AZ$201,AZ3,$DB$2:$DB$201,1,$H$2:$H$201,">"&H3,$H$2:$H$201,"<"&(Config!$B$8+1))+COUNTIFS($AZ$2:$AZ$201,AZ3,$DB$2:$DB$201,1,$H$2:$H$201,H3,$BA$2:$BA$201,">"&BA3)=0,1,0),0) -> 1 | DG3: =IF(AND(DB3=1,INT(N(H3))<=Config!$B$5),IF(COUNTIFS($AZ$2:$AZ$201,AZ3,$DB$2:$DB$201,1,$H$2:$H$201,">"&H3,$H$2:$H$201,"<"&(Config!$B$5+1))+COUNTIFS($AZ$2:$AZ$201,AZ3,$DB$2:$DB$201,1,$H$2:$H$201,H3,$BA$2:$BA$201,">"&BA3)=0,1,0),0) -> 1 | DH3: =IF(BB3=1,IF(COUNTIFS($AZ$2:$AZ$201,AZ3,$DD$2:$DD$201,1,$AR$2:$AR$201,"Y")>0,1,0),0) -> 1 | DI3: =IF(BB3=1,IF(COUNTIFS($AZ$2:$AZ$201,AZ3,$DE$2:$DE$201,1,$AR$2:$AR$201,"Y")>0,1,0),0) -> 1 | DJ3: =IF(BB3=1,IF(COUNTIFS($AZ$2:$AZ$201,AZ3,$DF$2:$DF$201,1,$AR$2:$AR$201,"Y")>0,1,0),0) -> 1 | DK3: =IF(BB3=1,IF(COUNTIFS($AZ$2:$AZ$201,AZ3,$DG$2:$DG$201,1,$AR$2:$AR$201,"Y")>0,1,0),0) -> 1 | DL3: =IF(AND(BF3=1,INT(N(H3))<=Config!$B$6,DH3=1,EI3=0),1,0) -> 0 | DM3: =IF(AND(BF3=1,INT(N(H3))<=Config!$B$7,DI3=1,EI3=0),1,0) -> 0 | DN3: =IF(AND(BF3=1,INT(N(H3))<=Config!$B$8,DJ3=1,EI3=0),1,0) -> 0 | DO3: =IF(AND(BF3=1,INT(N(H3))<=Config!$B$5,DK3=1,EI3=0),1,0) -> 0 | DP3: =IF(AND(CC3=1,INT(N(H3))<=Config!$B$6,DH3=1,EI3=0),1,0) -> 1 | DQ3: =IF(AND(CC3=1,INT(N(H3))<=Config!$B$7,DI3=1,EI3=0),1,0) -> 1 | DR3: =IF(AND(CC3=1,INT(N(H3))<=Config!$B$8,DJ3=1,EI3=0),1,0) -> 1 | DS3: =IF(AND(CC3=1,INT(N(H3))<=Config!$B$5,DK3=1,EI3=0),1,0) -> 1 | DT3: =IF(AND(CC3=1,INT(N(H3))<=Config!$B$6,DH3=0),1,0) -> 0 | DU3: =IF(AND(CC3=1,INT(N(H3))<=Config!$B$7,DI3=0),1,0) -> 0 | DV3: =IF(AND(CC3=1,INT(N(H3))<=Config!$B$8,DJ3=0),1,0) -> 0 | DW3: =IF(AND(CC3=1,INT(N(H3))<=Config!$B$5,DK3=0),1,0) -> 0 | DX3: =IF(TRIM($A3)="",0,ISTEXT(M3)+ISTEXT(O3)+ISTEXT(Y3)+ISTEXT(Z3)+ISTEXT(AA3)+ISTEXT(AV3)) -> 0 | DY3: =IF(BB3=1,IF(H3<>INT(H3),1,0),0) -> 0 | DZ3: =IF(TRIM($A3)="","",IF(TRIM(B3)="",SUBSTITUTE(SUBSTITUTE(SUBSTITUTE(SUBSTITUTE(SUBSTITUTE(SUBSTITUTE(LOWER(TRIM($A3)),"~",""),"*",""),"?",""),"<",""),">",""),"=",""),SUBSTITUTE(SUBSTITUTE(SUBSTITUTE(SUBSTITUTE(SUBSTITUTE(SUBSTITUTE(LOWER(TRIM(B3)),"~",""),"*",""),"?",""),"<",""),">",""),"=",""))) -> sample office 02 | EA3: =IF(CW3="","",IFERROR(IF(LEFT(LOWER(TRIM(INDEX(Clay_Offices!$A$2:$FZ$601,CW3,Sync!$C$19)&"")),4)="grp-",SUBSTITUTE(SUBSTITUTE(SUBSTITUTE(SUBSTITUTE(SUBSTITUTE(SUBSTITUTE(LOWER(TRIM(INDEX(Clay_Offices!$A$2:$FZ$601,CW3,Sync!$C$19)&"")),"~",""),"*",""),"?",""),"<",""),">",""),"=",""),""),"")) | EB3: =IF(EA3<>"",DZ3,"") | EC3: =IF(BC3=1,AZ3,"") -> sample office 02 | ED3: =IF(TRIM($A3)="","",IFERROR(INDEX($A$2:$A$201,MATCH(AZ3,$EC$2:$EC$201,0))&"",$A3&"")) -> SAMPLE-O-002 | EE3: =IF(BB3=1,IF(COUNTIFS($A$2:$A$201,$A3,$BB$2:$BB$201,1,$H$2:$H$201,"<"&H3)+COUNTIFS($A$2:$A$201,$A3,$BB$2:$BB$201,1,$H$2:$H$201,H3,$BA$2:$BA$201,"<"&BA3)=0,1,0),0) -> 1 | EF3: =IF(BC3=1,IF(COUNTIFS($AZ$2:$AZ$201,AZ3,$EE$2:$EE$201,1)>1,1,0),0) -> 0 | EG3: =IF(AND(CQ3=1),IF(COUNTIFS($AZ$2:$AZ$201,AZ3,$CQ$2:$CQ$201,1,$H$2:$H$201,">"&H3)+COUNTIFS($AZ$2:$AZ$201,AZ3,$CQ$2:$CQ$201,1,$H$2:$H$201,H3,$BA$2:$BA$201,">"&BA3)=0,1,0),0) -> 1 | EH3: =IF(BB3=1,IF(COUNTIFS($AZ$2:$AZ$201,AZ3,$EG$2:$EG$201,1)=0,"",SUMIFS($O$2:$O$201,$AZ$2:$AZ$201,AZ3,$EG$2:$EG$201,1)),"") -> 45 | EI3: =IF(AND(ISNUMBER(EH3),OR(N(EH3)<Config!$B$31,N(EH3)>Config!$B$33)),1,0) -> 0 | EJ3: =IF(AND(ISNUMBER(EH3),N(EH3)>=Config!$B$31,N(EH3)<Config!$B$32),1,0) -> 0 | EK3: =IF(AND(BF3=1,INT(N(H3))<=Config!$B$6,DH3=1,EI3=1),1,0) -> 0 | EL3: =IF(AND(BF3=1,INT(N(H3))<=Config!$B$7,DI3=1,EI3=1),1,0) -> 0 | EM3: =IF(AND(BF3=1,INT(N(H3))<=Config!$B$8,DJ3=1,EI3=1),1,0) -> 0 | EN3: =IF(AND(BF3=1,INT(N(H3))<=Config!$B$5,DK3=1,EI3=1),1,0) -> 0 | EO3: =IF(AND(DL3=1,EJ3=1),1,0) -> 0 | EP3: =IF(AND(DM3=1,EJ3=1),1,0) -> 0 | EQ3: =IF(AND(DN3=1,EJ3=1),1,0) -> 0 | ER3: =IF(AND(DO3=1,EJ3=1),1,0) -> 0
A4: SAMPLE-O-003 | B4: SAMPLE Office 03 | D4: SAMPLE Contact O03 | E4: Office Manager | F4: SAMPLE Clay offices table | G4: walk-in | H4: 46324 | I4: walk-in | J4: SAMPLE: pantry answer 03 | K4: SAMPLE snack service | L4: Y | O4: 120 | P4: SAMPLE: around 120 on a Tuesday | Q4: Y | R4: SAMPLE: brands email us, we ignore most | S4: SAMPLE: allergen info and no work for me | T4: SAMPLE: anything with nuts | U4: maybe | V4: SAMPLE: a photo is fine | W4: Y | X4: SAMPLE: I don't know | AA4: 0 | AC4: N | AF4: N | AG4: facilities | AI4: walk-up | AJ4: no | AL4: meat-snacks | AM4: SAMPLE: no jerky | AN4: vendor_fatigue | AQ4: SAMPLE: vendor_fatigue (office 03) | AR4: N | AV4: 8 | AW4: Y | AY4: =IF(TRIM($A4)="","",IF(AND(LEFT($A4,6)="SAMPLE",Config!$B$19<>"Y"),"",IF(NOT(ISNUMBER(H4)),"call_date is blank or not a date",IF(Sync!$C$5="","Clay paste is empty or has no row_id column: paste the Clay export on Clay_Offices",IF(CW4="","row_id not found in the Clay paste: add the Clay row or fix the row_id",IF(AND(ISNUMBER(CY4),CY4>=1,CY4<=5),"Clay status is "&CX4&": set call_done or later",IF(AND(BD4=1,CZ4<>BZ4),"Clay yes_in_principle should be "&BZ4,IF(AND(BD4=1,DA4<>H4),"Clay call_date should be "&TEXT(H4,"yyyy-mm-dd"),"")))))))) | AZ4: =IF(TRIM($A4)="","",IF(TRIM(C4)<>"",SUBSTITUTE(SUBSTITUTE(SUBSTITUTE(SUBSTITUTE(SUBSTITUTE(SUBSTITUTE(LOWER(TRIM(C4)),"~",""),"*",""),"?",""),"<",""),">",""),"=",""),IF(EA4<>"",EA4,IFERROR(INDEX($EA$2:$EA$201,MATCH(DZ4,$EB$2:$EB$201,0)),DZ4)))) -> sample office 03 | BA4: =ROW() -> 4 | BB4: =IF(AND(TRIM($A4)<>"",ISNUMBER(H4)),IF(AND(LEFT($A4,6)="SAMPLE",Config!$B$19<>"Y"),0,1),0) -> 1 | BC4: =IF(BB4=1,IF(COUNTIFS($AZ$2:$AZ$201,AZ4,$BB$2:$BB$201,1,$H$2:$H$201,"<"&H4)+COUNTIFS($AZ$2:$AZ$201,AZ4,$BB$2:$BB$201,1,$H$2:$H$201,H4,$BA$2:$BA$201,"<"&BA4)=0,1,0),0) -> 1 | BD4: =IF(BB4=1,IF(COUNTIFS($A$2:$A$201,$A4,$BB$2:$BB$201,1,$H$2:$H$201,">"&H4)+COUNTIFS($A$2:$A$201,$A4,$BB$2:$BB$201,1,$H$2:$H$201,H4,$BA$2:$BA$201,">"&BA4)=0,1,0),0) -> 1 | BE4: =IF(AND(BB4=1,AR4="Y",AC4="Y",TRIM(AH4)<>""),1,0) -> 0 | BF4: =IF(BE4=1,IF(COUNTIFS($AZ$2:$AZ$201,AZ4,$BE$2:$BE$201,1,$H$2:$H$201,"<"&H4)+COUNTIFS($AZ$2:$AZ$201,AZ4,$BE$2:$BE$201,1,$H$2:$H$201,H4,$BA$2:$BA$201,"<"&BA4)=0,1,0),0) -> 0 | BG4: =IF(AND(BB4=1,AR4="Y",BE4=0),1,0) -> 0 | BH4: =IF(AND(BB4=1,ISNUMBER(Y4)),1,0) -> 0 | BI4: =IF(BH4=1,IF(COUNTIFS($AZ$2:$AZ$201,AZ4,$BH$2:$BH$201,1,$H$2:$H$201,"<"&H4)+COUNTIFS($AZ$2:$AZ$201,AZ4,$BH$2:$BH$201,1,$H$2:$H$201,H4,$BA$2:$BA$201,"<"&BA4)=0,1,0),0) -> 0 | BJ4: =IF(AND(BI4=1,INT(N(H4))<=Config!$B$6),Y4,"") | BK4: =IF(AND(BI4=1,INT(N(H4))<=Config!$B$7),Y4,"") | BL4: =IF(AND(BI4=1,INT(N(H4))<=Config!$B$8),Y4,"") | BM4: =IF(AND(BI4=1,INT(N(H4))<=Config!$B$5),Y4,"") | BN4: =IF(CD4=1,IF(COUNTIFS($AZ$2:$AZ$201,AZ4,$CD$2:$CD$201,1,$H$2:$H$201,"<"&H4)+COUNTIFS($AZ$2:$AZ$201,AZ4,$CD$2:$CD$201,1,$H$2:$H$201,H4,$BA$2:$BA$201,"<"&BA4)=0,1,0),0) -> 0 | BO4: =IF(AND(BB4=1,ISNUMBER(M4)),1,0) -> 0 | BP4: =IF(BO4=1,IF(COUNTIFS($AZ$2:$AZ$201,AZ4,$BO$2:$BO$201,1,$H$2:$H$201,"<"&H4)+COUNTIFS($AZ$2:$AZ$201,AZ4,$BO$2:$BO$201,1,$H$2:$H$201,H4,$BA$2:$BA$201,"<"&BA4)=0,1,0),0) -> 0 | BQ4: =IF(AND(BP4=1,INT(N(H4))<=Config!$B$5),M4,"") | BR4: =IF(AND(BB4=1,OR(TRIM(X4)<>"",ISNUMBER(Y4))),1,0) -> 1 | BS4: =IF(BR4=1,IF(COUNTIFS($AZ$2:$AZ$201,AZ4,$BR$2:$BR$201,1,$H$2:$H$201,"<"&H4)+COUNTIFS($AZ$2:$AZ$201,AZ4,$BR$2:$BR$201,1,$H$2:$H$201,H4,$BA$2:$BA$201,"<"&BA4)=0,1,0),0) -> 1 | BT4: =IF(BS4=1,AZ4,"") -> sample office 03 | BU4: =IF(AND(BB4=1,W4="Y",TRIM(X4)=""),1,0) -> 0 | BV4: =IF(BB4=1,AN4&"","") -> vendor_fatigue | BW4: =IF(BB4=1,AO4&"","") | BX4: =IF(BB4=1,AP4&"","") | BY4: =IF(AND(BB4=1,ISNUMBER(AV4),INT(N(H4))<=Config!$B$5),AV4,"") -> 8 | BZ4: =IF(BB4=1,IF(COUNTIFS($A$2:$A$201,$A4,$DC$2:$DC$201,1,$AR$2:$AR$201,"Y")>0,"Y","N"),"") -> N | CA4: =IF(AND(BB4=1,AR4="maybe"),1,0) -> 0 | CB4: =IF(CA4=1,IF(COUNTIFS($AZ$2:$AZ$201,AZ4,$CA$2:$CA$201,1,$H$2:$H$201,"<"&H4)+COUNTIFS($AZ$2:$AZ$201,AZ4,$CA$2:$CA$201,1,$H$2:$H$201,H4,$BA$2:$BA$201,"<"&BA4)=0,1,0),0) -> 0 | CC4: =IF(AND(BB4=1,AR4="Y"),IF(COUNTIFS($AZ$2:$AZ$201,AZ4,$AR$2:$AR$201,"Y",$BB$2:$BB$201,1,$H$2:$H$201,"<"&H4)+COUNTIFS($AZ$2:$AZ$201,AZ4,$AR$2:$AR$201,"Y",$BB$2:$BB$201,1,$H$2:$H$201,H4,$BA$2:$BA$201,"<"&BA4)=0,1,0),0) -> 0 | CD4: =IF(AND(BH4=1,N(Y4)>=Config!$B$15),1,0) -> 0 | CE4: =IF(AND(BB4=1,AT4="Y"),1,0) -> 0 | CF4: =IF(CE4=1,IF(COUNTIFS($AZ$2:$AZ$201,AZ4,$CE$2:$CE$201,1,$H$2:$H$201,"<"&H4)+COUNTIFS($AZ$2:$AZ$201,AZ4,$CE$2:$CE$201,1,$H$2:$H$201,H4,$BA$2:$BA$201,"<"&BA4)=0,1,0),0) -> 0 | CG4: =IF(AND(BB4=1,G4="warm-intro"),1,0) -> 0 | CH4: =IF(CG4=1,IF(COUNTIFS($AZ$2:$AZ$201,AZ4,$CG$2:$CG$201,1,$H$2:$H$201,"<"&H4)+COUNTIFS($AZ$2:$AZ$201,AZ4,$CG$2:$CG$201,1,$H$2:$H$201,H4,$BA$2:$BA$201,"<"&BA4)=0,1,0),0) -> 0 | CI4: =IF(AND(BB4=1,Q4="Y"),1,0) -> 1 | CJ4: =IF(CI4=1,IF(COUNTIFS($AZ$2:$AZ$201,AZ4,$CI$2:$CI$201,1,$H$2:$H$201,"<"&H4)+COUNTIFS($AZ$2:$AZ$201,AZ4,$CI$2:$CI$201,1,$H$2:$H$201,H4,$BA$2:$BA$201,"<"&BA4)=0,1,0),0) -> 1 | CK4: =IF(AND(BB4=1,AF4="Y"),1,0) -> 0 | CL4: =IF(CK4=1,IF(COUNTIFS($AZ$2:$AZ$201,AZ4,$CK$2:$CK$201,1,$H$2:$H$201,"<"&H4)+COUNTIFS($AZ$2:$AZ$201,AZ4,$CK$2:$CK$201,1,$H$2:$H$201,H4,$BA$2:$BA$201,"<"&BA4)=0,1,0),0) -> 0 | CM4: =IF(AND(BB4=1,U4="Y"),1,0) -> 0 | CN4: =IF(CM4=1,IF(COUNTIFS($AZ$2:$AZ$201,AZ4,$CM$2:$CM$201,1,$H$2:$H$201,"<"&H4)+COUNTIFS($AZ$2:$AZ$201,AZ4,$CM$2:$CM$201,1,$H$2:$H$201,H4,$BA$2:$BA$201,"<"&BA4)=0,1,0),0) -> 0 | CO4: =IF(AND(BB4=1,L4="Y"),1,0) -> 1 | CP4: =IF(CO4=1,IF(COUNTIFS($AZ$2:$AZ$201,AZ4,$CO$2:$CO$201,1,$H$2:$H$201,"<"&H4)+COUNTIFS($AZ$2:$AZ$201,AZ4,$CO$2:$CO$201,1,$H$2:$H$201,H4,$BA$2:$BA$201,"<"&BA4)=0,1,0),0) -> 1 | CQ4: =IF(AND(BB4=1,ISNUMBER(O4)),1,0) -> 1 | CR4: =IF(CQ4=1,IF(COUNTIFS($AZ$2:$AZ$201,AZ4,$CQ$2:$CQ$201,1,$H$2:$H$201,"<"&H4)+COUNTIFS($AZ$2:$AZ$201,AZ4,$CQ$2:$CQ$201,1,$H$2:$H$201,H4,$BA$2:$BA$201,"<"&BA4)=0,1,0),0) -> 1 | CS4: =IF(AND(CR4=1,INT(N(H4))<=Config!$B$5),O4,"") -> 120 | CT4: =IF(AND(BB4=1,INT(N(H4))<=Config!$B$5),AG4&"","") -> facilities | CU4: =IF(AND(BB4=1,AU4="Y"),1,0) -> 0 | CV4: =IF(CU4=1,IF(COUNTIFS($AZ$2:$AZ$201,AZ4,$CU$2:$CU$201,1,$H$2:$H$201,"<"&H4)+COUNTIFS($AZ$2:$AZ$201,AZ4,$CU$2:$CU$201,1,$H$2:$H$201,H4,$BA$2:$BA$201,"<"&BA4)=0,1,0),0) -> 0 | CW4: =IF(BB4=1,IFERROR(MATCH($A4,INDEX(Clay_Offices!$A$2:$FZ$601,0,Sync!$C$5),0),""),"") -> 3 | CX4: =IF(CW4="","",IFERROR(INDEX(Clay_Offices!$A$2:$FZ$601,CW4,Sync!$C$7)&"","")) -> call_done | CY4: =IF(CX4="","",IFERROR(INDEX(Lists!$K$2:$K$15,MATCH(CX4,Lists!$J$2:$J$15,0)),"")) -> 6 | CZ4: =IF(CW4="","",IFERROR(INDEX(Clay_Offices!$A$2:$FZ$601,CW4,Sync!$C$17)&"","")) -> N | DA4: =IF(CW4="","",IFERROR(N(INDEX(Clay_Offices!$A$2:$FZ$601,CW4,Sync!$C$16)),0)) -> 46324 | DB4: =IF(AND(BB4=1,OR(AR4="Y",AR4="N",AR4="maybe")),1,0) -> 1 | DC4: =IF(AND(DB4=1),IF(COUNTIFS($A$2:$A$201,$A4,$DB$2:$DB$201,1,$H$2:$H$201,">"&H4)+COUNTIFS($A$2:$A$201,$A4,$DB$2:$DB$201,1,$H$2:$H$201,H4,$BA$2:$BA$201,">"&BA4)=0,1,0),0) -> 1 | DD4: =IF(AND(DB4=1,INT(N(H4))<=Config!$B$6),IF(COUNTIFS($AZ$2:$AZ$201,AZ4,$DB$2:$DB$201,1,$H$2:$H$201,">"&H4,$H$2:$H$201,"<"&(Config!$B$6+1))+COUNTIFS($AZ$2:$AZ$201,AZ4,$DB$2:$DB$201,1,$H$2:$H$201,H4,$BA$2:$BA$201,">"&BA4)=0,1,0),0) -> 1 | DE4: =IF(AND(DB4=1,INT(N(H4))<=Config!$B$7),IF(COUNTIFS($AZ$2:$AZ$201,AZ4,$DB$2:$DB$201,1,$H$2:$H$201,">"&H4,$H$2:$H$201,"<"&(Config!$B$7+1))+COUNTIFS($AZ$2:$AZ$201,AZ4,$DB$2:$DB$201,1,$H$2:$H$201,H4,$BA$2:$BA$201,">"&BA4)=0,1,0),0) -> 1 | DF4: =IF(AND(DB4=1,INT(N(H4))<=Config!$B$8),IF(COUNTIFS($AZ$2:$AZ$201,AZ4,$DB$2:$DB$201,1,$H$2:$H$201,">"&H4,$H$2:$H$201,"<"&(Config!$B$8+1))+COUNTIFS($AZ$2:$AZ$201,AZ4,$DB$2:$DB$201,1,$H$2:$H$201,H4,$BA$2:$BA$201,">"&BA4)=0,1,0),0) -> 1 | DG4: =IF(AND(DB4=1,INT(N(H4))<=Config!$B$5),IF(COUNTIFS($AZ$2:$AZ$201,AZ4,$DB$2:$DB$201,1,$H$2:$H$201,">"&H4,$H$2:$H$201,"<"&(Config!$B$5+1))+COUNTIFS($AZ$2:$AZ$201,AZ4,$DB$2:$DB$201,1,$H$2:$H$201,H4,$BA$2:$BA$201,">"&BA4)=0,1,0),0) -> 1 | DH4: =IF(BB4=1,IF(COUNTIFS($AZ$2:$AZ$201,AZ4,$DD$2:$DD$201,1,$AR$2:$AR$201,"Y")>0,1,0),0) -> 0 | DI4: =IF(BB4=1,IF(COUNTIFS($AZ$2:$AZ$201,AZ4,$DE$2:$DE$201,1,$AR$2:$AR$201,"Y")>0,1,0),0) -> 0 | DJ4: =IF(BB4=1,IF(COUNTIFS($AZ$2:$AZ$201,AZ4,$DF$2:$DF$201,1,$AR$2:$AR$201,"Y")>0,1,0),0) -> 0 | DK4: =IF(BB4=1,IF(COUNTIFS($AZ$2:$AZ$201,AZ4,$DG$2:$DG$201,1,$AR$2:$AR$201,"Y")>0,1,0),0) -> 0 | DL4: =IF(AND(BF4=1,INT(N(H4))<=Config!$B$6,DH4=1,EI4=0),1,0) -> 0 | DM4: =IF(AND(BF4=1,INT(N(H4))<=Config!$B$7,DI4=1,EI4=0),1,0) -> 0 | DN4: =IF(AND(BF4=1,INT(N(H4))<=Config!$B$8,DJ4=1,EI4=0),1,0) -> 0 | DO4: =IF(AND(BF4=1,INT(N(H4))<=Config!$B$5,DK4=1,EI4=0),1,0) -> 0 | DP4: =IF(AND(CC4=1,INT(N(H4))<=Config!$B$6,DH4=1,EI4=0),1,0) -> 0 | DQ4: =IF(AND(CC4=1,INT(N(H4))<=Config!$B$7,DI4=1,EI4=0),1,0) -> 0 | DR4: =IF(AND(CC4=1,INT(N(H4))<=Config!$B$8,DJ4=1,EI4=0),1,0) -> 0 | DS4: =IF(AND(CC4=1,INT(N(H4))<=Config!$B$5,DK4=1,EI4=0),1,0) -> 0 | DT4: =IF(AND(CC4=1,INT(N(H4))<=Config!$B$6,DH4=0),1,0) -> 0 | DU4: =IF(AND(CC4=1,INT(N(H4))<=Config!$B$7,DI4=0),1,0) -> 0 | DV4: =IF(AND(CC4=1,INT(N(H4))<=Config!$B$8,DJ4=0),1,0) -> 0 | DW4: =IF(AND(CC4=1,INT(N(H4))<=Config!$B$5,DK4=0),1,0) -> 0 | DX4: =IF(TRIM($A4)="",0,ISTEXT(M4)+ISTEXT(O4)+ISTEXT(Y4)+ISTEXT(Z4)+ISTEXT(AA4)+ISTEXT(AV4)) -> 0 | DY4: =IF(BB4=1,IF(H4<>INT(H4),1,0),0) -> 0 | DZ4: =IF(TRIM($A4)="","",IF(TRIM(B4)="",SUBSTITUTE(SUBSTITUTE(SUBSTITUTE(SUBSTITUTE(SUBSTITUTE(SUBSTITUTE(LOWER(TRIM($A4)),"~",""),"*",""),"?",""),"<",""),">",""),"=",""),SUBSTITUTE(SUBSTITUTE(SUBSTITUTE(SUBSTITUTE(SUBSTITUTE(SUBSTITUTE(LOWER(TRIM(B4)),"~",""),"*",""),"?",""),"<",""),">",""),"=",""))) -> sample office 03 | EA4: =IF(CW4="","",IFERROR(IF(LEFT(LOWER(TRIM(INDEX(Clay_Offices!$A$2:$FZ$601,CW4,Sync!$C$19)&"")),4)="grp-",SUBSTITUTE(SUBSTITUTE(SUBSTITUTE(SUBSTITUTE(SUBSTITUTE(SUBSTITUTE(LOWER(TRIM(INDEX(Clay_Offices!$A$2:$FZ$601,CW4,Sync!$C$19)&"")),"~",""),"*",""),"?",""),"<",""),">",""),"=",""),""),"")) | EB4: =IF(EA4<>"",DZ4,"") | EC4: =IF(BC4=1,AZ4,"") -> sample office 03 | ED4: =IF(TRIM($A4)="","",IFERROR(INDEX($A$2:$A$201,MATCH(AZ4,$EC$2:$EC$201,0))&"",$A4&"")) -> SAMPLE-O-003 | EE4: =IF(BB4=1,IF(COUNTIFS($A$2:$A$201,$A4,$BB$2:$BB$201,1,$H$2:$H$201,"<"&H4)+COUNTIFS($A$2:$A$201,$A4,$BB$2:$BB$201,1,$H$2:$H$201,H4,$BA$2:$BA$201,"<"&BA4)=0,1,0),0) -> 1 | EF4: =IF(BC4=1,IF(COUNTIFS($AZ$2:$AZ$201,AZ4,$EE$2:$EE$201,1)>1,1,0),0) -> 0 | EG4: =IF(AND(CQ4=1),IF(COUNTIFS($AZ$2:$AZ$201,AZ4,$CQ$2:$CQ$201,1,$H$2:$H$201,">"&H4)+COUNTIFS($AZ$2:$AZ$201,AZ4,$CQ$2:$CQ$201,1,$H$2:$H$201,H4,$BA$2:$BA$201,">"&BA4)=0,1,0),0) -> 1 | EH4: =IF(BB4=1,IF(COUNTIFS($AZ$2:$AZ$201,AZ4,$EG$2:$EG$201,1)=0,"",SUMIFS($O$2:$O$201,$AZ$2:$AZ$201,AZ4,$EG$2:$EG$201,1)),"") -> 120 | EI4: =IF(AND(ISNUMBER(EH4),OR(N(EH4)<Config!$B$31,N(EH4)>Config!$B$33)),1,0) -> 0 | EJ4: =IF(AND(ISNUMBER(EH4),N(EH4)>=Config!$B$31,N(EH4)<Config!$B$32),1,0) -> 0 | EK4: =IF(AND(BF4=1,INT(N(H4))<=Config!$B$6,DH4=1,EI4=1),1,0) -> 0 | EL4: =IF(AND(BF4=1,INT(N(H4))<=Config!$B$7,DI4=1,EI4=1),1,0) -> 0 | EM4: =IF(AND(BF4=1,INT(N(H4))<=Config!$B$8,DJ4=1,EI4=1),1,0) -> 0 | EN4: =IF(AND(BF4=1,INT(N(H4))<=Config!$B$5,DK4=1,EI4=1),1,0) -> 0 | EO4: =IF(AND(DL4=1,EJ4=1),1,0) -> 0 | EP4: =IF(AND(DM4=1,EJ4=1),1,0) -> 0 | EQ4: =IF(AND(DN4=1,EJ4=1),1,0) -> 0 | ER4: =IF(AND(DO4=1,EJ4=1),1,0) -> 0
A5: SAMPLE-O-004 | B5: SAMPLE Office 04 | D5: SAMPLE Contact O04 | E5: Workplace Experience Manager | F5: SAMPLE Clay offices table | G5: linkedin | H5: 46328 | I5: video | J5: SAMPLE: pantry answer 04 | K5: SAMPLE grocery order | L5: N | M5: 1500 | N5: SAMPLE: about $1500 a month | O5: 90 | P5: SAMPLE: around 90 on a Tuesday | Q5: N | R5: SAMPLE: brands email us, we ignore most | S5: SAMPLE: allergen info and no work for me | T5: SAMPLE: anything with nuts | U5: Y | V5: SAMPLE: a photo is fine | W5: Y | X5: SAMPLE: around $300 a month | Y5: 300 | Z5: 300 | AA5: 0 | AC5: Y | AD5: SAMPLE Owner O04 | AE5: Office Manager | AF5: Y | AH5: SAMPLE mornings before 10 | AI5: front desk | AJ5: unsure | AK5: SAMPLE: sign in at desk | AL5: chocolate-candy;sparkling-soda | AM5: SAMPLE: no jerky | AN5: needs_approval | AQ5: SAMPLE: needs_approval (office 04) | AR5: Y | AS5: asked_when | AT5: Y | AU5: Y | AV5: 10 | AW5: Y | AY5: =IF(TRIM($A5)="","",IF(AND(LEFT($A5,6)="SAMPLE",Config!$B$19<>"Y"),"",IF(NOT(ISNUMBER(H5)),"call_date is blank or not a date",IF(Sync!$C$5="","Clay paste is empty or has no row_id column: paste the Clay export on Clay_Offices",IF(CW5="","row_id not found in the Clay paste: add the Clay row or fix the row_id",IF(AND(ISNUMBER(CY5),CY5>=1,CY5<=5),"Clay status is "&CX5&": set call_done or later",IF(AND(BD5=1,CZ5<>BZ5),"Clay yes_in_principle should be "&BZ5,IF(AND(BD5=1,DA5<>H5),"Clay call_date should be "&TEXT(H5,"yyyy-mm-dd"),"")))))))) -> Clay status is replied: set call_done or later | AZ5: =IF(TRIM($A5)="","",IF(TRIM(C5)<>"",SUBSTITUTE(SUBSTITUTE(SUBSTITUTE(SUBSTITUTE(SUBSTITUTE(SUBSTITUTE(LOWER(TRIM(C5)),"~",""),"*",""),"?",""),"<",""),">",""),"=",""),IF(EA5<>"",EA5,IFERROR(INDEX($EA$2:$EA$201,MATCH(DZ5,$EB$2:$EB$201,0)),DZ5)))) -> sample office 04 | BA5: =ROW() -> 5 | BB5: =IF(AND(TRIM($A5)<>"",ISNUMBER(H5)),IF(AND(LEFT($A5,6)="SAMPLE",Config!$B$19<>"Y"),0,1),0) -> 1 | BC5: =IF(BB5=1,IF(COUNTIFS($AZ$2:$AZ$201,AZ5,$BB$2:$BB$201,1,$H$2:$H$201,"<"&H5)+COUNTIFS($AZ$2:$AZ$201,AZ5,$BB$2:$BB$201,1,$H$2:$H$201,H5,$BA$2:$BA$201,"<"&BA5)=0,1,0),0) -> 1 | BD5: =IF(BB5=1,IF(COUNTIFS($A$2:$A$201,$A5,$BB$2:$BB$201,1,$H$2:$H$201,">"&H5)+COUNTIFS($A$2:$A$201,$A5,$BB$2:$BB$201,1,$H$2:$H$201,H5,$BA$2:$BA$201,">"&BA5)=0,1,0),0) -> 0 | BE5: =IF(AND(BB5=1,AR5="Y",AC5="Y",TRIM(AH5)<>""),1,0) -> 1 | BF5: =IF(BE5=1,IF(COUNTIFS($AZ$2:$AZ$201,AZ5,$BE$2:$BE$201,1,$H$2:$H$201,"<"&H5)+COUNTIFS($AZ$2:$AZ$201,AZ5,$BE$2:$BE$201,1,$H$2:$H$201,H5,$BA$2:$BA$201,"<"&BA5)=0,1,0),0) -> 1 | BG5: =IF(AND(BB5=1,AR5="Y",BE5=0),1,0) -> 0 | BH5: =IF(AND(BB5=1,ISNUMBER(Y5)),1,0) -> 1 | BI5: =IF(BH5=1,IF(COUNTIFS($AZ$2:$AZ$201,AZ5,$BH$2:$BH$201,1,$H$2:$H$201,"<"&H5)+COUNTIFS($AZ$2:$AZ$201,AZ5,$BH$2:$BH$201,1,$H$2:$H$201,H5,$BA$2:$BA$201,"<"&BA5)=0,1,0),0) -> 1 | BJ5: =IF(AND(BI5=1,INT(N(H5))<=Config!$B$6),Y5,"") | BK5: =IF(AND(BI5=1,INT(N(H5))<=Config!$B$7),Y5,"") -> 300 | BL5: =IF(AND(BI5=1,INT(N(H5))<=Config!$B$8),Y5,"") -> 300 | BM5: =IF(AND(BI5=1,INT(N(H5))<=Config!$B$5),Y5,"") -> 300 | BN5: =IF(CD5=1,IF(COUNTIFS($AZ$2:$AZ$201,AZ5,$CD$2:$CD$201,1,$H$2:$H$201,"<"&H5)+COUNTIFS($AZ$2:$AZ$201,AZ5,$CD$2:$CD$201,1,$H$2:$H$201,H5,$BA$2:$BA$201,"<"&BA5)=0,1,0),0) -> 1 | BO5: =IF(AND(BB5=1,ISNUMBER(M5)),1,0) -> 1 | BP5: =IF(BO5=1,IF(COUNTIFS($AZ$2:$AZ$201,AZ5,$BO$2:$BO$201,1,$H$2:$H$201,"<"&H5)+COUNTIFS($AZ$2:$AZ$201,AZ5,$BO$2:$BO$201,1,$H$2:$H$201,H5,$BA$2:$BA$201,"<"&BA5)=0,1,0),0) -> 1 | BQ5: =IF(AND(BP5=1,INT(N(H5))<=Config!$B$5),M5,"") -> 1500 | BR5: =IF(AND(BB5=1,OR(TRIM(X5)<>"",ISNUMBER(Y5))),1,0) -> 1 | BS5: =IF(BR5=1,IF(COUNTIFS($AZ$2:$AZ$201,AZ5,$BR$2:$BR$201,1,$H$2:$H$201,"<"&H5)+COUNTIFS($AZ$2:$AZ$201,AZ5,$BR$2:$BR$201,1,$H$2:$H$201,H5,$BA$2:$BA$201,"<"&BA5)=0,1,0),0) -> 1 | BT5: =IF(BS5=1,AZ5,"") -> sample office 04 | BU5: =IF(AND(BB5=1,W5="Y",TRIM(X5)=""),1,0) -> 0 | BV5: =IF(BB5=1,AN5&"","") -> needs_approval | BW5: =IF(BB5=1,AO5&"","") | BX5: =IF(BB5=1,AP5&"","") | BY5: =IF(AND(BB5=1,ISNUMBER(AV5),INT(N(H5))<=Config!$B$5),AV5,"") -> 10 | BZ5: =IF(BB5=1,IF(COUNTIFS($A$2:$A$201,$A5,$DC$2:$DC$201,1,$AR$2:$AR$201,"Y")>0,"Y","N"),"") -> N | CA5: =IF(AND(BB5=1,AR5="maybe"),1,0) -> 0 | CB5: =IF(CA5=1,IF(COUNTIFS($AZ$2:$AZ$201,AZ5,$CA$2:$CA$201,1,$H$2:$H$201,"<"&H5)+COUNTIFS($AZ$2:$AZ$201,AZ5,$CA$2:$CA$201,1,$H$2:$H$201,H5,$BA$2:$BA$201,"<"&BA5)=0,1,0),0) -> 0 | CC5: =IF(AND(BB5=1,AR5="Y"),IF(COUNTIFS($AZ$2:$AZ$201,AZ5,$AR$2:$AR$201,"Y",$BB$2:$BB$201,1,$H$2:$H$201,"<"&H5)+COUNTIFS($AZ$2:$AZ$201,AZ5,$AR$2:$AR$201,"Y",$BB$2:$BB$201,1,$H$2:$H$201,H5,$BA$2:$BA$201,"<"&BA5)=0,1,0),0) -> 1 | CD5: =IF(AND(BH5=1,N(Y5)>=Config!$B$15),1,0) -> 1 | CE5: =IF(AND(BB5=1,AT5="Y"),1,0) -> 1 | CF5: =IF(CE5=1,IF(COUNTIFS($AZ$2:$AZ$201,AZ5,$CE$2:$CE$201,1,$H$2:$H$201,"<"&H5)+COUNTIFS($AZ$2:$AZ$201,AZ5,$CE$2:$CE$201,1,$H$2:$H$201,H5,$BA$2:$BA$201,"<"&BA5)=0,1,0),0) -> 1 | CG5: =IF(AND(BB5=1,G5="warm-intro"),1,0) -> 0 | CH5: =IF(CG5=1,IF(COUNTIFS($AZ$2:$AZ$201,AZ5,$CG$2:$CG$201,1,$H$2:$H$201,"<"&H5)+COUNTIFS($AZ$2:$AZ$201,AZ5,$CG$2:$CG$201,1,$H$2:$H$201,H5,$BA$2:$BA$201,"<"&BA5)=0,1,0),0) -> 0 | CI5: =IF(AND(BB5=1,Q5="Y"),1,0) -> 0 | CJ5: =IF(CI5=1,IF(COUNTIFS($AZ$2:$AZ$201,AZ5,$CI$2:$CI$201,1,$H$2:$H$201,"<"&H5)+COUNTIFS($AZ$2:$AZ$201,AZ5,$CI$2:$CI$201,1,$H$2:$H$201,H5,$BA$2:$BA$201,"<"&BA5)=0,1,0),0) -> 0 | CK5: =IF(AND(BB5=1,AF5="Y"),1,0) -> 1 | CL5: =IF(CK5=1,IF(COUNTIFS($AZ$2:$AZ$201,AZ5,$CK$2:$CK$201,1,$H$2:$H$201,"<"&H5)+COUNTIFS($AZ$2:$AZ$201,AZ5,$CK$2:$CK$201,1,$H$2:$H$201,H5,$BA$2:$BA$201,"<"&BA5)=0,1,0),0) -> 1 | CM5: =IF(AND(BB5=1,U5="Y"),1,0) -> 1 | CN5: =IF(CM5=1,IF(COUNTIFS($AZ$2:$AZ$201,AZ5,$CM$2:$CM$201,1,$H$2:$H$201,"<"&H5)+COUNTIFS($AZ$2:$AZ$201,AZ5,$CM$2:$CM$201,1,$H$2:$H$201,H5,$BA$2:$BA$201,"<"&BA5)=0,1,0),0) -> 1 | CO5: =IF(AND(BB5=1,L5="Y"),1,0) -> 0 | CP5: =IF(CO5=1,IF(COUNTIFS($AZ$2:$AZ$201,AZ5,$CO$2:$CO$201,1,$H$2:$H$201,"<"&H5)+COUNTIFS($AZ$2:$AZ$201,AZ5,$CO$2:$CO$201,1,$H$2:$H$201,H5,$BA$2:$BA$201,"<"&BA5)=0,1,0),0) -> 0 | CQ5: =IF(AND(BB5=1,ISNUMBER(O5)),1,0) -> 1 | CR5: =IF(CQ5=1,IF(COUNTIFS($AZ$2:$AZ$201,AZ5,$CQ$2:$CQ$201,1,$H$2:$H$201,"<"&H5)+COUNTIFS($AZ$2:$AZ$201,AZ5,$CQ$2:$CQ$201,1,$H$2:$H$201,H5,$BA$2:$BA$201,"<"&BA5)=0,1,0),0) -> 1 | CS5: =IF(AND(CR5=1,INT(N(H5))<=Config!$B$5),O5,"") -> 90 | CT5: =IF(AND(BB5=1,INT(N(H5))<=Config!$B$5),AG5&"","") | CU5: =IF(AND(BB5=1,AU5="Y"),1,0) -> 1 | CV5: =IF(CU5=1,IF(COUNTIFS($AZ$2:$AZ$201,AZ5,$CU$2:$CU$201,1,$H$2:$H$201,"<"&H5)+COUNTIFS($AZ$2:$AZ$201,AZ5,$CU$2:$CU$201,1,$H$2:$H$201,H5,$BA$2:$BA$201,"<"&BA5)=0,1,0),0) -> 1 | CW5: =IF(BB5=1,IFERROR(MATCH($A5,INDEX(Clay_Offices!$A$2:$FZ$601,0,Sync!$C$5),0),""),"") -> 4 | CX5: =IF(CW5="","",IFERROR(INDEX(Clay_Offices!$A$2:$FZ$601,CW5,Sync!$C$7)&"","")) -> replied | CY5: =IF(CX5="","",IFERROR(INDEX(Lists!$K$2:$K$15,MATCH(CX5,Lists!$J$2:$J$15,0)),"")) -> 4 | CZ5: =IF(CW5="","",IFERROR(INDEX(Clay_Offices!$A$2:$FZ$601,CW5,Sync!$C$17)&"","")) -> N | DA5: =IF(CW5="","",IFERROR(N(INDEX(Clay_Offices!$A$2:$FZ$601,CW5,Sync!$C$16)),0)) -> 46338 | DB5: =IF(AND(BB5=1,OR(AR5="Y",AR5="N",AR5="maybe")),1,0) -> 1 | DC5: =IF(AND(DB5=1),IF(COUNTIFS($A$2:$A$201,$A5,$DB$2:$DB$201,1,$H$2:$H$201,">"&H5)+COUNTIFS($A$2:$A$201,$A5,$DB$2:$DB$201,1,$H$2:$H$201,H5,$BA$2:$BA$201,">"&BA5)=0,1,0),0) -> 0 | DD5: =IF(AND(DB5=1,INT(N(H5))<=Config!$B$6),IF(COUNTIFS($AZ$2:$AZ$201,AZ5,$DB$2:$DB$201,1,$H$2:$H$201,">"&H5,$H$2:$H$201,"<"&(Config!$B$6+1))+COUNTIFS($AZ$2:$AZ$201,AZ5,$DB$2:$DB$201,1,$H$2:$H$201,H5,$BA$2:$BA$201,">"&BA5)=0,1,0),0) -> 0 | DE5: =IF(AND(DB5=1,INT(N(H5))<=Config!$B$7),IF(COUNTIFS($AZ$2:$AZ$201,AZ5,$DB$2:$DB$201,1,$H$2:$H$201,">"&H5,$H$2:$H$201,"<"&(Config!$B$7+1))+COUNTIFS($AZ$2:$AZ$201,AZ5,$DB$2:$DB$201,1,$H$2:$H$201,H5,$BA$2:$BA$201,">"&BA5)=0,1,0),0) -> 1 | DF5: =IF(AND(DB5=1,INT(N(H5))<=Config!$B$8),IF(COUNTIFS($AZ$2:$AZ$201,AZ5,$DB$2:$DB$201,1,$H$2:$H$201,">"&H5,$H$2:$H$201,"<"&(Config!$B$8+1))+COUNTIFS($AZ$2:$AZ$201,AZ5,$DB$2:$DB$201,1,$H$2:$H$201,H5,$BA$2:$BA$201,">"&BA5)=0,1,0),0) -> 0 | DG5: =IF(AND(DB5=1,INT(N(H5))<=Config!$B$5),IF(COUNTIFS($AZ$2:$AZ$201,AZ5,$DB$2:$DB$201,1,$H$2:$H$201,">"&H5,$H$2:$H$201,"<"&(Config!$B$5+1))+COUNTIFS($AZ$2:$AZ$201,AZ5,$DB$2:$DB$201,1,$H$2:$H$201,H5,$BA$2:$BA$201,">"&BA5)=0,1,0),0) -> 0 | DH5: =IF(BB5=1,IF(COUNTIFS($AZ$2:$AZ$201,AZ5,$DD$2:$DD$201,1,$AR$2:$AR$201,"Y")>0,1,0),0) -> 0 | DI5: =IF(BB5=1,IF(COUNTIFS($AZ$2:$AZ$201,AZ5,$DE$2:$DE$201,1,$AR$2:$AR$201,"Y")>0,1,0),0) -> 1 | DJ5: =IF(BB5=1,IF(COUNTIFS($AZ$2:$AZ$201,AZ5,$DF$2:$DF$201,1,$AR$2:$AR$201,"Y")>0,1,0),0) -> 0 | DK5: =IF(BB5=1,IF(COUNTIFS($AZ$2:$AZ$201,AZ5,$DG$2:$DG$201,1,$AR$2:$AR$201,"Y")>0,1,0),0) -> 0 | DL5: =IF(AND(BF5=1,INT(N(H5))<=Config!$B$6,DH5=1,EI5=0),1,0) -> 0 | DM5: =IF(AND(BF5=1,INT(N(H5))<=Config!$B$7,DI5=1,EI5=0),1,0) -> 1 | DN5: =IF(AND(BF5=1,INT(N(H5))<=Config!$B$8,DJ5=1,EI5=0),1,0) -> 0 | DO5: =IF(AND(BF5=1,INT(N(H5))<=Config!$B$5,DK5=1,EI5=0),1,0) -> 0 | DP5: =IF(AND(CC5=1,INT(N(H5))<=Config!$B$6,DH5=1,EI5=0),1,0) -> 0 | DQ5: =IF(AND(CC5=1,INT(N(H5))<=Config!$B$7,DI5=1,EI5=0),1,0) -> 1 | DR5: =IF(AND(CC5=1,INT(N(H5))<=Config!$B$8,DJ5=1,EI5=0),1,0) -> 0 | DS5: =IF(AND(CC5=1,INT(N(H5))<=Config!$B$5,DK5=1,EI5=0),1,0) -> 0 | DT5: =IF(AND(CC5=1,INT(N(H5))<=Config!$B$6,DH5=0),1,0) -> 0 | DU5: =IF(AND(CC5=1,INT(N(H5))<=Config!$B$7,DI5=0),1,0) -> 0 | DV5: =IF(AND(CC5=1,INT(N(H5))<=Config!$B$8,DJ5=0),1,0) -> 1 | DW5: =IF(AND(CC5=1,INT(N(H5))<=Config!$B$5,DK5=0),1,0) -> 1 | DX5: =IF(TRIM($A5)="",0,ISTEXT(M5)+ISTEXT(O5)+ISTEXT(Y5)+ISTEXT(Z5)+ISTEXT(AA5)+ISTEXT(AV5)) -> 0 | DY5: =IF(BB5=1,IF(H5<>INT(H5),1,0),0) -> 0 | DZ5: =IF(TRIM($A5)="","",IF(TRIM(B5)="",SUBSTITUTE(SUBSTITUTE(SUBSTITUTE(SUBSTITUTE(SUBSTITUTE(SUBSTITUTE(LOWER(TRIM($A5)),"~",""),"*",""),"?",""),"<",""),">",""),"=",""),SUBSTITUTE(SUBSTITUTE(SUBSTITUTE(SUBSTITUTE(SUBSTITUTE(SUBSTITUTE(LOWER(TRIM(B5)),"~",""),"*",""),"?",""),"<",""),">",""),"=",""))) -> sample office 04 | EA5: =IF(CW5="","",IFERROR(IF(LEFT(LOWER(TRIM(INDEX(Clay_Offices!$A$2:$FZ$601,CW5,Sync!$C$19)&"")),4)="grp-",SUBSTITUTE(SUBSTITUTE(SUBSTITUTE(SUBSTITUTE(SUBSTITUTE(SUBSTITUTE(LOWER(TRIM(INDEX(Clay_Offices!$A$2:$FZ$601,CW5,Sync!$C$19)&"")),"~",""),"*",""),"?",""),"<",""),">",""),"=",""),""),"")) | EB5: =IF(EA5<>"",DZ5,"") | EC5: =IF(BC5=1,AZ5,"") -> sample office 04 | ED5: =IF(TRIM($A5)="","",IFERROR(INDEX($A$2:$A$201,MATCH(AZ5,$EC$2:$EC$201,0))&"",$A5&"")) -> SAMPLE-O-004 | EE5: =IF(BB5=1,IF(COUNTIFS($A$2:$A$201,$A5,$BB$2:$BB$201,1,$H$2:$H$201,"<"&H5)+COUNTIFS($A$2:$A$201,$A5,$BB$2:$BB$201,1,$H$2:$H$201,H5,$BA$2:$BA$201,"<"&BA5)=0,1,0),0) -> 1 | EF5: =IF(BC5=1,IF(COUNTIFS($AZ$2:$AZ$201,AZ5,$EE$2:$EE$201,1)>1,1,0),0) -> 0 | EG5: =IF(AND(CQ5=1),IF(COUNTIFS($AZ$2:$AZ$201,AZ5,$CQ$2:$CQ$201,1,$H$2:$H$201,">"&H5)+COUNTIFS($AZ$2:$AZ$201,AZ5,$CQ$2:$CQ$201,1,$H$2:$H$201,H5,$BA$2:$BA$201,">"&BA5)=0,1,0),0) -> 0 | EH5: =IF(BB5=1,IF(COUNTIFS($AZ$2:$AZ$201,AZ5,$EG$2:$EG$201,1)=0,"",SUMIFS($O$2:$O$201,$AZ$2:$AZ$201,AZ5,$EG$2:$EG$201,1)),"") -> 90 | EI5: =IF(AND(ISNUMBER(EH5),OR(N(EH5)<Config!$B$31,N(EH5)>Config!$B$33)),1,0) -> 0 | EJ5: =IF(AND(ISNUMBER(EH5),N(EH5)>=Config!$B$31,N(EH5)<Config!$B$32),1,0) -> 0 | EK5: =IF(AND(BF5=1,INT(N(H5))<=Config!$B$6,DH5=1,EI5=1),1,0) -> 0 | EL5: =IF(AND(BF5=1,INT(N(H5))<=Config!$B$7,DI5=1,EI5=1),1,0) -> 0 | EM5: =IF(AND(BF5=1,INT(N(H5))<=Config!$B$8,DJ5=1,EI5=1),1,0) -> 0 | EN5: =IF(AND(BF5=1,INT(N(H5))<=Config!$B$5,DK5=1,EI5=1),1,0) -> 0 | EO5: =IF(AND(DL5=1,EJ5=1),1,0) -> 0 | EP5: =IF(AND(DM5=1,EJ5=1),1,0) -> 0 | EQ5: =IF(AND(DN5=1,EJ5=1),1,0) -> 0 | ER5: =IF(AND(DO5=1,EJ5=1),1,0) -> 0
A6: SAMPLE-O-005 | B6: SAMPLE Office 05 | D6: SAMPLE Contact O05 | E6: Office Manager | F6: SAMPLE Clay offices table | G6: linkedin | H6: 46329 | I6: phone | J6: SAMPLE: pantry answer 05 | K6: SAMPLE grocery order | L6: N | O6: 150 | P6: SAMPLE: around 150 on a Tuesday | Q6: Y | R6: SAMPLE: brands email us, we ignore most | S6: SAMPLE: allergen info and no work for me | T6: SAMPLE: anything with nuts | U6: maybe | V6: SAMPLE: a photo is fine | W6: Y | X6: SAMPLE: zero, it would come out of my budget | Y6: 0 | Z6: 0 | AA6: 0 | AC6: N | AF6: N | AG6: facilities | AI6: front desk | AJ6: no | AK6: SAMPLE: sign in at desk | AL6: meat-snacks | AM6: SAMPLE: no jerky | AN6: needs_approval | AO6: building_receiving | AQ6: SAMPLE: needs_approval / building_receiving (office 05) | AR6: maybe | AT6: Y | AV6: 7 | AW6: Y | AY6: =IF(TRIM($A6)="","",IF(AND(LEFT($A6,6)="SAMPLE",Config!$B$19<>"Y"),"",IF(NOT(ISNUMBER(H6)),"call_date is blank or not a date",IF(Sync!$C$5="","Clay paste is empty or has no row_id column: paste the Clay export on Clay_Offices",IF(CW6="","row_id not found in the Clay paste: add the Clay row or fix the row_id",IF(AND(ISNUMBER(CY6),CY6>=1,CY6<=5),"Clay status is "&CX6&": set call_done or later",IF(AND(BD6=1,CZ6<>BZ6),"Clay yes_in_principle should be "&BZ6,IF(AND(BD6=1,DA6<>H6),"Clay call_date should be "&TEXT(H6,"yyyy-mm-dd"),"")))))))) | AZ6: =IF(TRIM($A6)="","",IF(TRIM(C6)<>"",SUBSTITUTE(SUBSTITUTE(SUBSTITUTE(SUBSTITUTE(SUBSTITUTE(SUBSTITUTE(LOWER(TRIM(C6)),"~",""),"*",""),"?",""),"<",""),">",""),"=",""),IF(EA6<>"",EA6,IFERROR(INDEX($EA$2:$EA$201,MATCH(DZ6,$EB$2:$EB$201,0)),DZ6)))) -> sample office 05 | BA6: =ROW() -> 6 | BB6: =IF(AND(TRIM($A6)<>"",ISNUMBER(H6)),IF(AND(LEFT($A6,6)="SAMPLE",Config!$B$19<>"Y"),0,1),0) -> 1 | BC6: =IF(BB6=1,IF(COUNTIFS($AZ$2:$AZ$201,AZ6,$BB$2:$BB$201,1,$H$2:$H$201,"<"&H6)+COUNTIFS($AZ$2:$AZ$201,AZ6,$BB$2:$BB$201,1,$H$2:$H$201,H6,$BA$2:$BA$201,"<"&BA6)=0,1,0),0) -> 1 | BD6: =IF(BB6=1,IF(COUNTIFS($A$2:$A$201,$A6,$BB$2:$BB$201,1,$H$2:$H$201,">"&H6)+COUNTIFS($A$2:$A$201,$A6,$BB$2:$BB$201,1,$H$2:$H$201,H6,$BA$2:$BA$201,">"&BA6)=0,1,0),0) -> 1 | BE6: =IF(AND(BB6=1,AR6="Y",AC6="Y",TRIM(AH6)<>""),1,0) -> 0 | BF6: =IF(BE6=1,IF(COUNTIFS($AZ$2:$AZ$201,AZ6,$BE$2:$BE$201,1,$H$2:$H$201,"<"&H6)+COUNTIFS($AZ$2:$AZ$201,AZ6,$BE$2:$BE$201,1,$H$2:$H$201,H6,$BA$2:$BA$201,"<"&BA6)=0,1,0),0) -> 0 | BG6: =IF(AND(BB6=1,AR6="Y",BE6=0),1,0) -> 0 | BH6: =IF(AND(BB6=1,ISNUMBER(Y6)),1,0) -> 1 | BI6: =IF(BH6=1,IF(COUNTIFS($AZ$2:$AZ$201,AZ6,$BH$2:$BH$201,1,$H$2:$H$201,"<"&H6)+COUNTIFS($AZ$2:$AZ$201,AZ6,$BH$2:$BH$201,1,$H$2:$H$201,H6,$BA$2:$BA$201,"<"&BA6)=0,1,0),0) -> 1 | BJ6: =IF(AND(BI6=1,INT(N(H6))<=Config!$B$6),Y6,"") | BK6: =IF(AND(BI6=1,INT(N(H6))<=Config!$B$7),Y6,"") -> 0 | BL6: =IF(AND(BI6=1,INT(N(H6))<=Config!$B$8),Y6,"") -> 0 | BM6: =IF(AND(BI6=1,INT(N(H6))<=Config!$B$5),Y6,"") -> 0 | BN6: =IF(CD6=1,IF(COUNTIFS($AZ$2:$AZ$201,AZ6,$CD$2:$CD$201,1,$H$2:$H$201,"<"&H6)+COUNTIFS($AZ$2:$AZ$201,AZ6,$CD$2:$CD$201,1,$H$2:$H$201,H6,$BA$2:$BA$201,"<"&BA6)=0,1,0),0) -> 0 | BO6: =IF(AND(BB6=1,ISNUMBER(M6)),1,0) -> 0 | BP6: =IF(BO6=1,IF(COUNTIFS($AZ$2:$AZ$201,AZ6,$BO$2:$BO$201,1,$H$2:$H$201,"<"&H6)+COUNTIFS($AZ$2:$AZ$201,AZ6,$BO$2:$BO$201,1,$H$2:$H$201,H6,$BA$2:$BA$201,"<"&BA6)=0,1,0),0) -> 0 | BQ6: =IF(AND(BP6=1,INT(N(H6))<=Config!$B$5),M6,"") | BR6: =IF(AND(BB6=1,OR(TRIM(X6)<>"",ISNUMBER(Y6))),1,0) -> 1 | BS6: =IF(BR6=1,IF(COUNTIFS($AZ$2:$AZ$201,AZ6,$BR$2:$BR$201,1,$H$2:$H$201,"<"&H6)+COUNTIFS($AZ$2:$AZ$201,AZ6,$BR$2:$BR$201,1,$H$2:$H$201,H6,$BA$2:$BA$201,"<"&BA6)=0,1,0),0) -> 1 | BT6: =IF(BS6=1,AZ6,"") -> sample office 05 | BU6: =IF(AND(BB6=1,W6="Y",TRIM(X6)=""),1,0) -> 0 | BV6: =IF(BB6=1,AN6&"","") -> needs_approval | BW6: =IF(BB6=1,AO6&"","") -> building_receiving | BX6: =IF(BB6=1,AP6&"","") | BY6: =IF(AND(BB6=1,ISNUMBER(AV6),INT(N(H6))<=Config!$B$5),AV6,"") -> 7 | BZ6: =IF(BB6=1,IF(COUNTIFS($A$2:$A$201,$A6,$DC$2:$DC$201,1,$AR$2:$AR$201,"Y")>0,"Y","N"),"") -> N | CA6: =IF(AND(BB6=1,AR6="maybe"),1,0) -> 1 | CB6: =IF(CA6=1,IF(COUNTIFS($AZ$2:$AZ$201,AZ6,$CA$2:$CA$201,1,$H$2:$H$201,"<"&H6)+COUNTIFS($AZ$2:$AZ$201,AZ6,$CA$2:$CA$201,1,$H$2:$H$201,H6,$BA$2:$BA$201,"<"&BA6)=0,1,0),0) -> 1 | CC6: =IF(AND(BB6=1,AR6="Y"),IF(COUNTIFS($AZ$2:$AZ$201,AZ6,$AR$2:$AR$201,"Y",$BB$2:$BB$201,1,$H$2:$H$201,"<"&H6)+COUNTIFS($AZ$2:$AZ$201,AZ6,$AR$2:$AR$201,"Y",$BB$2:$BB$201,1,$H$2:$H$201,H6,$BA$2:$BA$201,"<"&BA6)=0,1,0),0) -> 0 | CD6: =IF(AND(BH6=1,N(Y6)>=Config!$B$15),1,0) -> 0 | CE6: =IF(AND(BB6=1,AT6="Y"),1,0) -> 1 | CF6: =IF(CE6=1,IF(COUNTIFS($AZ$2:$AZ$201,AZ6,$CE$2:$CE$201,1,$H$2:$H$201,"<"&H6)+COUNTIFS($AZ$2:$AZ$201,AZ6,$CE$2:$CE$201,1,$H$2:$H$201,H6,$BA$2:$BA$201,"<"&BA6)=0,1,0),0) -> 1 | CG6: =IF(AND(BB6=1,G6="warm-intro"),1,0) -> 0 | CH6: =IF(CG6=1,IF(COUNTIFS($AZ$2:$AZ$201,AZ6,$CG$2:$CG$201,1,$H$2:$H$201,"<"&H6)+COUNTIFS($AZ$2:$AZ$201,AZ6,$CG$2:$CG$201,1,$H$2:$H$201,H6,$BA$2:$BA$201,"<"&BA6)=0,1,0),0) -> 0 | CI6: =IF(AND(BB6=1,Q6="Y"),1,0) -> 1 | CJ6: =IF(CI6=1,IF(COUNTIFS($AZ$2:$AZ$201,AZ6,$CI$2:$CI$201,1,$H$2:$H$201,"<"&H6)+COUNTIFS($AZ$2:$AZ$201,AZ6,$CI$2:$CI$201,1,$H$2:$H$201,H6,$BA$2:$BA$201,"<"&BA6)=0,1,0),0) -> 1 | CK6: =IF(AND(BB6=1,AF6="Y"),1,0) -> 0 | CL6: =IF(CK6=1,IF(COUNTIFS($AZ$2:$AZ$201,AZ6,$CK$2:$CK$201,1,$H$2:$H$201,"<"&H6)+COUNTIFS($AZ$2:$AZ$201,AZ6,$CK$2:$CK$201,1,$H$2:$H$201,H6,$BA$2:$BA$201,"<"&BA6)=0,1,0),0) -> 0 | CM6: =IF(AND(BB6=1,U6="Y"),1,0) -> 0 | CN6: =IF(CM6=1,IF(COUNTIFS($AZ$2:$AZ$201,AZ6,$CM$2:$CM$201,1,$H$2:$H$201,"<"&H6)+COUNTIFS($AZ$2:$AZ$201,AZ6,$CM$2:$CM$201,1,$H$2:$H$201,H6,$BA$2:$BA$201,"<"&BA6)=0,1,0),0) -> 0 | CO6: =IF(AND(BB6=1,L6="Y"),1,0) -> 0 | CP6: =IF(CO6=1,IF(COUNTIFS($AZ$2:$AZ$201,AZ6,$CO$2:$CO$201,1,$H$2:$H$201,"<"&H6)+COUNTIFS($AZ$2:$AZ$201,AZ6,$CO$2:$CO$201,1,$H$2:$H$201,H6,$BA$2:$BA$201,"<"&BA6)=0,1,0),0) -> 0 | CQ6: =IF(AND(BB6=1,ISNUMBER(O6)),1,0) -> 1 | CR6: =IF(CQ6=1,IF(COUNTIFS($AZ$2:$AZ$201,AZ6,$CQ$2:$CQ$201,1,$H$2:$H$201,"<"&H6)+COUNTIFS($AZ$2:$AZ$201,AZ6,$CQ$2:$CQ$201,1,$H$2:$H$201,H6,$BA$2:$BA$201,"<"&BA6)=0,1,0),0) -> 1 | CS6: =IF(AND(CR6=1,INT(N(H6))<=Config!$B$5),O6,"") -> 150 | CT6: =IF(AND(BB6=1,INT(N(H6))<=Config!$B$5),AG6&"","") -> facilities | CU6: =IF(AND(BB6=1,AU6="Y"),1,0) -> 0 | CV6: =IF(CU6=1,IF(COUNTIFS($AZ$2:$AZ$201,AZ6,$CU$2:$CU$201,1,$H$2:$H$201,"<"&H6)+COUNTIFS($AZ$2:$AZ$201,AZ6,$CU$2:$CU$201,1,$H$2:$H$201,H6,$BA$2:$BA$201,"<"&BA6)=0,1,0),0) -> 0 | CW6: =IF(BB6=1,IFERROR(MATCH($A6,INDEX(Clay_Offices!$A$2:$FZ$601,0,Sync!$C$5),0),""),"") -> 5 | CX6: =IF(CW6="","",IFERROR(INDEX(Clay_Offices!$A$2:$FZ$601,CW6,Sync!$C$7)&"","")) -> call_done | CY6: =IF(CX6="","",IFERROR(INDEX(Lists!$K$2:$K$15,MATCH(CX6,Lists!$J$2:$J$15,0)),"")) -> 6 | CZ6: =IF(CW6="","",IFERROR(INDEX(Clay_Offices!$A$2:$FZ$601,CW6,Sync!$C$17)&"","")) -> N | DA6: =IF(CW6="","",IFERROR(N(INDEX(Clay_Offices!$A$2:$FZ$601,CW6,Sync!$C$16)),0)) -> 46329 | DB6: =IF(AND(BB6=1,OR(AR6="Y",AR6="N",AR6="maybe")),1,0) -> 1 | DC6: =IF(AND(DB6=1),IF(COUNTIFS($A$2:$A$201,$A6,$DB$2:$DB$201,1,$H$2:$H$201,">"&H6)+COUNTIFS($A$2:$A$201,$A6,$DB$2:$DB$201,1,$H$2:$H$201,H6,$BA$2:$BA$201,">"&BA6)=0,1,0),0) -> 1 | DD6: =IF(AND(DB6=1,INT(N(H6))<=Config!$B$6),IF(COUNTIFS($AZ$2:$AZ$201,AZ6,$DB$2:$DB$201,1,$H$2:$H$201,">"&H6,$H$2:$H$201,"<"&(Config!$B$6+1))+COUNTIFS($AZ$2:$AZ$201,AZ6,$DB$2:$DB$201,1,$H$2:$H$201,H6,$BA$2:$BA$201,">"&BA6)=0,1,0),0) -> 0 | DE6: =IF(AND(DB6=1,INT(N(H6))<=Config!$B$7),IF(COUNTIFS($AZ$2:$AZ$201,AZ6,$DB$2:$DB$201,1,$H$2:$H$201,">"&H6,$H$2:$H$201,"<"&(Config!$B$7+1))+COUNTIFS($AZ$2:$AZ$201,AZ6,$DB$2:$DB$201,1,$H$2:$H$201,H6,$BA$2:$BA$201,">"&BA6)=0,1,0),0) -> 1 | DF6: =IF(AND(DB6=1,INT(N(H6))<=Config!$B$8),IF(COUNTIFS($AZ$2:$AZ$201,AZ6,$DB$2:$DB$201,1,$H$2:$H$201,">"&H6,$H$2:$H$201,"<"&(Config!$B$8+1))+COUNTIFS($AZ$2:$AZ$201,AZ6,$DB$2:$DB$201,1,$H$2:$H$201,H6,$BA$2:$BA$201,">"&BA6)=0,1,0),0) -> 1 | DG6: =IF(AND(DB6=1,INT(N(H6))<=Config!$B$5),IF(COUNTIFS($AZ$2:$AZ$201,AZ6,$DB$2:$DB$201,1,$H$2:$H$201,">"&H6,$H$2:$H$201,"<"&(Config!$B$5+1))+COUNTIFS($AZ$2:$AZ$201,AZ6,$DB$2:$DB$201,1,$H$2:$H$201,H6,$BA$2:$BA$201,">"&BA6)=0,1,0),0) -> 1 | DH6: =IF(BB6=1,IF(COUNTIFS($AZ$2:$AZ$201,AZ6,$DD$2:$DD$201,1,$AR$2:$AR$201,"Y")>0,1,0),0) -> 0 | DI6: =IF(BB6=1,IF(COUNTIFS($AZ$2:$AZ$201,AZ6,$DE$2:$DE$201,1,$AR$2:$AR$201,"Y")>0,1,0),0) -> 0 | DJ6: =IF(BB6=1,IF(COUNTIFS($AZ$2:$AZ$201,AZ6,$DF$2:$DF$201,1,$AR$2:$AR$201,"Y")>0,1,0),0) -> 0 | DK6: =IF(BB6=1,IF(COUNTIFS($AZ$2:$AZ$201,AZ6,$DG$2:$DG$201,1,$AR$2:$AR$201,"Y")>0,1,0),0) -> 0 | DL6: =IF(AND(BF6=1,INT(N(H6))<=Config!$B$6,DH6=1,EI6=0),1,0) -> 0 | DM6: =IF(AND(BF6=1,INT(N(H6))<=Config!$B$7,DI6=1,EI6=0),1,0) -> 0 | DN6: =IF(AND(BF6=1,INT(N(H6))<=Config!$B$8,DJ6=1,EI6=0),1,0) -> 0 | DO6: =IF(AND(BF6=1,INT(N(H6))<=Config!$B$5,DK6=1,EI6=0),1,0) -> 0 | DP6: =IF(AND(CC6=1,INT(N(H6))<=Config!$B$6,DH6=1,EI6=0),1,0) -> 0 | DQ6: =IF(AND(CC6=1,INT(N(H6))<=Config!$B$7,DI6=1,EI6=0),1,0) -> 0 | DR6: =IF(AND(CC6=1,INT(N(H6))<=Config!$B$8,DJ6=1,EI6=0),1,0) -> 0 | DS6: =IF(AND(CC6=1,INT(N(H6))<=Config!$B$5,DK6=1,EI6=0),1,0) -> 0 | DT6: =IF(AND(CC6=1,INT(N(H6))<=Config!$B$6,DH6=0),1,0) -> 0 | DU6: =IF(AND(CC6=1,INT(N(H6))<=Config!$B$7,DI6=0),1,0) -> 0 | DV6: =IF(AND(CC6=1,INT(N(H6))<=Config!$B$8,DJ6=0),1,0) -> 0 | DW6: =IF(AND(CC6=1,INT(N(H6))<=Config!$B$5,DK6=0),1,0) -> 0 | DX6: =IF(TRIM($A6)="",0,ISTEXT(M6)+ISTEXT(O6)+ISTEXT(Y6)+ISTEXT(Z6)+ISTEXT(AA6)+ISTEXT(AV6)) -> 0 | DY6: =IF(BB6=1,IF(H6<>INT(H6),1,0),0) -> 0 | DZ6: =IF(TRIM($A6)="","",IF(TRIM(B6)="",SUBSTITUTE(SUBSTITUTE(SUBSTITUTE(SUBSTITUTE(SUBSTITUTE(SUBSTITUTE(LOWER(TRIM($A6)),"~",""),"*",""),"?",""),"<",""),">",""),"=",""),SUBSTITUTE(SUBSTITUTE(SUBSTITUTE(SUBSTITUTE(SUBSTITUTE(SUBSTITUTE(LOWER(TRIM(B6)),"~",""),"*",""),"?",""),"<",""),">",""),"=",""))) -> sample office 05 | EA6: =IF(CW6="","",IFERROR(IF(LEFT(LOWER(TRIM(INDEX(Clay_Offices!$A$2:$FZ$601,CW6,Sync!$C$19)&"")),4)="grp-",SUBSTITUTE(SUBSTITUTE(SUBSTITUTE(SUBSTITUTE(SUBSTITUTE(SUBSTITUTE(LOWER(TRIM(INDEX(Clay_Offices!$A$2:$FZ$601,CW6,Sync!$C$19)&"")),"~",""),"*",""),"?",""),"<",""),">",""),"=",""),""),"")) | EB6: =IF(EA6<>"",DZ6,"") | EC6: =IF(BC6=1,AZ6,"") -> sample office 05 | ED6: =IF(TRIM($A6)="","",IFERROR(INDEX($A$2:$A$201,MATCH(AZ6,$EC$2:$EC$201,0))&"",$A6&"")) -> SAMPLE-O-005 | EE6: =IF(BB6=1,IF(COUNTIFS($A$2:$A$201,$A6,$BB$2:$BB$201,1,$H$2:$H$201,"<"&H6)+COUNTIFS($A$2:$A$201,$A6,$BB$2:$BB$201,1,$H$2:$H$201,H6,$BA$2:$BA$201,"<"&BA6)=0,1,0),0) -> 1 | EF6: =IF(BC6=1,IF(COUNTIFS($AZ$2:$AZ$201,AZ6,$EE$2:$EE$201,1)>1,1,0),0) -> 0 | EG6: =IF(AND(CQ6=1),IF(COUNTIFS($AZ$2:$AZ$201,AZ6,$CQ$2:$CQ$201,1,$H$2:$H$201,">"&H6)+COUNTIFS($AZ$2:$AZ$201,AZ6,$CQ$2:$CQ$201,1,$H$2:$H$201,H6,$BA$2:$BA$201,">"&BA6)=0,1,0),0) -> 1 | EH6: =IF(BB6=1,IF(COUNTIFS($AZ$2:$AZ$201,AZ6,$EG$2:$EG$201,1)=0,"",SUMIFS($O$2:$O$201,$AZ$2:$AZ$201,AZ6,$EG$2:$EG$201,1)),"") -> 150 | EI6: =IF(AND(ISNUMBER(EH6),OR(N(EH6)<Config!$B$31,N(EH6)>Config!$B$33)),1,0) -> 0 | EJ6: =IF(AND(ISNUMBER(EH6),N(EH6)>=Config!$B$31,N(EH6)<Config!$B$32),1,0) -> 0 | EK6: =IF(AND(BF6=1,INT(N(H6))<=Config!$B$6,DH6=1,EI6=1),1,0) -> 0 | EL6: =IF(AND(BF6=1,INT(N(H6))<=Config!$B$7,DI6=1,EI6=1),1,0) -> 0 | EM6: =IF(AND(BF6=1,INT(N(H6))<=Config!$B$8,DJ6=1,EI6=1),1,0) -> 0 | EN6: =IF(AND(BF6=1,INT(N(H6))<=Config!$B$5,DK6=1,EI6=1),1,0) -> 0 | EO6: =IF(AND(DL6=1,EJ6=1),1,0) -> 0 | EP6: =IF(AND(DM6=1,EJ6=1),1,0) -> 0 | EQ6: =IF(AND(DN6=1,EJ6=1),1,0) -> 0 | ER6: =IF(AND(DO6=1,EJ6=1),1,0) -> 0
A7: SAMPLE-O-006 | B7: SAMPLE Office 06 | D7: SAMPLE Contact O06 | E7: Workplace Experience Manager | F7: SAMPLE Clay offices table | G7: walk-in | H7: 46330 | I7: in-person | J7: SAMPLE: pantry answer 06 | K7: SAMPLE snack service | L7: Y | M7: 300 | N7: SAMPLE: about $300 a month | O7: 55 | P7: SAMPLE: around 55 on a Tuesday | Q7: N | R7: SAMPLE: brands email us, we ignore most | S7: SAMPLE: allergen info and no work for me | T7: SAMPLE: anything with nuts | U7: Y | V7: SAMPLE: a photo is fine | W7: Y | X7: SAMPLE: fifty dollars, maybe | Y7: 50 | Z7: 50 | AA7: 0 | AC7: Y | AD7: SAMPLE Owner O06 | AE7: Office Manager | AF7: Y | AH7: SAMPLE Tue 8-10am | AI7: walk-up | AJ7: no | AL7: chocolate-candy;sparkling-soda | AM7: SAMPLE: no jerky | AN7: allergy_policy | AQ7: SAMPLE: allergy_policy (office 06) | AR7: Y | AS7: asked_when | AT7: Y | AV7: 11 | AW7: Y | AY7: =IF(TRIM($A7)="","",IF(AND(LEFT($A7,6)="SAMPLE",Config!$B$19<>"Y"),"",IF(NOT(ISNUMBER(H7)),"call_date is blank or not a date",IF(Sync!$C$5="","Clay paste is empty or has no row_id column: paste the Clay export on Clay_Offices",IF(CW7="","row_id not found in the Clay paste: add the Clay row or fix the row_id",IF(AND(ISNUMBER(CY7),CY7>=1,CY7<=5),"Clay status is "&CX7&": set call_done or later",IF(AND(BD7=1,CZ7<>BZ7),"Clay yes_in_principle should be "&BZ7,IF(AND(BD7=1,DA7<>H7),"Clay call_date should be "&TEXT(H7,"yyyy-mm-dd"),"")))))))) -> Clay yes_in_principle should be Y | AZ7: =IF(TRIM($A7)="","",IF(TRIM(C7)<>"",SUBSTITUTE(SUBSTITUTE(SUBSTITUTE(SUBSTITUTE(SUBSTITUTE(SUBSTITUTE(LOWER(TRIM(C7)),"~",""),"*",""),"?",""),"<",""),">",""),"=",""),IF(EA7<>"",EA7,IFERROR(INDEX($EA$2:$EA$201,MATCH(DZ7,$EB$2:$EB$201,0)),DZ7)))) -> sample office 06 | BA7: =ROW() -> 7 | BB7: =IF(AND(TRIM($A7)<>"",ISNUMBER(H7)),IF(AND(LEFT($A7,6)="SAMPLE",Config!$B$19<>"Y"),0,1),0) -> 1 | BC7: =IF(BB7=1,IF(COUNTIFS($AZ$2:$AZ$201,AZ7,$BB$2:$BB$201,1,$H$2:$H$201,"<"&H7)+COUNTIFS($AZ$2:$AZ$201,AZ7,$BB$2:$BB$201,1,$H$2:$H$201,H7,$BA$2:$BA$201,"<"&BA7)=0,1,0),0) -> 1 | BD7: =IF(BB7=1,IF(COUNTIFS($A$2:$A$201,$A7,$BB$2:$BB$201,1,$H$2:$H$201,">"&H7)+COUNTIFS($A$2:$A$201,$A7,$BB$2:$BB$201,1,$H$2:$H$201,H7,$BA$2:$BA$201,">"&BA7)=0,1,0),0) -> 1 | BE7: =IF(AND(BB7=1,AR7="Y",AC7="Y",TRIM(AH7)<>""),1,0) -> 1 | BF7: =IF(BE7=1,IF(COUNTIFS($AZ$2:$AZ$201,AZ7,$BE$2:$BE$201,1,$H$2:$H$201,"<"&H7)+COUNTIFS($AZ$2:$AZ$201,AZ7,$BE$2:$BE$201,1,$H$2:$H$201,H7,$BA$2:$BA$201,"<"&BA7)=0,1,0),0) -> 1 | BG7: =IF(AND(BB7=1,AR7="Y",BE7=0),1,0) -> 0 | BH7: =IF(AND(BB7=1,ISNUMBER(Y7)),1,0) -> 1 | BI7: =IF(BH7=1,IF(COUNTIFS($AZ$2:$AZ$201,AZ7,$BH$2:$BH$201,1,$H$2:$H$201,"<"&H7)+COUNTIFS($AZ$2:$AZ$201,AZ7,$BH$2:$BH$201,1,$H$2:$H$201,H7,$BA$2:$BA$201,"<"&BA7)=0,1,0),0) -> 1 | BJ7: =IF(AND(BI7=1,INT(N(H7))<=Config!$B$6),Y7,"") | BK7: =IF(AND(BI7=1,INT(N(H7))<=Config!$B$7),Y7,"") -> 50 | BL7: =IF(AND(BI7=1,INT(N(H7))<=Config!$B$8),Y7,"") -> 50 | BM7: =IF(AND(BI7=1,INT(N(H7))<=Config!$B$5),Y7,"") -> 50 | BN7: =IF(CD7=1,IF(COUNTIFS($AZ$2:$AZ$201,AZ7,$CD$2:$CD$201,1,$H$2:$H$201,"<"&H7)+COUNTIFS($AZ$2:$AZ$201,AZ7,$CD$2:$CD$201,1,$H$2:$H$201,H7,$BA$2:$BA$201,"<"&BA7)=0,1,0),0) -> 0 | BO7: =IF(AND(BB7=1,ISNUMBER(M7)),1,0) -> 1 | BP7: =IF(BO7=1,IF(COUNTIFS($AZ$2:$AZ$201,AZ7,$BO$2:$BO$201,1,$H$2:$H$201,"<"&H7)+COUNTIFS($AZ$2:$AZ$201,AZ7,$BO$2:$BO$201,1,$H$2:$H$201,H7,$BA$2:$BA$201,"<"&BA7)=0,1,0),0) -> 1 | BQ7: =IF(AND(BP7=1,INT(N(H7))<=Config!$B$5),M7,"") -> 300 | BR7: =IF(AND(BB7=1,OR(TRIM(X7)<>"",ISNUMBER(Y7))),1,0) -> 1 | BS7: =IF(BR7=1,IF(COUNTIFS($AZ$2:$AZ$201,AZ7,$BR$2:$BR$201,1,$H$2:$H$201,"<"&H7)+COUNTIFS($AZ$2:$AZ$201,AZ7,$BR$2:$BR$201,1,$H$2:$H$201,H7,$BA$2:$BA$201,"<"&BA7)=0,1,0),0) -> 1 | BT7: =IF(BS7=1,AZ7,"") -> sample office 06 | BU7: =IF(AND(BB7=1,W7="Y",TRIM(X7)=""),1,0) -> 0 | BV7: =IF(BB7=1,AN7&"","") -> allergy_policy | BW7: =IF(BB7=1,AO7&"","") | BX7: =IF(BB7=1,AP7&"","") | BY7: =IF(AND(BB7=1,ISNUMBER(AV7),INT(N(H7))<=Config!$B$5),AV7,"") -> 11 | BZ7: =IF(BB7=1,IF(COUNTIFS($A$2:$A$201,$A7,$DC$2:$DC$201,1,$AR$2:$AR$201,"Y")>0,"Y","N"),"") -> Y | CA7: =IF(AND(BB7=1,AR7="maybe"),1,0) -> 0 | CB7: =IF(CA7=1,IF(COUNTIFS($AZ$2:$AZ$201,AZ7,$CA$2:$CA$201,1,$H$2:$H$201,"<"&H7)+COUNTIFS($AZ$2:$AZ$201,AZ7,$CA$2:$CA$201,1,$H$2:$H$201,H7,$BA$2:$BA$201,"<"&BA7)=0,1,0),0) -> 0 | CC7: =IF(AND(BB7=1,AR7="Y"),IF(COUNTIFS($AZ$2:$AZ$201,AZ7,$AR$2:$AR$201,"Y",$BB$2:$BB$201,1,$H$2:$H$201,"<"&H7)+COUNTIFS($AZ$2:$AZ$201,AZ7,$AR$2:$AR$201,"Y",$BB$2:$BB$201,1,$H$2:$H$201,H7,$BA$2:$BA$201,"<"&BA7)=0,1,0),0) -> 1 | CD7: =IF(AND(BH7=1,N(Y7)>=Config!$B$15),1,0) -> 0 | CE7: =IF(AND(BB7=1,AT7="Y"),1,0) -> 1 | CF7: =IF(CE7=1,IF(COUNTIFS($AZ$2:$AZ$201,AZ7,$CE$2:$CE$201,1,$H$2:$H$201,"<"&H7)+COUNTIFS($AZ$2:$AZ$201,AZ7,$CE$2:$CE$201,1,$H$2:$H$201,H7,$BA$2:$BA$201,"<"&BA7)=0,1,0),0) -> 1 | CG7: =IF(AND(BB7=1,G7="warm-intro"),1,0) -> 0 | CH7: =IF(CG7=1,IF(COUNTIFS($AZ$2:$AZ$201,AZ7,$CG$2:$CG$201,1,$H$2:$H$201,"<"&H7)+COUNTIFS($AZ$2:$AZ$201,AZ7,$CG$2:$CG$201,1,$H$2:$H$201,H7,$BA$2:$BA$201,"<"&BA7)=0,1,0),0) -> 0 | CI7: =IF(AND(BB7=1,Q7="Y"),1,0) -> 0 | CJ7: =IF(CI7=1,IF(COUNTIFS($AZ$2:$AZ$201,AZ7,$CI$2:$CI$201,1,$H$2:$H$201,"<"&H7)+COUNTIFS($AZ$2:$AZ$201,AZ7,$CI$2:$CI$201,1,$H$2:$H$201,H7,$BA$2:$BA$201,"<"&BA7)=0,1,0),0) -> 0 | CK7: =IF(AND(BB7=1,AF7="Y"),1,0) -> 1 | CL7: =IF(CK7=1,IF(COUNTIFS($AZ$2:$AZ$201,AZ7,$CK$2:$CK$201,1,$H$2:$H$201,"<"&H7)+COUNTIFS($AZ$2:$AZ$201,AZ7,$CK$2:$CK$201,1,$H$2:$H$201,H7,$BA$2:$BA$201,"<"&BA7)=0,1,0),0) -> 1 | CM7: =IF(AND(BB7=1,U7="Y"),1,0) -> 1 | CN7: =IF(CM7=1,IF(COUNTIFS($AZ$2:$AZ$201,AZ7,$CM$2:$CM$201,1,$H$2:$H$201,"<"&H7)+COUNTIFS($AZ$2:$AZ$201,AZ7,$CM$2:$CM$201,1,$H$2:$H$201,H7,$BA$2:$BA$201,"<"&BA7)=0,1,0),0) -> 1 | CO7: =IF(AND(BB7=1,L7="Y"),1,0) -> 1 | CP7: =IF(CO7=1,IF(COUNTIFS($AZ$2:$AZ$201,AZ7,$CO$2:$CO$201,1,$H$2:$H$201,"<"&H7)+COUNTIFS($AZ$2:$AZ$201,AZ7,$CO$2:$CO$201,1,$H$2:$H$201,H7,$BA$2:$BA$201,"<"&BA7)=0,1,0),0) -> 1 | CQ7: =IF(AND(BB7=1,ISNUMBER(O7)),1,0) -> 1 | CR7: =IF(CQ7=1,IF(COUNTIFS($AZ$2:$AZ$201,AZ7,$CQ$2:$CQ$201,1,$H$2:$H$201,"<"&H7)+COUNTIFS($AZ$2:$AZ$201,AZ7,$CQ$2:$CQ$201,1,$H$2:$H$201,H7,$BA$2:$BA$201,"<"&BA7)=0,1,0),0) -> 1 | CS7: =IF(AND(CR7=1,INT(N(H7))<=Config!$B$5),O7,"") -> 55 | CT7: =IF(AND(BB7=1,INT(N(H7))<=Config!$B$5),AG7&"","") | CU7: =IF(AND(BB7=1,AU7="Y"),1,0) -> 0 | CV7: =IF(CU7=1,IF(COUNTIFS($AZ$2:$AZ$201,AZ7,$CU$2:$CU$201,1,$H$2:$H$201,"<"&H7)+COUNTIFS($AZ$2:$AZ$201,AZ7,$CU$2:$CU$201,1,$H$2:$H$201,H7,$BA$2:$BA$201,"<"&BA7)=0,1,0),0) -> 0 | CW7: =IF(BB7=1,IFERROR(MATCH($A7,INDEX(Clay_Offices!$A$2:$FZ$601,0,Sync!$C$5),0),""),"") -> 6 | CX7: =IF(CW7="","",IFERROR(INDEX(Clay_Offices!$A$2:$FZ$601,CW7,Sync!$C$7)&"","")) -> signed | CY7: =IF(CX7="","",IFERROR(INDEX(Lists!$K$2:$K$15,MATCH(CX7,Lists!$J$2:$J$15,0)),"")) -> 9 | CZ7: =IF(CW7="","",IFERROR(INDEX(Clay_Offices!$A$2:$FZ$601,CW7,Sync!$C$17)&"","")) | DA7: =IF(CW7="","",IFERROR(N(INDEX(Clay_Offices!$A$2:$FZ$601,CW7,Sync!$C$16)),0)) -> 46330 | DB7: =IF(AND(BB7=1,OR(AR7="Y",AR7="N",AR7="maybe")),1,0) -> 1 | DC7: =IF(AND(DB7=1),IF(COUNTIFS($A$2:$A$201,$A7,$DB$2:$DB$201,1,$H$2:$H$201,">"&H7)+COUNTIFS($A$2:$A$201,$A7,$DB$2:$DB$201,1,$H$2:$H$201,H7,$BA$2:$BA$201,">"&BA7)=0,1,0),0) -> 1 | DD7: =IF(AND(DB7=1,INT(N(H7))<=Config!$B$6),IF(COUNTIFS($AZ$2:$AZ$201,AZ7,$DB$2:$DB$201,1,$H$2:$H$201,">"&H7,$H$2:$H$201,"<"&(Config!$B$6+1))+COUNTIFS($AZ$2:$AZ$201,AZ7,$DB$2:$DB$201,1,$H$2:$H$201,H7,$BA$2:$BA$201,">"&BA7)=0,1,0),0) -> 0 | DE7: =IF(AND(DB7=1,INT(N(H7))<=Config!$B$7),IF(COUNTIFS($AZ$2:$AZ$201,AZ7,$DB$2:$DB$201,1,$H$2:$H$201,">"&H7,$H$2:$H$201,"<"&(Config!$B$7+1))+COUNTIFS($AZ$2:$AZ$201,AZ7,$DB$2:$DB$201,1,$H$2:$H$201,H7,$BA$2:$BA$201,">"&BA7)=0,1,0),0) -> 1 | DF7: =IF(AND(DB7=1,INT(N(H7))<=Config!$B$8),IF(COUNTIFS($AZ$2:$AZ$201,AZ7,$DB$2:$DB$201,1,$H$2:$H$201,">"&H7,$H$2:$H$201,"<"&(Config!$B$8+1))+COUNTIFS($AZ$2:$AZ$201,AZ7,$DB$2:$DB$201,1,$H$2:$H$201,H7,$BA$2:$BA$201,">"&BA7)=0,1,0),0) -> 1 | DG7: =IF(AND(DB7=1,INT(N(H7))<=Config!$B$5),IF(COUNTIFS($AZ$2:$AZ$201,AZ7,$DB$2:$DB$201,1,$H$2:$H$201,">"&H7,$H$2:$H$201,"<"&(Config!$B$5+1))+COUNTIFS($AZ$2:$AZ$201,AZ7,$DB$2:$DB$201,1,$H$2:$H$201,H7,$BA$2:$BA$201,">"&BA7)=0,1,0),0) -> 1 | DH7: =IF(BB7=1,IF(COUNTIFS($AZ$2:$AZ$201,AZ7,$DD$2:$DD$201,1,$AR$2:$AR$201,"Y")>0,1,0),0) -> 0 | DI7: =IF(BB7=1,IF(COUNTIFS($AZ$2:$AZ$201,AZ7,$DE$2:$DE$201,1,$AR$2:$AR$201,"Y")>0,1,0),0) -> 1 | DJ7: =IF(BB7=1,IF(COUNTIFS($AZ$2:$AZ$201,AZ7,$DF$2:$DF$201,1,$AR$2:$AR$201,"Y")>0,1,0),0) -> 1 | DK7: =IF(BB7=1,IF(COUNTIFS($AZ$2:$AZ$201,AZ7,$DG$2:$DG$201,1,$AR$2:$AR$201,"Y")>0,1,0),0) -> 1 | DL7: =IF(AND(BF7=1,INT(N(H7))<=Config!$B$6,DH7=1,EI7=0),1,0) -> 0 | DM7: =IF(AND(BF7=1,INT(N(H7))<=Config!$B$7,DI7=1,EI7=0),1,0) -> 1 | DN7: =IF(AND(BF7=1,INT(N(H7))<=Config!$B$8,DJ7=1,EI7=0),1,0) -> 1 | DO7: =IF(AND(BF7=1,INT(N(H7))<=Config!$B$5,DK7=1,EI7=0),1,0) -> 1 | DP7: =IF(AND(CC7=1,INT(N(H7))<=Config!$B$6,DH7=1,EI7=0),1,0) -> 0 | DQ7: =IF(AND(CC7=1,INT(N(H7))<=Config!$B$7,DI7=1,EI7=0),1,0) -> 1 | DR7: =IF(AND(CC7=1,INT(N(H7))<=Config!$B$8,DJ7=1,EI7=0),1,0) -> 1 | DS7: =IF(AND(CC7=1,INT(N(H7))<=Config!$B$5,DK7=1,EI7=0),1,0) -> 1 | DT7: =IF(AND(CC7=1,INT(N(H7))<=Config!$B$6,DH7=0),1,0) -> 0 | DU7: =IF(AND(CC7=1,INT(N(H7))<=Config!$B$7,DI7=0),1,0) -> 0 | DV7: =IF(AND(CC7=1,INT(N(H7))<=Config!$B$8,DJ7=0),1,0) -> 0 | DW7: =IF(AND(CC7=1,INT(N(H7))<=Config!$B$5,DK7=0),1,0) -> 0 | DX7: =IF(TRIM($A7)="",0,ISTEXT(M7)+ISTEXT(O7)+ISTEXT(Y7)+ISTEXT(Z7)+ISTEXT(AA7)+ISTEXT(AV7)) -> 0 | DY7: =IF(BB7=1,IF(H7<>INT(H7),1,0),0) -> 0 | DZ7: =IF(TRIM($A7)="","",IF(TRIM(B7)="",SUBSTITUTE(SUBSTITUTE(SUBSTITUTE(SUBSTITUTE(SUBSTITUTE(SUBSTITUTE(LOWER(TRIM($A7)),"~",""),"*",""),"?",""),"<",""),">",""),"=",""),SUBSTITUTE(SUBSTITUTE(SUBSTITUTE(SUBSTITUTE(SUBSTITUTE(SUBSTITUTE(LOWER(TRIM(B7)),"~",""),"*",""),"?",""),"<",""),">",""),"=",""))) -> sample office 06 | EA7: =IF(CW7="","",IFERROR(IF(LEFT(LOWER(TRIM(INDEX(Clay_Offices!$A$2:$FZ$601,CW7,Sync!$C$19)&"")),4)="grp-",SUBSTITUTE(SUBSTITUTE(SUBSTITUTE(SUBSTITUTE(SUBSTITUTE(SUBSTITUTE(LOWER(TRIM(INDEX(Clay_Offices!$A$2:$FZ$601,CW7,Sync!$C$19)&"")),"~",""),"*",""),"?",""),"<",""),">",""),"=",""),""),"")) | EB7: =IF(EA7<>"",DZ7,"") | EC7: =IF(BC7=1,AZ7,"") -> sample office 06 | ED7: =IF(TRIM($A7)="","",IFERROR(INDEX($A$2:$A$201,MATCH(AZ7,$EC$2:$EC$201,0))&"",$A7&"")) -> SAMPLE-O-006 | EE7: =IF(BB7=1,IF(COUNTIFS($A$2:$A$201,$A7,$BB$2:$BB$201,1,$H$2:$H$201,"<"&H7)+COUNTIFS($A$2:$A$201,$A7,$BB$2:$BB$201,1,$H$2:$H$201,H7,$BA$2:$BA$201,"<"&BA7)=0,1,0),0) -> 1 | EF7: =IF(BC7=1,IF(COUNTIFS($AZ$2:$AZ$201,AZ7,$EE$2:$EE$201,1)>1,1,0),0) -> 0 | EG7: =IF(AND(CQ7=1),IF(COUNTIFS($AZ$2:$AZ$201,AZ7,$CQ$2:$CQ$201,1,$H$2:$H$201,">"&H7)+COUNTIFS($AZ$2:$AZ$201,AZ7,$CQ$2:$CQ$201,1,$H$2:$H$201,H7,$BA$2:$BA$201,">"&BA7)=0,1,0),0) -> 1 | EH7: =IF(BB7=1,IF(COUNTIFS($AZ$2:$AZ$201,AZ7,$EG$2:$EG$201,1)=0,"",SUMIFS($O$2:$O$201,$AZ$2:$AZ$201,AZ7,$EG$2:$EG$201,1)),"") -> 55 | EI7: =IF(AND(ISNUMBER(EH7),OR(N(EH7)<Config!$B$31,N(EH7)>Config!$B$33)),1,0) -> 0 | EJ7: =IF(AND(ISNUMBER(EH7),N(EH7)>=Config!$B$31,N(EH7)<Config!$B$32),1,0) -> 0 | EK7: =IF(AND(BF7=1,INT(N(H7))<=Config!$B$6,DH7=1,EI7=1),1,0) -> 0 | EL7: =IF(AND(BF7=1,INT(N(H7))<=Config!$B$7,DI7=1,EI7=1),1,0) -> 0 | EM7: =IF(AND(BF7=1,INT(N(H7))<=Config!$B$8,DJ7=1,EI7=1),1,0) -> 0 | EN7: =IF(AND(BF7=1,INT(N(H7))<=Config!$B$5,DK7=1,EI7=1),1,0) -> 0 | EO7: =IF(AND(DL7=1,EJ7=1),1,0) -> 0 | EP7: =IF(AND(DM7=1,EJ7=1),1,0) -> 0 | EQ7: =IF(AND(DN7=1,EJ7=1),1,0) -> 0 | ER7: =IF(AND(DO7=1,EJ7=1),1,0) -> 0
