Workbook

Sheet Start
A1: =Config!$B$3&" · conversation tracker"
A2: What this is: the conversation and notes log for discovery and selling, one row per conversation, keyed by the Clay row_id.
A3: It is not a status store. Status, touches, replies, next actions and do-not-contact live in the Clay tables only (CONTRACTS 6.2).
A5: After every call (ten minutes, calls/post-call-note-template.md)
A6: 1. Type one row on Office_Log or Brand_Log: verbatims first, then numbers and codes.
A7: 2. Write back to the Clay row: call_date, status (call_done or yes_in_principle), yes_in_principle, call_notes ('see tracker <date>'), next_action, next_action_date.
A8: 3. Set clay_updated = Y and note_minutes.
A10: Every Friday (15 minutes)
A11: 1. Export the Clay offices table (all columns) and paste it on Clay_Offices at A1. Same for brands on Clay_Brands. Type both export dates on Config.
A12: 2. Open Scorecard. Fix every FIX under Data checks (the Sync tab and the red calc_sync_issue cells show where).
A13: 3. Read the Gate 0 block, the medians, the top objections and the reply rates. If a reply rate says UNDER 20%, run sending guide section 6.
A14: 4. Download pipeline_log as CSV (File > Download > CSV, this tab only) to desk-drop-outreach/exports/pipeline_log.csv and paste it into the financial model's Pipeline tab.
A15: 5. When an office signs or a brand pays: add the row on signed_offices or paid_brands, download that tab as CSV to desk-drop-outreach/handoff/.
... A26: Dates as YYYY-MM-DD. Money as plain numbers. Rows whose row_id starts with SAMPLE are ignored while include_sample = N.

Sheet Scorecard
A1: =IF((COUNTIF(Office_Log!$A$2:$A$201,"SAMPLE*")+COUNTIF(Brand_Log!$A$2:$A$201,"SAMPLE*")+COUNTIF(signed_offices!$W$2:$W$51,"SAMPLE*")+COUNTIF(paid_brands!$AC$2:$AC$51,"SAMPLE*")+COUNTIF(later_events!$C$2:$C$101,"SAMPLE*")+IFERROR(COUNTIF(INDEX(Clay_Offices!$A$2:$FZ$601,0,Sync!$C$5),"SAMPLE*"),0)+IFERROR(COUNTIF(INDEX(Clay_Brands!$A$2:$FZ$601,0,Sync!$D$5),"SAMPLE*"),0))>0,"SAMPLE: this file holds "&(COUNTIF(Office_Log!$A$2:$A$201,"SAMPLE*")+COUNTIF(Brand_Log!$A$2:$A$201,"SAMPLE*")+COUNTIF(signed_offices!$W$2:$W$51,"SAMPLE*")+COUNTIF(paid_brands!$AC$2:$AC$51,"SAMPLE*")+COUNTIF(later_events!$C$2:$C$101,"SAMPLE*")+IFERROR(COUNTIF(INDEX(Clay_Offices!$A$2:$FZ$601,0,Sync!$C$5),"SAMPLE*"),0)+IFERROR(COUNTIF(INDEX(Clay_Brands!$A$2:$FZ$601,0,Sync!$D$5),"SAMPLE*"),0))&" SAMPLE rows. Illustrative placeholders, not results. include_sample = "&Config!$B$19&IF(Config!$B$19="Y"," (SAMPLE rows are counted)"," (SAMPLE rows are ignored)"),"")
A2: =Config!$B$3&" · Friday scorecard"
A3: ="As of "&TEXT(Config!$B$5,"ddd yyyy-mm-dd")&". Gate 0 is "&TEXT(Config!$B$8,"ddd yyyy-mm-dd")&" (derived, founder to confirm). Counts are distinct offices or brands, by call_date."
A5: Measure | B5: Fri wk 1 | C5: Fri wk 2 | D5: Gate 0 | E5: As of | F5: Target | G5: How it is counted
A6: Cut-off date | B6: =Config!$B$6 | C6: =Config!$B$7 | D6: =Config!$B$8 | E6: =Config!$B$5
A7: Offices (Gate 0: at least 5 of 15 say yes in principle AND name a pantry owner AND a receiving window)
A8: Office conversations held | B8: =COUNTIFS(Office_Log!$AV$2:$AV$201,1,Office_Log!$G$2:$G$201,"<="&B$6) | C8: =COUNTIFS(Office_Log!$AV$2:$AV$201,1,Office_Log!$G$2:$G$201,"<="&C$6) | D8: =COUNTIFS(Office_Log!$AV$2:$AV$201,1,Office_Log!$G$2:$G$201,"<="&D$6) | E8: =COUNTIFS(Office_Log!$AV$2:$AV$201,1,Office_Log!$G$2:$G$201,"<="&E$6) | F8: =Config!$B$10 | G8: Distinct row_ids in Office_Log with a call_date on or before the cut-off.
A9: Yes in principle, pantry owner named, receiving window named | B9: =COUNTIFS(Office_Log!$AY$2:$AY$201,1,Office_Log!$G$2:$G$201,"<="&B$6) | C9: =COUNTIFS(Office_Log!$AY$2:$AY$201,1,Office_Log!$G$2:$G$201,"<="&C$6) | D9: =COUNTIFS(Office_Log!$AY$2:$AY$201,1,Office_Log!$G$2:$G$201,"<="&D$6) | E9: =COUNTIFS(Office_Log!$AY$2:$AY$201,1,Office_Log!$G$2:$G$201,"<="&E$6) | F9: =Config!$B$11 | G9: The Gate 0 count. One per office, from its first qualifying conversation.
A10: Gate 0, office side | B10: =IF(B9>=Config!$B$11,"PASS",IF(B$6<Config!$B$8,"not yet","FAIL")) | C10: =IF(C9>=Config!$B$11,"PASS",IF(C$6<Config!$B$8,"not yet","FAIL")) | D10: =IF(D9>=Config!$B$11,"PASS",IF(D$6<Config!$B$8,"not yet","FAIL")) | E10: =IF(E9>=Config!$B$11,"PASS",IF(E$6<Config!$B$8,"not yet","FAIL")) | G10: PASS once the count reaches the target. Before Gate 0 a shortfall reads 'not yet'; on or after Gate 0 it reads FAIL.
A11: Yes in principle, any (owner or window may be missing) | B11: =COUNTIFS(Office_Log!$BV$2:$BV$201,1,Office_Log!$G$2:$G$201,"<="&B$6) | C11: =COUNTIFS(Office_Log!$BV$2:$BV$201,1,Office_Log!$G$2:$G$201,"<="&C$6) | D11: =COUNTIFS(Office_Log!$BV$2:$BV$201,1,Office_Log!$G$2:$G$201,"<="&D$6) | E11: =COUNTIFS(Office_Log!$BV$2:$BV$201,1,Office_Log!$G$2:$G$201,"<="&E$6) | G11: Offices that said Y at least once. The gap to the row above is follow-up work: get the owner and the window.
A12: Said maybe at least once (someone else must agree) | B12: =COUNTIFS(Office_Log!$BU$2:$BU$201,1,Office_Log!$G$2:$G$201,"<="&B$6) | C12: =COUNTIFS(Office_Log!$BU$2:$BU$201,1,Office_Log!$G$2:$G$201,"<="&C$6) | D12: =COUNTIFS(Office_Log!$BU$2:$BU$201,1,Office_Log!$G$2:$G$201,"<="&D$6) | E12: =COUNTIFS(Office_Log!$BU$2:$BU$201,1,Office_Log!$G$2:$G$201,"<="&E$6) | G12: Plan Phase 1: 'I need to ask facilities and HR' is a maybe, not a yes.
A13: Median budget-probe answer, USD a month | B13: =IF(COUNT(Office_Log!$BC$2:$BC$201)=0,"none yet",MEDIAN(Office_Log!$BC$2:$BC$201)) | C13: =IF(COUNT(Office_Log!$BD$2:$BD$201)=0,"none yet",MEDIAN(Office_Log!$BD$2:$BD$201)) | D13: =IF(COUNT(Office_Log!$BE$2:$BE$201)=0,"none yet",MEDIAN(Office_Log!$BE$2:$BE$201)) | E13: =IF(COUNT(Office_Log!$BF$2:$BF$201)=0,"none yet",MEDIAN(Office_Log!$BF$2:$BF$201)) | G13: First numeric answer per office; a range counts at its low end; 'no budget' counts as 0; no number is left out.
A14: Offices that gave a number (0 included) | B14: =COUNT(Office_Log!$BC$2:$BC$201) | C14: =COUNT(Office_Log!$BD$2:$BD$201) | D14: =COUNT(Office_Log!$BE$2:$BE$201) | E14: =COUNT(Office_Log!$BF$2:$BF$201) | G14: The n behind the median.
A15: Of those, said no budget (0) | B15: =COUNTIF(Office_Log!$BC$2:$BC$201,0) | C15: =COUNTIF(Office_Log!$BD$2:$BD$201,0) | D15: =COUNTIF(Office_Log!$BE$2:$BE$201,0) | E15: =COUNTIF(Office_Log!$BF$2:$BF$201,0) | G15: Counted inside the median.
A16: Offices naming $100 a month or more (decision-rule input), as of | E16: =COUNTIFS(Office_Log!$BG$2:$BG$201,1,Office_Log!$G$2:$G$201,"<="&E$6) | G16: Plan decision rule: office-paid tier is tested if at least five offices named $100 a month or more.
A17: Median monthly pantry spend today, USD, as of | E17: =IF(COUNT(Office_Log!$BJ$2:$BJ$201)=0,"none yet",MEDIAN(Office_Log!$BJ$2:$BJ$201)) | F17: =COUNT(Office_Log!$BJ$2:$BJ$201) | G17: First number per office, from Q1. Context for the budget probe.
A19: Brands (Gate 0: at least 3 of 15 say they would pay $500 or more AND the speaker controls the budget)
A20: Brand conversations held | B20: =COUNTIFS(Brand_Log!$AO$2:$AO$201,1,Brand_Log!$G$2:$G$201,"<="&B$6) | C20: =COUNTIFS(Brand_Log!$AO$2:$AO$201,1,Brand_Log!$G$2:$G$201,"<="&C$6) | D20: =COUNTIFS(Brand_Log!$AO$2:$AO$201,1,Brand_Log!$G$2:$G$201,"<="&D$6) | E20: =COUNTIFS(Brand_Log!$AO$2:$AO$201,1,Brand_Log!$G$2:$G$201,"<="&E$6) | F20: =Config!$B$12 | G20: Distinct row_ids in Brand_Log with a call_date on or before the cut-off.
A21: Would pay $500 or more and controls the budget | B21: =COUNTIFS(Brand_Log!$AR$2:$AR$201,1,Brand_Log!$G$2:$G$201,"<="&B$6) | C21: =COUNTIFS(Brand_Log!$AR$2:$AR$201,1,Brand_Log!$G$2:$G$201,"<="&C$6) | D21: =COUNTIFS(Brand_Log!$AR$2:$AR$201,1,Brand_Log!$G$2:$G$201,"<="&D$6) | E21: =COUNTIFS(Brand_Log!$AR$2:$AR$201,1,Brand_Log!$G$2:$G$201,"<="&E$6) | F21: =Config!$B$13 | G21: The Gate 0 count: the higher of the before and after numbers is $500 or more, and controls_budget = Y. Same rule as the financial model.
A22: Gate 0, brand side | B22: =IF(B21>=Config!$B$13,"PASS",IF(B$6<Config!$B$8,"not yet","FAIL")) | C22: =IF(C21>=Config!$B$13,"PASS",IF(C$6<Config!$B$8,"not yet","FAIL")) | D22: =IF(D21>=Config!$B$13,"PASS",IF(D$6<Config!$B$8,"not yet","FAIL")) | E22: =IF(E21>=Config!$B$13,"PASS",IF(E$6<Config!$B$8,"not yet","FAIL")) | G22: PASS once the count reaches the target. Before Gate 0 a shortfall reads 'not yet'; on or after Gate 0 it reads FAIL.
A23: Strict read: named $500 or more BEFORE hearing $1,500, and controls the budget | B23: =COUNTIFS(Brand_Log!$AT$2:$AT$201,1,Brand_Log!$G$2:$G$201,"<="&B$6) | C23: =COUNTIFS(Brand_Log!$AT$2:$AT$201,1,Brand_Log!$G$2:$G$201,"<="&C$6) | D23: =COUNTIFS(Brand_Log!$AT$2:$AT$201,1,Brand_Log!$G$2:$G$201,"<="&D$6) | E23: =COUNTIFS(Brand_Log!$AT$2:$AT$201,1,Brand_Log!$G$2:$G$201,"<="&E$6) | G23: Shown so an anchored answer is not mistaken for an unprompted one.
A24: Said $500 or more but the speaker does not control the budget | B24: =COUNTIFS(Brand_Log!$AV$2:$AV$201,1,Brand_Log!$G$2:$G$201,"<="&B$6) | C24: =COUNTIFS(Brand_Log!$AV$2:$AV$201,1,Brand_Log!$G$2:$G$201,"<="&C$6) | D24: =COUNTIFS(Brand_Log!$AV$2:$AV$201,1,Brand_Log!$G$2:$G$201,"<="&D$6) | E24: =COUNTIFS(Brand_Log!$AV$2:$AV$201,1,Brand_Log!$G$2:$G$201,"<="&E$6) | G24: Not counted for Gate 0 from that conversation. Ask for a call with the budget owner.
A25: Median brand number before $1,500 was mentioned, USD per campaign | B25: =IF(COUNT(Brand_Log!$AY$2:$AY$201)=0,"none yet",MEDIAN(Brand_Log!$AY$2:$AY$201)) | C25: =IF(COUNT(Brand_Log!$AZ$2:$AZ$201)=0,"none yet",MEDIAN(Brand_Log!$AZ$2:$AZ$201)) | D25: =IF(COUNT(Brand_Log!$BA$2:$BA$201)=0,"none yet",MEDIAN(Brand_Log!$BA$2:$BA$201)) | E25: =IF(COUNT(Brand_Log!$BB$2:$BB$201)=0,"none yet",MEDIAN(Brand_Log!$BB$2:$BB$201)) | G25: First numeric before-answer per brand; 'nothing' counts as 0; no number is left out.
A26: Brands that named a number before $1,500 | B26: =COUNT(Brand_Log!$AY$2:$AY$201) | C26: =COUNT(Brand_Log!$AZ$2:$AZ$201) | D26: =COUNT(Brand_Log!$BA$2:$BA$201) | E26: =COUNT(Brand_Log!$BB$2:$BB$201) | G26: The n behind the median.
A27: Median brand number after hearing $1,500, USD per campaign | B27: =IF(COUNT(Brand_Log!$BE$2:$BE$201)=0,"none yet",MEDIAN(Brand_Log!$BE$2:$BE$201)) | C27: =IF(COUNT(Brand_Log!$BF$2:$BF$201)=0,"none yet",MEDIAN(Brand_Log!$BF$2:$BF$201)) | D27: =IF(COUNT(Brand_Log!$BG$2:$BG$201)=0,"none yet",MEDIAN(Brand_Log!$BG$2:$BG$201)) | E27: =IF(COUNT(Brand_Log!$BH$2:$BH$201)=0,"none yet",MEDIAN(Brand_Log!$BH$2:$BH$201)) | G27: First numeric after-answer per brand.
A28: Brands that answered after hearing $1,500 | B28: =COUNT(Brand_Log!$BE$2:$BE$201) | C28: =COUNT(Brand_Log!$BF$2:$BF$201) | D28: =COUNT(Brand_Log!$BG$2:$BG$201) | E28: =COUNT(Brand_Log!$BH$2:$BH$201) | G28: The n behind the median.
A29: Median quarterly sampling budget, USD (low end), as of | E29: =IF(COUNT(Brand_Log!$BK$2:$BK$201)=0,"none yet",MEDIAN(Brand_Log!$BK$2:$BK$201)) | F29: =COUNT(Brand_Log!$BK$2:$BK$201) | G29: From Q2. Context: a $600 or $1,500 campaign against what they spend now.
A31: Gate 0 overall
A32: Gate 0 result | B32: =IF(AND(B10="PASS",B22="PASS"),"PASS",IF(OR(B10="FAIL",B22="FAIL"),"FAIL","not yet")) | C32: =IF(AND(C10="PASS",C22="PASS"),"PASS",IF(OR(C10="FAIL",C22="FAIL"),"FAIL","not yet")) | D32: =IF(AND(D10="PASS",D22="PASS"),"PASS",IF(OR(D10="FAIL",D22="FAIL"),"FAIL","not yet")) | E32: =IF(AND(E10="PASS",E22="PASS"),"PASS",IF(OR(E10="FAIL",E22="FAIL"),"FAIL","not yet"))
A33: Sentence for the Gate 0 decision (as of) | B33: ="As of "&TEXT(E$6,"yyyy-mm-dd")&": "&E9&" of "&E8&" offices said yes with a pantry owner and a receiving window (target "&F9&"); "&E21&" of "&E20&" brands would pay $"&Config!$B$14&" or more and control the budget (target "&F21&"). Gate 0: "&E32&"."
A34: If it fails (plan) | B34: Fewer than 3 brands: test the office-paid version for three more weeks. Fewer than 5 offices: change the cluster or the office size band, not the model.
A36: Top three objections per side, as of (mentions across objection_1 to objection_3)
A37: Office | B37: Mentions | C37: First quote logged for that code
A38: Office side
A39: =IF(INDEX($L$41:$L$53,MATCH(LARGE($M$41:$M$53,1),$M$41:$M$53,0))<1,"1. none logged yet","1. "&INDEX($K$41:$K$53,MATCH(LARGE($M$41:$M$53,1),$M$41:$M$53,0))&" ("&INDEX($J$41:$J$53,MATCH(LARGE($M$41:$M$53,1),$M$41:$M$53,0))&")") | B39: =INDEX($L$41:$L$53,MATCH(LARGE($M$41:$M$53,1),$M$41:$M$53,0)) | C39: =IF(B39<1,"",IFERROR(INDEX(Office_Log!$AM$2:$AM$201,MATCH(INDEX($J$41:$J$53,MATCH(LARGE($M$41:$M$53,1),$M$41:$M$53,0)),Office_Log!$BO$2:$BO$201,0)),IFERROR(INDEX(Office_Log!$AM$2:$AM$201,MATCH(INDEX($J$41:$J$53,MATCH(LARGE($M$41:$M$53,1),$M$41:$M$53,0)),Office_Log!$BP$2:$BP$201,0)),IFERROR(INDEX(Office_Log!$AM$2:$AM$201,MATCH(INDEX($J$41:$J$53,MATCH(LARGE($M$41:$M$53,1),$M$41:$M$53,0)),Office_Log!$BQ$2:$BQ$201,0)),"")))) | J39: Objection counts used for the top three (as of). Ties go to the code listed first.
A40: =IF(INDEX($L$41:$L$53,MATCH(LARGE($M$41:$M$53,2),$M$41:$M$53,0))<1,"2. none logged yet","2. "&INDEX($K$41:$K$53,MATCH(LARGE($M$41:$M$53,2),$M$41:$M$53,0))&" ("&INDEX($J$41:$J$53,MATCH(LARGE($M$41:$M$53,2),$M$41:$M$53,0))&")") | B40: =INDEX($L$41:$L$53,MATCH(LARGE($M$41:$M$53,2),$M$41:$M$53,0)) | C40: =IF(B40<1,"",IFERROR(INDEX(Office_Log!$AM$2:$AM$201,MATCH(INDEX($J$41:$J$53,MATCH(LARGE($M$41:$M$53,2),$M$41:$M$53,0)),Office_Log!$BO$2:$BO$201,0)),IFERROR(INDEX(Office_Log!$AM$2:$AM$201,MATCH(INDEX($J$41:$J$53,MATCH(LARGE($M$41:$M$53,2),$M$41:$M$53,0)),Office_Log!$BP$2:$BP$201,0)),IFERROR(INDEX(Office_Log!$AM$2:$AM$201,MATCH(INDEX($J$41:$J$53,MATCH(LARGE($M$41:$M$53,2),$M$41:$M$53,0)),Office_Log!$BQ$2:$BQ$201,0)),"")))) | J40: office code | K40: office label | L40: office mentions | M40: office score | O40: brand code | P40: brand label | Q40: brand mentions | R40: brand score
A41: =IF(INDEX($L$41:$L$53,MATCH(LARGE($M$41:$M$53,3),$M$41:$M$53,0))<1,"3. none logged yet","3. "&INDEX($K$41:$K$53,MATCH(LARGE($M$41:$M$53,3),$M$41:$M$53,0))&" ("&INDEX($J$41:$J$53,MATCH(LARGE($M$41:$M$53,3),$M$41:$M$53,0))&")") | B41: =INDEX($L$41:$L$53,MATCH(LARGE($M$41:$M$53,3),$M$41:$M$53,0)) | C41: =IF(B41<1,"",IFERROR(INDEX(Office_Log!$AM$2:$AM$201,MATCH(INDEX($J$41:$J$53,MATCH(LARGE($M$41:$M$53,3),$M$41:$M$53,0)),Office_Log!$BO$2:$BO$201,0)),IFERROR(INDEX(Office_Log!$AM$2:$AM$201,MATCH(INDEX($J$41:$J$53,MATCH(LARGE($M$41:$M$53,3),$M$41:$M$53,0)),Office_Log!$BP$2:$BP$201,0)),IFERROR(INDEX(Office_Log!$AM$2:$AM$201,MATCH(INDEX($J$41:$J$53,MATCH(LARGE($M$41:$M$53,3),$M$41:$M$53,0)),Office_Log!$BQ$2:$BQ$201,0)),"")))) | J41: needs_approval | K41: I need to ask facilities, HR or someone else | L41: =COUNTIFS(Office_Log!$BO$2:$BO$201,J41,Office_Log!$G$2:$G$201,"<="&$E$6)+COUNTIFS(Office_Log!$BP$2:$BP$201,J41,Office_Log!$G$2:$G$201,"<="&$E$6)+COUNTIFS(Office_Log!$BQ$2:$BQ$201,J41,Office_Log!$G$2:$G$201,"<="&$E$6) | M41: =L41-1/1000 | O41: seed_ourselves | P41: We can seed offices ourselves for free | Q41: =COUNTIFS(Brand_Log!$BM$2:$BM$201,O41,Brand_Log!$G$2:$G$201,"<="&$E$6)+COUNTIFS(Brand_Log!$BN$2:$BN$201,O41,Brand_Log!$G$2:$G$201,"<="&$E$6)+COUNTIFS(Brand_Log!$BO$2:$BO$201,O41,Brand_Log!$G$2:$G$201,"<="&$E$6) | R41: =Q41-1/1000
A42: Brand side | J42: existing_vendor | K42: We already have a pantry vendor or contract | L42: =COUNTIFS(Office_Log!$BO$2:$BO$201,J42,Office_Log!$G$2:$G$201,"<="&$E$6)+COUNTIFS(Office_Log!$BP$2:$BP$201,J42,Office_Log!$G$2:$G$201,"<="&$E$6)+COUNTIFS(Office_Log!$BQ$2:$BQ$201,J42,Office_Log!$G$2:$G$201,"<="&$E$6) | M42: =L42-2/1000 | O42: price_per_sample | P42: $600 / the price is more than we pay per sample elsewhere | Q42: =COUNTIFS(Brand_Log!$BM$2:$BM$201,O42,Brand_Log!$G$2:$G$201,"<="&$E$6)+COUNTIFS(Brand_Log!$BN$2:$BN$201,O42,Brand_Log!$G$2:$G$201,"<="&$E$6)+COUNTIFS(Brand_Log!$BO$2:$BO$201,O42,Brand_Log!$G$2:$G$201,"<="&$E$6) | R42: =Q42-2/1000
A43: =IF(INDEX($Q$41:$Q$53,MATCH(LARGE($R$41:$R$53,1),$R$41:$R$53,0))<1,"1. none logged yet","1. "&INDEX($P$41:$P$53,MATCH(LARGE($R$41:$R$53,1),$R$41:$R$53,0))&" ("&INDEX($O$41:$O$53,MATCH(LARGE($R$41:$R$53,1),$R$41:$R$53,0))&")") | B43: =INDEX($Q$41:$Q$53,MATCH(LARGE($R$41:$R$53,1),$R$41:$R$53,0)) | C43: =IF(B43<1,"",IFERROR(INDEX(Brand_Log!$AE$2:$AE$201,MATCH(INDEX($O$41:$O$53,MATCH(LARGE($R$41:$R$53,1),$R$41:$R$53,0)),Brand_Log!$BM$2:$BM$201,0)),IFERROR(INDEX(Brand_Log!$AE$2:$AE$201,MATCH(INDEX($O$41:$O$53,MATCH(LARGE($R$41:$R$53,1),$R$41:$R$53,0)),Brand_Log!$BN$2:$BN$201,0)),IFERROR(INDEX(Brand_Log!$AE$2:$AE$201,MATCH(INDEX($O$41:$O$53,MATCH(LARGE($R$41:$R$53,1),$R$41:$R$53,0)),Brand_Log!$BO$2:$BO$201,0)),"")))) | J43: allergy_policy | K43: Allergy or food-safety worry | L43: =COUNTIFS(Office_Log!$BO$2:$BO$201,J43,Office_Log!$G$2:$G$201,"<="&$E$6)+COUNTIFS(Office_Log!$BP$2:$BP$201,J43,Office_Log!$G$2:$G$201,"<="&$E$6)+COUNTIFS(Office_Log!$BQ$2:$BQ$201,J43,Office_Log!$G$2:$G$201,"<="&$E$6) | M43: =L43-3/1000 | O43: free_trial | P43: Can we do a free trial first? | Q43: =COUNTIFS(Brand_Log!$BM$2:$BM$201,O43,Brand_Log!$G$2:$G$201,"<="&$E$6)+COUNTIFS(Brand_Log!$BN$2:$BN$201,O43,Brand_Log!$G$2:$G$201,"<="&$E$6)+COUNTIFS(Brand_Log!$BO$2:$BO$201,O43,Brand_Log!$G$2:$G$201,"<="&$E$6) | R43: =Q43-3/1000
A44: =IF(INDEX($Q$41:$Q$53,MATCH(LARGE($R$41:$R$53,2),$R$41:$R$53,0))<1,"2. none logged yet","2. "&INDEX($P$41:$P$53,MATCH(LARGE($R$41:$R$53,2),$R$41:$R$53,0))&" ("&INDEX($O$41:$O$53,MATCH(LARGE($R$41:$R$53,2),$R$41:$R$53,0))&")") | B44: =INDEX($Q$41:$Q$53,MATCH(LARGE($R$41:$R$53,2),$R$41:$R$53,0)) | C44: =IF(B44<1,"",IFERROR(INDEX(Brand_Log!$AE$2:$AE$201,MATCH(INDEX($O$41:$O$53,MATCH(LARGE($R$41:$R$53,2),$R$41:$R$53,0)),Brand_Log!$BM$2:$BM$201,0)),IFERROR(INDEX(Brand_Log!$AE$2:$AE$201,MATCH(INDEX($O$41:$O$53,MATCH(LARGE($R$41:$R$53,2),$R$41:$R$53,0)),Brand_Log!$BN$2:$BN$201,0)),IFERROR(INDEX(Brand_Log!$AE$2:$AE$201,MATCH(INDEX($O$41:$O$53,MATCH(LARGE($R$41:$R$53,2),$R$41:$R$53,0)),Brand_Log!$BO$2:$BO$201,0)),"")))) | J44: healthy_policy | K44: We only stock healthy items (wellness policy) | L44: =COUNTIFS(Office_Log!$BO$2:$BO$201,J44,Office_Log!$G$2:$G$201,"<="&$E$6)+COUNTIFS(Office_Log!$BP$2:$BP$201,J44,Office_Log!$G$2:$G$201,"<="&$E$6)+COUNTIFS(Office_Log!$BQ$2:$BQ$201,J44,Office_Log!$G$2:$G$201,"<="&$E$6) | M44: =L44-4/1000 | O44: what_we_get | P44: What do we actually get out of it? | Q44: =COUNTIFS(Brand_Log!$BM$2:$BM$201,O44,Brand_Log!$G$2:$G$201,"<="&$E$6)+COUNTIFS(Brand_Log!$BN$2:$BN$201,O44,Brand_Log!$G$2:$G$201,"<="&$E$6)+COUNTIFS(Brand_Log!$BO$2:$BO$201,O44,Brand_Log!$G$2:$G$201,"<="&$E$6) | R44: =Q44-4/1000
A45: =IF(INDEX($Q$41:$Q$53,MATCH(LARGE($R$41:$R$53,3),$R$41:$R$53,0))<1,"3. none logged yet","3. "&INDEX($P$41:$P$53,MATCH(LARGE($R$41:$R$53,3),$R$41:$R$53,0))&" ("&INDEX($O$41:$O$53,MATCH(LARGE($R$41:$R$53,3),$R$41:$R$53,0))&")") | B45: =INDEX($Q$41:$Q$53,MATCH(LARGE($R$41:$R$53,3),$R$41:$R$53,0)) | C45: =IF(B45<1,"",IFERROR(INDEX(Brand_Log!$AE$2:$AE$201,MATCH(INDEX($O$41:$O$53,MATCH(LARGE($R$41:$R$53,3),$R$41:$R$53,0)),Brand_Log!$BM$2:$BM$201,0)),IFERROR(INDEX(Brand_Log!$AE$2:$AE$201,MATCH(INDEX($O$41:$O$53,MATCH(LARGE($R$41:$R$53,3),$R$41:$R$53,0)),Brand_Log!$BN$2:$BN$201,0)),IFERROR(INDEX(Brand_Log!$AE$2:$AE$201,MATCH(INDEX($O$41:$O$53,MATCH(LARGE($R$41:$R$53,3),$R$41:$R$53,0)),Brand_Log!$BO$2:$BO$201,0)),"")))) | J45: building_receiving | K45: Building security, receiving or certificate rules | L45: =COUNTIFS(Office_Log!$BO$2:$BO$201,J45,Office_Log!$G$2:$G$201,"<="&$E$6)+COUNTIFS(Office_Log!$BP$2:$BP$201,J45,Office_Log!$G$2:$G$201,"<="&$E$6)+COUNTIFS(Office_Log!$BQ$2:$BQ$201,J45,Office_Log!$G$2:$G$201,"<="&$E$6) | M45: =L45-5/1000 | O45: budget_timing | P45: No budget now / budget timing | Q45: =COUNTIFS(Brand_Log!$BM$2:$BM$201,O45,Brand_Log!$G$2:$G$201,"<="&$E$6)+COUNTIFS(Brand_Log!$BN$2:$BN$201,O45,Brand_Log!$G$2:$G$201,"<="&$E$6)+COUNTIFS(Brand_Log!$BO$2:$BO$201,O45,Brand_Log!$G$2:$G$201,"<="&$E$6) | R45: =Q45-5/1000
J46: low_attendance | K46: Not enough people in on a given day | L46: =COUNTIFS(Office_Log!$BO$2:$BO$201,J46,Office_Log!$G$2:$G$201,"<="&$E$6)+COUNTIFS(Office_Log!$BP$2:$BP$201,J46,Office_Log!$G$2:$G$201,"<="&$E$6)+COUNTIFS(Office_Log!$BQ$2:$BQ$201,J46,Office_Log!$G$2:$G$201,"<="&$E$6) | M46: =L46-6/1000 | O46: inventory | P46: Inventory or shipping the units | Q46: =COUNTIFS(Brand_Log!$BM$2:$BM$201,O46,Brand_Log!$G$2:$G$201,"<="&$E$6)+COUNTIFS(Brand_Log!$BN$2:$BN$201,O46,Brand_Log!$G$2:$G$201,"<="&$E$6)+COUNTIFS(Brand_Log!$BO$2:$BO$201,O46,Brand_Log!$G$2:$G$201,"<="&$E$6) | R46: =Q46-6/1000
A47: Pace and reply rate (from the Friday Clay paste) | J47: commitments_too_much | K47: Photos, survey or debrief are too much work | L47: =COUNTIFS(Office_Log!$BO$2:$BO$201,J47,Office_Log!$G$2:$G$201,"<="&$E$6)+COUNTIFS(Office_Log!$BP$2:$BP$201,J47,Office_Log!$G$2:$G$201,"<="&$E$6)+COUNTIFS(Office_Log!$BQ$2:$BQ$201,J47,Office_Log!$G$2:$G$201,"<="&$E$6) | M47: =L47-7/1000 | O47: shelf_life | P47: Shelf life | Q47: =COUNTIFS(Brand_Log!$BM$2:$BM$201,O47,Brand_Log!$G$2:$G$201,"<="&$E$6)+COUNTIFS(Brand_Log!$BN$2:$BN$201,O47,Brand_Log!$G$2:$G$201,"<="&$E$6)+COUNTIFS(Brand_Log!$BO$2:$BO$201,O47,Brand_Log!$G$2:$G$201,"<="&$E$6) | R47: =Q47-7/1000
A48: Measure | B48: Fri wk 1 | C48: Fri wk 2 | D48: Gate 0 | E48: As of | G48: How it is counted | J48: survey_concern | K48: Survey or employee-data worry | L48: =COUNTIFS(Office_Log!$BO$2:$BO$201,J48,Office_Log!$G$2:$G$201,"<="&$E$6)+COUNTIFS(Office_Log!$BP$2:$BP$201,J48,Office_Log!$G$2:$G$201,"<="&$E$6)+COUNTIFS(Office_Log!$BQ$2:$BQ$201,J48,Office_Log!$G$2:$G$201,"<="&$E$6) | M48: =L48-8/1000 | O48: not_our_audience | P48: Office workers aren't our customer | Q48: =COUNTIFS(Brand_Log!$BM$2:$BM$201,O48,Brand_Log!$G$2:$G$201,"<="&$E$6)+COUNTIFS(Brand_Log!$BN$2:$BN$201,O48,Brand_Log!$G$2:$G$201,"<="&$E$6)+COUNTIFS(Brand_Log!$BO$2:$BO$201,O48,Brand_Log!$G$2:$G$201,"<="&$E$6) | R48: =Q48-8/1000
A49: Office first touches sent | B49: =IFERROR(COUNTIFS(INDEX(Clay_Offices!$A$2:$FZ$601,0,Sync!$C$11),"<="&B$6,INDEX(Clay_Offices!$A$2:$FZ$601,0,Sync!$C$5),Config!$B$20),0) | C49: =IFERROR(COUNTIFS(INDEX(Clay_Offices!$A$2:$FZ$601,0,Sync!$C$11),"<="&C$6,INDEX(Clay_Offices!$A$2:$FZ$601,0,Sync!$C$5),Config!$B$20),0) | D49: =IFERROR(COUNTIFS(INDEX(Clay_Offices!$A$2:$FZ$601,0,Sync!$C$11),"<="&D$6,INDEX(Clay_Offices!$A$2:$FZ$601,0,Sync!$C$5),Config!$B$20),0) | E49: =IFERROR(COUNTIFS(INDEX(Clay_Offices!$A$2:$FZ$601,0,Sync!$C$11),"<="&E$6,INDEX(Clay_Offices!$A$2:$FZ$601,0,Sync!$C$5),Config!$B$20),0) | G49: Clay rows with touch_1_date on or before the cut-off. | J49: vendor_fatigue | K49: We don't want vendors or marketing in the office | L49: =COUNTIFS(Office_Log!$BO$2:$BO$201,J49,Office_Log!$G$2:$G$201,"<="&$E$6)+COUNTIFS(Office_Log!$BP$2:$BP$201,J49,Office_Log!$G$2:$G$201,"<="&$E$6)+COUNTIFS(Office_Log!$BQ$2:$BQ$201,J49,Office_Log!$G$2:$G$201,"<="&$E$6) | M49: =L49-9/1000 | O49: want_proof | P49: Show me results from other brands first | Q49: =COUNTIFS(Brand_Log!$BM$2:$BM$201,O49,Brand_Log!$G$2:$G$201,"<="&$E$6)+COUNTIFS(Brand_Log!$BN$2:$BN$201,O49,Brand_Log!$G$2:$G$201,"<="&$E$6)+COUNTIFS(Brand_Log!$BO$2:$BO$201,O49,Brand_Log!$G$2:$G$201,"<="&$E$6) | R49: =Q49-9/1000
A50: Office replies (any human reply, opt-outs included) | B50: =IFERROR(COUNTIFS(INDEX(Clay_Offices!$A$2:$FZ$601,0,Sync!$C$14),"<="&B$6,INDEX(Clay_Offices!$A$2:$FZ$601,0,Sync!$C$5),Config!$B$20,INDEX(Clay_Offices!$A$2:$FZ$601,0,Sync!$C$15),"<>bounce",INDEX(Clay_Offices!$A$2:$FZ$601,0,Sync!$C$15),"<>out_of_office"),0) | C50: =IFERROR(COUNTIFS(INDEX(Clay_Offices!$A$2:$FZ$601,0,Sync!$C$14),"<="&C$6,INDEX(Clay_Offices!$A$2:$FZ$601,0,Sync!$C$5),Config!$B$20,INDEX(Clay_Offices!$A$2:$FZ$601,0,Sync!$C$15),"<>bounce",INDEX(Clay_Offices!$A$2:$FZ$601,0,Sync!$C$15),"<>out_of_office"),0) | D50: =IFERROR(COUNTIFS(INDEX(Clay_Offices!$A$2:$FZ$601,0,Sync!$C$14),"<="&D$6,INDEX(Clay_Offices!$A$2:$FZ$601,0,Sync!$C$5),Config!$B$20,INDEX(Clay_Offices!$A$2:$FZ$601,0,Sync!$C$15),"<>bounce",INDEX(Clay_Offices!$A$2:$FZ$601,0,Sync!$C$15),"<>out_of_office"),0) | E50: =IFERROR(COUNTIFS(INDEX(Clay_Offices!$A$2:$FZ$601,0,Sync!$C$14),"<="&E$6,INDEX(Clay_Offices!$A$2:$FZ$601,0,Sync!$C$5),Config!$B$20,INDEX(Clay_Offices!$A$2:$FZ$601,0,Sync!$C$15),"<>bounce",INDEX(Clay_Offices!$A$2:$FZ$601,0,Sync!$C$15),"<>out_of_office"),0) | G50: Rows with last_reply_date on or before the cut-off; bounces and auto-replies excluded. | J50: space | K50: No shelf or counter space | L50: =COUNTIFS(Office_Log!$BO$2:$BO$201,J50,Office_Log!$G$2:$G$201,"<="&$E$6)+COUNTIFS(Office_Log!$BP$2:$BP$201,J50,Office_Log!$G$2:$G$201,"<="&$E$6)+COUNTIFS(Office_Log!$BQ$2:$BQ$201,J50,Office_Log!$G$2:$G$201,"<="&$E$6) | M50: =L50-10/1000 | O50: want_sales_data | P50: We need sales or lift data, not feedback | Q50: =COUNTIFS(Brand_Log!$BM$2:$BM$201,O50,Brand_Log!$G$2:$G$201,"<="&$E$6)+COUNTIFS(Brand_Log!$BN$2:$BN$201,O50,Brand_Log!$G$2:$G$201,"<="&$E$6)+COUNTIFS(Brand_Log!$BO$2:$BO$201,O50,Brand_Log!$G$2:$G$201,"<="&$E$6) | R50: =Q50-10/1000
A51: Office reply rate | B51: =IF(B49=0,"",B50/B49) | C51: =IF(C49=0,"",C50/C49) | D51: =IF(D49=0,"",D50/D49) | E51: =IF(E49=0,"",E50/E49) | G51: Replies / first touches. The plan needs 20%. | J51: supply_irregular | K51: Irregular, roughly monthly supply isn't useful | L51: =COUNTIFS(Office_Log!$BO$2:$BO$201,J51,Office_Log!$G$2:$G$201,"<="&$E$6)+COUNTIFS(Office_Log!$BP$2:$BP$201,J51,Office_Log!$G$2:$G$201,"<="&$E$6)+COUNTIFS(Office_Log!$BQ$2:$BQ$201,J51,Office_Log!$G$2:$G$201,"<="&$E$6) | M51: =L51-11/1000 | O51: no_buy_path | P51: No store near the cluster and no online code | Q51: =COUNTIFS(Brand_Log!$BM$2:$BM$201,O51,Brand_Log!$G$2:$G$201,"<="&$E$6)+COUNTIFS(Brand_Log!$BN$2:$BN$201,O51,Brand_Log!$G$2:$G$201,"<="&$E$6)+COUNTIFS(Brand_Log!$BO$2:$BO$201,O51,Brand_Log!$G$2:$G$201,"<="&$E$6) | R51: =Q51-11/1000
A52: Office positive replies | B52: =IFERROR(COUNTIFS(INDEX(Clay_Offices!$A$2:$FZ$601,0,Sync!$C$14),"<="&B$6,INDEX(Clay_Offices!$A$2:$FZ$601,0,Sync!$C$5),Config!$B$20,INDEX(Clay_Offices!$A$2:$FZ$601,0,Sync!$C$15),"yes"),0)+IFERROR(COUNTIFS(INDEX(Clay_Offices!$A$2:$FZ$601,0,Sync!$C$14),"<="&B$6,INDEX(Clay_Offices!$A$2:$FZ$601,0,Sync!$C$5),Config!$B$20,INDEX(Clay_Offices!$A$2:$FZ$601,0,Sync!$C$15),"maybe"),0)+IFERROR(COUNTIFS(INDEX(Clay_Offices!$A$2:$FZ$601,0,Sync!$C$14),"<="&B$6,INDEX(Clay_Offices!$A$2:$FZ$601,0,Sync!$C$5),Config!$B$20,INDEX(Clay_Offices!$A$2:$FZ$601,0,Sync!$C$15),"needs_approval"),0)+IFERROR(COUNTIFS(INDEX(Clay_Offices!$A$2:$FZ$601,0,Sync!$C$14),"<="&B$6,INDEX(Clay_Offices!$A$2:$FZ$601,0,Sync!$C$5),Config!$B$20,INDEX(Clay_Offices!$A$2:$FZ$601,0,Sync!$C$15),"send_info"),0)+IFERROR(COUNTIFS(INDEX(Clay_Offices!$A$2:$FZ$601,0,Sync!$C$14),"<="&B$6,INDEX(Clay_Offices!$A$2:$FZ$601,0,Sync!$C$5),Config!$B$20,INDEX(Clay_Offices!$A$2:$FZ$601,0,Sync!$C$15),"referral"),0) | C52: =IFERROR(COUNTIFS(INDEX(Clay_Offices!$A$2:$FZ$601,0,Sync!$C$14),"<="&C$6,INDEX(Clay_Offices!$A$2:$FZ$601,0,Sync!$C$5),Config!$B$20,INDEX(Clay_Offices!$A$2:$FZ$601,0,Sync!$C$15),"yes"),0)+IFERROR(COUNTIFS(INDEX(Clay_Offices!$A$2:$FZ$601,0,Sync!$C$14),"<="&C$6,INDEX(Clay_Offices!$A$2:$FZ$601,0,Sync!$C$5),Config!$B$20,INDEX(Clay_Offices!$A$2:$FZ$601,0,Sync!$C$15),"maybe"),0)+IFERROR(COUNTIFS(INDEX(Clay_Offices!$A$2:$FZ$601,0,Sync!$C$14),"<="&C$6,INDEX(Clay_Offices!$A$2:$FZ$601,0,Sync!$C$5),Config!$B$20,INDEX(Clay_Offices!$A$2:$FZ$601,0,Sync!$C$15),"needs_approval"),0)+IFERROR(COUNTIFS(INDEX(Clay_Offices!$A$2:$FZ$601,0,Sync!$C$14),"<="&C$6,INDEX(Clay_Offices!$A$2:$FZ$601,0,Sync!$C$5),Config!$B$20,INDEX(Clay_Offices!$A$2:$FZ$601,0,Sync!$C$15),"send_info"),0)+IFERROR(COUNTIFS(INDEX(Clay_Offices!$A$2:$FZ$601,0,Sync!$C$14),"<="&C$6,INDEX(Clay_Offices!$A$2:$FZ$601,0,Sync!$C$5),Config!$B$20,INDEX(Clay_Offices!$A$2:$FZ$601,0,Sync!$C$15),"referral"),0) | D52: =IFERROR(COUNTIFS(INDEX(Clay_Offices!$A$2:$FZ$601,0,Sync!$C$14),"<="&D$6,INDEX(Clay_Offices!$A$2:$FZ$601,0,Sync!$C$5),Config!$B$20,INDEX(Clay_Offices!$A$2:$FZ$601,0,Sync!$C$15),"yes"),0)+IFERROR(COUNTIFS(INDEX(Clay_Offices!$A$2:$FZ$601,0,Sync!$C$14),"<="&D$6,INDEX(Clay_Offices!$A$2:$FZ$601,0,Sync!$C$5),Config!$B$20,INDEX(Clay_Offices!$A$2:$FZ$601,0,Sync!$C$15),"maybe"),0)+IFERROR(COUNTIFS(INDEX(Clay_Offices!$A$2:$FZ$601,0,Sync!$C$14),"<="&D$6,INDEX(Clay_Offices!$A$2:$FZ$601,0,Sync!$C$5),Config!$B$20,INDEX(Clay_Offices!$A$2:$FZ$601,0,Sync!$C$15),"needs_approval"),0)+IFERROR(COUNTIFS(INDEX(Clay_Offices!$A$2:$FZ$601,0,Sync!$C$14),"<="&D$6,INDEX(Clay_Offices!$A$2:$FZ$601,0,Sync!$C$5),Config!$B$20,INDEX(Clay_Offices!$A$2:$FZ$601,0,Sync!$C$15),"send_info"),0)+IFERROR(COUNTIFS(INDEX(Clay_Offices!$A$2:$FZ$601,0,Sync!$C$14),"<="&D$6,INDEX(Clay_Offices!$A$2:$FZ$601,0,Sync!$C$5),Config!$B$20,INDEX(Clay_Offices!$A$2:$FZ$601,0,Sync!$C$15),"referral"),0) | E52: =IFERROR(COUNTIFS(INDEX(Clay_Offices!$A$2:$FZ$601,0,Sync!$C$14),"<="&E$6,INDEX(Clay_Offices!$A$2:$FZ$601,0,Sync!$C$5),Config!$B$20,INDEX(Clay_Offices!$A$2:$FZ$601,0,Sync!$C$15),"yes"),0)+IFERROR(COUNTIFS(INDEX(Clay_Offices!$A$2:$FZ$601,0,Sync!$C$14),"<="&E$6,INDEX(Clay_Offices!$A$2:$FZ$601,0,Sync!$C$5),Config!$B$20,INDEX(Clay_Offices!$A$2:$FZ$601,0,Sync!$C$15),"maybe"),0)+IFERROR(COUNTIFS(INDEX(Clay_Offices!$A$2:$FZ$601,0,Sync!$C$14),"<="&E$6,INDEX(Clay_Offices!$A$2:$FZ$601,0,Sync!$C$5),Config!$B$20,INDEX(Clay_Offices!$A$2:$FZ$601,0,Sync!$C$15),"needs_approval"),0)+IFERROR(COUNTIFS(INDEX(Clay_Offices!$A$2:$FZ$601,0,Sync!$C$14),"<="&E$6,INDEX(Clay_Offices!$A$2:$FZ$601,0,Sync!$C$5),Config!$B$20,INDEX(Clay_Offices!$A$2:$FZ$601,0,Sync!$C$15),"send_info"),0)+IFERROR(COUNTIFS(INDEX(Clay_Offices!$A$2:$FZ$601,0,Sync!$C$14),"<="&E$6,INDEX(Clay_Offices!$A$2:$FZ$601,0,Sync!$C$5),Config!$B$20,INDEX(Clay_Offices!$A$2:$FZ$601,0,Sync!$C$15),"referral"),0) | G52: reply_type yes, maybe, needs_approval, send_info or referral. | J52: quality_unknown | K52: Don't know these brands; quality worry | L52: =COUNTIFS(Office_Log!$BO$2:$BO$201,J52,Office_Log!$G$2:$G$201,"<="&$E$6)+COUNTIFS(Office_Log!$BP$2:$BP$201,J52,Office_Log!$G$2:$G$201,"<="&$E$6)+COUNTIFS(Office_Log!$BQ$2:$BQ$201,J52,Office_Log!$G$2:$G$201,"<="&$E$6) | M52: =L52-12/1000 | O52: insurance | P52: No product liability certificate | Q52: =COUNTIFS(Brand_Log!$BM$2:$BM$201,O52,Brand_Log!$G$2:$G$201,"<="&$E$6)+COUNTIFS(Brand_Log!$BN$2:$BN$201,O52,Brand_Log!$G$2:$G$201,"<="&$E$6)+COUNTIFS(Brand_Log!$BO$2:$BO$201,O52,Brand_Log!$G$2:$G$201,"<="&$E$6) | R52: =Q52-12/1000
A53: Office conversations per first touch | B53: =IF(B49=0,"",B8/B49) | C53: =IF(C49=0,"",C8/C49) | D53: =IF(D49=0,"",D8/D49) | E53: =IF(E49=0,"",E8/E49) | G53: Conversations (above) / first touches. 15 from about 75 first touches is 20%. | J53: other | K53: Other (read the quotes) | L53: =COUNTIFS(Office_Log!$BO$2:$BO$201,J53,Office_Log!$G$2:$G$201,"<="&$E$6)+COUNTIFS(Office_Log!$BP$2:$BP$201,J53,Office_Log!$G$2:$G$201,"<="&$E$6)+COUNTIFS(Office_Log!$BQ$2:$BQ$201,J53,Office_Log!$G$2:$G$201,"<="&$E$6) | M53: =L53-13/1000 | O53: other | P53: Other (read the quotes) | Q53: =COUNTIFS(Brand_Log!$BM$2:$BM$201,O53,Brand_Log!$G$2:$G$201,"<="&$E$6)+COUNTIFS(Brand_Log!$BN$2:$BN$201,O53,Brand_Log!$G$2:$G$201,"<="&$E$6)+COUNTIFS(Brand_Log!$BO$2:$BO$201,O53,Brand_Log!$G$2:$G$201,"<="&$E$6) | R53: =Q53-13/1000
A54: Office opt-outs | B54: =IFERROR(COUNTIFS(INDEX(Clay_Offices!$A$2:$FZ$601,0,Sync!$C$18),"<="&B$6,INDEX(Clay_Offices!$A$2:$FZ$601,0,Sync!$C$5),Config!$B$20),0) | C54: =IFERROR(COUNTIFS(INDEX(Clay_Offices!$A$2:$FZ$601,0,Sync!$C$18),"<="&C$6,INDEX(Clay_Offices!$A$2:$FZ$601,0,Sync!$C$5),Config!$B$20),0) | D54: =IFERROR(COUNTIFS(INDEX(Clay_Offices!$A$2:$FZ$601,0,Sync!$C$18),"<="&D$6,INDEX(Clay_Offices!$A$2:$FZ$601,0,Sync!$C$5),Config!$B$20),0) | E54: =IFERROR(COUNTIFS(INDEX(Clay_Offices!$A$2:$FZ$601,0,Sync!$C$18),"<="&E$6,INDEX(Clay_Offices!$A$2:$FZ$601,0,Sync!$C$5),Config!$B$20),0) | G54: Rows with opt_out_date on or before the cut-off. Every one must have do_not_contact = Y.
A55: Office reply-rate check (as of) | B55: =IF(E49<Config!$B$17,"Too few first touches to judge ("&E49&" of "&Config!$B$17&").",IF(E51<Config!$B$16,"UNDER 20%: run sending/sending-setup.md section 6 before sending more.","OK: at or above 20%."))
A56: Brand first touches sent | B56: =IFERROR(COUNTIFS(INDEX(Clay_Brands!$A$2:$FZ$601,0,Sync!$D$11),"<="&B$6,INDEX(Clay_Brands!$A$2:$FZ$601,0,Sync!$D$5),Config!$B$20),0) | C56: =IFERROR(COUNTIFS(INDEX(Clay_Brands!$A$2:$FZ$601,0,Sync!$D$11),"<="&C$6,INDEX(Clay_Brands!$A$2:$FZ$601,0,Sync!$D$5),Config!$B$20),0) | D56: =IFERROR(COUNTIFS(INDEX(Clay_Brands!$A$2:$FZ$601,0,Sync!$D$11),"<="&D$6,INDEX(Clay_Brands!$A$2:$FZ$601,0,Sync!$D$5),Config!$B$20),0) | E56: =IFERROR(COUNTIFS(INDEX(Clay_Brands!$A$2:$FZ$601,0,Sync!$D$11),"<="&E$6,INDEX(Clay_Brands!$A$2:$FZ$601,0,Sync!$D$5),Config!$B$20),0) | G56: Clay rows with touch_1_date on or before the cut-off.
A57: Brand replies (any human reply, opt-outs included) | B57: =IFERROR(COUNTIFS(INDEX(Clay_Brands!$A$2:$FZ$601,0,Sync!$D$14),"<="&B$6,INDEX(Clay_Brands!$A$2:$FZ$601,0,Sync!$D$5),Config!$B$20,INDEX(Clay_Brands!$A$2:$FZ$601,0,Sync!$D$15),"<>bounce",INDEX(Clay_Brands!$A$2:$FZ$601,0,Sync!$D$15),"<>out_of_office"),0) | C57: =IFERROR(COUNTIFS(INDEX(Clay_Brands!$A$2:$FZ$601,0,Sync!$D$14),"<="&C$6,INDEX(Clay_Brands!$A$2:$FZ$601,0,Sync!$D$5),Config!$B$20,INDEX(Clay_Brands!$A$2:$FZ$601,0,Sync!$D$15),"<>bounce",INDEX(Clay_Brands!$A$2:$FZ$601,0,Sync!$D$15),"<>out_of_office"),0) | D57: =IFERROR(COUNTIFS(INDEX(Clay_Brands!$A$2:$FZ$601,0,Sync!$D$14),"<="&D$6,INDEX(Clay_Brands!$A$2:$FZ$601,0,Sync!$D$5),Config!$B$20,INDEX(Clay_Brands!$A$2:$FZ$601,0,Sync!$D$15),"<>bounce",INDEX(Clay_Brands!$A$2:$FZ$601,0,Sync!$D$15),"<>out_of_office"),0) | E57: =IFERROR(COUNTIFS(INDEX(Clay_Brands!$A$2:$FZ$601,0,Sync!$D$14),"<="&E$6,INDEX(Clay_Brands!$A$2:$FZ$601,0,Sync!$D$5),Config!$B$20,INDEX(Clay_Brands!$A$2:$FZ$601,0,Sync!$D$15),"<>bounce",INDEX(Clay_Brands!$A$2:$FZ$601,0,Sync!$D$15),"<>out_of_office"),0) | G57: Rows with last_reply_date on or before the cut-off; bounces and auto-replies excluded.
A58: Brand reply rate | B58: =IF(B56=0,"",B57/B56) | C58: =IF(C56=0,"",C57/C56) | D58: =IF(D56=0,"",D57/D56) | E58: =IF(E56=0,"",E57/E56) | G58: Replies / first touches. The plan needs 20%.
A59: Brand positive replies | B59: =IFERROR(COUNTIFS(INDEX(Clay_Brands!$A$2:$FZ$601,0,Sync!$D$14),"<="&B$6,INDEX(Clay_Brands!$A$2:$FZ$601,0,Sync!$D$5),Config!$B$20,INDEX(Clay_Brands!$A$2:$FZ$601,0,Sync!$D$15),"yes"),0)+IFERROR(COUNTIFS(INDEX(Clay_Brands!$A$2:$FZ$601,0,Sync!$D$14),"<="&B$6,INDEX(Clay_Brands!$A$2:$FZ$601,0,Sync!$D$5),Config!$B$20,INDEX(Clay_Brands!$A$2:$FZ$601,0,Sync!$D$15),"maybe"),0)+IFERROR(COUNTIFS(INDEX(Clay_Brands!$A$2:$FZ$601,0,Sync!$D$14),"<="&B$6,INDEX(Clay_Brands!$A$2:$FZ$601,0,Sync!$D$5),Config!$B$20,INDEX(Clay_Brands!$A$2:$FZ$601,0,Sync!$D$15),"needs_approval"),0)+IFERROR(COUNTIFS(INDEX(Clay_Brands!$A$2:$FZ$601,0,Sync!$D$14),"<="&B$6,INDEX(Clay_Brands!$A$2:$FZ$601,0,Sync!$D$5),Config!$B$20,INDEX(Clay_Brands!$A$2:$FZ$601,0,Sync!$D$15),"send_info"),0)+IFERROR(COUNTIFS(INDEX(Clay_Brands!$A$2:$FZ$601,0,Sync!$D$14),"<="&B$6,INDEX(Clay_Brands!$A$2:$FZ$601,0,Sync!$D$5),Config!$B$20,INDEX(Clay_Brands!$A$2:$FZ$601,0,Sync!$D$15),"referral"),0) | C59: =IFERROR(COUNTIFS(INDEX(Clay_Brands!$A$2:$FZ$601,0,Sync!$D$14),"<="&C$6,INDEX(Clay_Brands!$A$2:$FZ$601,0,Sync!$D$5),Config!$B$20,INDEX(Clay_Brands!$A$2:$FZ$601,0,Sync!$D$15),"yes"),0)+IFERROR(COUNTIFS(INDEX(Clay_Brands!$A$2:$FZ$601,0,Sync!$D$14),"<="&C$6,INDEX(Clay_Brands!$A$2:$FZ$601,0,Sync!$D$5),Config!$B$20,INDEX(Clay_Brands!$A$2:$FZ$601,0,Sync!$D$15),"maybe"),0)+IFERROR(COUNTIFS(INDEX(Clay_Brands!$A$2:$FZ$601,0,Sync!$D$14),"<="&C$6,INDEX(Clay_Brands!$A$2:$FZ$601,0,Sync!$D$5),Config!$B$20,INDEX(Clay_Brands!$A$2:$FZ$601,0,Sync!$D$15),"needs_approval"),0)+IFERROR(COUNTIFS(INDEX(Clay_Brands!$A$2:$FZ$601,0,Sync!$D$14),"<="&C$6,INDEX(Clay_Brands!$A$2:$FZ$601,0,Sync!$D$5),Config!$B$20,INDEX(Clay_Brands!$A$2:$FZ$601,0,Sync!$D$15),"send_info"),0)+IFERROR(COUNTIFS(INDEX(Clay_Brands!$A$2:$FZ$601,0,Sync!$D$14),"<="&C$6,INDEX(Clay_Brands!$A$2:$FZ$601,0,Sync!$D$5),Config!$B$20,INDEX(Clay_Brands!$A$2:$FZ$601,0,Sync!$D$15),"referral"),0) | D59: =IFERROR(COUNTIFS(INDEX(Clay_Brands!$A$2:$FZ$601,0,Sync!$D$14),"<="&D$6,INDEX(Clay_Brands!$A$2:$FZ$601,0,Sync!$D$5),Config!$B$20,INDEX(Clay_Brands!$A$2:$FZ$601,0,Sync!$D$15),"yes"),0)+IFERROR(COUNTIFS(INDEX(Clay_Brands!$A$2:$FZ$601,0,Sync!$D$14),"<="&D$6,INDEX(Clay_Brands!$A$2:$FZ$601,0,Sync!$D$5),Config!$B$20,INDEX(Clay_Brands!$A$2:$FZ$601,0,Sync!$D$15),"maybe"),0)+IFERROR(COUNTIFS(INDEX(Clay_Brands!$A$2:$FZ$601,0,Sync!$D$14),"<="&D$6,INDEX(Clay_Brands!$A$2:$FZ$601,0,Sync!$D$5),Config!$B$20,INDEX(Clay_Brands!$A$2:$FZ$601,0,Sync!$D$15),"needs_approval"),0)+IFERROR(COUNTIFS(INDEX(Clay_Brands!$A$2:$FZ$601,0,Sync!$D$14),"<="&D$6,INDEX(Clay_Brands!$A$2:$FZ$601,0,Sync!$D$5),Config!$B$20,INDEX(Clay_Brands!$A$2:$FZ$601,0,Sync!$D$15),"send_info"),0)+IFERROR(COUNTIFS(INDEX(Clay_Brands!$A$2:$FZ$601,0,Sync!$D$14),"<="&D$6,INDEX(Clay_Brands!$A$2:$FZ$601,0,Sync!$D$5),Config!$B$20,INDEX(Clay_Brands!$A$2:$FZ$601,0,Sync!$D$15),"referral"),0) | E59: =IFERROR(COUNTIFS(INDEX(Clay_Brands!$A$2:$FZ$601,0,Sync!$D$14),"<="&E$6,INDEX(Clay_Brands!$A$2:$FZ$601,0,Sync!$D$5),Config!$B$20,INDEX(Clay_Brands!$A$2:$FZ$601,0,Sync!$D$15),"yes"),0)+IFERROR(COUNTIFS(INDEX(Clay_Brands!$A$2:$FZ$601,0,Sync!$D$14),"<="&E$6,INDEX(Clay_Brands!$A$2:$FZ$601,0,Sync!$D$5),Config!$B$20,INDEX(Clay_Brands!$A$2:$FZ$601,0,Sync!$D$15),"maybe"),0)+IFERROR(COUNTIFS(INDEX(Clay_Brands!$A$2:$FZ$601,0,Sync!$D$14),"<="&E$6,INDEX(Clay_Brands!$A$2:$FZ$601,0,Sync!$D$5),Config!$B$20,INDEX(Clay_Brands!$A$2:$FZ$601,0,Sync!$D$15),"needs_approval"),0)+IFERROR(COUNTIFS(INDEX(Clay_Brands!$A$2:$FZ$601,0,Sync!$D$14),"<="&E$6,INDEX(Clay_Brands!$A$2:$FZ$601,0,Sync!$D$5),Config!$B$20,INDEX(Clay_Brands!$A$2:$FZ$601,0,Sync!$D$15),"send_info"),0)+IFERROR(COUNTIFS(INDEX(Clay_Brands!$A$2:$FZ$601,0,Sync!$D$14),"<="&E$6,INDEX(Clay_Brands!$A$2:$FZ$601,0,Sync!$D$5),Config!$B$20,INDEX(Clay_Brands!$A$2:$FZ$601,0,Sync!$D$15),"referral"),0) | G59: reply_type yes, maybe, needs_approval, send_info or referral.
A60: Brand conversations per first touch | B60: =IF(B56=0,"",B20/B56) | C60: =IF(C56=0,"",C20/C56) | D60: =IF(D56=0,"",D20/D56) | E60: =IF(E56=0,"",E20/E56) | G60: Conversations (above) / first touches. 15 from about 75 first touches is 20%.
A61: Brand opt-outs | B61: =IFERROR(COUNTIFS(INDEX(Clay_Brands!$A$2:$FZ$601,0,Sync!$D$18),"<="&B$6,INDEX(Clay_Brands!$A$2:$FZ$601,0,Sync!$D$5),Config!$B$20),0) | C61: =IFERROR(COUNTIFS(INDEX(Clay_Brands!$A$2:$FZ$601,0,Sync!$D$18),"<="&C$6,INDEX(Clay_Brands!$A$2:$FZ$601,0,Sync!$D$5),Config!$B$20),0) | D61: =IFERROR(COUNTIFS(INDEX(Clay_Brands!$A$2:$FZ$601,0,Sync!$D$18),"<="&D$6,INDEX(Clay_Brands!$A$2:$FZ$601,0,Sync!$D$5),Config!$B$20),0) | E61: =IFERROR(COUNTIFS(INDEX(Clay_Brands!$A$2:$FZ$601,0,Sync!$D$18),"<="&E$6,INDEX(Clay_Brands!$A$2:$FZ$601,0,Sync!$D$5),Config!$B$20),0) | G61: Rows with opt_out_date on or before the cut-off. Every one must have do_not_contact = Y.
A62: Brand reply-rate check (as of) | B62: =IF(E56<Config!$B$17,"Too few first touches to judge ("&E56&" of "&Config!$B$17&").",IF(E58<Config!$B$16,"UNDER 20%: run sending/sending-setup.md section 6 before sending more.","OK: at or above 20%."))
A63: Email bounces to date (offices + brands) / first touches to date | E63: =IF((E49+E56)=0,"",(IFERROR(COUNTIFS(INDEX(Clay_Offices!$A$2:$FZ$601,0,Sync!$C$15),"bounce",INDEX(Clay_Offices!$A$2:$FZ$601,0,Sync!$C$5),Config!$B$20),0)+IFERROR(COUNTIFS(INDEX(Clay_Brands!$A$2:$FZ$601,0,Sync!$D$15),"bounce",INDEX(Clay_Brands!$A$2:$FZ$601,0,Sync!$D$5),Config!$B$20),0))/(E49+E56)) | G63: Stop cold email from the domain and check the list if this passes 2% (sending guide section 6).
A65: By sequence variant and by channel, as of (pick winners only on large gaps; see sending guide 6.4)
A66: Sequence or channel | B66: Side | C66: First touches | D66: Replies | E66: Reply rate | G66: Positive replies
A67: office-discovery-A | B67: office | C67: =IFERROR(COUNTIFS(INDEX(Clay_Offices!$A$2:$FZ$601,0,Sync!$C$10),A67,INDEX(Clay_Offices!$A$2:$FZ$601,0,Sync!$C$11),"<="&$E$6,INDEX(Clay_Offices!$A$2:$FZ$601,0,Sync!$C$5),Config!$B$20),0) | D67: =IFERROR(COUNTIFS(INDEX(Clay_Offices!$A$2:$FZ$601,0,Sync!$C$10),A67,INDEX(Clay_Offices!$A$2:$FZ$601,0,Sync!$C$14),"<="&$E$6,INDEX(Clay_Offices!$A$2:$FZ$601,0,Sync!$C$5),Config!$B$20,INDEX(Clay_Offices!$A$2:$FZ$601,0,Sync!$C$15),"<>bounce",INDEX(Clay_Offices!$A$2:$FZ$601,0,Sync!$C$15),"<>out_of_office"),0) | E67: =IF(C67=0,"",D67/C67) | G67: =IFERROR(COUNTIFS(INDEX(Clay_Offices!$A$2:$FZ$601,0,Sync!$C$10),A67,INDEX(Clay_Offices!$A$2:$FZ$601,0,Sync!$C$14),"<="&$E$6,INDEX(Clay_Offices!$A$2:$FZ$601,0,Sync!$C$5),Config!$B$20,INDEX(Clay_Offices!$A$2:$FZ$601,0,Sync!$C$15),"yes"),0)+IFERROR(COUNTIFS(INDEX(Clay_Offices!$A$2:$FZ$601,0,Sync!$C$10),A67,INDEX(Clay_Offices!$A$2:$FZ$601,0,Sync!$C$14),"<="&$E$6,INDEX(Clay_Offices!$A$2:$FZ$601,0,Sync!$C$5),Config!$B$20,INDEX(Clay_Offices!$A$2:$FZ$601,0,Sync!$C$15),"maybe"),0)+IFERROR(COUNTIFS(INDEX(Clay_Offices!$A$2:$FZ$601,0,Sync!$C$10),A67,INDEX(Clay_Offices!$A$2:$FZ$601,0,Sync!$C$14),"<="&$E$6,INDEX(Clay_Offices!$A$2:$FZ$601,0,Sync!$C$5),Config!$B$20,INDEX(Clay_Offices!$A$2:$FZ$601,0,Sync!$C$15),"needs_approval"),0)+IFERROR(COUNTIFS(INDEX(Clay_Offices!$A$2:$FZ$601,0,Sync!$C$10),A67,INDEX(Clay_Offices!$A$2:$FZ$601,0,Sync!$C$14),"<="&$E$6,INDEX(Clay_Offices!$A$2:$FZ$601,0,Sync!$C$5),Config!$B$20,INDEX(Clay_Offices!$A$2:$FZ$601,0,Sync!$C$15),"send_info"),0)+IFERROR(COUNTIFS(INDEX(Clay_Offices!$A$2:$FZ$601,0,Sync!$C$10),A67,INDEX(Clay_Offices!$A$2:$FZ$601,0,Sync!$C$14),"<="&$E$6,INDEX(Clay_Offices!$A$2:$FZ$601,0,Sync!$C$5),Config!$B$20,INDEX(Clay_Offices!$A$2:$FZ$601,0,Sync!$C$15),"referral"),0)
A68: office-discovery-B | B68: office | C68: =IFERROR(COUNTIFS(INDEX(Clay_Offices!$A$2:$FZ$601,0,Sync!$C$10),A68,INDEX(Clay_Offices!$A$2:$FZ$601,0,Sync!$C$11),"<="&$E$6,INDEX(Clay_Offices!$A$2:$FZ$601,0,Sync!$C$5),Config!$B$20),0) | D68: =IFERROR(COUNTIFS(INDEX(Clay_Offices!$A$2:$FZ$601,0,Sync!$C$10),A68,INDEX(Clay_Offices!$A$2:$FZ$601,0,Sync!$C$14),"<="&$E$6,INDEX(Clay_Offices!$A$2:$FZ$601,0,Sync!$C$5),Config!$B$20,INDEX(Clay_Offices!$A$2:$FZ$601,0,Sync!$C$15),"<>bounce",INDEX(Clay_Offices!$A$2:$FZ$601,0,Sync!$C$15),"<>out_of_office"),0) | E68: =IF(C68=0,"",D68/C68) | G68: =IFERROR(COUNTIFS(INDEX(Clay_Offices!$A$2:$FZ$601,0,Sync!$C$10),A68,INDEX(Clay_Offices!$A$2:$FZ$601,0,Sync!$C$14),"<="&$E$6,INDEX(Clay_Offices!$A$2:$FZ$601,0,Sync!$C$5),Config!$B$20,INDEX(Clay_Offices!$A$2:$FZ$601,0,Sync!$C$15),"yes"),0)+IFERROR(COUNTIFS(INDEX(Clay_Offices!$A$2:$FZ$601,0,Sync!$C$10),A68,INDEX(Clay_Offices!$A$2:$FZ$601,0,Sync!$C$14),"<="&$E$6,INDEX(Clay_Offices!$A$2:$FZ$601,0,Sync!$C$5),Config!$B$20,INDEX(Clay_Offices!$A$2:$FZ$601,0,Sync!$C$15),"maybe"),0)+IFERROR(COUNTIFS(INDEX(Clay_Offices!$A$2:$FZ$601,0,Sync!$C$10),A68,INDEX(Clay_Offices!$A$2:$FZ$601,0,Sync!$C$14),"<="&$E$6,INDEX(Clay_Offices!$A$2:$FZ$601,0,Sync!$C$5),Config!$B$20,INDEX(Clay_Offices!$A$2:$FZ$601,0,Sync!$C$15),"needs_approval"),0)+IFERROR(COUNTIFS(INDEX(Clay_Offices!$A$2:$FZ$601,0,Sync!$C$10),A68,INDEX(Clay_Offices!$A$2:$FZ$601,0,Sync!$C$14),"<="&$E$6,INDEX(Clay_Offices!$A$2:$FZ$601,0,Sync!$C$5),Config!$B$20,INDEX(Clay_Offices!$A$2:$FZ$601,0,Sync!$C$15),"send_info"),0)+IFERROR(COUNTIFS(INDEX(Clay_Offices!$A$2:$FZ$601,0,Sync!$C$10),A68,INDEX(Clay_Offices!$A$2:$FZ$601,0,Sync!$C$14),"<="&$E$6,INDEX(Clay_Offices!$A$2:$FZ$601,0,Sync!$C$5),Config!$B$20,INDEX(Clay_Offices!$A$2:$FZ$601,0,Sync!$C$15),"referral"),0)
A69: office-selling-A | B69: office | C69: =IFERROR(COUNTIFS(INDEX(Clay_Offices!$A$2:$FZ$601,0,Sync!$C$10),A69,INDEX(Clay_Offices!$A$2:$FZ$601,0,Sync!$C$11),"<="&$E$6,INDEX(Clay_Offices!$A$2:$FZ$601,0,Sync!$C$5),Config!$B$20),0) | D69: =IFERROR(COUNTIFS(INDEX(Clay_Offices!$A$2:$FZ$601,0,Sync!$C$10),A69,INDEX(Clay_Offices!$A$2:$FZ$601,0,Sync!$C$14),"<="&$E$6,INDEX(Clay_Offices!$A$2:$FZ$601,0,Sync!$C$5),Config!$B$20,INDEX(Clay_Offices!$A$2:$FZ$601,0,Sync!$C$15),"<>bounce",INDEX(Clay_Offices!$A$2:$FZ$601,0,Sync!$C$15),"<>out_of_office"),0) | E69: =IF(C69=0,"",D69/C69) | G69: =IFERROR(COUNTIFS(INDEX(Clay_Offices!$A$2:$FZ$601,0,Sync!$C$10),A69,INDEX(Clay_Offices!$A$2:$FZ$601,0,Sync!$C$14),"<="&$E$6,INDEX(Clay_Offices!$A$2:$FZ$601,0,Sync!$C$5),Config!$B$20,INDEX(Clay_Offices!$A$2:$FZ$601,0,Sync!$C$15),"yes"),0)+IFERROR(COUNTIFS(INDEX(Clay_Offices!$A$2:$FZ$601,0,Sync!$C$10),A69,INDEX(Clay_Offices!$A$2:$FZ$601,0,Sync!$C$14),"<="&$E$6,INDEX(Clay_Offices!$A$2:$FZ$601,0,Sync!$C$5),Config!$B$20,INDEX(Clay_Offices!$A$2:$FZ$601,0,Sync!$C$15),"maybe"),0)+IFERROR(COUNTIFS(INDEX(Clay_Offices!$A$2:$FZ$601,0,Sync!$C$10),A69,INDEX(Clay_Offices!$A$2:$FZ$601,0,Sync!$C$14),"<="&$E$6,INDEX(Clay_Offices!$A$2:$FZ$601,0,Sync!$C$5),Config!$B$20,INDEX(Clay_Offices!$A$2:$FZ$601,0,Sync!$C$15),"needs_approval"),0)+IFERROR(COUNTIFS(INDEX(Clay_Offices!$A$2:$FZ$601,0,Sync!$C$10),A69,INDEX(Clay_Offices!$A$2:$FZ$601,0,Sync!$C$14),"<="&$E$6,INDEX(Clay_Offices!$A$2:$FZ$601,0,Sync!$C$5),Config!$B$20,INDEX(Clay_Offices!$A$2:$FZ$601,0,Sync!$C$15),"send_info"),0)+IFERROR(COUNTIFS(INDEX(Clay_Offices!$A$2:$FZ$601,0,Sync!$C$10),A69,INDEX(Clay_Offices!$A$2:$FZ$601,0,Sync!$C$14),"<="&$E$6,INDEX(Clay_Offices!$A$2:$FZ$601,0,Sync!$C$5),Config!$B$20,INDEX(Clay_Offices!$A$2:$FZ$601,0,Sync!$C$15),"referral"),0)
A70: office-selling-B | B70: office | C70: =IFERROR(COUNTIFS(INDEX(Clay_Offices!$A$2:$FZ$601,0,Sync!$C$10),A70,INDEX(Clay_Offices!$A$2:$FZ$601,0,Sync!$C$11),"<="&$E$6,INDEX(Clay_Offices!$A$2:$FZ$601,0,Sync!$C$5),Config!$B$20),0) | D70: =IFERROR(COUNTIFS(INDEX(Clay_Offices!$A$2:$FZ$601,0,Sync!$C$10),A70,INDEX(Clay_Offices!$A$2:$FZ$601,0,Sync!$C$14),"<="&$E$6,INDEX(Clay_Offices!$A$2:$FZ$601,0,Sync!$C$5),Config!$B$20,INDEX(Clay_Offices!$A$2:$FZ$601,0,Sync!$C$15),"<>bounce",INDEX(Clay_Offices!$A$2:$FZ$601,0,Sync!$C$15),"<>out_of_office"),0) | E70: =IF(C70=0,"",D70/C70) | G70: =IFERROR(COUNTIFS(INDEX(Clay_Offices!$A$2:$FZ$601,0,Sync!$C$10),A70,INDEX(Clay_Offices!$A$2:$FZ$601,0,Sync!$C$14),"<="&$E$6,INDEX(Clay_Offices!$A$2:$FZ$601,0,Sync!$C$5),Config!$B$20,INDEX(Clay_Offices!$A$2:$FZ$601,0,Sync!$C$15),"yes"),0)+IFERROR(COUNTIFS(INDEX(Clay_Offices!$A$2:$FZ$601,0,Sync!$C$10),A70,INDEX(Clay_Offices!$A$2:$FZ$601,0,Sync!$C$14),"<="&$E$6,INDEX(Clay_Offices!$A$2:$FZ$601,0,Sync!$C$5),Config!$B$20,INDEX(Clay_Offices!$A$2:$FZ$601,0,Sync!$C$15),"maybe"),0)+IFERROR(COUNTIFS(INDEX(Clay_Offices!$A$2:$FZ$601,0,Sync!$C$10),A70,INDEX(Clay_Offices!$A$2:$FZ$601,0,Sync!$C$14),"<="&$E$6,INDEX(Clay_Offices!$A$2:$FZ$601,0,Sync!$C$5),Config!$B$20,INDEX(Clay_Offices!$A$2:$FZ$601,0,Sync!$C$15),"needs_approval"),0)+IFERROR(COUNTIFS(INDEX(Clay_Offices!$A$2:$FZ$601,0,Sync!$C$10),A70,INDEX(Clay_Offices!$A$2:$FZ$601,0,Sync!$C$14),"<="&$E$6,INDEX(Clay_Offices!$A$2:$FZ$601,0,Sync!$C$5),Config!$B$20,INDEX(Clay_Offices!$A$2:$FZ$601,0,Sync!$C$15),"send_info"),0)+IFERROR(COUNTIFS(INDEX(Clay_Offices!$A$2:$FZ$601,0,Sync!$C$10),A70,INDEX(Clay_Offices!$A$2:$FZ$601,0,Sync!$C$14),"<="&$E$6,INDEX(Clay_Offices!$A$2:$FZ$601,0,Sync!$C$5),Config!$B$20,INDEX(Clay_Offices!$A$2:$FZ$601,0,Sync!$C$15),"referral"),0)
A71: brand-discovery-A | B71: brand | C71: =IFERROR(COUNTIFS(INDEX(Clay_Brands!$A$2:$FZ$601,0,Sync!$D$10),A71,INDEX(Clay_Brands!$A$2:$FZ$601,0,Sync!$D$11),"<="&$E$6,INDEX(Clay_Brands!$A$2:$FZ$601,0,Sync!$D$5),Config!$B$20),0) | D71: =IFERROR(COUNTIFS(INDEX(Clay_Brands!$A$2:$FZ$601,0,Sync!$D$10),A71,INDEX(Clay_Brands!$A$2:$FZ$601,0,Sync!$D$14),"<="&$E$6,INDEX(Clay_Brands!$A$2:$FZ$601,0,Sync!$D$5),Config!$B$20,INDEX(Clay_Brands!$A$2:$FZ$601,0,Sync!$D$15),"<>bounce",INDEX(Clay_Brands!$A$2:$FZ$601,0,Sync!$D$15),"<>out_of_office"),0) | E71: =IF(C71=0,"",D71/C71) | G71: =IFERROR(COUNTIFS(INDEX(Clay_Brands!$A$2:$FZ$601,0,Sync!$D$10),A71,INDEX(Clay_Brands!$A$2:$FZ$601,0,Sync!$D$14),"<="&$E$6,INDEX(Clay_Brands!$A$2:$FZ$601,0,Sync!$D$5),Config!$B$20,INDEX(Clay_Brands!$A$2:$FZ$601,0,Sync!$D$15),"yes"),0)+IFERROR(COUNTIFS(INDEX(Clay_Brands!$A$2:$FZ$601,0,Sync!$D$10),A71,INDEX(Clay_Brands!$A$2:$FZ$601,0,Sync!$D$14),"<="&$E$6,INDEX(Clay_Brands!$A$2:$FZ$601,0,Sync!$D$5),Config!$B$20,INDEX(Clay_Brands!$A$2:$FZ$601,0,Sync!$D$15),"maybe"),0)+IFERROR(COUNTIFS(INDEX(Clay_Brands!$A$2:$FZ$601,0,Sync!$D$10),A71,INDEX(Clay_Brands!$A$2:$FZ$601,0,Sync!$D$14),"<="&$E$6,INDEX(Clay_Brands!$A$2:$FZ$601,0,Sync!$D$5),Config!$B$20,INDEX(Clay_Brands!$A$2:$FZ$601,0,Sync!$D$15),"needs_approval"),0)+IFERROR(COUNTIFS(INDEX(Clay_Brands!$A$2:$FZ$601,0,Sync!$D$10),A71,INDEX(Clay_Brands!$A$2:$FZ$601,0,Sync!$D$14),"<="&$E$6,INDEX(Clay_Brands!$A$2:$FZ$601,0,Sync!$D$5),Config!$B$20,INDEX(Clay_Brands!$A$2:$FZ$601,0,Sync!$D$15),"send_info"),0)+IFERROR(COUNTIFS(INDEX(Clay_Brands!$A$2:$FZ$601,0,Sync!$D$10),A71,INDEX(Clay_Brands!$A$2:$FZ$601,0,Sync!$D$14),"<="&$E$6,INDEX(Clay_Brands!$A$2:$FZ$601,0,Sync!$D$5),Config!$B$20,INDEX(Clay_Brands!$A$2:$FZ$601,0,Sync!$D$15),"referral"),0)
A72: brand-discovery-B | B72: brand | C72: =IFERROR(COUNTIFS(INDEX(Clay_Brands!$A$2:$FZ$601,0,Sync!$D$10),A72,INDEX(Clay_Brands!$A$2:$FZ$601,0,Sync!$D$11),"<="&$E$6,INDEX(Clay_Brands!$A$2:$FZ$601,0,Sync!$D$5),Config!$B$20),0) | D72: =IFERROR(COUNTIFS(INDEX(Clay_Brands!$A$2:$FZ$601,0,Sync!$D$10),A72,INDEX(Clay_Brands!$A$2:$FZ$601,0,Sync!$D$14),"<="&$E$6,INDEX(Clay_Brands!$A$2:$FZ$601,0,Sync!$D$5),Config!$B$20,INDEX(Clay_Brands!$A$2:$FZ$601,0,Sync!$D$15),"<>bounce",INDEX(Clay_Brands!$A$2:$FZ$601,0,Sync!$D$15),"<>out_of_office"),0) | E72: =IF(C72=0,"",D72/C72) | G72: =IFERROR(COUNTIFS(INDEX(Clay_Brands!$A$2:$FZ$601,0,Sync!$D$10),A72,INDEX(Clay_Brands!$A$2:$FZ$601,0,Sync!$D$14),"<="&$E$6,INDEX(Clay_Brands!$A$2:$FZ$601,0,Sync!$D$5),Config!$B$20,INDEX(Clay_Brands!$A$2:$FZ$601,0,Sync!$D$15),"yes"),0)+IFERROR(COUNTIFS(INDEX(Clay_Brands!$A$2:$FZ$601,0,Sync!$D$10),A72,INDEX(Clay_Brands!$A$2:$FZ$601,0,Sync!$D$14),"<="&$E$6,INDEX(Clay_Brands!$A$2:$FZ$601,0,Sync!$D$5),Config!$B$20,INDEX(Clay_Brands!$A$2:$FZ$601,0,Sync!$D$15),"maybe"),0)+IFERROR(COUNTIFS(INDEX(Clay_Brands!$A$2:$FZ$601,0,Sync!$D$10),A72,INDEX(Clay_Brands!$A$2:$FZ$601,0,Sync!$D$14),"<="&$E$6,INDEX(Clay_Brands!$A$2:$FZ$601,0,Sync!$D$5),Config!$B$20,INDEX(Clay_Brands!$A$2:$FZ$601,0,Sync!$D$15),"needs_approval"),0)+IFERROR(COUNTIFS(INDEX(Clay_Brands!$A$2:$FZ$601,0,Sync!$D$10),A72,INDEX(Clay_Brands!$A$2:$FZ$601,0,Sync!$D$14),"<="&$E$6,INDEX(Clay_Brands!$A$2:$FZ$601,0,Sync!$D$5),Config!$B$20,INDEX(Clay_Brands!$A$2:$FZ$601,0,Sync!$D$15),"send_info"),0)+IFERROR(COUNTIFS(INDEX(Clay_Brands!$A$2:$FZ$601,0,Sync!$D$10),A72,INDEX(Clay_Brands!$A$2:$FZ$601,0,Sync!$D$14),"<="&$E$6,INDEX(Clay_Brands!$A$2:$FZ$601,0,Sync!$D$5),Config!$B$20,INDEX(Clay_Brands!$A$2:$FZ$601,0,Sync!$D$15),"referral"),0)
A73: brand-selling-A | B73: brand | C73: =IFERROR(COUNTIFS(INDEX(Clay_Brands!$A$2:$FZ$601,0,Sync!$D$10),A73,INDEX(Clay_Brands!$A$2:$FZ$601,0,Sync!$D$11),"<="&$E$6,INDEX(Clay_Brands!$A$2:$FZ$601,0,Sync!$D$5),Config!$B$20),0) | D73: =IFERROR(COUNTIFS(INDEX(Clay_Brands!$A$2:$FZ$601,0,Sync!$D$10),A73,INDEX(Clay_Brands!$A$2:$FZ$601,0,Sync!$D$14),"<="&$E$6,INDEX(Clay_Brands!$A$2:$FZ$601,0,Sync!$D$5),Config!$B$20,INDEX(Clay_Brands!$A$2:$FZ$601,0,Sync!$D$15),"<>bounce",INDEX(Clay_Brands!$A$2:$FZ$601,0,Sync!$D$15),"<>out_of_office"),0) | E73: =IF(C73=0,"",D73/C73) | G73: =IFERROR(COUNTIFS(INDEX(Clay_Brands!$A$2:$FZ$601,0,Sync!$D$10),A73,INDEX(Clay_Brands!$A$2:$FZ$601,0,Sync!$D$14),"<="&$E$6,INDEX(Clay_Brands!$A$2:$FZ$601,0,Sync!$D$5),Config!$B$20,INDEX(Clay_Brands!$A$2:$FZ$601,0,Sync!$D$15),"yes"),0)+IFERROR(COUNTIFS(INDEX(Clay_Brands!$A$2:$FZ$601,0,Sync!$D$10),A73,INDEX(Clay_Brands!$A$2:$FZ$601,0,Sync!$D$14),"<="&$E$6,INDEX(Clay_Brands!$A$2:$FZ$601,0,Sync!$D$5),Config!$B$20,INDEX(Clay_Brands!$A$2:$FZ$601,0,Sync!$D$15),"maybe"),0)+IFERROR(COUNTIFS(INDEX(Clay_Brands!$A$2:$FZ$601,0,Sync!$D$10),A73,INDEX(Clay_Brands!$A$2:$FZ$601,0,Sync!$D$14),"<="&$E$6,INDEX(Clay_Brands!$A$2:$FZ$601,0,Sync!$D$5),Config!$B$20,INDEX(Clay_Brands!$A$2:$FZ$601,0,Sync!$D$15),"needs_approval"),0)+IFERROR(COUNTIFS(INDEX(Clay_Brands!$A$2:$FZ$601,0,Sync!$D$10),A73,INDEX(Clay_Brands!$A$2:$FZ$601,0,Sync!$D$14),"<="&$E$6,INDEX(Clay_Brands!$A$2:$FZ$601,0,Sync!$D$5),Config!$B$20,INDEX(Clay_Brands!$A$2:$FZ$601,0,Sync!$D$15),"send_info"),0)+IFERROR(COUNTIFS(INDEX(Clay_Brands!$A$2:$FZ$601,0,Sync!$D$10),A73,INDEX(Clay_Brands!$A$2:$FZ$601,0,Sync!$D$14),"<="&$E$6,INDEX(Clay_Brands!$A$2:$FZ$601,0,Sync!$D$5),Config!$B$20,INDEX(Clay_Brands!$A$2:$FZ$601,0,Sync!$D$15),"referral"),0)
A74: brand-selling-B | B74: brand | C74: =IFERROR(COUNTIFS(INDEX(Clay_Brands!$A$2:$FZ$601,0,Sync!$D$10),A74,INDEX(Clay_Brands!$A$2:$FZ$601,0,Sync!$D$11),"<="&$E$6,INDEX(Clay_Brands!$A$2:$FZ$601,0,Sync!$D$5),Config!$B$20),0) | D74: =IFERROR(COUNTIFS(INDEX(Clay_Brands!$A$2:$FZ$601,0,Sync!$D$10),A74,INDEX(Clay_Brands!$A$2:$FZ$601,0,Sync!$D$14),"<="&$E$6,INDEX(Clay_Brands!$A$2:$FZ$601,0,Sync!$D$5),Config!$B$20,INDEX(Clay_Brands!$A$2:$FZ$601,0,Sync!$D$15),"<>bounce",INDEX(Clay_Brands!$A$2:$FZ$601,0,Sync!$D$15),"<>out_of_office"),0) | E74: =IF(C74=0,"",D74/C74) | G74: =IFERROR(COUNTIFS(INDEX(Clay_Brands!$A$2:$FZ$601,0,Sync!$D$10),A74,INDEX(Clay_Brands!$A$2:$FZ$601,0,Sync!$D$14),"<="&$E$6,INDEX(Clay_Brands!$A$2:$FZ$601,0,Sync!$D$5),Config!$B$20,INDEX(Clay_Brands!$A$2:$FZ$601,0,Sync!$D$15),"yes"),0)+IFERROR(COUNTIFS(INDEX(Clay_Brands!$A$2:$FZ$601,0,Sync!$D$10),A74,INDEX(Clay_Brands!$A$2:$FZ$601,0,Sync!$D$14),"<="&$E$6,INDEX(Clay_Brands!$A$2:$FZ$601,0,Sync!$D$5),Config!$B$20,INDEX(Clay_Brands!$A$2:$FZ$601,0,Sync!$D$15),"maybe"),0)+IFERROR(COUNTIFS(INDEX(Clay_Brands!$A$2:$FZ$601,0,Sync!$D$10),A74,INDEX(Clay_Brands!$A$2:$FZ$601,0,Sync!$D$14),"<="&$E$6,INDEX(Clay_Brands!$A$2:$FZ$601,0,Sync!$D$5),Config!$B$20,INDEX(Clay_Brands!$A$2:$FZ$601,0,Sync!$D$15),"needs_approval"),0)+IFERROR(COUNTIFS(INDEX(Clay_Brands!$A$2:$FZ$601,0,Sync!$D$10),A74,INDEX(Clay_Brands!$A$2:$FZ$601,0,Sync!$D$14),"<="&$E$6,INDEX(Clay_Brands!$A$2:$FZ$601,0,Sync!$D$5),Config!$B$20,INDEX(Clay_Brands!$A$2:$FZ$601,0,Sync!$D$15),"send_info"),0)+IFERROR(COUNTIFS(INDEX(Clay_Brands!$A$2:$FZ$601,0,Sync!$D$10),A74,INDEX(Clay_Brands!$A$2:$FZ$601,0,Sync!$D$14),"<="&$E$6,INDEX(Clay_Brands!$A$2:$FZ$601,0,Sync!$D$5),Config!$B$20,INDEX(Clay_Brands!$A$2:$FZ$601,0,Sync!$D$15),"referral"),0)
A75: office-conversion-A | B75: office | C75: =IFERROR(COUNTIFS(INDEX(Clay_Offices!$A$2:$FZ$601,0,Sync!$C$10),A75,INDEX(Clay_Offices!$A$2:$FZ$601,0,Sync!$C$11),"<="&$E$6,INDEX(Clay_Offices!$A$2:$FZ$601,0,Sync!$C$5),Config!$B$20),0) | D75: =IFERROR(COUNTIFS(INDEX(Clay_Offices!$A$2:$FZ$601,0,Sync!$C$10),A75,INDEX(Clay_Offices!$A$2:$FZ$601,0,Sync!$C$14),"<="&$E$6,INDEX(Clay_Offices!$A$2:$FZ$601,0,Sync!$C$5),Config!$B$20,INDEX(Clay_Offices!$A$2:$FZ$601,0,Sync!$C$15),"<>bounce",INDEX(Clay_Offices!$A$2:$FZ$601,0,Sync!$C$15),"<>out_of_office"),0) | E75: =IF(C75=0,"",D75/C75) | G75: =IFERROR(COUNTIFS(INDEX(Clay_Offices!$A$2:$FZ$601,0,Sync!$C$10),A75,INDEX(Clay_Offices!$A$2:$FZ$601,0,Sync!$C$14),"<="&$E$6,INDEX(Clay_Offices!$A$2:$FZ$601,0,Sync!$C$5),Config!$B$20,INDEX(Clay_Offices!$A$2:$FZ$601,0,Sync!$C$15),"yes"),0)+IFERROR(COUNTIFS(INDEX(Clay_Offices!$A$2:$FZ$601,0,Sync!$C$10),A75,INDEX(Clay_Offices!$A$2:$FZ$601,0,Sync!$C$14),"<="&$E$6,INDEX(Clay_Offices!$A$2:$FZ$601,0,Sync!$C$5),Config!$B$20,INDEX(Clay_Offices!$A$2:$FZ$601,0,Sync!$C$15),"maybe"),0)+IFERROR(COUNTIFS(INDEX(Clay_Offices!$A$2:$FZ$601,0,Sync!$C$10),A75,INDEX(Clay_Offices!$A$2:$FZ$601,0,Sync!$C$14),"<="&$E$6,INDEX(Clay_Offices!$A$2:$FZ$601,0,Sync!$C$5),Config!$B$20,INDEX(Clay_Offices!$A$2:$FZ$601,0,Sync!$C$15),"needs_approval"),0)+IFERROR(COUNTIFS(INDEX(Clay_Offices!$A$2:$FZ$601,0,Sync!$C$10),A75,INDEX(Clay_Offices!$A$2:$FZ$601,0,Sync!$C$14),"<="&$E$6,INDEX(Clay_Offices!$A$2:$FZ$601,0,Sync!$C$5),Config!$B$20,INDEX(Clay_Offices!$A$2:$FZ$601,0,Sync!$C$15),"send_info"),0)+IFERROR(COUNTIFS(INDEX(Clay_Offices!$A$2:$FZ$601,0,Sync!$C$10),A75,INDEX(Clay_Offices!$A$2:$FZ$601,0,Sync!$C$14),"<="&$E$6,INDEX(Clay_Offices!$A$2:$FZ$601,0,Sync!$C$5),Config!$B$20,INDEX(Clay_Offices!$A$2:$FZ$601,0,Sync!$C$15),"referral"),0)
A76: brand-conversion-A | B76: brand | C76: =IFERROR(COUNTIFS(INDEX(Clay_Brands!$A$2:$FZ$601,0,Sync!$D$10),A76,INDEX(Clay_Brands!$A$2:$FZ$601,0,Sync!$D$11),"<="&$E$6,INDEX(Clay_Brands!$A$2:$FZ$601,0,Sync!$D$5),Config!$B$20),0) | D76: =IFERROR(COUNTIFS(INDEX(Clay_Brands!$A$2:$FZ$601,0,Sync!$D$10),A76,INDEX(Clay_Brands!$A$2:$FZ$601,0,Sync!$D$14),"<="&$E$6,INDEX(Clay_Brands!$A$2:$FZ$601,0,Sync!$D$5),Config!$B$20,INDEX(Clay_Brands!$A$2:$FZ$601,0,Sync!$D$15),"<>bounce",INDEX(Clay_Brands!$A$2:$FZ$601,0,Sync!$D$15),"<>out_of_office"),0) | E76: =IF(C76=0,"",D76/C76) | G76: =IFERROR(COUNTIFS(INDEX(Clay_Brands!$A$2:$FZ$601,0,Sync!$D$10),A76,INDEX(Clay_Brands!$A$2:$FZ$601,0,Sync!$D$14),"<="&$E$6,INDEX(Clay_Brands!$A$2:$FZ$601,0,Sync!$D$5),Config!$B$20,INDEX(Clay_Brands!$A$2:$FZ$601,0,Sync!$D$15),"yes"),0)+IFERROR(COUNTIFS(INDEX(Clay_Brands!$A$2:$FZ$601,0,Sync!$D$10),A76,INDEX(Clay_Brands!$A$2:$FZ$601,0,Sync!$D$14),"<="&$E$6,INDEX(Clay_Brands!$A$2:$FZ$601,0,Sync!$D$5),Config!$B$20,INDEX(Clay_Brands!$A$2:$FZ$601,0,Sync!$D$15),"maybe"),0)+IFERROR(COUNTIFS(INDEX(Clay_Brands!$A$2:$FZ$601,0,Sync!$D$10),A76,INDEX(Clay_Brands!$A$2:$FZ$601,0,Sync!$D$14),"<="&$E$6,INDEX(Clay_Brands!$A$2:$FZ$601,0,Sync!$D$5),Config!$B$20,INDEX(Clay_Brands!$A$2:$FZ$601,0,Sync!$D$15),"needs_approval"),0)+IFERROR(COUNTIFS(INDEX(Clay_Brands!$A$2:$FZ$601,0,Sync!$D$10),A76,INDEX(Clay_Brands!$A$2:$FZ$601,0,Sync!$D$14),"<="&$E$6,INDEX(Clay_Brands!$A$2:$FZ$601,0,Sync!$D$5),Config!$B$20,INDEX(Clay_Brands!$A$2:$FZ$601,0,Sync!$D$15),"send_info"),0)+IFERROR(COUNTIFS(INDEX(Clay_Brands!$A$2:$FZ$601,0,Sync!$D$10),A76,INDEX(Clay_Brands!$A$2:$FZ$601,0,Sync!$D$14),"<="&$E$6,INDEX(Clay_Brands!$A$2:$FZ$601,0,Sync!$D$5),Config!$B$20,INDEX(Clay_Brands!$A$2:$FZ$601,0,Sync!$D$15),"referral"),0)
A77: channel: email | B77: office | C77: =IFERROR(COUNTIFS(INDEX(Clay_Offices!$A$2:$FZ$601,0,Sync!$C$9),"email",INDEX(Clay_Offices!$A$2:$FZ$601,0,Sync!$C$11),"<="&$E$6,INDEX(Clay_Offices!$A$2:$FZ$601,0,Sync!$C$5),Config!$B$20),0) | D77: =IFERROR(COUNTIFS(INDEX(Clay_Offices!$A$2:$FZ$601,0,Sync!$C$9),"email",INDEX(Clay_Offices!$A$2:$FZ$601,0,Sync!$C$14),"<="&$E$6,INDEX(Clay_Offices!$A$2:$FZ$601,0,Sync!$C$5),Config!$B$20,INDEX(Clay_Offices!$A$2:$FZ$601,0,Sync!$C$15),"<>bounce",INDEX(Clay_Offices!$A$2:$FZ$601,0,Sync!$C$15),"<>out_of_office"),0) | E77: =IF(C77=0,"",D77/C77) | G77: =IFERROR(COUNTIFS(INDEX(Clay_Offices!$A$2:$FZ$601,0,Sync!$C$9),"email",INDEX(Clay_Offices!$A$2:$FZ$601,0,Sync!$C$14),"<="&$E$6,INDEX(Clay_Offices!$A$2:$FZ$601,0,Sync!$C$5),Config!$B$20,INDEX(Clay_Offices!$A$2:$FZ$601,0,Sync!$C$15),"yes"),0)+IFERROR(COUNTIFS(INDEX(Clay_Offices!$A$2:$FZ$601,0,Sync!$C$9),"email",INDEX(Clay_Offices!$A$2:$FZ$601,0,Sync!$C$14),"<="&$E$6,INDEX(Clay_Offices!$A$2:$FZ$601,0,Sync!$C$5),Config!$B$20,INDEX(Clay_Offices!$A$2:$FZ$601,0,Sync!$C$15),"maybe"),0)+IFERROR(COUNTIFS(INDEX(Clay_Offices!$A$2:$FZ$601,0,Sync!$C$9),"email",INDEX(Clay_Offices!$A$2:$FZ$601,0,Sync!$C$14),"<="&$E$6,INDEX(Clay_Offices!$A$2:$FZ$601,0,Sync!$C$5),Config!$B$20,INDEX(Clay_Offices!$A$2:$FZ$601,0,Sync!$C$15),"needs_approval"),0)+IFERROR(COUNTIFS(INDEX(Clay_Offices!$A$2:$FZ$601,0,Sync!$C$9),"email",INDEX(Clay_Offices!$A$2:$FZ$601,0,Sync!$C$14),"<="&$E$6,INDEX(Clay_Offices!$A$2:$FZ$601,0,Sync!$C$5),Config!$B$20,INDEX(Clay_Offices!$A$2:$FZ$601,0,Sync!$C$15),"send_info"),0)+IFERROR(COUNTIFS(INDEX(Clay_Offices!$A$2:$FZ$601,0,Sync!$C$9),"email",INDEX(Clay_Offices!$A$2:$FZ$601,0,Sync!$C$14),"<="&$E$6,INDEX(Clay_Offices!$A$2:$FZ$601,0,Sync!$C$5),Config!$B$20,INDEX(Clay_Offices!$A$2:$FZ$601,0,Sync!$C$15),"referral"),0)
A78: channel: email | B78: brand | C78: =IFERROR(COUNTIFS(INDEX(Clay_Brands!$A$2:$FZ$601,0,Sync!$D$9),"email",INDEX(Clay_Brands!$A$2:$FZ$601,0,Sync!$D$11),"<="&$E$6,INDEX(Clay_Brands!$A$2:$FZ$601,0,Sync!$D$5),Config!$B$20),0) | D78: =IFERROR(COUNTIFS(INDEX(Clay_Brands!$A$2:$FZ$601,0,Sync!$D$9),"email",INDEX(Clay_Brands!$A$2:$FZ$601,0,Sync!$D$14),"<="&$E$6,INDEX(Clay_Brands!$A$2:$FZ$601,0,Sync!$D$5),Config!$B$20,INDEX(Clay_Brands!$A$2:$FZ$601,0,Sync!$D$15),"<>bounce",INDEX(Clay_Brands!$A$2:$FZ$601,0,Sync!$D$15),"<>out_of_office"),0) | E78: =IF(C78=0,"",D78/C78) | G78: =IFERROR(COUNTIFS(INDEX(Clay_Brands!$A$2:$FZ$601,0,Sync!$D$9),"email",INDEX(Clay_Brands!$A$2:$FZ$601,0,Sync!$D$14),"<="&$E$6,INDEX(Clay_Brands!$A$2:$FZ$601,0,Sync!$D$5),Config!$B$20,INDEX(Clay_Brands!$A$2:$FZ$601,0,Sync!$D$15),"yes"),0)+IFERROR(COUNTIFS(INDEX(Clay_Brands!$A$2:$FZ$601,0,Sync!$D$9),"email",INDEX(Clay_Brands!$A$2:$FZ$601,0,Sync!$D$14),"<="&$E$6,INDEX(Clay_Brands!$A$2:$FZ$601,0,Sync!$D$5),Config!$B$20,INDEX(Clay_Brands!$A$2:$FZ$601,0,Sync!$D$15),"maybe"),0)+IFERROR(COUNTIFS(INDEX(Clay_Brands!$A$2:$FZ$601,0,Sync!$D$9),"email",INDEX(Clay_Brands!$A$2:$FZ$601,0,Sync!$D$14),"<="&$E$6,INDEX(Clay_Brands!$A$2:$FZ$601,0,Sync!$D$5),Config!$B$20,INDEX(Clay_Brands!$A$2:$FZ$601,0,Sync!$D$15),"needs_approval"),0)+IFERROR(COUNTIFS(INDEX(Clay_Brands!$A$2:$FZ$601,0,Sync!$D$9),"email",INDEX(Clay_Brands!$A$2:$FZ$601,0,Sync!$D$14),"<="&$E$6,INDEX(Clay_Brands!$A$2:$FZ$601,0,Sync!$D$5),Config!$B$20,INDEX(Clay_Brands!$A$2:$FZ$601,0,Sync!$D$15),"send_info"),0)+IFERROR(COUNTIFS(INDEX(Clay_Brands!$A$2:$FZ$601,0,Sync!$D$9),"email",INDEX(Clay_Brands!$A$2:$FZ$601,0,Sync!$D$14),"<="&$E$6,INDEX(Clay_Brands!$A$2:$FZ$601,0,Sync!$D$5),Config!$B$20,INDEX(Clay_Brands!$A$2:$FZ$601,0,Sync!$D$15),"referral"),0)
A79: channel: linkedin | B79: office | C79: =IFERROR(COUNTIFS(INDEX(Clay_Offices!$A$2:$FZ$601,0,Sync!$C$9),"linkedin",INDEX(Clay_Offices!$A$2:$FZ$601,0,Sync!$C$11),"<="&$E$6,INDEX(Clay_Offices!$A$2:$FZ$601,0,Sync!$C$5),Config!$B$20),0) | D79: =IFERROR(COUNTIFS(INDEX(Clay_Offices!$A$2:$FZ$601,0,Sync!$C$9),"linkedin",INDEX(Clay_Offices!$A$2:$FZ$601,0,Sync!$C$14),"<="&$E$6,INDEX(Clay_Offices!$A$2:$FZ$601,0,Sync!$C$5),Config!$B$20,INDEX(Clay_Offices!$A$2:$FZ$601,0,Sync!$C$15),"<>bounce",INDEX(Clay_Offices!$A$2:$FZ$601,0,Sync!$C$15),"<>out_of_office"),0) | E79: =IF(C79=0,"",D79/C79) | G79: =IFERROR(COUNTIFS(INDEX(Clay_Offices!$A$2:$FZ$601,0,Sync!$C$9),"linkedin",INDEX(Clay_Offices!$A$2:$FZ$601,0,Sync!$C$14),"<="&$E$6,INDEX(Clay_Offices!$A$2:$FZ$601,0,Sync!$C$5),Config!$B$20,INDEX(Clay_Offices!$A$2:$FZ$601,0,Sync!$C$15),"yes"),0)+IFERROR(COUNTIFS(INDEX(Clay_Offices!$A$2:$FZ$601,0,Sync!$C$9),"linkedin",INDEX(Clay_Offices!$A$2:$FZ$601,0,Sync!$C$14),"<="&$E$6,INDEX(Clay_Offices!$A$2:$FZ$601,0,Sync!$C$5),Config!$B$20,INDEX(Clay_Offices!$A$2:$FZ$601,0,Sync!$C$15),"maybe"),0)+IFERROR(COUNTIFS(INDEX(Clay_Offices!$A$2:$FZ$601,0,Sync!$C$9),"linkedin",INDEX(Clay_Offices!$A$2:$FZ$601,0,Sync!$C$14),"<="&$E$6,INDEX(Clay_Offices!$A$2:$FZ$601,0,Sync!$C$5),Config!$B$20,INDEX(Clay_Offices!$A$2:$FZ$601,0,Sync!$C$15),"needs_approval"),0)+IFERROR(COUNTIFS(INDEX(Clay_Offices!$A$2:$FZ$601,0,Sync!$C$9),"linkedin",INDEX(Clay_Offices!$A$2:$FZ$601,0,Sync!$C$14),"<="&$E$6,INDEX(Clay_Offices!$A$2:$FZ$601,0,Sync!$C$5),Config!$B$20,INDEX(Clay_Offices!$A$2:$FZ$601,0,Sync!$C$15),"send_info"),0)+IFERROR(COUNTIFS(INDEX(Clay_Offices!$A$2:$FZ$601,0,Sync!$C$9),"linkedin",INDEX(Clay_Offices!$A$2:$FZ$601,0,Sync!$C$14),"<="&$E$6,INDEX(Clay_Offices!$A$2:$FZ$601,0,Sync!$C$5),Config!$B$20,INDEX(Clay_Offices!$A$2:$FZ$601,0,Sync!$C$15),"referral"),0)
A80: channel: linkedin | B80: brand | C80: =IFERROR(COUNTIFS(INDEX(Clay_Brands!$A$2:$FZ$601,0,Sync!$D$9),"linkedin",INDEX(Clay_Brands!$A$2:$FZ$601,0,Sync!$D$11),"<="&$E$6,INDEX(Clay_Brands!$A$2:$FZ$601,0,Sync!$D$5),Config!$B$20),0) | D80: =IFERROR(COUNTIFS(INDEX(Clay_Brands!$A$2:$FZ$601,0,Sync!$D$9),"linkedin",INDEX(Clay_Brands!$A$2:$FZ$601,0,Sync!$D$14),"<="&$E$6,INDEX(Clay_Brands!$A$2:$FZ$601,0,Sync!$D$5),Config!$B$20,INDEX(Clay_Brands!$A$2:$FZ$601,0,Sync!$D$15),"<>bounce",INDEX(Clay_Brands!$A$2:$FZ$601,0,Sync!$D$15),"<>out_of_office"),0) | E80: =IF(C80=0,"",D80/C80) | G80: =IFERROR(COUNTIFS(INDEX(Clay_Brands!$A$2:$FZ$601,0,Sync!$D$9),"linkedin",INDEX(Clay_Brands!$A$2:$FZ$601,0,Sync!$D$14),"<="&$E$6,INDEX(Clay_Brands!$A$2:$FZ$601,0,Sync!$D$5),Config!$B$20,INDEX(Clay_Brands!$A$2:$FZ$601,0,Sync!$D$15),"yes"),0)+IFERROR(COUNTIFS(INDEX(Clay_Brands!$A$2:$FZ$601,0,Sync!$D$9),"linkedin",INDEX(Clay_Brands!$A$2:$FZ$601,0,Sync!$D$14),"<="&$E$6,INDEX(Clay_Brands!$A$2:$FZ$601,0,Sync!$D$5),Config!$B$20,INDEX(Clay_Brands!$A$2:$FZ$601,0,Sync!$D$15),"maybe"),0)+IFERROR(COUNTIFS(INDEX(Clay_Brands!$A$2:$FZ$601,0,Sync!$D$9),"linkedin",INDEX(Clay_Brands!$A$2:$FZ$601,0,Sync!$D$14),"<="&$E$6,INDEX(Clay_Brands!$A$2:$FZ$601,0,Sync!$D$5),Config!$B$20,INDEX(Clay_Brands!$A$2:$FZ$601,0,Sync!$D$15),"needs_approval"),0)+IFERROR(COUNTIFS(INDEX(Clay_Brands!$A$2:$FZ$601,0,Sync!$D$9),"linkedin",INDEX(Clay_Brands!$A$2:$FZ$601,0,Sync!$D$14),"<="&$E$6,INDEX(Clay_Brands!$A$2:$FZ$601,0,Sync!$D$5),Config!$B$20,INDEX(Clay_Brands!$A$2:$FZ$601,0,Sync!$D$15),"send_info"),0)+IFERROR(COUNTIFS(INDEX(Clay_Brands!$A$2:$FZ$601,0,Sync!$D$9),"linkedin",INDEX(Clay_Brands!$A$2:$FZ$601,0,Sync!$D$14),"<="&$E$6,INDEX(Clay_Brands!$A$2:$FZ$601,0,Sync!$D$5),Config!$B$20,INDEX(Clay_Brands!$A$2:$FZ$601,0,Sync!$D$15),"referral"),0)
A81: channel: warm-intro | B81: office | C81: =IFERROR(COUNTIFS(INDEX(Clay_Offices!$A$2:$FZ$601,0,Sync!$C$9),"warm-intro",INDEX(Clay_Offices!$A$2:$FZ$601,0,Sync!$C$11),"<="&$E$6,INDEX(Clay_Offices!$A$2:$FZ$601,0,Sync!$C$5),Config!$B$20),0) | D81: =IFERROR(COUNTIFS(INDEX(Clay_Offices!$A$2:$FZ$601,0,Sync!$C$9),"warm-intro",INDEX(Clay_Offices!$A$2:$FZ$601,0,Sync!$C$14),"<="&$E$6,INDEX(Clay_Offices!$A$2:$FZ$601,0,Sync!$C$5),Config!$B$20,INDEX(Clay_Offices!$A$2:$FZ$601,0,Sync!$C$15),"<>bounce",INDEX(Clay_Offices!$A$2:$FZ$601,0,Sync!$C$15),"<>out_of_office"),0) | E81: =IF(C81=0,"",D81/C81) | G81: =IFERROR(COUNTIFS(INDEX(Clay_Offices!$A$2:$FZ$601,0,Sync!$C$9),"warm-intro",INDEX(Clay_Offices!$A$2:$FZ$601,0,Sync!$C$14),"<="&$E$6,INDEX(Clay_Offices!$A$2:$FZ$601,0,Sync!$C$5),Config!$B$20,INDEX(Clay_Offices!$A$2:$FZ$601,0,Sync!$C$15),"yes"),0)+IFERROR(COUNTIFS(INDEX(Clay_Offices!$A$2:$FZ$601,0,Sync!$C$9),"warm-intro",INDEX(Clay_Offices!$A$2:$FZ$601,0,Sync!$C$14),"<="&$E$6,INDEX(Clay_Offices!$A$2:$FZ$601,0,Sync!$C$5),Config!$B$20,INDEX(Clay_Offices!$A$2:$FZ$601,0,Sync!$C$15),"maybe"),0)+IFERROR(COUNTIFS(INDEX(Clay_Offices!$A$2:$FZ$601,0,Sync!$C$9),"warm-intro",INDEX(Clay_Offices!$A$2:$FZ$601,0,Sync!$C$14),"<="&$E$6,INDEX(Clay_Offices!$A$2:$FZ$601,0,Sync!$C$5),Config!$B$20,INDEX(Clay_Offices!$A$2:$FZ$601,0,Sync!$C$15),"needs_approval"),0)+IFERROR(COUNTIFS(INDEX(Clay_Offices!$A$2:$FZ$601,0,Sync!$C$9),"warm-intro",INDEX(Clay_Offices!$A$2:$FZ$601,0,Sync!$C$14),"<="&$E$6,INDEX(Clay_Offices!$A$2:$FZ$601,0,Sync!$C$5),Config!$B$20,INDEX(Clay_Offices!$A$2:$FZ$601,0,Sync!$C$15),"send_info"),0)+IFERROR(COUNTIFS(INDEX(Clay_Offices!$A$2:$FZ$601,0,Sync!$C$9),"warm-intro",INDEX(Clay_Offices!$A$2:$FZ$601,0,Sync!$C$14),"<="&$E$6,INDEX(Clay_Offices!$A$2:$FZ$601,0,Sync!$C$5),Config!$B$20,INDEX(Clay_Offices!$A$2:$FZ$601,0,Sync!$C$15),"referral"),0)
A82: channel: warm-intro | B82: brand | C82: =IFERROR(COUNTIFS(INDEX(Clay_Brands!$A$2:$FZ$601,0,Sync!$D$9),"warm-intro",INDEX(Clay_Brands!$A$2:$FZ$601,0,Sync!$D$11),"<="&$E$6,INDEX(Clay_Brands!$A$2:$FZ$601,0,Sync!$D$5),Config!$B$20),0) | D82: =IFERROR(COUNTIFS(INDEX(Clay_Brands!$A$2:$FZ$601,0,Sync!$D$9),"warm-intro",INDEX(Clay_Brands!$A$2:$FZ$601,0,Sync!$D$14),"<="&$E$6,INDEX(Clay_Brands!$A$2:$FZ$601,0,Sync!$D$5),Config!$B$20,INDEX(Clay_Brands!$A$2:$FZ$601,0,Sync!$D$15),"<>bounce",INDEX(Clay_Brands!$A$2:$FZ$601,0,Sync!$D$15),"<>out_of_office"),0) | E82: =IF(C82=0,"",D82/C82) | G82: =IFERROR(COUNTIFS(INDEX(Clay_Brands!$A$2:$FZ$601,0,Sync!$D$9),"warm-intro",INDEX(Clay_Brands!$A$2:$FZ$601,0,Sync!$D$14),"<="&$E$6,INDEX(Clay_Brands!$A$2:$FZ$601,0,Sync!$D$5),Config!$B$20,INDEX(Clay_Brands!$A$2:$FZ$601,0,Sync!$D$15),"yes"),0)+IFERROR(COUNTIFS(INDEX(Clay_Brands!$A$2:$FZ$601,0,Sync!$D$9),"warm-intro",INDEX(Clay_Brands!$A$2:$FZ$601,0,Sync!$D$14),"<="&$E$6,INDEX(Clay_Brands!$A$2:$FZ$601,0,Sync!$D$5),Config!$B$20,INDEX(Clay_Brands!$A$2:$FZ$601,0,Sync!$D$15),"maybe"),0)+IFERROR(COUNTIFS(INDEX(Clay_Brands!$A$2:$FZ$601,0,Sync!$D$9),"warm-intro",INDEX(Clay_Brands!$A$2:$FZ$601,0,Sync!$D$14),"<="&$E$6,INDEX(Clay_Brands!$A$2:$FZ$601,0,Sync!$D$5),Config!$B$20,INDEX(Clay_Brands!$A$2:$FZ$601,0,Sync!$D$15),"needs_approval"),0)+IFERROR(COUNTIFS(INDEX(Clay_Brands!$A$2:$FZ$601,0,Sync!$D$9),"warm-intro",INDEX(Clay_Brands!$A$2:$FZ$601,0,Sync!$D$14),"<="&$E$6,INDEX(Clay_Brands!$A$2:$FZ$601,0,Sync!$D$5),Config!$B$20,INDEX(Clay_Brands!$A$2:$FZ$601,0,Sync!$D$15),"send_info"),0)+IFERROR(COUNTIFS(INDEX(Clay_Brands!$A$2:$FZ$601,0,Sync!$D$9),"warm-intro",INDEX(Clay_Brands!$A$2:$FZ$601,0,Sync!$D$14),"<="&$E$6,INDEX(Clay_Brands!$A$2:$FZ$601,0,Sync!$D$5),Config!$B$20,INDEX(Clay_Brands!$A$2:$FZ$601,0,Sync!$D$15),"referral"),0)
A83: channel: walk-in | B83: office | C83: =IFERROR(COUNTIFS(INDEX(Clay_Offices!$A$2:$FZ$601,0,Sync!$C$9),"walk-in",INDEX(Clay_Offices!$A$2:$FZ$601,0,Sync!$C$11),"<="&$E$6,INDEX(Clay_Offices!$A$2:$FZ$601,0,Sync!$C$5),Config!$B$20),0) | D83: =IFERROR(COUNTIFS(INDEX(Clay_Offices!$A$2:$FZ$601,0,Sync!$C$9),"walk-in",INDEX(Clay_Offices!$A$2:$FZ$601,0,Sync!$C$14),"<="&$E$6,INDEX(Clay_Offices!$A$2:$FZ$601,0,Sync!$C$5),Config!$B$20,INDEX(Clay_Offices!$A$2:$FZ$601,0,Sync!$C$15),"<>bounce",INDEX(Clay_Offices!$A$2:$FZ$601,0,Sync!$C$15),"<>out_of_office"),0) | E83: =IF(C83=0,"",D83/C83) | G83: =IFERROR(COUNTIFS(INDEX(Clay_Offices!$A$2:$FZ$601,0,Sync!$C$9),"walk-in",INDEX(Clay_Offices!$A$2:$FZ$601,0,Sync!$C$14),"<="&$E$6,INDEX(Clay_Offices!$A$2:$FZ$601,0,Sync!$C$5),Config!$B$20,INDEX(Clay_Offices!$A$2:$FZ$601,0,Sync!$C$15),"yes"),0)+IFERROR(COUNTIFS(INDEX(Clay_Offices!$A$2:$FZ$601,0,Sync!$C$9),"walk-in",INDEX(Clay_Offices!$A$2:$FZ$601,0,Sync!$C$14),"<="&$E$6,INDEX(Clay_Offices!$A$2:$FZ$601,0,Sync!$C$5),Config!$B$20,INDEX(Clay_Offices!$A$2:$FZ$601,0,Sync!$C$15),"maybe"),0)+IFERROR(COUNTIFS(INDEX(Clay_Offices!$A$2:$FZ$601,0,Sync!$C$9),"walk-in",INDEX(Clay_Offices!$A$2:$FZ$601,0,Sync!$C$14),"<="&$E$6,INDEX(Clay_Offices!$A$2:$FZ$601,0,Sync!$C$5),Config!$B$20,INDEX(Clay_Offices!$A$2:$FZ$601,0,Sync!$C$15),"needs_approval"),0)+IFERROR(COUNTIFS(INDEX(Clay_Offices!$A$2:$FZ$601,0,Sync!$C$9),"walk-in",INDEX(Clay_Offices!$A$2:$FZ$601,0,Sync!$C$14),"<="&$E$6,INDEX(Clay_Offices!$A$2:$FZ$601,0,Sync!$C$5),Config!$B$20,INDEX(Clay_Offices!$A$2:$FZ$601,0,Sync!$C$15),"send_info"),0)+IFERROR(COUNTIFS(INDEX(Clay_Offices!$A$2:$FZ$601,0,Sync!$C$9),"walk-in",INDEX(Clay_Offices!$A$2:$FZ$601,0,Sync!$C$14),"<="&$E$6,INDEX(Clay_Offices!$A$2:$FZ$601,0,Sync!$C$5),Config!$B$20,INDEX(Clay_Offices!$A$2:$FZ$601,0,Sync!$C$15),"referral"),0)
A84: channel: walk-in | B84: brand | C84: =IFERROR(COUNTIFS(INDEX(Clay_Brands!$A$2:$FZ$601,0,Sync!$D$9),"walk-in",INDEX(Clay_Brands!$A$2:$FZ$601,0,Sync!$D$11),"<="&$E$6,INDEX(Clay_Brands!$A$2:$FZ$601,0,Sync!$D$5),Config!$B$20),0) | D84: =IFERROR(COUNTIFS(INDEX(Clay_Brands!$A$2:$FZ$601,0,Sync!$D$9),"walk-in",INDEX(Clay_Brands!$A$2:$FZ$601,0,Sync!$D$14),"<="&$E$6,INDEX(Clay_Brands!$A$2:$FZ$601,0,Sync!$D$5),Config!$B$20,INDEX(Clay_Brands!$A$2:$FZ$601,0,Sync!$D$15),"<>bounce",INDEX(Clay_Brands!$A$2:$FZ$601,0,Sync!$D$15),"<>out_of_office"),0) | E84: =IF(C84=0,"",D84/C84) | G84: =IFERROR(COUNTIFS(INDEX(Clay_Brands!$A$2:$FZ$601,0,Sync!$D$9),"walk-in",INDEX(Clay_Brands!$A$2:$FZ$601,0,Sync!$D$14),"<="&$E$6,INDEX(Clay_Brands!$A$2:$FZ$601,0,Sync!$D$5),Config!$B$20,INDEX(Clay_Brands!$A$2:$FZ$601,0,Sync!$D$15),"yes"),0)+IFERROR(COUNTIFS(INDEX(Clay_Brands!$A$2:$FZ$601,0,Sync!$D$9),"walk-in",INDEX(Clay_Brands!$A$2:$FZ$601,0,Sync!$D$14),"<="&$E$6,INDEX(Clay_Brands!$A$2:$FZ$601,0,Sync!$D$5),Config!$B$20,INDEX(Clay_Brands!$A$2:$FZ$601,0,Sync!$D$15),"maybe"),0)+IFERROR(COUNTIFS(INDEX(Clay_Brands!$A$2:$FZ$601,0,Sync!$D$9),"walk-in",INDEX(Clay_Brands!$A$2:$FZ$601,0,Sync!$D$14),"<="&$E$6,INDEX(Clay_Brands!$A$2:$FZ$601,0,Sync!$D$5),Config!$B$20,INDEX(Clay_Brands!$A$2:$FZ$601,0,Sync!$D$15),"needs_approval"),0)+IFERROR(COUNTIFS(INDEX(Clay_Brands!$A$2:$FZ$601,0,Sync!$D$9),"walk-in",INDEX(Clay_Brands!$A$2:$FZ$601,0,Sync!$D$14),"<="&$E$6,INDEX(Clay_Brands!$A$2:$FZ$601,0,Sync!$D$5),Config!$B$20,INDEX(Clay_Brands!$A$2:$FZ$601,0,Sync!$D$15),"send_info"),0)+IFERROR(COUNTIFS(INDEX(Clay_Brands!$A$2:$FZ$601,0,Sync!$D$9),"walk-in",INDEX(Clay_Brands!$A$2:$FZ$601,0,Sync!$D$14),"<="&$E$6,INDEX(Clay_Brands!$A$2:$FZ$601,0,Sync!$D$5),Config!$B$20,INDEX(Clay_Brands!$A$2:$FZ$601,0,Sync!$D$15),"referral"),0)
A85: Sequence names come from Clay's sequence column. Edit the names in column A to match the variants Part A's copy uses.
A87: Data checks (fix every FIX before reading the numbers above)
A88: Check | E88: Count | F88: Result | G88: What to do
A89: Office_Log rows with a sync issue | E89: =COUNTIF(Office_Log!$AS$2:$AS$201,"?*") | F89: =IF(N(E89)=0,"OK","FIX") | G89: Read calc_sync_issue on Office_Log; fix in Clay, then re-paste.
A90: Brand_Log rows with a sync issue | E90: =COUNTIF(Brand_Log!$AL$2:$AL$201,"?*") | F90: =IF(N(E90)=0,"OK","FIX") | G90: Read calc_sync_issue on Brand_Log.
A91: Clay office rows with an issue | E91: =COUNTIF(Sync!$G$22:$G$621,"?*") | F91: =IF(N(E91)=0,"OK","FIX") | G91: Sync tab, office list.
A92: Clay brand rows with an issue | E92: =COUNTIF(Sync!$N$22:$N$621,"?*") | F92: =IF(N(E92)=0,"OK","FIX") | G92: Sync tab, brand list.
A93: Handoff rows whose Clay status is not signed / paid | E93: =COUNTIF(Sync!$R$22:$R$71,"?*")+COUNTIF(Sync!$V$22:$V$71,"?*") | F93: =IF(N(E93)=0,"OK","FIX") | G93: Set the Clay status to signed or paid.
A94: Clay columns missing from a paste | E94: =COUNTIF(Sync!$E$5:$E$18,"?*") | F94: =IF(N(E94)=0,"OK","FIX") | G94: Export all columns from Clay (CONTRACTS 6.2 names).
A95: Days since the Clay offices paste (as of) | E95: =IF(Config!$B$21="",999,Config!$B$5-Config!$B$21) | F95: =IF(N(E95)<=1,"OK","FIX") | G95: Paste a fresh export each Friday and type its date on Config.
A96: Days since the Clay brands paste (as of) | E96: =IF(Config!$B$22="",999,Config!$B$5-Config!$B$22) | F96: =IF(N(E96)<=1,"OK","FIX") | G96: Same.
A97: Offices that said Y but owner or window is missing | E97: =SUM(Office_Log!$AZ$2:$AZ$201) | F97: ="info" | G97: They do not count for Gate 0 until both are named.
A98: Budget probe asked but no verbatim | E98: =SUM(Office_Log!$BN$2:$BN$201) | F98: =IF(N(E98)=0,"OK","FIX") | G98: Type the answer word for word.
A99: Brand number given but no verbatim | E99: =SUM(Brand_Log!$BL$2:$BL$201) | F99: =IF(N(E99)=0,"OK","FIX") | G99: Type the answer word for word.
A100: Log rows with a row_id but no real call_date | E100: =COUNTIF(Office_Log!$AS$2:$AS$201,"call_date*")+COUNTIF(Brand_Log!$AL$2:$AL$201,"call_date*") | F100: =IF(N(E100)=0,"OK","FIX") | G100: Type the date as YYYY-MM-DD.
A101: Clay touch_1_date cells stored as text | E101: =IFERROR(SUMPRODUCT(--ISTEXT(INDEX(Clay_Offices!$A$2:$FZ$601,0,Sync!$C$11))),0)+IFERROR(SUMPRODUCT(--ISTEXT(INDEX(Clay_Brands!$A$2:$FZ$601,0,Sync!$D$11))),0) | F101: =IF(N(E101)=0,"OK","FIX") | G101: Reformat the column as a date in Clay or here, or they drop out of every count.
A102: Pipeline events beyond the export rows | E102: =MAX(0,COUNT(Pipeline_Calc!$A$2:$A$5251)-1000) | F102: =IF(N(E102)=0,"OK","FIX") | G102: Raise EXPORT_N in tools/build_tracker.py and rebuild, or split the file.
A103: Notes over the ten-minute target (as of) | E103: =COUNTIF(Office_Log!$BR$2:$BR$201,">"&Config!$B$18)+COUNTIF(Brand_Log!$BP$2:$BP$201,">"&Config!$B$18) | F103: ="info" | G103: If this grows, trim the note template, not the verbatims.
A104: Median minutes per note (as of) | E104: =IFERROR(MEDIAN(Office_Log!$BR$2:$BR$201,Brand_Log!$BP$2:$BP$201),"none yet") | F104: ="info" | G104: Target 10 or less.
A105: SAMPLE rows in this file | E105: =COUNTIF(Office_Log!$A$2:$A$201,"SAMPLE*")+COUNTIF(Brand_Log!$A$2:$A$201,"SAMPLE*")+COUNTIF(signed_offices!$W$2:$W$51,"SAMPLE*")+COUNTIF(paid_brands!$AC$2:$AC$51,"SAMPLE*")+COUNTIF(later_events!$C$2:$C$101,"SAMPLE*")+IFERROR(COUNTIF(INDEX(Clay_Offices!$A$2:$FZ$601,0,Sync!$C$5),"SAMPLE*"),0)+IFERROR(COUNTIF(INDEX(Clay_Brands!$A$2:$FZ$601,0,Sync!$D$5),"SAMPLE*"),0) | F105: =IF(N(E105)=0,"OK",IF(Config!$B$19="Y","SAMPLE","ignored")) | G105: Delete them before real use, or keep include_sample = N so they are ignored.

Sheet Office_Log
A1: row_id | B1: company | C1: contact_name | D1: contact_title | E1: source | F1: channel | G1: call_date | H1: call_type | I1: q1_pantry_today_verbatim | J1: pantry_vendor | K1: monthly_pantry_spend_usd | L1: monthly_pantry_spend_verbatim | M1: tuesday_headcount | N1: headcount_verbatim | O1: q3_free_product_verbatim | P1: q4_yes_needs_verbatim | Q1: q4_no_triggers_verbatim | R1: q5_photo_and_survey | S1: q5_verbatim | T1: budget_probe_asked | U1: budget_probe_verbatim | V1: budget_probe_low_usd | W1: budget_probe_high_usd | X1: referrals_given_count | Y1: referrals_given | Z1: pantry_owner_named | AA1: pantry_owner_name | AB1: pantry_owner_title | AC1: owner_can_say_yes_alone | AD1: receiving_window | AE1: receiving_type | AF1: coi_required | AG1: security_notes | AH1: veto_categories | AI1: veto_verbatim | AJ1: objection_1 | AK1: objection_2 | AL1: objection_3 | AM1: objections_verbatim | AN1: yes_in_principle | AO1: yes_signals | AP1: note_minutes | AQ1: clay_updated | AR1: notes | AS1: calc_sync_issue | AT1: calc_row | AU1: calc_valid | AV1: calc_conv_first | AW1: calc_latest | AX1: calc_q_yes | AY1: calc_q_yes_first | AZ1: calc_yes_incomplete | BA1: calc_bp_has | BB1: calc_bp_first | BC1: calc_bp_w1 | BD1: calc_bp_w2 | BE1: calc_bp_g0 | BF1: calc_bp_asof | BG1: calc_bp100_first | BH1: calc_spend_has | BI1: calc_spend_first | BJ1: calc_spend_asof | BK1: calc_probe_row | BL1: calc_probe_first | BM1: calc_probe_key | BN1: calc_probe_missing_text | BO1: calc_obj1 | BP1: calc_obj2 | BQ1: calc_obj3 | BR1: calc_note_min | BS1: calc_yes_any | BT1: calc_maybe | BU1: calc_maybe_first | BV1: calc_yes_any_first | BW1: calc_bp100 | BX1: calc_clay_idx | BY1: calc_clay_status | BZ1: calc_clay_rank | CA1: calc_clay_yes | CB1: calc_clay_call_date
AS2: =IF(TRIM($A2)="","",IF(AND(LEFT($A2,6)="SAMPLE",Config!$B$19<>"Y"),"",IF(NOT(ISNUMBER(G2)),"call_date is blank or not a date",IF(Sync!$C$5="","Clay paste is empty or has no row_id column: paste the Clay export on Clay_Offices",IF(BX2="","row_id not found in the Clay paste: add the Clay row or fix the row_id",IF(AND(ISNUMBER(BZ2),BZ2>=1,BZ2<=5),"Clay status is "&BY2&": set call_done or later",IF(AND(AW2=1,CA2<>BS2),"Clay yes_in_principle should be "&BS2,IF(AND(AW2=1,CB2<>G2),"Clay call_date should be "&TEXT(G2,"yyyy-mm-dd"),"")))))))) | AT2: =ROW() | AU2: =IF(AND(TRIM($A2)<>"",ISNUMBER(G2)),IF(AND(LEFT($A2,6)="SAMPLE",Config!$B$19<>"Y"),0,1),0) | AV2: =IF(AU2=1,IF(COUNTIFS($A$2:$A$201,$A2,$AU$2:$AU$201,1,$G$2:$G$201,"<"&G2)+COUNTIFS($A$2:$A$201,$A2,$AU$2:$AU$201,1,$G$2:$G$201,G2,$AT$2:$AT$201,"<"&AT2)=0,1,0),0) | AW2: =IF(AU2=1,IF(COUNTIFS($A$2:$A$201,$A2,$AU$2:$AU$201,1,$G$2:$G$201,">"&G2)+COUNTIFS($A$2:$A$201,$A2,$AU$2:$AU$201,1,$G$2:$G$201,G2,$AT$2:$AT$201,">"&AT2)=0,1,0),0) | AX2: =IF(AND(AU2=1,AN2="Y",Z2="Y",TRIM(AD2)<>""),1,0) | AY2: =IF(AX2=1,IF(COUNTIFS($A$2:$A$201,$A2,$AX$2:$AX$201,1,$G$2:$G$201,"<"&G2)+COUNTIFS($A$2:$A$201,$A2,$AX$2:$AX$201,1,$G$2:$G$201,G2,$AT$2:$AT$201,"<"&AT2)=0,1,0),0) | AZ2: =IF(AND(AU2=1,AN2="Y",AX2=0),1,0) | BA2: =IF(AND(AU2=1,ISNUMBER(V2)),1,0) | BB2: =IF(BA2=1,IF(COUNTIFS($A$2:$A$201,$A2,$BA$2:$BA$201,1,$G$2:$G$201,"<"&G2)+COUNTIFS($A$2:$A$201,$A2,$BA$2:$BA$201,1,$G$2:$G$201,G2,$AT$2:$AT$201,"<"&AT2)=0,1,0),0) | BC2: =IF(AND(BB2=1,G2<=Config!$B$6),V2,"") | BD2: =IF(AND(BB2=1,G2<=Config!$B$7),V2,"") | BE2: =IF(AND(BB2=1,G2<=Config!$B$8),V2,"") | BF2: =IF(AND(BB2=1,G2<=Config!$B$5),V2,"") | BG2: =IF(BW2=1,IF(COUNTIFS($A$2:$A$201,$A2,$BW$2:$BW$201,1,$G$2:$G$201,"<"&G2)+COUNTIFS($A$2:$A$201,$A2,$BW$2:$BW$201,1,$G$2:$G$201,G2,$AT$2:$AT$201,"<"&AT2)=0,1,0),0) | BH2: =IF(AND(AU2=1,ISNUMBER(K2)),1,0) | BI2: =IF(BH2=1,IF(COUNTIFS($A$2:$A$201,$A2,$BH$2:$BH$201,1,$G$2:$G$201,"<"&G2)+COUNTIFS($A$2:$A$201,$A2,$BH$2:$BH$201,1,$G$2:$G$201,G2,$AT$2:$AT$201,"<"&AT2)=0,1,0),0) | BJ2: =IF(AND(BI2=1,G2<=Config!$B$5),K2,"") | BK2: =IF(AND(AU2=1,OR(TRIM(U2)<>"",ISNUMBER(V2))),1,0) | BL2: =IF(BK2=1,IF(COUNTIFS($A$2:$A$201,$A2,$BK$2:$BK$201,1,$G$2:$G$201,"<"&G2)+COUNTIFS($A$2:$A$201,$A2,$BK$2:$BK$201,1,$G$2:$G$201,G2,$AT$2:$AT$201,"<"&AT2)=0,1,0),0) | BM2: =IF(BL2=1,$A2,"") | BN2: =IF(AND(AU2=1,T2="Y",TRIM(U2)=""),1,0) | BO2: =IF(AU2=1,AJ2&"","") | BP2: =IF(AU2=1,AK2&"","") | BQ2: =IF(AU2=1,AL2&"","") | BR2: =IF(AND(AU2=1,ISNUMBER(AP2),G2<=Config!$B$5),AP2,"") | BS2: =IF(AU2=1,IF(COUNTIFS($A$2:$A$201,$A2,$AN$2:$AN$201,"Y",$AU$2:$AU$201,1)>0,"Y","N"),"") | BT2: =IF(AND(AU2=1,AN2="maybe"),1,0) | BU2: =IF(BT2=1,IF(COUNTIFS($A$2:$A$201,$A2,$BT$2:$BT$201,1,$G$2:$G$201,"<"&G2)+COUNTIFS($A$2:$A$201,$A2,$BT$2:$BT$201,1,$G$2:$G$201,G2,$AT$2:$AT$201,"<"&AT2)=0,1,0),0) | BV2: =IF(AND(AU2=1,AN2="Y"),IF(COUNTIFS($A$2:$A$201,$A2,$AN$2:$AN$201,"Y",$AU$2:$AU$201,1,$G$2:$G$201,"<"&G2)+COUNTIFS($A$2:$A$201,$A2,$AN$2:$AN$201,"Y",$AU$2:$AU$201,1,$G$2:$G$201,G2,$AT$2:$AT$201,"<"&AT2)=0,1,0),0) | BW2: =IF(AND(BA2=1,N(V2)>=Config!$B$15),1,0) | BX2: =IF(AU2=1,IFERROR(MATCH($A2,INDEX(Clay_Offices!$A$2:$FZ$601,0,Sync!$C$5),0),""),"") | BY2: =IF(BX2="","",IFERROR(INDEX(Clay_Offices!$A$2:$FZ$601,BX2,Sync!$C$7)&"","")) | BZ2: =IF(BY2="","",IFERROR(INDEX(Lists!$J$2:$J$15,MATCH(BY2,Lists!$I$2:$I$15,0)),"")) | CA2: =IF(BX2="","",IFERROR(INDEX(Clay_Offices!$A$2:$FZ$601,BX2,Sync!$C$17)&"","")) | CB2: =IF(BX2="","",IFERROR(N(INDEX(Clay_Offices!$A$2:$FZ$601,BX2,Sync!$C$16)),0))
AS3: =IF(TRIM($A3)="","",IF(AND(LEFT($A3,6)="SAMPLE",Config!$B$19<>"Y"),"",IF(NOT(ISNUMBER(G3)),"call_date is blank or not a date",IF(Sync!$C$5="","Clay paste is empty or has no row_id column: paste the Clay export on Clay_Offices",IF(BX3="","row_id not found in the Clay paste: add the Clay row or fix the row_id",IF(AND(ISNUMBER(BZ3),BZ3>=1,BZ3<=5),"Clay status is "&BY3&": set call_done or later",IF(AND(AW3=1,CA3<>BS3),"Clay yes_in_principle should be "&BS3,IF(AND(AW3=1,CB3<>G3),"Clay call_date should be "&TEXT(G3,"yyyy-mm-dd"),"")))))))) | AT3: =ROW() | AU3: =IF(AND(TRIM($A3)<>"",ISNUMBER(G3)),IF(AND(LEFT($A3,6)="SAMPLE",Config!$B$19<>"Y"),0,1),0) | AV3: =IF(AU3=1,IF(COUNTIFS($A$2:$A$201,$A3,$AU$2:$AU$201,1,$G$2:$G$201,"<"&G3)+COUNTIFS($A$2:$A$201,$A3,$AU$2:$AU$201,1,$G$2:$G$201,G3,$AT$2:$AT$201,"<"&AT3)=0,1,0),0) | AW3: =IF(AU3=1,IF(COUNTIFS($A$2:$A$201,$A3,$AU$2:$AU$201,1,$G$2:$G$201,">"&G3)+COUNTIFS($A$2:$A$201,$A3,$AU$2:$AU$201,1,$G$2:$G$201,G3,$AT$2:$AT$201,">"&AT3)=0,1,0),0) | AX3: =IF(AND(AU3=1,AN3="Y",Z3="Y",TRIM(AD3)<>""),1,0) | AY3: =IF(AX3=1,IF(COUNTIFS($A$2:$A$201,$A3,$AX$2:$AX$201,1,$G$2:$G$201,"<"&G3)+COUNTIFS($A$2:$A$201,$A3,$AX$2:$AX$201,1,$G$2:$G$201,G3,$AT$2:$AT$201,"<"&AT3)=0,1,0),0) | AZ3: =IF(AND(AU3=1,AN3="Y",AX3=0),1,0) | BA3: =IF(AND(AU3=1,ISNUMBER(V3)),1,0) | BB3: =IF(BA3=1,IF(COUNTIFS($A$2:$A$201,$A3,$BA$2:$BA$201,1,$G$2:$G$201,"<"&G3)+COUNTIFS($A$2:$A$201,$A3,$BA$2:$BA$201,1,$G$2:$G$201,G3,$AT$2:$AT$201,"<"&AT3)=0,1,0),0) | BC3: =IF(AND(BB3=1,G3<=Config!$B$6),V3,"") | BD3: =IF(AND(BB3=1,G3<=Config!$B$7),V3,"") | BE3: =IF(AND(BB3=1,G3<=Config!$B$8),V3,"") | BF3: =IF(AND(BB3=1,G3<=Config!$B$5),V3,"") | BG3: =IF(BW3=1,IF(COUNTIFS($A$2:$A$201,$A3,$BW$2:$BW$201,1,$G$2:$G$201,"<"&G3)+COUNTIFS($A$2:$A$201,$A3,$BW$2:$BW$201,1,$G$2:$G$201,G3,$AT$2:$AT$201,"<"&AT3)=0,1,0),0) | BH3: =IF(AND(AU3=1,ISNUMBER(K3)),1,0) | BI3: =IF(BH3=1,IF(COUNTIFS($A$2:$A$201,$A3,$BH$2:$BH$201,1,$G$2:$G$201,"<"&G3)+COUNTIFS($A$2:$A$201,$A3,$BH$2:$BH$201,1,$G$2:$G$201,G3,$AT$2:$AT$201,"<"&AT3)=0,1,0),0) | BJ3: =IF(AND(BI3=1,G3<=Config!$B$5),K3,"") | BK3: =IF(AND(AU3=1,OR(TRIM(U3)<>"",ISNUMBER(V3))),1,0) | BL3: =IF(BK3=1,IF(COUNTIFS($A$2:$A$201,$A3,$BK$2:$BK$201,1,$G$2:$G$201,"<"&G3)+COUNTIFS($A$2:$A$201,$A3,$BK$2:$BK$201,1,$G$2:$G$201,G3,$AT$2:$AT$201,"<"&AT3)=0,1,0),0) | BM3: =IF(BL3=1,$A3,"") | BN3: =IF(AND(AU3=1,T3="Y",TRIM(U3)=""),1,0) | BO3: =IF(AU3=1,AJ3&"","") | BP3: =IF(AU3=1,AK3&"","") | BQ3: =IF(AU3=1,AL3&"","") | BR3: =IF(AND(AU3=1,ISNUMBER(AP3),G3<=Config!$B$5),AP3,"") | BS3: =IF(AU3=1,IF(COUNTIFS($A$2:$A$201,$A3,$AN$2:$AN$201,"Y",$AU$2:$AU$201,1)>0,"Y","N"),"") | BT3: =IF(AND(AU3=1,AN3="maybe"),1,0) | BU3: =IF(BT3=1,IF(COUNTIFS($A$2:$A$201,$A3,$BT$2:$BT$201,1,$G$2:$G$201,"<"&G3)+COUNTIFS($A$2:$A$201,$A3,$BT$2:$BT$201,1,$G$2:$G$201,G3,$AT$2:$AT$201,"<"&AT3)=0,1,0),0) | BV3: =IF(AND(AU3=1,AN3="Y"),IF(COUNTIFS($A$2:$A$201,$A3,$AN$2:$AN$201,"Y",$AU$2:$AU$201,1,$G$2:$G$201,"<"&G3)+COUNTIFS($A$2:$A$201,$A3,$AN$2:$AN$201,"Y",$AU$2:$AU$201,1,$G$2:$G$201,G3,$AT$2:$AT$201,"<"&AT3)=0,1,0),0) | BW3: =IF(AND(BA3=1,N(V3)>=Config!$B$15),1,0) | BX3: =IF(AU3=1,IFERROR(MATCH($A3,INDEX(Clay_Offices!$A$2:$FZ$601,0,Sync!$C$5),0),""),"") | BY3: =IF(BX3="","",IFERROR(INDEX(Clay_Offices!$A$2:$FZ$601,BX3,Sync!$C$7)&"","")) | BZ3: =IF(BY3="","",IFERROR(INDEX(Lists!$J$2:$J$15,MATCH(BY3,Lists!$I$2:$I$15,0)),"")) | CA3: =IF(BX3="","",IFERROR(INDEX(Clay_Offices!$A$2:$FZ$601,BX3,Sync!$C$17)&"","")) | CB3: =IF(BX3="","",IFERROR(N(INDEX(Clay_Offices!$A$2:$FZ$601,BX3,Sync!$C$16)),0))
AS4: =IF(TRIM($A4)="","",IF(AND(LEFT($A4,6)="SAMPLE",Config!$B$19<>"Y"),"",IF(NOT(ISNUMBER(G4)),"call_date is blank or not a date",IF(Sync!$C$5="","Clay paste is empty or has no row_id column: paste the Clay export on Clay_Offices",IF(BX4="","row_id not found in the Clay paste: add the Clay row or fix the row_id",IF(AND(ISNUMBER(BZ4),BZ4>=1,BZ4<=5),"Clay status is "&BY4&": set call_done or later",IF(AND(AW4=1,CA4<>BS4),"Clay yes_in_principle should be "&BS4,IF(AND(AW4=1,CB4<>G4),"Clay call_date should be "&TEXT(G4,"yyyy-mm-dd"),"")))))))) | AT4: =ROW() | AU4: =IF(AND(TRIM($A4)<>"",ISNUMBER(G4)),IF(AND(LEFT($A4,6)="SAMPLE",Config!$B$19<>"Y"),0,1),0) | AV4: =IF(AU4=1,IF(COUNTIFS($A$2:$A$201,$A4,$AU$2:$AU$201,1,$G$2:$G$201,"<"&G4)+COUNTIFS($A$2:$A$201,$A4,$AU$2:$AU$201,1,$G$2:$G$201,G4,$AT$2:$AT$201,"<"&AT4)=0,1,0),0) | AW4: =IF(AU4=1,IF(COUNTIFS($A$2:$A$201,$A4,$AU$2:$AU$201,1,$G$2:$G$201,">"&G4)+COUNTIFS($A$2:$A$201,$A4,$AU$2:$AU$201,1,$G$2:$G$201,G4,$AT$2:$AT$201,">"&AT4)=0,1,0),0) | AX4: =IF(AND(AU4=1,AN4="Y",Z4="Y",TRIM(AD4)<>""),1,0) | AY4: =IF(AX4=1,IF(COUNTIFS($A$2:$A$201,$A4,$AX$2:$AX$201,1,$G$2:$G$201,"<"&G4)+COUNTIFS($A$2:$A$201,$A4,$AX$2:$AX$201,1,$G$2:$G$201,G4,$AT$2:$AT$201,"<"&AT4)=0,1,0),0) | AZ4: =IF(AND(AU4=1,AN4="Y",AX4=0),1,0) | BA4: =IF(AND(AU4=1,ISNUMBER(V4)),1,0) | BB4: =IF(BA4=1,IF(COUNTIFS($A$2:$A$201,$A4,$BA$2:$BA$201,1,$G$2:$G$201,"<"&G4)+COUNTIFS($A$2:$A$201,$A4,$BA$2:$BA$201,1,$G$2:$G$201,G4,$AT$2:$AT$201,"<"&AT4)=0,1,0),0) | BC4: =IF(AND(BB4=1,G4<=Config!$B$6),V4,"") | BD4: =IF(AND(BB4=1,G4<=Config!$B$7),V4,"") | BE4: =IF(AND(BB4=1,G4<=Config!$B$8),V4,"") | BF4: =IF(AND(BB4=1,G4<=Config!$B$5),V4,"") | BG4: =IF(BW4=1,IF(COUNTIFS($A$2:$A$201,$A4,$BW$2:$BW$201,1,$G$2:$G$201,"<"&G4)+COUNTIFS($A$2:$A$201,$A4,$BW$2:$BW$201,1,$G$2:$G$201,G4,$AT$2:$AT$201,"<"&AT4)=0,1,0),0) | BH4: =IF(AND(AU4=1,ISNUMBER(K4)),1,0) | BI4: =IF(BH4=1,IF(COUNTIFS($A$2:$A$201,$A4,$BH$2:$BH$201,1,$G$2:$G$201,"<"&G4)+COUNTIFS($A$2:$A$201,$A4,$BH$2:$BH$201,1,$G$2:$G$201,G4,$AT$2:$AT$201,"<"&AT4)=0,1,0),0) | BJ4: =IF(AND(BI4=1,G4<=Config!$B$5),K4,"") | BK4: =IF(AND(AU4=1,OR(TRIM(U4)<>"",ISNUMBER(V4))),1,0) | BL4: =IF(BK4=1,IF(COUNTIFS($A$2:$A$201,$A4,$BK$2:$BK$201,1,$G$2:$G$201,"<"&G4)+COUNTIFS($A$2:$A$201,$A4,$BK$2:$BK$201,1,$G$2:$G$201,G4,$AT$2:$AT$201,"<"&AT4)=0,1,0),0) | BM4: =IF(BL4=1,$A4,"") | BN4: =IF(AND(AU4=1,T4="Y",TRIM(U4)=""),1,0) | BO4: =IF(AU4=1,AJ4&"","") | BP4: =IF(AU4=1,AK4&"","") | BQ4: =IF(AU4=1,AL4&"","") | BR4: =IF(AND(AU4=1,ISNUMBER(AP4),G4<=Config!$B$5),AP4,"") | BS4: =IF(AU4=1,IF(COUNTIFS($A$2:$A$201,$A4,$AN$2:$AN$201,"Y",$AU$2:$AU$201,1)>0,"Y","N"),"") | BT4: =IF(AND(AU4=1,AN4="maybe"),1,0) | BU4: =IF(BT4=1,IF(COUNTIFS($A$2:$A$201,$A4,$BT$2:$BT$201,1,$G$2:$G$201,"<"&G4)+COUNTIFS($A$2:$A$201,$A4,$BT$2:$BT$201,1,$G$2:$G$201,G4,$AT$2:$AT$201,"<"&AT4)=0,1,0),0) | BV4: =IF(AND(AU4=1,AN4="Y"),IF(COUNTIFS($A$2:$A$201,$A4,$AN$2:$AN$201,"Y",$AU$2:$AU$201,1,$G$2:$G$201,"<"&G4)+COUNTIFS($A$2:$A$201,$A4,$AN$2:$AN$201,"Y",$AU$2:$AU$201,1,$G$2:$G$201,G4,$AT$2:$AT$201,"<"&AT4)=0,1,0),0) | BW4: =IF(AND(BA4=1,N(V4)>=Config!$B$15),1,0) | BX4: =IF(AU4=1,IFERROR(MATCH($A4,INDEX(Clay_Offices!$A$2:$FZ$601,0,Sync!$C$5),0),""),"") | BY4: =IF(BX4="","",IFERROR(INDEX(Clay_Offices!$A$2:$FZ$601,BX4,Sync!$C$7)&"","")) | BZ4: =IF(BY4="","",IFERROR(INDEX(Lists!$J$2:$J$15,MATCH(BY4,Lists!$I$2:$I$15,0)),"")) | CA4: =IF(BX4="","",IFERROR(INDEX(Clay_Offices!$A$2:$FZ$601,BX4,Sync!$C$17)&"","")) | CB4: =IF(BX4="","",IFERROR(N(INDEX(Clay_Offices!$A$2:$FZ$601,BX4,Sync!$C$16)),0))
AS5: =IF(TRIM($A5)="","",IF(AND(LEFT($A5,6)="SAMPLE",Config!$B$19<>"Y"),"",IF(NOT(ISNUMBER(G5)),"call_date is blank or not a date",IF(Sync!$C$5="","Clay paste is empty or has no row_id column: paste the Clay export on Clay_Offices",IF(BX5="","row_id not found in the Clay paste: add the Clay row or fix the row_id",IF(AND(ISNUMBER(BZ5),BZ5>=1,BZ5<=5),"Clay status is "&BY5&": set call_done or later",IF(AND(AW5=1,CA5<>BS5),"Clay yes_in_principle should be "&BS5,IF(AND(AW5=1,CB5<>G5),"Clay call_date should be "&TEXT(G5,"yyyy-mm-dd"),"")))))))) | AT5: =ROW() | AU5: =IF(AND(TRIM($A5)<>"",ISNUMBER(G5)),IF(AND(LEFT($A5,6)="SAMPLE",Config!$B$19<>"Y"),0,1),0) | AV5: =IF(AU5=1,IF(COUNTIFS($A$2:$A$201,$A5,$AU$2:$AU$201,1,$G$2:$G$201,"<"&G5)+COUNTIFS($A$2:$A$201,$A5,$AU$2:$AU$201,1,$G$2:$G$201,G5,$AT$2:$AT$201,"<"&AT5)=0,1,0),0) | AW5: =IF(AU5=1,IF(COUNTIFS($A$2:$A$201,$A5,$AU$2:$AU$201,1,$G$2:$G$201,">"&G5)+COUNTIFS($A$2:$A$201,$A5,$AU$2:$AU$201,1,$G$2:$G$201,G5,$AT$2:$AT$201,">"&AT5)=0,1,0),0) | AX5: =IF(AND(AU5=1,AN5="Y",Z5="Y",TRIM(AD5)<>""),1,0) | AY5: =IF(AX5=1,IF(COUNTIFS($A$2:$A$201,$A5,$AX$2:$AX$201,1,$G$2:$G$201,"<"&G5)+COUNTIFS($A$2:$A$201,$A5,$AX$2:$AX$201,1,$G$2:$G$201,G5,$AT$2:$AT$201,"<"&AT5)=0,1,0),0) | AZ5: =IF(AND(AU5=1,AN5="Y",AX5=0),1,0) | BA5: =IF(AND(AU5=1,ISNUMBER(V5)),1,0) | BB5: =IF(BA5=1,IF(COUNTIFS($A$2:$A$201,$A5,$BA$2:$BA$201,1,$G$2:$G$201,"<"&G5)+COUNTIFS($A$2:$A$201,$A5,$BA$2:$BA$201,1,$G$2:$G$201,G5,$AT$2:$AT$201,"<"&AT5)=0,1,0),0) | BC5: =IF(AND(BB5=1,G5<=Config!$B$6),V5,"") | BD5: =IF(AND(BB5=1,G5<=Config!$B$7),V5,"") | BE5: =IF(AND(BB5=1,G5<=Config!$B$8),V5,"") | BF5: =IF(AND(BB5=1,G5<=Config!$B$5),V5,"") | BG5: =IF(BW5=1,IF(COUNTIFS($A$2:$A$201,$A5,$BW$2:$BW$201,1,$G$2:$G$201,"<"&G5)+COUNTIFS($A$2:$A$201,$A5,$BW$2:$BW$201,1,$G$2:$G$201,G5,$AT$2:$AT$201,"<"&AT5)=0,1,0),0) | BH5: =IF(AND(AU5=1,ISNUMBER(K5)),1,0) | BI5: =IF(BH5=1,IF(COUNTIFS($A$2:$A$201,$A5,$BH$2:$BH$201,1,$G$2:$G$201,"<"&G5)+COUNTIFS($A$2:$A$201,$A5,$BH$2:$BH$201,1,$G$2:$G$201,G5,$AT$2:$AT$201,"<"&AT5)=0,1,0),0) | BJ5: =IF(AND(BI5=1,G5<=Config!$B$5),K5,"") | BK5: =IF(AND(AU5=1,OR(TRIM(U5)<>"",ISNUMBER(V5))),1,0) | BL5: =IF(BK5=1,IF(COUNTIFS($A$2:$A$201,$A5,$BK$2:$BK$201,1,$G$2:$G$201,"<"&G5)+COUNTIFS($A$2:$A$201,$A5,$BK$2:$BK$201,1,$G$2:$G$201,G5,$AT$2:$AT$201,"<"&AT5)=0,1,0),0) | BM5: =IF(BL5=1,$A5,"") | BN5: =IF(AND(AU5=1,T5="Y",TRIM(U5)=""),1,0) | BO5: =IF(AU5=1,AJ5&"","") | BP5: =IF(AU5=1,AK5&"","") | BQ5: =IF(AU5=1,AL5&"","") | BR5: =IF(AND(AU5=1,ISNUMBER(AP5),G5<=Config!$B$5),AP5,"") | BS5: =IF(AU5=1,IF(COUNTIFS($A$2:$A$201,$A5,$AN$2:$AN$201,"Y",$AU$2:$AU$201,1)>0,"Y","N"),"") | BT5: =IF(AND(AU5=1,AN5="maybe"),1,0) | BU5: =IF(BT5=1,IF(COUNTIFS($A$2:$A$201,$A5,$BT$2:$BT$201,1,$G$2:$G$201,"<"&G5)+COUNTIFS($A$2:$A$201,$A5,$BT$2:$BT$201,1,$G$2:$G$201,G5,$AT$2:$AT$201,"<"&AT5)=0,1,0),0) | BV5: =IF(AND(AU5=1,AN5="Y"),IF(COUNTIFS($A$2:$A$201,$A5,$AN$2:$AN$201,"Y",$AU$2:$AU$201,1,$G$2:$G$201,"<"&G5)+COUNTIFS($A$2:$A$201,$A5,$AN$2:$AN$201,"Y",$AU$2:$AU$201,1,$G$2:$G$201,G5,$AT$2:$AT$201,"<"&AT5)=0,1,0),0) | BW5: =IF(AND(BA5=1,N(V5)>=Config!$B$15),1,0) | BX5: =IF(AU5=1,IFERROR(MATCH($A5,INDEX(Clay_Offices!$A$2:$FZ$601,0,Sync!$C$5),0),""),"") | BY5: =IF(BX5="","",IFERROR(INDEX(Clay_Offices!$A$2:$FZ$601,BX5,Sync!$C$7)&"","")) | BZ5: =IF(BY5="","",IFERROR(INDEX(Lists!$J$2:$J$15,MATCH(BY5,Lists!$I$2:$I$15,0)),"")) | CA5: =IF(BX5="","",IFERROR(INDEX(Clay_Offices!$A$2:$FZ$601,BX5,Sync!$C$17)&"","")) | CB5: =IF(BX5="","",IFERROR(N(INDEX(Clay_Offices!$A$2:$FZ$601,BX5,Sync!$C$16)),0))
AS6: =IF(TRIM($A6)="","",IF(AND(LEFT($A6,6)="SAMPLE",Config!$B$19<>"Y"),"",IF(NOT(ISNUMBER(G6)),"call_date is blank or not a date",IF(Sync!$C$5="","Clay paste is empty or has no row_id column: paste the Clay export on Clay_Offices",IF(BX6="","row_id not found in the Clay paste: add the Clay row or fix the row_id",IF(AND(ISNUMBER(BZ6),BZ6>=1,BZ6<=5),"Clay status is "&BY6&": set call_done or later",IF(AND(AW6=1,CA6<>BS6),"Clay yes_in_principle should be "&BS6,IF(AND(AW6=1,CB6<>G6),"Clay call_date should be "&TEXT(G6,"yyyy-mm-dd"),"")))))))) | AT6: =ROW() | AU6: =IF(AND(TRIM($A6)<>"",ISNUMBER(G6)),IF(AND(LEFT($A6,6)="SAMPLE",Config!$B$19<>"Y"),0,1),0) | AV6: =IF(AU6=1,IF(COUNTIFS($A$2:$A$201,$A6,$AU$2:$AU$201,1,$G$2:$G$201,"<"&G6)+COUNTIFS($A$2:$A$201,$A6,$AU$2:$AU$201,1,$G$2:$G$201,G6,$AT$2:$AT$201,"<"&AT6)=0,1,0),0) | AW6: =IF(AU6=1,IF(COUNTIFS($A$2:$A$201,$A6,$AU$2:$AU$201,1,$G$2:$G$201,">"&G6)+COUNTIFS($A$2:$A$201,$A6,$AU$2:$AU$201,1,$G$2:$G$201,G6,$AT$2:$AT$201,">"&AT6)=0,1,0),0) | AX6: =IF(AND(AU6=1,AN6="Y",Z6="Y",TRIM(AD6)<>""),1,0) | AY6: =IF(AX6=1,IF(COUNTIFS($A$2:$A$201,$A6,$AX$2:$AX$201,1,$G$2:$G$201,"<"&G6)+COUNTIFS($A$2:$A$201,$A6,$AX$2:$AX$201,1,$G$2:$G$201,G6,$AT$2:$AT$201,"<"&AT6)=0,1,0),0) | AZ6: =IF(AND(AU6=1,AN6="Y",AX6=0),1,0) | BA6: =IF(AND(AU6=1,ISNUMBER(V6)),1,0) | BB6: =IF(BA6=1,IF(COUNTIFS($A$2:$A$201,$A6,$BA$2:$BA$201,1,$G$2:$G$201,"<"&G6)+COUNTIFS($A$2:$A$201,$A6,$BA$2:$BA$201,1,$G$2:$G$201,G6,$AT$2:$AT$201,"<"&AT6)=0,1,0),0) | BC6: =IF(AND(BB6=1,G6<=Config!$B$6),V6,"") | BD6: =IF(AND(BB6=1,G6<=Config!$B$7),V6,"") | BE6: =IF(AND(BB6=1,G6<=Config!$B$8),V6,"") | BF6: =IF(AND(BB6=1,G6<=Config!$B$5),V6,"") | BG6: =IF(BW6=1,IF(COUNTIFS($A$2:$A$201,$A6,$BW$2:$BW$201,1,$G$2:$G$201,"<"&G6)+COUNTIFS($A$2:$A$201,$A6,$BW$2:$BW$201,1,$G$2:$G$201,G6,$AT$2:$AT$201,"<"&AT6)=0,1,0),0) | BH6: =IF(AND(AU6=1,ISNUMBER(K6)),1,0) | BI6: =IF(BH6=1,IF(COUNTIFS($A$2:$A$201,$A6,$BH$2:$BH$201,1,$G$2:$G$201,"<"&G6)+COUNTIFS($A$2:$A$201,$A6,$BH$2:$BH$201,1,$G$2:$G$201,G6,$AT$2:$AT$201,"<"&AT6)=0,1,0),0) | BJ6: =IF(AND(BI6=1,G6<=Config!$B$5),K6,"") | BK6: =IF(AND(AU6=1,OR(TRIM(U6)<>"",ISNUMBER(V6))),1,0) | BL6: =IF(BK6=1,IF(COUNTIFS($A$2:$A$201,$A6,$BK$2:$BK$201,1,$G$2:$G$201,"<"&G6)+COUNTIFS($A$2:$A$201,$A6,$BK$2:$BK$201,1,$G$2:$G$201,G6,$AT$2:$AT$201,"<"&AT6)=0,1,0),0) | BM6: =IF(BL6=1,$A6,"") | BN6: =IF(AND(AU6=1,T6="Y",TRIM(U6)=""),1,0) | BO6: =IF(AU6=1,AJ6&"","") | BP6: =IF(AU6=1,AK6&"","") | BQ6: =IF(AU6=1,AL6&"","") | BR6: =IF(AND(AU6=1,ISNUMBER(AP6),G6<=Config!$B$5),AP6,"") | BS6: =IF(AU6=1,IF(COUNTIFS($A$2:$A$201,$A6,$AN$2:$AN$201,"Y",$AU$2:$AU$201,1)>0,"Y","N"),"") | BT6: =IF(AND(AU6=1,AN6="maybe"),1,0) | BU6: =IF(BT6=1,IF(COUNTIFS($A$2:$A$201,$A6,$BT$2:$BT$201,1,$G$2:$G$201,"<"&G6)+COUNTIFS($A$2:$A$201,$A6,$BT$2:$BT$201,1,$G$2:$G$201,G6,$AT$2:$AT$201,"<"&AT6)=0,1,0),0) | BV6: =IF(AND(AU6=1,AN6="Y"),IF(COUNTIFS($A$2:$A$201,$A6,$AN$2:$AN$201,"Y",$AU$2:$AU$201,1,$G$2:$G$201,"<"&G6)+COUNTIFS($A$2:$A$201,$A6,$AN$2:$AN$201,"Y",$AU$2:$AU$201,1,$G$2:$G$201,G6,$AT$2:$AT$201,"<"&AT6)=0,1,0),0) | BW6: =IF(AND(BA6=1,N(V6)>=Config!$B$15),1,0) | BX6: =IF(AU6=1,IFERROR(MATCH($A6,INDEX(Clay_Offices!$A$2:$FZ$601,0,Sync!$C$5),0),""),"") | BY6: =IF(BX6="","",IFERROR(INDEX(Clay_Offices!$A$2:$FZ$601,BX6,Sync!$C$7)&"","")) | BZ6: =IF(BY6="","",IFERROR(INDEX(Lists!$J$2:$J$15,MATCH(BY6,Lists!$I$2:$I$15,0)),"")) | CA6: =IF(BX6="","",IFERROR(INDEX(Clay_Offices!$A$2:$FZ$601,BX6,Sync!$C$17)&"","")) | CB6: =IF(BX6="","",IFERROR(N(INDEX(Clay_Offices!$A$2:$FZ$601,BX6,Sync!$C$16)),0))
AS7: =IF(TRIM($A7)="","",IF(AND(LEFT($A7,6)="SAMPLE",Config!$B$19<>"Y"),"",IF(NOT(ISNUMBER(G7)),"call_date is blank or not a date",IF(Sync!$C$5="","Clay paste is empty or has no row_id column: paste the Clay export on Clay_Offices",IF(BX7="","row_id not found in the Clay paste: add the Clay row or fix the row_id",IF(AND(ISNUMBER(BZ7),BZ7>=1,BZ7<=5),"Clay status is "&BY7&": set call_done or later",IF(AND(AW7=1,CA7<>BS7),"Clay yes_in_principle should be "&BS7,IF(AND(AW7=1,CB7<>G7),"Clay call_date should be "&TEXT(G7,"yyyy-mm-dd"),"")))))))) | AT7: =ROW() | AU7: =IF(AND(TRIM($A7)<>"",ISNUMBER(G7)),IF(AND(LEFT($A7,6)="SAMPLE",Config!$B$19<>"Y"),0,1),0) | AV7: =IF(AU7=1,IF(COUNTIFS($A$2:$A$201,$A7,$AU$2:$AU$201,1,$G$2:$G$201,"<"&G7)+COUNTIFS($A$2:$A$201,$A7,$AU$2:$AU$201,1,$G$2:$G$201,G7,$AT$2:$AT$201,"<"&AT7)=0,1,0),0) | AW7: =IF(AU7=1,IF(COUNTIFS($A$2:$A$201,$A7,$AU$2:$AU$201,1,$G$2:$G$201,">"&G7)+COUNTIFS($A$2:$A$201,$A7,$AU$2:$AU$201,1,$G$2:$G$201,G7,$AT$2:$AT$201,">"&AT7)=0,1,0),0) | AX7: =IF(AND(AU7=1,AN7="Y",Z7="Y",TRIM(AD7)<>""),1,0) | AY7: =IF(AX7=1,IF(COUNTIFS($A$2:$A$201,$A7,$AX$2:$AX$201,1,$G$2:$G$201,"<"&G7)+COUNTIFS($A$2:$A$201,$A7,$AX$2:$AX$201,1,$G$2:$G$201,G7,$AT$2:$AT$201,"<"&AT7)=0,1,0),0) | AZ7: =IF(AND(AU7=1,AN7="Y",AX7=0),1,0) | BA7: =IF(AND(AU7=1,ISNUMBER(V7)),1,0) | BB7: =IF(BA7=1,IF(COUNTIFS($A$2:$A$201,$A7,$BA$2:$BA$201,1,$G$2:$G$201,"<"&G7)+COUNTIFS($A$2:$A$201,$A7,$BA$2:$BA$201,1,$G$2:$G$201,G7,$AT$2:$AT$201,"<"&AT7)=0,1,0),0) | BC7: =IF(AND(BB7=1,G7<=Config!$B$6),V7,"") | BD7: =IF(AND(BB7=1,G7<=Config!$B$7),V7,"") | BE7: =IF(AND(BB7=1,G7<=Config!$B$8),V7,"") | BF7: =IF(AND(BB7=1,G7<=Config!$B$5),V7,"") | BG7: =IF(BW7=1,IF(COUNTIFS($A$2:$A$201,$A7,$BW$2:$BW$201,1,$G$2:$G$201,"<"&G7)+COUNTIFS($A$2:$A$201,$A7,$BW$2:$BW$201,1,$G$2:$G$201,G7,$AT$2:$AT$201,"<"&AT7)=0,1,0),0) | BH7: =IF(AND(AU7=1,ISNUMBER(K7)),1,0) | BI7: =IF(BH7=1,IF(COUNTIFS($A$2:$A$201,$A7,$BH$2:$BH$201,1,$G$2:$G$201,"<"&G7)+COUNTIFS($A$2:$A$201,$A7,$BH$2:$BH$201,1,$G$2:$G$201,G7,$AT$2:$AT$201,"<"&AT7)=0,1,0),0) | BJ7: =IF(AND(BI7=1,G7<=Config!$B$5),K7,"") | BK7: =IF(AND(AU7=1,OR(TRIM(U7)<>"",ISNUMBER(V7))),1,0) | BL7: =IF(BK7=1,IF(COUNTIFS($A$2:$A$201,$A7,$BK$2:$BK$201,1,$G$2:$G$201,"<"&G7)+COUNTIFS($A$2:$A$201,$A7,$BK$2:$BK$201,1,$G$2:$G$201,G7,$AT$2:$AT$201,"<"&AT7)=0,1,0),0) | BM7: =IF(BL7=1,$A7,"") | BN7: =IF(AND(AU7=1,T7="Y",TRIM(U7)=""),1,0) | BO7: =IF(AU7=1,AJ7&"","") | BP7: =IF(AU7=1,AK7&"","") | BQ7: =IF(AU7=1,AL7&"","") | BR7: =IF(AND(AU7=1,ISNUMBER(AP7),G7<=Config!$B$5),AP7,"") | BS7: =IF(AU7=1,IF(COUNTIFS($A$2:$A$201,$A7,$AN$2:$AN$201,"Y",$AU$2:$AU$201,1)>0,"Y","N"),"") | BT7: =IF(AND(AU7=1,AN7="maybe"),1,0) | BU7: =IF(BT7=1,IF(COUNTIFS($A$2:$A$201,$A7,$BT$2:$BT$201,1,$G$2:$G$201,"<"&G7)+COUNTIFS($A$2:$A$201,$A7,$BT$2:$BT$201,1,$G$2:$G$201,G7,$AT$2:$AT$201,"<"&AT7)=0,1,0),0) | BV7: =IF(AND(AU7=1,AN7="Y"),IF(COUNTIFS($A$2:$A$201,$A7,$AN$2:$AN$201,"Y",$AU$2:$AU$201,1,$G$2:$G$201,"<"&G7)+COUNTIFS($A$2:$A$201,$A7,$AN$2:$AN$201,"Y",$AU$2:$AU$201,1,$G$2:$G$201,G7,$AT$2:$AT$201,"<"&AT7)=0,1,0),0) | BW7: =IF(AND(BA7=1,N(V7)>=Config!$B$15),1,0) | BX7: =IF(AU7=1,IFERROR(MATCH($A7,INDEX(Clay_Offices!$A$2:$FZ$601,0,Sync!$C$5),0),""),"") | BY7: =IF(BX7="","",IFERROR(INDEX(Clay_Offices!$A$2:$FZ$601,BX7,Sync!$C$7)&"","")) | BZ7: =IF(BY7="","",IFERROR(INDEX(Lists!$J$2:$J$15,MATCH(BY7,Lists!$I$2:$I$15,0)),"")) | CA7: =IF(BX7="","",IFERROR(INDEX(Clay_Offices!$A$2:$FZ$601,BX7,Sync!$C$17)&"","")) | CB7: =IF(BX7="","",IFERROR(N(INDEX(Clay_Offices!$A$2:$FZ$601,BX7,Sync!$C$16)),0))
AS8: =IF(TRIM($A8)="","",IF(AND(LEFT($A8,6)="SAMPLE",Config!$B$19<>"Y"),"",IF(NOT(ISNUMBER(G8)),"call_date is blank or not a date",IF(Sync!$C$5="","Clay paste is empty or has no row_id column: paste the Clay export on Clay_Offices",IF(BX8="","row_id not found in the Clay paste: add the Clay row or fix the row_id",IF(AND(ISNUMBER(BZ8),BZ8>=1,BZ8<=5),"Clay status is "&BY8&": set call_done or later",IF(AND(AW8=1,CA8<>BS8),"Clay yes_in_principle should be "&BS8,IF(AND(AW8=1,CB8<>G8),"Clay call_date should be "&TEXT(G8,"yyyy-mm-dd"),"")))))))) | AT8: =ROW() | AU8: =IF(AND(TRIM($A8)<>"",ISNUMBER(G8)),IF(AND(LEFT($A8,6)="SAMPLE",Config!$B$19<>"Y"),0,1),0) | AV8: =IF(AU8=1,IF(COUNTIFS($A$2:$A$201,$A8,$AU$2:$AU$201,1,$G$2:$G$201,"<"&G8)+COUNTIFS($A$2:$A$201,$A8,$AU$2:$AU$201,1,$G$2:$G$201,G8,$AT$2:$AT$201,"<"&AT8)=0,1,0),0) | AW8: =IF(AU8=1,IF(COUNTIFS($A$2:$A$201,$A8,$AU$2:$AU$201,1,$G$2:$G$201,">"&G8)+COUNTIFS($A$2:$A$201,$A8,$AU$2:$AU$201,1,$G$2:$G$201,G8,$AT$2:$AT$201,">"&AT8)=0,1,0),0) | AX8: =IF(AND(AU8=1,AN8="Y",Z8="Y",TRIM(AD8)<>""),1,0) | AY8: =IF(AX8=1,IF(COUNTIFS($A$2:$A$201,$A8,$AX$2:$AX$201,1,$G$2:$G$201,"<"&G8)+COUNTIFS($A$2:$A$201,$A8,$AX$2:$AX$201,1,$G$2:$G$201,G8,$AT$2:$AT$201,"<"&AT8)=0,1,0),0) | AZ8: =IF(AND(AU8=1,AN8="Y",AX8=0),1,0) | BA8: =IF(AND(AU8=1,ISNUMBER(V8)),1,0) | BB8: =IF(BA8=1,IF(COUNTIFS($A$2:$A$201,$A8,$BA$2:$BA$201,1,$G$2:$G$201,"<"&G8)+COUNTIFS($A$2:$A$201,$A8,$BA$2:$BA$201,1,$G$2:$G$201,G8,$AT$2:$AT$201,"<"&AT8)=0,1,0),0) | BC8: =IF(AND(BB8=1,G8<=Config!$B$6),V8,"") | BD8: =IF(AND(BB8=1,G8<=Config!$B$7),V8,"") | BE8: =IF(AND(BB8=1,G8<=Config!$B$8),V8,"") | BF8: =IF(AND(BB8=1,G8<=Config!$B$5),V8,"") | BG8: =IF(BW8=1,IF(COUNTIFS($A$2:$A$201,$A8,$BW$2:$BW$201,1,$G$2:$G$201,"<"&G8)+COUNTIFS($A$2:$A$201,$A8,$BW$2:$BW$201,1,$G$2:$G$201,G8,$AT$2:$AT$201,"<"&AT8)=0,1,0),0) | BH8: =IF(AND(AU8=1,ISNUMBER(K8)),1,0) | BI8: =IF(BH8=1,IF(COUNTIFS($A$2:$A$201,$A8,$BH$2:$BH$201,1,$G$2:$G$201,"<"&G8)+COUNTIFS($A$2:$A$201,$A8,$BH$2:$BH$201,1,$G$2:$G$201,G8,$AT$2:$AT$201,"<"&AT8)=0,1,0),0) | BJ8: =IF(AND(BI8=1,G8<=Config!$B$5),K8,"") | BK8: =IF(AND(AU8=1,OR(TRIM(U8)<>"",ISNUMBER(V8))),1,0) | BL8: =IF(BK8=1,IF(COUNTIFS($A$2:$A$201,$A8,$BK$2:$BK$201,1,$G$2:$G$201,"<"&G8)+COUNTIFS($A$2:$A$201,$A8,$BK$2:$BK$201,1,$G$2:$G$201,G8,$AT$2:$AT$201,"<"&AT8)=0,1,0),0) | BM8: =IF(BL8=1,$A8,"") | BN8: =IF(AND(AU8=1,T8="Y",TRIM(U8)=""),1,0) | BO8: =IF(AU8=1,AJ8&"","") | BP8: =IF(AU8=1,AK8&"","") | BQ8: =IF(AU8=1,AL8&"","") | BR8: =IF(AND(AU8=1,ISNUMBER(AP8),G8<=Config!$B$5),AP8,"") | BS8: =IF(AU8=1,IF(COUNTIFS($A$2:$A$201,$A8,$AN$2:$AN$201,"Y",$AU$2:$AU$201,1)>0,"Y","N"),"") | BT8: =IF(AND(AU8=1,AN8="maybe"),1,0) | BU8: =IF(BT8=1,IF(COUNTIFS($A$2:$A$201,$A8,$BT$2:$BT$201,1,$G$2:$G$201,"<"&G8)+COUNTIFS($A$2:$A$201,$A8,$BT$2:$BT$201,1,$G$2:$G$201,G8,$AT$2:$AT$201,"<"&AT8)=0,1,0),0) | BV8: =IF(AND(AU8=1,AN8="Y"),IF(COUNTIFS($A$2:$A$201,$A8,$AN$2:$AN$201,"Y",$AU$2:$AU$201,1,$G$2:$G$201,"<"&G8)+COUNTIFS($A$2:$A$201,$A8,$AN$2:$AN$201,"Y",$AU$2:$AU$201,1,$G$2:$G$201,G8,$AT$2:$AT$201,"<"&AT8)=0,1,0),0) | BW8: =IF(AND(BA8=1,N(V8)>=Config!$B$15),1,0) | BX8: =IF(AU8=1,IFERROR(MATCH($A8,INDEX(Clay_Offices!$A$2:$FZ$601,0,Sync!$C$5),0),""),"") | BY8: =IF(BX8="","",IFERROR(INDEX(Clay_Offices!$A$2:$FZ$601,BX8,Sync!$C$7)&"","")) | BZ8: =IF(BY8="","",IFERROR(INDEX(Lists!$J$2:$J$15,MATCH(BY8,Lists!$I$2:$I$15,0)),"")) | CA8: =IF(BX8="","",IFERROR(INDEX(Clay_Offices!$A$2:$FZ$601,BX8,Sync!$C$17)&"","")) | CB8: =IF(BX8="","",IFERROR(N(INDEX(Clay_Offices!$A$2:$FZ$601,BX8,Sync!$C$16)),0))
AS9: =IF(TRIM($A9)="","",IF(AND(LEFT($A9,6)="SAMPLE",Config!$B$19<>"Y"),"",IF(NOT(ISNUMBER(G9)),"call_date is blank or not a date",IF(Sync!$C$5="","Clay paste is empty or has no row_id column: paste the Clay export on Clay_Offices",IF(BX9="","row_id not found in the Clay paste: add the Clay row or fix the row_id",IF(AND(ISNUMBER(BZ9),BZ9>=1,BZ9<=5),"Clay status is "&BY9&": set call_done or later",IF(AND(AW9=1,CA9<>BS9),"Clay yes_in_principle should be "&BS9,IF(AND(AW9=1,CB9<>G9),"Clay call_date should be "&TEXT(G9,"yyyy-mm-dd"),"")))))))) | AT9: =ROW() | AU9: =IF(AND(TRIM($A9)<>"",ISNUMBER(G9)),IF(AND(LEFT($A9,6)="SAMPLE",Config!$B$19<>"Y"),0,1),0) | AV9: =IF(AU9=1,IF(COUNTIFS($A$2:$A$201,$A9,$AU$2:$AU$201,1,$G$2:$G$201,"<"&G9)+COUNTIFS($A$2:$A$201,$A9,$AU$2:$AU$201,1,$G$2:$G$201,G9,$AT$2:$AT$201,"<"&AT9)=0,1,0),0) | AW9: =IF(AU9=1,IF(COUNTIFS($A$2:$A$201,$A9,$AU$2:$AU$201,1,$G$2:$G$201,">"&G9)+COUNTIFS($A$2:$A$201,$A9,$AU$2:$AU$201,1,$G$2:$G$201,G9,$AT$2:$AT$201,">"&AT9)=0,1,0),0) | AX9: =IF(AND(AU9=1,AN9="Y",Z9="Y",TRIM(AD9)<>""),1,0) | AY9: =IF(AX9=1,IF(COUNTIFS($A$2:$A$201,$A9,$AX$2:$AX$201,1,$G$2:$G$201,"<"&G9)+COUNTIFS($A$2:$A$201,$A9,$AX$2:$AX$201,1,$G$2:$G$201,G9,$AT$2:$AT$201,"<"&AT9)=0,1,0),0) | AZ9: =IF(AND(AU9=1,AN9="Y",AX9=0),1,0) | BA9: =IF(AND(AU9=1,ISNUMBER(V9)),1,0) | BB9: =IF(BA9=1,IF(COUNTIFS($A$2:$A$201,$A9,$BA$2:$BA$201,1,$G$2:$G$201,"<"&G9)+COUNTIFS($A$2:$A$201,$A9,$BA$2:$BA$201,1,$G$2:$G$201,G9,$AT$2:$AT$201,"<"&AT9)=0,1,0),0) | BC9: =IF(AND(BB9=1,G9<=Config!$B$6),V9,"") | BD9: =IF(AND(BB9=1,G9<=Config!$B$7),V9,"") | BE9: =IF(AND(BB9=1,G9<=Config!$B$8),V9,"") | BF9: =IF(AND(BB9=1,G9<=Config!$B$5),V9,"") | BG9: =IF(BW9=1,IF(COUNTIFS($A$2:$A$201,$A9,$BW$2:$BW$201,1,$G$2:$G$201,"<"&G9)+COUNTIFS($A$2:$A$201,$A9,$BW$2:$BW$201,1,$G$2:$G$201,G9,$AT$2:$AT$201,"<"&AT9)=0,1,0),0) | BH9: =IF(AND(AU9=1,ISNUMBER(K9)),1,0) | BI9: =IF(BH9=1,IF(COUNTIFS($A$2:$A$201,$A9,$BH$2:$BH$201,1,$G$2:$G$201,"<"&G9)+COUNTIFS($A$2:$A$201,$A9,$BH$2:$BH$201,1,$G$2:$G$201,G9,$AT$2:$AT$201,"<"&AT9)=0,1,0),0) | BJ9: =IF(AND(BI9=1,G9<=Config!$B$5),K9,"") | BK9: =IF(AND(AU9=1,OR(TRIM(U9)<>"",ISNUMBER(V9))),1,0) | BL9: =IF(BK9=1,IF(COUNTIFS($A$2:$A$201,$A9,$BK$2:$BK$201,1,$G$2:$G$201,"<"&G9)+COUNTIFS($A$2:$A$201,$A9,$BK$2:$BK$201,1,$G$2:$G$201,G9,$AT$2:$AT$201,"<"&AT9)=0,1,0),0) | BM9: =IF(BL9=1,$A9,"") | BN9: =IF(AND(AU9=1,T9="Y",TRIM(U9)=""),1,0) | BO9: =IF(AU9=1,AJ9&"","") | BP9: =IF(AU9=1,AK9&"","") | BQ9: =IF(AU9=1,AL9&"","") | BR9: =IF(AND(AU9=1,ISNUMBER(AP9),G9<=Config!$B$5),AP9,"") | BS9: =IF(AU9=1,IF(COUNTIFS($A$2:$A$201,$A9,$AN$2:$AN$201,"Y",$AU$2:$AU$201,1)>0,"Y","N"),"") | BT9: =IF(AND(AU9=1,AN9="maybe"),1,0) | BU9: =IF(BT9=1,IF(COUNTIFS($A$2:$A$201,$A9,$BT$2:$BT$201,1,$G$2:$G$201,"<"&G9)+COUNTIFS($A$2:$A$201,$A9,$BT$2:$BT$201,1,$G$2:$G$201,G9,$AT$2:$AT$201,"<"&AT9)=0,1,0),0) | BV9: =IF(AND(AU9=1,AN9="Y"),IF(COUNTIFS($A$2:$A$201,$A9,$AN$2:$AN$201,"Y",$AU$2:$AU$201,1,$G$2:$G$201,"<"&G9)+COUNTIFS($A$2:$A$201,$A9,$AN$2:$AN$201,"Y",$AU$2:$AU$201,1,$G$2:$G$201,G9,$AT$2:$AT$201,"<"&AT9)=0,1,0),0) | BW9: =IF(AND(BA9=1,N(V9)>=Config!$B$15),1,0) | BX9: =IF(AU9=1,IFERROR(MATCH($A9,INDEX(Clay_Offices!$A$2:$FZ$601,0,Sync!$C$5),0),""),"") | BY9: =IF(BX9="","",IFERROR(INDEX(Clay_Offices!$A$2:$FZ$601,BX9,Sync!$C$7)&"","")) | BZ9: =IF(BY9="","",IFERROR(INDEX(Lists!$J$2:$J$15,MATCH(BY9,Lists!$I$2:$I$15,0)),"")) | CA9: =IF(BX9="","",IFERROR(INDEX(Clay_Offices!$A$2:$FZ$601,BX9,Sync!$C$17)&"","")) | CB9: =IF(BX9="","",IFERROR(N(INDEX(Clay_Offices!$A$2:$FZ$601,BX9,Sync!$C$16)),0))
AS10: =IF(TRIM($A10)="","",IF(AND(LEFT($A10,6)="SAMPLE",Config!$B$19<>"Y"),"",IF(NOT(ISNUMBER(G10)),"call_date is blank or not a date",IF(Sync!$C$5="","Clay paste is empty or has no row_id column: paste the Clay export on Clay_Offices",IF(BX10="","row_id not found in the Clay paste: add the Clay row or fix the row_id",IF(AND(ISNUMBER(BZ10),BZ10>=1,BZ10<=5),"Clay status is "&BY10&": set call_done or later",IF(AND(AW10=1,CA10<>BS10),"Clay yes_in_principle should be "&BS10,IF(AND(AW10=1,CB10<>G10),"Clay call_date should be "&TEXT(G10,"yyyy-mm-dd"),"")))))))) | AT10: =ROW() | AU10: =IF(AND(TRIM($A10)<>"",ISNUMBER(G10)),IF(AND(LEFT($A10,6)="SAMPLE",Config!$B$19<>"Y"),0,1),0) | AV10: =IF(AU10=1,IF(COUNTIFS($A$2:$A$201,$A10,$AU$2:$AU$201,1,$G$2:$G$201,"<"&G10)+COUNTIFS($A$2:$A$201,$A10,$AU$2:$AU$201,1,$G$2:$G$201,G10,$AT$2:$AT$201,"<"&AT10)=0,1,0),0) | AW10: =IF(AU10=1,IF(COUNTIFS($A$2:$A$201,$A10,$AU$2:$AU$201,1,$G$2:$G$201,">"&G10)+COUNTIFS($A$2:$A$201,$A10,$AU$2:$AU$201,1,$G$2:$G$201,G10,$AT$2:$AT$201,">"&AT10)=0,1,0),0) | AX10: =IF(AND(AU10=1,AN10="Y",Z10="Y",TRIM(AD10)<>""),1,0) | AY10: =IF(AX10=1,IF(COUNTIFS($A$2:$A$201,$A10,$AX$2:$AX$201,1,$G$2:$G$201,"<"&G10)+COUNTIFS($A$2:$A$201,$A10,$AX$2:$AX$201,1,$G$2:$G$201,G10,$AT$2:$AT$201,"<"&AT10)=0,1,0),0) | AZ10: =IF(AND(AU10=1,AN10="Y",AX10=0),1,0) | BA10: =IF(AND(AU10=1,ISNUMBER(V10)),1,0) | BB10: =IF(BA10=1,IF(COUNTIFS($A$2:$A$201,$A10,$BA$2:$BA$201,1,$G$2:$G$201,"<"&G10)+COUNTIFS($A$2:$A$201,$A10,$BA$2:$BA$201,1,$G$2:$G$201,G10,$AT$2:$AT$201,"<"&AT10)=0,1,0),0) | BC10: =IF(AND(BB10=1,G10<=Config!$B$6),V10,"") | BD10: =IF(AND(BB10=1,G10<=Config!$B$7),V10,"") | BE10: =IF(AND(BB10=1,G10<=Config!$B$8),V10,"") | BF10: =IF(AND(BB10=1,G10<=Config!$B$5),V10,"") | BG10: =IF(BW10=1,IF(COUNTIFS($A$2:$A$201,$A10,$BW$2:$BW$201,1,$G$2:$G$201,"<"&G10)+COUNTIFS($A$2:$A$201,$A10,$BW$2:$BW$201,1,$G$2:$G$201,G10,$AT$2:$AT$201,"<"&AT10)=0,1,0),0) | BH10: =IF(AND(AU10=1,ISNUMBER(K10)),1,0) | BI10: =IF(BH10=1,IF(COUNTIFS($A$2:$A$201,$A10,$BH$2:$BH$201,1,$G$2:$G$201,"<"&G10)+COUNTIFS($A$2:$A$201,$A10,$BH$2:$BH$201,1,$G$2:$G$201,G10,$AT$2:$AT$201,"<"&AT10)=0,1,0),0) | BJ10: =IF(AND(BI10=1,G10<=Config!$B$5),K10,"") | BK10: =IF(AND(AU10=1,OR(TRIM(U10)<>"",ISNUMBER(V10))),1,0) | BL10: =IF(BK10=1,IF(COUNTIFS($A$2:$A$201,$A10,$BK$2:$BK$201,1,$G$2:$G$201,"<"&G10)+COUNTIFS($A$2:$A$201,$A10,$BK$2:$BK$201,1,$G$2:$G$201,G10,$AT$2:$AT$201,"<"&AT10)=0,1,0),0) | BM10: =IF(BL10=1,$A10,"") | BN10: =IF(AND(AU10=1,T10="Y",TRIM(U10)=""),1,0) | BO10: =IF(AU10=1,AJ10&"","") | BP10: =IF(AU10=1,AK10&"","") | BQ10: =IF(AU10=1,AL10&"","") | BR10: =IF(AND(AU10=1,ISNUMBER(AP10),G10<=Config!$B$5),AP10,"") | BS10: =IF(AU10=1,IF(COUNTIFS($A$2:$A$201,$A10,$AN$2:$AN$201,"Y",$AU$2:$AU$201,1)>0,"Y","N"),"") | BT10: =IF(AND(AU10=1,AN10="maybe"),1,0) | BU10: =IF(BT10=1,IF(COUNTIFS($A$2:$A$201,$A10,$BT$2:$BT$201,1,$G$2:$G$201,"<"&G10)+COUNTIFS($A$2:$A$201,$A10,$BT$2:$BT$201,1,$G$2:$G$201,G10,$AT$2:$AT$201,"<"&AT10)=0,1,0),0) | BV10: =IF(AND(AU10=1,AN10="Y"),IF(COUNTIFS($A$2:$A$201,$A10,$AN$2:$AN$201,"Y",$AU$2:$AU$201,1,$G$2:$G$201,"<"&G10)+COUNTIFS($A$2:$A$201,$A10,$AN$2:$AN$201,"Y",$AU$2:$AU$201,1,$G$2:$G$201,G10,$AT$2:$AT$201,"<"&AT10)=0,1,0),0) | BW10: =IF(AND(BA10=1,N(V10)>=Config!$B$15),1,0) | BX10: =IF(AU10=1,IFERROR(MATCH($A10,INDEX(Clay_Offices!$A$2:$FZ$601,0,Sync!$C$5),0),""),"") | BY10: =IF(BX10="","",IFERROR(INDEX(Clay_Offices!$A$2:$FZ$601,BX10,Sync!$C$7)&"","")) | BZ10: =IF(BY10="","",IFERROR(INDEX(Lists!$J$2:$J$15,MATCH(BY10,Lists!$I$2:$I$15,0)),"")) | CA10: =IF(BX10="","",IFERROR(INDEX(Clay_Offices!$A$2:$FZ$601,BX10,Sync!$C$17)&"","")) | CB10: =IF(BX10="","",IFERROR(N(INDEX(Clay_Offices!$A$2:$FZ$601,BX10,Sync!$C$16)),0))
AS11: =IF(TRIM($A11)="","",IF(AND(LEFT($A11,6)="SAMPLE",Config!$B$19<>"Y"),"",IF(NOT(ISNUMBER(G11)),"call_date is blank or not a date",IF(Sync!$C$5="","Clay paste is empty or has no row_id column: paste the Clay export on Clay_Offices",IF(BX11="","row_id not found in the Clay paste: add the Clay row or fix the row_id",IF(AND(ISNUMBER(BZ11),BZ11>=1,BZ11<=5),"Clay status is "&BY11&": set call_done or later",IF(AND(AW11=1,CA11<>BS11),"Clay yes_in_principle should be "&BS11,IF(AND(AW11=1,CB11<>G11),"Clay call_date should be "&TEXT(G11,"yyyy-mm-dd"),"")))))))) | AT11: =ROW() | AU11: =IF(AND(TRIM($A11)<>"",ISNUMBER(G11)),IF(AND(LEFT($A11,6)="SAMPLE",Config!$B$19<>"Y"),0,1),0) | AV11: =IF(AU11=1,IF(COUNTIFS($A$2:$A$201,$A11,$AU$2:$AU$201,1,$G$2:$G$201,"<"&G11)+COUNTIFS($A$2:$A$201,$A11,$AU$2:$AU$201,1,$G$2:$G$201,G11,$AT$2:$AT$201,"<"&AT11)=0,1,0),0) | AW11: =IF(AU11=1,IF(COUNTIFS($A$2:$A$201,$A11,$AU$2:$AU$201,1,$G$2:$G$201,">"&G11)+COUNTIFS($A$2:$A$201,$A11,$AU$2:$AU$201,1,$G$2:$G$201,G11,$AT$2:$AT$201,">"&AT11)=0,1,0),0) | AX11: =IF(AND(AU11=1,AN11="Y",Z11="Y",TRIM(AD11)<>""),1,0) | AY11: =IF(AX11=1,IF(COUNTIFS($A$2:$A$201,$A11,$AX$2:$AX$201,1,$G$2:$G$201,"<"&G11)+COUNTIFS($A$2:$A$201,$A11,$AX$2:$AX$201,1,$G$2:$G$201,G11,$AT$2:$AT$201,"<"&AT11)=0,1,0),0) | AZ11: =IF(AND(AU11=1,AN11="Y",AX11=0),1,0) | BA11: =IF(AND(AU11=1,ISNUMBER(V11)),1,0) | BB11: =IF(BA11=1,IF(COUNTIFS($A$2:$A$201,$A11,$BA$2:$BA$201,1,$G$2:$G$201,"<"&G11)+COUNTIFS($A$2:$A$201,$A11,$BA$2:$BA$201,1,$G$2:$G$201,G11,$AT$2:$AT$201,"<"&AT11)=0,1,0),0) | BC11: =IF(AND(BB11=1,G11<=Config!$B$6),V11,"") | BD11: =IF(AND(BB11=1,G11<=Config!$B$7),V11,"") | BE11: =IF(AND(BB11=1,G11<=Config!$B$8),V11,"") | BF11: =IF(AND(BB11=1,G11<=Config!$B$5),V11,"") | BG11: =IF(BW11=1,IF(COUNTIFS($A$2:$A$201,$A11,$BW$2:$BW$201,1,$G$2:$G$201,"<"&G11)+COUNTIFS($A$2:$A$201,$A11,$BW$2:$BW$201,1,$G$2:$G$201,G11,$AT$2:$AT$201,"<"&AT11)=0,1,0),0) | BH11: =IF(AND(AU11=1,ISNUMBER(K11)),1,0) | BI11: =IF(BH11=1,IF(COUNTIFS($A$2:$A$201,$A11,$BH$2:$BH$201,1,$G$2:$G$201,"<"&G11)+COUNTIFS($A$2:$A$201,$A11,$BH$2:$BH$201,1,$G$2:$G$201,G11,$AT$2:$AT$201,"<"&AT11)=0,1,0),0) | BJ11: =IF(AND(BI11=1,G11<=Config!$B$5),K11,"") | BK11: =IF(AND(AU11=1,OR(TRIM(U11)<>"",ISNUMBER(V11))),1,0) | BL11: =IF(BK11=1,IF(COUNTIFS($A$2:$A$201,$A11,$BK$2:$BK$201,1,$G$2:$G$201,"<"&G11)+COUNTIFS($A$2:$A$201,$A11,$BK$2:$BK$201,1,$G$2:$G$201,G11,$AT$2:$AT$201,"<"&AT11)=0,1,0),0) | BM11: =IF(BL11=1,$A11,"") | BN11: =IF(AND(AU11=1,T11="Y",TRIM(U11)=""),1,0) | BO11: =IF(AU11=1,AJ11&"","") | BP11: =IF(AU11=1,AK11&"","") | BQ11: =IF(AU11=1,AL11&"","") | BR11: =IF(AND(AU11=1,ISNUMBER(AP11),G11<=Config!$B$5),AP11,"") | BS11: =IF(AU11=1,IF(COUNTIFS($A$2:$A$201,$A11,$AN$2:$AN$201,"Y",$AU$2:$AU$201,1)>0,"Y","N"),"") | BT11: =IF(AND(AU11=1,AN11="maybe"),1,0) | BU11: =IF(BT11=1,IF(COUNTIFS($A$2:$A$201,$A11,$BT$2:$BT$201,1,$G$2:$G$201,"<"&G11)+COUNTIFS($A$2:$A$201,$A11,$BT$2:$BT$201,1,$G$2:$G$201,G11,$AT$2:$AT$201,"<"&AT11)=0,1,0),0) | BV11: =IF(AND(AU11=1,AN11="Y"),IF(COUNTIFS($A$2:$A$201,$A11,$AN$2:$AN$201,"Y",$AU$2:$AU$201,1,$G$2:$G$201,"<"&G11)+COUNTIFS($A$2:$A$201,$A11,$AN$2:$AN$201,"Y",$AU$2:$AU$201,1,$G$2:$G$201,G11,$AT$2:$AT$201,"<"&AT11)=0,1,0),0) | BW11: =IF(AND(BA11=1,N(V11)>=Config!$B$15),1,0) | BX11: =IF(AU11=1,IFERROR(MATCH($A11,INDEX(Clay_Offices!$A$2:$FZ$601,0,Sync!$C$5),0),""),"") | BY11: =IF(BX11="","",IFERROR(INDEX(Clay_Offices!$A$2:$FZ$601,BX11,Sync!$C$7)&"","")) | BZ11: =IF(BY11="","",IFERROR(INDEX(Lists!$J$2:$J$15,MATCH(BY11,Lists!$I$2:$I$15,0)),"")) | CA11: =IF(BX11="","",IFERROR(INDEX(Clay_Offices!$A$2:$FZ$601,BX11,Sync!$C$17)&"","")) | CB11: =IF(BX11="","",IFERROR(N(INDEX(Clay_Offices!$A$2:$FZ$601,BX11,Sync!$C$16)),0))
AS12: =IF(TRIM($A12)="","",IF(AND(LEFT($A12,6)="SAMPLE",Config!$B$19<>"Y"),"",IF(NOT(ISNUMBER(G12)),"call_date is blank or not a date",IF(Sync!$C$5="","Clay paste is empty or has no row_id column: paste the Clay export on Clay_Offices",IF(BX12="","row_id not found in the Clay paste: add the Clay row or fix the row_id",IF(AND(ISNUMBER(BZ12),BZ12>=1,BZ12<=5),"Clay status is "&BY12&": set call_done or later",IF(AND(AW12=1,CA12<>BS12),"Clay yes_in_principle should be "&BS12,IF(AND(AW12=1,CB12<>G12),"Clay call_date should be "&TEXT(G12,"yyyy-mm-dd"),"")))))))) | AT12: =ROW() | AU12: =IF(AND(TRIM($A12)<>"",ISNUMBER(G12)),IF(AND(LEFT($A12,6)="SAMPLE",Config!$B$19<>"Y"),0,1),0) | AV12: =IF(AU12=1,IF(COUNTIFS($A$2:$A$201,$A12,$AU$2:$AU$201,1,$G$2:$G$201,"<"&G12)+COUNTIFS($A$2:$A$201,$A12,$AU$2:$AU$201,1,$G$2:$G$201,G12,$AT$2:$AT$201,"<"&AT12)=0,1,0),0) | AW12: =IF(AU12=1,IF(COUNTIFS($A$2:$A$201,$A12,$AU$2:$AU$201,1,$G$2:$G$201,">"&G12)+COUNTIFS($A$2:$A$201,$A12,$AU$2:$AU$201,1,$G$2:$G$201,G12,$AT$2:$AT$201,">"&AT12)=0,1,0),0) | AX12: =IF(AND(AU12=1,AN12="Y",Z12="Y",TRIM(AD12)<>""),1,0) | AY12: =IF(AX12=1,IF(COUNTIFS($A$2:$A$201,$A12,$AX$2:$AX$201,1,$G$2:$G$201,"<"&G12)+COUNTIFS($A$2:$A$201,$A12,$AX$2:$AX$201,1,$G$2:$G$201,G12,$AT$2:$AT$201,"<"&AT12)=0,1,0),0) | AZ12: =IF(AND(AU12=1,AN12="Y",AX12=0),1,0) | BA12: =IF(AND(AU12=1,ISNUMBER(V12)),1,0) | BB12: =IF(BA12=1,IF(COUNTIFS($A$2:$A$201,$A12,$BA$2:$BA$201,1,$G$2:$G$201,"<"&G12)+COUNTIFS($A$2:$A$201,$A12,$BA$2:$BA$201,1,$G$2:$G$201,G12,$AT$2:$AT$201,"<"&AT12)=0,1,0),0) | BC12: =IF(AND(BB12=1,G12<=Config!$B$6),V12,"") | BD12: =IF(AND(BB12=1,G12<=Config!$B$7),V12,"") | BE12: =IF(AND(BB12=1,G12<=Config!$B$8),V12,"") | BF12: =IF(AND(BB12=1,G12<=Config!$B$5),V12,"") | BG12: =IF(BW12=1,IF(COUNTIFS($A$2:$A$201,$A12,$BW$2:$BW$201,1,$G$2:$G$201,"<"&G12)+COUNTIFS($A$2:$A$201,$A12,$BW$2:$BW$201,1,$G$2:$G$201,G12,$AT$2:$AT$201,"<"&AT12)=0,1,0),0) | BH12: =IF(AND(AU12=1,ISNUMBER(K12)),1,0) | BI12: =IF(BH12=1,IF(COUNTIFS($A$2:$A$201,$A12,$BH$2:$BH$201,1,$G$2:$G$201,"<"&G12)+COUNTIFS($A$2:$A$201,$A12,$BH$2:$BH$201,1,$G$2:$G$201,G12,$AT$2:$AT$201,"<"&AT12)=0,1,0),0) | BJ12: =IF(AND(BI12=1,G12<=Config!$B$5),K12,"") | BK12: =IF(AND(AU12=1,OR(TRIM(U12)<>"",ISNUMBER(V12))),1,0) | BL12: =IF(BK12=1,IF(COUNTIFS($A$2:$A$201,$A12,$BK$2:$BK$201,1,$G$2:$G$201,"<"&G12)+COUNTIFS($A$2:$A$201,$A12,$BK$2:$BK$201,1,$G$2:$G$201,G12,$AT$2:$AT$201,"<"&AT12)=0,1,0),0) | BM12: =IF(BL12=1,$A12,"") | BN12: =IF(AND(AU12=1,T12="Y",TRIM(U12)=""),1,0) | BO12: =IF(AU12=1,AJ12&"","") | BP12: =IF(AU12=1,AK12&"","") | BQ12: =IF(AU12=1,AL12&"","") | BR12: =IF(AND(AU12=1,ISNUMBER(AP12),G12<=Config!$B$5),AP12,"") | BS12: =IF(AU12=1,IF(COUNTIFS($A$2:$A$201,$A12,$AN$2:$AN$201,"Y",$AU$2:$AU$201,1)>0,"Y","N"),"") | BT12: =IF(AND(AU12=1,AN12="maybe"),1,0) | BU12: =IF(BT12=1,IF(COUNTIFS($A$2:$A$201,$A12,$BT$2:$BT$201,1,$G$2:$G$201,"<"&G12)+COUNTIFS($A$2:$A$201,$A12,$BT$2:$BT$201,1,$G$2:$G$201,G12,$AT$2:$AT$201,"<"&AT12)=0,1,0),0) | BV12: =IF(AND(AU12=1,AN12="Y"),IF(COUNTIFS($A$2:$A$201,$A12,$AN$2:$AN$201,"Y",$AU$2:$AU$201,1,$G$2:$G$201,"<"&G12)+COUNTIFS($A$2:$A$201,$A12,$AN$2:$AN$201,"Y",$AU$2:$AU$201,1,$G$2:$G$201,G12,$AT$2:$AT$201,"<"&AT12)=0,1,0),0) | BW12: =IF(AND(BA12=1,N(V12)>=Config!$B$15),1,0) | BX12: =IF(AU12=1,IFERROR(MATCH($A12,INDEX(Clay_Offices!$A$2:$FZ$601,0,Sync!$C$5),0),""),"") | BY12: =IF(BX12="","",IFERROR(INDEX(Clay_Offices!$A$2:$FZ$601,BX12,Sync!$C$7)&"","")) | BZ12: =IF(BY12="","",IFERROR(INDEX(Lists!$J$2:$J$15,MATCH(BY12,Lists!$I$2:$I$15,0)),"")) | CA12: =IF(BX12="","",IFERROR(INDEX(Clay_Offices!$A$2:$FZ$601,BX12,Sync!$C$17)&"","")) | CB12: =IF(BX12="","",IFERROR(N(INDEX(Clay_Offices!$A$2:$FZ$601,BX12,Sync!$C$16)),0))
AS13: =IF(TRIM($A13)="","",IF(AND(LEFT($A13,6)="SAMPLE",Config!$B$19<>"Y"),"",IF(NOT(ISNUMBER(G13)),"call_date is blank or not a date",IF(Sync!$C$5="","Clay paste is empty or has no row_id column: paste the Clay export on Clay_Offices",IF(BX13="","row_id not found in the Clay paste: add the Clay row or fix the row_id",IF(AND(ISNUMBER(BZ13),BZ13>=1,BZ13<=5),"Clay status is "&BY13&": set call_done or later",IF(AND(AW13=1,CA13<>BS13),"Clay yes_in_principle should be "&BS13,IF(AND(AW13=1,CB13<>G13),"Clay call_date should be "&TEXT(G13,"yyyy-mm-dd"),"")))))))) | AT13: =ROW() | AU13: =IF(AND(TRIM($A13)<>"",ISNUMBER(G13)),IF(AND(LEFT($A13,6)="SAMPLE",Config!$B$19<>"Y"),0,1),0) | AV13: =IF(AU13=1,IF(COUNTIFS($A$2:$A$201,$A13,$AU$2:$AU$201,1,$G$2:$G$201,"<"&G13)+COUNTIFS($A$2:$A$201,$A13,$AU$2:$AU$201,1,$G$2:$G$201,G13,$AT$2:$AT$201,"<"&AT13)=0,1,0),0) | AW13: =IF(AU13=1,IF(COUNTIFS($A$2:$A$201,$A13,$AU$2:$AU$201,1,$G$2:$G$201,">"&G13)+COUNTIFS($A$2:$A$201,$A13,$AU$2:$AU$201,1,$G$2:$G$201,G13,$AT$2:$AT$201,">"&AT13)=0,1,0),0) | AX13: =IF(AND(AU13=1,AN13="Y",Z13="Y",TRIM(AD13)<>""),1,0) | AY13: =IF(AX13=1,IF(COUNTIFS($A$2:$A$201,$A13,$AX$2:$AX$201,1,$G$2:$G$201,"<"&G13)+COUNTIFS($A$2:$A$201,$A13,$AX$2:$AX$201,1,$G$2:$G$201,G13,$AT$2:$AT$201,"<"&AT13)=0,1,0),0) | AZ13: =IF(AND(AU13=1,AN13="Y",AX13=0),1,0) | BA13: =IF(AND(AU13=1,ISNUMBER(V13)),1,0) | BB13: =IF(BA13=1,IF(COUNTIFS($A$2:$A$201,$A13,$BA$2:$BA$201,1,$G$2:$G$201,"<"&G13)+COUNTIFS($A$2:$A$201,$A13,$BA$2:$BA$201,1,$G$2:$G$201,G13,$AT$2:$AT$201,"<"&AT13)=0,1,0),0) | BC13: =IF(AND(BB13=1,G13<=Config!$B$6),V13,"") | BD13: =IF(AND(BB13=1,G13<=Config!$B$7),V13,"") | BE13: =IF(AND(BB13=1,G13<=Config!$B$8),V13,"") | BF13: =IF(AND(BB13=1,G13<=Config!$B$5),V13,"") | BG13: =IF(BW13=1,IF(COUNTIFS($A$2:$A$201,$A13,$BW$2:$BW$201,1,$G$2:$G$201,"<"&G13)+COUNTIFS($A$2:$A$201,$A13,$BW$2:$BW$201,1,$G$2:$G$201,G13,$AT$2:$AT$201,"<"&AT13)=0,1,0),0) | BH13: =IF(AND(AU13=1,ISNUMBER(K13)),1,0) | BI13: =IF(BH13=1,IF(COUNTIFS($A$2:$A$201,$A13,$BH$2:$BH$201,1,$G$2:$G$201,"<"&G13)+COUNTIFS($A$2:$A$201,$A13,$BH$2:$BH$201,1,$G$2:$G$201,G13,$AT$2:$AT$201,"<"&AT13)=0,1,0),0) | BJ13: =IF(AND(BI13=1,G13<=Config!$B$5),K13,"") | BK13: =IF(AND(AU13=1,OR(TRIM(U13)<>"",ISNUMBER(V13))),1,0) | BL13: =IF(BK13=1,IF(COUNTIFS($A$2:$A$201,$A13,$BK$2:$BK$201,1,$G$2:$G$201,"<"&G13)+COUNTIFS($A$2:$A$201,$A13,$BK$2:$BK$201,1,$G$2:$G$201,G13,$AT$2:$AT$201,"<"&AT13)=0,1,0),0) | BM13: =IF(BL13=1,$A13,"") | BN13: =IF(AND(AU13=1,T13="Y",TRIM(U13)=""),1,0) | BO13: =IF(AU13=1,AJ13&"","") | BP13: =IF(AU13=1,AK13&"","") | BQ13: =IF(AU13=1,AL13&"","") | BR13: =IF(AND(AU13=1,ISNUMBER(AP13),G13<=Config!$B$5),AP13,"") | BS13: =IF(AU13=1,IF(COUNTIFS($A$2:$A$201,$A13,$AN$2:$AN$201,"Y",$AU$2:$AU$201,1)>0,"Y","N"),"") | BT13: =IF(AND(AU13=1,AN13="maybe"),1,0) | BU13: =IF(BT13=1,IF(COUNTIFS($A$2:$A$201,$A13,$BT$2:$BT$201,1,$G$2:$G$201,"<"&G13)+COUNTIFS($A$2:$A$201,$A13,$BT$2:$BT$201,1,$G$2:$G$201,G13,$AT$2:$AT$201,"<"&AT13)=0,1,0),0) | BV13: =IF(AND(AU13=1,AN13="Y"),IF(COUNTIFS($A$2:$A$201,$A13,$AN$2:$AN$201,"Y",$AU$2:$AU$201,1,$G$2:$G$201,"<"&G13)+COUNTIFS($A$2:$A$201,$A13,$AN$2:$AN$201,"Y",$AU$2:$AU$201,1,$G$2:$G$201,G13,$AT$2:$AT$201,"<"&AT13)=0,1,0),0) | BW13: =IF(AND(BA13=1,N(V13)>=Config!$B$15),1,0) | BX13: =IF(AU13=1,IFERROR(MATCH($A13,INDEX(Clay_Offices!$A$2:$FZ$601,0,Sync!$C$5),0),""),"") | BY13: =IF(BX13="","",IFERROR(INDEX(Clay_Offices!$A$2:$FZ$601,BX13,Sync!$C$7)&"","")) | BZ13: =IF(BY13="","",IFERROR(INDEX(Lists!$J$2:$J$15,MATCH(BY13,Lists!$I$2:$I$15,0)),"")) | CA13: =IF(BX13="","",IFERROR(INDEX(Clay_Offices!$A$2:$FZ$601,BX13,Sync!$C$17)&"","")) | CB13: =IF(BX13="","",IFERROR(N(INDEX(Clay_Offices!$A$2:$FZ$601,BX13,Sync!$C$16)),0))
... AS201: =IF(TRIM($A201)="","",IF(AND(LEFT($A201,6)="SAMPLE",Config!$B$19<>"Y"),"",IF(NOT(ISNUMBER(G201)),"call_date is blank or not a date",IF(Sync!$C$5="","Clay paste is empty or has no row_id column: paste the Clay export on Clay_Offices",IF(BX201="","row_id not found in the Clay paste: add the Clay row or fix the row_id",IF(AND(ISNUMBER(BZ201),BZ201>=1,BZ201<=5),"Clay status is "&BY201&": set call_done or later",IF(AND(AW201=1,CA201<>BS201),"Clay yes_in_principle should be "&BS201,IF(AND(AW201=1,CB201<>G201),"Clay call_date should be "&TEXT(G201,"yyyy-mm-dd"),"")))))))) | AT201: =ROW() | AU201: =IF(AND(TRIM($A201)<>"",ISNUMBER(G201)),IF(AND(LEFT($A201,6)="SAMPLE",Config!$B$19<>"Y"),0,1),0) | AV201: =IF(AU201=1,IF(COUNTIFS($A$2:$A$201,$A201,$AU$2:$AU$201,1,$G$2:$G$201,"<"&G201)+COUNTIFS($A$2:$A$201,$A201,$AU$2:$AU$201,1,$G$2:$G$201,G201,$AT$2:$AT$201,"<"&AT201)=0,1,0),0) | AW201: =IF(AU201=1,IF(COUNTIFS($A$2:$A$201,$A201,$AU$2:$AU$201,1,$G$2:$G$201,">"&G201)+COUNTIFS($A$2:$A$201,$A201,$AU$2:$AU$201,1,$G$2:$G$201,G201,$AT$2:$AT$201,">"&AT201)=0,1,0),0) | AX201: =IF(AND(AU201=1,AN201="Y",Z201="Y",TRIM(AD201)<>""),1,0) | AY201: =IF(AX201=1,IF(COUNTIFS($A$2:$A$201,$A201,$AX$2:$AX$201,1,$G$2:$G$201,"<"&G201)+COUNTIFS($A$2:$A$201,$A201,$AX$2:$AX$201,1,$G$2:$G$201,G201,$AT$2:$AT$201,"<"&AT201)=0,1,0),0) | AZ201: =IF(AND(AU201=1,AN201="Y",AX201=0),1,0) | BA201: =IF(AND(AU201=1,ISNUMBER(V201)),1,0) | BB201: =IF(BA201=1,IF(COUNTIFS($A$2:$A$201,$A201,$BA$2:$BA$201,1,$G$2:$G$201,"<"&G201)+COUNTIFS($A$2:$A$201,$A201,$BA$2:$BA$201,1,$G$2:$G$201,G201,$AT$2:$AT$201,"<"&AT201)=0,1,0),0) | BC201: =IF(AND(BB201=1,G201<=Config!$B$6),V201,"") | BD201: =IF(AND(BB201=1,G201<=Config!$B$7),V201,"") | BE201: =IF(AND(BB201=1,G201<=Config!$B$8),V201,"") | BF201: =IF(AND(BB201=1,G201<=Config!$B$5),V201,"") | BG201: =IF(BW201=1,IF(COUNTIFS($A$2:$A$201,$A201,$BW$2:$BW$201,1,$G$2:$G$201,"<"&G201)+COUNTIFS($A$2:$A$201,$A201,$BW$2:$BW$201,1,$G$2:$G$201,G201,$AT$2:$AT$201,"<"&AT201)=0,1,0),0) | BH201: =IF(AND(AU201=1,ISNUMBER(K201)),1,0) | BI201: =IF(BH201=1,IF(COUNTIFS($A$2:$A$201,$A201,$BH$2:$BH$201,1,$G$2:$G$201,"<"&G201)+COUNTIFS($A$2:$A$201,$A201,$BH$2:$BH$201,1,$G$2:$G$201,G201,$AT$2:$AT$201,"<"&AT201)=0,1,0),0) | BJ201: =IF(AND(BI201=1,G201<=Config!$B$5),K201,"") | BK201: =IF(AND(AU201=1,OR(TRIM(U201)<>"",ISNUMBER(V201))),1,0) | BL201: =IF(BK201=1,IF(COUNTIFS($A$2:$A$201,$A201,$BK$2:$BK$201,1,$G$2:$G$201,"<"&G201)+COUNTIFS($A$2:$A$201,$A201,$BK$2:$BK$201,1,$G$2:$G$201,G201,$AT$2:$AT$201,"<"&AT201)=0,1,0),0) | BM201: =IF(BL201=1,$A201,"") | BN201: =IF(AND(AU201=1,T201="Y",TRIM(U201)=""),1,0) | BO201: =IF(AU201=1,AJ201&"","") | BP201: =IF(AU201=1,AK201&"","") | BQ201: =IF(AU201=1,AL201&"","") | BR201: =IF(AND(AU201=1,ISNUMBER(AP201),G201<=Config!$B$5),AP201,"") | BS201: =IF(AU201=1,IF(COUNTIFS($A$2:$A$201,$A201,$AN$2:$AN$201,"Y",$AU$2:$AU$201,1)>0,"Y","N"),"") | BT201: =IF(AND(AU201=1,AN201="maybe"),1,0) | BU201: =IF(BT201=1,IF(COUNTIFS($A$2:$A$201,$A201,$BT$2:$BT$201,1,$G$2:$G$201,"<"&G201)+COUNTIFS($A$2:$A$201,$A201,$BT$2:$BT$201,1,$G$2:$G$201,G201,$AT$2:$AT$201,"<"&AT201)=0,1,0),0) | BV201: =IF(AND(AU201=1,AN201="Y"),IF(COUNTIFS($A$2:$A$201,$A201,$AN$2:$AN$201,"Y",$AU$2:$AU$201,1,$G$2:$G$201,"<"&G201)+COUNTIFS($A$2:$A$201,$A201,$AN$2:$AN$201,"Y",$AU$2:$AU$201,1,$G$2:$G$201,G201,$AT$2:$AT$201,"<"&AT201)=0,1,0),0) | BW201: =IF(AND(BA201=1,N(V201)>=Config!$B$15),1,0) | BX201: =IF(AU201=1,IFERROR(MATCH($A201,INDEX(Clay_Offices!$A$2:$FZ$601,0,Sync!$C$5),0),""),"") | BY201: =IF(BX201="","",IFERROR(INDEX(Clay_Offices!$A$2:$FZ$601,BX201,Sync!$C$7)&"","")) | BZ201: =IF(BY201="","",IFERROR(INDEX(Lists!$J$2:$J$15,MATCH(BY201,Lists!$I$2:$I$15,0)),"")) | CA201: =IF(BX201="","",IFERROR(INDEX(Clay_Offices!$A$2:$FZ$601,BX201,Sync!$C$17)&"","")) | CB201: =IF(BX201="","",IFERROR(N(INDEX(Clay_Offices!$A$2:$FZ$601,BX201,Sync!$C$16)),0))

Sheet Brand_Log
A1: row_id | B1: company | C1: contact_name | D1: contact_title | E1: source | F1: channel | G1: call_date | H1: call_type | I1: q1_trial_now_verbatim | J1: q2_sampling_budget_quarter_low_usd | K1: q2_sampling_budget_quarter_high_usd | L1: q2_budget_verbatim | M1: budget_approver | N1: controls_budget | O1: can_approve_600_alone | P1: q3_seeded_offices | Q1: q3_verbatim | R1: wtp_before_usd | S1: wtp_before_verbatim | T1: wtp_conversion_note | U1: price_1500_mentioned | V1: wtp_after_usd | W1: wtp_after_verbatim | X1: q5_report_needs_verbatim | Y1: q6_buy_path_type | Z1: q6_buy_path_verbatim | AA1: q7_stoppers_verbatim | AB1: objection_1 | AC1: objection_2 | AD1: objection_3 | AE1: objections_verbatim | AF1: yes_in_principle | AG1: referrals_given_count | AH1: referrals_given | AI1: note_minutes | AJ1: clay_updated | AK1: notes | AL1: calc_sync_issue | AM1: calc_row | AN1: calc_valid | AO1: calc_conv_first | AP1: calc_latest | AQ1: calc_g0 | AR1: calc_g0_first | AS1: calc_g0_strict | AT1: calc_g0_strict_first | AU1: calc_g0_noctrl | AV1: calc_g0_noctrl_first | AW1: calc_wb_has | AX1: calc_wb_first | AY1: calc_wb_w1 | AZ1: calc_wb_w2 | BA1: calc_wb_g0 | BB1: calc_wb_asof | BC1: calc_wa_has | BD1: calc_wa_first | BE1: calc_wa_w1 | BF1: calc_wa_w2 | BG1: calc_wa_g0 | BH1: calc_wa_asof | BI1: calc_q2_has | BJ1: calc_q2_first | BK1: calc_q2_asof | BL1: calc_wtp_missing_text | BM1: calc_obj1 | BN1: calc_obj2 | BO1: calc_obj3 | BP1: calc_note_min | BQ1: calc_yes_any | BR1: calc_yes_any_first | BS1: calc_clay_idx | BT1: calc_clay_status | BU1: calc_clay_rank | BV1: calc_clay_yes | BW1: calc_clay_call_date
AL2: =IF(TRIM($A2)="","",IF(AND(LEFT($A2,6)="SAMPLE",Config!$B$19<>"Y"),"",IF(NOT(ISNUMBER(G2)),"call_date is blank or not a date",IF(Sync!$D$5="","Clay paste is empty or has no row_id column: paste the Clay export on Clay_Brands",IF(BS2="","row_id not found in the Clay paste: add the Clay row or fix the row_id",IF(AND(ISNUMBER(BU2),BU2>=1,BU2<=5),"Clay status is "&BT2&": set call_done or later",IF(AND(AP2=1,BV2<>BQ2),"Clay yes_in_principle should be "&BQ2,IF(AND(AP2=1,BW2<>G2),"Clay call_date should be "&TEXT(G2,"yyyy-mm-dd"),"")))))))) | AM2: =ROW() | AN2: =IF(AND(TRIM($A2)<>"",ISNUMBER(G2)),IF(AND(LEFT($A2,6)="SAMPLE",Config!$B$19<>"Y"),0,1),0) | AO2: =IF(AN2=1,IF(COUNTIFS($A$2:$A$201,$A2,$AN$2:$AN$201,1,$G$2:$G$201,"<"&G2)+COUNTIFS($A$2:$A$201,$A2,$AN$2:$AN$201,1,$G$2:$G$201,G2,$AM$2:$AM$201,"<"&AM2)=0,1,0),0) | AP2: =IF(AN2=1,IF(COUNTIFS($A$2:$A$201,$A2,$AN$2:$AN$201,1,$G$2:$G$201,">"&G2)+COUNTIFS($A$2:$A$201,$A2,$AN$2:$AN$201,1,$G$2:$G$201,G2,$AM$2:$AM$201,">"&AM2)=0,1,0),0) | AQ2: =IF(AND(AN2=1,N2="Y",MAX(N(R2),N(V2))>=Config!$B$14),1,0) | AR2: =IF(AQ2=1,IF(COUNTIFS($A$2:$A$201,$A2,$AQ$2:$AQ$201,1,$G$2:$G$201,"<"&G2)+COUNTIFS($A$2:$A$201,$A2,$AQ$2:$AQ$201,1,$G$2:$G$201,G2,$AM$2:$AM$201,"<"&AM2)=0,1,0),0) | AS2: =IF(AND(AN2=1,N2="Y",ISNUMBER(R2)),IF(R2>=Config!$B$14,1,0),0) | AT2: =IF(AS2=1,IF(COUNTIFS($A$2:$A$201,$A2,$AS$2:$AS$201,1,$G$2:$G$201,"<"&G2)+COUNTIFS($A$2:$A$201,$A2,$AS$2:$AS$201,1,$G$2:$G$201,G2,$AM$2:$AM$201,"<"&AM2)=0,1,0),0) | AU2: =IF(AND(AN2=1,N2<>"Y",MAX(N(R2),N(V2))>=Config!$B$14),1,0) | AV2: =IF(AU2=1,IF(COUNTIFS($A$2:$A$201,$A2,$AU$2:$AU$201,1,$G$2:$G$201,"<"&G2)+COUNTIFS($A$2:$A$201,$A2,$AU$2:$AU$201,1,$G$2:$G$201,G2,$AM$2:$AM$201,"<"&AM2)=0,1,0),0) | AW2: =IF(AND(AN2=1,ISNUMBER(R2)),1,0) | AX2: =IF(AW2=1,IF(COUNTIFS($A$2:$A$201,$A2,$AW$2:$AW$201,1,$G$2:$G$201,"<"&G2)+COUNTIFS($A$2:$A$201,$A2,$AW$2:$AW$201,1,$G$2:$G$201,G2,$AM$2:$AM$201,"<"&AM2)=0,1,0),0) | AY2: =IF(AND(AX2=1,G2<=Config!$B$6),R2,"") | AZ2: =IF(AND(AX2=1,G2<=Config!$B$7),R2,"") | BA2: =IF(AND(AX2=1,G2<=Config!$B$8),R2,"") | BB2: =IF(AND(AX2=1,G2<=Config!$B$5),R2,"") | BC2: =IF(AND(AN2=1,ISNUMBER(V2)),1,0) | BD2: =IF(BC2=1,IF(COUNTIFS($A$2:$A$201,$A2,$BC$2:$BC$201,1,$G$2:$G$201,"<"&G2)+COUNTIFS($A$2:$A$201,$A2,$BC$2:$BC$201,1,$G$2:$G$201,G2,$AM$2:$AM$201,"<"&AM2)=0,1,0),0) | BE2: =IF(AND(BD2=1,G2<=Config!$B$6),V2,"") | BF2: =IF(AND(BD2=1,G2<=Config!$B$7),V2,"") | BG2: =IF(AND(BD2=1,G2<=Config!$B$8),V2,"") | BH2: =IF(AND(BD2=1,G2<=Config!$B$5),V2,"") | BI2: =IF(AND(AN2=1,ISNUMBER(J2)),1,0) | BJ2: =IF(BI2=1,IF(COUNTIFS($A$2:$A$201,$A2,$BI$2:$BI$201,1,$G$2:$G$201,"<"&G2)+COUNTIFS($A$2:$A$201,$A2,$BI$2:$BI$201,1,$G$2:$G$201,G2,$AM$2:$AM$201,"<"&AM2)=0,1,0),0) | BK2: =IF(AND(BJ2=1,G2<=Config!$B$5),J2,"") | BL2: =IF(AND(AN2=1,OR(AND(ISNUMBER(R2),TRIM(S2)=""),AND(ISNUMBER(V2),TRIM(W2)=""))),1,0) | BM2: =IF(AN2=1,AB2&"","") | BN2: =IF(AN2=1,AC2&"","") | BO2: =IF(AN2=1,AD2&"","") | BP2: =IF(AND(AN2=1,ISNUMBER(AI2),G2<=Config!$B$5),AI2,"") | BQ2: =IF(AN2=1,IF(COUNTIFS($A$2:$A$201,$A2,$AF$2:$AF$201,"Y",$AN$2:$AN$201,1)>0,"Y","N"),"") | BR2: =IF(AND(AN2=1,AF2="Y"),IF(COUNTIFS($A$2:$A$201,$A2,$AF$2:$AF$201,"Y",$AN$2:$AN$201,1,$G$2:$G$201,"<"&G2)+COUNTIFS($A$2:$A$201,$A2,$AF$2:$AF$201,"Y",$AN$2:$AN$201,1,$G$2:$G$201,G2,$AM$2:$AM$201,"<"&AM2)=0,1,0),0) | BS2: =IF(AN2=1,IFERROR(MATCH($A2,INDEX(Clay_Brands!$A$2:$FZ$601,0,Sync!$D$5),0),""),"") | BT2: =IF(BS2="","",IFERROR(INDEX(Clay_Brands!$A$2:$FZ$601,BS2,Sync!$D$7)&"","")) | BU2: =IF(BT2="","",IFERROR(INDEX(Lists!$J$2:$J$15,MATCH(BT2,Lists!$I$2:$I$15,0)),"")) | BV2: =IF(BS2="","",IFERROR(INDEX(Clay_Brands!$A$2:$FZ$601,BS2,Sync!$D$17)&"","")) | BW2: =IF(BS2="","",IFERROR(N(INDEX(Clay_Brands!$A$2:$FZ$601,BS2,Sync!$D$16)),0))
AL3: =IF(TRIM($A3)="","",IF(AND(LEFT($A3,6)="SAMPLE",Config!$B$19<>"Y"),"",IF(NOT(ISNUMBER(G3)),"call_date is blank or not a date",IF(Sync!$D$5="","Clay paste is empty or has no row_id column: paste the Clay export on Clay_Brands",IF(BS3="","row_id not found in the Clay paste: add the Clay row or fix the row_id",IF(AND(ISNUMBER(BU3),BU3>=1,BU3<=5),"Clay status is "&BT3&": set call_done or later",IF(AND(AP3=1,BV3<>BQ3),"Clay yes_in_principle should be "&BQ3,IF(AND(AP3=1,BW3<>G3),"Clay call_date should be "&TEXT(G3,"yyyy-mm-dd"),"")))))))) | AM3: =ROW() | AN3: =IF(AND(TRIM($A3)<>"",ISNUMBER(G3)),IF(AND(LEFT($A3,6)="SAMPLE",Config!$B$19<>"Y"),0,1),0) | AO3: =IF(AN3=1,IF(COUNTIFS($A$2:$A$201,$A3,$AN$2:$AN$201,1,$G$2:$G$201,"<"&G3)+COUNTIFS($A$2:$A$201,$A3,$AN$2:$AN$201,1,$G$2:$G$201,G3,$AM$2:$AM$201,"<"&AM3)=0,1,0),0) | AP3: =IF(AN3=1,IF(COUNTIFS($A$2:$A$201,$A3,$AN$2:$AN$201,1,$G$2:$G$201,">"&G3)+COUNTIFS($A$2:$A$201,$A3,$AN$2:$AN$201,1,$G$2:$G$201,G3,$AM$2:$AM$201,">"&AM3)=0,1,0),0) | AQ3: =IF(AND(AN3=1,N3="Y",MAX(N(R3),N(V3))>=Config!$B$14),1,0) | AR3: =IF(AQ3=1,IF(COUNTIFS($A$2:$A$201,$A3,$AQ$2:$AQ$201,1,$G$2:$G$201,"<"&G3)+COUNTIFS($A$2:$A$201,$A3,$AQ$2:$AQ$201,1,$G$2:$G$201,G3,$AM$2:$AM$201,"<"&AM3)=0,1,0),0) | AS3: =IF(AND(AN3=1,N3="Y",ISNUMBER(R3)),IF(R3>=Config!$B$14,1,0),0) | AT3: =IF(AS3=1,IF(COUNTIFS($A$2:$A$201,$A3,$AS$2:$AS$201,1,$G$2:$G$201,"<"&G3)+COUNTIFS($A$2:$A$201,$A3,$AS$2:$AS$201,1,$G$2:$G$201,G3,$AM$2:$AM$201,"<"&AM3)=0,1,0),0) | AU3: =IF(AND(AN3=1,N3<>"Y",MAX(N(R3),N(V3))>=Config!$B$14),1,0) | AV3: =IF(AU3=1,IF(COUNTIFS($A$2:$A$201,$A3,$AU$2:$AU$201,1,$G$2:$G$201,"<"&G3)+COUNTIFS($A$2:$A$201,$A3,$AU$2:$AU$201,1,$G$2:$G$201,G3,$AM$2:$AM$201,"<"&AM3)=0,1,0),0) | AW3: =IF(AND(AN3=1,ISNUMBER(R3)),1,0) | AX3: =IF(AW3=1,IF(COUNTIFS($A$2:$A$201,$A3,$AW$2:$AW$201,1,$G$2:$G$201,"<"&G3)+COUNTIFS($A$2:$A$201,$A3,$AW$2:$AW$201,1,$G$2:$G$201,G3,$AM$2:$AM$201,"<"&AM3)=0,1,0),0) | AY3: =IF(AND(AX3=1,G3<=Config!$B$6),R3,"") | AZ3: =IF(AND(AX3=1,G3<=Config!$B$7),R3,"") | BA3: =IF(AND(AX3=1,G3<=Config!$B$8),R3,"") | BB3: =IF(AND(AX3=1,G3<=Config!$B$5),R3,"") | BC3: =IF(AND(AN3=1,ISNUMBER(V3)),1,0) | BD3: =IF(BC3=1,IF(COUNTIFS($A$2:$A$201,$A3,$BC$2:$BC$201,1,$G$2:$G$201,"<"&G3)+COUNTIFS($A$2:$A$201,$A3,$BC$2:$BC$201,1,$G$2:$G$201,G3,$AM$2:$AM$201,"<"&AM3)=0,1,0),0) | BE3: =IF(AND(BD3=1,G3<=Config!$B$6),V3,"") | BF3: =IF(AND(BD3=1,G3<=Config!$B$7),V3,"") | BG3: =IF(AND(BD3=1,G3<=Config!$B$8),V3,"") | BH3: =IF(AND(BD3=1,G3<=Config!$B$5),V3,"") | BI3: =IF(AND(AN3=1,ISNUMBER(J3)),1,0) | BJ3: =IF(BI3=1,IF(COUNTIFS($A$2:$A$201,$A3,$BI$2:$BI$201,1,$G$2:$G$201,"<"&G3)+COUNTIFS($A$2:$A$201,$A3,$BI$2:$BI$201,1,$G$2:$G$201,G3,$AM$2:$AM$201,"<"&AM3)=0,1,0),0) | BK3: =IF(AND(BJ3=1,G3<=Config!$B$5),J3,"") | BL3: =IF(AND(AN3=1,OR(AND(ISNUMBER(R3),TRIM(S3)=""),AND(ISNUMBER(V3),TRIM(W3)=""))),1,0) | BM3: =IF(AN3=1,AB3&"","") | BN3: =IF(AN3=1,AC3&"","") | BO3: =IF(AN3=1,AD3&"","") | BP3: =IF(AND(AN3=1,ISNUMBER(AI3),G3<=Config!$B$5),AI3,"") | BQ3: =IF(AN3=1,IF(COUNTIFS($A$2:$A$201,$A3,$AF$2:$AF$201,"Y",$AN$2:$AN$201,1)>0,"Y","N"),"") | BR3: =IF(AND(AN3=1,AF3="Y"),IF(COUNTIFS($A$2:$A$201,$A3,$AF$2:$AF$201,"Y",$AN$2:$AN$201,1,$G$2:$G$201,"<"&G3)+COUNTIFS($A$2:$A$201,$A3,$AF$2:$AF$201,"Y",$AN$2:$AN$201,1,$G$2:$G$201,G3,$AM$2:$AM$201,"<"&AM3)=0,1,0),0) | BS3: =IF(AN3=1,IFERROR(MATCH($A3,INDEX(Clay_Brands!$A$2:$FZ$601,0,Sync!$D$5),0),""),"") | BT3: =IF(BS3="","",IFERROR(INDEX(Clay_Brands!$A$2:$FZ$601,BS3,Sync!$D$7)&"","")) | BU3: =IF(BT3="","",IFERROR(INDEX(Lists!$J$2:$J$15,MATCH(BT3,Lists!$I$2:$I$15,0)),"")) | BV3: =IF(BS3="","",IFERROR(INDEX(Clay_Brands!$A$2:$FZ$601,BS3,Sync!$D$17)&"","")) | BW3: =IF(BS3="","",IFERROR(N(INDEX(Clay_Brands!$A$2:$FZ$601,BS3,Sync!$D$16)),0))
AL4: =IF(TRIM($A4)="","",IF(AND(LEFT($A4,6)="SAMPLE",Config!$B$19<>"Y"),"",IF(NOT(ISNUMBER(G4)),"call_date is blank or not a date",IF(Sync!$D$5="","Clay paste is empty or has no row_id column: paste the Clay export on Clay_Brands",IF(BS4="","row_id not found in the Clay paste: add the Clay row or fix the row_id",IF(AND(ISNUMBER(BU4),BU4>=1,BU4<=5),"Clay status is "&BT4&": set call_done or later",IF(AND(AP4=1,BV4<>BQ4),"Clay yes_in_principle should be "&BQ4,IF(AND(AP4=1,BW4<>G4),"Clay call_date should be "&TEXT(G4,"yyyy-mm-dd"),"")))))))) | AM4: =ROW() | AN4: =IF(AND(TRIM($A4)<>"",ISNUMBER(G4)),IF(AND(LEFT($A4,6)="SAMPLE",Config!$B$19<>"Y"),0,1),0) | AO4: =IF(AN4=1,IF(COUNTIFS($A$2:$A$201,$A4,$AN$2:$AN$201,1,$G$2:$G$201,"<"&G4)+COUNTIFS($A$2:$A$201,$A4,$AN$2:$AN$201,1,$G$2:$G$201,G4,$AM$2:$AM$201,"<"&AM4)=0,1,0),0) | AP4: =IF(AN4=1,IF(COUNTIFS($A$2:$A$201,$A4,$AN$2:$AN$201,1,$G$2:$G$201,">"&G4)+COUNTIFS($A$2:$A$201,$A4,$AN$2:$AN$201,1,$G$2:$G$201,G4,$AM$2:$AM$201,">"&AM4)=0,1,0),0) | AQ4: =IF(AND(AN4=1,N4="Y",MAX(N(R4),N(V4))>=Config!$B$14),1,0) | AR4: =IF(AQ4=1,IF(COUNTIFS($A$2:$A$201,$A4,$AQ$2:$AQ$201,1,$G$2:$G$201,"<"&G4)+COUNTIFS($A$2:$A$201,$A4,$AQ$2:$AQ$201,1,$G$2:$G$201,G4,$AM$2:$AM$201,"<"&AM4)=0,1,0),0) | AS4: =IF(AND(AN4=1,N4="Y",ISNUMBER(R4)),IF(R4>=Config!$B$14,1,0),0) | AT4: =IF(AS4=1,IF(COUNTIFS($A$2:$A$201,$A4,$AS$2:$AS$201,1,$G$2:$G$201,"<"&G4)+COUNTIFS($A$2:$A$201,$A4,$AS$2:$AS$201,1,$G$2:$G$201,G4,$AM$2:$AM$201,"<"&AM4)=0,1,0),0) | AU4: =IF(AND(AN4=1,N4<>"Y",MAX(N(R4),N(V4))>=Config!$B$14),1,0) | AV4: =IF(AU4=1,IF(COUNTIFS($A$2:$A$201,$A4,$AU$2:$AU$201,1,$G$2:$G$201,"<"&G4)+COUNTIFS($A$2:$A$201,$A4,$AU$2:$AU$201,1,$G$2:$G$201,G4,$AM$2:$AM$201,"<"&AM4)=0,1,0),0) | AW4: =IF(AND(AN4=1,ISNUMBER(R4)),1,0) | AX4: =IF(AW4=1,IF(COUNTIFS($A$2:$A$201,$A4,$AW$2:$AW$201,1,$G$2:$G$201,"<"&G4)+COUNTIFS($A$2:$A$201,$A4,$AW$2:$AW$201,1,$G$2:$G$201,G4,$AM$2:$AM$201,"<"&AM4)=0,1,0),0) | AY4: =IF(AND(AX4=1,G4<=Config!$B$6),R4,"") | AZ4: =IF(AND(AX4=1,G4<=Config!$B$7),R4,"") | BA4: =IF(AND(AX4=1,G4<=Config!$B$8),R4,"") | BB4: =IF(AND(AX4=1,G4<=Config!$B$5),R4,"") | BC4: =IF(AND(AN4=1,ISNUMBER(V4)),1,0) | BD4: =IF(BC4=1,IF(COUNTIFS($A$2:$A$201,$A4,$BC$2:$BC$201,1,$G$2:$G$201,"<"&G4)+COUNTIFS($A$2:$A$201,$A4,$BC$2:$BC$201,1,$G$2:$G$201,G4,$AM$2:$AM$201,"<"&AM4)=0,1,0),0) | BE4: =IF(AND(BD4=1,G4<=Config!$B$6),V4,"") | BF4: =IF(AND(BD4=1,G4<=Config!$B$7),V4,"") | BG4: =IF(AND(BD4=1,G4<=Config!$B$8),V4,"") | BH4: =IF(AND(BD4=1,G4<=Config!$B$5),V4,"") | BI4: =IF(AND(AN4=1,ISNUMBER(J4)),1,0) | BJ4: =IF(BI4=1,IF(COUNTIFS($A$2:$A$201,$A4,$BI$2:$BI$201,1,$G$2:$G$201,"<"&G4)+COUNTIFS($A$2:$A$201,$A4,$BI$2:$BI$201,1,$G$2:$G$201,G4,$AM$2:$AM$201,"<"&AM4)=0,1,0),0) | BK4: =IF(AND(BJ4=1,G4<=Config!$B$5),J4,"") | BL4: =IF(AND(AN4=1,OR(AND(ISNUMBER(R4),TRIM(S4)=""),AND(ISNUMBER(V4),TRIM(W4)=""))),1,0) | BM4: =IF(AN4=1,AB4&"","") | BN4: =IF(AN4=1,AC4&"","") | BO4: =IF(AN4=1,AD4&"","") | BP4: =IF(AND(AN4=1,ISNUMBER(AI4),G4<=Config!$B$5),AI4,"") | BQ4: =IF(AN4=1,IF(COUNTIFS($A$2:$A$201,$A4,$AF$2:$AF$201,"Y",$AN$2:$AN$201,1)>0,"Y","N"),"") | BR4: =IF(AND(AN4=1,AF4="Y"),IF(COUNTIFS($A$2:$A$201,$A4,$AF$2:$AF$201,"Y",$AN$2:$AN$201,1,$G$2:$G$201,"<"&G4)+COUNTIFS($A$2:$A$201,$A4,$AF$2:$AF$201,"Y",$AN$2:$AN$201,1,$G$2:$G$201,G4,$AM$2:$AM$201,"<"&AM4)=0,1,0),0) | BS4: =IF(AN4=1,IFERROR(MATCH($A4,INDEX(Clay_Brands!$A$2:$FZ$601,0,Sync!$D$5),0),""),"") | BT4: =IF(BS4="","",IFERROR(INDEX(Clay_Brands!$A$2:$FZ$601,BS4,Sync!$D$7)&"","")) | BU4: =IF(BT4="","",IFERROR(INDEX(Lists!$J$2:$J$15,MATCH(BT4,Lists!$I$2:$I$15,0)),"")) | BV4: =IF(BS4="","",IFERROR(INDEX(Clay_Brands!$A$2:$FZ$601,BS4,Sync!$D$17)&"","")) | BW4: =IF(BS4="","",IFERROR(N(INDEX(Clay_Brands!$A$2:$FZ$601,BS4,Sync!$D$16)),0))
AL5: =IF(TRIM($A5)="","",IF(AND(LEFT($A5,6)="SAMPLE",Config!$B$19<>"Y"),"",IF(NOT(ISNUMBER(G5)),"call_date is blank or not a date",IF(Sync!$D$5="","Clay paste is empty or has no row_id column: paste the Clay export on Clay_Brands",IF(BS5="","row_id not found in the Clay paste: add the Clay row or fix the row_id",IF(AND(ISNUMBER(BU5),BU5>=1,BU5<=5),"Clay status is "&BT5&": set call_done or later",IF(AND(AP5=1,BV5<>BQ5),"Clay yes_in_principle should be "&BQ5,IF(AND(AP5=1,BW5<>G5),"Clay call_date should be "&TEXT(G5,"yyyy-mm-dd"),"")))))))) | AM5: =ROW() | AN5: =IF(AND(TRIM($A5)<>"",ISNUMBER(G5)),IF(AND(LEFT($A5,6)="SAMPLE",Config!$B$19<>"Y"),0,1),0) | AO5: =IF(AN5=1,IF(COUNTIFS($A$2:$A$201,$A5,$AN$2:$AN$201,1,$G$2:$G$201,"<"&G5)+COUNTIFS($A$2:$A$201,$A5,$AN$2:$AN$201,1,$G$2:$G$201,G5,$AM$2:$AM$201,"<"&AM5)=0,1,0),0) | AP5: =IF(AN5=1,IF(COUNTIFS($A$2:$A$201,$A5,$AN$2:$AN$201,1,$G$2:$G$201,">"&G5)+COUNTIFS($A$2:$A$201,$A5,$AN$2:$AN$201,1,$G$2:$G$201,G5,$AM$2:$AM$201,">"&AM5)=0,1,0),0) | AQ5: =IF(AND(AN5=1,N5="Y",MAX(N(R5),N(V5))>=Config!$B$14),1,0) | AR5: =IF(AQ5=1,IF(COUNTIFS($A$2:$A$201,$A5,$AQ$2:$AQ$201,1,$G$2:$G$201,"<"&G5)+COUNTIFS($A$2:$A$201,$A5,$AQ$2:$AQ$201,1,$G$2:$G$201,G5,$AM$2:$AM$201,"<"&AM5)=0,1,0),0) | AS5: =IF(AND(AN5=1,N5="Y",ISNUMBER(R5)),IF(R5>=Config!$B$14,1,0),0) | AT5: =IF(AS5=1,IF(COUNTIFS($A$2:$A$201,$A5,$AS$2:$AS$201,1,$G$2:$G$201,"<"&G5)+COUNTIFS($A$2:$A$201,$A5,$AS$2:$AS$201,1,$G$2:$G$201,G5,$AM$2:$AM$201,"<"&AM5)=0,1,0),0) | AU5: =IF(AND(AN5=1,N5<>"Y",MAX(N(R5),N(V5))>=Config!$B$14),1,0) | AV5: =IF(AU5=1,IF(COUNTIFS($A$2:$A$201,$A5,$AU$2:$AU$201,1,$G$2:$G$201,"<"&G5)+COUNTIFS($A$2:$A$201,$A5,$AU$2:$AU$201,1,$G$2:$G$201,G5,$AM$2:$AM$201,"<"&AM5)=0,1,0),0) | AW5: =IF(AND(AN5=1,ISNUMBER(R5)),1,0) | AX5: =IF(AW5=1,IF(COUNTIFS($A$2:$A$201,$A5,$AW$2:$AW$201,1,$G$2:$G$201,"<"&G5)+COUNTIFS($A$2:$A$201,$A5,$AW$2:$AW$201,1,$G$2:$G$201,G5,$AM$2:$AM$201,"<"&AM5)=0,1,0),0) | AY5: =IF(AND(AX5=1,G5<=Config!$B$6),R5,"") | AZ5: =IF(AND(AX5=1,G5<=Config!$B$7),R5,"") | BA5: =IF(AND(AX5=1,G5<=Config!$B$8),R5,"") | BB5: =IF(AND(AX5=1,G5<=Config!$B$5),R5,"") | BC5: =IF(AND(AN5=1,ISNUMBER(V5)),1,0) | BD5: =IF(BC5=1,IF(COUNTIFS($A$2:$A$201,$A5,$BC$2:$BC$201,1,$G$2:$G$201,"<"&G5)+COUNTIFS($A$2:$A$201,$A5,$BC$2:$BC$201,1,$G$2:$G$201,G5,$AM$2:$AM$201,"<"&AM5)=0,1,0),0) | BE5: =IF(AND(BD5=1,G5<=Config!$B$6),V5,"") | BF5: =IF(AND(BD5=1,G5<=Config!$B$7),V5,"") | BG5: =IF(AND(BD5=1,G5<=Config!$B$8),V5,"") | BH5: =IF(AND(BD5=1,G5<=Config!$B$5),V5,"") | BI5: =IF(AND(AN5=1,ISNUMBER(J5)),1,0) | BJ5: =IF(BI5=1,IF(COUNTIFS($A$2:$A$201,$A5,$BI$2:$BI$201,1,$G$2:$G$201,"<"&G5)+COUNTIFS($A$2:$A$201,$A5,$BI$2:$BI$201,1,$G$2:$G$201,G5,$AM$2:$AM$201,"<"&AM5)=0,1,0),0) | BK5: =IF(AND(BJ5=1,G5<=Config!$B$5),J5,"") | BL5: =IF(AND(AN5=1,OR(AND(ISNUMBER(R5),TRIM(S5)=""),AND(ISNUMBER(V5),TRIM(W5)=""))),1,0) | BM5: =IF(AN5=1,AB5&"","") | BN5: =IF(AN5=1,AC5&"","") | BO5: =IF(AN5=1,AD5&"","") | BP5: =IF(AND(AN5=1,ISNUMBER(AI5),G5<=Config!$B$5),AI5,"") | BQ5: =IF(AN5=1,IF(COUNTIFS($A$2:$A$201,$A5,$AF$2:$AF$201,"Y",$AN$2:$AN$201,1)>0,"Y","N"),"") | BR5: =IF(AND(AN5=1,AF5="Y"),IF(COUNTIFS($A$2:$A$201,$A5,$AF$2:$AF$201,"Y",$AN$2:$AN$201,1,$G$2:$G$201,"<"&G5)+COUNTIFS($A$2:$A$201,$A5,$AF$2:$AF$201,"Y",$AN$2:$AN$201,1,$G$2:$G$201,G5,$AM$2:$AM$201,"<"&AM5)=0,1,0),0) | BS5: =IF(AN5=1,IFERROR(MATCH($A5,INDEX(Clay_Brands!$A$2:$FZ$601,0,Sync!$D$5),0),""),"") | BT5: =IF(BS5="","",IFERROR(INDEX(Clay_Brands!$A$2:$FZ$601,BS5,Sync!$D$7)&"","")) | BU5: =IF(BT5="","",IFERROR(INDEX(Lists!$J$2:$J$15,MATCH(BT5,Lists!$I$2:$I$15,0)),"")) | BV5: =IF(BS5="","",IFERROR(INDEX(Clay_Brands!$A$2:$FZ$601,BS5,Sync!$D$17)&"","")) | BW5: =IF(BS5="","",IFERROR(N(INDEX(Clay_Brands!$A$2:$FZ$601,BS5,Sync!$D$16)),0))
AL6: =IF(TRIM($A6)="","",IF(AND(LEFT($A6,6)="SAMPLE",Config!$B$19<>"Y"),"",IF(NOT(ISNUMBER(G6)),"call_date is blank or not a date",IF(Sync!$D$5="","Clay paste is empty or has no row_id column: paste the Clay export on Clay_Brands",IF(BS6="","row_id not found in the Clay paste: add the Clay row or fix the row_id",IF(AND(ISNUMBER(BU6),BU6>=1,BU6<=5),"Clay status is "&BT6&": set call_done or later",IF(AND(AP6=1,BV6<>BQ6),"Clay yes_in_principle should be "&BQ6,IF(AND(AP6=1,BW6<>G6),"Clay call_date should be "&TEXT(G6,"yyyy-mm-dd"),"")))))))) | AM6: =ROW() | AN6: =IF(AND(TRIM($A6)<>"",ISNUMBER(G6)),IF(AND(LEFT($A6,6)="SAMPLE",Config!$B$19<>"Y"),0,1),0) | AO6: =IF(AN6=1,IF(COUNTIFS($A$2:$A$201,$A6,$AN$2:$AN$201,1,$G$2:$G$201,"<"&G6)+COUNTIFS($A$2:$A$201,$A6,$AN$2:$AN$201,1,$G$2:$G$201,G6,$AM$2:$AM$201,"<"&AM6)=0,1,0),0) | AP6: =IF(AN6=1,IF(COUNTIFS($A$2:$A$201,$A6,$AN$2:$AN$201,1,$G$2:$G$201,">"&G6)+COUNTIFS($A$2:$A$201,$A6,$AN$2:$AN$201,1,$G$2:$G$201,G6,$AM$2:$AM$201,">"&AM6)=0,1,0),0) | AQ6: =IF(AND(AN6=1,N6="Y",MAX(N(R6),N(V6))>=Config!$B$14),1,0) | AR6: =IF(AQ6=1,IF(COUNTIFS($A$2:$A$201,$A6,$AQ$2:$AQ$201,1,$G$2:$G$201,"<"&G6)+COUNTIFS($A$2:$A$201,$A6,$AQ$2:$AQ$201,1,$G$2:$G$201,G6,$AM$2:$AM$201,"<"&AM6)=0,1,0),0) | AS6: =IF(AND(AN6=1,N6="Y",ISNUMBER(R6)),IF(R6>=Config!$B$14,1,0),0) | AT6: =IF(AS6=1,IF(COUNTIFS($A$2:$A$201,$A6,$AS$2:$AS$201,1,$G$2:$G$201,"<"&G6)+COUNTIFS($A$2:$A$201,$A6,$AS$2:$AS$201,1,$G$2:$G$201,G6,$AM$2:$AM$201,"<"&AM6)=0,1,0),0) | AU6: =IF(AND(AN6=1,N6<>"Y",MAX(N(R6),N(V6))>=Config!$B$14),1,0) | AV6: =IF(AU6=1,IF(COUNTIFS($A$2:$A$201,$A6,$AU$2:$AU$201,1,$G$2:$G$201,"<"&G6)+COUNTIFS($A$2:$A$201,$A6,$AU$2:$AU$201,1,$G$2:$G$201,G6,$AM$2:$AM$201,"<"&AM6)=0,1,0),0) | AW6: =IF(AND(AN6=1,ISNUMBER(R6)),1,0) | AX6: =IF(AW6=1,IF(COUNTIFS($A$2:$A$201,$A6,$AW$2:$AW$201,1,$G$2:$G$201,"<"&G6)+COUNTIFS($A$2:$A$201,$A6,$AW$2:$AW$201,1,$G$2:$G$201,G6,$AM$2:$AM$201,"<"&AM6)=0,1,0),0) | AY6: =IF(AND(AX6=1,G6<=Config!$B$6),R6,"") | AZ6: =IF(AND(AX6=1,G6<=Config!$B$7),R6,"") | BA6: =IF(AND(AX6=1,G6<=Config!$B$8),R6,"") | BB6: =IF(AND(AX6=1,G6<=Config!$B$5),R6,"") | BC6: =IF(AND(AN6=1,ISNUMBER(V6)),1,0) | BD6: =IF(BC6=1,IF(COUNTIFS($A$2:$A$201,$A6,$BC$2:$BC$201,1,$G$2:$G$201,"<"&G6)+COUNTIFS($A$2:$A$201,$A6,$BC$2:$BC$201,1,$G$2:$G$201,G6,$AM$2:$AM$201,"<"&AM6)=0,1,0),0) | BE6: =IF(AND(BD6=1,G6<=Config!$B$6),V6,"") | BF6: =IF(AND(BD6=1,G6<=Config!$B$7),V6,"") | BG6: =IF(AND(BD6=1,G6<=Config!$B$8),V6,"") | BH6: =IF(AND(BD6=1,G6<=Config!$B$5),V6,"") | BI6: =IF(AND(AN6=1,ISNUMBER(J6)),1,0) | BJ6: =IF(BI6=1,IF(COUNTIFS($A$2:$A$201,$A6,$BI$2:$BI$201,1,$G$2:$G$201,"<"&G6)+COUNTIFS($A$2:$A$201,$A6,$BI$2:$BI$201,1,$G$2:$G$201,G6,$AM$2:$AM$201,"<"&AM6)=0,1,0),0) | BK6: =IF(AND(BJ6=1,G6<=Config!$B$5),J6,"") | BL6: =IF(AND(AN6=1,OR(AND(ISNUMBER(R6),TRIM(S6)=""),AND(ISNUMBER(V6),TRIM(W6)=""))),1,0) | BM6: =IF(AN6=1,AB6&"","") | BN6: =IF(AN6=1,AC6&"","") | BO6: =IF(AN6=1,AD6&"","") | BP6: =IF(AND(AN6=1,ISNUMBER(AI6),G6<=Config!$B$5),AI6,"") | BQ6: =IF(AN6=1,IF(COUNTIFS($A$2:$A$201,$A6,$AF$2:$AF$201,"Y",$AN$2:$AN$201,1)>0,"Y","N"),"") | BR6: =IF(AND(AN6=1,AF6="Y"),IF(COUNTIFS($A$2:$A$201,$A6,$AF$2:$AF$201,"Y",$AN$2:$AN$201,1,$G$2:$G$201,"<"&G6)+COUNTIFS($A$2:$A$201,$A6,$AF$2:$AF$201,"Y",$AN$2:$AN$201,1,$G$2:$G$201,G6,$AM$2:$AM$201,"<"&AM6)=0,1,0),0) | BS6: =IF(AN6=1,IFERROR(MATCH($A6,INDEX(Clay_Brands!$A$2:$FZ$601,0,Sync!$D$5),0),""),"") | BT6: =IF(BS6="","",IFERROR(INDEX(Clay_Brands!$A$2:$FZ$601,BS6,Sync!$D$7)&"","")) | BU6: =IF(BT6="","",IFERROR(INDEX(Lists!$J$2:$J$15,MATCH(BT6,Lists!$I$2:$I$15,0)),"")) | BV6: =IF(BS6="","",IFERROR(INDEX(Clay_Brands!$A$2:$FZ$601,BS6,Sync!$D$17)&"","")) | BW6: =IF(BS6="","",IFERROR(N(INDEX(Clay_Brands!$A$2:$FZ$601,BS6,Sync!$D$16)),0))
AL7: =IF(TRIM($A7)="","",IF(AND(LEFT($A7,6)="SAMPLE",Config!$B$19<>"Y"),"",IF(NOT(ISNUMBER(G7)),"call_date is blank or not a date",IF(Sync!$D$5="","Clay paste is empty or has no row_id column: paste the Clay export on Clay_Brands",IF(BS7="","row_id not found in the Clay paste: add the Clay row or fix the row_id",IF(AND(ISNUMBER(BU7),BU7>=1,BU7<=5),"Clay status is "&BT7&": set call_done or later",IF(AND(AP7=1,BV7<>BQ7),"Clay yes_in_principle should be "&BQ7,IF(AND(AP7=1,BW7<>G7),"Clay call_date should be "&TEXT(G7,"yyyy-mm-dd"),"")))))))) | AM7: =ROW() | AN7: =IF(AND(TRIM($A7)<>"",ISNUMBER(G7)),IF(AND(LEFT($A7,6)="SAMPLE",Config!$B$19<>"Y"),0,1),0) | AO7: =IF(AN7=1,IF(COUNTIFS($A$2:$A$201,$A7,$AN$2:$AN$201,1,$G$2:$G$201,"<"&G7)+COUNTIFS($A$2:$A$201,$A7,$AN$2:$AN$201,1,$G$2:$G$201,G7,$AM$2:$AM$201,"<"&AM7)=0,1,0),0) | AP7: =IF(AN7=1,IF(COUNTIFS($A$2:$A$201,$A7,$AN$2:$AN$201,1,$G$2:$G$201,">"&G7)+COUNTIFS($A$2:$A$201,$A7,$AN$2:$AN$201,1,$G$2:$G$201,G7,$AM$2:$AM$201,">"&AM7)=0,1,0),0) | AQ7: =IF(AND(AN7=1,N7="Y",MAX(N(R7),N(V7))>=Config!$B$14),1,0) | AR7: =IF(AQ7=1,IF(COUNTIFS($A$2:$A$201,$A7,$AQ$2:$AQ$201,1,$G$2:$G$201,"<"&G7)+COUNTIFS($A$2:$A$201,$A7,$AQ$2:$AQ$201,1,$G$2:$G$201,G7,$AM$2:$AM$201,"<"&AM7)=0,1,0),0) | AS7: =IF(AND(AN7=1,N7="Y",ISNUMBER(R7)),IF(R7>=Config!$B$14,1,0),0) | AT7: =IF(AS7=1,IF(COUNTIFS($A$2:$A$201,$A7,$AS$2:$AS$201,1,$G$2:$G$201,"<"&G7)+COUNTIFS($A$2:$A$201,$A7,$AS$2:$AS$201,1,$G$2:$G$201,G7,$AM$2:$AM$201,"<"&AM7)=0,1,0),0) | AU7: =IF(AND(AN7=1,N7<>"Y",MAX(N(R7),N(V7))>=Config!$B$14),1,0) | AV7: =IF(AU7=1,IF(COUNTIFS($A$2:$A$201,$A7,$AU$2:$AU$201,1,$G$2:$G$201,"<"&G7)+COUNTIFS($A$2:$A$201,$A7,$AU$2:$AU$201,1,$G$2:$G$201,G7,$AM$2:$AM$201,"<"&AM7)=0,1,0),0) | AW7: =IF(AND(AN7=1,ISNUMBER(R7)),1,0) | AX7: =IF(AW7=1,IF(COUNTIFS($A$2:$A$201,$A7,$AW$2:$AW$201,1,$G$2:$G$201,"<"&G7)+COUNTIFS($A$2:$A$201,$A7,$AW$2:$AW$201,1,$G$2:$G$201,G7,$AM$2:$AM$201,"<"&AM7)=0,1,0),0) | AY7: =IF(AND(AX7=1,G7<=Config!$B$6),R7,"") | AZ7: =IF(AND(AX7=1,G7<=Config!$B$7),R7,"") | BA7: =IF(AND(AX7=1,G7<=Config!$B$8),R7,"") | BB7: =IF(AND(AX7=1,G7<=Config!$B$5),R7,"") | BC7: =IF(AND(AN7=1,ISNUMBER(V7)),1,0) | BD7: =IF(BC7=1,IF(COUNTIFS($A$2:$A$201,$A7,$BC$2:$BC$201,1,$G$2:$G$201,"<"&G7)+COUNTIFS($A$2:$A$201,$A7,$BC$2:$BC$201,1,$G$2:$G$201,G7,$AM$2:$AM$201,"<"&AM7)=0,1,0),0) | BE7: =IF(AND(BD7=1,G7<=Config!$B$6),V7,"") | BF7: =IF(AND(BD7=1,G7<=Config!$B$7),V7,"") | BG7: =IF(AND(BD7=1,G7<=Config!$B$8),V7,"") | BH7: =IF(AND(BD7=1,G7<=Config!$B$5),V7,"") | BI7: =IF(AND(AN7=1,ISNUMBER(J7)),1,0) | BJ7: =IF(BI7=1,IF(COUNTIFS($A$2:$A$201,$A7,$BI$2:$BI$201,1,$G$2:$G$201,"<"&G7)+COUNTIFS($A$2:$A$201,$A7,$BI$2:$BI$201,1,$G$2:$G$201,G7,$AM$2:$AM$201,"<"&AM7)=0,1,0),0) | BK7: =IF(AND(BJ7=1,G7<=Config!$B$5),J7,"") | BL7: =IF(AND(AN7=1,OR(AND(ISNUMBER(R7),TRIM(S7)=""),AND(ISNUMBER(V7),TRIM(W7)=""))),1,0) | BM7: =IF(AN7=1,AB7&"","") | BN7: =IF(AN7=1,AC7&"","") | BO7: =IF(AN7=1,AD7&"","") | BP7: =IF(AND(AN7=1,ISNUMBER(AI7),G7<=Config!$B$5),AI7,"") | BQ7: =IF(AN7=1,IF(COUNTIFS($A$2:$A$201,$A7,$AF$2:$AF$201,"Y",$AN$2:$AN$201,1)>0,"Y","N"),"") | BR7: =IF(AND(AN7=1,AF7="Y"),IF(COUNTIFS($A$2:$A$201,$A7,$AF$2:$AF$201,"Y",$AN$2:$AN$201,1,$G$2:$G$201,"<"&G7)+COUNTIFS($A$2:$A$201,$A7,$AF$2:$AF$201,"Y",$AN$2:$AN$201,1,$G$2:$G$201,G7,$AM$2:$AM$201,"<"&AM7)=0,1,0),0) | BS7: =IF(AN7=1,IFERROR(MATCH($A7,INDEX(Clay_Brands!$A$2:$FZ$601,0,Sync!$D$5),0),""),"") | BT7: =IF(BS7="","",IFERROR(INDEX(Clay_Brands!$A$2:$FZ$601,BS7,Sync!$D$7)&"","")) | BU7: =IF(BT7="","",IFERROR(INDEX(Lists!$J$2:$J$15,MATCH(BT7,Lists!$I$2:$I$15,0)),"")) | BV7: =IF(BS7="","",IFERROR(INDEX(Clay_Brands!$A$2:$FZ$601,BS7,Sync!$D$17)&"","")) | BW7: =IF(BS7="","",IFERROR(N(INDEX(Clay_Brands!$A$2:$FZ$601,BS7,Sync!$D$16)),0))
AL8: =IF(TRIM($A8)="","",IF(AND(LEFT($A8,6)="SAMPLE",Config!$B$19<>"Y"),"",IF(NOT(ISNUMBER(G8)),"call_date is blank or not a date",IF(Sync!$D$5="","Clay paste is empty or has no row_id column: paste the Clay export on Clay_Brands",IF(BS8="","row_id not found in the Clay paste: add the Clay row or fix the row_id",IF(AND(ISNUMBER(BU8),BU8>=1,BU8<=5),"Clay status is "&BT8&": set call_done or later",IF(AND(AP8=1,BV8<>BQ8),"Clay yes_in_principle should be "&BQ8,IF(AND(AP8=1,BW8<>G8),"Clay call_date should be "&TEXT(G8,"yyyy-mm-dd"),"")))))))) | AM8: =ROW() | AN8: =IF(AND(TRIM($A8)<>"",ISNUMBER(G8)),IF(AND(LEFT($A8,6)="SAMPLE",Config!$B$19<>"Y"),0,1),0) | AO8: =IF(AN8=1,IF(COUNTIFS($A$2:$A$201,$A8,$AN$2:$AN$201,1,$G$2:$G$201,"<"&G8)+COUNTIFS($A$2:$A$201,$A8,$AN$2:$AN$201,1,$G$2:$G$201,G8,$AM$2:$AM$201,"<"&AM8)=0,1,0),0) | AP8: =IF(AN8=1,IF(COUNTIFS($A$2:$A$201,$A8,$AN$2:$AN$201,1,$G$2:$G$201,">"&G8)+COUNTIFS($A$2:$A$201,$A8,$AN$2:$AN$201,1,$G$2:$G$201,G8,$AM$2:$AM$201,">"&AM8)=0,1,0),0) | AQ8: =IF(AND(AN8=1,N8="Y",MAX(N(R8),N(V8))>=Config!$B$14),1,0) | AR8: =IF(AQ8=1,IF(COUNTIFS($A$2:$A$201,$A8,$AQ$2:$AQ$201,1,$G$2:$G$201,"<"&G8)+COUNTIFS($A$2:$A$201,$A8,$AQ$2:$AQ$201,1,$G$2:$G$201,G8,$AM$2:$AM$201,"<"&AM8)=0,1,0),0) | AS8: =IF(AND(AN8=1,N8="Y",ISNUMBER(R8)),IF(R8>=Config!$B$14,1,0),0) | AT8: =IF(AS8=1,IF(COUNTIFS($A$2:$A$201,$A8,$AS$2:$AS$201,1,$G$2:$G$201,"<"&G8)+COUNTIFS($A$2:$A$201,$A8,$AS$2:$AS$201,1,$G$2:$G$201,G8,$AM$2:$AM$201,"<"&AM8)=0,1,0),0) | AU8: =IF(AND(AN8=1,N8<>"Y",MAX(N(R8),N(V8))>=Config!$B$14),1,0) | AV8: =IF(AU8=1,IF(COUNTIFS($A$2:$A$201,$A8,$AU$2:$AU$201,1,$G$2:$G$201,"<"&G8)+COUNTIFS($A$2:$A$201,$A8,$AU$2:$AU$201,1,$G$2:$G$201,G8,$AM$2:$AM$201,"<"&AM8)=0,1,0),0) | AW8: =IF(AND(AN8=1,ISNUMBER(R8)),1,0) | AX8: =IF(AW8=1,IF(COUNTIFS($A$2:$A$201,$A8,$AW$2:$AW$201,1,$G$2:$G$201,"<"&G8)+COUNTIFS($A$2:$A$201,$A8,$AW$2:$AW$201,1,$G$2:$G$201,G8,$AM$2:$AM$201,"<"&AM8)=0,1,0),0) | AY8: =IF(AND(AX8=1,G8<=Config!$B$6),R8,"") | AZ8: =IF(AND(AX8=1,G8<=Config!$B$7),R8,"") | BA8: =IF(AND(AX8=1,G8<=Config!$B$8),R8,"") | BB8: =IF(AND(AX8=1,G8<=Config!$B$5),R8,"") | BC8: =IF(AND(AN8=1,ISNUMBER(V8)),1,0) | BD8: =IF(BC8=1,IF(COUNTIFS($A$2:$A$201,$A8,$BC$2:$BC$201,1,$G$2:$G$201,"<"&G8)+COUNTIFS($A$2:$A$201,$A8,$BC$2:$BC$201,1,$G$2:$G$201,G8,$AM$2:$AM$201,"<"&AM8)=0,1,0),0) | BE8: =IF(AND(BD8=1,G8<=Config!$B$6),V8,"") | BF8: =IF(AND(BD8=1,G8<=Config!$B$7),V8,"") | BG8: =IF(AND(BD8=1,G8<=Config!$B$8),V8,"") | BH8: =IF(AND(BD8=1,G8<=Config!$B$5),V8,"") | BI8: =IF(AND(AN8=1,ISNUMBER(J8)),1,0) | BJ8: =IF(BI8=1,IF(COUNTIFS($A$2:$A$201,$A8,$BI$2:$BI$201,1,$G$2:$G$201,"<"&G8)+COUNTIFS($A$2:$A$201,$A8,$BI$2:$BI$201,1,$G$2:$G$201,G8,$AM$2:$AM$201,"<"&AM8)=0,1,0),0) | BK8: =IF(AND(BJ8=1,G8<=Config!$B$5),J8,"") | BL8: =IF(AND(AN8=1,OR(AND(ISNUMBER(R8),TRIM(S8)=""),AND(ISNUMBER(V8),TRIM(W8)=""))),1,0) | BM8: =IF(AN8=1,AB8&"","") | BN8: =IF(AN8=1,AC8&"","") | BO8: =IF(AN8=1,AD8&"","") | BP8: =IF(AND(AN8=1,ISNUMBER(AI8),G8<=Config!$B$5),AI8,"") | BQ8: =IF(AN8=1,IF(COUNTIFS($A$2:$A$201,$A8,$AF$2:$AF$201,"Y",$AN$2:$AN$201,1)>0,"Y","N"),"") | BR8: =IF(AND(AN8=1,AF8="Y"),IF(COUNTIFS($A$2:$A$201,$A8,$AF$2:$AF$201,"Y",$AN$2:$AN$201,1,$G$2:$G$201,"<"&G8)+COUNTIFS($A$2:$A$201,$A8,$AF$2:$AF$201,"Y",$AN$2:$AN$201,1,$G$2:$G$201,G8,$AM$2:$AM$201,"<"&AM8)=0,1,0),0) | BS8: =IF(AN8=1,IFERROR(MATCH($A8,INDEX(Clay_Brands!$A$2:$FZ$601,0,Sync!$D$5),0),""),"") | BT8: =IF(BS8="","",IFERROR(INDEX(Clay_Brands!$A$2:$FZ$601,BS8,Sync!$D$7)&"","")) | BU8: =IF(BT8="","",IFERROR(INDEX(Lists!$J$2:$J$15,MATCH(BT8,Lists!$I$2:$I$15,0)),"")) | BV8: =IF(BS8="","",IFERROR(INDEX(Clay_Brands!$A$2:$FZ$601,BS8,Sync!$D$17)&"","")) | BW8: =IF(BS8="","",IFERROR(N(INDEX(Clay_Brands!$A$2:$FZ$601,BS8,Sync!$D$16)),0))
AL9: =IF(TRIM($A9)="","",IF(AND(LEFT($A9,6)="SAMPLE",Config!$B$19<>"Y"),"",IF(NOT(ISNUMBER(G9)),"call_date is blank or not a date",IF(Sync!$D$5="","Clay paste is empty or has no row_id column: paste the Clay export on Clay_Brands",IF(BS9="","row_id not found in the Clay paste: add the Clay row or fix the row_id",IF(AND(ISNUMBER(BU9),BU9>=1,BU9<=5),"Clay status is "&BT9&": set call_done or later",IF(AND(AP9=1,BV9<>BQ9),"Clay yes_in_principle should be "&BQ9,IF(AND(AP9=1,BW9<>G9),"Clay call_date should be "&TEXT(G9,"yyyy-mm-dd"),"")))))))) | AM9: =ROW() | AN9: =IF(AND(TRIM($A9)<>"",ISNUMBER(G9)),IF(AND(LEFT($A9,6)="SAMPLE",Config!$B$19<>"Y"),0,1),0) | AO9: =IF(AN9=1,IF(COUNTIFS($A$2:$A$201,$A9,$AN$2:$AN$201,1,$G$2:$G$201,"<"&G9)+COUNTIFS($A$2:$A$201,$A9,$AN$2:$AN$201,1,$G$2:$G$201,G9,$AM$2:$AM$201,"<"&AM9)=0,1,0),0) | AP9: =IF(AN9=1,IF(COUNTIFS($A$2:$A$201,$A9,$AN$2:$AN$201,1,$G$2:$G$201,">"&G9)+COUNTIFS($A$2:$A$201,$A9,$AN$2:$AN$201,1,$G$2:$G$201,G9,$AM$2:$AM$201,">"&AM9)=0,1,0),0) | AQ9: =IF(AND(AN9=1,N9="Y",MAX(N(R9),N(V9))>=Config!$B$14),1,0) | AR9: =IF(AQ9=1,IF(COUNTIFS($A$2:$A$201,$A9,$AQ$2:$AQ$201,1,$G$2:$G$201,"<"&G9)+COUNTIFS($A$2:$A$201,$A9,$AQ$2:$AQ$201,1,$G$2:$G$201,G9,$AM$2:$AM$201,"<"&AM9)=0,1,0),0) | AS9: =IF(AND(AN9=1,N9="Y",ISNUMBER(R9)),IF(R9>=Config!$B$14,1,0),0) | AT9: =IF(AS9=1,IF(COUNTIFS($A$2:$A$201,$A9,$AS$2:$AS$201,1,$G$2:$G$201,"<"&G9)+COUNTIFS($A$2:$A$201,$A9,$AS$2:$AS$201,1,$G$2:$G$201,G9,$AM$2:$AM$201,"<"&AM9)=0,1,0),0) | AU9: =IF(AND(AN9=1,N9<>"Y",MAX(N(R9),N(V9))>=Config!$B$14),1,0) | AV9: =IF(AU9=1,IF(COUNTIFS($A$2:$A$201,$A9,$AU$2:$AU$201,1,$G$2:$G$201,"<"&G9)+COUNTIFS($A$2:$A$201,$A9,$AU$2:$AU$201,1,$G$2:$G$201,G9,$AM$2:$AM$201,"<"&AM9)=0,1,0),0) | AW9: =IF(AND(AN9=1,ISNUMBER(R9)),1,0) | AX9: =IF(AW9=1,IF(COUNTIFS($A$2:$A$201,$A9,$AW$2:$AW$201,1,$G$2:$G$201,"<"&G9)+COUNTIFS($A$2:$A$201,$A9,$AW$2:$AW$201,1,$G$2:$G$201,G9,$AM$2:$AM$201,"<"&AM9)=0,1,0),0) | AY9: =IF(AND(AX9=1,G9<=Config!$B$6),R9,"") | AZ9: =IF(AND(AX9=1,G9<=Config!$B$7),R9,"") | BA9: =IF(AND(AX9=1,G9<=Config!$B$8),R9,"") | BB9: =IF(AND(AX9=1,G9<=Config!$B$5),R9,"") | BC9: =IF(AND(AN9=1,ISNUMBER(V9)),1,0) | BD9: =IF(BC9=1,IF(COUNTIFS($A$2:$A$201,$A9,$BC$2:$BC$201,1,$G$2:$G$201,"<"&G9)+COUNTIFS($A$2:$A$201,$A9,$BC$2:$BC$201,1,$G$2:$G$201,G9,$AM$2:$AM$201,"<"&AM9)=0,1,0),0) | BE9: =IF(AND(BD9=1,G9<=Config!$B$6),V9,"") | BF9: =IF(AND(BD9=1,G9<=Config!$B$7),V9,"") | BG9: =IF(AND(BD9=1,G9<=Config!$B$8),V9,"") | BH9: =IF(AND(BD9=1,G9<=Config!$B$5),V9,"") | BI9: =IF(AND(AN9=1,ISNUMBER(J9)),1,0) | BJ9: =IF(BI9=1,IF(COUNTIFS($A$2:$A$201,$A9,$BI$2:$BI$201,1,$G$2:$G$201,"<"&G9)+COUNTIFS($A$2:$A$201,$A9,$BI$2:$BI$201,1,$G$2:$G$201,G9,$AM$2:$AM$201,"<"&AM9)=0,1,0),0) | BK9: =IF(AND(BJ9=1,G9<=Config!$B$5),J9,"") | BL9: =IF(AND(AN9=1,OR(AND(ISNUMBER(R9),TRIM(S9)=""),AND(ISNUMBER(V9),TRIM(W9)=""))),1,0) | BM9: =IF(AN9=1,AB9&"","") | BN9: =IF(AN9=1,AC9&"","") | BO9: =IF(AN9=1,AD9&"","") | BP9: =IF(AND(AN9=1,ISNUMBER(AI9),G9<=Config!$B$5),AI9,"") | BQ9: =IF(AN9=1,IF(COUNTIFS($A$2:$A$201,$A9,$AF$2:$AF$201,"Y",$AN$2:$AN$201,1)>0,"Y","N"),"") | BR9: =IF(AND(AN9=1,AF9="Y"),IF(COUNTIFS($A$2:$A$201,$A9,$AF$2:$AF$201,"Y",$AN$2:$AN$201,1,$G$2:$G$201,"<"&G9)+COUNTIFS($A$2:$A$201,$A9,$AF$2:$AF$201,"Y",$AN$2:$AN$201,1,$G$2:$G$201,G9,$AM$2:$AM$201,"<"&AM9)=0,1,0),0) | BS9: =IF(AN9=1,IFERROR(MATCH($A9,INDEX(Clay_Brands!$A$2:$FZ$601,0,Sync!$D$5),0),""),"") | BT9: =IF(BS9="","",IFERROR(INDEX(Clay_Brands!$A$2:$FZ$601,BS9,Sync!$D$7)&"","")) | BU9: =IF(BT9="","",IFERROR(INDEX(Lists!$J$2:$J$15,MATCH(BT9,Lists!$I$2:$I$15,0)),"")) | BV9: =IF(BS9="","",IFERROR(INDEX(Clay_Brands!$A$2:$FZ$601,BS9,Sync!$D$17)&"","")) | BW9: =IF(BS9="","",IFERROR(N(INDEX(Clay_Brands!$A$2:$FZ$601,BS9,Sync!$D$16)),0))
AL10: =IF(TRIM($A10)="","",IF(AND(LEFT($A10,6)="SAMPLE",Config!$B$19<>"Y"),"",IF(NOT(ISNUMBER(G10)),"call_date is blank or not a date",IF(Sync!$D$5="","Clay paste is empty or has no row_id column: paste the Clay export on Clay_Brands",IF(BS10="","row_id not found in the Clay paste: add the Clay row or fix the row_id",IF(AND(ISNUMBER(BU10),BU10>=1,BU10<=5),"Clay status is "&BT10&": set call_done or later",IF(AND(AP10=1,BV10<>BQ10),"Clay yes_in_principle should be "&BQ10,IF(AND(AP10=1,BW10<>G10),"Clay call_date should be "&TEXT(G10,"yyyy-mm-dd"),"")))))))) | AM10: =ROW() | AN10: =IF(AND(TRIM($A10)<>"",ISNUMBER(G10)),IF(AND(LEFT($A10,6)="SAMPLE",Config!$B$19<>"Y"),0,1),0) | AO10: =IF(AN10=1,IF(COUNTIFS($A$2:$A$201,$A10,$AN$2:$AN$201,1,$G$2:$G$201,"<"&G10)+COUNTIFS($A$2:$A$201,$A10,$AN$2:$AN$201,1,$G$2:$G$201,G10,$AM$2:$AM$201,"<"&AM10)=0,1,0),0) | AP10: =IF(AN10=1,IF(COUNTIFS($A$2:$A$201,$A10,$AN$2:$AN$201,1,$G$2:$G$201,">"&G10)+COUNTIFS($A$2:$A$201,$A10,$AN$2:$AN$201,1,$G$2:$G$201,G10,$AM$2:$AM$201,">"&AM10)=0,1,0),0) | AQ10: =IF(AND(AN10=1,N10="Y",MAX(N(R10),N(V10))>=Config!$B$14),1,0) | AR10: =IF(AQ10=1,IF(COUNTIFS($A$2:$A$201,$A10,$AQ$2:$AQ$201,1,$G$2:$G$201,"<"&G10)+COUNTIFS($A$2:$A$201,$A10,$AQ$2:$AQ$201,1,$G$2:$G$201,G10,$AM$2:$AM$201,"<"&AM10)=0,1,0),0) | AS10: =IF(AND(AN10=1,N10="Y",ISNUMBER(R10)),IF(R10>=Config!$B$14,1,0),0) | AT10: =IF(AS10=1,IF(COUNTIFS($A$2:$A$201,$A10,$AS$2:$AS$201,1,$G$2:$G$201,"<"&G10)+COUNTIFS($A$2:$A$201,$A10,$AS$2:$AS$201,1,$G$2:$G$201,G10,$AM$2:$AM$201,"<"&AM10)=0,1,0),0) | AU10: =IF(AND(AN10=1,N10<>"Y",MAX(N(R10),N(V10))>=Config!$B$14),1,0) | AV10: =IF(AU10=1,IF(COUNTIFS($A$2:$A$201,$A10,$AU$2:$AU$201,1,$G$2:$G$201,"<"&G10)+COUNTIFS($A$2:$A$201,$A10,$AU$2:$AU$201,1,$G$2:$G$201,G10,$AM$2:$AM$201,"<"&AM10)=0,1,0),0) | AW10: =IF(AND(AN10=1,ISNUMBER(R10)),1,0) | AX10: =IF(AW10=1,IF(COUNTIFS($A$2:$A$201,$A10,$AW$2:$AW$201,1,$G$2:$G$201,"<"&G10)+COUNTIFS($A$2:$A$201,$A10,$AW$2:$AW$201,1,$G$2:$G$201,G10,$AM$2:$AM$201,"<"&AM10)=0,1,0),0) | AY10: =IF(AND(AX10=1,G10<=Config!$B$6),R10,"") | AZ10: =IF(AND(AX10=1,G10<=Config!$B$7),R10,"") | BA10: =IF(AND(AX10=1,G10<=Config!$B$8),R10,"") | BB10: =IF(AND(AX10=1,G10<=Config!$B$5),R10,"") | BC10: =IF(AND(AN10=1,ISNUMBER(V10)),1,0) | BD10: =IF(BC10=1,IF(COUNTIFS($A$2:$A$201,$A10,$BC$2:$BC$201,1,$G$2:$G$201,"<"&G10)+COUNTIFS($A$2:$A$201,$A10,$BC$2:$BC$201,1,$G$2:$G$201,G10,$AM$2:$AM$201,"<"&AM10)=0,1,0),0) | BE10: =IF(AND(BD10=1,G10<=Config!$B$6),V10,"") | BF10: =IF(AND(BD10=1,G10<=Config!$B$7),V10,"") | BG10: =IF(AND(BD10=1,G10<=Config!$B$8),V10,"") | BH10: =IF(AND(BD10=1,G10<=Config!$B$5),V10,"") | BI10: =IF(AND(AN10=1,ISNUMBER(J10)),1,0) | BJ10: =IF(BI10=1,IF(COUNTIFS($A$2:$A$201,$A10,$BI$2:$BI$201,1,$G$2:$G$201,"<"&G10)+COUNTIFS($A$2:$A$201,$A10,$BI$2:$BI$201,1,$G$2:$G$201,G10,$AM$2:$AM$201,"<"&AM10)=0,1,0),0) | BK10: =IF(AND(BJ10=1,G10<=Config!$B$5),J10,"") | BL10: =IF(AND(AN10=1,OR(AND(ISNUMBER(R10),TRIM(S10)=""),AND(ISNUMBER(V10),TRIM(W10)=""))),1,0) | BM10: =IF(AN10=1,AB10&"","") | BN10: =IF(AN10=1,AC10&"","") | BO10: =IF(AN10=1,AD10&"","") | BP10: =IF(AND(AN10=1,ISNUMBER(AI10),G10<=Config!$B$5),AI10,"") | BQ10: =IF(AN10=1,IF(COUNTIFS($A$2:$A$201,$A10,$AF$2:$AF$201,"Y",$AN$2:$AN$201,1)>0,"Y","N"),"") | BR10: =IF(AND(AN10=1,AF10="Y"),IF(COUNTIFS($A$2:$A$201,$A10,$AF$2:$AF$201,"Y",$AN$2:$AN$201,1,$G$2:$G$201,"<"&G10)+COUNTIFS($A$2:$A$201,$A10,$AF$2:$AF$201,"Y",$AN$2:$AN$201,1,$G$2:$G$201,G10,$AM$2:$AM$201,"<"&AM10)=0,1,0),0) | BS10: =IF(AN10=1,IFERROR(MATCH($A10,INDEX(Clay_Brands!$A$2:$FZ$601,0,Sync!$D$5),0),""),"") | BT10: =IF(BS10="","",IFERROR(INDEX(Clay_Brands!$A$2:$FZ$601,BS10,Sync!$D$7)&"","")) | BU10: =IF(BT10="","",IFERROR(INDEX(Lists!$J$2:$J$15,MATCH(BT10,Lists!$I$2:$I$15,0)),"")) | BV10: =IF(BS10="","",IFERROR(INDEX(Clay_Brands!$A$2:$FZ$601,BS10,Sync!$D$17)&"","")) | BW10: =IF(BS10="","",IFERROR(N(INDEX(Clay_Brands!$A$2:$FZ$601,BS10,Sync!$D$16)),0))
AL11: =IF(TRIM($A11)="","",IF(AND(LEFT($A11,6)="SAMPLE",Config!$B$19<>"Y"),"",IF(NOT(ISNUMBER(G11)),"call_date is blank or not a date",IF(Sync!$D$5="","Clay paste is empty or has no row_id column: paste the Clay export on Clay_Brands",IF(BS11="","row_id not found in the Clay paste: add the Clay row or fix the row_id",IF(AND(ISNUMBER(BU11),BU11>=1,BU11<=5),"Clay status is "&BT11&": set call_done or later",IF(AND(AP11=1,BV11<>BQ11),"Clay yes_in_principle should be "&BQ11,IF(AND(AP11=1,BW11<>G11),"Clay call_date should be "&TEXT(G11,"yyyy-mm-dd"),"")))))))) | AM11: =ROW() | AN11: =IF(AND(TRIM($A11)<>"",ISNUMBER(G11)),IF(AND(LEFT($A11,6)="SAMPLE",Config!$B$19<>"Y"),0,1),0) | AO11: =IF(AN11=1,IF(COUNTIFS($A$2:$A$201,$A11,$AN$2:$AN$201,1,$G$2:$G$201,"<"&G11)+COUNTIFS($A$2:$A$201,$A11,$AN$2:$AN$201,1,$G$2:$G$201,G11,$AM$2:$AM$201,"<"&AM11)=0,1,0),0) | AP11: =IF(AN11=1,IF(COUNTIFS($A$2:$A$201,$A11,$AN$2:$AN$201,1,$G$2:$G$201,">"&G11)+COUNTIFS($A$2:$A$201,$A11,$AN$2:$AN$201,1,$G$2:$G$201,G11,$AM$2:$AM$201,">"&AM11)=0,1,0),0) | AQ11: =IF(AND(AN11=1,N11="Y",MAX(N(R11),N(V11))>=Config!$B$14),1,0) | AR11: =IF(AQ11=1,IF(COUNTIFS($A$2:$A$201,$A11,$AQ$2:$AQ$201,1,$G$2:$G$201,"<"&G11)+COUNTIFS($A$2:$A$201,$A11,$AQ$2:$AQ$201,1,$G$2:$G$201,G11,$AM$2:$AM$201,"<"&AM11)=0,1,0),0) | AS11: =IF(AND(AN11=1,N11="Y",ISNUMBER(R11)),IF(R11>=Config!$B$14,1,0),0) | AT11: =IF(AS11=1,IF(COUNTIFS($A$2:$A$201,$A11,$AS$2:$AS$201,1,$G$2:$G$201,"<"&G11)+COUNTIFS($A$2:$A$201,$A11,$AS$2:$AS$201,1,$G$2:$G$201,G11,$AM$2:$AM$201,"<"&AM11)=0,1,0),0) | AU11: =IF(AND(AN11=1,N11<>"Y",MAX(N(R11),N(V11))>=Config!$B$14),1,0) | AV11: =IF(AU11=1,IF(COUNTIFS($A$2:$A$201,$A11,$AU$2:$AU$201,1,$G$2:$G$201,"<"&G11)+COUNTIFS($A$2:$A$201,$A11,$AU$2:$AU$201,1,$G$2:$G$201,G11,$AM$2:$AM$201,"<"&AM11)=0,1,0),0) | AW11: =IF(AND(AN11=1,ISNUMBER(R11)),1,0) | AX11: =IF(AW11=1,IF(COUNTIFS($A$2:$A$201,$A11,$AW$2:$AW$201,1,$G$2:$G$201,"<"&G11)+COUNTIFS($A$2:$A$201,$A11,$AW$2:$AW$201,1,$G$2:$G$201,G11,$AM$2:$AM$201,"<"&AM11)=0,1,0),0) | AY11: =IF(AND(AX11=1,G11<=Config!$B$6),R11,"") | AZ11: =IF(AND(AX11=1,G11<=Config!$B$7),R11,"") | BA11: =IF(AND(AX11=1,G11<=Config!$B$8),R11,"") | BB11: =IF(AND(AX11=1,G11<=Config!$B$5),R11,"") | BC11: =IF(AND(AN11=1,ISNUMBER(V11)),1,0) | BD11: =IF(BC11=1,IF(COUNTIFS($A$2:$A$201,$A11,$BC$2:$BC$201,1,$G$2:$G$201,"<"&G11)+COUNTIFS($A$2:$A$201,$A11,$BC$2:$BC$201,1,$G$2:$G$201,G11,$AM$2:$AM$201,"<"&AM11)=0,1,0),0) | BE11: =IF(AND(BD11=1,G11<=Config!$B$6),V11,"") | BF11: =IF(AND(BD11=1,G11<=Config!$B$7),V11,"") | BG11: =IF(AND(BD11=1,G11<=Config!$B$8),V11,"") | BH11: =IF(AND(BD11=1,G11<=Config!$B$5),V11,"") | BI11: =IF(AND(AN11=1,ISNUMBER(J11)),1,0) | BJ11: =IF(BI11=1,IF(COUNTIFS($A$2:$A$201,$A11,$BI$2:$BI$201,1,$G$2:$G$201,"<"&G11)+COUNTIFS($A$2:$A$201,$A11,$BI$2:$BI$201,1,$G$2:$G$201,G11,$AM$2:$AM$201,"<"&AM11)=0,1,0),0) | BK11: =IF(AND(BJ11=1,G11<=Config!$B$5),J11,"") | BL11: =IF(AND(AN11=1,OR(AND(ISNUMBER(R11),TRIM(S11)=""),AND(ISNUMBER(V11),TRIM(W11)=""))),1,0) | BM11: =IF(AN11=1,AB11&"","") | BN11: =IF(AN11=1,AC11&"","") | BO11: =IF(AN11=1,AD11&"","") | BP11: =IF(AND(AN11=1,ISNUMBER(AI11),G11<=Config!$B$5),AI11,"") | BQ11: =IF(AN11=1,IF(COUNTIFS($A$2:$A$201,$A11,$AF$2:$AF$201,"Y",$AN$2:$AN$201,1)>0,"Y","N"),"") | BR11: =IF(AND(AN11=1,AF11="Y"),IF(COUNTIFS($A$2:$A$201,$A11,$AF$2:$AF$201,"Y",$AN$2:$AN$201,1,$G$2:$G$201,"<"&G11)+COUNTIFS($A$2:$A$201,$A11,$AF$2:$AF$201,"Y",$AN$2:$AN$201,1,$G$2:$G$201,G11,$AM$2:$AM$201,"<"&AM11)=0,1,0),0) | BS11: =IF(AN11=1,IFERROR(MATCH($A11,INDEX(Clay_Brands!$A$2:$FZ$601,0,Sync!$D$5),0),""),"") | BT11: =IF(BS11="","",IFERROR(INDEX(Clay_Brands!$A$2:$FZ$601,BS11,Sync!$D$7)&"","")) | BU11: =IF(BT11="","",IFERROR(INDEX(Lists!$J$2:$J$15,MATCH(BT11,Lists!$I$2:$I$15,0)),"")) | BV11: =IF(BS11="","",IFERROR(INDEX(Clay_Brands!$A$2:$FZ$601,BS11,Sync!$D$17)&"","")) | BW11: =IF(BS11="","",IFERROR(N(INDEX(Clay_Brands!$A$2:$FZ$601,BS11,Sync!$D$16)),0))
AL12: =IF(TRIM($A12)="","",IF(AND(LEFT($A12,6)="SAMPLE",Config!$B$19<>"Y"),"",IF(NOT(ISNUMBER(G12)),"call_date is blank or not a date",IF(Sync!$D$5="","Clay paste is empty or has no row_id column: paste the Clay export on Clay_Brands",IF(BS12="","row_id not found in the Clay paste: add the Clay row or fix the row_id",IF(AND(ISNUMBER(BU12),BU12>=1,BU12<=5),"Clay status is "&BT12&": set call_done or later",IF(AND(AP12=1,BV12<>BQ12),"Clay yes_in_principle should be "&BQ12,IF(AND(AP12=1,BW12<>G12),"Clay call_date should be "&TEXT(G12,"yyyy-mm-dd"),"")))))))) | AM12: =ROW() | AN12: =IF(AND(TRIM($A12)<>"",ISNUMBER(G12)),IF(AND(LEFT($A12,6)="SAMPLE",Config!$B$19<>"Y"),0,1),0) | AO12: =IF(AN12=1,IF(COUNTIFS($A$2:$A$201,$A12,$AN$2:$AN$201,1,$G$2:$G$201,"<"&G12)+COUNTIFS($A$2:$A$201,$A12,$AN$2:$AN$201,1,$G$2:$G$201,G12,$AM$2:$AM$201,"<"&AM12)=0,1,0),0) | AP12: =IF(AN12=1,IF(COUNTIFS($A$2:$A$201,$A12,$AN$2:$AN$201,1,$G$2:$G$201,">"&G12)+COUNTIFS($A$2:$A$201,$A12,$AN$2:$AN$201,1,$G$2:$G$201,G12,$AM$2:$AM$201,">"&AM12)=0,1,0),0) | AQ12: =IF(AND(AN12=1,N12="Y",MAX(N(R12),N(V12))>=Config!$B$14),1,0) | AR12: =IF(AQ12=1,IF(COUNTIFS($A$2:$A$201,$A12,$AQ$2:$AQ$201,1,$G$2:$G$201,"<"&G12)+COUNTIFS($A$2:$A$201,$A12,$AQ$2:$AQ$201,1,$G$2:$G$201,G12,$AM$2:$AM$201,"<"&AM12)=0,1,0),0) | AS12: =IF(AND(AN12=1,N12="Y",ISNUMBER(R12)),IF(R12>=Config!$B$14,1,0),0) | AT12: =IF(AS12=1,IF(COUNTIFS($A$2:$A$201,$A12,$AS$2:$AS$201,1,$G$2:$G$201,"<"&G12)+COUNTIFS($A$2:$A$201,$A12,$AS$2:$AS$201,1,$G$2:$G$201,G12,$AM$2:$AM$201,"<"&AM12)=0,1,0),0) | AU12: =IF(AND(AN12=1,N12<>"Y",MAX(N(R12),N(V12))>=Config!$B$14),1,0) | AV12: =IF(AU12=1,IF(COUNTIFS($A$2:$A$201,$A12,$AU$2:$AU$201,1,$G$2:$G$201,"<"&G12)+COUNTIFS($A$2:$A$201,$A12,$AU$2:$AU$201,1,$G$2:$G$201,G12,$AM$2:$AM$201,"<"&AM12)=0,1,0),0) | AW12: =IF(AND(AN12=1,ISNUMBER(R12)),1,0) | AX12: =IF(AW12=1,IF(COUNTIFS($A$2:$A$201,$A12,$AW$2:$AW$201,1,$G$2:$G$201,"<"&G12)+COUNTIFS($A$2:$A$201,$A12,$AW$2:$AW$201,1,$G$2:$G$201,G12,$AM$2:$AM$201,"<"&AM12)=0,1,0),0) | AY12: =IF(AND(AX12=1,G12<=Config!$B$6),R12,"") | AZ12: =IF(AND(AX12=1,G12<=Config!$B$7),R12,"") | BA12: =IF(AND(AX12=1,G12<=Config!$B$8),R12,"") | BB12: =IF(AND(AX12=1,G12<=Config!$B$5),R12,"") | BC12: =IF(AND(AN12=1,ISNUMBER(V12)),1,0) | BD12: =IF(BC12=1,IF(COUNTIFS($A$2:$A$201,$A12,$BC$2:$BC$201,1,$G$2:$G$201,"<"&G12)+COUNTIFS($A$2:$A$201,$A12,$BC$2:$BC$201,1,$G$2:$G$201,G12,$AM$2:$AM$201,"<"&AM12)=0,1,0),0) | BE12: =IF(AND(BD12=1,G12<=Config!$B$6),V12,"") | BF12: =IF(AND(BD12=1,G12<=Config!$B$7),V12,"") | BG12: =IF(AND(BD12=1,G12<=Config!$B$8),V12,"") | BH12: =IF(AND(BD12=1,G12<=Config!$B$5),V12,"") | BI12: =IF(AND(AN12=1,ISNUMBER(J12)),1,0) | BJ12: =IF(BI12=1,IF(COUNTIFS($A$2:$A$201,$A12,$BI$2:$BI$201,1,$G$2:$G$201,"<"&G12)+COUNTIFS($A$2:$A$201,$A12,$BI$2:$BI$201,1,$G$2:$G$201,G12,$AM$2:$AM$201,"<"&AM12)=0,1,0),0) | BK12: =IF(AND(BJ12=1,G12<=Config!$B$5),J12,"") | BL12: =IF(AND(AN12=1,OR(AND(ISNUMBER(R12),TRIM(S12)=""),AND(ISNUMBER(V12),TRIM(W12)=""))),1,0) | BM12: =IF(AN12=1,AB12&"","") | BN12: =IF(AN12=1,AC12&"","") | BO12: =IF(AN12=1,AD12&"","") | BP12: =IF(AND(AN12=1,ISNUMBER(AI12),G12<=Config!$B$5),AI12,"") | BQ12: =IF(AN12=1,IF(COUNTIFS($A$2:$A$201,$A12,$AF$2:$AF$201,"Y",$AN$2:$AN$201,1)>0,"Y","N"),"") | BR12: =IF(AND(AN12=1,AF12="Y"),IF(COUNTIFS($A$2:$A$201,$A12,$AF$2:$AF$201,"Y",$AN$2:$AN$201,1,$G$2:$G$201,"<"&G12)+COUNTIFS($A$2:$A$201,$A12,$AF$2:$AF$201,"Y",$AN$2:$AN$201,1,$G$2:$G$201,G12,$AM$2:$AM$201,"<"&AM12)=0,1,0),0) | BS12: =IF(AN12=1,IFERROR(MATCH($A12,INDEX(Clay_Brands!$A$2:$FZ$601,0,Sync!$D$5),0),""),"") | BT12: =IF(BS12="","",IFERROR(INDEX(Clay_Brands!$A$2:$FZ$601,BS12,Sync!$D$7)&"","")) | BU12: =IF(BT12="","",IFERROR(INDEX(Lists!$J$2:$J$15,MATCH(BT12,Lists!$I$2:$I$15,0)),"")) | BV12: =IF(BS12="","",IFERROR(INDEX(Clay_Brands!$A$2:$FZ$601,BS12,Sync!$D$17)&"","")) | BW12: =IF(BS12="","",IFERROR(N(INDEX(Clay_Brands!$A$2:$FZ$601,BS12,Sync!$D$16)),0))
AL13: =IF(TRIM($A13)="","",IF(AND(LEFT($A13,6)="SAMPLE",Config!$B$19<>"Y"),"",IF(NOT(ISNUMBER(G13)),"call_date is blank or not a date",IF(Sync!$D$5="","Clay paste is empty or has no row_id column: paste the Clay export on Clay_Brands",IF(BS13="","row_id not found in the Clay paste: add the Clay row or fix the row_id",IF(AND(ISNUMBER(BU13),BU13>=1,BU13<=5),"Clay status is "&BT13&": set call_done or later",IF(AND(AP13=1,BV13<>BQ13),"Clay yes_in_principle should be "&BQ13,IF(AND(AP13=1,BW13<>G13),"Clay call_date should be "&TEXT(G13,"yyyy-mm-dd"),"")))))))) | AM13: =ROW() | AN13: =IF(AND(TRIM($A13)<>"",ISNUMBER(G13)),IF(AND(LEFT($A13,6)="SAMPLE",Config!$B$19<>"Y"),0,1),0) | AO13: =IF(AN13=1,IF(COUNTIFS($A$2:$A$201,$A13,$AN$2:$AN$201,1,$G$2:$G$201,"<"&G13)+COUNTIFS($A$2:$A$201,$A13,$AN$2:$AN$201,1,$G$2:$G$201,G13,$AM$2:$AM$201,"<"&AM13)=0,1,0),0) | AP13: =IF(AN13=1,IF(COUNTIFS($A$2:$A$201,$A13,$AN$2:$AN$201,1,$G$2:$G$201,">"&G13)+COUNTIFS($A$2:$A$201,$A13,$AN$2:$AN$201,1,$G$2:$G$201,G13,$AM$2:$AM$201,">"&AM13)=0,1,0),0) | AQ13: =IF(AND(AN13=1,N13="Y",MAX(N(R13),N(V13))>=Config!$B$14),1,0) | AR13: =IF(AQ13=1,IF(COUNTIFS($A$2:$A$201,$A13,$AQ$2:$AQ$201,1,$G$2:$G$201,"<"&G13)+COUNTIFS($A$2:$A$201,$A13,$AQ$2:$AQ$201,1,$G$2:$G$201,G13,$AM$2:$AM$201,"<"&AM13)=0,1,0),0) | AS13: =IF(AND(AN13=1,N13="Y",ISNUMBER(R13)),IF(R13>=Config!$B$14,1,0),0) | AT13: =IF(AS13=1,IF(COUNTIFS($A$2:$A$201,$A13,$AS$2:$AS$201,1,$G$2:$G$201,"<"&G13)+COUNTIFS($A$2:$A$201,$A13,$AS$2:$AS$201,1,$G$2:$G$201,G13,$AM$2:$AM$201,"<"&AM13)=0,1,0),0) | AU13: =IF(AND(AN13=1,N13<>"Y",MAX(N(R13),N(V13))>=Config!$B$14),1,0) | AV13: =IF(AU13=1,IF(COUNTIFS($A$2:$A$201,$A13,$AU$2:$AU$201,1,$G$2:$G$201,"<"&G13)+COUNTIFS($A$2:$A$201,$A13,$AU$2:$AU$201,1,$G$2:$G$201,G13,$AM$2:$AM$201,"<"&AM13)=0,1,0),0) | AW13: =IF(AND(AN13=1,ISNUMBER(R13)),1,0) | AX13: =IF(AW13=1,IF(COUNTIFS($A$2:$A$201,$A13,$AW$2:$AW$201,1,$G$2:$G$201,"<"&G13)+COUNTIFS($A$2:$A$201,$A13,$AW$2:$AW$201,1,$G$2:$G$201,G13,$AM$2:$AM$201,"<"&AM13)=0,1,0),0) | AY13: =IF(AND(AX13=1,G13<=Config!$B$6),R13,"") | AZ13: =IF(AND(AX13=1,G13<=Config!$B$7),R13,"") | BA13: =IF(AND(AX13=1,G13<=Config!$B$8),R13,"") | BB13: =IF(AND(AX13=1,G13<=Config!$B$5),R13,"") | BC13: =IF(AND(AN13=1,ISNUMBER(V13)),1,0) | BD13: =IF(BC13=1,IF(COUNTIFS($A$2:$A$201,$A13,$BC$2:$BC$201,1,$G$2:$G$201,"<"&G13)+COUNTIFS($A$2:$A$201,$A13,$BC$2:$BC$201,1,$G$2:$G$201,G13,$AM$2:$AM$201,"<"&AM13)=0,1,0),0) | BE13: =IF(AND(BD13=1,G13<=Config!$B$6),V13,"") | BF13: =IF(AND(BD13=1,G13<=Config!$B$7),V13,"") | BG13: =IF(AND(BD13=1,G13<=Config!$B$8),V13,"") | BH13: =IF(AND(BD13=1,G13<=Config!$B$5),V13,"") | BI13: =IF(AND(AN13=1,ISNUMBER(J13)),1,0) | BJ13: =IF(BI13=1,IF(COUNTIFS($A$2:$A$201,$A13,$BI$2:$BI$201,1,$G$2:$G$201,"<"&G13)+COUNTIFS($A$2:$A$201,$A13,$BI$2:$BI$201,1,$G$2:$G$201,G13,$AM$2:$AM$201,"<"&AM13)=0,1,0),0) | BK13: =IF(AND(BJ13=1,G13<=Config!$B$5),J13,"") | BL13: =IF(AND(AN13=1,OR(AND(ISNUMBER(R13),TRIM(S13)=""),AND(ISNUMBER(V13),TRIM(W13)=""))),1,0) | BM13: =IF(AN13=1,AB13&"","") | BN13: =IF(AN13=1,AC13&"","") | BO13: =IF(AN13=1,AD13&"","") | BP13: =IF(AND(AN13=1,ISNUMBER(AI13),G13<=Config!$B$5),AI13,"") | BQ13: =IF(AN13=1,IF(COUNTIFS($A$2:$A$201,$A13,$AF$2:$AF$201,"Y",$AN$2:$AN$201,1)>0,"Y","N"),"") | BR13: =IF(AND(AN13=1,AF13="Y"),IF(COUNTIFS($A$2:$A$201,$A13,$AF$2:$AF$201,"Y",$AN$2:$AN$201,1,$G$2:$G$201,"<"&G13)+COUNTIFS($A$2:$A$201,$A13,$AF$2:$AF$201,"Y",$AN$2:$AN$201,1,$G$2:$G$201,G13,$AM$2:$AM$201,"<"&AM13)=0,1,0),0) | BS13: =IF(AN13=1,IFERROR(MATCH($A13,INDEX(Clay_Brands!$A$2:$FZ$601,0,Sync!$D$5),0),""),"") | BT13: =IF(BS13="","",IFERROR(INDEX(Clay_Brands!$A$2:$FZ$601,BS13,Sync!$D$7)&"","")) | BU13: =IF(BT13="","",IFERROR(INDEX(Lists!$J$2:$J$15,MATCH(BT13,Lists!$I$2:$I$15,0)),"")) | BV13: =IF(BS13="","",IFERROR(INDEX(Clay_Brands!$A$2:$FZ$601,BS13,Sync!$D$17)&"","")) | BW13: =IF(BS13="","",IFERROR(N(INDEX(Clay_Brands!$A$2:$FZ$601,BS13,Sync!$D$16)),0))
... AL201: =IF(TRIM($A201)="","",IF(AND(LEFT($A201,6)="SAMPLE",Config!$B$19<>"Y"),"",IF(NOT(ISNUMBER(G201)),"call_date is blank or not a date",IF(Sync!$D$5="","Clay paste is empty or has no row_id column: paste the Clay export on Clay_Brands",IF(BS201="","row_id not found in the Clay paste: add the Clay row or fix the row_id",IF(AND(ISNUMBER(BU201),BU201>=1,BU201<=5),"Clay status is "&BT201&": set call_done or later",IF(AND(AP201=1,BV201<>BQ201),"Clay yes_in_principle should be "&BQ201,IF(AND(AP201=1,BW201<>G201),"Clay call_date should be "&TEXT(G201,"yyyy-mm-dd"),"")))))))) | AM201: =ROW() | AN201: =IF(AND(TRIM($A201)<>"",ISNUMBER(G201)),IF(AND(LEFT($A201,6)="SAMPLE",Config!$B$19<>"Y"),0,1),0) | AO201: =IF(AN201=1,IF(COUNTIFS($A$2:$A$201,$A201,$AN$2:$AN$201,1,$G$2:$G$201,"<"&G201)+COUNTIFS($A$2:$A$201,$A201,$AN$2:$AN$201,1,$G$2:$G$201,G201,$AM$2:$AM$201,"<"&AM201)=0,1,0),0) | AP201: =IF(AN201=1,IF(COUNTIFS($A$2:$A$201,$A201,$AN$2:$AN$201,1,$G$2:$G$201,">"&G201)+COUNTIFS($A$2:$A$201,$A201,$AN$2:$AN$201,1,$G$2:$G$201,G201,$AM$2:$AM$201,">"&AM201)=0,1,0),0) | AQ201: =IF(AND(AN201=1,N201="Y",MAX(N(R201),N(V201))>=Config!$B$14),1,0) | AR201: =IF(AQ201=1,IF(COUNTIFS($A$2:$A$201,$A201,$AQ$2:$AQ$201,1,$G$2:$G$201,"<"&G201)+COUNTIFS($A$2:$A$201,$A201,$AQ$2:$AQ$201,1,$G$2:$G$201,G201,$AM$2:$AM$201,"<"&AM201)=0,1,0),0) | AS201: =IF(AND(AN201=1,N201="Y",ISNUMBER(R201)),IF(R201>=Config!$B$14,1,0),0) | AT201: =IF(AS201=1,IF(COUNTIFS($A$2:$A$201,$A201,$AS$2:$AS$201,1,$G$2:$G$201,"<"&G201)+COUNTIFS($A$2:$A$201,$A201,$AS$2:$AS$201,1,$G$2:$G$201,G201,$AM$2:$AM$201,"<"&AM201)=0,1,0),0) | AU201: =IF(AND(AN201=1,N201<>"Y",MAX(N(R201),N(V201))>=Config!$B$14),1,0) | AV201: =IF(AU201=1,IF(COUNTIFS($A$2:$A$201,$A201,$AU$2:$AU$201,1,$G$2:$G$201,"<"&G201)+COUNTIFS($A$2:$A$201,$A201,$AU$2:$AU$201,1,$G$2:$G$201,G201,$AM$2:$AM$201,"<"&AM201)=0,1,0),0) | AW201: =IF(AND(AN201=1,ISNUMBER(R201)),1,0) | AX201: =IF(AW201=1,IF(COUNTIFS($A$2:$A$201,$A201,$AW$2:$AW$201,1,$G$2:$G$201,"<"&G201)+COUNTIFS($A$2:$A$201,$A201,$AW$2:$AW$201,1,$G$2:$G$201,G201,$AM$2:$AM$201,"<"&AM201)=0,1,0),0) | AY201: =IF(AND(AX201=1,G201<=Config!$B$6),R201,"") | AZ201: =IF(AND(AX201=1,G201<=Config!$B$7),R201,"") | BA201: =IF(AND(AX201=1,G201<=Config!$B$8),R201,"") | BB201: =IF(AND(AX201=1,G201<=Config!$B$5),R201,"") | BC201: =IF(AND(AN201=1,ISNUMBER(V201)),1,0) | BD201: =IF(BC201=1,IF(COUNTIFS($A$2:$A$201,$A201,$BC$2:$BC$201,1,$G$2:$G$201,"<"&G201)+COUNTIFS($A$2:$A$201,$A201,$BC$2:$BC$201,1,$G$2:$G$201,G201,$AM$2:$AM$201,"<"&AM201)=0,1,0),0) | BE201: =IF(AND(BD201=1,G201<=Config!$B$6),V201,"") | BF201: =IF(AND(BD201=1,G201<=Config!$B$7),V201,"") | BG201: =IF(AND(BD201=1,G201<=Config!$B$8),V201,"") | BH201: =IF(AND(BD201=1,G201<=Config!$B$5),V201,"") | BI201: =IF(AND(AN201=1,ISNUMBER(J201)),1,0) | BJ201: =IF(BI201=1,IF(COUNTIFS($A$2:$A$201,$A201,$BI$2:$BI$201,1,$G$2:$G$201,"<"&G201)+COUNTIFS($A$2:$A$201,$A201,$BI$2:$BI$201,1,$G$2:$G$201,G201,$AM$2:$AM$201,"<"&AM201)=0,1,0),0) | BK201: =IF(AND(BJ201=1,G201<=Config!$B$5),J201,"") | BL201: =IF(AND(AN201=1,OR(AND(ISNUMBER(R201),TRIM(S201)=""),AND(ISNUMBER(V201),TRIM(W201)=""))),1,0) | BM201: =IF(AN201=1,AB201&"","") | BN201: =IF(AN201=1,AC201&"","") | BO201: =IF(AN201=1,AD201&"","") | BP201: =IF(AND(AN201=1,ISNUMBER(AI201),G201<=Config!$B$5),AI201,"") | BQ201: =IF(AN201=1,IF(COUNTIFS($A$2:$A$201,$A201,$AF$2:$AF$201,"Y",$AN$2:$AN$201,1)>0,"Y","N"),"") | BR201: =IF(AND(AN201=1,AF201="Y"),IF(COUNTIFS($A$2:$A$201,$A201,$AF$2:$AF$201,"Y",$AN$2:$AN$201,1,$G$2:$G$201,"<"&G201)+COUNTIFS($A$2:$A$201,$A201,$AF$2:$AF$201,"Y",$AN$2:$AN$201,1,$G$2:$G$201,G201,$AM$2:$AM$201,"<"&AM201)=0,1,0),0) | BS201: =IF(AN201=1,IFERROR(MATCH($A201,INDEX(Clay_Brands!$A$2:$FZ$601,0,Sync!$D$5),0),""),"") | BT201: =IF(BS201="","",IFERROR(INDEX(Clay_Brands!$A$2:$FZ$601,BS201,Sync!$D$7)&"","")) | BU201: =IF(BT201="","",IFERROR(INDEX(Lists!$J$2:$J$15,MATCH(BT201,Lists!$I$2:$I$15,0)),"")) | BV201: =IF(BS201="","",IFERROR(INDEX(Clay_Brands!$A$2:$FZ$601,BS201,Sync!$D$17)&"","")) | BW201: =IF(BS201="","",IFERROR(N(INDEX(Clay_Brands!$A$2:$FZ$601,BS201,Sync!$D$16)),0))

Sheet signed_offices
A1: submitted_at | B1: form_version | C1: company | D1: contact_name | E1: contact_title | F1: contact_email | G1: contact_phone | H1: office_address | I1: floor_suite | J1: tuesday_headcount | K1: pantry_owner_name | L1: pantry_owner_title | M1: pantry_owner_is_contact | N1: receiving_type | O1: receiving_window | P1: coi_required | Q1: survey_channel | R1: categories_wanted | S1: vetoes | T1: notes | U1: source | V1: office_id | W1: clay_row_id | X1: agreement_signed_date | Y1: agreement_file | Z1: founding_roster_named | AA1: budget_probe_verbatim | AB1: budget_probe_date | AC1: budget_probe_monthly_usd | AD1: agreement_version | AE1: owner_can_say_yes_alone
AA2: =IF(W2="","",IFERROR(INDEX(Office_Log!$U$2:$U$201,MATCH(W2,Office_Log!$BM$2:$BM$201,0))&"","")) | AB2: =IF(W2="","",IFERROR(IF(ISNUMBER(INDEX(Office_Log!$G$2:$G$201,MATCH(W2,Office_Log!$BM$2:$BM$201,0))),INDEX(Office_Log!$G$2:$G$201,MATCH(W2,Office_Log!$BM$2:$BM$201,0)),""),"")) | AC2: =IF(W2="","",IFERROR(IF(ISNUMBER(INDEX(Office_Log!$V$2:$V$201,MATCH(W2,Office_Log!$BM$2:$BM$201,0))),INDEX(Office_Log!$V$2:$V$201,MATCH(W2,Office_Log!$BM$2:$BM$201,0)),""),""))
AA3: =IF(W3="","",IFERROR(INDEX(Office_Log!$U$2:$U$201,MATCH(W3,Office_Log!$BM$2:$BM$201,0))&"","")) | AB3: =IF(W3="","",IFERROR(IF(ISNUMBER(INDEX(Office_Log!$G$2:$G$201,MATCH(W3,Office_Log!$BM$2:$BM$201,0))),INDEX(Office_Log!$G$2:$G$201,MATCH(W3,Office_Log!$BM$2:$BM$201,0)),""),"")) | AC3: =IF(W3="","",IFERROR(IF(ISNUMBER(INDEX(Office_Log!$V$2:$V$201,MATCH(W3,Office_Log!$BM$2:$BM$201,0))),INDEX(Office_Log!$V$2:$V$201,MATCH(W3,Office_Log!$BM$2:$BM$201,0)),""),""))
AA4: =IF(W4="","",IFERROR(INDEX(Office_Log!$U$2:$U$201,MATCH(W4,Office_Log!$BM$2:$BM$201,0))&"","")) | AB4: =IF(W4="","",IFERROR(IF(ISNUMBER(INDEX(Office_Log!$G$2:$G$201,MATCH(W4,Office_Log!$BM$2:$BM$201,0))),INDEX(Office_Log!$G$2:$G$201,MATCH(W4,Office_Log!$BM$2:$BM$201,0)),""),"")) | AC4: =IF(W4="","",IFERROR(IF(ISNUMBER(INDEX(Office_Log!$V$2:$V$201,MATCH(W4,Office_Log!$BM$2:$BM$201,0))),INDEX(Office_Log!$V$2:$V$201,MATCH(W4,Office_Log!$BM$2:$BM$201,0)),""),""))
AA5: =IF(W5="","",IFERROR(INDEX(Office_Log!$U$2:$U$201,MATCH(W5,Office_Log!$BM$2:$BM$201,0))&"","")) | AB5: =IF(W5="","",IFERROR(IF(ISNUMBER(INDEX(Office_Log!$G$2:$G$201,MATCH(W5,Office_Log!$BM$2:$BM$201,0))),INDEX(Office_Log!$G$2:$G$201,MATCH(W5,Office_Log!$BM$2:$BM$201,0)),""),"")) | AC5: =IF(W5="","",IFERROR(IF(ISNUMBER(INDEX(Office_Log!$V$2:$V$201,MATCH(W5,Office_Log!$BM$2:$BM$201,0))),INDEX(Office_Log!$V$2:$V$201,MATCH(W5,Office_Log!$BM$2:$BM$201,0)),""),""))
AA6: =IF(W6="","",IFERROR(INDEX(Office_Log!$U$2:$U$201,MATCH(W6,Office_Log!$BM$2:$BM$201,0))&"","")) | AB6: =IF(W6="","",IFERROR(IF(ISNUMBER(INDEX(Office_Log!$G$2:$G$201,MATCH(W6,Office_Log!$BM$2:$BM$201,0))),INDEX(Office_Log!$G$2:$G$201,MATCH(W6,Office_Log!$BM$2:$BM$201,0)),""),"")) | AC6: =IF(W6="","",IFERROR(IF(ISNUMBER(INDEX(Office_Log!$V$2:$V$201,MATCH(W6,Office_Log!$BM$2:$BM$201,0))),INDEX(Office_Log!$V$2:$V$201,MATCH(W6,Office_Log!$BM$2:$BM$201,0)),""),""))
AA7: =IF(W7="","",IFERROR(INDEX(Office_Log!$U$2:$U$201,MATCH(W7,Office_Log!$BM$2:$BM$201,0))&"","")) | AB7: =IF(W7="","",IFERROR(IF(ISNUMBER(INDEX(Office_Log!$G$2:$G$201,MATCH(W7,Office_Log!$BM$2:$BM$201,0))),INDEX(Office_Log!$G$2:$G$201,MATCH(W7,Office_Log!$BM$2:$BM$201,0)),""),"")) | AC7: =IF(W7="","",IFERROR(IF(ISNUMBER(INDEX(Office_Log!$V$2:$V$201,MATCH(W7,Office_Log!$BM$2:$BM$201,0))),INDEX(Office_Log!$V$2:$V$201,MATCH(W7,Office_Log!$BM$2:$BM$201,0)),""),""))
AA8: =IF(W8="","",IFERROR(INDEX(Office_Log!$U$2:$U$201,MATCH(W8,Office_Log!$BM$2:$BM$201,0))&"","")) | AB8: =IF(W8="","",IFERROR(IF(ISNUMBER(INDEX(Office_Log!$G$2:$G$201,MATCH(W8,Office_Log!$BM$2:$BM$201,0))),INDEX(Office_Log!$G$2:$G$201,MATCH(W8,Office_Log!$BM$2:$BM$201,0)),""),"")) | AC8: =IF(W8="","",IFERROR(IF(ISNUMBER(INDEX(Office_Log!$V$2:$V$201,MATCH(W8,Office_Log!$BM$2:$BM$201,0))),INDEX(Office_Log!$V$2:$V$201,MATCH(W8,Office_Log!$BM$2:$BM$201,0)),""),""))
AA9: =IF(W9="","",IFERROR(INDEX(Office_Log!$U$2:$U$201,MATCH(W9,Office_Log!$BM$2:$BM$201,0))&"","")) | AB9: =IF(W9="","",IFERROR(IF(ISNUMBER(INDEX(Office_Log!$G$2:$G$201,MATCH(W9,Office_Log!$BM$2:$BM$201,0))),INDEX(Office_Log!$G$2:$G$201,MATCH(W9,Office_Log!$BM$2:$BM$201,0)),""),"")) | AC9: =IF(W9="","",IFERROR(IF(ISNUMBER(INDEX(Office_Log!$V$2:$V$201,MATCH(W9,Office_Log!$BM$2:$BM$201,0))),INDEX(Office_Log!$V$2:$V$201,MATCH(W9,Office_Log!$BM$2:$BM$201,0)),""),""))
AA10: =IF(W10="","",IFERROR(INDEX(Office_Log!$U$2:$U$201,MATCH(W10,Office_Log!$BM$2:$BM$201,0))&"","")) | AB10: =IF(W10="","",IFERROR(IF(ISNUMBER(INDEX(Office_Log!$G$2:$G$201,MATCH(W10,Office_Log!$BM$2:$BM$201,0))),INDEX(Office_Log!$G$2:$G$201,MATCH(W10,Office_Log!$BM$2:$BM$201,0)),""),"")) | AC10: =IF(W10="","",IFERROR(IF(ISNUMBER(INDEX(Office_Log!$V$2:$V$201,MATCH(W10,Office_Log!$BM$2:$BM$201,0))),INDEX(Office_Log!$V$2:$V$201,MATCH(W10,Office_Log!$BM$2:$BM$201,0)),""),""))
AA11: =IF(W11="","",IFERROR(INDEX(Office_Log!$U$2:$U$201,MATCH(W11,Office_Log!$BM$2:$BM$201,0))&"","")) | AB11: =IF(W11="","",IFERROR(IF(ISNUMBER(INDEX(Office_Log!$G$2:$G$201,MATCH(W11,Office_Log!$BM$2:$BM$201,0))),INDEX(Office_Log!$G$2:$G$201,MATCH(W11,Office_Log!$BM$2:$BM$201,0)),""),"")) | AC11: =IF(W11="","",IFERROR(IF(ISNUMBER(INDEX(Office_Log!$V$2:$V$201,MATCH(W11,Office_Log!$BM$2:$BM$201,0))),INDEX(Office_Log!$V$2:$V$201,MATCH(W11,Office_Log!$BM$2:$BM$201,0)),""),""))
AA12: =IF(W12="","",IFERROR(INDEX(Office_Log!$U$2:$U$201,MATCH(W12,Office_Log!$BM$2:$BM$201,0))&"","")) | AB12: =IF(W12="","",IFERROR(IF(ISNUMBER(INDEX(Office_Log!$G$2:$G$201,MATCH(W12,Office_Log!$BM$2:$BM$201,0))),INDEX(Office_Log!$G$2:$G$201,MATCH(W12,Office_Log!$BM$2:$BM$201,0)),""),"")) | AC12: =IF(W12="","",IFERROR(IF(ISNUMBER(INDEX(Office_Log!$V$2:$V$201,MATCH(W12,Office_Log!$BM$2:$BM$201,0))),INDEX(Office_Log!$V$2:$V$201,MATCH(W12,Office_Log!$BM$2:$BM$201,0)),""),""))
AA13: =IF(W13="","",IFERROR(INDEX(Office_Log!$U$2:$U$201,MATCH(W13,Office_Log!$BM$2:$BM$201,0))&"","")) | AB13: =IF(W13="","",IFERROR(IF(ISNUMBER(INDEX(Office_Log!$G$2:$G$201,MATCH(W13,Office_Log!$BM$2:$BM$201,0))),INDEX(Office_Log!$G$2:$G$201,MATCH(W13,Office_Log!$BM$2:$BM$201,0)),""),"")) | AC13: =IF(W13="","",IFERROR(IF(ISNUMBER(INDEX(Office_Log!$V$2:$V$201,MATCH(W13,Office_Log!$BM$2:$BM$201,0))),INDEX(Office_Log!$V$2:$V$201,MATCH(W13,Office_Log!$BM$2:$BM$201,0)),""),""))
... AA51: =IF(W51="","",IFERROR(INDEX(Office_Log!$U$2:$U$201,MATCH(W51,Office_Log!$BM$2:$BM$201,0))&"","")) | AB51: =IF(W51="","",IFERROR(IF(ISNUMBER(INDEX(Office_Log!$G$2:$G$201,MATCH(W51,Office_Log!$BM$2:$BM$201,0))),INDEX(Office_Log!$G$2:$G$201,MATCH(W51,Office_Log!$BM$2:$BM$201,0)),""),"")) | AC51: =IF(W51="","",IFERROR(IF(ISNUMBER(INDEX(Office_Log!$V$2:$V$201,MATCH(W51,Office_Log!$BM$2:$BM$201,0))),INDEX(Office_Log!$V$2:$V$201,MATCH(W51,Office_Log!$BM$2:$BM$201,0)),""),""))

Sheet paid_brands
A1: submitted_at | B1: form_version | C1: brand_name | D1: website | E1: contact_name | F1: contact_title | G1: contact_email | H1: contact_phone | I1: product_sku | J1: category | K1: hq_city | L1: nyc_retailers | M1: online_store_url | N1: can_issue_discount_code | O1: preferred_timing | P1: budget_approver_is_contact | Q1: budget_approver_name_title | R1: q1_sealed_shelf_stable_60d | S1: q2_labeled_ingredients_allergens | T1: q3_buy_path_near_cluster | U1: q4_can_ship_275_in_10bd | V1: q5_product_liability_insurance | W1: q6_contact_can_approve_600 | X1: q7_why_now | Y1: excluded_category_confirmed | Z1: notes | AA1: source | AB1: brand_id | AC1: clay_row_id | AD1: tier | AE1: price_usd | AF1: offices_count | AG1: payment_terms | AH1: agreement_signed_date | AI1: invoice_id | AJ1: invoice_date | AK1: payment_received_date | AL1: coi_received_date | AM1: allergen_sheet_received_date | AN1: logo_received_date | AO1: card_sentences | AP1: allergen_line_verbatim | AQ1: retailer_line | AR1: discount_code | AS1: landing_url | AT1: unused_product_election | AU1: office_approvals | AV1: payment_1_usd | AW1: payment_1_date | AX1: payment_2_usd | AY1: payment_2_date | AZ1: agreement_version | BA1: coi_policy_end_date | BB1: newsletter_option | BC1: brand_privacy_url | BD1: allergen_source | BE1: may_contain_verbatim | BF1: flavor_name | BG1: flavor_name_2 | BH1: allergen_source_2 | BI1: allergen_line_verbatim_2 | BJ1: may_contain_verbatim_2 | BK1: verified_q1_sealed_shelf_stable_60d | BL1: verified_q2_labeled_ingredients_allergens | BM1: verified_q3_buy_path_near_cluster | BN1: verified_q4_can_ship_275_in_10bd | BO1: verified_q5_product_liability_insurance | BP1: verified_q6_contact_can_approve_600 | BQ1: verified_q7_why_now | BR1: verified_not_excluded | BS1: verified_date | BT1: verified_notes
AK2: =IF(ISNUMBER(AW2),AW2,"")
AK3: =IF(ISNUMBER(AW3),AW3,"")
AK4: =IF(ISNUMBER(AW4),AW4,"")
AK5: =IF(ISNUMBER(AW5),AW5,"")
AK6: =IF(ISNUMBER(AW6),AW6,"")
AK7: =IF(ISNUMBER(AW7),AW7,"")
AK8: =IF(ISNUMBER(AW8),AW8,"")
AK9: =IF(ISNUMBER(AW9),AW9,"")
AK10: =IF(ISNUMBER(AW10),AW10,"")
AK11: =IF(ISNUMBER(AW11),AW11,"")
AK12: =IF(ISNUMBER(AW12),AW12,"")
AK13: =IF(ISNUMBER(AW13),AW13,"")
... AK51: =IF(ISNUMBER(AW51),AW51,"")

Sheet later_events
A1: date | B1: side | C1: clay_row_id | D1: org_name | E1: event | F1: value_number | G1: value_text | H1: notes

Sheet Clay_Offices

Sheet Clay_Brands

Sheet Sync
A1: Sync: where the tracker and the Clay tables disagree. Clay is the status store; fix there, then re-paste.
A2: Rows 5 to 18 find each Clay column by its header. A blank number means that column is missing from the paste.
B4: Clay column | C4: offices col # | D4: brands col # | E4: note
B5: row_id | C5: =IFERROR(MATCH(B5,Clay_Offices!$A$1:$FZ$1,0),"") | D5: =IFERROR(MATCH(B5,Clay_Brands!$A$1:$FZ$1,0),"") | E5: =IF(AND(C5="",D5=""),"missing in both pastes",IF(C5="","missing in Clay_Offices",IF(D5="","missing in Clay_Brands","")))
B6: company | C6: =IFERROR(MATCH(B6,Clay_Offices!$A$1:$FZ$1,0),"") | D6: =IFERROR(MATCH(B6,Clay_Brands!$A$1:$FZ$1,0),"") | E6: =IF(AND(C6="",D6=""),"missing in both pastes",IF(C6="","missing in Clay_Offices",IF(D6="","missing in Clay_Brands","")))
B7: status | C7: =IFERROR(MATCH(B7,Clay_Offices!$A$1:$FZ$1,0),"") | D7: =IFERROR(MATCH(B7,Clay_Brands!$A$1:$FZ$1,0),"") | E7: =IF(AND(C7="",D7=""),"missing in both pastes",IF(C7="","missing in Clay_Offices",IF(D7="","missing in Clay_Brands","")))
B8: do_not_contact | C8: =IFERROR(MATCH(B8,Clay_Offices!$A$1:$FZ$1,0),"") | D8: =IFERROR(MATCH(B8,Clay_Brands!$A$1:$FZ$1,0),"") | E8: =IF(AND(C8="",D8=""),"missing in both pastes",IF(C8="","missing in Clay_Offices",IF(D8="","missing in Clay_Brands","")))
B9: channel | C9: =IFERROR(MATCH(B9,Clay_Offices!$A$1:$FZ$1,0),"") | D9: =IFERROR(MATCH(B9,Clay_Brands!$A$1:$FZ$1,0),"") | E9: =IF(AND(C9="",D9=""),"missing in both pastes",IF(C9="","missing in Clay_Offices",IF(D9="","missing in Clay_Brands","")))
B10: sequence | C10: =IFERROR(MATCH(B10,Clay_Offices!$A$1:$FZ$1,0),"") | D10: =IFERROR(MATCH(B10,Clay_Brands!$A$1:$FZ$1,0),"") | E10: =IF(AND(C10="",D10=""),"missing in both pastes",IF(C10="","missing in Clay_Offices",IF(D10="","missing in Clay_Brands","")))
B11: touch_1_date | C11: =IFERROR(MATCH(B11,Clay_Offices!$A$1:$FZ$1,0),"") | D11: =IFERROR(MATCH(B11,Clay_Brands!$A$1:$FZ$1,0),"") | E11: =IF(AND(C11="",D11=""),"missing in both pastes",IF(C11="","missing in Clay_Offices",IF(D11="","missing in Clay_Brands","")))
B12: touch_2_date | C12: =IFERROR(MATCH(B12,Clay_Offices!$A$1:$FZ$1,0),"") | D12: =IFERROR(MATCH(B12,Clay_Brands!$A$1:$FZ$1,0),"") | E12: =IF(AND(C12="",D12=""),"missing in both pastes",IF(C12="","missing in Clay_Offices",IF(D12="","missing in Clay_Brands","")))
B13: touch_3_date | C13: =IFERROR(MATCH(B13,Clay_Offices!$A$1:$FZ$1,0),"") | D13: =IFERROR(MATCH(B13,Clay_Brands!$A$1:$FZ$1,0),"") | E13: =IF(AND(C13="",D13=""),"missing in both pastes",IF(C13="","missing in Clay_Offices",IF(D13="","missing in Clay_Brands","")))
B14: last_reply_date | C14: =IFERROR(MATCH(B14,Clay_Offices!$A$1:$FZ$1,0),"") | D14: =IFERROR(MATCH(B14,Clay_Brands!$A$1:$FZ$1,0),"") | E14: =IF(AND(C14="",D14=""),"missing in both pastes",IF(C14="","missing in Clay_Offices",IF(D14="","missing in Clay_Brands","")))
B15: reply_type | C15: =IFERROR(MATCH(B15,Clay_Offices!$A$1:$FZ$1,0),"") | D15: =IFERROR(MATCH(B15,Clay_Brands!$A$1:$FZ$1,0),"") | E15: =IF(AND(C15="",D15=""),"missing in both pastes",IF(C15="","missing in Clay_Offices",IF(D15="","missing in Clay_Brands","")))
B16: call_date | C16: =IFERROR(MATCH(B16,Clay_Offices!$A$1:$FZ$1,0),"") | D16: =IFERROR(MATCH(B16,Clay_Brands!$A$1:$FZ$1,0),"") | E16: =IF(AND(C16="",D16=""),"missing in both pastes",IF(C16="","missing in Clay_Offices",IF(D16="","missing in Clay_Brands","")))
... B18: opt_out_date | C18: =IFERROR(MATCH(B18,Clay_Offices!$A$1:$FZ$1,0),"") | D18: =IFERROR(MATCH(B18,Clay_Brands!$A$1:$FZ$1,0),"") | E18: =IF(AND(C18="",D18=""),"missing in both pastes",IF(C18="","missing in Clay_Offices",IF(D18="","missing in Clay_Brands","")))
A20: Clay rows that disagree with the tracker or with themselves | P20: Handoff rows whose Clay status is not signed / paid
B21: i | C21: office row_id | D21: status | E21: do_not_contact | F21: in tracker | G21: issue | I21: i | J21: brand row_id | K21: status | L21: do_not_contact | M21: in tracker | N21: issue | P21: signed_offices clay_row_id | Q21: Clay status | R21: issue | T21: paid_brands clay_row_id | U21: Clay status | V21: issue
B22: 1 | C22: =IFERROR(INDEX(Clay_Offices!$A$2:$FZ$601,B22,$C$5)&"","") | D22: =IFERROR(INDEX(Clay_Offices!$A$2:$FZ$601,B22,$C$7)&"","") | E22: =IFERROR(INDEX(Clay_Offices!$A$2:$FZ$601,B22,$C$8)&"","") | F22: =IF(C22="","",IF(COUNTIF(Office_Log!$A$2:$A$201,C22)>0,"Y","N")) | G22: =IF(OR(C22="",AND(LEFT(C22,6)="SAMPLE",Config!$B$19<>"Y")),"",IF(IFERROR(INDEX(Lists!$J$2:$J$15,MATCH(D22,Lists!$I$2:$I$15,0)),-1)=-1,"status '"&D22&"' is not a CONTRACTS status",IF(AND(D22="signed",COUNTIF(signed_offices!$W$2:$W$51,C22)=0),"status signed but no signed_offices row"&IF(F22="N"," and no tracker row",""),IF(AND(IFERROR(INDEX(Lists!$J$2:$J$15,MATCH(D22,Lists!$I$2:$I$15,0)),-1)>=6,F22="N"),"status "&D22&" but no tracker row",IF(AND(E22="Y",D22<>"do_not_contact"),"do_not_contact = Y but status is "&D22,IF(AND(D22="do_not_contact",E22<>"Y"),"status do_not_contact but do_not_contact is not Y","")))))) | I22: 1 | J22: =IFERROR(INDEX(Clay_Brands!$A$2:$FZ$601,I22,$D$5)&"","") | K22: =IFERROR(INDEX(Clay_Brands!$A$2:$FZ$601,I22,$D$7)&"","") | L22: =IFERROR(INDEX(Clay_Brands!$A$2:$FZ$601,I22,$D$8)&"","") | M22: =IF(J22="","",IF(COUNTIF(Brand_Log!$A$2:$A$201,J22)>0,"Y","N")) | N22: =IF(OR(J22="",AND(LEFT(J22,6)="SAMPLE",Config!$B$19<>"Y")),"",IF(IFERROR(INDEX(Lists!$J$2:$J$15,MATCH(K22,Lists!$I$2:$I$15,0)),-1)=-1,"status '"&K22&"' is not a CONTRACTS status",IF(AND(K22="paid",COUNTIF(paid_brands!$AC$2:$AC$51,J22)=0),"status paid but no paid_brands row"&IF(M22="N"," and no tracker row",""),IF(AND(IFERROR(INDEX(Lists!$J$2:$J$15,MATCH(K22,Lists!$I$2:$I$15,0)),-1)>=6,M22="N"),"status "&K22&" but no tracker row",IF(AND(L22="Y",K22<>"do_not_contact"),"do_not_contact = Y but status is "&K22,IF(AND(K22="do_not_contact",L22<>"Y"),"status do_not_contact but do_not_contact is not Y","")))))) | P22: =IF(signed_offices!W2="","",signed_offices!W2&"") | Q22: =IF(P22="","",IFERROR(INDEX(Clay_Offices!$A$2:$FZ$601,MATCH(P22,INDEX(Clay_Offices!$A$2:$FZ$601,0,$C$5),0),$C$7)&"","not in Clay")) | R22: =IF(OR(P22="",AND(LEFT(P22,6)="SAMPLE",Config!$B$19<>"Y")),"",IF(Q22="signed","","Clay status is "&Q22&": set signed")) | T22: =IF(paid_brands!AC2="","",paid_brands!AC2&"") | U22: =IF(T22="","",IFERROR(INDEX(Clay_Brands!$A$2:$FZ$601,MATCH(T22,INDEX(Clay_Brands!$A$2:$FZ$601,0,$D$5),0),$D$7)&"","not in Clay")) | V22: =IF(OR(T22="",AND(LEFT(T22,6)="SAMPLE",Config!$B$19<>"Y")),"",IF(U22="paid","","Clay status is "&U22&": set paid"))
B23: 2 | C23: =IFERROR(INDEX(Clay_Offices!$A$2:$FZ$601,B23,$C$5)&"","") | D23: =IFERROR(INDEX(Clay_Offices!$A$2:$FZ$601,B23,$C$7)&"","") | E23: =IFERROR(INDEX(Clay_Offices!$A$2:$FZ$601,B23,$C$8)&"","") | F23: =IF(C23="","",IF(COUNTIF(Office_Log!$A$2:$A$201,C23)>0,"Y","N")) | G23: =IF(OR(C23="",AND(LEFT(C23,6)="SAMPLE",Config!$B$19<>"Y")),"",IF(IFERROR(INDEX(Lists!$J$2:$J$15,MATCH(D23,Lists!$I$2:$I$15,0)),-1)=-1,"status '"&D23&"' is not a CONTRACTS status",IF(AND(D23="signed",COUNTIF(signed_offices!$W$2:$W$51,C23)=0),"status signed but no signed_offices row"&IF(F23="N"," and no tracker row",""),IF(AND(IFERROR(INDEX(Lists!$J$2:$J$15,MATCH(D23,Lists!$I$2:$I$15,0)),-1)>=6,F23="N"),"status "&D23&" but no tracker row",IF(AND(E23="Y",D23<>"do_not_contact"),"do_not_contact = Y but status is "&D23,IF(AND(D23="do_not_contact",E23<>"Y"),"status do_not_contact but do_not_contact is not Y","")))))) | I23: 2 | J23: =IFERROR(INDEX(Clay_Brands!$A$2:$FZ$601,I23,$D$5)&"","") | K23: =IFERROR(INDEX(Clay_Brands!$A$2:$FZ$601,I23,$D$7)&"","") | L23: =IFERROR(INDEX(Clay_Brands!$A$2:$FZ$601,I23,$D$8)&"","") | M23: =IF(J23="","",IF(COUNTIF(Brand_Log!$A$2:$A$201,J23)>0,"Y","N")) | N23: =IF(OR(J23="",AND(LEFT(J23,6)="SAMPLE",Config!$B$19<>"Y")),"",IF(IFERROR(INDEX(Lists!$J$2:$J$15,MATCH(K23,Lists!$I$2:$I$15,0)),-1)=-1,"status '"&K23&"' is not a CONTRACTS status",IF(AND(K23="paid",COUNTIF(paid_brands!$AC$2:$AC$51,J23)=0),"status paid but no paid_brands row"&IF(M23="N"," and no tracker row",""),IF(AND(IFERROR(INDEX(Lists!$J$2:$J$15,MATCH(K23,Lists!$I$2:$I$15,0)),-1)>=6,M23="N"),"status "&K23&" but no tracker row",IF(AND(L23="Y",K23<>"do_not_contact"),"do_not_contact = Y but status is "&K23,IF(AND(K23="do_not_contact",L23<>"Y"),"status do_not_contact but do_not_contact is not Y","")))))) | P23: =IF(signed_offices!W3="","",signed_offices!W3&"") | Q23: =IF(P23="","",IFERROR(INDEX(Clay_Offices!$A$2:$FZ$601,MATCH(P23,INDEX(Clay_Offices!$A$2:$FZ$601,0,$C$5),0),$C$7)&"","not in Clay")) | R23: =IF(OR(P23="",AND(LEFT(P23,6)="SAMPLE",Config!$B$19<>"Y")),"",IF(Q23="signed","","Clay status is "&Q23&": set signed")) | T23: =IF(paid_brands!AC3="","",paid_brands!AC3&"") | U23: =IF(T23="","",IFERROR(INDEX(Clay_Brands!$A$2:$FZ$601,MATCH(T23,INDEX(Clay_Brands!$A$2:$FZ$601,0,$D$5),0),$D$7)&"","not in Clay")) | V23: =IF(OR(T23="",AND(LEFT(T23,6)="SAMPLE",Config!$B$19<>"Y")),"",IF(U23="paid","","Clay status is "&U23&": set paid"))
B24: 3 | C24: =IFERROR(INDEX(Clay_Offices!$A$2:$FZ$601,B24,$C$5)&"","") | D24: =IFERROR(INDEX(Clay_Offices!$A$2:$FZ$601,B24,$C$7)&"","") | E24: =IFERROR(INDEX(Clay_Offices!$A$2:$FZ$601,B24,$C$8)&"","") | F24: =IF(C24="","",IF(COUNTIF(Office_Log!$A$2:$A$201,C24)>0,"Y","N")) | G24: =IF(OR(C24="",AND(LEFT(C24,6)="SAMPLE",Config!$B$19<>"Y")),"",IF(IFERROR(INDEX(Lists!$J$2:$J$15,MATCH(D24,Lists!$I$2:$I$15,0)),-1)=-1,"status '"&D24&"' is not a CONTRACTS status",IF(AND(D24="signed",COUNTIF(signed_offices!$W$2:$W$51,C24)=0),"status signed but no signed_offices row"&IF(F24="N"," and no tracker row",""),IF(AND(IFERROR(INDEX(Lists!$J$2:$J$15,MATCH(D24,Lists!$I$2:$I$15,0)),-1)>=6,F24="N"),"status "&D24&" but no tracker row",IF(AND(E24="Y",D24<>"do_not_contact"),"do_not_contact = Y but status is "&D24,IF(AND(D24="do_not_contact",E24<>"Y"),"status do_not_contact but do_not_contact is not Y","")))))) | I24: 3 | J24: =IFERROR(INDEX(Clay_Brands!$A$2:$FZ$601,I24,$D$5)&"","") | K24: =IFERROR(INDEX(Clay_Brands!$A$2:$FZ$601,I24,$D$7)&"","") | L24: =IFERROR(INDEX(Clay_Brands!$A$2:$FZ$601,I24,$D$8)&"","") | M24: =IF(J24="","",IF(COUNTIF(Brand_Log!$A$2:$A$201,J24)>0,"Y","N")) | N24: =IF(OR(J24="",AND(LEFT(J24,6)="SAMPLE",Config!$B$19<>"Y")),"",IF(IFERROR(INDEX(Lists!$J$2:$J$15,MATCH(K24,Lists!$I$2:$I$15,0)),-1)=-1,"status '"&K24&"' is not a CONTRACTS status",IF(AND(K24="paid",COUNTIF(paid_brands!$AC$2:$AC$51,J24)=0),"status paid but no paid_brands row"&IF(M24="N"," and no tracker row",""),IF(AND(IFERROR(INDEX(Lists!$J$2:$J$15,MATCH(K24,Lists!$I$2:$I$15,0)),-1)>=6,M24="N"),"status "&K24&" but no tracker row",IF(AND(L24="Y",K24<>"do_not_contact"),"do_not_contact = Y but status is "&K24,IF(AND(K24="do_not_contact",L24<>"Y"),"status do_not_contact but do_not_contact is not Y","")))))) | P24: =IF(signed_offices!W4="","",signed_offices!W4&"") | Q24: =IF(P24="","",IFERROR(INDEX(Clay_Offices!$A$2:$FZ$601,MATCH(P24,INDEX(Clay_Offices!$A$2:$FZ$601,0,$C$5),0),$C$7)&"","not in Clay")) | R24: =IF(OR(P24="",AND(LEFT(P24,6)="SAMPLE",Config!$B$19<>"Y")),"",IF(Q24="signed","","Clay status is "&Q24&": set signed")) | T24: =IF(paid_brands!AC4="","",paid_brands!AC4&"") | U24: =IF(T24="","",IFERROR(INDEX(Clay_Brands!$A$2:$FZ$601,MATCH(T24,INDEX(Clay_Brands!$A$2:$FZ$601,0,$D$5),0),$D$7)&"","not in Clay")) | V24: =IF(OR(T24="",AND(LEFT(T24,6)="SAMPLE",Config!$B$19<>"Y")),"",IF(U24="paid","","Clay status is "&U24&": set paid"))
B25: 4 | C25: =IFERROR(INDEX(Clay_Offices!$A$2:$FZ$601,B25,$C$5)&"","") | D25: =IFERROR(INDEX(Clay_Offices!$A$2:$FZ$601,B25,$C$7)&"","") | E25: =IFERROR(INDEX(Clay_Offices!$A$2:$FZ$601,B25,$C$8)&"","") | F25: =IF(C25="","",IF(COUNTIF(Office_Log!$A$2:$A$201,C25)>0,"Y","N")) | G25: =IF(OR(C25="",AND(LEFT(C25,6)="SAMPLE",Config!$B$19<>"Y")),"",IF(IFERROR(INDEX(Lists!$J$2:$J$15,MATCH(D25,Lists!$I$2:$I$15,0)),-1)=-1,"status '"&D25&"' is not a CONTRACTS status",IF(AND(D25="signed",COUNTIF(signed_offices!$W$2:$W$51,C25)=0),"status signed but no signed_offices row"&IF(F25="N"," and no tracker row",""),IF(AND(IFERROR(INDEX(Lists!$J$2:$J$15,MATCH(D25,Lists!$I$2:$I$15,0)),-1)>=6,F25="N"),"status "&D25&" but no tracker row",IF(AND(E25="Y",D25<>"do_not_contact"),"do_not_contact = Y but status is "&D25,IF(AND(D25="do_not_contact",E25<>"Y"),"status do_not_contact but do_not_contact is not Y","")))))) | I25: 4 | J25: =IFERROR(INDEX(Clay_Brands!$A$2:$FZ$601,I25,$D$5)&"","") | K25: =IFERROR(INDEX(Clay_Brands!$A$2:$FZ$601,I25,$D$7)&"","") | L25: =IFERROR(INDEX(Clay_Brands!$A$2:$FZ$601,I25,$D$8)&"","") | M25: =IF(J25="","",IF(COUNTIF(Brand_Log!$A$2:$A$201,J25)>0,"Y","N")) | N25: =IF(OR(J25="",AND(LEFT(J25,6)="SAMPLE",Config!$B$19<>"Y")),"",IF(IFERROR(INDEX(Lists!$J$2:$J$15,MATCH(K25,Lists!$I$2:$I$15,0)),-1)=-1,"status '"&K25&"' is not a CONTRACTS status",IF(AND(K25="paid",COUNTIF(paid_brands!$AC$2:$AC$51,J25)=0),"status paid but no paid_brands row"&IF(M25="N"," and no tracker row",""),IF(AND(IFERROR(INDEX(Lists!$J$2:$J$15,MATCH(K25,Lists!$I$2:$I$15,0)),-1)>=6,M25="N"),"status "&K25&" but no tracker row",IF(AND(L25="Y",K25<>"do_not_contact"),"do_not_contact = Y but status is "&K25,IF(AND(K25="do_not_contact",L25<>"Y"),"status do_not_contact but do_not_contact is not Y","")))))) | P25: =IF(signed_offices!W5="","",signed_offices!W5&"") | Q25: =IF(P25="","",IFERROR(INDEX(Clay_Offices!$A$2:$FZ$601,MATCH(P25,INDEX(Clay_Offices!$A$2:$FZ$601,0,$C$5),0),$C$7)&"","not in Clay")) | R25: =IF(OR(P25="",AND(LEFT(P25,6)="SAMPLE",Config!$B$19<>"Y")),"",IF(Q25="signed","","Clay status is "&Q25&": set signed")) | T25: =IF(paid_brands!AC5="","",paid_brands!AC5&"") | U25: =IF(T25="","",IFERROR(INDEX(Clay_Brands!$A$2:$FZ$601,MATCH(T25,INDEX(Clay_Brands!$A$2:$FZ$601,0,$D$5),0),$D$7)&"","not in Clay")) | V25: =IF(OR(T25="",AND(LEFT(T25,6)="SAMPLE",Config!$B$19<>"Y")),"",IF(U25="paid","","Clay status is "&U25&": set paid"))
