Workbook

Sheet Assumptions
A1: QoE Evidence Review: commercial model inputs
A2: ILLUSTRATIVE MODEL. No time saving has been measured. Scenario results appear only after measured preparer and reviewer time reductions are entered.
A3: Freed salaried hours are capacity, not money. They become economic value only when they are redeployed, when a cost is actually avoided, or when delivery economics change.
A5: Legend
B6: 123 | C6: Blue text: an input you can change.
C7: Yellow fill: replace with your firm's own data (or a measured value) before relying on any output.
B8: =1+1 -> 2 | C8: Black text: a formula. Do not overwrite.
B9: 123 | C9: Grey column: ILLUSTRATIVE example values only. Not measured, not a forecast, not a benchmark.
A10: Percentages are stored as fractions (0.35 = 35%). Basis ASSUMPTION = your estimate; MEASURED = from a timed comparison only.
A12: Ref | B12: Input | C12: Your value | D12: Unit | E12: Basis (your value) | F12: Illustrative example | G12: Note
A13: I-01 | B13: Management adjustments tested per engagement | D13: adjustments | E13: ASSUMPTION | F13: 12 | G13: Seller-proposed EBITDA adjustments in a typical QoE. Use the median of your recent engagements.
A14: I-02 | B14: Baseline preparer hours per adjustment | D14: hours | E14: ASSUMPTION | F14: 6 | G14: Associate / senior hours per adjustment today: GL pull, tie-out, document review, support schedule. Take it from time codes, not recollection.
A15: I-03 | B15: Baseline reviewer hours per adjustment | D15: hours | E15: ASSUMPTION | F15: 1.5 | G15: Manager / senior manager review hours per adjustment today.
A16: I-04 | B16: Other engagement hours (unaffected by the tool) | D16: hours | E16: ASSUMPTION | F16: 500 | G16: Hours on the rest of the QoE: net working capital, net debt, databook, report, meetings. Needed to express freed hours as whole engagements.
A17: I-05 | B17: Measured preparer time reduction | D17: % of baseline hours | E17: =IF(ISNUMBER(C17),"MEASURED","MEASUREMENT PENDING") -> MEASUREMENT PENDING | F17: 0.4 | G17: From a timed comparison of the same adjustments with and without the tool. Leave blank until measured: the model shows no result without it. Illustrative value is NOT a measured result.
A18: I-06 | B18: Measured reviewer time reduction | D18: % of baseline hours | E18: =IF(ISNUMBER(C18),"MEASURED","MEASUREMENT PENDING") -> MEASUREMENT PENDING | F18: 0.15 | G18: Reviewer hours with vs without the tool, from the same timed comparison. Leave blank until measured. Illustrative value is NOT a measured result.
A19: I-07 | B19: QoE engagements per year per team | D19: engagements | E19: ASSUMPTION | F19: 20 | G19: Engagements the team delivers in a year.
A20: I-08 | B20: Blended preparer cost per hour | D20: USD / hour | E20: ASSUMPTION | F20: 90 | G20: Fully loaded cost (salary, benefits, overhead) per available hour. Cost, not bill rate.
A21: I-09 | B21: Blended reviewer cost per hour | D21: USD / hour | E21: ASSUMPTION | F21: 175 | G21: Fully loaded cost per available hour for managers / senior managers.
A22: I-10 | B22: Share of engagements on a fixed fee | D22: % of engagements | E22: ASSUMPTION | F22: 0.6 | G22: The rest are billed hourly.
A23: I-11 | B23: Fixed fee per QoE | D23: USD | E23: ASSUMPTION | F23: 150000 | G23: Average fixed fee, excluding expenses.
A24: I-12 | B24: Blended net realized bill rate | D24: USD / hour | E24: ASSUMPTION | F24: 300 | G24: Standard rate x realization. Prices hourly engagements and values redeployed hours.
A25: I-13 | B25: Share of freed hours redeployed | D25: % of freed hours | E25: ASSUMPTION | F25: 0.5 | G25: Share actually converted to billable or other engagement work. Depends on demand, not on the tool.
A26: I-14 | B26: Chargeable hours per FTE per year | D26: hours / year | E26: ASSUMPTION | F26: 1500 | G26: Converts freed hours into full-time equivalents.
A27: I-15 | B27: Incremental hires planned that freed capacity could replace | D27: hires | E27: ASSUMPTION | F27: 1 | G27: 0 if the team is not planning to hire. Capped at whole FTEs actually freed.
A28: I-16 | B28: Fully loaded annual cost per hire | D28: USD / year | E28: ASSUMPTION | F28: 140000 | G28: Salary, benefits, overhead, and recruiting cost for the role that would have been hired.
A30: Input checks
B31: Time reductions measured? | C31: =COUNT(C17,C18)=2 -> FALSE | F31: =COUNT(F17,F18)=2 -> TRUE
B32: All inputs entered? | C32: =COUNT(C13:C28)=16 -> FALSE | F32: =COUNT(F13:F28)=16 -> TRUE

Sheet Scenarios
A1: QoE Evidence Review: scenarios (capacity vs economic value)
A2: Freed salaried hours are capacity, not money. They become economic value only when they are redeployed, when a cost is actually avoided, or when delivery economics change. The four views below are alternatives: do not add them together.
A3: Every value on this sheet is a formula on the Assumptions sheet. 'n/a' means an input it needs is blank.
A5: Ref | B5: Line | C5: Your inputs | D5: Illustrative example (not measured) | E5: How computed
B6: Status | C6: =IF(NOT(Assumptions!C31),"Awaiting measured time reduction: no result",IF(Assumptions!C32,"All inputs entered","Some inputs blank: see n/a")) -> Awaiting measured time reduction: no result | D6: ="ILLUSTRATIVE, not measured: "&IF(NOT(Assumptions!F31),"Awaiting measured time reduction: no result",IF(Assumptions!F32,"All inputs entered","Some inputs blank: see n/a")) -> ILLUSTRATIVE, not measured: All inputs entered
A8: (a) Capacity only: hours, not dollars
A9: a.1 | B9: Baseline adjustment-review hours per engagement | C9: =IF(COUNT(Assumptions!$C$13,Assumptions!$C$14,Assumptions!$C$15)=3,Assumptions!$C$13*(Assumptions!$C$14+Assumptions!$C$15),"n/a") -> n/a | D9: =IF(COUNT(Assumptions!$F$13,Assumptions!$F$14,Assumptions!$F$15)=3,Assumptions!$F$13*(Assumptions!$F$14+Assumptions!$F$15),"n/a") -> 90 | E9: I-01 x (I-02 + I-03)
A10: a.2 | B10: Preparer hours freed per engagement | C10: =IF(COUNT(Assumptions!$C$13,Assumptions!$C$14,Assumptions!$C$17)=3,Assumptions!$C$13*Assumptions!$C$14*Assumptions!$C$17,"n/a") -> n/a | D10: =IF(COUNT(Assumptions!$F$13,Assumptions!$F$14,Assumptions!$F$17)=3,Assumptions!$F$13*Assumptions!$F$14*Assumptions!$F$17,"n/a") -> 28.8 | E10: I-01 x I-02 x I-05
A11: a.3 | B11: Reviewer hours freed per engagement | C11: =IF(COUNT(Assumptions!$C$13,Assumptions!$C$15,Assumptions!$C$18)=3,Assumptions!$C$13*Assumptions!$C$15*Assumptions!$C$18,"n/a") -> n/a | D11: =IF(COUNT(Assumptions!$F$13,Assumptions!$F$15,Assumptions!$F$18)=3,Assumptions!$F$13*Assumptions!$F$15*Assumptions!$F$18,"n/a") -> 2.7 | E11: I-01 x I-03 x I-06
A12: a.4 | B12: Total hours freed per engagement | C12: =IF(COUNT(C10,C11)=2,C10+C11,"n/a") -> n/a | D12: =IF(COUNT(D10,D11)=2,D10+D11,"n/a") -> 31.5 | E12: a.2 + a.3
A13: a.5 | B13: Hours freed per team per year | C13: =IF(COUNT(C12,Assumptions!$C$19)=2,C12*Assumptions!$C$19,"n/a") -> n/a | D13: =IF(COUNT(D12,Assumptions!$F$19)=2,D12*Assumptions!$F$19,"n/a") -> 630 | E13: a.4 x I-07
A14: a.6 | B14: Total hours per engagement with the tool | C14: =IF(COUNT(C9,Assumptions!$C$16,C12)=3,C9+Assumptions!$C$16-C12,"n/a") -> n/a | D14: =IF(COUNT(D9,Assumptions!$F$16,D12)=3,D9+Assumptions!$F$16-D12,"n/a") -> 558.5 | E14: a.1 + I-04 - a.4
A15: a.7 | B15: Equivalent additional engagements per year (if demand exists) | C15: =IF(COUNT(C13,C14)=2,IF(C14=0,"n/a",C13/C14),"n/a") -> n/a | D15: =IF(COUNT(D13,D14)=2,IF(D14=0,"n/a",D13/D14),"n/a") -> 1.1280215 | E15: a.5 / a.6
B16: Salaried staff cost the same whether or not these hours are used. Equivalent engagements are capacity for more work only if there is demand to fill it.
A18: (b) Fixed-fee margin: delivery economics
A19: b.1 | B19: Fixed-fee engagements per year | C19: =IF(COUNT(Assumptions!$C$19,Assumptions!$C$22)=2,Assumptions!$C$19*Assumptions!$C$22,"n/a") -> n/a | D19: =IF(COUNT(Assumptions!$F$19,Assumptions!$F$22)=2,Assumptions!$F$19*Assumptions!$F$22,"n/a") -> 12 | E19: I-07 x I-10
A20: b.2 | B20: Delivery cost avoided per engagement at standard cost (USD) | C20: =IF(COUNT(C10,Assumptions!$C$20,C11,Assumptions!$C$21)=4,C10*Assumptions!$C$20+C11*Assumptions!$C$21,"n/a") -> n/a | D20: =IF(COUNT(D10,Assumptions!$F$20,D11,Assumptions!$F$21)=4,D10*Assumptions!$F$20+D11*Assumptions!$F$21,"n/a") -> 3064.5 | E20: a.2 x I-08 + a.3 x I-09
A21: b.3 | B21: Margin lift per fixed-fee engagement (% of fee) | C21: =IF(COUNT(C20,Assumptions!$C$23)=2,IF(Assumptions!$C$23=0,"n/a",C20/Assumptions!$C$23),"n/a") -> n/a | D21: =IF(COUNT(D20,Assumptions!$F$23)=2,IF(Assumptions!$F$23=0,"n/a",D20/Assumptions!$F$23),"n/a") -> 0.02043 | E21: b.2 / I-11
A22: b.4 | B22: Engagement-margin improvement on fixed-fee work (USD per year) | C22: =IF(COUNT(C20,C19)=2,C20*C19,"n/a") -> n/a | D22: =IF(COUNT(D20,D19)=2,D20*D19,"n/a") -> 36774 | E22: b.2 x b.1
A23: b.5 | B23: Hourly-billed engagements per year | C23: =IF(COUNT(Assumptions!$C$19,Assumptions!$C$22)=2,Assumptions!$C$19*(1-Assumptions!$C$22),"n/a") -> n/a | D23: =IF(COUNT(Assumptions!$F$19,Assumptions!$F$22)=2,Assumptions!$F$19*(1-Assumptions!$F$22),"n/a") -> 8 | E23: I-07 x (1 - I-10)
A24: b.6 | B24: Fees forgone on hourly engagements (USD per year) | C24: =IF(COUNT(C12,Assumptions!$C$24,C23)=3,-C12*Assumptions!$C$24*C23,"n/a") -> n/a | D24: =IF(COUNT(D12,Assumptions!$F$24,D23)=3,-D12*Assumptions!$F$24*D23,"n/a") -> -75600 | E24: -(a.4 x I-12 x b.5)
A25: b.7 | B25: Delivery cost avoided on hourly engagements at standard cost (USD per year) | C25: =IF(COUNT(C20,C23)=2,C20*C23,"n/a") -> n/a | D25: =IF(COUNT(D20,D23)=2,D20*D23,"n/a") -> 24516 | E25: b.2 x b.5
A26: b.8 | B26: Net engagement-margin effect on hourly work (USD per year) | C26: =IF(COUNT(C24,C25)=2,C24+C25,"n/a") -> n/a | D26: =IF(COUNT(D24,D25)=2,D24+D25,"n/a") -> -51084 | E26: b.6 + b.7
B27: Engagement margin at standard cost (hours x cost rate). On a fixed fee the fee is unchanged, so fewer hours lift margin. On hourly work the client keeps the saving: billed fees fall with hours. The firm's cash profit changes only if the freed hours are redeployed (c) or a hire is avoided (d).
A29: (c) Redeployment: value only for hours actually redeployed
A30: c.1 | B30: Freed hours redeployed per year | C30: =IF(COUNT(C13,Assumptions!$C$25)=2,C13*Assumptions!$C$25,"n/a") -> n/a | D30: =IF(COUNT(D13,Assumptions!$F$25)=2,D13*Assumptions!$F$25,"n/a") -> 315 | E30: a.5 x I-13
A31: c.2 | B31: Freed hours not redeployed (no economic value) | C31: =IF(COUNT(C13,C30)=2,C13-C30,"n/a") -> n/a | D31: =IF(COUNT(D13,D30)=2,D13-D30,"n/a") -> 315 | E31: a.5 - c.1
A32: c.3 | B32: Value of redeployed hours (USD per year) | C32: =IF(COUNT(C30,Assumptions!$C$24)=2,C30*Assumptions!$C$24,"n/a") -> n/a | D32: =IF(COUNT(D30,Assumptions!$F$24)=2,D30*Assumptions!$F$24,"n/a") -> 94500 | E32: c.1 x I-12
B33: Hours that are not redeployed are idle capacity with no economic value.
A35: (d) Avoided incremental hire
A36: d.1 | B36: Full-time equivalents freed | C36: =IF(COUNT(C13,Assumptions!$C$26)=2,IF(Assumptions!$C$26=0,"n/a",C13/Assumptions!$C$26),"n/a") -> n/a | D36: =IF(COUNT(D13,Assumptions!$F$26)=2,IF(Assumptions!$F$26=0,"n/a",D13/Assumptions!$F$26),"n/a") -> 0.42 | E36: a.5 / I-14
A37: d.2 | B37: Hires avoided (capped at whole FTEs freed) | C37: =IF(COUNT(Assumptions!$C$27,C36)=2,MIN(Assumptions!$C$27,ROUNDDOWN(C36,0)),"n/a") -> n/a | D37: =IF(COUNT(Assumptions!$F$27,D36)=2,MIN(Assumptions!$F$27,ROUNDDOWN(D36,0)),"n/a") -> 0 | E37: MIN(I-15, whole FTEs in d.1)
A38: d.3 | B38: Hiring cost avoided (USD per year) | C38: =IF(COUNT(C37,Assumptions!$C$28)=2,C37*Assumptions!$C$28,"n/a") -> n/a | D38: =IF(COUNT(D37,Assumptions!$F$28)=2,D37*Assumptions!$F$28,"n/a") -> 0 | E38: d.2 x I-16
B39: Applies only if the team would otherwise hire. A fraction of an FTE does not avoid a hire.
