Workbook

Sheet README
A1: =Inputs!$C$8&" financial model v1: README"
A2: Version 1, built 2026-10-23. The company name lives in one cell (Inputs, section 1, 'Company name'); rename it there only.
A5: What this workbook is
A6: The workbook you open every week for six months to see whether the business is working. It answers three questions: what each drop earns per founder hour, how low cumulative cash goes and when, and which gate or decision scenario the real numbers point to.
A7: Every number is a planning estimate from plan.md, never a forecast. Every assumption sits in one labeled cell on Inputs with its unit and source. Every other number is a formula. Change one input and every output moves.
A9: Your weekly routine (about ten minutes)
A10: 1. Log hours | B10: Add the week's hours on Hours_Log (one row per entry: date, drop_id or blank, activity key, hours). If you use a paid Toggl plan, paste its export on Toggl_Import instead.
A11: 2. Log the pipeline | B11: Paste or type outreach events on Pipeline: conversations, yeses, signed offices with Tuesday headcount, paid brands, budget-probe answers, renewal answers.
A12: 3. After each drop | B12: Paste the campaign actuals and drop costs from the operations exports into Actuals_Campaigns and Actuals_DropCosts, then set 'Actuals in' to Y for that drop on Schedule.
A13: 4. Read the Dashboard | B13: Gates show pass, miss or not yet against real numbers only. The headline shows the next drop's contribution per hour, the lowest point of cash and the gap to the plan's $6,510.
A14: 5. Keep the plan current | B14: Edit Schedule when a date, delivery model or brand count changes. Edit Inputs when a quote comes in. The 'Changed?' column records every edit against the plan default.
A16: Change the price and read the result in under a minute
A17: Whole model | B17: Inputs, section 3, 'Standard price per office' (now $150). Type a new number. Read Dashboard: 'Its contribution per founder hour' and the drop table at the bottom.
A18: One drop only | B18: Calculator: type a price in 'Standard price per office'. The result column shows revenue, costs, hours and contribution per founder hour. Nothing else changes.
A19: Many prices at once | B19: Sensitivity, Table 1: contribution per founder hour for eight prices and one to five brands. Green cells clear the $50 Gate 3 target.
A21: Tabs, in the order you use them
A22: Dashboard | B22: Headline numbers, every gate threshold beside its live value with pass, miss or not yet, the decision rule, the scenario the numbers point to, six-month goals, and contribution per hour on each drop.
A23: Inputs | B23: Every assumption: prices, payment terms and lags, the processing toggle, units, every hard-cost line, monthly overhead, hours by activity, the delivery-model table, renewal, gates, startup outlays with timing, the start date. Yellow cells are inputs.
A24: Scenarios | B24: The plan's decision situations A to D as assumption sets, beside the plan base. Pick one on Inputs. It drives the two decision-window drops and the steady state.
A25: Schedule | B25: The editable drop schedule: date, delivery model, tier, offices, new offices, brands, renewals, and the switch to actuals. Checks Tuesday or Wednesday and every blackout.
A26: Calculator | B26: A single drop of any tier, brand count, office count and delivery model, run through the same engine.
A27: Drop_PnL | B27: Per-drop P&L on the plan basis for every scheduled drop, with hours by activity, contribution per founder hour, cash timing on the plan's terms, and live values (actual where in).
A28: Cash_Flow | B28: Weekly cash flow for 26 weeks with a monthly cross-check: brand receipts, direct costs, overhead paid once, startup outlays at their timing, cumulative cash and its lowest point.
A29: Steady_State | B29: The plan's monthly picture reproduced, the scenario in force at steady state, and break-even: campaigns to recover startup cash, campaigns a month to cover overhead, the brand count and price where contribution per hour crosses $50.
A30: Sensitivity | B30: Four plain-formula tables: price x brands, renewal x brands, renewal against the monthly steady state, price against the monthly steady state. Direction checks at the bottom.
A31: Plan_Check | B31: The plan's five scenario rows, the $1,000 reading, edge cases, the founder-hour table cell by cell, and a reconciliation of every plan figure: plan, model, difference, reason.
A32: Capital | B32: The plan's capital table line by line, where the model pays each line, and the cash the plan's table leaves out.
A33: Hours_Log | B33: The hand-filled hours log by the seven activity keys, with totals per drop and per week.
... A40: Lists | B40: Fixed keys (delivery model, tier, activities, events), federal holidays and blackouts. Add holidays or blackouts in the blank yellow rows.
A42: Colours and conventions
A43: Yellow cell, blue text | B43: An input. Type here.
A44: Grey cell | B44: Calculated on the Inputs tab. Do not type over it.
A45: Green cell | B45: A key output.
A46: Formulas | B46: No numeric literal other than 0 or 1 appears in any formula; conversions such as days per week sit in input cells. _work/audit_formulas.py checks this.
A47: Signs | B47: Cash outflows are negative on Cash_Flow. Costs are positive on the P&L tabs.
A48: Dates | B48: YYYY-MM-DD. Week 1 starts Monday 2026-10-26 (CONTRACTS section 3).
A50: Plan readings (each verified by Plan_Check; none is a fudge)
A51: (a) Display kit | B51: $8 per office per drop, not per brand. Only this reproduces the scenario hard costs: a three-brand courier drop is $80 + $300 + $75 + $30 + $50 + $135 = $670. Per brand it would be $830.
A52: (b) Campaign zero | B52: Reproduces with storage at $0 (sealed cases at home), transport $120 and processing at 3%: $40 + $120 + $0 + $30 + $50 + $36 = $276, which the plan rounds to $280. Contribution is $924 against the plan's $920, and $16.2 per hour.
A53: (c) Direct-ship row | B53: The three-brand direct-ship row ($370) keeps the $75 storage allocation and $0 transport.
A54: (d) The $1,000 price | B54: 'At $1,000 the three-brand drop drops to about $47 an hour' assumes no card processing: $2,465 / 52 h = $47.4. With processing at 3% it is $45.7.
A55: (e) Monthly steady state | B55: $9,000 revenue, about $1,350 hard costs and 104 hours is two three-brand courier drops: $1,340 in hard costs and $7,660 contribution. The plan rounds these.
A56: (f) Fixed overhead | B56: $60 software + $100 insurance + $150 storage + $0 phone = $310 a month, inside the plan's $200 to $350. With home storage it is $160.
A57: (g) Transport lump | B57: The plan's capital line 'Transport, campaigns zero to two: $600' does not reconcile to its own rates ($120 + $300 + $300 = $720). The model pays transport per drop at the rates; the capital table is reproduced as printed.
A58: (h) Hours per win | B58: Six hours per standard brand win = five qualified conversations of 45 minutes (20% close rate) plus 2.25 hours of proposal and paperwork. The close rate on Inputs moves it.
A60: How the model counts money (no double counting)
A61: Contribution follows the plan: revenue less hard costs, where hard costs include per-drop allocations of storage ($75), software ($30) and insurance ($50). Those allocations are views of monthly costs (monthly cost / two drops a month). The cash flow never reads them; it pays software, storage, insurance and phone once, from the Cash_Ledger schedule. Cash_Flow shows how much overhead the drops did not absorb in months with fewer than two drops.
A62: Startup outlays (formation, publication, licence, printing, domain, professional hours, trademark) are paid once at their timing. Per-drop direct costs (kits, transport, kit mailing, card processing) are paid on the drop's dates. The plan's capital table is reproduced on Capital for comparison only; the cash flow does not read it.
A63: Brand cash follows the plan's terms: founding brands pay in full before product ships (20 business days before the drop, so campaign zero's money lands at Gate 1); standard brands pay 50% at signature (at the latest, T-10) and 50% at placement confirmation (T+1). The invoice-to-cash lag is blank because the plan has none.
A65: How shared drop costs split across brands
A66: A drop's shared costs (display kits, transport, kit mailing, overhead allocations) and shared hours (office coordination, the base of receiving, drop day, checks, admin) are split equally across the brands on the drop wherever a per-brand figure is shown (Calculator, break-even). Revenue, card processing, brand sales hours, per-brand kitting and reporting hours belong to each brand. No figure in the model depends on the split except those per-brand views.
A68: Assumptions (numbered)
A69: 1 | B69: Prices are per office at the tier rate: $150 standard, $120 founding. Offices beyond the package (10 or 5) pay the $150 extra-office price. Founding-rate renewals pay $120 per office for any office count. A drop smaller than the package is priced pro rata; founder to confirm any minimum.
A70: 2 | B70: A drop with zero brands does not run: no cost, no hours.
A71: 3 | B71: Founder hours decompose the plan's table into rates: 10 hours per first (founding) brand, 6 per standard win, 2 per renewal, 4 per new office, 1 per existing office, 2 reporting per brand, 2 admin per drop, and logistics by delivery model (Inputs section 7). The rates reproduce all four columns exactly.
A72: 4 | B72: A renewal fills a brand slot on a later drop at that brand's tier price and costs 2 hours of brand sales instead of 6. In the decision-window drops, renewals = renewal rate x brands, rounded.
A73: 5 | B73: Card processing applies to every receipt while the toggle is 1 (high end of the 0% to 3% range). Set it to 0 to model bank transfer, the plan's preferred invoicing.
A74: 6 | B74: Insurance is $100 a month (the plan's working figure), paid as one annual premium of $1,200 at bind on Gate 1. The capital table's $500 to $1,500 range is shown beside it.
A75: 7 | B75: Storage: home for campaign zero, a $150-a-month unit from 2027-02-01 through the six months. Software $60 a month from week 1. Phone $0.
A76: 8 | B76: Courier transport is $30 a stop ($300 for ten stops; range $25 to $40). Founder delivery is $120 a drop. Direct-ship transport is $0; mailing the kit ahead needs a quote.
A77: 9 | B77: Startup outlays take the high end of each cost range unless the plan gives a working figure: publication $2,000 (New York County), warehouse licence $400, attorney and accountant about $700, trademark $350.
A78: 10 | B78: Gate tests use real numbers only: the pipeline log for Gates 0 and 1, campaign actuals for Gates 2 and 3. A gate is 'not yet' until its review date passes, then 'miss' if the threshold is not met.
A79: 11 | B79: Gate 2 tests five responses per office per brand campaign using survey_responses_min_office when operations supplies it, otherwise the average per office.
A80: 12 | B80: The steady state uses the courier model, as the plan's monthly picture does; direct-ship raises contribution per hour.
A82: Derived items (founder to confirm)
A83: D1 | B83: Calendar from CONTRACTS section 3: week 1 2026-10-26; Gate 0 2026-11-13; Gate 1 2026-12-11; campaign zero Tue 2027-01-12 (moved by the December blackout); Gate 2 2027-01-22; standard drops Tue 2027-02-09 and Tue 2027-02-23; Gate 3 Fri 2027-03-12; decision 2027-04-09.
A84: D2 | B84: Two decision-window drops, Tue 2027-03-23 and Tue 2027-04-06, direct-ship, three brands each: the simplest schedule that meets the six-month goal of two renewals and scenario B's 'two more drops'.
A85: D3 | B85: New offices: five in campaign zero, five more in standard run 1 (to reach ten), two in run 2 (to reach the goal of 12 active offices).
A86: D4 | B86: Founding payment 20 business days before the drop (campaign zero's money at Gate 1). Standard signature at T-10 (the latest that still lets a brand ship). Balance at T+1.
A87: D5 | B87: Startup timing: domain week 1; LLC filing, publication and professional hours at Gate 0; certificate of publication 2026-12-28; insurance, licence and printing at Gate 1; trademark at Gate 2.
A88: D6 | B88: Hour rates for receiving and kitting, drop day and checks by delivery model, derived from the plan's table (Inputs section 7).
A89: D7 | B89: Scenario levers the plan does not name use the plan base and say so (Scenarios, source column). Scenario B's renewal is 0%, the low end of 'under 30%'.
A91: Needs a quote or a founder decision (blank or flagged)
A92: Courier | B92: Three quotes for a ten-stop route. Default $30 a stop.
A93: Insurance | B93: Three general liability quotes. Default $100 a month.
A94: Kit mailing | B94: Postage to mail a display kit ahead of a direct-ship drop. Blank.
A95: Extra tent cards | B95: Whether each brand on a drop needs its own card ($1 to $2 each). Blank, per reading (a).
A96: Payment lag | B96: Your invoice terms. Blank = paid the day invoiced.
A97: Founder cash | B97: What you commit to the six months (plan question 7). Blank.
A98: Office-paid cost | B98: Cost to serve an office-paid office (scenario B). Blank.
A100: Measurement honesty
A101: The ladder stays in separate columns everywhere: delivered, placed, depleted, responded (tried is a survey answer), scanned, purchased (code redemptions). Incremental purchases are not measured, and the column says so. There is no field for sales lift, conversions or ROI.
A103: Google Sheets
A104: Built to open in Google Sheets with formulas intact: no macros, scripts, data tables, array formulas, named ranges or add-ons. Every function used appears in Google's Sheets function list (support.google.com/docs/table/25273, opened 2026-10-23). Import: File, Import, Upload, Replace spreadsheet. A live import was not possible from the build environment, so check Dashboard and Checks after the first import (unverified, founder to confirm).
A106: Changelog
A107: Round 1 | B107: Draft: built every tab, the shared engine, plan reproduction, cash flow, gates, scenarios, sensitivities and logs.

Sheet Dashboard
A1: =Inputs!$C$8&" financial model v1"
A2: =Inputs!$C$9
A3: Planning estimates, not a forecast. Gates count real numbers only (pipeline log and actuals). Change assumptions on Inputs; type real numbers into the logs.
B5: As of | C5: =Inputs!$C$17 | D5: Scenario in force | E5: =Inputs!$C$29 | F5: Model checks | G5: =IF(Checks!$D$34=0,"all integrity checks pass",Checks!$D$34&" integrity check(s) failing")
A7: Headline
B8: Measure | C8: Value | D8: Detail
B9: Next scheduled drop | C9: =IFERROR(INDEX(Drop_PnL!$A$7:$A$18,MATCH(1,Drop_PnL!$BG$7:$BG$18,0)),"none scheduled") | D9: =IFERROR(TEXT(INDEX(Drop_PnL!$B$7:$B$18,MATCH(1,Drop_PnL!$BG$7:$BG$18,0)),"ddd yyyy-mm-dd")&", "&INDEX(Drop_PnL!$C$7:$C$18,MATCH(1,Drop_PnL!$BG$7:$BG$18,0))&", "&INDEX(Drop_PnL!$G$7:$G$18,MATCH(1,Drop_PnL!$BG$7:$BG$18,0))&" brand(s), "&INDEX(Drop_PnL!$E$7:$E$18,MATCH(1,Drop_PnL!$BG$7:$BG$18,0))&" offices","")
B10: Its contribution per founder hour (plan) | C10: =IFERROR(INDEX(Drop_PnL!$AK$7:$AK$18,MATCH(1,Drop_PnL!$BG$7:$BG$18,0)),"n/a") | D10: =IFERROR("revenue "&TEXT(INDEX(Drop_PnL!$S$7:$S$18,MATCH(1,Drop_PnL!$BG$7:$BG$18,0)),"$#,##0")&", "&TEXT(INDEX(Drop_PnL!$AI$7:$AI$18,MATCH(1,Drop_PnL!$BG$7:$BG$18,0)),"0")&" founder hours","")
B11: Standard runs to Gate 3: contribution per founder hour, plan | C11: =E38 | D11: ="actual: "&IF(F38="","not yet",TEXT(F38,"$#,##0.0"))&"; target "&TEXT(Inputs!$C$126,"$#,##0")
B12: Lowest point of cumulative cash (before founder cash) | C12: =Cash_Flow!$C$32 | D12: ="in week "&Cash_Flow!$C$33&", starting "&TEXT(Cash_Flow!$C$34,"ddd yyyy-mm-dd")
B13: Capital to commit: lowest point plus the reserve | C13: =Cash_Flow!$C$37 | D13: ="reserve "&TEXT(Inputs!$C$107,"$#,##0")&" (plan)"
B14: Plan capital figure (high end of the plan's table) | C14: =Capital!$D$14 | D14: ="low end "&TEXT(Capital!$C$14,"$#,##0")
B15: Gap to the plan capital figure (positive = headroom) | C15: =Cash_Flow!$C$39 | D15: =IF(C15>=0,"the plan figure covers the model need","the model needs more than the plan figure")
B16: Founder cash committed | C16: =Cash_Flow!$C$40 | D16: =IF(Inputs!$C$105="","set it on Inputs (plan question 7)",IF(Inputs!$C$105>=Cash_Flow!$C$37,"covers capital to commit","short of capital to commit by "&TEXT(Cash_Flow!$C$37-Inputs!$C$105,"$#,##0")))
B17: Overhead paid but not absorbed by drops, six months | C17: =Cash_Flow!$C$69 | D17: ="paid "&TEXT(Cash_Flow!$C$68,"$#,##0")&", allocated to drops "&TEXT(Cash_Flow!$C$67,"$#,##0")&": the ramp-up months carry overhead with few drops"
B18: Six months all-in: contribution after all overhead per founder hour | C18: =IF(SUMIFS(Drop_PnL!$BC$7:$BC$18,Drop_PnL!$B$7:$B$18,"<="&Cash_Flow!$AB$6)+Inputs!$C$90*Inputs!$C$91>0,(SUMIFS(Drop_PnL!$BD$7:$BD$18,Drop_PnL!$B$7:$B$18,"<="&Cash_Flow!$AB$6)-Cash_Flow!$C$69)/(SUMIFS(Drop_PnL!$BC$7:$BC$18,Drop_PnL!$B$7:$B$18,"<="&Cash_Flow!$AB$6)+Inputs!$C$90*Inputs!$C$91),"n/a") | D18: ="includes "&TEXT(Inputs!$C$90*Inputs!$C$91,"0")&" discovery hours; after one-time startup outlays: "&IF(SUMIFS(Drop_PnL!$BC$7:$BC$18,Drop_PnL!$B$7:$B$18,"<="&Cash_Flow!$AB$6)+Inputs!$C$90*Inputs!$C$91>0,TEXT((SUMIFS(Drop_PnL!$BD$7:$BD$18,Drop_PnL!$B$7:$B$18,"<="&Cash_Flow!$AB$6)-Cash_Flow!$C$69-Inputs!$Q$160)/(SUMIFS(Drop_PnL!$BC$7:$BC$18,Drop_PnL!$B$7:$B$18,"<="&Cash_Flow!$AB$6)+Inputs!$C$90*Inputs!$C$91),"$#,##0.0"),"n/a")&" per hour"
B19: Steady state, scenario in force: contribution per month | C19: =Steady_State!$D$26 | D19: ="per founder hour "&IF(ISNUMBER(Steady_State!$D$27),TEXT(Steady_State!$D$27,"$#,##0.0"),"n/a")&"; net of all overhead "&TEXT(Steady_State!$D$37,"$#,##0")&" a month"
B20: Office-fatigue warnings on Schedule | C20: =COUNTIF(Schedule!$W$7:$W$18,"some*") | D20: =IF(C20=0,"no office gets two drops within four weeks","drops where some offices get a second drop within four weeks (plan: one drop a month)")
B21: Schedule rows changed or added since the derived default | C21: =COUNTIF(Schedule!$X$7:$X$18,"changed") | D21: =IF(C21=0,"schedule is the derived default","edited by you")
B22: Inputs changed from plan defaults | C22: =Inputs!$C$162 | D22: =IF(Checks!$D$36=0,"plan figures reproduce","plan reproduction differs in "&Checks!$D$36&" check(s); expected after edits")
A24: Gate dashboard (live values are actuals only)
A25: Gate | B25: Test | C25: Review date | D25: Threshold | E25: Model assumes | F25: Live value | G25: Status | H25: If it fails (plan)
A26: Gate 0 | B26: Office conversations held (context) | C26: =Inputs!$C$11 | D26: =Inputs!$C$112 | F26: =Pipeline!$U$5 | G26: info
A27: Gate 0 | B27: Offices yes in principle, with owner and receiving window | C27: =Inputs!$C$11 | D27: =Inputs!$C$111 | F27: =Pipeline!$U$6 | G27: =IF(F27="",IF(Inputs!$C$17>C27,"miss","not yet"),IF(F27>=D27,"pass",IF(Inputs!$C$17>C27,"miss","not yet"))) | H27: Fewer than 5 offices: change the cluster or office size band, not the model.
A28: Gate 0 | B28: Brand conversations held (context) | C28: =Inputs!$C$11 | D28: =Inputs!$C$115 | F28: =Pipeline!$U$7 | G28: info
A29: Gate 0 | B29: Brands that would pay $500 or more and control the budget | C29: =Inputs!$C$11 | D29: =Inputs!$C$113 | F29: =Pipeline!$U$8 | G29: =IF(F29="",IF(Inputs!$C$17>C29,"miss","not yet"),IF(F29>=D29,"pass",IF(Inputs!$C$17>C29,"miss","not yet"))) | H29: Fewer than 3: test the office-paid version for three more weeks before deciding.
A30: Gate 1 | B30: Offices signed | C30: =Inputs!$C$12 | D30: =Inputs!$C$116 | E30: =Drop_PnL!E7 | F30: =Pipeline!$U$9 | G30: =IF(F30="",IF(Inputs!$C$17>C30,"miss","not yet"),IF(F30>=D30,"pass",IF(Inputs!$C$17>C30,"miss","not yet"))) | H30: Offices sign but no brand pays even $600: pivot to office-paid or stop. No free campaign.
A31: Gate 1 | B31: Combined Tuesday headcount of signed offices | C31: =Inputs!$C$12 | D31: =Inputs!$C$117 | F31: =Pipeline!$U$10 | G31: =IF(F31="",IF(Inputs!$C$17>C31,"miss","not yet"),IF(F31>=D31,"pass",IF(Inputs!$C$17>C31,"miss","not yet")))
A32: Gate 1 | B32: Brands paid in full | C32: =Inputs!$C$12 | D32: =Inputs!$C$118 | E32: =Drop_PnL!G7 | F32: =Pipeline!$U$11 | G32: =IF(F32="",IF(Inputs!$C$17>C32,"miss","not yet"),IF(F32>=D32,"pass",IF(Inputs!$C$17>C32,"miss","not yet"))) | H32: One paid brand is a soft pass: run it, make the second sale first.
A33: Gate 2 | B33: Units placed within one business day (share of delivered) | C33: =Inputs!$C$13 | D33: =Inputs!$C$120 | F33: =IFERROR(INDEX(Drop_Actuals!$AG$7:$AG$18,MATCH(Inputs!$C$119,Drop_Actuals!$A$7:$A$18,0)),"") | G33: =IF(F33="",IF(Inputs!$C$17>C33,"miss","not yet"),IF(F33>=D33,"pass",IF(Inputs!$C$17>C33,"miss","not yet"))) | H33: Fix the procedure once (card, handoff, Slack post). A second miss is a stop signal.
A34: Gate 2 | B34: Brand campaigns under 5 survey responses per office (must be 0) | C34: =Inputs!$C$13 | D34: 0 | F34: =IF(N(IFERROR(INDEX(Drop_Actuals!$AF$7:$AF$18,MATCH(Inputs!$C$119,Drop_Actuals!$A$7:$A$18,0)),""))=0,"",IFERROR(INDEX(Drop_Actuals!$AH$7:$AH$18,MATCH(Inputs!$C$119,Drop_Actuals!$A$7:$A$18,0)),"")) | G34: =IF(F34="",IF(Inputs!$C$17>C34,"miss","not yet"),IF(F34<=D34,"pass",IF(Inputs!$C$17>C34,"miss","not yet")))
A35: Gate 2 | B35: Reports late (after T+7) or missing (must be 0) | C35: =Inputs!$C$13 | D35: 0 | F35: =IF(N(IFERROR(INDEX(Drop_Actuals!$AF$7:$AF$18,MATCH(Inputs!$C$119,Drop_Actuals!$A$7:$A$18,0)),""))=0,"",IFERROR(INDEX(Drop_Actuals!$AI$7:$AI$18,MATCH(Inputs!$C$119,Drop_Actuals!$A$7:$A$18,0)),"")) | G35: =IF(F35="",IF(Inputs!$C$17>C35,"miss","not yet"),IF(F35<=D35,"pass",IF(Inputs!$C$17>C35,"miss","not yet")))
A36: Gate 2 | B36: Brands that would buy again | C36: =Inputs!$C$13 | D36: =Inputs!$C$123 | F36: =IF(N(IFERROR(INDEX(Drop_Actuals!$AF$7:$AF$18,MATCH(Inputs!$C$119,Drop_Actuals!$A$7:$A$18,0)),""))=0,"",IFERROR(INDEX(Drop_Actuals!$AJ$7:$AJ$18,MATCH(Inputs!$C$119,Drop_Actuals!$A$7:$A$18,0)),"")) | G36: =IF(F36="",IF(Inputs!$C$17>C36,"miss","not yet"),IF(F36>=D36,"pass",IF(Inputs!$C$17>C36,"miss","not yet")))
A37: Gate 3 | B37: Renewals at $1,500 or more, signed by the review date | C37: =Inputs!$C$14 | D37: =Inputs!$C$124 | E37: =SUMIFS(Drop_PnL!$H$7:$H$18,Drop_PnL!$AQ$7:$AQ$18,"<="&Inputs!$C$14)-SUMIFS(Drop_PnL!$I$7:$I$18,Drop_PnL!$AQ$7:$AQ$18,"<="&Inputs!$C$14) | F37: =Pipeline!$U$12 | G37: =IF(F37="",IF(Inputs!$C$17>C37,"miss","not yet"),IF(F37>=D37,"pass",IF(Inputs!$C$17>C37,"miss","not yet"))) | H37: No renewal: redesign the evidence (velocity, redemptions), run one more drop. A second miss is a stop.
A38: Gate 3 | B38: Contribution per founder hour, standard runs | C38: =Inputs!$C$14 | D38: =Inputs!$C$126 | E38: =IF(SUMIFS(Drop_PnL!$AI$7:$AI$18,Drop_PnL!$D$7:$D$18,"standard",Drop_PnL!$B$7:$B$18,"<="&Inputs!$C$14)>0,SUMIFS(Drop_PnL!$AJ$7:$AJ$18,Drop_PnL!$D$7:$D$18,"standard",Drop_PnL!$B$7:$B$18,"<="&Inputs!$C$14)/SUMIFS(Drop_PnL!$AI$7:$AI$18,Drop_PnL!$D$7:$D$18,"standard",Drop_PnL!$B$7:$B$18,"<="&Inputs!$C$14),"") | F38: =IF(SUMIFS(Drop_Actuals!$R$7:$R$18,Drop_PnL!$D$7:$D$18,"standard",Drop_PnL!$B$7:$B$18,"<="&Inputs!$C$14,Drop_PnL!$AZ$7:$AZ$18,"Y")>0,SUMIFS(Drop_Actuals!$S$7:$S$18,Drop_PnL!$D$7:$D$18,"standard",Drop_PnL!$B$7:$B$18,"<="&Inputs!$C$14,Drop_PnL!$AZ$7:$AZ$18,"Y")/SUMIFS(Drop_Actuals!$R$7:$R$18,Drop_PnL!$D$7:$D$18,"standard",Drop_PnL!$B$7:$B$18,"<="&Inputs!$C$14,Drop_PnL!$AZ$7:$AZ$18,"Y"),"") | G38: =IF(F38="",IF(Inputs!$C$17>C38,"miss","not yet"),IF(F38>=D38,"pass",IF(Inputs!$C$17>C38,"miss","not yet")))
A40: Gate | B40: Review date | C40: Overall
A41: Gate 0 | B41: =C26 | C41: =IF(IF(G27="miss",1,0)+IF(G29="miss",1,0)>0,"miss",IF(IF(G27="not yet",1,0)+IF(G29="not yet",1,0)>0,"not yet","pass"))
A42: Gate 1 | B42: =C30 | C42: =IF(IF(G30="miss",1,0)+IF(G31="miss",1,0)+IF(G32="miss",1,0)>0,"miss",IF(IF(G30="not yet",1,0)+IF(G31="not yet",1,0)+IF(G32="not yet",1,0)>0,"not yet","pass"))
A43: Gate 2 | B43: =C33 | C43: =IF(IF(G33="miss",1,0)+IF(G34="miss",1,0)+IF(G35="miss",1,0)+IF(G36="miss",1,0)>0,"miss",IF(IF(G33="not yet",1,0)+IF(G34="not yet",1,0)+IF(G35="not yet",1,0)+IF(G36="not yet",1,0)>0,"not yet","pass"))
A44: Gate 3 | B44: =C37 | C44: =IF(IF(G37="miss",1,0)+IF(G38="miss",1,0)>0,"miss",IF(IF(G37="not yet",1,0)+IF(G38="not yet",1,0)>0,"not yet","pass"))
A46: Decision rule (plan): scale, switch to office-paid, or stop
B47: Brand renewal rate (renewed Y / answered Y or N) | C47: =IF(COUNTIF(Actuals_Campaigns!$W$5:$W$204,"Y")+COUNTIF(Actuals_Campaigns!$W$5:$W$204,"N")=0,"",COUNTIF(Actuals_Campaigns!$W$5:$W$204,"Y")/(COUNTIF(Actuals_Campaigns!$W$5:$W$204,"Y")+COUNTIF(Actuals_Campaigns!$W$5:$W$204,"N")))
B48: Offices that named $100 a month or more | C48: =Pipeline!$U$13
B49: Drops after Gate 3 with actuals in | C49: =COUNTIFS(Drop_PnL!$B$7:$B$18,">"&Inputs!$C$14,Drop_PnL!$AZ$7:$AZ$18,"Y",Drop_PnL!$N$7:$N$18,1)
B50: Gate 3 | C50: =Dashboard!$C$44
B51: The rule says | C51: =IF(C47="","not yet: no renewal answers",IF(AND(C50="pass",C47>=Inputs!$C$127),"Scale",IF(AND(C48>=Inputs!$C$128,C47<Inputs!$C$130,C49>=Inputs!$C$131),"Switch to office-paid",IF(AND(C47>=Inputs!$C$130,C47<Inputs!$C$127),"Rule silent: renewal between "&TEXT(Inputs!$C$130,"0%")&" and "&TEXT(Inputs!$C$127,"0%"),IF(Inputs!$C$17>Inputs!$C$15,"Stop","not yet: stop if nothing changes by the decision date")))))
B52: Stated once (plan) | C52: Scale if Gate 3 passed and renewal is 40% or more. Switch to office-paid if at least five offices named $100 a month or more and brand renewal is under 30% after two extra drops. Stop if both fail.
B54: Placement within one business day, all drops with actuals | C54: =IF(SUMIFS(Drop_Actuals!$V$7:$V$18,Drop_PnL!$AZ$7:$AZ$18,"Y")=0,"",SUMIFS(Drop_Actuals!$X$7:$X$18,Drop_PnL!$AZ$7:$AZ$18,"Y")/SUMIFS(Drop_Actuals!$V$7:$V$18,Drop_PnL!$AZ$7:$AZ$18,"Y"))
B55: Drops with actuals below the placement threshold | C55: =COUNTIFS(Drop_PnL!$AZ$7:$AZ$18,"Y",Drop_Actuals!$AG$7:$AG$18,"<"&Inputs!$C$120)
B56: Contribution per founder hour, all drops with actuals | C56: =IF(SUMIFS(Drop_Actuals!$R$7:$R$18,Drop_PnL!$AZ$7:$AZ$18,"Y")>0,SUMIFS(Drop_Actuals!$S$7:$S$18,Drop_PnL!$AZ$7:$AZ$18,"Y")/SUMIFS(Drop_Actuals!$R$7:$R$18,Drop_PnL!$AZ$7:$AZ$18,"Y"),"")
B57: Scenario the real numbers point to | C57: =IF(C54="","not enough data yet",IF(AND(C47<>"",N(C47)=0,C54<Inputs!$C$120),"D: neither converts",IF(C55>=Inputs!$C$132,"C: brands willing, offices unreliable",IF(AND(C47<>"",N(C47)<Inputs!$C$130),"B: brands pay once, offices love it",IF(AND(C47<>"",N(C47)>=Inputs!$C$127,C54>=Inputs!$C$120,N(C56)>=Inputs!$C$126),"A: both sides work","between scenarios: see the rule")))))
A60: Six-month goals (plan): planned by the schedule against actual
B61: Goal | C61: Target | D61: Planned (Schedule) | E61: Actual | F61: Status
B62: Paid campaigns | C62: =Inputs!$C$133 | D62: =SUMIFS(Drop_PnL!$G$7:$G$18,Drop_PnL!$B$7:$B$18,"<="&Cash_Flow!$AB$6) | E62: =COUNTIF(Actuals_Campaigns!$R$5:$R$204,">0") | F62: =IF(E62="",IF(Inputs!$C$17>Inputs!$C$15,"miss","not yet"),IF(E62>=C62,"pass",IF(Inputs!$C$17>Inputs!$C$15,"miss","not yet")))
B63: Renewals | C63: =Inputs!$C$134 | D63: =SUMIFS(Drop_PnL!$H$7:$H$18,Drop_PnL!$B$7:$B$18,"<="&Cash_Flow!$AB$6) | E63: =COUNTIF(Actuals_Campaigns!$W$5:$W$204,"Y") | F63: =IF(E63="",IF(Inputs!$C$17>Inputs!$C$15,"miss","not yet"),IF(E63>=C63,"pass",IF(Inputs!$C$17>Inputs!$C$15,"miss","not yet")))
B64: Active offices | C64: =Inputs!$C$135 | D64: =SUMIFS(Drop_PnL!$F$7:$F$18,Drop_PnL!$B$7:$B$18,"<="&Cash_Flow!$AB$6) | E64: =Pipeline!$U$22 | F64: =IF(E64="",IF(Inputs!$C$17>Inputs!$C$15,"miss","not yet"),IF(E64>=C64,"pass",IF(Inputs!$C$17>Inputs!$C$15,"miss","not yet")))
B65: Contribution per founder hour, standard runs | C65: =Inputs!$C$126 | D65: =E38 | E65: =F38 | F65: =IF(E65="",IF(Inputs!$C$17>Inputs!$C$15,"miss","not yet"),IF(E65>=C65,"pass",IF(Inputs!$C$17>Inputs!$C$15,"miss","not yet")))
A68: Contribution per founder hour on each drop (live: actual where in, otherwise plan) | K68: Target per hour | L68: =Inputs!$C$126
A69: drop_id | B69: Label | C69: Drop date | D69: Basis | E69: Delivery model | F69: Brands | G69: Offices | H69: Revenue | I69: Hard costs | J69: Founder hours | K69: Contribution | L69: Per founder hour
A70: =Drop_PnL!A7 | B70: =IF(Drop_PnL!B7="","",Schedule!B7&"") | C70: =IF(Drop_PnL!B7="","",Drop_PnL!B7) | D70: =Drop_PnL!BF7 | E70: =IF(Drop_PnL!B7="","",Drop_PnL!C7) | F70: =IF(Drop_PnL!B7="","",Drop_PnL!G7) | G70: =IF(Drop_PnL!B7="","",Drop_PnL!E7) | H70: =IF(Drop_PnL!B7="","",Drop_PnL!BA7) | I70: =IF(Drop_PnL!B7="","",Drop_PnL!BB7) | J70: =IF(Drop_PnL!B7="","",Drop_PnL!BC7) | K70: =IF(Drop_PnL!B7="","",Drop_PnL!BD7) | L70: =IF(Drop_PnL!B7="","",Drop_PnL!BE7)
A71: =Drop_PnL!A8 | B71: =IF(Drop_PnL!B8="","",Schedule!B8&"") | C71: =IF(Drop_PnL!B8="","",Drop_PnL!B8) | D71: =Drop_PnL!BF8 | E71: =IF(Drop_PnL!B8="","",Drop_PnL!C8) | F71: =IF(Drop_PnL!B8="","",Drop_PnL!G8) | G71: =IF(Drop_PnL!B8="","",Drop_PnL!E8) | H71: =IF(Drop_PnL!B8="","",Drop_PnL!BA8) | I71: =IF(Drop_PnL!B8="","",Drop_PnL!BB8) | J71: =IF(Drop_PnL!B8="","",Drop_PnL!BC8) | K71: =IF(Drop_PnL!B8="","",Drop_PnL!BD8) | L71: =IF(Drop_PnL!B8="","",Drop_PnL!BE8)
A72: =Drop_PnL!A9 | B72: =IF(Drop_PnL!B9="","",Schedule!B9&"") | C72: =IF(Drop_PnL!B9="","",Drop_PnL!B9) | D72: =Drop_PnL!BF9 | E72: =IF(Drop_PnL!B9="","",Drop_PnL!C9) | F72: =IF(Drop_PnL!B9="","",Drop_PnL!G9) | G72: =IF(Drop_PnL!B9="","",Drop_PnL!E9) | H72: =IF(Drop_PnL!B9="","",Drop_PnL!BA9) | I72: =IF(Drop_PnL!B9="","",Drop_PnL!BB9) | J72: =IF(Drop_PnL!B9="","",Drop_PnL!BC9) | K72: =IF(Drop_PnL!B9="","",Drop_PnL!BD9) | L72: =IF(Drop_PnL!B9="","",Drop_PnL!BE9)
A73: =Drop_PnL!A10 | B73: =IF(Drop_PnL!B10="","",Schedule!B10&"") | C73: =IF(Drop_PnL!B10="","",Drop_PnL!B10) | D73: =Drop_PnL!BF10 | E73: =IF(Drop_PnL!B10="","",Drop_PnL!C10) | F73: =IF(Drop_PnL!B10="","",Drop_PnL!G10) | G73: =IF(Drop_PnL!B10="","",Drop_PnL!E10) | H73: =IF(Drop_PnL!B10="","",Drop_PnL!BA10) | I73: =IF(Drop_PnL!B10="","",Drop_PnL!BB10) | J73: =IF(Drop_PnL!B10="","",Drop_PnL!BC10) | K73: =IF(Drop_PnL!B10="","",Drop_PnL!BD10) | L73: =IF(Drop_PnL!B10="","",Drop_PnL!BE10)
A74: =Drop_PnL!A11 | B74: =IF(Drop_PnL!B11="","",Schedule!B11&"") | C74: =IF(Drop_PnL!B11="","",Drop_PnL!B11) | D74: =Drop_PnL!BF11 | E74: =IF(Drop_PnL!B11="","",Drop_PnL!C11) | F74: =IF(Drop_PnL!B11="","",Drop_PnL!G11) | G74: =IF(Drop_PnL!B11="","",Drop_PnL!E11) | H74: =IF(Drop_PnL!B11="","",Drop_PnL!BA11) | I74: =IF(Drop_PnL!B11="","",Drop_PnL!BB11) | J74: =IF(Drop_PnL!B11="","",Drop_PnL!BC11) | K74: =IF(Drop_PnL!B11="","",Drop_PnL!BD11) | L74: =IF(Drop_PnL!B11="","",Drop_PnL!BE11)
A75: =Drop_PnL!A12 | B75: =IF(Drop_PnL!B12="","",Schedule!B12&"") | C75: =IF(Drop_PnL!B12="","",Drop_PnL!B12) | D75: =Drop_PnL!BF12 | E75: =IF(Drop_PnL!B12="","",Drop_PnL!C12) | F75: =IF(Drop_PnL!B12="","",Drop_PnL!G12) | G75: =IF(Drop_PnL!B12="","",Drop_PnL!E12) | H75: =IF(Drop_PnL!B12="","",Drop_PnL!BA12) | I75: =IF(Drop_PnL!B12="","",Drop_PnL!BB12) | J75: =IF(Drop_PnL!B12="","",Drop_PnL!BC12) | K75: =IF(Drop_PnL!B12="","",Drop_PnL!BD12) | L75: =IF(Drop_PnL!B12="","",Drop_PnL!BE12)
A76: =Drop_PnL!A13 | B76: =IF(Drop_PnL!B13="","",Schedule!B13&"") | C76: =IF(Drop_PnL!B13="","",Drop_PnL!B13) | D76: =Drop_PnL!BF13 | E76: =IF(Drop_PnL!B13="","",Drop_PnL!C13) | F76: =IF(Drop_PnL!B13="","",Drop_PnL!G13) | G76: =IF(Drop_PnL!B13="","",Drop_PnL!E13) | H76: =IF(Drop_PnL!B13="","",Drop_PnL!BA13) | I76: =IF(Drop_PnL!B13="","",Drop_PnL!BB13) | J76: =IF(Drop_PnL!B13="","",Drop_PnL!BC13) | K76: =IF(Drop_PnL!B13="","",Drop_PnL!BD13) | L76: =IF(Drop_PnL!B13="","",Drop_PnL!BE13)
A77: =Drop_PnL!A14 | B77: =IF(Drop_PnL!B14="","",Schedule!B14&"") | C77: =IF(Drop_PnL!B14="","",Drop_PnL!B14) | D77: =Drop_PnL!BF14 | E77: =IF(Drop_PnL!B14="","",Drop_PnL!C14) | F77: =IF(Drop_PnL!B14="","",Drop_PnL!G14) | G77: =IF(Drop_PnL!B14="","",Drop_PnL!E14) | H77: =IF(Drop_PnL!B14="","",Drop_PnL!BA14) | I77: =IF(Drop_PnL!B14="","",Drop_PnL!BB14) | J77: =IF(Drop_PnL!B14="","",Drop_PnL!BC14) | K77: =IF(Drop_PnL!B14="","",Drop_PnL!BD14) | L77: =IF(Drop_PnL!B14="","",Drop_PnL!BE14)
A78: =Drop_PnL!A15 | B78: =IF(Drop_PnL!B15="","",Schedule!B15&"") | C78: =IF(Drop_PnL!B15="","",Drop_PnL!B15) | D78: =Drop_PnL!BF15 | E78: =IF(Drop_PnL!B15="","",Drop_PnL!C15) | F78: =IF(Drop_PnL!B15="","",Drop_PnL!G15) | G78: =IF(Drop_PnL!B15="","",Drop_PnL!E15) | H78: =IF(Drop_PnL!B15="","",Drop_PnL!BA15) | I78: =IF(Drop_PnL!B15="","",Drop_PnL!BB15) | J78: =IF(Drop_PnL!B15="","",Drop_PnL!BC15) | K78: =IF(Drop_PnL!B15="","",Drop_PnL!BD15) | L78: =IF(Drop_PnL!B15="","",Drop_PnL!BE15)
A79: =Drop_PnL!A16 | B79: =IF(Drop_PnL!B16="","",Schedule!B16&"") | C79: =IF(Drop_PnL!B16="","",Drop_PnL!B16) | D79: =Drop_PnL!BF16 | E79: =IF(Drop_PnL!B16="","",Drop_PnL!C16) | F79: =IF(Drop_PnL!B16="","",Drop_PnL!G16) | G79: =IF(Drop_PnL!B16="","",Drop_PnL!E16) | H79: =IF(Drop_PnL!B16="","",Drop_PnL!BA16) | I79: =IF(Drop_PnL!B16="","",Drop_PnL!BB16) | J79: =IF(Drop_PnL!B16="","",Drop_PnL!BC16) | K79: =IF(Drop_PnL!B16="","",Drop_PnL!BD16) | L79: =IF(Drop_PnL!B16="","",Drop_PnL!BE16)
A80: =Drop_PnL!A17 | B80: =IF(Drop_PnL!B17="","",Schedule!B17&"") | C80: =IF(Drop_PnL!B17="","",Drop_PnL!B17) | D80: =Drop_PnL!BF17 | E80: =IF(Drop_PnL!B17="","",Drop_PnL!C17) | F80: =IF(Drop_PnL!B17="","",Drop_PnL!G17) | G80: =IF(Drop_PnL!B17="","",Drop_PnL!E17) | H80: =IF(Drop_PnL!B17="","",Drop_PnL!BA17) | I80: =IF(Drop_PnL!B17="","",Drop_PnL!BB17) | J80: =IF(Drop_PnL!B17="","",Drop_PnL!BC17) | K80: =IF(Drop_PnL!B17="","",Drop_PnL!BD17) | L80: =IF(Drop_PnL!B17="","",Drop_PnL!BE17)
A81: =Drop_PnL!A18 | B81: =IF(Drop_PnL!B18="","",Schedule!B18&"") | C81: =IF(Drop_PnL!B18="","",Drop_PnL!B18) | D81: =Drop_PnL!BF18 | E81: =IF(Drop_PnL!B18="","",Drop_PnL!C18) | F81: =IF(Drop_PnL!B18="","",Drop_PnL!G18) | G81: =IF(Drop_PnL!B18="","",Drop_PnL!E18) | H81: =IF(Drop_PnL!B18="","",Drop_PnL!BA18) | I81: =IF(Drop_PnL!B18="","",Drop_PnL!BB18) | J81: =IF(Drop_PnL!B18="","",Drop_PnL!BC18) | K81: =IF(Drop_PnL!B18="","",Drop_PnL!BD18) | L81: =IF(Drop_PnL!B18="","",Drop_PnL!BE18)
A82: Total | F82: =SUM(F70:F81) | G82: =SUM(G70:G81) | H82: =SUM(H70:H81) | I82: =SUM(I70:I81) | J82: =SUM(J70:J81) | K82: =SUM(K70:K81) | L82: =IF(J82>0,K82/J82,"n/a")
A84: Green: at or above the Gate 3 target per founder hour. Orange: below it. Campaign zero is expected to be below; the plan's own figure for it is $16. The total row is per founder hour across all scheduled drops, before overhead that drops do not absorb.

Sheet Inputs
A1: Inputs
A2: Every assumption in one labeled cell. Yellow cells are inputs. Grey cells are calculated; do not type over them.
A3: All defaults are planning estimates from plan.md, never forecasts. 'Plan default' keeps the original figure; 'Changed' flags any cell you edit.
A6: 1. Company and calendar
A7: key | B7: Assumption | C7: Value | D7: Unit | E7: Low | F7: High | G7: Status | H7: Source | I7: Notes | J7: Plan default | K7: Changed?
A8: company_name | B8: Company name (working name, not yet cleared) | C8: Desk Drop | D8: text | G8: working name | H8: Prompt; CONTRACTS s2 rename-ability | I8: The only cell that holds the company name. Rename here and every tab follows. | J8: Desk Drop | K8: =IF(C8&""=J8&"","","changed")
A9: tagline | B9: Tagline (working, may change) | C9: Emerging brands. Delivered to your workday. | D9: text | G9: working | H9: Prompt; CONTRACTS s2 | J9: Emerging brands. Delivered to your workday. | K9: =IF(C9&""=J9&"","","changed")
A10: week1_start | B10: Week 1 starts (Monday) | C10: 46321 | D10: date | G10: derived, founder to confirm | H10: CONTRACTS.md section 3 (canonical calendar) | I10: Week n starts on this date plus 7 x (n - 1) days. | J10: 46321 | K10: =IF(C10&""=J10&"","","changed")
A11: gate0_date | B11: Gate 0 review (end of week 3) | C11: 46339 | D11: date | G11: derived, founder to confirm | H11: CONTRACTS.md section 3 (canonical calendar) | J11: 46339 | K11: =IF(C11&""=J11&"","","changed")
A12: gate1_date | B12: Gate 1 review (end of week 7) | C12: 46367 | D12: date | G12: derived, founder to confirm | H12: CONTRACTS.md section 3 (canonical calendar) | J12: 46367 | K12: =IF(C12&""=J12&"","","changed")
A13: gate2_date | B13: Gate 2 review (campaign zero report, T+7) | C13: 46409 | D13: date | G13: derived, founder to confirm | H13: CONTRACTS.md section 3 (canonical calendar) | I13: Moved from the plan's week 9 because campaign zero moved to 2027-01-12 (December blackout collision). | J13: 46409 | K13: =IF(C13&""=J13&"","","changed")
A14: gate3_date | B14: Gate 3 review | C14: 46458 | D14: date | G14: derived, founder to confirm | H14: CONTRACTS.md section 3 (canonical calendar) | I14: Week 20; replaces the plan's week 16. | J14: 46458 | K14: =IF(C14&""=J14&"","","changed")
A15: decision_date | B15: Six-month decision (end of week 24) | C15: 46486 | D15: date | G15: derived, founder to confirm | H15: CONTRACTS.md section 3 (canonical calendar) | J15: 46486 | K15: =IF(C15&""=J15&"","","changed")
A16: as_of_override | B16: As-of date override (blank = today) | D16: date | G16: setting | H16: Model setting | I16: Leave blank to use today's date. Type a date to see gates and the next drop as of that day. | K16: =IF(C16&""=J16&"","","changed")
A17: as_of | B17: As-of date in use | C17: =IF(C16="",TODAY(),C16) | D17: date | G17: calculated | H17: Model
A18: days_per_week | B18: Days per week | C18: 7 | D18: days | G18: conversion | H18: Calendar | J18: 7 | K18: =IF(C18&""=J18&"","","changed")
A19: weeks_per_year | B19: Weeks per year | C19: 52 | D19: weeks | G19: conversion | H19: Calendar | J19: 52 | K19: =IF(C19&""=J19&"","","changed")
A20: months_per_year | B20: Months per year | C20: 12 | D20: months | G20: conversion | H20: Calendar | J20: 12 | K20: =IF(C20&""=J20&"","","changed")
A21: weeks_per_month | B21: Weeks per month | C21: =Inputs!$C$19/Inputs!$C$20 | D21: weeks | G21: calculated | H21: Weeks per year / months per year
A22: hours_per_day | B22: Hours per day (converts Toggl durations) | C22: 24 | D22: hours | G22: conversion | H22: Calendar | J22: 24 | K22: =IF(C22&""=J22&"","","changed")
A23: window_bd | B23: Campaign window | C23: 5 | D23: business days | G23: planning estimate | H23: plan.md, What brands buy: 'Five business days' | I23: T is day 1; the window closes at T+4. | J23: 5 | K23: =IF(C23&""=J23&"","","changed")
A24: drop_prefix | B24: Drop ID prefix | C24: DRP- | D24: text | G24: convention | H24: CONTRACTS s6.5 (DRP-###) | I24: Toggl projects named DRP-001 etc. map to drops. | J24: DRP- | K24: =IF(C24&""=J24&"","","changed")
A25: office_window_days | B25: An office should get at most one drop in this many days | C25: 28 | D25: days | G25: derived, founder to confirm | H25: plan.md, What has to be true #4: 'Offices accept one drop a month' | I25: Four weeks counts as monthly, so drops 28 days apart do not flag. Used for the office-fatigue warning on Schedule. | J25: 28 | K25: =IF(C25&""=J25&"","","changed")
A27: 2. Scenario in force
A28: key | B28: Assumption | C28: Value | D28: Unit | E28: Low | F28: High | G28: Status | H28: Source | I28: Notes | J28: Plan default | K28: Changed?
A29: active_scenario | B29: Scenario applied to drops after Gate 3 and to the steady state | C29: Plan base | D29: list | G29: setting | H29: plan.md, After the first standard runs: decision scenarios | I29: Plan base = the plan's 'What has to be true'. A to D = the plan's four decision situations. See the Scenarios tab. | J29: Plan base | K29: =IF(C29&""=J29&"","","changed")
A31: 3. Prices and payment terms
A32: key | B32: Assumption | C32: Value | D32: Unit | E32: Low | F32: High | G32: Status | H32: Source | I32: Notes | J32: Plan default | K32: Changed?
A33: price_std_office | B33: Standard price per office | C33: 150 | D33: USD per office | G33: planning estimate | H33: plan.md, Revised model: Price table | I33: $1,500 for 10 offices. Change this cell to test a price. | J33: 150 | K33: =IF(C33&""=J33&"","","changed")
A34: std_pkg_offices | B34: Standard package size | C34: 10 | D34: offices | G34: planning estimate | H34: plan.md, Revised model: Price table | J34: 10 | K34: =IF(C34&""=J34&"","","changed")
A35: std_pkg_price | B35: Standard package price | C35: =Inputs!$C$33*Inputs!$C$34 | D35: USD per brand | G35: calculated | H35: Price per office x package offices
A36: price_fnd_office | B36: Founding price per office | C36: 120 | D36: USD per office | E36: 120 | F36: 180 | G36: planning estimate | H36: plan.md, Revised model: Price table | I36: $600 for 5 offices. The plan's summary table once said $600 to $900; the decided price is $600 (low end shown as default). | J36: 120 | K36: =IF(C36&""=J36&"","","changed")
A37: fnd_pkg_offices | B37: Founding package size | C37: 5 | D37: offices | G37: planning estimate | H37: plan.md, Revised model: Price table | J37: 5 | K37: =IF(C37&""=J37&"","","changed")
A38: fnd_pkg_price | B38: Founding package price | C38: =Inputs!$C$36*Inputs!$C$37 | D38: USD per brand | G38: calculated | H38: Price per office x package offices
A39: extra_office_price | B39: Extra office beyond the package | C39: 150 | D39: USD per office | G39: planning estimate | H39: plan.md, Revised model: Price table | I39: Applies to offices beyond 5 (founding) or 10 (standard). Founding renewals stay at the founding rate per office for any office count. | J39: 150 | K39: =IF(C39&""=J39&"","","changed")
A40: founding_cap | B40: Founding tier closes after | C40: 3 | D40: brands | G40: planning estimate | H40: plan.md, Revised model: Price table | I40: 'First three brands only'. | J40: 3 | K40: =IF(C40&""=J40&"","","changed")
A41: founding_lock | B41: Founding price locked for | C41: 2 | D41: further campaigns | G41: planning estimate | H41: plan.md, Revised model: Price table | J41: 2 | K41: =IF(C41&""=J41&"","","changed")
A42: fnd_upfront_share | B42: Founding: share paid before product ships | C42: 1 | D42: share | G42: planning estimate | H42: plan.md, Revised model: Price table | I42: 'Paid in full before product ships'. | J42: 1 | K42: =IF(C42&""=J42&"","","changed")
A43: fnd_pay_lead_bd | B43: Founding: payment lands this many business days before the drop | C43: 20 | D43: business days | G43: derived, founder to confirm | H43: CONTRACTS.md section 3 (canonical calendar) | I43: Campaign zero's payment at Gate 1 (Fri 2026-12-11) is 20 business days before the Tue 2027-01-12 drop. | J43: 20 | K43: =IF(C43&""=J43&"","","changed")
A44: std_deposit_share | B44: Standard: share invoiced at signature | C44: 0.5 | D44: share | G44: planning estimate | H44: plan.md, Revised model: Price table | I44: 50% at signature, 50% at placement confirmation. | J44: 0.5 | K44: =IF(C44&""=J44&"","","changed")
A45: std_sign_lead_bd | B45: Standard: signature (deposit) this many business days before the drop | C45: 10 | D45: business days | G45: derived, founder to confirm | H45: plan.md, campaign calendar (brand ships at T-10) | I45: The latest signature that still lets the brand ship at T-10. Later cash is the conservative reading; the plan proposes drop dates three to four weeks out. | J45: 10 | K45: =IF(C45&""=J45&"","","changed")
A46: balance_lag_bd | B46: Standard: balance invoiced this many business days after the drop | C46: 1 | D46: business days | G46: derived, founder to confirm | H46: plan.md, What brands buy: placement within one business day | I46: Placement confirmation at T+1. | J46: 1 | K46: =IF(C46&""=J46&"","","changed")
A47: payment_lag_days | B47: Days from invoice to cash | D47: calendar days | G47: needs founder decision | H47: Not in the plan | I47: The plan states no invoice-to-cash lag. Blank = cash lands the day it is invoiced. Enter your invoice terms, for example 15. | K47: =IF(C47&""=J47&"","","changed")
A48: processing_rate | B48: Card processing rate | C48: 0.03 | D48: share of revenue | G48: planning estimate | H48: plan.md, Economics: hard-cost table | I48: Card fees. Zero by bank transfer. | J48: 0.03 | K48: =IF(C48&""=J48&"","","changed")
A49: processing_on | B49: Brands pay by card? 1 = yes, 0 = bank transfer | C49: 1 | D49: toggle | E49: 0 | F49: 1 | G49: setting | H49: plan.md, Economics: hard-cost table | I49: 1 is the high end of the plan's 0% to 3% range and matches its scenario rows. 0 is the plan's preferred invoicing (Wave, bank transfer). | J49: 1 | K49: =IF(C49&""=J49&"","","changed")
A51: 4. Units
A52: key | B52: Assumption | C52: Value | D52: Unit | E52: Low | F52: High | G52: Status | H52: Source | I52: Notes | J52: Plan default | K52: Changed?
A53: units_per_office | B53: Units per office per brand | C53: 50 | D53: units | G53: planning estimate | H53: plan.md, What brands buy | I53: Sized to Tuesday headcount (floor 30, ceiling 80). | J53: 50 | K53: =IF(C53&""=J53&"","","changed")
A54: reserve_share | B54: Reserve the brand ships on top | C54: 0.1 | D54: share | G54: planning estimate | H54: plan.md, What brands buy | J54: 0.1 | K54: =IF(C54&""=J54&"","","changed")
A56: 5. Hard costs and monthly overhead
A57: key | B57: Assumption | C57: Value | D57: Unit | E57: Low | F57: High | G57: Status | H57: Source | I57: Notes | J57: Plan default | K57: Changed?
A58: kit_per_office | B58: Display kit per office per drop (card, allergen line, case label) | C58: 8 | D58: USD per office per drop | G58: planning estimate | H58: plan.md, Economics: hard-cost table | I58: Plan reading (a): per office per drop, not per brand. Only this reproduces the scenario hard costs. | J58: 8 | K58: =IF(C58&""=J58&"","","changed")
A59: card_extra | B59: Extra tent card per additional brand per office | D59: USD per card | E59: 1 | F59: 2 | G59: needs founder decision | H59: plan.md, Hardware: tent cards roughly $1 to $2 each | I59: Reading (a) keeps one $8 kit per office even on a three-brand drop. If each brand needs its own card, enter $1 to $2. | K59: =IF(C59&""=J59&"","","changed")
A60: founder_transport | B60: Founder delivery (car rides) per drop | C60: 120 | D60: USD per drop | G60: planning estimate | H60: plan.md, Economics: hard-cost table | I60: 'You delivering costs about $120 in car rides.' | J60: 120 | K60: =IF(C60&""=J60&"","","changed")
A61: courier_per_stop | B61: Courier per stop | C61: 30 | D61: USD per stop | E61: 25 | F61: 40 | G61: planning estimate, needs quote | H61: plan.md, Economics: hard-cost table | I61: $300 for a ten-stop route is $30 a stop; plan range $25 to $40. No reliable published rate; get three quotes. | J61: 30 | K61: =IF(C61&""=J61&"","","changed")
A62: direct_transport | B62: Transport when brands ship direct | C62: 0 | D62: USD per drop | G62: planning estimate | H62: plan.md, scenario table, direct-ship row | I62: Plan reading (c): the $370 direct-ship row carries $0 transport. | J62: 0 | K62: =IF(C62&""=J62&"","","changed")
A63: kit_mail_per_office | B63: Mailing the display kit ahead (direct-ship) | D63: USD per office | G63: needs quote | H63: plan.md, Delivery by phase: '... mails the display kit ahead' | I63: The plan gives no figure. Blank counts as $0. | K63: =IF(C63&""=J63&"","","changed")
A64: kit_print_bd | B64: Kits printed this many business days before the drop | C64: 3 | D64: business days | G64: planning estimate | H64: plan.md, campaign calendar: T minus 3 | J64: 3 | K64: =IF(C64&""=J64&"","","changed")
A65: storage_choice | B65: Storage | C65: unit | D65: list | G65: setting | H65: plan.md, Economics: hard-cost table | I65: unit = small storage unit; home = sealed cases at home, $0. | J65: unit | K65: =IF(C65&""=J65&"","","changed")
A66: storage_monthly | B66: Storage unit per month | C66: 150 | D66: USD per month | G66: planning estimate | H66: plan.md, Economics: hard-cost table | I66: Allocation is half: $75 a drop at two drops a month. | J66: 150 | K66: =IF(C66&""=J66&"","","changed")
A67: storage_start | B67: Storage unit rented from | C67: 46419 | D67: date | G67: derived, founder to confirm | H67: Plan reading (b) | I67: First day of the first standard drop's month. Campaign zero stays at home, which is how its $280 reproduces. | J67: 46419 | K67: =IF(C67&""=J67&"","","changed")
A68: storage_end | B68: Storage unit released (blank = keep) | D68: date | G68: setting | H68: Plan reading (c) | I68: Blank keeps the unit through the window, as the plan's direct-ship row keeps the $75. | K68: =IF(C68&""=J68&"","","changed")
A69: software_monthly | B69: Software per month | C69: 60 | D69: USD per month | E69: 7 | F69: 81 | G69: planning estimate | H69: plan.md, Economics: Capital to the first six months; Tools table | I69: $360 for six months. Tools table sums to $7 to $81; the plan caps software under $60. | J69: 60 | K69: =IF(C69&""=J69&"","","changed")
A70: software_start | B70: Software paid from | C70: 46321 | D70: date | G70: derived, founder to confirm | H70: plan.md, Week 1 setup | J70: 46321 | K70: =IF(C70&""=J70&"","","changed")
A71: insurance_monthly | B71: General liability insurance per month | C71: 100 | D71: USD per month | E71: 41.666667 | F71: 125 | G71: planning estimate, needs quote | H71: plan.md, Economics: hard-cost table | I71: 'Roughly $100 a month'. Capital table range $500 to $1,500 a year, shown here per month. | J71: 100 | K71: =IF(C71&""=J71&"","","changed")
A72: insurance_billing | B72: Insurance billing | C72: annual | D72: list | G72: setting | H72: plan.md, Economics: Capital to the first six months | I72: annual = one year's premium paid at bind (capital table 'one year'). | J72: annual | K72: =IF(C72&""=J72&"","","changed")
A73: insurance_bind | B73: Insurance bound on | C73: 46367 | D73: date | G73: derived, founder to confirm | H73: plan.md, setup checklist: 'At Gate 1 pass: Insurance bound' | J73: 46367 | K73: =IF(C73&""=J73&"","","changed")
A74: phone_monthly | B74: Phone per month | C74: 0 | D74: USD per month | G74: planning estimate | H74: plan.md, Tools: 'Your phone', Google Voice $0 | J74: 0 | K74: =IF(C74&""=J74&"","","changed")
A75: alloc_drops_month | B75: Drops per month used to allocate overhead to a drop | C75: 2 | D75: drops per month | G75: planning estimate | H75: plan.md, Economics: hard-cost table | I75: Insurance $100 a month over two drops = $50; software $60 = $30; storage $150 = $75. | J75: 2 | K75: =IF(C75&""=J75&"","","changed")
A77: 6. Founder hours (rates; the plan's table is reproduced on Plan_Check)
A78: key | B78: Assumption | C78: Value | D78: Unit | E78: Low | F78: High | G78: Status | H78: Source | I78: Notes | J78: Plan default | K78: Changed?
A79: h_first_brand | B79: Brand sales per first (founding) brand | C79: 10 | D79: hours per brand | G79: planning estimate | H79: plan.md, Economics: founder-hour table | I79: '20 (10 per brand, first ones)'. | J79: 10 | K79: =IF(C79&""=J79&"","","changed")
A80: close_rate | B80: Close rate on qualified brand conversations | C80: 0.2 | D80: share | G80: planning estimate | H80: plan.md, What has to be true #2 | I80: One close from five. | J80: 0.2 | K80: =IF(C80&""=J80&"","","changed")
A81: h_per_conv | B81: Hours per qualified conversation | C81: 0.75 | D81: hours | G81: planning estimate | H81: plan.md, Economics: 'conversations of 45 minutes' | J81: 0.75 | K81: =IF(C81&""=J81&"","","changed")
A82: h_paperwork | B82: Proposal and paperwork per win | C82: 2.25 | D82: hours | G82: derived, founder to confirm | H82: plan.md, Economics: founder-hour table | I82: 6 - 5 x 0.75, so the plan's six hours per win reproduces at a 20% close rate. | J82: 2.25 | K82: =IF(C82&""=J82&"","","changed")
A83: h_win | B83: Brand sales per standard win | C83: =1/Inputs!$C$80*Inputs!$C$81+Inputs!$C$82 | D83: hours per brand | G83: calculated | H83: Conversations per win x hours each + paperwork | I83: 6.0 at plan inputs. Falls as the close rate rises.
A84: h_renewal | B84: Brand sales per renewal | C84: 2 | D84: hours per renewal | G84: planning estimate | H84: plan.md, Economics: 'A renewal takes about two hours' | J84: 2 | K84: =IF(C84&""=J84&"","","changed")
A85: h_new_office | B85: Office recruiting per new office | C85: 4 | D85: hours per office | G85: planning estimate | H85: plan.md, Economics: founder-hour table | I85: '20 (4 per new office)'. | J85: 4 | K85: =IF(C85&""=J85&"","","changed")
A86: h_existing_office | B86: Office coordination per existing office | C86: 1 | D86: hours per office | G86: planning estimate | H86: plan.md, Economics: founder-hour table | I86: '10 (1 per existing office)'. | J86: 1 | K86: =IF(C86&""=J86&"","","changed")
A87: rk_per_brand | B87: Receiving and kitting per brand | C87: 0.5 | D87: hours per brand | G87: derived, founder to confirm | H87: plan.md, Economics: founder-hour table | I87: (4 - 3) / (3 - 1): 1-brand drop 3 h, 3-brand drop 4 h. | J87: 0.5 | K87: =IF(C87&""=J87&"","","changed")
A88: rep_per_brand | B88: Reporting and debriefs per brand | C88: 2 | D88: hours per brand | G88: planning estimate | H88: plan.md, Economics: founder-hour table | I88: '6 (2 per brand)'. | J88: 2 | K88: =IF(C88&""=J88&"","","changed")
A89: admin_per_drop | B89: Admin and invoicing per drop | C89: 2 | D89: hours per drop | G89: planning estimate | H89: plan.md, Economics: founder-hour table | J89: 2 | K89: =IF(C89&""=J89&"","","changed")
A90: discovery_hours_week | B90: Discovery hours per week, weeks 1 to 3 (not tied to a drop) | C90: 15 | D90: hours per week | E90: 10 | F90: 15 | G90: planning estimate | H90: plan.md, Time budget: 'Phases 0 and 1 need 10 to 15 hours a week' | I90: High end. Weeks 4 to 7 selling and recruiting already sit in campaign zero's 57 hours. Used only in the six-month all-in view. | J90: 15 | K90: =IF(C90&""=J90&"","","changed")
A91: discovery_weeks | B91: Discovery weeks | C91: 3 | D91: weeks | G91: planning estimate | H91: plan.md, Phase 0 (weeks 1 to 3) | J91: 3 | K91: =IF(C91&""=J91&"","","changed")
A93: 7. Costs and hours that depend on the delivery model
A94: key | B94: Delivery model | C94: Transport per drop (USD) | D94: Transport per stop (USD) | E94: Kit mailing per office (USD) | F94: Receiving and kitting base (h) | G94: Drop day per office (h) | H94: Checks and pickup per office (h) | I94: Derivation from the plan's hour table
A95: model_table | B95: founder | C95: =Inputs!$C$60 | D95: 0 | E95: 0 | F95: 2 | G95: 1 | H95: 0.6 | I95: Campaign zero column (2 brands, 5 offices): receiving 3 = 2.0 + 0.5 x 2; drop day 5 h / 5 offices; checks 3 h / 5 offices.
A96: model_table | B96: courier | C96: 0 | D96: =Inputs!$C$61 | E96: 0 | F96: 2.5 | G96: 0.8 | H96: 0.4 | I96: 1-brand and 3-brand columns (10 offices): receiving 3 = 2.5 + 0.5 x 1 and 4 = 2.5 + 0.5 x 3; drop day 8 h / 10; checks 4 h / 10.
A97: model_table | B97: direct-ship | C97: =Inputs!$C$62 | D97: 0 | E97: =Inputs!$C$63 | F97: 0.5 | G97: 0.3 | H97: 0.4 | I97: Direct-ship column (3 brands, 10 offices): receiving 2 = 0.5 + 0.5 x 3; drop day 3 h / 10; checks 4 h / 10.
A99: 8. Renewal, steady state and founder capital
A100: key | B100: Assumption | C100: Value | D100: Unit | E100: Low | F100: High | G100: Status | H100: Source | I100: Notes | J100: Plan default | K100: Changed?
A101: renewal_rate_base | B101: Brands that renew within 90 days | C101: 0.4 | D101: share | G101: planning estimate | H101: plan.md, What has to be true #3 | I101: Used by the 'Plan base' scenario. Renewals cost 2 hours instead of 6, which is why they matter more than price. | J101: 0.4 | K101: =IF(C101&""=J101&"","","changed")
A102: plan_ss_drops | B102: Drops per month in the plan's monthly picture | C102: 2 | D102: drops per month | G102: planning estimate | H102: plan.md, Monthly picture at steady state | J102: 2 | K102: =IF(C102&""=J102&"","","changed")
A103: ss_model | B103: Steady-state delivery model | C103: courier | D103: list | G103: setting | H103: Plan reading (e) | I103: The plan's monthly picture is two three-brand courier drops. Direct-ship lifts contribution per hour. | J103: courier | K103: =IF(C103&""=J103&"","","changed")
A104: ss_offices | B104: Steady-state offices per drop | C104: 10 | D104: offices | G104: planning estimate | H104: plan.md, Monthly picture at steady state | J104: 10 | K104: =IF(C104&""=J104&"","","changed")
A105: founder_cash | B105: Cash the founder commits to the first six months | D105: USD | G105: needs founder decision | H105: plan.md, What I need from you #7 | I105: Blank until you decide. The plan's range is $3,360 to $6,510. | K105: =IF(C105&""=J105&"","","changed")
A106: founder_cash_date | B106: Founder cash goes in on | C106: 46321 | D106: date | G106: setting | H106: Model setting | J106: 46321 | K106: =IF(C106&""=J106&"","","changed")
A107: reserve_usd | B107: Reserve held back (not spent) | C107: 1000 | D107: USD | G107: planning estimate | H107: plan.md, Economics: Capital to the first six months | J107: 1000 | K107: =IF(C107&""=J107&"","","changed")
A109: 9. Gate thresholds, decision rule and six-month goals
A110: key | B110: Assumption | C110: Value | D110: Unit | E110: Low | F110: High | G110: Status | H110: Source | I110: Notes | J110: Plan default | K110: Changed?
...

Sheet Scenarios
A1: Scenarios A to D
A2: The plan's four decision situations as assumption sets. Pick one on Inputs ('Scenario in force'). The Active column feeds drops after Gate 3 and the steady state.
A3: Planning estimates. Where a scenario does not name a figure, it uses the plan base and says so. Nothing here is a forecast of which scenario will happen.
B5: Lever | C5: Plan base | D5: A | E5: B | F5: C | G5: D | H5: Active (in force) | I5: Unit | J5: Source and reading | L5: default: Plan base | M5: default: A | N5: default: B | O5: default: C | P5: default: D | Q5: Changed?
B6: Situation | C6: What has to be true | D6: Both sides work | E6: Brands pay once, offices love it | F6: Brands willing, offices unreliable | G6: Neither converts
B7: What the numbers show | C7: Three brands per drop, six hours or less per win, 40% renew, $1,500 holds | D7: 40% or more of brands renew; placement above 80%; contribution above $50 an hour | E7: Renewal under 30%; offices asking when the next drop is | F7: Placement under 80% twice; photos missing; responses under five | G7: No renewal, weak placement
B8: What to do next (plan) | C8: Run the plan | D8: Scale: second cluster, roster 20 to 30, price to $1,800 to $2,000, part-time delivery at about $25 an hour above two drops a month, launch-partner tier | E8: Fix the evidence, run two more drops; if renewal is still under 30%, switch to office-paid for offices that named $100 a month or more | F8: Replace the weakest offices, raise the commitment bar; if a third drop misses, stop | G8: Stop; write the post-mortem; keep office relationships warm
B10: Post-Gate-3 drops that run in the six months (of the two scheduled) | C10: 2 | D10: 2 | E10: 2 | F10: 1 | G10: 0 | H10: =INDEX(C10:G10,MATCH(Inputs!$C$29,$C$5:$G$5,0)) | I10: drops | J10: Base and A: two drops a month. B: 'run two more drops'. C: 'if a third drop misses, stop', so one more. D: 'Stop'. | L10: 2 | M10: 2 | N10: 2 | O10: 1 | P10: 0 | Q10: =IF(AND(C10&""=L10&"",D10&""=M10&"",E10&""=N10&"",F10&""=O10&"",G10&""=P10&""),"","changed")
B11: Brands per drop after Gate 3 | C11: 3 | D11: 3 | E11: 3 | F11: 3 | G11: 0 | H11: =INDEX(C11:G11,MATCH(Inputs!$C$29,$C$5:$G$5,0)) | I11: brands | J11: Plan: three brands per drop. D stops. | L11: 3 | M11: 3 | N11: 3 | O11: 3 | P11: 0 | Q11: =IF(AND(C11&""=L11&"",D11&""=M11&"",E11&""=N11&"",F11&""=O11&"",G11&""=P11&""),"","changed")
B12: Renewal rate (share of brand slots that are renewals) | C12: =Inputs!$C$101 | D12: 0.4 | E12: 0 | F12: =C12 | G12: 0 | H12: =INDEX(C12:G12,MATCH(Inputs!$C$29,$C$5:$G$5,0)) | I12: share | J12: A: '40% or more', low end. B: 'under 30%' and 'brands pay once': 0%, the low end of 0% to 29%. C: not named, plan base. D: 'No renewal'. | L12: =Inputs!$C$101 | M12: 0.4 | N12: 0 | O12: =C12 | P12: 0 | Q12: =IF(AND(C12&""=L12&"",D12&""=M12&"",E12&""=N12&"",F12&""=O12&"",G12&""=P12&""),"","changed")
B13: New offices recruited per post-Gate-3 drop | C13: 0 | D13: 0 | E13: 0 | G13: 0 | H13: =INDEX(C13:G13,MATCH(Inputs!$C$29,$C$5:$G$5,0)) | I13: offices | J13: C: 'replace the weakest offices'; the plan gives no count. Blank = 0; founder to set. | L13: 0 | M13: 0 | N13: 0 | P13: 0 | Q13: =IF(AND(C13&""=L13&"",D13&""=M13&"",E13&""=N13&"",F13&""=O13&"",G13&""=P13&""),"","changed")
B14: Standard price per office for drops after the decision date | C14: =Inputs!$C$33 | D14: 180 | E14: =Inputs!$C$33 | F14: =Inputs!$C$33 | G14: =Inputs!$C$33 | H14: =INDEX(C14:G14,MATCH(Inputs!$C$29,$C$5:$G$5,0)) | I14: USD per office | J14: A: 'raise the standard price to $1,800 to $2,000' = $180 to $200 per office; low end. | L14: =Inputs!$C$33 | M14: 180 | N14: =Inputs!$C$33 | O14: =Inputs!$C$33 | P14: =Inputs!$C$33 | Q14: =IF(AND(C14&""=L14&"",D14&""=M14&"",E14&""=N14&"",F14&""=O14&"",G14&""=P14&""),"","changed")
B15: Steady-state drops per month | C15: =Inputs!$C$102 | D15: 2 | E15: 2 | F15: 2 | G15: 0 | H15: =INDEX(C15:G15,MATCH(Inputs!$C$29,$C$5:$G$5,0)) | I15: drops per month | J15: Plan monthly picture: two drops a month. | L15: =Inputs!$C$102 | M15: 2 | N15: 2 | O15: 2 | P15: 0 | Q15: =IF(AND(C15&""=L15&"",D15&""=M15&"",E15&""=N15&"",F15&""=O15&"",G15&""=P15&""),"","changed")
B16: Steady-state brands per drop | C16: 3 | D16: 3 | E16: 3 | F16: 3 | G16: 0 | H16: =INDEX(C16:G16,MATCH(Inputs!$C$29,$C$5:$G$5,0)) | I16: brands | J16: Plan monthly picture: three-brand drops. | L16: 3 | M16: 3 | N16: 3 | O16: 3 | P16: 0 | Q16: =IF(AND(C16&""=L16&"",D16&""=M16&"",E16&""=N16&"",F16&""=O16&"",G16&""=P16&""),"","changed")
B17: Offices on an office-paid tier (steady state) | C17: 0 | D17: 0 | E17: 5 | F17: 0 | G17: 0 | H17: =INDEX(C17:G17,MATCH(Inputs!$C$29,$C$5:$G$5,0)) | I17: offices | J17: B: offices that named $100 a month or more; at least five. | L17: 0 | M17: 0 | N17: 5 | O17: 0 | P17: 0 | Q17: =IF(AND(C17&""=L17&"",D17&""=M17&"",E17&""=N17&"",F17&""=O17&"",G17&""=P17&""),"","changed")
B18: Office-paid fee per office per month | E18: 100 | H18: =INDEX(C18:G18,MATCH(Inputs!$C$29,$C$5:$G$5,0)) | I18: USD per month | J18: B: $100 to $200 a month; low end. | N18: 100 | Q18: =IF(AND(C18&""=L18&"",D18&""=M18&"",E18&""=N18&"",F18&""=O18&"",G18&""=P18&""),"","changed")
B19: Cost to serve one office-paid office per month | H19: =INDEX(C19:G19,MATCH(Inputs!$C$29,$C$5:$G$5,0)) | I19: USD per month | J19: Needs quote. The plan prices no cost for guaranteed twice-monthly curated drops. | Q19: =IF(AND(C19&""=L19&"",D19&""=M19&"",E19&""=N19&"",F19&""=O19&"",G19&""=P19&""),"","changed")
B20: Part-time delivery hire | C20: 25 | D20: 25 | H20: =INDEX(C20:G20,MATCH(Inputs!$C$29,$C$5:$G$5,0)) | I20: USD per hour | J20: A: 'about $25 an hour once you run more than two drops a month'. It replaces drop-day hours (model reading). | L20: 25 | M20: 25 | Q20: =IF(AND(C20&""=L20&"",D20&""=M20&"",E20&""=N20&"",F20&""=O20&"",G20&""=P20&""),"","changed")
B21: Hire once steady-state drops per month exceed | C21: 2 | D21: 2 | E21: 2 | F21: 2 | G21: 2 | H21: =INDEX(C21:G21,MATCH(Inputs!$C$29,$C$5:$G$5,0)) | I21: drops per month | J21: Plan: 'more than two drops a month'. | L21: 2 | M21: 2 | N21: 2 | O21: 2 | P21: 2 | Q21: =IF(AND(C21&""=L21&"",D21&""=M21&"",E21&""=N21&"",F21&""=O21&"",G21&""=P21&""),"","changed")
B23: How it works
B24: The two decision-window drops on Schedule (DRP-004, DRP-005) take brands, renewals and new offices from the Active column. Type over those Schedule cells to replace the scenario with real plans. The steady-state view and the sensitivity tables use the Active column too. Drops before Gate 3 do not change with the scenario.

Sheet Schedule
A1: Drop schedule
A2: One row per drop. Edit dates, delivery model, offices, brands and renewals. Rows marked derived are the simplest schedule that meets the plan; founder to confirm.
A3: Drop days are Tuesday or Wednesday only; no window may overlap a blackout (Lists). Set 'Actuals in' to Y once a drop's actuals are pasted, and the model switches that drop from plan to actual.
A4: Yellow = your input. Blue = follows the scenario in force (Scenarios tab); type over it to replace. Red 'changed' = the row no longer matches the derived default.
AA5: Derived defaults (for the 'Changed' flag; do not edit)
A6: drop_id | B6: Label | C6: Basis | D6: Post-Gate-3 sequence | E6: Drop date | F6: Day | G6: Delivery model | H6: Tier | I6: Offices | J6: New offices | K6: Brands | L6: of which renewals | M6: of which founding-rate renewals | N6: Actuals in (Y/N) | O6: Notes | P6: Tue or Wed? | Q6: Window closes (T+4) | R6: Blackout clash? | S6: Units brands ship (incl. reserve) | T6: Row check | U6: Office slots on drops in the last four weeks | V6: Roster to date (new offices so far) | W6: Office fatigue | X6: Changed from the derived default? | AA6: default date | AB6: default model | AC6: default tier | AD6: default offices | AE6: default new offices | AF6: default brands | AG6: default renewals | AH6: default founding renewals
A7: DRP-001 | B7: Campaign zero (founding) | C7: derived: CONTRACTS s3 | E7: 46399 | F7: =IF(E7="","",TEXT(E7,"ddd")) | G7: founder | H7: founding | I7: 5 | J7: 5 | K7: 2 | L7: 0 | M7: 0 | N7: N | O7: Stretch option Tue 2026-12-08 only if both brands pay by 2026-11-20. Brands asked to ship by 2026-12-22. | P7: =IF(E7="","",IF(OR(WEEKDAY(E7)=Lists!$V$4,WEEKDAY(E7)=Lists!$V$5),"ok","not Tue/Wed")) | Q7: =IF(E7="","",WORKDAY(E7,Inputs!$C$23-1,Lists!$N$4:$N$30)) | R7: =IF(E7="","",IF(COUNTIFS(Lists!$Q$4:$Q$12,"<="&Q7,Lists!$R$4:$R$12,">="&E7)>0,"clash","ok")) | S7: =IF(E7="","",N(K7)*N(I7)*Inputs!$C$53*(1+Inputs!$C$54)) | T7: =IF(E7="",IF(N(K7)>0,"date missing",""),IF(AND(P7="ok",R7="ok",N(J7)<=N(I7),N(L7)<=N(K7),N(M7)<=N(L7),OR(N(K7)=0,N(I7)>0),G7<>"",H7<>""),"ok","check")) | U7: =IF(OR(E7="",N(K7)=0),"",SUMIFS($I$7:$I$18,$E$7:$E$18,">"&E7-Inputs!$C$25,$E$7:$E$18,"<="&E7,$K$7:$K$18,">0")) | V7: =IF(E7="","",SUMIFS($J$7:$J$18,$E$7:$E$18,"<="&E7)) | W7: =IF(U7="","",IF(U7>V7,"some offices get a second drop within four weeks","ok")) | X7: =IF(AND(E7&""=AA7&"",G7&""=AB7&"",H7&""=AC7&"",I7&""=AD7&"",J7&""=AE7&"",K7&""=AF7&"",L7&""=AG7&"",M7&""=AH7&""),"","changed") | AA7: 46399 | AB7: founder | AC7: founding | AD7: 5 | AE7: 5 | AF7: 2 | AG7: 0 | AH7: 0
A8: DRP-002 | B8: Standard run 1 | C8: derived: CONTRACTS s3 | E8: 46427 | F8: =IF(E8="","",TEXT(E8,"ddd")) | G8: courier | H8: standard | I8: 10 | J8: 5 | K8: 3 | L8: 0 | M8: 0 | N8: N | O8: Campaigns one and two: founder plus courier (plan). Five new offices take the roster from 5 to 10. | P8: =IF(E8="","",IF(OR(WEEKDAY(E8)=Lists!$V$4,WEEKDAY(E8)=Lists!$V$5),"ok","not Tue/Wed")) | Q8: =IF(E8="","",WORKDAY(E8,Inputs!$C$23-1,Lists!$N$4:$N$30)) | R8: =IF(E8="","",IF(COUNTIFS(Lists!$Q$4:$Q$12,"<="&Q8,Lists!$R$4:$R$12,">="&E8)>0,"clash","ok")) | S8: =IF(E8="","",N(K8)*N(I8)*Inputs!$C$53*(1+Inputs!$C$54)) | T8: =IF(E8="",IF(N(K8)>0,"date missing",""),IF(AND(P8="ok",R8="ok",N(J8)<=N(I8),N(L8)<=N(K8),N(M8)<=N(L8),OR(N(K8)=0,N(I8)>0),G8<>"",H8<>""),"ok","check")) | U8: =IF(OR(E8="",N(K8)=0),"",SUMIFS($I$7:$I$18,$E$7:$E$18,">"&E8-Inputs!$C$25,$E$7:$E$18,"<="&E8,$K$7:$K$18,">0")) | V8: =IF(E8="","",SUMIFS($J$7:$J$18,$E$7:$E$18,"<="&E8)) | W8: =IF(U8="","",IF(U8>V8,"some offices get a second drop within four weeks","ok")) | X8: =IF(AND(E8&""=AA8&"",G8&""=AB8&"",H8&""=AC8&"",I8&""=AD8&"",J8&""=AE8&"",K8&""=AF8&"",L8&""=AG8&"",M8&""=AH8&""),"","changed") | AA8: 46427 | AB8: courier | AC8: standard | AD8: 10 | AE8: 5 | AF8: 3 | AG8: 0 | AH8: 0
A9: DRP-003 | B9: Standard run 2 | C9: derived: CONTRACTS s3 | E9: 46441 | F9: =IF(E9="","",TEXT(E9,"ddd")) | G9: courier | H9: standard | I9: 10 | J9: 2 | K9: 3 | L9: 0 | M9: 0 | N9: N | O9: Two new offices reach the six-month goal of 12 active offices. Two weeks after run 1, so most offices get two drops in February. | P9: =IF(E9="","",IF(OR(WEEKDAY(E9)=Lists!$V$4,WEEKDAY(E9)=Lists!$V$5),"ok","not Tue/Wed")) | Q9: =IF(E9="","",WORKDAY(E9,Inputs!$C$23-1,Lists!$N$4:$N$30)) | R9: =IF(E9="","",IF(COUNTIFS(Lists!$Q$4:$Q$12,"<="&Q9,Lists!$R$4:$R$12,">="&E9)>0,"clash","ok")) | S9: =IF(E9="","",N(K9)*N(I9)*Inputs!$C$53*(1+Inputs!$C$54)) | T9: =IF(E9="",IF(N(K9)>0,"date missing",""),IF(AND(P9="ok",R9="ok",N(J9)<=N(I9),N(L9)<=N(K9),N(M9)<=N(L9),OR(N(K9)=0,N(I9)>0),G9<>"",H9<>""),"ok","check")) | U9: =IF(OR(E9="",N(K9)=0),"",SUMIFS($I$7:$I$18,$E$7:$E$18,">"&E9-Inputs!$C$25,$E$7:$E$18,"<="&E9,$K$7:$K$18,">0")) | V9: =IF(E9="","",SUMIFS($J$7:$J$18,$E$7:$E$18,"<="&E9)) | W9: =IF(U9="","",IF(U9>V9,"some offices get a second drop within four weeks","ok")) | X9: =IF(AND(E9&""=AA9&"",G9&""=AB9&"",H9&""=AC9&"",I9&""=AD9&"",J9&""=AE9&"",K9&""=AF9&"",L9&""=AG9&"",M9&""=AH9&""),"","changed") | AA9: 46441 | AB9: courier | AC9: standard | AD9: 10 | AE9: 2 | AF9: 3 | AG9: 0 | AH9: 0
A10: DRP-004 | B10: Decision window drop 1 | C10: derived: scenario | D10: 1 | E10: 46469 | F10: =IF(E10="","",TEXT(E10,"ddd")) | G10: direct-ship | H10: standard | I10: 10 | J10: =IF(K10>0,N(Scenarios!$H$13),0) | K10: =IF(D10<=Scenarios!$H$10,Scenarios!$H$11,0) | L10: =ROUND(Scenarios!$H$12*K10,0) | M10: 0 | N10: N | O10: Campaign three onward: brands ship direct (plan). Brands, renewals and new offices follow the scenario in force. | P10: =IF(E10="","",IF(OR(WEEKDAY(E10)=Lists!$V$4,WEEKDAY(E10)=Lists!$V$5),"ok","not Tue/Wed")) | Q10: =IF(E10="","",WORKDAY(E10,Inputs!$C$23-1,Lists!$N$4:$N$30)) | R10: =IF(E10="","",IF(COUNTIFS(Lists!$Q$4:$Q$12,"<="&Q10,Lists!$R$4:$R$12,">="&E10)>0,"clash","ok")) | S10: =IF(E10="","",N(K10)*N(I10)*Inputs!$C$53*(1+Inputs!$C$54)) | T10: =IF(E10="",IF(N(K10)>0,"date missing",""),IF(AND(P10="ok",R10="ok",N(J10)<=N(I10),N(L10)<=N(K10),N(M10)<=N(L10),OR(N(K10)=0,N(I10)>0),G10<>"",H10<>""),"ok","check")) | U10: =IF(OR(E10="",N(K10)=0),"",SUMIFS($I$7:$I$18,$E$7:$E$18,">"&E10-Inputs!$C$25,$E$7:$E$18,"<="&E10,$K$7:$K$18,">0")) | V10: =IF(E10="","",SUMIFS($J$7:$J$18,$E$7:$E$18,"<="&E10)) | W10: =IF(U10="","",IF(U10>V10,"some offices get a second drop within four weeks","ok")) | X10: =IF(AND(E10&""=AA10&"",G10&""=AB10&"",H10&""=AC10&"",I10&""=AD10&"",J10&""=AE10&"",K10&""=AF10&"",L10&""=AG10&"",M10&""=AH10&""),"","changed") | AA10: 46469 | AB10: direct-ship | AC10: standard | AD10: 10 | AE10: =IF(K10>0,N(Scenarios!$H$13),0) | AF10: =IF(D10<=Scenarios!$H$10,Scenarios!$H$11,0) | AG10: =ROUND(Scenarios!$H$12*K10,0) | AH10: 0
A11: DRP-005 | B11: Decision window drop 2 | C11: derived: scenario | D11: 2 | E11: 46483 | F11: =IF(E11="","",TEXT(E11,"ddd")) | G11: direct-ship | H11: standard | I11: 10 | J11: =IF(K11>0,N(Scenarios!$H$13),0) | K11: =IF(D11<=Scenarios!$H$10,Scenarios!$H$11,0) | L11: =ROUND(Scenarios!$H$12*K11,0) | M11: 0 | N11: N | O11: Second extra drop before the decision (scenario B's 'two more drops'; two drops a month in the base). | P11: =IF(E11="","",IF(OR(WEEKDAY(E11)=Lists!$V$4,WEEKDAY(E11)=Lists!$V$5),"ok","not Tue/Wed")) | Q11: =IF(E11="","",WORKDAY(E11,Inputs!$C$23-1,Lists!$N$4:$N$30)) | R11: =IF(E11="","",IF(COUNTIFS(Lists!$Q$4:$Q$12,"<="&Q11,Lists!$R$4:$R$12,">="&E11)>0,"clash","ok")) | S11: =IF(E11="","",N(K11)*N(I11)*Inputs!$C$53*(1+Inputs!$C$54)) | T11: =IF(E11="",IF(N(K11)>0,"date missing",""),IF(AND(P11="ok",R11="ok",N(J11)<=N(I11),N(L11)<=N(K11),N(M11)<=N(L11),OR(N(K11)=0,N(I11)>0),G11<>"",H11<>""),"ok","check")) | U11: =IF(OR(E11="",N(K11)=0),"",SUMIFS($I$7:$I$18,$E$7:$E$18,">"&E11-Inputs!$C$25,$E$7:$E$18,"<="&E11,$K$7:$K$18,">0")) | V11: =IF(E11="","",SUMIFS($J$7:$J$18,$E$7:$E$18,"<="&E11)) | W11: =IF(U11="","",IF(U11>V11,"some offices get a second drop within four weeks","ok")) | X11: =IF(AND(E11&""=AA11&"",G11&""=AB11&"",H11&""=AC11&"",I11&""=AD11&"",J11&""=AE11&"",K11&""=AF11&"",L11&""=AG11&"",M11&""=AH11&""),"","changed") | AA11: 46483 | AB11: direct-ship | AC11: standard | AD11: 10 | AE11: =IF(K11>0,N(Scenarios!$H$13),0) | AF11: =IF(D11<=Scenarios!$H$10,Scenarios!$H$11,0) | AG11: =ROUND(Scenarios!$H$12*K11,0) | AH11: 0
A12: DRP-006 | C12: founder entry | F12: =IF(E12="","",TEXT(E12,"ddd")) | N12: N | P12: =IF(E12="","",IF(OR(WEEKDAY(E12)=Lists!$V$4,WEEKDAY(E12)=Lists!$V$5),"ok","not Tue/Wed")) | Q12: =IF(E12="","",WORKDAY(E12,Inputs!$C$23-1,Lists!$N$4:$N$30)) | R12: =IF(E12="","",IF(COUNTIFS(Lists!$Q$4:$Q$12,"<="&Q12,Lists!$R$4:$R$12,">="&E12)>0,"clash","ok")) | S12: =IF(E12="","",N(K12)*N(I12)*Inputs!$C$53*(1+Inputs!$C$54)) | T12: =IF(E12="",IF(N(K12)>0,"date missing",""),IF(AND(P12="ok",R12="ok",N(J12)<=N(I12),N(L12)<=N(K12),N(M12)<=N(L12),OR(N(K12)=0,N(I12)>0),G12<>"",H12<>""),"ok","check")) | U12: =IF(OR(E12="",N(K12)=0),"",SUMIFS($I$7:$I$18,$E$7:$E$18,">"&E12-Inputs!$C$25,$E$7:$E$18,"<="&E12,$K$7:$K$18,">0")) | V12: =IF(E12="","",SUMIFS($J$7:$J$18,$E$7:$E$18,"<="&E12)) | W12: =IF(U12="","",IF(U12>V12,"some offices get a second drop within four weeks","ok")) | X12: =IF(AND(E12&""=AA12&"",G12&""=AB12&"",H12&""=AC12&"",I12&""=AD12&"",J12&""=AE12&"",K12&""=AF12&"",L12&""=AG12&"",M12&""=AH12&""),"","changed")
A13: DRP-007 | C13: founder entry | F13: =IF(E13="","",TEXT(E13,"ddd")) | N13: N | P13: =IF(E13="","",IF(OR(WEEKDAY(E13)=Lists!$V$4,WEEKDAY(E13)=Lists!$V$5),"ok","not Tue/Wed")) | Q13: =IF(E13="","",WORKDAY(E13,Inputs!$C$23-1,Lists!$N$4:$N$30)) | R13: =IF(E13="","",IF(COUNTIFS(Lists!$Q$4:$Q$12,"<="&Q13,Lists!$R$4:$R$12,">="&E13)>0,"clash","ok")) | S13: =IF(E13="","",N(K13)*N(I13)*Inputs!$C$53*(1+Inputs!$C$54)) | T13: =IF(E13="",IF(N(K13)>0,"date missing",""),IF(AND(P13="ok",R13="ok",N(J13)<=N(I13),N(L13)<=N(K13),N(M13)<=N(L13),OR(N(K13)=0,N(I13)>0),G13<>"",H13<>""),"ok","check")) | U13: =IF(OR(E13="",N(K13)=0),"",SUMIFS($I$7:$I$18,$E$7:$E$18,">"&E13-Inputs!$C$25,$E$7:$E$18,"<="&E13,$K$7:$K$18,">0")) | V13: =IF(E13="","",SUMIFS($J$7:$J$18,$E$7:$E$18,"<="&E13)) | W13: =IF(U13="","",IF(U13>V13,"some offices get a second drop within four weeks","ok")) | X13: =IF(AND(E13&""=AA13&"",G13&""=AB13&"",H13&""=AC13&"",I13&""=AD13&"",J13&""=AE13&"",K13&""=AF13&"",L13&""=AG13&"",M13&""=AH13&""),"","changed")
A14: DRP-008 | C14: founder entry | F14: =IF(E14="","",TEXT(E14,"ddd")) | N14: N | P14: =IF(E14="","",IF(OR(WEEKDAY(E14)=Lists!$V$4,WEEKDAY(E14)=Lists!$V$5),"ok","not Tue/Wed")) | Q14: =IF(E14="","",WORKDAY(E14,Inputs!$C$23-1,Lists!$N$4:$N$30)) | R14: =IF(E14="","",IF(COUNTIFS(Lists!$Q$4:$Q$12,"<="&Q14,Lists!$R$4:$R$12,">="&E14)>0,"clash","ok")) | S14: =IF(E14="","",N(K14)*N(I14)*Inputs!$C$53*(1+Inputs!$C$54)) | T14: =IF(E14="",IF(N(K14)>0,"date missing",""),IF(AND(P14="ok",R14="ok",N(J14)<=N(I14),N(L14)<=N(K14),N(M14)<=N(L14),OR(N(K14)=0,N(I14)>0),G14<>"",H14<>""),"ok","check")) | U14: =IF(OR(E14="",N(K14)=0),"",SUMIFS($I$7:$I$18,$E$7:$E$18,">"&E14-Inputs!$C$25,$E$7:$E$18,"<="&E14,$K$7:$K$18,">0")) | V14: =IF(E14="","",SUMIFS($J$7:$J$18,$E$7:$E$18,"<="&E14)) | W14: =IF(U14="","",IF(U14>V14,"some offices get a second drop within four weeks","ok")) | X14: =IF(AND(E14&""=AA14&"",G14&""=AB14&"",H14&""=AC14&"",I14&""=AD14&"",J14&""=AE14&"",K14&""=AF14&"",L14&""=AG14&"",M14&""=AH14&""),"","changed")
A15: DRP-009 | C15: founder entry | F15: =IF(E15="","",TEXT(E15,"ddd")) | N15: N | P15: =IF(E15="","",IF(OR(WEEKDAY(E15)=Lists!$V$4,WEEKDAY(E15)=Lists!$V$5),"ok","not Tue/Wed")) | Q15: =IF(E15="","",WORKDAY(E15,Inputs!$C$23-1,Lists!$N$4:$N$30)) | R15: =IF(E15="","",IF(COUNTIFS(Lists!$Q$4:$Q$12,"<="&Q15,Lists!$R$4:$R$12,">="&E15)>0,"clash","ok")) | S15: =IF(E15="","",N(K15)*N(I15)*Inputs!$C$53*(1+Inputs!$C$54)) | T15: =IF(E15="",IF(N(K15)>0,"date missing",""),IF(AND(P15="ok",R15="ok",N(J15)<=N(I15),N(L15)<=N(K15),N(M15)<=N(L15),OR(N(K15)=0,N(I15)>0),G15<>"",H15<>""),"ok","check")) | U15: =IF(OR(E15="",N(K15)=0),"",SUMIFS($I$7:$I$18,$E$7:$E$18,">"&E15-Inputs!$C$25,$E$7:$E$18,"<="&E15,$K$7:$K$18,">0")) | V15: =IF(E15="","",SUMIFS($J$7:$J$18,$E$7:$E$18,"<="&E15)) | W15: =IF(U15="","",IF(U15>V15,"some offices get a second drop within four weeks","ok")) | X15: =IF(AND(E15&""=AA15&"",G15&""=AB15&"",H15&""=AC15&"",I15&""=AD15&"",J15&""=AE15&"",K15&""=AF15&"",L15&""=AG15&"",M15&""=AH15&""),"","changed")
A16: DRP-010 | C16: founder entry | F16: =IF(E16="","",TEXT(E16,"ddd")) | N16: N | P16: =IF(E16="","",IF(OR(WEEKDAY(E16)=Lists!$V$4,WEEKDAY(E16)=Lists!$V$5),"ok","not Tue/Wed")) | Q16: =IF(E16="","",WORKDAY(E16,Inputs!$C$23-1,Lists!$N$4:$N$30)) | R16: =IF(E16="","",IF(COUNTIFS(Lists!$Q$4:$Q$12,"<="&Q16,Lists!$R$4:$R$12,">="&E16)>0,"clash","ok")) | S16: =IF(E16="","",N(K16)*N(I16)*Inputs!$C$53*(1+Inputs!$C$54)) | T16: =IF(E16="",IF(N(K16)>0,"date missing",""),IF(AND(P16="ok",R16="ok",N(J16)<=N(I16),N(L16)<=N(K16),N(M16)<=N(L16),OR(N(K16)=0,N(I16)>0),G16<>"",H16<>""),"ok","check")) | U16: =IF(OR(E16="",N(K16)=0),"",SUMIFS($I$7:$I$18,$E$7:$E$18,">"&E16-Inputs!$C$25,$E$7:$E$18,"<="&E16,$K$7:$K$18,">0")) | V16: =IF(E16="","",SUMIFS($J$7:$J$18,$E$7:$E$18,"<="&E16)) | W16: =IF(U16="","",IF(U16>V16,"some offices get a second drop within four weeks","ok")) | X16: =IF(AND(E16&""=AA16&"",G16&""=AB16&"",H16&""=AC16&"",I16&""=AD16&"",J16&""=AE16&"",K16&""=AF16&"",L16&""=AG16&"",M16&""=AH16&""),"","changed")
A17: DRP-011 | C17: founder entry | F17: =IF(E17="","",TEXT(E17,"ddd")) | N17: N | P17: =IF(E17="","",IF(OR(WEEKDAY(E17)=Lists!$V$4,WEEKDAY(E17)=Lists!$V$5),"ok","not Tue/Wed")) | Q17: =IF(E17="","",WORKDAY(E17,Inputs!$C$23-1,Lists!$N$4:$N$30)) | R17: =IF(E17="","",IF(COUNTIFS(Lists!$Q$4:$Q$12,"<="&Q17,Lists!$R$4:$R$12,">="&E17)>0,"clash","ok")) | S17: =IF(E17="","",N(K17)*N(I17)*Inputs!$C$53*(1+Inputs!$C$54)) | T17: =IF(E17="",IF(N(K17)>0,"date missing",""),IF(AND(P17="ok",R17="ok",N(J17)<=N(I17),N(L17)<=N(K17),N(M17)<=N(L17),OR(N(K17)=0,N(I17)>0),G17<>"",H17<>""),"ok","check")) | U17: =IF(OR(E17="",N(K17)=0),"",SUMIFS($I$7:$I$18,$E$7:$E$18,">"&E17-Inputs!$C$25,$E$7:$E$18,"<="&E17,$K$7:$K$18,">0")) | V17: =IF(E17="","",SUMIFS($J$7:$J$18,$E$7:$E$18,"<="&E17)) | W17: =IF(U17="","",IF(U17>V17,"some offices get a second drop within four weeks","ok")) | X17: =IF(AND(E17&""=AA17&"",G17&""=AB17&"",H17&""=AC17&"",I17&""=AD17&"",J17&""=AE17&"",K17&""=AF17&"",L17&""=AG17&"",M17&""=AH17&""),"","changed")
A18: DRP-012 | C18: founder entry | F18: =IF(E18="","",TEXT(E18,"ddd")) | N18: N | P18: =IF(E18="","",IF(OR(WEEKDAY(E18)=Lists!$V$4,WEEKDAY(E18)=Lists!$V$5),"ok","not Tue/Wed")) | Q18: =IF(E18="","",WORKDAY(E18,Inputs!$C$23-1,Lists!$N$4:$N$30)) | R18: =IF(E18="","",IF(COUNTIFS(Lists!$Q$4:$Q$12,"<="&Q18,Lists!$R$4:$R$12,">="&E18)>0,"clash","ok")) | S18: =IF(E18="","",N(K18)*N(I18)*Inputs!$C$53*(1+Inputs!$C$54)) | T18: =IF(E18="",IF(N(K18)>0,"date missing",""),IF(AND(P18="ok",R18="ok",N(J18)<=N(I18),N(L18)<=N(K18),N(M18)<=N(L18),OR(N(K18)=0,N(I18)>0),G18<>"",H18<>""),"ok","check")) | U18: =IF(OR(E18="",N(K18)=0),"",SUMIFS($I$7:$I$18,$E$7:$E$18,">"&E18-Inputs!$C$25,$E$7:$E$18,"<="&E18,$K$7:$K$18,">0")) | V18: =IF(E18="","",SUMIFS($J$7:$J$18,$E$7:$E$18,"<="&E18)) | W18: =IF(U18="","",IF(U18>V18,"some offices get a second drop within four weeks","ok")) | X18: =IF(AND(E18&""=AA18&"",G18&""=AB18&"",H18&""=AC18&"",I18&""=AD18&"",J18&""=AE18&"",K18&""=AF18&"",L18&""=AG18&"",M18&""=AH18&""),"","changed")
B19: Totals | I19: =SUM(I7:I18) | J19: =SUM(J7:J18) | K19: =SUM(K7:K18) | L19: =SUM(L7:L18) | M19: =SUM(M7:M18) | S19: =SUM(S7:S18)
B21: Offices column counts every office on the drop; New offices counts the ones visiting for the first time (4 hours each instead of 1). Brands counts brand campaigns on the drop; renewals are part of that count (2 hours each instead of 6 or 10). Tier sets the price of the new brands; founding-rate renewals pay the founding rate per office.

Sheet Calculator
A1: Drop calculator
A2: Pick any tier, delivery model, office count and brand count. It runs the same engine as the drops and does not change the model.
A3: To test a price: type it in 'Standard price per office' below (or on Inputs to move the whole model). Read 'Contribution per founder hour'.
B5: Your drop | E5: Result
B6: Tier | C6: standard | E6: Line | F6: Whole drop | G6: Per brand (equal split of shared costs)
B7: Delivery model | C7: courier | E7: Revenue | F7: =S40 | G7: =IF(G40>0,F7/G40,"")
B8: Offices | C8: 10 | E8: Display kits | F8: =T40 | G8: =IF(G40>0,F8/G40,"")
B9: of which new offices | C9: 0 | E9: Transport | F9: =U40 | G9: =IF(G40>0,F9/G40,"")
B10: Brands | C10: 3 | E10: Kit mailing | F10: =V40 | G10: =IF(G40>0,F10/G40,"")
B11: of which renewals | C11: 0 | E11: Card processing | F11: =W40 | G11: =IF(G40>0,F11/G40,"")
B12: of which founding-rate renewals | C12: 0 | E12: Storage allocation | F12: =X40 | G12: =IF(G40>0,F12/G40,"")
B13: Standard price per office (blank = Inputs) | E13: Software allocation | F13: =Y40 | G13: =IF(G40>0,F13/G40,"")
B14: Founding price per office (blank = Inputs) | E14: Insurance allocation | F14: =Z40 | G14: =IF(G40>0,F14/G40,"")
B15: Storage allocated? Y/N (blank = Inputs choice) | E15: Hard costs | F15: =AA40 | G15: =IF(G40>0,F15/G40,"")
B16: Card processing? Y/N (blank = Inputs toggle) | E16: Contribution | F16: =AJ40 | G16: =IF(G40>0,F16/G40,"")
E17: brand_sales (h) | F17: =AB40 | G17: =IF(G40>0,F17/G40,"")
E18: office_coordination (h) | F18: =AC40 | G18: =IF(G40>0,F18/G40,"")
E19: receiving_kitting (h) | F19: =AD40 | G19: =IF(G40>0,F19/G40,"")
E20: drop_day (h) | F20: =AE40 | G20: =IF(G40>0,F20/G40,"")
E21: checks_pickup (h) | F21: =AF40 | G21: =IF(G40>0,F21/G40,"")
E22: reporting_debriefs (h) | F22: =AG40 | G22: =IF(G40>0,F22/G40,"")
E23: admin_invoicing (h) | F23: =AH40 | G23: =IF(G40>0,F23/G40,"")
E24: Founder hours | F24: =AI40 | G24: =IF(G40>0,F24/G40,"")
E25: Contribution per founder hour | F25: =AK40 | G25: =F25
E26: Against the Gate 3 target | F26: =IF(ISNUMBER(F25),IF(F25>=Inputs!$C$126,"at or above target","below target"),"n/a")
E27: Units each brand ships (incl. reserve) | F27: =E40*Inputs!$C$53*(1+Inputs!$C$54)
E29: Per-brand column: revenue and processing are averaged across brands, and shared costs and hours (kits, transport, allocations, office and drop-day time) are split equally. Brand sales and reporting hours are per brand already.
A37: Engine row: the same formulas as every row on Drop_PnL. Read-only; the result table above reads it.
A39: Drop or case | B39: Drop date | C39: Delivery model | D39: Tier | E39: Offices | F39: New offices | G39: Brands | H39: of which renewals | I39: of which founding-rate renewals | J39: Standard price per office | K39: Founding price per office | L39: Storage allocated (1/0) | M39: Card processing (1/0) | N39: Drop runs (1/0) | O39: New founding brands | P39: New standard brands | Q39: Revenue at founding rate | R39: Revenue at standard rate | S39: Revenue | T39: Display kits | U39: Transport | V39: Kit mailing | W39: Card processing | X39: Storage allocation | Y39: Software allocation | Z39: Insurance allocation | AA39: Hard costs | AB39: brand_sales (h) | AC39: office_coordination (h) | AD39: receiving_kitting (h) | AE39: drop_day (h) | AF39: checks_pickup (h) | AG39: reporting_debriefs (h) | AH39: admin_invoicing (h) | AI39: Founder hours | AJ39: Contribution | AK39: Contribution per founder hour | AL39: Direct costs (kits, transport, mailing, processing) | AM39: Overhead allocations (views of monthly costs)
A40: Calculator drop | C40: =$C$7 | D40: =$C$6 | E40: =N($C$8) | F40: =N($C$9) | G40: =N($C$10) | H40: =N($C$11) | I40: =N($C$12) | J40: =IF($C$13="",Inputs!$C$33,$C$13) | K40: =IF($C$14="",Inputs!$C$36,$C$14) | L40: =IF($C$15="",IF(Inputs!$C$65="unit",1,0),IF($C$15="Y",1,0)) | M40: =IF($C$16="",Inputs!$C$49,IF($C$16="Y",1,0)) | N40: =IF(G40>0,1,0) | O40: =IF(D40="founding",G40-H40,0) | P40: =IF(D40="standard",G40-H40,0) | Q40: =O40*(K40*MIN(E40,Inputs!$C$37)+Inputs!$C$39*MAX(E40-Inputs!$C$37,0))+I40*K40*E40 | R40: =(P40+H40-I40)*(J40*MIN(E40,Inputs!$C$34)+Inputs!$C$39*MAX(E40-Inputs!$C$34,0)) | S40: =Q40+R40 | T40: =N40*E40*(Inputs!$C$58+Inputs!$C$59*MAX(G40-1,0)) | U40: =IF(N40=0,0,INDEX(Inputs!$C$95:$C$97,MATCH(C40,Inputs!$B$95:$B$97,0))+INDEX(Inputs!$D$95:$D$97,MATCH(C40,Inputs!$B$95:$B$97,0))*E40) | V40: =IF(N40=0,0,INDEX(Inputs!$E$95:$E$97,MATCH(C40,Inputs!$B$95:$B$97,0))*E40) | W40: =S40*Inputs!$C$48*M40 | X40: =N40*L40*Inputs!$C$66/Inputs!$C$75 | Y40: =N40*Inputs!$C$69/Inputs!$C$75 | Z40: =N40*Inputs!$C$71/Inputs!$C$75 | AA40: =SUM(T40:Z40) | AB40: =O40*Inputs!$C$79+P40*Inputs!$C$83+H40*Inputs!$C$84 | AC40: =N40*(F40*Inputs!$C$85+(E40-F40)*Inputs!$C$86) | AD40: =IF(N40=0,0,INDEX(Inputs!$F$95:$F$97,MATCH(C40,Inputs!$B$95:$B$97,0))+Inputs!$C$87*G40) | AE40: =IF(N40=0,0,INDEX(Inputs!$G$95:$G$97,MATCH(C40,Inputs!$B$95:$B$97,0))*E40) | AF40: =IF(N40=0,0,INDEX(Inputs!$H$95:$H$97,MATCH(C40,Inputs!$B$95:$B$97,0))*E40) | AG40: =Inputs!$C$88*G40 | AH40: =N40*Inputs!$C$89 | AI40: =SUM(AB40:AH40) | AJ40: =S40-AA40 | AK40: =IF(AI40>0,AJ40/AI40,"n/a") | AL40: =T40+U40+V40+W40 | AM40: =X40+Y40+Z40

Sheet Drop_PnL
A1: Per-drop P&L (plan basis) with cash timing
A2: One row per Schedule row. Contribution = revenue minus hard costs, as the plan defines it. Overhead allocations are views; the cash flow pays overhead once.
A3: Planning estimates. The 'Live' columns switch to actuals when Schedule says 'Actuals in = Y'. Shared drop costs are split equally across the drop's brands where a per-brand figure is shown.
A5: Case | E5: Inputs to the engine | N5: Revenue | T5: Hard costs | AB5: Founder hours by activity | AJ5: Result | AL5: Split | AO5: Cash timing on the plan's terms (feeds Cash_Flow) | AZ5: Live: actual where Actuals in = Y, otherwise plan
A6: Drop or case | B6: Drop date | C6: Delivery model | D6: Tier | E6: Offices | F6: New offices | G6: Brands | H6: of which renewals | I6: of which founding-rate renewals | J6: Standard price per office | K6: Founding price per office | L6: Storage allocated (1/0) | M6: Card processing (1/0) | N6: Drop runs (1/0) | O6: New founding brands | P6: New standard brands | Q6: Revenue at founding rate | R6: Revenue at standard rate | S6: Revenue | T6: Display kits | U6: Transport | V6: Kit mailing | W6: Card processing | X6: Storage allocation | Y6: Software allocation | Z6: Insurance allocation | AA6: Hard costs | AB6: brand_sales (h) | AC6: office_coordination (h) | AD6: receiving_kitting (h) | AE6: drop_day (h) | AF6: checks_pickup (h) | AG6: reporting_debriefs (h) | AH6: admin_invoicing (h) | AI6: Founder hours | AJ6: Contribution | AK6: Contribution per founder hour | AL6: Direct costs (kits, transport, mailing, processing) | AM6: Overhead allocations (views of monthly costs) | AO6: Founding payment date | AP6: Founding payment | AQ6: Standard deposit date | AR6: Standard deposit | AS6: Balance date | AT6: Balance | AU6: Processing on founding payment | AV6: Processing on deposit | AW6: Processing on balance | AX6: Kits printed (and mailed) | AY6: Transport paid | AZ6: Actuals in | BA6: Live revenue | BB6: Live hard costs | BC6: Live founder hours | BD6: Live contribution | BE6: Live contribution per founder hour | BF6: Basis | BG6: Upcoming drop (1/0)
A7: =Schedule!A7 | B7: =IF(Schedule!E7="","",Schedule!E7) | C7: =IF(Schedule!G7="","",Schedule!G7) | D7: =IF(Schedule!H7="","",Schedule!H7) | E7: =N(Schedule!I7) | F7: =N(Schedule!J7) | G7: =N(Schedule!K7) | H7: =N(Schedule!L7) | I7: =N(Schedule!M7) | J7: =IF(AND(B7<>"",B7>Inputs!$C$15),Scenarios!$H$14,Inputs!$C$33) | K7: =Inputs!$C$36 | L7: =IF(AND(Inputs!$C$65="unit",B7<>"",B7>=Inputs!$C$67,OR(Inputs!$C$68="",B7<=Inputs!$C$68)),1,0) | M7: =Inputs!$C$49 | N7: =IF(G7>0,1,0) | O7: =IF(D7="founding",G7-H7,0) | P7: =IF(D7="standard",G7-H7,0) | Q7: =O7*(K7*MIN(E7,Inputs!$C$37)+Inputs!$C$39*MAX(E7-Inputs!$C$37,0))+I7*K7*E7 | R7: =(P7+H7-I7)*(J7*MIN(E7,Inputs!$C$34)+Inputs!$C$39*MAX(E7-Inputs!$C$34,0)) | S7: =Q7+R7 | T7: =N7*E7*(Inputs!$C$58+Inputs!$C$59*MAX(G7-1,0)) | U7: =IF(N7=0,0,INDEX(Inputs!$C$95:$C$97,MATCH(C7,Inputs!$B$95:$B$97,0))+INDEX(Inputs!$D$95:$D$97,MATCH(C7,Inputs!$B$95:$B$97,0))*E7) | V7: =IF(N7=0,0,INDEX(Inputs!$E$95:$E$97,MATCH(C7,Inputs!$B$95:$B$97,0))*E7) | W7: =S7*Inputs!$C$48*M7 | X7: =N7*L7*Inputs!$C$66/Inputs!$C$75 | Y7: =N7*Inputs!$C$69/Inputs!$C$75 | Z7: =N7*Inputs!$C$71/Inputs!$C$75 | AA7: =SUM(T7:Z7) | AB7: =O7*Inputs!$C$79+P7*Inputs!$C$83+H7*Inputs!$C$84 | AC7: =N7*(F7*Inputs!$C$85+(E7-F7)*Inputs!$C$86) | AD7: =IF(N7=0,0,INDEX(Inputs!$F$95:$F$97,MATCH(C7,Inputs!$B$95:$B$97,0))+Inputs!$C$87*G7) | AE7: =IF(N7=0,0,INDEX(Inputs!$G$95:$G$97,MATCH(C7,Inputs!$B$95:$B$97,0))*E7) | AF7: =IF(N7=0,0,INDEX(Inputs!$H$95:$H$97,MATCH(C7,Inputs!$B$95:$B$97,0))*E7) | AG7: =Inputs!$C$88*G7 | AH7: =N7*Inputs!$C$89 | AI7: =SUM(AB7:AH7) | AJ7: =S7-AA7 | AK7: =IF(AI7>0,AJ7/AI7,"n/a") | AL7: =T7+U7+V7+W7 | AM7: =X7+Y7+Z7 | AO7: =IF(OR(N7=0,AP7=0),"",WORKDAY(B7,-Inputs!$C$43,Lists!$N$4:$N$30)+N(Inputs!$C$47)) | AP7: =Q7*Inputs!$C$42 | AQ7: =IF(OR(N7=0,AR7=0),"",WORKDAY(B7,-Inputs!$C$45,Lists!$N$4:$N$30)+N(Inputs!$C$47)) | AR7: =R7*Inputs!$C$44 | AS7: =IF(OR(N7=0,AT7=0),"",WORKDAY(B7,Inputs!$C$46,Lists!$N$4:$N$30)+N(Inputs!$C$47)) | AT7: =Q7*(1-Inputs!$C$42)+R7*(1-Inputs!$C$44) | AU7: =AP7*Inputs!$C$48*M7 | AV7: =AR7*Inputs!$C$48*M7 | AW7: =AT7*Inputs!$C$48*M7 | AX7: =IF(N7=0,"",WORKDAY(B7,-Inputs!$C$64,Lists!$N$4:$N$30)) | AY7: =IF(N7=0,"",B7) | AZ7: =IF(Schedule!N7="Y","Y","N") | BA7: =IF(AZ7="Y",Drop_Actuals!D7,S7) | BB7: =IF(AZ7="Y",Drop_Actuals!J7,AA7) | BC7: =IF(AZ7="Y",Drop_Actuals!R7,AI7) | BD7: =BA7-BB7 | BE7: =IF(BC7>0,BD7/BC7,"n/a") | BF7: =IF(AND(N7=0,AZ7="N"),"",IF(AZ7="Y","actual","plan")) | BG7: =IF(AND(N7=1,B7>=Inputs!$C$17),1,0)
A8: =Schedule!A8 | B8: =IF(Schedule!E8="","",Schedule!E8) | C8: =IF(Schedule!G8="","",Schedule!G8) | D8: =IF(Schedule!H8="","",Schedule!H8) | E8: =N(Schedule!I8) | F8: =N(Schedule!J8) | G8: =N(Schedule!K8) | H8: =N(Schedule!L8) | I8: =N(Schedule!M8) | J8: =IF(AND(B8<>"",B8>Inputs!$C$15),Scenarios!$H$14,Inputs!$C$33) | K8: =Inputs!$C$36 | L8: =IF(AND(Inputs!$C$65="unit",B8<>"",B8>=Inputs!$C$67,OR(Inputs!$C$68="",B8<=Inputs!$C$68)),1,0) | M8: =Inputs!$C$49 | N8: =IF(G8>0,1,0) | O8: =IF(D8="founding",G8-H8,0) | P8: =IF(D8="standard",G8-H8,0) | Q8: =O8*(K8*MIN(E8,Inputs!$C$37)+Inputs!$C$39*MAX(E8-Inputs!$C$37,0))+I8*K8*E8 | R8: =(P8+H8-I8)*(J8*MIN(E8,Inputs!$C$34)+Inputs!$C$39*MAX(E8-Inputs!$C$34,0)) | S8: =Q8+R8 | T8: =N8*E8*(Inputs!$C$58+Inputs!$C$59*MAX(G8-1,0)) | U8: =IF(N8=0,0,INDEX(Inputs!$C$95:$C$97,MATCH(C8,Inputs!$B$95:$B$97,0))+INDEX(Inputs!$D$95:$D$97,MATCH(C8,Inputs!$B$95:$B$97,0))*E8) | V8: =IF(N8=0,0,INDEX(Inputs!$E$95:$E$97,MATCH(C8,Inputs!$B$95:$B$97,0))*E8) | W8: =S8*Inputs!$C$48*M8 | X8: =N8*L8*Inputs!$C$66/Inputs!$C$75 | Y8: =N8*Inputs!$C$69/Inputs!$C$75 | Z8: =N8*Inputs!$C$71/Inputs!$C$75 | AA8: =SUM(T8:Z8) | AB8: =O8*Inputs!$C$79+P8*Inputs!$C$83+H8*Inputs!$C$84 | AC8: =N8*(F8*Inputs!$C$85+(E8-F8)*Inputs!$C$86) | AD8: =IF(N8=0,0,INDEX(Inputs!$F$95:$F$97,MATCH(C8,Inputs!$B$95:$B$97,0))+Inputs!$C$87*G8) | AE8: =IF(N8=0,0,INDEX(Inputs!$G$95:$G$97,MATCH(C8,Inputs!$B$95:$B$97,0))*E8) | AF8: =IF(N8=0,0,INDEX(Inputs!$H$95:$H$97,MATCH(C8,Inputs!$B$95:$B$97,0))*E8) | AG8: =Inputs!$C$88*G8 | AH8: =N8*Inputs!$C$89 | AI8: =SUM(AB8:AH8) | AJ8: =S8-AA8 | AK8: =IF(AI8>0,AJ8/AI8,"n/a") | AL8: =T8+U8+V8+W8 | AM8: =X8+Y8+Z8 | AO8: =IF(OR(N8=0,AP8=0),"",WORKDAY(B8,-Inputs!$C$43,Lists!$N$4:$N$30)+N(Inputs!$C$47)) | AP8: =Q8*Inputs!$C$42 | AQ8: =IF(OR(N8=0,AR8=0),"",WORKDAY(B8,-Inputs!$C$45,Lists!$N$4:$N$30)+N(Inputs!$C$47)) | AR8: =R8*Inputs!$C$44 | AS8: =IF(OR(N8=0,AT8=0),"",WORKDAY(B8,Inputs!$C$46,Lists!$N$4:$N$30)+N(Inputs!$C$47)) | AT8: =Q8*(1-Inputs!$C$42)+R8*(1-Inputs!$C$44) | AU8: =AP8*Inputs!$C$48*M8 | AV8: =AR8*Inputs!$C$48*M8 | AW8: =AT8*Inputs!$C$48*M8 | AX8: =IF(N8=0,"",WORKDAY(B8,-Inputs!$C$64,Lists!$N$4:$N$30)) | AY8: =IF(N8=0,"",B8) | AZ8: =IF(Schedule!N8="Y","Y","N") | BA8: =IF(AZ8="Y",Drop_Actuals!D8,S8) | BB8: =IF(AZ8="Y",Drop_Actuals!J8,AA8) | BC8: =IF(AZ8="Y",Drop_Actuals!R8,AI8) | BD8: =BA8-BB8 | BE8: =IF(BC8>0,BD8/BC8,"n/a") | BF8: =IF(AND(N8=0,AZ8="N"),"",IF(AZ8="Y","actual","plan")) | BG8: =IF(AND(N8=1,B8>=Inputs!$C$17),1,0)
A9: =Schedule!A9 | B9: =IF(Schedule!E9="","",Schedule!E9) | C9: =IF(Schedule!G9="","",Schedule!G9) | D9: =IF(Schedule!H9="","",Schedule!H9) | E9: =N(Schedule!I9) | F9: =N(Schedule!J9) | G9: =N(Schedule!K9) | H9: =N(Schedule!L9) | I9: =N(Schedule!M9) | J9: =IF(AND(B9<>"",B9>Inputs!$C$15),Scenarios!$H$14,Inputs!$C$33) | K9: =Inputs!$C$36 | L9: =IF(AND(Inputs!$C$65="unit",B9<>"",B9>=Inputs!$C$67,OR(Inputs!$C$68="",B9<=Inputs!$C$68)),1,0) | M9: =Inputs!$C$49 | N9: =IF(G9>0,1,0) | O9: =IF(D9="founding",G9-H9,0) | P9: =IF(D9="standard",G9-H9,0) | Q9: =O9*(K9*MIN(E9,Inputs!$C$37)+Inputs!$C$39*MAX(E9-Inputs!$C$37,0))+I9*K9*E9 | R9: =(P9+H9-I9)*(J9*MIN(E9,Inputs!$C$34)+Inputs!$C$39*MAX(E9-Inputs!$C$34,0)) | S9: =Q9+R9 | T9: =N9*E9*(Inputs!$C$58+Inputs!$C$59*MAX(G9-1,0)) | U9: =IF(N9=0,0,INDEX(Inputs!$C$95:$C$97,MATCH(C9,Inputs!$B$95:$B$97,0))+INDEX(Inputs!$D$95:$D$97,MATCH(C9,Inputs!$B$95:$B$97,0))*E9) | V9: =IF(N9=0,0,INDEX(Inputs!$E$95:$E$97,MATCH(C9,Inputs!$B$95:$B$97,0))*E9) | W9: =S9*Inputs!$C$48*M9 | X9: =N9*L9*Inputs!$C$66/Inputs!$C$75 | Y9: =N9*Inputs!$C$69/Inputs!$C$75 | Z9: =N9*Inputs!$C$71/Inputs!$C$75 | AA9: =SUM(T9:Z9) | AB9: =O9*Inputs!$C$79+P9*Inputs!$C$83+H9*Inputs!$C$84 | AC9: =N9*(F9*Inputs!$C$85+(E9-F9)*Inputs!$C$86) | AD9: =IF(N9=0,0,INDEX(Inputs!$F$95:$F$97,MATCH(C9,Inputs!$B$95:$B$97,0))+Inputs!$C$87*G9) | AE9: =IF(N9=0,0,INDEX(Inputs!$G$95:$G$97,MATCH(C9,Inputs!$B$95:$B$97,0))*E9) | AF9: =IF(N9=0,0,INDEX(Inputs!$H$95:$H$97,MATCH(C9,Inputs!$B$95:$B$97,0))*E9) | AG9: =Inputs!$C$88*G9 | AH9: =N9*Inputs!$C$89 | AI9: =SUM(AB9:AH9) | AJ9: =S9-AA9 | AK9: =IF(AI9>0,AJ9/AI9,"n/a") | AL9: =T9+U9+V9+W9 | AM9: =X9+Y9+Z9 | AO9: =IF(OR(N9=0,AP9=0),"",WORKDAY(B9,-Inputs!$C$43,Lists!$N$4:$N$30)+N(Inputs!$C$47)) | AP9: =Q9*Inputs!$C$42 | AQ9: =IF(OR(N9=0,AR9=0),"",WORKDAY(B9,-Inputs!$C$45,Lists!$N$4:$N$30)+N(Inputs!$C$47)) | AR9: =R9*Inputs!$C$44 | AS9: =IF(OR(N9=0,AT9=0),"",WORKDAY(B9,Inputs!$C$46,Lists!$N$4:$N$30)+N(Inputs!$C$47)) | AT9: =Q9*(1-Inputs!$C$42)+R9*(1-Inputs!$C$44) | AU9: =AP9*Inputs!$C$48*M9 | AV9: =AR9*Inputs!$C$48*M9 | AW9: =AT9*Inputs!$C$48*M9 | AX9: =IF(N9=0,"",WORKDAY(B9,-Inputs!$C$64,Lists!$N$4:$N$30)) | AY9: =IF(N9=0,"",B9) | AZ9: =IF(Schedule!N9="Y","Y","N") | BA9: =IF(AZ9="Y",Drop_Actuals!D9,S9) | BB9: =IF(AZ9="Y",Drop_Actuals!J9,AA9) | BC9: =IF(AZ9="Y",Drop_Actuals!R9,AI9) | BD9: =BA9-BB9 | BE9: =IF(BC9>0,BD9/BC9,"n/a") | BF9: =IF(AND(N9=0,AZ9="N"),"",IF(AZ9="Y","actual","plan")) | BG9: =IF(AND(N9=1,B9>=Inputs!$C$17),1,0)
A10: =Schedule!A10 | B10: =IF(Schedule!E10="","",Schedule!E10) | C10: =IF(Schedule!G10="","",Schedule!G10) | D10: =IF(Schedule!H10="","",Schedule!H10) | E10: =N(Schedule!I10) | F10: =N(Schedule!J10) | G10: =N(Schedule!K10) | H10: =N(Schedule!L10) | I10: =N(Schedule!M10) | J10: =IF(AND(B10<>"",B10>Inputs!$C$15),Scenarios!$H$14,Inputs!$C$33) | K10: =Inputs!$C$36 | L10: =IF(AND(Inputs!$C$65="unit",B10<>"",B10>=Inputs!$C$67,OR(Inputs!$C$68="",B10<=Inputs!$C$68)),1,0) | M10: =Inputs!$C$49 | N10: =IF(G10>0,1,0) | O10: =IF(D10="founding",G10-H10,0) | P10: =IF(D10="standard",G10-H10,0) | Q10: =O10*(K10*MIN(E10,Inputs!$C$37)+Inputs!$C$39*MAX(E10-Inputs!$C$37,0))+I10*K10*E10 | R10: =(P10+H10-I10)*(J10*MIN(E10,Inputs!$C$34)+Inputs!$C$39*MAX(E10-Inputs!$C$34,0)) | S10: =Q10+R10 | T10: =N10*E10*(Inputs!$C$58+Inputs!$C$59*MAX(G10-1,0)) | U10: =IF(N10=0,0,INDEX(Inputs!$C$95:$C$97,MATCH(C10,Inputs!$B$95:$B$97,0))+INDEX(Inputs!$D$95:$D$97,MATCH(C10,Inputs!$B$95:$B$97,0))*E10) | V10: =IF(N10=0,0,INDEX(Inputs!$E$95:$E$97,MATCH(C10,Inputs!$B$95:$B$97,0))*E10) | W10: =S10*Inputs!$C$48*M10 | X10: =N10*L10*Inputs!$C$66/Inputs!$C$75 | Y10: =N10*Inputs!$C$69/Inputs!$C$75 | Z10: =N10*Inputs!$C$71/Inputs!$C$75 | AA10: =SUM(T10:Z10) | AB10: =O10*Inputs!$C$79+P10*Inputs!$C$83+H10*Inputs!$C$84 | AC10: =N10*(F10*Inputs!$C$85+(E10-F10)*Inputs!$C$86) | AD10: =IF(N10=0,0,INDEX(Inputs!$F$95:$F$97,MATCH(C10,Inputs!$B$95:$B$97,0))+Inputs!$C$87*G10) | AE10: =IF(N10=0,0,INDEX(Inputs!$G$95:$G$97,MATCH(C10,Inputs!$B$95:$B$97,0))*E10) | AF10: =IF(N10=0,0,INDEX(Inputs!$H$95:$H$97,MATCH(C10,Inputs!$B$95:$B$97,0))*E10) | AG10: =Inputs!$C$88*G10 | AH10: =N10*Inputs!$C$89 | AI10: =SUM(AB10:AH10) | AJ10: =S10-AA10 | AK10: =IF(AI10>0,AJ10/AI10,"n/a") | AL10: =T10+U10+V10+W10 | AM10: =X10+Y10+Z10 | AO10: =IF(OR(N10=0,AP10=0),"",WORKDAY(B10,-Inputs!$C$43,Lists!$N$4:$N$30)+N(Inputs!$C$47)) | AP10: =Q10*Inputs!$C$42 | AQ10: =IF(OR(N10=0,AR10=0),"",WORKDAY(B10,-Inputs!$C$45,Lists!$N$4:$N$30)+N(Inputs!$C$47)) | AR10: =R10*Inputs!$C$44 | AS10: =IF(OR(N10=0,AT10=0),"",WORKDAY(B10,Inputs!$C$46,Lists!$N$4:$N$30)+N(Inputs!$C$47)) | AT10: =Q10*(1-Inputs!$C$42)+R10*(1-Inputs!$C$44) | AU10: =AP10*Inputs!$C$48*M10 | AV10: =AR10*Inputs!$C$48*M10 | AW10: =AT10*Inputs!$C$48*M10 | AX10: =IF(N10=0,"",WORKDAY(B10,-Inputs!$C$64,Lists!$N$4:$N$30)) | AY10: =IF(N10=0,"",B10) | AZ10: =IF(Schedule!N10="Y","Y","N") | BA10: =IF(AZ10="Y",Drop_Actuals!D10,S10) | BB10: =IF(AZ10="Y",Drop_Actuals!J10,AA10) | BC10: =IF(AZ10="Y",Drop_Actuals!R10,AI10) | BD10: =BA10-BB10 | BE10: =IF(BC10>0,BD10/BC10,"n/a") | BF10: =IF(AND(N10=0,AZ10="N"),"",IF(AZ10="Y","actual","plan")) | BG10: =IF(AND(N10=1,B10>=Inputs!$C$17),1,0)
A11: =Schedule!A11 | B11: =IF(Schedule!E11="","",Schedule!E11) | C11: =IF(Schedule!G11="","",Schedule!G11) | D11: =IF(Schedule!H11="","",Schedule!H11) | E11: =N(Schedule!I11) | F11: =N(Schedule!J11) | G11: =N(Schedule!K11) | H11: =N(Schedule!L11) | I11: =N(Schedule!M11) | J11: =IF(AND(B11<>"",B11>Inputs!$C$15),Scenarios!$H$14,Inputs!$C$33) | K11: =Inputs!$C$36 | L11: =IF(AND(Inputs!$C$65="unit",B11<>"",B11>=Inputs!$C$67,OR(Inputs!$C$68="",B11<=Inputs!$C$68)),1,0) | M11: =Inputs!$C$49 | N11: =IF(G11>0,1,0) | O11: =IF(D11="founding",G11-H11,0) | P11: =IF(D11="standard",G11-H11,0) | Q11: =O11*(K11*MIN(E11,Inputs!$C$37)+Inputs!$C$39*MAX(E11-Inputs!$C$37,0))+I11*K11*E11 | R11: =(P11+H11-I11)*(J11*MIN(E11,Inputs!$C$34)+Inputs!$C$39*MAX(E11-Inputs!$C$34,0)) | S11: =Q11+R11 | T11: =N11*E11*(Inputs!$C$58+Inputs!$C$59*MAX(G11-1,0)) | U11: =IF(N11=0,0,INDEX(Inputs!$C$95:$C$97,MATCH(C11,Inputs!$B$95:$B$97,0))+INDEX(Inputs!$D$95:$D$97,MATCH(C11,Inputs!$B$95:$B$97,0))*E11) | V11: =IF(N11=0,0,INDEX(Inputs!$E$95:$E$97,MATCH(C11,Inputs!$B$95:$B$97,0))*E11) | W11: =S11*Inputs!$C$48*M11 | X11: =N11*L11*Inputs!$C$66/Inputs!$C$75 | Y11: =N11*Inputs!$C$69/Inputs!$C$75 | Z11: =N11*Inputs!$C$71/Inputs!$C$75 | AA11: =SUM(T11:Z11) | AB11: =O11*Inputs!$C$79+P11*Inputs!$C$83+H11*Inputs!$C$84 | AC11: =N11*(F11*Inputs!$C$85+(E11-F11)*Inputs!$C$86) | AD11: =IF(N11=0,0,INDEX(Inputs!$F$95:$F$97,MATCH(C11,Inputs!$B$95:$B$97,0))+Inputs!$C$87*G11) | AE11: =IF(N11=0,0,INDEX(Inputs!$G$95:$G$97,MATCH(C11,Inputs!$B$95:$B$97,0))*E11) | AF11: =IF(N11=0,0,INDEX(Inputs!$H$95:$H$97,MATCH(C11,Inputs!$B$95:$B$97,0))*E11) | AG11: =Inputs!$C$88*G11 | AH11: =N11*Inputs!$C$89 | AI11: =SUM(AB11:AH11) | AJ11: =S11-AA11 | AK11: =IF(AI11>0,AJ11/AI11,"n/a") | AL11: =T11+U11+V11+W11 | AM11: =X11+Y11+Z11 | AO11: =IF(OR(N11=0,AP11=0),"",WORKDAY(B11,-Inputs!$C$43,Lists!$N$4:$N$30)+N(Inputs!$C$47)) | AP11: =Q11*Inputs!$C$42 | AQ11: =IF(OR(N11=0,AR11=0),"",WORKDAY(B11,-Inputs!$C$45,Lists!$N$4:$N$30)+N(Inputs!$C$47)) | AR11: =R11*Inputs!$C$44 | AS11: =IF(OR(N11=0,AT11=0),"",WORKDAY(B11,Inputs!$C$46,Lists!$N$4:$N$30)+N(Inputs!$C$47)) | AT11: =Q11*(1-Inputs!$C$42)+R11*(1-Inputs!$C$44) | AU11: =AP11*Inputs!$C$48*M11 | AV11: =AR11*Inputs!$C$48*M11 | AW11: =AT11*Inputs!$C$48*M11 | AX11: =IF(N11=0,"",WORKDAY(B11,-Inputs!$C$64,Lists!$N$4:$N$30)) | AY11: =IF(N11=0,"",B11) | AZ11: =IF(Schedule!N11="Y","Y","N") | BA11: =IF(AZ11="Y",Drop_Actuals!D11,S11) | BB11: =IF(AZ11="Y",Drop_Actuals!J11,AA11) | BC11: =IF(AZ11="Y",Drop_Actuals!R11,AI11) | BD11: =BA11-BB11 | BE11: =IF(BC11>0,BD11/BC11,"n/a") | BF11: =IF(AND(N11=0,AZ11="N"),"",IF(AZ11="Y","actual","plan")) | BG11: =IF(AND(N11=1,B11>=Inputs!$C$17),1,0)
A12: =Schedule!A12 | B12: =IF(Schedule!E12="","",Schedule!E12) | C12: =IF(Schedule!G12="","",Schedule!G12) | D12: =IF(Schedule!H12="","",Schedule!H12) | E12: =N(Schedule!I12) | F12: =N(Schedule!J12) | G12: =N(Schedule!K12) | H12: =N(Schedule!L12) | I12: =N(Schedule!M12) | J12: =IF(AND(B12<>"",B12>Inputs!$C$15),Scenarios!$H$14,Inputs!$C$33) | K12: =Inputs!$C$36 | L12: =IF(AND(Inputs!$C$65="unit",B12<>"",B12>=Inputs!$C$67,OR(Inputs!$C$68="",B12<=Inputs!$C$68)),1,0) | M12: =Inputs!$C$49 | N12: =IF(G12>0,1,0) | O12: =IF(D12="founding",G12-H12,0) | P12: =IF(D12="standard",G12-H12,0) | Q12: =O12*(K12*MIN(E12,Inputs!$C$37)+Inputs!$C$39*MAX(E12-Inputs!$C$37,0))+I12*K12*E12 | R12: =(P12+H12-I12)*(J12*MIN(E12,Inputs!$C$34)+Inputs!$C$39*MAX(E12-Inputs!$C$34,0)) | S12: =Q12+R12 | T12: =N12*E12*(Inputs!$C$58+Inputs!$C$59*MAX(G12-1,0)) | U12: =IF(N12=0,0,INDEX(Inputs!$C$95:$C$97,MATCH(C12,Inputs!$B$95:$B$97,0))+INDEX(Inputs!$D$95:$D$97,MATCH(C12,Inputs!$B$95:$B$97,0))*E12) | V12: =IF(N12=0,0,INDEX(Inputs!$E$95:$E$97,MATCH(C12,Inputs!$B$95:$B$97,0))*E12) | W12: =S12*Inputs!$C$48*M12 | X12: =N12*L12*Inputs!$C$66/Inputs!$C$75 | Y12: =N12*Inputs!$C$69/Inputs!$C$75 | Z12: =N12*Inputs!$C$71/Inputs!$C$75 | AA12: =SUM(T12:Z12) | AB12: =O12*Inputs!$C$79+P12*Inputs!$C$83+H12*Inputs!$C$84 | AC12: =N12*(F12*Inputs!$C$85+(E12-F12)*Inputs!$C$86) | AD12: =IF(N12=0,0,INDEX(Inputs!$F$95:$F$97,MATCH(C12,Inputs!$B$95:$B$97,0))+Inputs!$C$87*G12) | AE12: =IF(N12=0,0,INDEX(Inputs!$G$95:$G$97,MATCH(C12,Inputs!$B$95:$B$97,0))*E12) | AF12: =IF(N12=0,0,INDEX(Inputs!$H$95:$H$97,MATCH(C12,Inputs!$B$95:$B$97,0))*E12) | AG12: =Inputs!$C$88*G12 | AH12: =N12*Inputs!$C$89 | AI12: =SUM(AB12:AH12) | AJ12: =S12-AA12 | AK12: =IF(AI12>0,AJ12/AI12,"n/a") | AL12: =T12+U12+V12+W12 | AM12: =X12+Y12+Z12 | AO12: =IF(OR(N12=0,AP12=0),"",WORKDAY(B12,-Inputs!$C$43,Lists!$N$4:$N$30)+N(Inputs!$C$47)) | AP12: =Q12*Inputs!$C$42 | AQ12: =IF(OR(N12=0,AR12=0),"",WORKDAY(B12,-Inputs!$C$45,Lists!$N$4:$N$30)+N(Inputs!$C$47)) | AR12: =R12*Inputs!$C$44 | AS12: =IF(OR(N12=0,AT12=0),"",WORKDAY(B12,Inputs!$C$46,Lists!$N$4:$N$30)+N(Inputs!$C$47)) | AT12: =Q12*(1-Inputs!$C$42)+R12*(1-Inputs!$C$44) | AU12: =AP12*Inputs!$C$48*M12 | AV12: =AR12*Inputs!$C$48*M12 | AW12: =AT12*Inputs!$C$48*M12 | AX12: =IF(N12=0,"",WORKDAY(B12,-Inputs!$C$64,Lists!$N$4:$N$30)) | AY12: =IF(N12=0,"",B12) | AZ12: =IF(Schedule!N12="Y","Y","N") | BA12: =IF(AZ12="Y",Drop_Actuals!D12,S12) | BB12: =IF(AZ12="Y",Drop_Actuals!J12,AA12) | BC12: =IF(AZ12="Y",Drop_Actuals!R12,AI12) | BD12: =BA12-BB12 | BE12: =IF(BC12>0,BD12/BC12,"n/a") | BF12: =IF(AND(N12=0,AZ12="N"),"",IF(AZ12="Y","actual","plan")) | BG12: =IF(AND(N12=1,B12>=Inputs!$C$17),1,0)
A13: =Schedule!A13 | B13: =IF(Schedule!E13="","",Schedule!E13) | C13: =IF(Schedule!G13="","",Schedule!G13) | D13: =IF(Schedule!H13="","",Schedule!H13) | E13: =N(Schedule!I13) | F13: =N(Schedule!J13) | G13: =N(Schedule!K13) | H13: =N(Schedule!L13) | I13: =N(Schedule!M13) | J13: =IF(AND(B13<>"",B13>Inputs!$C$15),Scenarios!$H$14,Inputs!$C$33) | K13: =Inputs!$C$36 | L13: =IF(AND(Inputs!$C$65="unit",B13<>"",B13>=Inputs!$C$67,OR(Inputs!$C$68="",B13<=Inputs!$C$68)),1,0) | M13: =Inputs!$C$49 | N13: =IF(G13>0,1,0) | O13: =IF(D13="founding",G13-H13,0) | P13: =IF(D13="standard",G13-H13,0) | Q13: =O13*(K13*MIN(E13,Inputs!$C$37)+Inputs!$C$39*MAX(E13-Inputs!$C$37,0))+I13*K13*E13 | R13: =(P13+H13-I13)*(J13*MIN(E13,Inputs!$C$34)+Inputs!$C$39*MAX(E13-Inputs!$C$34,0)) | S13: =Q13+R13 | T13: =N13*E13*(Inputs!$C$58+Inputs!$C$59*MAX(G13-1,0)) | U13: =IF(N13=0,0,INDEX(Inputs!$C$95:$C$97,MATCH(C13,Inputs!$B$95:$B$97,0))+INDEX(Inputs!$D$95:$D$97,MATCH(C13,Inputs!$B$95:$B$97,0))*E13) | V13: =IF(N13=0,0,INDEX(Inputs!$E$95:$E$97,MATCH(C13,Inputs!$B$95:$B$97,0))*E13) | W13: =S13*Inputs!$C$48*M13 | X13: =N13*L13*Inputs!$C$66/Inputs!$C$75 | Y13: =N13*Inputs!$C$69/Inputs!$C$75 | Z13: =N13*Inputs!$C$71/Inputs!$C$75 | AA13: =SUM(T13:Z13) | AB13: =O13*Inputs!$C$79+P13*Inputs!$C$83+H13*Inputs!$C$84 | AC13: =N13*(F13*Inputs!$C$85+(E13-F13)*Inputs!$C$86) | AD13: =IF(N13=0,0,INDEX(Inputs!$F$95:$F$97,MATCH(C13,Inputs!$B$95:$B$97,0))+Inputs!$C$87*G13) | AE13: =IF(N13=0,0,INDEX(Inputs!$G$95:$G$97,MATCH(C13,Inputs!$B$95:$B$97,0))*E13) | AF13: =IF(N13=0,0,INDEX(Inputs!$H$95:$H$97,MATCH(C13,Inputs!$B$95:$B$97,0))*E13) | AG13: =Inputs!$C$88*G13 | AH13: =N13*Inputs!$C$89 | AI13: =SUM(AB13:AH13) | AJ13: =S13-AA13 | AK13: =IF(AI13>0,AJ13/AI13,"n/a") | AL13: =T13+U13+V13+W13 | AM13: =X13+Y13+Z13 | AO13: =IF(OR(N13=0,AP13=0),"",WORKDAY(B13,-Inputs!$C$43,Lists!$N$4:$N$30)+N(Inputs!$C$47)) | AP13: =Q13*Inputs!$C$42 | AQ13: =IF(OR(N13=0,AR13=0),"",WORKDAY(B13,-Inputs!$C$45,Lists!$N$4:$N$30)+N(Inputs!$C$47)) | AR13: =R13*Inputs!$C$44 | AS13: =IF(OR(N13=0,AT13=0),"",WORKDAY(B13,Inputs!$C$46,Lists!$N$4:$N$30)+N(Inputs!$C$47)) | AT13: =Q13*(1-Inputs!$C$42)+R13*(1-Inputs!$C$44) | AU13: =AP13*Inputs!$C$48*M13 | AV13: =AR13*Inputs!$C$48*M13 | AW13: =AT13*Inputs!$C$48*M13 | AX13: =IF(N13=0,"",WORKDAY(B13,-Inputs!$C$64,Lists!$N$4:$N$30)) | AY13: =IF(N13=0,"",B13) | AZ13: =IF(Schedule!N13="Y","Y","N") | BA13: =IF(AZ13="Y",Drop_Actuals!D13,S13) | BB13: =IF(AZ13="Y",Drop_Actuals!J13,AA13) | BC13: =IF(AZ13="Y",Drop_Actuals!R13,AI13) | BD13: =BA13-BB13 | BE13: =IF(BC13>0,BD13/BC13,"n/a") | BF13: =IF(AND(N13=0,AZ13="N"),"",IF(AZ13="Y","actual","plan")) | BG13: =IF(AND(N13=1,B13>=Inputs!$C$17),1,0)
A14: =Schedule!A14 | B14: =IF(Schedule!E14="","",Schedule!E14) | C14: =IF(Schedule!G14="","",Schedule!G14) | D14: =IF(Schedule!H14="","",Schedule!H14) | E14: =N(Schedule!I14) | F14: =N(Schedule!J14) | G14: =N(Schedule!K14) | H14: =N(Schedule!L14) | I14: =N(Schedule!M14) | J14: =IF(AND(B14<>"",B14>Inputs!$C$15),Scenarios!$H$14,Inputs!$C$33) | K14: =Inputs!$C$36 | L14: =IF(AND(Inputs!$C$65="unit",B14<>"",B14>=Inputs!$C$67,OR(Inputs!$C$68="",B14<=Inputs!$C$68)),1,0) | M14: =Inputs!$C$49 | N14: =IF(G14>0,1,0) | O14: =IF(D14="founding",G14-H14,0) | P14: =IF(D14="standard",G14-H14,0) | Q14: =O14*(K14*MIN(E14,Inputs!$C$37)+Inputs!$C$39*MAX(E14-Inputs!$C$37,0))+I14*K14*E14 | R14: =(P14+H14-I14)*(J14*MIN(E14,Inputs!$C$34)+Inputs!$C$39*MAX(E14-Inputs!$C$34,0)) | S14: =Q14+R14 | T14: =N14*E14*(Inputs!$C$58+Inputs!$C$59*MAX(G14-1,0)) | U14: =IF(N14=0,0,INDEX(Inputs!$C$95:$C$97,MATCH(C14,Inputs!$B$95:$B$97,0))+INDEX(Inputs!$D$95:$D$97,MATCH(C14,Inputs!$B$95:$B$97,0))*E14) | V14: =IF(N14=0,0,INDEX(Inputs!$E$95:$E$97,MATCH(C14,Inputs!$B$95:$B$97,0))*E14) | W14: =S14*Inputs!$C$48*M14 | X14: =N14*L14*Inputs!$C$66/Inputs!$C$75 | Y14: =N14*Inputs!$C$69/Inputs!$C$75 | Z14: =N14*Inputs!$C$71/Inputs!$C$75 | AA14: =SUM(T14:Z14) | AB14: =O14*Inputs!$C$79+P14*Inputs!$C$83+H14*Inputs!$C$84 | AC14: =N14*(F14*Inputs!$C$85+(E14-F14)*Inputs!$C$86) | AD14: =IF(N14=0,0,INDEX(Inputs!$F$95:$F$97,MATCH(C14,Inputs!$B$95:$B$97,0))+Inputs!$C$87*G14) | AE14: =IF(N14=0,0,INDEX(Inputs!$G$95:$G$97,MATCH(C14,Inputs!$B$95:$B$97,0))*E14) | AF14: =IF(N14=0,0,INDEX(Inputs!$H$95:$H$97,MATCH(C14,Inputs!$B$95:$B$97,0))*E14) | AG14: =Inputs!$C$88*G14 | AH14: =N14*Inputs!$C$89 | AI14: =SUM(AB14:AH14) | AJ14: =S14-AA14 | AK14: =IF(AI14>0,AJ14/AI14,"n/a") | AL14: =T14+U14+V14+W14 | AM14: =X14+Y14+Z14 | AO14: =IF(OR(N14=0,AP14=0),"",WORKDAY(B14,-Inputs!$C$43,Lists!$N$4:$N$30)+N(Inputs!$C$47)) | AP14: =Q14*Inputs!$C$42 | AQ14: =IF(OR(N14=0,AR14=0),"",WORKDAY(B14,-Inputs!$C$45,Lists!$N$4:$N$30)+N(Inputs!$C$47)) | AR14: =R14*Inputs!$C$44 | AS14: =IF(OR(N14=0,AT14=0),"",WORKDAY(B14,Inputs!$C$46,Lists!$N$4:$N$30)+N(Inputs!$C$47)) | AT14: =Q14*(1-Inputs!$C$42)+R14*(1-Inputs!$C$44) | AU14: =AP14*Inputs!$C$48*M14 | AV14: =AR14*Inputs!$C$48*M14 | AW14: =AT14*Inputs!$C$48*M14 | AX14: =IF(N14=0,"",WORKDAY(B14,-Inputs!$C$64,Lists!$N$4:$N$30)) | AY14: =IF(N14=0,"",B14) | AZ14: =IF(Schedule!N14="Y","Y","N") | BA14: =IF(AZ14="Y",Drop_Actuals!D14,S14) | BB14: =IF(AZ14="Y",Drop_Actuals!J14,AA14) | BC14: =IF(AZ14="Y",Drop_Actuals!R14,AI14) | BD14: =BA14-BB14 | BE14: =IF(BC14>0,BD14/BC14,"n/a") | BF14: =IF(AND(N14=0,AZ14="N"),"",IF(AZ14="Y","actual","plan")) | BG14: =IF(AND(N14=1,B14>=Inputs!$C$17),1,0)
A15: =Schedule!A15 | B15: =IF(Schedule!E15="","",Schedule!E15) | C15: =IF(Schedule!G15="","",Schedule!G15) | D15: =IF(Schedule!H15="","",Schedule!H15) | E15: =N(Schedule!I15) | F15: =N(Schedule!J15) | G15: =N(Schedule!K15) | H15: =N(Schedule!L15) | I15: =N(Schedule!M15) | J15: =IF(AND(B15<>"",B15>Inputs!$C$15),Scenarios!$H$14,Inputs!$C$33) | K15: =Inputs!$C$36 | L15: =IF(AND(Inputs!$C$65="unit",B15<>"",B15>=Inputs!$C$67,OR(Inputs!$C$68="",B15<=Inputs!$C$68)),1,0) | M15: =Inputs!$C$49 | N15: =IF(G15>0,1,0) | O15: =IF(D15="founding",G15-H15,0) | P15: =IF(D15="standard",G15-H15,0) | Q15: =O15*(K15*MIN(E15,Inputs!$C$37)+Inputs!$C$39*MAX(E15-Inputs!$C$37,0))+I15*K15*E15 | R15: =(P15+H15-I15)*(J15*MIN(E15,Inputs!$C$34)+Inputs!$C$39*MAX(E15-Inputs!$C$34,0)) | S15: =Q15+R15 | T15: =N15*E15*(Inputs!$C$58+Inputs!$C$59*MAX(G15-1,0)) | U15: =IF(N15=0,0,INDEX(Inputs!$C$95:$C$97,MATCH(C15,Inputs!$B$95:$B$97,0))+INDEX(Inputs!$D$95:$D$97,MATCH(C15,Inputs!$B$95:$B$97,0))*E15) | V15: =IF(N15=0,0,INDEX(Inputs!$E$95:$E$97,MATCH(C15,Inputs!$B$95:$B$97,0))*E15) | W15: =S15*Inputs!$C$48*M15 | X15: =N15*L15*Inputs!$C$66/Inputs!$C$75 | Y15: =N15*Inputs!$C$69/Inputs!$C$75 | Z15: =N15*Inputs!$C$71/Inputs!$C$75 | AA15: =SUM(T15:Z15) | AB15: =O15*Inputs!$C$79+P15*Inputs!$C$83+H15*Inputs!$C$84 | AC15: =N15*(F15*Inputs!$C$85+(E15-F15)*Inputs!$C$86) | AD15: =IF(N15=0,0,INDEX(Inputs!$F$95:$F$97,MATCH(C15,Inputs!$B$95:$B$97,0))+Inputs!$C$87*G15) | AE15: =IF(N15=0,0,INDEX(Inputs!$G$95:$G$97,MATCH(C15,Inputs!$B$95:$B$97,0))*E15) | AF15: =IF(N15=0,0,INDEX(Inputs!$H$95:$H$97,MATCH(C15,Inputs!$B$95:$B$97,0))*E15) | AG15: =Inputs!$C$88*G15 | AH15: =N15*Inputs!$C$89 | AI15: =SUM(AB15:AH15) | AJ15: =S15-AA15 | AK15: =IF(AI15>0,AJ15/AI15,"n/a") | AL15: =T15+U15+V15+W15 | AM15: =X15+Y15+Z15 | AO15: =IF(OR(N15=0,AP15=0),"",WORKDAY(B15,-Inputs!$C$43,Lists!$N$4:$N$30)+N(Inputs!$C$47)) | AP15: =Q15*Inputs!$C$42 | AQ15: =IF(OR(N15=0,AR15=0),"",WORKDAY(B15,-Inputs!$C$45,Lists!$N$4:$N$30)+N(Inputs!$C$47)) | AR15: =R15*Inputs!$C$44 | AS15: =IF(OR(N15=0,AT15=0),"",WORKDAY(B15,Inputs!$C$46,Lists!$N$4:$N$30)+N(Inputs!$C$47)) | AT15: =Q15*(1-Inputs!$C$42)+R15*(1-Inputs!$C$44) | AU15: =AP15*Inputs!$C$48*M15 | AV15: =AR15*Inputs!$C$48*M15 | AW15: =AT15*Inputs!$C$48*M15 | AX15: =IF(N15=0,"",WORKDAY(B15,-Inputs!$C$64,Lists!$N$4:$N$30)) | AY15: =IF(N15=0,"",B15) | AZ15: =IF(Schedule!N15="Y","Y","N") | BA15: =IF(AZ15="Y",Drop_Actuals!D15,S15) | BB15: =IF(AZ15="Y",Drop_Actuals!J15,AA15) | BC15: =IF(AZ15="Y",Drop_Actuals!R15,AI15) | BD15: =BA15-BB15 | BE15: =IF(BC15>0,BD15/BC15,"n/a") | BF15: =IF(AND(N15=0,AZ15="N"),"",IF(AZ15="Y","actual","plan")) | BG15: =IF(AND(N15=1,B15>=Inputs!$C$17),1,0)
A16: =Schedule!A16 | B16: =IF(Schedule!E16="","",Schedule!E16) | C16: =IF(Schedule!G16="","",Schedule!G16) | D16: =IF(Schedule!H16="","",Schedule!H16) | E16: =N(Schedule!I16) | F16: =N(Schedule!J16) | G16: =N(Schedule!K16) | H16: =N(Schedule!L16) | I16: =N(Schedule!M16) | J16: =IF(AND(B16<>"",B16>Inputs!$C$15),Scenarios!$H$14,Inputs!$C$33) | K16: =Inputs!$C$36 | L16: =IF(AND(Inputs!$C$65="unit",B16<>"",B16>=Inputs!$C$67,OR(Inputs!$C$68="",B16<=Inputs!$C$68)),1,0) | M16: =Inputs!$C$49 | N16: =IF(G16>0,1,0) | O16: =IF(D16="founding",G16-H16,0) | P16: =IF(D16="standard",G16-H16,0) | Q16: =O16*(K16*MIN(E16,Inputs!$C$37)+Inputs!$C$39*MAX(E16-Inputs!$C$37,0))+I16*K16*E16 | R16: =(P16+H16-I16)*(J16*MIN(E16,Inputs!$C$34)+Inputs!$C$39*MAX(E16-Inputs!$C$34,0)) | S16: =Q16+R16 | T16: =N16*E16*(Inputs!$C$58+Inputs!$C$59*MAX(G16-1,0)) | U16: =IF(N16=0,0,INDEX(Inputs!$C$95:$C$97,MATCH(C16,Inputs!$B$95:$B$97,0))+INDEX(Inputs!$D$95:$D$97,MATCH(C16,Inputs!$B$95:$B$97,0))*E16) | V16: =IF(N16=0,0,INDEX(Inputs!$E$95:$E$97,MATCH(C16,Inputs!$B$95:$B$97,0))*E16) | W16: =S16*Inputs!$C$48*M16 | X16: =N16*L16*Inputs!$C$66/Inputs!$C$75 | Y16: =N16*Inputs!$C$69/Inputs!$C$75 | Z16: =N16*Inputs!$C$71/Inputs!$C$75 | AA16: =SUM(T16:Z16) | AB16: =O16*Inputs!$C$79+P16*Inputs!$C$83+H16*Inputs!$C$84 | AC16: =N16*(F16*Inputs!$C$85+(E16-F16)*Inputs!$C$86) | AD16: =IF(N16=0,0,INDEX(Inputs!$F$95:$F$97,MATCH(C16,Inputs!$B$95:$B$97,0))+Inputs!$C$87*G16) | AE16: =IF(N16=0,0,INDEX(Inputs!$G$95:$G$97,MATCH(C16,Inputs!$B$95:$B$97,0))*E16) | AF16: =IF(N16=0,0,INDEX(Inputs!$H$95:$H$97,MATCH(C16,Inputs!$B$95:$B$97,0))*E16) | AG16: =Inputs!$C$88*G16 | AH16: =N16*Inputs!$C$89 | AI16: =SUM(AB16:AH16) | AJ16: =S16-AA16 | AK16: =IF(AI16>0,AJ16/AI16,"n/a") | AL16: =T16+U16+V16+W16 | AM16: =X16+Y16+Z16 | AO16: =IF(OR(N16=0,AP16=0),"",WORKDAY(B16,-Inputs!$C$43,Lists!$N$4:$N$30)+N(Inputs!$C$47)) | AP16: =Q16*Inputs!$C$42 | AQ16: =IF(OR(N16=0,AR16=0),"",WORKDAY(B16,-Inputs!$C$45,Lists!$N$4:$N$30)+N(Inputs!$C$47)) | AR16: =R16*Inputs!$C$44 | AS16: =IF(OR(N16=0,AT16=0),"",WORKDAY(B16,Inputs!$C$46,Lists!$N$4:$N$30)+N(Inputs!$C$47)) | AT16: =Q16*(1-Inputs!$C$42)+R16*(1-Inputs!$C$44) | AU16: =AP16*Inputs!$C$48*M16 | AV16: =AR16*Inputs!$C$48*M16 | AW16: =AT16*Inputs!$C$48*M16 | AX16: =IF(N16=0,"",WORKDAY(B16,-Inputs!$C$64,Lists!$N$4:$N$30)) | AY16: =IF(N16=0,"",B16) | AZ16: =IF(Schedule!N16="Y","Y","N") | BA16: =IF(AZ16="Y",Drop_Actuals!D16,S16) | BB16: =IF(AZ16="Y",Drop_Actuals!J16,AA16) | BC16: =IF(AZ16="Y",Drop_Actuals!R16,AI16) | BD16: =BA16-BB16 | BE16: =IF(BC16>0,BD16/BC16,"n/a") | BF16: =IF(AND(N16=0,AZ16="N"),"",IF(AZ16="Y","actual","plan")) | BG16: =IF(AND(N16=1,B16>=Inputs!$C$17),1,0)
A17: =Schedule!A17 | B17: =IF(Schedule!E17="","",Schedule!E17) | C17: =IF(Schedule!G17="","",Schedule!G17) | D17: =IF(Schedule!H17="","",Schedule!H17) | E17: =N(Schedule!I17) | F17: =N(Schedule!J17) | G17: =N(Schedule!K17) | H17: =N(Schedule!L17) | I17: =N(Schedule!M17) | J17: =IF(AND(B17<>"",B17>Inputs!$C$15),Scenarios!$H$14,Inputs!$C$33) | K17: =Inputs!$C$36 | L17: =IF(AND(Inputs!$C$65="unit",B17<>"",B17>=Inputs!$C$67,OR(Inputs!$C$68="",B17<=Inputs!$C$68)),1,0) | M17: =Inputs!$C$49 | N17: =IF(G17>0,1,0) | O17: =IF(D17="founding",G17-H17,0) | P17: =IF(D17="standard",G17-H17,0) | Q17: =O17*(K17*MIN(E17,Inputs!$C$37)+Inputs!$C$39*MAX(E17-Inputs!$C$37,0))+I17*K17*E17 | R17: =(P17+H17-I17)*(J17*MIN(E17,Inputs!$C$34)+Inputs!$C$39*MAX(E17-Inputs!$C$34,0)) | S17: =Q17+R17 | T17: =N17*E17*(Inputs!$C$58+Inputs!$C$59*MAX(G17-1,0)) | U17: =IF(N17=0,0,INDEX(Inputs!$C$95:$C$97,MATCH(C17,Inputs!$B$95:$B$97,0))+INDEX(Inputs!$D$95:$D$97,MATCH(C17,Inputs!$B$95:$B$97,0))*E17) | V17: =IF(N17=0,0,INDEX(Inputs!$E$95:$E$97,MATCH(C17,Inputs!$B$95:$B$97,0))*E17) | W17: =S17*Inputs!$C$48*M17 | X17: =N17*L17*Inputs!$C$66/Inputs!$C$75 | Y17: =N17*Inputs!$C$69/Inputs!$C$75 | Z17: =N17*Inputs!$C$71/Inputs!$C$75 | AA17: =SUM(T17:Z17) | AB17: =O17*Inputs!$C$79+P17*Inputs!$C$83+H17*Inputs!$C$84 | AC17: =N17*(F17*Inputs!$C$85+(E17-F17)*Inputs!$C$86) | AD17: =IF(N17=0,0,INDEX(Inputs!$F$95:$F$97,MATCH(C17,Inputs!$B$95:$B$97,0))+Inputs!$C$87*G17) | AE17: =IF(N17=0,0,INDEX(Inputs!$G$95:$G$97,MATCH(C17,Inputs!$B$95:$B$97,0))*E17) | AF17: =IF(N17=0,0,INDEX(Inputs!$H$95:$H$97,MATCH(C17,Inputs!$B$95:$B$97,0))*E17) | AG17: =Inputs!$C$88*G17 | AH17: =N17*Inputs!$C$89 | AI17: =SUM(AB17:AH17) | AJ17: =S17-AA17 | AK17: =IF(AI17>0,AJ17/AI17,"n/a") | AL17: =T17+U17+V17+W17 | AM17: =X17+Y17+Z17 | AO17: =IF(OR(N17=0,AP17=0),"",WORKDAY(B17,-Inputs!$C$43,Lists!$N$4:$N$30)+N(Inputs!$C$47)) | AP17: =Q17*Inputs!$C$42 | AQ17: =IF(OR(N17=0,AR17=0),"",WORKDAY(B17,-Inputs!$C$45,Lists!$N$4:$N$30)+N(Inputs!$C$47)) | AR17: =R17*Inputs!$C$44 | AS17: =IF(OR(N17=0,AT17=0),"",WORKDAY(B17,Inputs!$C$46,Lists!$N$4:$N$30)+N(Inputs!$C$47)) | AT17: =Q17*(1-Inputs!$C$42)+R17*(1-Inputs!$C$44) | AU17: =AP17*Inputs!$C$48*M17 | AV17: =AR17*Inputs!$C$48*M17 | AW17: =AT17*Inputs!$C$48*M17 | AX17: =IF(N17=0,"",WORKDAY(B17,-Inputs!$C$64,Lists!$N$4:$N$30)) | AY17: =IF(N17=0,"",B17) | AZ17: =IF(Schedule!N17="Y","Y","N") | BA17: =IF(AZ17="Y",Drop_Actuals!D17,S17) | BB17: =IF(AZ17="Y",Drop_Actuals!J17,AA17) | BC17: =IF(AZ17="Y",Drop_Actuals!R17,AI17) | BD17: =BA17-BB17 | BE17: =IF(BC17>0,BD17/BC17,"n/a") | BF17: =IF(AND(N17=0,AZ17="N"),"",IF(AZ17="Y","actual","plan")) | BG17: =IF(AND(N17=1,B17>=Inputs!$C$17),1,0)
A18: =Schedule!A18 | B18: =IF(Schedule!E18="","",Schedule!E18) | C18: =IF(Schedule!G18="","",Schedule!G18) | D18: =IF(Schedule!H18="","",Schedule!H18) | E18: =N(Schedule!I18) | F18: =N(Schedule!J18) | G18: =N(Schedule!K18) | H18: =N(Schedule!L18) | I18: =N(Schedule!M18) | J18: =IF(AND(B18<>"",B18>Inputs!$C$15),Scenarios!$H$14,Inputs!$C$33) | K18: =Inputs!$C$36 | L18: =IF(AND(Inputs!$C$65="unit",B18<>"",B18>=Inputs!$C$67,OR(Inputs!$C$68="",B18<=Inputs!$C$68)),1,0) | M18: =Inputs!$C$49 | N18: =IF(G18>0,1,0) | O18: =IF(D18="founding",G18-H18,0) | P18: =IF(D18="standard",G18-H18,0) | Q18: =O18*(K18*MIN(E18,Inputs!$C$37)+Inputs!$C$39*MAX(E18-Inputs!$C$37,0))+I18*K18*E18 | R18: =(P18+H18-I18)*(J18*MIN(E18,Inputs!$C$34)+Inputs!$C$39*MAX(E18-Inputs!$C$34,0)) | S18: =Q18+R18 | T18: =N18*E18*(Inputs!$C$58+Inputs!$C$59*MAX(G18-1,0)) | U18: =IF(N18=0,0,INDEX(Inputs!$C$95:$C$97,MATCH(C18,Inputs!$B$95:$B$97,0))+INDEX(Inputs!$D$95:$D$97,MATCH(C18,Inputs!$B$95:$B$97,0))*E18) | V18: =IF(N18=0,0,INDEX(Inputs!$E$95:$E$97,MATCH(C18,Inputs!$B$95:$B$97,0))*E18) | W18: =S18*Inputs!$C$48*M18 | X18: =N18*L18*Inputs!$C$66/Inputs!$C$75 | Y18: =N18*Inputs!$C$69/Inputs!$C$75 | Z18: =N18*Inputs!$C$71/Inputs!$C$75 | AA18: =SUM(T18:Z18) | AB18: =O18*Inputs!$C$79+P18*Inputs!$C$83+H18*Inputs!$C$84 | AC18: =N18*(F18*Inputs!$C$85+(E18-F18)*Inputs!$C$86) | AD18: =IF(N18=0,0,INDEX(Inputs!$F$95:$F$97,MATCH(C18,Inputs!$B$95:$B$97,0))+Inputs!$C$87*G18) | AE18: =IF(N18=0,0,INDEX(Inputs!$G$95:$G$97,MATCH(C18,Inputs!$B$95:$B$97,0))*E18) | AF18: =IF(N18=0,0,INDEX(Inputs!$H$95:$H$97,MATCH(C18,Inputs!$B$95:$B$97,0))*E18) | AG18: =Inputs!$C$88*G18 | AH18: =N18*Inputs!$C$89 | AI18: =SUM(AB18:AH18) | AJ18: =S18-AA18 | AK18: =IF(AI18>0,AJ18/AI18,"n/a") | AL18: =T18+U18+V18+W18 | AM18: =X18+Y18+Z18 | AO18: =IF(OR(N18=0,AP18=0),"",WORKDAY(B18,-Inputs!$C$43,Lists!$N$4:$N$30)+N(Inputs!$C$47)) | AP18: =Q18*Inputs!$C$42 | AQ18: =IF(OR(N18=0,AR18=0),"",WORKDAY(B18,-Inputs!$C$45,Lists!$N$4:$N$30)+N(Inputs!$C$47)) | AR18: =R18*Inputs!$C$44 | AS18: =IF(OR(N18=0,AT18=0),"",WORKDAY(B18,Inputs!$C$46,Lists!$N$4:$N$30)+N(Inputs!$C$47)) | AT18: =Q18*(1-Inputs!$C$42)+R18*(1-Inputs!$C$44) | AU18: =AP18*Inputs!$C$48*M18 | AV18: =AR18*Inputs!$C$48*M18 | AW18: =AT18*Inputs!$C$48*M18 | AX18: =IF(N18=0,"",WORKDAY(B18,-Inputs!$C$64,Lists!$N$4:$N$30)) | AY18: =IF(N18=0,"",B18) | AZ18: =IF(Schedule!N18="Y","Y","N") | BA18: =IF(AZ18="Y",Drop_Actuals!D18,S18) | BB18: =IF(AZ18="Y",Drop_Actuals!J18,AA18) | BC18: =IF(AZ18="Y",Drop_Actuals!R18,AI18) | BD18: =BA18-BB18 | BE18: =IF(BC18>0,BD18/BC18,"n/a") | BF18: =IF(AND(N18=0,AZ18="N"),"",IF(AZ18="Y","actual","plan")) | BG18: =IF(AND(N18=1,B18>=Inputs!$C$17),1,0)
A19: Totals (all scheduled drops) | E19: =SUM(E7:E18) | F19: =SUM(F7:F18) | G19: =SUM(G7:G18) | H19: =SUM(H7:H18) | S19: =SUM(S7:S18) | T19: =SUM(T7:T18) | U19: =SUM(U7:U18) | V19: =SUM(V7:V18) | W19: =SUM(W7:W18) | X19: =SUM(X7:X18) | Y19: =SUM(Y7:Y18) | Z19: =SUM(Z7:Z18) | ... AJ19: =SUM(AJ7:AJ18) | AK19: =IF(AI19>0,AJ19/AI19,"n/a") | AL19: =SUM(AL7:AL18) | AM19: =SUM(AM7:AM18) | AP19: =SUM(AP7:AP18) | AR19: =SUM(AR7:AR18) | AT19: =SUM(AT7:AT18) | AU19: =SUM(AU7:AU18) | AV19: =SUM(AV7:AV18) | AW19: =SUM(AW7:AW18) | BA19: =SUM(BA7:BA18) | BB19: =SUM(BB7:BB18) | BC19: =SUM(BC7:BC18) | BD19: =SUM(BD7:BD18) | BE19: =IF(BC19>0,BD19/BC19,"n/a")

Sheet Cash_Flow
A1: Six-month cash flow, weekly
A2: Startup outlays at their timing, brand cash on the plan's terms, overhead paid once from Cash_Ledger. Outflows are negative.
A3: Planning estimates, not a forecast. Drops switch to actual cash when Schedule says Actuals in = Y.
B4: Week | C4: 1 | D4: 2 | E4: 3 | F4: 4 | G4: 5 | H4: 6 | I4: 7 | J4: 8 | K4: 9 | L4: 10 | M4: 11 | N4: 12 | O4: 13 | P4: 14 | Q4: 15 | R4: 16 | S4: 17 | T4: 18 | U4: 19 | V4: 20 | W4: 21 | X4: 22 | Y4: 23 | Z4: 24 | AA4: 25 | AB4: 26 | AC4: Six months
B5: Week starts | C5: =Inputs!$C$10 | D5: =C5+Inputs!$C$18 | E5: =D5+Inputs!$C$18 | F5: =E5+Inputs!$C$18 | G5: =F5+Inputs!$C$18 | H5: =G5+Inputs!$C$18 | I5: =H5+Inputs!$C$18 | J5: =I5+Inputs!$C$18 | K5: =J5+Inputs!$C$18 | ... AB5: =AA5+Inputs!$C$18
B6: Week ends | C6: =C5+Inputs!$C$18-1 | D6: =D5+Inputs!$C$18-1 | E6: =E5+Inputs!$C$18-1 | F6: =F5+Inputs!$C$18-1 | G6: =G5+Inputs!$C$18-1 | H6: =H5+Inputs!$C$18-1 | I6: =I5+Inputs!$C$18-1 | J6: =J5+Inputs!$C$18-1 | ... AB6: =AB5+Inputs!$C$18-1
B7: Month | C7: =TEXT(C5,"mmm yyyy") | D7: =TEXT(D5,"mmm yyyy") | E7: =TEXT(E5,"mmm yyyy") | F7: =TEXT(F5,"mmm yyyy") | G7: =TEXT(G5,"mmm yyyy") | H7: =TEXT(H5,"mmm yyyy") | I7: =TEXT(I5,"mmm yyyy") | J7: =TEXT(J5,"mmm yyyy") | ... AB7: =TEXT(AB5,"mmm yyyy")
A8: Receipts
B9: Brand receipts, plan (drops without actuals) | C9: =SUMIFS(Drop_PnL!$AP$7:$AP$18,Drop_PnL!$AO$7:$AO$18,">="&C$5,Drop_PnL!$AO$7:$AO$18,"<="&C$6,Drop_PnL!$AZ$7:$AZ$18,"N")+SUMIFS(Drop_PnL!$AR$7:$AR$18,Drop_PnL!$AQ$7:$AQ$18,">="&C$5,Drop_PnL!$AQ$7:$AQ$18,"<="&C$6,Drop_PnL!$AZ$7:$AZ$18,"N")+SUMIFS(Drop_PnL!$AT$7:$AT$18,Drop_PnL!$AS$7:$AS$18,">="&C$5,Drop_PnL!$AS$7:$AS$18,"<="&C$6,Drop_PnL!$AZ$7:$AZ$18,"N") | D9: =SUMIFS(Drop_PnL!$AP$7:$AP$18,Drop_PnL!$AO$7:$AO$18,">="&D$5,Drop_PnL!$AO$7:$AO$18,"<="&D$6,Drop_PnL!$AZ$7:$AZ$18,"N")+SUMIFS(Drop_PnL!$AR$7:$AR$18,Drop_PnL!$AQ$7:$AQ$18,">="&D$5,Drop_PnL!$AQ$7:$AQ$18,"<="&D$6,Drop_PnL!$AZ$7:$AZ$18,"N")+SUMIFS(Drop_PnL!$AT$7:$AT$18,Drop_PnL!$AS$7:$AS$18,">="&D$5,Drop_PnL!$AS$7:$AS$18,"<="&D$6,Drop_PnL!$AZ$7:$AZ$18,"N") | E9: =SUMIFS(Drop_PnL!$AP$7:$AP$18,Drop_PnL!$AO$7:$AO$18,">="&E$5,Drop_PnL!$AO$7:$AO$18,"<="&E$6,Drop_PnL!$AZ$7:$AZ$18,"N")+SUMIFS(Drop_PnL!$AR$7:$AR$18,Drop_PnL!$AQ$7:$AQ$18,">="&E$5,Drop_PnL!$AQ$7:$AQ$18,"<="&E$6,Drop_PnL!$AZ$7:$AZ$18,"N")+SUMIFS(Drop_PnL!$AT$7:$AT$18,Drop_PnL!$AS$7:$AS$18,">="&E$5,Drop_PnL!$AS$7:$AS$18,"<="&E$6,Drop_PnL!$AZ$7:$AZ$18,"N") | F9: =SUMIFS(Drop_PnL!$AP$7:$AP$18,Drop_PnL!$AO$7:$AO$18,">="&F$5,Drop_PnL!$AO$7:$AO$18,"<="&F$6,Drop_PnL!$AZ$7:$AZ$18,"N")+SUMIFS(Drop_PnL!$AR$7:$AR$18,Drop_PnL!$AQ$7:$AQ$18,">="&F$5,Drop_PnL!$AQ$7:$AQ$18,"<="&F$6,Drop_PnL!$AZ$7:$AZ$18,"N")+SUMIFS(Drop_PnL!$AT$7:$AT$18,Drop_PnL!$AS$7:$AS$18,">="&F$5,Drop_PnL!$AS$7:$AS$18,"<="&F$6,Drop_PnL!$AZ$7:$AZ$18,"N") | G9: =SUMIFS(Drop_PnL!$AP$7:$AP$18,Drop_PnL!$AO$7:$AO$18,">="&G$5,Drop_PnL!$AO$7:$AO$18,"<="&G$6,Drop_PnL!$AZ$7:$AZ$18,"N")+SUMIFS(Drop_PnL!$AR$7:$AR$18,Drop_PnL!$AQ$7:$AQ$18,">="&G$5,Drop_PnL!$AQ$7:$AQ$18,"<="&G$6,Drop_PnL!$AZ$7:$AZ$18,"N")+SUMIFS(Drop_PnL!$AT$7:$AT$18,Drop_PnL!$AS$7:$AS$18,">="&G$5,Drop_PnL!$AS$7:$AS$18,"<="&G$6,Drop_PnL!$AZ$7:$AZ$18,"N") | H9: =SUMIFS(Drop_PnL!$AP$7:$AP$18,Drop_PnL!$AO$7:$AO$18,">="&H$5,Drop_PnL!$AO$7:$AO$18,"<="&H$6,Drop_PnL!$AZ$7:$AZ$18,"N")+SUMIFS(Drop_PnL!$AR$7:$AR$18,Drop_PnL!$AQ$7:$AQ$18,">="&H$5,Drop_PnL!$AQ$7:$AQ$18,"<="&H$6,Drop_PnL!$AZ$7:$AZ$18,"N")+SUMIFS(Drop_PnL!$AT$7:$AT$18,Drop_PnL!$AS$7:$AS$18,">="&H$5,Drop_PnL!$AS$7:$AS$18,"<="&H$6,Drop_PnL!$AZ$7:$AZ$18,"N") | I9: =SUMIFS(Drop_PnL!$AP$7:$AP$18,Drop_PnL!$AO$7:$AO$18,">="&I$5,Drop_PnL!$AO$7:$AO$18,"<="&I$6,Drop_PnL!$AZ$7:$AZ$18,"N")+SUMIFS(Drop_PnL!$AR$7:$AR$18,Drop_PnL!$AQ$7:$AQ$18,">="&I$5,Drop_PnL!$AQ$7:$AQ$18,"<="&I$6,Drop_PnL!$AZ$7:$AZ$18,"N")+SUMIFS(Drop_PnL!$AT$7:$AT$18,Drop_PnL!$AS$7:$AS$18,">="&I$5,Drop_PnL!$AS$7:$AS$18,"<="&I$6,Drop_PnL!$AZ$7:$AZ$18,"N") | J9: =SUMIFS(Drop_PnL!$AP$7:$AP$18,Drop_PnL!$AO$7:$AO$18,">="&J$5,Drop_PnL!$AO$7:$AO$18,"<="&J$6,Drop_PnL!$AZ$7:$AZ$18,"N")+SUMIFS(Drop_PnL!$AR$7:$AR$18,Drop_PnL!$AQ$7:$AQ$18,">="&J$5,Drop_PnL!$AQ$7:$AQ$18,"<="&J$6,Drop_PnL!$AZ$7:$AZ$18,"N")+SUMIFS(Drop_PnL!$AT$7:$AT$18,Drop_PnL!$AS$7:$AS$18,">="&J$5,Drop_PnL!$AS$7:$AS$18,"<="&J$6,Drop_PnL!$AZ$7:$AZ$18,"N") | ... AB9: =SUMIFS(Drop_PnL!$AP$7:$AP$18,Drop_PnL!$AO$7:$AO$18,">="&AB$5,Drop_PnL!$AO$7:$AO$18,"<="&AB$6,Drop_PnL!$AZ$7:$AZ$18,"N")+SUMIFS(Drop_PnL!$AR$7:$AR$18,Drop_PnL!$AQ$7:$AQ$18,">="&AB$5,Drop_PnL!$AQ$7:$AQ$18,"<="&AB$6,Drop_PnL!$AZ$7:$AZ$18,"N")+SUMIFS(Drop_PnL!$AT$7:$AT$18,Drop_PnL!$AS$7:$AS$18,">="&AB$5,Drop_PnL!$AS$7:$AS$18,"<="&AB$6,Drop_PnL!$AZ$7:$AZ$18,"N") | AC9: =SUM(C9:AB9)
B10: Brand receipts, actual (drops with actuals) | C10: =SUMIFS(Actuals_Campaigns!$X$5:$X$204,Actuals_Campaigns!$Y$5:$Y$204,">="&C$5,Actuals_Campaigns!$Y$5:$Y$204,"<="&C$6,Actuals_Campaigns!$AB$5:$AB$204,"Y")+SUMIFS(Actuals_Campaigns!$AC$5:$AC$204,Actuals_Campaigns!$S$5:$S$204,">="&C$5,Actuals_Campaigns!$S$5:$S$204,"<="&C$6,Actuals_Campaigns!$AB$5:$AB$204,"Y") | D10: =SUMIFS(Actuals_Campaigns!$X$5:$X$204,Actuals_Campaigns!$Y$5:$Y$204,">="&D$5,Actuals_Campaigns!$Y$5:$Y$204,"<="&D$6,Actuals_Campaigns!$AB$5:$AB$204,"Y")+SUMIFS(Actuals_Campaigns!$AC$5:$AC$204,Actuals_Campaigns!$S$5:$S$204,">="&D$5,Actuals_Campaigns!$S$5:$S$204,"<="&D$6,Actuals_Campaigns!$AB$5:$AB$204,"Y") | E10: =SUMIFS(Actuals_Campaigns!$X$5:$X$204,Actuals_Campaigns!$Y$5:$Y$204,">="&E$5,Actuals_Campaigns!$Y$5:$Y$204,"<="&E$6,Actuals_Campaigns!$AB$5:$AB$204,"Y")+SUMIFS(Actuals_Campaigns!$AC$5:$AC$204,Actuals_Campaigns!$S$5:$S$204,">="&E$5,Actuals_Campaigns!$S$5:$S$204,"<="&E$6,Actuals_Campaigns!$AB$5:$AB$204,"Y") | F10: =SUMIFS(Actuals_Campaigns!$X$5:$X$204,Actuals_Campaigns!$Y$5:$Y$204,">="&F$5,Actuals_Campaigns!$Y$5:$Y$204,"<="&F$6,Actuals_Campaigns!$AB$5:$AB$204,"Y")+SUMIFS(Actuals_Campaigns!$AC$5:$AC$204,Actuals_Campaigns!$S$5:$S$204,">="&F$5,Actuals_Campaigns!$S$5:$S$204,"<="&F$6,Actuals_Campaigns!$AB$5:$AB$204,"Y") | G10: =SUMIFS(Actuals_Campaigns!$X$5:$X$204,Actuals_Campaigns!$Y$5:$Y$204,">="&G$5,Actuals_Campaigns!$Y$5:$Y$204,"<="&G$6,Actuals_Campaigns!$AB$5:$AB$204,"Y")+SUMIFS(Actuals_Campaigns!$AC$5:$AC$204,Actuals_Campaigns!$S$5:$S$204,">="&G$5,Actuals_Campaigns!$S$5:$S$204,"<="&G$6,Actuals_Campaigns!$AB$5:$AB$204,"Y") | H10: =SUMIFS(Actuals_Campaigns!$X$5:$X$204,Actuals_Campaigns!$Y$5:$Y$204,">="&H$5,Actuals_Campaigns!$Y$5:$Y$204,"<="&H$6,Actuals_Campaigns!$AB$5:$AB$204,"Y")+SUMIFS(Actuals_Campaigns!$AC$5:$AC$204,Actuals_Campaigns!$S$5:$S$204,">="&H$5,Actuals_Campaigns!$S$5:$S$204,"<="&H$6,Actuals_Campaigns!$AB$5:$AB$204,"Y") | I10: =SUMIFS(Actuals_Campaigns!$X$5:$X$204,Actuals_Campaigns!$Y$5:$Y$204,">="&I$5,Actuals_Campaigns!$Y$5:$Y$204,"<="&I$6,Actuals_Campaigns!$AB$5:$AB$204,"Y")+SUMIFS(Actuals_Campaigns!$AC$5:$AC$204,Actuals_Campaigns!$S$5:$S$204,">="&I$5,Actuals_Campaigns!$S$5:$S$204,"<="&I$6,Actuals_Campaigns!$AB$5:$AB$204,"Y") | J10: =SUMIFS(Actuals_Campaigns!$X$5:$X$204,Actuals_Campaigns!$Y$5:$Y$204,">="&J$5,Actuals_Campaigns!$Y$5:$Y$204,"<="&J$6,Actuals_Campaigns!$AB$5:$AB$204,"Y")+SUMIFS(Actuals_Campaigns!$AC$5:$AC$204,Actuals_Campaigns!$S$5:$S$204,">="&J$5,Actuals_Campaigns!$S$5:$S$204,"<="&J$6,Actuals_Campaigns!$AB$5:$AB$204,"Y") | ... AB10: =SUMIFS(Actuals_Campaigns!$X$5:$X$204,Actuals_Campaigns!$Y$5:$Y$204,">="&AB$5,Actuals_Campaigns!$Y$5:$Y$204,"<="&AB$6,Actuals_Campaigns!$AB$5:$AB$204,"Y")+SUMIFS(Actuals_Campaigns!$AC$5:$AC$204,Actuals_Campaigns!$S$5:$S$204,">="&AB$5,Actuals_Campaigns!$S$5:$S$204,"<="&AB$6,Actuals_Campaigns!$AB$5:$AB$204,"Y") | AC10: =SUM(C10:AB10)
B11: Total receipts | C11: =SUM(C9:C10) | D11: =SUM(D9:D10) | E11: =SUM(E9:E10) | F11: =SUM(F9:F10) | G11: =SUM(G9:G10) | H11: =SUM(H9:H10) | I11: =SUM(I9:I10) | J11: =SUM(J9:J10) | ... AB11: =SUM(AB9:AB10) | AC11: =SUM(C11:AB11)
A12: Direct drop costs
B13: Display kits, plan | C13: =-SUMIFS(Drop_PnL!$T$7:$T$18,Drop_PnL!$AX$7:$AX$18,">="&C$5,Drop_PnL!$AX$7:$AX$18,"<="&C$6,Drop_PnL!$AZ$7:$AZ$18,"N") | D13: =-SUMIFS(Drop_PnL!$T$7:$T$18,Drop_PnL!$AX$7:$AX$18,">="&D$5,Drop_PnL!$AX$7:$AX$18,"<="&D$6,Drop_PnL!$AZ$7:$AZ$18,"N") | E13: =-SUMIFS(Drop_PnL!$T$7:$T$18,Drop_PnL!$AX$7:$AX$18,">="&E$5,Drop_PnL!$AX$7:$AX$18,"<="&E$6,Drop_PnL!$AZ$7:$AZ$18,"N") | F13: =-SUMIFS(Drop_PnL!$T$7:$T$18,Drop_PnL!$AX$7:$AX$18,">="&F$5,Drop_PnL!$AX$7:$AX$18,"<="&F$6,Drop_PnL!$AZ$7:$AZ$18,"N") | G13: =-SUMIFS(Drop_PnL!$T$7:$T$18,Drop_PnL!$AX$7:$AX$18,">="&G$5,Drop_PnL!$AX$7:$AX$18,"<="&G$6,Drop_PnL!$AZ$7:$AZ$18,"N") | H13: =-SUMIFS(Drop_PnL!$T$7:$T$18,Drop_PnL!$AX$7:$AX$18,">="&H$5,Drop_PnL!$AX$7:$AX$18,"<="&H$6,Drop_PnL!$AZ$7:$AZ$18,"N") | I13: =-SUMIFS(Drop_PnL!$T$7:$T$18,Drop_PnL!$AX$7:$AX$18,">="&I$5,Drop_PnL!$AX$7:$AX$18,"<="&I$6,Drop_PnL!$AZ$7:$AZ$18,"N") | J13: =-SUMIFS(Drop_PnL!$T$7:$T$18,Drop_PnL!$AX$7:$AX$18,">="&J$5,Drop_PnL!$AX$7:$AX$18,"<="&J$6,Drop_PnL!$AZ$7:$AZ$18,"N") | ... AB13: =-SUMIFS(Drop_PnL!$T$7:$T$18,Drop_PnL!$AX$7:$AX$18,">="&AB$5,Drop_PnL!$AX$7:$AX$18,"<="&AB$6,Drop_PnL!$AZ$7:$AZ$18,"N") | AC13: =SUM(C13:AB13)
B14: Transport, plan | C14: =-SUMIFS(Drop_PnL!$U$7:$U$18,Drop_PnL!$AY$7:$AY$18,">="&C$5,Drop_PnL!$AY$7:$AY$18,"<="&C$6,Drop_PnL!$AZ$7:$AZ$18,"N") | D14: =-SUMIFS(Drop_PnL!$U$7:$U$18,Drop_PnL!$AY$7:$AY$18,">="&D$5,Drop_PnL!$AY$7:$AY$18,"<="&D$6,Drop_PnL!$AZ$7:$AZ$18,"N") | E14: =-SUMIFS(Drop_PnL!$U$7:$U$18,Drop_PnL!$AY$7:$AY$18,">="&E$5,Drop_PnL!$AY$7:$AY$18,"<="&E$6,Drop_PnL!$AZ$7:$AZ$18,"N") | F14: =-SUMIFS(Drop_PnL!$U$7:$U$18,Drop_PnL!$AY$7:$AY$18,">="&F$5,Drop_PnL!$AY$7:$AY$18,"<="&F$6,Drop_PnL!$AZ$7:$AZ$18,"N") | G14: =-SUMIFS(Drop_PnL!$U$7:$U$18,Drop_PnL!$AY$7:$AY$18,">="&G$5,Drop_PnL!$AY$7:$AY$18,"<="&G$6,Drop_PnL!$AZ$7:$AZ$18,"N") | H14: =-SUMIFS(Drop_PnL!$U$7:$U$18,Drop_PnL!$AY$7:$AY$18,">="&H$5,Drop_PnL!$AY$7:$AY$18,"<="&H$6,Drop_PnL!$AZ$7:$AZ$18,"N") | I14: =-SUMIFS(Drop_PnL!$U$7:$U$18,Drop_PnL!$AY$7:$AY$18,">="&I$5,Drop_PnL!$AY$7:$AY$18,"<="&I$6,Drop_PnL!$AZ$7:$AZ$18,"N") | J14: =-SUMIFS(Drop_PnL!$U$7:$U$18,Drop_PnL!$AY$7:$AY$18,">="&J$5,Drop_PnL!$AY$7:$AY$18,"<="&J$6,Drop_PnL!$AZ$7:$AZ$18,"N") | ... AB14: =-SUMIFS(Drop_PnL!$U$7:$U$18,Drop_PnL!$AY$7:$AY$18,">="&AB$5,Drop_PnL!$AY$7:$AY$18,"<="&AB$6,Drop_PnL!$AZ$7:$AZ$18,"N") | AC14: =SUM(C14:AB14)
B15: Kit mailing, plan (needs quote) | C15: =-SUMIFS(Drop_PnL!$V$7:$V$18,Drop_PnL!$AX$7:$AX$18,">="&C$5,Drop_PnL!$AX$7:$AX$18,"<="&C$6,Drop_PnL!$AZ$7:$AZ$18,"N") | D15: =-SUMIFS(Drop_PnL!$V$7:$V$18,Drop_PnL!$AX$7:$AX$18,">="&D$5,Drop_PnL!$AX$7:$AX$18,"<="&D$6,Drop_PnL!$AZ$7:$AZ$18,"N") | E15: =-SUMIFS(Drop_PnL!$V$7:$V$18,Drop_PnL!$AX$7:$AX$18,">="&E$5,Drop_PnL!$AX$7:$AX$18,"<="&E$6,Drop_PnL!$AZ$7:$AZ$18,"N") | F15: =-SUMIFS(Drop_PnL!$V$7:$V$18,Drop_PnL!$AX$7:$AX$18,">="&F$5,Drop_PnL!$AX$7:$AX$18,"<="&F$6,Drop_PnL!$AZ$7:$AZ$18,"N") | G15: =-SUMIFS(Drop_PnL!$V$7:$V$18,Drop_PnL!$AX$7:$AX$18,">="&G$5,Drop_PnL!$AX$7:$AX$18,"<="&G$6,Drop_PnL!$AZ$7:$AZ$18,"N") | H15: =-SUMIFS(Drop_PnL!$V$7:$V$18,Drop_PnL!$AX$7:$AX$18,">="&H$5,Drop_PnL!$AX$7:$AX$18,"<="&H$6,Drop_PnL!$AZ$7:$AZ$18,"N") | I15: =-SUMIFS(Drop_PnL!$V$7:$V$18,Drop_PnL!$AX$7:$AX$18,">="&I$5,Drop_PnL!$AX$7:$AX$18,"<="&I$6,Drop_PnL!$AZ$7:$AZ$18,"N") | J15: =-SUMIFS(Drop_PnL!$V$7:$V$18,Drop_PnL!$AX$7:$AX$18,">="&J$5,Drop_PnL!$AX$7:$AX$18,"<="&J$6,Drop_PnL!$AZ$7:$AZ$18,"N") | ... AB15: =-SUMIFS(Drop_PnL!$V$7:$V$18,Drop_PnL!$AX$7:$AX$18,">="&AB$5,Drop_PnL!$AX$7:$AX$18,"<="&AB$6,Drop_PnL!$AZ$7:$AZ$18,"N") | AC15: =SUM(C15:AB15)
B16: Card processing, plan | C16: =-(SUMIFS(Drop_PnL!$AU$7:$AU$18,Drop_PnL!$AO$7:$AO$18,">="&C$5,Drop_PnL!$AO$7:$AO$18,"<="&C$6,Drop_PnL!$AZ$7:$AZ$18,"N")+SUMIFS(Drop_PnL!$AV$7:$AV$18,Drop_PnL!$AQ$7:$AQ$18,">="&C$5,Drop_PnL!$AQ$7:$AQ$18,"<="&C$6,Drop_PnL!$AZ$7:$AZ$18,"N")+SUMIFS(Drop_PnL!$AW$7:$AW$18,Drop_PnL!$AS$7:$AS$18,">="&C$5,Drop_PnL!$AS$7:$AS$18,"<="&C$6,Drop_PnL!$AZ$7:$AZ$18,"N")) | D16: =-(SUMIFS(Drop_PnL!$AU$7:$AU$18,Drop_PnL!$AO$7:$AO$18,">="&D$5,Drop_PnL!$AO$7:$AO$18,"<="&D$6,Drop_PnL!$AZ$7:$AZ$18,"N")+SUMIFS(Drop_PnL!$AV$7:$AV$18,Drop_PnL!$AQ$7:$AQ$18,">="&D$5,Drop_PnL!$AQ$7:$AQ$18,"<="&D$6,Drop_PnL!$AZ$7:$AZ$18,"N")+SUMIFS(Drop_PnL!$AW$7:$AW$18,Drop_PnL!$AS$7:$AS$18,">="&D$5,Drop_PnL!$AS$7:$AS$18,"<="&D$6,Drop_PnL!$AZ$7:$AZ$18,"N")) | E16: =-(SUMIFS(Drop_PnL!$AU$7:$AU$18,Drop_PnL!$AO$7:$AO$18,">="&E$5,Drop_PnL!$AO$7:$AO$18,"<="&E$6,Drop_PnL!$AZ$7:$AZ$18,"N")+SUMIFS(Drop_PnL!$AV$7:$AV$18,Drop_PnL!$AQ$7:$AQ$18,">="&E$5,Drop_PnL!$AQ$7:$AQ$18,"<="&E$6,Drop_PnL!$AZ$7:$AZ$18,"N")+SUMIFS(Drop_PnL!$AW$7:$AW$18,Drop_PnL!$AS$7:$AS$18,">="&E$5,Drop_PnL!$AS$7:$AS$18,"<="&E$6,Drop_PnL!$AZ$7:$AZ$18,"N")) | F16: =-(SUMIFS(Drop_PnL!$AU$7:$AU$18,Drop_PnL!$AO$7:$AO$18,">="&F$5,Drop_PnL!$AO$7:$AO$18,"<="&F$6,Drop_PnL!$AZ$7:$AZ$18,"N")+SUMIFS(Drop_PnL!$AV$7:$AV$18,Drop_PnL!$AQ$7:$AQ$18,">="&F$5,Drop_PnL!$AQ$7:$AQ$18,"<="&F$6,Drop_PnL!$AZ$7:$AZ$18,"N")+SUMIFS(Drop_PnL!$AW$7:$AW$18,Drop_PnL!$AS$7:$AS$18,">="&F$5,Drop_PnL!$AS$7:$AS$18,"<="&F$6,Drop_PnL!$AZ$7:$AZ$18,"N")) | G16: =-(SUMIFS(Drop_PnL!$AU$7:$AU$18,Drop_PnL!$AO$7:$AO$18,">="&G$5,Drop_PnL!$AO$7:$AO$18,"<="&G$6,Drop_PnL!$AZ$7:$AZ$18,"N")+SUMIFS(Drop_PnL!$AV$7:$AV$18,Drop_PnL!$AQ$7:$AQ$18,">="&G$5,Drop_PnL!$AQ$7:$AQ$18,"<="&G$6,Drop_PnL!$AZ$7:$AZ$18,"N")+SUMIFS(Drop_PnL!$AW$7:$AW$18,Drop_PnL!$AS$7:$AS$18,">="&G$5,Drop_PnL!$AS$7:$AS$18,"<="&G$6,Drop_PnL!$AZ$7:$AZ$18,"N")) | H16: =-(SUMIFS(Drop_PnL!$AU$7:$AU$18,Drop_PnL!$AO$7:$AO$18,">="&H$5,Drop_PnL!$AO$7:$AO$18,"<="&H$6,Drop_PnL!$AZ$7:$AZ$18,"N")+SUMIFS(Drop_PnL!$AV$7:$AV$18,Drop_PnL!$AQ$7:$AQ$18,">="&H$5,Drop_PnL!$AQ$7:$AQ$18,"<="&H$6,Drop_PnL!$AZ$7:$AZ$18,"N")+SUMIFS(Drop_PnL!$AW$7:$AW$18,Drop_PnL!$AS$7:$AS$18,">="&H$5,Drop_PnL!$AS$7:$AS$18,"<="&H$6,Drop_PnL!$AZ$7:$AZ$18,"N")) | I16: =-(SUMIFS(Drop_PnL!$AU$7:$AU$18,Drop_PnL!$AO$7:$AO$18,">="&I$5,Drop_PnL!$AO$7:$AO$18,"<="&I$6,Drop_PnL!$AZ$7:$AZ$18,"N")+SUMIFS(Drop_PnL!$AV$7:$AV$18,Drop_PnL!$AQ$7:$AQ$18,">="&I$5,Drop_PnL!$AQ$7:$AQ$18,"<="&I$6,Drop_PnL!$AZ$7:$AZ$18,"N")+SUMIFS(Drop_PnL!$AW$7:$AW$18,Drop_PnL!$AS$7:$AS$18,">="&I$5,Drop_PnL!$AS$7:$AS$18,"<="&I$6,Drop_PnL!$AZ$7:$AZ$18,"N")) | J16: =-(SUMIFS(Drop_PnL!$AU$7:$AU$18,Drop_PnL!$AO$7:$AO$18,">="&J$5,Drop_PnL!$AO$7:$AO$18,"<="&J$6,Drop_PnL!$AZ$7:$AZ$18,"N")+SUMIFS(Drop_PnL!$AV$7:$AV$18,Drop_PnL!$AQ$7:$AQ$18,">="&J$5,Drop_PnL!$AQ$7:$AQ$18,"<="&J$6,Drop_PnL!$AZ$7:$AZ$18,"N")+SUMIFS(Drop_PnL!$AW$7:$AW$18,Drop_PnL!$AS$7:$AS$18,">="&J$5,Drop_PnL!$AS$7:$AS$18,"<="&J$6,Drop_PnL!$AZ$7:$AZ$18,"N")) | ... AB16: =-(SUMIFS(Drop_PnL!$AU$7:$AU$18,Drop_PnL!$AO$7:$AO$18,">="&AB$5,Drop_PnL!$AO$7:$AO$18,"<="&AB$6,Drop_PnL!$AZ$7:$AZ$18,"N")+SUMIFS(Drop_PnL!$AV$7:$AV$18,Drop_PnL!$AQ$7:$AQ$18,">="&AB$5,Drop_PnL!$AQ$7:$AQ$18,"<="&AB$6,Drop_PnL!$AZ$7:$AZ$18,"N")+SUMIFS(Drop_PnL!$AW$7:$AW$18,Drop_PnL!$AS$7:$AS$18,">="&AB$5,Drop_PnL!$AS$7:$AS$18,"<="&AB$6,Drop_PnL!$AZ$7:$AZ$18,"N")) | AC16: =SUM(C16:AB16)
B17: Direct costs and processing, actual | C17: =-(SUMIFS(Actuals_DropCosts!$F$5:$F$104,Actuals_DropCosts!$B$5:$B$104,">="&C$5,Actuals_DropCosts!$B$5:$B$104,"<="&C$6,Actuals_DropCosts!$K$5:$K$104,"Y")+SUMIFS(Actuals_DropCosts!$G$5:$G$104,Actuals_DropCosts!$B$5:$B$104,">="&C$5,Actuals_DropCosts!$B$5:$B$104,"<="&C$6,Actuals_DropCosts!$K$5:$K$104,"Y")+SUMIFS(Actuals_DropCosts!$H$5:$H$104,Actuals_DropCosts!$B$5:$B$104,">="&C$5,Actuals_DropCosts!$B$5:$B$104,"<="&C$6,Actuals_DropCosts!$K$5:$K$104,"Y")+SUMIFS(Actuals_Campaigns!$T$5:$T$204,Actuals_Campaigns!$S$5:$S$204,">="&C$5,Actuals_Campaigns!$S$5:$S$204,"<="&C$6,Actuals_Campaigns!$AB$5:$AB$204,"Y")) | D17: =-(SUMIFS(Actuals_DropCosts!$F$5:$F$104,Actuals_DropCosts!$B$5:$B$104,">="&D$5,Actuals_DropCosts!$B$5:$B$104,"<="&D$6,Actuals_DropCosts!$K$5:$K$104,"Y")+SUMIFS(Actuals_DropCosts!$G$5:$G$104,Actuals_DropCosts!$B$5:$B$104,">="&D$5,Actuals_DropCosts!$B$5:$B$104,"<="&D$6,Actuals_DropCosts!$K$5:$K$104,"Y")+SUMIFS(Actuals_DropCosts!$H$5:$H$104,Actuals_DropCosts!$B$5:$B$104,">="&D$5,Actuals_DropCosts!$B$5:$B$104,"<="&D$6,Actuals_DropCosts!$K$5:$K$104,"Y")+SUMIFS(Actuals_Campaigns!$T$5:$T$204,Actuals_Campaigns!$S$5:$S$204,">="&D$5,Actuals_Campaigns!$S$5:$S$204,"<="&D$6,Actuals_Campaigns!$AB$5:$AB$204,"Y")) | E17: =-(SUMIFS(Actuals_DropCosts!$F$5:$F$104,Actuals_DropCosts!$B$5:$B$104,">="&E$5,Actuals_DropCosts!$B$5:$B$104,"<="&E$6,Actuals_DropCosts!$K$5:$K$104,"Y")+SUMIFS(Actuals_DropCosts!$G$5:$G$104,Actuals_DropCosts!$B$5:$B$104,">="&E$5,Actuals_DropCosts!$B$5:$B$104,"<="&E$6,Actuals_DropCosts!$K$5:$K$104,"Y")+SUMIFS(Actuals_DropCosts!$H$5:$H$104,Actuals_DropCosts!$B$5:$B$104,">="&E$5,Actuals_DropCosts!$B$5:$B$104,"<="&E$6,Actuals_DropCosts!$K$5:$K$104,"Y")+SUMIFS(Actuals_Campaigns!$T$5:$T$204,Actuals_Campaigns!$S$5:$S$204,">="&E$5,Actuals_Campaigns!$S$5:$S$204,"<="&E$6,Actuals_Campaigns!$AB$5:$AB$204,"Y")) | F17: =-(SUMIFS(Actuals_DropCosts!$F$5:$F$104,Actuals_DropCosts!$B$5:$B$104,">="&F$5,Actuals_DropCosts!$B$5:$B$104,"<="&F$6,Actuals_DropCosts!$K$5:$K$104,"Y")+SUMIFS(Actuals_DropCosts!$G$5:$G$104,Actuals_DropCosts!$B$5:$B$104,">="&F$5,Actuals_DropCosts!$B$5:$B$104,"<="&F$6,Actuals_DropCosts!$K$5:$K$104,"Y")+SUMIFS(Actuals_DropCosts!$H$5:$H$104,Actuals_DropCosts!$B$5:$B$104,">="&F$5,Actuals_DropCosts!$B$5:$B$104,"<="&F$6,Actuals_DropCosts!$K$5:$K$104,"Y")+SUMIFS(Actuals_Campaigns!$T$5:$T$204,Actuals_Campaigns!$S$5:$S$204,">="&F$5,Actuals_Campaigns!$S$5:$S$204,"<="&F$6,Actuals_Campaigns!$AB$5:$AB$204,"Y")) | G17: =-(SUMIFS(Actuals_DropCosts!$F$5:$F$104,Actuals_DropCosts!$B$5:$B$104,">="&G$5,Actuals_DropCosts!$B$5:$B$104,"<="&G$6,Actuals_DropCosts!$K$5:$K$104,"Y")+SUMIFS(Actuals_DropCosts!$G$5:$G$104,Actuals_DropCosts!$B$5:$B$104,">="&G$5,Actuals_DropCosts!$B$5:$B$104,"<="&G$6,Actuals_DropCosts!$K$5:$K$104,"Y")+SUMIFS(Actuals_DropCosts!$H$5:$H$104,Actuals_DropCosts!$B$5:$B$104,">="&G$5,Actuals_DropCosts!$B$5:$B$104,"<="&G$6,Actuals_DropCosts!$K$5:$K$104,"Y")+SUMIFS(Actuals_Campaigns!$T$5:$T$204,Actuals_Campaigns!$S$5:$S$204,">="&G$5,Actuals_Campaigns!$S$5:$S$204,"<="&G$6,Actuals_Campaigns!$AB$5:$AB$204,"Y")) | H17: =-(SUMIFS(Actuals_DropCosts!$F$5:$F$104,Actuals_DropCosts!$B$5:$B$104,">="&H$5,Actuals_DropCosts!$B$5:$B$104,"<="&H$6,Actuals_DropCosts!$K$5:$K$104,"Y")+SUMIFS(Actuals_DropCosts!$G$5:$G$104,Actuals_DropCosts!$B$5:$B$104,">="&H$5,Actuals_DropCosts!$B$5:$B$104,"<="&H$6,Actuals_DropCosts!$K$5:$K$104,"Y")+SUMIFS(Actuals_DropCosts!$H$5:$H$104,Actuals_DropCosts!$B$5:$B$104,">="&H$5,Actuals_DropCosts!$B$5:$B$104,"<="&H$6,Actuals_DropCosts!$K$5:$K$104,"Y")+SUMIFS(Actuals_Campaigns!$T$5:$T$204,Actuals_Campaigns!$S$5:$S$204,">="&H$5,Actuals_Campaigns!$S$5:$S$204,"<="&H$6,Actuals_Campaigns!$AB$5:$AB$204,"Y")) | I17: =-(SUMIFS(Actuals_DropCosts!$F$5:$F$104,Actuals_DropCosts!$B$5:$B$104,">="&I$5,Actuals_DropCosts!$B$5:$B$104,"<="&I$6,Actuals_DropCosts!$K$5:$K$104,"Y")+SUMIFS(Actuals_DropCosts!$G$5:$G$104,Actuals_DropCosts!$B$5:$B$104,">="&I$5,Actuals_DropCosts!$B$5:$B$104,"<="&I$6,Actuals_DropCosts!$K$5:$K$104,"Y")+SUMIFS(Actuals_DropCosts!$H$5:$H$104,Actuals_DropCosts!$B$5:$B$104,">="&I$5,Actuals_DropCosts!$B$5:$B$104,"<="&I$6,Actuals_DropCosts!$K$5:$K$104,"Y")+SUMIFS(Actuals_Campaigns!$T$5:$T$204,Actuals_Campaigns!$S$5:$S$204,">="&I$5,Actuals_Campaigns!$S$5:$S$204,"<="&I$6,Actuals_Campaigns!$AB$5:$AB$204,"Y")) | J17: =-(SUMIFS(Actuals_DropCosts!$F$5:$F$104,Actuals_DropCosts!$B$5:$B$104,">="&J$5,Actuals_DropCosts!$B$5:$B$104,"<="&J$6,Actuals_DropCosts!$K$5:$K$104,"Y")+SUMIFS(Actuals_DropCosts!$G$5:$G$104,Actuals_DropCosts!$B$5:$B$104,">="&J$5,Actuals_DropCosts!$B$5:$B$104,"<="&J$6,Actuals_DropCosts!$K$5:$K$104,"Y")+SUMIFS(Actuals_DropCosts!$H$5:$H$104,Actuals_DropCosts!$B$5:$B$104,">="&J$5,Actuals_DropCosts!$B$5:$B$104,"<="&J$6,Actuals_DropCosts!$K$5:$K$104,"Y")+SUMIFS(Actuals_Campaigns!$T$5:$T$204,Actuals_Campaigns!$S$5:$S$204,">="&J$5,Actuals_Campaigns!$S$5:$S$204,"<="&J$6,Actuals_Campaigns!$AB$5:$AB$204,"Y")) | ... AB17: =-(SUMIFS(Actuals_DropCosts!$F$5:$F$104,Actuals_DropCosts!$B$5:$B$104,">="&AB$5,Actuals_DropCosts!$B$5:$B$104,"<="&AB$6,Actuals_DropCosts!$K$5:$K$104,"Y")+SUMIFS(Actuals_DropCosts!$G$5:$G$104,Actuals_DropCosts!$B$5:$B$104,">="&AB$5,Actuals_DropCosts!$B$5:$B$104,"<="&AB$6,Actuals_DropCosts!$K$5:$K$104,"Y")+SUMIFS(Actuals_DropCosts!$H$5:$H$104,Actuals_DropCosts!$B$5:$B$104,">="&AB$5,Actuals_DropCosts!$B$5:$B$104,"<="&AB$6,Actuals_DropCosts!$K$5:$K$104,"Y")+SUMIFS(Actuals_Campaigns!$T$5:$T$204,Actuals_Campaigns!$S$5:$S$204,">="&AB$5,Actuals_Campaigns!$S$5:$S$204,"<="&AB$6,Actuals_Campaigns!$AB$5:$AB$204,"Y")) | AC17: =SUM(C17:AB17)
B18: Total direct costs | C18: =SUM(C13:C17) | D18: =SUM(D13:D17) | E18: =SUM(E13:E17) | F18: =SUM(F13:F17) | G18: =SUM(G13:G17) | H18: =SUM(H13:H17) | I18: =SUM(I13:I17) | J18: =SUM(J13:J17) | ... AB18: =SUM(AB13:AB17) | AC18: =SUM(C18:AB18)
A19: Overhead, paid once here (drop allocations are views of these lines)
B20: Software | C20: =-SUMIFS(Cash_Ledger!$D$5:$D$53,Cash_Ledger!$C$5:$C$53,">="&C$5,Cash_Ledger!$C$5:$C$53,"<="&C$6,Cash_Ledger!$A$5:$A$53,"software") | D20: =-SUMIFS(Cash_Ledger!$D$5:$D$53,Cash_Ledger!$C$5:$C$53,">="&D$5,Cash_Ledger!$C$5:$C$53,"<="&D$6,Cash_Ledger!$A$5:$A$53,"software") | E20: =-SUMIFS(Cash_Ledger!$D$5:$D$53,Cash_Ledger!$C$5:$C$53,">="&E$5,Cash_Ledger!$C$5:$C$53,"<="&E$6,Cash_Ledger!$A$5:$A$53,"software") | F20: =-SUMIFS(Cash_Ledger!$D$5:$D$53,Cash_Ledger!$C$5:$C$53,">="&F$5,Cash_Ledger!$C$5:$C$53,"<="&F$6,Cash_Ledger!$A$5:$A$53,"software") | G20: =-SUMIFS(Cash_Ledger!$D$5:$D$53,Cash_Ledger!$C$5:$C$53,">="&G$5,Cash_Ledger!$C$5:$C$53,"<="&G$6,Cash_Ledger!$A$5:$A$53,"software") | H20: =-SUMIFS(Cash_Ledger!$D$5:$D$53,Cash_Ledger!$C$5:$C$53,">="&H$5,Cash_Ledger!$C$5:$C$53,"<="&H$6,Cash_Ledger!$A$5:$A$53,"software") | I20: =-SUMIFS(Cash_Ledger!$D$5:$D$53,Cash_Ledger!$C$5:$C$53,">="&I$5,Cash_Ledger!$C$5:$C$53,"<="&I$6,Cash_Ledger!$A$5:$A$53,"software") | J20: =-SUMIFS(Cash_Ledger!$D$5:$D$53,Cash_Ledger!$C$5:$C$53,">="&J$5,Cash_Ledger!$C$5:$C$53,"<="&J$6,Cash_Ledger!$A$5:$A$53,"software") | ... AB20: =-SUMIFS(Cash_Ledger!$D$5:$D$53,Cash_Ledger!$C$5:$C$53,">="&AB$5,Cash_Ledger!$C$5:$C$53,"<="&AB$6,Cash_Ledger!$A$5:$A$53,"software") | AC20: =SUM(C20:AB20)
B21: Insurance | C21: =-SUMIFS(Cash_Ledger!$D$5:$D$53,Cash_Ledger!$C$5:$C$53,">="&C$5,Cash_Ledger!$C$5:$C$53,"<="&C$6,Cash_Ledger!$A$5:$A$53,"insurance") | D21: =-SUMIFS(Cash_Ledger!$D$5:$D$53,Cash_Ledger!$C$5:$C$53,">="&D$5,Cash_Ledger!$C$5:$C$53,"<="&D$6,Cash_Ledger!$A$5:$A$53,"insurance") | E21: =-SUMIFS(Cash_Ledger!$D$5:$D$53,Cash_Ledger!$C$5:$C$53,">="&E$5,Cash_Ledger!$C$5:$C$53,"<="&E$6,Cash_Ledger!$A$5:$A$53,"insurance") | F21: =-SUMIFS(Cash_Ledger!$D$5:$D$53,Cash_Ledger!$C$5:$C$53,">="&F$5,Cash_Ledger!$C$5:$C$53,"<="&F$6,Cash_Ledger!$A$5:$A$53,"insurance") | G21: =-SUMIFS(Cash_Ledger!$D$5:$D$53,Cash_Ledger!$C$5:$C$53,">="&G$5,Cash_Ledger!$C$5:$C$53,"<="&G$6,Cash_Ledger!$A$5:$A$53,"insurance") | H21: =-SUMIFS(Cash_Ledger!$D$5:$D$53,Cash_Ledger!$C$5:$C$53,">="&H$5,Cash_Ledger!$C$5:$C$53,"<="&H$6,Cash_Ledger!$A$5:$A$53,"insurance") | I21: =-SUMIFS(Cash_Ledger!$D$5:$D$53,Cash_Ledger!$C$5:$C$53,">="&I$5,Cash_Ledger!$C$5:$C$53,"<="&I$6,Cash_Ledger!$A$5:$A$53,"insurance") | J21: =-SUMIFS(Cash_Ledger!$D$5:$D$53,Cash_Ledger!$C$5:$C$53,">="&J$5,Cash_Ledger!$C$5:$C$53,"<="&J$6,Cash_Ledger!$A$5:$A$53,"insurance") | ... AB21: =-SUMIFS(Cash_Ledger!$D$5:$D$53,Cash_Ledger!$C$5:$C$53,">="&AB$5,Cash_Ledger!$C$5:$C$53,"<="&AB$6,Cash_Ledger!$A$5:$A$53,"insurance") | AC21: =SUM(C21:AB21)
B22: Storage | C22: =-SUMIFS(Cash_Ledger!$D$5:$D$53,Cash_Ledger!$C$5:$C$53,">="&C$5,Cash_Ledger!$C$5:$C$53,"<="&C$6,Cash_Ledger!$A$5:$A$53,"storage") | D22: =-SUMIFS(Cash_Ledger!$D$5:$D$53,Cash_Ledger!$C$5:$C$53,">="&D$5,Cash_Ledger!$C$5:$C$53,"<="&D$6,Cash_Ledger!$A$5:$A$53,"storage") | E22: =-SUMIFS(Cash_Ledger!$D$5:$D$53,Cash_Ledger!$C$5:$C$53,">="&E$5,Cash_Ledger!$C$5:$C$53,"<="&E$6,Cash_Ledger!$A$5:$A$53,"storage") | F22: =-SUMIFS(Cash_Ledger!$D$5:$D$53,Cash_Ledger!$C$5:$C$53,">="&F$5,Cash_Ledger!$C$5:$C$53,"<="&F$6,Cash_Ledger!$A$5:$A$53,"storage") | G22: =-SUMIFS(Cash_Ledger!$D$5:$D$53,Cash_Ledger!$C$5:$C$53,">="&G$5,Cash_Ledger!$C$5:$C$53,"<="&G$6,Cash_Ledger!$A$5:$A$53,"storage") | H22: =-SUMIFS(Cash_Ledger!$D$5:$D$53,Cash_Ledger!$C$5:$C$53,">="&H$5,Cash_Ledger!$C$5:$C$53,"<="&H$6,Cash_Ledger!$A$5:$A$53,"storage") | I22: =-SUMIFS(Cash_Ledger!$D$5:$D$53,Cash_Ledger!$C$5:$C$53,">="&I$5,Cash_Ledger!$C$5:$C$53,"<="&I$6,Cash_Ledger!$A$5:$A$53,"storage") | J22: =-SUMIFS(Cash_Ledger!$D$5:$D$53,Cash_Ledger!$C$5:$C$53,">="&J$5,Cash_Ledger!$C$5:$C$53,"<="&J$6,Cash_Ledger!$A$5:$A$53,"storage") | ... AB22: =-SUMIFS(Cash_Ledger!$D$5:$D$53,Cash_Ledger!$C$5:$C$53,">="&AB$5,Cash_Ledger!$C$5:$C$53,"<="&AB$6,Cash_Ledger!$A$5:$A$53,"storage") | AC22: =SUM(C22:AB22)
B23: Phone | C23: =-SUMIFS(Cash_Ledger!$D$5:$D$53,Cash_Ledger!$C$5:$C$53,">="&C$5,Cash_Ledger!$C$5:$C$53,"<="&C$6,Cash_Ledger!$A$5:$A$53,"phone") | D23: =-SUMIFS(Cash_Ledger!$D$5:$D$53,Cash_Ledger!$C$5:$C$53,">="&D$5,Cash_Ledger!$C$5:$C$53,"<="&D$6,Cash_Ledger!$A$5:$A$53,"phone") | E23: =-SUMIFS(Cash_Ledger!$D$5:$D$53,Cash_Ledger!$C$5:$C$53,">="&E$5,Cash_Ledger!$C$5:$C$53,"<="&E$6,Cash_Ledger!$A$5:$A$53,"phone") | F23: =-SUMIFS(Cash_Ledger!$D$5:$D$53,Cash_Ledger!$C$5:$C$53,">="&F$5,Cash_Ledger!$C$5:$C$53,"<="&F$6,Cash_Ledger!$A$5:$A$53,"phone") | G23: =-SUMIFS(Cash_Ledger!$D$5:$D$53,Cash_Ledger!$C$5:$C$53,">="&G$5,Cash_Ledger!$C$5:$C$53,"<="&G$6,Cash_Ledger!$A$5:$A$53,"phone") | H23: =-SUMIFS(Cash_Ledger!$D$5:$D$53,Cash_Ledger!$C$5:$C$53,">="&H$5,Cash_Ledger!$C$5:$C$53,"<="&H$6,Cash_Ledger!$A$5:$A$53,"phone") | I23: =-SUMIFS(Cash_Ledger!$D$5:$D$53,Cash_Ledger!$C$5:$C$53,">="&I$5,Cash_Ledger!$C$5:$C$53,"<="&I$6,Cash_Ledger!$A$5:$A$53,"phone") | J23: =-SUMIFS(Cash_Ledger!$D$5:$D$53,Cash_Ledger!$C$5:$C$53,">="&J$5,Cash_Ledger!$C$5:$C$53,"<="&J$6,Cash_Ledger!$A$5:$A$53,"phone") | ... AB23: =-SUMIFS(Cash_Ledger!$D$5:$D$53,Cash_Ledger!$C$5:$C$53,">="&AB$5,Cash_Ledger!$C$5:$C$53,"<="&AB$6,Cash_Ledger!$A$5:$A$53,"phone") | AC23: =SUM(C23:AB23)
B24: Total overhead | C24: =SUM(C20:C23) | D24: =SUM(D20:D23) | E24: =SUM(E20:E23) | F24: =SUM(F20:F23) | G24: =SUM(G20:G23) | H24: =SUM(H20:H23) | I24: =SUM(I20:I23) | J24: =SUM(J20:J23) | ... AB24: =SUM(AB20:AB23) | AC24: =SUM(C24:AB24)
B25: Startup outlays (Inputs section 11) | C25: =-SUMIFS(Inputs!$Q$148:$Q$159,Inputs!$R$148:$R$159,">="&C$5,Inputs!$R$148:$R$159,"<="&C$6) | D25: =-SUMIFS(Inputs!$Q$148:$Q$159,Inputs!$R$148:$R$159,">="&D$5,Inputs!$R$148:$R$159,"<="&D$6) | E25: =-SUMIFS(Inputs!$Q$148:$Q$159,Inputs!$R$148:$R$159,">="&E$5,Inputs!$R$148:$R$159,"<="&E$6) | F25: =-SUMIFS(Inputs!$Q$148:$Q$159,Inputs!$R$148:$R$159,">="&F$5,Inputs!$R$148:$R$159,"<="&F$6) | G25: =-SUMIFS(Inputs!$Q$148:$Q$159,Inputs!$R$148:$R$159,">="&G$5,Inputs!$R$148:$R$159,"<="&G$6) | H25: =-SUMIFS(Inputs!$Q$148:$Q$159,Inputs!$R$148:$R$159,">="&H$5,Inputs!$R$148:$R$159,"<="&H$6) | I25: =-SUMIFS(Inputs!$Q$148:$Q$159,Inputs!$R$148:$R$159,">="&I$5,Inputs!$R$148:$R$159,"<="&I$6) | J25: =-SUMIFS(Inputs!$Q$148:$Q$159,Inputs!$R$148:$R$159,">="&J$5,Inputs!$R$148:$R$159,"<="&J$6) | ... AB25: =-SUMIFS(Inputs!$Q$148:$Q$159,Inputs!$R$148:$R$159,">="&AB$5,Inputs!$R$148:$R$159,"<="&AB$6) | AC25: =SUM(C25:AB25)
B26: Net cash flow | C26: =C11+C18+C24+C25 | D26: =D11+D18+D24+D25 | E26: =E11+E18+E24+E25 | F26: =F11+F18+F24+F25 | G26: =G11+G18+G24+G25 | H26: =H11+H18+H24+H25 | I26: =I11+I18+I24+I25 | J26: =J11+J18+J24+J25 | ... AB26: =AB11+AB18+AB24+AB25 | AC26: =SUM(C26:AB26)
B27: Cumulative net cash flow, before founder cash | C27: =C26 | D27: =C27+D26 | E27: =D27+E26 | F27: =E27+F26 | G27: =F27+G26 | H27: =G27+H26 | I27: =H27+I26 | J27: =I27+J26 | K27: =J27+K26 | ... AB27: =AA27+AB26 | AC27: =AB27
B28: Founder cash in | C28: =IF(AND(Inputs!$C$106>=C$5,Inputs!$C$106<=C$6),N(Inputs!$C$105),0) | D28: =IF(AND(Inputs!$C$106>=D$5,Inputs!$C$106<=D$6),N(Inputs!$C$105),0) | E28: =IF(AND(Inputs!$C$106>=E$5,Inputs!$C$106<=E$6),N(Inputs!$C$105),0) | F28: =IF(AND(Inputs!$C$106>=F$5,Inputs!$C$106<=F$6),N(Inputs!$C$105),0) | G28: =IF(AND(Inputs!$C$106>=G$5,Inputs!$C$106<=G$6),N(Inputs!$C$105),0) | H28: =IF(AND(Inputs!$C$106>=H$5,Inputs!$C$106<=H$6),N(Inputs!$C$105),0) | I28: =IF(AND(Inputs!$C$106>=I$5,Inputs!$C$106<=I$6),N(Inputs!$C$105),0) | J28: =IF(AND(Inputs!$C$106>=J$5,Inputs!$C$106<=J$6),N(Inputs!$C$105),0) | ... AB28: =IF(AND(Inputs!$C$106>=AB$5,Inputs!$C$106<=AB$6),N(Inputs!$C$105),0) | AC28: =SUM(C28:AB28)
B29: Cash balance with founder cash | C29: =C27+SUM($C28:C28) | D29: =D27+SUM($C28:D28) | E29: =E27+SUM($C28:E28) | F29: =F27+SUM($C28:F28) | G29: =G27+SUM($C28:G28) | H29: =H27+SUM($C28:H28) | I29: =I27+SUM($C28:I28) | J29: =J27+SUM($C28:J28) | ... AB29: =AB27+SUM($C28:AB28) | AC29: =AB29
A31: Lowest point and capital
B32: Lowest cumulative net cash flow (before founder cash) | C32: =MIN(C27:AB27)
B33: Week of the lowest point | C33: =INDEX(C4:AB4,MATCH(C32,C27:AB27,0))
B34: That week starts | C34: =INDEX(C5:AB5,MATCH(C32,C27:AB27,0))
B35: Peak cash need (the lowest point, as a positive number) | C35: =-MIN(0,C32)
B36: Reserve held back (plan) | C36: =Inputs!$C$107
B37: Capital to commit: peak need plus reserve | C37: =C35+C36
B38: Plan capital figure, high end (Capital tab) | C38: =Capital!D14
B39: Gap: plan capital figure minus capital to commit (positive = headroom) | C39: =C38-C37
B40: Founder cash committed (Inputs) | C40: =IF(Inputs!$C$105="","not set",Inputs!$C$105)
B41: Lowest cash balance with founder cash | C41: =MIN(C29:AB29)
B42: Cumulative net cash at the end of week 26 | C42: =AB27
A45: Monthly view (computed directly from the same sources, as a cross-check of the weekly grid)
B46: Month starts | C46: =DATE(YEAR(Inputs!$C$10),MONTH(Inputs!$C$10),1) | D46: =EDATE(C46,1) | E46: =EDATE(D46,1) | F46: =EDATE(E46,1) | G46: =EDATE(F46,1) | H46: =EDATE(G46,1) | I46: =EDATE(H46,1) | J46: Six months
B47: Counted from | C47: =MAX(C46,Inputs!$C$10) | D47: =MAX(D46,Inputs!$C$10) | E47: =MAX(E46,Inputs!$C$10) | F47: =MAX(F46,Inputs!$C$10) | G47: =MAX(G46,Inputs!$C$10) | H47: =MAX(H46,Inputs!$C$10) | I47: =MAX(I46,Inputs!$C$10)
B48: Counted to | C48: =MIN(EOMONTH(C46,0),Cash_Flow!$AB$6) | D48: =MIN(EOMONTH(D46,0),Cash_Flow!$AB$6) | E48: =MIN(EOMONTH(E46,0),Cash_Flow!$AB$6) | F48: =MIN(EOMONTH(F46,0),Cash_Flow!$AB$6) | G48: =MIN(EOMONTH(G46,0),Cash_Flow!$AB$6) | H48: =MIN(EOMONTH(H46,0),Cash_Flow!$AB$6) | I48: =MIN(EOMONTH(I46,0),Cash_Flow!$AB$6)
B49: Brand receipts, plan (drops without actuals) | C49: =SUMIFS(Drop_PnL!$AP$7:$AP$18,Drop_PnL!$AO$7:$AO$18,">="&C$47,Drop_PnL!$AO$7:$AO$18,"<="&C$48,Drop_PnL!$AZ$7:$AZ$18,"N")+SUMIFS(Drop_PnL!$AR$7:$AR$18,Drop_PnL!$AQ$7:$AQ$18,">="&C$47,Drop_PnL!$AQ$7:$AQ$18,"<="&C$48,Drop_PnL!$AZ$7:$AZ$18,"N")+SUMIFS(Drop_PnL!$AT$7:$AT$18,Drop_PnL!$AS$7:$AS$18,">="&C$47,Drop_PnL!$AS$7:$AS$18,"<="&C$48,Drop_PnL!$AZ$7:$AZ$18,"N") | D49: =SUMIFS(Drop_PnL!$AP$7:$AP$18,Drop_PnL!$AO$7:$AO$18,">="&D$47,Drop_PnL!$AO$7:$AO$18,"<="&D$48,Drop_PnL!$AZ$7:$AZ$18,"N")+SUMIFS(Drop_PnL!$AR$7:$AR$18,Drop_PnL!$AQ$7:$AQ$18,">="&D$47,Drop_PnL!$AQ$7:$AQ$18,"<="&D$48,Drop_PnL!$AZ$7:$AZ$18,"N")+SUMIFS(Drop_PnL!$AT$7:$AT$18,Drop_PnL!$AS$7:$AS$18,">="&D$47,Drop_PnL!$AS$7:$AS$18,"<="&D$48,Drop_PnL!$AZ$7:$AZ$18,"N") | E49: =SUMIFS(Drop_PnL!$AP$7:$AP$18,Drop_PnL!$AO$7:$AO$18,">="&E$47,Drop_PnL!$AO$7:$AO$18,"<="&E$48,Drop_PnL!$AZ$7:$AZ$18,"N")+SUMIFS(Drop_PnL!$AR$7:$AR$18,Drop_PnL!$AQ$7:$AQ$18,">="&E$47,Drop_PnL!$AQ$7:$AQ$18,"<="&E$48,Drop_PnL!$AZ$7:$AZ$18,"N")+SUMIFS(Drop_PnL!$AT$7:$AT$18,Drop_PnL!$AS$7:$AS$18,">="&E$47,Drop_PnL!$AS$7:$AS$18,"<="&E$48,Drop_PnL!$AZ$7:$AZ$18,"N") | F49: =SUMIFS(Drop_PnL!$AP$7:$AP$18,Drop_PnL!$AO$7:$AO$18,">="&F$47,Drop_PnL!$AO$7:$AO$18,"<="&F$48,Drop_PnL!$AZ$7:$AZ$18,"N")+SUMIFS(Drop_PnL!$AR$7:$AR$18,Drop_PnL!$AQ$7:$AQ$18,">="&F$47,Drop_PnL!$AQ$7:$AQ$18,"<="&F$48,Drop_PnL!$AZ$7:$AZ$18,"N")+SUMIFS(Drop_PnL!$AT$7:$AT$18,Drop_PnL!$AS$7:$AS$18,">="&F$47,Drop_PnL!$AS$7:$AS$18,"<="&F$48,Drop_PnL!$AZ$7:$AZ$18,"N") | G49: =SUMIFS(Drop_PnL!$AP$7:$AP$18,Drop_PnL!$AO$7:$AO$18,">="&G$47,Drop_PnL!$AO$7:$AO$18,"<="&G$48,Drop_PnL!$AZ$7:$AZ$18,"N")+SUMIFS(Drop_PnL!$AR$7:$AR$18,Drop_PnL!$AQ$7:$AQ$18,">="&G$47,Drop_PnL!$AQ$7:$AQ$18,"<="&G$48,Drop_PnL!$AZ$7:$AZ$18,"N")+SUMIFS(Drop_PnL!$AT$7:$AT$18,Drop_PnL!$AS$7:$AS$18,">="&G$47,Drop_PnL!$AS$7:$AS$18,"<="&G$48,Drop_PnL!$AZ$7:$AZ$18,"N") | H49: =SUMIFS(Drop_PnL!$AP$7:$AP$18,Drop_PnL!$AO$7:$AO$18,">="&H$47,Drop_PnL!$AO$7:$AO$18,"<="&H$48,Drop_PnL!$AZ$7:$AZ$18,"N")+SUMIFS(Drop_PnL!$AR$7:$AR$18,Drop_PnL!$AQ$7:$AQ$18,">="&H$47,Drop_PnL!$AQ$7:$AQ$18,"<="&H$48,Drop_PnL!$AZ$7:$AZ$18,"N")+SUMIFS(Drop_PnL!$AT$7:$AT$18,Drop_PnL!$AS$7:$AS$18,">="&H$47,Drop_PnL!$AS$7:$AS$18,"<="&H$48,Drop_PnL!$AZ$7:$AZ$18,"N") | I49: =SUMIFS(Drop_PnL!$AP$7:$AP$18,Drop_PnL!$AO$7:$AO$18,">="&I$47,Drop_PnL!$AO$7:$AO$18,"<="&I$48,Drop_PnL!$AZ$7:$AZ$18,"N")+SUMIFS(Drop_PnL!$AR$7:$AR$18,Drop_PnL!$AQ$7:$AQ$18,">="&I$47,Drop_PnL!$AQ$7:$AQ$18,"<="&I$48,Drop_PnL!$AZ$7:$AZ$18,"N")+SUMIFS(Drop_PnL!$AT$7:$AT$18,Drop_PnL!$AS$7:$AS$18,">="&I$47,Drop_PnL!$AS$7:$AS$18,"<="&I$48,Drop_PnL!$AZ$7:$AZ$18,"N") | J49: =SUM(C49:I49)
B50: Brand receipts, actual (drops with actuals) | C50: =SUMIFS(Actuals_Campaigns!$X$5:$X$204,Actuals_Campaigns!$Y$5:$Y$204,">="&C$47,Actuals_Campaigns!$Y$5:$Y$204,"<="&C$48,Actuals_Campaigns!$AB$5:$AB$204,"Y")+SUMIFS(Actuals_Campaigns!$AC$5:$AC$204,Actuals_Campaigns!$S$5:$S$204,">="&C$47,Actuals_Campaigns!$S$5:$S$204,"<="&C$48,Actuals_Campaigns!$AB$5:$AB$204,"Y") | D50: =SUMIFS(Actuals_Campaigns!$X$5:$X$204,Actuals_Campaigns!$Y$5:$Y$204,">="&D$47,Actuals_Campaigns!$Y$5:$Y$204,"<="&D$48,Actuals_Campaigns!$AB$5:$AB$204,"Y")+SUMIFS(Actuals_Campaigns!$AC$5:$AC$204,Actuals_Campaigns!$S$5:$S$204,">="&D$47,Actuals_Campaigns!$S$5:$S$204,"<="&D$48,Actuals_Campaigns!$AB$5:$AB$204,"Y") | E50: =SUMIFS(Actuals_Campaigns!$X$5:$X$204,Actuals_Campaigns!$Y$5:$Y$204,">="&E$47,Actuals_Campaigns!$Y$5:$Y$204,"<="&E$48,Actuals_Campaigns!$AB$5:$AB$204,"Y")+SUMIFS(Actuals_Campaigns!$AC$5:$AC$204,Actuals_Campaigns!$S$5:$S$204,">="&E$47,Actuals_Campaigns!$S$5:$S$204,"<="&E$48,Actuals_Campaigns!$AB$5:$AB$204,"Y") | F50: =SUMIFS(Actuals_Campaigns!$X$5:$X$204,Actuals_Campaigns!$Y$5:$Y$204,">="&F$47,Actuals_Campaigns!$Y$5:$Y$204,"<="&F$48,Actuals_Campaigns!$AB$5:$AB$204,"Y")+SUMIFS(Actuals_Campaigns!$AC$5:$AC$204,Actuals_Campaigns!$S$5:$S$204,">="&F$47,Actuals_Campaigns!$S$5:$S$204,"<="&F$48,Actuals_Campaigns!$AB$5:$AB$204,"Y") | G50: =SUMIFS(Actuals_Campaigns!$X$5:$X$204,Actuals_Campaigns!$Y$5:$Y$204,">="&G$47,Actuals_Campaigns!$Y$5:$Y$204,"<="&G$48,Actuals_Campaigns!$AB$5:$AB$204,"Y")+SUMIFS(Actuals_Campaigns!$AC$5:$AC$204,Actuals_Campaigns!$S$5:$S$204,">="&G$47,Actuals_Campaigns!$S$5:$S$204,"<="&G$48,Actuals_Campaigns!$AB$5:$AB$204,"Y") | H50: =SUMIFS(Actuals_Campaigns!$X$5:$X$204,Actuals_Campaigns!$Y$5:$Y$204,">="&H$47,Actuals_Campaigns!$Y$5:$Y$204,"<="&H$48,Actuals_Campaigns!$AB$5:$AB$204,"Y")+SUMIFS(Actuals_Campaigns!$AC$5:$AC$204,Actuals_Campaigns!$S$5:$S$204,">="&H$47,Actuals_Campaigns!$S$5:$S$204,"<="&H$48,Actuals_Campaigns!$AB$5:$AB$204,"Y") | I50: =SUMIFS(Actuals_Campaigns!$X$5:$X$204,Actuals_Campaigns!$Y$5:$Y$204,">="&I$47,Actuals_Campaigns!$Y$5:$Y$204,"<="&I$48,Actuals_Campaigns!$AB$5:$AB$204,"Y")+SUMIFS(Actuals_Campaigns!$AC$5:$AC$204,Actuals_Campaigns!$S$5:$S$204,">="&I$47,Actuals_Campaigns!$S$5:$S$204,"<="&I$48,Actuals_Campaigns!$AB$5:$AB$204,"Y") | J50: =SUM(C50:I50)
B51: Total receipts | C51: =C49+C50 | D51: =D49+D50 | E51: =E49+E50 | F51: =F49+F50 | G51: =G49+G50 | H51: =H49+H50 | I51: =I49+I50 | J51: =SUM(C51:I51)
B52: Display kits, plan | C52: =-SUMIFS(Drop_PnL!$T$7:$T$18,Drop_PnL!$AX$7:$AX$18,">="&C$47,Drop_PnL!$AX$7:$AX$18,"<="&C$48,Drop_PnL!$AZ$7:$AZ$18,"N") | D52: =-SUMIFS(Drop_PnL!$T$7:$T$18,Drop_PnL!$AX$7:$AX$18,">="&D$47,Drop_PnL!$AX$7:$AX$18,"<="&D$48,Drop_PnL!$AZ$7:$AZ$18,"N") | E52: =-SUMIFS(Drop_PnL!$T$7:$T$18,Drop_PnL!$AX$7:$AX$18,">="&E$47,Drop_PnL!$AX$7:$AX$18,"<="&E$48,Drop_PnL!$AZ$7:$AZ$18,"N") | F52: =-SUMIFS(Drop_PnL!$T$7:$T$18,Drop_PnL!$AX$7:$AX$18,">="&F$47,Drop_PnL!$AX$7:$AX$18,"<="&F$48,Drop_PnL!$AZ$7:$AZ$18,"N") | G52: =-SUMIFS(Drop_PnL!$T$7:$T$18,Drop_PnL!$AX$7:$AX$18,">="&G$47,Drop_PnL!$AX$7:$AX$18,"<="&G$48,Drop_PnL!$AZ$7:$AZ$18,"N") | H52: =-SUMIFS(Drop_PnL!$T$7:$T$18,Drop_PnL!$AX$7:$AX$18,">="&H$47,Drop_PnL!$AX$7:$AX$18,"<="&H$48,Drop_PnL!$AZ$7:$AZ$18,"N") | I52: =-SUMIFS(Drop_PnL!$T$7:$T$18,Drop_PnL!$AX$7:$AX$18,">="&I$47,Drop_PnL!$AX$7:$AX$18,"<="&I$48,Drop_PnL!$AZ$7:$AZ$18,"N") | J52: =SUM(C52:I52)
B53: Transport, plan | C53: =-SUMIFS(Drop_PnL!$U$7:$U$18,Drop_PnL!$AY$7:$AY$18,">="&C$47,Drop_PnL!$AY$7:$AY$18,"<="&C$48,Drop_PnL!$AZ$7:$AZ$18,"N") | D53: =-SUMIFS(Drop_PnL!$U$7:$U$18,Drop_PnL!$AY$7:$AY$18,">="&D$47,Drop_PnL!$AY$7:$AY$18,"<="&D$48,Drop_PnL!$AZ$7:$AZ$18,"N") | E53: =-SUMIFS(Drop_PnL!$U$7:$U$18,Drop_PnL!$AY$7:$AY$18,">="&E$47,Drop_PnL!$AY$7:$AY$18,"<="&E$48,Drop_PnL!$AZ$7:$AZ$18,"N") | F53: =-SUMIFS(Drop_PnL!$U$7:$U$18,Drop_PnL!$AY$7:$AY$18,">="&F$47,Drop_PnL!$AY$7:$AY$18,"<="&F$48,Drop_PnL!$AZ$7:$AZ$18,"N") | G53: =-SUMIFS(Drop_PnL!$U$7:$U$18,Drop_PnL!$AY$7:$AY$18,">="&G$47,Drop_PnL!$AY$7:$AY$18,"<="&G$48,Drop_PnL!$AZ$7:$AZ$18,"N") | H53: =-SUMIFS(Drop_PnL!$U$7:$U$18,Drop_PnL!$AY$7:$AY$18,">="&H$47,Drop_PnL!$AY$7:$AY$18,"<="&H$48,Drop_PnL!$AZ$7:$AZ$18,"N") | I53: =-SUMIFS(Drop_PnL!$U$7:$U$18,Drop_PnL!$AY$7:$AY$18,">="&I$47,Drop_PnL!$AY$7:$AY$18,"<="&I$48,Drop_PnL!$AZ$7:$AZ$18,"N") | J53: =SUM(C53:I53)
B54: Kit mailing, plan (needs quote) | C54: =-SUMIFS(Drop_PnL!$V$7:$V$18,Drop_PnL!$AX$7:$AX$18,">="&C$47,Drop_PnL!$AX$7:$AX$18,"<="&C$48,Drop_PnL!$AZ$7:$AZ$18,"N") | D54: =-SUMIFS(Drop_PnL!$V$7:$V$18,Drop_PnL!$AX$7:$AX$18,">="&D$47,Drop_PnL!$AX$7:$AX$18,"<="&D$48,Drop_PnL!$AZ$7:$AZ$18,"N") | E54: =-SUMIFS(Drop_PnL!$V$7:$V$18,Drop_PnL!$AX$7:$AX$18,">="&E$47,Drop_PnL!$AX$7:$AX$18,"<="&E$48,Drop_PnL!$AZ$7:$AZ$18,"N") | F54: =-SUMIFS(Drop_PnL!$V$7:$V$18,Drop_PnL!$AX$7:$AX$18,">="&F$47,Drop_PnL!$AX$7:$AX$18,"<="&F$48,Drop_PnL!$AZ$7:$AZ$18,"N") | G54: =-SUMIFS(Drop_PnL!$V$7:$V$18,Drop_PnL!$AX$7:$AX$18,">="&G$47,Drop_PnL!$AX$7:$AX$18,"<="&G$48,Drop_PnL!$AZ$7:$AZ$18,"N") | H54: =-SUMIFS(Drop_PnL!$V$7:$V$18,Drop_PnL!$AX$7:$AX$18,">="&H$47,Drop_PnL!$AX$7:$AX$18,"<="&H$48,Drop_PnL!$AZ$7:$AZ$18,"N") | I54: =-SUMIFS(Drop_PnL!$V$7:$V$18,Drop_PnL!$AX$7:$AX$18,">="&I$47,Drop_PnL!$AX$7:$AX$18,"<="&I$48,Drop_PnL!$AZ$7:$AZ$18,"N") | J54: =SUM(C54:I54)
B55: Card processing, plan | C55: =-(SUMIFS(Drop_PnL!$AU$7:$AU$18,Drop_PnL!$AO$7:$AO$18,">="&C$47,Drop_PnL!$AO$7:$AO$18,"<="&C$48,Drop_PnL!$AZ$7:$AZ$18,"N")+SUMIFS(Drop_PnL!$AV$7:$AV$18,Drop_PnL!$AQ$7:$AQ$18,">="&C$47,Drop_PnL!$AQ$7:$AQ$18,"<="&C$48,Drop_PnL!$AZ$7:$AZ$18,"N")+SUMIFS(Drop_PnL!$AW$7:$AW$18,Drop_PnL!$AS$7:$AS$18,">="&C$47,Drop_PnL!$AS$7:$AS$18,"<="&C$48,Drop_PnL!$AZ$7:$AZ$18,"N")) | D55: =-(SUMIFS(Drop_PnL!$AU$7:$AU$18,Drop_PnL!$AO$7:$AO$18,">="&D$47,Drop_PnL!$AO$7:$AO$18,"<="&D$48,Drop_PnL!$AZ$7:$AZ$18,"N")+SUMIFS(Drop_PnL!$AV$7:$AV$18,Drop_PnL!$AQ$7:$AQ$18,">="&D$47,Drop_PnL!$AQ$7:$AQ$18,"<="&D$48,Drop_PnL!$AZ$7:$AZ$18,"N")+SUMIFS(Drop_PnL!$AW$7:$AW$18,Drop_PnL!$AS$7:$AS$18,">="&D$47,Drop_PnL!$AS$7:$AS$18,"<="&D$48,Drop_PnL!$AZ$7:$AZ$18,"N")) | E55: =-(SUMIFS(Drop_PnL!$AU$7:$AU$18,Drop_PnL!$AO$7:$AO$18,">="&E$47,Drop_PnL!$AO$7:$AO$18,"<="&E$48,Drop_PnL!$AZ$7:$AZ$18,"N")+SUMIFS(Drop_PnL!$AV$7:$AV$18,Drop_PnL!$AQ$7:$AQ$18,">="&E$47,Drop_PnL!$AQ$7:$AQ$18,"<="&E$48,Drop_PnL!$AZ$7:$AZ$18,"N")+SUMIFS(Drop_PnL!$AW$7:$AW$18,Drop_PnL!$AS$7:$AS$18,">="&E$47,Drop_PnL!$AS$7:$AS$18,"<="&E$48,Drop_PnL!$AZ$7:$AZ$18,"N")) | F55: =-(SUMIFS(Drop_PnL!$AU$7:$AU$18,Drop_PnL!$AO$7:$AO$18,">="&F$47,Drop_PnL!$AO$7:$AO$18,"<="&F$48,Drop_PnL!$AZ$7:$AZ$18,"N")+SUMIFS(Drop_PnL!$AV$7:$AV$18,Drop_PnL!$AQ$7:$AQ$18,">="&F$47,Drop_PnL!$AQ$7:$AQ$18,"<="&F$48,Drop_PnL!$AZ$7:$AZ$18,"N")+SUMIFS(Drop_PnL!$AW$7:$AW$18,Drop_PnL!$AS$7:$AS$18,">="&F$47,Drop_PnL!$AS$7:$AS$18,"<="&F$48,Drop_PnL!$AZ$7:$AZ$18,"N")) | G55: =-(SUMIFS(Drop_PnL!$AU$7:$AU$18,Drop_PnL!$AO$7:$AO$18,">="&G$47,Drop_PnL!$AO$7:$AO$18,"<="&G$48,Drop_PnL!$AZ$7:$AZ$18,"N")+SUMIFS(Drop_PnL!$AV$7:$AV$18,Drop_PnL!$AQ$7:$AQ$18,">="&G$47,Drop_PnL!$AQ$7:$AQ$18,"<="&G$48,Drop_PnL!$AZ$7:$AZ$18,"N")+SUMIFS(Drop_PnL!$AW$7:$AW$18,Drop_PnL!$AS$7:$AS$18,">="&G$47,Drop_PnL!$AS$7:$AS$18,"<="&G$48,Drop_PnL!$AZ$7:$AZ$18,"N")) | H55: =-(SUMIFS(Drop_PnL!$AU$7:$AU$18,Drop_PnL!$AO$7:$AO$18,">="&H$47,Drop_PnL!$AO$7:$AO$18,"<="&H$48,Drop_PnL!$AZ$7:$AZ$18,"N")+SUMIFS(Drop_PnL!$AV$7:$AV$18,Drop_PnL!$AQ$7:$AQ$18,">="&H$47,Drop_PnL!$AQ$7:$AQ$18,"<="&H$48,Drop_PnL!$AZ$7:$AZ$18,"N")+SUMIFS(Drop_PnL!$AW$7:$AW$18,Drop_PnL!$AS$7:$AS$18,">="&H$47,Drop_PnL!$AS$7:$AS$18,"<="&H$48,Drop_PnL!$AZ$7:$AZ$18,"N")) | I55: =-(SUMIFS(Drop_PnL!$AU$7:$AU$18,Drop_PnL!$AO$7:$AO$18,">="&I$47,Drop_PnL!$AO$7:$AO$18,"<="&I$48,Drop_PnL!$AZ$7:$AZ$18,"N")+SUMIFS(Drop_PnL!$AV$7:$AV$18,Drop_PnL!$AQ$7:$AQ$18,">="&I$47,Drop_PnL!$AQ$7:$AQ$18,"<="&I$48,Drop_PnL!$AZ$7:$AZ$18,"N")+SUMIFS(Drop_PnL!$AW$7:$AW$18,Drop_PnL!$AS$7:$AS$18,">="&I$47,Drop_PnL!$AS$7:$AS$18,"<="&I$48,Drop_PnL!$AZ$7:$AZ$18,"N")) | J55: =SUM(C55:I55)
B56: Direct costs and processing, actual | C56: =-(SUMIFS(Actuals_DropCosts!$F$5:$F$104,Actuals_DropCosts!$B$5:$B$104,">="&C$47,Actuals_DropCosts!$B$5:$B$104,"<="&C$48,Actuals_DropCosts!$K$5:$K$104,"Y")+SUMIFS(Actuals_DropCosts!$G$5:$G$104,Actuals_DropCosts!$B$5:$B$104,">="&C$47,Actuals_DropCosts!$B$5:$B$104,"<="&C$48,Actuals_DropCosts!$K$5:$K$104,"Y")+SUMIFS(Actuals_DropCosts!$H$5:$H$104,Actuals_DropCosts!$B$5:$B$104,">="&C$47,Actuals_DropCosts!$B$5:$B$104,"<="&C$48,Actuals_DropCosts!$K$5:$K$104,"Y")+SUMIFS(Actuals_Campaigns!$T$5:$T$204,Actuals_Campaigns!$S$5:$S$204,">="&C$47,Actuals_Campaigns!$S$5:$S$204,"<="&C$48,Actuals_Campaigns!$AB$5:$AB$204,"Y")) | D56: =-(SUMIFS(Actuals_DropCosts!$F$5:$F$104,Actuals_DropCosts!$B$5:$B$104,">="&D$47,Actuals_DropCosts!$B$5:$B$104,"<="&D$48,Actuals_DropCosts!$K$5:$K$104,"Y")+SUMIFS(Actuals_DropCosts!$G$5:$G$104,Actuals_DropCosts!$B$5:$B$104,">="&D$47,Actuals_DropCosts!$B$5:$B$104,"<="&D$48,Actuals_DropCosts!$K$5:$K$104,"Y")+SUMIFS(Actuals_DropCosts!$H$5:$H$104,Actuals_DropCosts!$B$5:$B$104,">="&D$47,Actuals_DropCosts!$B$5:$B$104,"<="&D$48,Actuals_DropCosts!$K$5:$K$104,"Y")+SUMIFS(Actuals_Campaigns!$T$5:$T$204,Actuals_Campaigns!$S$5:$S$204,">="&D$47,Actuals_Campaigns!$S$5:$S$204,"<="&D$48,Actuals_Campaigns!$AB$5:$AB$204,"Y")) | E56: =-(SUMIFS(Actuals_DropCosts!$F$5:$F$104,Actuals_DropCosts!$B$5:$B$104,">="&E$47,Actuals_DropCosts!$B$5:$B$104,"<="&E$48,Actuals_DropCosts!$K$5:$K$104,"Y")+SUMIFS(Actuals_DropCosts!$G$5:$G$104,Actuals_DropCosts!$B$5:$B$104,">="&E$47,Actuals_DropCosts!$B$5:$B$104,"<="&E$48,Actuals_DropCosts!$K$5:$K$104,"Y")+SUMIFS(Actuals_DropCosts!$H$5:$H$104,Actuals_DropCosts!$B$5:$B$104,">="&E$47,Actuals_DropCosts!$B$5:$B$104,"<="&E$48,Actuals_DropCosts!$K$5:$K$104,"Y")+SUMIFS(Actuals_Campaigns!$T$5:$T$204,Actuals_Campaigns!$S$5:$S$204,">="&E$47,Actuals_Campaigns!$S$5:$S$204,"<="&E$48,Actuals_Campaigns!$AB$5:$AB$204,"Y")) | F56: =-(SUMIFS(Actuals_DropCosts!$F$5:$F$104,Actuals_DropCosts!$B$5:$B$104,">="&F$47,Actuals_DropCosts!$B$5:$B$104,"<="&F$48,Actuals_DropCosts!$K$5:$K$104,"Y")+SUMIFS(Actuals_DropCosts!$G$5:$G$104,Actuals_DropCosts!$B$5:$B$104,">="&F$47,Actuals_DropCosts!$B$5:$B$104,"<="&F$48,Actuals_DropCosts!$K$5:$K$104,"Y")+SUMIFS(Actuals_DropCosts!$H$5:$H$104,Actuals_DropCosts!$B$5:$B$104,">="&F$47,Actuals_DropCosts!$B$5:$B$104,"<="&F$48,Actuals_DropCosts!$K$5:$K$104,"Y")+SUMIFS(Actuals_Campaigns!$T$5:$T$204,Actuals_Campaigns!$S$5:$S$204,">="&F$47,Actuals_Campaigns!$S$5:$S$204,"<="&F$48,Actuals_Campaigns!$AB$5:$AB$204,"Y")) | G56: =-(SUMIFS(Actuals_DropCosts!$F$5:$F$104,Actuals_DropCosts!$B$5:$B$104,">="&G$47,Actuals_DropCosts!$B$5:$B$104,"<="&G$48,Actuals_DropCosts!$K$5:$K$104,"Y")+SUMIFS(Actuals_DropCosts!$G$5:$G$104,Actuals_DropCosts!$B$5:$B$104,">="&G$47,Actuals_DropCosts!$B$5:$B$104,"<="&G$48,Actuals_DropCosts!$K$5:$K$104,"Y")+SUMIFS(Actuals_DropCosts!$H$5:$H$104,Actuals_DropCosts!$B$5:$B$104,">="&G$47,Actuals_DropCosts!$B$5:$B$104,"<="&G$48,Actuals_DropCosts!$K$5:$K$104,"Y")+SUMIFS(Actuals_Campaigns!$T$5:$T$204,Actuals_Campaigns!$S$5:$S$204,">="&G$47,Actuals_Campaigns!$S$5:$S$204,"<="&G$48,Actuals_Campaigns!$AB$5:$AB$204,"Y")) | H56: =-(SUMIFS(Actuals_DropCosts!$F$5:$F$104,Actuals_DropCosts!$B$5:$B$104,">="&H$47,Actuals_DropCosts!$B$5:$B$104,"<="&H$48,Actuals_DropCosts!$K$5:$K$104,"Y")+SUMIFS(Actuals_DropCosts!$G$5:$G$104,Actuals_DropCosts!$B$5:$B$104,">="&H$47,Actuals_DropCosts!$B$5:$B$104,"<="&H$48,Actuals_DropCosts!$K$5:$K$104,"Y")+SUMIFS(Actuals_DropCosts!$H$5:$H$104,Actuals_DropCosts!$B$5:$B$104,">="&H$47,Actuals_DropCosts!$B$5:$B$104,"<="&H$48,Actuals_DropCosts!$K$5:$K$104,"Y")+SUMIFS(Actuals_Campaigns!$T$5:$T$204,Actuals_Campaigns!$S$5:$S$204,">="&H$47,Actuals_Campaigns!$S$5:$S$204,"<="&H$48,Actuals_Campaigns!$AB$5:$AB$204,"Y")) | I56: =-(SUMIFS(Actuals_DropCosts!$F$5:$F$104,Actuals_DropCosts!$B$5:$B$104,">="&I$47,Actuals_DropCosts!$B$5:$B$104,"<="&I$48,Actuals_DropCosts!$K$5:$K$104,"Y")+SUMIFS(Actuals_DropCosts!$G$5:$G$104,Actuals_DropCosts!$B$5:$B$104,">="&I$47,Actuals_DropCosts!$B$5:$B$104,"<="&I$48,Actuals_DropCosts!$K$5:$K$104,"Y")+SUMIFS(Actuals_DropCosts!$H$5:$H$104,Actuals_DropCosts!$B$5:$B$104,">="&I$47,Actuals_DropCosts!$B$5:$B$104,"<="&I$48,Actuals_DropCosts!$K$5:$K$104,"Y")+SUMIFS(Actuals_Campaigns!$T$5:$T$204,Actuals_Campaigns!$S$5:$S$204,">="&I$47,Actuals_Campaigns!$S$5:$S$204,"<="&I$48,Actuals_Campaigns!$AB$5:$AB$204,"Y")) | J56: =SUM(C56:I56)
B57: Total direct costs | C57: =C52+C53+C54+C55+C56 | D57: =D52+D53+D54+D55+D56 | E57: =E52+E53+E54+E55+E56 | F57: =F52+F53+F54+F55+F56 | G57: =G52+G53+G54+G55+G56 | H57: =H52+H53+H54+H55+H56 | I57: =I52+I53+I54+I55+I56 | J57: =SUM(C57:I57)
B58: Software | C58: =-SUMIFS(Cash_Ledger!$D$5:$D$53,Cash_Ledger!$C$5:$C$53,">="&C$47,Cash_Ledger!$C$5:$C$53,"<="&C$48,Cash_Ledger!$A$5:$A$53,"software") | D58: =-SUMIFS(Cash_Ledger!$D$5:$D$53,Cash_Ledger!$C$5:$C$53,">="&D$47,Cash_Ledger!$C$5:$C$53,"<="&D$48,Cash_Ledger!$A$5:$A$53,"software") | E58: =-SUMIFS(Cash_Ledger!$D$5:$D$53,Cash_Ledger!$C$5:$C$53,">="&E$47,Cash_Ledger!$C$5:$C$53,"<="&E$48,Cash_Ledger!$A$5:$A$53,"software") | F58: =-SUMIFS(Cash_Ledger!$D$5:$D$53,Cash_Ledger!$C$5:$C$53,">="&F$47,Cash_Ledger!$C$5:$C$53,"<="&F$48,Cash_Ledger!$A$5:$A$53,"software") | G58: =-SUMIFS(Cash_Ledger!$D$5:$D$53,Cash_Ledger!$C$5:$C$53,">="&G$47,Cash_Ledger!$C$5:$C$53,"<="&G$48,Cash_Ledger!$A$5:$A$53,"software") | H58: =-SUMIFS(Cash_Ledger!$D$5:$D$53,Cash_Ledger!$C$5:$C$53,">="&H$47,Cash_Ledger!$C$5:$C$53,"<="&H$48,Cash_Ledger!$A$5:$A$53,"software") | I58: =-SUMIFS(Cash_Ledger!$D$5:$D$53,Cash_Ledger!$C$5:$C$53,">="&I$47,Cash_Ledger!$C$5:$C$53,"<="&I$48,Cash_Ledger!$A$5:$A$53,"software") | J58: =SUM(C58:I58)
B59: Insurance | C59: =-SUMIFS(Cash_Ledger!$D$5:$D$53,Cash_Ledger!$C$5:$C$53,">="&C$47,Cash_Ledger!$C$5:$C$53,"<="&C$48,Cash_Ledger!$A$5:$A$53,"insurance") | D59: =-SUMIFS(Cash_Ledger!$D$5:$D$53,Cash_Ledger!$C$5:$C$53,">="&D$47,Cash_Ledger!$C$5:$C$53,"<="&D$48,Cash_Ledger!$A$5:$A$53,"insurance") | E59: =-SUMIFS(Cash_Ledger!$D$5:$D$53,Cash_Ledger!$C$5:$C$53,">="&E$47,Cash_Ledger!$C$5:$C$53,"<="&E$48,Cash_Ledger!$A$5:$A$53,"insurance") | F59: =-SUMIFS(Cash_Ledger!$D$5:$D$53,Cash_Ledger!$C$5:$C$53,">="&F$47,Cash_Ledger!$C$5:$C$53,"<="&F$48,Cash_Ledger!$A$5:$A$53,"insurance") | G59: =-SUMIFS(Cash_Ledger!$D$5:$D$53,Cash_Ledger!$C$5:$C$53,">="&G$47,Cash_Ledger!$C$5:$C$53,"<="&G$48,Cash_Ledger!$A$5:$A$53,"insurance") | H59: =-SUMIFS(Cash_Ledger!$D$5:$D$53,Cash_Ledger!$C$5:$C$53,">="&H$47,Cash_Ledger!$C$5:$C$53,"<="&H$48,Cash_Ledger!$A$5:$A$53,"insurance") | I59: =-SUMIFS(Cash_Ledger!$D$5:$D$53,Cash_Ledger!$C$5:$C$53,">="&I$47,Cash_Ledger!$C$5:$C$53,"<="&I$48,Cash_Ledger!$A$5:$A$53,"insurance") | J59: =SUM(C59:I59)
B60: Storage | C60: =-SUMIFS(Cash_Ledger!$D$5:$D$53,Cash_Ledger!$C$5:$C$53,">="&C$47,Cash_Ledger!$C$5:$C$53,"<="&C$48,Cash_Ledger!$A$5:$A$53,"storage") | D60: =-SUMIFS(Cash_Ledger!$D$5:$D$53,Cash_Ledger!$C$5:$C$53,">="&D$47,Cash_Ledger!$C$5:$C$53,"<="&D$48,Cash_Ledger!$A$5:$A$53,"storage") | E60: =-SUMIFS(Cash_Ledger!$D$5:$D$53,Cash_Ledger!$C$5:$C$53,">="&E$47,Cash_Ledger!$C$5:$C$53,"<="&E$48,Cash_Ledger!$A$5:$A$53,"storage") | F60: =-SUMIFS(Cash_Ledger!$D$5:$D$53,Cash_Ledger!$C$5:$C$53,">="&F$47,Cash_Ledger!$C$5:$C$53,"<="&F$48,Cash_Ledger!$A$5:$A$53,"storage") | G60: =-SUMIFS(Cash_Ledger!$D$5:$D$53,Cash_Ledger!$C$5:$C$53,">="&G$47,Cash_Ledger!$C$5:$C$53,"<="&G$48,Cash_Ledger!$A$5:$A$53,"storage") | H60: =-SUMIFS(Cash_Ledger!$D$5:$D$53,Cash_Ledger!$C$5:$C$53,">="&H$47,Cash_Ledger!$C$5:$C$53,"<="&H$48,Cash_Ledger!$A$5:$A$53,"storage") | I60: =-SUMIFS(Cash_Ledger!$D$5:$D$53,Cash_Ledger!$C$5:$C$53,">="&I$47,Cash_Ledger!$C$5:$C$53,"<="&I$48,Cash_Ledger!$A$5:$A$53,"storage") | J60: =SUM(C60:I60)
B61: Phone | C61: =-SUMIFS(Cash_Ledger!$D$5:$D$53,Cash_Ledger!$C$5:$C$53,">="&C$47,Cash_Ledger!$C$5:$C$53,"<="&C$48,Cash_Ledger!$A$5:$A$53,"phone") | D61: =-SUMIFS(Cash_Ledger!$D$5:$D$53,Cash_Ledger!$C$5:$C$53,">="&D$47,Cash_Ledger!$C$5:$C$53,"<="&D$48,Cash_Ledger!$A$5:$A$53,"phone") | E61: =-SUMIFS(Cash_Ledger!$D$5:$D$53,Cash_Ledger!$C$5:$C$53,">="&E$47,Cash_Ledger!$C$5:$C$53,"<="&E$48,Cash_Ledger!$A$5:$A$53,"phone") | F61: =-SUMIFS(Cash_Ledger!$D$5:$D$53,Cash_Ledger!$C$5:$C$53,">="&F$47,Cash_Ledger!$C$5:$C$53,"<="&F$48,Cash_Ledger!$A$5:$A$53,"phone") | G61: =-SUMIFS(Cash_Ledger!$D$5:$D$53,Cash_Ledger!$C$5:$C$53,">="&G$47,Cash_Ledger!$C$5:$C$53,"<="&G$48,Cash_Ledger!$A$5:$A$53,"phone") | H61: =-SUMIFS(Cash_Ledger!$D$5:$D$53,Cash_Ledger!$C$5:$C$53,">="&H$47,Cash_Ledger!$C$5:$C$53,"<="&H$48,Cash_Ledger!$A$5:$A$53,"phone") | I61: =-SUMIFS(Cash_Ledger!$D$5:$D$53,Cash_Ledger!$C$5:$C$53,">="&I$47,Cash_Ledger!$C$5:$C$53,"<="&I$48,Cash_Ledger!$A$5:$A$53,"phone") | J61: =SUM(C61:I61)
B62: Total overhead | C62: =C58+C59+C60+C61 | D62: =D58+D59+D60+D61 | E62: =E58+E59+E60+E61 | F62: =F58+F59+F60+F61 | G62: =G58+G59+G60+G61 | H62: =H58+H59+H60+H61 | I62: =I58+I59+I60+I61 | J62: =SUM(C62:I62)
B63: Startup outlays (Inputs section 11) | C63: =-SUMIFS(Inputs!$Q$148:$Q$159,Inputs!$R$148:$R$159,">="&C$47,Inputs!$R$148:$R$159,"<="&C$48) | D63: =-SUMIFS(Inputs!$Q$148:$Q$159,Inputs!$R$148:$R$159,">="&D$47,Inputs!$R$148:$R$159,"<="&D$48) | E63: =-SUMIFS(Inputs!$Q$148:$Q$159,Inputs!$R$148:$R$159,">="&E$47,Inputs!$R$148:$R$159,"<="&E$48) | F63: =-SUMIFS(Inputs!$Q$148:$Q$159,Inputs!$R$148:$R$159,">="&F$47,Inputs!$R$148:$R$159,"<="&F$48) | G63: =-SUMIFS(Inputs!$Q$148:$Q$159,Inputs!$R$148:$R$159,">="&G$47,Inputs!$R$148:$R$159,"<="&G$48) | H63: =-SUMIFS(Inputs!$Q$148:$Q$159,Inputs!$R$148:$R$159,">="&H$47,Inputs!$R$148:$R$159,"<="&H$48) | I63: =-SUMIFS(Inputs!$Q$148:$Q$159,Inputs!$R$148:$R$159,">="&I$47,Inputs!$R$148:$R$159,"<="&I$48) | J63: =SUM(C63:I63)
B64: Net cash flow | C64: =C51+C57+C62+C63 | D64: =D51+D57+D62+D63 | E64: =E51+E57+E62+E63 | F64: =F51+F57+F62+F63 | G64: =G51+G57+G62+G63 | H64: =H51+H57+H62+H63 | I64: =I51+I57+I62+I63 | J64: =SUM(C64:I64)
B66: Check: monthly six-month net equals the weekly six-month net (difference) | C66: =J64-AC26
B67: Overhead allocated to drops in the six months (a view, not paid) | C67: =SUMIFS(Drop_PnL!$AM$7:$AM$18,Drop_PnL!$B$7:$B$18,">="&Inputs!$C$10,Drop_PnL!$B$7:$B$18,"<="&Cash_Flow!$AB$6)
B68: Overhead paid in the six months (Cash_Ledger) | C68: =-AC24
B69: Overhead not absorbed by drops (paid less allocated) | C69: =C68-C67

Sheet Steady_State
A1: Monthly steady state and break-even
A2: Engine rows below compute one drop; the monthly view multiplies by drops per month and pays overhead once.
A3: Planning estimates, not a forecast. 'Plan reading (e)' reproduces the plan's monthly picture; 'Active scenario' uses the scenario in force on Inputs.
A5: Case | E5: Inputs to the engine | N5: Revenue | T5: Hard costs | AB5: Founder hours by activity | AJ5: Result | AL5: Split
A6: Drop or case | B6: Drop date | C6: Delivery model | D6: Tier | E6: Offices | F6: New offices | G6: Brands | H6: of which renewals | I6: of which founding-rate renewals | J6: Standard price per office | K6: Founding price per office | L6: Storage allocated (1/0) | M6: Card processing (1/0) | N6: Drop runs (1/0) | O6: New founding brands | P6: New standard brands | Q6: Revenue at founding rate | R6: Revenue at standard rate | S6: Revenue | T6: Display kits | U6: Transport | V6: Kit mailing | W6: Card processing | X6: Storage allocation | Y6: Software allocation | Z6: Insurance allocation | AA6: Hard costs | AB6: brand_sales (h) | AC6: office_coordination (h) | AD6: receiving_kitting (h) | AE6: drop_day (h) | AF6: checks_pickup (h) | AG6: reporting_debriefs (h) | AH6: admin_invoicing (h) | AI6: Founder hours | AJ6: Contribution | AK6: Contribution per founder hour | AL6: Direct costs (kits, transport, mailing, processing) | AM6: Overhead allocations (views of monthly costs)
A7: Plan reading (e): one three-brand courier drop, all new brands | C7: courier | D7: standard | E7: 10 | F7: 0 | G7: 3 | H7: 0 | I7: 0 | J7: 150 | K7: =Inputs!$C$36 | L7: 1 | M7: 1 | N7: =IF(G7>0,1,0) | O7: =IF(D7="founding",G7-H7,0) | P7: =IF(D7="standard",G7-H7,0) | Q7: =O7*(K7*MIN(E7,Inputs!$C$37)+Inputs!$C$39*MAX(E7-Inputs!$C$37,0))+I7*K7*E7 | R7: =(P7+H7-I7)*(J7*MIN(E7,Inputs!$C$34)+Inputs!$C$39*MAX(E7-Inputs!$C$34,0)) | S7: =Q7+R7 | T7: =N7*E7*(Inputs!$C$58+Inputs!$C$59*MAX(G7-1,0)) | U7: =IF(N7=0,0,INDEX(Inputs!$C$95:$C$97,MATCH(C7,Inputs!$B$95:$B$97,0))+INDEX(Inputs!$D$95:$D$97,MATCH(C7,Inputs!$B$95:$B$97,0))*E7) | V7: =IF(N7=0,0,INDEX(Inputs!$E$95:$E$97,MATCH(C7,Inputs!$B$95:$B$97,0))*E7) | W7: =S7*Inputs!$C$48*M7 | X7: =N7*L7*Inputs!$C$66/Inputs!$C$75 | Y7: =N7*Inputs!$C$69/Inputs!$C$75 | Z7: =N7*Inputs!$C$71/Inputs!$C$75 | AA7: =SUM(T7:Z7) | AB7: =O7*Inputs!$C$79+P7*Inputs!$C$83+H7*Inputs!$C$84 | AC7: =N7*(F7*Inputs!$C$85+(E7-F7)*Inputs!$C$86) | AD7: =IF(N7=0,0,INDEX(Inputs!$F$95:$F$97,MATCH(C7,Inputs!$B$95:$B$97,0))+Inputs!$C$87*G7) | AE7: =IF(N7=0,0,INDEX(Inputs!$G$95:$G$97,MATCH(C7,Inputs!$B$95:$B$97,0))*E7) | AF7: =IF(N7=0,0,INDEX(Inputs!$H$95:$H$97,MATCH(C7,Inputs!$B$95:$B$97,0))*E7) | AG7: =Inputs!$C$88*G7 | AH7: =N7*Inputs!$C$89 | AI7: =SUM(AB7:AH7) | AJ7: =S7-AA7 | AK7: =IF(AI7>0,AJ7/AI7,"n/a") | AL7: =T7+U7+V7+W7 | AM7: =X7+Y7+Z7
A8: Active scenario: one steady-state drop | C8: =Inputs!$C$103 | D8: standard | E8: =Inputs!$C$104 | F8: 0 | G8: =Scenarios!$H$16 | H8: =Scenarios!$H$12*G8 | I8: 0 | J8: =Scenarios!$H$14 | K8: =Inputs!$C$36 | L8: =IF(Inputs!$C$65="unit",1,0) | M8: =Inputs!$C$49 | N8: =IF(G8>0,1,0) | O8: =IF(D8="founding",G8-H8,0) | P8: =IF(D8="standard",G8-H8,0) | Q8: =O8*(K8*MIN(E8,Inputs!$C$37)+Inputs!$C$39*MAX(E8-Inputs!$C$37,0))+I8*K8*E8 | R8: =(P8+H8-I8)*(J8*MIN(E8,Inputs!$C$34)+Inputs!$C$39*MAX(E8-Inputs!$C$34,0)) | S8: =Q8+R8 | T8: =N8*E8*(Inputs!$C$58+Inputs!$C$59*MAX(G8-1,0)) | U8: =IF(N8=0,0,INDEX(Inputs!$C$95:$C$97,MATCH(C8,Inputs!$B$95:$B$97,0))+INDEX(Inputs!$D$95:$D$97,MATCH(C8,Inputs!$B$95:$B$97,0))*E8) | V8: =IF(N8=0,0,INDEX(Inputs!$E$95:$E$97,MATCH(C8,Inputs!$B$95:$B$97,0))*E8) | W8: =S8*Inputs!$C$48*M8 | X8: =N8*L8*Inputs!$C$66/Inputs!$C$75 | Y8: =N8*Inputs!$C$69/Inputs!$C$75 | Z8: =N8*Inputs!$C$71/Inputs!$C$75 | AA8: =SUM(T8:Z8) | AB8: =O8*Inputs!$C$79+P8*Inputs!$C$83+H8*Inputs!$C$84 | AC8: =N8*(F8*Inputs!$C$85+(E8-F8)*Inputs!$C$86) | AD8: =IF(N8=0,0,INDEX(Inputs!$F$95:$F$97,MATCH(C8,Inputs!$B$95:$B$97,0))+Inputs!$C$87*G8) | AE8: =IF(N8=0,0,INDEX(Inputs!$G$95:$G$97,MATCH(C8,Inputs!$B$95:$B$97,0))*E8) | AF8: =IF(N8=0,0,INDEX(Inputs!$H$95:$H$97,MATCH(C8,Inputs!$B$95:$B$97,0))*E8) | AG8: =Inputs!$C$88*G8 | AH8: =N8*Inputs!$C$89 | AI8: =SUM(AB8:AH8) | AJ8: =S8-AA8 | AK8: =IF(AI8>0,AJ8/AI8,"n/a") | AL8: =T8+U8+V8+W8 | AM8: =X8+Y8+Z8
A9: Break-even: one-brand standard courier drop, new brand | C9: courier | D9: standard | E9: =Inputs!$C$104 | F9: 0 | G9: 1 | H9: 0 | I9: 0 | J9: =Inputs!$C$33 | K9: =Inputs!$C$36 | L9: =IF(Inputs!$C$65="unit",1,0) | M9: =Inputs!$C$49 | N9: =IF(G9>0,1,0) | O9: =IF(D9="founding",G9-H9,0) | P9: =IF(D9="standard",G9-H9,0) | Q9: =O9*(K9*MIN(E9,Inputs!$C$37)+Inputs!$C$39*MAX(E9-Inputs!$C$37,0))+I9*K9*E9 | R9: =(P9+H9-I9)*(J9*MIN(E9,Inputs!$C$34)+Inputs!$C$39*MAX(E9-Inputs!$C$34,0)) | S9: =Q9+R9 | T9: =N9*E9*(Inputs!$C$58+Inputs!$C$59*MAX(G9-1,0)) | U9: =IF(N9=0,0,INDEX(Inputs!$C$95:$C$97,MATCH(C9,Inputs!$B$95:$B$97,0))+INDEX(Inputs!$D$95:$D$97,MATCH(C9,Inputs!$B$95:$B$97,0))*E9) | V9: =IF(N9=0,0,INDEX(Inputs!$E$95:$E$97,MATCH(C9,Inputs!$B$95:$B$97,0))*E9) | W9: =S9*Inputs!$C$48*M9 | X9: =N9*L9*Inputs!$C$66/Inputs!$C$75 | Y9: =N9*Inputs!$C$69/Inputs!$C$75 | Z9: =N9*Inputs!$C$71/Inputs!$C$75 | AA9: =SUM(T9:Z9) | AB9: =O9*Inputs!$C$79+P9*Inputs!$C$83+H9*Inputs!$C$84 | AC9: =N9*(F9*Inputs!$C$85+(E9-F9)*Inputs!$C$86) | AD9: =IF(N9=0,0,INDEX(Inputs!$F$95:$F$97,MATCH(C9,Inputs!$B$95:$B$97,0))+Inputs!$C$87*G9) | AE9: =IF(N9=0,0,INDEX(Inputs!$G$95:$G$97,MATCH(C9,Inputs!$B$95:$B$97,0))*E9) | AF9: =IF(N9=0,0,INDEX(Inputs!$H$95:$H$97,MATCH(C9,Inputs!$B$95:$B$97,0))*E9) | AG9: =Inputs!$C$88*G9 | AH9: =N9*Inputs!$C$89 | AI9: =SUM(AB9:AH9) | AJ9: =S9-AA9 | AK9: =IF(AI9>0,AJ9/AI9,"n/a") | AL9: =T9+U9+V9+W9 | AM9: =X9+Y9+Z9
A10: Crossing: courier, 1 new brand | C10: =Inputs!$C$103 | D10: standard | E10: =Inputs!$C$104 | F10: 0 | G10: 1 | H10: 0 | I10: 0 | J10: =Inputs!$C$33 | K10: =Inputs!$C$36 | L10: =IF(Inputs!$C$65="unit",1,0) | M10: =Inputs!$C$49 | N10: =IF(G10>0,1,0) | O10: =IF(D10="founding",G10-H10,0) | P10: =IF(D10="standard",G10-H10,0) | Q10: =O10*(K10*MIN(E10,Inputs!$C$37)+Inputs!$C$39*MAX(E10-Inputs!$C$37,0))+I10*K10*E10 | R10: =(P10+H10-I10)*(J10*MIN(E10,Inputs!$C$34)+Inputs!$C$39*MAX(E10-Inputs!$C$34,0)) | S10: =Q10+R10 | T10: =N10*E10*(Inputs!$C$58+Inputs!$C$59*MAX(G10-1,0)) | U10: =IF(N10=0,0,INDEX(Inputs!$C$95:$C$97,MATCH(C10,Inputs!$B$95:$B$97,0))+INDEX(Inputs!$D$95:$D$97,MATCH(C10,Inputs!$B$95:$B$97,0))*E10) | V10: =IF(N10=0,0,INDEX(Inputs!$E$95:$E$97,MATCH(C10,Inputs!$B$95:$B$97,0))*E10) | W10: =S10*Inputs!$C$48*M10 | X10: =N10*L10*Inputs!$C$66/Inputs!$C$75 | Y10: =N10*Inputs!$C$69/Inputs!$C$75 | Z10: =N10*Inputs!$C$71/Inputs!$C$75 | AA10: =SUM(T10:Z10) | AB10: =O10*Inputs!$C$79+P10*Inputs!$C$83+H10*Inputs!$C$84 | AC10: =N10*(F10*Inputs!$C$85+(E10-F10)*Inputs!$C$86) | AD10: =IF(N10=0,0,INDEX(Inputs!$F$95:$F$97,MATCH(C10,Inputs!$B$95:$B$97,0))+Inputs!$C$87*G10) | AE10: =IF(N10=0,0,INDEX(Inputs!$G$95:$G$97,MATCH(C10,Inputs!$B$95:$B$97,0))*E10) | AF10: =IF(N10=0,0,INDEX(Inputs!$H$95:$H$97,MATCH(C10,Inputs!$B$95:$B$97,0))*E10) | AG10: =Inputs!$C$88*G10 | AH10: =N10*Inputs!$C$89 | AI10: =SUM(AB10:AH10) | AJ10: =S10-AA10 | AK10: =IF(AI10>0,AJ10/AI10,"n/a") | AL10: =T10+U10+V10+W10 | AM10: =X10+Y10+Z10
A11: Crossing: courier, 2 new brands | C11: =Inputs!$C$103 | D11: standard | E11: =Inputs!$C$104 | F11: 0 | G11: 2 | H11: 0 | I11: 0 | J11: =Inputs!$C$33 | K11: =Inputs!$C$36 | L11: =IF(Inputs!$C$65="unit",1,0) | M11: =Inputs!$C$49 | N11: =IF(G11>0,1,0) | O11: =IF(D11="founding",G11-H11,0) | P11: =IF(D11="standard",G11-H11,0) | Q11: =O11*(K11*MIN(E11,Inputs!$C$37)+Inputs!$C$39*MAX(E11-Inputs!$C$37,0))+I11*K11*E11 | R11: =(P11+H11-I11)*(J11*MIN(E11,Inputs!$C$34)+Inputs!$C$39*MAX(E11-Inputs!$C$34,0)) | S11: =Q11+R11 | T11: =N11*E11*(Inputs!$C$58+Inputs!$C$59*MAX(G11-1,0)) | U11: =IF(N11=0,0,INDEX(Inputs!$C$95:$C$97,MATCH(C11,Inputs!$B$95:$B$97,0))+INDEX(Inputs!$D$95:$D$97,MATCH(C11,Inputs!$B$95:$B$97,0))*E11) | V11: =IF(N11=0,0,INDEX(Inputs!$E$95:$E$97,MATCH(C11,Inputs!$B$95:$B$97,0))*E11) | W11: =S11*Inputs!$C$48*M11 | X11: =N11*L11*Inputs!$C$66/Inputs!$C$75 | Y11: =N11*Inputs!$C$69/Inputs!$C$75 | Z11: =N11*Inputs!$C$71/Inputs!$C$75 | AA11: =SUM(T11:Z11) | AB11: =O11*Inputs!$C$79+P11*Inputs!$C$83+H11*Inputs!$C$84 | AC11: =N11*(F11*Inputs!$C$85+(E11-F11)*Inputs!$C$86) | AD11: =IF(N11=0,0,INDEX(Inputs!$F$95:$F$97,MATCH(C11,Inputs!$B$95:$B$97,0))+Inputs!$C$87*G11) | AE11: =IF(N11=0,0,INDEX(Inputs!$G$95:$G$97,MATCH(C11,Inputs!$B$95:$B$97,0))*E11) | AF11: =IF(N11=0,0,INDEX(Inputs!$H$95:$H$97,MATCH(C11,Inputs!$B$95:$B$97,0))*E11) | AG11: =Inputs!$C$88*G11 | AH11: =N11*Inputs!$C$89 | AI11: =SUM(AB11:AH11) | AJ11: =S11-AA11 | AK11: =IF(AI11>0,AJ11/AI11,"n/a") | AL11: =T11+U11+V11+W11 | AM11: =X11+Y11+Z11
A12: Crossing at the active renewal rate, 1 brand | C12: =Inputs!$C$103 | D12: standard | E12: =Inputs!$C$104 | F12: 0 | G12: 1 | H12: =Scenarios!$H$12*G12 | I12: 0 | J12: =Inputs!$C$33 | K12: =Inputs!$C$36 | L12: =IF(Inputs!$C$65="unit",1,0) | M12: =Inputs!$C$49 | N12: =IF(G12>0,1,0) | O12: =IF(D12="founding",G12-H12,0) | P12: =IF(D12="standard",G12-H12,0) | Q12: =O12*(K12*MIN(E12,Inputs!$C$37)+Inputs!$C$39*MAX(E12-Inputs!$C$37,0))+I12*K12*E12 | R12: =(P12+H12-I12)*(J12*MIN(E12,Inputs!$C$34)+Inputs!$C$39*MAX(E12-Inputs!$C$34,0)) | S12: =Q12+R12 | T12: =N12*E12*(Inputs!$C$58+Inputs!$C$59*MAX(G12-1,0)) | U12: =IF(N12=0,0,INDEX(Inputs!$C$95:$C$97,MATCH(C12,Inputs!$B$95:$B$97,0))+INDEX(Inputs!$D$95:$D$97,MATCH(C12,Inputs!$B$95:$B$97,0))*E12) | V12: =IF(N12=0,0,INDEX(Inputs!$E$95:$E$97,MATCH(C12,Inputs!$B$95:$B$97,0))*E12) | W12: =S12*Inputs!$C$48*M12 | X12: =N12*L12*Inputs!$C$66/Inputs!$C$75 | Y12: =N12*Inputs!$C$69/Inputs!$C$75 | Z12: =N12*Inputs!$C$71/Inputs!$C$75 | AA12: =SUM(T12:Z12) | AB12: =O12*Inputs!$C$79+P12*Inputs!$C$83+H12*Inputs!$C$84 | AC12: =N12*(F12*Inputs!$C$85+(E12-F12)*Inputs!$C$86) | AD12: =IF(N12=0,0,INDEX(Inputs!$F$95:$F$97,MATCH(C12,Inputs!$B$95:$B$97,0))+Inputs!$C$87*G12) | AE12: =IF(N12=0,0,INDEX(Inputs!$G$95:$G$97,MATCH(C12,Inputs!$B$95:$B$97,0))*E12) | AF12: =IF(N12=0,0,INDEX(Inputs!$H$95:$H$97,MATCH(C12,Inputs!$B$95:$B$97,0))*E12) | AG12: =Inputs!$C$88*G12 | AH12: =N12*Inputs!$C$89 | AI12: =SUM(AB12:AH12) | AJ12: =S12-AA12 | AK12: =IF(AI12>0,AJ12/AI12,"n/a") | AL12: =T12+U12+V12+W12 | AM12: =X12+Y12+Z12
A13: Crossing at the active renewal rate, 2 brands | C13: =Inputs!$C$103 | D13: standard | E13: =Inputs!$C$104 | F13: 0 | G13: 2 | H13: =Scenarios!$H$12*G13 | I13: 0 | J13: =Inputs!$C$33 | K13: =Inputs!$C$36 | L13: =IF(Inputs!$C$65="unit",1,0) | M13: =Inputs!$C$49 | N13: =IF(G13>0,1,0) | O13: =IF(D13="founding",G13-H13,0) | P13: =IF(D13="standard",G13-H13,0) | Q13: =O13*(K13*MIN(E13,Inputs!$C$37)+Inputs!$C$39*MAX(E13-Inputs!$C$37,0))+I13*K13*E13 | R13: =(P13+H13-I13)*(J13*MIN(E13,Inputs!$C$34)+Inputs!$C$39*MAX(E13-Inputs!$C$34,0)) | S13: =Q13+R13 | T13: =N13*E13*(Inputs!$C$58+Inputs!$C$59*MAX(G13-1,0)) | U13: =IF(N13=0,0,INDEX(Inputs!$C$95:$C$97,MATCH(C13,Inputs!$B$95:$B$97,0))+INDEX(Inputs!$D$95:$D$97,MATCH(C13,Inputs!$B$95:$B$97,0))*E13) | V13: =IF(N13=0,0,INDEX(Inputs!$E$95:$E$97,MATCH(C13,Inputs!$B$95:$B$97,0))*E13) | W13: =S13*Inputs!$C$48*M13 | X13: =N13*L13*Inputs!$C$66/Inputs!$C$75 | Y13: =N13*Inputs!$C$69/Inputs!$C$75 | Z13: =N13*Inputs!$C$71/Inputs!$C$75 | AA13: =SUM(T13:Z13) | AB13: =O13*Inputs!$C$79+P13*Inputs!$C$83+H13*Inputs!$C$84 | AC13: =N13*(F13*Inputs!$C$85+(E13-F13)*Inputs!$C$86) | AD13: =IF(N13=0,0,INDEX(Inputs!$F$95:$F$97,MATCH(C13,Inputs!$B$95:$B$97,0))+Inputs!$C$87*G13) | AE13: =IF(N13=0,0,INDEX(Inputs!$G$95:$G$97,MATCH(C13,Inputs!$B$95:$B$97,0))*E13) | AF13: =IF(N13=0,0,INDEX(Inputs!$H$95:$H$97,MATCH(C13,Inputs!$B$95:$B$97,0))*E13) | AG13: =Inputs!$C$88*G13 | AH13: =N13*Inputs!$C$89 | AI13: =SUM(AB13:AH13) | AJ13: =S13-AA13 | AK13: =IF(AI13>0,AJ13/AI13,"n/a") | AL13: =T13+U13+V13+W13 | AM13: =X13+Y13+Z13
A14: Crossing: direct-ship, 1 new brand | C14: direct-ship | D14: standard | E14: =Inputs!$C$104 | F14: 0 | G14: 1 | H14: 0 | I14: 0 | J14: =Inputs!$C$33 | K14: =Inputs!$C$36 | L14: =IF(Inputs!$C$65="unit",1,0) | M14: =Inputs!$C$49 | N14: =IF(G14>0,1,0) | O14: =IF(D14="founding",G14-H14,0) | P14: =IF(D14="standard",G14-H14,0) | Q14: =O14*(K14*MIN(E14,Inputs!$C$37)+Inputs!$C$39*MAX(E14-Inputs!$C$37,0))+I14*K14*E14 | R14: =(P14+H14-I14)*(J14*MIN(E14,Inputs!$C$34)+Inputs!$C$39*MAX(E14-Inputs!$C$34,0)) | S14: =Q14+R14 | T14: =N14*E14*(Inputs!$C$58+Inputs!$C$59*MAX(G14-1,0)) | U14: =IF(N14=0,0,INDEX(Inputs!$C$95:$C$97,MATCH(C14,Inputs!$B$95:$B$97,0))+INDEX(Inputs!$D$95:$D$97,MATCH(C14,Inputs!$B$95:$B$97,0))*E14) | V14: =IF(N14=0,0,INDEX(Inputs!$E$95:$E$97,MATCH(C14,Inputs!$B$95:$B$97,0))*E14) | W14: =S14*Inputs!$C$48*M14 | X14: =N14*L14*Inputs!$C$66/Inputs!$C$75 | Y14: =N14*Inputs!$C$69/Inputs!$C$75 | Z14: =N14*Inputs!$C$71/Inputs!$C$75 | AA14: =SUM(T14:Z14) | AB14: =O14*Inputs!$C$79+P14*Inputs!$C$83+H14*Inputs!$C$84 | AC14: =N14*(F14*Inputs!$C$85+(E14-F14)*Inputs!$C$86) | AD14: =IF(N14=0,0,INDEX(Inputs!$F$95:$F$97,MATCH(C14,Inputs!$B$95:$B$97,0))+Inputs!$C$87*G14) | AE14: =IF(N14=0,0,INDEX(Inputs!$G$95:$G$97,MATCH(C14,Inputs!$B$95:$B$97,0))*E14) | AF14: =IF(N14=0,0,INDEX(Inputs!$H$95:$H$97,MATCH(C14,Inputs!$B$95:$B$97,0))*E14) | AG14: =Inputs!$C$88*G14 | AH14: =N14*Inputs!$C$89 | AI14: =SUM(AB14:AH14) | AJ14: =S14-AA14 | AK14: =IF(AI14>0,AJ14/AI14,"n/a") | AL14: =T14+U14+V14+W14 | AM14: =X14+Y14+Z14
A15: Crossing: direct-ship, 2 new brands | C15: direct-ship | D15: standard | E15: =Inputs!$C$104 | F15: 0 | G15: 2 | H15: 0 | I15: 0 | J15: =Inputs!$C$33 | K15: =Inputs!$C$36 | L15: =IF(Inputs!$C$65="unit",1,0) | M15: =Inputs!$C$49 | N15: =IF(G15>0,1,0) | O15: =IF(D15="founding",G15-H15,0) | P15: =IF(D15="standard",G15-H15,0) | Q15: =O15*(K15*MIN(E15,Inputs!$C$37)+Inputs!$C$39*MAX(E15-Inputs!$C$37,0))+I15*K15*E15 | R15: =(P15+H15-I15)*(J15*MIN(E15,Inputs!$C$34)+Inputs!$C$39*MAX(E15-Inputs!$C$34,0)) | S15: =Q15+R15 | T15: =N15*E15*(Inputs!$C$58+Inputs!$C$59*MAX(G15-1,0)) | U15: =IF(N15=0,0,INDEX(Inputs!$C$95:$C$97,MATCH(C15,Inputs!$B$95:$B$97,0))+INDEX(Inputs!$D$95:$D$97,MATCH(C15,Inputs!$B$95:$B$97,0))*E15) | V15: =IF(N15=0,0,INDEX(Inputs!$E$95:$E$97,MATCH(C15,Inputs!$B$95:$B$97,0))*E15) | W15: =S15*Inputs!$C$48*M15 | X15: =N15*L15*Inputs!$C$66/Inputs!$C$75 | Y15: =N15*Inputs!$C$69/Inputs!$C$75 | Z15: =N15*Inputs!$C$71/Inputs!$C$75 | AA15: =SUM(T15:Z15) | AB15: =O15*Inputs!$C$79+P15*Inputs!$C$83+H15*Inputs!$C$84 | AC15: =N15*(F15*Inputs!$C$85+(E15-F15)*Inputs!$C$86) | AD15: =IF(N15=0,0,INDEX(Inputs!$F$95:$F$97,MATCH(C15,Inputs!$B$95:$B$97,0))+Inputs!$C$87*G15) | AE15: =IF(N15=0,0,INDEX(Inputs!$G$95:$G$97,MATCH(C15,Inputs!$B$95:$B$97,0))*E15) | AF15: =IF(N15=0,0,INDEX(Inputs!$H$95:$H$97,MATCH(C15,Inputs!$B$95:$B$97,0))*E15) | AG15: =Inputs!$C$88*G15 | AH15: =N15*Inputs!$C$89 | AI15: =SUM(AB15:AH15) | AJ15: =S15-AA15 | AK15: =IF(AI15>0,AJ15/AI15,"n/a") | AL15: =T15+U15+V15+W15 | AM15: =X15+Y15+Z15
A16: Price crossing: 3 brands at the first sensitivity price | C16: =Inputs!$C$103 | D16: standard | E16: =Inputs!$C$104 | F16: 0 | G16: 3 | H16: 0 | I16: 0 | J16: =Inputs!$C$139 | K16: =Inputs!$C$36 | L16: =IF(Inputs!$C$65="unit",1,0) | M16: =Inputs!$C$49 | N16: =IF(G16>0,1,0) | O16: =IF(D16="founding",G16-H16,0) | P16: =IF(D16="standard",G16-H16,0) | Q16: =O16*(K16*MIN(E16,Inputs!$C$37)+Inputs!$C$39*MAX(E16-Inputs!$C$37,0))+I16*K16*E16 | R16: =(P16+H16-I16)*(J16*MIN(E16,Inputs!$C$34)+Inputs!$C$39*MAX(E16-Inputs!$C$34,0)) | S16: =Q16+R16 | T16: =N16*E16*(Inputs!$C$58+Inputs!$C$59*MAX(G16-1,0)) | U16: =IF(N16=0,0,INDEX(Inputs!$C$95:$C$97,MATCH(C16,Inputs!$B$95:$B$97,0))+INDEX(Inputs!$D$95:$D$97,MATCH(C16,Inputs!$B$95:$B$97,0))*E16) | V16: =IF(N16=0,0,INDEX(Inputs!$E$95:$E$97,MATCH(C16,Inputs!$B$95:$B$97,0))*E16) | W16: =S16*Inputs!$C$48*M16 | X16: =N16*L16*Inputs!$C$66/Inputs!$C$75 | Y16: =N16*Inputs!$C$69/Inputs!$C$75 | Z16: =N16*Inputs!$C$71/Inputs!$C$75 | AA16: =SUM(T16:Z16) | AB16: =O16*Inputs!$C$79+P16*Inputs!$C$83+H16*Inputs!$C$84 | AC16: =N16*(F16*Inputs!$C$85+(E16-F16)*Inputs!$C$86) | AD16: =IF(N16=0,0,INDEX(Inputs!$F$95:$F$97,MATCH(C16,Inputs!$B$95:$B$97,0))+Inputs!$C$87*G16) | AE16: =IF(N16=0,0,INDEX(Inputs!$G$95:$G$97,MATCH(C16,Inputs!$B$95:$B$97,0))*E16) | AF16: =IF(N16=0,0,INDEX(Inputs!$H$95:$H$97,MATCH(C16,Inputs!$B$95:$B$97,0))*E16) | AG16: =Inputs!$C$88*G16 | AH16: =N16*Inputs!$C$89 | AI16: =SUM(AB16:AH16) | AJ16: =S16-AA16 | AK16: =IF(AI16>0,AJ16/AI16,"n/a") | AL16: =T16+U16+V16+W16 | AM16: =X16+Y16+Z16
A17: Price crossing: 3 brands at the first price plus one step | C17: =Inputs!$C$103 | D17: standard | E17: =Inputs!$C$104 | F17: 0 | G17: 3 | H17: 0 | I17: 0 | J17: =Inputs!$C$139+Inputs!$C$140 | K17: =Inputs!$C$36 | L17: =IF(Inputs!$C$65="unit",1,0) | M17: =Inputs!$C$49 | N17: =IF(G17>0,1,0) | O17: =IF(D17="founding",G17-H17,0) | P17: =IF(D17="standard",G17-H17,0) | Q17: =O17*(K17*MIN(E17,Inputs!$C$37)+Inputs!$C$39*MAX(E17-Inputs!$C$37,0))+I17*K17*E17 | R17: =(P17+H17-I17)*(J17*MIN(E17,Inputs!$C$34)+Inputs!$C$39*MAX(E17-Inputs!$C$34,0)) | S17: =Q17+R17 | T17: =N17*E17*(Inputs!$C$58+Inputs!$C$59*MAX(G17-1,0)) | U17: =IF(N17=0,0,INDEX(Inputs!$C$95:$C$97,MATCH(C17,Inputs!$B$95:$B$97,0))+INDEX(Inputs!$D$95:$D$97,MATCH(C17,Inputs!$B$95:$B$97,0))*E17) | V17: =IF(N17=0,0,INDEX(Inputs!$E$95:$E$97,MATCH(C17,Inputs!$B$95:$B$97,0))*E17) | W17: =S17*Inputs!$C$48*M17 | X17: =N17*L17*Inputs!$C$66/Inputs!$C$75 | Y17: =N17*Inputs!$C$69/Inputs!$C$75 | Z17: =N17*Inputs!$C$71/Inputs!$C$75 | AA17: =SUM(T17:Z17) | AB17: =O17*Inputs!$C$79+P17*Inputs!$C$83+H17*Inputs!$C$84 | AC17: =N17*(F17*Inputs!$C$85+(E17-F17)*Inputs!$C$86) | AD17: =IF(N17=0,0,INDEX(Inputs!$F$95:$F$97,MATCH(C17,Inputs!$B$95:$B$97,0))+Inputs!$C$87*G17) | AE17: =IF(N17=0,0,INDEX(Inputs!$G$95:$G$97,MATCH(C17,Inputs!$B$95:$B$97,0))*E17) | AF17: =IF(N17=0,0,INDEX(Inputs!$H$95:$H$97,MATCH(C17,Inputs!$B$95:$B$97,0))*E17) | AG17: =Inputs!$C$88*G17 | AH17: =N17*Inputs!$C$89 | AI17: =SUM(AB17:AH17) | AJ17: =S17-AA17 | AK17: =IF(AI17>0,AJ17/AI17,"n/a") | AL17: =T17+U17+V17+W17 | AM17: =X17+Y17+Z17
A20: Monthly steady state
B21: Line | C21: Plan reading (e) | D21: Active scenario | E21: Unit | F21: How it is built
B22: Drops per month | C22: =Inputs!$C$102 | D22: =Scenarios!$H$15 | E22: drops | F22: Inputs / Scenarios
B23: Revenue | C23: =C22*S7 | D23: =D22*S8 | E23: USD per month | F23: drops x one drop
B24: Hard costs (incl. overhead allocations) | C24: =C22*AA7 | D24: =D22*AA8 | E24: USD per month | F24: drops x one drop
B25: Founder hours | C25: =C22*AI7 | D25: =D22*AI8 | E25: hours per month | F25: drops x one drop
B26: Contribution (plan definition) | C26: =C23-C24 | D26: =D23-D24 | E26: USD per month | F26: revenue less hard costs
B27: Contribution per founder hour | C27: =IF(C25>0,C26/C25,"n/a") | D27: =IF(D25>0,D26/D25,"n/a") | E27: USD per hour
B28: Contribution per year at this rate | C28: =C26*Inputs!$C$20 | D28: =D26*Inputs!$C$20 | E28: USD per year | F28: before overhead not absorbed and before tax
B29: Founder hours per week | C29: =C25/Inputs!$C$21 | D29: =D25/Inputs!$C$21 | E29: hours per week | F29: monthly hours / weeks per month
B30: Overhead paid per month | C30: =(Inputs!$C$69+Inputs!$C$71+Inputs!$C$74+Inputs!$C$66*IF(Inputs!$C$65="unit",1,0)) | D30: =(Inputs!$C$69+Inputs!$C$71+Inputs!$C$74+Inputs!$C$66*IF(Inputs!$C$65="unit",1,0)) | E30: USD per month | F30: software + insurance + phone + storage if unit
B31: Overhead allocated to drops per month | C31: =C22*AM7 | D31: =D22*AM8 | E31: USD per month | F31: drops x allocation per drop
B32: Overhead not absorbed by drops | C32: =C30-C31 | D32: =D30-D31 | E32: USD per month | F32: paid less allocated; zero at two drops a month
B33: Office-paid tier revenue | C33: 0 | D33: =Scenarios!$H$17*N(Scenarios!$H$18) | E33: USD per month | F33: scenario B only
B34: Office-paid tier cost to serve (needs quote) | C34: 0 | D34: =Scenarios!$H$17*N(Scenarios!$H$19) | E34: USD per month | F34: blank until quoted
B35: Drop-day hours handed to a hire | C35: 0 | D35: =IF(D22>Scenarios!$H$21,D22*AE8,0) | E35: hours per month | F35: scenario A rule: hire above two drops a month
B36: Delivery hire cost | C36: 0 | D36: =D35*N(Scenarios!$H$20) | E36: USD per month
B37: Net monthly contribution after overhead, office tier and hire | C37: =C26-C32+C33-C34-C36 | D37: =D26-D32+D33-D34-D36 | E37: USD per month
B38: Founder hours net of the hire | C38: =C25-C35 | D38: =D25-D35 | E38: hours per month
B39: Net contribution per founder hour | C39: =IF(C38>0,C37/C38,"n/a") | D39: =IF(D38>0,D37/D38,"n/a") | E39: USD per hour
B40: New brand wins needed per month | C40: =C22*(G7-H7) | D40: =D22*(G8-H8) | E40: wins | F40: brand slots less renewals
B41: Qualified brand conversations per month | C41: =C40/Inputs!$C$80 | D41: =D40/Inputs!$C$80 | E41: conversations | F41: wins / close rate
B42: Office roster so no office gets more than one drop a month | C42: =C22*E7 | D42: =D22*E8 | E42: offices | F42: drops x offices per drop
A45: Break-even
B46: Measure | C46: Value | E46: Unit | F46: How it is built
B47: Startup outlays to recover (one-time cash, Inputs section 11) | C47: =Inputs!$Q$160 | E47: USD | F47: sum of startup cash amounts
B48: Contribution of a one-brand standard courier drop | C48: =AJ9 | E48: USD per campaign | F48: engine row 9
B49: Contribution per brand on a three-brand courier drop | C49: =AJ7/G7 | E49: USD per campaign | F49: engine row 7 / 3; shared costs split equally
B50: Campaigns to recover startup cash, one-brand drops | C50: =IF(C48>0,ROUNDUP(C47/C48,0),"never") | E50: campaigns | F50: startup / contribution, rounded up
B51: Campaigns to recover startup cash, three-brand drops | C51: =IF(C49>0,ROUNDUP(C47/C49,0),"never") | E51: campaigns | F51: startup / contribution per brand, rounded up
B52: One-brand standard drop: contribution before overhead allocations | C52: =AJ9+AM9 | E52: USD per campaign | F52: revenue less direct costs
B53: Overhead paid per month | C53: =Steady_State!$D$30 | E53: USD per month | F53: Monthly steady state
B54: Standard campaigns a month to cover overhead | C54: =IF(C52>0,ROUNDUP(C53/C52,0),"never") | E54: campaigns per month | F54: overhead / contribution before allocations, rounded up
B55: Brands per drop where contribution per hour reaches the Gate 3 target, new brands | C55: =IF((AJ11-AJ10)-Inputs!$C$126*(AI11-AI10)<=0,"never",MAX(0,1+(Inputs!$C$126*AI10-AJ10)/((AJ11-AJ10)-Inputs!$C$126*(AI11-AI10)))) | E55: brands per drop | F55: linear in brands: solved from engine rows 10 and 11
B56: Smallest whole number of brands that clears it | C56: =IF(ISNUMBER(C55),ROUNDUP(C55,0),"never") | E56: brands per drop
B57: Same, at the active renewal rate | C57: =IF((AJ13-AJ12)-Inputs!$C$126*(AI13-AI12)<=0,"never",MAX(0,1+(Inputs!$C$126*AI12-AJ12)/((AJ13-AJ12)-Inputs!$C$126*(AI13-AI12)))) | E57: brands per drop | F57: engine rows 12 and 13
B58: Same, brands ship direct | C58: =IF((AJ15-AJ14)-Inputs!$C$126*(AI15-AI14)<=0,"never",MAX(0,1+(Inputs!$C$126*AI14-AJ14)/((AJ15-AJ14)-Inputs!$C$126*(AI15-AI14)))) | E58: brands per drop | F58: engine rows 14 and 15
B59: Standard price per office where a three-brand drop reaches the target | C59: =IF(S17=S16,"never",J16+(Inputs!$C$126*AI16-AJ16)*(J17-J16)/(AJ17-AJ16)) | E59: USD per office | F59: linear in price: engine rows 16 and 17

Sheet Sensitivity
A1: Sensitivity tables
A2: Plain formulas, no data tables. Reference drop: standard tier, steady-state delivery model and offices, storage and processing as set on Inputs.
A3: Each cell recomputes contribution per founder hour from the inputs. Axis starts and steps are on Inputs section 10. A check cell compares the shortcut with the full engine.
B5: Reference-drop components (from Inputs) | E5: Cross-check with the full engine (current price, active renewal rate)
B6: Offices per drop | C6: =Inputs!$C$104 | E6: Brands used for the check | G6: 3
B7: Revenue kept after card processing | C7: =1-Inputs!$C$48*Inputs!$C$49 | E7: Shortcut formula | G7: =IF(($C$12+$G$6*((1-Scenarios!$H$12)*$C$13+Scenarios!$H$12*$C$14))>0,($G$6*(Inputs!$C$33*$C$9+$C$8)*$C$7-$C$10-$C$11*MAX($G$6-1,0))/($C$12+$G$6*((1-Scenarios!$H$12)*$C$13+Scenarios!$H$12*$C$14)),"n/a")
B8: Revenue per brand from offices beyond the package | C8: =Inputs!$C$39*MAX(C6-Inputs!$C$34,0) | E8: Full engine (row 77) | G8: =AK77
B9: Package offices priced at the per-office rate | C9: =MIN(C6,Inputs!$C$34) | E9: Difference (should be 0) | G9: =G7-G8
B10: Fixed cost per drop (kits, transport, mailing, allocations) | C10: =C6*Inputs!$C$58+INDEX(Inputs!$C$95:$C$97,MATCH(Inputs!$C$103,Inputs!$B$95:$B$97,0))+INDEX(Inputs!$D$95:$D$97,MATCH(Inputs!$C$103,Inputs!$B$95:$B$97,0))*C6+INDEX(Inputs!$E$95:$E$97,MATCH(Inputs!$C$103,Inputs!$B$95:$B$97,0))*C6+(IF(Inputs!$C$65="unit",1,0)*Inputs!$C$66+Inputs!$C$69+Inputs!$C$71)/Inputs!$C$75 | E10: Gate 3 target per founder hour (colours below) | G10: =Inputs!$C$126
B11: Extra card cost per brand beyond the first | C11: =C6*N(Inputs!$C$59)
B12: Fixed hours per drop (existing offices, logistics, admin) | C12: =C6*Inputs!$C$86+INDEX(Inputs!$F$95:$F$97,MATCH(Inputs!$C$103,Inputs!$B$95:$B$97,0))+INDEX(Inputs!$G$95:$G$97,MATCH(Inputs!$C$103,Inputs!$B$95:$B$97,0))*C6+INDEX(Inputs!$H$95:$H$97,MATCH(Inputs!$C$103,Inputs!$B$95:$B$97,0))*C6+Inputs!$C$89
B13: Hours per new brand | C13: =Inputs!$C$83+Inputs!$C$87+Inputs!$C$88
B14: Hours per renewing brand | C14: =Inputs!$C$84+Inputs!$C$87+Inputs!$C$88
B16: Table 1. Contribution per founder hour: price per office (rows) x brands per drop (columns), all brands new
B17: Price per office \ brands | C17: =Inputs!$C$141 | D17: =C17+Inputs!$C$142 | E17: =D17+Inputs!$C$142 | F17: =E17+Inputs!$C$142 | G17: =F17+Inputs!$C$142
B18: =Inputs!$C$139 | C18: =IF(($C$12+C$17*((1-0)*$C$13+0*$C$14))>0,(C$17*($B18*$C$9+$C$8)*$C$7-$C$10-$C$11*MAX(C$17-1,0))/($C$12+C$17*((1-0)*$C$13+0*$C$14)),"n/a") | D18: =IF(($C$12+D$17*((1-0)*$C$13+0*$C$14))>0,(D$17*($B18*$C$9+$C$8)*$C$7-$C$10-$C$11*MAX(D$17-1,0))/($C$12+D$17*((1-0)*$C$13+0*$C$14)),"n/a") | E18: =IF(($C$12+E$17*((1-0)*$C$13+0*$C$14))>0,(E$17*($B18*$C$9+$C$8)*$C$7-$C$10-$C$11*MAX(E$17-1,0))/($C$12+E$17*((1-0)*$C$13+0*$C$14)),"n/a") | F18: =IF(($C$12+F$17*((1-0)*$C$13+0*$C$14))>0,(F$17*($B18*$C$9+$C$8)*$C$7-$C$10-$C$11*MAX(F$17-1,0))/($C$12+F$17*((1-0)*$C$13+0*$C$14)),"n/a") | G18: =IF(($C$12+G$17*((1-0)*$C$13+0*$C$14))>0,(G$17*($B18*$C$9+$C$8)*$C$7-$C$10-$C$11*MAX(G$17-1,0))/($C$12+G$17*((1-0)*$C$13+0*$C$14)),"n/a")
B19: =B18+Inputs!$C$140 | C19: =IF(($C$12+C$17*((1-0)*$C$13+0*$C$14))>0,(C$17*($B19*$C$9+$C$8)*$C$7-$C$10-$C$11*MAX(C$17-1,0))/($C$12+C$17*((1-0)*$C$13+0*$C$14)),"n/a") | D19: =IF(($C$12+D$17*((1-0)*$C$13+0*$C$14))>0,(D$17*($B19*$C$9+$C$8)*$C$7-$C$10-$C$11*MAX(D$17-1,0))/($C$12+D$17*((1-0)*$C$13+0*$C$14)),"n/a") | E19: =IF(($C$12+E$17*((1-0)*$C$13+0*$C$14))>0,(E$17*($B19*$C$9+$C$8)*$C$7-$C$10-$C$11*MAX(E$17-1,0))/($C$12+E$17*((1-0)*$C$13+0*$C$14)),"n/a") | F19: =IF(($C$12+F$17*((1-0)*$C$13+0*$C$14))>0,(F$17*($B19*$C$9+$C$8)*$C$7-$C$10-$C$11*MAX(F$17-1,0))/($C$12+F$17*((1-0)*$C$13+0*$C$14)),"n/a") | G19: =IF(($C$12+G$17*((1-0)*$C$13+0*$C$14))>0,(G$17*($B19*$C$9+$C$8)*$C$7-$C$10-$C$11*MAX(G$17-1,0))/($C$12+G$17*((1-0)*$C$13+0*$C$14)),"n/a")
B20: =B19+Inputs!$C$140 | C20: =IF(($C$12+C$17*((1-0)*$C$13+0*$C$14))>0,(C$17*($B20*$C$9+$C$8)*$C$7-$C$10-$C$11*MAX(C$17-1,0))/($C$12+C$17*((1-0)*$C$13+0*$C$14)),"n/a") | D20: =IF(($C$12+D$17*((1-0)*$C$13+0*$C$14))>0,(D$17*($B20*$C$9+$C$8)*$C$7-$C$10-$C$11*MAX(D$17-1,0))/($C$12+D$17*((1-0)*$C$13+0*$C$14)),"n/a") | E20: =IF(($C$12+E$17*((1-0)*$C$13+0*$C$14))>0,(E$17*($B20*$C$9+$C$8)*$C$7-$C$10-$C$11*MAX(E$17-1,0))/($C$12+E$17*((1-0)*$C$13+0*$C$14)),"n/a") | F20: =IF(($C$12+F$17*((1-0)*$C$13+0*$C$14))>0,(F$17*($B20*$C$9+$C$8)*$C$7-$C$10-$C$11*MAX(F$17-1,0))/($C$12+F$17*((1-0)*$C$13+0*$C$14)),"n/a") | G20: =IF(($C$12+G$17*((1-0)*$C$13+0*$C$14))>0,(G$17*($B20*$C$9+$C$8)*$C$7-$C$10-$C$11*MAX(G$17-1,0))/($C$12+G$17*((1-0)*$C$13+0*$C$14)),"n/a")
B21: =B20+Inputs!$C$140 | C21: =IF(($C$12+C$17*((1-0)*$C$13+0*$C$14))>0,(C$17*($B21*$C$9+$C$8)*$C$7-$C$10-$C$11*MAX(C$17-1,0))/($C$12+C$17*((1-0)*$C$13+0*$C$14)),"n/a") | D21: =IF(($C$12+D$17*((1-0)*$C$13+0*$C$14))>0,(D$17*($B21*$C$9+$C$8)*$C$7-$C$10-$C$11*MAX(D$17-1,0))/($C$12+D$17*((1-0)*$C$13+0*$C$14)),"n/a") | E21: =IF(($C$12+E$17*((1-0)*$C$13+0*$C$14))>0,(E$17*($B21*$C$9+$C$8)*$C$7-$C$10-$C$11*MAX(E$17-1,0))/($C$12+E$17*((1-0)*$C$13+0*$C$14)),"n/a") | F21: =IF(($C$12+F$17*((1-0)*$C$13+0*$C$14))>0,(F$17*($B21*$C$9+$C$8)*$C$7-$C$10-$C$11*MAX(F$17-1,0))/($C$12+F$17*((1-0)*$C$13+0*$C$14)),"n/a") | G21: =IF(($C$12+G$17*((1-0)*$C$13+0*$C$14))>0,(G$17*($B21*$C$9+$C$8)*$C$7-$C$10-$C$11*MAX(G$17-1,0))/($C$12+G$17*((1-0)*$C$13+0*$C$14)),"n/a")
B22: =B21+Inputs!$C$140 | C22: =IF(($C$12+C$17*((1-0)*$C$13+0*$C$14))>0,(C$17*($B22*$C$9+$C$8)*$C$7-$C$10-$C$11*MAX(C$17-1,0))/($C$12+C$17*((1-0)*$C$13+0*$C$14)),"n/a") | D22: =IF(($C$12+D$17*((1-0)*$C$13+0*$C$14))>0,(D$17*($B22*$C$9+$C$8)*$C$7-$C$10-$C$11*MAX(D$17-1,0))/($C$12+D$17*((1-0)*$C$13+0*$C$14)),"n/a") | E22: =IF(($C$12+E$17*((1-0)*$C$13+0*$C$14))>0,(E$17*($B22*$C$9+$C$8)*$C$7-$C$10-$C$11*MAX(E$17-1,0))/($C$12+E$17*((1-0)*$C$13+0*$C$14)),"n/a") | F22: =IF(($C$12+F$17*((1-0)*$C$13+0*$C$14))>0,(F$17*($B22*$C$9+$C$8)*$C$7-$C$10-$C$11*MAX(F$17-1,0))/($C$12+F$17*((1-0)*$C$13+0*$C$14)),"n/a") | G22: =IF(($C$12+G$17*((1-0)*$C$13+0*$C$14))>0,(G$17*($B22*$C$9+$C$8)*$C$7-$C$10-$C$11*MAX(G$17-1,0))/($C$12+G$17*((1-0)*$C$13+0*$C$14)),"n/a")
B23: =B22+Inputs!$C$140 | C23: =IF(($C$12+C$17*((1-0)*$C$13+0*$C$14))>0,(C$17*($B23*$C$9+$C$8)*$C$7-$C$10-$C$11*MAX(C$17-1,0))/($C$12+C$17*((1-0)*$C$13+0*$C$14)),"n/a") | D23: =IF(($C$12+D$17*((1-0)*$C$13+0*$C$14))>0,(D$17*($B23*$C$9+$C$8)*$C$7-$C$10-$C$11*MAX(D$17-1,0))/($C$12+D$17*((1-0)*$C$13+0*$C$14)),"n/a") | E23: =IF(($C$12+E$17*((1-0)*$C$13+0*$C$14))>0,(E$17*($B23*$C$9+$C$8)*$C$7-$C$10-$C$11*MAX(E$17-1,0))/($C$12+E$17*((1-0)*$C$13+0*$C$14)),"n/a") | F23: =IF(($C$12+F$17*((1-0)*$C$13+0*$C$14))>0,(F$17*($B23*$C$9+$C$8)*$C$7-$C$10-$C$11*MAX(F$17-1,0))/($C$12+F$17*((1-0)*$C$13+0*$C$14)),"n/a") | G23: =IF(($C$12+G$17*((1-0)*$C$13+0*$C$14))>0,(G$17*($B23*$C$9+$C$8)*$C$7-$C$10-$C$11*MAX(G$17-1,0))/($C$12+G$17*((1-0)*$C$13+0*$C$14)),"n/a")
