Workbook

Sheet Offices
A1: row_id | B1: company | C1: website | D1: domain | E1: rank | F1: score_at_build | G1: ready_at_build | H1: primary_first_name | I1: primary_last_name | J1: primary_title | K1: primary_linkedin_url | L1: primary_contact_role | M1: primary_contact_status | N1: primary_contact_evidence | O1: primary_contact_source_url | P1: primary_contact_source_date | Q1: backup_first_name | R1: backup_last_name | S1: backup_title | T1: backup_linkedin_url | U1: backup_contact_role | V1: backup_contact_status | W1: backup_contact_evidence | X1: backup_contact_source_url | Y1: backup_contact_source_date | Z1: backup_contact_name_as_found | AA1: backup_contact_record_date | AB1: backup_contact_note | AC1: backup_contact_ny_base | AD1: backup_linkedin_status | AE1: street_address | AF1: floor | AG1: industry | AH1: employee_count | AI1: linkedin_company_url | AJ1: top50 | AK1: onsite_band | AL1: contacts_researched | AM1: onsite_high | AN1: onsite_confidence | AO1: attendance_signal | AP1: company_group | AQ1: hold_before_outreach | AR1: hold_reason | AS1: opt_out_date | AT1: ready_for_outreach | AU1: ready_reason | AV1: founder_ok_to_queue | AW1: promote_backup | AX1: onsite_founder_call | AY1: primary_first_name | AZ1: primary_last_name | BA1: primary_title | BB1: primary_linkedin_url | BC1: primary_work_email | BD1: primary_email_status | BE1: primary_contact_role | BF1: primary_contact_status | BG1: primary_contact_evidence | BH1: primary_contact_source_url | BI1: primary_contact_source_date | BJ1: primary_title_match | BK1: primary_check_before_send | BL1: primary_reason_who | BM1: backup_first_name | BN1: backup_last_name | BO1: backup_title | BP1: backup_linkedin_url | BQ1: backup_work_email | BR1: backup_email_status | BS1: backup_contact_role | BT1: backup_contact_status | BU1: backup_contact_evidence | BV1: backup_contact_source_url | BW1: backup_contact_source_date | BX1: backup_title_match | BY1: backup_check_before_send | BZ1: backup_reason_who | CA1: score_reason_core | CB1: channel_base | CC1: contact_name_as_found | CD1: contact_record_date | CE1: contact_note | CF1: contact_ny_base | CG1: linkedin_status | CH1: backup_contact_name_as_found | CI1: backup_contact_record_date | CJ1: backup_contact_note | CK1: backup_contact_ny_base | CL1: backup_linkedin_status | CM1: contacts_researched | CN1: gate_result | CO1: gate_reason | CP1: org_type | CQ1: b_id | CR1: website | CS1: industry | CT1: employee_count | CU1: employee_count_second | CV1: headcount_band | CW1: headcount_scope | CX1: headcount_check | CY1: headcount_source_url | CZ1: headcount_second_source_url | DA1: size_class | DB1: hq_city | DC1: hq_in_nyc | DD1: parent_company | DE1: linkedin_company_url | DF1: zip | DG1: lat | DH1: lon | DI1: in_boundary | DJ1: blocks_outside | DK1: building_id | DL1: building_name | DM1: address_source_url | DN1: address_source_date | DO1: address_source_type | DP1: second_source_url | DQ1: second_source_date | DR1: source_note | DS1: confidence | DT1: move_in_date | DU1: in_coworking | DV1: coworking_id | DW1: pantry_control | DX1: lobby_type | DY1: lobby_source_url | DZ1: lobby_note | EA1: coi_required | EB1: tuesday_named_in_policy | EC1: attendance_evidence | ED1: attendance_source_url | EE1: attendance_source_date | EF1: onsite_central | EG1: onsite_flags | EH1: onsite_space_check | EI1: onsite_basis | EJ1: onsite_label | EK1: onsite_fit_share | EL1: score_raw | EM1: score_onsite | EN1: score_size | EO1: score_attendance | EP1: score_address | EQ1: score_title | ER1: score_known | ES1: b_candidate_status | ET1: near_miss_class | EU1: nyc_office_may_fit | EV1: leased_sf_mentioned | EW1: leased_sf_source | EX1: b_notes | EY1: a_corrections | EZ1: linkedin_company_source | FA1: company_group_reason | FB1: sequence | FC1: touch_1_date | FD1: touch_2_date | FE1: touch_3_date | FF1: last_reply_date | FG1: reply_type | FH1: call_date | FI1: call_notes | FJ1: yes_in_principle | FK1: next_action | FL1: next_action_date | FM1: referral_from | FN1: street_short | FO1: why_now_hook | FP1: call_note_hook | FQ1: how_we_know | FR1: referrer_ok_to_name | FS1: in_flight | FT1: dnc_any | FU1: group_key | FV1: group_blocked | FW1: eligible | FX1: view_pick | FY1: in_daily_view | FZ1: view_slot | GA1: walk_ok | GB1: walk_slot | GC1: intact | GD1: row_order
A2: AO-C-009 | B2: Alpine Investors | C2: https://www.alpineinvestors.com | D2: alpineinvestors.com | E2: 1 | F2: 80.0 | G2: Y | H2: Jake | I2: Jones | J2: Office Coordinator, New York office | L2: pantry or office lead (primary) | M2: verified-page | N2: employer's own site | O2: https://alpineinvestors.com/group/alpine-management/page/4/ | P2: 2026-10-24 | Q2: Katira | R2: Getzen | S2: Office Coordinator, New York City office | U2: pantry or office lead (backup) | V2: verified-page | W2: employer's own site | X2: https://alpineinvestors.com/group/alpine-management/page/4/ | Y2: 2026-10-24 | Z2: Katira Getzen | AA2: 2025-03-11 | AB2: title_match=target; Alpine team page bio: "Katira is an Office Coordinator at Alpine's New York City office"; bio posted 2025-03-11. Darween Edouard (Executive Assistant, New York office, alpine-management/page/6, 2024-02-05) is a third option. A search snippet named a Harry Garcia as NYC Office Manager and EA (2023) but he is not on the current team page, so not recorded. | AC2: confirmed | AE2: 124 East 14th Street | AF2: 12 | AG2: private equity | AH2: 203 | AI2: https://www.linkedin.com/company/alpine-investors | AJ2: Y | AK2: 76-150 | AL2: Y | AM2: 136 | AN2: low | AO2: in-office-5 | AP2: AO-C-009 | AQ2: N | AT2: =IF($A2="","",IF(AND(CN2="pass",AQ2<>"Y",C2<>"",OR(AX2<>"Y",AV2="Y")),"Y","N")) -> Y | AU2: =IF($A2="","",_xlfn.TEXTJOIN("; ",TRUE(),IF(CN2<>"pass","gated out",""),IF(AQ2="Y","on hold: "&AR2,""),IF(C2="","no contact named on an opened page",""),IF(AND(AX2="Y",AV2<>"Y"),"Tuesday estimate band "&L2&": founder's call",""))) | AX2: N | AY2: Jake | AZ2: Jones | BA2: Office Coordinator, New York office | BC2: =IF($A2="","",IFERROR(INDEX(Enrichment!$A$2:$GZ$2000,MATCH($A2,INDEX(Enrichment!$A$2:$GZ$2000,0,MATCH("row_id",Enrichment!$A$1:$GZ$1,0)),0),MATCH("work_email",Enrichment!$A$1:$GZ$1,0))&"","")) | BD2: =IF($A2="","",IF(BC2="","none",IF(OR(IFERROR(INDEX(Enrichment!$A$2:$GZ$2000,MATCH($A2,INDEX(Enrichment!$A$2:$GZ$2000,0,MATCH("row_id",Enrichment!$A$1:$GZ$1,0)),0),MATCH("email_status",Enrichment!$A$1:$GZ$1,0))&"","")="verified",IFERROR(INDEX(Enrichment!$A$2:$GZ$2000,MATCH($A2,INDEX(Enrichment!$A$2:$GZ$2000,0,MATCH("row_id",Enrichment!$A$1:$GZ$1,0)),0),MATCH("email_status",Enrichment!$A$1:$GZ$1,0))&"","")="unverified"),IFERROR(INDEX(Enrichment!$A$2:$GZ$2000,MATCH($A2,INDEX(Enrichment!$A$2:$GZ$2000,0,MATCH("row_id",Enrichment!$A$1:$GZ$1,0)),0),MATCH("email_status",Enrichment!$A$1:$GZ$1,0))&"",""),"unverified"))) -> none | BE2: pantry or office lead (primary) | BF2: verified-page | BG2: employer's own site | BH2: https://alpineinvestors.com/group/alpine-management/page/4/ | BI2: 2026-10-24 | BJ2: exact | BK2: find Jake Jones at Alpine Investors on LinkedIn and paste the profile URL into primary_linkedin_url; the source is dated 2025-09-15: check Jake still holds the role | BL2: contact in the target titles named (Office Coordinator, New York office) | BM2: Katira | BN2: Getzen | BO2: Office Coordinator, New York City office | BQ2: =IF($A2="","",IFERROR(INDEX(Enrichment!$A$2:$GZ$2000,MATCH($A2,INDEX(Enrichment!$A$2:$GZ$2000,0,MATCH("row_id",Enrichment!$A$1:$GZ$1,0)),0),MATCH("backup_work_email",Enrichment!$A$1:$GZ$1,0))&"","")) | BR2: =IF($A2="","",IF(BQ2="","none",IF(OR(IFERROR(INDEX(Enrichment!$A$2:$GZ$2000,MATCH($A2,INDEX(Enrichment!$A$2:$GZ$2000,0,MATCH("row_id",Enrichment!$A$1:$GZ$1,0)),0),MATCH("backup_email_status",Enrichment!$A$1:$GZ$1,0))&"","")="verified",IFERROR(INDEX(Enrichment!$A$2:$GZ$2000,MATCH($A2,INDEX(Enrichment!$A$2:$GZ$2000,0,MATCH("row_id",Enrichment!$A$1:$GZ$1,0)),0),MATCH("backup_email_status",Enrichment!$A$1:$GZ$1,0))&"","")="unverified"),IFERROR(INDEX(Enrichment!$A$2:$GZ$2000,MATCH($A2,INDEX(Enrichment!$A$2:$GZ$2000,0,MATCH("row_id",Enrichment!$A$1:$GZ$1,0)),0),MATCH("backup_email_status",Enrichment!$A$1:$GZ$1,0))&"",""),"unverified"))) -> none | BS2: pantry or office lead (backup) | BT2: verified-page | BU2: employer's own site | BV2: https://alpineinvestors.com/group/alpine-management/page/4/ | BW2: 2026-10-24 | BX2: exact | BY2: find Katira Getzen at Alpine Investors on LinkedIn and paste the profile URL into backup_linkedin_url; the source is dated 2025-03-11: check Katira still holds the role | BZ2: contact in the target titles named (Office Coordinator, New York City office) | CA2: Tuesday estimate 88 to 136 (low confidence), under 500 staff company-wide, on-site 5 days a week per its profile, occupied at a high-confidence address | CB2: linkedin | CC2: Jake Jones | CD2: 2025-09-15 | CE2: title_match=target; Alpine team page bio: "Jake is an Office Coordinator at Alpine’s New York office"; bio posted 2025-09-15; also listed under Finance & Operations on alpineinvestors.com/team/. LinkedIn profile not searched. | CF2: confirmed | CH2: Katira Getzen | CI2: 2025-03-11 | CJ2: title_match=target; Alpine team page bio: "Katira is an Office Coordinator at Alpine's New York City office"; bio posted 2025-03-11. Darween Edouard (Executive Assistant, New York office, alpine-management/page/6, 2024-02-05) is a third option. A search snippet named a Harry Garcia as NYC Office Manager and EA (2023) but he is not on the current team page, so not recorded. | CK2: confirmed | CM2: Y | CN2: pass | CO2: passes all hard gates | CP2: company | CQ2: B-C-009 | CR2: https://www.alpineinvestors.com | CS2: private equity | CT2: 203 | CV2: 151-250 | CW2: whole-company | CX2: single-source | CY2: https://www.builtinnyc.com/company/alpine-investors | DA2: le500 | DB2: San Francisco | DC2: N | DD2: unknown | DE2: https://www.linkedin.com/company/alpine-investors | DF2: 10003 | DG2: 40.733674 | DH2: -73.988766 | DI2: Y | DJ2: 0 | DK2: B-B-002 | DL2: Zero Irving | DM2: https://www.alpineinvestors.com/contact/ | DN2: 2026-10-24 | DO2: company-site | DP2: https://commercialobserver.com/2022/11/alpine-investors-lease-zero-irving/ | DQ2: 2022-11-17 | DS2: high | DU2: N | DX2: unknown | EA2: unknown | EB2: N | EC2: Built In workplace type: OnSite Workplace; typical time on-site: 5 days a week | ED2: https://www.builtinnyc.com/company/alpine-investors/offices | EE2: 2026-10-24 | EF2: 109 | EH2: Y | EI2: 203 (Built In) staff (whole-company count) x 5% to 100% of them in the New York office (HQ outside New York; share assumed) x 67% (Partnership for NYC, firms under 500) in on a weekday; space-based for a company headquartered outside New York: 22,000 sf seats 88 to 176 at 250 to 125 sf per person, kept within the headcount math (7 to 136) (largest square footage the sources mention at this address; if the company holds more space here, intake corrects it) = 88 to 136, central 109; low confidence; estimate until intake replaces it. | EJ2: estimate until intake replaces it | EK2: 1 | EL2: 80 | EM2: 25 | EN2: 15 | EO2: 15 | EP2: 15 | EQ2: =IF($A2="","",IF(AH2="exact",10,IF(AH2="adjacent",5,0))) -> 0 | ER2: =IF($A2="","",IF(R2="Y",15,0)) -> 0 | ES2: candidate | EV2: 22,000 sf | EW2: B's sources | EX2: Site: 'NEW YORK Zero Irving, 124 East 14th St., 12th Floor New York, NY 10003'. CO 2022-11-17: five-year lease, 22,000 sf on the entire 12th floor and part of the 14th. Zero Irving is on the south side of 14th between Irving Pl and Third Ave (same tax block as Trader Joe's 142 E 14th), so margin. Built In NYC: 203 total employees, HQ San Francisco; NYC share unknown. | EZ2: linked from the company's own site (https://alpineinvestors.com/, opened 2026-10-24); LinkedIn not opened | FS2: =IF($A2="","",IF(ISNUMBER(MATCH(U2,{"queued","contacted","replied","call_booked","call_done","yes_in_principle","materials_sent"},0)),"Y","N")) -> N | FT2: =IF($A2="","",IF(OR(T2="Y",U2="do_not_contact",AS2&""<>""),"Y","N")) -> N | FU2: =IF($A2="","",IF(AP2&""<>"",AP2&"",$A2)) -> AO-C-009 | FV2: =IF($A2="","",IF(COUNTIFS($FU$2:$FU$1000,FU2,$FS$2:$FS$1000,"Y")+COUNTIFS($FU$2:$FU$1000,FU2,$FT$2:$FT$1000,"Y")>0,"Y","N")) -> N | FW2: =IF($A2="","",IF(AND(U2="new",T2="N",FT2="N",AT2="Y",FV2="N"),"Y","N")) -> N | FX2: =IF($A2="","",IF(FW2<>"Y","N",IF(COUNTIFS($FU$2:$FU$1000,FU2,$FW$2:$FW$1000,"Y",$J$2:$J$1000,">"&J2)+COUNTIFS($FU$2:$FU$1000,FU2,$FW$2:$FW$1000,"Y",$J$2:$J$1000,J2,$GD$2:$GD$1000,"<"&GD2)=0,"Y","N"))) -> N | FY2: =IF($A2="","",IF(AND(FW2="Y",FX2="Y",Y2&""<>""),IF(Y2<=10,"Y","N"),"N")) -> N | FZ2: =IF(FY2="Y",Y2,"") | GA2: =IF($A2="","",IF(AND(I2="walk-in",CN2="pass",U2="new",FT2="N",FV2="N",AQ2<>"Y"),"Y","N")) -> N | GB2: =IF(GA2<>"Y","",IF(COUNTIFS($GA$2:$GA$1000,"Y",$J$2:$J$1000,">"&J2)+COUNTIFS($GA$2:$GA$1000,"Y",$J$2:$J$1000,J2,$GD$2:$GD$1000,"<"&GD2)+1<=25,COUNTIFS($GA$2:$GA$1000,"Y",$J$2:$J$1000,">"&J2)+COUNTIFS($GA$2:$GA$1000,"Y",$J$2:$J$1000,J2,$GD$2:$GD$1000,"<"&GD2)+1,"")) | GC2: =IF(AND(_xlfn.ISFORMULA(C2),_xlfn.ISFORMULA(J2)),"Y","N") -> N | GD2: =ROW()-1 -> 1
A3: AO-C-035 | B3: Global Strategy Group | C3: https://www.globalstrategygroup.com | D3: globalstrategygroup.com | E3: 2 | F3: 80.0 | G3: Y | H3: Joan | I3: McHugh-Ward | J3: Manager, HQ-Office Services | L3: pantry or office lead (primary) | M3: verified-page | N3: employer's own site | O3: https://globalstrategygroup.com/team/ | P3: 2026-10-24 | Q3: Liana | R3: Kane | S3: Senior Executive Assistant to the CEO | T3: https://www.linkedin.com/in/liana-kane-ba771b29/ | U3: pantry or office lead (backup) | V3: verified-page | W3: employer's own site | X3: https://globalstrategygroup.com/team/liana-kane/ | Y3: 2026-10-24 | Z3: Liana Kane | AA3: 2026-09-07 | AB3: ny_base=confirmed; title_fit=family (EA to CEO). Company profile page gives the title and links this LinkedIn profile (LinkedIn not opened). The Org (https://theorg.com/org/global-strategy-group/person/liana-kane, updated 2026-09-07) attaches her to the New York HQ office. Bio lists office organization among her duties. | AC3: confirmed | AD3: listed on an opened page or in search results; LinkedIn itself not opened | AE3: 215 Park Avenue South | AF3: 15 | AG3: public affairs, research and communications consulting | AH3: 187 | AI3: https://www.linkedin.com/company/global-strategy-group | AJ3: Y | AK3: 76-150 | AL3: Y | AM3: 125 | AN3: low | AO3: in-office-5 | AP3: AO-C-035 | AQ3: N | AT3: =IF($A3="","",IF(AND(CN3="pass",AQ3<>"Y",C3<>"",OR(AX3<>"Y",AV3="Y")),"Y","N")) -> Y | AU3: =IF($A3="","",_xlfn.TEXTJOIN("; ",TRUE(),IF(CN3<>"pass","gated out",""),IF(AQ3="Y","on hold: "&AR3,""),IF(C3="","no contact named on an opened page",""),IF(AND(AX3="Y",AV3<>"Y"),"Tuesday estimate band "&L3&": founder's call",""))) | AX3: N | AY3: Joan | AZ3: McHugh-Ward | BA3: Manager, HQ-Office Services | BC3: =IF($A3="","",IFERROR(INDEX(Enrichment!$A$2:$GZ$2000,MATCH($A3,INDEX(Enrichment!$A$2:$GZ$2000,0,MATCH("row_id",Enrichment!$A$1:$GZ$1,0)),0),MATCH("work_email",Enrichment!$A$1:$GZ$1,0))&"","")) | BD3: =IF($A3="","",IF(BC3="","none",IF(OR(IFERROR(INDEX(Enrichment!$A$2:$GZ$2000,MATCH($A3,INDEX(Enrichment!$A$2:$GZ$2000,0,MATCH("row_id",Enrichment!$A$1:$GZ$1,0)),0),MATCH("email_status",Enrichment!$A$1:$GZ$1,0))&"","")="verified",IFERROR(INDEX(Enrichment!$A$2:$GZ$2000,MATCH($A3,INDEX(Enrichment!$A$2:$GZ$2000,0,MATCH("row_id",Enrichment!$A$1:$GZ$1,0)),0),MATCH("email_status",Enrichment!$A$1:$GZ$1,0))&"","")="unverified"),IFERROR(INDEX(Enrichment!$A$2:$GZ$2000,MATCH($A3,INDEX(Enrichment!$A$2:$GZ$2000,0,MATCH("row_id",Enrichment!$A$1:$GZ$1,0)),0),MATCH("email_status",Enrichment!$A$1:$GZ$1,0))&"",""),"unverified"))) -> none | BE3: pantry or office lead (primary) | BF3: verified-page | BG3: employer's own site | BH3: https://globalstrategygroup.com/team/ | BI3: 2026-10-24 | BJ3: exact | BK3: find Joan McHugh-Ward at Global Strategy Group on LinkedIn and paste the profile URL into primary_linkedin_url | BL3: contact in the target titles named (Manager, HQ-Office Services) | BM3: Liana | BN3: Kane | BO3: Senior Executive Assistant to the CEO | BP3: https://www.linkedin.com/in/liana-kane-ba771b29/ | BQ3: =IF($A3="","",IFERROR(INDEX(Enrichment!$A$2:$GZ$2000,MATCH($A3,INDEX(Enrichment!$A$2:$GZ$2000,0,MATCH("row_id",Enrichment!$A$1:$GZ$1,0)),0),MATCH("backup_work_email",Enrichment!$A$1:$GZ$1,0))&"","")) | BR3: =IF($A3="","",IF(BQ3="","none",IF(OR(IFERROR(INDEX(Enrichment!$A$2:$GZ$2000,MATCH($A3,INDEX(Enrichment!$A$2:$GZ$2000,0,MATCH("row_id",Enrichment!$A$1:$GZ$1,0)),0),MATCH("backup_email_status",Enrichment!$A$1:$GZ$1,0))&"","")="verified",IFERROR(INDEX(Enrichment!$A$2:$GZ$2000,MATCH($A3,INDEX(Enrichment!$A$2:$GZ$2000,0,MATCH("row_id",Enrichment!$A$1:$GZ$1,0)),0),MATCH("backup_email_status",Enrichment!$A$1:$GZ$1,0))&"","")="unverified"),IFERROR(INDEX(Enrichment!$A$2:$GZ$2000,MATCH($A3,INDEX(Enrichment!$A$2:$GZ$2000,0,MATCH("row_id",Enrichment!$A$1:$GZ$1,0)),0),MATCH("backup_email_status",Enrichment!$A$1:$GZ$1,0))&"",""),"unverified"))) -> none | BS3: pantry or office lead (backup) | BT3: verified-page | BU3: employer's own site | BV3: https://globalstrategygroup.com/team/liana-kane/ | BW3: 2026-10-24 | BX3: exact | BY3: open the LinkedIn URL and confirm it is Liana Kane, Senior Executive Assistant to the CEO at Global Strategy Group (found on another page, never opened) | BZ3: contact in the target titles named (Senior Executive Assistant to the CEO) | CA3: Tuesday estimate 63 to 125 (low confidence), under 500 staff company-wide, on-site 5 days a week per its profile, occupied at a high-confidence address | CB3: linkedin | CC3: Joan McHugh-Ward | CE3: ny_base=confirmed; title_fit=family (office services manager). Company team page lists 'Manager, HQ-Office Services'; her profile page https://globalstrategygroup.com/team/joan-mchugh/ is titled 'HQ Office Services'. GSG HQ is New York (215 Park Avenue South). No LinkedIn URL on the company page. | CF3: confirmed | CH3: Liana Kane | CI3: 2026-09-07 | CJ3: ny_base=confirmed; title_fit=family (EA to CEO). Company profile page gives the title and links this LinkedIn profile (LinkedIn not opened). The Org (https://theorg.com/org/global-strategy-group/person/liana-kane, updated 2026-09-07) attaches her to the New York HQ office. Bio lists office organization among her duties. | CK3: confirmed | CL3: listed on an opened page or in search results; LinkedIn itself not opened | CM3: Y | CN3: pass | CO3: passes all hard gates | CP3: company | CQ3: B-C-035 | CR3: https://www.globalstrategygroup.com | CS3: public affairs, research and communications consulting | CT3: 187 | CV3: 151-250 | CW3: whole-company | CX3: single-source | CY3: https://www.builtinnyc.com/company/global-strategy-group | DA3: le500 | DB3: New York | DC3: Y | DD3: unknown | DE3: https://www.linkedin.com/company/global-strategy-group | DF3: 10003 | DG3: 40.73686 | DH3: -73.988546 | DI3: Y | DJ3: 0 | DK3: B-B-016 | DL3: 215 Park Avenue South (SL Green managed) | DM3: https://www.globalstrategygroup.com/locations/ | DN3: 2026-10-23 | DO3: company-site | DP3: https://www.sec.gov/Archives/edgar/data/1013454/000153949726000704/n5676_x5-424h.htm | DQ3: 2026-02 | DR3: cites a sec.gov filing: agents do not open it (EDGAR demands a contact email); the founder may open it in a browser | DS3: high | DU3: N | DX3: security desk | DY3: https://www.metro-manhattan.com/buildings/215-park-avenue-south/ | EA3: unknown | EB3: N | EC3: Built In workplace type: OnSite Workplace; typical time on-site: 5 days a week; recent job tags: 1 Hybrid | ED3: https://www.builtinnyc.com/company/global-strategy-group/offices | EE3: 2026-10-24 | EF3: 89 | EH3: N | EI3: 187 (Built In) staff (whole-company count) x 50% to 100% of them in the New York office (HQ New York; share assumed) x 67% (Partnership for NYC, firms under 500) in on a weekday = 63 to 125, central 89; low confidence; estimate until intake replaces it. | EJ3: estimate until intake replaces it | EK3: 1 | EL3: 80 | EM3: 25 | EN3: 15 | EO3: 15 | EP3: 15 | EQ3: =IF($A3="","",IF(AH3="exact",10,IF(AH3="adjacent",5,0))) -> 0 | ER3: =IF($A3="","",IF(R3="Y",15,0)) -> 0 | ES3: candidate | EV3: 21,974 sf | EW3: B's sources | EX3: Locations page: '215 Park Avenue South, 15th Floor'. SEC rent roll 2026-02-05: 21,974 sf, lease to 2032-08-31. Built In NYC: 187 total employees across 8 offices, HQ New York. | Assembly 2026-10-24: SEC EDGAR source (sec.gov): this agent will not re-open it, because EDGAR serves only requests that carry a contact email and the project rule forbids sending one; the founder may open it in a browser. Review round 2: corner lot: the lot-centroid pin sat 20 m from E 18 ST but 39 m from PARK AVE S, so it was moved to the PARK AVE S frontage near the corner (14 m from the PARK AVE S centreline, 26 m from E 18 ST; 26 m from the old pin). Tax lot unchanged. | EZ3: linked from the company's own site (https://globalstrategygroup.com/, opened 2026-10-24); LinkedIn not opened | FS3: =IF($A3="","",IF(ISNUMBER(MATCH(U3,{"queued","contacted","replied","call_booked","call_done","yes_in_principle","materials_sent"},0)),"Y","N")) -> N | FT3: =IF($A3="","",IF(OR(T3="Y",U3="do_not_contact",AS3&""<>""),"Y","N")) -> N | FU3: =IF($A3="","",IF(AP3&""<>"",AP3&"",$A3)) -> AO-C-035 | FV3: =IF($A3="","",IF(COUNTIFS($FU$2:$FU$1000,FU3,$FS$2:$FS$1000,"Y")+COUNTIFS($FU$2:$FU$1000,FU3,$FT$2:$FT$1000,"Y")>0,"Y","N")) -> N | FW3: =IF($A3="","",IF(AND(U3="new",T3="N",FT3="N",AT3="Y",FV3="N"),"Y","N")) -> N | FX3: =IF($A3="","",IF(FW3<>"Y","N",IF(COUNTIFS($FU$2:$FU$1000,FU3,$FW$2:$FW$1000,"Y",$J$2:$J$1000,">"&J3)+COUNTIFS($FU$2:$FU$1000,FU3,$FW$2:$FW$1000,"Y",$J$2:$J$1000,J3,$GD$2:$GD$1000,"<"&GD3)=0,"Y","N"))) -> N | FY3: =IF($A3="","",IF(AND(FW3="Y",FX3="Y",Y3&""<>""),IF(Y3<=10,"Y","N"),"N")) -> N | FZ3: =IF(FY3="Y",Y3,"") | GA3: =IF($A3="","",IF(AND(I3="walk-in",CN3="pass",U3="new",FT3="N",FV3="N",AQ3<>"Y"),"Y","N")) -> N | GB3: =IF(GA3<>"Y","",IF(COUNTIFS($GA$2:$GA$1000,"Y",$J$2:$J$1000,">"&J3)+COUNTIFS($GA$2:$GA$1000,"Y",$J$2:$J$1000,J3,$GD$2:$GD$1000,"<"&GD3)+1<=25,COUNTIFS($GA$2:$GA$1000,"Y",$J$2:$J$1000,">"&J3)+COUNTIFS($GA$2:$GA$1000,"Y",$J$2:$J$1000,J3,$GD$2:$GD$1000,"<"&GD3)+1,"")) | GC3: =IF(AND(_xlfn.ISFORMULA(C3),_xlfn.ISFORMULA(J3)),"Y","N") -> N | GD3: =ROW()-1 -> 2
A4: AO-C-171 | B4: Signal AI | C4: https://www.signal-ai.com | D4: signal-ai.com | E4: 3 | F4: 80.0 | G4: Y | H4: Hannah | I4: Grow | J4: Senior People Operations Coordinator | L4: pantry or office lead (primary) | M4: crowd-listed | N4: The Org (crowd-edited org chart) | O4: https://theorg.com/org/signal-ai/person/hannah-grow | P4: 2026-10-24 | Q4: Lauren | R4: Stone | S4: Head Of People | U4: pantry or office lead (backup) | V4: crowd-listed | W4: The Org (crowd-edited org chart) | X4: https://theorg.com/org/signal-ai/person/lauren-stone | Y4: 2026-10-24 | Z4: Lauren Stone | AA4: 2025-05-01 | AB4: ny_base=confirmed (same New York office record); title_fit=variant (people lead). The Org updated 2025-05-01. | AC4: confirmed | AE4: 440 Park Avenue South | AF4: 14 | AG4: software (AI risk and reputation intelligence) | AH4: 226 | AI4: https://www.linkedin.com/company/signal-artificial-intelligence | AJ4: Y | AK4: 40-75 | AL4: Y | AM4: 89 | AN4: low | AO4: in-office-5 | AP4: AO-C-171 | AQ4: N | AT4: =IF($A4="","",IF(AND(CN4="pass",AQ4<>"Y",C4<>"",OR(AX4<>"Y",AV4="Y")),"Y","N")) -> Y | AU4: =IF($A4="","",_xlfn.TEXTJOIN("; ",TRUE(),IF(CN4<>"pass","gated out",""),IF(AQ4="Y","on hold: "&AR4,""),IF(C4="","no contact named on an opened page",""),IF(AND(AX4="Y",AV4<>"Y"),"Tuesday estimate band "&L4&": founder's call",""))) | AX4: N | AY4: Hannah | AZ4: Grow | BA4: Senior People Operations Coordinator | BC4: =IF($A4="","",IFERROR(INDEX(Enrichment!$A$2:$GZ$2000,MATCH($A4,INDEX(Enrichment!$A$2:$GZ$2000,0,MATCH("row_id",Enrichment!$A$1:$GZ$1,0)),0),MATCH("work_email",Enrichment!$A$1:$GZ$1,0))&"","")) | BD4: =IF($A4="","",IF(BC4="","none",IF(OR(IFERROR(INDEX(Enrichment!$A$2:$GZ$2000,MATCH($A4,INDEX(Enrichment!$A$2:$GZ$2000,0,MATCH("row_id",Enrichment!$A$1:$GZ$1,0)),0),MATCH("email_status",Enrichment!$A$1:$GZ$1,0))&"","")="verified",IFERROR(INDEX(Enrichment!$A$2:$GZ$2000,MATCH($A4,INDEX(Enrichment!$A$2:$GZ$2000,0,MATCH("row_id",Enrichment!$A$1:$GZ$1,0)),0),MATCH("email_status",Enrichment!$A$1:$GZ$1,0))&"","")="unverified"),IFERROR(INDEX(Enrichment!$A$2:$GZ$2000,MATCH($A4,INDEX(Enrichment!$A$2:$GZ$2000,0,MATCH("row_id",Enrichment!$A$1:$GZ$1,0)),0),MATCH("email_status",Enrichment!$A$1:$GZ$1,0))&"",""),"unverified"))) -> none | BE4: pantry or office lead (primary) | BF4: crowd-listed | BG4: The Org (crowd-edited org chart) | BH4: https://theorg.com/org/signal-ai/person/hannah-grow | BI4: 2026-10-24 | BJ4: exact | BK4: find Hannah Grow at Signal AI on LinkedIn and paste the profile URL into primary_linkedin_url (this also confirms the name: The Org is crowd-edited and marks it Unverified) | BL4: contact in the target titles named (Senior People Operations Coordinator) (crowd-listed on The Org) | BM4: Lauren | BN4: Stone | BO4: Head Of People | BQ4: =IF($A4="","",IFERROR(INDEX(Enrichment!$A$2:$GZ$2000,MATCH($A4,INDEX(Enrichment!$A$2:$GZ$2000,0,MATCH("row_id",Enrichment!$A$1:$GZ$1,0)),0),MATCH("backup_work_email",Enrichment!$A$1:$GZ$1,0))&"","")) | BR4: =IF($A4="","",IF(BQ4="","none",IF(OR(IFERROR(INDEX(Enrichment!$A$2:$GZ$2000,MATCH($A4,INDEX(Enrichment!$A$2:$GZ$2000,0,MATCH("row_id",Enrichment!$A$1:$GZ$1,0)),0),MATCH("backup_email_status",Enrichment!$A$1:$GZ$1,0))&"","")="verified",IFERROR(INDEX(Enrichment!$A$2:$GZ$2000,MATCH($A4,INDEX(Enrichment!$A$2:$GZ$2000,0,MATCH("row_id",Enrichment!$A$1:$GZ$1,0)),0),MATCH("backup_email_status",Enrichment!$A$1:$GZ$1,0))&"","")="unverified"),IFERROR(INDEX(Enrichment!$A$2:$GZ$2000,MATCH($A4,INDEX(Enrichment!$A$2:$GZ$2000,0,MATCH("row_id",Enrichment!$A$1:$GZ$1,0)),0),MATCH("backup_email_status",Enrichment!$A$1:$GZ$1,0))&"",""),"unverified"))) -> none | BS4: pantry or office lead (backup) | BT4: crowd-listed | BU4: The Org (crowd-edited org chart) | BV4: https://theorg.com/org/signal-ai/person/lauren-stone | BW4: 2026-10-24 | BX4: adjacent | BY4: find Lauren Stone at Signal AI on LinkedIn and paste the profile URL into backup_linkedin_url (this also confirms the name: The Org is crowd-edited and marks it Unverified); the source is dated 2025-05-01: check Lauren still holds the role; adjacent title: ask who runs the pantry | BZ4: adjacent contact named (Head Of People) (crowd-listed on The Org) | CA4: Tuesday estimate 45 to 89 (low confidence), under 500 staff company-wide, on-site 5 days a week per its profile, occupied at a high-confidence address | CB4: linkedin | CC4: Hannah Grow | CD4: 2026-02-09 | CE4: ny_base=confirmed (The Org attaches the role to Signal AI's New York office; that record shows 154 W 14th St while B's company-site address is 440 Park Avenue South); title_fit=family (people operations). The Org updated 2026-02-09. | CF4: confirmed | CH4: Lauren Stone | CI4: 2025-05-01 | CJ4: ny_base=confirmed (same New York office record); title_fit=variant (people lead). The Org updated 2025-05-01. | CK4: confirmed | CM4: Y | CN4: pass | CO4: passes all hard gates | CP4: company | CQ4: B-C-171 | CR4: https://www.signal-ai.com | CS4: software (AI risk and reputation intelligence) | CT4: 226 | CV4: 151-250 | CW4: whole-company | CX4: single-source | CY4: https://www.builtinnyc.com/company/signal-ai/offices | DA4: le500 | DB4: London | DC4: N | DD4: unknown | DE4: https://www.linkedin.com/company/signal-artificial-intelligence | DF4: 10016 | DG4: 40.744442 | DH4: -73.983525 | DI4: Y | DJ4: 0 | DK4: B-B-080 | DL4: 440 Park Avenue South (Samco Properties) | DM4: https://www.signal-ai.com/ | DN4: 2026-10-24 | DO4: company-site | DP4: https://commercialobserver.com/2022/12/signal-ai-doubles-offices-in-move-to-440-park-avenue-south/ | DQ4: 2022-12-19 | DS4: high | DU4: N | DX4: unknown | EA4: unknown | EB4: N | EC4: Built In workplace type: OnSite Workplace; typical time on-site: 5 days a week | ED4: https://www.builtinnyc.com/company/signal-ai/offices | EE4: 2026-10-24 | EF4: 63 | EH4: Y | EI4: 226 (Built In) staff (whole-company count) x 5% to 100% of them in the New York office (HQ outside New York; share assumed) x 67% (Partnership for NYC, firms under 500) in on a weekday; space-based for a company headquartered outside New York: 11,140 sf seats 45 to 89 at 250 to 125 sf per person, kept within the headcount math (8 to 151) (largest square footage the sources mention at this address; if the company holds more space here, intake corrects it) = 45 to 89, central 63; low confidence; estimate until intake replaces it. | EJ4: estimate until intake replaces it | EK4: 1 | EL4: 80 | EM4: 25 | EN4: 15 | EO4: 15 | EP4: 15 | EQ4: =IF($A4="","",IF(AH4="exact",10,IF(AH4="adjacent",5,0))) -> 0 | ER4: =IF($A4="","",IF(R4="Y",15,0)) -> 0 | ES4: candidate | EV4: 11,140 sf | EW4: B's sources | EX4: Built In lists New York office at 440 Park Avenue South, 14th Floor; 226 total employees (HQ London). CO 2022: 11,140 SF US HQ. | Assembly 2026-10-24: Review round 1: Signal AI's own site footer (opened 2026-10-24) lists 'United States 440 Park Avenue South, 14th floor, New York NY 10016' beside its London office, so the row stays high on its own page plus Built In. Review round 3: Built In is an employer-editable profile, so it no longer counts as the independent confirmation of the company's own page. The independent source is now CO 2022-12-19 (opened 2026-10-24): 'signed a lease for space at Samco Properties at 440 Park Avenue South' (11,140 sf; lease length not disclosed). The row stays high. Review round 2: corner lot: the lot-centroid pin sat 23 m from E 30 ST but 24 m from PARK AVE S, so it was moved to the PARK AVE S frontage near the corner (13 m from the PARK AVE S centreline, 27 m from E 30 ST; 12 m from the old pin). Tax lot unchanged. | EZ4: linked from the company's own site (https://signal-ai.com/, opened 2026-10-24); LinkedIn not opened | FS4: =IF($A4="","",IF(ISNUMBER(MATCH(U4,{"queued","contacted","replied","call_booked","call_done","yes_in_principle","materials_sent"},0)),"Y","N")) -> N | FT4: =IF($A4="","",IF(OR(T4="Y",U4="do_not_contact",AS4&""<>""),"Y","N")) -> N | FU4: =IF($A4="","",IF(AP4&""<>"",AP4&"",$A4)) -> AO-C-171 | FV4: =IF($A4="","",IF(COUNTIFS($FU$2:$FU$1000,FU4,$FS$2:$FS$1000,"Y")+COUNTIFS($FU$2:$FU$1000,FU4,$FT$2:$FT$1000,"Y")>0,"Y","N")) -> N | FW4: =IF($A4="","",IF(AND(U4="new",T4="N",FT4="N",AT4="Y",FV4="N"),"Y","N")) -> N | FX4: =IF($A4="","",IF(FW4<>"Y","N",IF(COUNTIFS($FU$2:$FU$1000,FU4,$FW$2:$FW$1000,"Y",$J$2:$J$1000,">"&J4)+COUNTIFS($FU$2:$FU$1000,FU4,$FW$2:$FW$1000,"Y",$J$2:$J$1000,J4,$GD$2:$GD$1000,"<"&GD4)=0,"Y","N"))) -> N | FY4: =IF($A4="","",IF(AND(FW4="Y",FX4="Y",Y4&""<>""),IF(Y4<=10,"Y","N"),"N")) -> N | FZ4: =IF(FY4="Y",Y4,"") | GA4: =IF($A4="","",IF(AND(I4="walk-in",CN4="pass",U4="new",FT4="N",FV4="N",AQ4<>"Y"),"Y","N")) -> N | GB4: =IF(GA4<>"Y","",IF(COUNTIFS($GA$2:$GA$1000,"Y",$J$2:$J$1000,">"&J4)+COUNTIFS($GA$2:$GA$1000,"Y",$J$2:$J$1000,J4,$GD$2:$GD$1000,"<"&GD4)+1<=25,COUNTIFS($GA$2:$GA$1000,"Y",$J$2:$J$1000,">"&J4)+COUNTIFS($GA$2:$GA$1000,"Y",$J$2:$J$1000,J4,$GD$2:$GD$1000,"<"&GD4)+1,"")) | GC4: =IF(AND(_xlfn.ISFORMULA(C4),_xlfn.ISFORMULA(J4)),"Y","N") -> N | GD4: =ROW()-1 -> 3
A5: AO-C-160 | B5: K Health | C5: https://khealth.com | D5: khealth.com | E5: 4 | F5: 76.5 | G5: Y | H5: Naomy | I5: Ambroise | J5: People Operations Generalist | L5: pantry or office lead (primary) | M5: crowd-listed | N5: The Org (crowd-edited org chart) | O5: https://theorg.com/org/k-health/person/naomy-ambroise | P5: 2026-10-24 | Q5: Ana | R5: Ramos | S5: VP of Operations | U5: pantry or office lead (backup) | V5: crowd-listed | W5: The Org (crowd-edited org chart) | X5: https://theorg.com/org/k-health/person/ana-ramos | Y5: 2026-10-24 | Z5: Ana Ramos | AA5: 2026-01-19 | AB5: ny_base=confirmed (The Org attaches the role to K Health's New York HQ office); title_fit=adjacent (operations lead, team 'Finance and Operations'). The Org updated 2026-01-19. | AC5: confirmed | AE5: 387 Park Avenue South | AF5: 9 | AG5: healthtech (AI primary care) | AH5: 363 | AI5: https://www.linkedin.com/company/khealthinc | AJ5: Y | AK5: 151-250 | AL5: Y | AM5: 281 | AN5: low | AO5: in-office-5 | AP5: AO-C-160 | AQ5: N | AS5: 2026-10-30 | AT5: =IF($A5="","",IF(AND(CN5="pass",AQ5<>"Y",C5<>"",OR(AX5<>"Y",AV5="Y")),"Y","N")) -> Y | AU5: =IF($A5="","",_xlfn.TEXTJOIN("; ",TRUE(),IF(CN5<>"pass","gated out",""),IF(AQ5="Y","on hold: "&AR5,""),IF(C5="","no contact named on an opened page",""),IF(AND(AX5="Y",AV5<>"Y"),"Tuesday estimate band "&L5&": founder's call",""))) | AX5: N | AY5: Naomy | AZ5: Ambroise | BA5: People Operations Generalist | BC5: =IF($A5="","",IFERROR(INDEX(Enrichment!$A$2:$GZ$2000,MATCH($A5,INDEX(Enrichment!$A$2:$GZ$2000,0,MATCH("row_id",Enrichment!$A$1:$GZ$1,0)),0),MATCH("work_email",Enrichment!$A$1:$GZ$1,0))&"","")) | BD5: =IF($A5="","",IF(BC5="","none",IF(OR(IFERROR(INDEX(Enrichment!$A$2:$GZ$2000,MATCH($A5,INDEX(Enrichment!$A$2:$GZ$2000,0,MATCH("row_id",Enrichment!$A$1:$GZ$1,0)),0),MATCH("email_status",Enrichment!$A$1:$GZ$1,0))&"","")="verified",IFERROR(INDEX(Enrichment!$A$2:$GZ$2000,MATCH($A5,INDEX(Enrichment!$A$2:$GZ$2000,0,MATCH("row_id",Enrichment!$A$1:$GZ$1,0)),0),MATCH("email_status",Enrichment!$A$1:$GZ$1,0))&"","")="unverified"),IFERROR(INDEX(Enrichment!$A$2:$GZ$2000,MATCH($A5,INDEX(Enrichment!$A$2:$GZ$2000,0,MATCH("row_id",Enrichment!$A$1:$GZ$1,0)),0),MATCH("email_status",Enrichment!$A$1:$GZ$1,0))&"",""),"unverified"))) -> none | BE5: pantry or office lead (primary) | BF5: crowd-listed | BG5: The Org (crowd-edited org chart) | BH5: https://theorg.com/org/k-health/person/naomy-ambroise | BI5: 2026-10-24 | BJ5: exact | BK5: find Naomy Ambroise at K Health on LinkedIn and paste the profile URL into primary_linkedin_url (this also confirms the name: The Org is crowd-edited and marks it Unverified) | BL5: contact in the target titles named (People Operations Generalist) (crowd-listed on The Org) | BM5: Ana | BN5: Ramos | BO5: VP of Operations | BQ5: =IF($A5="","",IFERROR(INDEX(Enrichment!$A$2:$GZ$2000,MATCH($A5,INDEX(Enrichment!$A$2:$GZ$2000,0,MATCH("row_id",Enrichment!$A$1:$GZ$1,0)),0),MATCH("backup_work_email",Enrichment!$A$1:$GZ$1,0))&"","")) | BR5: =IF($A5="","",IF(BQ5="","none",IF(OR(IFERROR(INDEX(Enrichment!$A$2:$GZ$2000,MATCH($A5,INDEX(Enrichment!$A$2:$GZ$2000,0,MATCH("row_id",Enrichment!$A$1:$GZ$1,0)),0),MATCH("backup_email_status",Enrichment!$A$1:$GZ$1,0))&"","")="verified",IFERROR(INDEX(Enrichment!$A$2:$GZ$2000,MATCH($A5,INDEX(Enrichment!$A$2:$GZ$2000,0,MATCH("row_id",Enrichment!$A$1:$GZ$1,0)),0),MATCH("backup_email_status",Enrichment!$A$1:$GZ$1,0))&"","")="unverified"),IFERROR(INDEX(Enrichment!$A$2:$GZ$2000,MATCH($A5,INDEX(Enrichment!$A$2:$GZ$2000,0,MATCH("row_id",Enrichment!$A$1:$GZ$1,0)),0),MATCH("backup_email_status",Enrichment!$A$1:$GZ$1,0))&"",""),"unverified"))) -> none | BS5: pantry or office lead (backup) | BT5: crowd-listed | BU5: The Org (crowd-edited org chart) | BV5: https://theorg.com/org/k-health/person/ana-ramos | BW5: 2026-10-24 | BX5: adjacent | BY5: find Ana Ramos at K Health on LinkedIn and paste the profile URL into backup_linkedin_url (this also confirms the name: The Org is crowd-edited and marks it Unverified); adjacent title: ask who runs the pantry | BZ5: adjacent contact named (VP of Operations) (crowd-listed on The Org) | CA5: Tuesday estimate 122 to 281 (low confidence), under 500 staff company-wide, on-site 5 days a week per its profile, occupied at a high-confidence address | CB5: linkedin | CC5: Naomy Ambroise | CD5: 2026-02-14 | CE5: ny_base=likely (The Org gives a New York location, no office attached); title_fit=family (people operations). The Org updated 2026-02-14. Search results showed a temporary 'Executive Assistant and Office Manager' New York posting (2026-09-04, job boards, not opened); it no longer appears on K Health's Greenhouse board (opened 2026-10-24), so an office manager may have just joined: ask for them by name. | CF5: likely | CH5: Ana Ramos | CI5: 2026-01-19 | CJ5: ny_base=confirmed (The Org attaches the role to K Health's New York HQ office); title_fit=adjacent (operations lead, team 'Finance and Operations'). The Org updated 2026-01-19. | CK5: confirmed | CM5: Y | CN5: pass | CO5: passes all hard gates | CP5: company | CQ5: B-C-160 | CR5: https://khealth.com | CS5: healthtech (AI primary care) | CT5: 363 | CU5: 419 | CV5: 251-500 | CW5: whole-company | CX5: agree | CY5: https://www.builtinnyc.com/company/k-health/offices | CZ5: https://www.reveliolabs.com/companies/k-health/employees | DA5: le500 | DB5: New York | DC5: Y | DD5: unknown | DE5: https://www.linkedin.com/company/khealthinc | DF5: 10016 | DG5: 40.742833 | DH5: -73.984174 | DI5: Y | DJ5: 0 | DK5: B-B-073 | DL5: 387 Park Avenue South (TF Cornerstone) | DM5: https://www.connectcre.com/stories/ai-native-hanover-park-leases-full-floor-at-387-park-ave-south/ | DN5: 2026-08-14 | DO5: leasing-press | DP5: https://khealth.com/terms-of-use/ | DQ5: 2026-10-24 | DS5: high | DU5: N | DX5: unknown | EA5: unknown | EB5: N | EC5: completed a long-term renewal at 387 PAS in late 2025. CONFLICT: Built In (363 employees, on-site 5 days) lists HQ at 298 5th Ave, 7th | ED5: https://www.builtinnyc.com/company/k-health/offices | EE5: 2026-10-23 | EF5: 185 | EG5: may exceed 250 | EH5: N | EI5: 363 (Built In) and 419 (Revelio Labs) staff (whole-company count) x 50% to 100% of them in the New York office (HQ New York; share assumed) x 67% (Partnership for NYC, firms under 500) in on a weekday = 122 to 281, central 185; low confidence; estimate until intake replaces it. | EJ5: estimate until intake replaces it | EK5: 0.86 | EL5: 76.5 | EM5: 21.5 | EN5: 15 | EO5: 15 | EP5: 15 | EQ5: =IF($A5="","",IF(AH5="exact",10,IF(AH5="adjacent",5,0))) -> 0 | ER5: =IF($A5="","",IF(R5="Y",15,0)) -> 0 | ES5: candidate | EX5: Connect CRE says K Health completed a long-term renewal at 387 PAS in late 2025. CONFLICT: Built In (363 employees, on-site 5 days) lists HQ at 298 5th Ave, 7th Floor (30th-31st St, margin). Founder to confirm which office is current. | Assembly 2026-10-24: Conflict resolved at assembly: K Health's own terms of use (opened 2026-10-24) give 'Company's Legal Department, 387 Park Ave South, 9th Floor, NY, NY 10016', which agrees with the Connect CRE renewal at 387 PAS (late 2025). Built In's 298 Fifth Ave, 7th floor is stale. Upgraded to high. Review round 2: a second count agrees with the band: Revelio Labs (K Health, Inc., HQ New York City): about 419 employees worldwide as of March 2026. Review round 2: corner lot: the lot-centroid pin sat 24 m from E 27 ST but 34 m from PARK AVE S, so it was moved to the PARK AVE S frontage near the corner (13 m from the PARK AVE S centreline, 26 m from E 27 ST; 21 m from the old pin). Tax lot unchanged. | EZ5: linked from the company's own site (https://khealth.com/, opened 2026-10-24); LinkedIn not opened | FS5: =IF($A5="","",IF(ISNUMBER(MATCH(U5,{"queued","contacted","replied","call_booked","call_done","yes_in_principle","materials_sent"},0)),"Y","N")) -> N | FT5: =IF($A5="","",IF(OR(T5="Y",U5="do_not_contact",AS5&""<>""),"Y","N")) -> Y | FU5: =IF($A5="","",IF(AP5&""<>"",AP5&"",$A5)) -> AO-C-160 | FV5: =IF($A5="","",IF(COUNTIFS($FU$2:$FU$1000,FU5,$FS$2:$FS$1000,"Y")+COUNTIFS($FU$2:$FU$1000,FU5,$FT$2:$FT$1000,"Y")>0,"Y","N")) -> Y | FW5: =IF($A5="","",IF(AND(U5="new",T5="N",FT5="N",AT5="Y",FV5="N"),"Y","N")) -> N | FX5: =IF($A5="","",IF(FW5<>"Y","N",IF(COUNTIFS($FU$2:$FU$1000,FU5,$FW$2:$FW$1000,"Y",$J$2:$J$1000,">"&J5)+COUNTIFS($FU$2:$FU$1000,FU5,$FW$2:$FW$1000,"Y",$J$2:$J$1000,J5,$GD$2:$GD$1000,"<"&GD5)=0,"Y","N"))) -> N | FY5: =IF($A5="","",IF(AND(FW5="Y",FX5="Y",Y5&""<>""),IF(Y5<=10,"Y","N"),"N")) -> N | FZ5: =IF(FY5="Y",Y5,"") | GA5: =IF($A5="","",IF(AND(I5="walk-in",CN5="pass",U5="new",FT5="N",FV5="N",AQ5<>"Y"),"Y","N")) -> N | GB5: =IF(GA5<>"Y","",IF(COUNTIFS($GA$2:$GA$1000,"Y",$J$2:$J$1000,">"&J5)+COUNTIFS($GA$2:$GA$1000,"Y",$J$2:$J$1000,J5,$GD$2:$GD$1000,"<"&GD5)+1<=25,COUNTIFS($GA$2:$GA$1000,"Y",$J$2:$J$1000,">"&J5)+COUNTIFS($GA$2:$GA$1000,"Y",$J$2:$J$1000,J5,$GD$2:$GD$1000,"<"&GD5)+1,"")) | GC5: =IF(AND(_xlfn.ISFORMULA(C5),_xlfn.ISFORMULA(J5)),"Y","N") -> N | GD5: =ROW()-1 -> 4
A6: AO-C-050 | B6: Global Trading Systems (GTS) | C6: https://gtsx.com | D6: gtsx.com | E6: 5 | F6: 75.9 | G6: Y | H6: Katherine | I6: Hickey | J6: Executive Assistant to CEO | L6: pantry or office lead (primary) | M6: crowd-listed | N6: The Org (crowd-edited org chart) | O6: https://theorg.com/org/global-trading-systems-1/person/katherine-hickey | P6: 2026-10-24 | V6: none | AE6: 625 Avenue of the Americas | AF6: 3 | AG6: electronic trading / market making | AH6: 420 | AI6: https://www.linkedin.com/company/global-trading-systems | AJ6: Y | AK6: 151-250 | AL6: Y | AM6: 281 | AN6: low | AO6: in-office-5 | AP6: AO-C-050 | AQ6: N | AT6: =IF($A6="","",IF(AND(CN6="pass",AQ6<>"Y",C6<>"",OR(AX6<>"Y",AV6="Y")),"Y","N")) -> Y | AU6: =IF($A6="","",_xlfn.TEXTJOIN("; ",TRUE(),IF(CN6<>"pass","gated out",""),IF(AQ6="Y","on hold: "&AR6,""),IF(C6="","no contact named on an opened page",""),IF(AND(AX6="Y",AV6<>"Y"),"Tuesday estimate band "&L6&": founder's call",""))) | AX6: N | AY6: Katherine | AZ6: Hickey | BA6: Executive Assistant to CEO | BC6: =IF($A6="","",IFERROR(INDEX(Enrichment!$A$2:$GZ$2000,MATCH($A6,INDEX(Enrichment!$A$2:$GZ$2000,0,MATCH("row_id",Enrichment!$A$1:$GZ$1,0)),0),MATCH("work_email",Enrichment!$A$1:$GZ$1,0))&"","")) | BD6: =IF($A6="","",IF(BC6="","none",IF(OR(IFERROR(INDEX(Enrichment!$A$2:$GZ$2000,MATCH($A6,INDEX(Enrichment!$A$2:$GZ$2000,0,MATCH("row_id",Enrichment!$A$1:$GZ$1,0)),0),MATCH("email_status",Enrichment!$A$1:$GZ$1,0))&"","")="verified",IFERROR(INDEX(Enrichment!$A$2:$GZ$2000,MATCH($A6,INDEX(Enrichment!$A$2:$GZ$2000,0,MATCH("row_id",Enrichment!$A$1:$GZ$1,0)),0),MATCH("email_status",Enrichment!$A$1:$GZ$1,0))&"","")="unverified"),IFERROR(INDEX(Enrichment!$A$2:$GZ$2000,MATCH($A6,INDEX(Enrichment!$A$2:$GZ$2000,0,MATCH("row_id",Enrichment!$A$1:$GZ$1,0)),0),MATCH("email_status",Enrichment!$A$1:$GZ$1,0))&"",""),"unverified"))) -> none | BE6: pantry or office lead (primary) | BF6: crowd-listed | BG6: The Org (crowd-edited org chart) | BH6: https://theorg.com/org/global-trading-systems-1/person/katherine-hickey | BI6: 2026-10-24 | BJ6: exact | BK6: find Katherine Hickey at Global Trading Systems (GTS) on LinkedIn and paste the profile URL into primary_linkedin_url (this also confirms the name: The Org is crowd-edited and marks it Unverified) | BL6: contact in the target titles named (Executive Assistant to CEO) (crowd-listed on The Org) | BQ6: =IF($A6="","",IFERROR(INDEX(Enrichment!$A$2:$GZ$2000,MATCH($A6,INDEX(Enrichment!$A$2:$GZ$2000,0,MATCH("row_id",Enrichment!$A$1:$GZ$1,0)),0),MATCH("backup_work_email",Enrichment!$A$1:$GZ$1,0))&"","")) | BR6: =IF($A6="","",IF(BQ6="","none",IF(OR(IFERROR(INDEX(Enrichment!$A$2:$GZ$2000,MATCH($A6,INDEX(Enrichment!$A$2:$GZ$2000,0,MATCH("row_id",Enrichment!$A$1:$GZ$1,0)),0),MATCH("backup_email_status",Enrichment!$A$1:$GZ$1,0))&"","")="verified",IFERROR(INDEX(Enrichment!$A$2:$GZ$2000,MATCH($A6,INDEX(Enrichment!$A$2:$GZ$2000,0,MATCH("row_id",Enrichment!$A$1:$GZ$1,0)),0),MATCH("backup_email_status",Enrichment!$A$1:$GZ$1,0))&"","")="unverified"),IFERROR(INDEX(Enrichment!$A$2:$GZ$2000,MATCH($A6,INDEX(Enrichment!$A$2:$GZ$2000,0,MATCH("row_id",Enrichment!$A$1:$GZ$1,0)),0),MATCH("backup_email_status",Enrichment!$A$1:$GZ$1,0))&"",""),"unverified"))) -> none | BT6: none | BX6: none | BY6: no backup named: back to research | BZ6: no backup contact named | CA6: Tuesday estimate 137 to 281 (low confidence), under 500 staff company-wide, on-site 5 days a week per its profile, occupied at a high-confidence address | CB6: linkedin | CC6: Katherine Hickey | CD6: 2026-01-28 | CE6: ny_base=confirmed; title_fit=family (EA to the CEO). The Org position page (opened 2026-10-24, updated 2026-01-28) lists her as Executive Assistant to CEO, located in the New York area; GTS is a New York firm. The Org is crowd-edited and marks crowd-added people Unverified. | CF6: confirmed | CM6: Y | CN6: pass | CO6: passes all hard gates | CP6: company | CQ6: B-C-050 | CR6: https://gtsx.com | CS6: electronic trading / market making | CT6: 420 | CU6: 410 | CV6: 251-500 | CW6: whole-company | CX6: agree | CY6: https://www.builtinnyc.com/company/gts | CZ6: https://www.reveliolabs.com/companies/global-trading-systems/employees | DA6: le500 | DB6: New York | DC6: Y | DD6: unknown | DE6: https://www.linkedin.com/company/global-trading-systems | DF6: 10011 | DG6: 40.74024 | DH6: -73.994996 | DI6: Y | DJ6: 0 | DK6: B-B-020 | DL6: 625 Avenue of the Americas (Taub family) | DM6: https://commercialobserver.com/2024/11/trading-firm-gts-lease-625-avenue-of-the-americas/ | DN6: 2024-11-21 | DO6: leasing-press | DP6: https://gtsx.com/locations/ | DQ6: 2026-10-24 | DS6: high | DU6: N | DX6: unknown | EA6: unknown | EB6: N | EC6: Built In workplace type: OnSite Workplace; typical time on-site: 5 days a week | ED6: https://www.builtinnyc.com/company/gts/offices | EE6: 2026-10-24 | EF6: 196 | EG6: may exceed 250 | EH6: N | EI6: 420 (Built In) and 410 (Revelio Labs) staff (whole-company count) x 50% to 100% of them in the New York office (HQ New York; share assumed) x 67% (Partnership for NYC, firms under 500) in on a weekday = 137 to 281, central 196; low confidence; estimate until intake replaces it. | EJ6: estimate until intake replaces it | EK6: 0.84 | EL6: 75.9 | EM6: 20.9 | EN6: 15 | EO6: 15 | EP6: 15 | EQ6: =IF($A6="","",IF(AH6="exact",10,IF(AH6="adjacent",5,0))) -> 0 | ER6: =IF($A6="","",IF(R6="Y",15,0)) -> 0 | ES6: candidate | EV6: 35,156 sf | EW6: B's sources | EX6: 15-year, 35,156 sf lease of the 3rd floor (CO Nov 2024), relocating from 545 Madison Ave; keeps 40 Wall St. Company locations page (opened 2026-10-24) lists New York at 625 Sixth Avenue, NY 10011. Built In shows 420 total employees and still lists 545 Madison Ave. | Assembly 2026-10-24: Review round 2: a second count agrees with the band: Revelio Labs (Global Trading Systems LLC, HQ New York City): about 410 employees worldwide as of March 2026. Review round 2: corner lot: the lot-centroid pin sat 37 m from W 19 ST but 38 m from AVE OF THE AMERICAS, so it was moved to the AVE OF THE AMERICAS frontage near the corner (18 m from the AVE OF THE AMERICAS centreline, 37 m from W 19 ST; 20 m from the old pin). Tax lot unchanged. | EZ6: linked from the company's own site (https://gtsx.com/, opened 2026-10-24); LinkedIn not opened | FS6: =IF($A6="","",IF(ISNUMBER(MATCH(U6,{"queued","contacted","replied","call_booked","call_done","yes_in_principle","materials_sent"},0)),"Y","N")) -> N | FT6: =IF($A6="","",IF(OR(T6="Y",U6="do_not_contact",AS6&""<>""),"Y","N")) -> N | FU6: =IF($A6="","",IF(AP6&""<>"",AP6&"",$A6)) -> AO-C-050 | FV6: =IF($A6="","",IF(COUNTIFS($FU$2:$FU$1000,FU6,$FS$2:$FS$1000,"Y")+COUNTIFS($FU$2:$FU$1000,FU6,$FT$2:$FT$1000,"Y")>0,"Y","N")) -> N | FW6: =IF($A6="","",IF(AND(U6="new",T6="N",FT6="N",AT6="Y",FV6="N"),"Y","N")) -> N | FX6: =IF($A6="","",IF(FW6<>"Y","N",IF(COUNTIFS($FU$2:$FU$1000,FU6,$FW$2:$FW$1000,"Y",$J$2:$J$1000,">"&J6)+COUNTIFS($FU$2:$FU$1000,FU6,$FW$2:$FW$1000,"Y",$J$2:$J$1000,J6,$GD$2:$GD$1000,"<"&GD6)=0,"Y","N"))) -> N | FY6: =IF($A6="","",IF(AND(FW6="Y",FX6="Y",Y6&""<>""),IF(Y6<=10,"Y","N"),"N")) -> N | FZ6: =IF(FY6="Y",Y6,"") | GA6: =IF($A6="","",IF(AND(I6="walk-in",CN6="pass",U6="new",FT6="N",FV6="N",AQ6<>"Y"),"Y","N")) -> N | GB6: =IF(GA6<>"Y","",IF(COUNTIFS($GA$2:$GA$1000,"Y",$J$2:$J$1000,">"&J6)+COUNTIFS($GA$2:$GA$1000,"Y",$J$2:$J$1000,J6,$GD$2:$GD$1000,"<"&GD6)+1<=25,COUNTIFS($GA$2:$GA$1000,"Y",$J$2:$J$1000,">"&J6)+COUNTIFS($GA$2:$GA$1000,"Y",$J$2:$J$1000,J6,$GD$2:$GD$1000,"<"&GD6)+1,"")) | GC6: =IF(AND(_xlfn.ISFORMULA(C6),_xlfn.ISFORMULA(J6)),"Y","N") -> N | GD6: =ROW()-1 -> 5
A7: AO-C-037 | B7: Nayya | C7: https://www.nayya.com | D7: nayya.com | E7: 6 | F7: 75.0 | G7: Y | H7: Phoebe | I7: Waxman | J7: Senior People Operations Analyst | L7: pantry or office lead (primary) | M7: crowd-listed | N7: The Org (crowd-edited org chart) | O7: https://theorg.com/org/nayya/person/phoebe-waxman | P7: 2026-10-24 | Q7: Amber | R7: Hewko | S7: Executive Assistant | U7: pantry or office lead (backup) | V7: crowd-listed | W7: The Org (crowd-edited org chart) | X7: https://theorg.com/org/nayya/person/amber-hewko | Y7: 2026-10-24 | Z7: Amber Hewko | AA7: 2025-05-30 | AB7: ny_base=unconfirmed (no location or office on The Org); title_fit=variant (The Org shows her reporting to the CEO, Sarah Liebel). The Org updated 2025-05-30. | AC7: unconfirmed | AE7: 215 Park Avenue South | AF7: 4 | AG7: benefits software (health tech) | AH7: 150 | AI7: https://www.linkedin.com/company/64515483 | AJ7: Y | AK7: 76-150 | AL7: Y | AM7: 134 | AN7: low | AO7: hybrid-3 | AP7: AO-C-037 | AQ7: N | AT7: =IF($A7="","",IF(AND(CN7="pass",AQ7<>"Y",C7<>"",OR(AX7<>"Y",AV7="Y")),"Y","N")) -> Y | AU7: =IF($A7="","",_xlfn.TEXTJOIN("; ",TRUE(),IF(CN7<>"pass","gated out",""),IF(AQ7="Y","on hold: "&AR7,""),IF(C7="","no contact named on an opened page",""),IF(AND(AX7="Y",AV7<>"Y"),"Tuesday estimate band "&L7&": founder's call",""))) | AX7: N | AY7: Phoebe | AZ7: Waxman | BA7: Senior People Operations Analyst | BC7: =IF($A7="","",IFERROR(INDEX(Enrichment!$A$2:$GZ$2000,MATCH($A7,INDEX(Enrichment!$A$2:$GZ$2000,0,MATCH("row_id",Enrichment!$A$1:$GZ$1,0)),0),MATCH("work_email",Enrichment!$A$1:$GZ$1,0))&"","")) | BD7: =IF($A7="","",IF(BC7="","none",IF(OR(IFERROR(INDEX(Enrichment!$A$2:$GZ$2000,MATCH($A7,INDEX(Enrichment!$A$2:$GZ$2000,0,MATCH("row_id",Enrichment!$A$1:$GZ$1,0)),0),MATCH("email_status",Enrichment!$A$1:$GZ$1,0))&"","")="verified",IFERROR(INDEX(Enrichment!$A$2:$GZ$2000,MATCH($A7,INDEX(Enrichment!$A$2:$GZ$2000,0,MATCH("row_id",Enrichment!$A$1:$GZ$1,0)),0),MATCH("email_status",Enrichment!$A$1:$GZ$1,0))&"","")="unverified"),IFERROR(INDEX(Enrichment!$A$2:$GZ$2000,MATCH($A7,INDEX(Enrichment!$A$2:$GZ$2000,0,MATCH("row_id",Enrichment!$A$1:$GZ$1,0)),0),MATCH("email_status",Enrichment!$A$1:$GZ$1,0))&"",""),"unverified"))) -> none | BE7: pantry or office lead (primary) | BF7: crowd-listed | BG7: The Org (crowd-edited org chart) | BH7: https://theorg.com/org/nayya/person/phoebe-waxman | BI7: 2026-10-24 | BJ7: exact | BK7: find Phoebe Waxman at Nayya on LinkedIn and paste the profile URL into primary_linkedin_url (this also confirms the name: The Org is crowd-edited and marks it Unverified) | BL7: contact in the target titles named (Senior People Operations Analyst) (crowd-listed on The Org) | BM7: Amber | BN7: Hewko | BO7: Executive Assistant | BQ7: =IF($A7="","",IFERROR(INDEX(Enrichment!$A$2:$GZ$2000,MATCH($A7,INDEX(Enrichment!$A$2:$GZ$2000,0,MATCH("row_id",Enrichment!$A$1:$GZ$1,0)),0),MATCH("backup_work_email",Enrichment!$A$1:$GZ$1,0))&"","")) | BR7: =IF($A7="","",IF(BQ7="","none",IF(OR(IFERROR(INDEX(Enrichment!$A$2:$GZ$2000,MATCH($A7,INDEX(Enrichment!$A$2:$GZ$2000,0,MATCH("row_id",Enrichment!$A$1:$GZ$1,0)),0),MATCH("backup_email_status",Enrichment!$A$1:$GZ$1,0))&"","")="verified",IFERROR(INDEX(Enrichment!$A$2:$GZ$2000,MATCH($A7,INDEX(Enrichment!$A$2:$GZ$2000,0,MATCH("row_id",Enrichment!$A$1:$GZ$1,0)),0),MATCH("backup_email_status",Enrichment!$A$1:$GZ$1,0))&"","")="unverified"),IFERROR(INDEX(Enrichment!$A$2:$GZ$2000,MATCH($A7,INDEX(Enrichment!$A$2:$GZ$2000,0,MATCH("row_id",Enrichment!$A$1:$GZ$1,0)),0),MATCH("backup_email_status",Enrichment!$A$1:$GZ$1,0))&"",""),"unverified"))) -> none | BS7: pantry or office lead (backup) | BT7: crowd-listed | BU7: The Org (crowd-edited org chart) | BV7: https://theorg.com/org/nayya/person/amber-hewko | BW7: 2026-10-24 | BX7: adjacent | BY7: find Amber Hewko at Nayya on LinkedIn and paste the profile URL into backup_linkedin_url (this also confirms the name: The Org is crowd-edited and marks it Unverified); the source is dated 2025-05-30: check Amber still holds the role; check Amber works from the New York office; adjacent title: ask who runs the pantry | BZ7: adjacent contact named (Executive Assistant) (crowd-listed on The Org) | CA7: Tuesday estimate 50 to 134 (low confidence), under 500 staff company-wide, hybrid 3 days, occupied at a high-confidence address | CB7: linkedin | CC7: Phoebe Waxman | CD7: 2026-01-24 | CE7: ny_base=likely (The Org gives a New York location, no office attached); title_fit=family (people operations). The Org updated 2026-01-24. Nayya has advertised a 5-days-in-office NYC Office Manager role (search results: builtinnyc.com/job/office-manager/297301, venturefizz, not opened); no name found for that seat. | CF7: likely | CH7: Amber Hewko | CI7: 2025-05-30 | CJ7: ny_base=unconfirmed (no location or office on The Org); title_fit=variant (The Org shows her reporting to the CEO, Sarah Liebel). The Org updated 2025-05-30. | CK7: unconfirmed | CM7: Y | CN7: pass | CO7: passes all hard gates | CP7: company | CQ7: B-C-037 | CR7: https://www.nayya.com | CS7: benefits software (health tech) | CT7: 150 | CU7: 200 | CV7: unknown | CW7: unknown | CX7: disagree | CY7: https://www.builtinnyc.com/company/nayya | CZ7: https://www.reveliolabs.com/companies/nayya-health/employees | DA7: le500 | DB7: New York | DC7: Y | DD7: unknown | DE7: https://www.linkedin.com/company/64515483 | DF7: 10003 | DG7: 40.73686 | DH7: -73.988546 | DI7: Y | DJ7: 0 | DK7: B-B-016 | DL7: 215 Park Avenue South (SL Green managed) | DM7: https://www.sec.gov/Archives/edgar/data/1013454/000153949726000704/n5676_x5-424h.htm | DN7: 2026-02 | DO7: other | DP7: https://www.nyrej.com/sl-green-signs-29-915-s-f-lease-with-nayya-health-at-215-park-ave-south | DQ7: 2024-12-10 | DR7: cites a sec.gov filing: agents do not open it (EDGAR demands a contact email); the founder may open it in a browser | DS7: high | DU7: N | DX7: security desk | DY7: https://www.metro-manhattan.com/buildings/215-park-avenue-south/ | EA7: unknown | EB7: N | EC7: Built In workplace type: Hybrid Workplace; typical time on-site: 3 days a week; recent job tags: 3 Hybrid | ED7: https://www.builtinnyc.com/company/nayya/offices | EE7: 2026-10-24 | EF7: 82 | EH7: N | EI7: 150 (Built In) and 200 (Revelio Labs) staff (whole-company count) x 50% to 100% of them in the New York office (HQ New York; share assumed) x 67% (Partnership for NYC, firms under 500) in on a weekday = 50 to 134, central 82; low confidence; estimate until intake replaces it. | EJ7: estimate until intake replaces it | EK7: 1 | EL7: 75 | EM7: 25 | EN7: 15 | EO7: 10 | EP7: 15 | EQ7: =IF($A7="","",IF(AH7="exact",10,IF(AH7="adjacent",5,0))) -> 0 | ER7: =IF($A7="","",IF(R7="Y",15,0)) -> 0 | ES7: candidate | EV7: 29,915 sf;12,660 sf | EW7: B's sources | EX7: SEC CMBS prospectus (Benchmark 2026-B42), rent roll dated 2026-02-05: Nayya Health Inc. 29,915 sf, lease to 2029-12-31, subleases its 18th-floor part (12,660 sf) to BaseTen Labs. NYREJ 2024-12-10: entire 4th floor plus part of 18th. Built In NYC: 150 total employees, HQ New York. | Assembly 2026-10-24: SEC EDGAR source (sec.gov): this agent will not re-open it, because EDGAR serves only requests that carry a contact email and the project rule forbids sending one; the founder may open it in a browser. Review round 2: band changed from 76-150 to unknown. Sources disagree: Built In shows 150 (76-150) and Revelio Labs (Nayya Health, Inc., HQ New York City): about 200 employees worldwide as of March 2026 (151-250). Band left unknown; founder to confirm at intake. Review round 2: corner lot: the lot-centroid pin sat 20 m from E 18 ST but 39 m from PARK AVE S, so it was moved to the PARK AVE S frontage near the corner (14 m from the PARK AVE S centreline, 26 m from E 18 ST; 26 m from the old pin). Tax lot unchanged. | EZ7: linked from the company's own site (https://www.nayya.com/, opened 2026-10-24); LinkedIn not opened | FS7: =IF($A7="","",IF(ISNUMBER(MATCH(U7,{"queued","contacted","replied","call_booked","call_done","yes_in_principle","materials_sent"},0)),"Y","N")) -> N | FT7: =IF($A7="","",IF(OR(T7="Y",U7="do_not_contact",AS7&""<>""),"Y","N")) -> N | FU7: =IF($A7="","",IF(AP7&""<>"",AP7&"",$A7)) -> AO-C-037 | FV7: =IF($A7="","",IF(COUNTIFS($FU$2:$FU$1000,FU7,$FS$2:$FS$1000,"Y")+COUNTIFS($FU$2:$FU$1000,FU7,$FT$2:$FT$1000,"Y")>0,"Y","N")) -> N | FW7: =IF($A7="","",IF(AND(U7="new",T7="N",FT7="N",AT7="Y",FV7="N"),"Y","N")) -> N | FX7: =IF($A7="","",IF(FW7<>"Y","N",IF(COUNTIFS($FU$2:$FU$1000,FU7,$FW$2:$FW$1000,"Y",$J$2:$J$1000,">"&J7)+COUNTIFS($FU$2:$FU$1000,FU7,$FW$2:$FW$1000,"Y",$J$2:$J$1000,J7,$GD$2:$GD$1000,"<"&GD7)=0,"Y","N"))) -> N | FY7: =IF($A7="","",IF(AND(FW7="Y",FX7="Y",Y7&""<>""),IF(Y7<=10,"Y","N"),"N")) -> N | FZ7: =IF(FY7="Y",Y7,"") | GA7: =IF($A7="","",IF(AND(I7="walk-in",CN7="pass",U7="new",FT7="N",FV7="N",AQ7<>"Y"),"Y","N")) -> N | GB7: =IF(GA7<>"Y","",IF(COUNTIFS($GA$2:$GA$1000,"Y",$J$2:$J$1000,">"&J7)+COUNTIFS($GA$2:$GA$1000,"Y",$J$2:$J$1000,J7,$GD$2:$GD$1000,"<"&GD7)+1<=25,COUNTIFS($GA$2:$GA$1000,"Y",$J$2:$J$1000,">"&J7)+COUNTIFS($GA$2:$GA$1000,"Y",$J$2:$J$1000,J7,$GD$2:$GD$1000,"<"&GD7)+1,"")) | GC7: =IF(AND(_xlfn.ISFORMULA(C7),_xlfn.ISFORMULA(J7)),"Y","N") -> N | GD7: =ROW()-1 -> 6
A8: AO-C-034 | B8: Cognitiv | C8: https://cognitiv.ai | D8: cognitiv.ai | E8: 7 | F8: 73.0 | G8: Y | H8: Jason | I8: Pellegrino | J8: SVP, People | L8: pantry or office lead (primary) | M8: verified-page | N8: employer's own site | O8: https://cognitiv.ai/about-us | P8: 2026-10-24 | Q8: Rebecca | R8: Aliab D. | S8: Vice President, Business Operations | U8: pantry or office lead (backup) | V8: crowd-listed | W8: The Org (crowd-edited org chart) | X8: https://theorg.com/org/cognitiv/person/rebecca-aliab-d | Y8: 2026-10-24 | Z8: Rebecca Aliab D. | AA8: 2026-01-19 | AB8: ny_base=confirmed; title_fit=adjacent (business operations lead). The Org attaches the role to Cognitiv's New York HQ office (updated 2026-01-19). Surname appears truncated on The Org ('Aliab D.'); founder to confirm the full name before outreach. | AC8: confirmed | AE8: 215 Park Avenue South | AF8: 16 | AG8: adtech (AI advertising) | AH8: 170 | AI8: https://www.linkedin.com/company/cognitiv | AJ8: Y | AK8: 76-150 | AL8: Y | AM8: 114 | AN8: low | AO8: hybrid-3 | AP8: AO-C-034 | AQ8: N | AT8: =IF($A8="","",IF(AND(CN8="pass",AQ8<>"Y",C8<>"",OR(AX8<>"Y",AV8="Y")),"Y","N")) -> Y | AU8: =IF($A8="","",_xlfn.TEXTJOIN("; ",TRUE(),IF(CN8<>"pass","gated out",""),IF(AQ8="Y","on hold: "&AR8,""),IF(C8="","no contact named on an opened page",""),IF(AND(AX8="Y",AV8<>"Y"),"Tuesday estimate band "&L8&": founder's call",""))) | AX8: N | AY8: Jason | AZ8: Pellegrino | BA8: SVP, People | BC8: =IF($A8="","",IFERROR(INDEX(Enrichment!$A$2:$GZ$2000,MATCH($A8,INDEX(Enrichment!$A$2:$GZ$2000,0,MATCH("row_id",Enrichment!$A$1:$GZ$1,0)),0),MATCH("work_email",Enrichment!$A$1:$GZ$1,0))&"","")) | BD8: =IF($A8="","",IF(BC8="","none",IF(OR(IFERROR(INDEX(Enrichment!$A$2:$GZ$2000,MATCH($A8,INDEX(Enrichment!$A$2:$GZ$2000,0,MATCH("row_id",Enrichment!$A$1:$GZ$1,0)),0),MATCH("email_status",Enrichment!$A$1:$GZ$1,0))&"","")="verified",IFERROR(INDEX(Enrichment!$A$2:$GZ$2000,MATCH($A8,INDEX(Enrichment!$A$2:$GZ$2000,0,MATCH("row_id",Enrichment!$A$1:$GZ$1,0)),0),MATCH("email_status",Enrichment!$A$1:$GZ$1,0))&"","")="unverified"),IFERROR(INDEX(Enrichment!$A$2:$GZ$2000,MATCH($A8,INDEX(Enrichment!$A$2:$GZ$2000,0,MATCH("row_id",Enrichment!$A$1:$GZ$1,0)),0),MATCH("email_status",Enrichment!$A$1:$GZ$1,0))&"",""),"unverified"))) -> none | BE8: pantry or office lead (primary) | BF8: verified-page | BG8: employer's own site | BH8: https://cognitiv.ai/about-us | BI8: 2026-10-24 | BJ8: adjacent | BK8: find Jason Pellegrino at Cognitiv on LinkedIn and paste the profile URL into primary_linkedin_url; adjacent title: ask who runs the pantry | BL8: adjacent contact named (SVP, People) | BM8: Rebecca | BN8: Aliab D. | BO8: Vice President, Business Operations | BQ8: =IF($A8="","",IFERROR(INDEX(Enrichment!$A$2:$GZ$2000,MATCH($A8,INDEX(Enrichment!$A$2:$GZ$2000,0,MATCH("row_id",Enrichment!$A$1:$GZ$1,0)),0),MATCH("backup_work_email",Enrichment!$A$1:$GZ$1,0))&"","")) | BR8: =IF($A8="","",IF(BQ8="","none",IF(OR(IFERROR(INDEX(Enrichment!$A$2:$GZ$2000,MATCH($A8,INDEX(Enrichment!$A$2:$GZ$2000,0,MATCH("row_id",Enrichment!$A$1:$GZ$1,0)),0),MATCH("backup_email_status",Enrichment!$A$1:$GZ$1,0))&"","")="verified",IFERROR(INDEX(Enrichment!$A$2:$GZ$2000,MATCH($A8,INDEX(Enrichment!$A$2:$GZ$2000,0,MATCH("row_id",Enrichment!$A$1:$GZ$1,0)),0),MATCH("backup_email_status",Enrichment!$A$1:$GZ$1,0))&"","")="unverified"),IFERROR(INDEX(Enrichment!$A$2:$GZ$2000,MATCH($A8,INDEX(Enrichment!$A$2:$GZ$2000,0,MATCH("row_id",Enrichment!$A$1:$GZ$1,0)),0),MATCH("backup_email_status",Enrichment!$A$1:$GZ$1,0))&"",""),"unverified"))) -> none | BS8: pantry or office lead (backup) | BT8: crowd-listed | BU8: The Org (crowd-edited org chart) | BV8: https://theorg.com/org/cognitiv/person/rebecca-aliab-d | BW8: 2026-10-24 | BX8: adjacent | BY8: find Rebecca Aliab D. at Cognitiv on LinkedIn and paste the profile URL into backup_linkedin_url (this also confirms the name: The Org is crowd-edited and marks it Unverified); adjacent title: ask who runs the pantry | BZ8: adjacent contact named (Vice President, Business Operations) (crowd-listed on The Org) | CA8: Tuesday estimate 56 to 114 (low confidence), under 500 staff company-wide, hybrid 3 days with Tuesday named as an office day, occupied at a high-confidence address | CB8: linkedin | CC8: Jason Pellegrino | CD8: 2026-03-04 | CE8: ny_base=confirmed; title_fit=variant (people lead). Listed on the company's Meet Our Team section. The Org (https://theorg.com/org/cognitiv/person/jason-pellegrino-phr, updated 2026-03-04) attaches him to Cognitiv's New York HQ office. No office manager found; Cognitiv's office-manager posting found in search was for Tel Aviv. | CF8: confirmed | CH8: Rebecca Aliab D. | CI8: 2026-01-19 | CJ8: ny_base=confirmed; title_fit=adjacent (business operations lead). The Org attaches the role to Cognitiv's New York HQ office (updated 2026-01-19). Surname appears truncated on The Org ('Aliab D.'); founder to confirm the full name before outreach. | CK8: confirmed | CM8: Y | CN8: pass | CO8: passes all hard gates | CP8: company | CQ8: B-C-034 | CR8: https://cognitiv.ai | CS8: adtech (AI advertising) | CT8: 170 | CU8: 166 | CV8: 151-250 | CW8: whole-company | CX8: agree | CY8: https://www.builtinnyc.com/company/cognitiv | CZ8: https://www.reveliolabs.com/companies/cognitiv/employees | DA8: le500 | DB8: New York | DC8: Y | DD8: unknown | DE8: https://www.linkedin.com/company/cognitiv | DF8: 10003 | DG8: 40.73686 | DH8: -73.988546 | DI8: Y | DJ8: 0 | DK8: B-B-016 | DL8: 215 Park Avenue South (SL Green managed) | DM8: https://cognitiv.ai/contact/ | DN8: 2026-10-23 | DO8: company-site | DP8: https://www.sec.gov/Archives/edgar/data/1013454/000153949726000704/n5676_x5-424h.htm | DQ8: 2026-02 | DR8: cites a sec.gov filing: agents do not open it (EDGAR demands a contact email); the founder may open it in a browser | DS8: high | DU8: N | DX8: security desk | DY8: https://www.metro-manhattan.com/buildings/215-park-avenue-south/ | EA8: unknown | EB8: Y | EC8: Built In workplace type: Hybrid Workplace; typical time on-site: 3 days a week; recent job tags: 3 Hybrid | ED8: https://www.builtinnyc.com/company/cognitiv/offices | EE8: 2026-10-24 | EF8: 80 | EH8: N | EI8: 170 (Built In) and 166 (Revelio Labs) staff (whole-company count) x 50% to 100% of them in the New York office (HQ New York; share assumed) x 67% (Partnership for NYC, firms under 500) in on a weekday = 56 to 114, central 80; low confidence; estimate until intake replaces it. | EJ8: estimate until intake replaces it | EK8: 1 | EL8: 73 | EM8: 25 | EN8: 15 | EO8: 13 | EP8: 15 | EQ8: =IF($A8="","",IF(AH8="exact",10,IF(AH8="adjacent",5,0))) -> 0 | ER8: =IF($A8="","",IF(R8="Y",15,0)) -> 0 | ES8: candidate | EV8: 16,612 sf | EW8: B's sources | EX8: Contact page: '215 Park Ave S, Floor 16 New York, NY 10003'. SEC prospectus: Cognitiv Corp. subleases Stellar Health's 16th floor (16,612 sf) through 2027-01-31, so the space may change after January 2027. Built In NYC: 170 total employees, 4 offices, HQ New York. | Assembly 2026-10-24: SEC EDGAR source (sec.gov): this agent will not re-open it, because EDGAR serves only requests that carry a contact email and the project rule forbids sending one; the founder may open it in a browser. Review round 2: a second count agrees with the band: Revelio Labs (Cognitiv Corp., HQ New York City): about 166 employees worldwide as of March 2026. Review round 2: corner lot: the lot-centroid pin sat 20 m from E 18 ST but 39 m from PARK AVE S, so it was moved to the PARK AVE S frontage near the corner (14 m from the PARK AVE S centreline, 26 m from E 18 ST; 26 m from the old pin). Tax lot unchanged. | EZ8: linked from the company's own site (https://www.cognitiv.ai/, opened 2026-10-24); LinkedIn not opened | FS8: =IF($A8="","",IF(ISNUMBER(MATCH(U8,{"queued","contacted","replied","call_booked","call_done","yes_in_principle","materials_sent"},0)),"Y","N")) -> N | FT8: =IF($A8="","",IF(OR(T8="Y",U8="do_not_contact",AS8&""<>""),"Y","N")) -> N | FU8: =IF($A8="","",IF(AP8&""<>"",AP8&"",$A8)) -> AO-C-034 | FV8: =IF($A8="","",IF(COUNTIFS($FU$2:$FU$1000,FU8,$FS$2:$FS$1000,"Y")+COUNTIFS($FU$2:$FU$1000,FU8,$FT$2:$FT$1000,"Y")>0,"Y","N")) -> N | FW8: =IF($A8="","",IF(AND(U8="new",T8="N",FT8="N",AT8="Y",FV8="N"),"Y","N")) -> N | FX8: =IF($A8="","",IF(FW8<>"Y","N",IF(COUNTIFS($FU$2:$FU$1000,FU8,$FW$2:$FW$1000,"Y",$J$2:$J$1000,">"&J8)+COUNTIFS($FU$2:$FU$1000,FU8,$FW$2:$FW$1000,"Y",$J$2:$J$1000,J8,$GD$2:$GD$1000,"<"&GD8)=0,"Y","N"))) -> N | FY8: =IF($A8="","",IF(AND(FW8="Y",FX8="Y",Y8&""<>""),IF(Y8<=10,"Y","N"),"N")) -> N | FZ8: =IF(FY8="Y",Y8,"") | GA8: =IF($A8="","",IF(AND(I8="walk-in",CN8="pass",U8="new",FT8="N",FV8="N",AQ8<>"Y"),"Y","N")) -> N | GB8: =IF(GA8<>"Y","",IF(COUNTIFS($GA$2:$GA$1000,"Y",$J$2:$J$1000,">"&J8)+COUNTIFS($GA$2:$GA$1000,"Y",$J$2:$J$1000,J8,$GD$2:$GD$1000,"<"&GD8)+1<=25,COUNTIFS($GA$2:$GA$1000,"Y",$J$2:$J$1000,">"&J8)+COUNTIFS($GA$2:$GA$1000,"Y",$J$2:$J$1000,J8,$GD$2:$GD$1000,"<"&GD8)+1,"")) | GC8: =IF(AND(_xlfn.ISFORMULA(C8),_xlfn.ISFORMULA(J8)),"Y","N") -> N | GD8: =ROW()-1 -> 7
A9: AO-C-091 | B9: 1stDibs | C9: https://www.1stdibs.com/ | D9: 1stdibs.com | E9: 8 | F9: 72.0 | G9: Y | H9: Lindsay | I9: Cusatis | J9: Executive Assistant to Chief Executive Officer; Manager | L9: pantry or office lead (primary) | M9: crowd-listed | N9: The Org (crowd-edited org chart) | O9: https://theorg.com/org/1stdibs/person/lindsay-cusatis | P9: 2026-10-24 | Q9: Maura | R9: Bermingham | S9: People Business Partner | U9: pantry or office lead (backup) | V9: crowd-listed | W9: The Org (crowd-edited org chart) | X9: https://theorg.com/org/1stdibs/person/maura-bermingham | Y9: 2026-10-24 | Z9: Maura Bermingham | AA9: 2025-05-23 | AB9: ny_base=likely (The Org gives a New York location, no office attached); title_fit=variant (people). The Org updated 2025-05-23. | AC9: likely | AE9: 300 Park Avenue South | AF9: 10 | AG9: Online marketplace (design, art, antiques) | AH9: 455 | AI9: https://www.linkedin.com/company/1stdibs | AJ9: Y | AK9: 76-150 | AL9: Y | AM9: 109 | AN9: low | AO9: hybrid-unspecified | AP9: AO-C-091 | AQ9: N | AT9: =IF($A9="","",IF(AND(CN9="pass",AQ9<>"Y",C9<>"",OR(AX9<>"Y",AV9="Y")),"Y","N")) -> Y | AU9: =IF($A9="","",_xlfn.TEXTJOIN("; ",TRUE(),IF(CN9<>"pass","gated out",""),IF(AQ9="Y","on hold: "&AR9,""),IF(C9="","no contact named on an opened page",""),IF(AND(AX9="Y",AV9<>"Y"),"Tuesday estimate band "&L9&": founder's call",""))) | AX9: N | AY9: Lindsay | AZ9: Cusatis | BA9: Executive Assistant to Chief Executive Officer; Manager | BC9: =IF($A9="","",IFERROR(INDEX(Enrichment!$A$2:$GZ$2000,MATCH($A9,INDEX(Enrichment!$A$2:$GZ$2000,0,MATCH("row_id",Enrichment!$A$1:$GZ$1,0)),0),MATCH("work_email",Enrichment!$A$1:$GZ$1,0))&"","")) | BD9: =IF($A9="","",IF(BC9="","none",IF(OR(IFERROR(INDEX(Enrichment!$A$2:$GZ$2000,MATCH($A9,INDEX(Enrichment!$A$2:$GZ$2000,0,MATCH("row_id",Enrichment!$A$1:$GZ$1,0)),0),MATCH("email_status",Enrichment!$A$1:$GZ$1,0))&"","")="verified",IFERROR(INDEX(Enrichment!$A$2:$GZ$2000,MATCH($A9,INDEX(Enrichment!$A$2:$GZ$2000,0,MATCH("row_id",Enrichment!$A$1:$GZ$1,0)),0),MATCH("email_status",Enrichment!$A$1:$GZ$1,0))&"","")="unverified"),IFERROR(INDEX(Enrichment!$A$2:$GZ$2000,MATCH($A9,INDEX(Enrichment!$A$2:$GZ$2000,0,MATCH("row_id",Enrichment!$A$1:$GZ$1,0)),0),MATCH("email_status",Enrichment!$A$1:$GZ$1,0))&"",""),"unverified"))) -> none | BE9: pantry or office lead (primary) | BF9: crowd-listed | BG9: The Org (crowd-edited org chart) | BH9: https://theorg.com/org/1stdibs/person/lindsay-cusatis | BI9: 2026-10-24 | BJ9: exact | BK9: find Lindsay Cusatis at 1stDibs on LinkedIn and paste the profile URL into primary_linkedin_url (this also confirms the name: The Org is crowd-edited and marks it Unverified); the source is dated 2024-11-24: check Lindsay still holds the role | BL9: contact in the target titles named (Executive Assistant to Chief Executive Officer; Manager) (crowd-listed on The Org) | BM9: Maura | BN9: Bermingham | BO9: People Business Partner | BQ9: =IF($A9="","",IFERROR(INDEX(Enrichment!$A$2:$GZ$2000,MATCH($A9,INDEX(Enrichment!$A$2:$GZ$2000,0,MATCH("row_id",Enrichment!$A$1:$GZ$1,0)),0),MATCH("backup_work_email",Enrichment!$A$1:$GZ$1,0))&"","")) | BR9: =IF($A9="","",IF(BQ9="","none",IF(OR(IFERROR(INDEX(Enrichment!$A$2:$GZ$2000,MATCH($A9,INDEX(Enrichment!$A$2:$GZ$2000,0,MATCH("row_id",Enrichment!$A$1:$GZ$1,0)),0),MATCH("backup_email_status",Enrichment!$A$1:$GZ$1,0))&"","")="verified",IFERROR(INDEX(Enrichment!$A$2:$GZ$2000,MATCH($A9,INDEX(Enrichment!$A$2:$GZ$2000,0,MATCH("row_id",Enrichment!$A$1:$GZ$1,0)),0),MATCH("backup_email_status",Enrichment!$A$1:$GZ$1,0))&"","")="unverified"),IFERROR(INDEX(Enrichment!$A$2:$GZ$2000,MATCH($A9,INDEX(Enrichment!$A$2:$GZ$2000,0,MATCH("row_id",Enrichment!$A$1:$GZ$1,0)),0),MATCH("backup_email_status",Enrichment!$A$1:$GZ$1,0))&"",""),"unverified"))) -> none | BS9: pantry or office lead (backup) | BT9: crowd-listed | BU9: The Org (crowd-edited org chart) | BV9: https://theorg.com/org/1stdibs/person/maura-bermingham | BW9: 2026-10-24 | BX9: adjacent | BY9: find Maura Bermingham at 1stDibs on LinkedIn and paste the profile URL into backup_linkedin_url (this also confirms the name: The Org is crowd-edited and marks it Unverified); the source is dated 2025-05-23: check Maura still holds the role; adjacent title: ask who runs the pantry | BZ9: adjacent contact named (People Business Partner) (crowd-listed on The Org) | CA9: Tuesday estimate 94 to 109 (low confidence), under 500 staff company-wide, hybrid (days not stated), occupied at a high-confidence address | CB9: linkedin | CC9: Lindsay Cusatis | CD9: 2024-11-24 | CE9: ny_base=confirmed (The Org attaches the role to 1stDibs's New York HQ office and shows her reporting to the CEO, David Rosenblatt); title_fit=family (EA to CEO). The Org updated 2024-11-24. | CF9: confirmed | CH9: Maura Bermingham | CI9: 2025-05-23 | CJ9: ny_base=likely (The Org gives a New York location, no office attached); title_fit=variant (people). The Org updated 2025-05-23. | CK9: likely | CM9: Y | CN9: pass | CO9: passes all hard gates | CP9: company | CQ9: B-C-091 | CR9: https://www.1stdibs.com/ | CS9: Online marketplace (design, art, antiques) | CT9: 455 | CU9: 281 | CV9: 251-500 | CW9: whole-company | CX9: agree | CY9: https://www.builtinnyc.com/company/1stdibs/offices | CZ9: https://www.reveliolabs.com/companies/1stdibs/employees | DA9: le500 | DB9: New York | DC9: Y | DD9: unknown | DE9: https://www.linkedin.com/company/1stdibs | DF9: 10010 | DG9: 40.739819 | DH9: -73.986885 | DI9: Y | DJ9: 0 | DK9: B-B-044 | DL9: 300 Park Avenue South (Rockrose); also addressed 290 Park Avenue South | DM9: https://www.1stdibs.com/about/user-agreement/ | DN9: 2026-10-23 | DO9: company-site | DP9: https://commercialobserver.com/2025/08/flexible-finance-relocating-41k-sf-300-park-avenue-south/ | DQ9: 2025-08-18 | DS9: high | DU9: N | DX9: security desk | DY9: https://rockrose.com/office/300-park-ave-s/ | EA9: unknown | EB9: N | EC9: Built In workplace type: OnSite Workplace; typical time on-site: 5 days a week (box) but policy text: teams set their own in-office days | ED9: https://www.builtinnyc.com/company/1stdibs/offices | EE9: 2026-10-24 | EF9: 94 | EH9: Y | EI9: 455 (Built In) and 281 (Revelio Labs) staff (whole-company count) x 50% to 100% of them in the New York office (HQ New York; share assumed) x 67% (Partnership for NYC, firms under 500) in on a weekday; capped by 13,671 sf at 125 sf per person (was 94 to 305); central capped at 13,671 sf / 150 sf per person (largest square footage the sources mention at this address; if the company holds more space here, intake corrects it) = 94 to 109, central 94; low confidence; estimate until intake replaces it. | EJ9: estimate until intake replaces it | EK9: 1 | EL9: 72 | EM9: 25 | EN9: 15 | EO9: 7 | EP9: 15 | EQ9: =IF($A9="","",IF(AH9="exact",10,IF(AH9="adjacent",5,0))) -> 0 | ER9: =IF($A9="","",IF(R9="Y",15,0)) -> 0 | ES9: candidate | EV9: 13,671 sf | EW9: B's sources | EX9: Company user agreement and privacy policy (live) give 300 Park Avenue South, 10th Floor. CO Mar 2024: HQ move from 51 Astor Place, 13,671 sf; CO Aug 2025 lists 1stDibs as a current tenant. Built In: 455 total employees (profile still shows 51 Astor Place). | Assembly 2026-10-24: Review round 2: a second count agrees with the band: Revelio Labs (1stdibs.com, Inc., HQ New York City): about 281 employees worldwide as of March 2026. Review round 2: corner lot: the lot-centroid pin sat 24 m from E 22 ST but 25 m from PARK AVE S, so it was moved to the PARK AVE S frontage near the corner (13 m from the PARK AVE S centreline, 27 m from E 22 ST; 12 m from the old pin). Tax lot unchanged. | EZ9: linked from the company's own site (https://www.1stdibs.com/, opened 2026-10-24); LinkedIn not opened | FS9: =IF($A9="","",IF(ISNUMBER(MATCH(U9,{"queued","contacted","replied","call_booked","call_done","yes_in_principle","materials_sent"},0)),"Y","N")) -> N | FT9: =IF($A9="","",IF(OR(T9="Y",U9="do_not_contact",AS9&""<>""),"Y","N")) -> N | FU9: =IF($A9="","",IF(AP9&""<>"",AP9&"",$A9)) -> AO-C-091 | FV9: =IF($A9="","",IF(COUNTIFS($FU$2:$FU$1000,FU9,$FS$2:$FS$1000,"Y")+COUNTIFS($FU$2:$FU$1000,FU9,$FT$2:$FT$1000,"Y")>0,"Y","N")) -> N | FW9: =IF($A9="","",IF(AND(U9="new",T9="N",FT9="N",AT9="Y",FV9="N"),"Y","N")) -> N | FX9: =IF($A9="","",IF(FW9<>"Y","N",IF(COUNTIFS($FU$2:$FU$1000,FU9,$FW$2:$FW$1000,"Y",$J$2:$J$1000,">"&J9)+COUNTIFS($FU$2:$FU$1000,FU9,$FW$2:$FW$1000,"Y",$J$2:$J$1000,J9,$GD$2:$GD$1000,"<"&GD9)=0,"Y","N"))) -> N | FY9: =IF($A9="","",IF(AND(FW9="Y",FX9="Y",Y9&""<>""),IF(Y9<=10,"Y","N"),"N")) -> N | FZ9: =IF(FY9="Y",Y9,"") | GA9: =IF($A9="","",IF(AND(I9="walk-in",CN9="pass",U9="new",FT9="N",FV9="N",AQ9<>"Y"),"Y","N")) -> N | GB9: =IF(GA9<>"Y","",IF(COUNTIFS($GA$2:$GA$1000,"Y",$J$2:$J$1000,">"&J9)+COUNTIFS($GA$2:$GA$1000,"Y",$J$2:$J$1000,J9,$GD$2:$GD$1000,"<"&GD9)+1<=25,COUNTIFS($GA$2:$GA$1000,"Y",$J$2:$J$1000,">"&J9)+COUNTIFS($GA$2:$GA$1000,"Y",$J$2:$J$1000,J9,$GD$2:$GD$1000,"<"&GD9)+1,"")) | GC9: =IF(AND(_xlfn.ISFORMULA(C9),_xlfn.ISFORMULA(J9)),"Y","N") -> N | GD9: =ROW()-1 -> 8
A10: AO-C-031 | B10: Dashlane | C10: https://www.dashlane.com | D10: dashlane.com | E10: 9 | F10: 72.0 | G10: Y | H10: Caroline | I10: Lee | J10: Workplace Experience Specialist | L10: pantry or office lead (primary) | M10: crowd-listed | N10: The Org (crowd-edited org chart) | O10: https://theorg.com/org/dashlane/person/caroline-lee | P10: 2026-10-24 | Q10: Pamela | R10: Golden | S10: SVP, Head of People | U10: pantry or office lead (backup) | V10: verified-page | W10: employer's own site | X10: https://www.dashlane.com/about/leadership | Y10: 2026-10-24 | Z10: Pamela Golden | AB10: ny_base=likely; title_fit=variant (head of people). Dashlane's own leadership page (opened 2026-10-24) lists 'Pamela Golden | SVP, Head of People'; the page gives no city. | AC10: likely | AE10: 44 West 18th Street | AF10: 4 | AG10: software (password management / security) | AH10: 284 | AI10: https://www.linkedin.com/company/dashlane | AJ10: Y | AK10: 76-150 | AL10: Y | AM10: 133 | AN10: low | AO10: hybrid-unspecified | AP10: AO-C-031 | AQ10: N | AT10: =IF($A10="","",IF(AND(CN10="pass",AQ10<>"Y",C10<>"",OR(AX10<>"Y",AV10="Y")),"Y","N")) -> Y | AU10: =IF($A10="","",_xlfn.TEXTJOIN("; ",TRUE(),IF(CN10<>"pass","gated out",""),IF(AQ10="Y","on hold: "&AR10,""),IF(C10="","no contact named on an opened page",""),IF(AND(AX10="Y",AV10<>"Y"),"Tuesday estimate band "&L10&": founder's call",""))) | AX10: N | AY10: Caroline | AZ10: Lee | BA10: Workplace Experience Specialist | BC10: =IF($A10="","",IFERROR(INDEX(Enrichment!$A$2:$GZ$2000,MATCH($A10,INDEX(Enrichment!$A$2:$GZ$2000,0,MATCH("row_id",Enrichment!$A$1:$GZ$1,0)),0),MATCH("work_email",Enrichment!$A$1:$GZ$1,0))&"","")) | BD10: =IF($A10="","",IF(BC10="","none",IF(OR(IFERROR(INDEX(Enrichment!$A$2:$GZ$2000,MATCH($A10,INDEX(Enrichment!$A$2:$GZ$2000,0,MATCH("row_id",Enrichment!$A$1:$GZ$1,0)),0),MATCH("email_status",Enrichment!$A$1:$GZ$1,0))&"","")="verified",IFERROR(INDEX(Enrichment!$A$2:$GZ$2000,MATCH($A10,INDEX(Enrichment!$A$2:$GZ$2000,0,MATCH("row_id",Enrichment!$A$1:$GZ$1,0)),0),MATCH("email_status",Enrichment!$A$1:$GZ$1,0))&"","")="unverified"),IFERROR(INDEX(Enrichment!$A$2:$GZ$2000,MATCH($A10,INDEX(Enrichment!$A$2:$GZ$2000,0,MATCH("row_id",Enrichment!$A$1:$GZ$1,0)),0),MATCH("email_status",Enrichment!$A$1:$GZ$1,0))&"",""),"unverified"))) -> none | BE10: pantry or office lead (primary) | BF10: crowd-listed | BG10: The Org (crowd-edited org chart) | BH10: https://theorg.com/org/dashlane/person/caroline-lee | BI10: 2026-10-24 | BJ10: exact | BK10: find Caroline Lee at Dashlane on LinkedIn and paste the profile URL into primary_linkedin_url (this also confirms the name: The Org is crowd-edited and marks it Unverified) | BL10: contact in the target titles named (Workplace Experience Specialist) (crowd-listed on The Org) | BM10: Pamela | BN10: Golden | BO10: SVP, Head of People | BQ10: =IF($A10="","",IFERROR(INDEX(Enrichment!$A$2:$GZ$2000,MATCH($A10,INDEX(Enrichment!$A$2:$GZ$2000,0,MATCH("row_id",Enrichment!$A$1:$GZ$1,0)),0),MATCH("backup_work_email",Enrichment!$A$1:$GZ$1,0))&"","")) | BR10: =IF($A10="","",IF(BQ10="","none",IF(OR(IFERROR(INDEX(Enrichment!$A$2:$GZ$2000,MATCH($A10,INDEX(Enrichment!$A$2:$GZ$2000,0,MATCH("row_id",Enrichment!$A$1:$GZ$1,0)),0),MATCH("backup_email_status",Enrichment!$A$1:$GZ$1,0))&"","")="verified",IFERROR(INDEX(Enrichment!$A$2:$GZ$2000,MATCH($A10,INDEX(Enrichment!$A$2:$GZ$2000,0,MATCH("row_id",Enrichment!$A$1:$GZ$1,0)),0),MATCH("backup_email_status",Enrichment!$A$1:$GZ$1,0))&"","")="unverified"),IFERROR(INDEX(Enrichment!$A$2:$GZ$2000,MATCH($A10,INDEX(Enrichment!$A$2:$GZ$2000,0,MATCH("row_id",Enrichment!$A$1:$GZ$1,0)),0),MATCH("backup_email_status",Enrichment!$A$1:$GZ$1,0))&"",""),"unverified"))) -> none | BS10: pantry or office lead (backup) | BT10: verified-page | BU10: employer's own site | BV10: https://www.dashlane.com/about/leadership | BW10: 2026-10-24 | BX10: adjacent | BY10: find Pamela Golden at Dashlane on LinkedIn and paste the profile URL into backup_linkedin_url; adjacent title: ask who runs the pantry | BZ10: adjacent contact named (SVP, Head of People) | CA10: Tuesday estimate 95 to 133 (low confidence), under 500 staff company-wide, hybrid (days not stated), occupied at a high-confidence address | CB10: linkedin | CC10: Caroline Lee | CD10: 2026-01-17 | CE10: ny_base=likely (The Org gives a New York location, no office attached); title_fit=family (workplace experience). The Org updated 2026-01-17. One name search found no LinkedIn URL. | CF10: likely | CH10: Pamela Golden | CJ10: ny_base=likely; title_fit=variant (head of people). Dashlane's own leadership page (opened 2026-10-24) lists 'Pamela Golden | SVP, Head of People'; the page gives no city. | CK10: likely | CM10: Y | CN10: pass | CO10: passes all hard gates | CP10: company | CQ10: B-C-031 | CR10: https://www.dashlane.com | CS10: software (password management / security) | CT10: 284 | CU10: 319 | CV10: 251-500 | CW10: whole-company | CX10: agree | CY10: https://www.builtinnyc.com/company/dashlane | CZ10: https://www.reveliolabs.com/companies/dashlane/employees | DA10: le500 | DB10: New York | DC10: Y | DD10: unknown | DE10: https://www.linkedin.com/company/dashlane | DF10: 10011 | DG10: 40.739342 | DH10: -73.994287 | DI10: Y | DJ10: 0 | DK10: B-B-013 | DL10: 44 West 18th Street | DM10: https://www.dashlane.com/terms | DN10: 2026-10-23 | DO10: company-site | DP10: https://commercialobserver.com/2019/04/dashlane-lease-44-west-18th-street-forty-four-eighteen-associates/ | DQ10: 2019-04-22 | DS10: high | DU10: N | DX10: unknown | EA10: unknown | EB10: N | EC10: Built In workplace type: Hybrid Workplace; typical time on-site: Flexible; recent job tags: 3 Hybrid | ED10: https://www.builtinnyc.com/company/dashlane/offices | EE10: 2026-10-24 | EF10: 111 | EH10: Y | EI10: 284 (Built In) and 319 (Revelio Labs) staff (whole-company count) x 50% to 100% of them in the New York office (HQ New York; share assumed) x 67% (Partnership for NYC, firms under 500) in on a weekday; capped by 16,625 sf at 125 sf per person (was 95 to 214); central capped at 16,625 sf / 150 sf per person (largest square footage the sources mention at this address; if the company holds more space here, intake corrects it) = 95 to 133, central 111; low confidence; estimate until intake replaces it. | EJ10: estimate until intake replaces it | EK10: 1 | EL10: 72 | EM10: 25 | EN10: 15 | EO10: 7 | EP10: 15 | EQ10: =IF($A10="","",IF(AH10="exact",10,IF(AH10="adjacent",5,0))) -> 0 | ER10: =IF($A10="","",IF(R10="Y",15,0)) -> 0 | ES10: candidate | EV10: 16,625 sf | EW10: https://commercialobserver.com/2019/04/dashlane-lease-44-west-18th-street-forty-four-eighteen-associates/ (opened 2026-10-24): '... behind a password management app of the same name, will move its headquarters to 16,625 square feet at 44 West 18th Street , Commercial Observer has learned. T' | EX10: Terms and privacy pages give Dashlane USA, Inc., 44 West 18th Street, 4th Floor; Built In lists HQ at 44 W 18th Street. Built In shows 284 total employees (Paris and NYC). Same building Hex lists as its prior NYC office. | Assembly 2026-10-24: Review round 3: Built In is an employer-editable profile, so it no longer counts as the independent confirmation of the company's own page. The independent source is now CO 2019-04-22 (opened 2026-10-24): 'signed a 10-year lease for the entire fourth floor' of 44 West 18th Street; Mann Report 2019-10-03 adds the third floor on a second 10-year lease. The row stays high. Review round 2: a second count agrees with the band: Revelio Labs (Dashlane, Inc., HQ New York City): about 319 employees worldwide as of March 2026. Pin moved to frontage at review round 1: the lot-centroid pin failed the block-face test (38 m from W 18 ST but 37 m from W 17 ST); pin moved to frontage: the lot's position along W 18 ST kept, set 21 m from the centreline on the side CSCL gives house number 44 (17 m from the old pin). Tax lot unchanged. New pin: 21 m from W 18 ST, 54 m from W 17 ST. | EZ10: linked from the company's own site (https://www.dashlane.com/, opened 2026-10-24); LinkedIn not opened | FS10: =IF($A10="","",IF(ISNUMBER(MATCH(U10,{"queued","contacted","replied","call_booked","call_done","yes_in_principle","materials_sent"},0)),"Y","N")) -> N | FT10: =IF($A10="","",IF(OR(T10="Y",U10="do_not_contact",AS10&""<>""),"Y","N")) -> N | FU10: =IF($A10="","",IF(AP10&""<>"",AP10&"",$A10)) -> AO-C-031 | FV10: =IF($A10="","",IF(COUNTIFS($FU$2:$FU$1000,FU10,$FS$2:$FS$1000,"Y")+COUNTIFS($FU$2:$FU$1000,FU10,$FT$2:$FT$1000,"Y")>0,"Y","N")) -> N | FW10: =IF($A10="","",IF(AND(U10="new",T10="N",FT10="N",AT10="Y",FV10="N"),"Y","N")) -> N | FX10: =IF($A10="","",IF(FW10<>"Y","N",IF(COUNTIFS($FU$2:$FU$1000,FU10,$FW$2:$FW$1000,"Y",$J$2:$J$1000,">"&J10)+COUNTIFS($FU$2:$FU$1000,FU10,$FW$2:$FW$1000,"Y",$J$2:$J$1000,J10,$GD$2:$GD$1000,"<"&GD10)=0,"Y","N"))) -> N | FY10: =IF($A10="","",IF(AND(FW10="Y",FX10="Y",Y10&""<>""),IF(Y10<=10,"Y","N"),"N")) -> N | FZ10: =IF(FY10="Y",Y10,"") | GA10: =IF($A10="","",IF(AND(I10="walk-in",CN10="pass",U10="new",FT10="N",FV10="N",AQ10<>"Y"),"Y","N")) -> N | GB10: =IF(GA10<>"Y","",IF(COUNTIFS($GA$2:$GA$1000,"Y",$J$2:$J$1000,">"&J10)+COUNTIFS($GA$2:$GA$1000,"Y",$J$2:$J$1000,J10,$GD$2:$GD$1000,"<"&GD10)+1<=25,COUNTIFS($GA$2:$GA$1000,"Y",$J$2:$J$1000,">"&J10)+COUNTIFS($GA$2:$GA$1000,"Y",$J$2:$J$1000,J10,$GD$2:$GD$1000,"<"&GD10)+1,"")) | GC10: =IF(AND(_xlfn.ISFORMULA(C10),_xlfn.ISFORMULA(J10)),"Y","N") -> N | GD10: =ROW()-1 -> 9
A11: AO-C-083 | B11: CompStak | C11: https://compstak.com | D11: compstak.com | E11: 10 | F11: 70.0 | G11: Y | H11: Maxine | I11: Swick | J11: VP, Head of People | L11: pantry or office lead (primary) | M11: crowd-listed | N11: The Org (crowd-edited org chart) | O11: https://theorg.com/org/compstak/person/maxine-swick | P11: 2026-10-24 | Q11: Alyssa | R11: Murrett | S11: VP, Operations | U11: pantry or office lead (backup) | V11: crowd-listed | W11: The Org (crowd-edited org chart) | X11: https://theorg.com/org/compstak/person/alyssa-murrett | Y11: 2026-10-24 | Z11: Alyssa Murrett | AA11: 2023-02-26 | AB11: ny_base=unconfirmed (no location or office on The Org); title_fit=adjacent (operations lead). This The Org record was last updated 2023-02-26 and may be stale. A newer record (https://theorg.com/org/compstak/person/alyssa-m, 'Alyssa M.', 'SVP, Operations & Marketing', updated 2025-06-27) may be the same person; founder to confirm. | AC11: unconfirmed | AE11: 675 Avenue of the Americas | AF11: 4 | AG11: software (commercial real estate data) | AH11: 150 | AI11: https://www.linkedin.com/company/compstak | AJ11: Y | AK11: 40-75 | AL11: Y | AM11: 105 | AN11: low | AO11: hybrid-3 | AP11: AO-C-083 | AQ11: N | AT11: =IF($A11="","",IF(AND(CN11="pass",AQ11<>"Y",C11<>"",OR(AX11<>"Y",AV11="Y")),"Y","N")) -> Y | AU11: =IF($A11="","",_xlfn.TEXTJOIN("; ",TRUE(),IF(CN11<>"pass","gated out",""),IF(AQ11="Y","on hold: "&AR11,""),IF(C11="","no contact named on an opened page",""),IF(AND(AX11="Y",AV11<>"Y"),"Tuesday estimate band "&L11&": founder's call",""))) | AX11: N | AY11: Maxine | AZ11: Swick | BA11: VP, Head of People | BC11: =IF($A11="","",IFERROR(INDEX(Enrichment!$A$2:$GZ$2000,MATCH($A11,INDEX(Enrichment!$A$2:$GZ$2000,0,MATCH("row_id",Enrichment!$A$1:$GZ$1,0)),0),MATCH("work_email",Enrichment!$A$1:$GZ$1,0))&"","")) | BD11: =IF($A11="","",IF(BC11="","none",IF(OR(IFERROR(INDEX(Enrichment!$A$2:$GZ$2000,MATCH($A11,INDEX(Enrichment!$A$2:$GZ$2000,0,MATCH("row_id",Enrichment!$A$1:$GZ$1,0)),0),MATCH("email_status",Enrichment!$A$1:$GZ$1,0))&"","")="verified",IFERROR(INDEX(Enrichment!$A$2:$GZ$2000,MATCH($A11,INDEX(Enrichment!$A$2:$GZ$2000,0,MATCH("row_id",Enrichment!$A$1:$GZ$1,0)),0),MATCH("email_status",Enrichment!$A$1:$GZ$1,0))&"","")="unverified"),IFERROR(INDEX(Enrichment!$A$2:$GZ$2000,MATCH($A11,INDEX(Enrichment!$A$2:$GZ$2000,0,MATCH("row_id",Enrichment!$A$1:$GZ$1,0)),0),MATCH("email_status",Enrichment!$A$1:$GZ$1,0))&"",""),"unverified"))) -> none | BE11: pantry or office lead (primary) | BF11: crowd-listed | BG11: The Org (crowd-edited org chart) | BH11: https://theorg.com/org/compstak/person/maxine-swick | BI11: 2026-10-24 | BJ11: adjacent | BK11: find Maxine Swick at CompStak on LinkedIn and paste the profile URL into primary_linkedin_url (this also confirms the name: The Org is crowd-edited and marks it Unverified); adjacent title: ask who runs the pantry | BL11: adjacent contact named (VP, Head of People) (crowd-listed on The Org) | BM11: Alyssa | BN11: Murrett | BO11: VP, Operations | BQ11: =IF($A11="","",IFERROR(INDEX(Enrichment!$A$2:$GZ$2000,MATCH($A11,INDEX(Enrichment!$A$2:$GZ$2000,0,MATCH("row_id",Enrichment!$A$1:$GZ$1,0)),0),MATCH("backup_work_email",Enrichment!$A$1:$GZ$1,0))&"","")) | BR11: =IF($A11="","",IF(BQ11="","none",IF(OR(IFERROR(INDEX(Enrichment!$A$2:$GZ$2000,MATCH($A11,INDEX(Enrichment!$A$2:$GZ$2000,0,MATCH("row_id",Enrichment!$A$1:$GZ$1,0)),0),MATCH("backup_email_status",Enrichment!$A$1:$GZ$1,0))&"","")="verified",IFERROR(INDEX(Enrichment!$A$2:$GZ$2000,MATCH($A11,INDEX(Enrichment!$A$2:$GZ$2000,0,MATCH("row_id",Enrichment!$A$1:$GZ$1,0)),0),MATCH("backup_email_status",Enrichment!$A$1:$GZ$1,0))&"","")="unverified"),IFERROR(INDEX(Enrichment!$A$2:$GZ$2000,MATCH($A11,INDEX(Enrichment!$A$2:$GZ$2000,0,MATCH("row_id",Enrichment!$A$1:$GZ$1,0)),0),MATCH("backup_email_status",Enrichment!$A$1:$GZ$1,0))&"",""),"unverified"))) -> none | BS11: pantry or office lead (backup) | BT11: crowd-listed | BU11: The Org (crowd-edited org chart) | BV11: https://theorg.com/org/compstak/person/alyssa-murrett | BW11: 2026-10-24 | BX11: adjacent | BY11: find Alyssa Murrett at CompStak on LinkedIn and paste the profile URL into backup_linkedin_url (this also confirms the name: The Org is crowd-edited and marks it Unverified); the source is dated 2023-02-26: check Alyssa still holds the role; check Alyssa works from the New York office; adjacent title: ask who runs the pantry | BZ11: adjacent contact named (VP, Operations) (crowd-listed on The Org) | CA11: Tuesday estimate 50 to 105 (low confidence), under 500 staff company-wide, hybrid 3 days, occupied at a high-confidence address | CB11: linkedin | CC11: Maxine Swick | CD11: 2026-08-12 | CE11: ny_base=confirmed (The Org attaches the role to CompStak's New York HQ office); title_fit=variant (people lead). The Org updated 2026-08-12. CompStak has advertised a part-time New York Office Manager (search results: builtin.com/job/part-time-office-manager/7262140 and jobs.lever.co/compstak, not opened); no name found for that seat. | CF11: confirmed | CH11: Alyssa Murrett | CI11: 2023-02-26 | CJ11: ny_base=unconfirmed (no location or office on The Org); title_fit=adjacent (operations lead). This The Org record was last updated 2023-02-26 and may be stale. A newer record (https://theorg.com/org/compstak/person/alyssa-m, 'Alyssa M.', 'SVP, Operations & Marketing', updated 2025-06-27) may be the same person; founder to confirm. | CK11: unconfirmed | CM11: Y | CN11: pass | CO11: passes all hard gates | CP11: company | CQ11: B-C-083 | CR11: https://compstak.com | CS11: software (commercial real estate data) | CT11: 150 | CU11: 157 | CV11: unknown | CW11: unknown | CX11: disagree | CY11: https://www.builtinnyc.com/company/compstak | CZ11: https://www.reveliolabs.com/companies/compstak/employees | DA11: le500 | DB11: New York | DC11: Y | DD11: unknown | DE11: https://www.linkedin.com/company/compstak | DF11: 10010 | DG11: 40.742014 | DH11: -73.993705 | DI11: Y | DJ11: 0 | DK11: B-B-038 | DL11: Adams Dry Goods / Mattel Building (GFP Real Estate) | DM11: https://compstak.com/about | DN11: 2026-10-24 | DO11: company-site | DP11: https://commercialobserver.com/2022/12/compstak-leases-27k-sf-at-675-avenue-of-the-americas/ | DQ11: 2022-12-20 | DS11: high | DU11: N | DX11: unknown | EA11: unknown | EB11: N | EC11: Built In workplace type: Hybrid Workplace; typical time on-site: 3 days a week; recent job tags: 3 Hybrid | ED11: https://www.builtinnyc.com/company/compstak/offices | EE11: 2026-10-24 | EF11: 72 | EH11: N | EI11: 150 (Built In) and 157 (Revelio Labs) staff (whole-company count) x 50% to 100% of them in the New York office (HQ New York; share assumed) x 67% (Partnership for NYC, firms under 500) in on a weekday = 50 to 105, central 72; low confidence; estimate until intake replaces it. | EJ11: estimate until intake replaces it | EK11: 1 | EL11: 70 | EM11: 25 | EN11: 15 | EO11: 10 | EP11: 15 | EQ11: =IF($A11="","",IF(AH11="exact",10,IF(AH11="adjacent",5,0))) -> 0 | ER11: =IF($A11="","",IF(R11="Y",15,0)) -> 0 | ES11: candidate | EV11: 25,644 sf | EW11: B's sources | EX11: Built In lists HQ at 675 6th Ave, 4th Floor; CO Dec 2022 reported the five-year, 25,644 sf HQ lease (term runs to about 2027). Built In shows 150 total employees. | Assembly 2026-10-24: Review round 1: CompStak's own About page (opened 2026-10-24) prints '675 6th Ave, Floor 4, New York, NY 10010', so the row stays high on its own page plus Built In. The CO 2022-12-20 lease is the older third source. Review round 3: Built In is an employer-editable profile, so it no longer counts as the independent confirmation of the company's own page. The independent source is now CO 2022-12-20 (opened 2026-10-24): 'signed a five-year lease to relocate its global headquarters to 25,644 square feet at 675 Avenue of the Americas'. The row stays high. Review round 2: band changed from 76-150 to unknown. Sources disagree: Built In shows 150 (76-150) and Revelio Labs (CompStak, Inc., HQ New York City): about 157 employees worldwide as of March 2026 (151-250). Band left unknown; founder to confirm at intake. Review round 2: corner lot: the lot-centroid pin sat 39 m from W 21 ST but 46 m from AVE OF THE AMERICAS, so it was moved to the AVE OF THE AMERICAS frontage near the corner (18 m from the AVE OF THE AMERICAS centreline, 39 m from W 21 ST; 28 m from the old pin). Tax lot unchanged. | EZ11: linked from the company's own site (https://compstak.com/, opened 2026-10-24); LinkedIn not opened | FS11: =IF($A11="","",IF(ISNUMBER(MATCH(U11,{"queued","contacted","replied","call_booked","call_done","yes_in_principle","materials_sent"},0)),"Y","N")) -> N | FT11: =IF($A11="","",IF(OR(T11="Y",U11="do_not_contact",AS11&""<>""),"Y","N")) -> N | FU11: =IF($A11="","",IF(AP11&""<>"",AP11&"",$A11)) -> AO-C-083 | FV11: =IF($A11="","",IF(COUNTIFS($FU$2:$FU$1000,FU11,$FS$2:$FS$1000,"Y")+COUNTIFS($FU$2:$FU$1000,FU11,$FT$2:$FT$1000,"Y")>0,"Y","N")) -> N | FW11: =IF($A11="","",IF(AND(U11="new",T11="N",FT11="N",AT11="Y",FV11="N"),"Y","N")) -> N | FX11: =IF($A11="","",IF(FW11<>"Y","N",IF(COUNTIFS($FU$2:$FU$1000,FU11,$FW$2:$FW$1000,"Y",$J$2:$J$1000,">"&J11)+COUNTIFS($FU$2:$FU$1000,FU11,$FW$2:$FW$1000,"Y",$J$2:$J$1000,J11,$GD$2:$GD$1000,"<"&GD11)=0,"Y","N"))) -> N | FY11: =IF($A11="","",IF(AND(FW11="Y",FX11="Y",Y11&""<>""),IF(Y11<=10,"Y","N"),"N")) -> N | FZ11: =IF(FY11="Y",Y11,"") | GA11: =IF($A11="","",IF(AND(I11="walk-in",CN11="pass",U11="new",FT11="N",FV11="N",AQ11<>"Y"),"Y","N")) -> N | GB11: =IF(GA11<>"Y","",IF(COUNTIFS($GA$2:$GA$1000,"Y",$J$2:$J$1000,">"&J11)+COUNTIFS($GA$2:$GA$1000,"Y",$J$2:$J$1000,J11,$GD$2:$GD$1000,"<"&GD11)+1<=25,COUNTIFS($GA$2:$GA$1000,"Y",$J$2:$J$1000,">"&J11)+COUNTIFS($GA$2:$GA$1000,"Y",$J$2:$J$1000,J11,$GD$2:$GD$1000,"<"&GD11)+1,"")) | GC11: =IF(AND(_xlfn.ISFORMULA(C11),_xlfn.ISFORMULA(J11)),"Y","N") -> N | GD11: =ROW()-1 -> 10
A12: AO-C-052 | B12: Bombas | C12: https://bombas.com | D12: bombas.com | E12: 11 | F12: 70.0 | G12: Y | H12: Carlos | I12: Arellano | J12: Workplace Coordinator | L12: pantry or office lead (primary) | M12: crowd-listed | N12: The Org (crowd-edited org chart) | O12: https://theorg.com/org/bombas/person/carlos-arellano | P12: 2026-10-24 | Q12: Melissa | R12: King | S12: Executive Assistant | U12: pantry or office lead (backup) | V12: crowd-listed | W12: The Org (crowd-edited org chart) | X12: https://theorg.com/org/bombas/person/melissa-king | Y12: 2026-10-24 | Z12: Melissa King | AA12: 2025-05-15 | AB12: ny_base=confirmed (The Org attaches the role to the 881 Broadway HQ office); title_fit=variant (The Org shows her reporting to the CEO, Jason Larose). The Org updated 2025-05-15. Alternate: Timothy Meola, Executive Assistant, also reporting to the CEO (https://theorg.com/org/bombas/person/timothy-meola). | AC12: confirmed | AE12: 881 Broadway | AF12: 2 | AG12: apparel brand (socks and basics) | AH12: 223 | AI12: unknown | AJ12: Y | AK12: 76-150 | AL12: Y | AM12: 203 | AN12: low | AO12: in-office-5 | AP12: AO-C-052 | AQ12: N | AT12: =IF($A12="","",IF(AND(CN12="pass",AQ12<>"Y",C12<>"",OR(AX12<>"Y",AV12="Y")),"Y","N")) -> Y | AU12: =IF($A12="","",_xlfn.TEXTJOIN("; ",TRUE(),IF(CN12<>"pass","gated out",""),IF(AQ12="Y","on hold: "&AR12,""),IF(C12="","no contact named on an opened page",""),IF(AND(AX12="Y",AV12<>"Y"),"Tuesday estimate band "&L12&": founder's call",""))) | AX12: N | AY12: Carlos | AZ12: Arellano | BA12: Workplace Coordinator | BC12: =IF($A12="","",IFERROR(INDEX(Enrichment!$A$2:$GZ$2000,MATCH($A12,INDEX(Enrichment!$A$2:$GZ$2000,0,MATCH("row_id",Enrichment!$A$1:$GZ$1,0)),0),MATCH("work_email",Enrichment!$A$1:$GZ$1,0))&"","")) | BD12: =IF($A12="","",IF(BC12="","none",IF(OR(IFERROR(INDEX(Enrichment!$A$2:$GZ$2000,MATCH($A12,INDEX(Enrichment!$A$2:$GZ$2000,0,MATCH("row_id",Enrichment!$A$1:$GZ$1,0)),0),MATCH("email_status",Enrichment!$A$1:$GZ$1,0))&"","")="verified",IFERROR(INDEX(Enrichment!$A$2:$GZ$2000,MATCH($A12,INDEX(Enrichment!$A$2:$GZ$2000,0,MATCH("row_id",Enrichment!$A$1:$GZ$1,0)),0),MATCH("email_status",Enrichment!$A$1:$GZ$1,0))&"","")="unverified"),IFERROR(INDEX(Enrichment!$A$2:$GZ$2000,MATCH($A12,INDEX(Enrichment!$A$2:$GZ$2000,0,MATCH("row_id",Enrichment!$A$1:$GZ$1,0)),0),MATCH("email_status",Enrichment!$A$1:$GZ$1,0))&"",""),"unverified"))) -> none | BE12: pantry or office lead (primary) | BF12: crowd-listed | BG12: The Org (crowd-edited org chart) | BH12: https://theorg.com/org/bombas/person/carlos-arellano | BI12: 2026-10-24 | BJ12: exact | BK12: find Carlos Arellano at Bombas on LinkedIn and paste the profile URL into primary_linkedin_url (this also confirms the name: The Org is crowd-edited and marks it Unverified); the source is dated 2024-11-14: check Carlos still holds the role | BL12: contact in the target titles named (Workplace Coordinator) (crowd-listed on The Org) | BM12: Melissa | BN12: King | BO12: Executive Assistant | BQ12: =IF($A12="","",IFERROR(INDEX(Enrichment!$A$2:$GZ$2000,MATCH($A12,INDEX(Enrichment!$A$2:$GZ$2000,0,MATCH("row_id",Enrichment!$A$1:$GZ$1,0)),0),MATCH("backup_work_email",Enrichment!$A$1:$GZ$1,0))&"","")) | BR12: =IF($A12="","",IF(BQ12="","none",IF(OR(IFERROR(INDEX(Enrichment!$A$2:$GZ$2000,MATCH($A12,INDEX(Enrichment!$A$2:$GZ$2000,0,MATCH("row_id",Enrichment!$A$1:$GZ$1,0)),0),MATCH("backup_email_status",Enrichment!$A$1:$GZ$1,0))&"","")="verified",IFERROR(INDEX(Enrichment!$A$2:$GZ$2000,MATCH($A12,INDEX(Enrichment!$A$2:$GZ$2000,0,MATCH("row_id",Enrichment!$A$1:$GZ$1,0)),0),MATCH("backup_email_status",Enrichment!$A$1:$GZ$1,0))&"","")="unverified"),IFERROR(INDEX(Enrichment!$A$2:$GZ$2000,MATCH($A12,INDEX(Enrichment!$A$2:$GZ$2000,0,MATCH("row_id",Enrichment!$A$1:$GZ$1,0)),0),MATCH("backup_email_status",Enrichment!$A$1:$GZ$1,0))&"",""),"unverified"))) -> none | BS12: pantry or office lead (backup) | BT12: crowd-listed | BU12: The Org (crowd-edited org chart) | BV12: https://theorg.com/org/bombas/person/melissa-king | BW12: 2026-10-24 | BX12: adjacent | BY12: find Melissa King at Bombas on LinkedIn and paste the profile URL into backup_linkedin_url (this also confirms the name: The Org is crowd-edited and marks it Unverified); the source is dated 2025-05-15: check Melissa still holds the role; adjacent title: ask who runs the pantry | BZ12: adjacent contact named (Executive Assistant) (crowd-listed on The Org) | CA12: Tuesday estimate 75 to 203 (low confidence), under 500 staff company-wide, on-site 5 days a week per its profile, occupancy-unconfirmed at a low-confidence address | CB12: linkedin | CC12: Carlos Arellano | CD12: 2024-11-14 | CE12: ny_base=likely (The Org gives a New York location, no office attached); title_fit=variant (workplace coordinator). The Org updated 2024-11-14, so the role may be stale: founder to confirm. | CF12: likely | CH12: Melissa King | CI12: 2025-05-15 | CJ12: ny_base=confirmed (The Org attaches the role to the 881 Broadway HQ office); title_fit=variant (The Org shows her reporting to the CEO, Jason Larose). The Org updated 2025-05-15. Alternate: Timothy Meola, Executive Assistant, also reporting to the CEO (https://theorg.com/org/bombas/person/timothy-meola). | CK12: confirmed | CM12: Y | CN12: pass | CO12: passes all hard gates | CP12: company | CQ12: B-C-052 | CR12: https://bombas.com | CS12: apparel brand (socks and basics) | CT12: 223 | CU12: 303 | CV12: unknown | CW12: unknown | CX12: disagree | CY12: https://www.builtinnyc.com/company/bombas | CZ12: https://www.reveliolabs.com/companies/bombas/employees | DA12: le500 | DB12: New York | DC12: Y | DD12: unknown | DE12: unknown | DF12: 10003 | DG12: 40.738311 | DH12: -73.990185 | DI12: Y | DJ12: 0 | DK12: B-B-023 | DL12: 115 Fifth Avenue / 881 Broadway (Arnold Constable block) | DM12: https://www.builtinnyc.com/company/bombas/offices | DN12: 2026-10-23 | DO12: builtin | DP12: https://commercialobserver.com/2019/04/bombas-lease-881-broadway-the-winter-organization/ | DQ12: 2019-04-10 | DS12: low | DU12: N | DX12: security desk | DY12: https://www.metro-manhattan.com/buildings/115-fifth-avenue/ | EA12: unknown | EB12: N | EC12: Built In workplace type: OnSite Workplace; typical time on-site: 5 days a week; recent job tags: 3 In-Office | ED12: https://www.builtinnyc.com/company/bombas/offices | EE12: 2026-10-24 | EF12: 123 | EH12: N | EI12: 223 (Built In) and 303 (Revelio Labs) staff (whole-company count) x 50% to 100% of them in the New York office (HQ New York; share assumed) x 67% (Partnership for NYC, firms under 500) in on a weekday = 75 to 203, central 123; low confidence; estimate until intake replaces it. | EJ12: estimate until intake replaces it | EK12: 1 | EL12: 70 | EM12: 25 | EN12: 15 | EO12: 15 | EP12: 5 | EQ12: =IF($A12="","",IF(AH12="exact",10,IF(AH12="adjacent",5,0))) -> 0 | ER12: =IF($A12="","",IF(R12="Y",15,0)) -> 0 | ES12: candidate | EV12: 33,300 sf | EW12: B's sources | EX12: Built In (opened 2026-10-23) lists HQ at 881 Broadway, which shares tax lot 1008470062 with 115 Fifth Avenue. CO Apr 2019 reported a 10-year lease of the entire 2nd floor (33,300 sf), running to about 2029. Company site returned HTTP 429 to our fetches. Built In shows 223 total employees. Consumer brand. | Assembly 2026-10-24: Review round 1: lowered from high to medium. Built In is undated and the CO lease is 2019-04-10; bombas.com returned HTTP 429 again on 2026-10-24. Confidence lowered at assembly from medium to low: review round 2: the only source dated within 24 months is an undated third-party profile (Built In, Deskpass or LiquidSpace), which can only confirm a dated or own-site source. Review round 3: lease status set from occupied to occupancy-unconfirmed: only an undated profile places it here (Built In, Deskpass or LiquidSpace), and B treats such profiles as often stale. Check the lobby directory on the walk. Review round 2: band changed from 151-250 to unknown. Sources disagree: Built In shows 223 (151-250) and Revelio Labs (Bombas LLC, HQ New York City): about 303 employees worldwide as of March 2026 (251-500). Band left unknown; founder to confirm at intake. Review round 2: corner lot: the lot-centroid pin sat 21 m from E 19 ST but 57 m from BROADWAY, so it was moved to the BROADWAY frontage near the corner (15 m from the BROADWAY centreline, 26 m from E 19 ST; 46 m from the old pin). Tax lot unchanged. | FS12: =IF($A12="","",IF(ISNUMBER(MATCH(U12,{"queued","contacted","replied","call_booked","call_done","yes_in_principle","materials_sent"},0)),"Y","N")) -> N | FT12: =IF($A12="","",IF(OR(T12="Y",U12="do_not_contact",AS12&""<>""),"Y","N")) -> N | FU12: =IF($A12="","",IF(AP12&""<>"",AP12&"",$A12)) -> AO-C-052 | FV12: =IF($A12="","",IF(COUNTIFS($FU$2:$FU$1000,FU12,$FS$2:$FS$1000,"Y")+COUNTIFS($FU$2:$FU$1000,FU12,$FT$2:$FT$1000,"Y")>0,"Y","N")) -> N | FW12: =IF($A12="","",IF(AND(U12="new",T12="N",FT12="N",AT12="Y",FV12="N"),"Y","N")) -> N | FX12: =IF($A12="","",IF(FW12<>"Y","N",IF(COUNTIFS($FU$2:$FU$1000,FU12,$FW$2:$FW$1000,"Y",$J$2:$J$1000,">"&J12)+COUNTIFS($FU$2:$FU$1000,FU12,$FW$2:$FW$1000,"Y",$J$2:$J$1000,J12,$GD$2:$GD$1000,"<"&GD12)=0,"Y","N"))) -> N | FY12: =IF($A12="","",IF(AND(FW12="Y",FX12="Y",Y12&""<>""),IF(Y12<=10,"Y","N"),"N")) -> N | FZ12: =IF(FY12="Y",Y12,"") | GA12: =IF($A12="","",IF(AND(I12="walk-in",CN12="pass",U12="new",FT12="N",FV12="N",AQ12<>"Y"),"Y","N")) -> N | GB12: =IF(GA12<>"Y","",IF(COUNTIFS($GA$2:$GA$1000,"Y",$J$2:$J$1000,">"&J12)+COUNTIFS($GA$2:$GA$1000,"Y",$J$2:$J$1000,J12,$GD$2:$GD$1000,"<"&GD12)+1<=25,COUNTIFS($GA$2:$GA$1000,"Y",$J$2:$J$1000,">"&J12)+COUNTIFS($GA$2:$GA$1000,"Y",$J$2:$J$1000,J12,$GD$2:$GD$1000,"<"&GD12)+1,"")) | GC12: =IF(AND(_xlfn.ISFORMULA(C12),_xlfn.ISFORMULA(J12)),"Y","N") -> N | GD12: =ROW()-1 -> 11
A13: AO-C-096 | B13: Inspiren | C13: https://www.inspiren.com/ | D13: inspiren.com | E13: 12 | F13: 67.0 | G13: Y | H13: Jared | I13: Zimmer | J13: Chief of Staff to CCO | L13: pantry or office lead (primary) | M13: crowd-listed | N13: The Org (crowd-edited org chart) | O13: https://theorg.com/org/inspiren/person/jared-zimmer | P13: 2026-10-24 | V13: none | AE13: 61 West 23rd Street | AF13: full floor (floor number not stated) | AG13: Healthcare technology (AI for senior living) | AH13: 150 | AI13: https://www.linkedin.com/company/inspirenhealth | AJ13: Y | AK13: 40-75 | AL13: Y | AM13: 67 | AN13: low | AO13: hybrid-unspecified | AP13: AO-C-096 | AQ13: N | AT13: =IF($A13="","",IF(AND(CN13="pass",AQ13<>"Y",C13<>"",OR(AX13<>"Y",AV13="Y")),"Y","N")) -> Y | AU13: =IF($A13="","",_xlfn.TEXTJOIN("; ",TRUE(),IF(CN13<>"pass","gated out",""),IF(AQ13="Y","on hold: "&AR13,""),IF(C13="","no contact named on an opened page",""),IF(AND(AX13="Y",AV13<>"Y"),"Tuesday estimate band "&L13&": founder's call",""))) | AX13: N | AY13: Jared | AZ13: Zimmer | BA13: Chief of Staff to CCO | BC13: =IF($A13="","",IFERROR(INDEX(Enrichment!$A$2:$GZ$2000,MATCH($A13,INDEX(Enrichment!$A$2:$GZ$2000,0,MATCH("row_id",Enrichment!$A$1:$GZ$1,0)),0),MATCH("work_email",Enrichment!$A$1:$GZ$1,0))&"","")) | BD13: =IF($A13="","",IF(BC13="","none",IF(OR(IFERROR(INDEX(Enrichment!$A$2:$GZ$2000,MATCH($A13,INDEX(Enrichment!$A$2:$GZ$2000,0,MATCH("row_id",Enrichment!$A$1:$GZ$1,0)),0),MATCH("email_status",Enrichment!$A$1:$GZ$1,0))&"","")="verified",IFERROR(INDEX(Enrichment!$A$2:$GZ$2000,MATCH($A13,INDEX(Enrichment!$A$2:$GZ$2000,0,MATCH("row_id",Enrichment!$A$1:$GZ$1,0)),0),MATCH("email_status",Enrichment!$A$1:$GZ$1,0))&"","")="unverified"),IFERROR(INDEX(Enrichment!$A$2:$GZ$2000,MATCH($A13,INDEX(Enrichment!$A$2:$GZ$2000,0,MATCH("row_id",Enrichment!$A$1:$GZ$1,0)),0),MATCH("email_status",Enrichment!$A$1:$GZ$1,0))&"",""),"unverified"))) -> none | BE13: pantry or office lead (primary) | BF13: crowd-listed | BG13: The Org (crowd-edited org chart) | BH13: https://theorg.com/org/inspiren/person/jared-zimmer | BI13: 2026-10-24 | BJ13: adjacent | BK13: find Jared Zimmer at Inspiren on LinkedIn and paste the profile URL into primary_linkedin_url (this also confirms the name: The Org is crowd-edited and marks it Unverified); adjacent title: ask who runs the pantry | BL13: adjacent contact named (Chief of Staff to CCO) (crowd-listed on The Org) | BQ13: =IF($A13="","",IFERROR(INDEX(Enrichment!$A$2:$GZ$2000,MATCH($A13,INDEX(Enrichment!$A$2:$GZ$2000,0,MATCH("row_id",Enrichment!$A$1:$GZ$1,0)),0),MATCH("backup_work_email",Enrichment!$A$1:$GZ$1,0))&"","")) | BR13: =IF($A13="","",IF(BQ13="","none",IF(OR(IFERROR(INDEX(Enrichment!$A$2:$GZ$2000,MATCH($A13,INDEX(Enrichment!$A$2:$GZ$2000,0,MATCH("row_id",Enrichment!$A$1:$GZ$1,0)),0),MATCH("backup_email_status",Enrichment!$A$1:$GZ$1,0))&"","")="verified",IFERROR(INDEX(Enrichment!$A$2:$GZ$2000,MATCH($A13,INDEX(Enrichment!$A$2:$GZ$2000,0,MATCH("row_id",Enrichment!$A$1:$GZ$1,0)),0),MATCH("backup_email_status",Enrichment!$A$1:$GZ$1,0))&"","")="unverified"),IFERROR(INDEX(Enrichment!$A$2:$GZ$2000,MATCH($A13,INDEX(Enrichment!$A$2:$GZ$2000,0,MATCH("row_id",Enrichment!$A$1:$GZ$1,0)),0),MATCH("backup_email_status",Enrichment!$A$1:$GZ$1,0))&"",""),"unverified"))) -> none | BT13: none | BX13: none | BY13: no backup named: back to research | BZ13: no backup contact named | CA13: Tuesday estimate 50 to 67 (low confidence), under 500 staff company-wide, hybrid (days not stated), occupied at a high-confidence address | CB13: linkedin | CC13: Jared Zimmer | CD13: 2026-03-09 | CE13: ny_base=likely (The Org gives a New York location, no office attached); title_fit=adjacent (chief of staff at a small firm, but to the chief commercial officer, not the CEO). The Org updated 2026-03-09. Inspiren's HR coordinator on The Org is not placed in New York. | CF13: likely | CM13: Y | CN13: pass | CO13: passes all hard gates | CP13: company | CQ13: B-C-096 | CR13: https://www.inspiren.com/ | CS13: Healthcare technology (AI for senior living) | CT13: 150 | CV13: 76-150 | CW13: whole-company | CX13: single-source | CY13: https://www.builtinnyc.com/company/inspiren/offices | DA13: le500 | DB13: New York | DC13: Y | DD13: unknown | DE13: https://www.linkedin.com/company/inspirenhealth | DF13: 10010 | DG13: 40.742771 | DH13: -73.991782 | DI13: Y | DJ13: 0 | DK13: B-B-047 | DL13: 61 West 23rd Street (Zegna family; Taconic development partner) | DM13: https://commercialobserver.com/2026/09/normal-computing-inspiren-leases-61-west-23rd-street/ | DN13: 2026-09-21 | DO13: leasing-press | DP13: https://www.builtinnyc.com/company/inspiren/offices | DQ13: 2026-10-23 | DS13: high | DU13: N | DX13: unknown | EA13: unknown | EB13: N | EC13: Built In workplace type: Hybrid Workplace; typical time on-site: Flexible; recent job tags: 3 In-Office | ED13: https://www.builtinnyc.com/company/inspiren/offices | EE13: 2026-10-24 | EF13: 56 | EH13: Y | EI13: 150 (Built In) staff (whole-company count) x 50% to 100% of them in the New York office (HQ New York; share assumed) x 67% (Partnership for NYC, firms under 500) in on a weekday; capped by 8,367 sf at 125 sf per person (was 50 to 100); central capped at 8,367 sf / 150 sf per person (largest square footage the sources mention at this address; if the company holds more space here, intake corrects it) = 50 to 67, central 56; low confidence; estimate until intake replaces it. | EJ13: estimate until intake replaces it | EK13: 1 | EL13: 67 | EM13: 25 | EN13: 15 | EO13: 7 | EP13: 15 | EQ13: =IF($A13="","",IF(AH13="exact",10,IF(AH13="adjacent",5,0))) -> 0 | ER13: =IF($A13="","",IF(R13="Y",15,0)) -> 0 | ES13: candidate | EV13: 8,367 sf | EW13: B's sources | EX13: CO: moved into 8,367 sf in early Sept 2026, first permanent NYC office (previously Brooklyn Navy Yard). Built In lists HQ 61 W 23rd St and 150 total employees (live profile, undated). | EZ13: linked from the company's own site (https://www.inspiren.com/, opened 2026-10-24); LinkedIn not opened | FS13: =IF($A13="","",IF(ISNUMBER(MATCH(U13,{"queued","contacted","replied","call_booked","call_done","yes_in_principle","materials_sent"},0)),"Y","N")) -> N | FT13: =IF($A13="","",IF(OR(T13="Y",U13="do_not_contact",AS13&""<>""),"Y","N")) -> N | FU13: =IF($A13="","",IF(AP13&""<>"",AP13&"",$A13)) -> AO-C-096 | FV13: =IF($A13="","",IF(COUNTIFS($FU$2:$FU$1000,FU13,$FS$2:$FS$1000,"Y")+COUNTIFS($FU$2:$FU$1000,FU13,$FT$2:$FT$1000,"Y")>0,"Y","N")) -> N | FW13: =IF($A13="","",IF(AND(U13="new",T13="N",FT13="N",AT13="Y",FV13="N"),"Y","N")) -> N | FX13: =IF($A13="","",IF(FW13<>"Y","N",IF(COUNTIFS($FU$2:$FU$1000,FU13,$FW$2:$FW$1000,"Y",$J$2:$J$1000,">"&J13)+COUNTIFS($FU$2:$FU$1000,FU13,$FW$2:$FW$1000,"Y",$J$2:$J$1000,J13,$GD$2:$GD$1000,"<"&GD13)=0,"Y","N"))) -> N | FY13: =IF($A13="","",IF(AND(FW13="Y",FX13="Y",Y13&""<>""),IF(Y13<=10,"Y","N"),"N")) -> N | FZ13: =IF(FY13="Y",Y13,"") | GA13: =IF($A13="","",IF(AND(I13="walk-in",CN13="pass",U13="new",FT13="N",FV13="N",AQ13<>"Y"),"Y","N")) -> N | GB13: =IF(GA13<>"Y","",IF(COUNTIFS($GA$2:$GA$1000,"Y",$J$2:$J$1000,">"&J13)+COUNTIFS($GA$2:$GA$1000,"Y",$J$2:$J$1000,J13,$GD$2:$GD$1000,"<"&GD13)+1<=25,COUNTIFS($GA$2:$GA$1000,"Y",$J$2:$J$1000,">"&J13)+COUNTIFS($GA$2:$GA$1000,"Y",$J$2:$J$1000,J13,$GD$2:$GD$1000,"<"&GD13)+1,"")) | GC13: =IF(AND(_xlfn.ISFORMULA(C13),_xlfn.ISFORMULA(J13)),"Y","N") -> N | GD13: =ROW()-1 -> 12
A14: AO-C-038 | B14: Stellar Health | C14: https://www.stellarhealth.net | D14: stellarhealth.net | E14: 13 | F14: 67.0 | G14: Y | H14: Stavroula | I14: Zimaras | J14: Chief of Staff to CEO | L14: pantry or office lead (primary) | M14: crowd-listed | N14: The Org (crowd-edited org chart) | O14: https://theorg.com/org/stellar-health/person/stavroula-zimaras | P14: 2026-10-24 | Q14: Paul | R14: Savary | S14: Director HR Business Partner | U14: pantry or office lead (backup) | V14: crowd-listed | W14: The Org (crowd-edited org chart) | X14: https://theorg.com/org/stellar-health/person/paul-savary-1 | Y14: 2026-10-24 | Z14: Paul Savary | AA14: 2026-09-19 | AB14: ny_base=likely (The Org gives a New York location, no office attached); title_fit=variant (HR). The Org updated 2026-09-19. Alternate: Katy Huber, Chief Human Resources Officer (https://theorg.com/org/stellar-health/person/katy-huber, NY HQ office, but last updated 2024-10-29). | AC14: likely | AE14: 215 Park Avenue South | AF14: unknown | AG14: health tech (value-based care software) | AH14: 165 | AI14: unknown | AJ14: Y | AK14: 76-150 | AL14: Y | AM14: 126 | AN14: low | AO14: hybrid-unspecified | AP14: AO-C-038 | AQ14: N | AT14: =IF($A14="","",IF(AND(CN14="pass",AQ14<>"Y",C14<>"",OR(AX14<>"Y",AV14="Y")),"Y","N")) -> Y | AU14: =IF($A14="","",_xlfn.TEXTJOIN("; ",TRUE(),IF(CN14<>"pass","gated out",""),IF(AQ14="Y","on hold: "&AR14,""),IF(C14="","no contact named on an opened page",""),IF(AND(AX14="Y",AV14<>"Y"),"Tuesday estimate band "&L14&": founder's call",""))) | AX14: N | AY14: Stavroula | AZ14: Zimaras | BA14: Chief of Staff to CEO | BC14: =IF($A14="","",IFERROR(INDEX(Enrichment!$A$2:$GZ$2000,MATCH($A14,INDEX(Enrichment!$A$2:$GZ$2000,0,MATCH("row_id",Enrichment!$A$1:$GZ$1,0)),0),MATCH("work_email",Enrichment!$A$1:$GZ$1,0))&"","")) | BD14: =IF($A14="","",IF(BC14="","none",IF(OR(IFERROR(INDEX(Enrichment!$A$2:$GZ$2000,MATCH($A14,INDEX(Enrichment!$A$2:$GZ$2000,0,MATCH("row_id",Enrichment!$A$1:$GZ$1,0)),0),MATCH("email_status",Enrichment!$A$1:$GZ$1,0))&"","")="verified",IFERROR(INDEX(Enrichment!$A$2:$GZ$2000,MATCH($A14,INDEX(Enrichment!$A$2:$GZ$2000,0,MATCH("row_id",Enrichment!$A$1:$GZ$1,0)),0),MATCH("email_status",Enrichment!$A$1:$GZ$1,0))&"","")="unverified"),IFERROR(INDEX(Enrichment!$A$2:$GZ$2000,MATCH($A14,INDEX(Enrichment!$A$2:$GZ$2000,0,MATCH("row_id",Enrichment!$A$1:$GZ$1,0)),0),MATCH("email_status",Enrichment!$A$1:$GZ$1,0))&"",""),"unverified"))) -> none | BE14: pantry or office lead (primary) | BF14: crowd-listed | BG14: The Org (crowd-edited org chart) | BH14: https://theorg.com/org/stellar-health/person/stavroula-zimaras | BI14: 2026-10-24 | BJ14: adjacent | BK14: find Stavroula Zimaras at Stellar Health on LinkedIn and paste the profile URL into primary_linkedin_url (this also confirms the name: The Org is crowd-edited and marks it Unverified); adjacent title: ask who runs the pantry | BL14: adjacent contact named (Chief of Staff to CEO) (crowd-listed on The Org) | BM14: Paul | BN14: Savary | BO14: Director HR Business Partner | BQ14: =IF($A14="","",IFERROR(INDEX(Enrichment!$A$2:$GZ$2000,MATCH($A14,INDEX(Enrichment!$A$2:$GZ$2000,0,MATCH("row_id",Enrichment!$A$1:$GZ$1,0)),0),MATCH("backup_work_email",Enrichment!$A$1:$GZ$1,0))&"","")) | BR14: =IF($A14="","",IF(BQ14="","none",IF(OR(IFERROR(INDEX(Enrichment!$A$2:$GZ$2000,MATCH($A14,INDEX(Enrichment!$A$2:$GZ$2000,0,MATCH("row_id",Enrichment!$A$1:$GZ$1,0)),0),MATCH("backup_email_status",Enrichment!$A$1:$GZ$1,0))&"","")="verified",IFERROR(INDEX(Enrichment!$A$2:$GZ$2000,MATCH($A14,INDEX(Enrichment!$A$2:$GZ$2000,0,MATCH("row_id",Enrichment!$A$1:$GZ$1,0)),0),MATCH("backup_email_status",Enrichment!$A$1:$GZ$1,0))&"","")="unverified"),IFERROR(INDEX(Enrichment!$A$2:$GZ$2000,MATCH($A14,INDEX(Enrichment!$A$2:$GZ$2000,0,MATCH("row_id",Enrichment!$A$1:$GZ$1,0)),0),MATCH("backup_email_status",Enrichment!$A$1:$GZ$1,0))&"",""),"unverified"))) -> none | BS14: pantry or office lead (backup) | BT14: crowd-listed | BU14: The Org (crowd-edited org chart) | BV14: https://theorg.com/org/stellar-health/person/paul-savary-1 | BW14: 2026-10-24 | BX14: adjacent | BY14: find Paul Savary at Stellar Health on LinkedIn and paste the profile URL into backup_linkedin_url (this also confirms the name: The Org is crowd-edited and marks it Unverified); adjacent title: ask who runs the pantry | BZ14: adjacent contact named (Director HR Business Partner) (crowd-listed on The Org) | CA14: Tuesday estimate 55 to 126 (low confidence), under 500 staff company-wide, hybrid (days not stated), occupied at a high-confidence address | CB14: linkedin | CC14: Stavroula Zimaras | CD14: 2026-06-30 | CE14: ny_base=confirmed (The Org attaches the role to Stellar Health's New York HQ office; that record shows 127 West 26th Street while B has 215 Park Avenue South); title_fit=variant (chief of staff to the CEO at a 76-150 office). The Org updated 2026-06-30. | CF14: confirmed | CH14: Paul Savary | CI14: 2026-09-19 | CJ14: ny_base=likely (The Org gives a New York location, no office attached); title_fit=variant (HR). The Org updated 2026-09-19. Alternate: Katy Huber, Chief Human Resources Officer (https://theorg.com/org/stellar-health/person/katy-huber, NY HQ office, but last updated 2024-10-29). | CK14: likely | CM14: Y | CN14: pass | CO14: passes all hard gates | CP14: company | CQ14: B-C-038 | CR14: https://www.stellarhealth.net | CS14: health tech (value-based care software) | CT14: 165 | CU14: 188 | CV14: 151-250 | CW14: whole-company | CX14: agree | CY14: https://www.builtinnyc.com/company/stellar-health | CZ14: https://www.reveliolabs.com/companies/stellar-health-group/employees | DA14: le500 | DB14: New York | DC14: Y | DD14: unknown | DE14: unknown | DF14: 10003 | DG14: 40.73686 | DH14: -73.988546 | DI14: Y | DJ14: 0 | DK14: B-B-016 | DL14: 215 Park Avenue South (SL Green managed) | DM14: https://www.sec.gov/Archives/edgar/data/1013454/000153949726000704/n5676_x5-424h.htm | DN14: 2026-02 | DO14: other | DP14: https://www.nyrej.com/sl-green-signs-29-915-s-f-lease-with-nayya-health-at-215-park-ave-south | DQ14: 2024-12-10 | DR14: cites a sec.gov filing: agents do not open it (EDGAR demands a contact email); the founder may open it in a browser | DS14: high | DU14: N | DX14: security desk | DY14: https://www.metro-manhattan.com/buildings/215-park-avenue-south/ | EA14: unknown | EB14: N | EC14: Built In workplace type: Hybrid Workplace; typical time on-site: Not Specified | ED14: https://www.builtinnyc.com/company/stellar-health/offices | EE14: 2026-10-24 | EF14: 83 | EH14: N | EI14: 165 (Built In) and 188 (Revelio Labs) staff (whole-company count) x 50% to 100% of them in the New York office (HQ New York; share assumed) x 67% (Partnership for NYC, firms under 500) in on a weekday = 55 to 126, central 83; low confidence; estimate until intake replaces it. | EJ14: estimate until intake replaces it | EK14: 1 | EL14: 67 | EM14: 25 | EN14: 15 | EO14: 7 | EP14: 15 | EQ14: =IF($A14="","",IF(AH14="exact",10,IF(AH14="adjacent",5,0))) -> 0 | ER14: =IF($A14="","",IF(R14="Y",15,0)) -> 0 | ES14: candidate | EV14: 33,224 sf | EW14: B's sources | EX14: SEC rent roll 2026-02-05: The Stellar Health Group, Inc. 33,224 sf over two floors, lease to 2030-12-31; it subleases its 16th floor to Cognitiv, so it occupies one floor (floor number not stated). NYREJ 2024-12 lists Stellar Health Group as a tenant. Built In NYC: 165 total employees, HQ New York. | Assembly 2026-10-24: SEC EDGAR source (sec.gov): this agent will not re-open it, because EDGAR serves only requests that carry a contact email and the project rule forbids sending one; the founder may open it in a browser. Review round 2: a second count agrees with the band: Revelio Labs (The Stellar Health Group, Inc., HQ New York City): about 188 employees worldwide as of March 2026. Review round 2: corner lot: the lot-centroid pin sat 20 m from E 18 ST but 39 m from PARK AVE S, so it was moved to the PARK AVE S frontage near the corner (14 m from the PARK AVE S centreline, 26 m from E 18 ST; 26 m from the old pin). Tax lot unchanged. | FS14: =IF($A14="","",IF(ISNUMBER(MATCH(U14,{"queued","contacted","replied","call_booked","call_done","yes_in_principle","materials_sent"},0)),"Y","N")) -> N | FT14: =IF($A14="","",IF(OR(T14="Y",U14="do_not_contact",AS14&""<>""),"Y","N")) -> N | FU14: =IF($A14="","",IF(AP14&""<>"",AP14&"",$A14)) -> AO-C-038 | FV14: =IF($A14="","",IF(COUNTIFS($FU$2:$FU$1000,FU14,$FS$2:$FS$1000,"Y")+COUNTIFS($FU$2:$FU$1000,FU14,$FT$2:$FT$1000,"Y")>0,"Y","N")) -> N | FW14: =IF($A14="","",IF(AND(U14="new",T14="N",FT14="N",AT14="Y",FV14="N"),"Y","N")) -> N | FX14: =IF($A14="","",IF(FW14<>"Y","N",IF(COUNTIFS($FU$2:$FU$1000,FU14,$FW$2:$FW$1000,"Y",$J$2:$J$1000,">"&J14)+COUNTIFS($FU$2:$FU$1000,FU14,$FW$2:$FW$1000,"Y",$J$2:$J$1000,J14,$GD$2:$GD$1000,"<"&GD14)=0,"Y","N"))) -> N | FY14: =IF($A14="","",IF(AND(FW14="Y",FX14="Y",Y14&""<>""),IF(Y14<=10,"Y","N"),"N")) -> N | FZ14: =IF(FY14="Y",Y14,"") | GA14: =IF($A14="","",IF(AND(I14="walk-in",CN14="pass",U14="new",FT14="N",FV14="N",AQ14<>"Y"),"Y","N")) -> N | GB14: =IF(GA14<>"Y","",IF(COUNTIFS($GA$2:$GA$1000,"Y",$J$2:$J$1000,">"&J14)+COUNTIFS($GA$2:$GA$1000,"Y",$J$2:$J$1000,J14,$GD$2:$GD$1000,"<"&GD14)+1<=25,COUNTIFS($GA$2:$GA$1000,"Y",$J$2:$J$1000,">"&J14)+COUNTIFS($GA$2:$GA$1000,"Y",$J$2:$J$1000,J14,$GD$2:$GD$1000,"<"&GD14)+1,"")) | GC14: =IF(AND(_xlfn.ISFORMULA(C14),_xlfn.ISFORMULA(J14)),"Y","N") -> N | GD14: =ROW()-1 -> 13
A15: AO-C-130 | B15: Butterfly Network | C15: https://www.butterflynetwork.com | D15: butterflynetwork.com | E15: 19 | F15: 62.7 | G15: Y | H15: Katie | I15: Gowryluk | J15: Chief Of Staff | L15: pantry or office lead (primary) | M15: crowd-listed | N15: The Org (crowd-edited org chart) | O15: https://theorg.com/org/butterfly-network/person/katie-gowryluk | P15: 2026-10-24 | V15: none | AE15: 11 East 26th Street | AF15: 7-8 | AG15: medical devices (handheld ultrasound) | AH15: 443 | AI15: https://www.linkedin.com/company/2338924 | AJ15: Y | AK15: 40-75 | AL15: Y | AM15: 180 | AN15: low | AO15: unknown | AP15: AO-C-047 | AQ15: N | AT15: =IF($A15="","",IF(AND(CN15="pass",AQ15<>"Y",C15<>"",OR(AX15<>"Y",AV15="Y")),"Y","N")) -> Y | AU15: =IF($A15="","",_xlfn.TEXTJOIN("; ",TRUE(),IF(CN15<>"pass","gated out",""),IF(AQ15="Y","on hold: "&AR15,""),IF(C15="","no contact named on an opened page",""),IF(AND(AX15="Y",AV15<>"Y"),"Tuesday estimate band "&L15&": founder's call",""))) | AX15: N | BC15: =IF($A15="","",IFERROR(INDEX(Enrichment!$A$2:$GZ$2000,MATCH($A15,INDEX(Enrichment!$A$2:$GZ$2000,0,MATCH("row_id",Enrichment!$A$1:$GZ$1,0)),0),MATCH("work_email",Enrichment!$A$1:$GZ$1,0))&"","")) | BD15: =IF($A15="","",IF(BC15="","none",IF(OR(IFERROR(INDEX(Enrichment!$A$2:$GZ$2000,MATCH($A15,INDEX(Enrichment!$A$2:$GZ$2000,0,MATCH("row_id",Enrichment!$A$1:$GZ$1,0)),0),MATCH("email_status",Enrichment!$A$1:$GZ$1,0))&"","")="verified",IFERROR(INDEX(Enrichment!$A$2:$GZ$2000,MATCH($A15,INDEX(Enrichment!$A$2:$GZ$2000,0,MATCH("row_id",Enrichment!$A$1:$GZ$1,0)),0),MATCH("email_status",Enrichment!$A$1:$GZ$1,0))&"","")="unverified"),IFERROR(INDEX(Enrichment!$A$2:$GZ$2000,MATCH($A15,INDEX(Enrichment!$A$2:$GZ$2000,0,MATCH("row_id",Enrichment!$A$1:$GZ$1,0)),0),MATCH("email_status",Enrichment!$A$1:$GZ$1,0))&"",""),"unverified"))) -> none | BE15: pantry or office lead (primary) | BF15: unverified | BG15: search snippet only (not opened) | BH15: https://www.datanyze.com/people/Andy-Ng/2966944280 | BI15: 2026-10-24 | BJ15: adjacent | BK15: no named contact: on the Walk list tab (ask for whoever runs the pantry), or use the company contact form | BL15: contact seen only in a search snippet | BQ15: =IF($A15="","",IFERROR(INDEX(Enrichment!$A$2:$GZ$2000,MATCH($A15,INDEX(Enrichment!$A$2:$GZ$2000,0,MATCH("row_id",Enrichment!$A$1:$GZ$1,0)),0),MATCH("backup_work_email",Enrichment!$A$1:$GZ$1,0))&"","")) | BR15: =IF($A15="","",IF(BQ15="","none",IF(OR(IFERROR(INDEX(Enrichment!$A$2:$GZ$2000,MATCH($A15,INDEX(Enrichment!$A$2:$GZ$2000,0,MATCH("row_id",Enrichment!$A$1:$GZ$1,0)),0),MATCH("backup_email_status",Enrichment!$A$1:$GZ$1,0))&"","")="verified",IFERROR(INDEX(Enrichment!$A$2:$GZ$2000,MATCH($A15,INDEX(Enrichment!$A$2:$GZ$2000,0,MATCH("row_id",Enrichment!$A$1:$GZ$1,0)),0),MATCH("backup_email_status",Enrichment!$A$1:$GZ$1,0))&"","")="unverified"),IFERROR(INDEX(Enrichment!$A$2:$GZ$2000,MATCH($A15,INDEX(Enrichment!$A$2:$GZ$2000,0,MATCH("row_id",Enrichment!$A$1:$GZ$1,0)),0),MATCH("backup_email_status",Enrichment!$A$1:$GZ$1,0))&"",""),"unverified"))) -> none | BT15: none | BX15: none | BY15: no backup named: back to research | BZ15: no backup contact named | CA15: Tuesday estimate 113 to 180 (low confidence), under 500 staff company-wide, no attendance signal, occupied at a high-confidence address | CB15: walk-in | CC15: Andy Ng | CE15: ny_base=unconfirmed (search snippet only: a third-party profile listing an Operations Administrator at the New York headquarters; the page returned HTTP 403 and was not opened); title_fit=variant (office administration). The Org has no Vita Coco contact in the target titles placed in New York (its HR Director and People Coordinator records are outside New York). | CF15: unconfirmed | CM15: Y | CN15: pass | CO15: passes all hard gates | CP15: company | CQ15: B-C-047 | CR15: https://thevitacococompany.com | CS15: beverage brand (coconut water) | CT15: 336 | CU15: 368 | CV15: 251-500 | CW15: whole-company | CX15: agree | CY15: https://www.sec.gov/Archives/edgar/data/1482981/000148298126000022/coco-20251231.htm | CZ15: https://www.reveliolabs.com/companies/vita-coco/employees | DA15: le500 | DB15: New York | DC15: Y | DD15: unknown | DE15: unknown | DF15: 10003 | DG15: 40.73865 | DH15: -73.991471 | DI15: Y | DJ15: 0 | DK15: B-B-018 | DL15: 111 Fifth Avenue (Winter Organization) | DM15: https://www.sec.gov/Archives/edgar/data/1482981/000148298126000022/coco-20251231.htm | DN15: 2026-02-18 | DO15: other | DP15: https://commercialobserver.com/2024/09/vita-coco-111-fifth-avenue/ | DQ15: 2024-09-10 | DR15: cites a sec.gov filing: agents do not open it (EDGAR demands a contact email); the founder may open it in a browser | DS15: high | DU15: N | DX15: unknown | EA15: unknown | EB15: N | EC15: unknown | EF15: 143 | EH15: Y | EI15: 336 (sec.gov) and 368 (Revelio Labs) staff (whole-company count) x 50% to 100% of them in the New York office (HQ New York; share assumed) x 67% (Partnership for NYC, firms under 500) in on a weekday; capped by 22,530 sf at 125 sf per person (was 113 to 247) (largest square footage the sources mention at this address; if the company holds more space here, intake corrects it) = 113 to 180, central 143; low confidence; estimate until intake replaces it. | EJ15: estimate until intake replaces it | EK15: 1 | EL15: 66 | EM15: 25 | EN15: 15 | EO15: 6 | EP15: 15 | EQ15: =IF($A15="","",IF(AH15="exact",10,IF(AH15="adjacent",5,0))) -> 0 | ER15: =IF($A15="","",IF(R15="Y",15,0)) -> 0 | ES15: candidate | EV15: 22,530 sf | EW15: B's sources | EX15: FY2025 10-K cover lists principal executive offices at 111 Fifth Avenue, Second Floor; it reports 336 full-time employees at 2025-12-31, 235 of them in the U.S. CO Sept 2024 reported the 22,530 sf, 10-year HQ lease (moved from 250 Park Ave S). Built In shows 613, which conflicts with the 10-K; the 10-K is used. Beverage brand: possible brand-side contact as well as an office. | Assembly 2026-10-24: SEC EDGAR source (sec.gov): this agent will not re-open it, because EDGAR serves only requests that carry a contact email and the project rule forbids sending one; the founder may open it in a browser. Review round 2: a second count agrees with the band: Revelio Labs (The Vita Coco Co, HQ New York City): about 368 employees worldwide as of March 2026. Review round 2: corner lot: the lot-centroid pin sat 24 m from E 18 ST but 45 m from 5 AVE, so it was moved to the 5 AVE frontage near the corner (17 m from the 5 AVE centreline, 27 m from E 18 ST; 29 m from the old pin). Tax lot unchanged. | FS15: =IF($A15="","",IF(ISNUMBER(MATCH(U15,{"queued","contacted","replied","call_booked","call_done","yes_in_principle","materials_sent"},0)),"Y","N")) -> N | FT15: =IF($A15="","",IF(OR(T15="Y",U15="do_not_contact",AS15&""<>""),"Y","N")) -> N | FU15: =IF($A15="","",IF(AP15&""<>"",AP15&"",$A15)) -> AO-C-047 | FV15: =IF($A15="","",IF(COUNTIFS($FU$2:$FU$1000,FU15,$FS$2:$FS$1000,"Y")+COUNTIFS($FU$2:$FU$1000,FU15,$FT$2:$FT$1000,"Y")>0,"Y","N")) -> N | FW15: =IF($A15="","",IF(AND(U15="new",T15="N",FT15="N",AT15="Y",FV15="N"),"Y","N")) -> N | FX15: =IF($A15="","",IF(FW15<>"Y","N",IF(COUNTIFS($FU$2:$FU$1000,FU15,$FW$2:$FW$1000,"Y",$J$2:$J$1000,">"&J15)+COUNTIFS($FU$2:$FU$1000,FU15,$FW$2:$FW$1000,"Y",$J$2:$J$1000,J15,$GD$2:$GD$1000,"<"&GD15)=0,"Y","N"))) -> N | FY15: =IF($A15="","",IF(AND(FW15="Y",FX15="Y",Y15&""<>""),IF(Y15<=10,"Y","N"),"N")) -> N | FZ15: =IF(FY15="Y",Y15,"") | GA15: =IF($A15="","",IF(AND(I15="walk-in",CN15="pass",U15="new",FT15="N",FV15="N",AQ15<>"Y"),"Y","N")) -> N | GB15: =IF(GA15<>"Y","",IF(COUNTIFS($GA$2:$GA$1000,"Y",$J$2:$J$1000,">"&J15)+COUNTIFS($GA$2:$GA$1000,"Y",$J$2:$J$1000,J15,$GD$2:$GD$1000,"<"&GD15)+1<=25,COUNTIFS($GA$2:$GA$1000,"Y",$J$2:$J$1000,">"&J15)+COUNTIFS($GA$2:$GA$1000,"Y",$J$2:$J$1000,J15,$GD$2:$GD$1000,"<"&GD15)+1,"")) | GC15: =IF(AND(_xlfn.ISFORMULA(C15),_xlfn.ISFORMULA(J15)),"Y","N") -> N | GD15: =ROW()-1 -> 14
A16: AO-C-262 | B16: Criteo | C16: https://www.criteo.com | D16: criteo.com | E16: 20 | F16: 62.0 | G16: Y | H16: Manuela | I16: Montagnana | J16: Chief People Officer | L16: pantry or office lead (primary) | M16: crowd-listed | N16: The Org (crowd-edited org chart) | O16: https://theorg.com/org/criteo/person/manuela-montagnana | P16: 2026-10-24 | V16: none | AE16: 387 Park Avenue South | AF16: top floor and penthouse | AG16: adtech (commerce media) | AH16: 2868 | AI16: https://www.linkedin.com/company/criteo | AJ16: Y | AK16: 76-150 | AL16: Y | AM16: 172 | AN16: low | AO16: in-office-5 | AP16: AO-C-082 | AQ16: N | AR16: lease signed, move not confirmed: check the lobby directory before outreach (B) | AT16: =IF($A16="","",IF(AND(CN16="pass",AQ16<>"Y",C16<>"",OR(AX16<>"Y",AV16="Y")),"Y","N")) -> Y | AU16: =IF($A16="","",_xlfn.TEXTJOIN("; ",TRUE(),IF(CN16<>"pass","gated out",""),IF(AQ16="Y","on hold: "&AR16,""),IF(C16="","no contact named on an opened page",""),IF(AND(AX16="Y",AV16<>"Y"),"Tuesday estimate band "&L16&": founder's call",""))) | AX16: N | AY16: David | AZ16: Reed | BA16: Strategy and Operations | BC16: =IF($A16="","",IFERROR(INDEX(Enrichment!$A$2:$GZ$2000,MATCH($A16,INDEX(Enrichment!$A$2:$GZ$2000,0,MATCH("row_id",Enrichment!$A$1:$GZ$1,0)),0),MATCH("work_email",Enrichment!$A$1:$GZ$1,0))&"","")) | BD16: =IF($A16="","",IF(BC16="","none",IF(OR(IFERROR(INDEX(Enrichment!$A$2:$GZ$2000,MATCH($A16,INDEX(Enrichment!$A$2:$GZ$2000,0,MATCH("row_id",Enrichment!$A$1:$GZ$1,0)),0),MATCH("email_status",Enrichment!$A$1:$GZ$1,0))&"","")="verified",IFERROR(INDEX(Enrichment!$A$2:$GZ$2000,MATCH($A16,INDEX(Enrichment!$A$2:$GZ$2000,0,MATCH("row_id",Enrichment!$A$1:$GZ$1,0)),0),MATCH("email_status",Enrichment!$A$1:$GZ$1,0))&"","")="unverified"),IFERROR(INDEX(Enrichment!$A$2:$GZ$2000,MATCH($A16,INDEX(Enrichment!$A$2:$GZ$2000,0,MATCH("row_id",Enrichment!$A$1:$GZ$1,0)),0),MATCH("email_status",Enrichment!$A$1:$GZ$1,0))&"",""),"unverified"))) -> none | BE16: pantry or office lead (primary) | BF16: crowd-listed | BG16: The Org (crowd-edited org chart) | BH16: https://theorg.com/org/candid-health/person/david-reed | BI16: 2026-10-24 | BJ16: adjacent | BK16: find David Reed at Candid Health on LinkedIn and paste the profile URL into primary_linkedin_url (this also confirms the name: The Org is crowd-edited and marks it Unverified); adjacent title: ask who runs the pantry | BL16: adjacent contact named (Strategy and Operations) (crowd-listed on The Org) | BM16: Sierra | BN16: Agarwal | BO16: Strategy and Operations | BQ16: =IF($A16="","",IFERROR(INDEX(Enrichment!$A$2:$GZ$2000,MATCH($A16,INDEX(Enrichment!$A$2:$GZ$2000,0,MATCH("row_id",Enrichment!$A$1:$GZ$1,0)),0),MATCH("backup_work_email",Enrichment!$A$1:$GZ$1,0))&"","")) | BR16: =IF($A16="","",IF(BQ16="","none",IF(OR(IFERROR(INDEX(Enrichment!$A$2:$GZ$2000,MATCH($A16,INDEX(Enrichment!$A$2:$GZ$2000,0,MATCH("row_id",Enrichment!$A$1:$GZ$1,0)),0),MATCH("backup_email_status",Enrichment!$A$1:$GZ$1,0))&"","")="verified",IFERROR(INDEX(Enrichment!$A$2:$GZ$2000,MATCH($A16,INDEX(Enrichment!$A$2:$GZ$2000,0,MATCH("row_id",Enrichment!$A$1:$GZ$1,0)),0),MATCH("backup_email_status",Enrichment!$A$1:$GZ$1,0))&"","")="unverified"),IFERROR(INDEX(Enrichment!$A$2:$GZ$2000,MATCH($A16,INDEX(Enrichment!$A$2:$GZ$2000,0,MATCH("row_id",Enrichment!$A$1:$GZ$1,0)),0),MATCH("backup_email_status",Enrichment!$A$1:$GZ$1,0))&"",""),"unverified"))) -> none | BS16: pantry or office lead (backup) | BT16: crowd-listed | BU16: The Org (crowd-edited org chart) | BV16: https://theorg.com/org/candid-health/person/sierra-agarwal | BW16: 2026-10-24 | BX16: adjacent | BY16: find Sierra Agarwal at Candid Health on LinkedIn and paste the profile URL into backup_linkedin_url (this also confirms the name: The Org is crowd-edited and marks it Unverified); adjacent title: ask who runs the pantry | BZ16: adjacent contact named (Strategy and Operations) (crowd-listed on The Org) | CA16: Tuesday estimate 44 to 172 (low confidence), under 500 staff company-wide, on-site 5 days a week per its profile, signed-not-occupied at a medium-confidence address (hold: lease signed, move not confirmed) | CB16: linkedin | CC16: David Reed | CD16: 2026-08-30 | CE16: ny_base=likely; title_fit=adjacent (business operations). The Org position page (opened 2026-10-24, updated 2026-08-30) places him in the New York area. No office, people or EA title in New York found; ask who runs the office. | CF16: likely | CH16: Sierra Agarwal | CI16: 2026-08-28 | CJ16: ny_base=likely; title_fit=adjacent. The Org position page (opened 2026-10-24, updated 2026-08-28), New York area. | CK16: likely | CM16: Y | CN16: pass | CO16: passes all hard gates | CP16: company | CQ16: B-C-082 | CR16: https://www.candidhealth.com | CS16: software (healthcare billing) | CT16: 256 | CU16: 130+ | CV16: unknown | CW16: unknown | CX16: disagree | CY16: https://www.builtinnyc.com/company/candid | CZ16: https://www.candidhealth.com/about | DA16: le500 | DB16: New York | DC16: Y | DD16: unknown | DE16: https://www.linkedin.com/company/candid-health | DF16: 10010 | DG16: 40.742014 | DH16: -73.993705 | DI16: Y | DJ16: 0 | DK16: B-B-038 | DL16: Adams Dry Goods / Mattel Building (GFP Real Estate) | DM16: https://commercialobserver.com/2026/01/candid-health-lease-675-avenue-of-the-americas/ | DN16: 2026-01-27 | DO16: leasing-press | DP16: https://rebusinessonline.com/candid-health-signs-28687-sf-office-lease-in-midtown-manhattan/ | DQ16: 2026-04-13 | DS16: medium | DT16: unknown | DU16: N | DX16: unknown | EA16: unknown | EB16: N | EC16: 6 total employees) still lists 44 W 28th St and Columbus OH. CMO quoted on an intentional in-office culture. | Assembly 2026-10-24: Revie | ED16: https://www.builtinnyc.com/company/candid | EE16: 2026-10-23 | EF16: 87 | EH16: N | EI16: 256 (Built In) and 130+ (candidhealth.com) staff (whole-company count) x 50% to 100% of them in the New York office (HQ New York; share assumed) x 67% (Partnership for NYC, firms under 500) in on a weekday = 44 to 172, central 87; low confidence; estimate until intake replaces it. | EJ16: estimate until intake replaces it | EK16: 1 | EL16: 65 | EM16: 25 | EN16: 15 | EO16: 15 | EP16: 5 | EQ16: =IF($A16="","",IF(AH16="exact",10,IF(AH16="adjacent",5,0))) -> 0 | ER16: =IF($A16="","",IF(R16="Y",15,0)) -> 0 | ES16: candidate | EV16: 28,687 sf | EW16: B's sources | EX16: Seven-year, 28,687 sf lease on the 3rd floor, relocating from 44 W 28th St. Built In (slug 'candid', 256 total employees) still lists 44 W 28th St and Columbus OH. CMO quoted on an intentional in-office culture. | Assembly 2026-10-24: Review round 2: band changed from 251-500 to unknown. Sources disagree: Built In shows 256 (251-500) and Candid Health's own About page timeline, 2025 entry: 'Grew team to 130+ employees' (opened 2026-10-24) (76-150). Band left unknown; founder to confirm at intake. Review round 3: headcount_second_source_date left blank (date not stated): the About page timeline puts 'Grew team to 130+ employees' under 2025 with no month; the page was opened 2026-10-24. Review round 2: corner lot: the lot-centroid pin sat 39 m from W 21 ST but 46 m from AVE OF THE AMERICAS, so it was moved to the AVE OF THE AMERICAS frontage near the corner (18 m from the AVE OF THE AMERICAS centreline, 39 m from W 21 ST; 28 m from the old pin). Tax lot unchanged. | EZ16: linked from the company's own site (https://candidhealth.com/, opened 2026-10-24); LinkedIn not opened | FS16: =IF($A16="","",IF(ISNUMBER(MATCH(U16,{"queued","contacted","replied","call_booked","call_done","yes_in_principle","materials_sent"},0)),"Y","N")) -> N | FT16: =IF($A16="","",IF(OR(T16="Y",U16="do_not_contact",AS16&""<>""),"Y","N")) -> N | FU16: =IF($A16="","",IF(AP16&""<>"",AP16&"",$A16)) -> AO-C-082 | FV16: =IF($A16="","",IF(COUNTIFS($FU$2:$FU$1000,FU16,$FS$2:$FS$1000,"Y")+COUNTIFS($FU$2:$FU$1000,FU16,$FT$2:$FT$1000,"Y")>0,"Y","N")) -> N | FW16: =IF($A16="","",IF(AND(U16="new",T16="N",FT16="N",AT16="Y",FV16="N"),"Y","N")) -> N | FX16: =IF($A16="","",IF(FW16<>"Y","N",IF(COUNTIFS($FU$2:$FU$1000,FU16,$FW$2:$FW$1000,"Y",$J$2:$J$1000,">"&J16)+COUNTIFS($FU$2:$FU$1000,FU16,$FW$2:$FW$1000,"Y",$J$2:$J$1000,J16,$GD$2:$GD$1000,"<"&GD16)=0,"Y","N"))) -> N | FY16: =IF($A16="","",IF(AND(FW16="Y",FX16="Y",Y16&""<>""),IF(Y16<=10,"Y","N"),"N")) -> N | FZ16: =IF(FY16="Y",Y16,"") | GA16: =IF($A16="","",IF(AND(I16="walk-in",CN16="pass",U16="new",FT16="N",FV16="N",AQ16<>"Y"),"Y","N")) -> N | GB16: =IF(GA16<>"Y","",IF(COUNTIFS($GA$2:$GA$1000,"Y",$J$2:$J$1000,">"&J16)+COUNTIFS($GA$2:$GA$1000,"Y",$J$2:$J$1000,J16,$GD$2:$GD$1000,"<"&GD16)+1<=25,COUNTIFS($GA$2:$GA$1000,"Y",$J$2:$J$1000,">"&J16)+COUNTIFS($GA$2:$GA$1000,"Y",$J$2:$J$1000,J16,$GD$2:$GD$1000,"<"&GD16)+1,"")) | GC16: =IF(AND(_xlfn.ISFORMULA(C16),_xlfn.ISFORMULA(J16)),"Y","N") -> N | GD16: =ROW()-1 -> 15
A17: AO-C-098 | B17: BrainPOP | C17: https://www.brainpop.com/ | D17: brainpop.com | E17: 21 | F17: 61.0 | G17: Y | H17: Lilly | I17: Santiago | J17: Executive Assistant to Chief Executive Officer/Office Coordinator | L17: pantry or office lead (primary) | M17: crowd-listed | N17: The Org (crowd-edited org chart) | O17: https://theorg.com/org/brainpop/person/lilly-santiago | P17: 2026-10-24 | Q17: Crystal | R17: Spence | S17: Operations Lead, Office of CEO | U17: pantry or office lead (backup) | V17: crowd-listed | W17: The Org (crowd-edited org chart) | X17: https://theorg.com/org/brainpop/person/crystal-spence | Y17: 2026-10-24 | Z17: Crystal Spence | AA17: 2026-01-20 | AB17: ny_base=confirmed (The Org attaches the role to BrainPOP's New York HQ office); title_fit=variant (office of the CEO). The Org updated 2026-01-20. | AC17: confirmed | AE17: 71 West 23rd Street | AF17: 17 | AG17: Education technology | AH17: 225 | AI17: unknown | AJ17: Y | AK17: 76-150 | AL17: Y | AM17: 82 | AN17: low | AO17: in-office-5 | AP17: AO-C-048 | AQ17: N | AT17: =IF($A17="","",IF(AND(CN17="pass",AQ17<>"Y",C17<>"",OR(AX17<>"Y",AV17="Y")),"Y","N")) -> Y | AU17: =IF($A17="","",_xlfn.TEXTJOIN("; ",TRUE(),IF(CN17<>"pass","gated out",""),IF(AQ17="Y","on hold: "&AR17,""),IF(C17="","no contact named on an opened page",""),IF(AND(AX17="Y",AV17<>"Y"),"Tuesday estimate band "&L17&": founder's call",""))) | AX17: N | BC17: =IF($A17="","",IFERROR(INDEX(Enrichment!$A$2:$GZ$2000,MATCH($A17,INDEX(Enrichment!$A$2:$GZ$2000,0,MATCH("row_id",Enrichment!$A$1:$GZ$1,0)),0),MATCH("work_email",Enrichment!$A$1:$GZ$1,0))&"","")) | BD17: =IF($A17="","",IF(BC17="","none",IF(OR(IFERROR(INDEX(Enrichment!$A$2:$GZ$2000,MATCH($A17,INDEX(Enrichment!$A$2:$GZ$2000,0,MATCH("row_id",Enrichment!$A$1:$GZ$1,0)),0),MATCH("email_status",Enrichment!$A$1:$GZ$1,0))&"","")="verified",IFERROR(INDEX(Enrichment!$A$2:$GZ$2000,MATCH($A17,INDEX(Enrichment!$A$2:$GZ$2000,0,MATCH("row_id",Enrichment!$A$1:$GZ$1,0)),0),MATCH("email_status",Enrichment!$A$1:$GZ$1,0))&"","")="unverified"),IFERROR(INDEX(Enrichment!$A$2:$GZ$2000,MATCH($A17,INDEX(Enrichment!$A$2:$GZ$2000,0,MATCH("row_id",Enrichment!$A$1:$GZ$1,0)),0),MATCH("email_status",Enrichment!$A$1:$GZ$1,0))&"",""),"unverified"))) -> none | BF17: none | BJ17: none | BK17: no named contact: on the Walk list tab (ask for whoever runs the pantry), or use the company contact form | BL17: no contact found in public sources (walk-in) | BQ17: =IF($A17="","",IFERROR(INDEX(Enrichment!$A$2:$GZ$2000,MATCH($A17,INDEX(Enrichment!$A$2:$GZ$2000,0,MATCH("row_id",Enrichment!$A$1:$GZ$1,0)),0),MATCH("backup_work_email",Enrichment!$A$1:$GZ$1,0))&"","")) | BR17: =IF($A17="","",IF(BQ17="","none",IF(OR(IFERROR(INDEX(Enrichment!$A$2:$GZ$2000,MATCH($A17,INDEX(Enrichment!$A$2:$GZ$2000,0,MATCH("row_id",Enrichment!$A$1:$GZ$1,0)),0),MATCH("backup_email_status",Enrichment!$A$1:$GZ$1,0))&"","")="verified",IFERROR(INDEX(Enrichment!$A$2:$GZ$2000,MATCH($A17,INDEX(Enrichment!$A$2:$GZ$2000,0,MATCH("row_id",Enrichment!$A$1:$GZ$1,0)),0),MATCH("backup_email_status",Enrichment!$A$1:$GZ$1,0))&"","")="unverified"),IFERROR(INDEX(Enrichment!$A$2:$GZ$2000,MATCH($A17,INDEX(Enrichment!$A$2:$GZ$2000,0,MATCH("row_id",Enrichment!$A$1:$GZ$1,0)),0),MATCH("backup_email_status",Enrichment!$A$1:$GZ$1,0))&"",""),"unverified"))) -> none | BT17: none | BX17: none | BY17: no backup named: back to research | BZ17: no backup contact named | CA17: Tuesday estimate 31 to 82 (low confidence), under 500 staff company-wide, on-site 5 days a week per its profile, occupied at a high-confidence address | CB17: walk-in | CM17: Y | CN17: pass | CO17: passes all hard gates | CP17: company | CQ17: B-C-048 | CR17: https://aterian.io | CS17: consumer products (e-commerce brands) | CT17: 122 | CU17: 94 | CV17: 76-150 | CW17: whole-company | CX17: agree | CY17: https://www.builtinnyc.com/company/aterian | CZ17: https://www.reveliolabs.com/companies/aterian-group/employees | DA17: le500 | DB17: New York | DC17: Y | DD17: unknown | DE17: https://www.linkedin.com/company/aterian-inc | DF17: 10003 | DG17: 40.737722 | DH17: -73.989367 | DI17: Y | DJ17: 0 | DK17: B-B-019 | DL17: 37 East 18th Street (Zar Property NY) | DM17: https://www.builtinnyc.com/company/aterian/offices | DN17: 2026-10-23 | DO17: builtin | DP17: https://commercialobserver.com/2026/06/phia-lease-zar-property-37-east-18th-street/ | DQ17: 2026-06-03 | DS17: high | DU17: N | DX17: unknown | EA17: unknown | EB17: N | EC17: Built In workplace type: OnSite Workplace; typical time on-site: 5 days a week | ED17: https://www.builtinnyc.com/company/aterian/offices | EE17: 2026-10-24 | EF17: 50 | EH17: N | EI17: 122 (Built In) and 94 (Revelio Labs) staff (whole-company count) x 50% to 100% of them in the New York office (HQ New York; share assumed) x 67% (Partnership for NYC, firms under 500) in on a weekday = 31 to 82, central 50; low confidence; estimate until intake replaces it. | EJ17: estimate until intake replaces it | EK17: 0.74 | EL17: 63.4 | EM17: 18.4 | EN17: 15 | EO17: 15 | EP17: 15 | EQ17: =IF($A17="","",IF(AH17="exact",10,IF(AH17="adjacent",5,0))) -> 0 | ER17: =IF($A17="","",IF(R17="Y",15,0)) -> 0 | ES17: candidate | EX17: Built In HQ address 37 E 18th Street; CO June 2026 lists e-commerce services company Mohawk Group (Aterian's former name) as a current tenant. Built In shows 122 total employees. | Assembly 2026-10-24: Review round 2: a second count agrees with the band: Revelio Labs (Aterian Group, Inc., HQ New York City): about 94 employees worldwide as of March 2026. | EZ17: linked from The Org's company record (https://theorg.com/org/aterian, opened 2026-10-24); LinkedIn not opened | FS17: =IF($A17="","",IF(ISNUMBER(MATCH(U17,{"queued","contacted","replied","call_booked","call_done","yes_in_principle","materials_sent"},0)),"Y","N")) -> N | FT17: =IF($A17="","",IF(OR(T17="Y",U17="do_not_contact",AS17&""<>""),"Y","N")) -> N | FU17: =IF($A17="","",IF(AP17&""<>"",AP17&"",$A17)) -> AO-C-048 | FV17: =IF($A17="","",IF(COUNTIFS($FU$2:$FU$1000,FU17,$FS$2:$FS$1000,"Y")+COUNTIFS($FU$2:$FU$1000,FU17,$FT$2:$FT$1000,"Y")>0,"Y","N")) -> N | FW17: =IF($A17="","",IF(AND(U17="new",T17="N",FT17="N",AT17="Y",FV17="N"),"Y","N")) -> N | FX17: =IF($A17="","",IF(FW17<>"Y","N",IF(COUNTIFS($FU$2:$FU$1000,FU17,$FW$2:$FW$1000,"Y",$J$2:$J$1000,">"&J17)+COUNTIFS($FU$2:$FU$1000,FU17,$FW$2:$FW$1000,"Y",$J$2:$J$1000,J17,$GD$2:$GD$1000,"<"&GD17)=0,"Y","N"))) -> N | FY17: =IF($A17="","",IF(AND(FW17="Y",FX17="Y",Y17&""<>""),IF(Y17<=10,"Y","N"),"N")) -> N | FZ17: =IF(FY17="Y",Y17,"") | GA17: =IF($A17="","",IF(AND(I17="walk-in",CN17="pass",U17="new",FT17="N",FV17="N",AQ17<>"Y"),"Y","N")) -> N | GB17: =IF(GA17<>"Y","",IF(COUNTIFS($GA$2:$GA$1000,"Y",$J$2:$J$1000,">"&J17)+COUNTIFS($GA$2:$GA$1000,"Y",$J$2:$J$1000,J17,$GD$2:$GD$1000,"<"&GD17)+1<=25,COUNTIFS($GA$2:$GA$1000,"Y",$J$2:$J$1000,">"&J17)+COUNTIFS($GA$2:$GA$1000,"Y",$J$2:$J$1000,J17,$GD$2:$GD$1000,"<"&GD17)+1,"")) | GC17: =IF(AND(_xlfn.ISFORMULA(C17),_xlfn.ISFORMULA(J17)),"Y","N") -> N | GD17: =ROW()-1 -> 16
A18: AO-C-061 | B18: Daily Harvest | C18: https://www.daily-harvest.com | D18: daily-harvest.com | E18: 22 | F18: 61.0 | G18: Y | H18: Jessica | I18: Lawson | J18: Chief of Staff | L18: pantry or office lead (primary) | M18: crowd-listed | N18: The Org (crowd-edited org chart) | O18: https://theorg.com/org/daily-harvest/person/jessica-lawson | P18: 2026-10-24 | V18: none | AE18: 37 West 20th Street | AF18: unknown | AG18: food brand (frozen meals, DTC) | AH18: 267 | AI18: https://www.linkedin.com/company/daily-harvest | AJ18: Y | AK18: 76-150 | AL18: Y | AM18: 101 | AN18: low | AO18: hybrid-3 | AP18: AO-C-033 | AQ18: N | AT18: =IF($A18="","",IF(AND(CN18="pass",AQ18<>"Y",C18<>"",OR(AX18<>"Y",AV18="Y")),"Y","N")) -> Y | AU18: =IF($A18="","",_xlfn.TEXTJOIN("; ",TRUE(),IF(CN18<>"pass","gated out",""),IF(AQ18="Y","on hold: "&AR18,""),IF(C18="","no contact named on an opened page",""),IF(AND(AX18="Y",AV18<>"Y"),"Tuesday estimate band "&L18&": founder's call",""))) | AX18: N | BC18: =IF($A18="","",IFERROR(INDEX(Enrichment!$A$2:$GZ$2000,MATCH($A18,INDEX(Enrichment!$A$2:$GZ$2000,0,MATCH("row_id",Enrichment!$A$1:$GZ$1,0)),0),MATCH("work_email",Enrichment!$A$1:$GZ$1,0))&"","")) | BD18: =IF($A18="","",IF(BC18="","none",IF(OR(IFERROR(INDEX(Enrichment!$A$2:$GZ$2000,MATCH($A18,INDEX(Enrichment!$A$2:$GZ$2000,0,MATCH("row_id",Enrichment!$A$1:$GZ$1,0)),0),MATCH("email_status",Enrichment!$A$1:$GZ$1,0))&"","")="verified",IFERROR(INDEX(Enrichment!$A$2:$GZ$2000,MATCH($A18,INDEX(Enrichment!$A$2:$GZ$2000,0,MATCH("row_id",Enrichment!$A$1:$GZ$1,0)),0),MATCH("email_status",Enrichment!$A$1:$GZ$1,0))&"","")="unverified"),IFERROR(INDEX(Enrichment!$A$2:$GZ$2000,MATCH($A18,INDEX(Enrichment!$A$2:$GZ$2000,0,MATCH("row_id",Enrichment!$A$1:$GZ$1,0)),0),MATCH("email_status",Enrichment!$A$1:$GZ$1,0))&"",""),"unverified"))) -> none | BF18: none | BJ18: none | BK18: no named contact: on the Walk list tab (ask for whoever runs the pantry), or use the company contact form | BL18: no contact found in public sources (walk-in) | BQ18: =IF($A18="","",IFERROR(INDEX(Enrichment!$A$2:$GZ$2000,MATCH($A18,INDEX(Enrichment!$A$2:$GZ$2000,0,MATCH("row_id",Enrichment!$A$1:$GZ$1,0)),0),MATCH("backup_work_email",Enrichment!$A$1:$GZ$1,0))&"","")) | BR18: =IF($A18="","",IF(BQ18="","none",IF(OR(IFERROR(INDEX(Enrichment!$A$2:$GZ$2000,MATCH($A18,INDEX(Enrichment!$A$2:$GZ$2000,0,MATCH("row_id",Enrichment!$A$1:$GZ$1,0)),0),MATCH("backup_email_status",Enrichment!$A$1:$GZ$1,0))&"","")="verified",IFERROR(INDEX(Enrichment!$A$2:$GZ$2000,MATCH($A18,INDEX(Enrichment!$A$2:$GZ$2000,0,MATCH("row_id",Enrichment!$A$1:$GZ$1,0)),0),MATCH("backup_email_status",Enrichment!$A$1:$GZ$1,0))&"","")="unverified"),IFERROR(INDEX(Enrichment!$A$2:$GZ$2000,MATCH($A18,INDEX(Enrichment!$A$2:$GZ$2000,0,MATCH("row_id",Enrichment!$A$1:$GZ$1,0)),0),MATCH("backup_email_status",Enrichment!$A$1:$GZ$1,0))&"",""),"unverified"))) -> none | BT18: none | BX18: none | BY18: no backup named: back to research | BZ18: no backup contact named | CA18: Tuesday estimate 51 to 101 (low confidence), under 500 staff company-wide, hybrid 3 days, occupied at a medium-confidence address | CB18: walk-in | CM18: Y | CN18: pass | CO18: passes all hard gates | CP18: company | CQ18: B-C-033 | CR18: https://www.baseten.co | CS18: AI infrastructure software | CT18: 350 | CU18: 285 | CV18: 251-500 | CW18: whole-company | CX18: agree | CY18: https://www.builtinnyc.com/company/baseten | CZ18: https://www.reveliolabs.com/companies/baseten-labs/employees | DA18: le500 | DB18: San Francisco | DC18: N | DD18: unknown | DE18: https://www.linkedin.com/company/baseten | DF18: 10003 | DG18: 40.73686 | DH18: -73.988546 | DI18: Y | DJ18: 0 | DK18: B-B-016 | DL18: 215 Park Avenue South (SL Green managed) | DM18: https://www.sec.gov/Archives/edgar/data/1013454/000153949726000704/n5676_x5-424h.htm | DN18: 2026-02 | DO18: other | DR18: cites a sec.gov filing: agents do not open it (EDGAR demands a contact email); the founder may open it in a browser | DS18: medium | DU18: N | DX18: security desk | DY18: https://www.metro-manhattan.com/buildings/215-park-avenue-south/ | EA18: unknown | EB18: N | EC18: Built In workplace type: Hybrid Workplace; typical time on-site: 3 days a week; recent job tags: 3 Hybrid | ED18: https://www.builtinnyc.com/company/baseten/offices | EE18: 2026-10-24 | EF18: 72 | EH18: Y | EI18: 350 (Built In) and 285 (Revelio Labs) staff (whole-company count) x 5% to 100% of them in the New York office (HQ outside New York; share assumed) x 67% (Partnership for NYC, firms under 500) in on a weekday; space-based for a company headquartered outside New York: 12,660 sf seats 51 to 101 at 250 to 125 sf per person, kept within the headcount math (10 to 234) (largest square footage the sources mention at this address; if the company holds more space here, intake corrects it) = 51 to 101, central 72; low confidence; estimate until intake replaces it. | EJ18: estimate until intake replaces it | EK18: 1 | EL18: 63 | EM18: 25 | EN18: 15 | EO18: 10 | EP18: 13 | EQ18: =IF($A18="","",IF(AH18="exact",10,IF(AH18="adjacent",5,0))) -> 0 | ER18: =IF($A18="","",IF(R18="Y",15,0)) -> 0 | ES18: candidate | EV18: 12,660 sf | EW18: B's sources | EX18: SEC prospectus: BaseTen Labs, Inc. subleases 12,660 sf of Nayya's 18th floor through 2029-12-30. Built In NYC: 350 total employees, HQ San Francisco, 2 offices; NYC share unknown. | Assembly 2026-10-24: SEC EDGAR source (sec.gov): this agent will not re-open it, because EDGAR serves only requests that carry a contact email and the project rule forbids sending one; the founder may open it in a browser. Review round 2: a second count agrees with the band: Revelio Labs (Baseten Labs, Inc., HQ San Francisco): about 285 employees worldwide as of March 2026. Review round 2: corner lot: the lot-centroid pin sat 20 m from E 18 ST but 39 m from PARK AVE S, so it was moved to the PARK AVE S frontage near the corner (14 m from the PARK AVE S centreline, 26 m from E 18 ST; 26 m from the old pin). Tax lot unchanged. | EZ18: linked from the company's own site (https://www.baseten.co/, opened 2026-10-24); LinkedIn not opened | FS18: =IF($A18="","",IF(ISNUMBER(MATCH(U18,{"queued","contacted","replied","call_booked","call_done","yes_in_principle","materials_sent"},0)),"Y","N")) -> N | FT18: =IF($A18="","",IF(OR(T18="Y",U18="do_not_contact",AS18&""<>""),"Y","N")) -> N | FU18: =IF($A18="","",IF(AP18&""<>"",AP18&"",$A18)) -> AO-C-033 | FV18: =IF($A18="","",IF(COUNTIFS($FU$2:$FU$1000,FU18,$FS$2:$FS$1000,"Y")+COUNTIFS($FU$2:$FU$1000,FU18,$FT$2:$FT$1000,"Y")>0,"Y","N")) -> N | FW18: =IF($A18="","",IF(AND(U18="new",T18="N",FT18="N",AT18="Y",FV18="N"),"Y","N")) -> N | FX18: =IF($A18="","",IF(FW18<>"Y","N",IF(COUNTIFS($FU$2:$FU$1000,FU18,$FW$2:$FW$1000,"Y",$J$2:$J$1000,">"&J18)+COUNTIFS($FU$2:$FU$1000,FU18,$FW$2:$FW$1000,"Y",$J$2:$J$1000,J18,$GD$2:$GD$1000,"<"&GD18)=0,"Y","N"))) -> N | FY18: =IF($A18="","",IF(AND(FW18="Y",FX18="Y",Y18&""<>""),IF(Y18<=10,"Y","N"),"N")) -> N | FZ18: =IF(FY18="Y",Y18,"") | GA18: =IF($A18="","",IF(AND(I18="walk-in",CN18="pass",U18="new",FT18="N",FV18="N",AQ18<>"Y"),"Y","N")) -> N | GB18: =IF(GA18<>"Y","",IF(COUNTIFS($GA$2:$GA$1000,"Y",$J$2:$J$1000,">"&J18)+COUNTIFS($GA$2:$GA$1000,"Y",$J$2:$J$1000,J18,$GD$2:$GD$1000,"<"&GD18)+1<=25,COUNTIFS($GA$2:$GA$1000,"Y",$J$2:$J$1000,">"&J18)+COUNTIFS($GA$2:$GA$1000,"Y",$J$2:$J$1000,J18,$GD$2:$GD$1000,"<"&GD18)+1,"")) | GC18: =IF(AND(_xlfn.ISFORMULA(C18),_xlfn.ISFORMULA(J18)),"Y","N") -> N | GD18: =ROW()-1 -> 17
A19: AO-C-111 | B19: Wellcom Worldwide | C19: https://www.wellcomworldwide.com/ | D19: wellcomworldwide.com | E19: 23 | F19: 61.0 | G19: Y | H19: Jillian | I19: Cruz | J19: Executive Assistant to Global CEO | L19: pantry or office lead (primary) | M19: crowd-listed | N19: The Org (crowd-edited org chart) | O19: https://theorg.com/org/wellcom-worldwide/person/jillian-cruz | P19: 2026-10-24 | V19: none | AE19: 16 Madison Square West | AF19: unknown | AG19: Creative production agency | AH19: 336 | AI19: https://www.linkedin.com/company/wellcom_2 | AJ19: Y | AK19: 76-150 | AL19: Y | AM19: 64 | AN19: low | AO19: in-office-5 | AP19: AO-C-021 | AQ19: N | AT19: =IF($A19="","",IF(AND(CN19="pass",AQ19<>"Y",C19<>"",OR(AX19<>"Y",AV19="Y")),"Y","N")) -> Y | AU19: =IF($A19="","",_xlfn.TEXTJOIN("; ",TRUE(),IF(CN19<>"pass","gated out",""),IF(AQ19="Y","on hold: "&AR19,""),IF(C19="","no contact named on an opened page",""),IF(AND(AX19="Y",AV19<>"Y"),"Tuesday estimate band "&L19&": founder's call",""))) | AX19: N | BC19: =IF($A19="","",IFERROR(INDEX(Enrichment!$A$2:$GZ$2000,MATCH($A19,INDEX(Enrichment!$A$2:$GZ$2000,0,MATCH("row_id",Enrichment!$A$1:$GZ$1,0)),0),MATCH("work_email",Enrichment!$A$1:$GZ$1,0))&"","")) | BD19: =IF($A19="","",IF(BC19="","none",IF(OR(IFERROR(INDEX(Enrichment!$A$2:$GZ$2000,MATCH($A19,INDEX(Enrichment!$A$2:$GZ$2000,0,MATCH("row_id",Enrichment!$A$1:$GZ$1,0)),0),MATCH("email_status",Enrichment!$A$1:$GZ$1,0))&"","")="verified",IFERROR(INDEX(Enrichment!$A$2:$GZ$2000,MATCH($A19,INDEX(Enrichment!$A$2:$GZ$2000,0,MATCH("row_id",Enrichment!$A$1:$GZ$1,0)),0),MATCH("email_status",Enrichment!$A$1:$GZ$1,0))&"","")="unverified"),IFERROR(INDEX(Enrichment!$A$2:$GZ$2000,MATCH($A19,INDEX(Enrichment!$A$2:$GZ$2000,0,MATCH("row_id",Enrichment!$A$1:$GZ$1,0)),0),MATCH("email_status",Enrichment!$A$1:$GZ$1,0))&"",""),"unverified"))) -> none | BF19: none | BJ19: none | BK19: no named contact: on the Walk list tab (ask for whoever runs the pantry), or use the company contact form | BL19: contacts not researched yet | BQ19: =IF($A19="","",IFERROR(INDEX(Enrichment!$A$2:$GZ$2000,MATCH($A19,INDEX(Enrichment!$A$2:$GZ$2000,0,MATCH("row_id",Enrichment!$A$1:$GZ$1,0)),0),MATCH("backup_work_email",Enrichment!$A$1:$GZ$1,0))&"","")) | BR19: =IF($A19="","",IF(BQ19="","none",IF(OR(IFERROR(INDEX(Enrichment!$A$2:$GZ$2000,MATCH($A19,INDEX(Enrichment!$A$2:$GZ$2000,0,MATCH("row_id",Enrichment!$A$1:$GZ$1,0)),0),MATCH("backup_email_status",Enrichment!$A$1:$GZ$1,0))&"","")="verified",IFERROR(INDEX(Enrichment!$A$2:$GZ$2000,MATCH($A19,INDEX(Enrichment!$A$2:$GZ$2000,0,MATCH("row_id",Enrichment!$A$1:$GZ$1,0)),0),MATCH("backup_email_status",Enrichment!$A$1:$GZ$1,0))&"","")="unverified"),IFERROR(INDEX(Enrichment!$A$2:$GZ$2000,MATCH($A19,INDEX(Enrichment!$A$2:$GZ$2000,0,MATCH("row_id",Enrichment!$A$1:$GZ$1,0)),0),MATCH("backup_email_status",Enrichment!$A$1:$GZ$1,0))&"",""),"unverified"))) -> none | BT19: none | BX19: none | BY19: no backup named: back to research | BZ19: no backup contact named | CA19: Tuesday estimate 40 to 64 (low confidence), under 500 staff company-wide, on-site 5 days a week per its profile, occupancy-unconfirmed at a medium-confidence address | CB19: walk-in | CM19: N | CN19: pass | CO19: passes all hard gates | CP19: company | CQ19: B-C-021 | CR19: https://www.scalemicrogrids.com | CS19: energy infrastructure finance | CT19: 95 | CV19: 76-150 | CW19: whole-company | CX19: single-source | CY19: https://www.builtinnyc.com/company/scale-microgrids | DA19: le500 | DB19: Ridgewood | DC19: N | DD19: unknown | DE19: https://www.linkedin.com/company/10701082 | DF19: 10011 | DG19: 40.738405 | DH19: -73.99394 | DI19: Y | DJ19: 0 | DK19: B-B-008 | DL19: 26 West 17th Street | DM19: https://commercialobserver.com/2025/03/faire-lease-26-west-17th-street/ | DN19: 2025-03-27 | DO19: leasing-press | DP19: https://www.scalemicrogrids.com/contact | DQ19: 2026-10-23 | DS19: medium | DU19: N | DX19: unknown | EA19: unknown | EB19: N | EC19: Built In workplace type: OnSite Workplace; typical time on-site: 5 days a week; recent job tags: 2 Hybrid, 1 In-Office | ED19: https://www.builtinnyc.com/company/scale-microgrids/offices | EE19: 2026-10-24 | EF19: 51 | EH19: Y | EI19: 95 (Built In) staff (whole-company count) x 5% to 100% of them in the New York office (HQ outside New York; share assumed) x 67% (Partnership for NYC, firms under 500) in on a weekday; space-based for a company headquartered outside New York: 10,000 sf seats 40 to 80 at 250 to 125 sf per person, kept within the headcount math (3 to 64) (largest square footage the sources mention at this address; if the company holds more space here, intake corrects it) = 40 to 64, central 51; low confidence; estimate until intake replaces it. | EJ19: estimate until intake replaces it | EK19: 1 | EL19: 63 | EM19: 25 | EN19: 15 | EO19: 15 | EP19: 8 | EQ19: =IF($A19="","",IF(AH19="exact",10,IF(AH19="adjacent",5,0))) -> 0 | ER19: =IF($A19="","",IF(R19="Y",15,0)) -> 0 | ES19: candidate | EV19: 10,000 sf | EW19: B's sources | EX19: CO 2025-03-27: 10,000 sf on the 11th floor. Built In NYC: 95 total employees, HQ Ridgewood NJ. Company contact page lists a New York regional office (city only, no street), so second source confirms NYC presence, not the street address. | EZ19: linked from the company's own site (https://www.scalemicrogrids.com/, opened 2026-10-24); LinkedIn not opened | FS19: =IF($A19="","",IF(ISNUMBER(MATCH(U19,{"queued","contacted","replied","call_booked","call_done","yes_in_principle","materials_sent"},0)),"Y","N")) -> N | FT19: =IF($A19="","",IF(OR(T19="Y",U19="do_not_contact",AS19&""<>""),"Y","N")) -> N | FU19: =IF($A19="","",IF(AP19&""<>"",AP19&"",$A19)) -> AO-C-021 | FV19: =IF($A19="","",IF(COUNTIFS($FU$2:$FU$1000,FU19,$FS$2:$FS$1000,"Y")+COUNTIFS($FU$2:$FU$1000,FU19,$FT$2:$FT$1000,"Y")>0,"Y","N")) -> N | FW19: =IF($A19="","",IF(AND(U19="new",T19="N",FT19="N",AT19="Y",FV19="N"),"Y","N")) -> N | FX19: =IF($A19="","",IF(FW19<>"Y","N",IF(COUNTIFS($FU$2:$FU$1000,FU19,$FW$2:$FW$1000,"Y",$J$2:$J$1000,">"&J19)+COUNTIFS($FU$2:$FU$1000,FU19,$FW$2:$FW$1000,"Y",$J$2:$J$1000,J19,$GD$2:$GD$1000,"<"&GD19)=0,"Y","N"))) -> N | FY19: =IF($A19="","",IF(AND(FW19="Y",FX19="Y",Y19&""<>""),IF(Y19<=10,"Y","N"),"N")) -> N | FZ19: =IF(FY19="Y",Y19,"") | GA19: =IF($A19="","",IF(AND(I19="walk-in",CN19="pass",U19="new",FT19="N",FV19="N",AQ19<>"Y"),"Y","N")) -> N | GB19: =IF(GA19<>"Y","",IF(COUNTIFS($GA$2:$GA$1000,"Y",$J$2:$J$1000,">"&J19)+COUNTIFS($GA$2:$GA$1000,"Y",$J$2:$J$1000,J19,$GD$2:$GD$1000,"<"&GD19)+1<=25,COUNTIFS($GA$2:$GA$1000,"Y",$J$2:$J$1000,">"&J19)+COUNTIFS($GA$2:$GA$1000,"Y",$J$2:$J$1000,J19,$GD$2:$GD$1000,"<"&GD19)+1,"")) | GC19: =IF(AND(_xlfn.ISFORMULA(C19),_xlfn.ISFORMULA(J19)),"Y","N") -> N | GD19: =ROW()-1 -> 18
A20: AO-C-101 | B20: TripleLift | C20: https://triplelift.com/ | D20: triplelift.com | E20: 24 | F20: 60.1 | G20: Y | H20: Abby | I20: Hamilton | J20: Chief People Officer | L20: pantry or office lead (primary) | M20: verified-page | N20: employer's own site | O20: https://triplelift.com/about/ | P20: 2026-10-24 | V20: none | AE20: 53 West 23rd Street | AF20: 12 | AG20: Advertising technology | AH20: 335 | AI20: https://www.linkedin.com/company/triplelift | AJ20: Y | AK20: 151-250 | AL20: Y | AM20: 297 | AN20: low | AO20: in-office-5 | AP20: AO-C-130 | AQ20: N | AT20: =IF($A20="","",IF(AND(CN20="pass",AQ20<>"Y",C20<>"",OR(AX20<>"Y",AV20="Y")),"Y","N")) -> Y | AU20: =IF($A20="","",_xlfn.TEXTJOIN("; ",TRUE(),IF(CN20<>"pass","gated out",""),IF(AQ20="Y","on hold: "&AR20,""),IF(C20="","no contact named on an opened page",""),IF(AND(AX20="Y",AV20<>"Y"),"Tuesday estimate band "&L20&": founder's call",""))) | AX20: N | AY20: Katie | AZ20: Gowryluk | BA20: Chief Of Staff | BC20: =IF($A20="","",IFERROR(INDEX(Enrichment!$A$2:$GZ$2000,MATCH($A20,INDEX(Enrichment!$A$2:$GZ$2000,0,MATCH("row_id",Enrichment!$A$1:$GZ$1,0)),0),MATCH("work_email",Enrichment!$A$1:$GZ$1,0))&"","")) | BD20: =IF($A20="","",IF(BC20="","none",IF(OR(IFERROR(INDEX(Enrichment!$A$2:$GZ$2000,MATCH($A20,INDEX(Enrichment!$A$2:$GZ$2000,0,MATCH("row_id",Enrichment!$A$1:$GZ$1,0)),0),MATCH("email_status",Enrichment!$A$1:$GZ$1,0))&"","")="verified",IFERROR(INDEX(Enrichment!$A$2:$GZ$2000,MATCH($A20,INDEX(Enrichment!$A$2:$GZ$2000,0,MATCH("row_id",Enrichment!$A$1:$GZ$1,0)),0),MATCH("email_status",Enrichment!$A$1:$GZ$1,0))&"","")="unverified"),IFERROR(INDEX(Enrichment!$A$2:$GZ$2000,MATCH($A20,INDEX(Enrichment!$A$2:$GZ$2000,0,MATCH("row_id",Enrichment!$A$1:$GZ$1,0)),0),MATCH("email_status",Enrichment!$A$1:$GZ$1,0))&"",""),"unverified"))) -> none | BE20: pantry or office lead (primary) | BF20: crowd-listed | BG20: The Org (crowd-edited org chart) | BH20: https://theorg.com/org/butterfly-network/person/katie-gowryluk | BI20: 2026-10-24 | BJ20: adjacent | BK20: find Katie Gowryluk at Butterfly Network on LinkedIn and paste the profile URL into primary_linkedin_url (this also confirms the name: The Org is crowd-edited and marks it Unverified); the source is dated 2025-05-22: check Katie still holds the role; adjacent title: ask who runs the pantry | BL20: adjacent contact named (Chief Of Staff) (crowd-listed on The Org) | BQ20: =IF($A20="","",IFERROR(INDEX(Enrichment!$A$2:$GZ$2000,MATCH($A20,INDEX(Enrichment!$A$2:$GZ$2000,0,MATCH("row_id",Enrichment!$A$1:$GZ$1,0)),0),MATCH("backup_work_email",Enrichment!$A$1:$GZ$1,0))&"","")) | BR20: =IF($A20="","",IF(BQ20="","none",IF(OR(IFERROR(INDEX(Enrichment!$A$2:$GZ$2000,MATCH($A20,INDEX(Enrichment!$A$2:$GZ$2000,0,MATCH("row_id",Enrichment!$A$1:$GZ$1,0)),0),MATCH("backup_email_status",Enrichment!$A$1:$GZ$1,0))&"","")="verified",IFERROR(INDEX(Enrichment!$A$2:$GZ$2000,MATCH($A20,INDEX(Enrichment!$A$2:$GZ$2000,0,MATCH("row_id",Enrichment!$A$1:$GZ$1,0)),0),MATCH("backup_email_status",Enrichment!$A$1:$GZ$1,0))&"","")="unverified"),IFERROR(INDEX(Enrichment!$A$2:$GZ$2000,MATCH($A20,INDEX(Enrichment!$A$2:$GZ$2000,0,MATCH("row_id",Enrichment!$A$1:$GZ$1,0)),0),MATCH("backup_email_status",Enrichment!$A$1:$GZ$1,0))&"",""),"unverified"))) -> none | BT20: none | BX20: none | BY20: no backup named: back to research | BZ20: no backup contact named | CA20: Tuesday estimate 8 to 297 (low confidence), under 500 staff company-wide, on-site 5 days a week per its profile, occupied at a high-confidence address | CB20: linkedin | CC20: Katie Gowryluk | CD20: 2025-05-22 | CE20: ny_base=likely (The Org gives the New York metro area, no office attached); title_fit=adjacent (chief of staff at a firm of several hundred). The Org updated 2025-05-22. Butterfly advertised an 'Office Operations Manager & Executive Assistant' role, 5 days in the New York office (search result, Welcome to the Jungle, marked no longer available); that seat is probably filled, name not found. | CF20: likely | CM20: Y | CN20: pass | CO20: passes all hard gates | CP20: company | CQ20: B-C-130 | CR20: https://www.butterflynetwork.com | CS20: medical devices (handheld ultrasound) | CT20: 443 | CU20: 236 | CV20: unknown | CW20: unknown | CX20: disagree | CY20: https://www.builtinnyc.com/company/butterfly-network-inc/offices | CZ20: https://www.reveliolabs.com/companies/butterfly-network/employees | DA20: le500 | DB20: Burlington | DC20: N | DD20: unknown | DE20: https://www.linkedin.com/company/2338924 | DF20: 10010 | DG20: 40.743309 | DH20: -73.987329 | DI20: Y | DJ20: 0 | DK20: B-B-065 | DL20: 11 East 26th Street (Rockrose; joined to 15 East 26th Street) | DM20: https://commercialobserver.com/2025/09/activate-consulting-doubles-its-nomad-footprint/ | DN20: 2025-09-30 | DO20: leasing-press | DP20: https://www.builtinnyc.com/company/butterfly-network-inc/offices | DQ20: 2026-10-23 | DS20: high | DU20: N | DX20: unknown | EA20: unknown | EB20: N | EC20: w York office at '11 E 26th Street, Floor 7 & 8' (HQ Burlington MA), 443 total employees, on-site 5 days a week. CO lists it among building t | ED20: https://www.builtinnyc.com/company/butterfly-network-inc/offices | EE20: 2026-10-23 | EF20: 49 | EG20: may be under 30;may exceed 250 | EH20: N | EI20: 443 (Built In) and 236 (Revelio Labs) staff (whole-company count) x 5% to 100% of them in the New York office (HQ outside New York; share assumed) x 67% (Partnership for NYC, firms under 500) in on a weekday = 8 to 297, central 49; low confidence; estimate until intake replaces it. | EJ20: estimate until intake replaces it | EK20: 0.51 | EL20: 62.7 | EM20: 12.7 | EN20: 15 | EO20: 15 | EP20: 15 | EQ20: =IF($A20="","",IF(AH20="exact",10,IF(AH20="adjacent",5,0))) -> 0 | ER20: =IF($A20="","",IF(R20="Y",15,0)) -> 0 | ES20: candidate | EX20: Built In lists New York office at '11 E 26th Street, Floor 7 & 8' (HQ Burlington MA), 443 total employees, on-site 5 days a week. CO lists it among building tenants. | Assembly 2026-10-24: Review round 2: band changed from 251-500 to unknown. Sources disagree: Built In shows 443 (251-500) and Revelio Labs (Butterfly Network, Inc., HQ Burlington, Massachusetts): about 236 employees worldwide as of March 2026 (151-250). Band left unknown; founder to confirm at intake. Pin moved to frontage at review round 1: the lot-centroid pin failed the block-face test (39 m from E 26 ST but 39 m from E 27 ST); pin moved to frontage: the lot's position along E 26 ST kept, set 21 m from the centreline on the side CSCL gives house number 11 (18 m from the old pin). Tax lot unchanged. New pin: 21 m from E 26 ST, 57 m from E 27 ST. | EZ20: linked from the company's own site (https://www.butterflynetwork.com/, opened 2026-10-24); LinkedIn not opened | FS20: =IF($A20="","",IF(ISNUMBER(MATCH(U20,{"queued","contacted","replied","call_booked","call_done","yes_in_principle","materials_sent"},0)),"Y","N")) -> N | FT20: =IF($A20="","",IF(OR(T20="Y",U20="do_not_contact",AS20&""<>""),"Y","N")) -> N | FU20: =IF($A20="","",IF(AP20&""<>"",AP20&"",$A20)) -> AO-C-130 | FV20: =IF($A20="","",IF(COUNTIFS($FU$2:$FU$1000,FU20,$FS$2:$FS$1000,"Y")+COUNTIFS($FU$2:$FU$1000,FU20,$FT$2:$FT$1000,"Y")>0,"Y","N")) -> N | FW20: =IF($A20="","",IF(AND(U20="new",T20="N",FT20="N",AT20="Y",FV20="N"),"Y","N")) -> N | FX20: =IF($A20="","",IF(FW20<>"Y","N",IF(COUNTIFS($FU$2:$FU$1000,FU20,$FW$2:$FW$1000,"Y",$J$2:$J$1000,">"&J20)+COUNTIFS($FU$2:$FU$1000,FU20,$FW$2:$FW$1000,"Y",$J$2:$J$1000,J20,$GD$2:$GD$1000,"<"&GD20)=0,"Y","N"))) -> N | FY20: =IF($A20="","",IF(AND(FW20="Y",FX20="Y",Y20&""<>""),IF(Y20<=10,"Y","N"),"N")) -> N | FZ20: =IF(FY20="Y",Y20,"") | GA20: =IF($A20="","",IF(AND(I20="walk-in",CN20="pass",U20="new",FT20="N",FV20="N",AQ20<>"Y"),"Y","N")) -> N | GB20: =IF(GA20<>"Y","",IF(COUNTIFS($GA$2:$GA$1000,"Y",$J$2:$J$1000,">"&J20)+COUNTIFS($GA$2:$GA$1000,"Y",$J$2:$J$1000,J20,$GD$2:$GD$1000,"<"&GD20)+1<=25,COUNTIFS($GA$2:$GA$1000,"Y",$J$2:$J$1000,">"&J20)+COUNTIFS($GA$2:$GA$1000,"Y",$J$2:$J$1000,J20,$GD$2:$GD$1000,"<"&GD20)+1,"")) | GC20: =IF(AND(_xlfn.ISFORMULA(C20),_xlfn.ISFORMULA(J20)),"Y","N") -> N | GD20: =ROW()-1 -> 19
A21: AO-C-157 | B21: Primary Venture Partners | C21: https://www.primary.vc | D21: primary.vc | E21: 28 | F21: 58.8 | G21: Y | H21: Alexandra | I21: Lappas | J21: Office Manager | L21: pantry or office lead (primary) | M21: verified-page | N21: employer's own site | O21: https://www.primary.vc/people | P21: 2026-10-24 | Q21: Emma | R21: Balin | S21: VP Strategy, Chief of Staff | U21: pantry or office lead (backup) | V21: verified-page | W21: employer's own site | X21: https://www.primary.vc/people | Y21: 2026-10-24 | Z21: Emma Balin | AB21: title_match=target; Operations section, same page (opened 2026-10-24). Other Operations staff on the page: Lily Moran, Receptionist, and five Executive Assistants (none labelled EA to the managing partner). | AC21: likely | AE21: 386 Park Avenue South | AF21: 13-14 | AG21: venture capital | AH21: 40 | AI21: https://www.linkedin.com/company/primary-venture-partners | AJ21: Y | AK21: 40-75 | AL21: Y | AM21: 168 | AN21: low | AO21: in-office-5 | AP21: AO-C-262 | AQ21: N | AT21: =IF($A21="","",IF(AND(CN21="pass",AQ21<>"Y",C21<>"",OR(AX21<>"Y",AV21="Y")),"Y","N")) -> Y | AU21: =IF($A21="","",_xlfn.TEXTJOIN("; ",TRUE(),IF(CN21<>"pass","gated out",""),IF(AQ21="Y","on hold: "&AR21,""),IF(C21="","no contact named on an opened page",""),IF(AND(AX21="Y",AV21<>"Y"),"Tuesday estimate band "&L21&": founder's call",""))) | AX21: N | AY21: Manuela | AZ21: Montagnana | BA21: Chief People Officer | BC21: =IF($A21="","",IFERROR(INDEX(Enrichment!$A$2:$GZ$2000,MATCH($A21,INDEX(Enrichment!$A$2:$GZ$2000,0,MATCH("row_id",Enrichment!$A$1:$GZ$1,0)),0),MATCH("work_email",Enrichment!$A$1:$GZ$1,0))&"","")) | BD21: =IF($A21="","",IF(BC21="","none",IF(OR(IFERROR(INDEX(Enrichment!$A$2:$GZ$2000,MATCH($A21,INDEX(Enrichment!$A$2:$GZ$2000,0,MATCH("row_id",Enrichment!$A$1:$GZ$1,0)),0),MATCH("email_status",Enrichment!$A$1:$GZ$1,0))&"","")="verified",IFERROR(INDEX(Enrichment!$A$2:$GZ$2000,MATCH($A21,INDEX(Enrichment!$A$2:$GZ$2000,0,MATCH("row_id",Enrichment!$A$1:$GZ$1,0)),0),MATCH("email_status",Enrichment!$A$1:$GZ$1,0))&"","")="unverified"),IFERROR(INDEX(Enrichment!$A$2:$GZ$2000,MATCH($A21,INDEX(Enrichment!$A$2:$GZ$2000,0,MATCH("row_id",Enrichment!$A$1:$GZ$1,0)),0),MATCH("email_status",Enrichment!$A$1:$GZ$1,0))&"",""),"unverified"))) -> none | BE21: pantry or office lead (primary) | BF21: crowd-listed | BG21: The Org (crowd-edited org chart) | BH21: https://theorg.com/org/criteo/person/manuela-montagnana | BI21: 2026-10-24 | BJ21: adjacent | BK21: find Manuela Montagnana at Criteo on LinkedIn and paste the profile URL into primary_linkedin_url (this also confirms the name: The Org is crowd-edited and marks it Unverified); the source is dated 2024-11-04: check Manuela still holds the role; adjacent title: ask who runs the pantry | BL21: adjacent contact named (Chief People Officer) (crowd-listed on The Org) | BQ21: =IF($A21="","",IFERROR(INDEX(Enrichment!$A$2:$GZ$2000,MATCH($A21,INDEX(Enrichment!$A$2:$GZ$2000,0,MATCH("row_id",Enrichment!$A$1:$GZ$1,0)),0),MATCH("backup_work_email",Enrichment!$A$1:$GZ$1,0))&"","")) | BR21: =IF($A21="","",IF(BQ21="","none",IF(OR(IFERROR(INDEX(Enrichment!$A$2:$GZ$2000,MATCH($A21,INDEX(Enrichment!$A$2:$GZ$2000,0,MATCH("row_id",Enrichment!$A$1:$GZ$1,0)),0),MATCH("backup_email_status",Enrichment!$A$1:$GZ$1,0))&"","")="verified",IFERROR(INDEX(Enrichment!$A$2:$GZ$2000,MATCH($A21,INDEX(Enrichment!$A$2:$GZ$2000,0,MATCH("row_id",Enrichment!$A$1:$GZ$1,0)),0),MATCH("backup_email_status",Enrichment!$A$1:$GZ$1,0))&"","")="unverified"),IFERROR(INDEX(Enrichment!$A$2:$GZ$2000,MATCH($A21,INDEX(Enrichment!$A$2:$GZ$2000,0,MATCH("row_id",Enrichment!$A$1:$GZ$1,0)),0),MATCH("backup_email_status",Enrichment!$A$1:$GZ$1,0))&"",""),"unverified"))) -> none | BT21: none | BX21: none | BY21: no backup named: back to research | BZ21: no backup contact named | CA21: Tuesday estimate 84 to 168 (low confidence), 1,001 to 4,999 staff company-wide, on-site 5 days a week per its profile, occupied at a high-confidence address | CB21: linkedin | CC21: Manuela Montagnana | CD21: 2024-11-04 | CE21: ny_base=confirmed; title_fit=adjacent (global people lead). The Org position page (opened 2026-10-24, updated 2024-11-04) attaches her to Criteo's New York office. A global executive: ask who runs the New York office. | CF21: confirmed | CM21: Y | CN21: pass | CO21: passes all hard gates | CP21: company | CQ21: B-C-262 | CR21: https://www.criteo.com | CS21: adtech (commerce media) | CT21: 2868 | CV21: over-500 | CW21: whole-company | CX21: single-source | CY21: https://www.builtinnyc.com/company/criteo/offices | DA21: 1001-4999 | DB21: unknown | DC21: unknown | DD21: unknown | DE21: https://www.linkedin.com/company/criteo | DF21: 10016 | DG21: 40.742833 | DH21: -73.984174 | DI21: Y | DJ21: 0 | DK21: B-B-073 | DL21: 387 Park Avenue South (TF Cornerstone) | DM21: https://commercialobserver.com/2024/11/criteo-lease-387-park-avenue-south/ | DN21: 2024-11-19 | DO21: leasing-press | DP21: https://www.builtinnyc.com/company/criteo/offices | DQ21: 2026-10-23 | DS21: high | DU21: N | DX21: unknown | EA21: unknown | EB21: N | EC21: Built In workplace type: OnSite Workplace; typical time on-site: 5 days a week; recent job tags: 3 In-Office | ED21: https://www.builtinnyc.com/company/criteo/offices | EE21: 2026-10-24 | EF21: 119 | EH21: Y | EI21: 2868 (Built In) staff (whole-company count) x 5% to 100% of them in the New York office (HQ city unknown; share assumed) x 57% (Partnership for NYC, all Manhattan firms; no figure for 500 to 4,999) in on a weekday; space-based for a company headquartered outside New York: 21,000 sf seats 84 to 168 at 250 to 125 sf per person, kept within the headcount math (82 to 1635) (largest square footage the sources mention at this address; if the company holds more space here, intake corrects it) = 84 to 168, central 119; low confidence; estimate until intake replaces it. | EJ21: estimate until intake replaces it | EK21: 1 | EL21: 62 | EM21: 25 | EN21: 2 | EO21: 15 | EP21: 15 | EQ21: =IF($A21="","",IF(AH21="exact",10,IF(AH21="adjacent",5,0))) -> 0 | ER21: =IF($A21="","",IF(R21="Y",15,0)) -> 0 | ES21: near-miss-over-500 | ET21: over-1,000 (1,001 to 4,999) | EU21: N | EV21: 21,000 sf | EW21: B's sources | EX21: CO 2024-11-19: 10-year extension on the 21,000 SF penthouse it has leased since 2015 at the top of 387 PAS. Built In lists 387 Park Ave S and 100 Avenue of the Americas; 2,868 total employees. Over 500: near-miss. Review round 2: corner lot: the lot-centroid pin sat 24 m from E 27 ST but 34 m from PARK AVE S, so it was moved to the PARK AVE S frontage near the corner (13 m from the PARK AVE S centreline, 26 m from E 27 ST; 21 m from the old pin). Tax lot unchanged. | EZ21: linked from the company's own site (https://www.criteo.com/, opened 2026-10-24); LinkedIn not opened | FS21: =IF($A21="","",IF(ISNUMBER(MATCH(U21,{"queued","contacted","replied","call_booked","call_done","yes_in_principle","materials_sent"},0)),"Y","N")) -> N | FT21: =IF($A21="","",IF(OR(T21="Y",U21="do_not_contact",AS21&""<>""),"Y","N")) -> N | FU21: =IF($A21="","",IF(AP21&""<>"",AP21&"",$A21)) -> AO-C-262 | FV21: =IF($A21="","",IF(COUNTIFS($FU$2:$FU$1000,FU21,$FS$2:$FS$1000,"Y")+COUNTIFS($FU$2:$FU$1000,FU21,$FT$2:$FT$1000,"Y")>0,"Y","N")) -> N | FW21: =IF($A21="","",IF(AND(U21="new",T21="N",FT21="N",AT21="Y",FV21="N"),"Y","N")) -> N | FX21: =IF($A21="","",IF(FW21<>"Y","N",IF(COUNTIFS($FU$2:$FU$1000,FU21,$FW$2:$FW$1000,"Y",$J$2:$J$1000,">"&J21)+COUNTIFS($FU$2:$FU$1000,FU21,$FW$2:$FW$1000,"Y",$J$2:$J$1000,J21,$GD$2:$GD$1000,"<"&GD21)=0,"Y","N"))) -> N | FY21: =IF($A21="","",IF(AND(FW21="Y",FX21="Y",Y21&""<>""),IF(Y21<=10,"Y","N"),"N")) -> N | FZ21: =IF(FY21="Y",Y21,"") | GA21: =IF($A21="","",IF(AND(I21="walk-in",CN21="pass",U21="new",FT21="N",FV21="N",AQ21<>"Y"),"Y","N")) -> N | GB21: =IF(GA21<>"Y","",IF(COUNTIFS($GA$2:$GA$1000,"Y",$J$2:$J$1000,">"&J21)+COUNTIFS($GA$2:$GA$1000,"Y",$J$2:$J$1000,J21,$GD$2:$GD$1000,"<"&GD21)+1<=25,COUNTIFS($GA$2:$GA$1000,"Y",$J$2:$J$1000,">"&J21)+COUNTIFS($GA$2:$GA$1000,"Y",$J$2:$J$1000,J21,$GD$2:$GD$1000,"<"&GD21)+1,"")) | GC21: =IF(AND(_xlfn.ISFORMULA(C21),_xlfn.ISFORMULA(J21)),"Y","N") -> N | GD21: =ROW()-1 -> 20
A22: AO-C-028 | B22: Valon | C22: https://valon.ai | D22: valon.ai | E22: 30 | F22: 58.0 | G22: Y | H22: Marisa | I22: Rackson | J22: Head of People | L22: pantry or office lead (primary) | M22: verified-page | N22: employer's own site | O22: https://www.valon.ai/about | P22: 2026-10-24 | Q22: Ariel | R22: Brito | S22: Chief of Staff | U22: pantry or office lead (backup) | V22: verified-page | W22: employer's own site | X22: https://www.valon.ai/about | Y22: 2026-10-24 | Z22: Ariel Brito | AB22: title_match=adjacent; Same page (opened 2026-10-24); city not stated. | AC22: likely | AE22: 860 Broadway | AF22: 4 | AG22: fintech (mortgage servicing software) | AH22: 529 | AI22: https://www.linkedin.com/company/valon-technologies | AJ22: Y | AK22: 76-150 | AL22: Y | AM22: 151 | AN22: low | AO22: hybrid-unspecified | AP22: AO-C-098 | AQ22: N | AT22: =IF($A22="","",IF(AND(CN22="pass",AQ22<>"Y",C22<>"",OR(AX22<>"Y",AV22="Y")),"Y","N")) -> Y | AU22: =IF($A22="","",_xlfn.TEXTJOIN("; ",TRUE(),IF(CN22<>"pass","gated out",""),IF(AQ22="Y","on hold: "&AR22,""),IF(C22="","no contact named on an opened page",""),IF(AND(AX22="Y",AV22<>"Y"),"Tuesday estimate band "&L22&": founder's call",""))) | AX22: N | AY22: Lilly | AZ22: Santiago | BA22: Executive Assistant to Chief Executive Officer/Office Coordinator | BC22: =IF($A22="","",IFERROR(INDEX(Enrichment!$A$2:$GZ$2000,MATCH($A22,INDEX(Enrichment!$A$2:$GZ$2000,0,MATCH("row_id",Enrichment!$A$1:$GZ$1,0)),0),MATCH("work_email",Enrichment!$A$1:$GZ$1,0))&"","")) | BD22: =IF($A22="","",IF(BC22="","none",IF(OR(IFERROR(INDEX(Enrichment!$A$2:$GZ$2000,MATCH($A22,INDEX(Enrichment!$A$2:$GZ$2000,0,MATCH("row_id",Enrichment!$A$1:$GZ$1,0)),0),MATCH("email_status",Enrichment!$A$1:$GZ$1,0))&"","")="verified",IFERROR(INDEX(Enrichment!$A$2:$GZ$2000,MATCH($A22,INDEX(Enrichment!$A$2:$GZ$2000,0,MATCH("row_id",Enrichment!$A$1:$GZ$1,0)),0),MATCH("email_status",Enrichment!$A$1:$GZ$1,0))&"","")="unverified"),IFERROR(INDEX(Enrichment!$A$2:$GZ$2000,MATCH($A22,INDEX(Enrichment!$A$2:$GZ$2000,0,MATCH("row_id",Enrichment!$A$1:$GZ$1,0)),0),MATCH("email_status",Enrichment!$A$1:$GZ$1,0))&"",""),"unverified"))) -> none | BE22: pantry or office lead (primary) | BF22: crowd-listed | BG22: The Org (crowd-edited org chart) | BH22: https://theorg.com/org/brainpop/person/lilly-santiago | BI22: 2026-10-24 | BJ22: adjacent | BK22: find Lilly Santiago at BrainPOP on LinkedIn and paste the profile URL into primary_linkedin_url (this also confirms the name: The Org is crowd-edited and marks it Unverified); check Lilly works from the New York office; adjacent title: ask who runs the pantry | BL22: adjacent contact named (Executive Assistant to Chief Executive Officer/Office Coordinator) (crowd-listed on The Org) | BM22: Crystal | BN22: Spence | BO22: Operations Lead, Office of CEO | BQ22: =IF($A22="","",IFERROR(INDEX(Enrichment!$A$2:$GZ$2000,MATCH($A22,INDEX(Enrichment!$A$2:$GZ$2000,0,MATCH("row_id",Enrichment!$A$1:$GZ$1,0)),0),MATCH("backup_work_email",Enrichment!$A$1:$GZ$1,0))&"","")) | BR22: =IF($A22="","",IF(BQ22="","none",IF(OR(IFERROR(INDEX(Enrichment!$A$2:$GZ$2000,MATCH($A22,INDEX(Enrichment!$A$2:$GZ$2000,0,MATCH("row_id",Enrichment!$A$1:$GZ$1,0)),0),MATCH("backup_email_status",Enrichment!$A$1:$GZ$1,0))&"","")="verified",IFERROR(INDEX(Enrichment!$A$2:$GZ$2000,MATCH($A22,INDEX(Enrichment!$A$2:$GZ$2000,0,MATCH("row_id",Enrichment!$A$1:$GZ$1,0)),0),MATCH("backup_email_status",Enrichment!$A$1:$GZ$1,0))&"","")="unverified"),IFERROR(INDEX(Enrichment!$A$2:$GZ$2000,MATCH($A22,INDEX(Enrichment!$A$2:$GZ$2000,0,MATCH("row_id",Enrichment!$A$1:$GZ$1,0)),0),MATCH("backup_email_status",Enrichment!$A$1:$GZ$1,0))&"",""),"unverified"))) -> none | BS22: pantry or office lead (backup) | BT22: crowd-listed | BU22: The Org (crowd-edited org chart) | BV22: https://theorg.com/org/brainpop/person/crystal-spence | BW22: 2026-10-24 | BX22: adjacent | BY22: find Crystal Spence at BrainPOP on LinkedIn and paste the profile URL into backup_linkedin_url (this also confirms the name: The Org is crowd-edited and marks it Unverified); adjacent title: ask who runs the pantry | BZ22: adjacent contact named (Operations Lead, Office of CEO) (crowd-listed on The Org) | CA22: Tuesday estimate 75 to 151 (low confidence), under 500 staff company-wide with a named parent (Kirkbi A/S), hybrid (days not stated), occupied at a medium-confidence address | CB22: linkedin | CC22: Lilly Santiago | CD22: 2026-02-12 | CE22: ny_base=unconfirmed (The Org location says only 'United States', no office attached; BrainPOP HQ is New York); title_fit=family (EA to CEO and office coordinator; The Org shows her reporting to the CEO, Lorin Thomas-Tavel). The Org updated 2026-02-12. | CF22: unconfirmed | CH22: Crystal Spence | CI22: 2026-01-20 | CJ22: ny_base=confirmed (The Org attaches the role to BrainPOP's New York HQ office); title_fit=variant (office of the CEO). The Org updated 2026-01-20. | CK22: confirmed | CM22: Y | CN22: pass | CO22: passes all hard gates | CP22: company | CQ22: B-C-098 | CR22: https://www.brainpop.com/ | CS22: Education technology | CT22: 225 | CV22: 151-250 | CW22: whole-company | CX22: single-source | CY22: https://www.builtinnyc.com/company/brainpop/offices | DA22: le500 | DB22: New York | DC22: Y | DD22: Kirkbi A/S | DE22: unknown | DF22: 10010 | DG22: 40.743043 | DH22: -73.99233 | DI22: Y | DJ22: 0 | DK22: B-B-048 | DL22: 71 West 23rd Street | DM22: https://www.brainpop.com/discover/terms-of-use | DN22: 2026-10-24 | DO22: company-site | DP22: https://www.builtinnyc.com/company/brainpop/offices | DQ22: 2026-10-24 | DS22: medium | DU22: N | DX22: unknown | EA22: unknown | EB22: N | EC22: Built In workplace type: Hybrid Workplace; typical time on-site: Flexible | ED22: https://www.builtinnyc.com/company/brainpop/offices | EE22: 2026-10-24 | EF22: 106 | EH22: N | EI22: 225 (Built In) staff (whole-company count) x 50% to 100% of them in the New York office (HQ New York; share assumed) x 67% (Partnership for NYC, firms under 500) in on a weekday = 75 to 151, central 106; low confidence; estimate until intake replaces it. | EJ22: estimate until intake replaces it | EK22: 1 | EL22: 61 | EM22: 25 | EN22: 11 | EO22: 7 | EP22: 13 | EQ22: =IF($A22="","",IF(AH22="exact",10,IF(AH22="adjacent",5,0))) -> 0 | ER22: =IF($A22="","",IF(R22="Y",15,0)) -> 0 | ES22: candidate | EX22: Terms of use and privacy policy (live) give '71 W 23rd St., 17th Fl. New York, NY 10010'. Built In (independent): HQ New York, office in the Flatiron district 'down the street from the iconic landmark Flatiron Building and Madison Square Park'; 225 total employees. | Assembly 2026-10-24: Review round 3: Built In is an employer-editable profile, so it no longer counts as the independent confirmation of the company's own page. The only independent source found is CO 2010-08-10 (opened 2026-10-24): a 15-year lease for the entire 17th floor, so its stated term ended about 2025 and it cannot confirm the office today. The row is medium on its own live page. Confidence lowered at assembly from high to medium: review round 3: the second source is an employer-editable profile (Built In), which does not independently confirm the company's own page. | FS22: =IF($A22="","",IF(ISNUMBER(MATCH(U22,{"queued","contacted","replied","call_booked","call_done","yes_in_principle","materials_sent"},0)),"Y","N")) -> N | FT22: =IF($A22="","",IF(OR(T22="Y",U22="do_not_contact",AS22&""<>""),"Y","N")) -> N | FU22: =IF($A22="","",IF(AP22&""<>"",AP22&"",$A22)) -> AO-C-098 | FV22: =IF($A22="","",IF(COUNTIFS($FU$2:$FU$1000,FU22,$FS$2:$FS$1000,"Y")+COUNTIFS($FU$2:$FU$1000,FU22,$FT$2:$FT$1000,"Y")>0,"Y","N")) -> N | FW22: =IF($A22="","",IF(AND(U22="new",T22="N",FT22="N",AT22="Y",FV22="N"),"Y","N")) -> N | FX22: =IF($A22="","",IF(FW22<>"Y","N",IF(COUNTIFS($FU$2:$FU$1000,FU22,$FW$2:$FW$1000,"Y",$J$2:$J$1000,">"&J22)+COUNTIFS($FU$2:$FU$1000,FU22,$FW$2:$FW$1000,"Y",$J$2:$J$1000,J22,$GD$2:$GD$1000,"<"&GD22)=0,"Y","N"))) -> N | FY22: =IF($A22="","",IF(AND(FW22="Y",FX22="Y",Y22&""<>""),IF(Y22<=10,"Y","N"),"N")) -> N | FZ22: =IF(FY22="Y",Y22,"") | GA22: =IF($A22="","",IF(AND(I22="walk-in",CN22="pass",U22="new",FT22="N",FV22="N",AQ22<>"Y"),"Y","N")) -> N | GB22: =IF(GA22<>"Y","",IF(COUNTIFS($GA$2:$GA$1000,"Y",$J$2:$J$1000,">"&J22)+COUNTIFS($GA$2:$GA$1000,"Y",$J$2:$J$1000,J22,$GD$2:$GD$1000,"<"&GD22)+1<=25,COUNTIFS($GA$2:$GA$1000,"Y",$J$2:$J$1000,">"&J22)+COUNTIFS($GA$2:$GA$1000,"Y",$J$2:$J$1000,J22,$GD$2:$GD$1000,"<"&GD22)+1,"")) | GC22: =IF(AND(_xlfn.ISFORMULA(C22),_xlfn.ISFORMULA(J22)),"Y","N") -> N | GD22: =ROW()-1 -> 21
A23: AO-C-155 | B23: Primary Wave | C23: https://www.primarywave.com | D23: primarywave.com | E23: 32 | F23: 57.8 | G23: Y | H23: Sophia | I23: Popovits | J23: NY Facilities and Culture Manager | L23: pantry or office lead (primary) | M23: verified-page | N23: employer's own site | O23: https://primarywave.com/team/?filter=human-resources | P23: 2026-10-24 | Q23: Shevonne | R23: James | S23: Senior Human Resources Manager | U23: pantry or office lead (backup) | V23: verified-page | W23: employer's own site | X23: https://primarywave.com/team/?filter=human-resources | Y23: 2026-10-24 | Z23: Shevonne James | AB23: title_match=target; Same page (opened 2026-10-24); city not stated. Also on the tab: Mike Chorny, Operations Manager / IT, and Jessica Wilkins, Senior Executive Assistant (executive not named). | AC23: likely | AE23: 1165 Broadway | AF23: 5 (per site; CO 2024: top two floors) | AG23: music publishing and marketing | AH23: 109 | AI23: unknown | AJ23: Y | AK23: 40-75 | AL23: Y | AM23: 179 | AN23: low | AO23: in-office-5 | AP23: AO-C-061 | AQ23: N | AT23: =IF($A23="","",IF(AND(CN23="pass",AQ23<>"Y",C23<>"",OR(AX23<>"Y",AV23="Y")),"Y","N")) -> Y | AU23: =IF($A23="","",_xlfn.TEXTJOIN("; ",TRUE(),IF(CN23<>"pass","gated out",""),IF(AQ23="Y","on hold: "&AR23,""),IF(C23="","no contact named on an opened page",""),IF(AND(AX23="Y",AV23<>"Y"),"Tuesday estimate band "&L23&": founder's call",""))) | AX23: N | AY23: Jessica | AZ23: Lawson | BA23: Chief of Staff | BC23: =IF($A23="","",IFERROR(INDEX(Enrichment!$A$2:$GZ$2000,MATCH($A23,INDEX(Enrichment!$A$2:$GZ$2000,0,MATCH("row_id",Enrichment!$A$1:$GZ$1,0)),0),MATCH("work_email",Enrichment!$A$1:$GZ$1,0))&"","")) | BD23: =IF($A23="","",IF(BC23="","none",IF(OR(IFERROR(INDEX(Enrichment!$A$2:$GZ$2000,MATCH($A23,INDEX(Enrichment!$A$2:$GZ$2000,0,MATCH("row_id",Enrichment!$A$1:$GZ$1,0)),0),MATCH("email_status",Enrichment!$A$1:$GZ$1,0))&"","")="verified",IFERROR(INDEX(Enrichment!$A$2:$GZ$2000,MATCH($A23,INDEX(Enrichment!$A$2:$GZ$2000,0,MATCH("row_id",Enrichment!$A$1:$GZ$1,0)),0),MATCH("email_status",Enrichment!$A$1:$GZ$1,0))&"","")="unverified"),IFERROR(INDEX(Enrichment!$A$2:$GZ$2000,MATCH($A23,INDEX(Enrichment!$A$2:$GZ$2000,0,MATCH("row_id",Enrichment!$A$1:$GZ$1,0)),0),MATCH("email_status",Enrichment!$A$1:$GZ$1,0))&"",""),"unverified"))) -> none | BE23: pantry or office lead (primary) | BF23: crowd-listed | BG23: The Org (crowd-edited org chart) | BH23: https://theorg.com/org/daily-harvest/person/jessica-lawson | BI23: 2026-10-24 | BJ23: adjacent | BK23: find Jessica Lawson at Daily Harvest on LinkedIn and paste the profile URL into primary_linkedin_url (this also confirms the name: The Org is crowd-edited and marks it Unverified); the source is dated 2024-03-04: check Jessica still holds the role; check Jessica works from the New York office; adjacent title: ask who runs the pantry | BL23: adjacent contact named (Chief of Staff) (crowd-listed on The Org) | BQ23: =IF($A23="","",IFERROR(INDEX(Enrichment!$A$2:$GZ$2000,MATCH($A23,INDEX(Enrichment!$A$2:$GZ$2000,0,MATCH("row_id",Enrichment!$A$1:$GZ$1,0)),0),MATCH("backup_work_email",Enrichment!$A$1:$GZ$1,0))&"","")) | BR23: =IF($A23="","",IF(BQ23="","none",IF(OR(IFERROR(INDEX(Enrichment!$A$2:$GZ$2000,MATCH($A23,INDEX(Enrichment!$A$2:$GZ$2000,0,MATCH("row_id",Enrichment!$A$1:$GZ$1,0)),0),MATCH("backup_email_status",Enrichment!$A$1:$GZ$1,0))&"","")="verified",IFERROR(INDEX(Enrichment!$A$2:$GZ$2000,MATCH($A23,INDEX(Enrichment!$A$2:$GZ$2000,0,MATCH("row_id",Enrichment!$A$1:$GZ$1,0)),0),MATCH("backup_email_status",Enrichment!$A$1:$GZ$1,0))&"","")="unverified"),IFERROR(INDEX(Enrichment!$A$2:$GZ$2000,MATCH($A23,INDEX(Enrichment!$A$2:$GZ$2000,0,MATCH("row_id",Enrichment!$A$1:$GZ$1,0)),0),MATCH("backup_email_status",Enrichment!$A$1:$GZ$1,0))&"",""),"unverified"))) -> none | BT23: none | BX23: none | BY23: no backup named: back to research | BZ23: no backup contact named | CA23: Tuesday estimate 89 to 179 (low confidence), under 500 staff company-wide with a named parent (Chobani), on-site 5 days a week per its profile, occupancy-unconfirmed at a low-confidence address | CB23: linkedin | CC23: Jessica Lawson | CD23: 2024-03-04 | CE23: ny_base=unconfirmed (no location or office on The Org); title_fit=variant (chief of staff). The Org last updated 2024-03-04, so this may be stale: founder to confirm. The Org's Daily Harvest office record is 1115 Broadway; B has 37 West 20th Street (occupancy-unconfirmed). | CF23: unconfirmed | CM23: Y | CN23: pass | CO23: passes all hard gates | CP23: company | CQ23: B-C-061 | CR23: https://www.daily-harvest.com | CS23: food brand (frozen meals, DTC) | CT23: 267 | CV23: 251-500 | CW23: whole-company | CX23: single-source | CY23: https://www.builtinnyc.com/company/daily-harvest | DA23: le500 | DB23: New York | DC23: Y | DD23: Chobani | DE23: https://www.linkedin.com/company/daily-harvest | DF23: 10011 | DG23: 40.740813 | DH23: -73.993107 | DI23: Y | DJ23: 0 | DK23: B-B-030 | DL23: 37 West 20th Street | DM23: https://www.builtinnyc.com/company/daily-harvest/offices | DN23: 2026-10-23 | DO23: builtin | DS23: low | DU23: N | DX23: security desk | DY23: https://www.metro-manhattan.com/buildings/37-west-20th-street-office-space-for-lease/ | EA23: unknown | EB23: N | EC23: Built In lists HQ at 37 West 20th Street and an on-site workplace, typical time on-site 5 days a week. Built In shows 267 total emp | ED23: https://www.builtinnyc.com/company/daily-harvest | EE23: 2026-10-23 | EF23: 126 | EH23: N | EI23: 267 (Built In) staff (whole-company count) x 50% to 100% of them in the New York office (HQ New York; share assumed) x 67% (Partnership for NYC, firms under 500) in on a weekday = 89 to 179, central 126; low confidence; estimate until intake replaces it. | EJ23: estimate until intake replaces it | EK23: 1 | EL23: 61 | EM23: 25 | EN23: 11 | EO23: 15 | EP23: 5 | EQ23: =IF($A23="","",IF(AH23="exact",10,IF(AH23="adjacent",5,0))) -> 0 | ER23: =IF($A23="","",IF(R23="Y",15,0)) -> 0 | ES23: candidate | EX23: Built In lists HQ at 37 West 20th Street and an on-site workplace, typical time on-site 5 days a week. Built In shows 267 total employees. Company terms/privacy URLs returned 404, so not cross-checked. Food company: possible brand-side contact too (frozen, so not an eligible product: refrigerated and frozen goods are excluded). | Assembly 2026-10-24: Confidence lowered at assembly from medium to low: review round 2: the only source dated within 24 months is an undated third-party profile (Built In, Deskpass or LiquidSpace), which can only confirm a dated or own-site source. Review round 3: lease status set from occupied to occupancy-unconfirmed: only an undated profile places it here (Built In, Deskpass or LiquidSpace), and B treats such profiles as often stale. Check the lobby directory on the walk. | EZ23: linked from The Org's company record (https://theorg.com/org/daily-harvest, opened 2026-10-24); LinkedIn not opened | FS23: =IF($A23="","",IF(ISNUMBER(MATCH(U23,{"queued","contacted","replied","call_booked","call_done","yes_in_principle","materials_sent"},0)),"Y","N")) -> N | FT23: =IF($A23="","",IF(OR(T23="Y",U23="do_not_contact",AS23&""<>""),"Y","N")) -> N | FU23: =IF($A23="","",IF(AP23&""<>"",AP23&"",$A23)) -> AO-C-061 | FV23: =IF($A23="","",IF(COUNTIFS($FU$2:$FU$1000,FU23,$FS$2:$FS$1000,"Y")+COUNTIFS($FU$2:$FU$1000,FU23,$FT$2:$FT$1000,"Y")>0,"Y","N")) -> N | FW23: =IF($A23="","",IF(AND(U23="new",T23="N",FT23="N",AT23="Y",FV23="N"),"Y","N")) -> N | FX23: =IF($A23="","",IF(FW23<>"Y","N",IF(COUNTIFS($FU$2:$FU$1000,FU23,$FW$2:$FW$1000,"Y",$J$2:$J$1000,">"&J23)+COUNTIFS($FU$2:$FU$1000,FU23,$FW$2:$FW$1000,"Y",$J$2:$J$1000,J23,$GD$2:$GD$1000,"<"&GD23)=0,"Y","N"))) -> N | FY23: =IF($A23="","",IF(AND(FW23="Y",FX23="Y",Y23&""<>""),IF(Y23<=10,"Y","N"),"N")) -> N | FZ23: =IF(FY23="Y",Y23,"") | GA23: =IF($A23="","",IF(AND(I23="walk-in",CN23="pass",U23="new",FT23="N",FV23="N",AQ23<>"Y"),"Y","N")) -> N | GB23: =IF(GA23<>"Y","",IF(COUNTIFS($GA$2:$GA$1000,"Y",$J$2:$J$1000,">"&J23)+COUNTIFS($GA$2:$GA$1000,"Y",$J$2:$J$1000,J23,$GD$2:$GD$1000,"<"&GD23)+1<=25,COUNTIFS($GA$2:$GA$1000,"Y",$J$2:$J$1000,">"&J23)+COUNTIFS($GA$2:$GA$1000,"Y",$J$2:$J$1000,J23,$GD$2:$GD$1000,"<"&GD23)+1,"")) | GC23: =IF(AND(_xlfn.ISFORMULA(C23),_xlfn.ISFORMULA(J23)),"Y","N") -> N | GD23: =ROW()-1 -> 22
