Workbook

Sheet README
A1: =Inputs!$C$8&" financial model v1: README" -> Desk Drop financial model v1: README
A2: Version 1, built 2026-10-23 to 2026-10-24. The company name lives in one cell (Inputs, section 1, 'Company name'); rename it there only.
A5: What this workbook is
A6: The workbook you open every week for six months to see whether the business is working. It answers three questions: what each drop earns per founder hour, how low cumulative cash goes and when, and which gate or decision scenario the real numbers point to.
A7: Every number is a planning estimate from plan.md or the legal pack, never a forecast; fees the legal pack verified say 'verified' and the date on Inputs. Every assumption sits in one labeled cell on Inputs with its unit and source. Every other number is a formula. Change one input and every output moves. The only typed figures outside Inputs are the plan's own numbers, kept for comparison on purpose: the Plan_Check cases, the plan columns on Capital, and the 'Plan reading (e), fixed for comparison' row on Steady_State.
A9: Your weekly routine (about ten minutes)
A10: 1. Log hours | B10: Add the week's hours on Hours_Log (one row per entry: date, drop_id or blank, activity key, hours). If you use a paid Toggl plan, paste its export on Toggl_Import instead.
A11: 2. Log the pipeline | B11: Paste or type outreach events on Pipeline: conversations, yeses, signed offices with Tuesday headcount, paid brands, budget-probe answers, renewal answers.
A12: 3. After each drop | B12: Paste the campaign actuals and drop costs from the operations exports into Actuals_Campaigns and Actuals_DropCosts. Set 'Actuals in' to Y for that drop on Schedule once revenue, payments, direct costs and hours are final (by T+10, the debrief). code_redemptions_day30 (T+30) and renewal answers can be filled in later: they move no money or hours. The Gate 3 rate stays 'not yet' until every standard run dated by the review has actuals in. Dates must arrive as real dates and amounts as numbers: if Checks says 'stored as text', see 'Dates and amounts' below.
A13: 4. Read the Dashboard | B13: Next to 'Checks' it should say 'all integrity and data checks pass'; if not, open Checks first, because a failing data check means pasted rows are being ignored. Gates show pass, miss or not yet against real numbers only. The headline shows the next drop's contribution per hour, the price in force, the lowest point of cash and the gap to the plan's $6,510.
A14: 5. Check against the bank (optional) | B14: Type your actual bank balance at the end of the week on Cash_Flow, row 30. Row 31 shows the variance against the model; the summary shows the latest week.
A15: 6. Keep the plan current | B15: Edit Schedule when a date, delivery model or brand count changes. Edit Inputs when a quote comes in. The 'Changed?' column records every edit against the plan default.
A17: Change the price and read the result in under a minute
A18: Whole model | B18: ="Inputs, section 3, 'Standard price per office' (now "&TEXT(Inputs!$C$39,"$#,##0")&"). Type a new number. On the Dashboard read 'Price in force' (it shows your number), then "&"'A standard drop at that price: contribution per founder hour' (the next row), 'Standard runs to Gate 3' and the drop table at the bottom. "&"'Its contribution per founder hour' does not move: the next drop is campaign zero, at the founding rate." -> Inputs, section 3, 'Standard price per office' (now $150). Type a new number. On the Dashboard read 'Price in force' (it shows your number), then 'A standard drop at that price: contribution per founder hour' (the next row), 'Standard runs to Gate 3' and the drop table at the bottom. 'Its contribution per founder hour' does not move: the next drop is campaign zero, at the founding rate.
A19: One drop only | B19: Calculator: type a price in 'Standard price per office'. The result column shows revenue, costs, hours and contribution per founder hour. Nothing else changes.
A20: Many prices at once | B20: Sensitivity, Table 1: contribution per founder hour for eight prices and one to five brands. Green cells clear the $50 Gate 3 target.
A22: Tabs, in the order you use them
A23: Dashboard | B23: Headline numbers; cash at each stop point (paid out, brand cash received, refunds owed on campaigns not yet run, and the net if you stop at each gate); every gate threshold beside its live value with pass, miss or not yet; the decision rule, the scenario the numbers point to, six-month goals, and contribution per hour on each drop.
A24: Inputs | B24: Every assumption: prices, payment terms and lags, the processing toggle, units, every hard-cost line, monthly overhead, hours by activity, the delivery-model table, renewal, gates, startup outlays with timing, the start date. Yellow cells are inputs.
A25: Scenarios | B25: The plan's decision situations A to D as assumption sets, beside the plan base. Pick one on Inputs. It drives the two decision-window drops and the steady state.
A26: Schedule | B26: The editable drop schedule: date, delivery model, tier, offices, new offices, brands, renewals, and the switch to actuals. Checks Tuesday or Wednesday and every blackout. Columns Y to AE show the brand wins and qualified conversations each drop needs, cumulated to its sign-by date, beside the Pipeline's actual counts; AF to AH flag a decision-window drop whose debrief lands after the decision date; AI shows the offices to add so no office gets two drops within four weeks. A drop you add takes the next spare drop_id (DRP-006 onward) and may sit out of date order: that is fine, because every total, the cash flow and the Dashboard's next drop read dates, not row order. Never re-sort the rows: the drop_id is the key every actuals file uses.
A27: Calculator | B27: A single drop of any tier, brand count, office count and delivery model, run through the same engine.
A28: Drop_PnL | B28: Per-drop P&L on the plan basis for every scheduled drop, with hours by activity, contribution per founder hour, cash timing on the plan's terms, and live values (actual where in).
A29: Cash_Flow | B29: Weekly cash flow for 26 weeks with a monthly cross-check: brand receipts, direct costs, overhead paid once, startup outlays at their timing, cumulative cash and its lowest point. Row 30 takes your actual bank balance; row 31 shows the variance. Below the monthly view: overhead not absorbed, and insurance prepaid beyond the six months.
A30: Steady_State | B30: The plan's monthly picture reproduced (row 7, fixed for comparison), a standard drop on today's Inputs (row 8), the scenario in force at steady state, and break-even: campaigns to recover startup cash, campaigns a month to cover overhead, the brand count and price where contribution per hour crosses $50. Every break-even line follows Inputs.
A31: Sensitivity | B31: Four plain-formula tables: price x brands, renewal x brands, renewal against the monthly steady state, price against the monthly steady state. Direction checks at the bottom.
A32: Plan_Check | B32: The plan's five scenario rows, the $1,000 reading, edge cases, the founder-hour table cell by cell, and a reconciliation of every plan figure: plan, model, difference, reason.
A33: Capital | B33: The plan's capital table line by line, where the model pays each line, and the cash the plan's table leaves out.
A34: Hours_Log | B34: The hand-filled hours log by the seven activity keys, with totals per drop and per week.
... A41: Lists | B41: Fixed keys (delivery model, tier, activities, events), federal holidays and blackouts. Add holidays or blackouts in the blank yellow rows.
A43: Colours and conventions
A44: Yellow cell, blue text | B44: An input. Type here.
A45: Blue cell | B45: An input whose default follows another cell (a gate date, Inputs or the scenario in force). Type over it to replace; the 'Changed' flag records it.
A46: Grey cell | B46: Calculated on the Inputs tab. Do not type over it.
A47: Green cell | B47: A key output.
A48: Formulas | B48: No numeric literal other than 0 or 1 appears in any formula; conversions such as days per week sit in input cells. _work/audit_formulas.py checks this.
A49: Signs | B49: Cash outflows are negative on Cash_Flow. Costs are positive on the P&L tabs.
A50: Dates | B50: YYYY-MM-DD. Week 1 starts Monday 2026-10-26 (CONTRACTS section 3). Moving week 1 does not move the gate or drop dates, which are typed CONTRACTS dates: move them too (Checks flags week 1 moved on its own).
A51: Dates and amounts must be real dates and numbers | B51: Every date window and every amount is a SUMIFS, so a date or amount stored as text drops out of the cash flow and the gates with no error. Checks has one 'stored as text' line per paste tab, and the Dashboard banner turns red. To avoid it: bring the CSV in with File, Import, 'Replace data starting at selected cell', with cell A4 of the tab selected (support.google.com/docs/answer/40608, opened 2026-10-24); if the dialog offers to convert text to numbers and dates, leave it on (unverified, founder to confirm). To fix a column that is already text: put =DATEVALUE(cell) for a date or =VALUE(cell) for an amount in a spare column, copy it, paste it back over the original column as values only, and clear the spare column. A format change alone may leave stored text as text, so read the Checks line again after the fix.
A53: Plan readings (each verified by Plan_Check; none is a fudge)
A54: (a) Display kit | B54: $8 per office per drop, not per brand. Only this reproduces the scenario hard costs: a three-brand courier drop is $80 + $300 + $75 + $30 + $50 + $135 = $670. Per brand it would be $830.
A55: (b) Campaign zero | B55: Reproduces with storage at $0 (sealed cases at home), transport $120 and processing at 3%: $40 + $120 + $0 + $30 + $50 + $36 = $276, which the plan rounds to $280. Contribution is $924 against the plan's $920, and $16.2 per hour.
A56: (c) Direct-ship row | B56: The three-brand direct-ship row ($370) keeps the $75 storage allocation and $0 transport.
A57: (d) The $1,000 price | B57: 'At $1,000 the three-brand drop drops to about $47 an hour' assumes no card processing: $2,465 / 52 h = $47.4. With processing at 3% it is $45.7.
A58: (e) Monthly steady state | B58: $9,000 revenue, about $1,350 hard costs and 104 hours is two three-brand courier drops: $1,340 in hard costs and $7,660 contribution. The plan rounds these.
A59: (f) Fixed overhead | B59: $60 software + $100 insurance + $150 storage + $0 phone = $310 a month, inside the plan's $200 to $350. With home storage it is $160.
A60: (g) Transport lump | B60: The plan's capital line 'Transport, campaigns zero to two: $600' does not reconcile to its own rates ($120 + $300 + $300 = $720). The model pays transport per drop at the rates; the capital table is reproduced as printed.
A61: (h) Hours per win | B61: Six hours per standard brand win = five qualified conversations of 45 minutes (20% close rate) plus 2.25 hours of proposal and paperwork. The close rate on Inputs moves it.
A63: How the model counts money (no double counting)
A64: Contribution follows the plan: revenue less hard costs, where hard costs include per-drop allocations of storage ($75), software ($30) and insurance ($50). Those allocations are views of monthly costs (monthly cost / two drops a month). The cash flow never reads them; it pays software, storage, insurance and phone once, from the Cash_Ledger schedule. Cash_Flow shows how much overhead the drops did not absorb in months with fewer than two drops. The six-month all-in rate on the Dashboard charges overhead on an expensed basis: the annual insurance premium paid at bind covers about a year, so the part that covers months after the six months ($700 at defaults) is shown as prepaid and left out of the rate. The cash flow still pays the full premium at bind.
A65: Startup outlays (formation, publication, licence, printing, domain, professional hours, trademark) are paid once at their timing. Per-drop direct costs (kits, transport, kit mailing, card processing) are paid on the drop's dates. The plan's capital table is reproduced on Capital for comparison only; the cash flow does not read it.
A66: Brand cash follows the plan's terms: founding brands pay in full before product ships (20 business days before the drop, so campaign zero's money lands at Gate 1); standard brands pay 50% at signature (at the latest, T-10) and 50% at placement confirmation (T+1). The invoice-to-cash lag is blank because the plan has none.
A68: How shared drop costs split across brands
A69: A drop's shared costs (display kits, transport, kit mailing, overhead allocations) and shared hours (office coordination, the base of receiving, drop day, checks, admin) are split equally across the brands on the drop wherever a per-brand figure is shown (Calculator, break-even). Revenue, card processing, brand sales hours, per-brand kitting and reporting hours belong to each brand. No figure in the model depends on the split except those per-brand views.
A71: Assumptions (numbered)
A72: 1 | B72: Prices are per office at the tier rate: $150 standard, $120 founding. Offices beyond the package (10 or 5) pay the $150 extra-office price. Founding-rate renewals pay $120 per office for any office count. A drop smaller than the package is priced pro rata; founder to confirm any minimum.
A73: 2 | B73: A drop with zero brands does not run: no cost, no hours.
A74: 3 | B74: Founder hours decompose the plan's table into rates: 10 hours per first (founding) brand, 6 per standard win, 2 per renewal, 4 per new office, 1 per existing office, 2 reporting per brand, 2 admin per drop, and logistics by delivery model (Inputs section 7). The rates reproduce all four columns exactly.
A75: 4 | B75: A renewal fills a brand slot on a later drop at that brand's tier price and costs 2 hours of brand sales instead of 6. In the decision-window drops, renewals = renewal rate x brands, rounded. In the steady state they are not rounded (expected values).
A76: 5 | B76: Card processing applies to every receipt while the toggle is 1 (high end of the 0% to 3% range). Set it to 0 to model bank transfer, the plan's preferred invoicing.
A77: 6 | B77: General liability insurance is $100 a month (the plan's working figure and the legal pack's $1,200 a year), paid as one annual premium at bind on Gate 1, inside the legal pack's latest bind date of 2026-12-21. Needs three quotes. For the all-in rate, each month of cover is expensed in the month it starts: five months fall inside the window, so $700 of the premium is prepaid beyond it.
A78: 7 | B78: Storage: home for campaign zero, a $150-a-month unit from 2027-02-01 through the six months. Software $60 a month from week 1. Phone $0.
A79: 8 | B79: Courier transport is $30 a stop ($300 for ten stops; range $25 to $40). Founder delivery is $120 a drop. Direct-ship transport is $0; mailing the kit ahead needs a quote.
A80: 9 | B80: Formation, licence, professional-hour and filing figures come from the legal pack (desk-drop-legal-pack/figures.csv, read 2026-10-24 and re-read after its 01:52 and 02:33 updates the same day): Articles $200 and Certificate of Publication $50 (verified 2026-10-23); licence $400 (fee verified, whether required unknown); attorney $400 and accountant $300 (plan estimates that keep the plan's 'about $700' for both hours); IT-204-LL $25 (verified). Newspaper publication is the plan's high end, $2,000 (range $250 to $2,000, no working figure in the plan), because the legal pack's figure is not yet verified: its working $1,745 for New York County and $345 for Albany County both still need a quote. Printing ($300) and domain ($100) are plan estimates.
A81: 10 | B81: The trademark application ($350 per class, verified) is in the six months, paid on the Gate 2 day if campaign zero passes: the plan's setup checklist lists 'Trademark application, if the campaign was a pass' after campaign zero, and the legal pack now times it from about Mon 2027-01-25, inside the six months. The plan's capital table has no line for it. The Gate 2 day is the earliest and most cautious date. USPTO refused a prior DESK-DROP application as merely descriptive: set Include = N if the attorney advises against filing.
A82: 11 | B82: Hired and non-owned auto cover and building additional-insured endorsements are blank (needs quote, legal pack). Campaign zero's car rides need the auto add-on. A mailing address (PO box or private mailbox, only if you will not use a home address) and a registered agent (Albany County route only, Include = N) are blank too; the legal pack invents no figure for either.
A83: 12 | B83: Gate tests use real numbers only: the pipeline log for Gates 0 and 1, campaign actuals for Gates 2 and 3. A gate is 'not yet' until its review date passes, then 'miss' if the threshold is not met.
... A101: 30 | B101: Cash at each stop point: 'paid out' is gross, with no brand money. 'Net if you stop here' adds brand cash received by the review day and takes off refunds of payments for campaigns whose drop has not run (at Gate 3, the decision-window deposits). Card fees on refunded payments are not recovered.
A103: Derived items (founder to confirm)
A104: D1 | B104: Calendar from CONTRACTS section 3: week 1 2026-10-26; Gate 0 2026-11-13; Gate 1 2026-12-11; campaign zero Tue 2027-01-12 (moved by the December blackout); Gate 2 2027-01-22; standard drops Tue 2027-02-09 and Tue 2027-02-23; Gate 3 Fri 2027-03-12; decision 2027-04-09.
A105: D2 | B105: Two decision-window drops, Tue 2027-03-23 and Tue 2027-04-06, direct-ship, three brands each. They are not in the plan's roadmap table (campaign zero and two standard runs, 8 paid campaigns against the goal of 6). They come from the decision rule ('after two extra drops'), scenario B ('run two more drops') and scenario A (two drops a month). They carry the schedule's two renewals. The Dashboard shows the six-month all-in rate and week-26 cash with and without them: at defaults $33.8 an hour and $2,839 for the roadmap alone, $52.5 and $11,409 with them. The schedule needs 12 new brand wins by 2027-03-23 (about 60 qualified conversations at a 20% close rate); Schedule columns Y to AE show them by sign-by date beside the Pipeline's actual counts.
A106: D3 | B106: New offices: five in campaign zero; standard run 1 fills its ten (five new); run 2 adds the two that reach the goal of 12 active offices. These are formulas of Inputs, so changing the drop size or the goal moves them.
A107: D4 | B107: Founding payment 20 business days before the drop (campaign zero's money at Gate 1). Standard signature at T-10 (the latest that still lets a brand ship). Balance at T+1.
A108: D5 | B108: Startup timing, each a formula of the date it depends on (legal pack timing, re-read 2026-10-24 after its 02:33 update): domain and any mailbox in week 1; attorney hour Wed 2026-11-18 and accountant hour Fri 2026-11-20 (3 and 5 business days after Gate 0); LLC filing Thu 2026-11-19 (4 business days after Gate 0, the day after the attorney hour); publication 10 business days after filing (Fri 2026-12-04, skipping Thanksgiving); insurance, its add-ons, licence and printing at Gate 1; Certificate of Publication after the sixth weekly run (2027-01-15); trademark at Gate 2; IT-204-LL on its statutory date, 2027-03-15. If Gate 0 or Gate 1 slips, these move with it.
A109: D6 | B109: Hour rates for receiving and kitting, drop day and checks by delivery model, derived from the plan's table (Inputs section 7).
A110: D7 | B110: Scenario levers the plan does not name follow the plan base by formula (blue cells on Scenarios), so an Inputs edit reaches every scenario. Scenario B's renewal is 0%, the low end of 'under 30%'. Scenario A's post-decision price is $180, the low end of $1,800 to $2,000. Scenario A recruits 4 new offices on each decision-window drop, taking the 12-office roster to 20, the low end of 'grow the roster to 20 to 30 offices'.
A111: D8 | B111: One drop per office every 28 days counts as 'one a month' for the office-fatigue warning.
A112: D9 | B112: Courier $30 a stop is the plan's $300 route divided by ten stops. Proposal and paperwork 2.25 hours make the plan's six hours per win at a 20% close rate.
A113: D10 | B113: Gate 2 follows its drop on Schedule: the campaign-zero date plus seven business days (2027-01-22). The storage unit starts on the first day of the month of the first standard drop that runs (2027-02-01).
A114: D11 | B114: DRP-005's debrief (T+10) is Tue 2027-04-20, after the canonical decision date of Fri 2027-04-09 (CONTRACTS section 3). The model keeps the canonical date and warns on the Dashboard; REPORT.md asks whether to move the review to 2027-04-20.
A116: Needs a quote or a founder decision (blank or flagged)
A117: Courier | B117: Three quotes for a ten-stop route. Default $30 a stop.
A118: Insurance | B118: Three general liability quotes, plus hired and non-owned auto and any building endorsements. Default $100 a month; add-ons blank.
A119: Publication | B119: A quote once the county named in the Articles is settled. Default $2,000, the plan's high end, until then. The legal pack's working figures: New York County $1,745, Albany County $345 if the attorney confirms it fits.
A120: Kit mailing | B120: Postage to mail a display kit ahead of a direct-ship drop. Blank.
A121: Extra tent cards | B121: Whether each brand on a drop needs its own card ($1 to $2 each). Blank, per reading (a).
A122: Payment lag | B122: Your invoice terms. Blank = paid the day invoiced.
A123: Founder cash | B123: What you commit to the six months (plan question 7). Blank.
A124: Office-paid cost | B124: Cost to serve an office-paid office (scenario B). Blank.
A125: Mailing address | B125: A PO box or private mailbox for email footers and the LLC notice, only if you will not use a home address (legal pack, CAN-SPAM). Blank; Include = Y, so a quote flows in when typed.
A126: Registered agent | B126: Only if the attorney confirms the Albany County route for the Articles (legal pack). Blank; Include = N.
A128: Measurement honesty
A129: The ladder stays in separate columns everywhere: delivered, placed, depleted, responded (tried is a survey answer), scanned, purchased (code redemptions). Incremental purchases are not measured, and the column says so. There is no field for sales lift, conversions or ROI.
A131: Google Sheets
A132: Built to open in Google Sheets with formulas intact: no macros, scripts, data tables, array formulas, named ranges or add-ons. Every function used (38) appears in Google's Sheets function list (support.google.com/docs/table/25273, opened 2026-10-23 and 2026-10-24). Every INDEX over a single row names its row and column (INDEX(range, 1, column)), because Google documents INDEX's second argument as the row. Import: open a blank spreadsheet in Google Sheets, then File, Import, choose the .xlsx, 'Replace spreadsheet', Import (support.google.com/docs/answer/40608, opened 2026-10-24). A live import was not possible from the build environment, so check after the first import (unverified, founder to confirm): the Dashboard says 'all integrity and data checks pass', Checks shows 0 failing, Scenarios!H10 shows 2 and Cash_Flow!C35 shows 13 (not #REF!).
A134: Changelog
A135: Round 1 | B135: Draft: built every tab on one shared drop engine; plan rows, hour table, capital table and steady state reproduce. The audit found one numeric literal (a '2' in the scenario pointer), a ROW() call, the company name inside a source quote, and a circular reference between the error scan and Dashboard cells that read Checks. All fixed; 28 of 28 checks pass.
A136: Round 2 | B136: Pulled the legal pack's figures.csv (publication $1,745, attorney $400 and accountant $300, IT-204-LL $25, trademark out of the six months, two needs-quote insurance add-ons). Added office-fatigue warnings, change tracking on Scenarios and Schedule, overhead-not-absorbed and six-month all-in views, Gate 3 planned renewals counted by signature date, and tolerance cells instead of exact equality. Re-laid the Dashboard after a visual check.
A137: Round 3 | B137: Moved offices and brands per drop onto Inputs and made the derived Schedule rows formulas of them (new offices backed out from the 12-office goal). Unsmoothed the cash chart, top-aligned every cell, blanked unused drop rows. Behaviour tests cover a SAMPLE actuals run through every gate.
A138: Round 4 | B138: Final review: verified the last three functions (DATEVALUE, TIMEVALUE, FIND) on Google's Sheets list, made every plan-row tolerance the same, wrote HANDOFF, README and REPORT, and regenerated the CSV snapshots. Audit 0 literals; 28 of 28 checks; 54 of 54 tests.
...

Sheet Dashboard
A1: =Inputs!$C$8&" financial model v1" -> Desk Drop financial model v1
A2: =Inputs!$C$9 -> Emerging brands. Delivered to your workday.
A3: Planning estimates, not a forecast. Gates count real numbers only (pipeline log and actuals). Change assumptions on Inputs; type real numbers into the logs.
A4: SAMPLE DATA. A scratch copy loaded with SAMPLE exports from campaign-ops. Illustrative placeholders, not results.
B5: As of | C5: =Inputs!$C$17 -> 46430 | D5: Scenario | E5: =Inputs!$C$35 -> Plan base | F5: Checks | G5: =IF(Checks!$D$45>0,Checks!$D$45&" integrity check(s) failing: see Checks",IF(Checks!$D$46>0,Checks!$D$46&" data check(s) failing: pasted rows are ignored or misread (see Checks)","all integrity and data checks pass")) -> all integrity and data checks pass
A7: Headline
B8: Measure | C8: Value | D8: Detail
B9: Next scheduled drop | C9: =IFERROR(INDEX(Drop_PnL!$A$7:$A$18,MATCH(MIN(Drop_PnL!$BJ$7:$BJ$18),Drop_PnL!$BJ$7:$BJ$18,0)),"none scheduled") -> DRP-003 | D9: =IFERROR(TEXT(INDEX(Drop_PnL!$B$7:$B$18,MATCH(MIN(Drop_PnL!$BJ$7:$BJ$18),Drop_PnL!$BJ$7:$BJ$18,0)),"ddd yyyy-mm-dd")&", "&INDEX(Drop_PnL!$C$7:$C$18,MATCH(MIN(Drop_PnL!$BJ$7:$BJ$18),Drop_PnL!$BJ$7:$BJ$18,0))&", "&INDEX(Drop_PnL!$G$7:$G$18,MATCH(MIN(Drop_PnL!$BJ$7:$BJ$18),Drop_PnL!$BJ$7:$BJ$18,0))&" brand(s), "&INDEX(Drop_PnL!$E$7:$E$18,MATCH(MIN(Drop_PnL!$BJ$7:$BJ$18),Drop_PnL!$BJ$7:$BJ$18,0))&" offices, "&INDEX(Drop_PnL!$D$7:$D$18,MATCH(MIN(Drop_PnL!$BJ$7:$BJ$18),Drop_PnL!$BJ$7:$BJ$18,0))&" tier","") -> Tue 2027-02-23, courier, 3 brand(s), 10 offices, standard tier
B10: Its contribution per founder hour (plan) | C10: =IFERROR(INDEX(Drop_PnL!$AK$7:$AK$18,MATCH(MIN(Drop_PnL!$BJ$7:$BJ$18),Drop_PnL!$BJ$7:$BJ$18,0)),"n/a") -> 66.034483 | D10: =IFERROR("revenue "&TEXT(INDEX(Drop_PnL!$S$7:$S$18,MATCH(MIN(Drop_PnL!$BJ$7:$BJ$18),Drop_PnL!$BJ$7:$BJ$18,0)),"$#,##0")&", "&TEXT(INDEX(Drop_PnL!$AI$7:$AI$18,MATCH(MIN(Drop_PnL!$BJ$7:$BJ$18),Drop_PnL!$BJ$7:$BJ$18,0)),"0")&" founder hours; campaign zero is at the founding rate, so the standard price does not move it","") -> revenue $4,500, 58 founder hours; campaign zero is at the founding rate, so the standard price does not move it
B11: Price in force: standard price per office (Inputs, section 3) | C11: =Inputs!$C$39 -> 150 | D11: ="standard package "&TEXT(Inputs!$C$41,"$#,##0")&" for "&Inputs!$C$40&" offices; founding "&TEXT(Inputs!$C$42,"$#,##0")&" per office. Change the price on Inputs and read the next row." -> standard package $1,500 for 10 offices; founding $120 per office. Change the price on Inputs and read the next row.
B12: A standard drop at that price: contribution per founder hour | C12: =Steady_State!$AK$8 -> 73.653846 | D12: =Steady_State!$G$8&" new brands, "&Steady_State!$E$8&" offices, "&Steady_State!$C$8&": revenue "&TEXT(Steady_State!$S$8,"$#,##0")&", contribution "&TEXT(Steady_State!$AJ$8,"$#,##0")&", "&TEXT(Steady_State!$AI$8,"0")&" founder hours" -> 3 new brands, 10 offices, courier: revenue $4,500, contribution $3,830, 52 founder hours
B13: Standard runs to Gate 3: contribution per founder hour, plan | C13: =IF(E54="","n/a",E54) -> 61.28 | D13: ="actual: "&IF(F54="","not yet",TEXT(F54,"$#,##0.0"))&" ("&F55&" of "&D55&" standard runs with actuals in); target "&TEXT(Inputs!$C$136,"$#,##0") -> actual: not yet (0 of 2 standard runs with actuals in); target $50
B14: Same, if the roster grows so no office gets two drops within four weeks | C14: =IF(SUMIFS(Drop_PnL!$AI$7:$AI$18,Drop_PnL!$D$7:$D$18,"standard",Drop_PnL!$B$7:$B$18,"<="&Inputs!$C$14)+(SUMIFS(Schedule!$AI$7:$AI$18,Schedule!$H$7:$H$18,"standard",Schedule!$E$7:$E$18,"<="&Inputs!$C$14))*(Inputs!$C$95-Inputs!$C$96)>0,SUMIFS(Drop_PnL!$AJ$7:$AJ$18,Drop_PnL!$D$7:$D$18,"standard",Drop_PnL!$B$7:$B$18,"<="&Inputs!$C$14)/(SUMIFS(Drop_PnL!$AI$7:$AI$18,Drop_PnL!$D$7:$D$18,"standard",Drop_PnL!$B$7:$B$18,"<="&Inputs!$C$14)+(SUMIFS(Schedule!$AI$7:$AI$18,Schedule!$H$7:$H$18,"standard",Schedule!$E$7:$E$18,"<="&Inputs!$C$14))*(Inputs!$C$95-Inputs!$C$96)),"n/a") -> 51.409396 | D14: ="adds "&TEXT(SUMIFS(Schedule!$AI$7:$AI$18,Schedule!$H$7:$H$18,"standard",Schedule!$E$7:$E$18,"<="&Inputs!$C$14),"0")&" new offices and "&TEXT((SUMIFS(Schedule!$AI$7:$AI$18,Schedule!$H$7:$H$18,"standard",Schedule!$E$7:$E$18,"<="&Inputs!$C$14))*(Inputs!$C$95-Inputs!$C$96),"0")&" founder hours to the standard runs; the plan wants one drop per office a month (a roster of about 20)" -> adds 8 new offices and 24 founder hours to the standard runs; the plan wants one drop per office a month (a roster of about 20)
B15: Lowest point of cumulative cash (before founder cash) | C15: =Cash_Flow!$C$34 -> -4552 | D15: ="in week "&Cash_Flow!$C$35&", starting "&TEXT(Cash_Flow!$C$36,"ddd yyyy-mm-dd") -> in week 13, starting Mon 2027-01-18
B16: Capital to commit: lowest point plus the reserve | C16: =Cash_Flow!$C$39 -> 5552 | D16: ="reserve "&TEXT(Inputs!$C$117,"$#,##0")&" (plan)"&IF(Inputs!$C$175>0,"; counts "&Inputs!$C$175&" unpriced cost line(s) as $0 until quoted (Inputs, status needs quote or needs founder decision)","") -> reserve $1,000 (plan); counts 5 unpriced cost line(s) as $0 until quoted (Inputs, status needs quote or needs founder decision)
B17: Plan capital figure (high end of the plan's table) | C17: =Capital!$D$14 -> 6510 | D17: ="low end "&TEXT(Capital!$C$14,"$#,##0") -> low end $3,360
B18: Gap to the plan capital figure (positive = headroom) | C18: =Cash_Flow!$C$41 -> 958 | D18: =IF(C18>=0,"the plan figure covers the model need","the model needs more than the plan figure") -> the plan figure covers the model need
B19: Founder cash committed | C19: =Cash_Flow!$C$42 -> not set | D19: =IF(Inputs!$C$115="","set it on Inputs (plan question 7)",IF(Inputs!$C$115>=Cash_Flow!$C$39,"covers capital to commit","short of capital to commit by "&TEXT(Cash_Flow!$C$39-Inputs!$C$115,"$#,##0"))) -> set it on Inputs (plan question 7)
B20: Overhead paid but not absorbed by drops, six months (cash) | C20: =Cash_Flow!$C$72 -> 1310 | D20: ="paid "&TEXT(Cash_Flow!$C$71,"$#,##0")&", allocated to drops "&TEXT(Cash_Flow!$C$70,"$#,##0")&"; of that gap, "&TEXT(Cash_Flow!$C$75,"$#,##0")&" is insurance prepaid beyond the six months and the rest is ramp-up months with few drops" -> paid $2,010, allocated to drops $700; of that gap, $700 is insurance prepaid beyond the six months and the rest is ramp-up months with few drops
B21: Six months all-in per founder hour: roadmap drops only (to Gate 3) | C21: =IF((SUMIFS(Drop_PnL!$BC$7:$BC$18,Drop_PnL!$B$7:$B$18,"<="&Inputs!$C$14)+MAX(Inputs!$C$100*Inputs!$C$101,Hours_Log!$Z$53))>0,(SUMIFS(Drop_PnL!$BD$7:$BD$18,Drop_PnL!$B$7:$B$18,"<="&Inputs!$C$14)+SUMIFS(Drop_PnL!$AM$7:$AM$18,Drop_PnL!$B$7:$B$18,">="&Inputs!$C$10,Drop_PnL!$B$7:$B$18,"<="&Inputs!$C$14)-Cash_Flow!$C$76)/(SUMIFS(Drop_PnL!$BC$7:$BC$18,Drop_PnL!$B$7:$B$18,"<="&Inputs!$C$14)+MAX(Inputs!$C$100*Inputs!$C$101,Hours_Log!$Z$53)),"n/a") -> 33.427313 | D21: ="campaign zero and the standard runs, with all six months of overhead (expensed basis) and "&IF(Hours_Log!$Z$53>Inputs!$C$100*Inputs!$C$101,TEXT(Hours_Log!$Z$53,"0")&" logged hours not tied to a drop",TEXT(Inputs!$C$100*Inputs!$C$101,"0")&" planned discovery hours")&"; after one-time startup outlays: "&IF((SUMIFS(Drop_PnL!$BC$7:$BC$18,Drop_PnL!$B$7:$B$18,"<="&Inputs!$C$14)+MAX(Inputs!$C$100*Inputs!$C$101,Hours_Log!$Z$53))>0,TEXT(((SUMIFS(Drop_PnL!$BD$7:$BD$18,Drop_PnL!$B$7:$B$18,"<="&Inputs!$C$14)+SUMIFS(Drop_PnL!$AM$7:$AM$18,Drop_PnL!$B$7:$B$18,">="&Inputs!$C$10,Drop_PnL!$B$7:$B$18,"<="&Inputs!$C$14)-Cash_Flow!$C$76)-Inputs!$Q$172)/(SUMIFS(Drop_PnL!$BC$7:$BC$18,Drop_PnL!$B$7:$B$18,"<="&Inputs!$C$14)+MAX(Inputs!$C$100*Inputs!$C$101,Hours_Log!$Z$53)),"$#,##0.0"),"n/a")&" per hour" -> campaign zero and the standard runs, with all six months of overhead (expensed basis) and 45 planned discovery hours; after one-time startup outlays: $15.3 per hour
B22: Six months all-in per founder hour: with the decision-window drops (derived, not in the plan's roadmap) | C22: =IF((SUMIFS(Drop_PnL!$BC$7:$BC$18,Drop_PnL!$B$7:$B$18,"<="&Cash_Flow!$AB$6)+MAX(Inputs!$C$100*Inputs!$C$101,Hours_Log!$Z$53))>0,(SUMIFS(Drop_PnL!$BD$7:$BD$18,Drop_PnL!$B$7:$B$18,"<="&Cash_Flow!$AB$6)+SUMIFS(Drop_PnL!$AM$7:$AM$18,Drop_PnL!$B$7:$B$18,">="&Inputs!$C$10,Drop_PnL!$B$7:$B$18,"<="&Cash_Flow!$AB$6)-Cash_Flow!$C$76)/(SUMIFS(Drop_PnL!$BC$7:$BC$18,Drop_PnL!$B$7:$B$18,"<="&Cash_Flow!$AB$6)+MAX(Inputs!$C$100*Inputs!$C$101,Hours_Log!$Z$53)),"n/a") -> 52.291262 | D22: ="adds "&COUNTIFS(Drop_PnL!$B$7:$B$18,">"&Inputs!$C$14,Drop_PnL!$B$7:$B$18,"<="&Cash_Flow!$AB$6,Drop_PnL!$N$7:$N$18,1)&" drop(s) after Gate 3, with "&IF(Hours_Log!$Z$53>Inputs!$C$100*Inputs!$C$101,TEXT(Hours_Log!$Z$53,"0")&" logged hours not tied to a drop",TEXT(Inputs!$C$100*Inputs!$C$101,"0")&" planned discovery hours")&"; insurance prepaid beyond the window ("&TEXT(Cash_Flow!$C$75,"$#,##0")&") is left out; after one-time startup outlays: "&IF((SUMIFS(Drop_PnL!$BC$7:$BC$18,Drop_PnL!$B$7:$B$18,"<="&Cash_Flow!$AB$6)+MAX(Inputs!$C$100*Inputs!$C$101,Hours_Log!$Z$53))>0,TEXT(((SUMIFS(Drop_PnL!$BD$7:$BD$18,Drop_PnL!$B$7:$B$18,"<="&Cash_Flow!$AB$6)+SUMIFS(Drop_PnL!$AM$7:$AM$18,Drop_PnL!$B$7:$B$18,">="&Inputs!$C$10,Drop_PnL!$B$7:$B$18,"<="&Cash_Flow!$AB$6)-Cash_Flow!$C$76)-Inputs!$Q$172)/(SUMIFS(Drop_PnL!$BC$7:$BC$18,Drop_PnL!$B$7:$B$18,"<="&Cash_Flow!$AB$6)+MAX(Inputs!$C$100*Inputs!$C$101,Hours_Log!$Z$53)),"$#,##0.0"),"n/a")&" per hour" -> adds 2 drop(s) after Gate 3, with 45 planned discovery hours; insurance prepaid beyond the window ($700) is left out; after one-time startup outlays: $38.9 per hour
B23: Cumulative cash at week 26: roadmap drops only | C23: =Cash_Flow!$C$44-SUMIFS(Drop_PnL!$BI$7:$BI$18,Drop_PnL!$B$7:$B$18,">"&Inputs!$C$14) -> 2763 | D23: ="the decision-window drops add "&TEXT(C24-C23,"$#,##0")&" by week 26" -> the decision-window drops add $8,570 by week 26
B24: Cumulative cash at week 26: with the decision-window drops (derived) | C24: =Cash_Flow!$C$44 -> 11333 | D24: ="before founder cash; lowest balance with founder cash "&IF(Inputs!$C$115="","(founder cash not set)",TEXT(Cash_Flow!$C$43,"$#,##0")) -> before founder cash; lowest balance with founder cash (founder cash not set)
B25: Steady state, scenario in force: contribution per month | C25: =Steady_State!$D$27 -> 7660 | D25: ="per founder hour "&IF(ISNUMBER(Steady_State!$D$28),TEXT(Steady_State!$D$28,"$#,##0.0"),"n/a")&"; net of all overhead "&TEXT(Steady_State!$D$39,"$#,##0")&" a month"&IF(AND(N(Scenarios!$H$17)>0,Scenarios!$R$19=1),"; office-paid revenue left out of the net until its cost to serve is quoted","") -> per founder hour $81.1; net of all overhead $7,660 a month
B26: Office-fatigue warnings on Schedule | C26: =COUNTIF(Schedule!$W$7:$W$18,"some*") -> 2 | D26: =IF(C26=0,"no office gets two drops within four weeks","drops where some offices get a second drop within four weeks (plan: one drop a month); see the Gate 3 rate with a bigger roster above") -> drops where some offices get a second drop within four weeks (plan: one drop a month); see the Gate 3 rate with a bigger roster above
B27: Decision-window drops whose debrief (T+10) lands after the decision date | C27: =COUNTIF(Schedule!$AG$7:$AG$18,"after the decision") -> 1 | D27: =IF(C27=0,"every decision-window drop reports by the decision date","last debrief "&TEXT(MAX(Schedule!$AH$7:$AH$18),"ddd yyyy-mm-dd")&", after the "&TEXT(Inputs!$C$15,"ddd yyyy-mm-dd")&" decision: the switch test cannot finish in time (REPORT.md, question 1)") -> last debrief Tue 2027-04-20, after the Fri 2027-04-09 decision: the switch test cannot finish in time (REPORT.md, question 1)
B28: Schedule rows changed or added since the derived default | C28: =COUNTIF(Schedule!$X$7:$X$18,"changed") -> 0 | D28: =IF(C28=0,"schedule is the derived default","edited by you") -> schedule is the derived default
B29: Inputs changed from plan defaults | C29: =Inputs!$C$174 -> 1 | D29: =IF(Checks!$D$47=0,"plan figures reproduce","plan reproduction differs in "&Checks!$D$47&" check(s); expected after edits") -> plan figures reproduce
A31: Cash at each stop point (before founder cash)
B32: Review | C32: Date | D32: Paid out before the review day (gross; no brand money) | E32: Brand cash received by the review day | F32: Refunds owed if you stop: payments received for drops not yet run | G32: Net if you stop here: paid out + received - refunds | H32: Cumulative net cash at the end of that week, if every gate passes
B33: Gate 0 | C33: =Inputs!$C$11 -> 46339 | D33: =-SUMIFS(Drop_PnL!$T$7:$T$18,Drop_PnL!$AX$7:$AX$18,">="&Inputs!$C$10,Drop_PnL!$AX$7:$AX$18,"<="&(Inputs!$C$11-1),Drop_PnL!$AZ$7:$AZ$18,"N")-SUMIFS(Drop_PnL!$U$7:$U$18,Drop_PnL!$AY$7:$AY$18,">="&Inputs!$C$10,Drop_PnL!$AY$7:$AY$18,"<="&(Inputs!$C$11-1),Drop_PnL!$AZ$7:$AZ$18,"N")-SUMIFS(Drop_PnL!$V$7:$V$18,Drop_PnL!$AX$7:$AX$18,">="&Inputs!$C$10,Drop_PnL!$AX$7:$AX$18,"<="&(Inputs!$C$11-1),Drop_PnL!$AZ$7:$AZ$18,"N")-(SUMIFS(Drop_PnL!$AU$7:$AU$18,Drop_PnL!$AO$7:$AO$18,">="&Inputs!$C$10,Drop_PnL!$AO$7:$AO$18,"<="&(Inputs!$C$11-1),Drop_PnL!$AZ$7:$AZ$18,"N")+SUMIFS(Drop_PnL!$AV$7:$AV$18,Drop_PnL!$AQ$7:$AQ$18,">="&Inputs!$C$10,Drop_PnL!$AQ$7:$AQ$18,"<="&(Inputs!$C$11-1),Drop_PnL!$AZ$7:$AZ$18,"N")+SUMIFS(Drop_PnL!$AW$7:$AW$18,Drop_PnL!$AS$7:$AS$18,">="&Inputs!$C$10,Drop_PnL!$AS$7:$AS$18,"<="&(Inputs!$C$11-1),Drop_PnL!$AZ$7:$AZ$18,"N"))-(SUMIFS(Actuals_DropCosts!$F$5:$F$104,Actuals_DropCosts!$B$5:$B$104,">="&Inputs!$C$10,Actuals_DropCosts!$B$5:$B$104,"<="&(Inputs!$C$11-1),Actuals_DropCosts!$U$5:$U$104,"Y")+SUMIFS(Actuals_DropCosts!$G$5:$G$104,Actuals_DropCosts!$B$5:$B$104,">="&Inputs!$C$10,Actuals_DropCosts!$B$5:$B$104,"<="&(Inputs!$C$11-1),Actuals_DropCosts!$U$5:$U$104,"Y")+SUMIFS(Actuals_DropCosts!$H$5:$H$104,Actuals_DropCosts!$B$5:$B$104,">="&Inputs!$C$10,Actuals_DropCosts!$B$5:$B$104,"<="&(Inputs!$C$11-1),Actuals_DropCosts!$U$5:$U$104,"Y")+SUMIFS(Actuals_Campaigns!$T$5:$T$204,Actuals_Campaigns!$S$5:$S$204,">="&Inputs!$C$10,Actuals_Campaigns!$S$5:$S$204,"<="&(Inputs!$C$11-1),Actuals_Campaigns!$AL$5:$AL$204,"Y"))-SUMIFS(Cash_Ledger!$D$5:$D$53,Cash_Ledger!$C$5:$C$53,">="&Inputs!$C$10,Cash_Ledger!$C$5:$C$53,"<="&(Inputs!$C$11-1),Cash_Ledger!$A$5:$A$53,"software")-SUMIFS(Cash_Ledger!$D$5:$D$53,Cash_Ledger!$C$5:$C$53,">="&Inputs!$C$10,Cash_Ledger!$C$5:$C$53,"<="&(Inputs!$C$11-1),Cash_Ledger!$A$5:$A$53,"insurance")-SUMIFS(Cash_Ledger!$D$5:$D$53,Cash_Ledger!$C$5:$C$53,">="&Inputs!$C$10,Cash_Ledger!$C$5:$C$53,"<="&(Inputs!$C$11-1),Cash_Ledger!$A$5:$A$53,"storage")-SUMIFS(Cash_Ledger!$D$5:$D$53,Cash_Ledger!$C$5:$C$53,">="&Inputs!$C$10,Cash_Ledger!$C$5:$C$53,"<="&(Inputs!$C$11-1),Cash_Ledger!$A$5:$A$53,"phone")-SUMIFS(Inputs!$Q$158:$Q$171,Inputs!$R$158:$R$171,">="&Inputs!$C$10,Inputs!$R$158:$R$171,"<="&(Inputs!$C$11-1)) -> -160 | E33: =SUMIFS(Drop_PnL!$AP$7:$AP$18,Drop_PnL!$AO$7:$AO$18,">="&Inputs!$C$10,Drop_PnL!$AO$7:$AO$18,"<="&Inputs!$C$11,Drop_PnL!$AZ$7:$AZ$18,"N")+SUMIFS(Drop_PnL!$AR$7:$AR$18,Drop_PnL!$AQ$7:$AQ$18,">="&Inputs!$C$10,Drop_PnL!$AQ$7:$AQ$18,"<="&Inputs!$C$11,Drop_PnL!$AZ$7:$AZ$18,"N")+SUMIFS(Drop_PnL!$AT$7:$AT$18,Drop_PnL!$AS$7:$AS$18,">="&Inputs!$C$10,Drop_PnL!$AS$7:$AS$18,"<="&Inputs!$C$11,Drop_PnL!$AZ$7:$AZ$18,"N")+SUMIFS(Actuals_Campaigns!$X$5:$X$204,Actuals_Campaigns!$Y$5:$Y$204,">="&Inputs!$C$10,Actuals_Campaigns!$Y$5:$Y$204,"<="&Inputs!$C$11,Actuals_Campaigns!$AL$5:$AL$204,"Y")+SUMIFS(Actuals_Campaigns!$AM$5:$AM$204,Actuals_Campaigns!$S$5:$S$204,">="&Inputs!$C$10,Actuals_Campaigns!$S$5:$S$204,"<="&Inputs!$C$11,Actuals_Campaigns!$AL$5:$AL$204,"Y") -> 0 | F33: =SUMIFS(Drop_PnL!$AP$7:$AP$18,Drop_PnL!$AO$7:$AO$18,"<="&Inputs!$C$11,Drop_PnL!$B$7:$B$18,">"&Inputs!$C$11,Drop_PnL!$AZ$7:$AZ$18,"N")+SUMIFS(Drop_PnL!$AR$7:$AR$18,Drop_PnL!$AQ$7:$AQ$18,"<="&Inputs!$C$11,Drop_PnL!$B$7:$B$18,">"&Inputs!$C$11,Drop_PnL!$AZ$7:$AZ$18,"N")+SUMIFS(Drop_PnL!$AT$7:$AT$18,Drop_PnL!$AS$7:$AS$18,"<="&Inputs!$C$11,Drop_PnL!$B$7:$B$18,">"&Inputs!$C$11,Drop_PnL!$AZ$7:$AZ$18,"N")+SUMIFS(Actuals_Campaigns!$X$5:$X$204,Actuals_Campaigns!$Y$5:$Y$204,"<="&Inputs!$C$11,Actuals_Campaigns!$C$5:$C$204,">"&Inputs!$C$11,Actuals_Campaigns!$AL$5:$AL$204,"Y")+SUMIFS(Actuals_Campaigns!$AM$5:$AM$204,Actuals_Campaigns!$S$5:$S$204,"<="&Inputs!$C$11,Actuals_Campaigns!$C$5:$C$204,">"&Inputs!$C$11,Actuals_Campaigns!$AL$5:$AL$204,"Y") -> 0 | G33: =D33+E33-F33 -> -160 | H33: =SUMIFS(Cash_Flow!$C$26:$AB$26,Cash_Flow!$C$5:$AB$5,"<="&Inputs!$C$11) -> -160
B34: Gate 1 | C34: =Inputs!$C$12 -> 46367 | D34: =-SUMIFS(Drop_PnL!$T$7:$T$18,Drop_PnL!$AX$7:$AX$18,">="&Inputs!$C$10,Drop_PnL!$AX$7:$AX$18,"<="&(Inputs!$C$12-1),Drop_PnL!$AZ$7:$AZ$18,"N")-SUMIFS(Drop_PnL!$U$7:$U$18,Drop_PnL!$AY$7:$AY$18,">="&Inputs!$C$10,Drop_PnL!$AY$7:$AY$18,"<="&(Inputs!$C$12-1),Drop_PnL!$AZ$7:$AZ$18,"N")-SUMIFS(Drop_PnL!$V$7:$V$18,Drop_PnL!$AX$7:$AX$18,">="&Inputs!$C$10,Drop_PnL!$AX$7:$AX$18,"<="&(Inputs!$C$12-1),Drop_PnL!$AZ$7:$AZ$18,"N")-(SUMIFS(Drop_PnL!$AU$7:$AU$18,Drop_PnL!$AO$7:$AO$18,">="&Inputs!$C$10,Drop_PnL!$AO$7:$AO$18,"<="&(Inputs!$C$12-1),Drop_PnL!$AZ$7:$AZ$18,"N")+SUMIFS(Drop_PnL!$AV$7:$AV$18,Drop_PnL!$AQ$7:$AQ$18,">="&Inputs!$C$10,Drop_PnL!$AQ$7:$AQ$18,"<="&(Inputs!$C$12-1),Drop_PnL!$AZ$7:$AZ$18,"N")+SUMIFS(Drop_PnL!$AW$7:$AW$18,Drop_PnL!$AS$7:$AS$18,">="&Inputs!$C$10,Drop_PnL!$AS$7:$AS$18,"<="&(Inputs!$C$12-1),Drop_PnL!$AZ$7:$AZ$18,"N"))-(SUMIFS(Actuals_DropCosts!$F$5:$F$104,Actuals_DropCosts!$B$5:$B$104,">="&Inputs!$C$10,Actuals_DropCosts!$B$5:$B$104,"<="&(Inputs!$C$12-1),Actuals_DropCosts!$U$5:$U$104,"Y")+SUMIFS(Actuals_DropCosts!$G$5:$G$104,Actuals_DropCosts!$B$5:$B$104,">="&Inputs!$C$10,Actuals_DropCosts!$B$5:$B$104,"<="&(Inputs!$C$12-1),Actuals_DropCosts!$U$5:$U$104,"Y")+SUMIFS(Actuals_DropCosts!$H$5:$H$104,Actuals_DropCosts!$B$5:$B$104,">="&Inputs!$C$10,Actuals_DropCosts!$B$5:$B$104,"<="&(Inputs!$C$12-1),Actuals_DropCosts!$U$5:$U$104,"Y")+SUMIFS(Actuals_Campaigns!$T$5:$T$204,Actuals_Campaigns!$S$5:$S$204,">="&Inputs!$C$10,Actuals_Campaigns!$S$5:$S$204,"<="&(Inputs!$C$12-1),Actuals_Campaigns!$AL$5:$AL$204,"Y"))-SUMIFS(Cash_Ledger!$D$5:$D$53,Cash_Ledger!$C$5:$C$53,">="&Inputs!$C$10,Cash_Ledger!$C$5:$C$53,"<="&(Inputs!$C$12-1),Cash_Ledger!$A$5:$A$53,"software")-SUMIFS(Cash_Ledger!$D$5:$D$53,Cash_Ledger!$C$5:$C$53,">="&Inputs!$C$10,Cash_Ledger!$C$5:$C$53,"<="&(Inputs!$C$12-1),Cash_Ledger!$A$5:$A$53,"insurance")-SUMIFS(Cash_Ledger!$D$5:$D$53,Cash_Ledger!$C$5:$C$53,">="&Inputs!$C$10,Cash_Ledger!$C$5:$C$53,"<="&(Inputs!$C$12-1),Cash_Ledger!$A$5:$A$53,"storage")-SUMIFS(Cash_Ledger!$D$5:$D$53,Cash_Ledger!$C$5:$C$53,">="&Inputs!$C$10,Cash_Ledger!$C$5:$C$53,"<="&(Inputs!$C$12-1),Cash_Ledger!$A$5:$A$53,"phone")-SUMIFS(Inputs!$Q$158:$Q$171,Inputs!$R$158:$R$171,">="&Inputs!$C$10,Inputs!$R$158:$R$171,"<="&(Inputs!$C$12-1)) -> -3120 | E34: =SUMIFS(Drop_PnL!$AP$7:$AP$18,Drop_PnL!$AO$7:$AO$18,">="&Inputs!$C$10,Drop_PnL!$AO$7:$AO$18,"<="&Inputs!$C$12,Drop_PnL!$AZ$7:$AZ$18,"N")+SUMIFS(Drop_PnL!$AR$7:$AR$18,Drop_PnL!$AQ$7:$AQ$18,">="&Inputs!$C$10,Drop_PnL!$AQ$7:$AQ$18,"<="&Inputs!$C$12,Drop_PnL!$AZ$7:$AZ$18,"N")+SUMIFS(Drop_PnL!$AT$7:$AT$18,Drop_PnL!$AS$7:$AS$18,">="&Inputs!$C$10,Drop_PnL!$AS$7:$AS$18,"<="&Inputs!$C$12,Drop_PnL!$AZ$7:$AZ$18,"N")+SUMIFS(Actuals_Campaigns!$X$5:$X$204,Actuals_Campaigns!$Y$5:$Y$204,">="&Inputs!$C$10,Actuals_Campaigns!$Y$5:$Y$204,"<="&Inputs!$C$12,Actuals_Campaigns!$AL$5:$AL$204,"Y")+SUMIFS(Actuals_Campaigns!$AM$5:$AM$204,Actuals_Campaigns!$S$5:$S$204,">="&Inputs!$C$10,Actuals_Campaigns!$S$5:$S$204,"<="&Inputs!$C$12,Actuals_Campaigns!$AL$5:$AL$204,"Y") -> 1080 | F34: =SUMIFS(Drop_PnL!$AP$7:$AP$18,Drop_PnL!$AO$7:$AO$18,"<="&Inputs!$C$12,Drop_PnL!$B$7:$B$18,">"&Inputs!$C$12,Drop_PnL!$AZ$7:$AZ$18,"N")+SUMIFS(Drop_PnL!$AR$7:$AR$18,Drop_PnL!$AQ$7:$AQ$18,"<="&Inputs!$C$12,Drop_PnL!$B$7:$B$18,">"&Inputs!$C$12,Drop_PnL!$AZ$7:$AZ$18,"N")+SUMIFS(Drop_PnL!$AT$7:$AT$18,Drop_PnL!$AS$7:$AS$18,"<="&Inputs!$C$12,Drop_PnL!$B$7:$B$18,">"&Inputs!$C$12,Drop_PnL!$AZ$7:$AZ$18,"N")+SUMIFS(Actuals_Campaigns!$X$5:$X$204,Actuals_Campaigns!$Y$5:$Y$204,"<="&Inputs!$C$12,Actuals_Campaigns!$C$5:$C$204,">"&Inputs!$C$12,Actuals_Campaigns!$AL$5:$AL$204,"Y")+SUMIFS(Actuals_Campaigns!$AM$5:$AM$204,Actuals_Campaigns!$S$5:$S$204,"<="&Inputs!$C$12,Actuals_Campaigns!$C$5:$C$204,">"&Inputs!$C$12,Actuals_Campaigns!$AL$5:$AL$204,"Y") -> 1080 | G34: =D34+E34-F34 -> -3120 | H34: =SUMIFS(Cash_Flow!$C$26:$AB$26,Cash_Flow!$C$5:$AB$5,"<="&Inputs!$C$12) -> -3940
B35: Gate 2 | C35: =Inputs!$C$13 -> 46409 | D35: =-SUMIFS(Drop_PnL!$T$7:$T$18,Drop_PnL!$AX$7:$AX$18,">="&Inputs!$C$10,Drop_PnL!$AX$7:$AX$18,"<="&(Inputs!$C$13-1),Drop_PnL!$AZ$7:$AZ$18,"N")-SUMIFS(Drop_PnL!$U$7:$U$18,Drop_PnL!$AY$7:$AY$18,">="&Inputs!$C$10,Drop_PnL!$AY$7:$AY$18,"<="&(Inputs!$C$13-1),Drop_PnL!$AZ$7:$AZ$18,"N")-SUMIFS(Drop_PnL!$V$7:$V$18,Drop_PnL!$AX$7:$AX$18,">="&Inputs!$C$10,Drop_PnL!$AX$7:$AX$18,"<="&(Inputs!$C$13-1),Drop_PnL!$AZ$7:$AZ$18,"N")-(SUMIFS(Drop_PnL!$AU$7:$AU$18,Drop_PnL!$AO$7:$AO$18,">="&Inputs!$C$10,Drop_PnL!$AO$7:$AO$18,"<="&(Inputs!$C$13-1),Drop_PnL!$AZ$7:$AZ$18,"N")+SUMIFS(Drop_PnL!$AV$7:$AV$18,Drop_PnL!$AQ$7:$AQ$18,">="&Inputs!$C$10,Drop_PnL!$AQ$7:$AQ$18,"<="&(Inputs!$C$13-1),Drop_PnL!$AZ$7:$AZ$18,"N")+SUMIFS(Drop_PnL!$AW$7:$AW$18,Drop_PnL!$AS$7:$AS$18,">="&Inputs!$C$10,Drop_PnL!$AS$7:$AS$18,"<="&(Inputs!$C$13-1),Drop_PnL!$AZ$7:$AZ$18,"N"))-(SUMIFS(Actuals_DropCosts!$F$5:$F$104,Actuals_DropCosts!$B$5:$B$104,">="&Inputs!$C$10,Actuals_DropCosts!$B$5:$B$104,"<="&(Inputs!$C$13-1),Actuals_DropCosts!$U$5:$U$104,"Y")+SUMIFS(Actuals_DropCosts!$G$5:$G$104,Actuals_DropCosts!$B$5:$B$104,">="&Inputs!$C$10,Actuals_DropCosts!$B$5:$B$104,"<="&(Inputs!$C$13-1),Actuals_DropCosts!$U$5:$U$104,"Y")+SUMIFS(Actuals_DropCosts!$H$5:$H$104,Actuals_DropCosts!$B$5:$B$104,">="&Inputs!$C$10,Actuals_DropCosts!$B$5:$B$104,"<="&(Inputs!$C$13-1),Actuals_DropCosts!$U$5:$U$104,"Y")+SUMIFS(Actuals_Campaigns!$T$5:$T$204,Actuals_Campaigns!$S$5:$S$204,">="&Inputs!$C$10,Actuals_Campaigns!$S$5:$S$204,"<="&(Inputs!$C$13-1),Actuals_Campaigns!$AL$5:$AL$204,"Y"))-SUMIFS(Cash_Ledger!$D$5:$D$53,Cash_Ledger!$C$5:$C$53,">="&Inputs!$C$10,Cash_Ledger!$C$5:$C$53,"<="&(Inputs!$C$13-1),Cash_Ledger!$A$5:$A$53,"software")-SUMIFS(Cash_Ledger!$D$5:$D$53,Cash_Ledger!$C$5:$C$53,">="&Inputs!$C$10,Cash_Ledger!$C$5:$C$53,"<="&(Inputs!$C$13-1),Cash_Ledger!$A$5:$A$53,"insurance")-SUMIFS(Cash_Ledger!$D$5:$D$53,Cash_Ledger!$C$5:$C$53,">="&Inputs!$C$10,Cash_Ledger!$C$5:$C$53,"<="&(Inputs!$C$13-1),Cash_Ledger!$A$5:$A$53,"storage")-SUMIFS(Cash_Ledger!$D$5:$D$53,Cash_Ledger!$C$5:$C$53,">="&Inputs!$C$10,Cash_Ledger!$C$5:$C$53,"<="&(Inputs!$C$13-1),Cash_Ledger!$A$5:$A$53,"phone")-SUMIFS(Inputs!$Q$158:$Q$171,Inputs!$R$158:$R$171,">="&Inputs!$C$10,Inputs!$R$158:$R$171,"<="&(Inputs!$C$13-1)) -> -5282 | E35: =SUMIFS(Drop_PnL!$AP$7:$AP$18,Drop_PnL!$AO$7:$AO$18,">="&Inputs!$C$10,Drop_PnL!$AO$7:$AO$18,"<="&Inputs!$C$13,Drop_PnL!$AZ$7:$AZ$18,"N")+SUMIFS(Drop_PnL!$AR$7:$AR$18,Drop_PnL!$AQ$7:$AQ$18,">="&Inputs!$C$10,Drop_PnL!$AQ$7:$AQ$18,"<="&Inputs!$C$13,Drop_PnL!$AZ$7:$AZ$18,"N")+SUMIFS(Drop_PnL!$AT$7:$AT$18,Drop_PnL!$AS$7:$AS$18,">="&Inputs!$C$10,Drop_PnL!$AS$7:$AS$18,"<="&Inputs!$C$13,Drop_PnL!$AZ$7:$AZ$18,"N")+SUMIFS(Actuals_Campaigns!$X$5:$X$204,Actuals_Campaigns!$Y$5:$Y$204,">="&Inputs!$C$10,Actuals_Campaigns!$Y$5:$Y$204,"<="&Inputs!$C$13,Actuals_Campaigns!$AL$5:$AL$204,"Y")+SUMIFS(Actuals_Campaigns!$AM$5:$AM$204,Actuals_Campaigns!$S$5:$S$204,">="&Inputs!$C$10,Actuals_Campaigns!$S$5:$S$204,"<="&Inputs!$C$13,Actuals_Campaigns!$AL$5:$AL$204,"Y") -> 1080 | F35: =SUMIFS(Drop_PnL!$AP$7:$AP$18,Drop_PnL!$AO$7:$AO$18,"<="&Inputs!$C$13,Drop_PnL!$B$7:$B$18,">"&Inputs!$C$13,Drop_PnL!$AZ$7:$AZ$18,"N")+SUMIFS(Drop_PnL!$AR$7:$AR$18,Drop_PnL!$AQ$7:$AQ$18,"<="&Inputs!$C$13,Drop_PnL!$B$7:$B$18,">"&Inputs!$C$13,Drop_PnL!$AZ$7:$AZ$18,"N")+SUMIFS(Drop_PnL!$AT$7:$AT$18,Drop_PnL!$AS$7:$AS$18,"<="&Inputs!$C$13,Drop_PnL!$B$7:$B$18,">"&Inputs!$C$13,Drop_PnL!$AZ$7:$AZ$18,"N")+SUMIFS(Actuals_Campaigns!$X$5:$X$204,Actuals_Campaigns!$Y$5:$Y$204,"<="&Inputs!$C$13,Actuals_Campaigns!$C$5:$C$204,">"&Inputs!$C$13,Actuals_Campaigns!$AL$5:$AL$204,"Y")+SUMIFS(Actuals_Campaigns!$AM$5:$AM$204,Actuals_Campaigns!$S$5:$S$204,"<="&Inputs!$C$13,Actuals_Campaigns!$C$5:$C$204,">"&Inputs!$C$13,Actuals_Campaigns!$AL$5:$AL$204,"Y") -> 0 | G35: =D35+E35-F35 -> -4202 | H35: =SUMIFS(Cash_Flow!$C$26:$AB$26,Cash_Flow!$C$5:$AB$5,"<="&Inputs!$C$13) -> -4552
B36: Gate 3 | C36: =Inputs!$C$14 -> 46458 | D36: =-SUMIFS(Drop_PnL!$T$7:$T$18,Drop_PnL!$AX$7:$AX$18,">="&Inputs!$C$10,Drop_PnL!$AX$7:$AX$18,"<="&(Inputs!$C$14-1),Drop_PnL!$AZ$7:$AZ$18,"N")-SUMIFS(Drop_PnL!$U$7:$U$18,Drop_PnL!$AY$7:$AY$18,">="&Inputs!$C$10,Drop_PnL!$AY$7:$AY$18,"<="&(Inputs!$C$14-1),Drop_PnL!$AZ$7:$AZ$18,"N")-SUMIFS(Drop_PnL!$V$7:$V$18,Drop_PnL!$AX$7:$AX$18,">="&Inputs!$C$10,Drop_PnL!$AX$7:$AX$18,"<="&(Inputs!$C$14-1),Drop_PnL!$AZ$7:$AZ$18,"N")-(SUMIFS(Drop_PnL!$AU$7:$AU$18,Drop_PnL!$AO$7:$AO$18,">="&Inputs!$C$10,Drop_PnL!$AO$7:$AO$18,"<="&(Inputs!$C$14-1),Drop_PnL!$AZ$7:$AZ$18,"N")+SUMIFS(Drop_PnL!$AV$7:$AV$18,Drop_PnL!$AQ$7:$AQ$18,">="&Inputs!$C$10,Drop_PnL!$AQ$7:$AQ$18,"<="&(Inputs!$C$14-1),Drop_PnL!$AZ$7:$AZ$18,"N")+SUMIFS(Drop_PnL!$AW$7:$AW$18,Drop_PnL!$AS$7:$AS$18,">="&Inputs!$C$10,Drop_PnL!$AS$7:$AS$18,"<="&(Inputs!$C$14-1),Drop_PnL!$AZ$7:$AZ$18,"N"))-(SUMIFS(Actuals_DropCosts!$F$5:$F$104,Actuals_DropCosts!$B$5:$B$104,">="&Inputs!$C$10,Actuals_DropCosts!$B$5:$B$104,"<="&(Inputs!$C$14-1),Actuals_DropCosts!$U$5:$U$104,"Y")+SUMIFS(Actuals_DropCosts!$G$5:$G$104,Actuals_DropCosts!$B$5:$B$104,">="&Inputs!$C$10,Actuals_DropCosts!$B$5:$B$104,"<="&(Inputs!$C$14-1),Actuals_DropCosts!$U$5:$U$104,"Y")+SUMIFS(Actuals_DropCosts!$H$5:$H$104,Actuals_DropCosts!$B$5:$B$104,">="&Inputs!$C$10,Actuals_DropCosts!$B$5:$B$104,"<="&(Inputs!$C$14-1),Actuals_DropCosts!$U$5:$U$104,"Y")+SUMIFS(Actuals_Campaigns!$T$5:$T$204,Actuals_Campaigns!$S$5:$S$204,">="&Inputs!$C$10,Actuals_Campaigns!$S$5:$S$204,"<="&(Inputs!$C$14-1),Actuals_Campaigns!$AL$5:$AL$204,"Y"))-SUMIFS(Cash_Ledger!$D$5:$D$53,Cash_Ledger!$C$5:$C$53,">="&Inputs!$C$10,Cash_Ledger!$C$5:$C$53,"<="&(Inputs!$C$14-1),Cash_Ledger!$A$5:$A$53,"software")-SUMIFS(Cash_Ledger!$D$5:$D$53,Cash_Ledger!$C$5:$C$53,">="&Inputs!$C$10,Cash_Ledger!$C$5:$C$53,"<="&(Inputs!$C$14-1),Cash_Ledger!$A$5:$A$53,"insurance")-SUMIFS(Cash_Ledger!$D$5:$D$53,Cash_Ledger!$C$5:$C$53,">="&Inputs!$C$10,Cash_Ledger!$C$5:$C$53,"<="&(Inputs!$C$14-1),Cash_Ledger!$A$5:$A$53,"storage")-SUMIFS(Cash_Ledger!$D$5:$D$53,Cash_Ledger!$C$5:$C$53,">="&Inputs!$C$10,Cash_Ledger!$C$5:$C$53,"<="&(Inputs!$C$14-1),Cash_Ledger!$A$5:$A$53,"phone")-SUMIFS(Inputs!$Q$158:$Q$171,Inputs!$R$158:$R$171,">="&Inputs!$C$10,Inputs!$R$158:$R$171,"<="&(Inputs!$C$14-1)) -> -7149.5 | E36: =SUMIFS(Drop_PnL!$AP$7:$AP$18,Drop_PnL!$AO$7:$AO$18,">="&Inputs!$C$10,Drop_PnL!$AO$7:$AO$18,"<="&Inputs!$C$14,Drop_PnL!$AZ$7:$AZ$18,"N")+SUMIFS(Drop_PnL!$AR$7:$AR$18,Drop_PnL!$AQ$7:$AQ$18,">="&Inputs!$C$10,Drop_PnL!$AQ$7:$AQ$18,"<="&Inputs!$C$14,Drop_PnL!$AZ$7:$AZ$18,"N")+SUMIFS(Drop_PnL!$AT$7:$AT$18,Drop_PnL!$AS$7:$AS$18,">="&Inputs!$C$10,Drop_PnL!$AS$7:$AS$18,"<="&Inputs!$C$14,Drop_PnL!$AZ$7:$AZ$18,"N")+SUMIFS(Actuals_Campaigns!$X$5:$X$204,Actuals_Campaigns!$Y$5:$Y$204,">="&Inputs!$C$10,Actuals_Campaigns!$Y$5:$Y$204,"<="&Inputs!$C$14,Actuals_Campaigns!$AL$5:$AL$204,"Y")+SUMIFS(Actuals_Campaigns!$AM$5:$AM$204,Actuals_Campaigns!$S$5:$S$204,">="&Inputs!$C$10,Actuals_Campaigns!$S$5:$S$204,"<="&Inputs!$C$14,Actuals_Campaigns!$AL$5:$AL$204,"Y") -> 12330 | F36: =SUMIFS(Drop_PnL!$AP$7:$AP$18,Drop_PnL!$AO$7:$AO$18,"<="&Inputs!$C$14,Drop_PnL!$B$7:$B$18,">"&Inputs!$C$14,Drop_PnL!$AZ$7:$AZ$18,"N")+SUMIFS(Drop_PnL!$AR$7:$AR$18,Drop_PnL!$AQ$7:$AQ$18,"<="&Inputs!$C$14,Drop_PnL!$B$7:$B$18,">"&Inputs!$C$14,Drop_PnL!$AZ$7:$AZ$18,"N")+SUMIFS(Drop_PnL!$AT$7:$AT$18,Drop_PnL!$AS$7:$AS$18,"<="&Inputs!$C$14,Drop_PnL!$B$7:$B$18,">"&Inputs!$C$14,Drop_PnL!$AZ$7:$AZ$18,"N")+SUMIFS(Actuals_Campaigns!$X$5:$X$204,Actuals_Campaigns!$Y$5:$Y$204,"<="&Inputs!$C$14,Actuals_Campaigns!$C$5:$C$204,">"&Inputs!$C$14,Actuals_Campaigns!$AL$5:$AL$204,"Y")+SUMIFS(Actuals_Campaigns!$AM$5:$AM$204,Actuals_Campaigns!$S$5:$S$204,"<="&Inputs!$C$14,Actuals_Campaigns!$C$5:$C$204,">"&Inputs!$C$14,Actuals_Campaigns!$AL$5:$AL$204,"Y") -> 2250 | G36: =D36+E36-F36 -> 2930.5 | H36: =SUMIFS(Cash_Flow!$C$26:$AB$26,Cash_Flow!$C$5:$AB$5,"<="&Inputs!$C$14) -> 5180.5
B37: Six-month decision | C37: =Inputs!$C$15 -> 46486 | D37: =-SUMIFS(Drop_PnL!$T$7:$T$18,Drop_PnL!$AX$7:$AX$18,">="&Inputs!$C$10,Drop_PnL!$AX$7:$AX$18,"<="&(Inputs!$C$15-1),Drop_PnL!$AZ$7:$AZ$18,"N")-SUMIFS(Drop_PnL!$U$7:$U$18,Drop_PnL!$AY$7:$AY$18,">="&Inputs!$C$10,Drop_PnL!$AY$7:$AY$18,"<="&(Inputs!$C$15-1),Drop_PnL!$AZ$7:$AZ$18,"N")-SUMIFS(Drop_PnL!$V$7:$V$18,Drop_PnL!$AX$7:$AX$18,">="&Inputs!$C$10,Drop_PnL!$AX$7:$AX$18,"<="&(Inputs!$C$15-1),Drop_PnL!$AZ$7:$AZ$18,"N")-(SUMIFS(Drop_PnL!$AU$7:$AU$18,Drop_PnL!$AO$7:$AO$18,">="&Inputs!$C$10,Drop_PnL!$AO$7:$AO$18,"<="&(Inputs!$C$15-1),Drop_PnL!$AZ$7:$AZ$18,"N")+SUMIFS(Drop_PnL!$AV$7:$AV$18,Drop_PnL!$AQ$7:$AQ$18,">="&Inputs!$C$10,Drop_PnL!$AQ$7:$AQ$18,"<="&(Inputs!$C$15-1),Drop_PnL!$AZ$7:$AZ$18,"N")+SUMIFS(Drop_PnL!$AW$7:$AW$18,Drop_PnL!$AS$7:$AS$18,">="&Inputs!$C$10,Drop_PnL!$AS$7:$AS$18,"<="&(Inputs!$C$15-1),Drop_PnL!$AZ$7:$AZ$18,"N"))-(SUMIFS(Actuals_DropCosts!$F$5:$F$104,Actuals_DropCosts!$B$5:$B$104,">="&Inputs!$C$10,Actuals_DropCosts!$B$5:$B$104,"<="&(Inputs!$C$15-1),Actuals_DropCosts!$U$5:$U$104,"Y")+SUMIFS(Actuals_DropCosts!$G$5:$G$104,Actuals_DropCosts!$B$5:$B$104,">="&Inputs!$C$10,Actuals_DropCosts!$B$5:$B$104,"<="&(Inputs!$C$15-1),Actuals_DropCosts!$U$5:$U$104,"Y")+SUMIFS(Actuals_DropCosts!$H$5:$H$104,Actuals_DropCosts!$B$5:$B$104,">="&Inputs!$C$10,Actuals_DropCosts!$B$5:$B$104,"<="&(Inputs!$C$15-1),Actuals_DropCosts!$U$5:$U$104,"Y")+SUMIFS(Actuals_Campaigns!$T$5:$T$204,Actuals_Campaigns!$S$5:$S$204,">="&Inputs!$C$10,Actuals_Campaigns!$S$5:$S$204,"<="&(Inputs!$C$15-1),Actuals_Campaigns!$AL$5:$AL$204,"Y"))-SUMIFS(Cash_Ledger!$D$5:$D$53,Cash_Ledger!$C$5:$C$53,">="&Inputs!$C$10,Cash_Ledger!$C$5:$C$53,"<="&(Inputs!$C$15-1),Cash_Ledger!$A$5:$A$53,"software")-SUMIFS(Cash_Ledger!$D$5:$D$53,Cash_Ledger!$C$5:$C$53,">="&Inputs!$C$10,Cash_Ledger!$C$5:$C$53,"<="&(Inputs!$C$15-1),Cash_Ledger!$A$5:$A$53,"insurance")-SUMIFS(Cash_Ledger!$D$5:$D$53,Cash_Ledger!$C$5:$C$53,">="&Inputs!$C$10,Cash_Ledger!$C$5:$C$53,"<="&(Inputs!$C$15-1),Cash_Ledger!$A$5:$A$53,"storage")-SUMIFS(Cash_Ledger!$D$5:$D$53,Cash_Ledger!$C$5:$C$53,">="&Inputs!$C$10,Cash_Ledger!$C$5:$C$53,"<="&(Inputs!$C$15-1),Cash_Ledger!$A$5:$A$53,"phone")-SUMIFS(Inputs!$Q$158:$Q$171,Inputs!$R$158:$R$171,">="&Inputs!$C$10,Inputs!$R$158:$R$171,"<="&(Inputs!$C$15-1)) -> -7747 | E37: =SUMIFS(Drop_PnL!$AP$7:$AP$18,Drop_PnL!$AO$7:$AO$18,">="&Inputs!$C$10,Drop_PnL!$AO$7:$AO$18,"<="&Inputs!$C$15,Drop_PnL!$AZ$7:$AZ$18,"N")+SUMIFS(Drop_PnL!$AR$7:$AR$18,Drop_PnL!$AQ$7:$AQ$18,">="&Inputs!$C$10,Drop_PnL!$AQ$7:$AQ$18,"<="&Inputs!$C$15,Drop_PnL!$AZ$7:$AZ$18,"N")+SUMIFS(Drop_PnL!$AT$7:$AT$18,Drop_PnL!$AS$7:$AS$18,">="&Inputs!$C$10,Drop_PnL!$AS$7:$AS$18,"<="&Inputs!$C$15,Drop_PnL!$AZ$7:$AZ$18,"N")+SUMIFS(Actuals_Campaigns!$X$5:$X$204,Actuals_Campaigns!$Y$5:$Y$204,">="&Inputs!$C$10,Actuals_Campaigns!$Y$5:$Y$204,"<="&Inputs!$C$15,Actuals_Campaigns!$AL$5:$AL$204,"Y")+SUMIFS(Actuals_Campaigns!$AM$5:$AM$204,Actuals_Campaigns!$S$5:$S$204,">="&Inputs!$C$10,Actuals_Campaigns!$S$5:$S$204,"<="&Inputs!$C$15,Actuals_Campaigns!$AL$5:$AL$204,"Y") -> 19080 | F37: =SUMIFS(Drop_PnL!$AP$7:$AP$18,Drop_PnL!$AO$7:$AO$18,"<="&Inputs!$C$15,Drop_PnL!$B$7:$B$18,">"&Inputs!$C$15,Drop_PnL!$AZ$7:$AZ$18,"N")+SUMIFS(Drop_PnL!$AR$7:$AR$18,Drop_PnL!$AQ$7:$AQ$18,"<="&Inputs!$C$15,Drop_PnL!$B$7:$B$18,">"&Inputs!$C$15,Drop_PnL!$AZ$7:$AZ$18,"N")+SUMIFS(Drop_PnL!$AT$7:$AT$18,Drop_PnL!$AS$7:$AS$18,"<="&Inputs!$C$15,Drop_PnL!$B$7:$B$18,">"&Inputs!$C$15,Drop_PnL!$AZ$7:$AZ$18,"N")+SUMIFS(Actuals_Campaigns!$X$5:$X$204,Actuals_Campaigns!$Y$5:$Y$204,"<="&Inputs!$C$15,Actuals_Campaigns!$C$5:$C$204,">"&Inputs!$C$15,Actuals_Campaigns!$AL$5:$AL$204,"Y")+SUMIFS(Actuals_Campaigns!$AM$5:$AM$204,Actuals_Campaigns!$S$5:$S$204,"<="&Inputs!$C$15,Actuals_Campaigns!$C$5:$C$204,">"&Inputs!$C$15,Actuals_Campaigns!$AL$5:$AL$204,"Y") -> 0 | G37: =D37+E37-F37 -> 11333 | H37: =SUMIFS(Cash_Flow!$C$26:$AB$26,Cash_Flow!$C$5:$AB$5,"<="&Inputs!$C$15) -> 11333
B38: Paid out counts every outflow dated before the review day (startup outlays, overhead, drop costs, card fees) and no brand money: at Gate 1 it is what you are out if no brand pays. Spending the plan makes on the review day itself is left out, because you make it only if the gate passes (at Gate 1: insurance, the licence and printing; at Gate 2: the trademark). Net if you stop here adds the brand cash received by that day and takes off what you would refund: payments for campaigns whose drop has not run yet (founding payments, deposits). Card fees on refunded payments are not recovered. Founding brands pay on Gate 1 day by default.
A40: Gate dashboard (live values are actuals only)
A41: Gate | B41: Test | C41: Review date | D41: Threshold | E41: Model assumes | F41: Live value | G41: Status | H41: If it fails (plan)
A42: Gate 0 | B42: Office conversations held (context) | C42: =Inputs!$C$11 -> 46339 | D42: =Inputs!$C$122 -> 15 | F42: =Pipeline!$AH$5 -> 0 | G42: info
A43: Gate 0 | B43: Offices yes in principle, with owner and receiving window | C43: =Inputs!$C$11 -> 46339 | D43: =Inputs!$C$121 -> 5 | F43: =Pipeline!$AH$6 -> 0 | G43: =IF(F43="",IF(Inputs!$C$17>C43,"miss","not yet"),IF(F43>=D43,"pass",IF(Inputs!$C$17>C43,"miss","not yet"))) -> miss | H43: Fewer than 5 offices: change the cluster or office size band, not the model.
A44: Gate 0 | B44: Brand conversations held (context) | C44: =Inputs!$C$11 -> 46339 | D44: =Inputs!$C$125 -> 15 | F44: =Pipeline!$AH$7 -> 0 | G44: info
A45: Gate 0 | B45: Brands that would pay $500 or more and control the budget | C45: =Inputs!$C$11 -> 46339 | D45: =Inputs!$C$123 -> 3 | F45: =Pipeline!$AH$8 -> 0 | G45: =IF(F45="",IF(Inputs!$C$17>C45,"miss","not yet"),IF(F45>=D45,"pass",IF(Inputs!$C$17>C45,"miss","not yet"))) -> miss | H45: Fewer than 3: test the office-paid version for three more weeks before deciding.
A46: Gate 1 | B46: Offices signed | C46: =Inputs!$C$12 -> 46367 | D46: =Inputs!$C$126 -> 5 | E46: =Drop_PnL!E7 -> 5 | F46: =Pipeline!$AH$9 -> 0 | G46: =IF(F46="",IF(Inputs!$C$17>C46,"miss","not yet"),IF(F46>=D46,"pass",IF(Inputs!$C$17>C46,"miss","not yet"))) -> miss | H46: Offices sign but no brand pays even $600: pivot to office-paid or stop. No free campaign.
A47: Gate 1 | B47: Combined Tuesday headcount of signed offices | C47: =Inputs!$C$12 -> 46367 | D47: =Inputs!$C$127 -> 350 | F47: =Pipeline!$AH$10 -> 0 | G47: =IF(F47="",IF(Inputs!$C$17>C47,"miss","not yet"),IF(F47>=D47,"pass",IF(Inputs!$C$17>C47,"miss","not yet"))) -> miss
A48: Gate 1 | B48: Brands paid in full | C48: =Inputs!$C$12 -> 46367 | D48: =Inputs!$C$128 -> 2 | E48: =Drop_PnL!G7 -> 2 | F48: =Pipeline!$AH$11 -> 2 | G48: =IF(F48="",IF(Inputs!$C$17>C48,"miss","not yet"),IF(F48>=D48,"pass",IF(Inputs!$C$17>C48,"miss","not yet"))) -> pass | H48: One paid brand is a soft pass: run it, make the second sale first.
A49: Gate 2 | B49: Units placed within one business day (share of delivered) | C49: =Inputs!$C$13 -> 46409 | D49: =Inputs!$C$130 -> 0.8 | F49: =IFERROR(INDEX(Drop_Actuals!$AG$7:$AG$18,MATCH(Inputs!$C$129,Drop_Actuals!$A$7:$A$18,0)),"") -> 0.896 | G49: =IF(F49="",IF(Inputs!$C$17>C49,"miss","not yet"),IF(F49>=D49,"pass",IF(Inputs!$C$17>C49,"miss","not yet"))) -> pass | H49: Fix the procedure once (card, handoff, Slack post). A second miss is a stop signal.
A50: Gate 2 | B50: Brand campaigns under 5 survey responses per office (must be 0) | C50: =Inputs!$C$13 -> 46409 | D50: 0 | F50: =IF(N(IFERROR(INDEX(Drop_Actuals!$AF$7:$AF$18,MATCH(Inputs!$C$129,Drop_Actuals!$A$7:$A$18,0)),""))=0,"",IFERROR(INDEX(Drop_Actuals!$AH$7:$AH$18,MATCH(Inputs!$C$129,Drop_Actuals!$A$7:$A$18,0)),"")) -> 1 | G50: =IF(F50="",IF(Inputs!$C$17>C50,"miss","not yet"),IF(F50<=D50,"pass",IF(Inputs!$C$17>C50,"miss","not yet"))) -> miss
A51: Gate 2 | B51: Reports late (after T+7) or missing (must be 0) | C51: =Inputs!$C$13 -> 46409 | D51: 0 | F51: =IF(N(IFERROR(INDEX(Drop_Actuals!$AF$7:$AF$18,MATCH(Inputs!$C$129,Drop_Actuals!$A$7:$A$18,0)),""))=0,"",IFERROR(INDEX(Drop_Actuals!$AI$7:$AI$18,MATCH(Inputs!$C$129,Drop_Actuals!$A$7:$A$18,0)),"")) -> 0 | G51: =IF(F51="",IF(Inputs!$C$17>C51,"miss","not yet"),IF(F51<=D51,"pass",IF(Inputs!$C$17>C51,"miss","not yet"))) -> pass
A52: Gate 2 | B52: Brands that would buy again | C52: =Inputs!$C$13 -> 46409 | D52: =Inputs!$C$133 -> 1 | F52: =IF(N(IFERROR(INDEX(Drop_Actuals!$AF$7:$AF$18,MATCH(Inputs!$C$129,Drop_Actuals!$A$7:$A$18,0)),""))=0,"",IFERROR(INDEX(Drop_Actuals!$AJ$7:$AJ$18,MATCH(Inputs!$C$129,Drop_Actuals!$A$7:$A$18,0)),"")) -> 1 | G52: =IF(F52="",IF(Inputs!$C$17>C52,"miss","not yet"),IF(F52>=D52,"pass",IF(Inputs!$C$17>C52,"miss","not yet"))) -> pass
A53: Gate 3 | B53: Renewals at $1,500 or more, signed by the review date | C53: =Inputs!$C$14 -> 46458 | D53: =Inputs!$C$134 -> 1 | E53: =SUMIFS(Drop_PnL!$H$7:$H$18,Drop_PnL!$AQ$7:$AQ$18,"<="&Inputs!$C$14)-SUMIFS(Drop_PnL!$I$7:$I$18,Drop_PnL!$AQ$7:$AQ$18,"<="&Inputs!$C$14) -> 1 | F53: =Pipeline!$AH$12 -> 0 | G53: =IF(F53="",IF(Inputs!$C$17>C53,"miss","not yet"),IF(F53>=D53,"pass",IF(Inputs!$C$17>C53,"miss","not yet"))) -> not yet | H53: No renewal: redesign the evidence (velocity, redemptions), run one more drop. A second miss is a stop.
A54: Gate 3 | B54: Contribution per founder hour, standard runs | C54: =Inputs!$C$14 -> 46458 | D54: =Inputs!$C$136 -> 50 | E54: =IF(SUMIFS(Drop_PnL!$AI$7:$AI$18,Drop_PnL!$D$7:$D$18,"standard",Drop_PnL!$B$7:$B$18,"<="&Inputs!$C$14)>0,SUMIFS(Drop_PnL!$AJ$7:$AJ$18,Drop_PnL!$D$7:$D$18,"standard",Drop_PnL!$B$7:$B$18,"<="&Inputs!$C$14)/SUMIFS(Drop_PnL!$AI$7:$AI$18,Drop_PnL!$D$7:$D$18,"standard",Drop_PnL!$B$7:$B$18,"<="&Inputs!$C$14),"") -> 61.28 | F54: =IF(SUMIFS(Drop_Actuals!$R$7:$R$18,Drop_PnL!$D$7:$D$18,"standard",Drop_PnL!$B$7:$B$18,"<="&Inputs!$C$14,Drop_PnL!$AZ$7:$AZ$18,"Y")>0,SUMIFS(Drop_Actuals!$S$7:$S$18,Drop_PnL!$D$7:$D$18,"standard",Drop_PnL!$B$7:$B$18,"<="&Inputs!$C$14,Drop_PnL!$AZ$7:$AZ$18,"Y")/SUMIFS(Drop_Actuals!$R$7:$R$18,Drop_PnL!$D$7:$D$18,"standard",Drop_PnL!$B$7:$B$18,"<="&Inputs!$C$14,Drop_PnL!$AZ$7:$AZ$18,"Y"),"") | G54: =IF(AND(D55>0,F55<D55),"not yet: "&(D55-F55)&" standard run(s) without actuals",IF(F54="",IF(Inputs!$C$17>C54,"miss","not yet"),IF(F54>=D54,"pass",IF(Inputs!$C$17>C54,"miss","not yet")))) -> not yet: 2 standard run(s) without actuals | H54: Not yet until every standard run dated by the review date has actuals in (next row).
A55: Gate 3 | B55: Standard runs dated by the review date with actuals in (the rate above uses only these; threshold = all of them) | C55: =Inputs!$C$14 -> 46458 | D55: =COUNTIFS(Drop_PnL!$D$7:$D$18,"standard",Drop_PnL!$B$7:$B$18,"<="&Inputs!$C$14,Drop_PnL!$N$7:$N$18,1) -> 2 | F55: =COUNTIFS(Drop_PnL!$D$7:$D$18,"standard",Drop_PnL!$B$7:$B$18,"<="&Inputs!$C$14,Drop_PnL!$N$7:$N$18,1,Drop_PnL!$AZ$7:$AZ$18,"Y") -> 0 | G55: =IF(D55=0,"",IF(F55>=D55,"complete",(D55-F55)&" without actuals")) -> 2 without actuals | H55: Set Actuals in = Y by T+10; code_redemptions_day30 can follow later (HANDOFF 2.4).
A57: Gate | B57: Review date | C57: Overall
A58: Gate 0 | B58: =C42 -> 46339 | C58: =IF(IF(G43="miss",1,0)+IF(G45="miss",1,0)>0,"miss",IF(IF(LEFT(G43,LEN("not yet"))="not yet",1,0)+IF(LEFT(G45,LEN("not yet"))="not yet",1,0)>0,"not yet","pass")) -> miss
A59: Gate 1 | B59: =C46 -> 46367 | C59: =IF(IF(G46="miss",1,0)+IF(G47="miss",1,0)+IF(G48="miss",1,0)>0,"miss",IF(IF(LEFT(G46,LEN("not yet"))="not yet",1,0)+IF(LEFT(G47,LEN("not yet"))="not yet",1,0)+IF(LEFT(G48,LEN("not yet"))="not yet",1,0)>0,"not yet","pass")) -> miss
A60: Gate 2 | B60: =C49 -> 46409 | C60: =IF(IF(G49="miss",1,0)+IF(G50="miss",1,0)+IF(G51="miss",1,0)+IF(G52="miss",1,0)>0,"miss",IF(IF(LEFT(G49,LEN("not yet"))="not yet",1,0)+IF(LEFT(G50,LEN("not yet"))="not yet",1,0)+IF(LEFT(G51,LEN("not yet"))="not yet",1,0)+IF(LEFT(G52,LEN("not yet"))="not yet",1,0)>0,"not yet","pass")) -> miss
A61: Gate 3 | B61: =C53 -> 46458 | C61: =IF(IF(G53="miss",1,0)+IF(G54="miss",1,0)>0,"miss",IF(IF(LEFT(G53,LEN("not yet"))="not yet",1,0)+IF(LEFT(G54,LEN("not yet"))="not yet",1,0)>0,"not yet","pass")) -> not yet
A63: Decision rule (plan): scale, switch to office-paid, or stop
B64: Brand renewal rate, each brand once (renewed Y / answered Y or N) | C64: =IF(SUM(Actuals_Campaigns!$AQ$5:$AQ$204)=0,"",SUM(Actuals_Campaigns!$AR$5:$AR$204)/SUM(Actuals_Campaigns!$AQ$5:$AQ$204)) -> 0.5
B65: Offices that named $100 a month or more | C65: =Pipeline!$AH$13 -> 0
B66: Drops after Gate 3 with actuals in | C66: =COUNTIFS(Drop_PnL!$B$7:$B$18,">"&Inputs!$C$14,Drop_PnL!$AZ$7:$AZ$18,"Y",Drop_PnL!$N$7:$N$18,1) -> 0
B67: Gate 3 | C67: =Dashboard!$C$61 -> not yet
B68: The rule says | C68: =IF(C64="","not yet: no renewal answers",IF(AND(C67="pass",C64>=Inputs!$C$137),"Scale",IF(AND(C65>=Inputs!$C$138,C64<Inputs!$C$140,C66>=Inputs!$C$141),"Switch to office-paid",IF(AND(C64>=Inputs!$C$140,C64<Inputs!$C$137),"Rule silent: renewal between "&TEXT(Inputs!$C$140,"0%")&" and "&TEXT(Inputs!$C$137,"0%"),IF(AND(C64<Inputs!$C$140,C66<Inputs!$C$141),"not yet: the switch test needs "&(Inputs!$C$141-C66)&" more extra drop(s) with actuals (plan: run two more drops first)",IF(AND(C64>=Inputs!$C$137,C67="not yet"),"not yet: renewal clears the scale bar; Gate 3 is still open",IF(Inputs!$C$17>Inputs!$C$15,"Stop: both tests fail","not yet: stop if nothing changes by the decision date"))))))) -> not yet: renewal clears the scale bar; Gate 3 is still open
B69: Stated once (plan) | C69: Scale if Gate 3 passed and renewal is 40% or more. Switch to office-paid if at least five offices named $100 a month or more and brand renewal is under 30% after two extra drops. Stop if both fail.
B71: Placement within one business day, all drops with actuals | C71: =IF(SUMIFS(Drop_Actuals!$V$7:$V$18,Drop_PnL!$AZ$7:$AZ$18,"Y")=0,"",SUMIFS(Drop_Actuals!$X$7:$X$18,Drop_PnL!$AZ$7:$AZ$18,"Y")/SUMIFS(Drop_Actuals!$V$7:$V$18,Drop_PnL!$AZ$7:$AZ$18,"Y")) -> 0.896
B72: Drops with actuals below the placement threshold | C72: =COUNTIFS(Drop_PnL!$AZ$7:$AZ$18,"Y",Drop_Actuals!$AG$7:$AG$18,"<"&Inputs!$C$130) -> 0
B73: Contribution per founder hour, all drops with actuals | C73: =IF(SUMIFS(Drop_Actuals!$R$7:$R$18,Drop_PnL!$AZ$7:$AZ$18,"Y")>0,SUMIFS(Drop_Actuals!$S$7:$S$18,Drop_PnL!$AZ$7:$AZ$18,"Y")/SUMIFS(Drop_Actuals!$R$7:$R$18,Drop_PnL!$AZ$7:$AZ$18,"Y"),"") -> 14.877193
B74: Drops whose results are due (debrief T+10 by the as-of date) with actuals in | C74: =COUNTIFS(Schedule!$AF$7:$AF$18,"<="&Inputs!$C$17,Schedule!$N$7:$N$18,"Y")&" of "&COUNTIFS(Schedule!$AF$7:$AF$18,"<="&Inputs!$C$17) -> 1 of 1 | D74: =IF(COUNTIFS(Schedule!$AF$7:$AF$18,"<="&Inputs!$C$17)>COUNTIFS(Schedule!$AF$7:$AF$18,"<="&Inputs!$C$17,Schedule!$N$7:$N$18,"Y"),"the three lines above and the pointer below leave out "&(COUNTIFS(Schedule!$AF$7:$AF$18,"<="&Inputs!$C$17)-COUNTIFS(Schedule!$AF$7:$AF$18,"<="&Inputs!$C$17,Schedule!$N$7:$N$18,"Y"))&" drop(s) whose results are due","every drop whose results are due is in") -> every drop whose results are due is in
B75: Scenario the real numbers point to | C75: =IF(C71="","not enough data yet",IF(AND(C64<>"",N(C64)=0,C71<Inputs!$C$130),"D: neither converts",IF(C72>=Inputs!$C$142,"C: brands willing, offices unreliable",IF(C64="","not enough data: no renewal answers yet",IF(N(C64)<Inputs!$C$140,"B: brands pay once, offices love it",IF(AND(N(C64)>=Inputs!$C$137,C71>=Inputs!$C$130,N(C73)>=Inputs!$C$136),"A: both sides work","between scenarios: see the rule"))))))&IF(COUNTIFS(Schedule!$AF$7:$AF$18,"<="&Inputs!$C$17)>COUNTIFS(Schedule!$AF$7:$AF$18,"<="&Inputs!$C$17,Schedule!$N$7:$N$18,"Y"),"; "&(COUNTIFS(Schedule!$AF$7:$AF$18,"<="&Inputs!$C$17)-COUNTIFS(Schedule!$AF$7:$AF$18,"<="&Inputs!$C$17,Schedule!$N$7:$N$18,"Y"))&" drop(s) with results due have no actuals yet, so this can change","") -> between scenarios: see the rule
A78: Six-month goals (plan): planned by the schedule against actual
B79: Goal | C79: Target | D79: Planned (Schedule) | E79: Actual | F79: Status
B80: Paid campaigns | C80: =Inputs!$C$143 -> 6 | D80: =SUMIFS(Drop_PnL!$G$7:$G$18,Drop_PnL!$B$7:$B$18,"<="&Cash_Flow!$AB$6) -> 14 | E80: =COUNTIF(Actuals_Campaigns!$R$5:$R$204,">0") -> 2 | F80: =IF(E80="",IF(Inputs!$C$17>Inputs!$C$15,"miss","not yet"),IF(E80>=C80,"pass",IF(Inputs!$C$17>Inputs!$C$15,"miss","not yet"))) -> not yet
B81: Renewals | C81: =Inputs!$C$144 -> 2 | D81: =SUMIFS(Drop_PnL!$H$7:$H$18,Drop_PnL!$B$7:$B$18,"<="&Cash_Flow!$AB$6) -> 2 | E81: =COUNTIF(Actuals_Campaigns!$W$5:$W$204,"Y") -> 1 | F81: =IF(E81="",IF(Inputs!$C$17>Inputs!$C$15,"miss","not yet"),IF(E81>=C81,"pass",IF(Inputs!$C$17>Inputs!$C$15,"miss","not yet"))) -> not yet
B82: Active offices | C82: =Inputs!$C$145 -> 12 | D82: =SUMIFS(Drop_PnL!$F$7:$F$18,Drop_PnL!$B$7:$B$18,"<="&Cash_Flow!$AB$6,Drop_PnL!$N$7:$N$18,1) -> 12 | E82: =Pipeline!$AH$24 -> 0 | F82: =IF(E82="",IF(Inputs!$C$17>Inputs!$C$15,"miss","not yet"),IF(E82>=C82,"pass",IF(Inputs!$C$17>Inputs!$C$15,"miss","not yet"))) -> not yet
B83: Contribution per founder hour, standard runs | C83: =Inputs!$C$136 -> 50 | D83: =E54 -> 61.28 | E83: =F54 | F83: =IF(AND(D55>0,F55<D55),"not yet: "&(D55-F55)&" standard run(s) without actuals",IF(E83="",IF(Inputs!$C$17>Inputs!$C$15,"miss","not yet"),IF(E83>=C83,"pass",IF(Inputs!$C$17>Inputs!$C$15,"miss","not yet")))) -> not yet: 2 standard run(s) without actuals
A86: Contribution per founder hour on each drop (live: actual where in, otherwise plan) | J86: Target per founder hour | L86: =Inputs!$C$136 -> 50
A87: drop_id | B87: Label | C87: Drop date | D87: Basis | E87: Delivery model | F87: Brands | G87: Offices | H87: Revenue | I87: Hard costs | J87: Founder hours | K87: Contribution | L87: Per founder hour
A88: =IF(Drop_PnL!B7="","",Drop_PnL!A7) -> DRP-001 | B88: =IF(Drop_PnL!B7="","",Schedule!B7&"") -> Campaign zero (founding) | C88: =IF(Drop_PnL!B7="","",Drop_PnL!B7) -> 46399 | D88: =Drop_PnL!BF7 -> actual | E88: =IF(Drop_PnL!B7="","",Drop_PnL!C7) -> founder | F88: =IF(Drop_PnL!B7="","",Drop_PnL!G7) -> 2 | G88: =IF(Drop_PnL!B7="","",Drop_PnL!E7) -> 5 | H88: =IF(Drop_PnL!B7="","",Drop_PnL!BA7) -> 1080 | I88: =IF(Drop_PnL!B7="","",Drop_PnL!BB7) -> 232 | J88: =IF(Drop_PnL!B7="","",Drop_PnL!BC7) -> 57 | K88: =IF(Drop_PnL!B7="","",Drop_PnL!BD7) -> 848 | L88: =IF(Drop_PnL!B7="","",Drop_PnL!BE7) -> 14.877193
A89: =IF(Drop_PnL!B8="","",Drop_PnL!A8) -> DRP-002 | B89: =IF(Drop_PnL!B8="","",Schedule!B8&"") -> Standard run 1 | C89: =IF(Drop_PnL!B8="","",Drop_PnL!B8) -> 46427 | D89: =Drop_PnL!BF8 -> plan | E89: =IF(Drop_PnL!B8="","",Drop_PnL!C8) -> courier | F89: =IF(Drop_PnL!B8="","",Drop_PnL!G8) -> 3 | G89: =IF(Drop_PnL!B8="","",Drop_PnL!E8) -> 10 | H89: =IF(Drop_PnL!B8="","",Drop_PnL!BA8) -> 4500 | I89: =IF(Drop_PnL!B8="","",Drop_PnL!BB8) -> 670 | J89: =IF(Drop_PnL!B8="","",Drop_PnL!BC8) -> 67 | K89: =IF(Drop_PnL!B8="","",Drop_PnL!BD8) -> 3830 | L89: =IF(Drop_PnL!B8="","",Drop_PnL!BE8) -> 57.164179
A90: =IF(Drop_PnL!B9="","",Drop_PnL!A9) -> DRP-003 | B90: =IF(Drop_PnL!B9="","",Schedule!B9&"") -> Standard run 2 | C90: =IF(Drop_PnL!B9="","",Drop_PnL!B9) -> 46441 | D90: =Drop_PnL!BF9 -> plan | E90: =IF(Drop_PnL!B9="","",Drop_PnL!C9) -> courier | F90: =IF(Drop_PnL!B9="","",Drop_PnL!G9) -> 3 | G90: =IF(Drop_PnL!B9="","",Drop_PnL!E9) -> 10 | H90: =IF(Drop_PnL!B9="","",Drop_PnL!BA9) -> 4500 | I90: =IF(Drop_PnL!B9="","",Drop_PnL!BB9) -> 670 | J90: =IF(Drop_PnL!B9="","",Drop_PnL!BC9) -> 58 | K90: =IF(Drop_PnL!B9="","",Drop_PnL!BD9) -> 3830 | L90: =IF(Drop_PnL!B9="","",Drop_PnL!BE9) -> 66.034483
A91: =IF(Drop_PnL!B10="","",Drop_PnL!A10) -> DRP-004 | B91: =IF(Drop_PnL!B10="","",Schedule!B10&"") -> Decision window drop 1 | C91: =IF(Drop_PnL!B10="","",Drop_PnL!B10) -> 46469 | D91: =Drop_PnL!BF10 -> plan | E91: =IF(Drop_PnL!B10="","",Drop_PnL!C10) -> direct-ship | F91: =IF(Drop_PnL!B10="","",Drop_PnL!G10) -> 3 | G91: =IF(Drop_PnL!B10="","",Drop_PnL!E10) -> 10 | H91: =IF(Drop_PnL!B10="","",Drop_PnL!BA10) -> 4500 | I91: =IF(Drop_PnL!B10="","",Drop_PnL!BB10) -> 370 | J91: =IF(Drop_PnL!B10="","",Drop_PnL!BC10) -> 41 | K91: =IF(Drop_PnL!B10="","",Drop_PnL!BD10) -> 4130 | L91: =IF(Drop_PnL!B10="","",Drop_PnL!BE10) -> 100.73171
A92: =IF(Drop_PnL!B11="","",Drop_PnL!A11) -> DRP-005 | B92: =IF(Drop_PnL!B11="","",Schedule!B11&"") -> Decision window drop 2 | C92: =IF(Drop_PnL!B11="","",Drop_PnL!B11) -> 46483 | D92: =Drop_PnL!BF11 -> plan | E92: =IF(Drop_PnL!B11="","",Drop_PnL!C11) -> direct-ship | F92: =IF(Drop_PnL!B11="","",Drop_PnL!G11) -> 3 | G92: =IF(Drop_PnL!B11="","",Drop_PnL!E11) -> 10 | H92: =IF(Drop_PnL!B11="","",Drop_PnL!BA11) -> 4500 | I92: =IF(Drop_PnL!B11="","",Drop_PnL!BB11) -> 370 | J92: =IF(Drop_PnL!B11="","",Drop_PnL!BC11) -> 41 | K92: =IF(Drop_PnL!B11="","",Drop_PnL!BD11) -> 4130 | L92: =IF(Drop_PnL!B11="","",Drop_PnL!BE11) -> 100.73171
A93: =IF(Drop_PnL!B12="","",Drop_PnL!A12) | B93: =IF(Drop_PnL!B12="","",Schedule!B12&"") | C93: =IF(Drop_PnL!B12="","",Drop_PnL!B12) | D93: =Drop_PnL!BF12 | E93: =IF(Drop_PnL!B12="","",Drop_PnL!C12) | F93: =IF(Drop_PnL!B12="","",Drop_PnL!G12) | G93: =IF(Drop_PnL!B12="","",Drop_PnL!E12) | H93: =IF(Drop_PnL!B12="","",Drop_PnL!BA12) | I93: =IF(Drop_PnL!B12="","",Drop_PnL!BB12) | J93: =IF(Drop_PnL!B12="","",Drop_PnL!BC12) | K93: =IF(Drop_PnL!B12="","",Drop_PnL!BD12) | L93: =IF(Drop_PnL!B12="","",Drop_PnL!BE12)
A94: =IF(Drop_PnL!B13="","",Drop_PnL!A13) | B94: =IF(Drop_PnL!B13="","",Schedule!B13&"") | C94: =IF(Drop_PnL!B13="","",Drop_PnL!B13) | D94: =Drop_PnL!BF13 | E94: =IF(Drop_PnL!B13="","",Drop_PnL!C13) | F94: =IF(Drop_PnL!B13="","",Drop_PnL!G13) | G94: =IF(Drop_PnL!B13="","",Drop_PnL!E13) | H94: =IF(Drop_PnL!B13="","",Drop_PnL!BA13) | I94: =IF(Drop_PnL!B13="","",Drop_PnL!BB13) | J94: =IF(Drop_PnL!B13="","",Drop_PnL!BC13) | K94: =IF(Drop_PnL!B13="","",Drop_PnL!BD13) | L94: =IF(Drop_PnL!B13="","",Drop_PnL!BE13)
A95: =IF(Drop_PnL!B14="","",Drop_PnL!A14) | B95: =IF(Drop_PnL!B14="","",Schedule!B14&"") | C95: =IF(Drop_PnL!B14="","",Drop_PnL!B14) | D95: =Drop_PnL!BF14 | E95: =IF(Drop_PnL!B14="","",Drop_PnL!C14) | F95: =IF(Drop_PnL!B14="","",Drop_PnL!G14) | G95: =IF(Drop_PnL!B14="","",Drop_PnL!E14) | H95: =IF(Drop_PnL!B14="","",Drop_PnL!BA14) | I95: =IF(Drop_PnL!B14="","",Drop_PnL!BB14) | J95: =IF(Drop_PnL!B14="","",Drop_PnL!BC14) | K95: =IF(Drop_PnL!B14="","",Drop_PnL!BD14) | L95: =IF(Drop_PnL!B14="","",Drop_PnL!BE14)
A96: =IF(Drop_PnL!B15="","",Drop_PnL!A15) | B96: =IF(Drop_PnL!B15="","",Schedule!B15&"") | C96: =IF(Drop_PnL!B15="","",Drop_PnL!B15) | D96: =Drop_PnL!BF15 | E96: =IF(Drop_PnL!B15="","",Drop_PnL!C15) | F96: =IF(Drop_PnL!B15="","",Drop_PnL!G15) | G96: =IF(Drop_PnL!B15="","",Drop_PnL!E15) | H96: =IF(Drop_PnL!B15="","",Drop_PnL!BA15) | I96: =IF(Drop_PnL!B15="","",Drop_PnL!BB15) | J96: =IF(Drop_PnL!B15="","",Drop_PnL!BC15) | K96: =IF(Drop_PnL!B15="","",Drop_PnL!BD15) | L96: =IF(Drop_PnL!B15="","",Drop_PnL!BE15)
A97: =IF(Drop_PnL!B16="","",Drop_PnL!A16) | B97: =IF(Drop_PnL!B16="","",Schedule!B16&"") | C97: =IF(Drop_PnL!B16="","",Drop_PnL!B16) | D97: =Drop_PnL!BF16 | E97: =IF(Drop_PnL!B16="","",Drop_PnL!C16) | F97: =IF(Drop_PnL!B16="","",Drop_PnL!G16) | G97: =IF(Drop_PnL!B16="","",Drop_PnL!E16) | H97: =IF(Drop_PnL!B16="","",Drop_PnL!BA16) | I97: =IF(Drop_PnL!B16="","",Drop_PnL!BB16) | J97: =IF(Drop_PnL!B16="","",Drop_PnL!BC16) | K97: =IF(Drop_PnL!B16="","",Drop_PnL!BD16) | L97: =IF(Drop_PnL!B16="","",Drop_PnL!BE16)
A98: =IF(Drop_PnL!B17="","",Drop_PnL!A17) | B98: =IF(Drop_PnL!B17="","",Schedule!B17&"") | C98: =IF(Drop_PnL!B17="","",Drop_PnL!B17) | D98: =Drop_PnL!BF17 | E98: =IF(Drop_PnL!B17="","",Drop_PnL!C17) | F98: =IF(Drop_PnL!B17="","",Drop_PnL!G17) | G98: =IF(Drop_PnL!B17="","",Drop_PnL!E17) | H98: =IF(Drop_PnL!B17="","",Drop_PnL!BA17) | I98: =IF(Drop_PnL!B17="","",Drop_PnL!BB17) | J98: =IF(Drop_PnL!B17="","",Drop_PnL!BC17) | K98: =IF(Drop_PnL!B17="","",Drop_PnL!BD17) | L98: =IF(Drop_PnL!B17="","",Drop_PnL!BE17)
A99: =IF(Drop_PnL!B18="","",Drop_PnL!A18) | B99: =IF(Drop_PnL!B18="","",Schedule!B18&"") | C99: =IF(Drop_PnL!B18="","",Drop_PnL!B18) | D99: =Drop_PnL!BF18 | E99: =IF(Drop_PnL!B18="","",Drop_PnL!C18) | F99: =IF(Drop_PnL!B18="","",Drop_PnL!G18) | G99: =IF(Drop_PnL!B18="","",Drop_PnL!E18) | H99: =IF(Drop_PnL!B18="","",Drop_PnL!BA18) | I99: =IF(Drop_PnL!B18="","",Drop_PnL!BB18) | J99: =IF(Drop_PnL!B18="","",Drop_PnL!BC18) | K99: =IF(Drop_PnL!B18="","",Drop_PnL!BD18) | L99: =IF(Drop_PnL!B18="","",Drop_PnL!BE18)
A100: Total | F100: =SUM(F88:F99) -> 14 | G100: =SUM(G88:G99) -> 45 | H100: =SUM(H88:H99) -> 19080 | I100: =SUM(I88:I99) -> 2312 | J100: =SUM(J88:J99) -> 264 | K100: =SUM(K88:K99) -> 16768 | L100: =IF(J100>0,K100/J100,"n/a") -> 63.515152
A102: Green: at or above the Gate 3 target per founder hour. Orange: below it. Campaign zero is expected to be below; the plan's own figure for it is $16. The total row is per founder hour across all scheduled drops, before overhead that drops do not absorb. Rows follow Schedule's row order, so a drop you add sits at the bottom whatever its date.

Sheet Inputs
A1: Inputs
A2: Every assumption in one labeled cell. Yellow cells are inputs. Blue cells are inputs that follow another cell by default; type over them to replace. Grey cells are calculated; do not type over them.
A3: All defaults are planning estimates from plan.md, never forecasts. 'Plan default' keeps the original figure; 'Changed' flags any cell you edit.
A6: 1. Company and calendar
A7: key | B7: Assumption | C7: Value | D7: Unit | E7: Low | F7: High | G7: Status | H7: Source | I7: Notes | J7: Plan default | K7: Changed?
A8: company_name | B8: Company name (working name, not yet cleared) | C8: Desk Drop | D8: text | G8: working name | H8: Prompt; CONTRACTS s2 rename-ability | I8: The only cell that holds the company name. Rename here and every tab follows. Not counted as a change. | J8: not tracked | K8: =IF(C8="","missing","")
A9: tagline | B9: Tagline (working, may change) | C9: Emerging brands. Delivered to your workday. | D9: text | G9: working | H9: Prompt; CONTRACTS s2 | I9: The only cell that holds the tagline. | J9: not tracked | K9: =IF(C9="","missing","")
A10: week1_start | B10: Week 1 starts (Monday) | C10: 46321 | D10: date | G10: derived, founder to confirm | H10: CONTRACTS.md section 3 (canonical calendar) | I10: Week n starts on this date plus 7 x (n - 1) days. Moving it moves the cash-flow weeks, software, the domain and any mailbox only. The gate dates below and the drop dates on Schedule are typed CONTRACTS dates: move them too. Checks flags week 1 moved on its own (review R3-09). | J10: 46321 | K10: =IF(C10&""=J10&"","","changed")
A11: gate0_date | B11: Gate 0 review (end of week 3) | C11: 46339 | D11: date | G11: derived, founder to confirm | H11: CONTRACTS.md section 3 (canonical calendar) | J11: 46339 | K11: =IF(C11&""=J11&"","","changed")
A12: gate1_date | B12: Gate 1 review (end of week 7) | C12: 46367 | D12: date | G12: derived, founder to confirm | H12: CONTRACTS.md section 3 (canonical calendar) | J12: 46367 | K12: =IF(C12&""=J12&"","","changed")
A13: gate2_date | B13: Gate 2 review (campaign zero report, T+7) | C13: =IFERROR(WORKDAY(INDEX(Schedule!$E$7:$E$18,MATCH(Inputs!$C$129,Schedule!$A$7:$A$18,0)),Inputs!$C$132,Lists!$N$4:$N$30),"") -> 46409 | D13: date | G13: derived, founder to confirm | H13: CONTRACTS.md section 3 (canonical calendar) | I13: Follows the Gate 2 drop on Schedule: its date plus the report deadline (T+7, 2027-01-22 by default). Moved from the plan's week 9 because campaign zero moved to 2027-01-12 (December blackout collision). | J13: =IFERROR(WORKDAY(INDEX(Schedule!$E$7:$E$18,MATCH(Inputs!$C$129,Schedule!$A$7:$A$18,0)),Inputs!$C$132,Lists!$N$4:$N$30),"") -> 46409 | K13: =IF(C13&""=J13&"","","changed")
A14: gate3_date | B14: Gate 3 review | C14: 46458 | D14: date | G14: derived, founder to confirm | H14: CONTRACTS.md section 3 (canonical calendar) | I14: Week 20; replaces the plan's week 16. | J14: 46458 | K14: =IF(C14&""=J14&"","","changed")
A15: decision_date | B15: Six-month decision (end of week 24) | C15: 46486 | D15: date | G15: derived, founder to confirm | H15: CONTRACTS.md section 3 (canonical calendar) | J15: 46486 | K15: =IF(C15&""=J15&"","","changed")
A16: as_of_override | B16: As-of date override (blank = today) | C16: 46430 | D16: date | G16: setting | H16: Model setting | I16: Leave blank to use today's date. Type a date to see gates and the next drop as of that day. | K16: =IF(C16&""=J16&"","","changed") -> changed
A17: as_of | B17: As-of date in use | C17: =IF(C16="",TODAY(),C16) -> 46430 | D17: date | G17: calculated | H17: Model
A18: days_per_week | B18: Days per week | C18: 7 | D18: days | G18: conversion | H18: Calendar | J18: 7 | K18: =IF(C18&""=J18&"","","changed")
A19: weeks_per_year | B19: Weeks per year | C19: 52 | D19: weeks | G19: conversion | H19: Calendar | J19: 52 | K19: =IF(C19&""=J19&"","","changed")
A20: months_per_year | B20: Months per year | C20: 12 | D20: months | G20: conversion | H20: Calendar | J20: 12 | K20: =IF(C20&""=J20&"","","changed")
A21: weeks_per_month | B21: Weeks per month | C21: =Inputs!$C$19/Inputs!$C$20 -> 4.3333333 | D21: weeks | G21: calculated | H21: Weeks per year / months per year
A22: hours_per_day | B22: Hours per day (converts Toggl durations) | C22: 24 | D22: hours | G22: conversion | H22: Calendar | J22: 24 | K22: =IF(C22&""=J22&"","","changed")
A23: window_bd | B23: Campaign window | C23: 5 | D23: business days | G23: planning estimate | H23: plan.md, What brands buy: 'Five business days' | I23: T is day 1; the window closes at T+4. | J23: 5 | K23: =IF(C23&""=J23&"","","changed")
A24: debrief_bd | B24: Debrief this many business days after the drop (T+10) | C24: 10 | D24: business days | G24: planning estimate | H24: CONTRACTS.md section 3 (canonical calendar) (debrief at T+10) | I24: Used to flag a decision-window drop whose results land after the decision date (Schedule, Dashboard). | J24: 10 | K24: =IF(C24&""=J24&"","","changed")
A25: llc_filing_bd | B25: LLC Articles filed this many business days after Gate 0 | C25: 4 | D25: business days | G25: derived, founder to confirm | H25: desk-drop-legal-pack/figures.csv (re-read 2026-10-24, after its 02:33 update), Articles timing: 'never before the attorney hour; earliest Thu 2026-11-19' | I25: Sets the filing date in section 11: Fri 2026-11-13 plus 4 business days is Thu 2026-11-19, the day after the attorney hour. | J25: 4 | K25: =IF(C25&""=J25&"","","changed")
A26: attorney_bd | B26: Attorney hour held this many business days after Gate 0 | C26: 3 | D26: business days | G26: derived, founder to confirm | H26: desk-drop-legal-pack/figures.csv (re-read 2026-10-24, after its 02:33 update), attorney_hour timing: 'booked at Gate 0 ... held early in week 4, by Wed 2026-11-18' | I26: Sets the attorney payment date in section 11 (Wed 2026-11-18). | J26: 3 | K26: =IF(C26&""=J26&"","","changed")
A27: accountant_bd | B27: Accountant hour held this many business days after Gate 0 | C27: 5 | D27: business days | G27: derived, founder to confirm | H27: desk-drop-legal-pack/figures.csv (re-read 2026-10-24, after its 02:33 update), accountant_hour timing: 'held in week 4, by Fri 2026-11-20' | I27: Sets the accountant payment date in section 11 (Fri 2026-11-20). | J27: 5 | K27: =IF(C27&""=J27&"","","changed")
A28: pub_order_bd | B28: Newspaper publication ordered this many business days after the LLC filing | C28: 10 | D28: business days | G28: derived, founder to confirm | H28: desk-drop-legal-pack/figures.csv (re-read 2026-10-24, after its 02:33 update), publication timing: 'Order within 10 business days of filing' | I28: Sets the publication payment date in section 11 (Fri 2026-12-04, skipping Thanksgiving). | J28: 10 | K28: =IF(C28&""=J28&"","","changed")
A29: pub_weeks | B29: Weekly newspaper runs before the Certificate of Publication is filed | C29: 6 | D29: weeks | G29: planning estimate | H29: plan.md, Legal table: 'publish in two newspapers for six weeks' | I29: Sets the certificate's payment date in section 11. | J29: 6 | K29: =IF(C29&""=J29&"","","changed")
A30: drop_prefix | B30: Drop ID prefix | C30: DRP- | D30: text | G30: convention | H30: CONTRACTS s6.5 (DRP-###) | I30: Toggl projects named DRP-001 etc. map to drops. | J30: DRP- | K30: =IF(C30&""=J30&"","","changed")
A31: office_window_days | B31: An office should get at most one drop in this many days | C31: 28 | D31: days | G31: derived, founder to confirm | H31: plan.md, What has to be true #4: 'Offices accept one drop a month' | I31: Four weeks counts as monthly, so drops 28 days apart do not flag. Used for the office-fatigue warning on Schedule. | J31: 28 | K31: =IF(C31&""=J31&"","","changed")
A33: 2. Scenario in force
A34: key | B34: Assumption | C34: Value | D34: Unit | E34: Low | F34: High | G34: Status | H34: Source | I34: Notes | J34: Plan default | K34: Changed?
A35: active_scenario | B35: Scenario applied to drops after Gate 3 and to the steady state | C35: Plan base | D35: list | G35: setting | H35: plan.md, After the first standard runs: decision scenarios | I35: Plan base = the plan's 'What has to be true'. A to D = the plan's four decision situations. See the Scenarios tab. | J35: Plan base | K35: =IF(C35&""=J35&"","","changed")
A37: 3. Prices and payment terms
A38: key | B38: Assumption | C38: Value | D38: Unit | E38: Low | F38: High | G38: Status | H38: Source | I38: Notes | J38: Plan default | K38: Changed?
A39: price_std_office | B39: Standard price per office | C39: 150 | D39: USD per office | G39: planning estimate | H39: plan.md, Revised model: Price table | I39: $1,500 for 10 offices. Change this cell to test a price. | J39: 150 | K39: =IF(C39&""=J39&"","","changed")
A40: std_pkg_offices | B40: Standard package size | C40: 10 | D40: offices | G40: planning estimate | H40: plan.md, Revised model: Price table | J40: 10 | K40: =IF(C40&""=J40&"","","changed")
A41: std_pkg_price | B41: Standard package price | C41: =Inputs!$C$39*Inputs!$C$40 -> 1500 | D41: USD per brand | G41: calculated | H41: Price per office x package offices
A42: price_fnd_office | B42: Founding price per office | C42: 120 | D42: USD per office | E42: 120 | F42: 180 | G42: planning estimate | H42: plan.md, Revised model: Price table | I42: $600 for 5 offices. The plan's summary table once said $600 to $900; the decided price is $600 (low end shown as default). | J42: 120 | K42: =IF(C42&""=J42&"","","changed")
A43: fnd_pkg_offices | B43: Founding package size | C43: 5 | D43: offices | G43: planning estimate | H43: plan.md, Revised model: Price table | J43: 5 | K43: =IF(C43&""=J43&"","","changed")
A44: fnd_pkg_price | B44: Founding package price | C44: =Inputs!$C$42*Inputs!$C$43 -> 600 | D44: USD per brand | G44: calculated | H44: Price per office x package offices
A45: extra_office_price | B45: Extra office beyond the package | C45: 150 | D45: USD per office | G45: planning estimate | H45: plan.md, Revised model: Price table | I45: Applies to offices beyond 5 (founding) or 10 (standard). Founding renewals stay at the founding rate per office for any office count. | J45: 150 | K45: =IF(C45&""=J45&"","","changed")
A46: founding_cap | B46: Founding tier closes after | C46: 3 | D46: brands | G46: planning estimate | H46: plan.md, Revised model: Price table | I46: 'First three brands only'. | J46: 3 | K46: =IF(C46&""=J46&"","","changed")
A47: founding_lock | B47: Founding price locked for | C47: 2 | D47: further campaigns | G47: planning estimate | H47: plan.md, Revised model: Price table | J47: 2 | K47: =IF(C47&""=J47&"","","changed")
A48: fnd_upfront_share | B48: Founding: share paid before product ships | C48: 1 | D48: share | G48: planning estimate | H48: plan.md, Revised model: Price table | I48: 'Paid in full before product ships'. | J48: 1 | K48: =IF(C48&""=J48&"","","changed")
A49: fnd_pay_lead_bd | B49: Founding: payment lands this many business days before the drop | C49: 20 | D49: business days | G49: derived, founder to confirm | H49: CONTRACTS.md section 3 (canonical calendar) | I49: Campaign zero's payment at Gate 1 (Fri 2026-12-11) is 20 business days before the Tue 2027-01-12 drop. | J49: 20 | K49: =IF(C49&""=J49&"","","changed")
A50: std_deposit_share | B50: Standard: share invoiced at signature | C50: 0.5 | D50: share | G50: planning estimate | H50: plan.md, Revised model: Price table | I50: 50% at signature, 50% at placement confirmation. | J50: 0.5 | K50: =IF(C50&""=J50&"","","changed")
A51: std_sign_lead_bd | B51: Standard: signature (deposit) this many business days before the drop | C51: 10 | D51: business days | G51: derived, founder to confirm | H51: plan.md, campaign calendar (brand ships at T-10) | I51: The latest signature that still lets the brand ship at T-10. Later cash is the conservative reading; the plan proposes drop dates three to four weeks out. | J51: 10 | K51: =IF(C51&""=J51&"","","changed")
A52: balance_lag_bd | B52: Standard: balance invoiced this many business days after the drop | C52: 1 | D52: business days | G52: derived, founder to confirm | H52: plan.md, What brands buy: placement within one business day | I52: Placement confirmation at T+1. | J52: 1 | K52: =IF(C52&""=J52&"","","changed")
A53: payment_lag_days | B53: Days from invoice to cash | D53: calendar days | G53: needs founder decision | H53: Not in the plan | I53: The plan states no invoice-to-cash lag. Blank = cash lands the day it is invoiced. Enter your invoice terms, for example 15. | K53: =IF(C53&""=J53&"","","changed")
A54: processing_rate | B54: Card processing rate | C54: 0.03 | D54: share of revenue | G54: planning estimate | H54: plan.md, Economics: hard-cost table | I54: Card fees. Zero by bank transfer. | J54: 0.03 | K54: =IF(C54&""=J54&"","","changed")
A55: processing_on | B55: Brands pay by card? 1 = yes, 0 = bank transfer | C55: 1 | D55: toggle | E55: 0 | F55: 1 | G55: setting | H55: plan.md, Economics: hard-cost table | I55: 1 is the high end of the plan's 0% to 3% range and matches its scenario rows. 0 is the plan's preferred invoicing (Wave, bank transfer). | J55: 1 | K55: =IF(C55&""=J55&"","","changed")
A57: 4. Drop size defaults (feed the derived Schedule rows) and units
A58: key | B58: Assumption | C58: Value | D58: Unit | E58: Low | F58: High | G58: Status | H58: Source | I58: Notes | J58: Plan default | K58: Changed?
A59: c0_offices | B59: Offices on campaign zero | C59: 5 | D59: offices | G59: planning estimate | H59: plan.md, scenario table: 'Campaign zero: 2 founding brands, 5 offices' | J59: 5 | K59: =IF(C59&""=J59&"","","changed")
A60: c0_brands | B60: Brands on campaign zero | C60: 2 | D60: brands | G60: planning estimate | H60: plan.md, scenario table and Gate 1 ('2 brands paid') | J60: 2 | K60: =IF(C60&""=J60&"","","changed")
A61: std_offices_drop | B61: Offices per standard drop | C61: 10 | D61: offices | G61: planning estimate | H61: plan.md, 'Standard runs of 10 offices and 3 brands per drop' | J61: 10 | K61: =IF(C61&""=J61&"","","changed")
A62: std_brands_drop | B62: Brands per standard drop | C62: 3 | D62: brands | G62: planning estimate | H62: plan.md, What has to be true #1: 'Three brands per drop' | I62: Feeds the standard Schedule rows and the plan-base scenario. | J62: 3 | K62: =IF(C62&""=J62&"","","changed")
A63: units_per_office | B63: Units per office per brand | C63: 50 | D63: units | G63: planning estimate | H63: plan.md, What brands buy | I63: Sized to Tuesday headcount (floor 30, ceiling 80). | J63: 50 | K63: =IF(C63&""=J63&"","","changed")
A64: reserve_share | B64: Reserve the brand ships on top | C64: 0.1 | D64: share | G64: planning estimate | H64: plan.md, What brands buy | J64: 0.1 | K64: =IF(C64&""=J64&"","","changed")
A66: 5. Hard costs and monthly overhead
A67: key | B67: Assumption | C67: Value | D67: Unit | E67: Low | F67: High | G67: Status | H67: Source | I67: Notes | J67: Plan default | K67: Changed?
A68: kit_per_office | B68: Display kit per office per drop (card, allergen line, case label) | C68: 8 | D68: USD per office per drop | G68: planning estimate | H68: plan.md, Economics: hard-cost table | I68: Plan reading (a): per office per drop, not per brand. Only this reproduces the scenario hard costs. | J68: 8 | K68: =IF(C68&""=J68&"","","changed")
A69: card_extra | B69: Extra tent card per additional brand per office | D69: USD per card | E69: 1 | F69: 2 | G69: needs founder decision | H69: plan.md, Hardware: tent cards roughly $1 to $2 each | I69: Reading (a) keeps one $8 kit per office even on a three-brand drop. If each brand needs its own card, enter $1 to $2. | K69: =IF(C69&""=J69&"","","changed")
A70: founder_transport | B70: Founder delivery (car rides) per drop | C70: 120 | D70: USD per drop | G70: planning estimate | H70: plan.md, Economics: hard-cost table | I70: 'You delivering costs about $120 in car rides.' | J70: 120 | K70: =IF(C70&""=J70&"","","changed")
A71: courier_per_stop | B71: Courier per stop | C71: 30 | D71: USD per stop | E71: 25 | F71: 40 | G71: planning estimate, needs quote | H71: plan.md, Economics: hard-cost table | I71: $300 for a ten-stop route is $30 a stop; plan range $25 to $40. No reliable published rate; get three quotes. | J71: 30 | K71: =IF(C71&""=J71&"","","changed")
A72: direct_transport | B72: Transport when brands ship direct | C72: 0 | D72: USD per drop | G72: planning estimate | H72: plan.md, scenario table, direct-ship row | I72: Plan reading (c): the $370 direct-ship row carries $0 transport. | J72: 0 | K72: =IF(C72&""=J72&"","","changed")
A73: kit_mail_per_office | B73: Mailing the display kit ahead (direct-ship) | D73: USD per office | G73: needs quote | H73: plan.md, Delivery by phase: '... mails the display kit ahead' | I73: The plan gives no figure. Blank counts as $0. | K73: =IF(C73&""=J73&"","","changed")
A74: kit_print_bd | B74: Kits printed this many business days before the drop | C74: 3 | D74: business days | G74: planning estimate | H74: plan.md, campaign calendar: T minus 3 | J74: 3 | K74: =IF(C74&""=J74&"","","changed")
A75: storage_choice | B75: Storage | C75: unit | D75: list | G75: setting | H75: plan.md, Economics: hard-cost table | I75: unit = small storage unit; home = sealed cases at home, $0. | J75: unit | K75: =IF(C75&""=J75&"","","changed")
A76: storage_monthly | B76: Storage unit per month | C76: 150 | D76: USD per month | G76: planning estimate | H76: plan.md, Economics: hard-cost table | I76: Allocation is half: $75 a drop at two drops a month. | J76: 150 | K76: =IF(C76&""=J76&"","","changed")
A77: storage_start | B77: Storage unit rented from | C77: =IF(COUNT(Schedule!$AJ$7:$AJ$18)=0,"",EOMONTH(MIN(Schedule!$AJ$7:$AJ$18),-1)+1) -> 46419 | D77: date | G77: derived, founder to confirm | H77: Plan reading (b) | I77: Follows Schedule: the first day of the month of the first standard drop that runs (2027-02-01 by default). Blank when no standard drop runs. Campaign zero stays at home, which is how its $280 reproduces. | J77: =IF(COUNT(Schedule!$AJ$7:$AJ$18)=0,"",EOMONTH(MIN(Schedule!$AJ$7:$AJ$18),-1)+1) -> 46419 | K77: =IF(C77&""=J77&"","","changed")
A78: storage_end | B78: Storage unit released (blank = keep) | D78: date | G78: setting | H78: Plan reading (c) | I78: Blank keeps the unit through the window, as the plan's direct-ship row keeps the $75. | K78: =IF(C78&""=J78&"","","changed")
A79: software_monthly | B79: Software per month | C79: 60 | D79: USD per month | E79: 7 | F79: 81 | G79: planning estimate | H79: plan.md, Economics: Capital to the first six months; Tools table | I79: $360 for six months. Tools table sums to $7 to $81; the plan caps software under $60. | J79: 60 | K79: =IF(C79&""=J79&"","","changed")
A80: software_start | B80: Software paid from | C80: =Inputs!$C$10 -> 46321 | D80: date | G80: derived, founder to confirm | H80: plan.md, Week 1 setup | I80: Follows week 1. | J80: =Inputs!$C$10 -> 46321 | K80: =IF(C80&""=J80&"","","changed")
A81: insurance_monthly | B81: General liability insurance per month | C81: 100 | D81: USD per month | E81: 41.666667 | F81: 125 | G81: plan estimate (legal pack); three quotes before binding | H81: plan.md, Economics: hard-cost table; desk-drop-legal-pack/figures.csv (re-read 2026-10-24, after its 02:33 update) | I81: 'Roughly $100 a month'. Capital table range $500 to $1,500 a year, shown here per month. The legal pack carries $1,200 a year as a plan estimate and asks for a quote before binding. | J81: 100 | K81: =IF(C81&""=J81&"","","changed")
A82: insurance_billing | B82: Insurance billing | C82: annual | D82: list | G82: setting | H82: plan.md, Economics: Capital to the first six months | I82: annual = one year's premium paid at bind (capital table 'one year'). | J82: annual | K82: =IF(C82&""=J82&"","","changed")
A83: insurance_bind | B83: Insurance bound on | C83: =Inputs!$C$12 -> 46367 | D83: date | G83: derived, founder to confirm | H83: plan.md, setup checklist: 'At Gate 1 pass: Insurance bound' | I83: Follows Gate 1. The legal pack's latest bind date is 2026-12-21. | J83: =Inputs!$C$12 -> 46367 | K83: =IF(C83&""=J83&"","","changed")
A84: phone_monthly | B84: Phone per month | C84: 0 | D84: USD per month | G84: planning estimate | H84: plan.md, Tools: 'Your phone', Google Voice $0 | J84: 0 | K84: =IF(C84&""=J84&"","","changed")
A85: alloc_drops_month | B85: Drops per month used to allocate overhead to a drop | C85: 2 | D85: drops per month | G85: planning estimate | H85: plan.md, Economics: hard-cost table | I85: Insurance $100 a month over two drops = $50; software $60 = $30; storage $150 = $75. | J85: 2 | K85: =IF(C85&""=J85&"","","changed")
A87: 6. Founder hours (rates; the plan's table is reproduced on Plan_Check)
A88: key | B88: Assumption | C88: Value | D88: Unit | E88: Low | F88: High | G88: Status | H88: Source | I88: Notes | J88: Plan default | K88: Changed?
A89: h_first_brand | B89: Brand sales per first (founding) brand | C89: 10 | D89: hours per brand | G89: planning estimate | H89: plan.md, Economics: founder-hour table | I89: '20 (10 per brand, first ones)'. | J89: 10 | K89: =IF(C89&""=J89&"","","changed")
A90: close_rate | B90: Close rate on qualified brand conversations | C90: 0.2 | D90: share | G90: planning estimate | H90: plan.md, What has to be true #2 | I90: One close from five. | J90: 0.2 | K90: =IF(C90&""=J90&"","","changed")
A91: h_per_conv | B91: Hours per qualified conversation | C91: 0.75 | D91: hours | G91: planning estimate | H91: plan.md, Economics: 'conversations of 45 minutes' | J91: 0.75 | K91: =IF(C91&""=J91&"","","changed")
A92: h_paperwork | B92: Proposal and paperwork per win | C92: 2.25 | D92: hours | G92: derived, founder to confirm | H92: plan.md, Economics: founder-hour table | I92: 6 - 5 x 0.75, so the plan's six hours per win reproduces at a 20% close rate. | J92: 2.25 | K92: =IF(C92&""=J92&"","","changed")
A93: h_win | B93: Brand sales per standard win | C93: =1/Inputs!$C$90*Inputs!$C$91+Inputs!$C$92 -> 6 | D93: hours per brand | G93: calculated | H93: Conversations per win x hours each + paperwork | I93: 6.0 at plan inputs. Falls as the close rate rises.
A94: h_renewal | B94: Brand sales per renewal | C94: 2 | D94: hours per renewal | G94: planning estimate | H94: plan.md, Economics: 'A renewal takes about two hours' | J94: 2 | K94: =IF(C94&""=J94&"","","changed")
A95: h_new_office | B95: Office recruiting per new office | C95: 4 | D95: hours per office | G95: planning estimate | H95: plan.md, Economics: founder-hour table | I95: '20 (4 per new office)'. | J95: 4 | K95: =IF(C95&""=J95&"","","changed")
A96: h_existing_office | B96: Office coordination per existing office | C96: 1 | D96: hours per office | G96: planning estimate | H96: plan.md, Economics: founder-hour table | I96: '10 (1 per existing office)'. | J96: 1 | K96: =IF(C96&""=J96&"","","changed")
A97: rk_per_brand | B97: Receiving and kitting per brand | C97: 0.5 | D97: hours per brand | G97: derived, founder to confirm | H97: plan.md, Economics: founder-hour table | I97: (4 - 3) / (3 - 1): 1-brand drop 3 h, 3-brand drop 4 h. | J97: 0.5 | K97: =IF(C97&""=J97&"","","changed")
A98: rep_per_brand | B98: Reporting and debriefs per brand | C98: 2 | D98: hours per brand | G98: planning estimate | H98: plan.md, Economics: founder-hour table | I98: '6 (2 per brand)'. | J98: 2 | K98: =IF(C98&""=J98&"","","changed")
A99: admin_per_drop | B99: Admin and invoicing per drop | C99: 2 | D99: hours per drop | G99: planning estimate | H99: plan.md, Economics: founder-hour table | J99: 2 | K99: =IF(C99&""=J99&"","","changed")
A100: discovery_hours_week | B100: Discovery hours per week, weeks 1 to 3 (not tied to a drop) | C100: 15 | D100: hours per week | E100: 10 | F100: 15 | G100: planning estimate | H100: plan.md, Time budget: 'Phases 0 and 1 need 10 to 15 hours a week' | I100: High end. Weeks 4 to 7 selling and recruiting already sit in campaign zero's 57 hours. Used only in the six-month all-in view. | J100: 15 | K100: =IF(C100&""=J100&"","","changed")
A101: discovery_weeks | B101: Discovery weeks | C101: 3 | D101: weeks | G101: planning estimate | H101: plan.md, Phase 0 (weeks 1 to 3) | J101: 3 | K101: =IF(C101&""=J101&"","","changed")
A103: 7. Costs and hours that depend on the delivery model
A104: key | B104: Delivery model | C104: Transport per drop (USD) | D104: Transport per stop (USD) | E104: Kit mailing per office (USD) | F104: Receiving and kitting base (h) | G104: Drop day per office (h) | H104: Checks and pickup per office (h) | I104: Derivation from the plan's hour table
A105: model_table | B105: founder | C105: =Inputs!$C$70 -> 120 | D105: 0 | E105: 0 | F105: 2 | G105: 1 | H105: 0.6 | I105: Campaign zero column (2 brands, 5 offices): receiving 3 = 2.0 + 0.5 x 2; drop day 5 h / 5 offices; checks 3 h / 5 offices.
A106: model_table | B106: courier | C106: 0 | D106: =Inputs!$C$71 -> 30 | E106: 0 | F106: 2.5 | G106: 0.8 | H106: 0.4 | I106: 1-brand and 3-brand columns (10 offices): receiving 3 = 2.5 + 0.5 x 1 and 4 = 2.5 + 0.5 x 3; drop day 8 h / 10; checks 4 h / 10.
A107: model_table | B107: direct-ship | C107: =Inputs!$C$72 -> 0 | D107: 0 | E107: =Inputs!$C$73 -> 0 | F107: 0.5 | G107: 0.3 | H107: 0.4 | I107: Direct-ship column (3 brands, 10 offices): receiving 2 = 0.5 + 0.5 x 3; drop day 3 h / 10; checks 4 h / 10.
A109: 8. Renewal, steady state and founder capital
...

Sheet Scenarios
A1: Scenarios A to D
A2: The plan's four decision situations as assumption sets. Pick one on Inputs ('Scenario in force'). The Active column feeds drops after Gate 3 and the steady state.
A3: Planning estimates. Where a scenario does not name a figure, it follows the plan base (blue cells) and says so. Nothing here is a forecast of which scenario will happen.
B5: Lever | C5: Plan base | D5: A | E5: B | F5: C | G5: D | H5: Active (in force) | I5: Unit | J5: Source and reading | L5: default: Plan base | M5: default: A | N5: default: B | O5: default: C | P5: default: D | Q5: Changed? | R5: Blank in force? (1 = needs a figure)
B6: Situation | C6: What has to be true | D6: Both sides work | E6: Brands pay once, offices love it | F6: Brands willing, offices unreliable | G6: Neither converts
B7: What the numbers show | C7: Three brands per drop, six hours or less per win, 40% renew, $1,500 holds | D7: 40% or more of brands renew; placement above 80%; contribution above $50 an hour | E7: Renewal under 30%; offices asking when the next drop is | F7: Placement under 80% twice; photos missing; responses under five | G7: No renewal, weak placement
B8: What to do next (plan) | C8: Run the plan | D8: Scale: second cluster, roster 20 to 30, price to $1,800 to $2,000, part-time delivery at about $25 an hour above two drops a month, launch-partner tier | E8: Fix the evidence, run two more drops; if renewal is still under 30%, switch to office-paid for offices that named $100 a month or more | F8: Replace the weakest offices, raise the commitment bar; if a third drop misses, stop | G8: Stop; write the post-mortem; keep office relationships warm
B10: Post-Gate-3 drops that run in the six months (of the two scheduled) | C10: 2 | D10: 2 | E10: 2 | F10: 1 | G10: 0 | H10: =INDEX(C10:G10,1,MATCH(Inputs!$C$35,$C$5:$G$5,0)) -> 2 | I10: drops | J10: Base and A: two drops a month. B: 'run two more drops'. C: 'if a third drop misses, stop', so one more. D: 'Stop'. | L10: 2 | M10: 2 | N10: 2 | O10: 1 | P10: 0 | Q10: =IF(AND(C10&""=L10&"",D10&""=M10&"",E10&""=N10&"",F10&""=O10&"",G10&""=P10&""),"","changed") | R10: =IF(INDEX(C10:G10,1,MATCH(Inputs!$C$35,$C$5:$G$5,0))="",1,0) -> 0
B11: Brands per drop after Gate 3 | C11: =Inputs!$C$62 -> 3 | D11: =$C11 -> 3 | E11: =$C11 -> 3 | F11: =$C11 -> 3 | G11: 0 | H11: =INDEX(C11:G11,1,MATCH(Inputs!$C$35,$C$5:$G$5,0)) -> 3 | I11: brands | J11: Plan: three brands per drop (Inputs, 'Brands per standard drop'). A, B and C do not name a figure, so they follow the plan base. D stops. | L11: =Inputs!$C$62 -> 3 | M11: =$C11 -> 3 | N11: =$C11 -> 3 | O11: =$C11 -> 3 | P11: 0 | Q11: =IF(AND(C11&""=L11&"",D11&""=M11&"",E11&""=N11&"",F11&""=O11&"",G11&""=P11&""),"","changed") | R11: =IF(INDEX(C11:G11,1,MATCH(Inputs!$C$35,$C$5:$G$5,0))="",1,0) -> 0
B12: Renewal rate (share of brand slots that are renewals) | C12: =Inputs!$C$111 -> 0.4 | D12: 0.4 | E12: 0 | F12: =C12 -> 0.4 | G12: 0 | H12: =INDEX(C12:G12,1,MATCH(Inputs!$C$35,$C$5:$G$5,0)) -> 0.4 | I12: share | J12: A: '40% or more', low end. B: 'under 30%' and 'brands pay once': 0%, the low end of 0% to 29%. C: not named, plan base. D: 'No renewal'. | L12: =Inputs!$C$111 -> 0.4 | M12: 0.4 | N12: 0 | O12: =C12 -> 0.4 | P12: 0 | Q12: =IF(AND(C12&""=L12&"",D12&""=M12&"",E12&""=N12&"",F12&""=O12&"",G12&""=P12&""),"","changed") | R12: =IF(INDEX(C12:G12,1,MATCH(Inputs!$C$35,$C$5:$G$5,0))="",1,0) -> 0
B13: New offices recruited per post-Gate-3 drop | C13: 0 | D13: 4 | E13: 0 | G13: 0 | H13: =INDEX(C13:G13,1,MATCH(Inputs!$C$35,$C$5:$G$5,0)) -> 0 | I13: offices | J13: A: 'Grow the roster to 20 to 30 offices': 4 new offices on each of the two decision-window drops take the 12-office roster to 20, the low end (derived, founder to confirm; review R3-08). C: 'replace the weakest offices'; the plan gives no count. Blank = 0; founder to set. | L13: 0 | M13: 4 | N13: 0 | P13: 0 | Q13: =IF(AND(C13&""=L13&"",D13&""=M13&"",E13&""=N13&"",F13&""=O13&"",G13&""=P13&""),"","changed") | R13: =IF(INDEX(C13:G13,1,MATCH(Inputs!$C$35,$C$5:$G$5,0))="",1,0) -> 0
B14: Standard price per office for drops after the decision date | C14: =Inputs!$C$39 -> 150 | D14: 180 | E14: =Inputs!$C$39 -> 150 | F14: =Inputs!$C$39 -> 150 | G14: =Inputs!$C$39 -> 150 | H14: =INDEX(C14:G14,1,MATCH(Inputs!$C$35,$C$5:$G$5,0)) -> 150 | I14: USD per office | J14: A: 'raise the standard price to $1,800 to $2,000' = $180 to $200 per office; low end. | L14: =Inputs!$C$39 -> 150 | M14: 180 | N14: =Inputs!$C$39 -> 150 | O14: =Inputs!$C$39 -> 150 | P14: =Inputs!$C$39 -> 150 | Q14: =IF(AND(C14&""=L14&"",D14&""=M14&"",E14&""=N14&"",F14&""=O14&"",G14&""=P14&""),"","changed") | R14: =IF(INDEX(C14:G14,1,MATCH(Inputs!$C$35,$C$5:$G$5,0))="",1,0) -> 0
B15: Steady-state drops per month | C15: =Inputs!$C$112 -> 2 | D15: =$C15 -> 2 | E15: =$C15 -> 2 | F15: =$C15 -> 2 | G15: 0 | H15: =INDEX(C15:G15,1,MATCH(Inputs!$C$35,$C$5:$G$5,0)) -> 2 | I15: drops per month | J15: Plan monthly picture: two drops a month (Inputs section 8). A, B and C follow the plan base. D stops. | L15: =Inputs!$C$112 -> 2 | M15: =$C15 -> 2 | N15: =$C15 -> 2 | O15: =$C15 -> 2 | P15: 0 | Q15: =IF(AND(C15&""=L15&"",D15&""=M15&"",E15&""=N15&"",F15&""=O15&"",G15&""=P15&""),"","changed") | R15: =IF(INDEX(C15:G15,1,MATCH(Inputs!$C$35,$C$5:$G$5,0))="",1,0) -> 0
B16: Steady-state brands per drop | C16: =Inputs!$C$62 -> 3 | D16: =$C16 -> 3 | E16: =$C16 -> 3 | F16: =$C16 -> 3 | G16: 0 | H16: =INDEX(C16:G16,1,MATCH(Inputs!$C$35,$C$5:$G$5,0)) -> 3 | I16: brands | J16: Plan monthly picture: three-brand drops (Inputs, 'Brands per standard drop'). A, B and C follow the plan base. D stops. | L16: =Inputs!$C$62 -> 3 | M16: =$C16 -> 3 | N16: =$C16 -> 3 | O16: =$C16 -> 3 | P16: 0 | Q16: =IF(AND(C16&""=L16&"",D16&""=M16&"",E16&""=N16&"",F16&""=O16&"",G16&""=P16&""),"","changed") | R16: =IF(INDEX(C16:G16,1,MATCH(Inputs!$C$35,$C$5:$G$5,0))="",1,0) -> 0
B17: Offices on an office-paid tier (steady state) | C17: 0 | D17: 0 | E17: 5 | F17: 0 | G17: 0 | H17: =INDEX(C17:G17,1,MATCH(Inputs!$C$35,$C$5:$G$5,0)) -> 0 | I17: offices | J17: B: offices that named $100 a month or more; at least five. | L17: 0 | M17: 0 | N17: 5 | O17: 0 | P17: 0 | Q17: =IF(AND(C17&""=L17&"",D17&""=M17&"",E17&""=N17&"",F17&""=O17&"",G17&""=P17&""),"","changed") | R17: =IF(INDEX(C17:G17,1,MATCH(Inputs!$C$35,$C$5:$G$5,0))="",1,0) -> 0
B18: Office-paid fee per office per month | E18: 100 | H18: =INDEX(C18:G18,1,MATCH(Inputs!$C$35,$C$5:$G$5,0)) -> 0 | I18: USD per month | J18: B: $100 to $200 a month; low end. | N18: 100 | Q18: =IF(AND(C18&""=L18&"",D18&""=M18&"",E18&""=N18&"",F18&""=O18&"",G18&""=P18&""),"","changed") | R18: =IF(INDEX(C18:G18,1,MATCH(Inputs!$C$35,$C$5:$G$5,0))="",1,0) -> 1
B19: Cost to serve one office-paid office per month | H19: =INDEX(C19:G19,1,MATCH(Inputs!$C$35,$C$5:$G$5,0)) -> 0 | I19: USD per month | J19: Needs quote. The plan prices no cost for guaranteed twice-monthly curated drops. | Q19: =IF(AND(C19&""=L19&"",D19&""=M19&"",E19&""=N19&"",F19&""=O19&"",G19&""=P19&""),"","changed") | R19: =IF(INDEX(C19:G19,1,MATCH(Inputs!$C$35,$C$5:$G$5,0))="",1,0) -> 1
B20: Part-time delivery hire | C20: 25 | D20: 25 | H20: =INDEX(C20:G20,1,MATCH(Inputs!$C$35,$C$5:$G$5,0)) -> 25 | I20: USD per hour | J20: A: 'about $25 an hour once you run more than two drops a month'. It replaces drop-day hours (model reading). | L20: 25 | M20: 25 | Q20: =IF(AND(C20&""=L20&"",D20&""=M20&"",E20&""=N20&"",F20&""=O20&"",G20&""=P20&""),"","changed") | R20: =IF(INDEX(C20:G20,1,MATCH(Inputs!$C$35,$C$5:$G$5,0))="",1,0) -> 0
B21: Hire once steady-state drops per month exceed | C21: 2 | D21: =$C21 -> 2 | E21: =$C21 -> 2 | F21: =$C21 -> 2 | G21: =$C21 -> 2 | H21: =INDEX(C21:G21,1,MATCH(Inputs!$C$35,$C$5:$G$5,0)) -> 2 | I21: drops per month | J21: Plan: 'more than two drops a month'. One rule for every scenario, so A to D follow the plan base. | L21: 2 | M21: =$C21 -> 2 | N21: =$C21 -> 2 | O21: =$C21 -> 2 | P21: =$C21 -> 2 | Q21: =IF(AND(C21&""=L21&"",D21&""=M21&"",E21&""=N21&"",F21&""=O21&"",G21&""=P21&""),"","changed") | R21: =IF(INDEX(C21:G21,1,MATCH(Inputs!$C$35,$C$5:$G$5,0))="",1,0) -> 0
B23: How it works
B24: The two decision-window drops on Schedule (DRP-004, DRP-005) take brands, renewals and new offices from the Active column. Type over those Schedule cells to replace the scenario with real plans. The steady-state view and the sensitivity tables use the Active column too. Drops before Gate 3 do not change with the scenario. A lever left blank in the scenario in force counts as zero, and column R flags it: scenario B's office-paid revenue is left out of the steady-state net until its cost to serve is quoted.

Sheet Schedule
A1: Drop schedule
A2: One row per drop. Edit dates, delivery model, offices, brands and renewals. Rows marked derived are the simplest schedule that meets the plan; founder to confirm.
A3: Planning estimates, not a forecast. Drop days are Tuesday or Wednesday only; no window may overlap a blackout (Lists). Set 'Actuals in' to Y once a drop's actuals are pasted, and the model switches that drop from plan to actual.
A4: Yellow = your input. Blue = follows Inputs or the scenario in force; type over it to replace. Red 'changed' = the row no longer matches the derived default.
Y5: Brand wins the schedule needs, beside the pipeline's actual counts | AF5: Results against the decision date | AL5: Derived defaults (for the 'Changed' flag; do not edit)
A6: drop_id | B6: Label | C6: Basis | D6: Post-Gate-3 sequence | E6: Drop date | F6: Day | G6: Delivery model | H6: Tier | I6: Offices | J6: New offices | K6: Brands | L6: of which renewals | M6: of which founding-rate renewals | N6: Actuals in (Y/N) | O6: Notes | P6: Tue or Wed? | Q6: Window closes (T+4) | R6: Blackout clash? | S6: Units brands ship (incl. reserve) | T6: Row check | U6: Office slots on drops in the last four weeks | V6: Roster to date (new offices so far) | W6: Office fatigue | X6: Changed from the derived default? | Y6: Sign by (latest deposit or full payment) | Z6: New brand wins needed (brands less renewals) | AA6: Qualified brand conversations implied (wins / close rate) | AB6: Wins needed, cumulative to this sign-by date | AC6: Conversations implied, cumulative | AD6: Actual: brands paid by this sign-by date (Pipeline) | AE6: Actual: brand conversations by this sign-by date (Pipeline) | AF6: Debrief (T+10) | AG6: Results after the decision date? | AH6: Debrief date, if after the decision | AI6: Offices to add so none gets two drops within four weeks | AJ6: Standard drop that runs: its date (sets the storage start) | AL6: default date | AM6: default model | AN6: default tier | AO6: default offices | AP6: default new offices | AQ6: default brands | AR6: default renewals | AS6: default founding renewals
A7: DRP-001 | B7: Campaign zero (founding) | C7: derived: CONTRACTS s3 | E7: 46399 | F7: =IF(E7="","",TEXT(E7,"ddd")) -> Tue | G7: founder | H7: founding | I7: =Inputs!$C$59 -> 5 | J7: =IF(N(K7)=0,0,I7) -> 5 | K7: =Inputs!$C$60 -> 2 | L7: 0 | M7: 0 | N7: Y | O7: Stretch option Tue 2026-12-08 only if both brands pay by 2026-11-20. Brands asked to ship by 2026-12-22. | P7: =IF(E7="","",IF(OR(WEEKDAY(E7)=Lists!$V$4,WEEKDAY(E7)=Lists!$V$5),"ok","not Tue/Wed")) -> ok | Q7: =IF(E7="","",WORKDAY(E7,Inputs!$C$23-1,Lists!$N$4:$N$30)) -> 46406 | R7: =IF(E7="","",IF(COUNTIFS(Lists!$Q$4:$Q$12,"<="&Q7,Lists!$R$4:$R$12,">="&E7)>0,"clash","ok")) -> ok | S7: =IF(E7="","",N(K7)*N(I7)*Inputs!$C$63*(1+Inputs!$C$64)) -> 550 | T7: =IF(E7="",IF(N(K7)>0,"date missing",""),IF(AND(P7="ok",R7="ok",N(J7)<=N(I7),N(L7)<=N(K7),N(M7)<=N(L7),OR(N(K7)=0,N(I7)>0),G7<>"",H7<>""),"ok","check")) -> ok | U7: =IF(OR(E7="",N(K7)=0),"",SUMIFS($I$7:$I$18,$E$7:$E$18,">"&E7-Inputs!$C$31,$E$7:$E$18,"<="&E7,$K$7:$K$18,">0")) -> 5 | V7: =IF(E7="","",SUMIFS($J$7:$J$18,$E$7:$E$18,"<="&E7)) -> 5 | W7: =IF(U7="","",IF(U7>V7,"some offices get a second drop within four weeks","ok")) -> ok | X7: =IF(AND(E7&""=AL7&"",G7&""=AM7&"",H7&""=AN7&"",I7&""=AO7&"",J7&""=AP7&"",K7&""=AQ7&"",L7&""=AR7&"",M7&""=AS7&""),"","changed") | Y7: =IF(OR(E7="",N(K7)=0),"",WORKDAY(E7,-IF(H7="founding",Inputs!$C$49,Inputs!$C$51),Lists!$N$4:$N$30)) -> 46367 | Z7: =IF(Y7="","",N(K7)-N(L7)) -> 2 | AA7: =IF(Z7="","",Z7/Inputs!$C$90) -> 10 | AB7: =IF(Y7="","",SUMIFS($Z$7:$Z$18,$Y$7:$Y$18,"<="&Y7)) -> 2 | AC7: =IF(AB7="","",AB7/Inputs!$C$90) -> 10 | AD7: =IF(Y7="","",SUMIFS(Pipeline!$T$5:$T$1004,Pipeline!$B$5:$B$1004,"brand",Pipeline!$E$5:$E$1004,"paid",Pipeline!$A$5:$A$1004,"<="&Y7)) -> 2 | AE7: =IF(Y7="","",SUMIFS(Pipeline!$T$5:$T$1004,Pipeline!$B$5:$B$1004,"brand",Pipeline!$E$5:$E$1004,"conversation",Pipeline!$A$5:$A$1004,"<="&Y7)) -> 0 | AF7: =IF(Y7="","",WORKDAY(E7,Inputs!$C$24,Lists!$N$4:$N$30)) -> 46414 | AG7: =IF(AF7="","",IF(AND(E7>Inputs!$C$14,E7<=Inputs!$C$15,AF7>Inputs!$C$15),"after the decision","ok")) -> ok | AH7: =IF(AG7="after the decision",AF7,"") | AI7: =IF(U7="","",MIN(N(I7)-N(J7),MAX(0,U7-V7))) -> 0 | AJ7: =IF(AND(H7="standard",N(K7)>0,E7<>""),E7,"") | AL7: 46399 | AM7: founder | AN7: founding | AO7: =Inputs!$C$59 -> 5 | AP7: =IF(N(K7)=0,0,I7) -> 5 | AQ7: =Inputs!$C$60 -> 2 | AR7: 0 | AS7: 0
A8: DRP-002 | B8: Standard run 1 | C8: derived: CONTRACTS s3 | E8: 46427 | F8: =IF(E8="","",TEXT(E8,"ddd")) -> Tue | G8: courier | H8: standard | I8: =Inputs!$C$61 -> 10 | J8: =IF(N(K8)=0,0,MAX(0,I8-SUM(J$7:J7))) -> 5 | K8: =Inputs!$C$62 -> 3 | L8: 0 | M8: 0 | N8: N | O8: Campaigns one and two: founder plus courier (plan). New offices fill the drop: five take the roster from 5 to 10. No founding renewal: its latest signature (T-10, 2027-01-26) is two business days after the campaign-zero report. | P8: =IF(E8="","",IF(OR(WEEKDAY(E8)=Lists!$V$4,WEEKDAY(E8)=Lists!$V$5),"ok","not Tue/Wed")) -> ok | Q8: =IF(E8="","",WORKDAY(E8,Inputs!$C$23-1,Lists!$N$4:$N$30)) -> 46434 | R8: =IF(E8="","",IF(COUNTIFS(Lists!$Q$4:$Q$12,"<="&Q8,Lists!$R$4:$R$12,">="&E8)>0,"clash","ok")) -> ok | S8: =IF(E8="","",N(K8)*N(I8)*Inputs!$C$63*(1+Inputs!$C$64)) -> 1650 | T8: =IF(E8="",IF(N(K8)>0,"date missing",""),IF(AND(P8="ok",R8="ok",N(J8)<=N(I8),N(L8)<=N(K8),N(M8)<=N(L8),OR(N(K8)=0,N(I8)>0),G8<>"",H8<>""),"ok","check")) -> ok | U8: =IF(OR(E8="",N(K8)=0),"",SUMIFS($I$7:$I$18,$E$7:$E$18,">"&E8-Inputs!$C$31,$E$7:$E$18,"<="&E8,$K$7:$K$18,">0")) -> 10 | V8: =IF(E8="","",SUMIFS($J$7:$J$18,$E$7:$E$18,"<="&E8)) -> 10 | W8: =IF(U8="","",IF(U8>V8,"some offices get a second drop within four weeks","ok")) -> ok | X8: =IF(AND(E8&""=AL8&"",G8&""=AM8&"",H8&""=AN8&"",I8&""=AO8&"",J8&""=AP8&"",K8&""=AQ8&"",L8&""=AR8&"",M8&""=AS8&""),"","changed") | Y8: =IF(OR(E8="",N(K8)=0),"",WORKDAY(E8,-IF(H8="founding",Inputs!$C$49,Inputs!$C$51),Lists!$N$4:$N$30)) -> 46413 | Z8: =IF(Y8="","",N(K8)-N(L8)) -> 3 | AA8: =IF(Z8="","",Z8/Inputs!$C$90) -> 15 | AB8: =IF(Y8="","",SUMIFS($Z$7:$Z$18,$Y$7:$Y$18,"<="&Y8)) -> 5 | AC8: =IF(AB8="","",AB8/Inputs!$C$90) -> 25 | AD8: =IF(Y8="","",SUMIFS(Pipeline!$T$5:$T$1004,Pipeline!$B$5:$B$1004,"brand",Pipeline!$E$5:$E$1004,"paid",Pipeline!$A$5:$A$1004,"<="&Y8)) -> 2 | AE8: =IF(Y8="","",SUMIFS(Pipeline!$T$5:$T$1004,Pipeline!$B$5:$B$1004,"brand",Pipeline!$E$5:$E$1004,"conversation",Pipeline!$A$5:$A$1004,"<="&Y8)) -> 0 | AF8: =IF(Y8="","",WORKDAY(E8,Inputs!$C$24,Lists!$N$4:$N$30)) -> 46442 | AG8: =IF(AF8="","",IF(AND(E8>Inputs!$C$14,E8<=Inputs!$C$15,AF8>Inputs!$C$15),"after the decision","ok")) -> ok | AH8: =IF(AG8="after the decision",AF8,"") | AI8: =IF(U8="","",MIN(N(I8)-N(J8),MAX(0,U8-V8))) -> 0 | AJ8: =IF(AND(H8="standard",N(K8)>0,E8<>""),E8,"") -> 46427 | AL8: 46427 | AM8: courier | AN8: standard | AO8: =Inputs!$C$61 -> 10 | AP8: =IF(N(K8)=0,0,MAX(0,I8-SUM(J$7:J7))) -> 5 | AQ8: =Inputs!$C$62 -> 3 | AR8: 0 | AS8: 0
A9: DRP-003 | B9: Standard run 2 | C9: derived: CONTRACTS s3 | E9: 46441 | F9: =IF(E9="","",TEXT(E9,"ddd")) -> Tue | G9: courier | H9: standard | I9: =Inputs!$C$61 -> 10 | J9: =IF(N(K9)=0,0,MAX(0,MIN(I9,Inputs!$C$145-SUM(J$7:J8)))) -> 2 | K9: =Inputs!$C$62 -> 3 | L9: 0 | M9: 0 | N9: N | O9: New offices reach the six-month goal of 12 active offices (two). Two weeks after run 1, so most offices get two drops in February. No founding renewal by default (README assumption 18). | P9: =IF(E9="","",IF(OR(WEEKDAY(E9)=Lists!$V$4,WEEKDAY(E9)=Lists!$V$5),"ok","not Tue/Wed")) -> ok | Q9: =IF(E9="","",WORKDAY(E9,Inputs!$C$23-1,Lists!$N$4:$N$30)) -> 46447 | R9: =IF(E9="","",IF(COUNTIFS(Lists!$Q$4:$Q$12,"<="&Q9,Lists!$R$4:$R$12,">="&E9)>0,"clash","ok")) -> ok | S9: =IF(E9="","",N(K9)*N(I9)*Inputs!$C$63*(1+Inputs!$C$64)) -> 1650 | T9: =IF(E9="",IF(N(K9)>0,"date missing",""),IF(AND(P9="ok",R9="ok",N(J9)<=N(I9),N(L9)<=N(K9),N(M9)<=N(L9),OR(N(K9)=0,N(I9)>0),G9<>"",H9<>""),"ok","check")) -> ok | U9: =IF(OR(E9="",N(K9)=0),"",SUMIFS($I$7:$I$18,$E$7:$E$18,">"&E9-Inputs!$C$31,$E$7:$E$18,"<="&E9,$K$7:$K$18,">0")) -> 20 | V9: =IF(E9="","",SUMIFS($J$7:$J$18,$E$7:$E$18,"<="&E9)) -> 12 | W9: =IF(U9="","",IF(U9>V9,"some offices get a second drop within four weeks","ok")) -> some offices get a second drop within four weeks | X9: =IF(AND(E9&""=AL9&"",G9&""=AM9&"",H9&""=AN9&"",I9&""=AO9&"",J9&""=AP9&"",K9&""=AQ9&"",L9&""=AR9&"",M9&""=AS9&""),"","changed") | Y9: =IF(OR(E9="",N(K9)=0),"",WORKDAY(E9,-IF(H9="founding",Inputs!$C$49,Inputs!$C$51),Lists!$N$4:$N$30)) -> 46426 | Z9: =IF(Y9="","",N(K9)-N(L9)) -> 3 | AA9: =IF(Z9="","",Z9/Inputs!$C$90) -> 15 | AB9: =IF(Y9="","",SUMIFS($Z$7:$Z$18,$Y$7:$Y$18,"<="&Y9)) -> 8 | AC9: =IF(AB9="","",AB9/Inputs!$C$90) -> 40 | AD9: =IF(Y9="","",SUMIFS(Pipeline!$T$5:$T$1004,Pipeline!$B$5:$B$1004,"brand",Pipeline!$E$5:$E$1004,"paid",Pipeline!$A$5:$A$1004,"<="&Y9)) -> 2 | AE9: =IF(Y9="","",SUMIFS(Pipeline!$T$5:$T$1004,Pipeline!$B$5:$B$1004,"brand",Pipeline!$E$5:$E$1004,"conversation",Pipeline!$A$5:$A$1004,"<="&Y9)) -> 0 | AF9: =IF(Y9="","",WORKDAY(E9,Inputs!$C$24,Lists!$N$4:$N$30)) -> 46455 | AG9: =IF(AF9="","",IF(AND(E9>Inputs!$C$14,E9<=Inputs!$C$15,AF9>Inputs!$C$15),"after the decision","ok")) -> ok | AH9: =IF(AG9="after the decision",AF9,"") | AI9: =IF(U9="","",MIN(N(I9)-N(J9),MAX(0,U9-V9))) -> 8 | AJ9: =IF(AND(H9="standard",N(K9)>0,E9<>""),E9,"") -> 46441 | AL9: 46441 | AM9: courier | AN9: standard | AO9: =Inputs!$C$61 -> 10 | AP9: =IF(N(K9)=0,0,MAX(0,MIN(I9,Inputs!$C$145-SUM(J$7:J8)))) -> 2 | AQ9: =Inputs!$C$62 -> 3 | AR9: 0 | AS9: 0
A10: DRP-004 | B10: Decision window drop 1 | C10: derived: scenario | D10: 1 | E10: 46469 | F10: =IF(E10="","",TEXT(E10,"ddd")) -> Tue | G10: direct-ship | H10: standard | I10: =Inputs!$C$61 -> 10 | J10: =IF(K10>0,N(Scenarios!$H$13),0) -> 0 | K10: =IF(D10<=Scenarios!$H$10,Scenarios!$H$11,0) -> 3 | L10: =ROUND(Scenarios!$H$12*K10,0) -> 1 | M10: 0 | N10: N | O10: Campaign three onward: brands ship direct (plan). Brands, renewals and new offices follow the scenario in force. Not in the plan's roadmap table; derived from the decision rule's 'two extra drops'. | P10: =IF(E10="","",IF(OR(WEEKDAY(E10)=Lists!$V$4,WEEKDAY(E10)=Lists!$V$5),"ok","not Tue/Wed")) -> ok | Q10: =IF(E10="","",WORKDAY(E10,Inputs!$C$23-1,Lists!$N$4:$N$30)) -> 46475 | R10: =IF(E10="","",IF(COUNTIFS(Lists!$Q$4:$Q$12,"<="&Q10,Lists!$R$4:$R$12,">="&E10)>0,"clash","ok")) -> ok | S10: =IF(E10="","",N(K10)*N(I10)*Inputs!$C$63*(1+Inputs!$C$64)) -> 1650 | T10: =IF(E10="",IF(N(K10)>0,"date missing",""),IF(AND(P10="ok",R10="ok",N(J10)<=N(I10),N(L10)<=N(K10),N(M10)<=N(L10),OR(N(K10)=0,N(I10)>0),G10<>"",H10<>""),"ok","check")) -> ok | U10: =IF(OR(E10="",N(K10)=0),"",SUMIFS($I$7:$I$18,$E$7:$E$18,">"&E10-Inputs!$C$31,$E$7:$E$18,"<="&E10,$K$7:$K$18,">0")) -> 10 | V10: =IF(E10="","",SUMIFS($J$7:$J$18,$E$7:$E$18,"<="&E10)) -> 12 | W10: =IF(U10="","",IF(U10>V10,"some offices get a second drop within four weeks","ok")) -> ok | X10: =IF(AND(E10&""=AL10&"",G10&""=AM10&"",H10&""=AN10&"",I10&""=AO10&"",J10&""=AP10&"",K10&""=AQ10&"",L10&""=AR10&"",M10&""=AS10&""),"","changed") | Y10: =IF(OR(E10="",N(K10)=0),"",WORKDAY(E10,-IF(H10="founding",Inputs!$C$49,Inputs!$C$51),Lists!$N$4:$N$30)) -> 46455 | Z10: =IF(Y10="","",N(K10)-N(L10)) -> 2 | AA10: =IF(Z10="","",Z10/Inputs!$C$90) -> 10 | AB10: =IF(Y10="","",SUMIFS($Z$7:$Z$18,$Y$7:$Y$18,"<="&Y10)) -> 10 | AC10: =IF(AB10="","",AB10/Inputs!$C$90) -> 50 | AD10: =IF(Y10="","",SUMIFS(Pipeline!$T$5:$T$1004,Pipeline!$B$5:$B$1004,"brand",Pipeline!$E$5:$E$1004,"paid",Pipeline!$A$5:$A$1004,"<="&Y10)) -> 2 | AE10: =IF(Y10="","",SUMIFS(Pipeline!$T$5:$T$1004,Pipeline!$B$5:$B$1004,"brand",Pipeline!$E$5:$E$1004,"conversation",Pipeline!$A$5:$A$1004,"<="&Y10)) -> 0 | AF10: =IF(Y10="","",WORKDAY(E10,Inputs!$C$24,Lists!$N$4:$N$30)) -> 46483 | AG10: =IF(AF10="","",IF(AND(E10>Inputs!$C$14,E10<=Inputs!$C$15,AF10>Inputs!$C$15),"after the decision","ok")) -> ok | AH10: =IF(AG10="after the decision",AF10,"") | AI10: =IF(U10="","",MIN(N(I10)-N(J10),MAX(0,U10-V10))) -> 0 | AJ10: =IF(AND(H10="standard",N(K10)>0,E10<>""),E10,"") -> 46469 | AL10: 46469 | AM10: direct-ship | AN10: standard | AO10: =Inputs!$C$61 -> 10 | AP10: =IF(K10>0,N(Scenarios!$H$13),0) -> 0 | AQ10: =IF(D10<=Scenarios!$H$10,Scenarios!$H$11,0) -> 3 | AR10: =ROUND(Scenarios!$H$12*K10,0) -> 1 | AS10: 0
A11: DRP-005 | B11: Decision window drop 2 | C11: derived: scenario | D11: 2 | E11: 46483 | F11: =IF(E11="","",TEXT(E11,"ddd")) -> Tue | G11: direct-ship | H11: standard | I11: =Inputs!$C$61 -> 10 | J11: =IF(K11>0,N(Scenarios!$H$13),0) -> 0 | K11: =IF(D11<=Scenarios!$H$10,Scenarios!$H$11,0) -> 3 | L11: =ROUND(Scenarios!$H$12*K11,0) -> 1 | M11: 0 | N11: N | O11: Second extra drop (scenario B's 'two more drops'; two drops a month in the base). Its debrief (T+10) lands after the 2027-04-09 decision: see REPORT.md, question 1. | P11: =IF(E11="","",IF(OR(WEEKDAY(E11)=Lists!$V$4,WEEKDAY(E11)=Lists!$V$5),"ok","not Tue/Wed")) -> ok | Q11: =IF(E11="","",WORKDAY(E11,Inputs!$C$23-1,Lists!$N$4:$N$30)) -> 46489 | R11: =IF(E11="","",IF(COUNTIFS(Lists!$Q$4:$Q$12,"<="&Q11,Lists!$R$4:$R$12,">="&E11)>0,"clash","ok")) -> ok | S11: =IF(E11="","",N(K11)*N(I11)*Inputs!$C$63*(1+Inputs!$C$64)) -> 1650 | T11: =IF(E11="",IF(N(K11)>0,"date missing",""),IF(AND(P11="ok",R11="ok",N(J11)<=N(I11),N(L11)<=N(K11),N(M11)<=N(L11),OR(N(K11)=0,N(I11)>0),G11<>"",H11<>""),"ok","check")) -> ok | U11: =IF(OR(E11="",N(K11)=0),"",SUMIFS($I$7:$I$18,$E$7:$E$18,">"&E11-Inputs!$C$31,$E$7:$E$18,"<="&E11,$K$7:$K$18,">0")) -> 20 | V11: =IF(E11="","",SUMIFS($J$7:$J$18,$E$7:$E$18,"<="&E11)) -> 12 | W11: =IF(U11="","",IF(U11>V11,"some offices get a second drop within four weeks","ok")) -> some offices get a second drop within four weeks | X11: =IF(AND(E11&""=AL11&"",G11&""=AM11&"",H11&""=AN11&"",I11&""=AO11&"",J11&""=AP11&"",K11&""=AQ11&"",L11&""=AR11&"",M11&""=AS11&""),"","changed") | Y11: =IF(OR(E11="",N(K11)=0),"",WORKDAY(E11,-IF(H11="founding",Inputs!$C$49,Inputs!$C$51),Lists!$N$4:$N$30)) -> 46469 | Z11: =IF(Y11="","",N(K11)-N(L11)) -> 2 | AA11: =IF(Z11="","",Z11/Inputs!$C$90) -> 10 | AB11: =IF(Y11="","",SUMIFS($Z$7:$Z$18,$Y$7:$Y$18,"<="&Y11)) -> 12 | AC11: =IF(AB11="","",AB11/Inputs!$C$90) -> 60 | AD11: =IF(Y11="","",SUMIFS(Pipeline!$T$5:$T$1004,Pipeline!$B$5:$B$1004,"brand",Pipeline!$E$5:$E$1004,"paid",Pipeline!$A$5:$A$1004,"<="&Y11)) -> 2 | AE11: =IF(Y11="","",SUMIFS(Pipeline!$T$5:$T$1004,Pipeline!$B$5:$B$1004,"brand",Pipeline!$E$5:$E$1004,"conversation",Pipeline!$A$5:$A$1004,"<="&Y11)) -> 0 | AF11: =IF(Y11="","",WORKDAY(E11,Inputs!$C$24,Lists!$N$4:$N$30)) -> 46497 | AG11: =IF(AF11="","",IF(AND(E11>Inputs!$C$14,E11<=Inputs!$C$15,AF11>Inputs!$C$15),"after the decision","ok")) -> after the decision | AH11: =IF(AG11="after the decision",AF11,"") -> 46497 | AI11: =IF(U11="","",MIN(N(I11)-N(J11),MAX(0,U11-V11))) -> 8 | AJ11: =IF(AND(H11="standard",N(K11)>0,E11<>""),E11,"") -> 46483 | AL11: 46483 | AM11: direct-ship | AN11: standard | AO11: =Inputs!$C$61 -> 10 | AP11: =IF(K11>0,N(Scenarios!$H$13),0) -> 0 | AQ11: =IF(D11<=Scenarios!$H$10,Scenarios!$H$11,0) -> 3 | AR11: =ROUND(Scenarios!$H$12*K11,0) -> 1 | AS11: 0
A12: DRP-006 | C12: founder entry | F12: =IF(E12="","",TEXT(E12,"ddd")) | N12: N | P12: =IF(E12="","",IF(OR(WEEKDAY(E12)=Lists!$V$4,WEEKDAY(E12)=Lists!$V$5),"ok","not Tue/Wed")) | Q12: =IF(E12="","",WORKDAY(E12,Inputs!$C$23-1,Lists!$N$4:$N$30)) | R12: =IF(E12="","",IF(COUNTIFS(Lists!$Q$4:$Q$12,"<="&Q12,Lists!$R$4:$R$12,">="&E12)>0,"clash","ok")) | S12: =IF(E12="","",N(K12)*N(I12)*Inputs!$C$63*(1+Inputs!$C$64)) | T12: =IF(E12="",IF(N(K12)>0,"date missing",""),IF(AND(P12="ok",R12="ok",N(J12)<=N(I12),N(L12)<=N(K12),N(M12)<=N(L12),OR(N(K12)=0,N(I12)>0),G12<>"",H12<>""),"ok","check")) | U12: =IF(OR(E12="",N(K12)=0),"",SUMIFS($I$7:$I$18,$E$7:$E$18,">"&E12-Inputs!$C$31,$E$7:$E$18,"<="&E12,$K$7:$K$18,">0")) | V12: =IF(E12="","",SUMIFS($J$7:$J$18,$E$7:$E$18,"<="&E12)) | W12: =IF(U12="","",IF(U12>V12,"some offices get a second drop within four weeks","ok")) | X12: =IF(AND(E12&""=AL12&"",G12&""=AM12&"",H12&""=AN12&"",I12&""=AO12&"",J12&""=AP12&"",K12&""=AQ12&"",L12&""=AR12&"",M12&""=AS12&""),"","changed") | Y12: =IF(OR(E12="",N(K12)=0),"",WORKDAY(E12,-IF(H12="founding",Inputs!$C$49,Inputs!$C$51),Lists!$N$4:$N$30)) | Z12: =IF(Y12="","",N(K12)-N(L12)) | AA12: =IF(Z12="","",Z12/Inputs!$C$90) | AB12: =IF(Y12="","",SUMIFS($Z$7:$Z$18,$Y$7:$Y$18,"<="&Y12)) | AC12: =IF(AB12="","",AB12/Inputs!$C$90) | AD12: =IF(Y12="","",SUMIFS(Pipeline!$T$5:$T$1004,Pipeline!$B$5:$B$1004,"brand",Pipeline!$E$5:$E$1004,"paid",Pipeline!$A$5:$A$1004,"<="&Y12)) | AE12: =IF(Y12="","",SUMIFS(Pipeline!$T$5:$T$1004,Pipeline!$B$5:$B$1004,"brand",Pipeline!$E$5:$E$1004,"conversation",Pipeline!$A$5:$A$1004,"<="&Y12)) | AF12: =IF(Y12="","",WORKDAY(E12,Inputs!$C$24,Lists!$N$4:$N$30)) | AG12: =IF(AF12="","",IF(AND(E12>Inputs!$C$14,E12<=Inputs!$C$15,AF12>Inputs!$C$15),"after the decision","ok")) | AH12: =IF(AG12="after the decision",AF12,"") | AI12: =IF(U12="","",MIN(N(I12)-N(J12),MAX(0,U12-V12))) | AJ12: =IF(AND(H12="standard",N(K12)>0,E12<>""),E12,"")
A13: DRP-007 | C13: founder entry | F13: =IF(E13="","",TEXT(E13,"ddd")) | N13: N | P13: =IF(E13="","",IF(OR(WEEKDAY(E13)=Lists!$V$4,WEEKDAY(E13)=Lists!$V$5),"ok","not Tue/Wed")) | Q13: =IF(E13="","",WORKDAY(E13,Inputs!$C$23-1,Lists!$N$4:$N$30)) | R13: =IF(E13="","",IF(COUNTIFS(Lists!$Q$4:$Q$12,"<="&Q13,Lists!$R$4:$R$12,">="&E13)>0,"clash","ok")) | S13: =IF(E13="","",N(K13)*N(I13)*Inputs!$C$63*(1+Inputs!$C$64)) | T13: =IF(E13="",IF(N(K13)>0,"date missing",""),IF(AND(P13="ok",R13="ok",N(J13)<=N(I13),N(L13)<=N(K13),N(M13)<=N(L13),OR(N(K13)=0,N(I13)>0),G13<>"",H13<>""),"ok","check")) | U13: =IF(OR(E13="",N(K13)=0),"",SUMIFS($I$7:$I$18,$E$7:$E$18,">"&E13-Inputs!$C$31,$E$7:$E$18,"<="&E13,$K$7:$K$18,">0")) | V13: =IF(E13="","",SUMIFS($J$7:$J$18,$E$7:$E$18,"<="&E13)) | W13: =IF(U13="","",IF(U13>V13,"some offices get a second drop within four weeks","ok")) | X13: =IF(AND(E13&""=AL13&"",G13&""=AM13&"",H13&""=AN13&"",I13&""=AO13&"",J13&""=AP13&"",K13&""=AQ13&"",L13&""=AR13&"",M13&""=AS13&""),"","changed") | Y13: =IF(OR(E13="",N(K13)=0),"",WORKDAY(E13,-IF(H13="founding",Inputs!$C$49,Inputs!$C$51),Lists!$N$4:$N$30)) | Z13: =IF(Y13="","",N(K13)-N(L13)) | AA13: =IF(Z13="","",Z13/Inputs!$C$90) | AB13: =IF(Y13="","",SUMIFS($Z$7:$Z$18,$Y$7:$Y$18,"<="&Y13)) | AC13: =IF(AB13="","",AB13/Inputs!$C$90) | AD13: =IF(Y13="","",SUMIFS(Pipeline!$T$5:$T$1004,Pipeline!$B$5:$B$1004,"brand",Pipeline!$E$5:$E$1004,"paid",Pipeline!$A$5:$A$1004,"<="&Y13)) | AE13: =IF(Y13="","",SUMIFS(Pipeline!$T$5:$T$1004,Pipeline!$B$5:$B$1004,"brand",Pipeline!$E$5:$E$1004,"conversation",Pipeline!$A$5:$A$1004,"<="&Y13)) | AF13: =IF(Y13="","",WORKDAY(E13,Inputs!$C$24,Lists!$N$4:$N$30)) | AG13: =IF(AF13="","",IF(AND(E13>Inputs!$C$14,E13<=Inputs!$C$15,AF13>Inputs!$C$15),"after the decision","ok")) | AH13: =IF(AG13="after the decision",AF13,"") | AI13: =IF(U13="","",MIN(N(I13)-N(J13),MAX(0,U13-V13))) | AJ13: =IF(AND(H13="standard",N(K13)>0,E13<>""),E13,"")
A14: DRP-008 | C14: founder entry | F14: =IF(E14="","",TEXT(E14,"ddd")) | N14: N | P14: =IF(E14="","",IF(OR(WEEKDAY(E14)=Lists!$V$4,WEEKDAY(E14)=Lists!$V$5),"ok","not Tue/Wed")) | Q14: =IF(E14="","",WORKDAY(E14,Inputs!$C$23-1,Lists!$N$4:$N$30)) | R14: =IF(E14="","",IF(COUNTIFS(Lists!$Q$4:$Q$12,"<="&Q14,Lists!$R$4:$R$12,">="&E14)>0,"clash","ok")) | S14: =IF(E14="","",N(K14)*N(I14)*Inputs!$C$63*(1+Inputs!$C$64)) | T14: =IF(E14="",IF(N(K14)>0,"date missing",""),IF(AND(P14="ok",R14="ok",N(J14)<=N(I14),N(L14)<=N(K14),N(M14)<=N(L14),OR(N(K14)=0,N(I14)>0),G14<>"",H14<>""),"ok","check")) | U14: =IF(OR(E14="",N(K14)=0),"",SUMIFS($I$7:$I$18,$E$7:$E$18,">"&E14-Inputs!$C$31,$E$7:$E$18,"<="&E14,$K$7:$K$18,">0")) | V14: =IF(E14="","",SUMIFS($J$7:$J$18,$E$7:$E$18,"<="&E14)) | W14: =IF(U14="","",IF(U14>V14,"some offices get a second drop within four weeks","ok")) | X14: =IF(AND(E14&""=AL14&"",G14&""=AM14&"",H14&""=AN14&"",I14&""=AO14&"",J14&""=AP14&"",K14&""=AQ14&"",L14&""=AR14&"",M14&""=AS14&""),"","changed") | Y14: =IF(OR(E14="",N(K14)=0),"",WORKDAY(E14,-IF(H14="founding",Inputs!$C$49,Inputs!$C$51),Lists!$N$4:$N$30)) | Z14: =IF(Y14="","",N(K14)-N(L14)) | AA14: =IF(Z14="","",Z14/Inputs!$C$90) | AB14: =IF(Y14="","",SUMIFS($Z$7:$Z$18,$Y$7:$Y$18,"<="&Y14)) | AC14: =IF(AB14="","",AB14/Inputs!$C$90) | AD14: =IF(Y14="","",SUMIFS(Pipeline!$T$5:$T$1004,Pipeline!$B$5:$B$1004,"brand",Pipeline!$E$5:$E$1004,"paid",Pipeline!$A$5:$A$1004,"<="&Y14)) | AE14: =IF(Y14="","",SUMIFS(Pipeline!$T$5:$T$1004,Pipeline!$B$5:$B$1004,"brand",Pipeline!$E$5:$E$1004,"conversation",Pipeline!$A$5:$A$1004,"<="&Y14)) | AF14: =IF(Y14="","",WORKDAY(E14,Inputs!$C$24,Lists!$N$4:$N$30)) | AG14: =IF(AF14="","",IF(AND(E14>Inputs!$C$14,E14<=Inputs!$C$15,AF14>Inputs!$C$15),"after the decision","ok")) | AH14: =IF(AG14="after the decision",AF14,"") | AI14: =IF(U14="","",MIN(N(I14)-N(J14),MAX(0,U14-V14))) | AJ14: =IF(AND(H14="standard",N(K14)>0,E14<>""),E14,"")
A15: DRP-009 | C15: founder entry | F15: =IF(E15="","",TEXT(E15,"ddd")) | N15: N | P15: =IF(E15="","",IF(OR(WEEKDAY(E15)=Lists!$V$4,WEEKDAY(E15)=Lists!$V$5),"ok","not Tue/Wed")) | Q15: =IF(E15="","",WORKDAY(E15,Inputs!$C$23-1,Lists!$N$4:$N$30)) | R15: =IF(E15="","",IF(COUNTIFS(Lists!$Q$4:$Q$12,"<="&Q15,Lists!$R$4:$R$12,">="&E15)>0,"clash","ok")) | S15: =IF(E15="","",N(K15)*N(I15)*Inputs!$C$63*(1+Inputs!$C$64)) | T15: =IF(E15="",IF(N(K15)>0,"date missing",""),IF(AND(P15="ok",R15="ok",N(J15)<=N(I15),N(L15)<=N(K15),N(M15)<=N(L15),OR(N(K15)=0,N(I15)>0),G15<>"",H15<>""),"ok","check")) | U15: =IF(OR(E15="",N(K15)=0),"",SUMIFS($I$7:$I$18,$E$7:$E$18,">"&E15-Inputs!$C$31,$E$7:$E$18,"<="&E15,$K$7:$K$18,">0")) | V15: =IF(E15="","",SUMIFS($J$7:$J$18,$E$7:$E$18,"<="&E15)) | W15: =IF(U15="","",IF(U15>V15,"some offices get a second drop within four weeks","ok")) | X15: =IF(AND(E15&""=AL15&"",G15&""=AM15&"",H15&""=AN15&"",I15&""=AO15&"",J15&""=AP15&"",K15&""=AQ15&"",L15&""=AR15&"",M15&""=AS15&""),"","changed") | Y15: =IF(OR(E15="",N(K15)=0),"",WORKDAY(E15,-IF(H15="founding",Inputs!$C$49,Inputs!$C$51),Lists!$N$4:$N$30)) | Z15: =IF(Y15="","",N(K15)-N(L15)) | AA15: =IF(Z15="","",Z15/Inputs!$C$90) | AB15: =IF(Y15="","",SUMIFS($Z$7:$Z$18,$Y$7:$Y$18,"<="&Y15)) | AC15: =IF(AB15="","",AB15/Inputs!$C$90) | AD15: =IF(Y15="","",SUMIFS(Pipeline!$T$5:$T$1004,Pipeline!$B$5:$B$1004,"brand",Pipeline!$E$5:$E$1004,"paid",Pipeline!$A$5:$A$1004,"<="&Y15)) | AE15: =IF(Y15="","",SUMIFS(Pipeline!$T$5:$T$1004,Pipeline!$B$5:$B$1004,"brand",Pipeline!$E$5:$E$1004,"conversation",Pipeline!$A$5:$A$1004,"<="&Y15)) | AF15: =IF(Y15="","",WORKDAY(E15,Inputs!$C$24,Lists!$N$4:$N$30)) | AG15: =IF(AF15="","",IF(AND(E15>Inputs!$C$14,E15<=Inputs!$C$15,AF15>Inputs!$C$15),"after the decision","ok")) | AH15: =IF(AG15="after the decision",AF15,"") | AI15: =IF(U15="","",MIN(N(I15)-N(J15),MAX(0,U15-V15))) | AJ15: =IF(AND(H15="standard",N(K15)>0,E15<>""),E15,"")
A16: DRP-010 | C16: founder entry | F16: =IF(E16="","",TEXT(E16,"ddd")) | N16: N | P16: =IF(E16="","",IF(OR(WEEKDAY(E16)=Lists!$V$4,WEEKDAY(E16)=Lists!$V$5),"ok","not Tue/Wed")) | Q16: =IF(E16="","",WORKDAY(E16,Inputs!$C$23-1,Lists!$N$4:$N$30)) | R16: =IF(E16="","",IF(COUNTIFS(Lists!$Q$4:$Q$12,"<="&Q16,Lists!$R$4:$R$12,">="&E16)>0,"clash","ok")) | S16: =IF(E16="","",N(K16)*N(I16)*Inputs!$C$63*(1+Inputs!$C$64)) | T16: =IF(E16="",IF(N(K16)>0,"date missing",""),IF(AND(P16="ok",R16="ok",N(J16)<=N(I16),N(L16)<=N(K16),N(M16)<=N(L16),OR(N(K16)=0,N(I16)>0),G16<>"",H16<>""),"ok","check")) | U16: =IF(OR(E16="",N(K16)=0),"",SUMIFS($I$7:$I$18,$E$7:$E$18,">"&E16-Inputs!$C$31,$E$7:$E$18,"<="&E16,$K$7:$K$18,">0")) | V16: =IF(E16="","",SUMIFS($J$7:$J$18,$E$7:$E$18,"<="&E16)) | W16: =IF(U16="","",IF(U16>V16,"some offices get a second drop within four weeks","ok")) | X16: =IF(AND(E16&""=AL16&"",G16&""=AM16&"",H16&""=AN16&"",I16&""=AO16&"",J16&""=AP16&"",K16&""=AQ16&"",L16&""=AR16&"",M16&""=AS16&""),"","changed") | Y16: =IF(OR(E16="",N(K16)=0),"",WORKDAY(E16,-IF(H16="founding",Inputs!$C$49,Inputs!$C$51),Lists!$N$4:$N$30)) | Z16: =IF(Y16="","",N(K16)-N(L16)) | AA16: =IF(Z16="","",Z16/Inputs!$C$90) | AB16: =IF(Y16="","",SUMIFS($Z$7:$Z$18,$Y$7:$Y$18,"<="&Y16)) | AC16: =IF(AB16="","",AB16/Inputs!$C$90) | AD16: =IF(Y16="","",SUMIFS(Pipeline!$T$5:$T$1004,Pipeline!$B$5:$B$1004,"brand",Pipeline!$E$5:$E$1004,"paid",Pipeline!$A$5:$A$1004,"<="&Y16)) | AE16: =IF(Y16="","",SUMIFS(Pipeline!$T$5:$T$1004,Pipeline!$B$5:$B$1004,"brand",Pipeline!$E$5:$E$1004,"conversation",Pipeline!$A$5:$A$1004,"<="&Y16)) | AF16: =IF(Y16="","",WORKDAY(E16,Inputs!$C$24,Lists!$N$4:$N$30)) | AG16: =IF(AF16="","",IF(AND(E16>Inputs!$C$14,E16<=Inputs!$C$15,AF16>Inputs!$C$15),"after the decision","ok")) | AH16: =IF(AG16="after the decision",AF16,"") | AI16: =IF(U16="","",MIN(N(I16)-N(J16),MAX(0,U16-V16))) | AJ16: =IF(AND(H16="standard",N(K16)>0,E16<>""),E16,"")
A17: DRP-011 | C17: founder entry | F17: =IF(E17="","",TEXT(E17,"ddd")) | N17: N | P17: =IF(E17="","",IF(OR(WEEKDAY(E17)=Lists!$V$4,WEEKDAY(E17)=Lists!$V$5),"ok","not Tue/Wed")) | Q17: =IF(E17="","",WORKDAY(E17,Inputs!$C$23-1,Lists!$N$4:$N$30)) | R17: =IF(E17="","",IF(COUNTIFS(Lists!$Q$4:$Q$12,"<="&Q17,Lists!$R$4:$R$12,">="&E17)>0,"clash","ok")) | S17: =IF(E17="","",N(K17)*N(I17)*Inputs!$C$63*(1+Inputs!$C$64)) | T17: =IF(E17="",IF(N(K17)>0,"date missing",""),IF(AND(P17="ok",R17="ok",N(J17)<=N(I17),N(L17)<=N(K17),N(M17)<=N(L17),OR(N(K17)=0,N(I17)>0),G17<>"",H17<>""),"ok","check")) | U17: =IF(OR(E17="",N(K17)=0),"",SUMIFS($I$7:$I$18,$E$7:$E$18,">"&E17-Inputs!$C$31,$E$7:$E$18,"<="&E17,$K$7:$K$18,">0")) | V17: =IF(E17="","",SUMIFS($J$7:$J$18,$E$7:$E$18,"<="&E17)) | W17: =IF(U17="","",IF(U17>V17,"some offices get a second drop within four weeks","ok")) | X17: =IF(AND(E17&""=AL17&"",G17&""=AM17&"",H17&""=AN17&"",I17&""=AO17&"",J17&""=AP17&"",K17&""=AQ17&"",L17&""=AR17&"",M17&""=AS17&""),"","changed") | Y17: =IF(OR(E17="",N(K17)=0),"",WORKDAY(E17,-IF(H17="founding",Inputs!$C$49,Inputs!$C$51),Lists!$N$4:$N$30)) | Z17: =IF(Y17="","",N(K17)-N(L17)) | AA17: =IF(Z17="","",Z17/Inputs!$C$90) | AB17: =IF(Y17="","",SUMIFS($Z$7:$Z$18,$Y$7:$Y$18,"<="&Y17)) | AC17: =IF(AB17="","",AB17/Inputs!$C$90) | AD17: =IF(Y17="","",SUMIFS(Pipeline!$T$5:$T$1004,Pipeline!$B$5:$B$1004,"brand",Pipeline!$E$5:$E$1004,"paid",Pipeline!$A$5:$A$1004,"<="&Y17)) | AE17: =IF(Y17="","",SUMIFS(Pipeline!$T$5:$T$1004,Pipeline!$B$5:$B$1004,"brand",Pipeline!$E$5:$E$1004,"conversation",Pipeline!$A$5:$A$1004,"<="&Y17)) | AF17: =IF(Y17="","",WORKDAY(E17,Inputs!$C$24,Lists!$N$4:$N$30)) | AG17: =IF(AF17="","",IF(AND(E17>Inputs!$C$14,E17<=Inputs!$C$15,AF17>Inputs!$C$15),"after the decision","ok")) | AH17: =IF(AG17="after the decision",AF17,"") | AI17: =IF(U17="","",MIN(N(I17)-N(J17),MAX(0,U17-V17))) | AJ17: =IF(AND(H17="standard",N(K17)>0,E17<>""),E17,"")
A18: DRP-012 | C18: founder entry | F18: =IF(E18="","",TEXT(E18,"ddd")) | N18: N | P18: =IF(E18="","",IF(OR(WEEKDAY(E18)=Lists!$V$4,WEEKDAY(E18)=Lists!$V$5),"ok","not Tue/Wed")) | Q18: =IF(E18="","",WORKDAY(E18,Inputs!$C$23-1,Lists!$N$4:$N$30)) | R18: =IF(E18="","",IF(COUNTIFS(Lists!$Q$4:$Q$12,"<="&Q18,Lists!$R$4:$R$12,">="&E18)>0,"clash","ok")) | S18: =IF(E18="","",N(K18)*N(I18)*Inputs!$C$63*(1+Inputs!$C$64)) | T18: =IF(E18="",IF(N(K18)>0,"date missing",""),IF(AND(P18="ok",R18="ok",N(J18)<=N(I18),N(L18)<=N(K18),N(M18)<=N(L18),OR(N(K18)=0,N(I18)>0),G18<>"",H18<>""),"ok","check")) | U18: =IF(OR(E18="",N(K18)=0),"",SUMIFS($I$7:$I$18,$E$7:$E$18,">"&E18-Inputs!$C$31,$E$7:$E$18,"<="&E18,$K$7:$K$18,">0")) | V18: =IF(E18="","",SUMIFS($J$7:$J$18,$E$7:$E$18,"<="&E18)) | W18: =IF(U18="","",IF(U18>V18,"some offices get a second drop within four weeks","ok")) | X18: =IF(AND(E18&""=AL18&"",G18&""=AM18&"",H18&""=AN18&"",I18&""=AO18&"",J18&""=AP18&"",K18&""=AQ18&"",L18&""=AR18&"",M18&""=AS18&""),"","changed") | Y18: =IF(OR(E18="",N(K18)=0),"",WORKDAY(E18,-IF(H18="founding",Inputs!$C$49,Inputs!$C$51),Lists!$N$4:$N$30)) | Z18: =IF(Y18="","",N(K18)-N(L18)) | AA18: =IF(Z18="","",Z18/Inputs!$C$90) | AB18: =IF(Y18="","",SUMIFS($Z$7:$Z$18,$Y$7:$Y$18,"<="&Y18)) | AC18: =IF(AB18="","",AB18/Inputs!$C$90) | AD18: =IF(Y18="","",SUMIFS(Pipeline!$T$5:$T$1004,Pipeline!$B$5:$B$1004,"brand",Pipeline!$E$5:$E$1004,"paid",Pipeline!$A$5:$A$1004,"<="&Y18)) | AE18: =IF(Y18="","",SUMIFS(Pipeline!$T$5:$T$1004,Pipeline!$B$5:$B$1004,"brand",Pipeline!$E$5:$E$1004,"conversation",Pipeline!$A$5:$A$1004,"<="&Y18)) | AF18: =IF(Y18="","",WORKDAY(E18,Inputs!$C$24,Lists!$N$4:$N$30)) | AG18: =IF(AF18="","",IF(AND(E18>Inputs!$C$14,E18<=Inputs!$C$15,AF18>Inputs!$C$15),"after the decision","ok")) | AH18: =IF(AG18="after the decision",AF18,"") | AI18: =IF(U18="","",MIN(N(I18)-N(J18),MAX(0,U18-V18))) | AJ18: =IF(AND(H18="standard",N(K18)>0,E18<>""),E18,"")
B19: Totals | I19: =SUM(I7:I18) -> 45 | J19: =SUM(J7:J18) -> 12 | K19: =SUM(K7:K18) -> 14 | L19: =SUM(L7:L18) -> 2 | M19: =SUM(M7:M18) -> 0 | S19: =SUM(S7:S18) -> 7150 | Z19: =SUM(Z7:Z18) -> 12 | AA19: =SUM(AA7:AA18) -> 60
B21: Offices column counts every office on the drop; New offices counts the ones visiting for the first time (4 hours each instead of 1). Brands counts brand campaigns on the drop; renewals are part of that count (2 hours each instead of 6 or 10). Tier sets the price of the new brands; founding-rate renewals pay the founding rate per office.
B22: Columns Y to AE: the new brand wins each drop needs and the qualified conversations they imply at the close rate on Inputs, cumulated to each drop's sign-by date, beside the Pipeline's actual distinct brands paid and brand conversations by that date. Columns AF to AH: each drop's debrief date; a drop in the decision window whose debrief lands after the decision date is flagged, because its results cannot count toward the decision rule. Column AI: offices to add so no office gets a second drop within four weeks (the Dashboard shows the Gate 3 rate with them). Column AJ: the date of each standard drop that runs; the storage unit is rented from the first of the month of the earliest one.

Sheet Calculator
A1: Drop calculator
A2: Pick any tier, delivery model, office count and brand count. It runs the same engine as the drops and does not change the model.
A3: Planning estimates, not a forecast. To test a price: type it in 'Standard price per office' below (or on Inputs to move the whole model). Read 'Contribution per founder hour'.
B5: Your drop | E5: Result
B6: Tier | C6: standard | E6: Line | F6: Whole drop | G6: Per brand (equal split of shared costs)
B7: Delivery model | C7: courier | E7: Revenue | F7: =S40 -> 4500 | G7: =IF(G40>0,F7/G40,"") -> 1500
B8: Offices | C8: 10 | E8: Display kits | F8: =T40 -> 80 | G8: =IF(G40>0,F8/G40,"") -> 26.666667
B9: of which new offices | C9: 0 | E9: Transport | F9: =U40 -> 300 | G9: =IF(G40>0,F9/G40,"") -> 100
B10: Brands | C10: 3 | E10: Kit mailing | F10: =V40 -> 0 | G10: =IF(G40>0,F10/G40,"") -> 0
B11: of which renewals | C11: 0 | E11: Card processing | F11: =W40 -> 135 | G11: =IF(G40>0,F11/G40,"") -> 45
B12: of which founding-rate renewals | C12: 0 | E12: Storage allocation | F12: =X40 -> 75 | G12: =IF(G40>0,F12/G40,"") -> 25
B13: Standard price per office (blank = Inputs) | E13: Software allocation | F13: =Y40 -> 30 | G13: =IF(G40>0,F13/G40,"") -> 10
B14: Founding price per office (blank = Inputs) | E14: Insurance allocation | F14: =Z40 -> 50 | G14: =IF(G40>0,F14/G40,"") -> 16.666667
B15: Storage allocated? Y/N (blank = Inputs choice) | E15: Hard costs | F15: =AA40 -> 670 | G15: =IF(G40>0,F15/G40,"") -> 223.33333
B16: Card processing? Y/N (blank = Inputs toggle) | E16: Contribution | F16: =AJ40 -> 3830 | G16: =IF(G40>0,F16/G40,"") -> 1276.6667
E17: brand_sales (h) | F17: =AB40 -> 18 | G17: =IF(G40>0,F17/G40,"") -> 6
E18: office_coordination (h) | F18: =AC40 -> 10 | G18: =IF(G40>0,F18/G40,"") -> 3.3333333
E19: receiving_kitting (h) | F19: =AD40 -> 4 | G19: =IF(G40>0,F19/G40,"") -> 1.3333333
E20: drop_day (h) | F20: =AE40 -> 8 | G20: =IF(G40>0,F20/G40,"") -> 2.6666667
E21: checks_pickup (h) | F21: =AF40 -> 4 | G21: =IF(G40>0,F21/G40,"") -> 1.3333333
E22: reporting_debriefs (h) | F22: =AG40 -> 6 | G22: =IF(G40>0,F22/G40,"") -> 2
E23: admin_invoicing (h) | F23: =AH40 -> 2 | G23: =IF(G40>0,F23/G40,"") -> 0.66666667
E24: Founder hours | F24: =AI40 -> 52 | G24: =IF(G40>0,F24/G40,"") -> 17.333333
E25: Contribution per founder hour | F25: =AK40 -> 73.653846 | G25: =F25 -> 73.653846
E26: Against the Gate 3 target | F26: =IF(ISNUMBER(F25),IF(F25>=Inputs!$C$136,"at or above target","below target"),"n/a") -> at or above target
E27: Units each brand ships (incl. reserve) | F27: =E40*Inputs!$C$63*(1+Inputs!$C$64) -> 550
E29: Per-brand column: revenue and processing are averaged across brands, and shared costs and hours (kits, transport, allocations, office and drop-day time) are split equally. Brand sales and reporting hours are per brand already.
A37: Engine row: the same formulas as every row on Drop_PnL. Read-only; the result table above reads it.
A39: Drop or case | B39: Drop date | C39: Delivery model | D39: Tier | E39: Offices | F39: New offices | G39: Brands | H39: of which renewals | I39: of which founding-rate renewals | J39: Standard price per office | K39: Founding price per office | L39: Storage allocated (1/0) | M39: Card processing (1/0) | N39: Drop runs (1/0) | O39: New founding brands | P39: New standard brands | Q39: Revenue at founding rate | R39: Revenue at standard rate | S39: Revenue | T39: Display kits | U39: Transport | V39: Kit mailing | W39: Card processing | X39: Storage allocation | Y39: Software allocation | Z39: Insurance allocation | AA39: Hard costs | AB39: brand_sales (h) | AC39: office_coordination (h) | AD39: receiving_kitting (h) | AE39: drop_day (h) | AF39: checks_pickup (h) | AG39: reporting_debriefs (h) | AH39: admin_invoicing (h) | AI39: Founder hours | AJ39: Contribution | AK39: Contribution per founder hour | AL39: Direct costs (kits, transport, mailing, processing) | AM39: Overhead allocations (views of monthly costs)
A40: Calculator drop | C40: =$C$7 -> courier | D40: =$C$6 -> standard | E40: =N($C$8) -> 10 | F40: =N($C$9) -> 0 | G40: =N($C$10) -> 3 | H40: =N($C$11) -> 0 | I40: =N($C$12) -> 0 | J40: =IF($C$13="",Inputs!$C$39,$C$13) -> 150 | K40: =IF($C$14="",Inputs!$C$42,$C$14) -> 120 | L40: =IF($C$15="",IF(Inputs!$C$75="unit",1,0),IF($C$15="Y",1,0)) -> 1 | M40: =IF($C$16="",Inputs!$C$55,IF($C$16="Y",1,0)) -> 1 | N40: =IF(G40>0,1,0) -> 1 | O40: =IF(D40="founding",G40-H40,0) -> 0 | P40: =IF(D40="standard",G40-H40,0) -> 3 | Q40: =O40*(K40*MIN(E40,Inputs!$C$43)+Inputs!$C$45*MAX(E40-Inputs!$C$43,0))+I40*K40*E40 -> 0 | R40: =(P40+H40-I40)*(J40*MIN(E40,Inputs!$C$40)+Inputs!$C$45*MAX(E40-Inputs!$C$40,0)) -> 4500 | S40: =Q40+R40 -> 4500 | T40: =N40*E40*(Inputs!$C$68+Inputs!$C$69*MAX(G40-1,0)) -> 80 | U40: =IF(N40=0,0,INDEX(Inputs!$C$105:$C$107,MATCH(C40,Inputs!$B$105:$B$107,0))+INDEX(Inputs!$D$105:$D$107,MATCH(C40,Inputs!$B$105:$B$107,0))*E40) -> 300 | V40: =IF(N40=0,0,INDEX(Inputs!$E$105:$E$107,MATCH(C40,Inputs!$B$105:$B$107,0))*E40) -> 0 | W40: =S40*Inputs!$C$54*M40 -> 135 | X40: =N40*L40*Inputs!$C$76/Inputs!$C$85 -> 75 | Y40: =N40*Inputs!$C$79/Inputs!$C$85 -> 30 | Z40: =N40*Inputs!$C$81/Inputs!$C$85 -> 50 | AA40: =SUM(T40:Z40) -> 670 | AB40: =O40*Inputs!$C$89+P40*Inputs!$C$93+H40*Inputs!$C$94 -> 18 | AC40: =N40*(F40*Inputs!$C$95+(E40-F40)*Inputs!$C$96) -> 10 | AD40: =IF(N40=0,0,INDEX(Inputs!$F$105:$F$107,MATCH(C40,Inputs!$B$105:$B$107,0))+Inputs!$C$97*G40) -> 4 | AE40: =IF(N40=0,0,INDEX(Inputs!$G$105:$G$107,MATCH(C40,Inputs!$B$105:$B$107,0))*E40) -> 8 | AF40: =IF(N40=0,0,INDEX(Inputs!$H$105:$H$107,MATCH(C40,Inputs!$B$105:$B$107,0))*E40) -> 4 | AG40: =Inputs!$C$98*G40 -> 6 | AH40: =N40*Inputs!$C$99 -> 2 | AI40: =SUM(AB40:AH40) -> 52 | AJ40: =S40-AA40 -> 3830 | AK40: =IF(AI40>0,AJ40/AI40,"n/a") -> 73.653846 | AL40: =T40+U40+V40+W40 -> 515 | AM40: =X40+Y40+Z40 -> 155

Sheet Drop_PnL
A1: Per-drop P&L (plan basis) with cash timing
A2: One row per Schedule row. Contribution = revenue minus hard costs, as the plan defines it. Overhead allocations are views; the cash flow pays overhead once.
A3: Planning estimates. The 'Live' columns switch to actuals when Schedule says 'Actuals in = Y'. Shared drop costs are split equally across the drop's brands where a per-brand figure is shown.
A5: Case | E5: Inputs to the engine | N5: Revenue | T5: Hard costs | AB5: Founder hours by activity | AJ5: Result | AL5: Split | AO5: Cash timing on the plan's terms (feeds Cash_Flow) | AZ5: Live: actual where Actuals in = Y, otherwise plan | BH5: Per-drop cash inside the 26 weeks
A6: Drop or case | B6: Drop date | C6: Delivery model | D6: Tier | E6: Offices | F6: New offices | G6: Brands | H6: of which renewals | I6: of which founding-rate renewals | J6: Standard price per office | K6: Founding price per office | L6: Storage allocated (1/0) | M6: Card processing (1/0) | N6: Drop runs (1/0) | O6: New founding brands | P6: New standard brands | Q6: Revenue at founding rate | R6: Revenue at standard rate | S6: Revenue | T6: Display kits | U6: Transport | V6: Kit mailing | W6: Card processing | X6: Storage allocation | Y6: Software allocation | Z6: Insurance allocation | AA6: Hard costs | AB6: brand_sales (h) | AC6: office_coordination (h) | AD6: receiving_kitting (h) | AE6: drop_day (h) | AF6: checks_pickup (h) | AG6: reporting_debriefs (h) | AH6: admin_invoicing (h) | AI6: Founder hours | AJ6: Contribution | AK6: Contribution per founder hour | AL6: Direct costs (kits, transport, mailing, processing) | AM6: Overhead allocations (views of monthly costs) | AO6: Founding payment date | AP6: Founding payment | AQ6: Standard deposit date | AR6: Standard deposit | AS6: Balance date | AT6: Balance | AU6: Processing on founding payment | AV6: Processing on deposit | AW6: Processing on balance | AX6: Kits printed (and mailed) | AY6: Transport paid | AZ6: Actuals in | BA6: Live revenue | BB6: Live hard costs | BC6: Live founder hours | BD6: Live contribution | BE6: Live contribution per founder hour | BF6: Basis | BG6: Upcoming drop (1/0) | BH6: Net cash inside the six months, plan (receipts less direct costs) | BI6: Net cash inside the six months, live | BJ6: Upcoming drop: its date (the Dashboard takes the earliest)
A7: =Schedule!A7 -> DRP-001 | B7: =IF(Schedule!E7="","",Schedule!E7) -> 46399 | C7: =IF(Schedule!G7="","",Schedule!G7) -> founder | D7: =IF(Schedule!H7="","",Schedule!H7) -> founding | E7: =N(Schedule!I7) -> 5 | F7: =N(Schedule!J7) -> 5 | G7: =N(Schedule!K7) -> 2 | H7: =N(Schedule!L7) -> 0 | I7: =N(Schedule!M7) -> 0 | J7: =IF(AND(B7<>"",B7>Inputs!$C$15),Scenarios!$H$14,Inputs!$C$39) -> 150 | K7: =Inputs!$C$42 -> 120 | L7: =IF(AND(Inputs!$C$75="unit",B7<>"",Inputs!$C$77<>"",B7>=Inputs!$C$77,OR(Inputs!$C$78="",B7<=Inputs!$C$78)),1,0) -> 0 | M7: =Inputs!$C$55 -> 1 | N7: =IF(G7>0,1,0) -> 1 | O7: =IF(D7="founding",G7-H7,0) -> 2 | P7: =IF(D7="standard",G7-H7,0) -> 0 | Q7: =O7*(K7*MIN(E7,Inputs!$C$43)+Inputs!$C$45*MAX(E7-Inputs!$C$43,0))+I7*K7*E7 -> 1200 | R7: =(P7+H7-I7)*(J7*MIN(E7,Inputs!$C$40)+Inputs!$C$45*MAX(E7-Inputs!$C$40,0)) -> 0 | S7: =Q7+R7 -> 1200 | T7: =N7*E7*(Inputs!$C$68+Inputs!$C$69*MAX(G7-1,0)) -> 40 | U7: =IF(N7=0,0,INDEX(Inputs!$C$105:$C$107,MATCH(C7,Inputs!$B$105:$B$107,0))+INDEX(Inputs!$D$105:$D$107,MATCH(C7,Inputs!$B$105:$B$107,0))*E7) -> 120 | V7: =IF(N7=0,0,INDEX(Inputs!$E$105:$E$107,MATCH(C7,Inputs!$B$105:$B$107,0))*E7) -> 0 | W7: =S7*Inputs!$C$54*M7 -> 36 | X7: =N7*L7*Inputs!$C$76/Inputs!$C$85 -> 0 | Y7: =N7*Inputs!$C$79/Inputs!$C$85 -> 30 | Z7: =N7*Inputs!$C$81/Inputs!$C$85 -> 50 | AA7: =SUM(T7:Z7) -> 276 | AB7: =O7*Inputs!$C$89+P7*Inputs!$C$93+H7*Inputs!$C$94 -> 20 | AC7: =N7*(F7*Inputs!$C$95+(E7-F7)*Inputs!$C$96) -> 20 | AD7: =IF(N7=0,0,INDEX(Inputs!$F$105:$F$107,MATCH(C7,Inputs!$B$105:$B$107,0))+Inputs!$C$97*G7) -> 3 | AE7: =IF(N7=0,0,INDEX(Inputs!$G$105:$G$107,MATCH(C7,Inputs!$B$105:$B$107,0))*E7) -> 5 | AF7: =IF(N7=0,0,INDEX(Inputs!$H$105:$H$107,MATCH(C7,Inputs!$B$105:$B$107,0))*E7) -> 3 | AG7: =Inputs!$C$98*G7 -> 4 | AH7: =N7*Inputs!$C$99 -> 2 | AI7: =SUM(AB7:AH7) -> 57 | AJ7: =S7-AA7 -> 924 | AK7: =IF(AI7>0,AJ7/AI7,"n/a") -> 16.210526 | AL7: =T7+U7+V7+W7 -> 196 | AM7: =X7+Y7+Z7 -> 80 | AO7: =IF(OR(N7=0,AP7=0),"",WORKDAY(B7,-Inputs!$C$49,Lists!$N$4:$N$30)+N(Inputs!$C$53)) -> 46367 | AP7: =Q7*Inputs!$C$48 -> 1200 | AQ7: =IF(OR(N7=0,AR7=0),"",WORKDAY(B7,-Inputs!$C$51,Lists!$N$4:$N$30)+N(Inputs!$C$53)) | AR7: =R7*Inputs!$C$50 -> 0 | AS7: =IF(OR(N7=0,AT7=0),"",WORKDAY(B7,Inputs!$C$52,Lists!$N$4:$N$30)+N(Inputs!$C$53)) | AT7: =Q7*(1-Inputs!$C$48)+R7*(1-Inputs!$C$50) -> 0 | AU7: =AP7*Inputs!$C$54*M7 -> 36 | AV7: =AR7*Inputs!$C$54*M7 -> 0 | AW7: =AT7*Inputs!$C$54*M7 -> 0 | AX7: =IF(N7=0,"",WORKDAY(B7,-Inputs!$C$74,Lists!$N$4:$N$30)) -> 46394 | AY7: =IF(N7=0,"",B7) -> 46399 | AZ7: =IF(Schedule!N7="Y","Y","N") -> Y | BA7: =IF(AZ7="Y",Drop_Actuals!D7,S7) -> 1080 | BB7: =IF(AZ7="Y",Drop_Actuals!J7,AA7) -> 232 | BC7: =IF(AZ7="Y",Drop_Actuals!R7,AI7) -> 57 | BD7: =BA7-BB7 -> 848 | BE7: =IF(BC7>0,BD7/BC7,"n/a") -> 14.877193 | BF7: =IF(AND(N7=0,AZ7="N"),"",IF(AZ7="Y","actual","plan")) -> actual | BG7: =IF(AND(N7=1,B7>=Inputs!$C$17),1,0) -> 0 | BH7: =IF(AND(AO7<>"",AO7>=Inputs!$C$10,AO7<=Cash_Flow!$AB$6),AP7-AU7,0)+IF(AND(AQ7<>"",AQ7>=Inputs!$C$10,AQ7<=Cash_Flow!$AB$6),AR7-AV7,0)+IF(AND(AS7<>"",AS7>=Inputs!$C$10,AS7<=Cash_Flow!$AB$6),AT7-AW7,0)-IF(AND(AX7<>"",AX7>=Inputs!$C$10,AX7<=Cash_Flow!$AB$6),T7+V7,0)-IF(AND(AY7<>"",AY7>=Inputs!$C$10,AY7<=Cash_Flow!$AB$6),U7,0) -> 1004 | BI7: =IF(AZ7="Y",Drop_Actuals!AM7,BH7) -> 928 | BJ7: =IF(BG7=1,B7,"")
A8: =Schedule!A8 -> DRP-002 | B8: =IF(Schedule!E8="","",Schedule!E8) -> 46427 | C8: =IF(Schedule!G8="","",Schedule!G8) -> courier | D8: =IF(Schedule!H8="","",Schedule!H8) -> standard | E8: =N(Schedule!I8) -> 10 | F8: =N(Schedule!J8) -> 5 | G8: =N(Schedule!K8) -> 3 | H8: =N(Schedule!L8) -> 0 | I8: =N(Schedule!M8) -> 0 | J8: =IF(AND(B8<>"",B8>Inputs!$C$15),Scenarios!$H$14,Inputs!$C$39) -> 150 | K8: =Inputs!$C$42 -> 120 | L8: =IF(AND(Inputs!$C$75="unit",B8<>"",Inputs!$C$77<>"",B8>=Inputs!$C$77,OR(Inputs!$C$78="",B8<=Inputs!$C$78)),1,0) -> 1 | M8: =Inputs!$C$55 -> 1 | N8: =IF(G8>0,1,0) -> 1 | O8: =IF(D8="founding",G8-H8,0) -> 0 | P8: =IF(D8="standard",G8-H8,0) -> 3 | Q8: =O8*(K8*MIN(E8,Inputs!$C$43)+Inputs!$C$45*MAX(E8-Inputs!$C$43,0))+I8*K8*E8 -> 0 | R8: =(P8+H8-I8)*(J8*MIN(E8,Inputs!$C$40)+Inputs!$C$45*MAX(E8-Inputs!$C$40,0)) -> 4500 | S8: =Q8+R8 -> 4500 | T8: =N8*E8*(Inputs!$C$68+Inputs!$C$69*MAX(G8-1,0)) -> 80 | U8: =IF(N8=0,0,INDEX(Inputs!$C$105:$C$107,MATCH(C8,Inputs!$B$105:$B$107,0))+INDEX(Inputs!$D$105:$D$107,MATCH(C8,Inputs!$B$105:$B$107,0))*E8) -> 300 | V8: =IF(N8=0,0,INDEX(Inputs!$E$105:$E$107,MATCH(C8,Inputs!$B$105:$B$107,0))*E8) -> 0 | W8: =S8*Inputs!$C$54*M8 -> 135 | X8: =N8*L8*Inputs!$C$76/Inputs!$C$85 -> 75 | Y8: =N8*Inputs!$C$79/Inputs!$C$85 -> 30 | Z8: =N8*Inputs!$C$81/Inputs!$C$85 -> 50 | AA8: =SUM(T8:Z8) -> 670 | AB8: =O8*Inputs!$C$89+P8*Inputs!$C$93+H8*Inputs!$C$94 -> 18 | AC8: =N8*(F8*Inputs!$C$95+(E8-F8)*Inputs!$C$96) -> 25 | AD8: =IF(N8=0,0,INDEX(Inputs!$F$105:$F$107,MATCH(C8,Inputs!$B$105:$B$107,0))+Inputs!$C$97*G8) -> 4 | AE8: =IF(N8=0,0,INDEX(Inputs!$G$105:$G$107,MATCH(C8,Inputs!$B$105:$B$107,0))*E8) -> 8 | AF8: =IF(N8=0,0,INDEX(Inputs!$H$105:$H$107,MATCH(C8,Inputs!$B$105:$B$107,0))*E8) -> 4 | AG8: =Inputs!$C$98*G8 -> 6 | AH8: =N8*Inputs!$C$99 -> 2 | AI8: =SUM(AB8:AH8) -> 67 | AJ8: =S8-AA8 -> 3830 | AK8: =IF(AI8>0,AJ8/AI8,"n/a") -> 57.164179 | AL8: =T8+U8+V8+W8 -> 515 | AM8: =X8+Y8+Z8 -> 155 | AO8: =IF(OR(N8=0,AP8=0),"",WORKDAY(B8,-Inputs!$C$49,Lists!$N$4:$N$30)+N(Inputs!$C$53)) | AP8: =Q8*Inputs!$C$48 -> 0 | AQ8: =IF(OR(N8=0,AR8=0),"",WORKDAY(B8,-Inputs!$C$51,Lists!$N$4:$N$30)+N(Inputs!$C$53)) -> 46413 | AR8: =R8*Inputs!$C$50 -> 2250 | AS8: =IF(OR(N8=0,AT8=0),"",WORKDAY(B8,Inputs!$C$52,Lists!$N$4:$N$30)+N(Inputs!$C$53)) -> 46428 | AT8: =Q8*(1-Inputs!$C$48)+R8*(1-Inputs!$C$50) -> 2250 | AU8: =AP8*Inputs!$C$54*M8 -> 0 | AV8: =AR8*Inputs!$C$54*M8 -> 67.5 | AW8: =AT8*Inputs!$C$54*M8 -> 67.5 | AX8: =IF(N8=0,"",WORKDAY(B8,-Inputs!$C$74,Lists!$N$4:$N$30)) -> 46422 | AY8: =IF(N8=0,"",B8) -> 46427 | AZ8: =IF(Schedule!N8="Y","Y","N") -> N | BA8: =IF(AZ8="Y",Drop_Actuals!D8,S8) -> 4500 | BB8: =IF(AZ8="Y",Drop_Actuals!J8,AA8) -> 670 | BC8: =IF(AZ8="Y",Drop_Actuals!R8,AI8) -> 67 | BD8: =BA8-BB8 -> 3830 | BE8: =IF(BC8>0,BD8/BC8,"n/a") -> 57.164179 | BF8: =IF(AND(N8=0,AZ8="N"),"",IF(AZ8="Y","actual","plan")) -> plan | BG8: =IF(AND(N8=1,B8>=Inputs!$C$17),1,0) -> 0 | BH8: =IF(AND(AO8<>"",AO8>=Inputs!$C$10,AO8<=Cash_Flow!$AB$6),AP8-AU8,0)+IF(AND(AQ8<>"",AQ8>=Inputs!$C$10,AQ8<=Cash_Flow!$AB$6),AR8-AV8,0)+IF(AND(AS8<>"",AS8>=Inputs!$C$10,AS8<=Cash_Flow!$AB$6),AT8-AW8,0)-IF(AND(AX8<>"",AX8>=Inputs!$C$10,AX8<=Cash_Flow!$AB$6),T8+V8,0)-IF(AND(AY8<>"",AY8>=Inputs!$C$10,AY8<=Cash_Flow!$AB$6),U8,0) -> 3985 | BI8: =IF(AZ8="Y",Drop_Actuals!AM8,BH8) -> 3985 | BJ8: =IF(BG8=1,B8,"")
A9: =Schedule!A9 -> DRP-003 | B9: =IF(Schedule!E9="","",Schedule!E9) -> 46441 | C9: =IF(Schedule!G9="","",Schedule!G9) -> courier | D9: =IF(Schedule!H9="","",Schedule!H9) -> standard | E9: =N(Schedule!I9) -> 10 | F9: =N(Schedule!J9) -> 2 | G9: =N(Schedule!K9) -> 3 | H9: =N(Schedule!L9) -> 0 | I9: =N(Schedule!M9) -> 0 | J9: =IF(AND(B9<>"",B9>Inputs!$C$15),Scenarios!$H$14,Inputs!$C$39) -> 150 | K9: =Inputs!$C$42 -> 120 | L9: =IF(AND(Inputs!$C$75="unit",B9<>"",Inputs!$C$77<>"",B9>=Inputs!$C$77,OR(Inputs!$C$78="",B9<=Inputs!$C$78)),1,0) -> 1 | M9: =Inputs!$C$55 -> 1 | N9: =IF(G9>0,1,0) -> 1 | O9: =IF(D9="founding",G9-H9,0) -> 0 | P9: =IF(D9="standard",G9-H9,0) -> 3 | Q9: =O9*(K9*MIN(E9,Inputs!$C$43)+Inputs!$C$45*MAX(E9-Inputs!$C$43,0))+I9*K9*E9 -> 0 | R9: =(P9+H9-I9)*(J9*MIN(E9,Inputs!$C$40)+Inputs!$C$45*MAX(E9-Inputs!$C$40,0)) -> 4500 | S9: =Q9+R9 -> 4500 | T9: =N9*E9*(Inputs!$C$68+Inputs!$C$69*MAX(G9-1,0)) -> 80 | U9: =IF(N9=0,0,INDEX(Inputs!$C$105:$C$107,MATCH(C9,Inputs!$B$105:$B$107,0))+INDEX(Inputs!$D$105:$D$107,MATCH(C9,Inputs!$B$105:$B$107,0))*E9) -> 300 | V9: =IF(N9=0,0,INDEX(Inputs!$E$105:$E$107,MATCH(C9,Inputs!$B$105:$B$107,0))*E9) -> 0 | W9: =S9*Inputs!$C$54*M9 -> 135 | X9: =N9*L9*Inputs!$C$76/Inputs!$C$85 -> 75 | Y9: =N9*Inputs!$C$79/Inputs!$C$85 -> 30 | Z9: =N9*Inputs!$C$81/Inputs!$C$85 -> 50 | AA9: =SUM(T9:Z9) -> 670 | AB9: =O9*Inputs!$C$89+P9*Inputs!$C$93+H9*Inputs!$C$94 -> 18 | AC9: =N9*(F9*Inputs!$C$95+(E9-F9)*Inputs!$C$96) -> 16 | AD9: =IF(N9=0,0,INDEX(Inputs!$F$105:$F$107,MATCH(C9,Inputs!$B$105:$B$107,0))+Inputs!$C$97*G9) -> 4 | AE9: =IF(N9=0,0,INDEX(Inputs!$G$105:$G$107,MATCH(C9,Inputs!$B$105:$B$107,0))*E9) -> 8 | AF9: =IF(N9=0,0,INDEX(Inputs!$H$105:$H$107,MATCH(C9,Inputs!$B$105:$B$107,0))*E9) -> 4 | AG9: =Inputs!$C$98*G9 -> 6 | AH9: =N9*Inputs!$C$99 -> 2 | AI9: =SUM(AB9:AH9) -> 58 | AJ9: =S9-AA9 -> 3830 | AK9: =IF(AI9>0,AJ9/AI9,"n/a") -> 66.034483 | AL9: =T9+U9+V9+W9 -> 515 | AM9: =X9+Y9+Z9 -> 155 | AO9: =IF(OR(N9=0,AP9=0),"",WORKDAY(B9,-Inputs!$C$49,Lists!$N$4:$N$30)+N(Inputs!$C$53)) | AP9: =Q9*Inputs!$C$48 -> 0 | AQ9: =IF(OR(N9=0,AR9=0),"",WORKDAY(B9,-Inputs!$C$51,Lists!$N$4:$N$30)+N(Inputs!$C$53)) -> 46426 | AR9: =R9*Inputs!$C$50 -> 2250 | AS9: =IF(OR(N9=0,AT9=0),"",WORKDAY(B9,Inputs!$C$52,Lists!$N$4:$N$30)+N(Inputs!$C$53)) -> 46442 | AT9: =Q9*(1-Inputs!$C$48)+R9*(1-Inputs!$C$50) -> 2250 | AU9: =AP9*Inputs!$C$54*M9 -> 0 | AV9: =AR9*Inputs!$C$54*M9 -> 67.5 | AW9: =AT9*Inputs!$C$54*M9 -> 67.5 | AX9: =IF(N9=0,"",WORKDAY(B9,-Inputs!$C$74,Lists!$N$4:$N$30)) -> 46436 | AY9: =IF(N9=0,"",B9) -> 46441 | AZ9: =IF(Schedule!N9="Y","Y","N") -> N | BA9: =IF(AZ9="Y",Drop_Actuals!D9,S9) -> 4500 | BB9: =IF(AZ9="Y",Drop_Actuals!J9,AA9) -> 670 | BC9: =IF(AZ9="Y",Drop_Actuals!R9,AI9) -> 58 | BD9: =BA9-BB9 -> 3830 | BE9: =IF(BC9>0,BD9/BC9,"n/a") -> 66.034483 | BF9: =IF(AND(N9=0,AZ9="N"),"",IF(AZ9="Y","actual","plan")) -> plan | BG9: =IF(AND(N9=1,B9>=Inputs!$C$17),1,0) -> 1 | BH9: =IF(AND(AO9<>"",AO9>=Inputs!$C$10,AO9<=Cash_Flow!$AB$6),AP9-AU9,0)+IF(AND(AQ9<>"",AQ9>=Inputs!$C$10,AQ9<=Cash_Flow!$AB$6),AR9-AV9,0)+IF(AND(AS9<>"",AS9>=Inputs!$C$10,AS9<=Cash_Flow!$AB$6),AT9-AW9,0)-IF(AND(AX9<>"",AX9>=Inputs!$C$10,AX9<=Cash_Flow!$AB$6),T9+V9,0)-IF(AND(AY9<>"",AY9>=Inputs!$C$10,AY9<=Cash_Flow!$AB$6),U9,0) -> 3985 | BI9: =IF(AZ9="Y",Drop_Actuals!AM9,BH9) -> 3985 | BJ9: =IF(BG9=1,B9,"") -> 46441
A10: =Schedule!A10 -> DRP-004 | B10: =IF(Schedule!E10="","",Schedule!E10) -> 46469 | C10: =IF(Schedule!G10="","",Schedule!G10) -> direct-ship | D10: =IF(Schedule!H10="","",Schedule!H10) -> standard | E10: =N(Schedule!I10) -> 10 | F10: =N(Schedule!J10) -> 0 | G10: =N(Schedule!K10) -> 3 | H10: =N(Schedule!L10) -> 1 | I10: =N(Schedule!M10) -> 0 | J10: =IF(AND(B10<>"",B10>Inputs!$C$15),Scenarios!$H$14,Inputs!$C$39) -> 150 | K10: =Inputs!$C$42 -> 120 | L10: =IF(AND(Inputs!$C$75="unit",B10<>"",Inputs!$C$77<>"",B10>=Inputs!$C$77,OR(Inputs!$C$78="",B10<=Inputs!$C$78)),1,0) -> 1 | M10: =Inputs!$C$55 -> 1 | N10: =IF(G10>0,1,0) -> 1 | O10: =IF(D10="founding",G10-H10,0) -> 0 | P10: =IF(D10="standard",G10-H10,0) -> 2 | Q10: =O10*(K10*MIN(E10,Inputs!$C$43)+Inputs!$C$45*MAX(E10-Inputs!$C$43,0))+I10*K10*E10 -> 0 | R10: =(P10+H10-I10)*(J10*MIN(E10,Inputs!$C$40)+Inputs!$C$45*MAX(E10-Inputs!$C$40,0)) -> 4500 | S10: =Q10+R10 -> 4500 | T10: =N10*E10*(Inputs!$C$68+Inputs!$C$69*MAX(G10-1,0)) -> 80 | U10: =IF(N10=0,0,INDEX(Inputs!$C$105:$C$107,MATCH(C10,Inputs!$B$105:$B$107,0))+INDEX(Inputs!$D$105:$D$107,MATCH(C10,Inputs!$B$105:$B$107,0))*E10) -> 0 | V10: =IF(N10=0,0,INDEX(Inputs!$E$105:$E$107,MATCH(C10,Inputs!$B$105:$B$107,0))*E10) -> 0 | W10: =S10*Inputs!$C$54*M10 -> 135 | X10: =N10*L10*Inputs!$C$76/Inputs!$C$85 -> 75 | Y10: =N10*Inputs!$C$79/Inputs!$C$85 -> 30 | Z10: =N10*Inputs!$C$81/Inputs!$C$85 -> 50 | AA10: =SUM(T10:Z10) -> 370 | AB10: =O10*Inputs!$C$89+P10*Inputs!$C$93+H10*Inputs!$C$94 -> 14 | AC10: =N10*(F10*Inputs!$C$95+(E10-F10)*Inputs!$C$96) -> 10 | AD10: =IF(N10=0,0,INDEX(Inputs!$F$105:$F$107,MATCH(C10,Inputs!$B$105:$B$107,0))+Inputs!$C$97*G10) -> 2 | AE10: =IF(N10=0,0,INDEX(Inputs!$G$105:$G$107,MATCH(C10,Inputs!$B$105:$B$107,0))*E10) -> 3 | AF10: =IF(N10=0,0,INDEX(Inputs!$H$105:$H$107,MATCH(C10,Inputs!$B$105:$B$107,0))*E10) -> 4 | AG10: =Inputs!$C$98*G10 -> 6 | AH10: =N10*Inputs!$C$99 -> 2 | AI10: =SUM(AB10:AH10) -> 41 | AJ10: =S10-AA10 -> 4130 | AK10: =IF(AI10>0,AJ10/AI10,"n/a") -> 100.73171 | AL10: =T10+U10+V10+W10 -> 215 | AM10: =X10+Y10+Z10 -> 155 | AO10: =IF(OR(N10=0,AP10=0),"",WORKDAY(B10,-Inputs!$C$49,Lists!$N$4:$N$30)+N(Inputs!$C$53)) | AP10: =Q10*Inputs!$C$48 -> 0 | AQ10: =IF(OR(N10=0,AR10=0),"",WORKDAY(B10,-Inputs!$C$51,Lists!$N$4:$N$30)+N(Inputs!$C$53)) -> 46455 | AR10: =R10*Inputs!$C$50 -> 2250 | AS10: =IF(OR(N10=0,AT10=0),"",WORKDAY(B10,Inputs!$C$52,Lists!$N$4:$N$30)+N(Inputs!$C$53)) -> 46470 | AT10: =Q10*(1-Inputs!$C$48)+R10*(1-Inputs!$C$50) -> 2250 | AU10: =AP10*Inputs!$C$54*M10 -> 0 | AV10: =AR10*Inputs!$C$54*M10 -> 67.5 | AW10: =AT10*Inputs!$C$54*M10 -> 67.5 | AX10: =IF(N10=0,"",WORKDAY(B10,-Inputs!$C$74,Lists!$N$4:$N$30)) -> 46464 | AY10: =IF(N10=0,"",B10) -> 46469 | AZ10: =IF(Schedule!N10="Y","Y","N") -> N | BA10: =IF(AZ10="Y",Drop_Actuals!D10,S10) -> 4500 | BB10: =IF(AZ10="Y",Drop_Actuals!J10,AA10) -> 370 | BC10: =IF(AZ10="Y",Drop_Actuals!R10,AI10) -> 41 | BD10: =BA10-BB10 -> 4130 | BE10: =IF(BC10>0,BD10/BC10,"n/a") -> 100.73171 | BF10: =IF(AND(N10=0,AZ10="N"),"",IF(AZ10="Y","actual","plan")) -> plan | BG10: =IF(AND(N10=1,B10>=Inputs!$C$17),1,0) -> 1 | BH10: =IF(AND(AO10<>"",AO10>=Inputs!$C$10,AO10<=Cash_Flow!$AB$6),AP10-AU10,0)+IF(AND(AQ10<>"",AQ10>=Inputs!$C$10,AQ10<=Cash_Flow!$AB$6),AR10-AV10,0)+IF(AND(AS10<>"",AS10>=Inputs!$C$10,AS10<=Cash_Flow!$AB$6),AT10-AW10,0)-IF(AND(AX10<>"",AX10>=Inputs!$C$10,AX10<=Cash_Flow!$AB$6),T10+V10,0)-IF(AND(AY10<>"",AY10>=Inputs!$C$10,AY10<=Cash_Flow!$AB$6),U10,0) -> 4285 | BI10: =IF(AZ10="Y",Drop_Actuals!AM10,BH10) -> 4285 | BJ10: =IF(BG10=1,B10,"") -> 46469
A11: =Schedule!A11 -> DRP-005 | B11: =IF(Schedule!E11="","",Schedule!E11) -> 46483 | C11: =IF(Schedule!G11="","",Schedule!G11) -> direct-ship | D11: =IF(Schedule!H11="","",Schedule!H11) -> standard | E11: =N(Schedule!I11) -> 10 | F11: =N(Schedule!J11) -> 0 | G11: =N(Schedule!K11) -> 3 | H11: =N(Schedule!L11) -> 1 | I11: =N(Schedule!M11) -> 0 | J11: =IF(AND(B11<>"",B11>Inputs!$C$15),Scenarios!$H$14,Inputs!$C$39) -> 150 | K11: =Inputs!$C$42 -> 120 | L11: =IF(AND(Inputs!$C$75="unit",B11<>"",Inputs!$C$77<>"",B11>=Inputs!$C$77,OR(Inputs!$C$78="",B11<=Inputs!$C$78)),1,0) -> 1 | M11: =Inputs!$C$55 -> 1 | N11: =IF(G11>0,1,0) -> 1 | O11: =IF(D11="founding",G11-H11,0) -> 0 | P11: =IF(D11="standard",G11-H11,0) -> 2 | Q11: =O11*(K11*MIN(E11,Inputs!$C$43)+Inputs!$C$45*MAX(E11-Inputs!$C$43,0))+I11*K11*E11 -> 0 | R11: =(P11+H11-I11)*(J11*MIN(E11,Inputs!$C$40)+Inputs!$C$45*MAX(E11-Inputs!$C$40,0)) -> 4500 | S11: =Q11+R11 -> 4500 | T11: =N11*E11*(Inputs!$C$68+Inputs!$C$69*MAX(G11-1,0)) -> 80 | U11: =IF(N11=0,0,INDEX(Inputs!$C$105:$C$107,MATCH(C11,Inputs!$B$105:$B$107,0))+INDEX(Inputs!$D$105:$D$107,MATCH(C11,Inputs!$B$105:$B$107,0))*E11) -> 0 | V11: =IF(N11=0,0,INDEX(Inputs!$E$105:$E$107,MATCH(C11,Inputs!$B$105:$B$107,0))*E11) -> 0 | W11: =S11*Inputs!$C$54*M11 -> 135 | X11: =N11*L11*Inputs!$C$76/Inputs!$C$85 -> 75 | Y11: =N11*Inputs!$C$79/Inputs!$C$85 -> 30 | Z11: =N11*Inputs!$C$81/Inputs!$C$85 -> 50 | AA11: =SUM(T11:Z11) -> 370 | AB11: =O11*Inputs!$C$89+P11*Inputs!$C$93+H11*Inputs!$C$94 -> 14 | AC11: =N11*(F11*Inputs!$C$95+(E11-F11)*Inputs!$C$96) -> 10 | AD11: =IF(N11=0,0,INDEX(Inputs!$F$105:$F$107,MATCH(C11,Inputs!$B$105:$B$107,0))+Inputs!$C$97*G11) -> 2 | AE11: =IF(N11=0,0,INDEX(Inputs!$G$105:$G$107,MATCH(C11,Inputs!$B$105:$B$107,0))*E11) -> 3 | AF11: =IF(N11=0,0,INDEX(Inputs!$H$105:$H$107,MATCH(C11,Inputs!$B$105:$B$107,0))*E11) -> 4 | AG11: =Inputs!$C$98*G11 -> 6 | AH11: =N11*Inputs!$C$99 -> 2 | AI11: =SUM(AB11:AH11) -> 41 | AJ11: =S11-AA11 -> 4130 | AK11: =IF(AI11>0,AJ11/AI11,"n/a") -> 100.73171 | AL11: =T11+U11+V11+W11 -> 215 | AM11: =X11+Y11+Z11 -> 155 | AO11: =IF(OR(N11=0,AP11=0),"",WORKDAY(B11,-Inputs!$C$49,Lists!$N$4:$N$30)+N(Inputs!$C$53)) | AP11: =Q11*Inputs!$C$48 -> 0 | AQ11: =IF(OR(N11=0,AR11=0),"",WORKDAY(B11,-Inputs!$C$51,Lists!$N$4:$N$30)+N(Inputs!$C$53)) -> 46469 | AR11: =R11*Inputs!$C$50 -> 2250 | AS11: =IF(OR(N11=0,AT11=0),"",WORKDAY(B11,Inputs!$C$52,Lists!$N$4:$N$30)+N(Inputs!$C$53)) -> 46484 | AT11: =Q11*(1-Inputs!$C$48)+R11*(1-Inputs!$C$50) -> 2250 | AU11: =AP11*Inputs!$C$54*M11 -> 0 | AV11: =AR11*Inputs!$C$54*M11 -> 67.5 | AW11: =AT11*Inputs!$C$54*M11 -> 67.5 | AX11: =IF(N11=0,"",WORKDAY(B11,-Inputs!$C$74,Lists!$N$4:$N$30)) -> 46478 | AY11: =IF(N11=0,"",B11) -> 46483 | AZ11: =IF(Schedule!N11="Y","Y","N") -> N | BA11: =IF(AZ11="Y",Drop_Actuals!D11,S11) -> 4500 | BB11: =IF(AZ11="Y",Drop_Actuals!J11,AA11) -> 370 | BC11: =IF(AZ11="Y",Drop_Actuals!R11,AI11) -> 41 | BD11: =BA11-BB11 -> 4130 | BE11: =IF(BC11>0,BD11/BC11,"n/a") -> 100.73171 | BF11: =IF(AND(N11=0,AZ11="N"),"",IF(AZ11="Y","actual","plan")) -> plan | BG11: =IF(AND(N11=1,B11>=Inputs!$C$17),1,0) -> 1 | BH11: =IF(AND(AO11<>"",AO11>=Inputs!$C$10,AO11<=Cash_Flow!$AB$6),AP11-AU11,0)+IF(AND(AQ11<>"",AQ11>=Inputs!$C$10,AQ11<=Cash_Flow!$AB$6),AR11-AV11,0)+IF(AND(AS11<>"",AS11>=Inputs!$C$10,AS11<=Cash_Flow!$AB$6),AT11-AW11,0)-IF(AND(AX11<>"",AX11>=Inputs!$C$10,AX11<=Cash_Flow!$AB$6),T11+V11,0)-IF(AND(AY11<>"",AY11>=Inputs!$C$10,AY11<=Cash_Flow!$AB$6),U11,0) -> 4285 | BI11: =IF(AZ11="Y",Drop_Actuals!AM11,BH11) -> 4285 | BJ11: =IF(BG11=1,B11,"") -> 46483
A12: =Schedule!A12 -> DRP-006 | B12: =IF(Schedule!E12="","",Schedule!E12) | C12: =IF(Schedule!G12="","",Schedule!G12) | D12: =IF(Schedule!H12="","",Schedule!H12) | E12: =N(Schedule!I12) -> 0 | F12: =N(Schedule!J12) -> 0 | G12: =N(Schedule!K12) -> 0 | H12: =N(Schedule!L12) -> 0 | I12: =N(Schedule!M12) -> 0 | J12: =IF(AND(B12<>"",B12>Inputs!$C$15),Scenarios!$H$14,Inputs!$C$39) -> 150 | K12: =Inputs!$C$42 -> 120 | L12: =IF(AND(Inputs!$C$75="unit",B12<>"",Inputs!$C$77<>"",B12>=Inputs!$C$77,OR(Inputs!$C$78="",B12<=Inputs!$C$78)),1,0) -> 0 | M12: =Inputs!$C$55 -> 1 | N12: =IF(G12>0,1,0) -> 0 | O12: =IF(D12="founding",G12-H12,0) -> 0 | P12: =IF(D12="standard",G12-H12,0) -> 0 | Q12: =O12*(K12*MIN(E12,Inputs!$C$43)+Inputs!$C$45*MAX(E12-Inputs!$C$43,0))+I12*K12*E12 -> 0 | R12: =(P12+H12-I12)*(J12*MIN(E12,Inputs!$C$40)+Inputs!$C$45*MAX(E12-Inputs!$C$40,0)) -> 0 | S12: =Q12+R12 -> 0 | T12: =N12*E12*(Inputs!$C$68+Inputs!$C$69*MAX(G12-1,0)) -> 0 | U12: =IF(N12=0,0,INDEX(Inputs!$C$105:$C$107,MATCH(C12,Inputs!$B$105:$B$107,0))+INDEX(Inputs!$D$105:$D$107,MATCH(C12,Inputs!$B$105:$B$107,0))*E12) -> 0 | V12: =IF(N12=0,0,INDEX(Inputs!$E$105:$E$107,MATCH(C12,Inputs!$B$105:$B$107,0))*E12) -> 0 | W12: =S12*Inputs!$C$54*M12 -> 0 | X12: =N12*L12*Inputs!$C$76/Inputs!$C$85 -> 0 | Y12: =N12*Inputs!$C$79/Inputs!$C$85 -> 0 | Z12: =N12*Inputs!$C$81/Inputs!$C$85 -> 0 | AA12: =SUM(T12:Z12) -> 0 | AB12: =O12*Inputs!$C$89+P12*Inputs!$C$93+H12*Inputs!$C$94 -> 0 | AC12: =N12*(F12*Inputs!$C$95+(E12-F12)*Inputs!$C$96) -> 0 | AD12: =IF(N12=0,0,INDEX(Inputs!$F$105:$F$107,MATCH(C12,Inputs!$B$105:$B$107,0))+Inputs!$C$97*G12) -> 0 | AE12: =IF(N12=0,0,INDEX(Inputs!$G$105:$G$107,MATCH(C12,Inputs!$B$105:$B$107,0))*E12) -> 0 | AF12: =IF(N12=0,0,INDEX(Inputs!$H$105:$H$107,MATCH(C12,Inputs!$B$105:$B$107,0))*E12) -> 0 | AG12: =Inputs!$C$98*G12 -> 0 | AH12: =N12*Inputs!$C$99 -> 0 | AI12: =SUM(AB12:AH12) -> 0 | AJ12: =S12-AA12 -> 0 | AK12: =IF(AI12>0,AJ12/AI12,"n/a") -> n/a | AL12: =T12+U12+V12+W12 -> 0 | AM12: =X12+Y12+Z12 -> 0 | AO12: =IF(OR(N12=0,AP12=0),"",WORKDAY(B12,-Inputs!$C$49,Lists!$N$4:$N$30)+N(Inputs!$C$53)) | AP12: =Q12*Inputs!$C$48 -> 0 | AQ12: =IF(OR(N12=0,AR12=0),"",WORKDAY(B12,-Inputs!$C$51,Lists!$N$4:$N$30)+N(Inputs!$C$53)) | AR12: =R12*Inputs!$C$50 -> 0 | AS12: =IF(OR(N12=0,AT12=0),"",WORKDAY(B12,Inputs!$C$52,Lists!$N$4:$N$30)+N(Inputs!$C$53)) | AT12: =Q12*(1-Inputs!$C$48)+R12*(1-Inputs!$C$50) -> 0 | AU12: =AP12*Inputs!$C$54*M12 -> 0 | AV12: =AR12*Inputs!$C$54*M12 -> 0 | AW12: =AT12*Inputs!$C$54*M12 -> 0 | AX12: =IF(N12=0,"",WORKDAY(B12,-Inputs!$C$74,Lists!$N$4:$N$30)) | AY12: =IF(N12=0,"",B12) | AZ12: =IF(Schedule!N12="Y","Y","N") -> N | BA12: =IF(AZ12="Y",Drop_Actuals!D12,S12) -> 0 | BB12: =IF(AZ12="Y",Drop_Actuals!J12,AA12) -> 0 | BC12: =IF(AZ12="Y",Drop_Actuals!R12,AI12) -> 0 | BD12: =BA12-BB12 -> 0 | BE12: =IF(BC12>0,BD12/BC12,"n/a") -> n/a | BF12: =IF(AND(N12=0,AZ12="N"),"",IF(AZ12="Y","actual","plan")) | BG12: =IF(AND(N12=1,B12>=Inputs!$C$17),1,0) -> 0 | BH12: =IF(AND(AO12<>"",AO12>=Inputs!$C$10,AO12<=Cash_Flow!$AB$6),AP12-AU12,0)+IF(AND(AQ12<>"",AQ12>=Inputs!$C$10,AQ12<=Cash_Flow!$AB$6),AR12-AV12,0)+IF(AND(AS12<>"",AS12>=Inputs!$C$10,AS12<=Cash_Flow!$AB$6),AT12-AW12,0)-IF(AND(AX12<>"",AX12>=Inputs!$C$10,AX12<=Cash_Flow!$AB$6),T12+V12,0)-IF(AND(AY12<>"",AY12>=Inputs!$C$10,AY12<=Cash_Flow!$AB$6),U12,0) -> 0 | BI12: =IF(AZ12="Y",Drop_Actuals!AM12,BH12) -> 0 | BJ12: =IF(BG12=1,B12,"")
A13: =Schedule!A13 -> DRP-007 | B13: =IF(Schedule!E13="","",Schedule!E13) | C13: =IF(Schedule!G13="","",Schedule!G13) | D13: =IF(Schedule!H13="","",Schedule!H13) | E13: =N(Schedule!I13) -> 0 | F13: =N(Schedule!J13) -> 0 | G13: =N(Schedule!K13) -> 0 | H13: =N(Schedule!L13) -> 0 | I13: =N(Schedule!M13) -> 0 | J13: =IF(AND(B13<>"",B13>Inputs!$C$15),Scenarios!$H$14,Inputs!$C$39) -> 150 | K13: =Inputs!$C$42 -> 120 | L13: =IF(AND(Inputs!$C$75="unit",B13<>"",Inputs!$C$77<>"",B13>=Inputs!$C$77,OR(Inputs!$C$78="",B13<=Inputs!$C$78)),1,0) -> 0 | M13: =Inputs!$C$55 -> 1 | N13: =IF(G13>0,1,0) -> 0 | O13: =IF(D13="founding",G13-H13,0) -> 0 | P13: =IF(D13="standard",G13-H13,0) -> 0 | Q13: =O13*(K13*MIN(E13,Inputs!$C$43)+Inputs!$C$45*MAX(E13-Inputs!$C$43,0))+I13*K13*E13 -> 0 | R13: =(P13+H13-I13)*(J13*MIN(E13,Inputs!$C$40)+Inputs!$C$45*MAX(E13-Inputs!$C$40,0)) -> 0 | S13: =Q13+R13 -> 0 | T13: =N13*E13*(Inputs!$C$68+Inputs!$C$69*MAX(G13-1,0)) -> 0 | U13: =IF(N13=0,0,INDEX(Inputs!$C$105:$C$107,MATCH(C13,Inputs!$B$105:$B$107,0))+INDEX(Inputs!$D$105:$D$107,MATCH(C13,Inputs!$B$105:$B$107,0))*E13) -> 0 | V13: =IF(N13=0,0,INDEX(Inputs!$E$105:$E$107,MATCH(C13,Inputs!$B$105:$B$107,0))*E13) -> 0 | W13: =S13*Inputs!$C$54*M13 -> 0 | X13: =N13*L13*Inputs!$C$76/Inputs!$C$85 -> 0 | Y13: =N13*Inputs!$C$79/Inputs!$C$85 -> 0 | Z13: =N13*Inputs!$C$81/Inputs!$C$85 -> 0 | AA13: =SUM(T13:Z13) -> 0 | AB13: =O13*Inputs!$C$89+P13*Inputs!$C$93+H13*Inputs!$C$94 -> 0 | AC13: =N13*(F13*Inputs!$C$95+(E13-F13)*Inputs!$C$96) -> 0 | AD13: =IF(N13=0,0,INDEX(Inputs!$F$105:$F$107,MATCH(C13,Inputs!$B$105:$B$107,0))+Inputs!$C$97*G13) -> 0 | AE13: =IF(N13=0,0,INDEX(Inputs!$G$105:$G$107,MATCH(C13,Inputs!$B$105:$B$107,0))*E13) -> 0 | AF13: =IF(N13=0,0,INDEX(Inputs!$H$105:$H$107,MATCH(C13,Inputs!$B$105:$B$107,0))*E13) -> 0 | AG13: =Inputs!$C$98*G13 -> 0 | AH13: =N13*Inputs!$C$99 -> 0 | AI13: =SUM(AB13:AH13) -> 0 | AJ13: =S13-AA13 -> 0 | AK13: =IF(AI13>0,AJ13/AI13,"n/a") -> n/a | AL13: =T13+U13+V13+W13 -> 0 | AM13: =X13+Y13+Z13 -> 0 | AO13: =IF(OR(N13=0,AP13=0),"",WORKDAY(B13,-Inputs!$C$49,Lists!$N$4:$N$30)+N(Inputs!$C$53)) | AP13: =Q13*Inputs!$C$48 -> 0 | AQ13: =IF(OR(N13=0,AR13=0),"",WORKDAY(B13,-Inputs!$C$51,Lists!$N$4:$N$30)+N(Inputs!$C$53)) | AR13: =R13*Inputs!$C$50 -> 0 | AS13: =IF(OR(N13=0,AT13=0),"",WORKDAY(B13,Inputs!$C$52,Lists!$N$4:$N$30)+N(Inputs!$C$53)) | AT13: =Q13*(1-Inputs!$C$48)+R13*(1-Inputs!$C$50) -> 0 | AU13: =AP13*Inputs!$C$54*M13 -> 0 | AV13: =AR13*Inputs!$C$54*M13 -> 0 | AW13: =AT13*Inputs!$C$54*M13 -> 0 | AX13: =IF(N13=0,"",WORKDAY(B13,-Inputs!$C$74,Lists!$N$4:$N$30)) | AY13: =IF(N13=0,"",B13) | AZ13: =IF(Schedule!N13="Y","Y","N") -> N | BA13: =IF(AZ13="Y",Drop_Actuals!D13,S13) -> 0 | BB13: =IF(AZ13="Y",Drop_Actuals!J13,AA13) -> 0 | BC13: =IF(AZ13="Y",Drop_Actuals!R13,AI13) -> 0 | BD13: =BA13-BB13 -> 0 | BE13: =IF(BC13>0,BD13/BC13,"n/a") -> n/a | BF13: =IF(AND(N13=0,AZ13="N"),"",IF(AZ13="Y","actual","plan")) | BG13: =IF(AND(N13=1,B13>=Inputs!$C$17),1,0) -> 0 | BH13: =IF(AND(AO13<>"",AO13>=Inputs!$C$10,AO13<=Cash_Flow!$AB$6),AP13-AU13,0)+IF(AND(AQ13<>"",AQ13>=Inputs!$C$10,AQ13<=Cash_Flow!$AB$6),AR13-AV13,0)+IF(AND(AS13<>"",AS13>=Inputs!$C$10,AS13<=Cash_Flow!$AB$6),AT13-AW13,0)-IF(AND(AX13<>"",AX13>=Inputs!$C$10,AX13<=Cash_Flow!$AB$6),T13+V13,0)-IF(AND(AY13<>"",AY13>=Inputs!$C$10,AY13<=Cash_Flow!$AB$6),U13,0) -> 0 | BI13: =IF(AZ13="Y",Drop_Actuals!AM13,BH13) -> 0 | BJ13: =IF(BG13=1,B13,"")
A14: =Schedule!A14 -> DRP-008 | B14: =IF(Schedule!E14="","",Schedule!E14) | C14: =IF(Schedule!G14="","",Schedule!G14) | D14: =IF(Schedule!H14="","",Schedule!H14) | E14: =N(Schedule!I14) -> 0 | F14: =N(Schedule!J14) -> 0 | G14: =N(Schedule!K14) -> 0 | H14: =N(Schedule!L14) -> 0 | I14: =N(Schedule!M14) -> 0 | J14: =IF(AND(B14<>"",B14>Inputs!$C$15),Scenarios!$H$14,Inputs!$C$39) -> 150 | K14: =Inputs!$C$42 -> 120 | L14: =IF(AND(Inputs!$C$75="unit",B14<>"",Inputs!$C$77<>"",B14>=Inputs!$C$77,OR(Inputs!$C$78="",B14<=Inputs!$C$78)),1,0) -> 0 | M14: =Inputs!$C$55 -> 1 | N14: =IF(G14>0,1,0) -> 0 | O14: =IF(D14="founding",G14-H14,0) -> 0 | P14: =IF(D14="standard",G14-H14,0) -> 0 | Q14: =O14*(K14*MIN(E14,Inputs!$C$43)+Inputs!$C$45*MAX(E14-Inputs!$C$43,0))+I14*K14*E14 -> 0 | R14: =(P14+H14-I14)*(J14*MIN(E14,Inputs!$C$40)+Inputs!$C$45*MAX(E14-Inputs!$C$40,0)) -> 0 | S14: =Q14+R14 -> 0 | T14: =N14*E14*(Inputs!$C$68+Inputs!$C$69*MAX(G14-1,0)) -> 0 | U14: =IF(N14=0,0,INDEX(Inputs!$C$105:$C$107,MATCH(C14,Inputs!$B$105:$B$107,0))+INDEX(Inputs!$D$105:$D$107,MATCH(C14,Inputs!$B$105:$B$107,0))*E14) -> 0 | V14: =IF(N14=0,0,INDEX(Inputs!$E$105:$E$107,MATCH(C14,Inputs!$B$105:$B$107,0))*E14) -> 0 | W14: =S14*Inputs!$C$54*M14 -> 0 | X14: =N14*L14*Inputs!$C$76/Inputs!$C$85 -> 0 | Y14: =N14*Inputs!$C$79/Inputs!$C$85 -> 0 | Z14: =N14*Inputs!$C$81/Inputs!$C$85 -> 0 | AA14: =SUM(T14:Z14) -> 0 | AB14: =O14*Inputs!$C$89+P14*Inputs!$C$93+H14*Inputs!$C$94 -> 0 | AC14: =N14*(F14*Inputs!$C$95+(E14-F14)*Inputs!$C$96) -> 0 | AD14: =IF(N14=0,0,INDEX(Inputs!$F$105:$F$107,MATCH(C14,Inputs!$B$105:$B$107,0))+Inputs!$C$97*G14) -> 0 | AE14: =IF(N14=0,0,INDEX(Inputs!$G$105:$G$107,MATCH(C14,Inputs!$B$105:$B$107,0))*E14) -> 0 | AF14: =IF(N14=0,0,INDEX(Inputs!$H$105:$H$107,MATCH(C14,Inputs!$B$105:$B$107,0))*E14) -> 0 | AG14: =Inputs!$C$98*G14 -> 0 | AH14: =N14*Inputs!$C$99 -> 0 | AI14: =SUM(AB14:AH14) -> 0 | AJ14: =S14-AA14 -> 0 | AK14: =IF(AI14>0,AJ14/AI14,"n/a") -> n/a | AL14: =T14+U14+V14+W14 -> 0 | AM14: =X14+Y14+Z14 -> 0 | AO14: =IF(OR(N14=0,AP14=0),"",WORKDAY(B14,-Inputs!$C$49,Lists!$N$4:$N$30)+N(Inputs!$C$53)) | AP14: =Q14*Inputs!$C$48 -> 0 | AQ14: =IF(OR(N14=0,AR14=0),"",WORKDAY(B14,-Inputs!$C$51,Lists!$N$4:$N$30)+N(Inputs!$C$53)) | AR14: =R14*Inputs!$C$50 -> 0 | AS14: =IF(OR(N14=0,AT14=0),"",WORKDAY(B14,Inputs!$C$52,Lists!$N$4:$N$30)+N(Inputs!$C$53)) | AT14: =Q14*(1-Inputs!$C$48)+R14*(1-Inputs!$C$50) -> 0 | AU14: =AP14*Inputs!$C$54*M14 -> 0 | AV14: =AR14*Inputs!$C$54*M14 -> 0 | AW14: =AT14*Inputs!$C$54*M14 -> 0 | AX14: =IF(N14=0,"",WORKDAY(B14,-Inputs!$C$74,Lists!$N$4:$N$30)) | AY14: =IF(N14=0,"",B14) | AZ14: =IF(Schedule!N14="Y","Y","N") -> N | BA14: =IF(AZ14="Y",Drop_Actuals!D14,S14) -> 0 | BB14: =IF(AZ14="Y",Drop_Actuals!J14,AA14) -> 0 | BC14: =IF(AZ14="Y",Drop_Actuals!R14,AI14) -> 0 | BD14: =BA14-BB14 -> 0 | BE14: =IF(BC14>0,BD14/BC14,"n/a") -> n/a | BF14: =IF(AND(N14=0,AZ14="N"),"",IF(AZ14="Y","actual","plan")) | BG14: =IF(AND(N14=1,B14>=Inputs!$C$17),1,0) -> 0 | BH14: =IF(AND(AO14<>"",AO14>=Inputs!$C$10,AO14<=Cash_Flow!$AB$6),AP14-AU14,0)+IF(AND(AQ14<>"",AQ14>=Inputs!$C$10,AQ14<=Cash_Flow!$AB$6),AR14-AV14,0)+IF(AND(AS14<>"",AS14>=Inputs!$C$10,AS14<=Cash_Flow!$AB$6),AT14-AW14,0)-IF(AND(AX14<>"",AX14>=Inputs!$C$10,AX14<=Cash_Flow!$AB$6),T14+V14,0)-IF(AND(AY14<>"",AY14>=Inputs!$C$10,AY14<=Cash_Flow!$AB$6),U14,0) -> 0 | BI14: =IF(AZ14="Y",Drop_Actuals!AM14,BH14) -> 0 | BJ14: =IF(BG14=1,B14,"")
A15: =Schedule!A15 -> DRP-009 | B15: =IF(Schedule!E15="","",Schedule!E15) | C15: =IF(Schedule!G15="","",Schedule!G15) | D15: =IF(Schedule!H15="","",Schedule!H15) | E15: =N(Schedule!I15) -> 0 | F15: =N(Schedule!J15) -> 0 | G15: =N(Schedule!K15) -> 0 | H15: =N(Schedule!L15) -> 0 | I15: =N(Schedule!M15) -> 0 | J15: =IF(AND(B15<>"",B15>Inputs!$C$15),Scenarios!$H$14,Inputs!$C$39) -> 150 | K15: =Inputs!$C$42 -> 120 | L15: =IF(AND(Inputs!$C$75="unit",B15<>"",Inputs!$C$77<>"",B15>=Inputs!$C$77,OR(Inputs!$C$78="",B15<=Inputs!$C$78)),1,0) -> 0 | M15: =Inputs!$C$55 -> 1 | N15: =IF(G15>0,1,0) -> 0 | O15: =IF(D15="founding",G15-H15,0) -> 0 | P15: =IF(D15="standard",G15-H15,0) -> 0 | Q15: =O15*(K15*MIN(E15,Inputs!$C$43)+Inputs!$C$45*MAX(E15-Inputs!$C$43,0))+I15*K15*E15 -> 0 | R15: =(P15+H15-I15)*(J15*MIN(E15,Inputs!$C$40)+Inputs!$C$45*MAX(E15-Inputs!$C$40,0)) -> 0 | S15: =Q15+R15 -> 0 | T15: =N15*E15*(Inputs!$C$68+Inputs!$C$69*MAX(G15-1,0)) -> 0 | U15: =IF(N15=0,0,INDEX(Inputs!$C$105:$C$107,MATCH(C15,Inputs!$B$105:$B$107,0))+INDEX(Inputs!$D$105:$D$107,MATCH(C15,Inputs!$B$105:$B$107,0))*E15) -> 0 | V15: =IF(N15=0,0,INDEX(Inputs!$E$105:$E$107,MATCH(C15,Inputs!$B$105:$B$107,0))*E15) -> 0 | W15: =S15*Inputs!$C$54*M15 -> 0 | X15: =N15*L15*Inputs!$C$76/Inputs!$C$85 -> 0 | Y15: =N15*Inputs!$C$79/Inputs!$C$85 -> 0 | Z15: =N15*Inputs!$C$81/Inputs!$C$85 -> 0 | AA15: =SUM(T15:Z15) -> 0 | AB15: =O15*Inputs!$C$89+P15*Inputs!$C$93+H15*Inputs!$C$94 -> 0 | AC15: =N15*(F15*Inputs!$C$95+(E15-F15)*Inputs!$C$96) -> 0 | AD15: =IF(N15=0,0,INDEX(Inputs!$F$105:$F$107,MATCH(C15,Inputs!$B$105:$B$107,0))+Inputs!$C$97*G15) -> 0 | AE15: =IF(N15=0,0,INDEX(Inputs!$G$105:$G$107,MATCH(C15,Inputs!$B$105:$B$107,0))*E15) -> 0 | AF15: =IF(N15=0,0,INDEX(Inputs!$H$105:$H$107,MATCH(C15,Inputs!$B$105:$B$107,0))*E15) -> 0 | AG15: =Inputs!$C$98*G15 -> 0 | AH15: =N15*Inputs!$C$99 -> 0 | AI15: =SUM(AB15:AH15) -> 0 | AJ15: =S15-AA15 -> 0 | AK15: =IF(AI15>0,AJ15/AI15,"n/a") -> n/a | AL15: =T15+U15+V15+W15 -> 0 | AM15: =X15+Y15+Z15 -> 0 | AO15: =IF(OR(N15=0,AP15=0),"",WORKDAY(B15,-Inputs!$C$49,Lists!$N$4:$N$30)+N(Inputs!$C$53)) | AP15: =Q15*Inputs!$C$48 -> 0 | AQ15: =IF(OR(N15=0,AR15=0),"",WORKDAY(B15,-Inputs!$C$51,Lists!$N$4:$N$30)+N(Inputs!$C$53)) | AR15: =R15*Inputs!$C$50 -> 0 | AS15: =IF(OR(N15=0,AT15=0),"",WORKDAY(B15,Inputs!$C$52,Lists!$N$4:$N$30)+N(Inputs!$C$53)) | AT15: =Q15*(1-Inputs!$C$48)+R15*(1-Inputs!$C$50) -> 0 | AU15: =AP15*Inputs!$C$54*M15 -> 0 | AV15: =AR15*Inputs!$C$54*M15 -> 0 | AW15: =AT15*Inputs!$C$54*M15 -> 0 | AX15: =IF(N15=0,"",WORKDAY(B15,-Inputs!$C$74,Lists!$N$4:$N$30)) | AY15: =IF(N15=0,"",B15) | AZ15: =IF(Schedule!N15="Y","Y","N") -> N | BA15: =IF(AZ15="Y",Drop_Actuals!D15,S15) -> 0 | BB15: =IF(AZ15="Y",Drop_Actuals!J15,AA15) -> 0 | BC15: =IF(AZ15="Y",Drop_Actuals!R15,AI15) -> 0 | BD15: =BA15-BB15 -> 0 | BE15: =IF(BC15>0,BD15/BC15,"n/a") -> n/a | BF15: =IF(AND(N15=0,AZ15="N"),"",IF(AZ15="Y","actual","plan")) | BG15: =IF(AND(N15=1,B15>=Inputs!$C$17),1,0) -> 0 | BH15: =IF(AND(AO15<>"",AO15>=Inputs!$C$10,AO15<=Cash_Flow!$AB$6),AP15-AU15,0)+IF(AND(AQ15<>"",AQ15>=Inputs!$C$10,AQ15<=Cash_Flow!$AB$6),AR15-AV15,0)+IF(AND(AS15<>"",AS15>=Inputs!$C$10,AS15<=Cash_Flow!$AB$6),AT15-AW15,0)-IF(AND(AX15<>"",AX15>=Inputs!$C$10,AX15<=Cash_Flow!$AB$6),T15+V15,0)-IF(AND(AY15<>"",AY15>=Inputs!$C$10,AY15<=Cash_Flow!$AB$6),U15,0) -> 0 | BI15: =IF(AZ15="Y",Drop_Actuals!AM15,BH15) -> 0 | BJ15: =IF(BG15=1,B15,"")
A16: =Schedule!A16 -> DRP-010 | B16: =IF(Schedule!E16="","",Schedule!E16) | C16: =IF(Schedule!G16="","",Schedule!G16) | D16: =IF(Schedule!H16="","",Schedule!H16) | E16: =N(Schedule!I16) -> 0 | F16: =N(Schedule!J16) -> 0 | G16: =N(Schedule!K16) -> 0 | H16: =N(Schedule!L16) -> 0 | I16: =N(Schedule!M16) -> 0 | J16: =IF(AND(B16<>"",B16>Inputs!$C$15),Scenarios!$H$14,Inputs!$C$39) -> 150 | K16: =Inputs!$C$42 -> 120 | L16: =IF(AND(Inputs!$C$75="unit",B16<>"",Inputs!$C$77<>"",B16>=Inputs!$C$77,OR(Inputs!$C$78="",B16<=Inputs!$C$78)),1,0) -> 0 | M16: =Inputs!$C$55 -> 1 | N16: =IF(G16>0,1,0) -> 0 | O16: =IF(D16="founding",G16-H16,0) -> 0 | P16: =IF(D16="standard",G16-H16,0) -> 0 | Q16: =O16*(K16*MIN(E16,Inputs!$C$43)+Inputs!$C$45*MAX(E16-Inputs!$C$43,0))+I16*K16*E16 -> 0 | R16: =(P16+H16-I16)*(J16*MIN(E16,Inputs!$C$40)+Inputs!$C$45*MAX(E16-Inputs!$C$40,0)) -> 0 | S16: =Q16+R16 -> 0 | T16: =N16*E16*(Inputs!$C$68+Inputs!$C$69*MAX(G16-1,0)) -> 0 | U16: =IF(N16=0,0,INDEX(Inputs!$C$105:$C$107,MATCH(C16,Inputs!$B$105:$B$107,0))+INDEX(Inputs!$D$105:$D$107,MATCH(C16,Inputs!$B$105:$B$107,0))*E16) -> 0 | V16: =IF(N16=0,0,INDEX(Inputs!$E$105:$E$107,MATCH(C16,Inputs!$B$105:$B$107,0))*E16) -> 0 | W16: =S16*Inputs!$C$54*M16 -> 0 | X16: =N16*L16*Inputs!$C$76/Inputs!$C$85 -> 0 | Y16: =N16*Inputs!$C$79/Inputs!$C$85 -> 0 | Z16: =N16*Inputs!$C$81/Inputs!$C$85 -> 0 | AA16: =SUM(T16:Z16) -> 0 | AB16: =O16*Inputs!$C$89+P16*Inputs!$C$93+H16*Inputs!$C$94 -> 0 | AC16: =N16*(F16*Inputs!$C$95+(E16-F16)*Inputs!$C$96) -> 0 | AD16: =IF(N16=0,0,INDEX(Inputs!$F$105:$F$107,MATCH(C16,Inputs!$B$105:$B$107,0))+Inputs!$C$97*G16) -> 0 | AE16: =IF(N16=0,0,INDEX(Inputs!$G$105:$G$107,MATCH(C16,Inputs!$B$105:$B$107,0))*E16) -> 0 | AF16: =IF(N16=0,0,INDEX(Inputs!$H$105:$H$107,MATCH(C16,Inputs!$B$105:$B$107,0))*E16) -> 0 | AG16: =Inputs!$C$98*G16 -> 0 | AH16: =N16*Inputs!$C$99 -> 0 | AI16: =SUM(AB16:AH16) -> 0 | AJ16: =S16-AA16 -> 0 | AK16: =IF(AI16>0,AJ16/AI16,"n/a") -> n/a | AL16: =T16+U16+V16+W16 -> 0 | AM16: =X16+Y16+Z16 -> 0 | AO16: =IF(OR(N16=0,AP16=0),"",WORKDAY(B16,-Inputs!$C$49,Lists!$N$4:$N$30)+N(Inputs!$C$53)) | AP16: =Q16*Inputs!$C$48 -> 0 | AQ16: =IF(OR(N16=0,AR16=0),"",WORKDAY(B16,-Inputs!$C$51,Lists!$N$4:$N$30)+N(Inputs!$C$53)) | AR16: =R16*Inputs!$C$50 -> 0 | AS16: =IF(OR(N16=0,AT16=0),"",WORKDAY(B16,Inputs!$C$52,Lists!$N$4:$N$30)+N(Inputs!$C$53)) | AT16: =Q16*(1-Inputs!$C$48)+R16*(1-Inputs!$C$50) -> 0 | AU16: =AP16*Inputs!$C$54*M16 -> 0 | AV16: =AR16*Inputs!$C$54*M16 -> 0 | AW16: =AT16*Inputs!$C$54*M16 -> 0 | AX16: =IF(N16=0,"",WORKDAY(B16,-Inputs!$C$74,Lists!$N$4:$N$30)) | AY16: =IF(N16=0,"",B16) | AZ16: =IF(Schedule!N16="Y","Y","N") -> N | BA16: =IF(AZ16="Y",Drop_Actuals!D16,S16) -> 0 | BB16: =IF(AZ16="Y",Drop_Actuals!J16,AA16) -> 0 | BC16: =IF(AZ16="Y",Drop_Actuals!R16,AI16) -> 0 | BD16: =BA16-BB16 -> 0 | BE16: =IF(BC16>0,BD16/BC16,"n/a") -> n/a | BF16: =IF(AND(N16=0,AZ16="N"),"",IF(AZ16="Y","actual","plan")) | BG16: =IF(AND(N16=1,B16>=Inputs!$C$17),1,0) -> 0 | BH16: =IF(AND(AO16<>"",AO16>=Inputs!$C$10,AO16<=Cash_Flow!$AB$6),AP16-AU16,0)+IF(AND(AQ16<>"",AQ16>=Inputs!$C$10,AQ16<=Cash_Flow!$AB$6),AR16-AV16,0)+IF(AND(AS16<>"",AS16>=Inputs!$C$10,AS16<=Cash_Flow!$AB$6),AT16-AW16,0)-IF(AND(AX16<>"",AX16>=Inputs!$C$10,AX16<=Cash_Flow!$AB$6),T16+V16,0)-IF(AND(AY16<>"",AY16>=Inputs!$C$10,AY16<=Cash_Flow!$AB$6),U16,0) -> 0 | BI16: =IF(AZ16="Y",Drop_Actuals!AM16,BH16) -> 0 | BJ16: =IF(BG16=1,B16,"")
A17: =Schedule!A17 -> DRP-011 | B17: =IF(Schedule!E17="","",Schedule!E17) | C17: =IF(Schedule!G17="","",Schedule!G17) | D17: =IF(Schedule!H17="","",Schedule!H17) | E17: =N(Schedule!I17) -> 0 | F17: =N(Schedule!J17) -> 0 | G17: =N(Schedule!K17) -> 0 | H17: =N(Schedule!L17) -> 0 | I17: =N(Schedule!M17) -> 0 | J17: =IF(AND(B17<>"",B17>Inputs!$C$15),Scenarios!$H$14,Inputs!$C$39) -> 150 | K17: =Inputs!$C$42 -> 120 | L17: =IF(AND(Inputs!$C$75="unit",B17<>"",Inputs!$C$77<>"",B17>=Inputs!$C$77,OR(Inputs!$C$78="",B17<=Inputs!$C$78)),1,0) -> 0 | M17: =Inputs!$C$55 -> 1 | N17: =IF(G17>0,1,0) -> 0 | O17: =IF(D17="founding",G17-H17,0) -> 0 | P17: =IF(D17="standard",G17-H17,0) -> 0 | Q17: =O17*(K17*MIN(E17,Inputs!$C$43)+Inputs!$C$45*MAX(E17-Inputs!$C$43,0))+I17*K17*E17 -> 0 | R17: =(P17+H17-I17)*(J17*MIN(E17,Inputs!$C$40)+Inputs!$C$45*MAX(E17-Inputs!$C$40,0)) -> 0 | S17: =Q17+R17 -> 0 | T17: =N17*E17*(Inputs!$C$68+Inputs!$C$69*MAX(G17-1,0)) -> 0 | U17: =IF(N17=0,0,INDEX(Inputs!$C$105:$C$107,MATCH(C17,Inputs!$B$105:$B$107,0))+INDEX(Inputs!$D$105:$D$107,MATCH(C17,Inputs!$B$105:$B$107,0))*E17) -> 0 | V17: =IF(N17=0,0,INDEX(Inputs!$E$105:$E$107,MATCH(C17,Inputs!$B$105:$B$107,0))*E17) -> 0 | W17: =S17*Inputs!$C$54*M17 -> 0 | X17: =N17*L17*Inputs!$C$76/Inputs!$C$85 -> 0 | Y17: =N17*Inputs!$C$79/Inputs!$C$85 -> 0 | Z17: =N17*Inputs!$C$81/Inputs!$C$85 -> 0 | AA17: =SUM(T17:Z17) -> 0 | AB17: =O17*Inputs!$C$89+P17*Inputs!$C$93+H17*Inputs!$C$94 -> 0 | AC17: =N17*(F17*Inputs!$C$95+(E17-F17)*Inputs!$C$96) -> 0 | AD17: =IF(N17=0,0,INDEX(Inputs!$F$105:$F$107,MATCH(C17,Inputs!$B$105:$B$107,0))+Inputs!$C$97*G17) -> 0 | AE17: =IF(N17=0,0,INDEX(Inputs!$G$105:$G$107,MATCH(C17,Inputs!$B$105:$B$107,0))*E17) -> 0 | AF17: =IF(N17=0,0,INDEX(Inputs!$H$105:$H$107,MATCH(C17,Inputs!$B$105:$B$107,0))*E17) -> 0 | AG17: =Inputs!$C$98*G17 -> 0 | AH17: =N17*Inputs!$C$99 -> 0 | AI17: =SUM(AB17:AH17) -> 0 | AJ17: =S17-AA17 -> 0 | AK17: =IF(AI17>0,AJ17/AI17,"n/a") -> n/a | AL17: =T17+U17+V17+W17 -> 0 | AM17: =X17+Y17+Z17 -> 0 | AO17: =IF(OR(N17=0,AP17=0),"",WORKDAY(B17,-Inputs!$C$49,Lists!$N$4:$N$30)+N(Inputs!$C$53)) | AP17: =Q17*Inputs!$C$48 -> 0 | AQ17: =IF(OR(N17=0,AR17=0),"",WORKDAY(B17,-Inputs!$C$51,Lists!$N$4:$N$30)+N(Inputs!$C$53)) | AR17: =R17*Inputs!$C$50 -> 0 | AS17: =IF(OR(N17=0,AT17=0),"",WORKDAY(B17,Inputs!$C$52,Lists!$N$4:$N$30)+N(Inputs!$C$53)) | AT17: =Q17*(1-Inputs!$C$48)+R17*(1-Inputs!$C$50) -> 0 | AU17: =AP17*Inputs!$C$54*M17 -> 0 | AV17: =AR17*Inputs!$C$54*M17 -> 0 | AW17: =AT17*Inputs!$C$54*M17 -> 0 | AX17: =IF(N17=0,"",WORKDAY(B17,-Inputs!$C$74,Lists!$N$4:$N$30)) | AY17: =IF(N17=0,"",B17) | AZ17: =IF(Schedule!N17="Y","Y","N") -> N | BA17: =IF(AZ17="Y",Drop_Actuals!D17,S17) -> 0 | BB17: =IF(AZ17="Y",Drop_Actuals!J17,AA17) -> 0 | BC17: =IF(AZ17="Y",Drop_Actuals!R17,AI17) -> 0 | BD17: =BA17-BB17 -> 0 | BE17: =IF(BC17>0,BD17/BC17,"n/a") -> n/a | BF17: =IF(AND(N17=0,AZ17="N"),"",IF(AZ17="Y","actual","plan")) | BG17: =IF(AND(N17=1,B17>=Inputs!$C$17),1,0) -> 0 | BH17: =IF(AND(AO17<>"",AO17>=Inputs!$C$10,AO17<=Cash_Flow!$AB$6),AP17-AU17,0)+IF(AND(AQ17<>"",AQ17>=Inputs!$C$10,AQ17<=Cash_Flow!$AB$6),AR17-AV17,0)+IF(AND(AS17<>"",AS17>=Inputs!$C$10,AS17<=Cash_Flow!$AB$6),AT17-AW17,0)-IF(AND(AX17<>"",AX17>=Inputs!$C$10,AX17<=Cash_Flow!$AB$6),T17+V17,0)-IF(AND(AY17<>"",AY17>=Inputs!$C$10,AY17<=Cash_Flow!$AB$6),U17,0) -> 0 | BI17: =IF(AZ17="Y",Drop_Actuals!AM17,BH17) -> 0 | BJ17: =IF(BG17=1,B17,"")
A18: =Schedule!A18 -> DRP-012 | B18: =IF(Schedule!E18="","",Schedule!E18) | C18: =IF(Schedule!G18="","",Schedule!G18) | D18: =IF(Schedule!H18="","",Schedule!H18) | E18: =N(Schedule!I18) -> 0 | F18: =N(Schedule!J18) -> 0 | G18: =N(Schedule!K18) -> 0 | H18: =N(Schedule!L18) -> 0 | I18: =N(Schedule!M18) -> 0 | J18: =IF(AND(B18<>"",B18>Inputs!$C$15),Scenarios!$H$14,Inputs!$C$39) -> 150 | K18: =Inputs!$C$42 -> 120 | L18: =IF(AND(Inputs!$C$75="unit",B18<>"",Inputs!$C$77<>"",B18>=Inputs!$C$77,OR(Inputs!$C$78="",B18<=Inputs!$C$78)),1,0) -> 0 | M18: =Inputs!$C$55 -> 1 | N18: =IF(G18>0,1,0) -> 0 | O18: =IF(D18="founding",G18-H18,0) -> 0 | P18: =IF(D18="standard",G18-H18,0) -> 0 | Q18: =O18*(K18*MIN(E18,Inputs!$C$43)+Inputs!$C$45*MAX(E18-Inputs!$C$43,0))+I18*K18*E18 -> 0 | R18: =(P18+H18-I18)*(J18*MIN(E18,Inputs!$C$40)+Inputs!$C$45*MAX(E18-Inputs!$C$40,0)) -> 0 | S18: =Q18+R18 -> 0 | T18: =N18*E18*(Inputs!$C$68+Inputs!$C$69*MAX(G18-1,0)) -> 0 | U18: =IF(N18=0,0,INDEX(Inputs!$C$105:$C$107,MATCH(C18,Inputs!$B$105:$B$107,0))+INDEX(Inputs!$D$105:$D$107,MATCH(C18,Inputs!$B$105:$B$107,0))*E18) -> 0 | V18: =IF(N18=0,0,INDEX(Inputs!$E$105:$E$107,MATCH(C18,Inputs!$B$105:$B$107,0))*E18) -> 0 | W18: =S18*Inputs!$C$54*M18 -> 0 | X18: =N18*L18*Inputs!$C$76/Inputs!$C$85 -> 0 | Y18: =N18*Inputs!$C$79/Inputs!$C$85 -> 0 | Z18: =N18*Inputs!$C$81/Inputs!$C$85 -> 0 | AA18: =SUM(T18:Z18) -> 0 | AB18: =O18*Inputs!$C$89+P18*Inputs!$C$93+H18*Inputs!$C$94 -> 0 | AC18: =N18*(F18*Inputs!$C$95+(E18-F18)*Inputs!$C$96) -> 0 | AD18: =IF(N18=0,0,INDEX(Inputs!$F$105:$F$107,MATCH(C18,Inputs!$B$105:$B$107,0))+Inputs!$C$97*G18) -> 0 | AE18: =IF(N18=0,0,INDEX(Inputs!$G$105:$G$107,MATCH(C18,Inputs!$B$105:$B$107,0))*E18) -> 0 | AF18: =IF(N18=0,0,INDEX(Inputs!$H$105:$H$107,MATCH(C18,Inputs!$B$105:$B$107,0))*E18) -> 0 | AG18: =Inputs!$C$98*G18 -> 0 | AH18: =N18*Inputs!$C$99 -> 0 | AI18: =SUM(AB18:AH18) -> 0 | AJ18: =S18-AA18 -> 0 | AK18: =IF(AI18>0,AJ18/AI18,"n/a") -> n/a | AL18: =T18+U18+V18+W18 -> 0 | AM18: =X18+Y18+Z18 -> 0 | AO18: =IF(OR(N18=0,AP18=0),"",WORKDAY(B18,-Inputs!$C$49,Lists!$N$4:$N$30)+N(Inputs!$C$53)) | AP18: =Q18*Inputs!$C$48 -> 0 | AQ18: =IF(OR(N18=0,AR18=0),"",WORKDAY(B18,-Inputs!$C$51,Lists!$N$4:$N$30)+N(Inputs!$C$53)) | AR18: =R18*Inputs!$C$50 -> 0 | AS18: =IF(OR(N18=0,AT18=0),"",WORKDAY(B18,Inputs!$C$52,Lists!$N$4:$N$30)+N(Inputs!$C$53)) | AT18: =Q18*(1-Inputs!$C$48)+R18*(1-Inputs!$C$50) -> 0 | AU18: =AP18*Inputs!$C$54*M18 -> 0 | AV18: =AR18*Inputs!$C$54*M18 -> 0 | AW18: =AT18*Inputs!$C$54*M18 -> 0 | AX18: =IF(N18=0,"",WORKDAY(B18,-Inputs!$C$74,Lists!$N$4:$N$30)) | AY18: =IF(N18=0,"",B18) | AZ18: =IF(Schedule!N18="Y","Y","N") -> N | BA18: =IF(AZ18="Y",Drop_Actuals!D18,S18) -> 0 | BB18: =IF(AZ18="Y",Drop_Actuals!J18,AA18) -> 0 | BC18: =IF(AZ18="Y",Drop_Actuals!R18,AI18) -> 0 | BD18: =BA18-BB18 -> 0 | BE18: =IF(BC18>0,BD18/BC18,"n/a") -> n/a | BF18: =IF(AND(N18=0,AZ18="N"),"",IF(AZ18="Y","actual","plan")) | BG18: =IF(AND(N18=1,B18>=Inputs!$C$17),1,0) -> 0 | BH18: =IF(AND(AO18<>"",AO18>=Inputs!$C$10,AO18<=Cash_Flow!$AB$6),AP18-AU18,0)+IF(AND(AQ18<>"",AQ18>=Inputs!$C$10,AQ18<=Cash_Flow!$AB$6),AR18-AV18,0)+IF(AND(AS18<>"",AS18>=Inputs!$C$10,AS18<=Cash_Flow!$AB$6),AT18-AW18,0)-IF(AND(AX18<>"",AX18>=Inputs!$C$10,AX18<=Cash_Flow!$AB$6),T18+V18,0)-IF(AND(AY18<>"",AY18>=Inputs!$C$10,AY18<=Cash_Flow!$AB$6),U18,0) -> 0 | BI18: =IF(AZ18="Y",Drop_Actuals!AM18,BH18) -> 0 | BJ18: =IF(BG18=1,B18,"")
A19: Totals (all scheduled drops) | E19: =SUM(E7:E18) -> 45 | F19: =SUM(F7:F18) -> 12 | G19: =SUM(G7:G18) -> 14 | H19: =SUM(H7:H18) -> 2 | S19: =SUM(S7:S18) -> 19200 | T19: =SUM(T7:T18) -> 360 | U19: =SUM(U7:U18) -> 720 | V19: =SUM(V7:V18) -> 0 | W19: =SUM(W7:W18) -> 576 | X19: =SUM(X7:X18) -> 300 | Y19: =SUM(Y7:Y18) -> 150 | Z19: =SUM(Z7:Z18) -> 250 | ... AJ19: =SUM(AJ7:AJ18) -> 16844 | AK19: =IF(AI19>0,AJ19/AI19,"n/a") -> 63.80303 | AL19: =SUM(AL7:AL18) -> 1656 | AM19: =SUM(AM7:AM18) -> 700 | AP19: =SUM(AP7:AP18) -> 1200 | AR19: =SUM(AR7:AR18) -> 9000 | AT19: =SUM(AT7:AT18) -> 9000 | AU19: =SUM(AU7:AU18) -> 36 | AV19: =SUM(AV7:AV18) -> 270 | AW19: =SUM(AW7:AW18) -> 270 | BA19: =SUM(BA7:BA18) -> 19080 | BB19: =SUM(BB7:BB18) -> 2312 | BC19: =SUM(BC7:BC18) -> 264 | BD19: =SUM(BD7:BD18) -> 16768 | BE19: =IF(BC19>0,BD19/BC19,"n/a") -> 63.515152 | BH19: =SUM(BH7:BH18) -> 17544 | BI19: =SUM(BI7:BI18) -> 17468

Sheet Cash_Flow
A1: Six-month cash flow, weekly
A2: Startup outlays at their timing, brand cash on the plan's terms, overhead paid once from Cash_Ledger. Outflows are negative.
A3: Planning estimates, not a forecast. Drops switch to actual cash when Schedule says Actuals in = Y.
B4: Week | C4: 1 | D4: 2 | E4: 3 | F4: 4 | G4: 5 | H4: 6 | I4: 7 | J4: 8 | K4: 9 | L4: 10 | M4: 11 | N4: 12 | O4: 13 | P4: 14 | Q4: 15 | R4: 16 | S4: 17 | T4: 18 | U4: 19 | V4: 20 | W4: 21 | X4: 22 | Y4: 23 | Z4: 24 | AA4: 25 | AB4: 26 | AC4: Six months
B5: Week starts | C5: =Inputs!$C$10 -> 46321 | D5: =C5+Inputs!$C$18 -> 46328 | E5: =D5+Inputs!$C$18 -> 46335 | F5: =E5+Inputs!$C$18 -> 46342 | G5: =F5+Inputs!$C$18 -> 46349 | H5: =G5+Inputs!$C$18 -> 46356 | I5: =H5+Inputs!$C$18 -> 46363 | J5: =I5+Inputs!$C$18 -> 46370 | K5: =J5+Inputs!$C$18 -> 46377 | ... AB5: =AA5+Inputs!$C$18 -> 46496
B6: Week ends | C6: =C5+Inputs!$C$18-1 -> 46327 | D6: =D5+Inputs!$C$18-1 -> 46334 | E6: =E5+Inputs!$C$18-1 -> 46341 | F6: =F5+Inputs!$C$18-1 -> 46348 | G6: =G5+Inputs!$C$18-1 -> 46355 | H6: =H5+Inputs!$C$18-1 -> 46362 | I6: =I5+Inputs!$C$18-1 -> 46369 | J6: =J5+Inputs!$C$18-1 -> 46376 | ... AB6: =AB5+Inputs!$C$18-1 -> 46502
B7: Month | C7: =TEXT(C5,"mmm yyyy") -> Oct 2026 | D7: =TEXT(D5,"mmm yyyy") -> Nov 2026 | E7: =TEXT(E5,"mmm yyyy") -> Nov 2026 | F7: =TEXT(F5,"mmm yyyy") -> Nov 2026 | G7: =TEXT(G5,"mmm yyyy") -> Nov 2026 | H7: =TEXT(H5,"mmm yyyy") -> Nov 2026 | I7: =TEXT(I5,"mmm yyyy") -> Dec 2026 | J7: =TEXT(J5,"mmm yyyy") -> Dec 2026 | ... AB7: =TEXT(AB5,"mmm yyyy") -> Apr 2027
A8: Receipts
B9: Brand receipts, plan (drops without actuals) | C9: =SUMIFS(Drop_PnL!$AP$7:$AP$18,Drop_PnL!$AO$7:$AO$18,">="&C$5,Drop_PnL!$AO$7:$AO$18,"<="&C$6,Drop_PnL!$AZ$7:$AZ$18,"N")+SUMIFS(Drop_PnL!$AR$7:$AR$18,Drop_PnL!$AQ$7:$AQ$18,">="&C$5,Drop_PnL!$AQ$7:$AQ$18,"<="&C$6,Drop_PnL!$AZ$7:$AZ$18,"N")+SUMIFS(Drop_PnL!$AT$7:$AT$18,Drop_PnL!$AS$7:$AS$18,">="&C$5,Drop_PnL!$AS$7:$AS$18,"<="&C$6,Drop_PnL!$AZ$7:$AZ$18,"N") -> 0 | D9: =SUMIFS(Drop_PnL!$AP$7:$AP$18,Drop_PnL!$AO$7:$AO$18,">="&D$5,Drop_PnL!$AO$7:$AO$18,"<="&D$6,Drop_PnL!$AZ$7:$AZ$18,"N")+SUMIFS(Drop_PnL!$AR$7:$AR$18,Drop_PnL!$AQ$7:$AQ$18,">="&D$5,Drop_PnL!$AQ$7:$AQ$18,"<="&D$6,Drop_PnL!$AZ$7:$AZ$18,"N")+SUMIFS(Drop_PnL!$AT$7:$AT$18,Drop_PnL!$AS$7:$AS$18,">="&D$5,Drop_PnL!$AS$7:$AS$18,"<="&D$6,Drop_PnL!$AZ$7:$AZ$18,"N") -> 0 | E9: =SUMIFS(Drop_PnL!$AP$7:$AP$18,Drop_PnL!$AO$7:$AO$18,">="&E$5,Drop_PnL!$AO$7:$AO$18,"<="&E$6,Drop_PnL!$AZ$7:$AZ$18,"N")+SUMIFS(Drop_PnL!$AR$7:$AR$18,Drop_PnL!$AQ$7:$AQ$18,">="&E$5,Drop_PnL!$AQ$7:$AQ$18,"<="&E$6,Drop_PnL!$AZ$7:$AZ$18,"N")+SUMIFS(Drop_PnL!$AT$7:$AT$18,Drop_PnL!$AS$7:$AS$18,">="&E$5,Drop_PnL!$AS$7:$AS$18,"<="&E$6,Drop_PnL!$AZ$7:$AZ$18,"N") -> 0 | F9: =SUMIFS(Drop_PnL!$AP$7:$AP$18,Drop_PnL!$AO$7:$AO$18,">="&F$5,Drop_PnL!$AO$7:$AO$18,"<="&F$6,Drop_PnL!$AZ$7:$AZ$18,"N")+SUMIFS(Drop_PnL!$AR$7:$AR$18,Drop_PnL!$AQ$7:$AQ$18,">="&F$5,Drop_PnL!$AQ$7:$AQ$18,"<="&F$6,Drop_PnL!$AZ$7:$AZ$18,"N")+SUMIFS(Drop_PnL!$AT$7:$AT$18,Drop_PnL!$AS$7:$AS$18,">="&F$5,Drop_PnL!$AS$7:$AS$18,"<="&F$6,Drop_PnL!$AZ$7:$AZ$18,"N") -> 0 | G9: =SUMIFS(Drop_PnL!$AP$7:$AP$18,Drop_PnL!$AO$7:$AO$18,">="&G$5,Drop_PnL!$AO$7:$AO$18,"<="&G$6,Drop_PnL!$AZ$7:$AZ$18,"N")+SUMIFS(Drop_PnL!$AR$7:$AR$18,Drop_PnL!$AQ$7:$AQ$18,">="&G$5,Drop_PnL!$AQ$7:$AQ$18,"<="&G$6,Drop_PnL!$AZ$7:$AZ$18,"N")+SUMIFS(Drop_PnL!$AT$7:$AT$18,Drop_PnL!$AS$7:$AS$18,">="&G$5,Drop_PnL!$AS$7:$AS$18,"<="&G$6,Drop_PnL!$AZ$7:$AZ$18,"N") -> 0 | H9: =SUMIFS(Drop_PnL!$AP$7:$AP$18,Drop_PnL!$AO$7:$AO$18,">="&H$5,Drop_PnL!$AO$7:$AO$18,"<="&H$6,Drop_PnL!$AZ$7:$AZ$18,"N")+SUMIFS(Drop_PnL!$AR$7:$AR$18,Drop_PnL!$AQ$7:$AQ$18,">="&H$5,Drop_PnL!$AQ$7:$AQ$18,"<="&H$6,Drop_PnL!$AZ$7:$AZ$18,"N")+SUMIFS(Drop_PnL!$AT$7:$AT$18,Drop_PnL!$AS$7:$AS$18,">="&H$5,Drop_PnL!$AS$7:$AS$18,"<="&H$6,Drop_PnL!$AZ$7:$AZ$18,"N") -> 0 | I9: =SUMIFS(Drop_PnL!$AP$7:$AP$18,Drop_PnL!$AO$7:$AO$18,">="&I$5,Drop_PnL!$AO$7:$AO$18,"<="&I$6,Drop_PnL!$AZ$7:$AZ$18,"N")+SUMIFS(Drop_PnL!$AR$7:$AR$18,Drop_PnL!$AQ$7:$AQ$18,">="&I$5,Drop_PnL!$AQ$7:$AQ$18,"<="&I$6,Drop_PnL!$AZ$7:$AZ$18,"N")+SUMIFS(Drop_PnL!$AT$7:$AT$18,Drop_PnL!$AS$7:$AS$18,">="&I$5,Drop_PnL!$AS$7:$AS$18,"<="&I$6,Drop_PnL!$AZ$7:$AZ$18,"N") -> 0 | J9: =SUMIFS(Drop_PnL!$AP$7:$AP$18,Drop_PnL!$AO$7:$AO$18,">="&J$5,Drop_PnL!$AO$7:$AO$18,"<="&J$6,Drop_PnL!$AZ$7:$AZ$18,"N")+SUMIFS(Drop_PnL!$AR$7:$AR$18,Drop_PnL!$AQ$7:$AQ$18,">="&J$5,Drop_PnL!$AQ$7:$AQ$18,"<="&J$6,Drop_PnL!$AZ$7:$AZ$18,"N")+SUMIFS(Drop_PnL!$AT$7:$AT$18,Drop_PnL!$AS$7:$AS$18,">="&J$5,Drop_PnL!$AS$7:$AS$18,"<="&J$6,Drop_PnL!$AZ$7:$AZ$18,"N") -> 0 | ... AB9: =SUMIFS(Drop_PnL!$AP$7:$AP$18,Drop_PnL!$AO$7:$AO$18,">="&AB$5,Drop_PnL!$AO$7:$AO$18,"<="&AB$6,Drop_PnL!$AZ$7:$AZ$18,"N")+SUMIFS(Drop_PnL!$AR$7:$AR$18,Drop_PnL!$AQ$7:$AQ$18,">="&AB$5,Drop_PnL!$AQ$7:$AQ$18,"<="&AB$6,Drop_PnL!$AZ$7:$AZ$18,"N")+SUMIFS(Drop_PnL!$AT$7:$AT$18,Drop_PnL!$AS$7:$AS$18,">="&AB$5,Drop_PnL!$AS$7:$AS$18,"<="&AB$6,Drop_PnL!$AZ$7:$AZ$18,"N") -> 0 | AC9: =SUM(C9:AB9) -> 18000
B10: Brand receipts, actual (drops with actuals) | C10: =SUMIFS(Actuals_Campaigns!$X$5:$X$204,Actuals_Campaigns!$Y$5:$Y$204,">="&C$5,Actuals_Campaigns!$Y$5:$Y$204,"<="&C$6,Actuals_Campaigns!$AL$5:$AL$204,"Y")+SUMIFS(Actuals_Campaigns!$AM$5:$AM$204,Actuals_Campaigns!$S$5:$S$204,">="&C$5,Actuals_Campaigns!$S$5:$S$204,"<="&C$6,Actuals_Campaigns!$AL$5:$AL$204,"Y") -> 0 | D10: =SUMIFS(Actuals_Campaigns!$X$5:$X$204,Actuals_Campaigns!$Y$5:$Y$204,">="&D$5,Actuals_Campaigns!$Y$5:$Y$204,"<="&D$6,Actuals_Campaigns!$AL$5:$AL$204,"Y")+SUMIFS(Actuals_Campaigns!$AM$5:$AM$204,Actuals_Campaigns!$S$5:$S$204,">="&D$5,Actuals_Campaigns!$S$5:$S$204,"<="&D$6,Actuals_Campaigns!$AL$5:$AL$204,"Y") -> 0 | E10: =SUMIFS(Actuals_Campaigns!$X$5:$X$204,Actuals_Campaigns!$Y$5:$Y$204,">="&E$5,Actuals_Campaigns!$Y$5:$Y$204,"<="&E$6,Actuals_Campaigns!$AL$5:$AL$204,"Y")+SUMIFS(Actuals_Campaigns!$AM$5:$AM$204,Actuals_Campaigns!$S$5:$S$204,">="&E$5,Actuals_Campaigns!$S$5:$S$204,"<="&E$6,Actuals_Campaigns!$AL$5:$AL$204,"Y") -> 0 | F10: =SUMIFS(Actuals_Campaigns!$X$5:$X$204,Actuals_Campaigns!$Y$5:$Y$204,">="&F$5,Actuals_Campaigns!$Y$5:$Y$204,"<="&F$6,Actuals_Campaigns!$AL$5:$AL$204,"Y")+SUMIFS(Actuals_Campaigns!$AM$5:$AM$204,Actuals_Campaigns!$S$5:$S$204,">="&F$5,Actuals_Campaigns!$S$5:$S$204,"<="&F$6,Actuals_Campaigns!$AL$5:$AL$204,"Y") -> 0 | G10: =SUMIFS(Actuals_Campaigns!$X$5:$X$204,Actuals_Campaigns!$Y$5:$Y$204,">="&G$5,Actuals_Campaigns!$Y$5:$Y$204,"<="&G$6,Actuals_Campaigns!$AL$5:$AL$204,"Y")+SUMIFS(Actuals_Campaigns!$AM$5:$AM$204,Actuals_Campaigns!$S$5:$S$204,">="&G$5,Actuals_Campaigns!$S$5:$S$204,"<="&G$6,Actuals_Campaigns!$AL$5:$AL$204,"Y") -> 0 | H10: =SUMIFS(Actuals_Campaigns!$X$5:$X$204,Actuals_Campaigns!$Y$5:$Y$204,">="&H$5,Actuals_Campaigns!$Y$5:$Y$204,"<="&H$6,Actuals_Campaigns!$AL$5:$AL$204,"Y")+SUMIFS(Actuals_Campaigns!$AM$5:$AM$204,Actuals_Campaigns!$S$5:$S$204,">="&H$5,Actuals_Campaigns!$S$5:$S$204,"<="&H$6,Actuals_Campaigns!$AL$5:$AL$204,"Y") -> 0 | I10: =SUMIFS(Actuals_Campaigns!$X$5:$X$204,Actuals_Campaigns!$Y$5:$Y$204,">="&I$5,Actuals_Campaigns!$Y$5:$Y$204,"<="&I$6,Actuals_Campaigns!$AL$5:$AL$204,"Y")+SUMIFS(Actuals_Campaigns!$AM$5:$AM$204,Actuals_Campaigns!$S$5:$S$204,">="&I$5,Actuals_Campaigns!$S$5:$S$204,"<="&I$6,Actuals_Campaigns!$AL$5:$AL$204,"Y") -> 1080 | J10: =SUMIFS(Actuals_Campaigns!$X$5:$X$204,Actuals_Campaigns!$Y$5:$Y$204,">="&J$5,Actuals_Campaigns!$Y$5:$Y$204,"<="&J$6,Actuals_Campaigns!$AL$5:$AL$204,"Y")+SUMIFS(Actuals_Campaigns!$AM$5:$AM$204,Actuals_Campaigns!$S$5:$S$204,">="&J$5,Actuals_Campaigns!$S$5:$S$204,"<="&J$6,Actuals_Campaigns!$AL$5:$AL$204,"Y") -> 0 | ... AB10: =SUMIFS(Actuals_Campaigns!$X$5:$X$204,Actuals_Campaigns!$Y$5:$Y$204,">="&AB$5,Actuals_Campaigns!$Y$5:$Y$204,"<="&AB$6,Actuals_Campaigns!$AL$5:$AL$204,"Y")+SUMIFS(Actuals_Campaigns!$AM$5:$AM$204,Actuals_Campaigns!$S$5:$S$204,">="&AB$5,Actuals_Campaigns!$S$5:$S$204,"<="&AB$6,Actuals_Campaigns!$AL$5:$AL$204,"Y") -> 0 | AC10: =SUM(C10:AB10) -> 1080
B11: Total receipts | C11: =SUM(C9:C10) -> 0 | D11: =SUM(D9:D10) -> 0 | E11: =SUM(E9:E10) -> 0 | F11: =SUM(F9:F10) -> 0 | G11: =SUM(G9:G10) -> 0 | H11: =SUM(H9:H10) -> 0 | I11: =SUM(I9:I10) -> 1080 | J11: =SUM(J9:J10) -> 0 | ... AB11: =SUM(AB9:AB10) -> 0 | AC11: =SUM(C11:AB11) -> 19080
