Workbook

Sheet README
A1: ="Campaign tracker · "&config!$B$2 -> Campaign tracker · Desk Drop
A2: Every number in a brand report comes from a row in this file or a photo. Type only in white cells. Grey cells are formulas: never type over them. Cream tabs are written by forms, scripts or a pasted file.
A3: Rename: change config!B2 (company_name). Nothing else in this file holds the name. The printed pieces take it from desk-drop-identity/brand.json: change both the same day; every tool refuses while they differ (README, Rename).
A5: Tabs in the order a campaign touches them
A6: office_intake, brand_intake: website form rows (CONTRACTS 6.3), written by the website's script when it is bound to this file.
A7: office_form, brand_form: the founder-side Google Forms' response tabs; office_intake_founder, brand_intake_founder turn them into the same 6.3 columns.
A8: in_signed_offices: paste E's signed_offices.csv. offices: type the office_id; the rest fills by header name.
A9: brands: type brand_id and intake_key (the brand's submitted_at); the seven checks fill in. in_paid_brands: paste E's paid_brands.csv to check it.
A10: drops: one row per route. The date is refused unless it is a Tuesday or Wednesday business day with a window clear of blackouts.
A11: campaigns: one row per brand per drop: terms, card text, survey links, report inputs, and every ladder number.
A12: invoices: issue, then log paid_date. The ship date is released only when the pre-ship payment is in, the agreement is signed, the certificate checked and the offices approved.
A13: approvals: one row per office per campaign: the office's yes, its units, and its whole ladder (formulas).
A14: stops: one row per office per drop: the route.
... A29: Google Sheets: File > Settings > Locale United States, Time zone America/New_York.

Sheet dashboard
A1: ="Campaign tracker · "&config!$B$2 -> Campaign tracker · Desk Drop
A2: =IF(COUNTIF(campaigns!$A$2:$A$51,"SAMPLE*")+COUNTIF(drops!$A$2:$A$21,"SAMPLE*")>0,"SAMPLE DATA. Illustrative placeholders, not results.","") -> SAMPLE DATA. Illustrative placeholders, not results.
A3: Today | B3: =IF(config!$B$37<>"",config!$B$37,TODAY()) -> 46468
A5: Checks to fix (0 everywhere = nothing to fix; lines starting info: are facts, not counted)
A6: check | B6: count | C6: where to look
A7: Drops with a refused date | B7: =IFERROR(COUNTIF(drops!$I$2:$I$21,"REFUSED*"),0) -> 0 | C7: drops, date_check
A8: Campaigns with checks to read | B8: =IFERROR(COUNTIF(campaigns!$DV$2:$DV$51,"?*")-COUNTIF(campaigns!$DV$2:$DV$51,"info:*"),0) -> 0 | C8: campaigns, checks
A9: Campaigns on ship HOLD | B9: =IFERROR(COUNTIF(campaigns!$BW$2:$BW$51,"HOLD*"),0) -> 0 | C9: campaigns, ship_release
A10: Office rows with checks | B10: =IFERROR(COUNTIF(approvals!$AP$2:$AP$251,"?*")-COUNTIF(approvals!$AP$2:$AP$251,"info:*"),0) -> 0 | C10: approvals, checks
A11: Stops with checks | B11: =IFERROR(COUNTIF(stops!$AD$2:$AD$151,"?*")-COUNTIF(stops!$AD$2:$AD$151,"info:*"),0) -> 0 | C11: stops, checks
A12: Inventory rows with checks | B12: =IFERROR(COUNTIF(inventory!$Q$2:$Q$801,"?*")-COUNTIF(inventory!$Q$2:$Q$801,"info:*"),0) -> 0 | C12: inventory, checks
A13: Count rows with checks | B13: =IFERROR(COUNTIF(counts!$K$2:$K$701,"?*")-COUNTIF(counts!$K$2:$K$701,"info:*"),0) -> 0 | C13: counts, checks
A14: Photo rows with checks | B14: =IFERROR(COUNTIF(photos!$Q$2:$Q$701,"?*")-COUNTIF(photos!$Q$2:$Q$701,"info:*"),0) -> 0 | C14: photos, checks
A15: Link rows with checks | B15: =IFERROR(COUNTIF(links!$I$2:$I$501,"?*")-COUNTIF(links!$I$2:$I$501,"info:*"),0) -> 0 | C15: links, checks
A16: Scan readings with checks | B16: =IFERROR(COUNTIF(scans!$J$2:$J$1601,"?*")-COUNTIF(scans!$J$2:$J$1601,"info:*"),0) -> 0 | C16: scans, checks
A17: Issues open | B17: =IFERROR(SUMPRODUCT((LEN(issues!$A$2:$A$121)>0)*(LEN(issues!$L$2:$L$121)=0)),0) -> 0 | C17: issues
A18: Issue rows with checks | B18: =IFERROR(COUNTIF(issues!$O$2:$O$121,"?*")-COUNTIF(issues!$O$2:$O$121,"info:*"),0) -> 0 | C18: issues, checks
A19: Hours rows with checks | B19: =IFERROR(COUNTIF(hours!$G$2:$G$1501,"?*")-COUNTIF(hours!$G$2:$G$1501,"info:*"),0) -> 0 | C19: hours, checks
A20: Cost rows with checks | B20: =IFERROR(COUNTIF(costs!$I$2:$I$301,"?*")-COUNTIF(costs!$I$2:$I$301,"info:*"),0) -> 0 | C20: costs, checks
A21: Invoices overdue | B21: =IFERROR(COUNTIF(invoices!$Q$2:$Q$151,"overdue"),0) -> 0 | C21: invoices, status
A22: Invoice rows with checks | B22: =IFERROR(COUNTIF(invoices!$S$2:$S$151,"?*")-COUNTIF(invoices!$S$2:$S$151,"info:*"),0) -> 0 | C22: invoices, checks
A23: Brands in E's paid_brands.csv not on brands | B23: =IFERROR(SUMPRODUCT((in_paid_brands!$A$2:$A$81<>"")*(COUNTIF(brands!$A$2:$A$41,INDEX(in_paid_brands!$A$2:$BZ$81,0,MATCH("brand_id",in_paid_brands!$A$1:$BZ$1,0)))=0)),0) -> 0 | C23: in_paid_brands
A24: Offices in E's signed_offices.csv not on offices | B24: =IFERROR(SUMPRODUCT((in_signed_offices!$A$2:$A$81<>"")*(COUNTIF(offices!$A$2:$A$61,INDEX(in_signed_offices!$A$2:$BZ$81,0,MATCH("office_id",in_signed_offices!$A$1:$BZ$1,0)))=0)),0) -> 0 | C24: in_signed_offices
A25: Offices that left: contact details past their keep date | B25: =IFERROR(SUMPRODUCT((offices!$K$2:$K$61="left")*ISNUMBER(offices!$L$2:$L$61)*((IF(config!$B$37<>"",config!$B$37,TODAY())-offices!$L$2:$L$61)>config!$B$42)*((LEN(offices!$S$2:$S$61)+LEN(offices!$U$2:$U$61)+LEN(offices!$V$2:$V$61)+LEN(offices!$AJ$2:$AJ$61))>0)),0) -> 0 | C25: offices: clear names, emails, phones in in_signed_offices, office_intake, office_form
A26: Brands whose payments in E's paid_brands.csv differ from the invoices tab | B26: =IFERROR(COUNTIF(brands!$AJ$2:$AJ$41,"?*"),0) -> 0 | C26: brands, e_payment_check (E's file feeds the financial model's Pipeline; the invoices tab releases the ship date)
A27: Tabs over 90% full (rows below the last formula row are not counted) | B27: =IFERROR((COUNTA(drops!$A:$A)-1>0.9*20)+(COUNTA(brands!$A:$A)-1>0.9*40)+(COUNTA(offices!$A:$A)-1>0.9*60)+(COUNTA(campaigns!$A:$A)-1>0.9*50)+(COUNTA(approvals!$A:$A)-1>0.9*250)+(COUNTA(stops!$A:$A)-1>0.9*150)+(COUNTA(inventory!$A:$A)-1>0.9*800)+(COUNTA(counts!$A:$A)-1>0.9*700)+(COUNTA(photos!$A:$A)-1>0.9*700)+(COUNTA(scans!$A:$A)-1>0.9*1600)+(COUNTA(redemptions!$A:$A)-1>0.9*120)+(COUNTA(issues!$A:$A)-1>0.9*120)+(COUNTA(hours!$A:$A)-1>0.9*1500)+(COUNTA(costs!$A:$A)-1>0.9*300)+(COUNTA(invoices!$A:$A)-1>0.9*150)+(COUNTA(INDIRECT("office_form!A:A"))-1>0.9*80)+(COUNTA(INDIRECT("brand_form!A:A"))-1>0.9*80)+(COUNTA(in_signed_offices!$A:$A)-1>0.9*80)+(COUNTA(in_paid_brands!$A:$A)-1>0.9*80)+(COUNTA(office_intake!$A:$A)-1>0.9*400)+(COUNTA(brand_intake!$A:$A)-1>0.9*400)+(COUNTA(survey_frozen!$A:$A)-1>0.9*250),0) -> 0 | C27: runbook, 'Speed and size': rebuild with tools/build_tracker.py --size full before a tab runs out
A28: Offices with roster checks (declined twice, coworking, outside the boundary) | B28: =IFERROR(COUNTIF(offices!$AR$2:$AR$61,"?*")-COUNTIF(offices!$AR$2:$AR$61,"info:*"),0) -> 0 | C28: offices, checks (review round 2)
A30: Drops
A31: drop | B31: date | C31: model | D31: status | E31: date check | F31: next step | G31: on | H31: stops | I31: brands | J31: units | K31: revenue | L31: direct cost | M31: cost per stop | N31: founder hours | O31: contribution before overhead | P31: per founder hour, before overhead | Q31: G2 placed in 1 bd | R31: G2 fewest responses | S31: G2 reports late | T31: G2 buy again
A32: =IF(INDEX(drops!$A$2:$A$21,1)="","",INDEX(drops!$A$2:$A$21,1)) -> SAMPLE-DRP-001 | B32: =IF(INDEX(drops!$A$2:$A$21,1)="","",INDEX(drops!$B$2:$B$21,1)) -> 46399 | C32: =IF(INDEX(drops!$A$2:$A$21,1)="","",INDEX(drops!$C$2:$C$21,1)) -> founder | D32: =IF(INDEX(drops!$A$2:$A$21,1)="","",INDEX(drops!$D$2:$D$21,1)) -> confirmed | E32: =IF(INDEX(drops!$A$2:$A$21,1)="","",INDEX(drops!$I$2:$I$21,1)) -> OK | F32: =IF(INDEX(drops!$A$2:$A$21,1)="","",INDEX(drops!$X$2:$X$21,1)) -> done | G32: =IF(INDEX(drops!$A$2:$A$21,1)="","",INDEX(drops!$Y$2:$Y$21,1)) | H32: =IF(INDEX(drops!$A$2:$A$21,1)="","",INDEX(drops!$AA$2:$AA$21,1)) -> 5 | I32: =IF(INDEX(drops!$A$2:$A$21,1)="","",INDEX(drops!$Z$2:$Z$21,1)) -> 2 | J32: =IF(INDEX(drops!$A$2:$A$21,1)="","",INDEX(drops!$AB$2:$AB$21,1)) -> 500 | K32: =IF(INDEX(drops!$A$2:$A$21,1)="","",INDEX(drops!$AC$2:$AC$21,1)) -> 1080 | L32: =IF(INDEX(drops!$A$2:$A$21,1)="","",INDEX(drops!$AG$2:$AG$21,1)) -> 152 | M32: =IF(INDEX(drops!$A$2:$A$21,1)="","",INDEX(drops!$AH$2:$AH$21,1)) -> 30.4 | N32: =IF(INDEX(drops!$A$2:$A$21,1)="","",INDEX(drops!$AI$2:$AI$21,1)) -> 57 | O32: =IF(INDEX(drops!$A$2:$A$21,1)="","",INDEX(drops!$AJ$2:$AJ$21,1)) -> 928 | P32: =IF(INDEX(drops!$A$2:$A$21,1)="","",INDEX(drops!$AK$2:$AK$21,1)) -> 16.28 | Q32: =IF(INDEX(drops!$A$2:$A$21,1)="","",INDEX(drops!$AL$2:$AL$21,1)) -> 0.896 | R32: =IF(INDEX(drops!$A$2:$A$21,1)="","",INDEX(drops!$AM$2:$AM$21,1)) -> 4 | S32: =IF(INDEX(drops!$A$2:$A$21,1)="","",INDEX(drops!$AN$2:$AN$21,1)) -> 0 | T32: =IF(INDEX(drops!$A$2:$A$21,1)="","",INDEX(drops!$AO$2:$AO$21,1)) -> 1
A33: =IF(INDEX(drops!$A$2:$A$21,2)="","",INDEX(drops!$A$2:$A$21,2)) -> SAMPLE-DRP-002 | B33: =IF(INDEX(drops!$A$2:$A$21,2)="","",INDEX(drops!$B$2:$B$21,2)) -> 46427 | C33: =IF(INDEX(drops!$A$2:$A$21,2)="","",INDEX(drops!$C$2:$C$21,2)) -> courier | D33: =IF(INDEX(drops!$A$2:$A$21,2)="","",INDEX(drops!$D$2:$D$21,2)) -> confirmed | E33: =IF(INDEX(drops!$A$2:$A$21,2)="","",INDEX(drops!$I$2:$I$21,2)) -> OK | F33: =IF(INDEX(drops!$A$2:$A$21,2)="","",INDEX(drops!$X$2:$X$21,2)) -> done | G33: =IF(INDEX(drops!$A$2:$A$21,2)="","",INDEX(drops!$Y$2:$Y$21,2)) | H33: =IF(INDEX(drops!$A$2:$A$21,2)="","",INDEX(drops!$AA$2:$AA$21,2)) -> 10 | I33: =IF(INDEX(drops!$A$2:$A$21,2)="","",INDEX(drops!$Z$2:$Z$21,2)) -> 3 | J33: =IF(INDEX(drops!$A$2:$A$21,2)="","",INDEX(drops!$AB$2:$AB$21,2)) -> 1455 | K33: =IF(INDEX(drops!$A$2:$A$21,2)="","",INDEX(drops!$AC$2:$AC$21,2)) -> 4350 | L33: =IF(INDEX(drops!$A$2:$A$21,2)="","",INDEX(drops!$AG$2:$AG$21,2)) -> 590 | M33: =IF(INDEX(drops!$A$2:$A$21,2)="","",INDEX(drops!$AH$2:$AH$21,2)) -> 59 | N33: =IF(INDEX(drops!$A$2:$A$21,2)="","",INDEX(drops!$AI$2:$AI$21,2)) -> 52 | O33: =IF(INDEX(drops!$A$2:$A$21,2)="","",INDEX(drops!$AJ$2:$AJ$21,2)) -> 3760 | P33: =IF(INDEX(drops!$A$2:$A$21,2)="","",INDEX(drops!$AK$2:$AK$21,2)) -> 72.31 | Q33: =IF(INDEX(drops!$A$2:$A$21,2)="","",INDEX(drops!$AL$2:$AL$21,2)) -> 1 | R33: =IF(INDEX(drops!$A$2:$A$21,2)="","",INDEX(drops!$AM$2:$AM$21,2)) -> 4 | S33: =IF(INDEX(drops!$A$2:$A$21,2)="","",INDEX(drops!$AN$2:$AN$21,2)) -> 0 | T33: =IF(INDEX(drops!$A$2:$A$21,2)="","",INDEX(drops!$AO$2:$AO$21,2)) -> 2
A34: =IF(INDEX(drops!$A$2:$A$21,3)="","",INDEX(drops!$A$2:$A$21,3)) -> SAMPLE-DRP-003 | B34: =IF(INDEX(drops!$A$2:$A$21,3)="","",INDEX(drops!$B$2:$B$21,3)) -> 46441 | C34: =IF(INDEX(drops!$A$2:$A$21,3)="","",INDEX(drops!$C$2:$C$21,3)) -> courier | D34: =IF(INDEX(drops!$A$2:$A$21,3)="","",INDEX(drops!$D$2:$D$21,3)) -> confirmed | E34: =IF(INDEX(drops!$A$2:$A$21,3)="","",INDEX(drops!$I$2:$I$21,3)) -> OK | F34: =IF(INDEX(drops!$A$2:$A$21,3)="","",INDEX(drops!$X$2:$X$21,3)) -> T+30 redemption check | G34: =IF(INDEX(drops!$A$2:$A$21,3)="","",INDEX(drops!$Y$2:$Y$21,3)) -> 46471 | H34: =IF(INDEX(drops!$A$2:$A$21,3)="","",INDEX(drops!$AA$2:$AA$21,3)) -> 10 | I34: =IF(INDEX(drops!$A$2:$A$21,3)="","",INDEX(drops!$Z$2:$Z$21,3)) -> 1 | J34: =IF(INDEX(drops!$A$2:$A$21,3)="","",INDEX(drops!$AB$2:$AB$21,3)) -> 465 | K34: =IF(INDEX(drops!$A$2:$A$21,3)="","",INDEX(drops!$AC$2:$AC$21,3)) -> 1350 | L34: =IF(INDEX(drops!$A$2:$A$21,3)="","",INDEX(drops!$AG$2:$AG$21,3)) -> 380 | M34: =IF(INDEX(drops!$A$2:$A$21,3)="","",INDEX(drops!$AH$2:$AH$21,3)) -> 38 | N34: =IF(INDEX(drops!$A$2:$A$21,3)="","",INDEX(drops!$AI$2:$AI$21,3)) -> 20.5 | O34: =IF(INDEX(drops!$A$2:$A$21,3)="","",INDEX(drops!$AJ$2:$AJ$21,3)) -> 970 | P34: =IF(INDEX(drops!$A$2:$A$21,3)="","",INDEX(drops!$AK$2:$AK$21,3)) -> 47.32 | Q34: =IF(INDEX(drops!$A$2:$A$21,3)="","",INDEX(drops!$AL$2:$AL$21,3)) -> 1 | R34: =IF(INDEX(drops!$A$2:$A$21,3)="","",INDEX(drops!$AM$2:$AM$21,3)) -> 5 | S34: =IF(INDEX(drops!$A$2:$A$21,3)="","",INDEX(drops!$AN$2:$AN$21,3)) -> 0 | T34: =IF(INDEX(drops!$A$2:$A$21,3)="","",INDEX(drops!$AO$2:$AO$21,3)) -> 1
A35: =IF(INDEX(drops!$A$2:$A$21,4)="","",INDEX(drops!$A$2:$A$21,4)) -> SAMPLE-DRP-004 | B35: =IF(INDEX(drops!$A$2:$A$21,4)="","",INDEX(drops!$B$2:$B$21,4)) -> 46469 | C35: =IF(INDEX(drops!$A$2:$A$21,4)="","",INDEX(drops!$C$2:$C$21,4)) -> direct-ship | D35: =IF(INDEX(drops!$A$2:$A$21,4)="","",INDEX(drops!$D$2:$D$21,4)) -> confirmed | E35: =IF(INDEX(drops!$A$2:$A$21,4)="","",INDEX(drops!$I$2:$I$21,4)) -> OK | F35: =IF(INDEX(drops!$A$2:$A$21,4)="","",INDEX(drops!$X$2:$X$21,4)) -> T-1 confirm owners, pack | G35: =IF(INDEX(drops!$A$2:$A$21,4)="","",INDEX(drops!$Y$2:$Y$21,4)) -> 46468 | H35: =IF(INDEX(drops!$A$2:$A$21,4)="","",INDEX(drops!$AA$2:$AA$21,4)) -> 10 | I35: =IF(INDEX(drops!$A$2:$A$21,4)="","",INDEX(drops!$Z$2:$Z$21,4)) -> 2 | J35: =IF(INDEX(drops!$A$2:$A$21,4)="","",INDEX(drops!$AB$2:$AB$21,4)) -> 1030 | K35: =IF(INDEX(drops!$A$2:$A$21,4)="","",INDEX(drops!$AC$2:$AC$21,4)) -> 1950 | L35: =IF(INDEX(drops!$A$2:$A$21,4)="","",INDEX(drops!$AG$2:$AG$21,4)) -> 205 | M35: =IF(INDEX(drops!$A$2:$A$21,4)="","",INDEX(drops!$AH$2:$AH$21,4)) -> 20.5 | N35: =IF(INDEX(drops!$A$2:$A$21,4)="","",INDEX(drops!$AI$2:$AI$21,4)) -> 8 | O35: =IF(INDEX(drops!$A$2:$A$21,4)="","",INDEX(drops!$AJ$2:$AJ$21,4)) -> 1745 | P35: =IF(INDEX(drops!$A$2:$A$21,4)="","",INDEX(drops!$AK$2:$AK$21,4)) -> 218.13 | Q35: =IF(INDEX(drops!$A$2:$A$21,4)="","",INDEX(drops!$AL$2:$AL$21,4)) | R35: =IF(INDEX(drops!$A$2:$A$21,4)="","",INDEX(drops!$AM$2:$AM$21,4)) -> 0 | S35: =IF(INDEX(drops!$A$2:$A$21,4)="","",INDEX(drops!$AN$2:$AN$21,4)) -> 0 | T35: =IF(INDEX(drops!$A$2:$A$21,4)="","",INDEX(drops!$AO$2:$AO$21,4)) -> 0
A36: =IF(INDEX(drops!$A$2:$A$21,5)="","",INDEX(drops!$A$2:$A$21,5)) | B36: =IF(INDEX(drops!$A$2:$A$21,5)="","",INDEX(drops!$B$2:$B$21,5)) | C36: =IF(INDEX(drops!$A$2:$A$21,5)="","",INDEX(drops!$C$2:$C$21,5)) | D36: =IF(INDEX(drops!$A$2:$A$21,5)="","",INDEX(drops!$D$2:$D$21,5)) | E36: =IF(INDEX(drops!$A$2:$A$21,5)="","",INDEX(drops!$I$2:$I$21,5)) | F36: =IF(INDEX(drops!$A$2:$A$21,5)="","",INDEX(drops!$X$2:$X$21,5)) | G36: =IF(INDEX(drops!$A$2:$A$21,5)="","",INDEX(drops!$Y$2:$Y$21,5)) | H36: =IF(INDEX(drops!$A$2:$A$21,5)="","",INDEX(drops!$AA$2:$AA$21,5)) | I36: =IF(INDEX(drops!$A$2:$A$21,5)="","",INDEX(drops!$Z$2:$Z$21,5)) | J36: =IF(INDEX(drops!$A$2:$A$21,5)="","",INDEX(drops!$AB$2:$AB$21,5)) | K36: =IF(INDEX(drops!$A$2:$A$21,5)="","",INDEX(drops!$AC$2:$AC$21,5)) | L36: =IF(INDEX(drops!$A$2:$A$21,5)="","",INDEX(drops!$AG$2:$AG$21,5)) | M36: =IF(INDEX(drops!$A$2:$A$21,5)="","",INDEX(drops!$AH$2:$AH$21,5)) | N36: =IF(INDEX(drops!$A$2:$A$21,5)="","",INDEX(drops!$AI$2:$AI$21,5)) | O36: =IF(INDEX(drops!$A$2:$A$21,5)="","",INDEX(drops!$AJ$2:$AJ$21,5)) | P36: =IF(INDEX(drops!$A$2:$A$21,5)="","",INDEX(drops!$AK$2:$AK$21,5)) | Q36: =IF(INDEX(drops!$A$2:$A$21,5)="","",INDEX(drops!$AL$2:$AL$21,5)) | R36: =IF(INDEX(drops!$A$2:$A$21,5)="","",INDEX(drops!$AM$2:$AM$21,5)) | S36: =IF(INDEX(drops!$A$2:$A$21,5)="","",INDEX(drops!$AN$2:$AN$21,5)) | T36: =IF(INDEX(drops!$A$2:$A$21,5)="","",INDEX(drops!$AO$2:$AO$21,5))
A37: =IF(INDEX(drops!$A$2:$A$21,6)="","",INDEX(drops!$A$2:$A$21,6)) | B37: =IF(INDEX(drops!$A$2:$A$21,6)="","",INDEX(drops!$B$2:$B$21,6)) | C37: =IF(INDEX(drops!$A$2:$A$21,6)="","",INDEX(drops!$C$2:$C$21,6)) | D37: =IF(INDEX(drops!$A$2:$A$21,6)="","",INDEX(drops!$D$2:$D$21,6)) | E37: =IF(INDEX(drops!$A$2:$A$21,6)="","",INDEX(drops!$I$2:$I$21,6)) | F37: =IF(INDEX(drops!$A$2:$A$21,6)="","",INDEX(drops!$X$2:$X$21,6)) | G37: =IF(INDEX(drops!$A$2:$A$21,6)="","",INDEX(drops!$Y$2:$Y$21,6)) | H37: =IF(INDEX(drops!$A$2:$A$21,6)="","",INDEX(drops!$AA$2:$AA$21,6)) | I37: =IF(INDEX(drops!$A$2:$A$21,6)="","",INDEX(drops!$Z$2:$Z$21,6)) | J37: =IF(INDEX(drops!$A$2:$A$21,6)="","",INDEX(drops!$AB$2:$AB$21,6)) | K37: =IF(INDEX(drops!$A$2:$A$21,6)="","",INDEX(drops!$AC$2:$AC$21,6)) | L37: =IF(INDEX(drops!$A$2:$A$21,6)="","",INDEX(drops!$AG$2:$AG$21,6)) | M37: =IF(INDEX(drops!$A$2:$A$21,6)="","",INDEX(drops!$AH$2:$AH$21,6)) | N37: =IF(INDEX(drops!$A$2:$A$21,6)="","",INDEX(drops!$AI$2:$AI$21,6)) | O37: =IF(INDEX(drops!$A$2:$A$21,6)="","",INDEX(drops!$AJ$2:$AJ$21,6)) | P37: =IF(INDEX(drops!$A$2:$A$21,6)="","",INDEX(drops!$AK$2:$AK$21,6)) | Q37: =IF(INDEX(drops!$A$2:$A$21,6)="","",INDEX(drops!$AL$2:$AL$21,6)) | R37: =IF(INDEX(drops!$A$2:$A$21,6)="","",INDEX(drops!$AM$2:$AM$21,6)) | S37: =IF(INDEX(drops!$A$2:$A$21,6)="","",INDEX(drops!$AN$2:$AN$21,6)) | T37: =IF(INDEX(drops!$A$2:$A$21,6)="","",INDEX(drops!$AO$2:$AO$21,6))
A38: =IF(INDEX(drops!$A$2:$A$21,7)="","",INDEX(drops!$A$2:$A$21,7)) | B38: =IF(INDEX(drops!$A$2:$A$21,7)="","",INDEX(drops!$B$2:$B$21,7)) | C38: =IF(INDEX(drops!$A$2:$A$21,7)="","",INDEX(drops!$C$2:$C$21,7)) | D38: =IF(INDEX(drops!$A$2:$A$21,7)="","",INDEX(drops!$D$2:$D$21,7)) | E38: =IF(INDEX(drops!$A$2:$A$21,7)="","",INDEX(drops!$I$2:$I$21,7)) | F38: =IF(INDEX(drops!$A$2:$A$21,7)="","",INDEX(drops!$X$2:$X$21,7)) | G38: =IF(INDEX(drops!$A$2:$A$21,7)="","",INDEX(drops!$Y$2:$Y$21,7)) | H38: =IF(INDEX(drops!$A$2:$A$21,7)="","",INDEX(drops!$AA$2:$AA$21,7)) | I38: =IF(INDEX(drops!$A$2:$A$21,7)="","",INDEX(drops!$Z$2:$Z$21,7)) | J38: =IF(INDEX(drops!$A$2:$A$21,7)="","",INDEX(drops!$AB$2:$AB$21,7)) | K38: =IF(INDEX(drops!$A$2:$A$21,7)="","",INDEX(drops!$AC$2:$AC$21,7)) | L38: =IF(INDEX(drops!$A$2:$A$21,7)="","",INDEX(drops!$AG$2:$AG$21,7)) | M38: =IF(INDEX(drops!$A$2:$A$21,7)="","",INDEX(drops!$AH$2:$AH$21,7)) | N38: =IF(INDEX(drops!$A$2:$A$21,7)="","",INDEX(drops!$AI$2:$AI$21,7)) | O38: =IF(INDEX(drops!$A$2:$A$21,7)="","",INDEX(drops!$AJ$2:$AJ$21,7)) | P38: =IF(INDEX(drops!$A$2:$A$21,7)="","",INDEX(drops!$AK$2:$AK$21,7)) | Q38: =IF(INDEX(drops!$A$2:$A$21,7)="","",INDEX(drops!$AL$2:$AL$21,7)) | R38: =IF(INDEX(drops!$A$2:$A$21,7)="","",INDEX(drops!$AM$2:$AM$21,7)) | S38: =IF(INDEX(drops!$A$2:$A$21,7)="","",INDEX(drops!$AN$2:$AN$21,7)) | T38: =IF(INDEX(drops!$A$2:$A$21,7)="","",INDEX(drops!$AO$2:$AO$21,7))
A39: =IF(INDEX(drops!$A$2:$A$21,8)="","",INDEX(drops!$A$2:$A$21,8)) | B39: =IF(INDEX(drops!$A$2:$A$21,8)="","",INDEX(drops!$B$2:$B$21,8)) | C39: =IF(INDEX(drops!$A$2:$A$21,8)="","",INDEX(drops!$C$2:$C$21,8)) | D39: =IF(INDEX(drops!$A$2:$A$21,8)="","",INDEX(drops!$D$2:$D$21,8)) | E39: =IF(INDEX(drops!$A$2:$A$21,8)="","",INDEX(drops!$I$2:$I$21,8)) | F39: =IF(INDEX(drops!$A$2:$A$21,8)="","",INDEX(drops!$X$2:$X$21,8)) | G39: =IF(INDEX(drops!$A$2:$A$21,8)="","",INDEX(drops!$Y$2:$Y$21,8)) | H39: =IF(INDEX(drops!$A$2:$A$21,8)="","",INDEX(drops!$AA$2:$AA$21,8)) | I39: =IF(INDEX(drops!$A$2:$A$21,8)="","",INDEX(drops!$Z$2:$Z$21,8)) | J39: =IF(INDEX(drops!$A$2:$A$21,8)="","",INDEX(drops!$AB$2:$AB$21,8)) | K39: =IF(INDEX(drops!$A$2:$A$21,8)="","",INDEX(drops!$AC$2:$AC$21,8)) | L39: =IF(INDEX(drops!$A$2:$A$21,8)="","",INDEX(drops!$AG$2:$AG$21,8)) | M39: =IF(INDEX(drops!$A$2:$A$21,8)="","",INDEX(drops!$AH$2:$AH$21,8)) | N39: =IF(INDEX(drops!$A$2:$A$21,8)="","",INDEX(drops!$AI$2:$AI$21,8)) | O39: =IF(INDEX(drops!$A$2:$A$21,8)="","",INDEX(drops!$AJ$2:$AJ$21,8)) | P39: =IF(INDEX(drops!$A$2:$A$21,8)="","",INDEX(drops!$AK$2:$AK$21,8)) | Q39: =IF(INDEX(drops!$A$2:$A$21,8)="","",INDEX(drops!$AL$2:$AL$21,8)) | R39: =IF(INDEX(drops!$A$2:$A$21,8)="","",INDEX(drops!$AM$2:$AM$21,8)) | S39: =IF(INDEX(drops!$A$2:$A$21,8)="","",INDEX(drops!$AN$2:$AN$21,8)) | T39: =IF(INDEX(drops!$A$2:$A$21,8)="","",INDEX(drops!$AO$2:$AO$21,8))
A40: =IF(INDEX(drops!$A$2:$A$21,9)="","",INDEX(drops!$A$2:$A$21,9)) | B40: =IF(INDEX(drops!$A$2:$A$21,9)="","",INDEX(drops!$B$2:$B$21,9)) | C40: =IF(INDEX(drops!$A$2:$A$21,9)="","",INDEX(drops!$C$2:$C$21,9)) | D40: =IF(INDEX(drops!$A$2:$A$21,9)="","",INDEX(drops!$D$2:$D$21,9)) | E40: =IF(INDEX(drops!$A$2:$A$21,9)="","",INDEX(drops!$I$2:$I$21,9)) | F40: =IF(INDEX(drops!$A$2:$A$21,9)="","",INDEX(drops!$X$2:$X$21,9)) | G40: =IF(INDEX(drops!$A$2:$A$21,9)="","",INDEX(drops!$Y$2:$Y$21,9)) | H40: =IF(INDEX(drops!$A$2:$A$21,9)="","",INDEX(drops!$AA$2:$AA$21,9)) | I40: =IF(INDEX(drops!$A$2:$A$21,9)="","",INDEX(drops!$Z$2:$Z$21,9)) | J40: =IF(INDEX(drops!$A$2:$A$21,9)="","",INDEX(drops!$AB$2:$AB$21,9)) | K40: =IF(INDEX(drops!$A$2:$A$21,9)="","",INDEX(drops!$AC$2:$AC$21,9)) | L40: =IF(INDEX(drops!$A$2:$A$21,9)="","",INDEX(drops!$AG$2:$AG$21,9)) | M40: =IF(INDEX(drops!$A$2:$A$21,9)="","",INDEX(drops!$AH$2:$AH$21,9)) | N40: =IF(INDEX(drops!$A$2:$A$21,9)="","",INDEX(drops!$AI$2:$AI$21,9)) | O40: =IF(INDEX(drops!$A$2:$A$21,9)="","",INDEX(drops!$AJ$2:$AJ$21,9)) | P40: =IF(INDEX(drops!$A$2:$A$21,9)="","",INDEX(drops!$AK$2:$AK$21,9)) | Q40: =IF(INDEX(drops!$A$2:$A$21,9)="","",INDEX(drops!$AL$2:$AL$21,9)) | R40: =IF(INDEX(drops!$A$2:$A$21,9)="","",INDEX(drops!$AM$2:$AM$21,9)) | S40: =IF(INDEX(drops!$A$2:$A$21,9)="","",INDEX(drops!$AN$2:$AN$21,9)) | T40: =IF(INDEX(drops!$A$2:$A$21,9)="","",INDEX(drops!$AO$2:$AO$21,9))
A41: =IF(INDEX(drops!$A$2:$A$21,10)="","",INDEX(drops!$A$2:$A$21,10)) | B41: =IF(INDEX(drops!$A$2:$A$21,10)="","",INDEX(drops!$B$2:$B$21,10)) | C41: =IF(INDEX(drops!$A$2:$A$21,10)="","",INDEX(drops!$C$2:$C$21,10)) | D41: =IF(INDEX(drops!$A$2:$A$21,10)="","",INDEX(drops!$D$2:$D$21,10)) | E41: =IF(INDEX(drops!$A$2:$A$21,10)="","",INDEX(drops!$I$2:$I$21,10)) | F41: =IF(INDEX(drops!$A$2:$A$21,10)="","",INDEX(drops!$X$2:$X$21,10)) | G41: =IF(INDEX(drops!$A$2:$A$21,10)="","",INDEX(drops!$Y$2:$Y$21,10)) | H41: =IF(INDEX(drops!$A$2:$A$21,10)="","",INDEX(drops!$AA$2:$AA$21,10)) | I41: =IF(INDEX(drops!$A$2:$A$21,10)="","",INDEX(drops!$Z$2:$Z$21,10)) | J41: =IF(INDEX(drops!$A$2:$A$21,10)="","",INDEX(drops!$AB$2:$AB$21,10)) | K41: =IF(INDEX(drops!$A$2:$A$21,10)="","",INDEX(drops!$AC$2:$AC$21,10)) | L41: =IF(INDEX(drops!$A$2:$A$21,10)="","",INDEX(drops!$AG$2:$AG$21,10)) | M41: =IF(INDEX(drops!$A$2:$A$21,10)="","",INDEX(drops!$AH$2:$AH$21,10)) | N41: =IF(INDEX(drops!$A$2:$A$21,10)="","",INDEX(drops!$AI$2:$AI$21,10)) | O41: =IF(INDEX(drops!$A$2:$A$21,10)="","",INDEX(drops!$AJ$2:$AJ$21,10)) | P41: =IF(INDEX(drops!$A$2:$A$21,10)="","",INDEX(drops!$AK$2:$AK$21,10)) | Q41: =IF(INDEX(drops!$A$2:$A$21,10)="","",INDEX(drops!$AL$2:$AL$21,10)) | R41: =IF(INDEX(drops!$A$2:$A$21,10)="","",INDEX(drops!$AM$2:$AM$21,10)) | S41: =IF(INDEX(drops!$A$2:$A$21,10)="","",INDEX(drops!$AN$2:$AN$21,10)) | T41: =IF(INDEX(drops!$A$2:$A$21,10)="","",INDEX(drops!$AO$2:$AO$21,10))
A42: =IF(INDEX(drops!$A$2:$A$21,11)="","",INDEX(drops!$A$2:$A$21,11)) | B42: =IF(INDEX(drops!$A$2:$A$21,11)="","",INDEX(drops!$B$2:$B$21,11)) | C42: =IF(INDEX(drops!$A$2:$A$21,11)="","",INDEX(drops!$C$2:$C$21,11)) | D42: =IF(INDEX(drops!$A$2:$A$21,11)="","",INDEX(drops!$D$2:$D$21,11)) | E42: =IF(INDEX(drops!$A$2:$A$21,11)="","",INDEX(drops!$I$2:$I$21,11)) | F42: =IF(INDEX(drops!$A$2:$A$21,11)="","",INDEX(drops!$X$2:$X$21,11)) | G42: =IF(INDEX(drops!$A$2:$A$21,11)="","",INDEX(drops!$Y$2:$Y$21,11)) | H42: =IF(INDEX(drops!$A$2:$A$21,11)="","",INDEX(drops!$AA$2:$AA$21,11)) | I42: =IF(INDEX(drops!$A$2:$A$21,11)="","",INDEX(drops!$Z$2:$Z$21,11)) | J42: =IF(INDEX(drops!$A$2:$A$21,11)="","",INDEX(drops!$AB$2:$AB$21,11)) | K42: =IF(INDEX(drops!$A$2:$A$21,11)="","",INDEX(drops!$AC$2:$AC$21,11)) | L42: =IF(INDEX(drops!$A$2:$A$21,11)="","",INDEX(drops!$AG$2:$AG$21,11)) | M42: =IF(INDEX(drops!$A$2:$A$21,11)="","",INDEX(drops!$AH$2:$AH$21,11)) | N42: =IF(INDEX(drops!$A$2:$A$21,11)="","",INDEX(drops!$AI$2:$AI$21,11)) | O42: =IF(INDEX(drops!$A$2:$A$21,11)="","",INDEX(drops!$AJ$2:$AJ$21,11)) | P42: =IF(INDEX(drops!$A$2:$A$21,11)="","",INDEX(drops!$AK$2:$AK$21,11)) | Q42: =IF(INDEX(drops!$A$2:$A$21,11)="","",INDEX(drops!$AL$2:$AL$21,11)) | R42: =IF(INDEX(drops!$A$2:$A$21,11)="","",INDEX(drops!$AM$2:$AM$21,11)) | S42: =IF(INDEX(drops!$A$2:$A$21,11)="","",INDEX(drops!$AN$2:$AN$21,11)) | T42: =IF(INDEX(drops!$A$2:$A$21,11)="","",INDEX(drops!$AO$2:$AO$21,11))
A43: =IF(INDEX(drops!$A$2:$A$21,12)="","",INDEX(drops!$A$2:$A$21,12)) | B43: =IF(INDEX(drops!$A$2:$A$21,12)="","",INDEX(drops!$B$2:$B$21,12)) | C43: =IF(INDEX(drops!$A$2:$A$21,12)="","",INDEX(drops!$C$2:$C$21,12)) | D43: =IF(INDEX(drops!$A$2:$A$21,12)="","",INDEX(drops!$D$2:$D$21,12)) | E43: =IF(INDEX(drops!$A$2:$A$21,12)="","",INDEX(drops!$I$2:$I$21,12)) | F43: =IF(INDEX(drops!$A$2:$A$21,12)="","",INDEX(drops!$X$2:$X$21,12)) | G43: =IF(INDEX(drops!$A$2:$A$21,12)="","",INDEX(drops!$Y$2:$Y$21,12)) | H43: =IF(INDEX(drops!$A$2:$A$21,12)="","",INDEX(drops!$AA$2:$AA$21,12)) | I43: =IF(INDEX(drops!$A$2:$A$21,12)="","",INDEX(drops!$Z$2:$Z$21,12)) | J43: =IF(INDEX(drops!$A$2:$A$21,12)="","",INDEX(drops!$AB$2:$AB$21,12)) | K43: =IF(INDEX(drops!$A$2:$A$21,12)="","",INDEX(drops!$AC$2:$AC$21,12)) | L43: =IF(INDEX(drops!$A$2:$A$21,12)="","",INDEX(drops!$AG$2:$AG$21,12)) | M43: =IF(INDEX(drops!$A$2:$A$21,12)="","",INDEX(drops!$AH$2:$AH$21,12)) | N43: =IF(INDEX(drops!$A$2:$A$21,12)="","",INDEX(drops!$AI$2:$AI$21,12)) | O43: =IF(INDEX(drops!$A$2:$A$21,12)="","",INDEX(drops!$AJ$2:$AJ$21,12)) | P43: =IF(INDEX(drops!$A$2:$A$21,12)="","",INDEX(drops!$AK$2:$AK$21,12)) | Q43: =IF(INDEX(drops!$A$2:$A$21,12)="","",INDEX(drops!$AL$2:$AL$21,12)) | R43: =IF(INDEX(drops!$A$2:$A$21,12)="","",INDEX(drops!$AM$2:$AM$21,12)) | S43: =IF(INDEX(drops!$A$2:$A$21,12)="","",INDEX(drops!$AN$2:$AN$21,12)) | T43: =IF(INDEX(drops!$A$2:$A$21,12)="","",INDEX(drops!$AO$2:$AO$21,12))
A44: =IF(INDEX(drops!$A$2:$A$21,13)="","",INDEX(drops!$A$2:$A$21,13)) | B44: =IF(INDEX(drops!$A$2:$A$21,13)="","",INDEX(drops!$B$2:$B$21,13)) | C44: =IF(INDEX(drops!$A$2:$A$21,13)="","",INDEX(drops!$C$2:$C$21,13)) | D44: =IF(INDEX(drops!$A$2:$A$21,13)="","",INDEX(drops!$D$2:$D$21,13)) | E44: =IF(INDEX(drops!$A$2:$A$21,13)="","",INDEX(drops!$I$2:$I$21,13)) | F44: =IF(INDEX(drops!$A$2:$A$21,13)="","",INDEX(drops!$X$2:$X$21,13)) | G44: =IF(INDEX(drops!$A$2:$A$21,13)="","",INDEX(drops!$Y$2:$Y$21,13)) | H44: =IF(INDEX(drops!$A$2:$A$21,13)="","",INDEX(drops!$AA$2:$AA$21,13)) | I44: =IF(INDEX(drops!$A$2:$A$21,13)="","",INDEX(drops!$Z$2:$Z$21,13)) | J44: =IF(INDEX(drops!$A$2:$A$21,13)="","",INDEX(drops!$AB$2:$AB$21,13)) | K44: =IF(INDEX(drops!$A$2:$A$21,13)="","",INDEX(drops!$AC$2:$AC$21,13)) | L44: =IF(INDEX(drops!$A$2:$A$21,13)="","",INDEX(drops!$AG$2:$AG$21,13)) | M44: =IF(INDEX(drops!$A$2:$A$21,13)="","",INDEX(drops!$AH$2:$AH$21,13)) | N44: =IF(INDEX(drops!$A$2:$A$21,13)="","",INDEX(drops!$AI$2:$AI$21,13)) | O44: =IF(INDEX(drops!$A$2:$A$21,13)="","",INDEX(drops!$AJ$2:$AJ$21,13)) | P44: =IF(INDEX(drops!$A$2:$A$21,13)="","",INDEX(drops!$AK$2:$AK$21,13)) | Q44: =IF(INDEX(drops!$A$2:$A$21,13)="","",INDEX(drops!$AL$2:$AL$21,13)) | R44: =IF(INDEX(drops!$A$2:$A$21,13)="","",INDEX(drops!$AM$2:$AM$21,13)) | S44: =IF(INDEX(drops!$A$2:$A$21,13)="","",INDEX(drops!$AN$2:$AN$21,13)) | T44: =IF(INDEX(drops!$A$2:$A$21,13)="","",INDEX(drops!$AO$2:$AO$21,13))
A45: =IF(INDEX(drops!$A$2:$A$21,14)="","",INDEX(drops!$A$2:$A$21,14)) | B45: =IF(INDEX(drops!$A$2:$A$21,14)="","",INDEX(drops!$B$2:$B$21,14)) | C45: =IF(INDEX(drops!$A$2:$A$21,14)="","",INDEX(drops!$C$2:$C$21,14)) | D45: =IF(INDEX(drops!$A$2:$A$21,14)="","",INDEX(drops!$D$2:$D$21,14)) | E45: =IF(INDEX(drops!$A$2:$A$21,14)="","",INDEX(drops!$I$2:$I$21,14)) | F45: =IF(INDEX(drops!$A$2:$A$21,14)="","",INDEX(drops!$X$2:$X$21,14)) | G45: =IF(INDEX(drops!$A$2:$A$21,14)="","",INDEX(drops!$Y$2:$Y$21,14)) | H45: =IF(INDEX(drops!$A$2:$A$21,14)="","",INDEX(drops!$AA$2:$AA$21,14)) | I45: =IF(INDEX(drops!$A$2:$A$21,14)="","",INDEX(drops!$Z$2:$Z$21,14)) | J45: =IF(INDEX(drops!$A$2:$A$21,14)="","",INDEX(drops!$AB$2:$AB$21,14)) | K45: =IF(INDEX(drops!$A$2:$A$21,14)="","",INDEX(drops!$AC$2:$AC$21,14)) | L45: =IF(INDEX(drops!$A$2:$A$21,14)="","",INDEX(drops!$AG$2:$AG$21,14)) | M45: =IF(INDEX(drops!$A$2:$A$21,14)="","",INDEX(drops!$AH$2:$AH$21,14)) | N45: =IF(INDEX(drops!$A$2:$A$21,14)="","",INDEX(drops!$AI$2:$AI$21,14)) | O45: =IF(INDEX(drops!$A$2:$A$21,14)="","",INDEX(drops!$AJ$2:$AJ$21,14)) | P45: =IF(INDEX(drops!$A$2:$A$21,14)="","",INDEX(drops!$AK$2:$AK$21,14)) | Q45: =IF(INDEX(drops!$A$2:$A$21,14)="","",INDEX(drops!$AL$2:$AL$21,14)) | R45: =IF(INDEX(drops!$A$2:$A$21,14)="","",INDEX(drops!$AM$2:$AM$21,14)) | S45: =IF(INDEX(drops!$A$2:$A$21,14)="","",INDEX(drops!$AN$2:$AN$21,14)) | T45: =IF(INDEX(drops!$A$2:$A$21,14)="","",INDEX(drops!$AO$2:$AO$21,14))
A46: =IF(INDEX(drops!$A$2:$A$21,15)="","",INDEX(drops!$A$2:$A$21,15)) | B46: =IF(INDEX(drops!$A$2:$A$21,15)="","",INDEX(drops!$B$2:$B$21,15)) | C46: =IF(INDEX(drops!$A$2:$A$21,15)="","",INDEX(drops!$C$2:$C$21,15)) | D46: =IF(INDEX(drops!$A$2:$A$21,15)="","",INDEX(drops!$D$2:$D$21,15)) | E46: =IF(INDEX(drops!$A$2:$A$21,15)="","",INDEX(drops!$I$2:$I$21,15)) | F46: =IF(INDEX(drops!$A$2:$A$21,15)="","",INDEX(drops!$X$2:$X$21,15)) | G46: =IF(INDEX(drops!$A$2:$A$21,15)="","",INDEX(drops!$Y$2:$Y$21,15)) | H46: =IF(INDEX(drops!$A$2:$A$21,15)="","",INDEX(drops!$AA$2:$AA$21,15)) | I46: =IF(INDEX(drops!$A$2:$A$21,15)="","",INDEX(drops!$Z$2:$Z$21,15)) | J46: =IF(INDEX(drops!$A$2:$A$21,15)="","",INDEX(drops!$AB$2:$AB$21,15)) | K46: =IF(INDEX(drops!$A$2:$A$21,15)="","",INDEX(drops!$AC$2:$AC$21,15)) | L46: =IF(INDEX(drops!$A$2:$A$21,15)="","",INDEX(drops!$AG$2:$AG$21,15)) | M46: =IF(INDEX(drops!$A$2:$A$21,15)="","",INDEX(drops!$AH$2:$AH$21,15)) | N46: =IF(INDEX(drops!$A$2:$A$21,15)="","",INDEX(drops!$AI$2:$AI$21,15)) | O46: =IF(INDEX(drops!$A$2:$A$21,15)="","",INDEX(drops!$AJ$2:$AJ$21,15)) | P46: =IF(INDEX(drops!$A$2:$A$21,15)="","",INDEX(drops!$AK$2:$AK$21,15)) | Q46: =IF(INDEX(drops!$A$2:$A$21,15)="","",INDEX(drops!$AL$2:$AL$21,15)) | R46: =IF(INDEX(drops!$A$2:$A$21,15)="","",INDEX(drops!$AM$2:$AM$21,15)) | S46: =IF(INDEX(drops!$A$2:$A$21,15)="","",INDEX(drops!$AN$2:$AN$21,15)) | T46: =IF(INDEX(drops!$A$2:$A$21,15)="","",INDEX(drops!$AO$2:$AO$21,15))
A47: Contribution here = revenue (net of credit notes) - direct costs (kit, transport, other) - card fees, before overhead. The financial model also subtracts its planned overhead allocation (software, insurance, storage), so its figure per drop is lower by that amount.
A48: Campaigns (every rung kept separate)
A49: campaign | B49: brand | C49: drop | D49: tier | E49: ship release | F49: offices approved | G49: on the drop | H49: contracted | I49: delivered | J49: placed within 1 bd | K49: share | L49: topped up | M49: depleted by day 5 | N49: responded | O49: fewest at one office | P49: said they tried | Q49: avg rating | R49: QR scans | S49: code redemptions | T49: revenue | U49: per founder hour, before overhead | V49: G2 placed | W49: G2 responses | X49: G2 report | Y49: buy again | Z49: checks
A50: =IF(INDEX(campaigns!$A$2:$A$51,1)="","",INDEX(campaigns!$A$2:$A$51,1)) -> SAMPLE-CMP-001 | B50: =IF(INDEX(campaigns!$A$2:$A$51,1)="","",INDEX(campaigns!$BE$2:$BE$51,1)) -> SAMPLE Brightside | C50: =IF(INDEX(campaigns!$A$2:$A$51,1)="","",INDEX(campaigns!$BG$2:$BG$51,1)) -> 46399 | D50: =IF(INDEX(campaigns!$A$2:$A$51,1)="","",INDEX(campaigns!$D$2:$D$51,1)) -> founding | E50: =IF(INDEX(campaigns!$A$2:$A$51,1)="","",INDEX(campaigns!$BW$2:$BW$51,1)) -> RELEASED 2026-12-18: ship by Tue 2026-12-22 (latest Mon 2026-12-28) | F50: =IF(INDEX(campaigns!$A$2:$A$51,1)="","",INDEX(campaigns!$BO$2:$BO$51,1)) -> 5 | G50: =IF(INDEX(campaigns!$A$2:$A$51,1)="","",INDEX(campaigns!$BP$2:$BP$51,1)) -> 5 | H50: =IF(INDEX(campaigns!$A$2:$A$51,1)="","",INDEX(campaigns!$F$2:$F$51,1)) -> 5 | I50: =IF(INDEX(campaigns!$A$2:$A$51,1)="","",INDEX(campaigns!$CB$2:$CB$51,1)) -> 250 | J50: =IF(INDEX(campaigns!$A$2:$A$51,1)="","",INDEX(campaigns!$CD$2:$CD$51,1)) -> 198 | K50: =IF(INDEX(campaigns!$A$2:$A$51,1)="","",INDEX(campaigns!$CE$2:$CE$51,1)) -> 0.792 | L50: =IF(INDEX(campaigns!$A$2:$A$51,1)="","",INDEX(campaigns!$CF$2:$CF$51,1)) -> 5 | M50: =IF(INDEX(campaigns!$A$2:$A$51,1)="","",INDEX(campaigns!$CG$2:$CG$51,1)) -> 200 | N50: =IF(INDEX(campaigns!$A$2:$A$51,1)="","",INDEX(campaigns!$CH$2:$CH$51,1)) -> 34 | O50: =IF(INDEX(campaigns!$A$2:$A$51,1)="","",INDEX(campaigns!$CI$2:$CI$51,1)) -> 4 | P50: =IF(INDEX(campaigns!$A$2:$A$51,1)="","",INDEX(campaigns!$CK$2:$CK$51,1)) -> 25 | Q50: =IF(INDEX(campaigns!$A$2:$A$51,1)="","",INDEX(campaigns!$CP$2:$CP$51,1)) -> 4.2 | R50: =IF(INDEX(campaigns!$A$2:$A$51,1)="","",INDEX(campaigns!$CX$2:$CX$51,1)) -> 45 | S50: =IF(INDEX(campaigns!$A$2:$A$51,1)="","",INDEX(campaigns!$CZ$2:$CZ$51,1)) -> 11 | T50: =IF(INDEX(campaigns!$A$2:$A$51,1)="","",INDEX(campaigns!$DC$2:$DC$51,1)) -> 480 | U50: =IF(INDEX(campaigns!$A$2:$A$51,1)="","",INDEX(campaigns!$DM$2:$DM$51,1)) -> 14.18 | V50: =IF(INDEX(campaigns!$A$2:$A$51,1)="","",INDEX(campaigns!$DS$2:$DS$51,1)) -> miss | W50: =IF(INDEX(campaigns!$A$2:$A$51,1)="","",INDEX(campaigns!$DT$2:$DT$51,1)) -> miss | X50: =IF(INDEX(campaigns!$A$2:$A$51,1)="","",INDEX(campaigns!$DU$2:$DU$51,1)) -> pass | Y50: =IF(INDEX(campaigns!$A$2:$A$51,1)="","",INDEX(campaigns!$AV$2:$AV$51,1)) -> yes | Z50: =IF(INDEX(campaigns!$A$2:$A$51,1)="","",INDEX(campaigns!$DV$2:$DV$51,1)) -> info: 1 in-window responses with a card code that matches no office (not counted); info: brand insurance ends 2027-06-30: diary the renewal certificate;
A51: =IF(INDEX(campaigns!$A$2:$A$51,2)="","",INDEX(campaigns!$A$2:$A$51,2)) -> SAMPLE-CMP-002 | B51: =IF(INDEX(campaigns!$A$2:$A$51,2)="","",INDEX(campaigns!$BE$2:$BE$51,2)) -> SAMPLE Northbound | C51: =IF(INDEX(campaigns!$A$2:$A$51,2)="","",INDEX(campaigns!$BG$2:$BG$51,2)) -> 46399 | D51: =IF(INDEX(campaigns!$A$2:$A$51,2)="","",INDEX(campaigns!$D$2:$D$51,2)) -> founding | E51: =IF(INDEX(campaigns!$A$2:$A$51,2)="","",INDEX(campaigns!$BW$2:$BW$51,2)) -> RELEASED 2026-12-18: ship by Tue 2026-12-22 (latest Mon 2026-12-28) | F51: =IF(INDEX(campaigns!$A$2:$A$51,2)="","",INDEX(campaigns!$BO$2:$BO$51,2)) -> 5 | G51: =IF(INDEX(campaigns!$A$2:$A$51,2)="","",INDEX(campaigns!$BP$2:$BP$51,2)) -> 5 | H51: =IF(INDEX(campaigns!$A$2:$A$51,2)="","",INDEX(campaigns!$F$2:$F$51,2)) -> 5 | I51: =IF(INDEX(campaigns!$A$2:$A$51,2)="","",INDEX(campaigns!$CB$2:$CB$51,2)) -> 250 | J51: =IF(INDEX(campaigns!$A$2:$A$51,2)="","",INDEX(campaigns!$CD$2:$CD$51,2)) -> 250 | K51: =IF(INDEX(campaigns!$A$2:$A$51,2)="","",INDEX(campaigns!$CE$2:$CE$51,2)) -> 1 | L51: =IF(INDEX(campaigns!$A$2:$A$51,2)="","",INDEX(campaigns!$CF$2:$CF$51,2)) -> 6 | M51: =IF(INDEX(campaigns!$A$2:$A$51,2)="","",INDEX(campaigns!$CG$2:$CG$51,2)) -> 238 | N51: =IF(INDEX(campaigns!$A$2:$A$51,2)="","",INDEX(campaigns!$CH$2:$CH$51,2)) -> 32 | O51: =IF(INDEX(campaigns!$A$2:$A$51,2)="","",INDEX(campaigns!$CI$2:$CI$51,2)) -> 5 | P51: =IF(INDEX(campaigns!$A$2:$A$51,2)="","",INDEX(campaigns!$CK$2:$CK$51,2)) -> 21 | Q51: =IF(INDEX(campaigns!$A$2:$A$51,2)="","",INDEX(campaigns!$CP$2:$CP$51,2)) -> 4.1 | R51: =IF(INDEX(campaigns!$A$2:$A$51,2)="","",INDEX(campaigns!$CX$2:$CX$51,2)) -> 39 | S51: =IF(INDEX(campaigns!$A$2:$A$51,2)="","",INDEX(campaigns!$CZ$2:$CZ$51,2)) -> 4 | T51: =IF(INDEX(campaigns!$A$2:$A$51,2)="","",INDEX(campaigns!$DC$2:$DC$51,2)) -> 600 | U51: =IF(INDEX(campaigns!$A$2:$A$51,2)="","",INDEX(campaigns!$DM$2:$DM$51,2)) -> 18.39 | V51: =IF(INDEX(campaigns!$A$2:$A$51,2)="","",INDEX(campaigns!$DS$2:$DS$51,2)) -> pass | W51: =IF(INDEX(campaigns!$A$2:$A$51,2)="","",INDEX(campaigns!$DT$2:$DT$51,2)) -> pass | X51: =IF(INDEX(campaigns!$A$2:$A$51,2)="","",INDEX(campaigns!$DU$2:$DU$51,2)) -> pass | Y51: =IF(INDEX(campaigns!$A$2:$A$51,2)="","",INDEX(campaigns!$AV$2:$AV$51,2)) -> maybe | Z51: =IF(INDEX(campaigns!$A$2:$A$51,2)="","",INDEX(campaigns!$DV$2:$DV$51,2))
A52: =IF(INDEX(campaigns!$A$2:$A$51,3)="","",INDEX(campaigns!$A$2:$A$51,3)) -> SAMPLE-CMP-003 | B52: =IF(INDEX(campaigns!$A$2:$A$51,3)="","",INDEX(campaigns!$BE$2:$BE$51,3)) -> SAMPLE Tallgrass | C52: =IF(INDEX(campaigns!$A$2:$A$51,3)="","",INDEX(campaigns!$BG$2:$BG$51,3)) -> 46427 | D52: =IF(INDEX(campaigns!$A$2:$A$51,3)="","",INDEX(campaigns!$D$2:$D$51,3)) -> standard | E52: =IF(INDEX(campaigns!$A$2:$A$51,3)="","",INDEX(campaigns!$BW$2:$BW$51,3)) -> RELEASED 2027-01-14: ship by Tue 2027-01-26 (latest Tue 2027-01-26) | F52: =IF(INDEX(campaigns!$A$2:$A$51,3)="","",INDEX(campaigns!$BO$2:$BO$51,3)) -> 10 | G52: =IF(INDEX(campaigns!$A$2:$A$51,3)="","",INDEX(campaigns!$BP$2:$BP$51,3)) -> 10 | H52: =IF(INDEX(campaigns!$A$2:$A$51,3)="","",INDEX(campaigns!$F$2:$F$51,3)) -> 10 | I52: =IF(INDEX(campaigns!$A$2:$A$51,3)="","",INDEX(campaigns!$CB$2:$CB$51,3)) -> 485 | J52: =IF(INDEX(campaigns!$A$2:$A$51,3)="","",INDEX(campaigns!$CD$2:$CD$51,3)) -> 485 | K52: =IF(INDEX(campaigns!$A$2:$A$51,3)="","",INDEX(campaigns!$CE$2:$CE$51,3)) -> 1 | L52: =IF(INDEX(campaigns!$A$2:$A$51,3)="","",INDEX(campaigns!$CF$2:$CF$51,3)) -> 0 | M52: =IF(INDEX(campaigns!$A$2:$A$51,3)="","",INDEX(campaigns!$CG$2:$CG$51,3)) -> 443 | N52: =IF(INDEX(campaigns!$A$2:$A$51,3)="","",INDEX(campaigns!$CH$2:$CH$51,3)) -> 76 | O52: =IF(INDEX(campaigns!$A$2:$A$51,3)="","",INDEX(campaigns!$CI$2:$CI$51,3)) -> 6 | P52: =IF(INDEX(campaigns!$A$2:$A$51,3)="","",INDEX(campaigns!$CK$2:$CK$51,3)) -> 54 | Q52: =IF(INDEX(campaigns!$A$2:$A$51,3)="","",INDEX(campaigns!$CP$2:$CP$51,3)) -> 4.1 | R52: =IF(INDEX(campaigns!$A$2:$A$51,3)="","",INDEX(campaigns!$CX$2:$CX$51,3)) -> 83 | S52: =IF(INDEX(campaigns!$A$2:$A$51,3)="","",INDEX(campaigns!$CZ$2:$CZ$51,3)) -> 17 | T52: =IF(INDEX(campaigns!$A$2:$A$51,3)="","",INDEX(campaigns!$DC$2:$DC$51,3)) -> 1500 | U52: =IF(INDEX(campaigns!$A$2:$A$51,3)="","",INDEX(campaigns!$DM$2:$DM$51,3)) -> 73.42 | V52: =IF(INDEX(campaigns!$A$2:$A$51,3)="","",INDEX(campaigns!$DS$2:$DS$51,3)) -> pass | W52: =IF(INDEX(campaigns!$A$2:$A$51,3)="","",INDEX(campaigns!$DT$2:$DT$51,3)) -> pass | X52: =IF(INDEX(campaigns!$A$2:$A$51,3)="","",INDEX(campaigns!$DU$2:$DU$51,3)) -> pass | Y52: =IF(INDEX(campaigns!$A$2:$A$51,3)="","",INDEX(campaigns!$AV$2:$AV$51,3)) -> yes | Z52: =IF(INDEX(campaigns!$A$2:$A$51,3)="","",INDEX(campaigns!$DV$2:$DV$51,3))
A53: =IF(INDEX(campaigns!$A$2:$A$51,4)="","",INDEX(campaigns!$A$2:$A$51,4)) -> SAMPLE-CMP-004 | B53: =IF(INDEX(campaigns!$A$2:$A$51,4)="","",INDEX(campaigns!$BE$2:$BE$51,4)) -> SAMPLE Orchard Row | C53: =IF(INDEX(campaigns!$A$2:$A$51,4)="","",INDEX(campaigns!$BG$2:$BG$51,4)) -> 46427 | D53: =IF(INDEX(campaigns!$A$2:$A$51,4)="","",INDEX(campaigns!$D$2:$D$51,4)) -> standard | E53: =IF(INDEX(campaigns!$A$2:$A$51,4)="","",INDEX(campaigns!$BW$2:$BW$51,4)) -> RELEASED 2027-01-14: ship by Tue 2027-01-26 (latest Tue 2027-01-26) | F53: =IF(INDEX(campaigns!$A$2:$A$51,4)="","",INDEX(campaigns!$BO$2:$BO$51,4)) -> 9 | G53: =IF(INDEX(campaigns!$A$2:$A$51,4)="","",INDEX(campaigns!$BP$2:$BP$51,4)) -> 9 | H53: =IF(INDEX(campaigns!$A$2:$A$51,4)="","",INDEX(campaigns!$F$2:$F$51,4)) -> 10 | I53: =IF(INDEX(campaigns!$A$2:$A$51,4)="","",INDEX(campaigns!$CB$2:$CB$51,4)) -> 455 | J53: =IF(INDEX(campaigns!$A$2:$A$51,4)="","",INDEX(campaigns!$CD$2:$CD$51,4)) -> 455 | K53: =IF(INDEX(campaigns!$A$2:$A$51,4)="","",INDEX(campaigns!$CE$2:$CE$51,4)) -> 1 | L53: =IF(INDEX(campaigns!$A$2:$A$51,4)="","",INDEX(campaigns!$CF$2:$CF$51,4)) -> 6 | M53: =IF(INDEX(campaigns!$A$2:$A$51,4)="","",INDEX(campaigns!$CG$2:$CG$51,4)) -> 428 | N53: =IF(INDEX(campaigns!$A$2:$A$51,4)="","",INDEX(campaigns!$CH$2:$CH$51,4)) -> 71 | O53: =IF(INDEX(campaigns!$A$2:$A$51,4)="","",INDEX(campaigns!$CI$2:$CI$51,4)) -> 6 | P53: =IF(INDEX(campaigns!$A$2:$A$51,4)="","",INDEX(campaigns!$CK$2:$CK$51,4)) -> 55 | Q53: =IF(INDEX(campaigns!$A$2:$A$51,4)="","",INDEX(campaigns!$CP$2:$CP$51,4)) -> 4.2 | R53: =IF(INDEX(campaigns!$A$2:$A$51,4)="","",INDEX(campaigns!$CX$2:$CX$51,4)) -> 71 | S53: =IF(INDEX(campaigns!$A$2:$A$51,4)="","",INDEX(campaigns!$CZ$2:$CZ$51,4)) -> 8 | T53: =IF(INDEX(campaigns!$A$2:$A$51,4)="","",INDEX(campaigns!$DC$2:$DC$51,4)) -> 1350 | U53: =IF(INDEX(campaigns!$A$2:$A$51,4)="","",INDEX(campaigns!$DM$2:$DM$51,4)) -> 69.92 | V53: =IF(INDEX(campaigns!$A$2:$A$51,4)="","",INDEX(campaigns!$DS$2:$DS$51,4)) -> pass | W53: =IF(INDEX(campaigns!$A$2:$A$51,4)="","",INDEX(campaigns!$DT$2:$DT$51,4)) -> pass | X53: =IF(INDEX(campaigns!$A$2:$A$51,4)="","",INDEX(campaigns!$DU$2:$DU$51,4)) -> pass | Y53: =IF(INDEX(campaigns!$A$2:$A$51,4)="","",INDEX(campaigns!$AV$2:$AV$51,4)) -> maybe | Z53: =IF(INDEX(campaigns!$A$2:$A$51,4)="","",INDEX(campaigns!$DV$2:$DV$51,4)) -> info: 1 office(s) short of the contract: add a roster office or credit $150 each;
A54: =IF(INDEX(campaigns!$A$2:$A$51,5)="","",INDEX(campaigns!$A$2:$A$51,5)) -> SAMPLE-CMP-005 | B54: =IF(INDEX(campaigns!$A$2:$A$51,5)="","",INDEX(campaigns!$BE$2:$BE$51,5)) -> SAMPLE Kettle Ridge | C54: =IF(INDEX(campaigns!$A$2:$A$51,5)="","",INDEX(campaigns!$BG$2:$BG$51,5)) -> 46427 | D54: =IF(INDEX(campaigns!$A$2:$A$51,5)="","",INDEX(campaigns!$D$2:$D$51,5)) -> standard | E54: =IF(INDEX(campaigns!$A$2:$A$51,5)="","",INDEX(campaigns!$BW$2:$BW$51,5)) -> RELEASED 2027-01-14: ship by Tue 2027-01-26 (latest Tue 2027-01-26) | F54: =IF(INDEX(campaigns!$A$2:$A$51,5)="","",INDEX(campaigns!$BO$2:$BO$51,5)) -> 10 | G54: =IF(INDEX(campaigns!$A$2:$A$51,5)="","",INDEX(campaigns!$BP$2:$BP$51,5)) -> 10 | H54: =IF(INDEX(campaigns!$A$2:$A$51,5)="","",INDEX(campaigns!$F$2:$F$51,5)) -> 10 | I54: =IF(INDEX(campaigns!$A$2:$A$51,5)="","",INDEX(campaigns!$CB$2:$CB$51,5)) -> 515 | J54: =IF(INDEX(campaigns!$A$2:$A$51,5)="","",INDEX(campaigns!$CD$2:$CD$51,5)) -> 515 | K54: =IF(INDEX(campaigns!$A$2:$A$51,5)="","",INDEX(campaigns!$CE$2:$CE$51,5)) -> 1 | L54: =IF(INDEX(campaigns!$A$2:$A$51,5)="","",INDEX(campaigns!$CF$2:$CF$51,5)) -> 12 | M54: =IF(INDEX(campaigns!$A$2:$A$51,5)="","",INDEX(campaigns!$CG$2:$CG$51,5)) -> 474 | N54: =IF(INDEX(campaigns!$A$2:$A$51,5)="","",INDEX(campaigns!$CH$2:$CH$51,5)) -> 77 | O54: =IF(INDEX(campaigns!$A$2:$A$51,5)="","",INDEX(campaigns!$CI$2:$CI$51,5)) -> 4 | P54: =IF(INDEX(campaigns!$A$2:$A$51,5)="","",INDEX(campaigns!$CK$2:$CK$51,5)) -> 51 | Q54: =IF(INDEX(campaigns!$A$2:$A$51,5)="","",INDEX(campaigns!$CP$2:$CP$51,5)) -> 4.3 | R54: =IF(INDEX(campaigns!$A$2:$A$51,5)="","",INDEX(campaigns!$CX$2:$CX$51,5)) -> 79 | S54: =IF(INDEX(campaigns!$A$2:$A$51,5)="","",INDEX(campaigns!$CZ$2:$CZ$51,5)) -> 21 | T54: =IF(INDEX(campaigns!$A$2:$A$51,5)="","",INDEX(campaigns!$DC$2:$DC$51,5)) -> 1500 | U54: =IF(INDEX(campaigns!$A$2:$A$51,5)="","",INDEX(campaigns!$DM$2:$DM$51,5)) -> 73.42 | V54: =IF(INDEX(campaigns!$A$2:$A$51,5)="","",INDEX(campaigns!$DS$2:$DS$51,5)) -> pass | W54: =IF(INDEX(campaigns!$A$2:$A$51,5)="","",INDEX(campaigns!$DT$2:$DT$51,5)) -> miss | X54: =IF(INDEX(campaigns!$A$2:$A$51,5)="","",INDEX(campaigns!$DU$2:$DU$51,5)) -> pass | Y54: =IF(INDEX(campaigns!$A$2:$A$51,5)="","",INDEX(campaigns!$AV$2:$AV$51,5)) -> yes | Z54: =IF(INDEX(campaigns!$A$2:$A$51,5)="","",INDEX(campaigns!$DV$2:$DV$51,5))
A55: =IF(INDEX(campaigns!$A$2:$A$51,6)="","",INDEX(campaigns!$A$2:$A$51,6)) -> SAMPLE-CMP-006 | B55: =IF(INDEX(campaigns!$A$2:$A$51,6)="","",INDEX(campaigns!$BE$2:$BE$51,6)) -> SAMPLE Saltmarsh | C55: =IF(INDEX(campaigns!$A$2:$A$51,6)="","",INDEX(campaigns!$BG$2:$BG$51,6)) -> 46441 | D55: =IF(INDEX(campaigns!$A$2:$A$51,6)="","",INDEX(campaigns!$D$2:$D$51,6)) -> standard | E55: =IF(INDEX(campaigns!$A$2:$A$51,6)="","",INDEX(campaigns!$BW$2:$BW$51,6)) -> RELEASED 2027-01-28: ship by Mon 2027-02-08 (latest Mon 2027-02-08) | F55: =IF(INDEX(campaigns!$A$2:$A$51,6)="","",INDEX(campaigns!$BO$2:$BO$51,6)) -> 10 | G55: =IF(INDEX(campaigns!$A$2:$A$51,6)="","",INDEX(campaigns!$BP$2:$BP$51,6)) -> 9 | H55: =IF(INDEX(campaigns!$A$2:$A$51,6)="","",INDEX(campaigns!$F$2:$F$51,6)) -> 10 | I55: =IF(INDEX(campaigns!$A$2:$A$51,6)="","",INDEX(campaigns!$CB$2:$CB$51,6)) -> 425 | J55: =IF(INDEX(campaigns!$A$2:$A$51,6)="","",INDEX(campaigns!$CD$2:$CD$51,6)) -> 425 | K55: =IF(INDEX(campaigns!$A$2:$A$51,6)="","",INDEX(campaigns!$CE$2:$CE$51,6)) -> 1 | L55: =IF(INDEX(campaigns!$A$2:$A$51,6)="","",INDEX(campaigns!$CF$2:$CF$51,6)) -> 12 | M55: =IF(INDEX(campaigns!$A$2:$A$51,6)="","",INDEX(campaigns!$CG$2:$CG$51,6)) -> 408 | N55: =IF(INDEX(campaigns!$A$2:$A$51,6)="","",INDEX(campaigns!$CH$2:$CH$51,6)) -> 62 | O55: =IF(INDEX(campaigns!$A$2:$A$51,6)="","",INDEX(campaigns!$CI$2:$CI$51,6)) -> 5 | P55: =IF(INDEX(campaigns!$A$2:$A$51,6)="","",INDEX(campaigns!$CK$2:$CK$51,6)) -> 49 | Q55: =IF(INDEX(campaigns!$A$2:$A$51,6)="","",INDEX(campaigns!$CP$2:$CP$51,6)) -> 4.4 | R55: =IF(INDEX(campaigns!$A$2:$A$51,6)="","",INDEX(campaigns!$CX$2:$CX$51,6)) -> 71 | S55: =IF(INDEX(campaigns!$A$2:$A$51,6)="","",INDEX(campaigns!$CZ$2:$CZ$51,6)) -> 7 | T55: =IF(INDEX(campaigns!$A$2:$A$51,6)="","",INDEX(campaigns!$DC$2:$DC$51,6)) -> 1350 | U55: =IF(INDEX(campaigns!$A$2:$A$51,6)="","",INDEX(campaigns!$DM$2:$DM$51,6)) -> 47.32 | V55: =IF(INDEX(campaigns!$A$2:$A$51,6)="","",INDEX(campaigns!$DS$2:$DS$51,6)) -> pass | W55: =IF(INDEX(campaigns!$A$2:$A$51,6)="","",INDEX(campaigns!$DT$2:$DT$51,6)) -> pass | X55: =IF(INDEX(campaigns!$A$2:$A$51,6)="","",INDEX(campaigns!$DU$2:$DU$51,6)) -> pass | Y55: =IF(INDEX(campaigns!$A$2:$A$51,6)="","",INDEX(campaigns!$AV$2:$AV$51,6)) -> yes | Z55: =IF(INDEX(campaigns!$A$2:$A$51,6)="","",INDEX(campaigns!$DV$2:$DV$51,6))
A56: =IF(INDEX(campaigns!$A$2:$A$51,7)="","",INDEX(campaigns!$A$2:$A$51,7)) -> SAMPLE-CMP-007 | B56: =IF(INDEX(campaigns!$A$2:$A$51,7)="","",INDEX(campaigns!$BE$2:$BE$51,7)) -> SAMPLE Brightside | C56: =IF(INDEX(campaigns!$A$2:$A$51,7)="","",INDEX(campaigns!$BG$2:$BG$51,7)) -> 46469 | D56: =IF(INDEX(campaigns!$A$2:$A$51,7)="","",INDEX(campaigns!$D$2:$D$51,7)) -> founding | E56: =IF(INDEX(campaigns!$A$2:$A$51,7)="","",INDEX(campaigns!$BW$2:$BW$51,7)) -> RELEASED 2027-03-01: ship by Tue 2027-03-09 (latest Tue 2027-03-09) | F56: =IF(INDEX(campaigns!$A$2:$A$51,7)="","",INDEX(campaigns!$BO$2:$BO$51,7)) -> 10 | G56: =IF(INDEX(campaigns!$A$2:$A$51,7)="","",INDEX(campaigns!$BP$2:$BP$51,7)) -> 10 | H56: =IF(INDEX(campaigns!$A$2:$A$51,7)="","",INDEX(campaigns!$F$2:$F$51,7)) -> 10 | I56: =IF(INDEX(campaigns!$A$2:$A$51,7)="","",INDEX(campaigns!$CB$2:$CB$51,7)) -> 0 | J56: =IF(INDEX(campaigns!$A$2:$A$51,7)="","",INDEX(campaigns!$CD$2:$CD$51,7)) -> 0 | K56: =IF(INDEX(campaigns!$A$2:$A$51,7)="","",INDEX(campaigns!$CE$2:$CE$51,7)) | L56: =IF(INDEX(campaigns!$A$2:$A$51,7)="","",INDEX(campaigns!$CF$2:$CF$51,7)) -> 0 | M56: =IF(INDEX(campaigns!$A$2:$A$51,7)="","",INDEX(campaigns!$CG$2:$CG$51,7)) | N56: =IF(INDEX(campaigns!$A$2:$A$51,7)="","",INDEX(campaigns!$CH$2:$CH$51,7)) -> 0 | O56: =IF(INDEX(campaigns!$A$2:$A$51,7)="","",INDEX(campaigns!$CI$2:$CI$51,7)) -> 0 | P56: =IF(INDEX(campaigns!$A$2:$A$51,7)="","",INDEX(campaigns!$CK$2:$CK$51,7)) -> 0 | Q56: =IF(INDEX(campaigns!$A$2:$A$51,7)="","",INDEX(campaigns!$CP$2:$CP$51,7)) | R56: =IF(INDEX(campaigns!$A$2:$A$51,7)="","",INDEX(campaigns!$CX$2:$CX$51,7)) -> 0 | S56: =IF(INDEX(campaigns!$A$2:$A$51,7)="","",INDEX(campaigns!$CZ$2:$CZ$51,7)) | T56: =IF(INDEX(campaigns!$A$2:$A$51,7)="","",INDEX(campaigns!$DC$2:$DC$51,7)) -> 1200 | U56: =IF(INDEX(campaigns!$A$2:$A$51,7)="","",INDEX(campaigns!$DM$2:$DM$51,7)) -> 274.38 | V56: =IF(INDEX(campaigns!$A$2:$A$51,7)="","",INDEX(campaigns!$DS$2:$DS$51,7)) | W56: =IF(INDEX(campaigns!$A$2:$A$51,7)="","",INDEX(campaigns!$DT$2:$DT$51,7)) -> miss | X56: =IF(INDEX(campaigns!$A$2:$A$51,7)="","",INDEX(campaigns!$DU$2:$DU$51,7)) -> due | Y56: =IF(INDEX(campaigns!$A$2:$A$51,7)="","",INDEX(campaigns!$AV$2:$AV$51,7)) -> 0 | Z56: =IF(INDEX(campaigns!$A$2:$A$51,7)="","",INDEX(campaigns!$DV$2:$DV$51,7)) -> info: brand insurance ends 2027-06-30: diary the renewal certificate;
A57: =IF(INDEX(campaigns!$A$2:$A$51,8)="","",INDEX(campaigns!$A$2:$A$51,8)) -> SAMPLE-CMP-008 | B57: =IF(INDEX(campaigns!$A$2:$A$51,8)="","",INDEX(campaigns!$BE$2:$BE$51,8)) -> SAMPLE Tallgrass | C57: =IF(INDEX(campaigns!$A$2:$A$51,8)="","",INDEX(campaigns!$BG$2:$BG$51,8)) -> 46469 | D57: =IF(INDEX(campaigns!$A$2:$A$51,8)="","",INDEX(campaigns!$D$2:$D$51,8)) -> standard | E57: =IF(INDEX(campaigns!$A$2:$A$51,8)="","",INDEX(campaigns!$BW$2:$BW$51,8)) -> RELEASED 2027-02-26: ship by Tue 2027-03-09 (latest Tue 2027-03-09) | F57: =IF(INDEX(campaigns!$A$2:$A$51,8)="","",INDEX(campaigns!$BO$2:$BO$51,8)) -> 10 | G57: =IF(INDEX(campaigns!$A$2:$A$51,8)="","",INDEX(campaigns!$BP$2:$BP$51,8)) -> 10 | H57: =IF(INDEX(campaigns!$A$2:$A$51,8)="","",INDEX(campaigns!$F$2:$F$51,8)) -> 10 | I57: =IF(INDEX(campaigns!$A$2:$A$51,8)="","",INDEX(campaigns!$CB$2:$CB$51,8)) -> 0 | J57: =IF(INDEX(campaigns!$A$2:$A$51,8)="","",INDEX(campaigns!$CD$2:$CD$51,8)) -> 0 | K57: =IF(INDEX(campaigns!$A$2:$A$51,8)="","",INDEX(campaigns!$CE$2:$CE$51,8)) | L57: =IF(INDEX(campaigns!$A$2:$A$51,8)="","",INDEX(campaigns!$CF$2:$CF$51,8)) -> 0 | M57: =IF(INDEX(campaigns!$A$2:$A$51,8)="","",INDEX(campaigns!$CG$2:$CG$51,8)) | N57: =IF(INDEX(campaigns!$A$2:$A$51,8)="","",INDEX(campaigns!$CH$2:$CH$51,8)) -> 0 | O57: =IF(INDEX(campaigns!$A$2:$A$51,8)="","",INDEX(campaigns!$CI$2:$CI$51,8)) -> 0 | P57: =IF(INDEX(campaigns!$A$2:$A$51,8)="","",INDEX(campaigns!$CK$2:$CK$51,8)) -> 0 | Q57: =IF(INDEX(campaigns!$A$2:$A$51,8)="","",INDEX(campaigns!$CP$2:$CP$51,8)) | R57: =IF(INDEX(campaigns!$A$2:$A$51,8)="","",INDEX(campaigns!$CX$2:$CX$51,8)) -> 0 | S57: =IF(INDEX(campaigns!$A$2:$A$51,8)="","",INDEX(campaigns!$CZ$2:$CZ$51,8)) | T57: =IF(INDEX(campaigns!$A$2:$A$51,8)="","",INDEX(campaigns!$DC$2:$DC$51,8)) -> 750 | U57: =IF(INDEX(campaigns!$A$2:$A$51,8)="","",INDEX(campaigns!$DM$2:$DM$51,8)) -> 161.88 | V57: =IF(INDEX(campaigns!$A$2:$A$51,8)="","",INDEX(campaigns!$DS$2:$DS$51,8)) | W57: =IF(INDEX(campaigns!$A$2:$A$51,8)="","",INDEX(campaigns!$DT$2:$DT$51,8)) -> miss | X57: =IF(INDEX(campaigns!$A$2:$A$51,8)="","",INDEX(campaigns!$DU$2:$DU$51,8)) -> due | Y57: =IF(INDEX(campaigns!$A$2:$A$51,8)="","",INDEX(campaigns!$AV$2:$AV$51,8)) -> 0 | Z57: =IF(INDEX(campaigns!$A$2:$A$51,8)="","",INDEX(campaigns!$DV$2:$DV$51,8))
A58: =IF(INDEX(campaigns!$A$2:$A$51,9)="","",INDEX(campaigns!$A$2:$A$51,9)) | B58: =IF(INDEX(campaigns!$A$2:$A$51,9)="","",INDEX(campaigns!$BE$2:$BE$51,9)) | C58: =IF(INDEX(campaigns!$A$2:$A$51,9)="","",INDEX(campaigns!$BG$2:$BG$51,9)) | D58: =IF(INDEX(campaigns!$A$2:$A$51,9)="","",INDEX(campaigns!$D$2:$D$51,9)) | E58: =IF(INDEX(campaigns!$A$2:$A$51,9)="","",INDEX(campaigns!$BW$2:$BW$51,9)) | F58: =IF(INDEX(campaigns!$A$2:$A$51,9)="","",INDEX(campaigns!$BO$2:$BO$51,9)) | G58: =IF(INDEX(campaigns!$A$2:$A$51,9)="","",INDEX(campaigns!$BP$2:$BP$51,9)) | H58: =IF(INDEX(campaigns!$A$2:$A$51,9)="","",INDEX(campaigns!$F$2:$F$51,9)) | I58: =IF(INDEX(campaigns!$A$2:$A$51,9)="","",INDEX(campaigns!$CB$2:$CB$51,9)) | J58: =IF(INDEX(campaigns!$A$2:$A$51,9)="","",INDEX(campaigns!$CD$2:$CD$51,9)) | K58: =IF(INDEX(campaigns!$A$2:$A$51,9)="","",INDEX(campaigns!$CE$2:$CE$51,9)) | L58: =IF(INDEX(campaigns!$A$2:$A$51,9)="","",INDEX(campaigns!$CF$2:$CF$51,9)) | M58: =IF(INDEX(campaigns!$A$2:$A$51,9)="","",INDEX(campaigns!$CG$2:$CG$51,9)) | N58: =IF(INDEX(campaigns!$A$2:$A$51,9)="","",INDEX(campaigns!$CH$2:$CH$51,9)) | O58: =IF(INDEX(campaigns!$A$2:$A$51,9)="","",INDEX(campaigns!$CI$2:$CI$51,9)) | P58: =IF(INDEX(campaigns!$A$2:$A$51,9)="","",INDEX(campaigns!$CK$2:$CK$51,9)) | Q58: =IF(INDEX(campaigns!$A$2:$A$51,9)="","",INDEX(campaigns!$CP$2:$CP$51,9)) | R58: =IF(INDEX(campaigns!$A$2:$A$51,9)="","",INDEX(campaigns!$CX$2:$CX$51,9)) | S58: =IF(INDEX(campaigns!$A$2:$A$51,9)="","",INDEX(campaigns!$CZ$2:$CZ$51,9)) | T58: =IF(INDEX(campaigns!$A$2:$A$51,9)="","",INDEX(campaigns!$DC$2:$DC$51,9)) | U58: =IF(INDEX(campaigns!$A$2:$A$51,9)="","",INDEX(campaigns!$DM$2:$DM$51,9)) | V58: =IF(INDEX(campaigns!$A$2:$A$51,9)="","",INDEX(campaigns!$DS$2:$DS$51,9)) | W58: =IF(INDEX(campaigns!$A$2:$A$51,9)="","",INDEX(campaigns!$DT$2:$DT$51,9)) | X58: =IF(INDEX(campaigns!$A$2:$A$51,9)="","",INDEX(campaigns!$DU$2:$DU$51,9)) | Y58: =IF(INDEX(campaigns!$A$2:$A$51,9)="","",INDEX(campaigns!$AV$2:$AV$51,9)) | Z58: =IF(INDEX(campaigns!$A$2:$A$51,9)="","",INDEX(campaigns!$DV$2:$DV$51,9))
A59: =IF(INDEX(campaigns!$A$2:$A$51,10)="","",INDEX(campaigns!$A$2:$A$51,10)) | B59: =IF(INDEX(campaigns!$A$2:$A$51,10)="","",INDEX(campaigns!$BE$2:$BE$51,10)) | C59: =IF(INDEX(campaigns!$A$2:$A$51,10)="","",INDEX(campaigns!$BG$2:$BG$51,10)) | D59: =IF(INDEX(campaigns!$A$2:$A$51,10)="","",INDEX(campaigns!$D$2:$D$51,10)) | E59: =IF(INDEX(campaigns!$A$2:$A$51,10)="","",INDEX(campaigns!$BW$2:$BW$51,10)) | F59: =IF(INDEX(campaigns!$A$2:$A$51,10)="","",INDEX(campaigns!$BO$2:$BO$51,10)) | G59: =IF(INDEX(campaigns!$A$2:$A$51,10)="","",INDEX(campaigns!$BP$2:$BP$51,10)) | H59: =IF(INDEX(campaigns!$A$2:$A$51,10)="","",INDEX(campaigns!$F$2:$F$51,10)) | I59: =IF(INDEX(campaigns!$A$2:$A$51,10)="","",INDEX(campaigns!$CB$2:$CB$51,10)) | J59: =IF(INDEX(campaigns!$A$2:$A$51,10)="","",INDEX(campaigns!$CD$2:$CD$51,10)) | K59: =IF(INDEX(campaigns!$A$2:$A$51,10)="","",INDEX(campaigns!$CE$2:$CE$51,10)) | L59: =IF(INDEX(campaigns!$A$2:$A$51,10)="","",INDEX(campaigns!$CF$2:$CF$51,10)) | M59: =IF(INDEX(campaigns!$A$2:$A$51,10)="","",INDEX(campaigns!$CG$2:$CG$51,10)) | N59: =IF(INDEX(campaigns!$A$2:$A$51,10)="","",INDEX(campaigns!$CH$2:$CH$51,10)) | O59: =IF(INDEX(campaigns!$A$2:$A$51,10)="","",INDEX(campaigns!$CI$2:$CI$51,10)) | P59: =IF(INDEX(campaigns!$A$2:$A$51,10)="","",INDEX(campaigns!$CK$2:$CK$51,10)) | Q59: =IF(INDEX(campaigns!$A$2:$A$51,10)="","",INDEX(campaigns!$CP$2:$CP$51,10)) | R59: =IF(INDEX(campaigns!$A$2:$A$51,10)="","",INDEX(campaigns!$CX$2:$CX$51,10)) | S59: =IF(INDEX(campaigns!$A$2:$A$51,10)="","",INDEX(campaigns!$CZ$2:$CZ$51,10)) | T59: =IF(INDEX(campaigns!$A$2:$A$51,10)="","",INDEX(campaigns!$DC$2:$DC$51,10)) | U59: =IF(INDEX(campaigns!$A$2:$A$51,10)="","",INDEX(campaigns!$DM$2:$DM$51,10)) | V59: =IF(INDEX(campaigns!$A$2:$A$51,10)="","",INDEX(campaigns!$DS$2:$DS$51,10)) | W59: =IF(INDEX(campaigns!$A$2:$A$51,10)="","",INDEX(campaigns!$DT$2:$DT$51,10)) | X59: =IF(INDEX(campaigns!$A$2:$A$51,10)="","",INDEX(campaigns!$DU$2:$DU$51,10)) | Y59: =IF(INDEX(campaigns!$A$2:$A$51,10)="","",INDEX(campaigns!$AV$2:$AV$51,10)) | Z59: =IF(INDEX(campaigns!$A$2:$A$51,10)="","",INDEX(campaigns!$DV$2:$DV$51,10))
A60: =IF(INDEX(campaigns!$A$2:$A$51,11)="","",INDEX(campaigns!$A$2:$A$51,11)) | B60: =IF(INDEX(campaigns!$A$2:$A$51,11)="","",INDEX(campaigns!$BE$2:$BE$51,11)) | C60: =IF(INDEX(campaigns!$A$2:$A$51,11)="","",INDEX(campaigns!$BG$2:$BG$51,11)) | D60: =IF(INDEX(campaigns!$A$2:$A$51,11)="","",INDEX(campaigns!$D$2:$D$51,11)) | E60: =IF(INDEX(campaigns!$A$2:$A$51,11)="","",INDEX(campaigns!$BW$2:$BW$51,11)) | F60: =IF(INDEX(campaigns!$A$2:$A$51,11)="","",INDEX(campaigns!$BO$2:$BO$51,11)) | G60: =IF(INDEX(campaigns!$A$2:$A$51,11)="","",INDEX(campaigns!$BP$2:$BP$51,11)) | H60: =IF(INDEX(campaigns!$A$2:$A$51,11)="","",INDEX(campaigns!$F$2:$F$51,11)) | I60: =IF(INDEX(campaigns!$A$2:$A$51,11)="","",INDEX(campaigns!$CB$2:$CB$51,11)) | J60: =IF(INDEX(campaigns!$A$2:$A$51,11)="","",INDEX(campaigns!$CD$2:$CD$51,11)) | K60: =IF(INDEX(campaigns!$A$2:$A$51,11)="","",INDEX(campaigns!$CE$2:$CE$51,11)) | L60: =IF(INDEX(campaigns!$A$2:$A$51,11)="","",INDEX(campaigns!$CF$2:$CF$51,11)) | M60: =IF(INDEX(campaigns!$A$2:$A$51,11)="","",INDEX(campaigns!$CG$2:$CG$51,11)) | N60: =IF(INDEX(campaigns!$A$2:$A$51,11)="","",INDEX(campaigns!$CH$2:$CH$51,11)) | O60: =IF(INDEX(campaigns!$A$2:$A$51,11)="","",INDEX(campaigns!$CI$2:$CI$51,11)) | P60: =IF(INDEX(campaigns!$A$2:$A$51,11)="","",INDEX(campaigns!$CK$2:$CK$51,11)) | Q60: =IF(INDEX(campaigns!$A$2:$A$51,11)="","",INDEX(campaigns!$CP$2:$CP$51,11)) | R60: =IF(INDEX(campaigns!$A$2:$A$51,11)="","",INDEX(campaigns!$CX$2:$CX$51,11)) | S60: =IF(INDEX(campaigns!$A$2:$A$51,11)="","",INDEX(campaigns!$CZ$2:$CZ$51,11)) | T60: =IF(INDEX(campaigns!$A$2:$A$51,11)="","",INDEX(campaigns!$DC$2:$DC$51,11)) | U60: =IF(INDEX(campaigns!$A$2:$A$51,11)="","",INDEX(campaigns!$DM$2:$DM$51,11)) | V60: =IF(INDEX(campaigns!$A$2:$A$51,11)="","",INDEX(campaigns!$DS$2:$DS$51,11)) | W60: =IF(INDEX(campaigns!$A$2:$A$51,11)="","",INDEX(campaigns!$DT$2:$DT$51,11)) | X60: =IF(INDEX(campaigns!$A$2:$A$51,11)="","",INDEX(campaigns!$DU$2:$DU$51,11)) | Y60: =IF(INDEX(campaigns!$A$2:$A$51,11)="","",INDEX(campaigns!$AV$2:$AV$51,11)) | Z60: =IF(INDEX(campaigns!$A$2:$A$51,11)="","",INDEX(campaigns!$DV$2:$DV$51,11))
A61: =IF(INDEX(campaigns!$A$2:$A$51,12)="","",INDEX(campaigns!$A$2:$A$51,12)) | B61: =IF(INDEX(campaigns!$A$2:$A$51,12)="","",INDEX(campaigns!$BE$2:$BE$51,12)) | C61: =IF(INDEX(campaigns!$A$2:$A$51,12)="","",INDEX(campaigns!$BG$2:$BG$51,12)) | D61: =IF(INDEX(campaigns!$A$2:$A$51,12)="","",INDEX(campaigns!$D$2:$D$51,12)) | E61: =IF(INDEX(campaigns!$A$2:$A$51,12)="","",INDEX(campaigns!$BW$2:$BW$51,12)) | F61: =IF(INDEX(campaigns!$A$2:$A$51,12)="","",INDEX(campaigns!$BO$2:$BO$51,12)) | G61: =IF(INDEX(campaigns!$A$2:$A$51,12)="","",INDEX(campaigns!$BP$2:$BP$51,12)) | H61: =IF(INDEX(campaigns!$A$2:$A$51,12)="","",INDEX(campaigns!$F$2:$F$51,12)) | I61: =IF(INDEX(campaigns!$A$2:$A$51,12)="","",INDEX(campaigns!$CB$2:$CB$51,12)) | J61: =IF(INDEX(campaigns!$A$2:$A$51,12)="","",INDEX(campaigns!$CD$2:$CD$51,12)) | K61: =IF(INDEX(campaigns!$A$2:$A$51,12)="","",INDEX(campaigns!$CE$2:$CE$51,12)) | L61: =IF(INDEX(campaigns!$A$2:$A$51,12)="","",INDEX(campaigns!$CF$2:$CF$51,12)) | M61: =IF(INDEX(campaigns!$A$2:$A$51,12)="","",INDEX(campaigns!$CG$2:$CG$51,12)) | N61: =IF(INDEX(campaigns!$A$2:$A$51,12)="","",INDEX(campaigns!$CH$2:$CH$51,12)) | O61: =IF(INDEX(campaigns!$A$2:$A$51,12)="","",INDEX(campaigns!$CI$2:$CI$51,12)) | P61: =IF(INDEX(campaigns!$A$2:$A$51,12)="","",INDEX(campaigns!$CK$2:$CK$51,12)) | Q61: =IF(INDEX(campaigns!$A$2:$A$51,12)="","",INDEX(campaigns!$CP$2:$CP$51,12)) | R61: =IF(INDEX(campaigns!$A$2:$A$51,12)="","",INDEX(campaigns!$CX$2:$CX$51,12)) | S61: =IF(INDEX(campaigns!$A$2:$A$51,12)="","",INDEX(campaigns!$CZ$2:$CZ$51,12)) | T61: =IF(INDEX(campaigns!$A$2:$A$51,12)="","",INDEX(campaigns!$DC$2:$DC$51,12)) | U61: =IF(INDEX(campaigns!$A$2:$A$51,12)="","",INDEX(campaigns!$DM$2:$DM$51,12)) | V61: =IF(INDEX(campaigns!$A$2:$A$51,12)="","",INDEX(campaigns!$DS$2:$DS$51,12)) | W61: =IF(INDEX(campaigns!$A$2:$A$51,12)="","",INDEX(campaigns!$DT$2:$DT$51,12)) | X61: =IF(INDEX(campaigns!$A$2:$A$51,12)="","",INDEX(campaigns!$DU$2:$DU$51,12)) | Y61: =IF(INDEX(campaigns!$A$2:$A$51,12)="","",INDEX(campaigns!$AV$2:$AV$51,12)) | Z61: =IF(INDEX(campaigns!$A$2:$A$51,12)="","",INDEX(campaigns!$DV$2:$DV$51,12))
A62: =IF(INDEX(campaigns!$A$2:$A$51,13)="","",INDEX(campaigns!$A$2:$A$51,13)) | B62: =IF(INDEX(campaigns!$A$2:$A$51,13)="","",INDEX(campaigns!$BE$2:$BE$51,13)) | C62: =IF(INDEX(campaigns!$A$2:$A$51,13)="","",INDEX(campaigns!$BG$2:$BG$51,13)) | D62: =IF(INDEX(campaigns!$A$2:$A$51,13)="","",INDEX(campaigns!$D$2:$D$51,13)) | E62: =IF(INDEX(campaigns!$A$2:$A$51,13)="","",INDEX(campaigns!$BW$2:$BW$51,13)) | F62: =IF(INDEX(campaigns!$A$2:$A$51,13)="","",INDEX(campaigns!$BO$2:$BO$51,13)) | G62: =IF(INDEX(campaigns!$A$2:$A$51,13)="","",INDEX(campaigns!$BP$2:$BP$51,13)) | H62: =IF(INDEX(campaigns!$A$2:$A$51,13)="","",INDEX(campaigns!$F$2:$F$51,13)) | I62: =IF(INDEX(campaigns!$A$2:$A$51,13)="","",INDEX(campaigns!$CB$2:$CB$51,13)) | J62: =IF(INDEX(campaigns!$A$2:$A$51,13)="","",INDEX(campaigns!$CD$2:$CD$51,13)) | K62: =IF(INDEX(campaigns!$A$2:$A$51,13)="","",INDEX(campaigns!$CE$2:$CE$51,13)) | L62: =IF(INDEX(campaigns!$A$2:$A$51,13)="","",INDEX(campaigns!$CF$2:$CF$51,13)) | M62: =IF(INDEX(campaigns!$A$2:$A$51,13)="","",INDEX(campaigns!$CG$2:$CG$51,13)) | N62: =IF(INDEX(campaigns!$A$2:$A$51,13)="","",INDEX(campaigns!$CH$2:$CH$51,13)) | O62: =IF(INDEX(campaigns!$A$2:$A$51,13)="","",INDEX(campaigns!$CI$2:$CI$51,13)) | P62: =IF(INDEX(campaigns!$A$2:$A$51,13)="","",INDEX(campaigns!$CK$2:$CK$51,13)) | Q62: =IF(INDEX(campaigns!$A$2:$A$51,13)="","",INDEX(campaigns!$CP$2:$CP$51,13)) | R62: =IF(INDEX(campaigns!$A$2:$A$51,13)="","",INDEX(campaigns!$CX$2:$CX$51,13)) | S62: =IF(INDEX(campaigns!$A$2:$A$51,13)="","",INDEX(campaigns!$CZ$2:$CZ$51,13)) | T62: =IF(INDEX(campaigns!$A$2:$A$51,13)="","",INDEX(campaigns!$DC$2:$DC$51,13)) | U62: =IF(INDEX(campaigns!$A$2:$A$51,13)="","",INDEX(campaigns!$DM$2:$DM$51,13)) | V62: =IF(INDEX(campaigns!$A$2:$A$51,13)="","",INDEX(campaigns!$DS$2:$DS$51,13)) | W62: =IF(INDEX(campaigns!$A$2:$A$51,13)="","",INDEX(campaigns!$DT$2:$DT$51,13)) | X62: =IF(INDEX(campaigns!$A$2:$A$51,13)="","",INDEX(campaigns!$DU$2:$DU$51,13)) | Y62: =IF(INDEX(campaigns!$A$2:$A$51,13)="","",INDEX(campaigns!$AV$2:$AV$51,13)) | Z62: =IF(INDEX(campaigns!$A$2:$A$51,13)="","",INDEX(campaigns!$DV$2:$DV$51,13))
A63: =IF(INDEX(campaigns!$A$2:$A$51,14)="","",INDEX(campaigns!$A$2:$A$51,14)) | B63: =IF(INDEX(campaigns!$A$2:$A$51,14)="","",INDEX(campaigns!$BE$2:$BE$51,14)) | C63: =IF(INDEX(campaigns!$A$2:$A$51,14)="","",INDEX(campaigns!$BG$2:$BG$51,14)) | D63: =IF(INDEX(campaigns!$A$2:$A$51,14)="","",INDEX(campaigns!$D$2:$D$51,14)) | E63: =IF(INDEX(campaigns!$A$2:$A$51,14)="","",INDEX(campaigns!$BW$2:$BW$51,14)) | F63: =IF(INDEX(campaigns!$A$2:$A$51,14)="","",INDEX(campaigns!$BO$2:$BO$51,14)) | G63: =IF(INDEX(campaigns!$A$2:$A$51,14)="","",INDEX(campaigns!$BP$2:$BP$51,14)) | H63: =IF(INDEX(campaigns!$A$2:$A$51,14)="","",INDEX(campaigns!$F$2:$F$51,14)) | I63: =IF(INDEX(campaigns!$A$2:$A$51,14)="","",INDEX(campaigns!$CB$2:$CB$51,14)) | J63: =IF(INDEX(campaigns!$A$2:$A$51,14)="","",INDEX(campaigns!$CD$2:$CD$51,14)) | K63: =IF(INDEX(campaigns!$A$2:$A$51,14)="","",INDEX(campaigns!$CE$2:$CE$51,14)) | L63: =IF(INDEX(campaigns!$A$2:$A$51,14)="","",INDEX(campaigns!$CF$2:$CF$51,14)) | M63: =IF(INDEX(campaigns!$A$2:$A$51,14)="","",INDEX(campaigns!$CG$2:$CG$51,14)) | N63: =IF(INDEX(campaigns!$A$2:$A$51,14)="","",INDEX(campaigns!$CH$2:$CH$51,14)) | O63: =IF(INDEX(campaigns!$A$2:$A$51,14)="","",INDEX(campaigns!$CI$2:$CI$51,14)) | P63: =IF(INDEX(campaigns!$A$2:$A$51,14)="","",INDEX(campaigns!$CK$2:$CK$51,14)) | Q63: =IF(INDEX(campaigns!$A$2:$A$51,14)="","",INDEX(campaigns!$CP$2:$CP$51,14)) | R63: =IF(INDEX(campaigns!$A$2:$A$51,14)="","",INDEX(campaigns!$CX$2:$CX$51,14)) | S63: =IF(INDEX(campaigns!$A$2:$A$51,14)="","",INDEX(campaigns!$CZ$2:$CZ$51,14)) | T63: =IF(INDEX(campaigns!$A$2:$A$51,14)="","",INDEX(campaigns!$DC$2:$DC$51,14)) | U63: =IF(INDEX(campaigns!$A$2:$A$51,14)="","",INDEX(campaigns!$DM$2:$DM$51,14)) | V63: =IF(INDEX(campaigns!$A$2:$A$51,14)="","",INDEX(campaigns!$DS$2:$DS$51,14)) | W63: =IF(INDEX(campaigns!$A$2:$A$51,14)="","",INDEX(campaigns!$DT$2:$DT$51,14)) | X63: =IF(INDEX(campaigns!$A$2:$A$51,14)="","",INDEX(campaigns!$DU$2:$DU$51,14)) | Y63: =IF(INDEX(campaigns!$A$2:$A$51,14)="","",INDEX(campaigns!$AV$2:$AV$51,14)) | Z63: =IF(INDEX(campaigns!$A$2:$A$51,14)="","",INDEX(campaigns!$DV$2:$DV$51,14))
A64: =IF(INDEX(campaigns!$A$2:$A$51,15)="","",INDEX(campaigns!$A$2:$A$51,15)) | B64: =IF(INDEX(campaigns!$A$2:$A$51,15)="","",INDEX(campaigns!$BE$2:$BE$51,15)) | C64: =IF(INDEX(campaigns!$A$2:$A$51,15)="","",INDEX(campaigns!$BG$2:$BG$51,15)) | D64: =IF(INDEX(campaigns!$A$2:$A$51,15)="","",INDEX(campaigns!$D$2:$D$51,15)) | E64: =IF(INDEX(campaigns!$A$2:$A$51,15)="","",INDEX(campaigns!$BW$2:$BW$51,15)) | F64: =IF(INDEX(campaigns!$A$2:$A$51,15)="","",INDEX(campaigns!$BO$2:$BO$51,15)) | G64: =IF(INDEX(campaigns!$A$2:$A$51,15)="","",INDEX(campaigns!$BP$2:$BP$51,15)) | H64: =IF(INDEX(campaigns!$A$2:$A$51,15)="","",INDEX(campaigns!$F$2:$F$51,15)) | I64: =IF(INDEX(campaigns!$A$2:$A$51,15)="","",INDEX(campaigns!$CB$2:$CB$51,15)) | J64: =IF(INDEX(campaigns!$A$2:$A$51,15)="","",INDEX(campaigns!$CD$2:$CD$51,15)) | K64: =IF(INDEX(campaigns!$A$2:$A$51,15)="","",INDEX(campaigns!$CE$2:$CE$51,15)) | L64: =IF(INDEX(campaigns!$A$2:$A$51,15)="","",INDEX(campaigns!$CF$2:$CF$51,15)) | M64: =IF(INDEX(campaigns!$A$2:$A$51,15)="","",INDEX(campaigns!$CG$2:$CG$51,15)) | N64: =IF(INDEX(campaigns!$A$2:$A$51,15)="","",INDEX(campaigns!$CH$2:$CH$51,15)) | O64: =IF(INDEX(campaigns!$A$2:$A$51,15)="","",INDEX(campaigns!$CI$2:$CI$51,15)) | P64: =IF(INDEX(campaigns!$A$2:$A$51,15)="","",INDEX(campaigns!$CK$2:$CK$51,15)) | Q64: =IF(INDEX(campaigns!$A$2:$A$51,15)="","",INDEX(campaigns!$CP$2:$CP$51,15)) | R64: =IF(INDEX(campaigns!$A$2:$A$51,15)="","",INDEX(campaigns!$CX$2:$CX$51,15)) | S64: =IF(INDEX(campaigns!$A$2:$A$51,15)="","",INDEX(campaigns!$CZ$2:$CZ$51,15)) | T64: =IF(INDEX(campaigns!$A$2:$A$51,15)="","",INDEX(campaigns!$DC$2:$DC$51,15)) | U64: =IF(INDEX(campaigns!$A$2:$A$51,15)="","",INDEX(campaigns!$DM$2:$DM$51,15)) | V64: =IF(INDEX(campaigns!$A$2:$A$51,15)="","",INDEX(campaigns!$DS$2:$DS$51,15)) | W64: =IF(INDEX(campaigns!$A$2:$A$51,15)="","",INDEX(campaigns!$DT$2:$DT$51,15)) | X64: =IF(INDEX(campaigns!$A$2:$A$51,15)="","",INDEX(campaigns!$DU$2:$DU$51,15)) | Y64: =IF(INDEX(campaigns!$A$2:$A$51,15)="","",INDEX(campaigns!$AV$2:$AV$51,15)) | Z64: =IF(INDEX(campaigns!$A$2:$A$51,15)="","",INDEX(campaigns!$DV$2:$DV$51,15))
A65: =IF(INDEX(campaigns!$A$2:$A$51,16)="","",INDEX(campaigns!$A$2:$A$51,16)) | B65: =IF(INDEX(campaigns!$A$2:$A$51,16)="","",INDEX(campaigns!$BE$2:$BE$51,16)) | C65: =IF(INDEX(campaigns!$A$2:$A$51,16)="","",INDEX(campaigns!$BG$2:$BG$51,16)) | D65: =IF(INDEX(campaigns!$A$2:$A$51,16)="","",INDEX(campaigns!$D$2:$D$51,16)) | E65: =IF(INDEX(campaigns!$A$2:$A$51,16)="","",INDEX(campaigns!$BW$2:$BW$51,16)) | F65: =IF(INDEX(campaigns!$A$2:$A$51,16)="","",INDEX(campaigns!$BO$2:$BO$51,16)) | G65: =IF(INDEX(campaigns!$A$2:$A$51,16)="","",INDEX(campaigns!$BP$2:$BP$51,16)) | H65: =IF(INDEX(campaigns!$A$2:$A$51,16)="","",INDEX(campaigns!$F$2:$F$51,16)) | I65: =IF(INDEX(campaigns!$A$2:$A$51,16)="","",INDEX(campaigns!$CB$2:$CB$51,16)) | J65: =IF(INDEX(campaigns!$A$2:$A$51,16)="","",INDEX(campaigns!$CD$2:$CD$51,16)) | K65: =IF(INDEX(campaigns!$A$2:$A$51,16)="","",INDEX(campaigns!$CE$2:$CE$51,16)) | L65: =IF(INDEX(campaigns!$A$2:$A$51,16)="","",INDEX(campaigns!$CF$2:$CF$51,16)) | M65: =IF(INDEX(campaigns!$A$2:$A$51,16)="","",INDEX(campaigns!$CG$2:$CG$51,16)) | N65: =IF(INDEX(campaigns!$A$2:$A$51,16)="","",INDEX(campaigns!$CH$2:$CH$51,16)) | O65: =IF(INDEX(campaigns!$A$2:$A$51,16)="","",INDEX(campaigns!$CI$2:$CI$51,16)) | P65: =IF(INDEX(campaigns!$A$2:$A$51,16)="","",INDEX(campaigns!$CK$2:$CK$51,16)) | Q65: =IF(INDEX(campaigns!$A$2:$A$51,16)="","",INDEX(campaigns!$CP$2:$CP$51,16)) | R65: =IF(INDEX(campaigns!$A$2:$A$51,16)="","",INDEX(campaigns!$CX$2:$CX$51,16)) | S65: =IF(INDEX(campaigns!$A$2:$A$51,16)="","",INDEX(campaigns!$CZ$2:$CZ$51,16)) | T65: =IF(INDEX(campaigns!$A$2:$A$51,16)="","",INDEX(campaigns!$DC$2:$DC$51,16)) | U65: =IF(INDEX(campaigns!$A$2:$A$51,16)="","",INDEX(campaigns!$DM$2:$DM$51,16)) | V65: =IF(INDEX(campaigns!$A$2:$A$51,16)="","",INDEX(campaigns!$DS$2:$DS$51,16)) | W65: =IF(INDEX(campaigns!$A$2:$A$51,16)="","",INDEX(campaigns!$DT$2:$DT$51,16)) | X65: =IF(INDEX(campaigns!$A$2:$A$51,16)="","",INDEX(campaigns!$DU$2:$DU$51,16)) | Y65: =IF(INDEX(campaigns!$A$2:$A$51,16)="","",INDEX(campaigns!$AV$2:$AV$51,16)) | Z65: =IF(INDEX(campaigns!$A$2:$A$51,16)="","",INDEX(campaigns!$DV$2:$DV$51,16))
A66: =IF(INDEX(campaigns!$A$2:$A$51,17)="","",INDEX(campaigns!$A$2:$A$51,17)) | B66: =IF(INDEX(campaigns!$A$2:$A$51,17)="","",INDEX(campaigns!$BE$2:$BE$51,17)) | C66: =IF(INDEX(campaigns!$A$2:$A$51,17)="","",INDEX(campaigns!$BG$2:$BG$51,17)) | D66: =IF(INDEX(campaigns!$A$2:$A$51,17)="","",INDEX(campaigns!$D$2:$D$51,17)) | E66: =IF(INDEX(campaigns!$A$2:$A$51,17)="","",INDEX(campaigns!$BW$2:$BW$51,17)) | F66: =IF(INDEX(campaigns!$A$2:$A$51,17)="","",INDEX(campaigns!$BO$2:$BO$51,17)) | G66: =IF(INDEX(campaigns!$A$2:$A$51,17)="","",INDEX(campaigns!$BP$2:$BP$51,17)) | H66: =IF(INDEX(campaigns!$A$2:$A$51,17)="","",INDEX(campaigns!$F$2:$F$51,17)) | I66: =IF(INDEX(campaigns!$A$2:$A$51,17)="","",INDEX(campaigns!$CB$2:$CB$51,17)) | J66: =IF(INDEX(campaigns!$A$2:$A$51,17)="","",INDEX(campaigns!$CD$2:$CD$51,17)) | K66: =IF(INDEX(campaigns!$A$2:$A$51,17)="","",INDEX(campaigns!$CE$2:$CE$51,17)) | L66: =IF(INDEX(campaigns!$A$2:$A$51,17)="","",INDEX(campaigns!$CF$2:$CF$51,17)) | M66: =IF(INDEX(campaigns!$A$2:$A$51,17)="","",INDEX(campaigns!$CG$2:$CG$51,17)) | N66: =IF(INDEX(campaigns!$A$2:$A$51,17)="","",INDEX(campaigns!$CH$2:$CH$51,17)) | O66: =IF(INDEX(campaigns!$A$2:$A$51,17)="","",INDEX(campaigns!$CI$2:$CI$51,17)) | P66: =IF(INDEX(campaigns!$A$2:$A$51,17)="","",INDEX(campaigns!$CK$2:$CK$51,17)) | Q66: =IF(INDEX(campaigns!$A$2:$A$51,17)="","",INDEX(campaigns!$CP$2:$CP$51,17)) | R66: =IF(INDEX(campaigns!$A$2:$A$51,17)="","",INDEX(campaigns!$CX$2:$CX$51,17)) | S66: =IF(INDEX(campaigns!$A$2:$A$51,17)="","",INDEX(campaigns!$CZ$2:$CZ$51,17)) | T66: =IF(INDEX(campaigns!$A$2:$A$51,17)="","",INDEX(campaigns!$DC$2:$DC$51,17)) | U66: =IF(INDEX(campaigns!$A$2:$A$51,17)="","",INDEX(campaigns!$DM$2:$DM$51,17)) | V66: =IF(INDEX(campaigns!$A$2:$A$51,17)="","",INDEX(campaigns!$DS$2:$DS$51,17)) | W66: =IF(INDEX(campaigns!$A$2:$A$51,17)="","",INDEX(campaigns!$DT$2:$DT$51,17)) | X66: =IF(INDEX(campaigns!$A$2:$A$51,17)="","",INDEX(campaigns!$DU$2:$DU$51,17)) | Y66: =IF(INDEX(campaigns!$A$2:$A$51,17)="","",INDEX(campaigns!$AV$2:$AV$51,17)) | Z66: =IF(INDEX(campaigns!$A$2:$A$51,17)="","",INDEX(campaigns!$DV$2:$DV$51,17))
A67: =IF(INDEX(campaigns!$A$2:$A$51,18)="","",INDEX(campaigns!$A$2:$A$51,18)) | B67: =IF(INDEX(campaigns!$A$2:$A$51,18)="","",INDEX(campaigns!$BE$2:$BE$51,18)) | C67: =IF(INDEX(campaigns!$A$2:$A$51,18)="","",INDEX(campaigns!$BG$2:$BG$51,18)) | D67: =IF(INDEX(campaigns!$A$2:$A$51,18)="","",INDEX(campaigns!$D$2:$D$51,18)) | E67: =IF(INDEX(campaigns!$A$2:$A$51,18)="","",INDEX(campaigns!$BW$2:$BW$51,18)) | F67: =IF(INDEX(campaigns!$A$2:$A$51,18)="","",INDEX(campaigns!$BO$2:$BO$51,18)) | G67: =IF(INDEX(campaigns!$A$2:$A$51,18)="","",INDEX(campaigns!$BP$2:$BP$51,18)) | H67: =IF(INDEX(campaigns!$A$2:$A$51,18)="","",INDEX(campaigns!$F$2:$F$51,18)) | I67: =IF(INDEX(campaigns!$A$2:$A$51,18)="","",INDEX(campaigns!$CB$2:$CB$51,18)) | J67: =IF(INDEX(campaigns!$A$2:$A$51,18)="","",INDEX(campaigns!$CD$2:$CD$51,18)) | K67: =IF(INDEX(campaigns!$A$2:$A$51,18)="","",INDEX(campaigns!$CE$2:$CE$51,18)) | L67: =IF(INDEX(campaigns!$A$2:$A$51,18)="","",INDEX(campaigns!$CF$2:$CF$51,18)) | M67: =IF(INDEX(campaigns!$A$2:$A$51,18)="","",INDEX(campaigns!$CG$2:$CG$51,18)) | N67: =IF(INDEX(campaigns!$A$2:$A$51,18)="","",INDEX(campaigns!$CH$2:$CH$51,18)) | O67: =IF(INDEX(campaigns!$A$2:$A$51,18)="","",INDEX(campaigns!$CI$2:$CI$51,18)) | P67: =IF(INDEX(campaigns!$A$2:$A$51,18)="","",INDEX(campaigns!$CK$2:$CK$51,18)) | Q67: =IF(INDEX(campaigns!$A$2:$A$51,18)="","",INDEX(campaigns!$CP$2:$CP$51,18)) | R67: =IF(INDEX(campaigns!$A$2:$A$51,18)="","",INDEX(campaigns!$CX$2:$CX$51,18)) | S67: =IF(INDEX(campaigns!$A$2:$A$51,18)="","",INDEX(campaigns!$CZ$2:$CZ$51,18)) | T67: =IF(INDEX(campaigns!$A$2:$A$51,18)="","",INDEX(campaigns!$DC$2:$DC$51,18)) | U67: =IF(INDEX(campaigns!$A$2:$A$51,18)="","",INDEX(campaigns!$DM$2:$DM$51,18)) | V67: =IF(INDEX(campaigns!$A$2:$A$51,18)="","",INDEX(campaigns!$DS$2:$DS$51,18)) | W67: =IF(INDEX(campaigns!$A$2:$A$51,18)="","",INDEX(campaigns!$DT$2:$DT$51,18)) | X67: =IF(INDEX(campaigns!$A$2:$A$51,18)="","",INDEX(campaigns!$DU$2:$DU$51,18)) | Y67: =IF(INDEX(campaigns!$A$2:$A$51,18)="","",INDEX(campaigns!$AV$2:$AV$51,18)) | Z67: =IF(INDEX(campaigns!$A$2:$A$51,18)="","",INDEX(campaigns!$DV$2:$DV$51,18))
A68: =IF(INDEX(campaigns!$A$2:$A$51,19)="","",INDEX(campaigns!$A$2:$A$51,19)) | B68: =IF(INDEX(campaigns!$A$2:$A$51,19)="","",INDEX(campaigns!$BE$2:$BE$51,19)) | C68: =IF(INDEX(campaigns!$A$2:$A$51,19)="","",INDEX(campaigns!$BG$2:$BG$51,19)) | D68: =IF(INDEX(campaigns!$A$2:$A$51,19)="","",INDEX(campaigns!$D$2:$D$51,19)) | E68: =IF(INDEX(campaigns!$A$2:$A$51,19)="","",INDEX(campaigns!$BW$2:$BW$51,19)) | F68: =IF(INDEX(campaigns!$A$2:$A$51,19)="","",INDEX(campaigns!$BO$2:$BO$51,19)) | G68: =IF(INDEX(campaigns!$A$2:$A$51,19)="","",INDEX(campaigns!$BP$2:$BP$51,19)) | H68: =IF(INDEX(campaigns!$A$2:$A$51,19)="","",INDEX(campaigns!$F$2:$F$51,19)) | I68: =IF(INDEX(campaigns!$A$2:$A$51,19)="","",INDEX(campaigns!$CB$2:$CB$51,19)) | J68: =IF(INDEX(campaigns!$A$2:$A$51,19)="","",INDEX(campaigns!$CD$2:$CD$51,19)) | K68: =IF(INDEX(campaigns!$A$2:$A$51,19)="","",INDEX(campaigns!$CE$2:$CE$51,19)) | L68: =IF(INDEX(campaigns!$A$2:$A$51,19)="","",INDEX(campaigns!$CF$2:$CF$51,19)) | M68: =IF(INDEX(campaigns!$A$2:$A$51,19)="","",INDEX(campaigns!$CG$2:$CG$51,19)) | N68: =IF(INDEX(campaigns!$A$2:$A$51,19)="","",INDEX(campaigns!$CH$2:$CH$51,19)) | O68: =IF(INDEX(campaigns!$A$2:$A$51,19)="","",INDEX(campaigns!$CI$2:$CI$51,19)) | P68: =IF(INDEX(campaigns!$A$2:$A$51,19)="","",INDEX(campaigns!$CK$2:$CK$51,19)) | Q68: =IF(INDEX(campaigns!$A$2:$A$51,19)="","",INDEX(campaigns!$CP$2:$CP$51,19)) | R68: =IF(INDEX(campaigns!$A$2:$A$51,19)="","",INDEX(campaigns!$CX$2:$CX$51,19)) | S68: =IF(INDEX(campaigns!$A$2:$A$51,19)="","",INDEX(campaigns!$CZ$2:$CZ$51,19)) | T68: =IF(INDEX(campaigns!$A$2:$A$51,19)="","",INDEX(campaigns!$DC$2:$DC$51,19)) | U68: =IF(INDEX(campaigns!$A$2:$A$51,19)="","",INDEX(campaigns!$DM$2:$DM$51,19)) | V68: =IF(INDEX(campaigns!$A$2:$A$51,19)="","",INDEX(campaigns!$DS$2:$DS$51,19)) | W68: =IF(INDEX(campaigns!$A$2:$A$51,19)="","",INDEX(campaigns!$DT$2:$DT$51,19)) | X68: =IF(INDEX(campaigns!$A$2:$A$51,19)="","",INDEX(campaigns!$DU$2:$DU$51,19)) | Y68: =IF(INDEX(campaigns!$A$2:$A$51,19)="","",INDEX(campaigns!$AV$2:$AV$51,19)) | Z68: =IF(INDEX(campaigns!$A$2:$A$51,19)="","",INDEX(campaigns!$DV$2:$DV$51,19))
A69: =IF(INDEX(campaigns!$A$2:$A$51,20)="","",INDEX(campaigns!$A$2:$A$51,20)) | B69: =IF(INDEX(campaigns!$A$2:$A$51,20)="","",INDEX(campaigns!$BE$2:$BE$51,20)) | C69: =IF(INDEX(campaigns!$A$2:$A$51,20)="","",INDEX(campaigns!$BG$2:$BG$51,20)) | D69: =IF(INDEX(campaigns!$A$2:$A$51,20)="","",INDEX(campaigns!$D$2:$D$51,20)) | E69: =IF(INDEX(campaigns!$A$2:$A$51,20)="","",INDEX(campaigns!$BW$2:$BW$51,20)) | F69: =IF(INDEX(campaigns!$A$2:$A$51,20)="","",INDEX(campaigns!$BO$2:$BO$51,20)) | G69: =IF(INDEX(campaigns!$A$2:$A$51,20)="","",INDEX(campaigns!$BP$2:$BP$51,20)) | H69: =IF(INDEX(campaigns!$A$2:$A$51,20)="","",INDEX(campaigns!$F$2:$F$51,20)) | I69: =IF(INDEX(campaigns!$A$2:$A$51,20)="","",INDEX(campaigns!$CB$2:$CB$51,20)) | J69: =IF(INDEX(campaigns!$A$2:$A$51,20)="","",INDEX(campaigns!$CD$2:$CD$51,20)) | K69: =IF(INDEX(campaigns!$A$2:$A$51,20)="","",INDEX(campaigns!$CE$2:$CE$51,20)) | L69: =IF(INDEX(campaigns!$A$2:$A$51,20)="","",INDEX(campaigns!$CF$2:$CF$51,20)) | M69: =IF(INDEX(campaigns!$A$2:$A$51,20)="","",INDEX(campaigns!$CG$2:$CG$51,20)) | N69: =IF(INDEX(campaigns!$A$2:$A$51,20)="","",INDEX(campaigns!$CH$2:$CH$51,20)) | O69: =IF(INDEX(campaigns!$A$2:$A$51,20)="","",INDEX(campaigns!$CI$2:$CI$51,20)) | P69: =IF(INDEX(campaigns!$A$2:$A$51,20)="","",INDEX(campaigns!$CK$2:$CK$51,20)) | Q69: =IF(INDEX(campaigns!$A$2:$A$51,20)="","",INDEX(campaigns!$CP$2:$CP$51,20)) | R69: =IF(INDEX(campaigns!$A$2:$A$51,20)="","",INDEX(campaigns!$CX$2:$CX$51,20)) | S69: =IF(INDEX(campaigns!$A$2:$A$51,20)="","",INDEX(campaigns!$CZ$2:$CZ$51,20)) | T69: =IF(INDEX(campaigns!$A$2:$A$51,20)="","",INDEX(campaigns!$DC$2:$DC$51,20)) | U69: =IF(INDEX(campaigns!$A$2:$A$51,20)="","",INDEX(campaigns!$DM$2:$DM$51,20)) | V69: =IF(INDEX(campaigns!$A$2:$A$51,20)="","",INDEX(campaigns!$DS$2:$DS$51,20)) | W69: =IF(INDEX(campaigns!$A$2:$A$51,20)="","",INDEX(campaigns!$DT$2:$DT$51,20)) | X69: =IF(INDEX(campaigns!$A$2:$A$51,20)="","",INDEX(campaigns!$DU$2:$DU$51,20)) | Y69: =IF(INDEX(campaigns!$A$2:$A$51,20)="","",INDEX(campaigns!$AV$2:$AV$51,20)) | Z69: =IF(INDEX(campaigns!$A$2:$A$51,20)="","",INDEX(campaigns!$DV$2:$DV$51,20))
A70: =IF(INDEX(campaigns!$A$2:$A$51,21)="","",INDEX(campaigns!$A$2:$A$51,21)) | B70: =IF(INDEX(campaigns!$A$2:$A$51,21)="","",INDEX(campaigns!$BE$2:$BE$51,21)) | C70: =IF(INDEX(campaigns!$A$2:$A$51,21)="","",INDEX(campaigns!$BG$2:$BG$51,21)) | D70: =IF(INDEX(campaigns!$A$2:$A$51,21)="","",INDEX(campaigns!$D$2:$D$51,21)) | E70: =IF(INDEX(campaigns!$A$2:$A$51,21)="","",INDEX(campaigns!$BW$2:$BW$51,21)) | F70: =IF(INDEX(campaigns!$A$2:$A$51,21)="","",INDEX(campaigns!$BO$2:$BO$51,21)) | G70: =IF(INDEX(campaigns!$A$2:$A$51,21)="","",INDEX(campaigns!$BP$2:$BP$51,21)) | H70: =IF(INDEX(campaigns!$A$2:$A$51,21)="","",INDEX(campaigns!$F$2:$F$51,21)) | I70: =IF(INDEX(campaigns!$A$2:$A$51,21)="","",INDEX(campaigns!$CB$2:$CB$51,21)) | J70: =IF(INDEX(campaigns!$A$2:$A$51,21)="","",INDEX(campaigns!$CD$2:$CD$51,21)) | K70: =IF(INDEX(campaigns!$A$2:$A$51,21)="","",INDEX(campaigns!$CE$2:$CE$51,21)) | L70: =IF(INDEX(campaigns!$A$2:$A$51,21)="","",INDEX(campaigns!$CF$2:$CF$51,21)) | M70: =IF(INDEX(campaigns!$A$2:$A$51,21)="","",INDEX(campaigns!$CG$2:$CG$51,21)) | N70: =IF(INDEX(campaigns!$A$2:$A$51,21)="","",INDEX(campaigns!$CH$2:$CH$51,21)) | O70: =IF(INDEX(campaigns!$A$2:$A$51,21)="","",INDEX(campaigns!$CI$2:$CI$51,21)) | P70: =IF(INDEX(campaigns!$A$2:$A$51,21)="","",INDEX(campaigns!$CK$2:$CK$51,21)) | Q70: =IF(INDEX(campaigns!$A$2:$A$51,21)="","",INDEX(campaigns!$CP$2:$CP$51,21)) | R70: =IF(INDEX(campaigns!$A$2:$A$51,21)="","",INDEX(campaigns!$CX$2:$CX$51,21)) | S70: =IF(INDEX(campaigns!$A$2:$A$51,21)="","",INDEX(campaigns!$CZ$2:$CZ$51,21)) | T70: =IF(INDEX(campaigns!$A$2:$A$51,21)="","",INDEX(campaigns!$DC$2:$DC$51,21)) | U70: =IF(INDEX(campaigns!$A$2:$A$51,21)="","",INDEX(campaigns!$DM$2:$DM$51,21)) | V70: =IF(INDEX(campaigns!$A$2:$A$51,21)="","",INDEX(campaigns!$DS$2:$DS$51,21)) | W70: =IF(INDEX(campaigns!$A$2:$A$51,21)="","",INDEX(campaigns!$DT$2:$DT$51,21)) | X70: =IF(INDEX(campaigns!$A$2:$A$51,21)="","",INDEX(campaigns!$DU$2:$DU$51,21)) | Y70: =IF(INDEX(campaigns!$A$2:$A$51,21)="","",INDEX(campaigns!$AV$2:$AV$51,21)) | Z70: =IF(INDEX(campaigns!$A$2:$A$51,21)="","",INDEX(campaigns!$DV$2:$DV$51,21))
A71: =IF(INDEX(campaigns!$A$2:$A$51,22)="","",INDEX(campaigns!$A$2:$A$51,22)) | B71: =IF(INDEX(campaigns!$A$2:$A$51,22)="","",INDEX(campaigns!$BE$2:$BE$51,22)) | C71: =IF(INDEX(campaigns!$A$2:$A$51,22)="","",INDEX(campaigns!$BG$2:$BG$51,22)) | D71: =IF(INDEX(campaigns!$A$2:$A$51,22)="","",INDEX(campaigns!$D$2:$D$51,22)) | E71: =IF(INDEX(campaigns!$A$2:$A$51,22)="","",INDEX(campaigns!$BW$2:$BW$51,22)) | F71: =IF(INDEX(campaigns!$A$2:$A$51,22)="","",INDEX(campaigns!$BO$2:$BO$51,22)) | G71: =IF(INDEX(campaigns!$A$2:$A$51,22)="","",INDEX(campaigns!$BP$2:$BP$51,22)) | H71: =IF(INDEX(campaigns!$A$2:$A$51,22)="","",INDEX(campaigns!$F$2:$F$51,22)) | I71: =IF(INDEX(campaigns!$A$2:$A$51,22)="","",INDEX(campaigns!$CB$2:$CB$51,22)) | J71: =IF(INDEX(campaigns!$A$2:$A$51,22)="","",INDEX(campaigns!$CD$2:$CD$51,22)) | K71: =IF(INDEX(campaigns!$A$2:$A$51,22)="","",INDEX(campaigns!$CE$2:$CE$51,22)) | L71: =IF(INDEX(campaigns!$A$2:$A$51,22)="","",INDEX(campaigns!$CF$2:$CF$51,22)) | M71: =IF(INDEX(campaigns!$A$2:$A$51,22)="","",INDEX(campaigns!$CG$2:$CG$51,22)) | N71: =IF(INDEX(campaigns!$A$2:$A$51,22)="","",INDEX(campaigns!$CH$2:$CH$51,22)) | O71: =IF(INDEX(campaigns!$A$2:$A$51,22)="","",INDEX(campaigns!$CI$2:$CI$51,22)) | P71: =IF(INDEX(campaigns!$A$2:$A$51,22)="","",INDEX(campaigns!$CK$2:$CK$51,22)) | Q71: =IF(INDEX(campaigns!$A$2:$A$51,22)="","",INDEX(campaigns!$CP$2:$CP$51,22)) | R71: =IF(INDEX(campaigns!$A$2:$A$51,22)="","",INDEX(campaigns!$CX$2:$CX$51,22)) | S71: =IF(INDEX(campaigns!$A$2:$A$51,22)="","",INDEX(campaigns!$CZ$2:$CZ$51,22)) | T71: =IF(INDEX(campaigns!$A$2:$A$51,22)="","",INDEX(campaigns!$DC$2:$DC$51,22)) | U71: =IF(INDEX(campaigns!$A$2:$A$51,22)="","",INDEX(campaigns!$DM$2:$DM$51,22)) | V71: =IF(INDEX(campaigns!$A$2:$A$51,22)="","",INDEX(campaigns!$DS$2:$DS$51,22)) | W71: =IF(INDEX(campaigns!$A$2:$A$51,22)="","",INDEX(campaigns!$DT$2:$DT$51,22)) | X71: =IF(INDEX(campaigns!$A$2:$A$51,22)="","",INDEX(campaigns!$DU$2:$DU$51,22)) | Y71: =IF(INDEX(campaigns!$A$2:$A$51,22)="","",INDEX(campaigns!$AV$2:$AV$51,22)) | Z71: =IF(INDEX(campaigns!$A$2:$A$51,22)="","",INDEX(campaigns!$DV$2:$DV$51,22))
A72: =IF(INDEX(campaigns!$A$2:$A$51,23)="","",INDEX(campaigns!$A$2:$A$51,23)) | B72: =IF(INDEX(campaigns!$A$2:$A$51,23)="","",INDEX(campaigns!$BE$2:$BE$51,23)) | C72: =IF(INDEX(campaigns!$A$2:$A$51,23)="","",INDEX(campaigns!$BG$2:$BG$51,23)) | D72: =IF(INDEX(campaigns!$A$2:$A$51,23)="","",INDEX(campaigns!$D$2:$D$51,23)) | E72: =IF(INDEX(campaigns!$A$2:$A$51,23)="","",INDEX(campaigns!$BW$2:$BW$51,23)) | F72: =IF(INDEX(campaigns!$A$2:$A$51,23)="","",INDEX(campaigns!$BO$2:$BO$51,23)) | G72: =IF(INDEX(campaigns!$A$2:$A$51,23)="","",INDEX(campaigns!$BP$2:$BP$51,23)) | H72: =IF(INDEX(campaigns!$A$2:$A$51,23)="","",INDEX(campaigns!$F$2:$F$51,23)) | I72: =IF(INDEX(campaigns!$A$2:$A$51,23)="","",INDEX(campaigns!$CB$2:$CB$51,23)) | J72: =IF(INDEX(campaigns!$A$2:$A$51,23)="","",INDEX(campaigns!$CD$2:$CD$51,23)) | K72: =IF(INDEX(campaigns!$A$2:$A$51,23)="","",INDEX(campaigns!$CE$2:$CE$51,23)) | L72: =IF(INDEX(campaigns!$A$2:$A$51,23)="","",INDEX(campaigns!$CF$2:$CF$51,23)) | M72: =IF(INDEX(campaigns!$A$2:$A$51,23)="","",INDEX(campaigns!$CG$2:$CG$51,23)) | N72: =IF(INDEX(campaigns!$A$2:$A$51,23)="","",INDEX(campaigns!$CH$2:$CH$51,23)) | O72: =IF(INDEX(campaigns!$A$2:$A$51,23)="","",INDEX(campaigns!$CI$2:$CI$51,23)) | P72: =IF(INDEX(campaigns!$A$2:$A$51,23)="","",INDEX(campaigns!$CK$2:$CK$51,23)) | Q72: =IF(INDEX(campaigns!$A$2:$A$51,23)="","",INDEX(campaigns!$CP$2:$CP$51,23)) | R72: =IF(INDEX(campaigns!$A$2:$A$51,23)="","",INDEX(campaigns!$CX$2:$CX$51,23)) | S72: =IF(INDEX(campaigns!$A$2:$A$51,23)="","",INDEX(campaigns!$CZ$2:$CZ$51,23)) | T72: =IF(INDEX(campaigns!$A$2:$A$51,23)="","",INDEX(campaigns!$DC$2:$DC$51,23)) | U72: =IF(INDEX(campaigns!$A$2:$A$51,23)="","",INDEX(campaigns!$DM$2:$DM$51,23)) | V72: =IF(INDEX(campaigns!$A$2:$A$51,23)="","",INDEX(campaigns!$DS$2:$DS$51,23)) | W72: =IF(INDEX(campaigns!$A$2:$A$51,23)="","",INDEX(campaigns!$DT$2:$DT$51,23)) | X72: =IF(INDEX(campaigns!$A$2:$A$51,23)="","",INDEX(campaigns!$DU$2:$DU$51,23)) | Y72: =IF(INDEX(campaigns!$A$2:$A$51,23)="","",INDEX(campaigns!$AV$2:$AV$51,23)) | Z72: =IF(INDEX(campaigns!$A$2:$A$51,23)="","",INDEX(campaigns!$DV$2:$DV$51,23))
A73: =IF(INDEX(campaigns!$A$2:$A$51,24)="","",INDEX(campaigns!$A$2:$A$51,24)) | B73: =IF(INDEX(campaigns!$A$2:$A$51,24)="","",INDEX(campaigns!$BE$2:$BE$51,24)) | C73: =IF(INDEX(campaigns!$A$2:$A$51,24)="","",INDEX(campaigns!$BG$2:$BG$51,24)) | D73: =IF(INDEX(campaigns!$A$2:$A$51,24)="","",INDEX(campaigns!$D$2:$D$51,24)) | E73: =IF(INDEX(campaigns!$A$2:$A$51,24)="","",INDEX(campaigns!$BW$2:$BW$51,24)) | F73: =IF(INDEX(campaigns!$A$2:$A$51,24)="","",INDEX(campaigns!$BO$2:$BO$51,24)) | G73: =IF(INDEX(campaigns!$A$2:$A$51,24)="","",INDEX(campaigns!$BP$2:$BP$51,24)) | H73: =IF(INDEX(campaigns!$A$2:$A$51,24)="","",INDEX(campaigns!$F$2:$F$51,24)) | I73: =IF(INDEX(campaigns!$A$2:$A$51,24)="","",INDEX(campaigns!$CB$2:$CB$51,24)) | J73: =IF(INDEX(campaigns!$A$2:$A$51,24)="","",INDEX(campaigns!$CD$2:$CD$51,24)) | K73: =IF(INDEX(campaigns!$A$2:$A$51,24)="","",INDEX(campaigns!$CE$2:$CE$51,24)) | L73: =IF(INDEX(campaigns!$A$2:$A$51,24)="","",INDEX(campaigns!$CF$2:$CF$51,24)) | M73: =IF(INDEX(campaigns!$A$2:$A$51,24)="","",INDEX(campaigns!$CG$2:$CG$51,24)) | N73: =IF(INDEX(campaigns!$A$2:$A$51,24)="","",INDEX(campaigns!$CH$2:$CH$51,24)) | O73: =IF(INDEX(campaigns!$A$2:$A$51,24)="","",INDEX(campaigns!$CI$2:$CI$51,24)) | P73: =IF(INDEX(campaigns!$A$2:$A$51,24)="","",INDEX(campaigns!$CK$2:$CK$51,24)) | Q73: =IF(INDEX(campaigns!$A$2:$A$51,24)="","",INDEX(campaigns!$CP$2:$CP$51,24)) | R73: =IF(INDEX(campaigns!$A$2:$A$51,24)="","",INDEX(campaigns!$CX$2:$CX$51,24)) | S73: =IF(INDEX(campaigns!$A$2:$A$51,24)="","",INDEX(campaigns!$CZ$2:$CZ$51,24)) | T73: =IF(INDEX(campaigns!$A$2:$A$51,24)="","",INDEX(campaigns!$DC$2:$DC$51,24)) | U73: =IF(INDEX(campaigns!$A$2:$A$51,24)="","",INDEX(campaigns!$DM$2:$DM$51,24)) | V73: =IF(INDEX(campaigns!$A$2:$A$51,24)="","",INDEX(campaigns!$DS$2:$DS$51,24)) | W73: =IF(INDEX(campaigns!$A$2:$A$51,24)="","",INDEX(campaigns!$DT$2:$DT$51,24)) | X73: =IF(INDEX(campaigns!$A$2:$A$51,24)="","",INDEX(campaigns!$DU$2:$DU$51,24)) | Y73: =IF(INDEX(campaigns!$A$2:$A$51,24)="","",INDEX(campaigns!$AV$2:$AV$51,24)) | Z73: =IF(INDEX(campaigns!$A$2:$A$51,24)="","",INDEX(campaigns!$DV$2:$DV$51,24))
A74: =IF(INDEX(campaigns!$A$2:$A$51,25)="","",INDEX(campaigns!$A$2:$A$51,25)) | B74: =IF(INDEX(campaigns!$A$2:$A$51,25)="","",INDEX(campaigns!$BE$2:$BE$51,25)) | C74: =IF(INDEX(campaigns!$A$2:$A$51,25)="","",INDEX(campaigns!$BG$2:$BG$51,25)) | D74: =IF(INDEX(campaigns!$A$2:$A$51,25)="","",INDEX(campaigns!$D$2:$D$51,25)) | E74: =IF(INDEX(campaigns!$A$2:$A$51,25)="","",INDEX(campaigns!$BW$2:$BW$51,25)) | F74: =IF(INDEX(campaigns!$A$2:$A$51,25)="","",INDEX(campaigns!$BO$2:$BO$51,25)) | G74: =IF(INDEX(campaigns!$A$2:$A$51,25)="","",INDEX(campaigns!$BP$2:$BP$51,25)) | H74: =IF(INDEX(campaigns!$A$2:$A$51,25)="","",INDEX(campaigns!$F$2:$F$51,25)) | I74: =IF(INDEX(campaigns!$A$2:$A$51,25)="","",INDEX(campaigns!$CB$2:$CB$51,25)) | J74: =IF(INDEX(campaigns!$A$2:$A$51,25)="","",INDEX(campaigns!$CD$2:$CD$51,25)) | K74: =IF(INDEX(campaigns!$A$2:$A$51,25)="","",INDEX(campaigns!$CE$2:$CE$51,25)) | L74: =IF(INDEX(campaigns!$A$2:$A$51,25)="","",INDEX(campaigns!$CF$2:$CF$51,25)) | M74: =IF(INDEX(campaigns!$A$2:$A$51,25)="","",INDEX(campaigns!$CG$2:$CG$51,25)) | N74: =IF(INDEX(campaigns!$A$2:$A$51,25)="","",INDEX(campaigns!$CH$2:$CH$51,25)) | O74: =IF(INDEX(campaigns!$A$2:$A$51,25)="","",INDEX(campaigns!$CI$2:$CI$51,25)) | P74: =IF(INDEX(campaigns!$A$2:$A$51,25)="","",INDEX(campaigns!$CK$2:$CK$51,25)) | Q74: =IF(INDEX(campaigns!$A$2:$A$51,25)="","",INDEX(campaigns!$CP$2:$CP$51,25)) | R74: =IF(INDEX(campaigns!$A$2:$A$51,25)="","",INDEX(campaigns!$CX$2:$CX$51,25)) | S74: =IF(INDEX(campaigns!$A$2:$A$51,25)="","",INDEX(campaigns!$CZ$2:$CZ$51,25)) | T74: =IF(INDEX(campaigns!$A$2:$A$51,25)="","",INDEX(campaigns!$DC$2:$DC$51,25)) | U74: =IF(INDEX(campaigns!$A$2:$A$51,25)="","",INDEX(campaigns!$DM$2:$DM$51,25)) | V74: =IF(INDEX(campaigns!$A$2:$A$51,25)="","",INDEX(campaigns!$DS$2:$DS$51,25)) | W74: =IF(INDEX(campaigns!$A$2:$A$51,25)="","",INDEX(campaigns!$DT$2:$DT$51,25)) | X74: =IF(INDEX(campaigns!$A$2:$A$51,25)="","",INDEX(campaigns!$DU$2:$DU$51,25)) | Y74: =IF(INDEX(campaigns!$A$2:$A$51,25)="","",INDEX(campaigns!$AV$2:$AV$51,25)) | Z74: =IF(INDEX(campaigns!$A$2:$A$51,25)="","",INDEX(campaigns!$DV$2:$DV$51,25))
A75: =IF(INDEX(campaigns!$A$2:$A$51,26)="","",INDEX(campaigns!$A$2:$A$51,26)) | B75: =IF(INDEX(campaigns!$A$2:$A$51,26)="","",INDEX(campaigns!$BE$2:$BE$51,26)) | C75: =IF(INDEX(campaigns!$A$2:$A$51,26)="","",INDEX(campaigns!$BG$2:$BG$51,26)) | D75: =IF(INDEX(campaigns!$A$2:$A$51,26)="","",INDEX(campaigns!$D$2:$D$51,26)) | E75: =IF(INDEX(campaigns!$A$2:$A$51,26)="","",INDEX(campaigns!$BW$2:$BW$51,26)) | F75: =IF(INDEX(campaigns!$A$2:$A$51,26)="","",INDEX(campaigns!$BO$2:$BO$51,26)) | G75: =IF(INDEX(campaigns!$A$2:$A$51,26)="","",INDEX(campaigns!$BP$2:$BP$51,26)) | H75: =IF(INDEX(campaigns!$A$2:$A$51,26)="","",INDEX(campaigns!$F$2:$F$51,26)) | I75: =IF(INDEX(campaigns!$A$2:$A$51,26)="","",INDEX(campaigns!$CB$2:$CB$51,26)) | J75: =IF(INDEX(campaigns!$A$2:$A$51,26)="","",INDEX(campaigns!$CD$2:$CD$51,26)) | K75: =IF(INDEX(campaigns!$A$2:$A$51,26)="","",INDEX(campaigns!$CE$2:$CE$51,26)) | L75: =IF(INDEX(campaigns!$A$2:$A$51,26)="","",INDEX(campaigns!$CF$2:$CF$51,26)) | M75: =IF(INDEX(campaigns!$A$2:$A$51,26)="","",INDEX(campaigns!$CG$2:$CG$51,26)) | N75: =IF(INDEX(campaigns!$A$2:$A$51,26)="","",INDEX(campaigns!$CH$2:$CH$51,26)) | O75: =IF(INDEX(campaigns!$A$2:$A$51,26)="","",INDEX(campaigns!$CI$2:$CI$51,26)) | P75: =IF(INDEX(campaigns!$A$2:$A$51,26)="","",INDEX(campaigns!$CK$2:$CK$51,26)) | Q75: =IF(INDEX(campaigns!$A$2:$A$51,26)="","",INDEX(campaigns!$CP$2:$CP$51,26)) | R75: =IF(INDEX(campaigns!$A$2:$A$51,26)="","",INDEX(campaigns!$CX$2:$CX$51,26)) | S75: =IF(INDEX(campaigns!$A$2:$A$51,26)="","",INDEX(campaigns!$CZ$2:$CZ$51,26)) | T75: =IF(INDEX(campaigns!$A$2:$A$51,26)="","",INDEX(campaigns!$DC$2:$DC$51,26)) | U75: =IF(INDEX(campaigns!$A$2:$A$51,26)="","",INDEX(campaigns!$DM$2:$DM$51,26)) | V75: =IF(INDEX(campaigns!$A$2:$A$51,26)="","",INDEX(campaigns!$DS$2:$DS$51,26)) | W75: =IF(INDEX(campaigns!$A$2:$A$51,26)="","",INDEX(campaigns!$DT$2:$DT$51,26)) | X75: =IF(INDEX(campaigns!$A$2:$A$51,26)="","",INDEX(campaigns!$DU$2:$DU$51,26)) | Y75: =IF(INDEX(campaigns!$A$2:$A$51,26)="","",INDEX(campaigns!$AV$2:$AV$51,26)) | Z75: =IF(INDEX(campaigns!$A$2:$A$51,26)="","",INDEX(campaigns!$DV$2:$DV$51,26))
A76: =IF(INDEX(campaigns!$A$2:$A$51,27)="","",INDEX(campaigns!$A$2:$A$51,27)) | B76: =IF(INDEX(campaigns!$A$2:$A$51,27)="","",INDEX(campaigns!$BE$2:$BE$51,27)) | C76: =IF(INDEX(campaigns!$A$2:$A$51,27)="","",INDEX(campaigns!$BG$2:$BG$51,27)) | D76: =IF(INDEX(campaigns!$A$2:$A$51,27)="","",INDEX(campaigns!$D$2:$D$51,27)) | E76: =IF(INDEX(campaigns!$A$2:$A$51,27)="","",INDEX(campaigns!$BW$2:$BW$51,27)) | F76: =IF(INDEX(campaigns!$A$2:$A$51,27)="","",INDEX(campaigns!$BO$2:$BO$51,27)) | G76: =IF(INDEX(campaigns!$A$2:$A$51,27)="","",INDEX(campaigns!$BP$2:$BP$51,27)) | H76: =IF(INDEX(campaigns!$A$2:$A$51,27)="","",INDEX(campaigns!$F$2:$F$51,27)) | I76: =IF(INDEX(campaigns!$A$2:$A$51,27)="","",INDEX(campaigns!$CB$2:$CB$51,27)) | J76: =IF(INDEX(campaigns!$A$2:$A$51,27)="","",INDEX(campaigns!$CD$2:$CD$51,27)) | K76: =IF(INDEX(campaigns!$A$2:$A$51,27)="","",INDEX(campaigns!$CE$2:$CE$51,27)) | L76: =IF(INDEX(campaigns!$A$2:$A$51,27)="","",INDEX(campaigns!$CF$2:$CF$51,27)) | M76: =IF(INDEX(campaigns!$A$2:$A$51,27)="","",INDEX(campaigns!$CG$2:$CG$51,27)) | N76: =IF(INDEX(campaigns!$A$2:$A$51,27)="","",INDEX(campaigns!$CH$2:$CH$51,27)) | O76: =IF(INDEX(campaigns!$A$2:$A$51,27)="","",INDEX(campaigns!$CI$2:$CI$51,27)) | P76: =IF(INDEX(campaigns!$A$2:$A$51,27)="","",INDEX(campaigns!$CK$2:$CK$51,27)) | Q76: =IF(INDEX(campaigns!$A$2:$A$51,27)="","",INDEX(campaigns!$CP$2:$CP$51,27)) | R76: =IF(INDEX(campaigns!$A$2:$A$51,27)="","",INDEX(campaigns!$CX$2:$CX$51,27)) | S76: =IF(INDEX(campaigns!$A$2:$A$51,27)="","",INDEX(campaigns!$CZ$2:$CZ$51,27)) | T76: =IF(INDEX(campaigns!$A$2:$A$51,27)="","",INDEX(campaigns!$DC$2:$DC$51,27)) | U76: =IF(INDEX(campaigns!$A$2:$A$51,27)="","",INDEX(campaigns!$DM$2:$DM$51,27)) | V76: =IF(INDEX(campaigns!$A$2:$A$51,27)="","",INDEX(campaigns!$DS$2:$DS$51,27)) | W76: =IF(INDEX(campaigns!$A$2:$A$51,27)="","",INDEX(campaigns!$DT$2:$DT$51,27)) | X76: =IF(INDEX(campaigns!$A$2:$A$51,27)="","",INDEX(campaigns!$DU$2:$DU$51,27)) | Y76: =IF(INDEX(campaigns!$A$2:$A$51,27)="","",INDEX(campaigns!$AV$2:$AV$51,27)) | Z76: =IF(INDEX(campaigns!$A$2:$A$51,27)="","",INDEX(campaigns!$DV$2:$DV$51,27))
A77: =IF(INDEX(campaigns!$A$2:$A$51,28)="","",INDEX(campaigns!$A$2:$A$51,28)) | B77: =IF(INDEX(campaigns!$A$2:$A$51,28)="","",INDEX(campaigns!$BE$2:$BE$51,28)) | C77: =IF(INDEX(campaigns!$A$2:$A$51,28)="","",INDEX(campaigns!$BG$2:$BG$51,28)) | D77: =IF(INDEX(campaigns!$A$2:$A$51,28)="","",INDEX(campaigns!$D$2:$D$51,28)) | E77: =IF(INDEX(campaigns!$A$2:$A$51,28)="","",INDEX(campaigns!$BW$2:$BW$51,28)) | F77: =IF(INDEX(campaigns!$A$2:$A$51,28)="","",INDEX(campaigns!$BO$2:$BO$51,28)) | G77: =IF(INDEX(campaigns!$A$2:$A$51,28)="","",INDEX(campaigns!$BP$2:$BP$51,28)) | H77: =IF(INDEX(campaigns!$A$2:$A$51,28)="","",INDEX(campaigns!$F$2:$F$51,28)) | I77: =IF(INDEX(campaigns!$A$2:$A$51,28)="","",INDEX(campaigns!$CB$2:$CB$51,28)) | J77: =IF(INDEX(campaigns!$A$2:$A$51,28)="","",INDEX(campaigns!$CD$2:$CD$51,28)) | K77: =IF(INDEX(campaigns!$A$2:$A$51,28)="","",INDEX(campaigns!$CE$2:$CE$51,28)) | L77: =IF(INDEX(campaigns!$A$2:$A$51,28)="","",INDEX(campaigns!$CF$2:$CF$51,28)) | M77: =IF(INDEX(campaigns!$A$2:$A$51,28)="","",INDEX(campaigns!$CG$2:$CG$51,28)) | N77: =IF(INDEX(campaigns!$A$2:$A$51,28)="","",INDEX(campaigns!$CH$2:$CH$51,28)) | O77: =IF(INDEX(campaigns!$A$2:$A$51,28)="","",INDEX(campaigns!$CI$2:$CI$51,28)) | P77: =IF(INDEX(campaigns!$A$2:$A$51,28)="","",INDEX(campaigns!$CK$2:$CK$51,28)) | Q77: =IF(INDEX(campaigns!$A$2:$A$51,28)="","",INDEX(campaigns!$CP$2:$CP$51,28)) | R77: =IF(INDEX(campaigns!$A$2:$A$51,28)="","",INDEX(campaigns!$CX$2:$CX$51,28)) | S77: =IF(INDEX(campaigns!$A$2:$A$51,28)="","",INDEX(campaigns!$CZ$2:$CZ$51,28)) | T77: =IF(INDEX(campaigns!$A$2:$A$51,28)="","",INDEX(campaigns!$DC$2:$DC$51,28)) | U77: =IF(INDEX(campaigns!$A$2:$A$51,28)="","",INDEX(campaigns!$DM$2:$DM$51,28)) | V77: =IF(INDEX(campaigns!$A$2:$A$51,28)="","",INDEX(campaigns!$DS$2:$DS$51,28)) | W77: =IF(INDEX(campaigns!$A$2:$A$51,28)="","",INDEX(campaigns!$DT$2:$DT$51,28)) | X77: =IF(INDEX(campaigns!$A$2:$A$51,28)="","",INDEX(campaigns!$DU$2:$DU$51,28)) | Y77: =IF(INDEX(campaigns!$A$2:$A$51,28)="","",INDEX(campaigns!$AV$2:$AV$51,28)) | Z77: =IF(INDEX(campaigns!$A$2:$A$51,28)="","",INDEX(campaigns!$DV$2:$DV$51,28))
A78: =IF(INDEX(campaigns!$A$2:$A$51,29)="","",INDEX(campaigns!$A$2:$A$51,29)) | B78: =IF(INDEX(campaigns!$A$2:$A$51,29)="","",INDEX(campaigns!$BE$2:$BE$51,29)) | C78: =IF(INDEX(campaigns!$A$2:$A$51,29)="","",INDEX(campaigns!$BG$2:$BG$51,29)) | D78: =IF(INDEX(campaigns!$A$2:$A$51,29)="","",INDEX(campaigns!$D$2:$D$51,29)) | E78: =IF(INDEX(campaigns!$A$2:$A$51,29)="","",INDEX(campaigns!$BW$2:$BW$51,29)) | F78: =IF(INDEX(campaigns!$A$2:$A$51,29)="","",INDEX(campaigns!$BO$2:$BO$51,29)) | G78: =IF(INDEX(campaigns!$A$2:$A$51,29)="","",INDEX(campaigns!$BP$2:$BP$51,29)) | H78: =IF(INDEX(campaigns!$A$2:$A$51,29)="","",INDEX(campaigns!$F$2:$F$51,29)) | I78: =IF(INDEX(campaigns!$A$2:$A$51,29)="","",INDEX(campaigns!$CB$2:$CB$51,29)) | J78: =IF(INDEX(campaigns!$A$2:$A$51,29)="","",INDEX(campaigns!$CD$2:$CD$51,29)) | K78: =IF(INDEX(campaigns!$A$2:$A$51,29)="","",INDEX(campaigns!$CE$2:$CE$51,29)) | L78: =IF(INDEX(campaigns!$A$2:$A$51,29)="","",INDEX(campaigns!$CF$2:$CF$51,29)) | M78: =IF(INDEX(campaigns!$A$2:$A$51,29)="","",INDEX(campaigns!$CG$2:$CG$51,29)) | N78: =IF(INDEX(campaigns!$A$2:$A$51,29)="","",INDEX(campaigns!$CH$2:$CH$51,29)) | O78: =IF(INDEX(campaigns!$A$2:$A$51,29)="","",INDEX(campaigns!$CI$2:$CI$51,29)) | P78: =IF(INDEX(campaigns!$A$2:$A$51,29)="","",INDEX(campaigns!$CK$2:$CK$51,29)) | Q78: =IF(INDEX(campaigns!$A$2:$A$51,29)="","",INDEX(campaigns!$CP$2:$CP$51,29)) | R78: =IF(INDEX(campaigns!$A$2:$A$51,29)="","",INDEX(campaigns!$CX$2:$CX$51,29)) | S78: =IF(INDEX(campaigns!$A$2:$A$51,29)="","",INDEX(campaigns!$CZ$2:$CZ$51,29)) | T78: =IF(INDEX(campaigns!$A$2:$A$51,29)="","",INDEX(campaigns!$DC$2:$DC$51,29)) | U78: =IF(INDEX(campaigns!$A$2:$A$51,29)="","",INDEX(campaigns!$DM$2:$DM$51,29)) | V78: =IF(INDEX(campaigns!$A$2:$A$51,29)="","",INDEX(campaigns!$DS$2:$DS$51,29)) | W78: =IF(INDEX(campaigns!$A$2:$A$51,29)="","",INDEX(campaigns!$DT$2:$DT$51,29)) | X78: =IF(INDEX(campaigns!$A$2:$A$51,29)="","",INDEX(campaigns!$DU$2:$DU$51,29)) | Y78: =IF(INDEX(campaigns!$A$2:$A$51,29)="","",INDEX(campaigns!$AV$2:$AV$51,29)) | Z78: =IF(INDEX(campaigns!$A$2:$A$51,29)="","",INDEX(campaigns!$DV$2:$DV$51,29))
A79: =IF(INDEX(campaigns!$A$2:$A$51,30)="","",INDEX(campaigns!$A$2:$A$51,30)) | B79: =IF(INDEX(campaigns!$A$2:$A$51,30)="","",INDEX(campaigns!$BE$2:$BE$51,30)) | C79: =IF(INDEX(campaigns!$A$2:$A$51,30)="","",INDEX(campaigns!$BG$2:$BG$51,30)) | D79: =IF(INDEX(campaigns!$A$2:$A$51,30)="","",INDEX(campaigns!$D$2:$D$51,30)) | E79: =IF(INDEX(campaigns!$A$2:$A$51,30)="","",INDEX(campaigns!$BW$2:$BW$51,30)) | F79: =IF(INDEX(campaigns!$A$2:$A$51,30)="","",INDEX(campaigns!$BO$2:$BO$51,30)) | G79: =IF(INDEX(campaigns!$A$2:$A$51,30)="","",INDEX(campaigns!$BP$2:$BP$51,30)) | H79: =IF(INDEX(campaigns!$A$2:$A$51,30)="","",INDEX(campaigns!$F$2:$F$51,30)) | I79: =IF(INDEX(campaigns!$A$2:$A$51,30)="","",INDEX(campaigns!$CB$2:$CB$51,30)) | J79: =IF(INDEX(campaigns!$A$2:$A$51,30)="","",INDEX(campaigns!$CD$2:$CD$51,30)) | K79: =IF(INDEX(campaigns!$A$2:$A$51,30)="","",INDEX(campaigns!$CE$2:$CE$51,30)) | L79: =IF(INDEX(campaigns!$A$2:$A$51,30)="","",INDEX(campaigns!$CF$2:$CF$51,30)) | M79: =IF(INDEX(campaigns!$A$2:$A$51,30)="","",INDEX(campaigns!$CG$2:$CG$51,30)) | N79: =IF(INDEX(campaigns!$A$2:$A$51,30)="","",INDEX(campaigns!$CH$2:$CH$51,30)) | O79: =IF(INDEX(campaigns!$A$2:$A$51,30)="","",INDEX(campaigns!$CI$2:$CI$51,30)) | P79: =IF(INDEX(campaigns!$A$2:$A$51,30)="","",INDEX(campaigns!$CK$2:$CK$51,30)) | Q79: =IF(INDEX(campaigns!$A$2:$A$51,30)="","",INDEX(campaigns!$CP$2:$CP$51,30)) | R79: =IF(INDEX(campaigns!$A$2:$A$51,30)="","",INDEX(campaigns!$CX$2:$CX$51,30)) | S79: =IF(INDEX(campaigns!$A$2:$A$51,30)="","",INDEX(campaigns!$CZ$2:$CZ$51,30)) | T79: =IF(INDEX(campaigns!$A$2:$A$51,30)="","",INDEX(campaigns!$DC$2:$DC$51,30)) | U79: =IF(INDEX(campaigns!$A$2:$A$51,30)="","",INDEX(campaigns!$DM$2:$DM$51,30)) | V79: =IF(INDEX(campaigns!$A$2:$A$51,30)="","",INDEX(campaigns!$DS$2:$DS$51,30)) | W79: =IF(INDEX(campaigns!$A$2:$A$51,30)="","",INDEX(campaigns!$DT$2:$DT$51,30)) | X79: =IF(INDEX(campaigns!$A$2:$A$51,30)="","",INDEX(campaigns!$DU$2:$DU$51,30)) | Y79: =IF(INDEX(campaigns!$A$2:$A$51,30)="","",INDEX(campaigns!$AV$2:$AV$51,30)) | Z79: =IF(INDEX(campaigns!$A$2:$A$51,30)="","",INDEX(campaigns!$DV$2:$DV$51,30))
A81: Incremental purchases are not measured. No column here adds the rungs together.
A83: Founder hours by activity
A84: activity | B84: all hours | C84: not tied to a drop | D84: =IF(INDEX(drops!$A$2:$A$21,1)="","",INDEX(drops!$A$2:$A$21,1)) -> SAMPLE-DRP-001 | E84: =IF(INDEX(drops!$A$2:$A$21,2)="","",INDEX(drops!$A$2:$A$21,2)) -> SAMPLE-DRP-002 | F84: =IF(INDEX(drops!$A$2:$A$21,3)="","",INDEX(drops!$A$2:$A$21,3)) -> SAMPLE-DRP-003 | G84: =IF(INDEX(drops!$A$2:$A$21,4)="","",INDEX(drops!$A$2:$A$21,4)) -> SAMPLE-DRP-004 | H84: =IF(INDEX(drops!$A$2:$A$21,5)="","",INDEX(drops!$A$2:$A$21,5)) | I84: =IF(INDEX(drops!$A$2:$A$21,6)="","",INDEX(drops!$A$2:$A$21,6))
A85: brand_sales | B85: =SUMIFS(hours!$E$2:$E$1501,hours!$D$2:$D$1501,"brand_sales") -> 55.5 | C85: =SUMIFS(hours!$E$2:$E$1501,hours!$D$2:$D$1501,"brand_sales",hours!$B$2:$B$1501,"") -> 7.5 | D85: =IF(D84="","",SUMIFS(hours!$E$2:$E$1501,hours!$D$2:$D$1501,"brand_sales",hours!$B$2:$B$1501,D84)) -> 20 | E85: =IF(E84="","",SUMIFS(hours!$E$2:$E$1501,hours!$D$2:$D$1501,"brand_sales",hours!$B$2:$B$1501,E84)) -> 18 | F85: =IF(F84="","",SUMIFS(hours!$E$2:$E$1501,hours!$D$2:$D$1501,"brand_sales",hours!$B$2:$B$1501,F84)) -> 6 | G85: =IF(G84="","",SUMIFS(hours!$E$2:$E$1501,hours!$D$2:$D$1501,"brand_sales",hours!$B$2:$B$1501,G84)) -> 4 | H85: =IF(H84="","",SUMIFS(hours!$E$2:$E$1501,hours!$D$2:$D$1501,"brand_sales",hours!$B$2:$B$1501,H84)) | I85: =IF(I84="","",SUMIFS(hours!$E$2:$E$1501,hours!$D$2:$D$1501,"brand_sales",hours!$B$2:$B$1501,I84))
A86: office_coordination | B86: =SUMIFS(hours!$E$2:$E$1501,hours!$D$2:$D$1501,"office_coordination") -> 40.5 | C86: =SUMIFS(hours!$E$2:$E$1501,hours!$D$2:$D$1501,"office_coordination",hours!$B$2:$B$1501,"") -> 7.5 | D86: =IF(D84="","",SUMIFS(hours!$E$2:$E$1501,hours!$D$2:$D$1501,"office_coordination",hours!$B$2:$B$1501,D84)) -> 20 | E86: =IF(E84="","",SUMIFS(hours!$E$2:$E$1501,hours!$D$2:$D$1501,"office_coordination",hours!$B$2:$B$1501,E84)) -> 10 | F86: =IF(F84="","",SUMIFS(hours!$E$2:$E$1501,hours!$D$2:$D$1501,"office_coordination",hours!$B$2:$B$1501,F84)) -> 1.5 | G86: =IF(G84="","",SUMIFS(hours!$E$2:$E$1501,hours!$D$2:$D$1501,"office_coordination",hours!$B$2:$B$1501,G84)) -> 1.5 | H86: =IF(H84="","",SUMIFS(hours!$E$2:$E$1501,hours!$D$2:$D$1501,"office_coordination",hours!$B$2:$B$1501,H84)) | I86: =IF(I84="","",SUMIFS(hours!$E$2:$E$1501,hours!$D$2:$D$1501,"office_coordination",hours!$B$2:$B$1501,I84))
A87: receiving_kitting | B87: =SUMIFS(hours!$E$2:$E$1501,hours!$D$2:$D$1501,"receiving_kitting") -> 12.5 | C87: =SUMIFS(hours!$E$2:$E$1501,hours!$D$2:$D$1501,"receiving_kitting",hours!$B$2:$B$1501,"") -> 0 | D87: =IF(D84="","",SUMIFS(hours!$E$2:$E$1501,hours!$D$2:$D$1501,"receiving_kitting",hours!$B$2:$B$1501,D84)) -> 3 | E87: =IF(E84="","",SUMIFS(hours!$E$2:$E$1501,hours!$D$2:$D$1501,"receiving_kitting",hours!$B$2:$B$1501,E84)) -> 4 | F87: =IF(F84="","",SUMIFS(hours!$E$2:$E$1501,hours!$D$2:$D$1501,"receiving_kitting",hours!$B$2:$B$1501,F84)) -> 3 | G87: =IF(G84="","",SUMIFS(hours!$E$2:$E$1501,hours!$D$2:$D$1501,"receiving_kitting",hours!$B$2:$B$1501,G84)) -> 2.5 | H87: =IF(H84="","",SUMIFS(hours!$E$2:$E$1501,hours!$D$2:$D$1501,"receiving_kitting",hours!$B$2:$B$1501,H84)) | I87: =IF(I84="","",SUMIFS(hours!$E$2:$E$1501,hours!$D$2:$D$1501,"receiving_kitting",hours!$B$2:$B$1501,I84))
A88: drop_day | B88: =SUMIFS(hours!$E$2:$E$1501,hours!$D$2:$D$1501,"drop_day") -> 17 | C88: =SUMIFS(hours!$E$2:$E$1501,hours!$D$2:$D$1501,"drop_day",hours!$B$2:$B$1501,"") -> 0 | D88: =IF(D84="","",SUMIFS(hours!$E$2:$E$1501,hours!$D$2:$D$1501,"drop_day",hours!$B$2:$B$1501,D84)) -> 5 | E88: =IF(E84="","",SUMIFS(hours!$E$2:$E$1501,hours!$D$2:$D$1501,"drop_day",hours!$B$2:$B$1501,E84)) -> 8 | F88: =IF(F84="","",SUMIFS(hours!$E$2:$E$1501,hours!$D$2:$D$1501,"drop_day",hours!$B$2:$B$1501,F84)) -> 4 | G88: =IF(G84="","",SUMIFS(hours!$E$2:$E$1501,hours!$D$2:$D$1501,"drop_day",hours!$B$2:$B$1501,G84)) -> 0 | H88: =IF(H84="","",SUMIFS(hours!$E$2:$E$1501,hours!$D$2:$D$1501,"drop_day",hours!$B$2:$B$1501,H84)) | I88: =IF(I84="","",SUMIFS(hours!$E$2:$E$1501,hours!$D$2:$D$1501,"drop_day",hours!$B$2:$B$1501,I84))
A89: checks_pickup | B89: =SUMIFS(hours!$E$2:$E$1501,hours!$D$2:$D$1501,"checks_pickup") -> 10 | C89: =SUMIFS(hours!$E$2:$E$1501,hours!$D$2:$D$1501,"checks_pickup",hours!$B$2:$B$1501,"") -> 0 | D89: =IF(D84="","",SUMIFS(hours!$E$2:$E$1501,hours!$D$2:$D$1501,"checks_pickup",hours!$B$2:$B$1501,D84)) -> 3 | E89: =IF(E84="","",SUMIFS(hours!$E$2:$E$1501,hours!$D$2:$D$1501,"checks_pickup",hours!$B$2:$B$1501,E84)) -> 4 | F89: =IF(F84="","",SUMIFS(hours!$E$2:$E$1501,hours!$D$2:$D$1501,"checks_pickup",hours!$B$2:$B$1501,F84)) -> 3 | G89: =IF(G84="","",SUMIFS(hours!$E$2:$E$1501,hours!$D$2:$D$1501,"checks_pickup",hours!$B$2:$B$1501,G84)) -> 0 | H89: =IF(H84="","",SUMIFS(hours!$E$2:$E$1501,hours!$D$2:$D$1501,"checks_pickup",hours!$B$2:$B$1501,H84)) | I89: =IF(I84="","",SUMIFS(hours!$E$2:$E$1501,hours!$D$2:$D$1501,"checks_pickup",hours!$B$2:$B$1501,I84))
A90: reporting_debriefs | B90: =SUMIFS(hours!$E$2:$E$1501,hours!$D$2:$D$1501,"reporting_debriefs") -> 12 | C90: =SUMIFS(hours!$E$2:$E$1501,hours!$D$2:$D$1501,"reporting_debriefs",hours!$B$2:$B$1501,"") -> 0 | D90: =IF(D84="","",SUMIFS(hours!$E$2:$E$1501,hours!$D$2:$D$1501,"reporting_debriefs",hours!$B$2:$B$1501,D84)) -> 4 | E90: =IF(E84="","",SUMIFS(hours!$E$2:$E$1501,hours!$D$2:$D$1501,"reporting_debriefs",hours!$B$2:$B$1501,E84)) -> 6 | F90: =IF(F84="","",SUMIFS(hours!$E$2:$E$1501,hours!$D$2:$D$1501,"reporting_debriefs",hours!$B$2:$B$1501,F84)) -> 2 | G90: =IF(G84="","",SUMIFS(hours!$E$2:$E$1501,hours!$D$2:$D$1501,"reporting_debriefs",hours!$B$2:$B$1501,G84)) -> 0 | H90: =IF(H84="","",SUMIFS(hours!$E$2:$E$1501,hours!$D$2:$D$1501,"reporting_debriefs",hours!$B$2:$B$1501,H84)) | I90: =IF(I84="","",SUMIFS(hours!$E$2:$E$1501,hours!$D$2:$D$1501,"reporting_debriefs",hours!$B$2:$B$1501,I84))
A91: admin_invoicing | B91: =SUMIFS(hours!$E$2:$E$1501,hours!$D$2:$D$1501,"admin_invoicing") -> 5 | C91: =SUMIFS(hours!$E$2:$E$1501,hours!$D$2:$D$1501,"admin_invoicing",hours!$B$2:$B$1501,"") -> 0 | D91: =IF(D84="","",SUMIFS(hours!$E$2:$E$1501,hours!$D$2:$D$1501,"admin_invoicing",hours!$B$2:$B$1501,D84)) -> 2 | E91: =IF(E84="","",SUMIFS(hours!$E$2:$E$1501,hours!$D$2:$D$1501,"admin_invoicing",hours!$B$2:$B$1501,E84)) -> 2 | F91: =IF(F84="","",SUMIFS(hours!$E$2:$E$1501,hours!$D$2:$D$1501,"admin_invoicing",hours!$B$2:$B$1501,F84)) -> 1 | G91: =IF(G84="","",SUMIFS(hours!$E$2:$E$1501,hours!$D$2:$D$1501,"admin_invoicing",hours!$B$2:$B$1501,G84)) -> 0 | H91: =IF(H84="","",SUMIFS(hours!$E$2:$E$1501,hours!$D$2:$D$1501,"admin_invoicing",hours!$B$2:$B$1501,H84)) | I91: =IF(I84="","",SUMIFS(hours!$E$2:$E$1501,hours!$D$2:$D$1501,"admin_invoicing",hours!$B$2:$B$1501,I84))
A92: total | B92: =SUM(B85:B91) -> 152.5 | C92: =SUM(C85:C91) -> 15 | D92: =IF(D84="","",SUM(D85:D91)) -> 57 | E92: =IF(E84="","",SUM(E85:E91)) -> 52 | F92: =IF(F84="","",SUM(F85:F91)) -> 20.5 | G92: =IF(G84="","",SUM(G85:G91)) -> 8 | H92: =IF(H84="","",SUM(H85:H91)) | I92: =IF(I84="","",SUM(I85:I91))

Sheet survey_dashboard
A1: Survey responses
A2: Campaign | B2: =IF(INDEX(campaigns!$A$2:$A$51,1)="","",INDEX(campaigns!$A$2:$A$51,1)) -> SAMPLE-CMP-001 | C2: Type a campaign_id over B2 to switch. Counts are live from the campaign's form tab, inside the window T to T+4 only.
A3: =IF(LEFT($B$2,6)="SAMPLE","SAMPLE DATA. Illustrative placeholders, not results.","") -> SAMPLE DATA. Illustrative placeholders, not results.
A4: =IF($B$2="","",IFERROR(INDEX(campaigns!$BE$2:$BE$51,MATCH($B$2,campaigns!$A$2:$A$51,0)),"")&" · drop "&TEXT(IFERROR(INDEX(campaigns!$BG$2:$BG$51,MATCH($B$2,campaigns!$A$2:$A$51,0)),""),"ddd yyyy-mm-dd")&" · window closes "&TEXT(IFERROR(INDEX(drops!$R$2:$R$21,MATCH(IFERROR(INDEX(campaigns!$B$2:$B$51,MATCH($B$2,campaigns!$A$2:$A$51,0)),""),drops!$A$2:$A$21,0)),""),"ddd yyyy-mm-dd")) -> SAMPLE Brightside · drop Tue 2027-01-12 · window closes Tue 2027-01-19
A6: office | B6: company | C6: responses | D6: said they tried | E6: didn't see it | F6: not for me | G6: gone when they looked | H6: ratings | I6: avg rating | J6: would buy: yes | K6: maybe | L6: no | M6: comments | N6: status
A7: =IFERROR(INDEX(approvals!$M$2:$M$251,MATCH($B$2&"|"&1,approvals!$AZ$2:$AZ$251,0)),"") -> A | B7: =IFERROR(INDEX(approvals!$K$2:$K$251,MATCH($B$2&"|"&1,approvals!$AZ$2:$AZ$251,0)),"") -> SAMPLE Northpoint Software | C7: =IFERROR(INDEX(approvals!$AL$2:$AL$251,MATCH($B$2&"|"&1,approvals!$AZ$2:$AZ$251,0)),"") -> 9 | D7: =IFERROR(INDEX(approvals!$AM$2:$AM$251,MATCH($B$2&"|"&1,approvals!$AZ$2:$AZ$251,0)),"") -> 8 | E7: =IFERROR(INDEX(approvals!$AQ$2:$AQ$251,MATCH($B$2&"|"&1,approvals!$AZ$2:$AZ$251,0)),"") -> 1 | F7: =IFERROR(INDEX(approvals!$AR$2:$AR$251,MATCH($B$2&"|"&1,approvals!$AZ$2:$AZ$251,0)),"") -> 0 | G7: =IFERROR(INDEX(approvals!$AS$2:$AS$251,MATCH($B$2&"|"&1,approvals!$AZ$2:$AZ$251,0)),"") -> 0 | H7: =IFERROR(INDEX(approvals!$AT$2:$AT$251,MATCH($B$2&"|"&1,approvals!$AZ$2:$AZ$251,0)),"") -> 8 | I7: =IFERROR(IF(INDEX(approvals!$AT$2:$AT$251,MATCH($B$2&"|"&1,approvals!$AZ$2:$AZ$251,0))=0,"",ROUND(INDEX(approvals!$AU$2:$AU$251,MATCH($B$2&"|"&1,approvals!$AZ$2:$AZ$251,0))/INDEX(approvals!$AT$2:$AT$251,MATCH($B$2&"|"&1,approvals!$AZ$2:$AZ$251,0)),1)),"") -> 3.9 | J7: =IFERROR(INDEX(approvals!$AV$2:$AV$251,MATCH($B$2&"|"&1,approvals!$AZ$2:$AZ$251,0)),"") -> 2 | K7: =IFERROR(INDEX(approvals!$AW$2:$AW$251,MATCH($B$2&"|"&1,approvals!$AZ$2:$AZ$251,0)),"") -> 3 | L7: =IFERROR(INDEX(approvals!$AX$2:$AX$251,MATCH($B$2&"|"&1,approvals!$AZ$2:$AZ$251,0)),"") -> 3 | M7: =IFERROR(INDEX(approvals!$AY$2:$AY$251,MATCH($B$2&"|"&1,approvals!$AZ$2:$AZ$251,0)),"") -> 5 | N7: =IFERROR(IF(INDEX(approvals!$AL$2:$AL$251,MATCH($B$2&"|"&1,approvals!$AZ$2:$AZ$251,0))>=config!$B$30,"OK","under "&config!$B$30&": ask the owner to re-post"),"") -> OK
A8: =IFERROR(INDEX(approvals!$M$2:$M$251,MATCH($B$2&"|"&2,approvals!$AZ$2:$AZ$251,0)),"") -> B | B8: =IFERROR(INDEX(approvals!$K$2:$K$251,MATCH($B$2&"|"&2,approvals!$AZ$2:$AZ$251,0)),"") -> SAMPLE Ferro Architecture | C8: =IFERROR(INDEX(approvals!$AL$2:$AL$251,MATCH($B$2&"|"&2,approvals!$AZ$2:$AZ$251,0)),"") -> 6 | D8: =IFERROR(INDEX(approvals!$AM$2:$AM$251,MATCH($B$2&"|"&2,approvals!$AZ$2:$AZ$251,0)),"") -> 5 | E8: =IFERROR(INDEX(approvals!$AQ$2:$AQ$251,MATCH($B$2&"|"&2,approvals!$AZ$2:$AZ$251,0)),"") -> 0 | F8: =IFERROR(INDEX(approvals!$AR$2:$AR$251,MATCH($B$2&"|"&2,approvals!$AZ$2:$AZ$251,0)),"") -> 1 | G8: =IFERROR(INDEX(approvals!$AS$2:$AS$251,MATCH($B$2&"|"&2,approvals!$AZ$2:$AZ$251,0)),"") -> 0 | H8: =IFERROR(INDEX(approvals!$AT$2:$AT$251,MATCH($B$2&"|"&2,approvals!$AZ$2:$AZ$251,0)),"") -> 5 | I8: =IFERROR(IF(INDEX(approvals!$AT$2:$AT$251,MATCH($B$2&"|"&2,approvals!$AZ$2:$AZ$251,0))=0,"",ROUND(INDEX(approvals!$AU$2:$AU$251,MATCH($B$2&"|"&2,approvals!$AZ$2:$AZ$251,0))/INDEX(approvals!$AT$2:$AT$251,MATCH($B$2&"|"&2,approvals!$AZ$2:$AZ$251,0)),1)),"") -> 4.8 | J8: =IFERROR(INDEX(approvals!$AV$2:$AV$251,MATCH($B$2&"|"&2,approvals!$AZ$2:$AZ$251,0)),"") -> 3 | K8: =IFERROR(INDEX(approvals!$AW$2:$AW$251,MATCH($B$2&"|"&2,approvals!$AZ$2:$AZ$251,0)),"") -> 1 | L8: =IFERROR(INDEX(approvals!$AX$2:$AX$251,MATCH($B$2&"|"&2,approvals!$AZ$2:$AZ$251,0)),"") -> 1 | M8: =IFERROR(INDEX(approvals!$AY$2:$AY$251,MATCH($B$2&"|"&2,approvals!$AZ$2:$AZ$251,0)),"") -> 3 | N8: =IFERROR(IF(INDEX(approvals!$AL$2:$AL$251,MATCH($B$2&"|"&2,approvals!$AZ$2:$AZ$251,0))>=config!$B$30,"OK","under "&config!$B$30&": ask the owner to re-post"),"") -> OK
A9: =IFERROR(INDEX(approvals!$M$2:$M$251,MATCH($B$2&"|"&3,approvals!$AZ$2:$AZ$251,0)),"") -> C | B9: =IFERROR(INDEX(approvals!$K$2:$K$251,MATCH($B$2&"|"&3,approvals!$AZ$2:$AZ$251,0)),"") -> SAMPLE Halcyon Media | C9: =IFERROR(INDEX(approvals!$AL$2:$AL$251,MATCH($B$2&"|"&3,approvals!$AZ$2:$AZ$251,0)),"") -> 8 | D9: =IFERROR(INDEX(approvals!$AM$2:$AM$251,MATCH($B$2&"|"&3,approvals!$AZ$2:$AZ$251,0)),"") -> 3 | E9: =IFERROR(INDEX(approvals!$AQ$2:$AQ$251,MATCH($B$2&"|"&3,approvals!$AZ$2:$AZ$251,0)),"") -> 3 | F9: =IFERROR(INDEX(approvals!$AR$2:$AR$251,MATCH($B$2&"|"&3,approvals!$AZ$2:$AZ$251,0)),"") -> 1 | G9: =IFERROR(INDEX(approvals!$AS$2:$AS$251,MATCH($B$2&"|"&3,approvals!$AZ$2:$AZ$251,0)),"") -> 1 | H9: =IFERROR(INDEX(approvals!$AT$2:$AT$251,MATCH($B$2&"|"&3,approvals!$AZ$2:$AZ$251,0)),"") -> 3 | I9: =IFERROR(IF(INDEX(approvals!$AT$2:$AT$251,MATCH($B$2&"|"&3,approvals!$AZ$2:$AZ$251,0))=0,"",ROUND(INDEX(approvals!$AU$2:$AU$251,MATCH($B$2&"|"&3,approvals!$AZ$2:$AZ$251,0))/INDEX(approvals!$AT$2:$AT$251,MATCH($B$2&"|"&3,approvals!$AZ$2:$AZ$251,0)),1)),"") -> 4.3 | J9: =IFERROR(INDEX(approvals!$AV$2:$AV$251,MATCH($B$2&"|"&3,approvals!$AZ$2:$AZ$251,0)),"") -> 2 | K9: =IFERROR(INDEX(approvals!$AW$2:$AW$251,MATCH($B$2&"|"&3,approvals!$AZ$2:$AZ$251,0)),"") -> 0 | L9: =IFERROR(INDEX(approvals!$AX$2:$AX$251,MATCH($B$2&"|"&3,approvals!$AZ$2:$AZ$251,0)),"") -> 1 | M9: =IFERROR(INDEX(approvals!$AY$2:$AY$251,MATCH($B$2&"|"&3,approvals!$AZ$2:$AZ$251,0)),"") -> 5 | N9: =IFERROR(IF(INDEX(approvals!$AL$2:$AL$251,MATCH($B$2&"|"&3,approvals!$AZ$2:$AZ$251,0))>=config!$B$30,"OK","under "&config!$B$30&": ask the owner to re-post"),"") -> OK
A10: =IFERROR(INDEX(approvals!$M$2:$M$251,MATCH($B$2&"|"&4,approvals!$AZ$2:$AZ$251,0)),"") -> D | B10: =IFERROR(INDEX(approvals!$K$2:$K$251,MATCH($B$2&"|"&4,approvals!$AZ$2:$AZ$251,0)),"") -> SAMPLE Union Food Fund | C10: =IFERROR(INDEX(approvals!$AL$2:$AL$251,MATCH($B$2&"|"&4,approvals!$AZ$2:$AZ$251,0)),"") -> 4 | D10: =IFERROR(INDEX(approvals!$AM$2:$AM$251,MATCH($B$2&"|"&4,approvals!$AZ$2:$AZ$251,0)),"") -> 2 | E10: =IFERROR(INDEX(approvals!$AQ$2:$AQ$251,MATCH($B$2&"|"&4,approvals!$AZ$2:$AZ$251,0)),"") -> 1 | F10: =IFERROR(INDEX(approvals!$AR$2:$AR$251,MATCH($B$2&"|"&4,approvals!$AZ$2:$AZ$251,0)),"") -> 0 | G10: =IFERROR(INDEX(approvals!$AS$2:$AS$251,MATCH($B$2&"|"&4,approvals!$AZ$2:$AZ$251,0)),"") -> 1 | H10: =IFERROR(INDEX(approvals!$AT$2:$AT$251,MATCH($B$2&"|"&4,approvals!$AZ$2:$AZ$251,0)),"") -> 2 | I10: =IFERROR(IF(INDEX(approvals!$AT$2:$AT$251,MATCH($B$2&"|"&4,approvals!$AZ$2:$AZ$251,0))=0,"",ROUND(INDEX(approvals!$AU$2:$AU$251,MATCH($B$2&"|"&4,approvals!$AZ$2:$AZ$251,0))/INDEX(approvals!$AT$2:$AT$251,MATCH($B$2&"|"&4,approvals!$AZ$2:$AZ$251,0)),1)),"") -> 4 | J10: =IFERROR(INDEX(approvals!$AV$2:$AV$251,MATCH($B$2&"|"&4,approvals!$AZ$2:$AZ$251,0)),"") -> 1 | K10: =IFERROR(INDEX(approvals!$AW$2:$AW$251,MATCH($B$2&"|"&4,approvals!$AZ$2:$AZ$251,0)),"") -> 1 | L10: =IFERROR(INDEX(approvals!$AX$2:$AX$251,MATCH($B$2&"|"&4,approvals!$AZ$2:$AZ$251,0)),"") -> 0 | M10: =IFERROR(INDEX(approvals!$AY$2:$AY$251,MATCH($B$2&"|"&4,approvals!$AZ$2:$AZ$251,0)),"") -> 3 | N10: =IFERROR(IF(INDEX(approvals!$AL$2:$AL$251,MATCH($B$2&"|"&4,approvals!$AZ$2:$AZ$251,0))>=config!$B$30,"OK","under "&config!$B$30&": ask the owner to re-post"),"") -> under 5: ask the owner to re-post
A11: =IFERROR(INDEX(approvals!$M$2:$M$251,MATCH($B$2&"|"&5,approvals!$AZ$2:$AZ$251,0)),"") -> E | B11: =IFERROR(INDEX(approvals!$K$2:$K$251,MATCH($B$2&"|"&5,approvals!$AZ$2:$AZ$251,0)),"") -> SAMPLE Studio Marlow | C11: =IFERROR(INDEX(approvals!$AL$2:$AL$251,MATCH($B$2&"|"&5,approvals!$AZ$2:$AZ$251,0)),"") -> 7 | D11: =IFERROR(INDEX(approvals!$AM$2:$AM$251,MATCH($B$2&"|"&5,approvals!$AZ$2:$AZ$251,0)),"") -> 7 | E11: =IFERROR(INDEX(approvals!$AQ$2:$AQ$251,MATCH($B$2&"|"&5,approvals!$AZ$2:$AZ$251,0)),"") -> 0 | F11: =IFERROR(INDEX(approvals!$AR$2:$AR$251,MATCH($B$2&"|"&5,approvals!$AZ$2:$AZ$251,0)),"") -> 0 | G11: =IFERROR(INDEX(approvals!$AS$2:$AS$251,MATCH($B$2&"|"&5,approvals!$AZ$2:$AZ$251,0)),"") -> 0 | H11: =IFERROR(INDEX(approvals!$AT$2:$AT$251,MATCH($B$2&"|"&5,approvals!$AZ$2:$AZ$251,0)),"") -> 7 | I11: =IFERROR(IF(INDEX(approvals!$AT$2:$AT$251,MATCH($B$2&"|"&5,approvals!$AZ$2:$AZ$251,0))=0,"",ROUND(INDEX(approvals!$AU$2:$AU$251,MATCH($B$2&"|"&5,approvals!$AZ$2:$AZ$251,0))/INDEX(approvals!$AT$2:$AT$251,MATCH($B$2&"|"&5,approvals!$AZ$2:$AZ$251,0)),1)),"") -> 4.3 | J11: =IFERROR(INDEX(approvals!$AV$2:$AV$251,MATCH($B$2&"|"&5,approvals!$AZ$2:$AZ$251,0)),"") -> 2 | K11: =IFERROR(INDEX(approvals!$AW$2:$AW$251,MATCH($B$2&"|"&5,approvals!$AZ$2:$AZ$251,0)),"") -> 3 | L11: =IFERROR(INDEX(approvals!$AX$2:$AX$251,MATCH($B$2&"|"&5,approvals!$AZ$2:$AZ$251,0)),"") -> 2 | M11: =IFERROR(INDEX(approvals!$AY$2:$AY$251,MATCH($B$2&"|"&5,approvals!$AZ$2:$AZ$251,0)),"") -> 2 | N11: =IFERROR(IF(INDEX(approvals!$AL$2:$AL$251,MATCH($B$2&"|"&5,approvals!$AZ$2:$AZ$251,0))>=config!$B$30,"OK","under "&config!$B$30&": ask the owner to re-post"),"") -> OK
A12: =IFERROR(INDEX(approvals!$M$2:$M$251,MATCH($B$2&"|"&6,approvals!$AZ$2:$AZ$251,0)),"") | B12: =IFERROR(INDEX(approvals!$K$2:$K$251,MATCH($B$2&"|"&6,approvals!$AZ$2:$AZ$251,0)),"") | C12: =IFERROR(INDEX(approvals!$AL$2:$AL$251,MATCH($B$2&"|"&6,approvals!$AZ$2:$AZ$251,0)),"") | D12: =IFERROR(INDEX(approvals!$AM$2:$AM$251,MATCH($B$2&"|"&6,approvals!$AZ$2:$AZ$251,0)),"") | E12: =IFERROR(INDEX(approvals!$AQ$2:$AQ$251,MATCH($B$2&"|"&6,approvals!$AZ$2:$AZ$251,0)),"") | F12: =IFERROR(INDEX(approvals!$AR$2:$AR$251,MATCH($B$2&"|"&6,approvals!$AZ$2:$AZ$251,0)),"") | G12: =IFERROR(INDEX(approvals!$AS$2:$AS$251,MATCH($B$2&"|"&6,approvals!$AZ$2:$AZ$251,0)),"") | H12: =IFERROR(INDEX(approvals!$AT$2:$AT$251,MATCH($B$2&"|"&6,approvals!$AZ$2:$AZ$251,0)),"") | I12: =IFERROR(IF(INDEX(approvals!$AT$2:$AT$251,MATCH($B$2&"|"&6,approvals!$AZ$2:$AZ$251,0))=0,"",ROUND(INDEX(approvals!$AU$2:$AU$251,MATCH($B$2&"|"&6,approvals!$AZ$2:$AZ$251,0))/INDEX(approvals!$AT$2:$AT$251,MATCH($B$2&"|"&6,approvals!$AZ$2:$AZ$251,0)),1)),"") | J12: =IFERROR(INDEX(approvals!$AV$2:$AV$251,MATCH($B$2&"|"&6,approvals!$AZ$2:$AZ$251,0)),"") | K12: =IFERROR(INDEX(approvals!$AW$2:$AW$251,MATCH($B$2&"|"&6,approvals!$AZ$2:$AZ$251,0)),"") | L12: =IFERROR(INDEX(approvals!$AX$2:$AX$251,MATCH($B$2&"|"&6,approvals!$AZ$2:$AZ$251,0)),"") | M12: =IFERROR(INDEX(approvals!$AY$2:$AY$251,MATCH($B$2&"|"&6,approvals!$AZ$2:$AZ$251,0)),"") | N12: =IFERROR(IF(INDEX(approvals!$AL$2:$AL$251,MATCH($B$2&"|"&6,approvals!$AZ$2:$AZ$251,0))>=config!$B$30,"OK","under "&config!$B$30&": ask the owner to re-post"),"")
A13: =IFERROR(INDEX(approvals!$M$2:$M$251,MATCH($B$2&"|"&7,approvals!$AZ$2:$AZ$251,0)),"") | B13: =IFERROR(INDEX(approvals!$K$2:$K$251,MATCH($B$2&"|"&7,approvals!$AZ$2:$AZ$251,0)),"") | C13: =IFERROR(INDEX(approvals!$AL$2:$AL$251,MATCH($B$2&"|"&7,approvals!$AZ$2:$AZ$251,0)),"") | D13: =IFERROR(INDEX(approvals!$AM$2:$AM$251,MATCH($B$2&"|"&7,approvals!$AZ$2:$AZ$251,0)),"") | E13: =IFERROR(INDEX(approvals!$AQ$2:$AQ$251,MATCH($B$2&"|"&7,approvals!$AZ$2:$AZ$251,0)),"") | F13: =IFERROR(INDEX(approvals!$AR$2:$AR$251,MATCH($B$2&"|"&7,approvals!$AZ$2:$AZ$251,0)),"") | G13: =IFERROR(INDEX(approvals!$AS$2:$AS$251,MATCH($B$2&"|"&7,approvals!$AZ$2:$AZ$251,0)),"") | H13: =IFERROR(INDEX(approvals!$AT$2:$AT$251,MATCH($B$2&"|"&7,approvals!$AZ$2:$AZ$251,0)),"") | I13: =IFERROR(IF(INDEX(approvals!$AT$2:$AT$251,MATCH($B$2&"|"&7,approvals!$AZ$2:$AZ$251,0))=0,"",ROUND(INDEX(approvals!$AU$2:$AU$251,MATCH($B$2&"|"&7,approvals!$AZ$2:$AZ$251,0))/INDEX(approvals!$AT$2:$AT$251,MATCH($B$2&"|"&7,approvals!$AZ$2:$AZ$251,0)),1)),"") | J13: =IFERROR(INDEX(approvals!$AV$2:$AV$251,MATCH($B$2&"|"&7,approvals!$AZ$2:$AZ$251,0)),"") | K13: =IFERROR(INDEX(approvals!$AW$2:$AW$251,MATCH($B$2&"|"&7,approvals!$AZ$2:$AZ$251,0)),"") | L13: =IFERROR(INDEX(approvals!$AX$2:$AX$251,MATCH($B$2&"|"&7,approvals!$AZ$2:$AZ$251,0)),"") | M13: =IFERROR(INDEX(approvals!$AY$2:$AY$251,MATCH($B$2&"|"&7,approvals!$AZ$2:$AZ$251,0)),"") | N13: =IFERROR(IF(INDEX(approvals!$AL$2:$AL$251,MATCH($B$2&"|"&7,approvals!$AZ$2:$AZ$251,0))>=config!$B$30,"OK","under "&config!$B$30&": ask the owner to re-post"),"")
A14: =IFERROR(INDEX(approvals!$M$2:$M$251,MATCH($B$2&"|"&8,approvals!$AZ$2:$AZ$251,0)),"") | B14: =IFERROR(INDEX(approvals!$K$2:$K$251,MATCH($B$2&"|"&8,approvals!$AZ$2:$AZ$251,0)),"") | C14: =IFERROR(INDEX(approvals!$AL$2:$AL$251,MATCH($B$2&"|"&8,approvals!$AZ$2:$AZ$251,0)),"") | D14: =IFERROR(INDEX(approvals!$AM$2:$AM$251,MATCH($B$2&"|"&8,approvals!$AZ$2:$AZ$251,0)),"") | E14: =IFERROR(INDEX(approvals!$AQ$2:$AQ$251,MATCH($B$2&"|"&8,approvals!$AZ$2:$AZ$251,0)),"") | F14: =IFERROR(INDEX(approvals!$AR$2:$AR$251,MATCH($B$2&"|"&8,approvals!$AZ$2:$AZ$251,0)),"") | G14: =IFERROR(INDEX(approvals!$AS$2:$AS$251,MATCH($B$2&"|"&8,approvals!$AZ$2:$AZ$251,0)),"") | H14: =IFERROR(INDEX(approvals!$AT$2:$AT$251,MATCH($B$2&"|"&8,approvals!$AZ$2:$AZ$251,0)),"") | I14: =IFERROR(IF(INDEX(approvals!$AT$2:$AT$251,MATCH($B$2&"|"&8,approvals!$AZ$2:$AZ$251,0))=0,"",ROUND(INDEX(approvals!$AU$2:$AU$251,MATCH($B$2&"|"&8,approvals!$AZ$2:$AZ$251,0))/INDEX(approvals!$AT$2:$AT$251,MATCH($B$2&"|"&8,approvals!$AZ$2:$AZ$251,0)),1)),"") | J14: =IFERROR(INDEX(approvals!$AV$2:$AV$251,MATCH($B$2&"|"&8,approvals!$AZ$2:$AZ$251,0)),"") | K14: =IFERROR(INDEX(approvals!$AW$2:$AW$251,MATCH($B$2&"|"&8,approvals!$AZ$2:$AZ$251,0)),"") | L14: =IFERROR(INDEX(approvals!$AX$2:$AX$251,MATCH($B$2&"|"&8,approvals!$AZ$2:$AZ$251,0)),"") | M14: =IFERROR(INDEX(approvals!$AY$2:$AY$251,MATCH($B$2&"|"&8,approvals!$AZ$2:$AZ$251,0)),"") | N14: =IFERROR(IF(INDEX(approvals!$AL$2:$AL$251,MATCH($B$2&"|"&8,approvals!$AZ$2:$AZ$251,0))>=config!$B$30,"OK","under "&config!$B$30&": ask the owner to re-post"),"")
A15: =IFERROR(INDEX(approvals!$M$2:$M$251,MATCH($B$2&"|"&9,approvals!$AZ$2:$AZ$251,0)),"") | B15: =IFERROR(INDEX(approvals!$K$2:$K$251,MATCH($B$2&"|"&9,approvals!$AZ$2:$AZ$251,0)),"") | C15: =IFERROR(INDEX(approvals!$AL$2:$AL$251,MATCH($B$2&"|"&9,approvals!$AZ$2:$AZ$251,0)),"") | D15: =IFERROR(INDEX(approvals!$AM$2:$AM$251,MATCH($B$2&"|"&9,approvals!$AZ$2:$AZ$251,0)),"") | E15: =IFERROR(INDEX(approvals!$AQ$2:$AQ$251,MATCH($B$2&"|"&9,approvals!$AZ$2:$AZ$251,0)),"") | F15: =IFERROR(INDEX(approvals!$AR$2:$AR$251,MATCH($B$2&"|"&9,approvals!$AZ$2:$AZ$251,0)),"") | G15: =IFERROR(INDEX(approvals!$AS$2:$AS$251,MATCH($B$2&"|"&9,approvals!$AZ$2:$AZ$251,0)),"") | H15: =IFERROR(INDEX(approvals!$AT$2:$AT$251,MATCH($B$2&"|"&9,approvals!$AZ$2:$AZ$251,0)),"") | I15: =IFERROR(IF(INDEX(approvals!$AT$2:$AT$251,MATCH($B$2&"|"&9,approvals!$AZ$2:$AZ$251,0))=0,"",ROUND(INDEX(approvals!$AU$2:$AU$251,MATCH($B$2&"|"&9,approvals!$AZ$2:$AZ$251,0))/INDEX(approvals!$AT$2:$AT$251,MATCH($B$2&"|"&9,approvals!$AZ$2:$AZ$251,0)),1)),"") | J15: =IFERROR(INDEX(approvals!$AV$2:$AV$251,MATCH($B$2&"|"&9,approvals!$AZ$2:$AZ$251,0)),"") | K15: =IFERROR(INDEX(approvals!$AW$2:$AW$251,MATCH($B$2&"|"&9,approvals!$AZ$2:$AZ$251,0)),"") | L15: =IFERROR(INDEX(approvals!$AX$2:$AX$251,MATCH($B$2&"|"&9,approvals!$AZ$2:$AZ$251,0)),"") | M15: =IFERROR(INDEX(approvals!$AY$2:$AY$251,MATCH($B$2&"|"&9,approvals!$AZ$2:$AZ$251,0)),"") | N15: =IFERROR(IF(INDEX(approvals!$AL$2:$AL$251,MATCH($B$2&"|"&9,approvals!$AZ$2:$AZ$251,0))>=config!$B$30,"OK","under "&config!$B$30&": ask the owner to re-post"),"")
A16: =IFERROR(INDEX(approvals!$M$2:$M$251,MATCH($B$2&"|"&10,approvals!$AZ$2:$AZ$251,0)),"") | B16: =IFERROR(INDEX(approvals!$K$2:$K$251,MATCH($B$2&"|"&10,approvals!$AZ$2:$AZ$251,0)),"") | C16: =IFERROR(INDEX(approvals!$AL$2:$AL$251,MATCH($B$2&"|"&10,approvals!$AZ$2:$AZ$251,0)),"") | D16: =IFERROR(INDEX(approvals!$AM$2:$AM$251,MATCH($B$2&"|"&10,approvals!$AZ$2:$AZ$251,0)),"") | E16: =IFERROR(INDEX(approvals!$AQ$2:$AQ$251,MATCH($B$2&"|"&10,approvals!$AZ$2:$AZ$251,0)),"") | F16: =IFERROR(INDEX(approvals!$AR$2:$AR$251,MATCH($B$2&"|"&10,approvals!$AZ$2:$AZ$251,0)),"") | G16: =IFERROR(INDEX(approvals!$AS$2:$AS$251,MATCH($B$2&"|"&10,approvals!$AZ$2:$AZ$251,0)),"") | H16: =IFERROR(INDEX(approvals!$AT$2:$AT$251,MATCH($B$2&"|"&10,approvals!$AZ$2:$AZ$251,0)),"") | I16: =IFERROR(IF(INDEX(approvals!$AT$2:$AT$251,MATCH($B$2&"|"&10,approvals!$AZ$2:$AZ$251,0))=0,"",ROUND(INDEX(approvals!$AU$2:$AU$251,MATCH($B$2&"|"&10,approvals!$AZ$2:$AZ$251,0))/INDEX(approvals!$AT$2:$AT$251,MATCH($B$2&"|"&10,approvals!$AZ$2:$AZ$251,0)),1)),"") | J16: =IFERROR(INDEX(approvals!$AV$2:$AV$251,MATCH($B$2&"|"&10,approvals!$AZ$2:$AZ$251,0)),"") | K16: =IFERROR(INDEX(approvals!$AW$2:$AW$251,MATCH($B$2&"|"&10,approvals!$AZ$2:$AZ$251,0)),"") | L16: =IFERROR(INDEX(approvals!$AX$2:$AX$251,MATCH($B$2&"|"&10,approvals!$AZ$2:$AZ$251,0)),"") | M16: =IFERROR(INDEX(approvals!$AY$2:$AY$251,MATCH($B$2&"|"&10,approvals!$AZ$2:$AZ$251,0)),"") | N16: =IFERROR(IF(INDEX(approvals!$AL$2:$AL$251,MATCH($B$2&"|"&10,approvals!$AZ$2:$AZ$251,0))>=config!$B$30,"OK","under "&config!$B$30&": ask the owner to re-post"),"")
A17: =IFERROR(INDEX(approvals!$M$2:$M$251,MATCH($B$2&"|"&11,approvals!$AZ$2:$AZ$251,0)),"") | B17: =IFERROR(INDEX(approvals!$K$2:$K$251,MATCH($B$2&"|"&11,approvals!$AZ$2:$AZ$251,0)),"") | C17: =IFERROR(INDEX(approvals!$AL$2:$AL$251,MATCH($B$2&"|"&11,approvals!$AZ$2:$AZ$251,0)),"") | D17: =IFERROR(INDEX(approvals!$AM$2:$AM$251,MATCH($B$2&"|"&11,approvals!$AZ$2:$AZ$251,0)),"") | E17: =IFERROR(INDEX(approvals!$AQ$2:$AQ$251,MATCH($B$2&"|"&11,approvals!$AZ$2:$AZ$251,0)),"") | F17: =IFERROR(INDEX(approvals!$AR$2:$AR$251,MATCH($B$2&"|"&11,approvals!$AZ$2:$AZ$251,0)),"") | G17: =IFERROR(INDEX(approvals!$AS$2:$AS$251,MATCH($B$2&"|"&11,approvals!$AZ$2:$AZ$251,0)),"") | H17: =IFERROR(INDEX(approvals!$AT$2:$AT$251,MATCH($B$2&"|"&11,approvals!$AZ$2:$AZ$251,0)),"") | I17: =IFERROR(IF(INDEX(approvals!$AT$2:$AT$251,MATCH($B$2&"|"&11,approvals!$AZ$2:$AZ$251,0))=0,"",ROUND(INDEX(approvals!$AU$2:$AU$251,MATCH($B$2&"|"&11,approvals!$AZ$2:$AZ$251,0))/INDEX(approvals!$AT$2:$AT$251,MATCH($B$2&"|"&11,approvals!$AZ$2:$AZ$251,0)),1)),"") | J17: =IFERROR(INDEX(approvals!$AV$2:$AV$251,MATCH($B$2&"|"&11,approvals!$AZ$2:$AZ$251,0)),"") | K17: =IFERROR(INDEX(approvals!$AW$2:$AW$251,MATCH($B$2&"|"&11,approvals!$AZ$2:$AZ$251,0)),"") | L17: =IFERROR(INDEX(approvals!$AX$2:$AX$251,MATCH($B$2&"|"&11,approvals!$AZ$2:$AZ$251,0)),"") | M17: =IFERROR(INDEX(approvals!$AY$2:$AY$251,MATCH($B$2&"|"&11,approvals!$AZ$2:$AZ$251,0)),"") | N17: =IFERROR(IF(INDEX(approvals!$AL$2:$AL$251,MATCH($B$2&"|"&11,approvals!$AZ$2:$AZ$251,0))>=config!$B$30,"OK","under "&config!$B$30&": ask the owner to re-post"),"")
A18: =IFERROR(INDEX(approvals!$M$2:$M$251,MATCH($B$2&"|"&12,approvals!$AZ$2:$AZ$251,0)),"") | B18: =IFERROR(INDEX(approvals!$K$2:$K$251,MATCH($B$2&"|"&12,approvals!$AZ$2:$AZ$251,0)),"") | C18: =IFERROR(INDEX(approvals!$AL$2:$AL$251,MATCH($B$2&"|"&12,approvals!$AZ$2:$AZ$251,0)),"") | D18: =IFERROR(INDEX(approvals!$AM$2:$AM$251,MATCH($B$2&"|"&12,approvals!$AZ$2:$AZ$251,0)),"") | E18: =IFERROR(INDEX(approvals!$AQ$2:$AQ$251,MATCH($B$2&"|"&12,approvals!$AZ$2:$AZ$251,0)),"") | F18: =IFERROR(INDEX(approvals!$AR$2:$AR$251,MATCH($B$2&"|"&12,approvals!$AZ$2:$AZ$251,0)),"") | G18: =IFERROR(INDEX(approvals!$AS$2:$AS$251,MATCH($B$2&"|"&12,approvals!$AZ$2:$AZ$251,0)),"") | H18: =IFERROR(INDEX(approvals!$AT$2:$AT$251,MATCH($B$2&"|"&12,approvals!$AZ$2:$AZ$251,0)),"") | I18: =IFERROR(IF(INDEX(approvals!$AT$2:$AT$251,MATCH($B$2&"|"&12,approvals!$AZ$2:$AZ$251,0))=0,"",ROUND(INDEX(approvals!$AU$2:$AU$251,MATCH($B$2&"|"&12,approvals!$AZ$2:$AZ$251,0))/INDEX(approvals!$AT$2:$AT$251,MATCH($B$2&"|"&12,approvals!$AZ$2:$AZ$251,0)),1)),"") | J18: =IFERROR(INDEX(approvals!$AV$2:$AV$251,MATCH($B$2&"|"&12,approvals!$AZ$2:$AZ$251,0)),"") | K18: =IFERROR(INDEX(approvals!$AW$2:$AW$251,MATCH($B$2&"|"&12,approvals!$AZ$2:$AZ$251,0)),"") | L18: =IFERROR(INDEX(approvals!$AX$2:$AX$251,MATCH($B$2&"|"&12,approvals!$AZ$2:$AZ$251,0)),"") | M18: =IFERROR(INDEX(approvals!$AY$2:$AY$251,MATCH($B$2&"|"&12,approvals!$AZ$2:$AZ$251,0)),"") | N18: =IFERROR(IF(INDEX(approvals!$AL$2:$AL$251,MATCH($B$2&"|"&12,approvals!$AZ$2:$AZ$251,0))>=config!$B$30,"OK","under "&config!$B$30&": ask the owner to re-post"),"")
A19: total | C19: =SUM(C7:C18) -> 34 | D19: =SUM(D7:D18) -> 25 | E19: =SUM(E7:E18) -> 5 | F19: =SUM(F7:F18) -> 2 | G19: =SUM(G7:G18) -> 2 | H19: =SUM(H7:H18) -> 25 | I19: =IFERROR(IFERROR(INDEX(campaigns!$CP$2:$CP$51,MATCH($B$2,campaigns!$A$2:$A$51,0)),""),"") -> 4.2 | J19: =SUM(J7:J18) -> 10 | K19: =SUM(K7:K18) -> 8 | L19: =SUM(L7:L18) -> 7 | M19: =SUM(M7:M18) -> 18
A21: Not counted
A22: outside the window (before T or after T+4) | C22: =IFERROR(INDEX(campaigns!$CU$2:$CU$51,MATCH($B$2,campaigns!$A$2:$A$51,0)),"") -> 2
A23: card code matches no office on this campaign | C23: =IFERROR(INDEX(campaigns!$CV$2:$CV$51,MATCH($B$2,campaigns!$A$2:$A$51,0)),"") -> 1
A24: from an office not on the drop (it said no, or turned the brand away at the door) | C24: =IFERROR(INDEX(campaigns!$CW$2:$CW$51,MATCH($B$2,campaigns!$A$2:$A$51,0)),"") -> 0
A26: Who sees what (legal pack file 13, D6 and D9): this sheet is the founder's only. The brand gets totals and at most three comments word for word; each office gets its own summary, never answers row by row. No email address is ever in this file: newsletter sign-ups live only in the campaign's separate sign-up form.

Sheet report
A1: =IF(LEFT($B$2,6)="SAMPLE","SAMPLE DATA. Illustrative placeholders, not results.","") -> SAMPLE DATA. Illustrative placeholders, not results.
A2: Campaign | B2: =IF(INDEX(campaigns!$A$2:$A$51,1)="","",INDEX(campaigns!$A$2:$A$51,1)) -> SAMPLE-CMP-001 | D2: Type a campaign_id over B2. Everything below is formulas over the logged rows: nothing is retyped. The PDF comes from tools/make_report.py.
A4: =IF($B$2="","",IFERROR(INDEX(campaigns!$BE$2:$BE$51,MATCH($B$2,campaigns!$A$2:$A$51,0)),"")&IF(IFERROR(INDEX(campaigns!$J$2:$J$51,MATCH($B$2,campaigns!$A$2:$A$51,0)),"")<>""," · "&IFERROR(INDEX(campaigns!$J$2:$J$51,MATCH($B$2,campaigns!$A$2:$A$51,0)),""),"")&" · "&config!$B$11&" · Drop "&TEXT(IFERROR(INDEX(campaigns!$BG$2:$BG$51,MATCH($B$2,campaigns!$A$2:$A$51,0)),""),"ddd yyyy-mm-dd")&" · Window "&TEXT(IFERROR(INDEX(campaigns!$BG$2:$BG$51,MATCH($B$2,campaigns!$A$2:$A$51,0)),""),"ddd yyyy-mm-dd")&" to "&TEXT(IFERROR(INDEX(drops!$R$2:$R$21,MATCH(IFERROR(INDEX(campaigns!$B$2:$B$51,MATCH($B$2,campaigns!$A$2:$A$51,0)),""),drops!$A$2:$A$21,0)),""),"ddd yyyy-mm-dd")) -> SAMPLE Brightside · SAMPLE Sea Salt Lentil Crisps, 1 oz bags · Flatiron, NoMad and Union Square · Drop Tue 2027-01-12 · Window Tue 2027-01-12 to Tue 2027-01-19
A6: Delivered | B6: Placed | C6: Depleted | D6: Responded | E6: Scanned | F6: Purchased | G6: Incremental
A7: =IFERROR(INDEX(campaigns!$CB$2:$CB$51,MATCH($B$2,campaigns!$A$2:$A$51,0)),"") -> 250 | B7: =IFERROR(INDEX(campaigns!$CC$2:$CC$51,MATCH($B$2,campaigns!$A$2:$A$51,0)),"") -> 248 | C7: =IFERROR(INDEX(campaigns!$CG$2:$CG$51,MATCH($B$2,campaigns!$A$2:$A$51,0)),"") -> 200 | D7: =IFERROR(INDEX(campaigns!$CH$2:$CH$51,MATCH($B$2,campaigns!$A$2:$A$51,0)),"") -> 34 | E7: =IFERROR(INDEX(campaigns!$CX$2:$CX$51,MATCH($B$2,campaigns!$A$2:$A$51,0)),"") -> 45 | F7: =IFERROR(INDEX(campaigns!$CZ$2:$CZ$51,MATCH($B$2,campaigns!$A$2:$A$51,0)),"") -> 11 | G7: ="not measured" -> not measured
A8: =IF($B$2="","","handed over on the drop day") -> handed over on the drop day | B8: =IF($B$2="","","within one business day: "&IFERROR(INDEX(campaigns!$CD$2:$CD$51,MATCH($B$2,campaigns!$A$2:$A$51,0)),"")&" of "&IFERROR(INDEX(campaigns!$CB$2:$CB$51,MATCH($B$2,campaigns!$A$2:$A$51,0)),"")&IF(IFERROR(INDEX(campaigns!$CE$2:$CE$51,MATCH($B$2,campaigns!$A$2:$A$51,0)),"")="",""," ("&TEXT(IFERROR(INDEX(campaigns!$CE$2:$CE$51,MATCH($B$2,campaigns!$A$2:$A$51,0)),""),"0%")&")")) -> within one business day: 198 of 250 (79%) | C8: =IF($B$2="","","gone by day 5; plus "&IFERROR(INDEX(campaigns!$CF$2:$CF$51,MATCH($B$2,campaigns!$A$2:$A$51,0)),"")&" day-3 top-ups from reserve") -> gone by day 5; plus 5 day-3 top-ups from reserve | D8: =IF($B$2="","","survey responses; "&IFERROR(INDEX(campaigns!$CK$2:$CK$51,MATCH($B$2,campaigns!$A$2:$A$51,0)),"")&" said they tried it") -> survey responses; 25 said they tried it | E8: =IF($B$2="","","QR scans, T to T+4") -> QR scans, T to T+4 | F8: =IF($B$2="","","code redemptions reported by the brand"&IF(IFERROR(INDEX(campaigns!$DA$2:$DA$51,MATCH($B$2,campaigns!$A$2:$A$51,0)),"")="",""," as of "&TEXT(IFERROR(INDEX(campaigns!$DA$2:$DA$51,MATCH($B$2,campaigns!$A$2:$A$51,0)),""),"yyyy-mm-dd"))) -> code redemptions reported by the brand as of 2027-02-11 | G8: =IF($B$2="","","this report does not show whether the campaign caused any sale") -> this report does not show whether the campaign caused any sale
A10: Office | B10: Industry | C10: Tuesday headcount | D10: Units delivered | E10: Units placed | F10: Topped up | G10: Gone by day 5 | H10: Responses | I10: QR scans | J10: Placement photo | K10: Later photo
A11: =IFERROR(INDEX(approvals!$M$2:$M$251,MATCH($B$2&"|"&1,approvals!$AZ$2:$AZ$251,0))&IF(INDEX(approvals!$AB$2:$AB$251,MATCH($B$2&"|"&1,approvals!$AZ$2:$AZ$251,0))="N","*",""),"") -> A | B11: =IFERROR(INDEX(offices!$AI$2:$AI$61,MATCH(INDEX(approvals!$B$2:$B$251,MATCH($B$2&"|"&1,approvals!$AZ$2:$AZ$251,0)),offices!$A$2:$A$61,0)),"") -> SAMPLE Software | C11: =IFERROR(SUBSTITUTE(INDEX(offices!$AK$2:$AK$61,MATCH(INDEX(approvals!$B$2:$B$251,MATCH($B$2&"|"&1,approvals!$AZ$2:$AZ$251,0)),offices!$A$2:$A$61,0)),"-"," to "),"") -> 40 to 75 | D11: =IFERROR(INDEX(approvals!$U$2:$U$251,MATCH($B$2&"|"&1,approvals!$AZ$2:$AZ$251,0)),"") -> 40 | E11: =IFERROR(INDEX(approvals!$AA$2:$AA$251,MATCH($B$2&"|"&1,approvals!$AZ$2:$AZ$251,0)),"") -> 40 | F11: =IFERROR(INDEX(approvals!$AD$2:$AD$251,MATCH($B$2&"|"&1,approvals!$AZ$2:$AZ$251,0)),"") -> 5 | G11: =IFERROR(INDEX(approvals!$AG$2:$AG$251,MATCH($B$2&"|"&1,approvals!$AZ$2:$AZ$251,0)),"") -> 44 | H11: =IFERROR(INDEX(approvals!$AL$2:$AL$251,MATCH($B$2&"|"&1,approvals!$AZ$2:$AZ$251,0)),"") -> 9 | I11: =IFERROR(INDEX(approvals!$AN$2:$AN$251,MATCH($B$2&"|"&1,approvals!$AZ$2:$AZ$251,0)),"") -> 14 | J11: =IFERROR(IF(INDEX(approvals!$Y$2:$Y$251,MATCH($B$2&"|"&1,approvals!$AZ$2:$AZ$251,0))="","none received",TEXT(INDEX(approvals!$Y$2:$Y$251,MATCH($B$2&"|"&1,approvals!$AZ$2:$AZ$251,0)),"yyyy-mm-dd")),"") -> 2027-01-12 | K11: =IFERROR(IF(INDEX(approvals!$AI$2:$AI$251,MATCH($B$2&"|"&1,approvals!$AZ$2:$AZ$251,0))="","none received",TEXT(INDEX(approvals!$AI$2:$AI$251,MATCH($B$2&"|"&1,approvals!$AZ$2:$AZ$251,0)),"yyyy-mm-dd")),"") -> 2027-01-19
A12: =IFERROR(INDEX(approvals!$M$2:$M$251,MATCH($B$2&"|"&2,approvals!$AZ$2:$AZ$251,0))&IF(INDEX(approvals!$AB$2:$AB$251,MATCH($B$2&"|"&2,approvals!$AZ$2:$AZ$251,0))="N","*",""),"") -> B | B12: =IFERROR(INDEX(offices!$AI$2:$AI$61,MATCH(INDEX(approvals!$B$2:$B$251,MATCH($B$2&"|"&2,approvals!$AZ$2:$AZ$251,0)),offices!$A$2:$A$61,0)),"") -> SAMPLE Architecture | C12: =IFERROR(SUBSTITUTE(INDEX(offices!$AK$2:$AK$61,MATCH(INDEX(approvals!$B$2:$B$251,MATCH($B$2&"|"&2,approvals!$AZ$2:$AZ$251,0)),offices!$A$2:$A$61,0)),"-"," to "),"") -> 40 to 75 | D12: =IFERROR(INDEX(approvals!$U$2:$U$251,MATCH($B$2&"|"&2,approvals!$AZ$2:$AZ$251,0)),"") -> 40 | E12: =IFERROR(INDEX(approvals!$AA$2:$AA$251,MATCH($B$2&"|"&2,approvals!$AZ$2:$AZ$251,0)),"") -> 38 | F12: =IFERROR(INDEX(approvals!$AD$2:$AD$251,MATCH($B$2&"|"&2,approvals!$AZ$2:$AZ$251,0)),"") -> 0 | G12: =IFERROR(INDEX(approvals!$AG$2:$AG$251,MATCH($B$2&"|"&2,approvals!$AZ$2:$AZ$251,0)),"") -> 31 | H12: =IFERROR(INDEX(approvals!$AL$2:$AL$251,MATCH($B$2&"|"&2,approvals!$AZ$2:$AZ$251,0)),"") -> 6 | I12: =IFERROR(INDEX(approvals!$AN$2:$AN$251,MATCH($B$2&"|"&2,approvals!$AZ$2:$AZ$251,0)),"") -> 7 | J12: =IFERROR(IF(INDEX(approvals!$Y$2:$Y$251,MATCH($B$2&"|"&2,approvals!$AZ$2:$AZ$251,0))="","none received",TEXT(INDEX(approvals!$Y$2:$Y$251,MATCH($B$2&"|"&2,approvals!$AZ$2:$AZ$251,0)),"yyyy-mm-dd")),"") -> 2027-01-12 | K12: =IFERROR(IF(INDEX(approvals!$AI$2:$AI$251,MATCH($B$2&"|"&2,approvals!$AZ$2:$AZ$251,0))="","none received",TEXT(INDEX(approvals!$AI$2:$AI$251,MATCH($B$2&"|"&2,approvals!$AZ$2:$AZ$251,0)),"yyyy-mm-dd")),"") -> 2027-01-19
A13: =IFERROR(INDEX(approvals!$M$2:$M$251,MATCH($B$2&"|"&3,approvals!$AZ$2:$AZ$251,0))&IF(INDEX(approvals!$AB$2:$AB$251,MATCH($B$2&"|"&3,approvals!$AZ$2:$AZ$251,0))="N","*",""),"") -> C | B13: =IFERROR(INDEX(offices!$AI$2:$AI$61,MATCH(INDEX(approvals!$B$2:$B$251,MATCH($B$2&"|"&3,approvals!$AZ$2:$AZ$251,0)),offices!$A$2:$A$61,0)),"") -> SAMPLE Media | C13: =IFERROR(SUBSTITUTE(INDEX(offices!$AK$2:$AK$61,MATCH(INDEX(approvals!$B$2:$B$251,MATCH($B$2&"|"&3,approvals!$AZ$2:$AZ$251,0)),offices!$A$2:$A$61,0)),"-"," to "),"") -> 76 to 150 | D13: =IFERROR(INDEX(approvals!$U$2:$U$251,MATCH($B$2&"|"&3,approvals!$AZ$2:$AZ$251,0)),"") -> 50 | E13: =IFERROR(INDEX(approvals!$AA$2:$AA$251,MATCH($B$2&"|"&3,approvals!$AZ$2:$AZ$251,0)),"") -> 50 | F13: =IFERROR(INDEX(approvals!$AD$2:$AD$251,MATCH($B$2&"|"&3,approvals!$AZ$2:$AZ$251,0)),"") -> 0 | G13: =IFERROR(INDEX(approvals!$AG$2:$AG$251,MATCH($B$2&"|"&3,approvals!$AZ$2:$AZ$251,0)),"") -> 41 | H13: =IFERROR(INDEX(approvals!$AL$2:$AL$251,MATCH($B$2&"|"&3,approvals!$AZ$2:$AZ$251,0)),"") -> 8 | I13: =IFERROR(INDEX(approvals!$AN$2:$AN$251,MATCH($B$2&"|"&3,approvals!$AZ$2:$AZ$251,0)),"") -> 11 | J13: =IFERROR(IF(INDEX(approvals!$Y$2:$Y$251,MATCH($B$2&"|"&3,approvals!$AZ$2:$AZ$251,0))="","none received",TEXT(INDEX(approvals!$Y$2:$Y$251,MATCH($B$2&"|"&3,approvals!$AZ$2:$AZ$251,0)),"yyyy-mm-dd")),"") -> 2027-01-12 | K13: =IFERROR(IF(INDEX(approvals!$AI$2:$AI$251,MATCH($B$2&"|"&3,approvals!$AZ$2:$AZ$251,0))="","none received",TEXT(INDEX(approvals!$AI$2:$AI$251,MATCH($B$2&"|"&3,approvals!$AZ$2:$AZ$251,0)),"yyyy-mm-dd")),"") -> 2027-01-19
A14: =IFERROR(INDEX(approvals!$M$2:$M$251,MATCH($B$2&"|"&4,approvals!$AZ$2:$AZ$251,0))&IF(INDEX(approvals!$AB$2:$AB$251,MATCH($B$2&"|"&4,approvals!$AZ$2:$AZ$251,0))="N","*",""),"") -> D* | B14: =IFERROR(INDEX(offices!$AI$2:$AI$61,MATCH(INDEX(approvals!$B$2:$B$251,MATCH($B$2&"|"&4,approvals!$AZ$2:$AZ$251,0)),offices!$A$2:$A$61,0)),"") -> SAMPLE Nonprofit | C14: =IFERROR(SUBSTITUTE(INDEX(offices!$AK$2:$AK$61,MATCH(INDEX(approvals!$B$2:$B$251,MATCH($B$2&"|"&4,approvals!$AZ$2:$AZ$251,0)),offices!$A$2:$A$61,0)),"-"," to "),"") -> 76 to 150 | D14: =IFERROR(INDEX(approvals!$U$2:$U$251,MATCH($B$2&"|"&4,approvals!$AZ$2:$AZ$251,0)),"") -> 50 | E14: =IFERROR(INDEX(approvals!$AA$2:$AA$251,MATCH($B$2&"|"&4,approvals!$AZ$2:$AZ$251,0)),"") -> 50 | F14: =IFERROR(INDEX(approvals!$AD$2:$AD$251,MATCH($B$2&"|"&4,approvals!$AZ$2:$AZ$251,0)),"") -> 0 | G14: =IFERROR(INDEX(approvals!$AG$2:$AG$251,MATCH($B$2&"|"&4,approvals!$AZ$2:$AZ$251,0)),"") -> 22 | H14: =IFERROR(INDEX(approvals!$AL$2:$AL$251,MATCH($B$2&"|"&4,approvals!$AZ$2:$AZ$251,0)),"") -> 4 | I14: =IFERROR(INDEX(approvals!$AN$2:$AN$251,MATCH($B$2&"|"&4,approvals!$AZ$2:$AZ$251,0)),"") -> 4 | J14: =IFERROR(IF(INDEX(approvals!$Y$2:$Y$251,MATCH($B$2&"|"&4,approvals!$AZ$2:$AZ$251,0))="","none received",TEXT(INDEX(approvals!$Y$2:$Y$251,MATCH($B$2&"|"&4,approvals!$AZ$2:$AZ$251,0)),"yyyy-mm-dd")),"") -> 2027-01-14 | K14: =IFERROR(IF(INDEX(approvals!$AI$2:$AI$251,MATCH($B$2&"|"&4,approvals!$AZ$2:$AZ$251,0))="","none received",TEXT(INDEX(approvals!$AI$2:$AI$251,MATCH($B$2&"|"&4,approvals!$AZ$2:$AZ$251,0)),"yyyy-mm-dd")),"") -> 2027-01-19
A15: =IFERROR(INDEX(approvals!$M$2:$M$251,MATCH($B$2&"|"&5,approvals!$AZ$2:$AZ$251,0))&IF(INDEX(approvals!$AB$2:$AB$251,MATCH($B$2&"|"&5,approvals!$AZ$2:$AZ$251,0))="N","*",""),"") -> E | B15: =IFERROR(INDEX(offices!$AI$2:$AI$61,MATCH(INDEX(approvals!$B$2:$B$251,MATCH($B$2&"|"&5,approvals!$AZ$2:$AZ$251,0)),offices!$A$2:$A$61,0)),"") -> SAMPLE Design studio | C15: =IFERROR(SUBSTITUTE(INDEX(offices!$AK$2:$AK$61,MATCH(INDEX(approvals!$B$2:$B$251,MATCH($B$2&"|"&5,approvals!$AZ$2:$AZ$251,0)),offices!$A$2:$A$61,0)),"-"," to "),"") -> 151 to 250 | D15: =IFERROR(INDEX(approvals!$U$2:$U$251,MATCH($B$2&"|"&5,approvals!$AZ$2:$AZ$251,0)),"") -> 70 | E15: =IFERROR(INDEX(approvals!$AA$2:$AA$251,MATCH($B$2&"|"&5,approvals!$AZ$2:$AZ$251,0)),"") -> 70 | F15: =IFERROR(INDEX(approvals!$AD$2:$AD$251,MATCH($B$2&"|"&5,approvals!$AZ$2:$AZ$251,0)),"") -> 0 | G15: =IFERROR(INDEX(approvals!$AG$2:$AG$251,MATCH($B$2&"|"&5,approvals!$AZ$2:$AZ$251,0)),"") -> 62 | H15: =IFERROR(INDEX(approvals!$AL$2:$AL$251,MATCH($B$2&"|"&5,approvals!$AZ$2:$AZ$251,0)),"") -> 7 | I15: =IFERROR(INDEX(approvals!$AN$2:$AN$251,MATCH($B$2&"|"&5,approvals!$AZ$2:$AZ$251,0)),"") -> 9 | J15: =IFERROR(IF(INDEX(approvals!$Y$2:$Y$251,MATCH($B$2&"|"&5,approvals!$AZ$2:$AZ$251,0))="","none received",TEXT(INDEX(approvals!$Y$2:$Y$251,MATCH($B$2&"|"&5,approvals!$AZ$2:$AZ$251,0)),"yyyy-mm-dd")),"") -> 2027-01-12 | K15: =IFERROR(IF(INDEX(approvals!$AI$2:$AI$251,MATCH($B$2&"|"&5,approvals!$AZ$2:$AZ$251,0))="","none received",TEXT(INDEX(approvals!$AI$2:$AI$251,MATCH($B$2&"|"&5,approvals!$AZ$2:$AZ$251,0)),"yyyy-mm-dd")),"") -> 2027-01-19
A16: =IFERROR(INDEX(approvals!$M$2:$M$251,MATCH($B$2&"|"&6,approvals!$AZ$2:$AZ$251,0))&IF(INDEX(approvals!$AB$2:$AB$251,MATCH($B$2&"|"&6,approvals!$AZ$2:$AZ$251,0))="N","*",""),"") | B16: =IFERROR(INDEX(offices!$AI$2:$AI$61,MATCH(INDEX(approvals!$B$2:$B$251,MATCH($B$2&"|"&6,approvals!$AZ$2:$AZ$251,0)),offices!$A$2:$A$61,0)),"") | C16: =IFERROR(SUBSTITUTE(INDEX(offices!$AK$2:$AK$61,MATCH(INDEX(approvals!$B$2:$B$251,MATCH($B$2&"|"&6,approvals!$AZ$2:$AZ$251,0)),offices!$A$2:$A$61,0)),"-"," to "),"") | D16: =IFERROR(INDEX(approvals!$U$2:$U$251,MATCH($B$2&"|"&6,approvals!$AZ$2:$AZ$251,0)),"") | E16: =IFERROR(INDEX(approvals!$AA$2:$AA$251,MATCH($B$2&"|"&6,approvals!$AZ$2:$AZ$251,0)),"") | F16: =IFERROR(INDEX(approvals!$AD$2:$AD$251,MATCH($B$2&"|"&6,approvals!$AZ$2:$AZ$251,0)),"") | G16: =IFERROR(INDEX(approvals!$AG$2:$AG$251,MATCH($B$2&"|"&6,approvals!$AZ$2:$AZ$251,0)),"") | H16: =IFERROR(INDEX(approvals!$AL$2:$AL$251,MATCH($B$2&"|"&6,approvals!$AZ$2:$AZ$251,0)),"") | I16: =IFERROR(INDEX(approvals!$AN$2:$AN$251,MATCH($B$2&"|"&6,approvals!$AZ$2:$AZ$251,0)),"") | J16: =IFERROR(IF(INDEX(approvals!$Y$2:$Y$251,MATCH($B$2&"|"&6,approvals!$AZ$2:$AZ$251,0))="","none received",TEXT(INDEX(approvals!$Y$2:$Y$251,MATCH($B$2&"|"&6,approvals!$AZ$2:$AZ$251,0)),"yyyy-mm-dd")),"") | K16: =IFERROR(IF(INDEX(approvals!$AI$2:$AI$251,MATCH($B$2&"|"&6,approvals!$AZ$2:$AZ$251,0))="","none received",TEXT(INDEX(approvals!$AI$2:$AI$251,MATCH($B$2&"|"&6,approvals!$AZ$2:$AZ$251,0)),"yyyy-mm-dd")),"")
A17: =IFERROR(INDEX(approvals!$M$2:$M$251,MATCH($B$2&"|"&7,approvals!$AZ$2:$AZ$251,0))&IF(INDEX(approvals!$AB$2:$AB$251,MATCH($B$2&"|"&7,approvals!$AZ$2:$AZ$251,0))="N","*",""),"") | B17: =IFERROR(INDEX(offices!$AI$2:$AI$61,MATCH(INDEX(approvals!$B$2:$B$251,MATCH($B$2&"|"&7,approvals!$AZ$2:$AZ$251,0)),offices!$A$2:$A$61,0)),"") | C17: =IFERROR(SUBSTITUTE(INDEX(offices!$AK$2:$AK$61,MATCH(INDEX(approvals!$B$2:$B$251,MATCH($B$2&"|"&7,approvals!$AZ$2:$AZ$251,0)),offices!$A$2:$A$61,0)),"-"," to "),"") | D17: =IFERROR(INDEX(approvals!$U$2:$U$251,MATCH($B$2&"|"&7,approvals!$AZ$2:$AZ$251,0)),"") | E17: =IFERROR(INDEX(approvals!$AA$2:$AA$251,MATCH($B$2&"|"&7,approvals!$AZ$2:$AZ$251,0)),"") | F17: =IFERROR(INDEX(approvals!$AD$2:$AD$251,MATCH($B$2&"|"&7,approvals!$AZ$2:$AZ$251,0)),"") | G17: =IFERROR(INDEX(approvals!$AG$2:$AG$251,MATCH($B$2&"|"&7,approvals!$AZ$2:$AZ$251,0)),"") | H17: =IFERROR(INDEX(approvals!$AL$2:$AL$251,MATCH($B$2&"|"&7,approvals!$AZ$2:$AZ$251,0)),"") | I17: =IFERROR(INDEX(approvals!$AN$2:$AN$251,MATCH($B$2&"|"&7,approvals!$AZ$2:$AZ$251,0)),"") | J17: =IFERROR(IF(INDEX(approvals!$Y$2:$Y$251,MATCH($B$2&"|"&7,approvals!$AZ$2:$AZ$251,0))="","none received",TEXT(INDEX(approvals!$Y$2:$Y$251,MATCH($B$2&"|"&7,approvals!$AZ$2:$AZ$251,0)),"yyyy-mm-dd")),"") | K17: =IFERROR(IF(INDEX(approvals!$AI$2:$AI$251,MATCH($B$2&"|"&7,approvals!$AZ$2:$AZ$251,0))="","none received",TEXT(INDEX(approvals!$AI$2:$AI$251,MATCH($B$2&"|"&7,approvals!$AZ$2:$AZ$251,0)),"yyyy-mm-dd")),"")
A18: =IFERROR(INDEX(approvals!$M$2:$M$251,MATCH($B$2&"|"&8,approvals!$AZ$2:$AZ$251,0))&IF(INDEX(approvals!$AB$2:$AB$251,MATCH($B$2&"|"&8,approvals!$AZ$2:$AZ$251,0))="N","*",""),"") | B18: =IFERROR(INDEX(offices!$AI$2:$AI$61,MATCH(INDEX(approvals!$B$2:$B$251,MATCH($B$2&"|"&8,approvals!$AZ$2:$AZ$251,0)),offices!$A$2:$A$61,0)),"") | C18: =IFERROR(SUBSTITUTE(INDEX(offices!$AK$2:$AK$61,MATCH(INDEX(approvals!$B$2:$B$251,MATCH($B$2&"|"&8,approvals!$AZ$2:$AZ$251,0)),offices!$A$2:$A$61,0)),"-"," to "),"") | D18: =IFERROR(INDEX(approvals!$U$2:$U$251,MATCH($B$2&"|"&8,approvals!$AZ$2:$AZ$251,0)),"") | E18: =IFERROR(INDEX(approvals!$AA$2:$AA$251,MATCH($B$2&"|"&8,approvals!$AZ$2:$AZ$251,0)),"") | F18: =IFERROR(INDEX(approvals!$AD$2:$AD$251,MATCH($B$2&"|"&8,approvals!$AZ$2:$AZ$251,0)),"") | G18: =IFERROR(INDEX(approvals!$AG$2:$AG$251,MATCH($B$2&"|"&8,approvals!$AZ$2:$AZ$251,0)),"") | H18: =IFERROR(INDEX(approvals!$AL$2:$AL$251,MATCH($B$2&"|"&8,approvals!$AZ$2:$AZ$251,0)),"") | I18: =IFERROR(INDEX(approvals!$AN$2:$AN$251,MATCH($B$2&"|"&8,approvals!$AZ$2:$AZ$251,0)),"") | J18: =IFERROR(IF(INDEX(approvals!$Y$2:$Y$251,MATCH($B$2&"|"&8,approvals!$AZ$2:$AZ$251,0))="","none received",TEXT(INDEX(approvals!$Y$2:$Y$251,MATCH($B$2&"|"&8,approvals!$AZ$2:$AZ$251,0)),"yyyy-mm-dd")),"") | K18: =IFERROR(IF(INDEX(approvals!$AI$2:$AI$251,MATCH($B$2&"|"&8,approvals!$AZ$2:$AZ$251,0))="","none received",TEXT(INDEX(approvals!$AI$2:$AI$251,MATCH($B$2&"|"&8,approvals!$AZ$2:$AZ$251,0)),"yyyy-mm-dd")),"")
A19: =IFERROR(INDEX(approvals!$M$2:$M$251,MATCH($B$2&"|"&9,approvals!$AZ$2:$AZ$251,0))&IF(INDEX(approvals!$AB$2:$AB$251,MATCH($B$2&"|"&9,approvals!$AZ$2:$AZ$251,0))="N","*",""),"") | B19: =IFERROR(INDEX(offices!$AI$2:$AI$61,MATCH(INDEX(approvals!$B$2:$B$251,MATCH($B$2&"|"&9,approvals!$AZ$2:$AZ$251,0)),offices!$A$2:$A$61,0)),"") | C19: =IFERROR(SUBSTITUTE(INDEX(offices!$AK$2:$AK$61,MATCH(INDEX(approvals!$B$2:$B$251,MATCH($B$2&"|"&9,approvals!$AZ$2:$AZ$251,0)),offices!$A$2:$A$61,0)),"-"," to "),"") | D19: =IFERROR(INDEX(approvals!$U$2:$U$251,MATCH($B$2&"|"&9,approvals!$AZ$2:$AZ$251,0)),"") | E19: =IFERROR(INDEX(approvals!$AA$2:$AA$251,MATCH($B$2&"|"&9,approvals!$AZ$2:$AZ$251,0)),"") | F19: =IFERROR(INDEX(approvals!$AD$2:$AD$251,MATCH($B$2&"|"&9,approvals!$AZ$2:$AZ$251,0)),"") | G19: =IFERROR(INDEX(approvals!$AG$2:$AG$251,MATCH($B$2&"|"&9,approvals!$AZ$2:$AZ$251,0)),"") | H19: =IFERROR(INDEX(approvals!$AL$2:$AL$251,MATCH($B$2&"|"&9,approvals!$AZ$2:$AZ$251,0)),"") | I19: =IFERROR(INDEX(approvals!$AN$2:$AN$251,MATCH($B$2&"|"&9,approvals!$AZ$2:$AZ$251,0)),"") | J19: =IFERROR(IF(INDEX(approvals!$Y$2:$Y$251,MATCH($B$2&"|"&9,approvals!$AZ$2:$AZ$251,0))="","none received",TEXT(INDEX(approvals!$Y$2:$Y$251,MATCH($B$2&"|"&9,approvals!$AZ$2:$AZ$251,0)),"yyyy-mm-dd")),"") | K19: =IFERROR(IF(INDEX(approvals!$AI$2:$AI$251,MATCH($B$2&"|"&9,approvals!$AZ$2:$AZ$251,0))="","none received",TEXT(INDEX(approvals!$AI$2:$AI$251,MATCH($B$2&"|"&9,approvals!$AZ$2:$AZ$251,0)),"yyyy-mm-dd")),"")
A20: =IFERROR(INDEX(approvals!$M$2:$M$251,MATCH($B$2&"|"&10,approvals!$AZ$2:$AZ$251,0))&IF(INDEX(approvals!$AB$2:$AB$251,MATCH($B$2&"|"&10,approvals!$AZ$2:$AZ$251,0))="N","*",""),"") | B20: =IFERROR(INDEX(offices!$AI$2:$AI$61,MATCH(INDEX(approvals!$B$2:$B$251,MATCH($B$2&"|"&10,approvals!$AZ$2:$AZ$251,0)),offices!$A$2:$A$61,0)),"") | C20: =IFERROR(SUBSTITUTE(INDEX(offices!$AK$2:$AK$61,MATCH(INDEX(approvals!$B$2:$B$251,MATCH($B$2&"|"&10,approvals!$AZ$2:$AZ$251,0)),offices!$A$2:$A$61,0)),"-"," to "),"") | D20: =IFERROR(INDEX(approvals!$U$2:$U$251,MATCH($B$2&"|"&10,approvals!$AZ$2:$AZ$251,0)),"") | E20: =IFERROR(INDEX(approvals!$AA$2:$AA$251,MATCH($B$2&"|"&10,approvals!$AZ$2:$AZ$251,0)),"") | F20: =IFERROR(INDEX(approvals!$AD$2:$AD$251,MATCH($B$2&"|"&10,approvals!$AZ$2:$AZ$251,0)),"") | G20: =IFERROR(INDEX(approvals!$AG$2:$AG$251,MATCH($B$2&"|"&10,approvals!$AZ$2:$AZ$251,0)),"") | H20: =IFERROR(INDEX(approvals!$AL$2:$AL$251,MATCH($B$2&"|"&10,approvals!$AZ$2:$AZ$251,0)),"") | I20: =IFERROR(INDEX(approvals!$AN$2:$AN$251,MATCH($B$2&"|"&10,approvals!$AZ$2:$AZ$251,0)),"") | J20: =IFERROR(IF(INDEX(approvals!$Y$2:$Y$251,MATCH($B$2&"|"&10,approvals!$AZ$2:$AZ$251,0))="","none received",TEXT(INDEX(approvals!$Y$2:$Y$251,MATCH($B$2&"|"&10,approvals!$AZ$2:$AZ$251,0)),"yyyy-mm-dd")),"") | K20: =IFERROR(IF(INDEX(approvals!$AI$2:$AI$251,MATCH($B$2&"|"&10,approvals!$AZ$2:$AZ$251,0))="","none received",TEXT(INDEX(approvals!$AI$2:$AI$251,MATCH($B$2&"|"&10,approvals!$AZ$2:$AZ$251,0)),"yyyy-mm-dd")),"")
A21: =IFERROR(INDEX(approvals!$M$2:$M$251,MATCH($B$2&"|"&11,approvals!$AZ$2:$AZ$251,0))&IF(INDEX(approvals!$AB$2:$AB$251,MATCH($B$2&"|"&11,approvals!$AZ$2:$AZ$251,0))="N","*",""),"") | B21: =IFERROR(INDEX(offices!$AI$2:$AI$61,MATCH(INDEX(approvals!$B$2:$B$251,MATCH($B$2&"|"&11,approvals!$AZ$2:$AZ$251,0)),offices!$A$2:$A$61,0)),"") | C21: =IFERROR(SUBSTITUTE(INDEX(offices!$AK$2:$AK$61,MATCH(INDEX(approvals!$B$2:$B$251,MATCH($B$2&"|"&11,approvals!$AZ$2:$AZ$251,0)),offices!$A$2:$A$61,0)),"-"," to "),"") | D21: =IFERROR(INDEX(approvals!$U$2:$U$251,MATCH($B$2&"|"&11,approvals!$AZ$2:$AZ$251,0)),"") | E21: =IFERROR(INDEX(approvals!$AA$2:$AA$251,MATCH($B$2&"|"&11,approvals!$AZ$2:$AZ$251,0)),"") | F21: =IFERROR(INDEX(approvals!$AD$2:$AD$251,MATCH($B$2&"|"&11,approvals!$AZ$2:$AZ$251,0)),"") | G21: =IFERROR(INDEX(approvals!$AG$2:$AG$251,MATCH($B$2&"|"&11,approvals!$AZ$2:$AZ$251,0)),"") | H21: =IFERROR(INDEX(approvals!$AL$2:$AL$251,MATCH($B$2&"|"&11,approvals!$AZ$2:$AZ$251,0)),"") | I21: =IFERROR(INDEX(approvals!$AN$2:$AN$251,MATCH($B$2&"|"&11,approvals!$AZ$2:$AZ$251,0)),"") | J21: =IFERROR(IF(INDEX(approvals!$Y$2:$Y$251,MATCH($B$2&"|"&11,approvals!$AZ$2:$AZ$251,0))="","none received",TEXT(INDEX(approvals!$Y$2:$Y$251,MATCH($B$2&"|"&11,approvals!$AZ$2:$AZ$251,0)),"yyyy-mm-dd")),"") | K21: =IFERROR(IF(INDEX(approvals!$AI$2:$AI$251,MATCH($B$2&"|"&11,approvals!$AZ$2:$AZ$251,0))="","none received",TEXT(INDEX(approvals!$AI$2:$AI$251,MATCH($B$2&"|"&11,approvals!$AZ$2:$AZ$251,0)),"yyyy-mm-dd")),"")
A22: =IFERROR(INDEX(approvals!$M$2:$M$251,MATCH($B$2&"|"&12,approvals!$AZ$2:$AZ$251,0))&IF(INDEX(approvals!$AB$2:$AB$251,MATCH($B$2&"|"&12,approvals!$AZ$2:$AZ$251,0))="N","*",""),"") | B22: =IFERROR(INDEX(offices!$AI$2:$AI$61,MATCH(INDEX(approvals!$B$2:$B$251,MATCH($B$2&"|"&12,approvals!$AZ$2:$AZ$251,0)),offices!$A$2:$A$61,0)),"") | C22: =IFERROR(SUBSTITUTE(INDEX(offices!$AK$2:$AK$61,MATCH(INDEX(approvals!$B$2:$B$251,MATCH($B$2&"|"&12,approvals!$AZ$2:$AZ$251,0)),offices!$A$2:$A$61,0)),"-"," to "),"") | D22: =IFERROR(INDEX(approvals!$U$2:$U$251,MATCH($B$2&"|"&12,approvals!$AZ$2:$AZ$251,0)),"") | E22: =IFERROR(INDEX(approvals!$AA$2:$AA$251,MATCH($B$2&"|"&12,approvals!$AZ$2:$AZ$251,0)),"") | F22: =IFERROR(INDEX(approvals!$AD$2:$AD$251,MATCH($B$2&"|"&12,approvals!$AZ$2:$AZ$251,0)),"") | G22: =IFERROR(INDEX(approvals!$AG$2:$AG$251,MATCH($B$2&"|"&12,approvals!$AZ$2:$AZ$251,0)),"") | H22: =IFERROR(INDEX(approvals!$AL$2:$AL$251,MATCH($B$2&"|"&12,approvals!$AZ$2:$AZ$251,0)),"") | I22: =IFERROR(INDEX(approvals!$AN$2:$AN$251,MATCH($B$2&"|"&12,approvals!$AZ$2:$AZ$251,0)),"") | J22: =IFERROR(IF(INDEX(approvals!$Y$2:$Y$251,MATCH($B$2&"|"&12,approvals!$AZ$2:$AZ$251,0))="","none received",TEXT(INDEX(approvals!$Y$2:$Y$251,MATCH($B$2&"|"&12,approvals!$AZ$2:$AZ$251,0)),"yyyy-mm-dd")),"") | K22: =IFERROR(IF(INDEX(approvals!$AI$2:$AI$251,MATCH($B$2&"|"&12,approvals!$AZ$2:$AZ$251,0))="","none received",TEXT(INDEX(approvals!$AI$2:$AI$251,MATCH($B$2&"|"&12,approvals!$AZ$2:$AZ$251,0)),"yyyy-mm-dd")),"")
A23: Total | D23: =SUM(D11:D22) -> 250 | E23: =SUM(E11:E22) -> 248 | F23: =SUM(F11:F22) -> 5 | G23: =SUM(G11:G22) -> 200 | H23: =SUM(H11:H22) -> 34 | I23: =SUM(I11:I22) -> 45
A24: =IF(COUNTIF(A11:A22,"*~*")>0,"* placed after the first business day","") -> * placed after the first business day
A26: =IF($B$2="","","Survey (n = "&IFERROR(INDEX(campaigns!$CH$2:$CH$51,MATCH($B$2,campaigns!$A$2:$A$51,0)),"")&"): tried "&IF(N(IFERROR(INDEX(campaigns!$CH$2:$CH$51,MATCH($B$2,campaigns!$A$2:$A$51,0)),""))=0,"-",TEXT(IFERROR(INDEX(campaigns!$CK$2:$CK$51,MATCH($B$2,campaigns!$A$2:$A$51,0)),"")/IFERROR(INDEX(campaigns!$CH$2:$CH$51,MATCH($B$2,campaigns!$A$2:$A$51,0)),""),"0%")&" ("&IFERROR(INDEX(campaigns!$CK$2:$CK$51,MATCH($B$2,campaigns!$A$2:$A$51,0)),"")&")")&" · average rating "&IFERROR(INDEX(campaigns!$CP$2:$CP$51,MATCH($B$2,campaigns!$A$2:$A$51,0)),"")&" of 5 ("&IFERROR(INDEX(campaigns!$CO$2:$CO$51,MATCH($B$2,campaigns!$A$2:$A$51,0)),"")&" ratings) · would buy, of "&(N(IFERROR(INDEX(campaigns!$CQ$2:$CQ$51,MATCH($B$2,campaigns!$A$2:$A$51,0)),""))+N(IFERROR(INDEX(campaigns!$CR$2:$CR$51,MATCH($B$2,campaigns!$A$2:$A$51,0)),""))+N(IFERROR(INDEX(campaigns!$CS$2:$CS$51,MATCH($B$2,campaigns!$A$2:$A$51,0)),"")))&" who answered: yes "&IF(N((N(IFERROR(INDEX(campaigns!$CQ$2:$CQ$51,MATCH($B$2,campaigns!$A$2:$A$51,0)),""))+N(IFERROR(INDEX(campaigns!$CR$2:$CR$51,MATCH($B$2,campaigns!$A$2:$A$51,0)),""))+N(IFERROR(INDEX(campaigns!$CS$2:$CS$51,MATCH($B$2,campaigns!$A$2:$A$51,0)),""))))=0,"-",TEXT(IFERROR(INDEX(campaigns!$CQ$2:$CQ$51,MATCH($B$2,campaigns!$A$2:$A$51,0)),"")/(N(IFERROR(INDEX(campaigns!$CQ$2:$CQ$51,MATCH($B$2,campaigns!$A$2:$A$51,0)),""))+N(IFERROR(INDEX(campaigns!$CR$2:$CR$51,MATCH($B$2,campaigns!$A$2:$A$51,0)),""))+N(IFERROR(INDEX(campaigns!$CS$2:$CS$51,MATCH($B$2,campaigns!$A$2:$A$51,0)),""))),"0%")&" ("&IFERROR(INDEX(campaigns!$CQ$2:$CQ$51,MATCH($B$2,campaigns!$A$2:$A$51,0)),"")&")")&", maybe "&IF(N((N(IFERROR(INDEX(campaigns!$CQ$2:$CQ$51,MATCH($B$2,campaigns!$A$2:$A$51,0)),""))+N(IFERROR(INDEX(campaigns!$CR$2:$CR$51,MATCH($B$2,campaigns!$A$2:$A$51,0)),""))+N(IFERROR(INDEX(campaigns!$CS$2:$CS$51,MATCH($B$2,campaigns!$A$2:$A$51,0)),""))))=0,"-",TEXT(IFERROR(INDEX(campaigns!$CR$2:$CR$51,MATCH($B$2,campaigns!$A$2:$A$51,0)),"")/(N(IFERROR(INDEX(campaigns!$CQ$2:$CQ$51,MATCH($B$2,campaigns!$A$2:$A$51,0)),""))+N(IFERROR(INDEX(campaigns!$CR$2:$CR$51,MATCH($B$2,campaigns!$A$2:$A$51,0)),""))+N(IFERROR(INDEX(campaigns!$CS$2:$CS$51,MATCH($B$2,campaigns!$A$2:$A$51,0)),""))),"0%")&" ("&IFERROR(INDEX(campaigns!$CR$2:$CR$51,MATCH($B$2,campaigns!$A$2:$A$51,0)),"")&")")&", no "&IF(N((N(IFERROR(INDEX(campaigns!$CQ$2:$CQ$51,MATCH($B$2,campaigns!$A$2:$A$51,0)),""))+N(IFERROR(INDEX(campaigns!$CR$2:$CR$51,MATCH($B$2,campaigns!$A$2:$A$51,0)),""))+N(IFERROR(INDEX(campaigns!$CS$2:$CS$51,MATCH($B$2,campaigns!$A$2:$A$51,0)),""))))=0,"-",TEXT(IFERROR(INDEX(campaigns!$CS$2:$CS$51,MATCH($B$2,campaigns!$A$2:$A$51,0)),"")/(N(IFERROR(INDEX(campaigns!$CQ$2:$CQ$51,MATCH($B$2,campaigns!$A$2:$A$51,0)),""))+N(IFERROR(INDEX(campaigns!$CR$2:$CR$51,MATCH($B$2,campaigns!$A$2:$A$51,0)),""))+N(IFERROR(INDEX(campaigns!$CS$2:$CS$51,MATCH($B$2,campaigns!$A$2:$A$51,0)),""))),"0%")&" ("&IFERROR(INDEX(campaigns!$CS$2:$CS$51,MATCH($B$2,campaigns!$A$2:$A$51,0)),"")&")")) -> Survey (n = 34): tried 74% (25) · average rating 4.2 of 5 (25 ratings) · would buy, of 25 who answered: yes 40% (10), maybe 32% (8), no 28% (7)
A27: =IF($B$2="","","Did not try: didn't see it "&IFERROR(INDEX(campaigns!$CL$2:$CL$51,MATCH($B$2,campaigns!$A$2:$A$51,0)),"")&", not for me "&IFERROR(INDEX(campaigns!$CM$2:$CM$51,MATCH($B$2,campaigns!$A$2:$A$51,0)),"")&", gone by the time they looked "&IFERROR(INDEX(campaigns!$CN$2:$CN$51,MATCH($B$2,campaigns!$A$2:$A$51,0)),"")) -> Did not try: didn't see it 5, not for me 2, gone by the time they looked 2
A28: =IF(IFERROR(INDEX(campaigns!$AL$2:$AL$51,MATCH($B$2,campaigns!$A$2:$A$51,0)),"")="","","“"&IFERROR(INDEX(campaigns!$AL$2:$AL$51,MATCH($B$2,campaigns!$A$2:$A$51,0)),"")&"”") -> “SAMPLE Saw it by the coffee machine and took two. Really good.”
A29: =IF(IFERROR(INDEX(campaigns!$AM$2:$AM$51,MATCH($B$2,campaigns!$A$2:$A$51,0)),"")="","","“"&IFERROR(INDEX(campaigns!$AM$2:$AM$51,MATCH($B$2,campaigns!$A$2:$A$51,0)),"")&"”") -> “SAMPLE A bit too salty for me.”
A30: =IF(IFERROR(INDEX(campaigns!$AN$2:$AN$51,MATCH($B$2,campaigns!$A$2:$A$51,0)),"")="","","“"&IFERROR(INDEX(campaigns!$AN$2:$AN$51,MATCH($B$2,campaigns!$A$2:$A$51,0)),"")&"”") -> “SAMPLE Asked [name removed] to save me a bag. Really good.”
A31: =IF($B$2="","","Three of "&IFERROR(INDEX(campaigns!$CT$2:$CT$51,MATCH($B$2,campaigns!$A$2:$A$51,0)),"")&" comments, word for word.") -> Three of 18 comments, word for word.
A33: =IF($B$2="","","Engagement: "&N(IFERROR(INDEX(campaigns!$CX$2:$CX$51,MATCH($B$2,campaigns!$A$2:$A$51,0)),""))&" QR scans across "&IFERROR(INDEX(campaigns!$BP$2:$BP$51,MATCH($B$2,campaigns!$A$2:$A$51,0)),"")&" offices · "&IF(IFERROR(INDEX(campaigns!$CZ$2:$CZ$51,MATCH($B$2,campaigns!$A$2:$A$51,0)),"")="","no code redemptions reported yet",IFERROR(INDEX(campaigns!$CZ$2:$CZ$51,MATCH($B$2,campaigns!$A$2:$A$51,0)),"")&" code redemptions to date")) -> Engagement: 45 QR scans across 5 offices · 11 code redemptions to date
A35: What we learned
A36: =IFERROR(INDEX(campaigns!$AO$2:$AO$51,MATCH($B$2,campaigns!$A$2:$A$51,0)),"") -> SAMPLE Office D placed a day late; agree a placement time at intake. SAMPLE Four people found it gone by the time they looked. SAMPLE Salt level came up in comments more than once.
A38: Recommendation
A39: =IFERROR(INDEX(campaigns!$AP$2:$AP$51,MATCH($B$2,campaigns!$A$2:$A$51,0)),"") -> SAMPLE Renew into offices A, C and E at the founding price. Same card.
A41: Limitations
A42: Each number is a separate step, counted as stated. Delivered: our count at handoff. Placed: units visible in the placement photo; an office may hold some back for later. Depleted: from photos or the pantry owner's count by day 5; one person may take several, and sharing and disposal are invisible. Tuesday headcount: a range the office reports; not everyone visits the pantry. Survey responses: anonymous and self-selected, from small samples, so one answer can move a share by several points. A QR scan is curiosity, not intent. Code redemptions: reported by the brand; some of those people would have bought anyway. Retailer sales, where shown, are confounded by everything else that happened that month and are suggestive only. Incremental purchases were not measured, so this report does not show whether the campaign caused any sale.
A44: ="Prepared by "&config!$B$4&" · "&config!$B$2&" · "&config!$B$6 -> Prepared by [FOUNDER NAME] · Desk Drop · [EMAIL]

Sheet config
A1: key | B1: value | C1: note
A2: company_name | B2: Desk Drop | C2: THE ONE PLACE the working name lives. Everything that prints the name reads this cell. Rename = change this cell (and BRAND_NAME in desk-drop-identity/brand.json for the printed pieces).
A3: tagline | B3: Emerging brands. Delivered to your workday. | C3: TAGLINE, working, may change.
A4: founder_name | B4: [FOUNDER NAME]
A5: founder_phone | B5: [PHONE] | C5: Printed on case labels, route sheets and messages.
A6: founder_email | B6: [EMAIL]
A7: postal_address | B7: [POSTAL ADDRESS] | C7: Mailing address (CAN-SPAM footer, invoices).
A8: receiving_address | B8: [RECEIVING ADDRESS] | C8: Where brands ship cases (founder and courier models). A street address that takes parcels; a PO box cannot receive carrier freight.
A9: short_link_domain | B9: go.example.com | C9: The short-link domain (links/QR-AND-LINKS.md). Never put the company name in a link's back-half.
A10: survey_privacy_url | B10: https://example.com/survey-privacy | C10: The full survey notice, hosted by the website (legal pack file 13, Part C).
A11: cluster_name | B11: Flatiron, NoMad and Union Square | C11: Printed in report headers.
A12: time_zone | B12: America/New_York | C12: Set the same in File > Settings (Google Sheets) so form timestamps match.
A13: units_base | B13: 30 | C13: Units per office = base + per_person x Tuesday headcount, rounded to 5, between min and max.
A14: units_per_person | B14: 0.2
A15: units_min | B15: 30 | C15: Plan: floor 30.
A16: units_max | B16: 80 | C16: Plan: ceiling 80.
A17: units_round | B17: 5
A18: reserve_share | B18: 0.1 | C18: Brand ships 10% extra as reserve.
A19: min_shelf_life_days | B19: 60 | C19: Days of shelf life left on the drop day (brand agreement section 2(b)).
A20: founding_price_usd | B20: 600 | C20: Founding: 5 offices, first three brands only.
A21: founding_offices | B21: 5
A22: standard_price_usd | B22: 1500 | C22: Standard: 10 offices.
A23: standard_offices | B23: 10
A24: extra_office_usd | B24: 150 | C24: Each office beyond the package.
A25: founding_lock_per_office_usd | B25: 120 | C25: A founding brand's next two campaigns: 120 per office up to 10 offices, then 150.
A26: founding_lock_max_offices | B26: 10
A27: founding_due_bd | B27: 5 | C27: Founding price due within five business days of the invoice, and before shipping.
A28: deposit_share | B28: 0.5 | C28: Standard: 50% on signing, 50% at placement confirmation (T+1).
A29: approvals_explicit_drops | B29: 3 | C29: An office's first three drops need its explicit yes; after that, opt-out with five business days' notice.
A30: min_responses_per_office | B30: 5 | C30: Office commitment; Gate 2.
A31: gate2_placed_share | B31: 0.8 | C31: Gate 2: 80% of units placed within one business day.
A32: newsletter_keep_days | B32: 30 | C32: Consented emails: our copy deleted 30 days after passing on (file 13, D8).
A33: answers_keep_months | B33: 12 | C33: Raw survey answers deleted 12 months after the campaign (file 13, D8).
A34: report_office_names | B34: letters | C34: letters = offices shown as A, B, C in brand reports; names_if_public = name only where public_naming_ok = Y.
A35: brand_form_version | B35: brand-gform-1.0 | C35: Founder-side brand form version (1.x asks about 275 units and $600; 2.x about 550 and $1,500).
A36: office_form_version | B36: office-gform-1.0 | C36: Founder-side office form version.
A37: today_override | B37: 46468 | C37: Leave empty. A date here replaces TODAY() everywhere (used by the dry runs).
A38: invoice_prefix | B38: INV-
A39: bank_details | B39: [BANK NAME] · Account name [ACCOUNT NAME] · Routing [ROUTING NUMBER] · Account [ACCOUNT NUMBER] | C39: Printed on invoices. Business account only (legal pack file 04).
A40: sales_tax_note | B40: Prices do not include sales tax. If any applies, it is shown above. | C40: Printed on invoices. Confirm with the accountant before the first invoice (legal pack file 09).
A41: office_summary_min_answers | B41: 5 | C41: An office summary breaks a brand's answers down (rating, would buy, comments) only where the office gave at least this many answers, and shows no rating or would-buy split from fewer people; below it, the count only, so no one's answer can be picked out (file 13, D9). 5 = the office's own commitment (review round 1 raised it from 3).
A42: contacts_keep_days_after_leaving | B42: 365 | C42: An office that left: clear its people's names, emails and phones (in_signed_offices, office_intake, office_form) this many days after left_date. Company, address and campaign counts stay.

Sheet calendar
A1: holiday | B1: name | D1: blackout_start | E1: blackout_end | F1: reason | H1: Source: CONTRACTS section 3 (derived, founder to confirm). US federal holidays by rule, observed dates; written by tools/opscal.py. Do not edit: rebuild with tools/build_tracker.py, or add a row by hand only to add a new year.
A2: 46023 | B2: New Year's Day | D2: 46202 | E2: 46206 | F2: week of 4 July (observed 2026-07-03)
A3: 46041 | B3: Martin Luther King Jr. Day | D3: 46252 | E3: 46265 | F3: last two weeks of August
A4: 46069 | B4: Washington's Birthday | D4: 46374 | E4: 46387 | F4: last two weeks of December
A5: 46167 | B5: Memorial Day | D5: 46573 | E5: 46577 | F5: week of 4 July (observed 2027-07-05)
A6: 46192 | B6: Juneteenth | D6: 46617 | E6: 46630 | F6: last two weeks of August
A7: 46206 | B7: Independence Day (observed) | D7: 46739 | E7: 46752 | F7: last two weeks of December
A8: 46272 | B8: Labor Day | D8: 46937 | E8: 46941 | F8: week of 4 July (observed 2028-07-04)
A9: 46307 | B9: Columbus Day | D9: 46983 | E9: 46996 | F9: last two weeks of August
A10: 46337 | B10: Veterans Day | D10: 47105 | E10: 47118 | F10: last two weeks of December
A11: 46352 | B11: Thanksgiving Day | D11: 47301 | E11: 47305 | F11: week of 4 July (observed 2029-07-04)
A12: 46381 | B12: Christmas Day | D12: 47348 | E12: 47361 | F12: last two weeks of August
A13: 46388 | B13: New Year's Day | D13: 47470 | E13: 47483 | F13: last two weeks of December
... A16: 46538 | B16: Memorial Day | D16: 47835 | E16: 47848 | F16: last two weeks of December
A17: 46556 | B17: Juneteenth (observed)
A18: 46573 | B18: Independence Day (observed)
A19: 46636 | B19: Labor Day
A20: 46671 | B20: Columbus Day
A21: 46702 | B21: Veterans Day
A22: 46716 | B22: Thanksgiving Day
A23: 46745 | B23: Christmas Day (observed)
A24: 46752 | B24: New Year's Day (observed)
A25: 46769 | B25: Martin Luther King Jr. Day
A26: 46804 | B26: Washington's Birthday
A27: 46902 | B27: Memorial Day
A28: 46923 | B28: Juneteenth
... A56: 47842 | B56: Christmas Day

Sheet drops
A1: drop_id | B1: drop_date | C1: delivery_model | D1: status | E1: receiving_location | F1: courier_or_van | G1: backup_person | H1: notes | I1: date_check | J1: weekday | K1: t_minus_10 | L1: ship_by_requested | M1: t_minus_5 | N1: t_minus_3 | O1: t_minus_1 | P1: t_plus_1 | Q1: t_plus_2 | R1: t_plus_4 | S1: t_plus_5 | T1: t_plus_7 | U1: t_plus_10 | V1: t_plus_14 | W1: t_plus_30_cal | X1: next_step | Y1: next_step_date | Z1: campaigns | AA1: stops | AB1: units_allocated | AC1: revenue_usd | AD1: kit_cost_usd | AE1: transport_cost_usd | AF1: other_direct_cost_usd | AG1: direct_cost_usd | AH1: cost_per_stop_usd | AI1: hours | AJ1: contribution_usd | AK1: contribution_per_hour_usd | AL1: gate2_placed_share | AM1: gate2_min_responses | AN1: gate2_reports_late | AO1: gate2_buy_again_yes
A2: SAMPLE-DRP-001 | B2: 46399 | C2: founder | D2: confirmed | E2: SAMPLE receiving address (founder's home, sealed cases) | F2: SAMPLE car service between stops | G2: SAMPLE backup (briefed 2027-01-08) | H2: SAMPLE campaign zero | I2: =IF($B2="","",IF(AND(WEEKDAY($B2)<>3,WEEKDAY($B2)<>4),"REFUSED: a "&TEXT($B2,"dddd")&". Tuesday or Wednesday only",IF(COUNTIF(calendar!$A$2:$A$80,$B2)>0,"REFUSED: a federal holiday",IF(COUNTIFS(calendar!$D$2:$D$20,"<="&WORKDAY($B2,4,calendar!$A$2:$A$80),calendar!$E$2:$E$20,">="&$B2)>0,"REFUSED: the five-day window overlaps a blackout","OK")))) -> OK | J2: =IF($B2="","",TEXT($B2,"ddd")) -> Tue | K2: =IF($I2="OK",WORKDAY($B2,-10,calendar!$A$2:$A$80),"") -> 46384 | L2: =IF($I2="OK",IF(SUMPRODUCT((calendar!$D$2:$D$20<=$M2)*(calendar!$E$2:$E$20>=$K2)*calendar!$D$2:$D$20)=0,$K2,MIN($K2,WORKDAY(SUMPRODUCT((calendar!$D$2:$D$20<=$M2)*(calendar!$E$2:$E$20>=$K2)*calendar!$D$2:$D$20)+5,-1,calendar!$A$2:$A$80))),"") -> 46378 | M2: =IF($I2="OK",WORKDAY($B2,-5,calendar!$A$2:$A$80),"") -> 46392 | N2: =IF($I2="OK",WORKDAY($B2,-3,calendar!$A$2:$A$80),"") -> 46394 | O2: =IF($I2="OK",WORKDAY($B2,-1,calendar!$A$2:$A$80),"") -> 46398 | P2: =IF($I2="OK",WORKDAY($B2,1,calendar!$A$2:$A$80),"") -> 46400 | Q2: =IF($I2="OK",WORKDAY($B2,2,calendar!$A$2:$A$80),"") -> 46401 | R2: =IF($I2="OK",WORKDAY($B2,4,calendar!$A$2:$A$80),"") -> 46406 | S2: =IF($I2="OK",WORKDAY($B2,5,calendar!$A$2:$A$80),"") -> 46407 | T2: =IF($I2="OK",WORKDAY($B2,7,calendar!$A$2:$A$80),"") -> 46409 | U2: =IF($I2="OK",WORKDAY($B2,10,calendar!$A$2:$A$80),"") -> 46414 | V2: =IF($I2="OK",WORKDAY($B2,14,calendar!$A$2:$A$80),"") -> 46420 | W2: =IF($I2="OK",$B2+30,"") -> 46429 | X2: =IF(NOT($I2="OK"),"",IF($K2>=IF(config!$B$37<>"",config!$B$37,TODAY()),"T-10 brand ships; approvals in",IF($M2>=IF(config!$B$37<>"",config!$B$37,TODAY()),"T-5 receive and count",IF($N2>=IF(config!$B$37<>"",config!$B$37,TODAY()),"T-3 print cards, send windows and posts",IF($O2>=IF(config!$B$37<>"",config!$B$37,TODAY()),"T-1 confirm owners, pack",IF($B2>=IF(config!$B$37<>"",config!$B$37,TODAY()),"T drop day",IF($P2>=IF(config!$B$37<>"",config!$B$37,TODAY()),"T+1 placement confirmation",IF($Q2>=IF(config!$B$37<>"",config!$B$37,TODAY()),"T+2 day-3 photos and top-ups",IF($R2>=IF(config!$B$37<>"",config!$B$37,TODAY()),"T+4 close survey, leftovers",IF($S2>=IF(config!$B$37<>"",config!$B$37,TODAY()),"T+5 newsletter list, reserve",IF($T2>=IF(config!$B$37<>"",config!$B$37,TODAY()),"T+7 report and office summaries",IF($U2>=IF(config!$B$37<>"",config!$B$37,TODAY()),"T+10 brand debrief, export actuals",IF($V2>=IF(config!$B$37<>"",config!$B$37,TODAY()),"T+14 return-label deadline",IF($W2>=IF(config!$B$37<>"",config!$B$37,TODAY()),"T+30 redemption check","done")))))))))))))) -> done | Y2: =IF(NOT($I2="OK"),"",IF($K2>=IF(config!$B$37<>"",config!$B$37,TODAY()),$K2,IF($M2>=IF(config!$B$37<>"",config!$B$37,TODAY()),$M2,IF($N2>=IF(config!$B$37<>"",config!$B$37,TODAY()),$N2,IF($O2>=IF(config!$B$37<>"",config!$B$37,TODAY()),$O2,IF($B2>=IF(config!$B$37<>"",config!$B$37,TODAY()),$B2,IF($P2>=IF(config!$B$37<>"",config!$B$37,TODAY()),$P2,IF($Q2>=IF(config!$B$37<>"",config!$B$37,TODAY()),$Q2,IF($R2>=IF(config!$B$37<>"",config!$B$37,TODAY()),$R2,IF($S2>=IF(config!$B$37<>"",config!$B$37,TODAY()),$S2,IF($T2>=IF(config!$B$37<>"",config!$B$37,TODAY()),$T2,IF($U2>=IF(config!$B$37<>"",config!$B$37,TODAY()),$U2,IF($V2>=IF(config!$B$37<>"",config!$B$37,TODAY()),$V2,IF($W2>=IF(config!$B$37<>"",config!$B$37,TODAY()),$W2,"")))))))))))))) | Z2: =IF($A2="","",COUNTIF(campaigns!$B$2:$B$51,$A2)) -> 2 | AA2: =IF($A2="","",COUNTIF(stops!$A$2:$A$151,$A2)) -> 5 | AB2: =IF($A2="","",SUMIFS(approvals!$S$2:$S$251,approvals!$H$2:$H$251,$A2,approvals!$P$2:$P$251,"Y")) -> 500 | AC2: =IF($A2="","",SUMIFS(campaigns!$DC$2:$DC$51,campaigns!$B$2:$B$51,$A2)) -> 1080 | AD2: =IF($A2="","",SUMIFS(costs!$E$2:$E$301,costs!$B$2:$B$301,$A2,costs!$D$2:$D$301,"kit")) -> 80 | AE2: =IF($A2="","",SUMIFS(costs!$E$2:$E$301,costs!$B$2:$B$301,$A2,costs!$D$2:$D$301,"transport")) -> 63 | AF2: =IF($A2="","",SUMIFS(costs!$E$2:$E$301,costs!$B$2:$B$301,$A2,costs!$D$2:$D$301,"other_direct")) -> 9 | AG2: =IF($A2="","",$AD2+$AE2+$AF2) -> 152 | AH2: =IF(OR($A2="",N($AA2)=0),"",ROUND($AG2/$AA2,2)) -> 30.4 | AI2: =IF($A2="","",SUMIFS(hours!$E$2:$E$1501,hours!$B$2:$B$1501,$A2)) -> 57 | AJ2: =IF($A2="","",$AC2-SUMIFS(campaigns!$DG$2:$DG$51,campaigns!$B$2:$B$51,$A2)-$AG2) -> 928 | AK2: =IF(OR($A2="",N($AI2)=0),"",ROUND($AJ2/$AI2,2)) -> 16.28 | AL2: =IF(OR($A2="",SUMIFS(campaigns!$CB$2:$CB$51,campaigns!$B$2:$B$51,$A2)=0),"",SUMIFS(campaigns!$CD$2:$CD$51,campaigns!$B$2:$B$51,$A2)/SUMIFS(campaigns!$CB$2:$CB$51,campaigns!$B$2:$B$51,$A2)) -> 0.896 | AM2: =IF(OR($A2="",COUNTIFS(approvals!$H$2:$H$251,$A2,approvals!$Q$2:$Q$251,"Y")=0),"",SUMPRODUCT(MIN(approvals!$BB$2:$BB$251+(approvals!$H$2:$H$251<>$A2)*1000000))) -> 4 | AN2: =IF(OR($A2="",$T2=""),"",COUNTIFS(campaigns!$B$2:$B$51,$A2,campaigns!$DU$2:$DU$51,"late")) -> 0 | AO2: =IF($A2="","",COUNTIFS(campaigns!$B$2:$B$51,$A2,campaigns!$AV$2:$AV$51,"yes")) -> 1
A3: SAMPLE-DRP-002 | B3: 46427 | C3: courier | D3: confirmed | E3: SAMPLE receiving address (founder's home, sealed cases) | F3: SAMPLE Example Courier, booking SAMPLE-BK-0209, pickup 7:45 am | G3: SAMPLE backup (briefed 2027-02-05) | H3: SAMPLE first standard run | I3: =IF($B3="","",IF(AND(WEEKDAY($B3)<>3,WEEKDAY($B3)<>4),"REFUSED: a "&TEXT($B3,"dddd")&". Tuesday or Wednesday only",IF(COUNTIF(calendar!$A$2:$A$80,$B3)>0,"REFUSED: a federal holiday",IF(COUNTIFS(calendar!$D$2:$D$20,"<="&WORKDAY($B3,4,calendar!$A$2:$A$80),calendar!$E$2:$E$20,">="&$B3)>0,"REFUSED: the five-day window overlaps a blackout","OK")))) -> OK | J3: =IF($B3="","",TEXT($B3,"ddd")) -> Tue | K3: =IF($I3="OK",WORKDAY($B3,-10,calendar!$A$2:$A$80),"") -> 46413 | L3: =IF($I3="OK",IF(SUMPRODUCT((calendar!$D$2:$D$20<=$M3)*(calendar!$E$2:$E$20>=$K3)*calendar!$D$2:$D$20)=0,$K3,MIN($K3,WORKDAY(SUMPRODUCT((calendar!$D$2:$D$20<=$M3)*(calendar!$E$2:$E$20>=$K3)*calendar!$D$2:$D$20)+5,-1,calendar!$A$2:$A$80))),"") -> 46413 | M3: =IF($I3="OK",WORKDAY($B3,-5,calendar!$A$2:$A$80),"") -> 46420 | N3: =IF($I3="OK",WORKDAY($B3,-3,calendar!$A$2:$A$80),"") -> 46422 | O3: =IF($I3="OK",WORKDAY($B3,-1,calendar!$A$2:$A$80),"") -> 46426 | P3: =IF($I3="OK",WORKDAY($B3,1,calendar!$A$2:$A$80),"") -> 46428 | Q3: =IF($I3="OK",WORKDAY($B3,2,calendar!$A$2:$A$80),"") -> 46429 | R3: =IF($I3="OK",WORKDAY($B3,4,calendar!$A$2:$A$80),"") -> 46434 | S3: =IF($I3="OK",WORKDAY($B3,5,calendar!$A$2:$A$80),"") -> 46435 | T3: =IF($I3="OK",WORKDAY($B3,7,calendar!$A$2:$A$80),"") -> 46437 | U3: =IF($I3="OK",WORKDAY($B3,10,calendar!$A$2:$A$80),"") -> 46442 | V3: =IF($I3="OK",WORKDAY($B3,14,calendar!$A$2:$A$80),"") -> 46448 | W3: =IF($I3="OK",$B3+30,"") -> 46457 | X3: =IF(NOT($I3="OK"),"",IF($K3>=IF(config!$B$37<>"",config!$B$37,TODAY()),"T-10 brand ships; approvals in",IF($M3>=IF(config!$B$37<>"",config!$B$37,TODAY()),"T-5 receive and count",IF($N3>=IF(config!$B$37<>"",config!$B$37,TODAY()),"T-3 print cards, send windows and posts",IF($O3>=IF(config!$B$37<>"",config!$B$37,TODAY()),"T-1 confirm owners, pack",IF($B3>=IF(config!$B$37<>"",config!$B$37,TODAY()),"T drop day",IF($P3>=IF(config!$B$37<>"",config!$B$37,TODAY()),"T+1 placement confirmation",IF($Q3>=IF(config!$B$37<>"",config!$B$37,TODAY()),"T+2 day-3 photos and top-ups",IF($R3>=IF(config!$B$37<>"",config!$B$37,TODAY()),"T+4 close survey, leftovers",IF($S3>=IF(config!$B$37<>"",config!$B$37,TODAY()),"T+5 newsletter list, reserve",IF($T3>=IF(config!$B$37<>"",config!$B$37,TODAY()),"T+7 report and office summaries",IF($U3>=IF(config!$B$37<>"",config!$B$37,TODAY()),"T+10 brand debrief, export actuals",IF($V3>=IF(config!$B$37<>"",config!$B$37,TODAY()),"T+14 return-label deadline",IF($W3>=IF(config!$B$37<>"",config!$B$37,TODAY()),"T+30 redemption check","done")))))))))))))) -> done | Y3: =IF(NOT($I3="OK"),"",IF($K3>=IF(config!$B$37<>"",config!$B$37,TODAY()),$K3,IF($M3>=IF(config!$B$37<>"",config!$B$37,TODAY()),$M3,IF($N3>=IF(config!$B$37<>"",config!$B$37,TODAY()),$N3,IF($O3>=IF(config!$B$37<>"",config!$B$37,TODAY()),$O3,IF($B3>=IF(config!$B$37<>"",config!$B$37,TODAY()),$B3,IF($P3>=IF(config!$B$37<>"",config!$B$37,TODAY()),$P3,IF($Q3>=IF(config!$B$37<>"",config!$B$37,TODAY()),$Q3,IF($R3>=IF(config!$B$37<>"",config!$B$37,TODAY()),$R3,IF($S3>=IF(config!$B$37<>"",config!$B$37,TODAY()),$S3,IF($T3>=IF(config!$B$37<>"",config!$B$37,TODAY()),$T3,IF($U3>=IF(config!$B$37<>"",config!$B$37,TODAY()),$U3,IF($V3>=IF(config!$B$37<>"",config!$B$37,TODAY()),$V3,IF($W3>=IF(config!$B$37<>"",config!$B$37,TODAY()),$W3,"")))))))))))))) | Z3: =IF($A3="","",COUNTIF(campaigns!$B$2:$B$51,$A3)) -> 3 | AA3: =IF($A3="","",COUNTIF(stops!$A$2:$A$151,$A3)) -> 10 | AB3: =IF($A3="","",SUMIFS(approvals!$S$2:$S$251,approvals!$H$2:$H$251,$A3,approvals!$P$2:$P$251,"Y")) -> 1455 | AC3: =IF($A3="","",SUMIFS(campaigns!$DC$2:$DC$51,campaigns!$B$2:$B$51,$A3)) -> 4350 | AD3: =IF($A3="","",SUMIFS(costs!$E$2:$E$301,costs!$B$2:$B$301,$A3,costs!$D$2:$D$301,"kit")) -> 232 | AE3: =IF($A3="","",SUMIFS(costs!$E$2:$E$301,costs!$B$2:$B$301,$A3,costs!$D$2:$D$301,"transport")) -> 358 | AF3: =IF($A3="","",SUMIFS(costs!$E$2:$E$301,costs!$B$2:$B$301,$A3,costs!$D$2:$D$301,"other_direct")) -> 0 | AG3: =IF($A3="","",$AD3+$AE3+$AF3) -> 590 | AH3: =IF(OR($A3="",N($AA3)=0),"",ROUND($AG3/$AA3,2)) -> 59 | AI3: =IF($A3="","",SUMIFS(hours!$E$2:$E$1501,hours!$B$2:$B$1501,$A3)) -> 52 | AJ3: =IF($A3="","",$AC3-SUMIFS(campaigns!$DG$2:$DG$51,campaigns!$B$2:$B$51,$A3)-$AG3) -> 3760 | AK3: =IF(OR($A3="",N($AI3)=0),"",ROUND($AJ3/$AI3,2)) -> 72.31 | AL3: =IF(OR($A3="",SUMIFS(campaigns!$CB$2:$CB$51,campaigns!$B$2:$B$51,$A3)=0),"",SUMIFS(campaigns!$CD$2:$CD$51,campaigns!$B$2:$B$51,$A3)/SUMIFS(campaigns!$CB$2:$CB$51,campaigns!$B$2:$B$51,$A3)) -> 1 | AM3: =IF(OR($A3="",COUNTIFS(approvals!$H$2:$H$251,$A3,approvals!$Q$2:$Q$251,"Y")=0),"",SUMPRODUCT(MIN(approvals!$BB$2:$BB$251+(approvals!$H$2:$H$251<>$A3)*1000000))) -> 4 | AN3: =IF(OR($A3="",$T3=""),"",COUNTIFS(campaigns!$B$2:$B$51,$A3,campaigns!$DU$2:$DU$51,"late")) -> 0 | AO3: =IF($A3="","",COUNTIFS(campaigns!$B$2:$B$51,$A3,campaigns!$AV$2:$AV$51,"yes")) -> 2
A4: SAMPLE-DRP-003 | B4: 46441 | C4: courier | D4: confirmed | E4: SAMPLE receiving address (founder's home, sealed cases) | F4: SAMPLE Example Courier, booking SAMPLE-BK-0223, pickup 7:45 am | G4: SAMPLE backup (briefed 2027-02-19) | H4: SAMPLE second standard run (exception run) | I4: =IF($B4="","",IF(AND(WEEKDAY($B4)<>3,WEEKDAY($B4)<>4),"REFUSED: a "&TEXT($B4,"dddd")&". Tuesday or Wednesday only",IF(COUNTIF(calendar!$A$2:$A$80,$B4)>0,"REFUSED: a federal holiday",IF(COUNTIFS(calendar!$D$2:$D$20,"<="&WORKDAY($B4,4,calendar!$A$2:$A$80),calendar!$E$2:$E$20,">="&$B4)>0,"REFUSED: the five-day window overlaps a blackout","OK")))) -> OK | J4: =IF($B4="","",TEXT($B4,"ddd")) -> Tue | K4: =IF($I4="OK",WORKDAY($B4,-10,calendar!$A$2:$A$80),"") -> 46426 | L4: =IF($I4="OK",IF(SUMPRODUCT((calendar!$D$2:$D$20<=$M4)*(calendar!$E$2:$E$20>=$K4)*calendar!$D$2:$D$20)=0,$K4,MIN($K4,WORKDAY(SUMPRODUCT((calendar!$D$2:$D$20<=$M4)*(calendar!$E$2:$E$20>=$K4)*calendar!$D$2:$D$20)+5,-1,calendar!$A$2:$A$80))),"") -> 46426 | M4: =IF($I4="OK",WORKDAY($B4,-5,calendar!$A$2:$A$80),"") -> 46434 | N4: =IF($I4="OK",WORKDAY($B4,-3,calendar!$A$2:$A$80),"") -> 46436 | O4: =IF($I4="OK",WORKDAY($B4,-1,calendar!$A$2:$A$80),"") -> 46440 | P4: =IF($I4="OK",WORKDAY($B4,1,calendar!$A$2:$A$80),"") -> 46442 | Q4: =IF($I4="OK",WORKDAY($B4,2,calendar!$A$2:$A$80),"") -> 46443 | R4: =IF($I4="OK",WORKDAY($B4,4,calendar!$A$2:$A$80),"") -> 46447 | S4: =IF($I4="OK",WORKDAY($B4,5,calendar!$A$2:$A$80),"") -> 46448 | T4: =IF($I4="OK",WORKDAY($B4,7,calendar!$A$2:$A$80),"") -> 46450 | U4: =IF($I4="OK",WORKDAY($B4,10,calendar!$A$2:$A$80),"") -> 46455 | V4: =IF($I4="OK",WORKDAY($B4,14,calendar!$A$2:$A$80),"") -> 46461 | W4: =IF($I4="OK",$B4+30,"") -> 46471 | X4: =IF(NOT($I4="OK"),"",IF($K4>=IF(config!$B$37<>"",config!$B$37,TODAY()),"T-10 brand ships; approvals in",IF($M4>=IF(config!$B$37<>"",config!$B$37,TODAY()),"T-5 receive and count",IF($N4>=IF(config!$B$37<>"",config!$B$37,TODAY()),"T-3 print cards, send windows and posts",IF($O4>=IF(config!$B$37<>"",config!$B$37,TODAY()),"T-1 confirm owners, pack",IF($B4>=IF(config!$B$37<>"",config!$B$37,TODAY()),"T drop day",IF($P4>=IF(config!$B$37<>"",config!$B$37,TODAY()),"T+1 placement confirmation",IF($Q4>=IF(config!$B$37<>"",config!$B$37,TODAY()),"T+2 day-3 photos and top-ups",IF($R4>=IF(config!$B$37<>"",config!$B$37,TODAY()),"T+4 close survey, leftovers",IF($S4>=IF(config!$B$37<>"",config!$B$37,TODAY()),"T+5 newsletter list, reserve",IF($T4>=IF(config!$B$37<>"",config!$B$37,TODAY()),"T+7 report and office summaries",IF($U4>=IF(config!$B$37<>"",config!$B$37,TODAY()),"T+10 brand debrief, export actuals",IF($V4>=IF(config!$B$37<>"",config!$B$37,TODAY()),"T+14 return-label deadline",IF($W4>=IF(config!$B$37<>"",config!$B$37,TODAY()),"T+30 redemption check","done")))))))))))))) -> T+30 redemption check | Y4: =IF(NOT($I4="OK"),"",IF($K4>=IF(config!$B$37<>"",config!$B$37,TODAY()),$K4,IF($M4>=IF(config!$B$37<>"",config!$B$37,TODAY()),$M4,IF($N4>=IF(config!$B$37<>"",config!$B$37,TODAY()),$N4,IF($O4>=IF(config!$B$37<>"",config!$B$37,TODAY()),$O4,IF($B4>=IF(config!$B$37<>"",config!$B$37,TODAY()),$B4,IF($P4>=IF(config!$B$37<>"",config!$B$37,TODAY()),$P4,IF($Q4>=IF(config!$B$37<>"",config!$B$37,TODAY()),$Q4,IF($R4>=IF(config!$B$37<>"",config!$B$37,TODAY()),$R4,IF($S4>=IF(config!$B$37<>"",config!$B$37,TODAY()),$S4,IF($T4>=IF(config!$B$37<>"",config!$B$37,TODAY()),$T4,IF($U4>=IF(config!$B$37<>"",config!$B$37,TODAY()),$U4,IF($V4>=IF(config!$B$37<>"",config!$B$37,TODAY()),$V4,IF($W4>=IF(config!$B$37<>"",config!$B$37,TODAY()),$W4,"")))))))))))))) -> 46471 | Z4: =IF($A4="","",COUNTIF(campaigns!$B$2:$B$51,$A4)) -> 1 | AA4: =IF($A4="","",COUNTIF(stops!$A$2:$A$151,$A4)) -> 10 | AB4: =IF($A4="","",SUMIFS(approvals!$S$2:$S$251,approvals!$H$2:$H$251,$A4,approvals!$P$2:$P$251,"Y")) -> 465 | AC4: =IF($A4="","",SUMIFS(campaigns!$DC$2:$DC$51,campaigns!$B$2:$B$51,$A4)) -> 1350 | AD4: =IF($A4="","",SUMIFS(costs!$E$2:$E$301,costs!$B$2:$B$301,$A4,costs!$D$2:$D$301,"kit")) -> 80 | AE4: =IF($A4="","",SUMIFS(costs!$E$2:$E$301,costs!$B$2:$B$301,$A4,costs!$D$2:$D$301,"transport")) -> 300 | AF4: =IF($A4="","",SUMIFS(costs!$E$2:$E$301,costs!$B$2:$B$301,$A4,costs!$D$2:$D$301,"other_direct")) -> 0 | AG4: =IF($A4="","",$AD4+$AE4+$AF4) -> 380 | AH4: =IF(OR($A4="",N($AA4)=0),"",ROUND($AG4/$AA4,2)) -> 38 | AI4: =IF($A4="","",SUMIFS(hours!$E$2:$E$1501,hours!$B$2:$B$1501,$A4)) -> 20.5 | AJ4: =IF($A4="","",$AC4-SUMIFS(campaigns!$DG$2:$DG$51,campaigns!$B$2:$B$51,$A4)-$AG4) -> 970 | AK4: =IF(OR($A4="",N($AI4)=0),"",ROUND($AJ4/$AI4,2)) -> 47.32 | AL4: =IF(OR($A4="",SUMIFS(campaigns!$CB$2:$CB$51,campaigns!$B$2:$B$51,$A4)=0),"",SUMIFS(campaigns!$CD$2:$CD$51,campaigns!$B$2:$B$51,$A4)/SUMIFS(campaigns!$CB$2:$CB$51,campaigns!$B$2:$B$51,$A4)) -> 1 | AM4: =IF(OR($A4="",COUNTIFS(approvals!$H$2:$H$251,$A4,approvals!$Q$2:$Q$251,"Y")=0),"",SUMPRODUCT(MIN(approvals!$BB$2:$BB$251+(approvals!$H$2:$H$251<>$A4)*1000000))) -> 5 | AN4: =IF(OR($A4="",$T4=""),"",COUNTIFS(campaigns!$B$2:$B$51,$A4,campaigns!$DU$2:$DU$51,"late")) -> 0 | AO4: =IF($A4="","",COUNTIFS(campaigns!$B$2:$B$51,$A4,campaigns!$AV$2:$AV$51,"yes")) -> 1
A5: SAMPLE-DRP-004 | B5: 46469 | C5: direct-ship | D5: confirmed | E5: SAMPLE direct to each office; reserve (and SAMPLE-O-009's cartons) to the receiving address | G5: SAMPLE backup (briefed 2027-03-19) | H5: SAMPLE third run (direct-ship run) | I5: =IF($B5="","",IF(AND(WEEKDAY($B5)<>3,WEEKDAY($B5)<>4),"REFUSED: a "&TEXT($B5,"dddd")&". Tuesday or Wednesday only",IF(COUNTIF(calendar!$A$2:$A$80,$B5)>0,"REFUSED: a federal holiday",IF(COUNTIFS(calendar!$D$2:$D$20,"<="&WORKDAY($B5,4,calendar!$A$2:$A$80),calendar!$E$2:$E$20,">="&$B5)>0,"REFUSED: the five-day window overlaps a blackout","OK")))) -> OK | J5: =IF($B5="","",TEXT($B5,"ddd")) -> Tue | K5: =IF($I5="OK",WORKDAY($B5,-10,calendar!$A$2:$A$80),"") -> 46455 | L5: =IF($I5="OK",IF(SUMPRODUCT((calendar!$D$2:$D$20<=$M5)*(calendar!$E$2:$E$20>=$K5)*calendar!$D$2:$D$20)=0,$K5,MIN($K5,WORKDAY(SUMPRODUCT((calendar!$D$2:$D$20<=$M5)*(calendar!$E$2:$E$20>=$K5)*calendar!$D$2:$D$20)+5,-1,calendar!$A$2:$A$80))),"") -> 46455 | M5: =IF($I5="OK",WORKDAY($B5,-5,calendar!$A$2:$A$80),"") -> 46462 | N5: =IF($I5="OK",WORKDAY($B5,-3,calendar!$A$2:$A$80),"") -> 46464 | O5: =IF($I5="OK",WORKDAY($B5,-1,calendar!$A$2:$A$80),"") -> 46468 | P5: =IF($I5="OK",WORKDAY($B5,1,calendar!$A$2:$A$80),"") -> 46470 | Q5: =IF($I5="OK",WORKDAY($B5,2,calendar!$A$2:$A$80),"") -> 46471 | R5: =IF($I5="OK",WORKDAY($B5,4,calendar!$A$2:$A$80),"") -> 46475 | S5: =IF($I5="OK",WORKDAY($B5,5,calendar!$A$2:$A$80),"") -> 46476 | T5: =IF($I5="OK",WORKDAY($B5,7,calendar!$A$2:$A$80),"") -> 46478 | U5: =IF($I5="OK",WORKDAY($B5,10,calendar!$A$2:$A$80),"") -> 46483 | V5: =IF($I5="OK",WORKDAY($B5,14,calendar!$A$2:$A$80),"") -> 46489 | W5: =IF($I5="OK",$B5+30,"") -> 46499 | X5: =IF(NOT($I5="OK"),"",IF($K5>=IF(config!$B$37<>"",config!$B$37,TODAY()),"T-10 brand ships; approvals in",IF($M5>=IF(config!$B$37<>"",config!$B$37,TODAY()),"T-5 receive and count",IF($N5>=IF(config!$B$37<>"",config!$B$37,TODAY()),"T-3 print cards, send windows and posts",IF($O5>=IF(config!$B$37<>"",config!$B$37,TODAY()),"T-1 confirm owners, pack",IF($B5>=IF(config!$B$37<>"",config!$B$37,TODAY()),"T drop day",IF($P5>=IF(config!$B$37<>"",config!$B$37,TODAY()),"T+1 placement confirmation",IF($Q5>=IF(config!$B$37<>"",config!$B$37,TODAY()),"T+2 day-3 photos and top-ups",IF($R5>=IF(config!$B$37<>"",config!$B$37,TODAY()),"T+4 close survey, leftovers",IF($S5>=IF(config!$B$37<>"",config!$B$37,TODAY()),"T+5 newsletter list, reserve",IF($T5>=IF(config!$B$37<>"",config!$B$37,TODAY()),"T+7 report and office summaries",IF($U5>=IF(config!$B$37<>"",config!$B$37,TODAY()),"T+10 brand debrief, export actuals",IF($V5>=IF(config!$B$37<>"",config!$B$37,TODAY()),"T+14 return-label deadline",IF($W5>=IF(config!$B$37<>"",config!$B$37,TODAY()),"T+30 redemption check","done")))))))))))))) -> T-1 confirm owners, pack | Y5: =IF(NOT($I5="OK"),"",IF($K5>=IF(config!$B$37<>"",config!$B$37,TODAY()),$K5,IF($M5>=IF(config!$B$37<>"",config!$B$37,TODAY()),$M5,IF($N5>=IF(config!$B$37<>"",config!$B$37,TODAY()),$N5,IF($O5>=IF(config!$B$37<>"",config!$B$37,TODAY()),$O5,IF($B5>=IF(config!$B$37<>"",config!$B$37,TODAY()),$B5,IF($P5>=IF(config!$B$37<>"",config!$B$37,TODAY()),$P5,IF($Q5>=IF(config!$B$37<>"",config!$B$37,TODAY()),$Q5,IF($R5>=IF(config!$B$37<>"",config!$B$37,TODAY()),$R5,IF($S5>=IF(config!$B$37<>"",config!$B$37,TODAY()),$S5,IF($T5>=IF(config!$B$37<>"",config!$B$37,TODAY()),$T5,IF($U5>=IF(config!$B$37<>"",config!$B$37,TODAY()),$U5,IF($V5>=IF(config!$B$37<>"",config!$B$37,TODAY()),$V5,IF($W5>=IF(config!$B$37<>"",config!$B$37,TODAY()),$W5,"")))))))))))))) -> 46468 | Z5: =IF($A5="","",COUNTIF(campaigns!$B$2:$B$51,$A5)) -> 2 | AA5: =IF($A5="","",COUNTIF(stops!$A$2:$A$151,$A5)) -> 10 | AB5: =IF($A5="","",SUMIFS(approvals!$S$2:$S$251,approvals!$H$2:$H$251,$A5,approvals!$P$2:$P$251,"Y")) -> 1030 | AC5: =IF($A5="","",SUMIFS(campaigns!$DC$2:$DC$51,campaigns!$B$2:$B$51,$A5)) -> 1950 | AD5: =IF($A5="","",SUMIFS(costs!$E$2:$E$301,costs!$B$2:$B$301,$A5,costs!$D$2:$D$301,"kit")) -> 160 | AE5: =IF($A5="","",SUMIFS(costs!$E$2:$E$301,costs!$B$2:$B$301,$A5,costs!$D$2:$D$301,"transport")) -> 0 | AF5: =IF($A5="","",SUMIFS(costs!$E$2:$E$301,costs!$B$2:$B$301,$A5,costs!$D$2:$D$301,"other_direct")) -> 45 | AG5: =IF($A5="","",$AD5+$AE5+$AF5) -> 205 | AH5: =IF(OR($A5="",N($AA5)=0),"",ROUND($AG5/$AA5,2)) -> 20.5 | AI5: =IF($A5="","",SUMIFS(hours!$E$2:$E$1501,hours!$B$2:$B$1501,$A5)) -> 8 | AJ5: =IF($A5="","",$AC5-SUMIFS(campaigns!$DG$2:$DG$51,campaigns!$B$2:$B$51,$A5)-$AG5) -> 1745 | AK5: =IF(OR($A5="",N($AI5)=0),"",ROUND($AJ5/$AI5,2)) -> 218.13 | AL5: =IF(OR($A5="",SUMIFS(campaigns!$CB$2:$CB$51,campaigns!$B$2:$B$51,$A5)=0),"",SUMIFS(campaigns!$CD$2:$CD$51,campaigns!$B$2:$B$51,$A5)/SUMIFS(campaigns!$CB$2:$CB$51,campaigns!$B$2:$B$51,$A5)) | AM5: =IF(OR($A5="",COUNTIFS(approvals!$H$2:$H$251,$A5,approvals!$Q$2:$Q$251,"Y")=0),"",SUMPRODUCT(MIN(approvals!$BB$2:$BB$251+(approvals!$H$2:$H$251<>$A5)*1000000))) -> 0 | AN5: =IF(OR($A5="",$T5=""),"",COUNTIFS(campaigns!$B$2:$B$51,$A5,campaigns!$DU$2:$DU$51,"late")) -> 0 | AO5: =IF($A5="","",COUNTIFS(campaigns!$B$2:$B$51,$A5,campaigns!$AV$2:$AV$51,"yes")) -> 0
I6: =IF($B6="","",IF(AND(WEEKDAY($B6)<>3,WEEKDAY($B6)<>4),"REFUSED: a "&TEXT($B6,"dddd")&". Tuesday or Wednesday only",IF(COUNTIF(calendar!$A$2:$A$80,$B6)>0,"REFUSED: a federal holiday",IF(COUNTIFS(calendar!$D$2:$D$20,"<="&WORKDAY($B6,4,calendar!$A$2:$A$80),calendar!$E$2:$E$20,">="&$B6)>0,"REFUSED: the five-day window overlaps a blackout","OK")))) | J6: =IF($B6="","",TEXT($B6,"ddd")) | K6: =IF($I6="OK",WORKDAY($B6,-10,calendar!$A$2:$A$80),"") | L6: =IF($I6="OK",IF(SUMPRODUCT((calendar!$D$2:$D$20<=$M6)*(calendar!$E$2:$E$20>=$K6)*calendar!$D$2:$D$20)=0,$K6,MIN($K6,WORKDAY(SUMPRODUCT((calendar!$D$2:$D$20<=$M6)*(calendar!$E$2:$E$20>=$K6)*calendar!$D$2:$D$20)+5,-1,calendar!$A$2:$A$80))),"") | M6: =IF($I6="OK",WORKDAY($B6,-5,calendar!$A$2:$A$80),"") | N6: =IF($I6="OK",WORKDAY($B6,-3,calendar!$A$2:$A$80),"") | O6: =IF($I6="OK",WORKDAY($B6,-1,calendar!$A$2:$A$80),"") | P6: =IF($I6="OK",WORKDAY($B6,1,calendar!$A$2:$A$80),"") | Q6: =IF($I6="OK",WORKDAY($B6,2,calendar!$A$2:$A$80),"") | R6: =IF($I6="OK",WORKDAY($B6,4,calendar!$A$2:$A$80),"") | S6: =IF($I6="OK",WORKDAY($B6,5,calendar!$A$2:$A$80),"") | T6: =IF($I6="OK",WORKDAY($B6,7,calendar!$A$2:$A$80),"") | U6: =IF($I6="OK",WORKDAY($B6,10,calendar!$A$2:$A$80),"") | V6: =IF($I6="OK",WORKDAY($B6,14,calendar!$A$2:$A$80),"") | W6: =IF($I6="OK",$B6+30,"") | X6: =IF(NOT($I6="OK"),"",IF($K6>=IF(config!$B$37<>"",config!$B$37,TODAY()),"T-10 brand ships; approvals in",IF($M6>=IF(config!$B$37<>"",config!$B$37,TODAY()),"T-5 receive and count",IF($N6>=IF(config!$B$37<>"",config!$B$37,TODAY()),"T-3 print cards, send windows and posts",IF($O6>=IF(config!$B$37<>"",config!$B$37,TODAY()),"T-1 confirm owners, pack",IF($B6>=IF(config!$B$37<>"",config!$B$37,TODAY()),"T drop day",IF($P6>=IF(config!$B$37<>"",config!$B$37,TODAY()),"T+1 placement confirmation",IF($Q6>=IF(config!$B$37<>"",config!$B$37,TODAY()),"T+2 day-3 photos and top-ups",IF($R6>=IF(config!$B$37<>"",config!$B$37,TODAY()),"T+4 close survey, leftovers",IF($S6>=IF(config!$B$37<>"",config!$B$37,TODAY()),"T+5 newsletter list, reserve",IF($T6>=IF(config!$B$37<>"",config!$B$37,TODAY()),"T+7 report and office summaries",IF($U6>=IF(config!$B$37<>"",config!$B$37,TODAY()),"T+10 brand debrief, export actuals",IF($V6>=IF(config!$B$37<>"",config!$B$37,TODAY()),"T+14 return-label deadline",IF($W6>=IF(config!$B$37<>"",config!$B$37,TODAY()),"T+30 redemption check","done")))))))))))))) | Y6: =IF(NOT($I6="OK"),"",IF($K6>=IF(config!$B$37<>"",config!$B$37,TODAY()),$K6,IF($M6>=IF(config!$B$37<>"",config!$B$37,TODAY()),$M6,IF($N6>=IF(config!$B$37<>"",config!$B$37,TODAY()),$N6,IF($O6>=IF(config!$B$37<>"",config!$B$37,TODAY()),$O6,IF($B6>=IF(config!$B$37<>"",config!$B$37,TODAY()),$B6,IF($P6>=IF(config!$B$37<>"",config!$B$37,TODAY()),$P6,IF($Q6>=IF(config!$B$37<>"",config!$B$37,TODAY()),$Q6,IF($R6>=IF(config!$B$37<>"",config!$B$37,TODAY()),$R6,IF($S6>=IF(config!$B$37<>"",config!$B$37,TODAY()),$S6,IF($T6>=IF(config!$B$37<>"",config!$B$37,TODAY()),$T6,IF($U6>=IF(config!$B$37<>"",config!$B$37,TODAY()),$U6,IF($V6>=IF(config!$B$37<>"",config!$B$37,TODAY()),$V6,IF($W6>=IF(config!$B$37<>"",config!$B$37,TODAY()),$W6,"")))))))))))))) | Z6: =IF($A6="","",COUNTIF(campaigns!$B$2:$B$51,$A6)) | AA6: =IF($A6="","",COUNTIF(stops!$A$2:$A$151,$A6)) | AB6: =IF($A6="","",SUMIFS(approvals!$S$2:$S$251,approvals!$H$2:$H$251,$A6,approvals!$P$2:$P$251,"Y")) | AC6: =IF($A6="","",SUMIFS(campaigns!$DC$2:$DC$51,campaigns!$B$2:$B$51,$A6)) | AD6: =IF($A6="","",SUMIFS(costs!$E$2:$E$301,costs!$B$2:$B$301,$A6,costs!$D$2:$D$301,"kit")) | AE6: =IF($A6="","",SUMIFS(costs!$E$2:$E$301,costs!$B$2:$B$301,$A6,costs!$D$2:$D$301,"transport")) | AF6: =IF($A6="","",SUMIFS(costs!$E$2:$E$301,costs!$B$2:$B$301,$A6,costs!$D$2:$D$301,"other_direct")) | AG6: =IF($A6="","",$AD6+$AE6+$AF6) | AH6: =IF(OR($A6="",N($AA6)=0),"",ROUND($AG6/$AA6,2)) | AI6: =IF($A6="","",SUMIFS(hours!$E$2:$E$1501,hours!$B$2:$B$1501,$A6)) | AJ6: =IF($A6="","",$AC6-SUMIFS(campaigns!$DG$2:$DG$51,campaigns!$B$2:$B$51,$A6)-$AG6) | AK6: =IF(OR($A6="",N($AI6)=0),"",ROUND($AJ6/$AI6,2)) | AL6: =IF(OR($A6="",SUMIFS(campaigns!$CB$2:$CB$51,campaigns!$B$2:$B$51,$A6)=0),"",SUMIFS(campaigns!$CD$2:$CD$51,campaigns!$B$2:$B$51,$A6)/SUMIFS(campaigns!$CB$2:$CB$51,campaigns!$B$2:$B$51,$A6)) | AM6: =IF(OR($A6="",COUNTIFS(approvals!$H$2:$H$251,$A6,approvals!$Q$2:$Q$251,"Y")=0),"",SUMPRODUCT(MIN(approvals!$BB$2:$BB$251+(approvals!$H$2:$H$251<>$A6)*1000000))) | AN6: =IF(OR($A6="",$T6=""),"",COUNTIFS(campaigns!$B$2:$B$51,$A6,campaigns!$DU$2:$DU$51,"late")) | AO6: =IF($A6="","",COUNTIFS(campaigns!$B$2:$B$51,$A6,campaigns!$AV$2:$AV$51,"yes"))
I7: =IF($B7="","",IF(AND(WEEKDAY($B7)<>3,WEEKDAY($B7)<>4),"REFUSED: a "&TEXT($B7,"dddd")&". Tuesday or Wednesday only",IF(COUNTIF(calendar!$A$2:$A$80,$B7)>0,"REFUSED: a federal holiday",IF(COUNTIFS(calendar!$D$2:$D$20,"<="&WORKDAY($B7,4,calendar!$A$2:$A$80),calendar!$E$2:$E$20,">="&$B7)>0,"REFUSED: the five-day window overlaps a blackout","OK")))) | J7: =IF($B7="","",TEXT($B7,"ddd")) | K7: =IF($I7="OK",WORKDAY($B7,-10,calendar!$A$2:$A$80),"") | L7: =IF($I7="OK",IF(SUMPRODUCT((calendar!$D$2:$D$20<=$M7)*(calendar!$E$2:$E$20>=$K7)*calendar!$D$2:$D$20)=0,$K7,MIN($K7,WORKDAY(SUMPRODUCT((calendar!$D$2:$D$20<=$M7)*(calendar!$E$2:$E$20>=$K7)*calendar!$D$2:$D$20)+5,-1,calendar!$A$2:$A$80))),"") | M7: =IF($I7="OK",WORKDAY($B7,-5,calendar!$A$2:$A$80),"") | N7: =IF($I7="OK",WORKDAY($B7,-3,calendar!$A$2:$A$80),"") | O7: =IF($I7="OK",WORKDAY($B7,-1,calendar!$A$2:$A$80),"") | P7: =IF($I7="OK",WORKDAY($B7,1,calendar!$A$2:$A$80),"") | Q7: =IF($I7="OK",WORKDAY($B7,2,calendar!$A$2:$A$80),"") | R7: =IF($I7="OK",WORKDAY($B7,4,calendar!$A$2:$A$80),"") | S7: =IF($I7="OK",WORKDAY($B7,5,calendar!$A$2:$A$80),"") | T7: =IF($I7="OK",WORKDAY($B7,7,calendar!$A$2:$A$80),"") | U7: =IF($I7="OK",WORKDAY($B7,10,calendar!$A$2:$A$80),"") | V7: =IF($I7="OK",WORKDAY($B7,14,calendar!$A$2:$A$80),"") | W7: =IF($I7="OK",$B7+30,"") | X7: =IF(NOT($I7="OK"),"",IF($K7>=IF(config!$B$37<>"",config!$B$37,TODAY()),"T-10 brand ships; approvals in",IF($M7>=IF(config!$B$37<>"",config!$B$37,TODAY()),"T-5 receive and count",IF($N7>=IF(config!$B$37<>"",config!$B$37,TODAY()),"T-3 print cards, send windows and posts",IF($O7>=IF(config!$B$37<>"",config!$B$37,TODAY()),"T-1 confirm owners, pack",IF($B7>=IF(config!$B$37<>"",config!$B$37,TODAY()),"T drop day",IF($P7>=IF(config!$B$37<>"",config!$B$37,TODAY()),"T+1 placement confirmation",IF($Q7>=IF(config!$B$37<>"",config!$B$37,TODAY()),"T+2 day-3 photos and top-ups",IF($R7>=IF(config!$B$37<>"",config!$B$37,TODAY()),"T+4 close survey, leftovers",IF($S7>=IF(config!$B$37<>"",config!$B$37,TODAY()),"T+5 newsletter list, reserve",IF($T7>=IF(config!$B$37<>"",config!$B$37,TODAY()),"T+7 report and office summaries",IF($U7>=IF(config!$B$37<>"",config!$B$37,TODAY()),"T+10 brand debrief, export actuals",IF($V7>=IF(config!$B$37<>"",config!$B$37,TODAY()),"T+14 return-label deadline",IF($W7>=IF(config!$B$37<>"",config!$B$37,TODAY()),"T+30 redemption check","done")))))))))))))) | Y7: =IF(NOT($I7="OK"),"",IF($K7>=IF(config!$B$37<>"",config!$B$37,TODAY()),$K7,IF($M7>=IF(config!$B$37<>"",config!$B$37,TODAY()),$M7,IF($N7>=IF(config!$B$37<>"",config!$B$37,TODAY()),$N7,IF($O7>=IF(config!$B$37<>"",config!$B$37,TODAY()),$O7,IF($B7>=IF(config!$B$37<>"",config!$B$37,TODAY()),$B7,IF($P7>=IF(config!$B$37<>"",config!$B$37,TODAY()),$P7,IF($Q7>=IF(config!$B$37<>"",config!$B$37,TODAY()),$Q7,IF($R7>=IF(config!$B$37<>"",config!$B$37,TODAY()),$R7,IF($S7>=IF(config!$B$37<>"",config!$B$37,TODAY()),$S7,IF($T7>=IF(config!$B$37<>"",config!$B$37,TODAY()),$T7,IF($U7>=IF(config!$B$37<>"",config!$B$37,TODAY()),$U7,IF($V7>=IF(config!$B$37<>"",config!$B$37,TODAY()),$V7,IF($W7>=IF(config!$B$37<>"",config!$B$37,TODAY()),$W7,"")))))))))))))) | Z7: =IF($A7="","",COUNTIF(campaigns!$B$2:$B$51,$A7)) | AA7: =IF($A7="","",COUNTIF(stops!$A$2:$A$151,$A7)) | AB7: =IF($A7="","",SUMIFS(approvals!$S$2:$S$251,approvals!$H$2:$H$251,$A7,approvals!$P$2:$P$251,"Y")) | AC7: =IF($A7="","",SUMIFS(campaigns!$DC$2:$DC$51,campaigns!$B$2:$B$51,$A7)) | AD7: =IF($A7="","",SUMIFS(costs!$E$2:$E$301,costs!$B$2:$B$301,$A7,costs!$D$2:$D$301,"kit")) | AE7: =IF($A7="","",SUMIFS(costs!$E$2:$E$301,costs!$B$2:$B$301,$A7,costs!$D$2:$D$301,"transport")) | AF7: =IF($A7="","",SUMIFS(costs!$E$2:$E$301,costs!$B$2:$B$301,$A7,costs!$D$2:$D$301,"other_direct")) | AG7: =IF($A7="","",$AD7+$AE7+$AF7) | AH7: =IF(OR($A7="",N($AA7)=0),"",ROUND($AG7/$AA7,2)) | AI7: =IF($A7="","",SUMIFS(hours!$E$2:$E$1501,hours!$B$2:$B$1501,$A7)) | AJ7: =IF($A7="","",$AC7-SUMIFS(campaigns!$DG$2:$DG$51,campaigns!$B$2:$B$51,$A7)-$AG7) | AK7: =IF(OR($A7="",N($AI7)=0),"",ROUND($AJ7/$AI7,2)) | AL7: =IF(OR($A7="",SUMIFS(campaigns!$CB$2:$CB$51,campaigns!$B$2:$B$51,$A7)=0),"",SUMIFS(campaigns!$CD$2:$CD$51,campaigns!$B$2:$B$51,$A7)/SUMIFS(campaigns!$CB$2:$CB$51,campaigns!$B$2:$B$51,$A7)) | AM7: =IF(OR($A7="",COUNTIFS(approvals!$H$2:$H$251,$A7,approvals!$Q$2:$Q$251,"Y")=0),"",SUMPRODUCT(MIN(approvals!$BB$2:$BB$251+(approvals!$H$2:$H$251<>$A7)*1000000))) | AN7: =IF(OR($A7="",$T7=""),"",COUNTIFS(campaigns!$B$2:$B$51,$A7,campaigns!$DU$2:$DU$51,"late")) | AO7: =IF($A7="","",COUNTIFS(campaigns!$B$2:$B$51,$A7,campaigns!$AV$2:$AV$51,"yes"))
I8: =IF($B8="","",IF(AND(WEEKDAY($B8)<>3,WEEKDAY($B8)<>4),"REFUSED: a "&TEXT($B8,"dddd")&". Tuesday or Wednesday only",IF(COUNTIF(calendar!$A$2:$A$80,$B8)>0,"REFUSED: a federal holiday",IF(COUNTIFS(calendar!$D$2:$D$20,"<="&WORKDAY($B8,4,calendar!$A$2:$A$80),calendar!$E$2:$E$20,">="&$B8)>0,"REFUSED: the five-day window overlaps a blackout","OK")))) | J8: =IF($B8="","",TEXT($B8,"ddd")) | K8: =IF($I8="OK",WORKDAY($B8,-10,calendar!$A$2:$A$80),"") | L8: =IF($I8="OK",IF(SUMPRODUCT((calendar!$D$2:$D$20<=$M8)*(calendar!$E$2:$E$20>=$K8)*calendar!$D$2:$D$20)=0,$K8,MIN($K8,WORKDAY(SUMPRODUCT((calendar!$D$2:$D$20<=$M8)*(calendar!$E$2:$E$20>=$K8)*calendar!$D$2:$D$20)+5,-1,calendar!$A$2:$A$80))),"") | M8: =IF($I8="OK",WORKDAY($B8,-5,calendar!$A$2:$A$80),"") | N8: =IF($I8="OK",WORKDAY($B8,-3,calendar!$A$2:$A$80),"") | O8: =IF($I8="OK",WORKDAY($B8,-1,calendar!$A$2:$A$80),"") | P8: =IF($I8="OK",WORKDAY($B8,1,calendar!$A$2:$A$80),"") | Q8: =IF($I8="OK",WORKDAY($B8,2,calendar!$A$2:$A$80),"") | R8: =IF($I8="OK",WORKDAY($B8,4,calendar!$A$2:$A$80),"") | S8: =IF($I8="OK",WORKDAY($B8,5,calendar!$A$2:$A$80),"") | T8: =IF($I8="OK",WORKDAY($B8,7,calendar!$A$2:$A$80),"") | U8: =IF($I8="OK",WORKDAY($B8,10,calendar!$A$2:$A$80),"") | V8: =IF($I8="OK",WORKDAY($B8,14,calendar!$A$2:$A$80),"") | W8: =IF($I8="OK",$B8+30,"") | X8: =IF(NOT($I8="OK"),"",IF($K8>=IF(config!$B$37<>"",config!$B$37,TODAY()),"T-10 brand ships; approvals in",IF($M8>=IF(config!$B$37<>"",config!$B$37,TODAY()),"T-5 receive and count",IF($N8>=IF(config!$B$37<>"",config!$B$37,TODAY()),"T-3 print cards, send windows and posts",IF($O8>=IF(config!$B$37<>"",config!$B$37,TODAY()),"T-1 confirm owners, pack",IF($B8>=IF(config!$B$37<>"",config!$B$37,TODAY()),"T drop day",IF($P8>=IF(config!$B$37<>"",config!$B$37,TODAY()),"T+1 placement confirmation",IF($Q8>=IF(config!$B$37<>"",config!$B$37,TODAY()),"T+2 day-3 photos and top-ups",IF($R8>=IF(config!$B$37<>"",config!$B$37,TODAY()),"T+4 close survey, leftovers",IF($S8>=IF(config!$B$37<>"",config!$B$37,TODAY()),"T+5 newsletter list, reserve",IF($T8>=IF(config!$B$37<>"",config!$B$37,TODAY()),"T+7 report and office summaries",IF($U8>=IF(config!$B$37<>"",config!$B$37,TODAY()),"T+10 brand debrief, export actuals",IF($V8>=IF(config!$B$37<>"",config!$B$37,TODAY()),"T+14 return-label deadline",IF($W8>=IF(config!$B$37<>"",config!$B$37,TODAY()),"T+30 redemption check","done")))))))))))))) | Y8: =IF(NOT($I8="OK"),"",IF($K8>=IF(config!$B$37<>"",config!$B$37,TODAY()),$K8,IF($M8>=IF(config!$B$37<>"",config!$B$37,TODAY()),$M8,IF($N8>=IF(config!$B$37<>"",config!$B$37,TODAY()),$N8,IF($O8>=IF(config!$B$37<>"",config!$B$37,TODAY()),$O8,IF($B8>=IF(config!$B$37<>"",config!$B$37,TODAY()),$B8,IF($P8>=IF(config!$B$37<>"",config!$B$37,TODAY()),$P8,IF($Q8>=IF(config!$B$37<>"",config!$B$37,TODAY()),$Q8,IF($R8>=IF(config!$B$37<>"",config!$B$37,TODAY()),$R8,IF($S8>=IF(config!$B$37<>"",config!$B$37,TODAY()),$S8,IF($T8>=IF(config!$B$37<>"",config!$B$37,TODAY()),$T8,IF($U8>=IF(config!$B$37<>"",config!$B$37,TODAY()),$U8,IF($V8>=IF(config!$B$37<>"",config!$B$37,TODAY()),$V8,IF($W8>=IF(config!$B$37<>"",config!$B$37,TODAY()),$W8,"")))))))))))))) | Z8: =IF($A8="","",COUNTIF(campaigns!$B$2:$B$51,$A8)) | AA8: =IF($A8="","",COUNTIF(stops!$A$2:$A$151,$A8)) | AB8: =IF($A8="","",SUMIFS(approvals!$S$2:$S$251,approvals!$H$2:$H$251,$A8,approvals!$P$2:$P$251,"Y")) | AC8: =IF($A8="","",SUMIFS(campaigns!$DC$2:$DC$51,campaigns!$B$2:$B$51,$A8)) | AD8: =IF($A8="","",SUMIFS(costs!$E$2:$E$301,costs!$B$2:$B$301,$A8,costs!$D$2:$D$301,"kit")) | AE8: =IF($A8="","",SUMIFS(costs!$E$2:$E$301,costs!$B$2:$B$301,$A8,costs!$D$2:$D$301,"transport")) | AF8: =IF($A8="","",SUMIFS(costs!$E$2:$E$301,costs!$B$2:$B$301,$A8,costs!$D$2:$D$301,"other_direct")) | AG8: =IF($A8="","",$AD8+$AE8+$AF8) | AH8: =IF(OR($A8="",N($AA8)=0),"",ROUND($AG8/$AA8,2)) | AI8: =IF($A8="","",SUMIFS(hours!$E$2:$E$1501,hours!$B$2:$B$1501,$A8)) | AJ8: =IF($A8="","",$AC8-SUMIFS(campaigns!$DG$2:$DG$51,campaigns!$B$2:$B$51,$A8)-$AG8) | AK8: =IF(OR($A8="",N($AI8)=0),"",ROUND($AJ8/$AI8,2)) | AL8: =IF(OR($A8="",SUMIFS(campaigns!$CB$2:$CB$51,campaigns!$B$2:$B$51,$A8)=0),"",SUMIFS(campaigns!$CD$2:$CD$51,campaigns!$B$2:$B$51,$A8)/SUMIFS(campaigns!$CB$2:$CB$51,campaigns!$B$2:$B$51,$A8)) | AM8: =IF(OR($A8="",COUNTIFS(approvals!$H$2:$H$251,$A8,approvals!$Q$2:$Q$251,"Y")=0),"",SUMPRODUCT(MIN(approvals!$BB$2:$BB$251+(approvals!$H$2:$H$251<>$A8)*1000000))) | AN8: =IF(OR($A8="",$T8=""),"",COUNTIFS(campaigns!$B$2:$B$51,$A8,campaigns!$DU$2:$DU$51,"late")) | AO8: =IF($A8="","",COUNTIFS(campaigns!$B$2:$B$51,$A8,campaigns!$AV$2:$AV$51,"yes"))
I9: =IF($B9="","",IF(AND(WEEKDAY($B9)<>3,WEEKDAY($B9)<>4),"REFUSED: a "&TEXT($B9,"dddd")&". Tuesday or Wednesday only",IF(COUNTIF(calendar!$A$2:$A$80,$B9)>0,"REFUSED: a federal holiday",IF(COUNTIFS(calendar!$D$2:$D$20,"<="&WORKDAY($B9,4,calendar!$A$2:$A$80),calendar!$E$2:$E$20,">="&$B9)>0,"REFUSED: the five-day window overlaps a blackout","OK")))) | J9: =IF($B9="","",TEXT($B9,"ddd")) | K9: =IF($I9="OK",WORKDAY($B9,-10,calendar!$A$2:$A$80),"") | L9: =IF($I9="OK",IF(SUMPRODUCT((calendar!$D$2:$D$20<=$M9)*(calendar!$E$2:$E$20>=$K9)*calendar!$D$2:$D$20)=0,$K9,MIN($K9,WORKDAY(SUMPRODUCT((calendar!$D$2:$D$20<=$M9)*(calendar!$E$2:$E$20>=$K9)*calendar!$D$2:$D$20)+5,-1,calendar!$A$2:$A$80))),"") | M9: =IF($I9="OK",WORKDAY($B9,-5,calendar!$A$2:$A$80),"") | N9: =IF($I9="OK",WORKDAY($B9,-3,calendar!$A$2:$A$80),"") | O9: =IF($I9="OK",WORKDAY($B9,-1,calendar!$A$2:$A$80),"") | P9: =IF($I9="OK",WORKDAY($B9,1,calendar!$A$2:$A$80),"") | Q9: =IF($I9="OK",WORKDAY($B9,2,calendar!$A$2:$A$80),"") | R9: =IF($I9="OK",WORKDAY($B9,4,calendar!$A$2:$A$80),"") | S9: =IF($I9="OK",WORKDAY($B9,5,calendar!$A$2:$A$80),"") | T9: =IF($I9="OK",WORKDAY($B9,7,calendar!$A$2:$A$80),"") | U9: =IF($I9="OK",WORKDAY($B9,10,calendar!$A$2:$A$80),"") | V9: =IF($I9="OK",WORKDAY($B9,14,calendar!$A$2:$A$80),"") | W9: =IF($I9="OK",$B9+30,"") | X9: =IF(NOT($I9="OK"),"",IF($K9>=IF(config!$B$37<>"",config!$B$37,TODAY()),"T-10 brand ships; approvals in",IF($M9>=IF(config!$B$37<>"",config!$B$37,TODAY()),"T-5 receive and count",IF($N9>=IF(config!$B$37<>"",config!$B$37,TODAY()),"T-3 print cards, send windows and posts",IF($O9>=IF(config!$B$37<>"",config!$B$37,TODAY()),"T-1 confirm owners, pack",IF($B9>=IF(config!$B$37<>"",config!$B$37,TODAY()),"T drop day",IF($P9>=IF(config!$B$37<>"",config!$B$37,TODAY()),"T+1 placement confirmation",IF($Q9>=IF(config!$B$37<>"",config!$B$37,TODAY()),"T+2 day-3 photos and top-ups",IF($R9>=IF(config!$B$37<>"",config!$B$37,TODAY()),"T+4 close survey, leftovers",IF($S9>=IF(config!$B$37<>"",config!$B$37,TODAY()),"T+5 newsletter list, reserve",IF($T9>=IF(config!$B$37<>"",config!$B$37,TODAY()),"T+7 report and office summaries",IF($U9>=IF(config!$B$37<>"",config!$B$37,TODAY()),"T+10 brand debrief, export actuals",IF($V9>=IF(config!$B$37<>"",config!$B$37,TODAY()),"T+14 return-label deadline",IF($W9>=IF(config!$B$37<>"",config!$B$37,TODAY()),"T+30 redemption check","done")))))))))))))) | Y9: =IF(NOT($I9="OK"),"",IF($K9>=IF(config!$B$37<>"",config!$B$37,TODAY()),$K9,IF($M9>=IF(config!$B$37<>"",config!$B$37,TODAY()),$M9,IF($N9>=IF(config!$B$37<>"",config!$B$37,TODAY()),$N9,IF($O9>=IF(config!$B$37<>"",config!$B$37,TODAY()),$O9,IF($B9>=IF(config!$B$37<>"",config!$B$37,TODAY()),$B9,IF($P9>=IF(config!$B$37<>"",config!$B$37,TODAY()),$P9,IF($Q9>=IF(config!$B$37<>"",config!$B$37,TODAY()),$Q9,IF($R9>=IF(config!$B$37<>"",config!$B$37,TODAY()),$R9,IF($S9>=IF(config!$B$37<>"",config!$B$37,TODAY()),$S9,IF($T9>=IF(config!$B$37<>"",config!$B$37,TODAY()),$T9,IF($U9>=IF(config!$B$37<>"",config!$B$37,TODAY()),$U9,IF($V9>=IF(config!$B$37<>"",config!$B$37,TODAY()),$V9,IF($W9>=IF(config!$B$37<>"",config!$B$37,TODAY()),$W9,"")))))))))))))) | Z9: =IF($A9="","",COUNTIF(campaigns!$B$2:$B$51,$A9)) | AA9: =IF($A9="","",COUNTIF(stops!$A$2:$A$151,$A9)) | AB9: =IF($A9="","",SUMIFS(approvals!$S$2:$S$251,approvals!$H$2:$H$251,$A9,approvals!$P$2:$P$251,"Y")) | AC9: =IF($A9="","",SUMIFS(campaigns!$DC$2:$DC$51,campaigns!$B$2:$B$51,$A9)) | AD9: =IF($A9="","",SUMIFS(costs!$E$2:$E$301,costs!$B$2:$B$301,$A9,costs!$D$2:$D$301,"kit")) | AE9: =IF($A9="","",SUMIFS(costs!$E$2:$E$301,costs!$B$2:$B$301,$A9,costs!$D$2:$D$301,"transport")) | AF9: =IF($A9="","",SUMIFS(costs!$E$2:$E$301,costs!$B$2:$B$301,$A9,costs!$D$2:$D$301,"other_direct")) | AG9: =IF($A9="","",$AD9+$AE9+$AF9) | AH9: =IF(OR($A9="",N($AA9)=0),"",ROUND($AG9/$AA9,2)) | AI9: =IF($A9="","",SUMIFS(hours!$E$2:$E$1501,hours!$B$2:$B$1501,$A9)) | AJ9: =IF($A9="","",$AC9-SUMIFS(campaigns!$DG$2:$DG$51,campaigns!$B$2:$B$51,$A9)-$AG9) | AK9: =IF(OR($A9="",N($AI9)=0),"",ROUND($AJ9/$AI9,2)) | AL9: =IF(OR($A9="",SUMIFS(campaigns!$CB$2:$CB$51,campaigns!$B$2:$B$51,$A9)=0),"",SUMIFS(campaigns!$CD$2:$CD$51,campaigns!$B$2:$B$51,$A9)/SUMIFS(campaigns!$CB$2:$CB$51,campaigns!$B$2:$B$51,$A9)) | AM9: =IF(OR($A9="",COUNTIFS(approvals!$H$2:$H$251,$A9,approvals!$Q$2:$Q$251,"Y")=0),"",SUMPRODUCT(MIN(approvals!$BB$2:$BB$251+(approvals!$H$2:$H$251<>$A9)*1000000))) | AN9: =IF(OR($A9="",$T9=""),"",COUNTIFS(campaigns!$B$2:$B$51,$A9,campaigns!$DU$2:$DU$51,"late")) | AO9: =IF($A9="","",COUNTIFS(campaigns!$B$2:$B$51,$A9,campaigns!$AV$2:$AV$51,"yes"))
